{
  "type": "Feature",
  "properties": {
    "gn:country":"TR",
    "gn:fcode":"PPL",
    "gn:pop":0,
    "iso:country":"TR",
    "name:ara_x_preferred":[
        "\u0623\u0631\u0646\u0627\u0641\u0648\u062a \u0643\u0648\u064a"
    ],
    "name:eng_x_preferred":[
        "Arnavutk\u00f6y"
    ],
    "name:fra_x_preferred":[
        "Arnavutk\u00f6y"
    ],
    "name:ita_x_preferred":[
        "Arnavutk\u00f6y"
    ],
    "name:por_x_preferred":[
        "Arnavutk\u00f6y"
    ],
    "name:tur_x_preferred":[
        "Arnavutk\u00f6y"
    ],
    "name:unk_x_variant":[
        "Arnaut Kioi"
    ],
    "qs:name":"Arnavutk\u00f6y",
    "qs:name_adm0":"Turkey",
    "qs:name_adm1":"\u0130stanbul",
    "qs:photos_9k":1,
    "qs:photos_9r":1,
    "qs:photos_all":5,
    "qs:photos_sr":0,
    "qs:placetype":"Town",
    "qs:pop_sr":"0",
    "wd:wordcount":411,
    "wof:name":"Arnavutk\u00f6y",
    "wof:placetype":"locality",
    "wof:population":0
},
  "geometry": {"coordinates":[29.03333,41.06667],"type":"Point"}
}