{
  "type": "Feature",
  "properties": {
    "gn:admin1_code":"38.0",
    "gn:asciiname":"Akmezar",
    "gn:country_code":"TR",
    "gn:dem":1367,
    "gn:feature_class":"P",
    "gn:feature_code":"PPL",
    "gn:name":"Akmezar",
    "gn:population":0,
    "gn:timezone":"Europe/Istanbul",
    "iso:country":"TR",
    "wof:name":"Akmezar",
    "wof:placetype":"locality"
},
  "geometry": {"coordinates":[35.99793,38.44818],"type":"Point"}
}