{
  "type": "Feature",
  "properties": {
    "gn:country":"TR",
    "gn:fcode":"PPLA2",
    "gn:population":60916,
    "iso:country":"TR",
    "name:ara_x_preferred":[
        "\u0642\u0631\u064a \u062e\u0627\u0646"
    ],
    "name:azb_x_preferred":[
        "\u0642\u06cc\u0631\u06cc\u0642 \u062e\u0627\u0646"
    ],
    "name:cat_x_preferred":[
        "K\u0131r\u0131khan"
    ],
    "name:ceb_x_preferred":[
        "K\u0131r\u0131khan \u0130l\u00e7esi"
    ],
    "name:cym_x_preferred":[
        "K\u0131r\u0131khan"
    ],
    "name:deu_x_preferred":[
        "K\u0131r\u0131khan"
    ],
    "name:diq_x_preferred":[
        "K\u0131r\u0131khan"
    ],
    "name:ell_x_preferred":[
        "\u039a\u03b9\u03c1\u03b9\u03c7\u03ac\u03bd"
    ],
    "name:eng_x_preferred":[
        "K\u0131r\u0131khan"
    ],
    "name:epo_x_preferred":[
        "K\u0131r\u0131khan"
    ],
    "name:fas_x_preferred":[
        "\u0642\u0627\u0631\u0627\u062e\u0627\u0646"
    ],
    "name:fra_x_preferred":[
        "K\u0131r\u0131khan"
    ],
    "name:gag_x_preferred":[
        "K\u0131r\u0131khan"
    ],
    "name:ita_x_preferred":[
        "Distretto di K\u0131r\u0131khan"
    ],
    "name:min_x_preferred":[
        "K\u0131r\u0131khan"
    ],
    "name:mrj_x_preferred":[
        "\u041a\u044b\u0440\u044b\u043a\u0445\u0430\u043d"
    ],
    "name:msa_x_preferred":[
        "K\u0131r\u0131khan"
    ],
    "name:nan_x_preferred":[
        "K\u0131r\u0131khan"
    ],
    "name:nld_x_preferred":[
        "K\u0131r\u0131khan"
    ],
    "name:nno_x_preferred":[
        "K\u0131r\u0131khan"
    ],
    "name:nob_x_preferred":[
        "K\u0131r\u0131khan"
    ],
    "name:pnb_x_preferred":[
        "\u0636\u0644\u0639 \u06a9\u0631\u06cc\u062e\u0627\u0646"
    ],
    "name:pol_x_preferred":[
        "K\u0131r\u0131khan"
    ],
    "name:rus_x_preferred":[
        "\u041a\u044b\u0440\u044b\u043a\u0445\u0430\u043d"
    ],
    "name:sco_x_preferred":[
        "K\u0131r\u0131khan"
    ],
    "name:spa_x_preferred":[
        "K\u0131r\u0131khan"
    ],
    "name:swa_x_preferred":[
        "K\u0131r\u0131khan"
    ],
    "name:tur_x_preferred":[
        "K\u0131r\u0131khan"
    ],
    "name:urd_x_preferred":[
        "\u06a9\u06cc\u0631\u06cc\u062e\u0627\u0646"
    ],
    "name:vie_x_preferred":[
        "K\u0131r\u0131khan"
    ],
    "name:zho_x_preferred":[
        "\u514b\u52d2\u514b\u6f22"
    ],
    "qs:name":"K\u0131r\u0131khan",
    "qs:photos_9r":0,
    "qs:photos_sr":0,
    "qs:pop_sr":"8",
    "wd:wordcount":163,
    "wof:name":"K\u0131r\u0131khan",
    "wof:placetype":"locality",
    "wof:population":60916
},
  "geometry": {"coordinates":[36.35755,36.49939],"type":"Point"}
}