{
  "type": "Feature",
  "properties": {
    "gn:country":"TR",
    "gn:fcode":"PPLX",
    "gn:pop":0,
    "iso:country":"TR",
    "qs:name":"G\u00f6\u00e7erler",
    "qs:name_adm0":"Turkey",
    "qs:name_adm1":"Antalya",
    "qs:photos":2,
    "qs:photos_1k":1,
    "qs:photos_9k":1,
    "qs:photos_9r":1,
    "qs:photos_all":2,
    "qs:photos_sr":1,
    "qs:placetype":"Suburb",
    "qs:pop_sr":"0",
    "wd:wordcount":27,
    "wof:name":"G\u00f6\u00e7erler",
    "wof:placetype":"neighbourhood",
    "wof:population":0
},
  "geometry": {"coordinates":[30.66158,36.94823],"type":"Point"}
}