{
  "type": "Feature",
  "properties": {
    "gn:admin1_code":"20",
    "gn:asciiname":"Hayriye",
    "gn:country_code":"TR",
    "gn:dem":1224,
    "gn:feature_class":"P",
    "gn:feature_code":"PPL",
    "gn:name":"Hayriye",
    "gn:population":0,
    "gn:timezone":"Europe/Istanbul",
    "iso:country":"TR",
    "name:tur_x_preferred":[
        "Hayriye"
    ],
    "wof:name":"Hayriye",
    "wof:placetype":"locality"
},
  "geometry": {"coordinates":[29.64898,37.65204],"type":"Point"}
}