{
  "type": "Feature",
  "properties": {
    "gn:admin1_code":"25",
    "gn:asciiname":"Toprakkale",
    "gn:country_code":"TR",
    "gn:dem":1696,
    "gn:feature_class":"P",
    "gn:feature_code":"PPL",
    "gn:name":"Toprakkale",
    "gn:population":0,
    "gn:timezone":"Europe/Istanbul",
    "iso:country":"TR",
    "name:tur_x_preferred":[
        "Toprakkale"
    ],
    "wof:name":"Toprakkale",
    "wof:placetype":"locality"
},
  "geometry": {"coordinates":[41.7992,39.38276],"type":"Point"}
}