{
  "type": "Feature",
  "properties": {
    "gn:admin1_code":"68",
    "gn:asciiname":"Okcular",
    "gn:country_code":"TR",
    "gn:dem":1231,
    "gn:feature_class":"P",
    "gn:feature_code":"PPL",
    "gn:name":"Ok\u00e7ular",
    "gn:population":0,
    "gn:timezone":"Europe/Istanbul",
    "iso:country":"TR",
    "wof:name":"Okcular",
    "wof:placetype":"locality"
},
  "geometry": {"coordinates":[33.03923,40.38008],"type":"Point"}
}