{
  "type": "Feature",
  "properties": {
    "gn:admin1_code":"17.0",
    "gn:asciiname":"Daralan",
    "gn:country_code":"TR",
    "gn:dem":454,
    "gn:feature_class":"P",
    "gn:feature_code":"PPL",
    "gn:name":"Daralan",
    "gn:population":0,
    "gn:timezone":"Europe/Istanbul",
    "iso:country":"TR",
    "name:tur_x_preferred":[
        "Daralan"
    ],
    "name:tur_x_variant":[
        "Daralanoba"
    ],
    "wof:name":"Daralan",
    "wof:placetype":"locality"
},
  "geometry": {"coordinates":[27.4356,39.81899],"type":"Point"}
}