{
  "type": "Feature",
  "properties": {
    "gn:admin1_code":"43",
    "gn:asciiname":"Karacakas",
    "gn:country_code":"TR",
    "gn:dem":903,
    "gn:feature_class":"P",
    "gn:feature_code":"PPL",
    "gn:name":"Karacaka\u015f",
    "gn:population":0,
    "gn:timezone":"Europe/Istanbul",
    "iso:country":"TR",
    "name:tur_x_preferred":[
        "Karacaka\u015f"
    ],
    "name:und_x_variant":[
        "Karaa\u011fa\u00e7 K\u00f6y\u00fc",
        "Karaa\u011fa\u00e7"
    ],
    "wof:name":"Karacakas",
    "wof:placetype":"locality"
},
  "geometry": {"coordinates":[29.53584,39.46983],"type":"Point"}
}