{
  "type": "Feature",
  "properties": {
    "gn:admin1_code":"63",
    "gn:asciiname":"Adzhem",
    "gn:country_code":"TR",
    "gn:dem":729,
    "gn:feature_class":"P",
    "gn:feature_code":"PPL",
    "gn:name":"Adzhem",
    "gn:population":0,
    "gn:timezone":"Europe/Istanbul",
    "iso:country":"TR",
    "wof:name":"Adzhem",
    "wof:placetype":"locality"
},
  "geometry": {"coordinates":[38.52314000000001,37.30367],"type":"Point"}
}