{
  "type": "Feature",
  "properties": {
    "gn:admin1_code":"77.0",
    "gn:asciiname":"Bugdayli",
    "gn:country_code":"TR",
    "gn:dem":1789,
    "gn:feature_class":"P",
    "gn:feature_code":"PPL",
    "gn:name":"Bu\u011fdayl\u0131",
    "gn:population":0,
    "gn:timezone":"Europe/Istanbul",
    "iso:country":"TR",
    "name:und_x_variant":[
        "Tanzut",
        "Danzut",
        "Bu\u011fdayl\u0131"
    ],
    "wof:name":"Bugdayli",
    "wof:placetype":"locality"
},
  "geometry": {"coordinates":[40.27325,40.32123],"type":"Point"}
}