{
  "type": "Feature",
  "properties": {
    "gn:admin1_code":"23.0",
    "gn:asciiname":"Surekli",
    "gn:country_code":"TR",
    "gn:dem":1424,
    "gn:feature_class":"P",
    "gn:feature_code":"PPL",
    "gn:name":"S\u00fcrekli",
    "gn:population":0,
    "gn:timezone":"Europe/Istanbul",
    "iso:country":"TR",
    "name:tur_x_preferred":[
        "S\u00fcrekli"
    ],
    "wof:name":"Surekli",
    "wof:placetype":"locality"
},
  "geometry": {"coordinates":[39.80082,38.74586],"type":"Point"}
}