{
  "type": "Feature",
  "properties": {
    "gn:admin1_code":"33",
    "gn:asciiname":"Cariksaraylar",
    "gn:cc2":"TR",
    "gn:country_code":"TR",
    "gn:dem":1239,
    "gn:feature_class":"P",
    "gn:feature_code":"PPL",
    "gn:name":"\u00c7ar\u0131ksaraylar",
    "gn:population":0,
    "gn:timezone":"Europe/Istanbul",
    "iso:country":"TR",
    "name:und_x_variant":[
        "\u00c7ar\u0131ksaray",
        "\u00c7ar\u0131ksaraylar"
    ],
    "wof:name":"Cariksaraylar",
    "wof:placetype":"locality"
},
  "geometry": {"coordinates":[31.41556,38.1175],"type":"Point"}
}