{
  "type": "Feature",
  "properties": {
    "gn:admin1_code":"31",
    "gn:asciiname":"Hasanhuseyin",
    "gn:country_code":"TR",
    "gn:dem":104,
    "gn:feature_class":"P",
    "gn:feature_code":"PPL",
    "gn:name":"Hasanh\u00fcseyin",
    "gn:population":0,
    "gn:timezone":"Europe/Istanbul",
    "iso:country":"TR",
    "name:tur_x_preferred":[
        "Hasanh\u00fcseyin"
    ],
    "wof:name":"Hasanhuseyin",
    "wof:placetype":"locality"
},
  "geometry": {"coordinates":[36.33205,36.22555],"type":"Point"}
}