{
  "type": "Feature",
  "properties": {
    "gn:admin1_code":"65",
    "gn:asciiname":"Bilgec",
    "gn:country_code":"TR",
    "gn:dem":2233,
    "gn:feature_class":"P",
    "gn:feature_code":"PPL",
    "gn:name":"Bilge\u00e7",
    "gn:population":0,
    "gn:timezone":"Europe/Istanbul",
    "iso:country":"TR",
    "name:und_x_variant":[
        "Kanira\u015f",
        "Kanire\u015f",
        "Kaniri\u015f",
        "Bilge\u00e7"
    ],
    "wof:name":"Bilgec",
    "wof:placetype":"locality"
},
  "geometry": {"coordinates":[44.2954,38.24119],"type":"Point"}
}