{
  "type": "Feature",
  "properties": {
    "gn:admin1_code":"83",
    "gn:asciiname":"Ekinli",
    "gn:country_code":"TR",
    "gn:dem":667,
    "gn:feature_class":"P",
    "gn:feature_code":"PPL",
    "gn:name":"Ekinli",
    "gn:population":0,
    "gn:timezone":"Europe/Istanbul",
    "iso:country":"TR",
    "name:und_x_variant":[
        "K\u00fcdevir",
        "G\u00fcdevir",
        "Ekinli"
    ],
    "wof:name":"Ekinli",
    "wof:placetype":"locality"
},
  "geometry": {"coordinates":[37.36503,36.81981],"type":"Point"}
}