{
  "type": "Feature",
  "properties": {
    "iso:country":"TR",
    "name:baq_x_preferred":[
        "\u00d6rnektepe"
    ],
    "name:cat_x_preferred":[
        "\u00d6rnektepe"
    ],
    "name:cze_x_preferred":[
        "\u00d6rnektepe"
    ],
    "name:dan_x_preferred":[
        "\u00d6rnektepe"
    ],
    "name:dut_x_preferred":[
        "\u00d6rnektepe"
    ],
    "name:eng_x_preferred":[
        "\u00d6rnektepe"
    ],
    "name:fin_x_preferred":[
        "\u00d6rnektepe"
    ],
    "name:ger_x_preferred":[
        "\u00d6rnektepe"
    ],
    "name:glg_x_preferred":[
        "\u00d6rnektepe"
    ],
    "name:ita_x_preferred":[
        "\u00d6rnektepe"
    ],
    "name:nno_x_preferred":[
        "\u00d6rnektepe"
    ],
    "name:nob_x_preferred":[
        "\u00d6rnektepe"
    ],
    "name:oci_x_preferred":[
        "\u00d6rnektepe"
    ],
    "name:pol_x_preferred":[
        "\u00d6rnektepe"
    ],
    "name:por_x_preferred":[
        "\u00d6rnektepe"
    ],
    "name:rum_x_preferred":[
        "\u00d6rnektepe"
    ],
    "name:sco_x_preferred":[
        "\u00d6rnektepe"
    ],
    "name:slo_x_preferred":[
        "\u00d6rnektepe"
    ],
    "name:slv_x_preferred":[
        "\u00d6rnektepe"
    ],
    "name:spa_x_preferred":[
        "\u00d6rnektepe"
    ],
    "name:swe_x_preferred":[
        "\u00d6rnektepe"
    ],
    "name:tgl_x_preferred":[
        "\u00d6rnektepe"
    ],
    "name:tur_x_preferred":[
        "\u00d6rnektepe"
    ],
    "name:war_x_preferred":[
        "\u00d6rnektepe"
    ],
    "qs:name":"\u00d6rnektepe",
    "qs:name_adm0":"Turkey",
    "qs:name_adm1":"\u0130stanbul",
    "qs:photos":465,
    "qs:photos_1k":94,
    "qs:photos_9k":2,
    "qs:photos_9r":5,
    "qs:photos_all":465,
    "qs:photos_sr":7,
    "qs:placetype":"Suburb",
    "qs:pop_sr":"0",
    "wof:name":"\u00d6rnektepe",
    "wof:placetype":"neighbourhood"
},
  "geometry": {"coordinates":[28.948545,41.060132],"type":"Point"}
}