{
  "type": "Feature",
  "properties": {
    "gn:admin1_code":"74",
    "gn:asciiname":"Dalbasti",
    "gn:country_code":"TR",
    "gn:dem":1510,
    "gn:feature_class":"P",
    "gn:feature_code":"PPL",
    "gn:name":"Dalbast\u0131",
    "gn:population":0,
    "gn:timezone":"Europe/Istanbul",
    "iso:country":"TR",
    "name:und_x_variant":[
        "Homar",
        "Humar",
        "Dalbast\u0131"
    ],
    "wof:name":"Dalbasti",
    "wof:placetype":"locality"
},
  "geometry": {"coordinates":[42.93899999999999,37.90434000000001],"type":"Point"}
}