{
  "type": "Feature",
  "properties": {
    "gn:admin1_code":"55.0",
    "gn:asciiname":"Ordukoy",
    "gn:country_code":"TR",
    "gn:dem":40,
    "gn:feature_class":"P",
    "gn:feature_code":"PPL",
    "gn:name":"Orduk\u00f6y",
    "gn:population":0,
    "gn:timezone":"Europe/Istanbul",
    "iso:country":"TR",
    "name:rus_x_preferred":[
        "\u041e\u0440\u0434\u0443"
    ],
    "name:und_x_variant":[
        "Orduk\u00f6y",
        "Ordu"
    ],
    "wof:name":"Ordukoy",
    "wof:placetype":"locality"
},
  "geometry": {"coordinates":[36.70164000000001,41.09403],"type":"Point"}
}