{
  "type": "Feature",
  "properties": {
    "gn:admin1_code":"64",
    "gn:asciiname":"Hacimahmut",
    "gn:country_code":"TR",
    "gn:dem":851,
    "gn:feature_class":"P",
    "gn:feature_code":"PPL",
    "gn:name":"Hac\u0131mahmut",
    "gn:population":0,
    "gn:timezone":"Europe/Istanbul",
    "iso:country":"TR",
    "name:tur_x_preferred":[
        "Hac\u0131mahmut"
    ],
    "wof:name":"Hacimahmut",
    "wof:placetype":"locality"
},
  "geometry": {"coordinates":[28.98836,38.50459],"type":"Point"}
}