{
  "type": "Feature",
  "properties": {
    "gn:admin1_code":"35",
    "gn:asciiname":"Buyukkomurcu",
    "gn:country_code":"TR",
    "gn:dem":681,
    "gn:feature_class":"P",
    "gn:feature_code":"PPL",
    "gn:name":"B\u00fcy\u00fckk\u00f6m\u00fcrc\u00fc",
    "gn:population":0,
    "gn:timezone":"Europe/Istanbul",
    "iso:country":"TR",
    "name:und_x_variant":[
        "K\u00f6m\u00fcrc\u00fc",
        "B\u00fcy\u00fckk\u00f6m\u00fcrc\u00fc"
    ],
    "wof:name":"Buyukkomurcu",
    "wof:placetype":"locality"
},
  "geometry": {"coordinates":[27.76024,38.01992],"type":"Point"}
}