{
  "type": "Feature",
  "properties": {
    "gn:admin1_code":"43.0",
    "gn:asciiname":"Ahiler",
    "gn:country_code":"TR",
    "gn:dem":1106,
    "gn:feature_class":"P",
    "gn:feature_code":"PPL",
    "gn:name":"Ahiler",
    "gn:population":0,
    "gn:timezone":"Europe/Istanbul",
    "iso:country":"TR",
    "name:und_x_variant":[
        "Ah\u0131lar"
    ],
    "wof:name":"Ahiler",
    "wof:placetype":"locality"
},
  "geometry": {"coordinates":[30.229,39.25944000000001],"type":"Point"}
}