{
  "type": "Feature",
  "properties": {
    "gn:admin1_code":"19.0",
    "gn:asciiname":"Yukari Obrgu",
    "gn:country_code":"TR",
    "gn:dem":1263,
    "gn:feature_class":"P",
    "gn:feature_code":"PPL",
    "gn:name":"Yukar\u0131 Obr\u011fu",
    "gn:population":0,
    "gn:timezone":"Europe/Istanbul",
    "iso:country":"TR",
    "name:tur_x_preferred":[
        "Yukar\u0131 Obr\u011fu"
    ],
    "name:und_x_variant":[
        "Kalise"
    ],
    "wof:name":"Yukari Obrgu",
    "wof:placetype":"locality"
},
  "geometry": {"coordinates":[34.47565,41.02642],"type":"Point"}
}