{
  "type": "Feature",
  "properties": {
    "gn:admin1_code":"16",
    "gn:asciiname":"Zaferiye",
    "gn:country_code":"TR",
    "gn:dem":906,
    "gn:feature_class":"P",
    "gn:feature_code":"PPL",
    "gn:name":"Zaferiye",
    "gn:population":0,
    "gn:timezone":"Europe/Istanbul",
    "iso:country":"TR",
    "name:tur_x_preferred":[
        "Zaferiye"
    ],
    "wof:name":"Zaferiye",
    "wof:placetype":"locality"
},
  "geometry": {"coordinates":[28.81826,39.75315],"type":"Point"}
}