{
  "type": "Feature",
  "properties": {
    "gn:admin1_code":"83.0",
    "gn:asciiname":"Gollu",
    "gn:country_code":"TR",
    "gn:dem":912,
    "gn:feature_class":"P",
    "gn:feature_code":"PPL",
    "gn:name":"G\u00f6ll\u00fc",
    "gn:population":0,
    "gn:timezone":"Europe/Istanbul",
    "iso:country":"TR",
    "name:azb_x_preferred":[
        "\u06af\u0648\u0644\u0644\u0648(\u0646\u0645\u06cc\u0646)"
    ],
    "name:ceb_x_preferred":[
        "Kol\u0101l\u016b"
    ],
    "name:fas_x_preferred":[
        "\u06af\u0644\u200c\u0644\u0648"
    ],
    "name:msa_x_preferred":[
        "Gollu"
    ],
    "name:mzn_x_preferred":[
        "\u06af\u0644\u200c\u0644\u0648"
    ],
    "name:swe_x_preferred":[
        "Kol\u0101l\u016b"
    ],
    "wof:name":"Gollu",
    "wof:placetype":"locality"
},
  "geometry": {"coordinates":[37.4141,37.3357],"type":"Point"}
}