{
  "type": "Feature",
  "properties": {
    "gn:admin1_code":"14",
    "gn:asciiname":"Yukarikuldan",
    "gn:country_code":"TR",
    "gn:dem":1064,
    "gn:feature_class":"P",
    "gn:feature_code":"PPL",
    "gn:name":"Yukar\u0131kuldan",
    "gn:population":0,
    "gn:timezone":"Europe/Istanbul",
    "iso:country":"TR",
    "wof:name":"Yukarikuldan",
    "wof:placetype":"locality"
},
  "geometry": {"coordinates":[32.02023,40.7605],"type":"Point"}
}