{
  "type": "Feature",
  "properties": {
    "gn:admin1_code":"35",
    "gn:asciiname":"Kodukburun",
    "gn:country_code":"TR",
    "gn:dem":505,
    "gn:feature_class":"P",
    "gn:feature_code":"PPL",
    "gn:name":"Kodukburun",
    "gn:population":0,
    "gn:timezone":"Europe/Istanbul",
    "iso:country":"TR",
    "name:tur_x_preferred":[
        "Kodukburun"
    ],
    "wof:name":"Kodukburun",
    "wof:placetype":"locality"
},
  "geometry": {"coordinates":[27.34608,39.04064],"type":"Point"}
}