{
  "type": "Feature",
  "properties": {
    "gn:admin1_code":"02",
    "gn:asciiname":"Seke",
    "gn:country_code":"TR",
    "gn:dem":563,
    "gn:feature_class":"P",
    "gn:feature_code":"PPL",
    "gn:name":"Seke",
    "gn:population":0,
    "gn:timezone":"Europe/Istanbul",
    "iso:country":"TR",
    "name:und_x_variant":[
        "Sek\u00fck",
        "Be\u015fa\u011fa\u00e7"
    ],
    "wof:name":"Seke",
    "wof:placetype":"locality"
},
  "geometry": {"coordinates":[38.69085,37.70404],"type":"Point"}
}