{
  "type": "Feature",
  "properties": {
    "gn:admin1_code":"46",
    "gn:asciiname":"Buyuktatli",
    "gn:country_code":"TR",
    "gn:dem":1560,
    "gn:feature_class":"P",
    "gn:feature_code":"PPL",
    "gn:name":"B\u00fcy\u00fcktatl\u0131",
    "gn:population":0,
    "gn:timezone":"Europe/Istanbul",
    "iso:country":"TR",
    "name:und_x_variant":[
        "B\u00fcy\u00fcktatlar",
        "B\u00fcy\u00fcktatl\u0131"
    ],
    "wof:name":"Buyuktatli",
    "wof:placetype":"locality"
},
  "geometry": {"coordinates":[36.97883,38.48998],"type":"Point"}
}