{
  "type": "Feature",
  "properties": {
    "gn:admin1_code":"09",
    "gn:asciiname":"Selatin",
    "gn:country_code":"TR",
    "gn:dem":373,
    "gn:feature_class":"P",
    "gn:feature_code":"PPL",
    "gn:name":"Sel\u00e2tin",
    "gn:population":0,
    "gn:timezone":"Europe/Istanbul",
    "iso:country":"TR",
    "wof:name":"Selatin",
    "wof:placetype":"locality"
},
  "geometry": {"coordinates":[27.49833,37.96972],"type":"Point"}
}