{
  "type": "Feature",
  "properties": {
    "gn:admin1_code":"68",
    "gn:asciiname":"Gulbagi",
    "gn:country_code":"TR",
    "gn:dem":1112,
    "gn:feature_class":"P",
    "gn:feature_code":"PPL",
    "gn:name":"G\u00fclba\u011f\u0131",
    "gn:population":0,
    "gn:timezone":"Europe/Istanbul",
    "iso:country":"TR",
    "name:und_x_variant":[
        "G\u00fclba\u011f\u0131",
        "T\u0131ra\u015f"
    ],
    "wof:name":"Gulbagi",
    "wof:placetype":"locality"
},
  "geometry": {"coordinates":[32.92562,39.34443],"type":"Point"}
}