{
  "type": "Feature",
  "properties": {
    "gn:admin1_code":"24.0",
    "gn:asciiname":"Yaylabeli",
    "gn:country_code":"TR",
    "gn:dem":1932,
    "gn:feature_class":"P",
    "gn:feature_code":"PPL",
    "gn:name":"Yaylabeli",
    "gn:population":0,
    "gn:timezone":"Europe/Istanbul",
    "iso:country":"TR",
    "name:tur_x_preferred":[
        "Yaylabeli"
    ],
    "wof:name":"Yaylabeli",
    "wof:placetype":"locality"
},
  "geometry": {"coordinates":[38.9418,39.9589],"type":"Point"}
}