{
  "type": "Feature",
  "properties": {
    "gn:admin1_code":"76",
    "gn:asciiname":"Cukurca",
    "gn:country_code":"TR",
    "gn:dem":1020,
    "gn:feature_class":"P",
    "gn:feature_code":"PPL",
    "gn:name":"\u00c7ukurca",
    "gn:population":0,
    "gn:timezone":"Europe/Istanbul",
    "iso:country":"TR",
    "name:und_x_variant":[
        "\u00c7ukurca",
        "\u00c7\u0131rr\u0131"
    ],
    "wof:name":"Cukurca",
    "wof:placetype":"locality"
},
  "geometry": {"coordinates":[41.64507,38.22465],"type":"Point"}
}