{
  "type": "Feature",
  "properties": {
    "gn:admin1_code":"31",
    "gn:asciiname":"Dedecinar Isk.",
    "gn:country_code":"TR",
    "gn:dem":406,
    "gn:feature_class":"P",
    "gn:feature_code":"PPL",
    "gn:name":"Dede\u00e7\u0131nar \u0130sk.",
    "gn:population":0,
    "gn:timezone":"Europe/Istanbul",
    "iso:country":"TR",
    "name:tur_x_preferred":[
        "Dede\u00e7\u0131nar \u0130sk."
    ],
    "wof:name":"Dedecinar Isk.",
    "wof:placetype":"locality"
},
  "geometry": {"coordinates":[36.3999,36.63388],"type":"Point"}
}