{
  "type": "Feature",
  "properties": {
    "gn:admin1_code":"71",
    "gn:asciiname":"Gonen",
    "gn:country_code":"TR",
    "gn:dem":1256,
    "gn:feature_class":"P",
    "gn:feature_code":"PPL",
    "gn:name":"G\u00f6nen",
    "gn:population":0,
    "gn:timezone":"Europe/Istanbul",
    "iso:country":"TR",
    "name:ceb_x_preferred":[
        "Gonen"
    ],
    "name:ces_x_preferred":[
        "Gonen"
    ],
    "name:fra_x_preferred":[
        "Gonen"
    ],
    "name:heb_x_preferred":[
        "\u05d2\u05d5\u05e0\u05df"
    ],
    "name:nno_x_preferred":[
        "Gonen"
    ],
    "name:pol_x_preferred":[
        "Gonen"
    ],
    "wof:name":"Gonen",
    "wof:placetype":"locality"
},
  "geometry": {"coordinates":[31.86038,37.76858],"type":"Point"}
}