{
  "type": "Feature",
  "properties": {
    "gn:admin1_code":"63.0",
    "gn:asciiname":"Akincak",
    "gn:country_code":"TR",
    "gn:dem":640,
    "gn:feature_class":"P",
    "gn:feature_code":"PPL",
    "gn:name":"Ak\u0131ncak",
    "gn:population":0,
    "gn:timezone":"Europe/Istanbul",
    "iso:country":"TR",
    "name:tur_x_preferred":[
        "Ak\u0131ncak"
    ],
    "wof:name":"Akincak",
    "wof:placetype":"locality"
},
  "geometry": {"coordinates":[39.15,37.46667],"type":"Point"}
}