{
  "type": "Feature",
  "properties": {
    "gn:admin1_code":"63",
    "gn:asciiname":"Buyuk Salkim",
    "gn:country_code":"TR",
    "gn:dem":709,
    "gn:feature_class":"P",
    "gn:feature_code":"PPL",
    "gn:name":"B\u00fcy\u00fck Salk\u0131m",
    "gn:population":0,
    "gn:timezone":"Europe/Istanbul",
    "iso:country":"TR",
    "name:tur_x_preferred":[
        "B\u00fcy\u00fck Salk\u0131m"
    ],
    "wof:name":"Buyuk Salkim",
    "wof:placetype":"locality"
},
  "geometry": {"coordinates":[38.89891,37.36475],"type":"Point"}
}