{
  "type": "Feature",
  "properties": {
    "gn:admin1_code":"43",
    "gn:asciiname":"Arifler",
    "gn:country_code":"TR",
    "gn:dem":1220,
    "gn:feature_class":"P",
    "gn:feature_code":"PPL",
    "gn:name":"Arifler",
    "gn:population":0,
    "gn:timezone":"Europe/Istanbul",
    "iso:country":"TR",
    "name:tur_x_preferred":[
        "Arifler"
    ],
    "wof:name":"Arifler",
    "wof:placetype":"locality"
},
  "geometry": {"coordinates":[29.70705,39.68748],"type":"Point"}
}