{
  "type": "Feature",
  "properties": {
    "gn:admin1_code":"16",
    "gn:asciiname":"Ebe",
    "gn:country_code":"TR",
    "gn:dem":268,
    "gn:feature_class":"P",
    "gn:feature_code":"PPL",
    "gn:name":"Ebe",
    "gn:population":0,
    "gn:timezone":"Europe/Istanbul",
    "iso:country":"TR",
    "name:ceb_x_preferred":[
        "Ebe"
    ],
    "name:fra_x_preferred":[
        "EBE"
    ],
    "name:swe_x_preferred":[
        "Ebe"
    ],
    "name:tur_x_preferred":[
        "Ebe"
    ],
    "wof:name":"Ebe",
    "wof:placetype":"locality"
},
  "geometry": {"coordinates":[29.75001,40.25924000000001],"type":"Point"}
}