{
  "type": "Feature",
  "properties": {
    "gn:admin1_code":"76.0",
    "gn:asciiname":"Bulgurlu",
    "gn:country_code":"TR",
    "gn:dem":691,
    "gn:feature_class":"P",
    "gn:feature_code":"PPL",
    "gn:name":"Bulgurlu",
    "gn:population":0,
    "gn:timezone":"Europe/Istanbul",
    "iso:country":"TR",
    "wof:name":"Bulgurlu",
    "wof:placetype":"locality"
},
  "geometry": {"coordinates":[41.29777,38.1194],"type":"Point"}
}