{
  "type": "Feature",
  "properties": {
    "gn:admin1_code":"46",
    "gn:asciiname":"Bozhuyuk",
    "gn:country_code":"TR",
    "gn:dem":1535,
    "gn:feature_class":"P",
    "gn:feature_code":"PPL",
    "gn:name":"Bozh\u00fcy\u00fck",
    "gn:population":0,
    "gn:timezone":"Europe/Istanbul",
    "iso:country":"TR",
    "wof:name":"Bozhuyuk",
    "wof:placetype":"locality"
},
  "geometry": {"coordinates":[36.50061,38.14548],"type":"Point"}
}