{
  "type": "Feature",
  "properties": {
    "gn:admin1_code":"44",
    "gn:asciiname":"Bicir",
    "gn:country_code":"TR",
    "gn:dem":1304,
    "gn:feature_class":"P",
    "gn:feature_code":"PPL",
    "gn:name":"B\u0131c\u0131r",
    "gn:population":0,
    "gn:timezone":"Europe/Istanbul",
    "iso:country":"TR",
    "name:tur_x_preferred":[
        "B\u0131c\u0131r"
    ],
    "wof:name":"Bicir",
    "wof:placetype":"locality"
},
  "geometry": {"coordinates":[37.57362,38.92246],"type":"Point"}
}