{
  "type": "Feature",
  "properties": {
    "gn:admin1_code":"25.0",
    "gn:asciiname":"Kuslu",
    "gn:country_code":"TR",
    "gn:dem":1552,
    "gn:feature_class":"P",
    "gn:feature_code":"PPL",
    "gn:name":"Ku\u015flu",
    "gn:population":0,
    "gn:timezone":"Europe/Istanbul",
    "iso:country":"TR",
    "wof:name":"Kuslu",
    "wof:placetype":"locality"
},
  "geometry": {"coordinates":[41.08074000000001,40.52721],"type":"Point"}
}