{
  "type": "Feature",
  "properties": {
    "gn:admin1_code":"70",
    "gn:asciiname":"Genisdere",
    "gn:country_code":"TR",
    "gn:dem":1296,
    "gn:feature_class":"P",
    "gn:feature_code":"PPL",
    "gn:name":"Geni\u015fdere",
    "gn:population":0,
    "gn:timezone":"Europe/Istanbul",
    "iso:country":"TR",
    "wof:name":"Genisdere",
    "wof:placetype":"locality"
},
  "geometry": {"coordinates":[44.02639,37.33],"type":"Point"}
}