{
  "type": "Feature",
  "properties": {
    "gn:admin1_code":"66",
    "gn:asciiname":"Divanli",
    "gn:country_code":"TR",
    "gn:dem":1242,
    "gn:feature_class":"P",
    "gn:feature_code":"PPL",
    "gn:name":"Divanl\u0131",
    "gn:population":0,
    "gn:timezone":"Europe/Istanbul",
    "iso:country":"TR",
    "wof:name":"Divanli",
    "wof:placetype":"locality"
},
  "geometry": {"coordinates":[34.84135999999999,39.75293],"type":"Point"}
}