{
  "type": "Feature",
  "properties": {
    "gn:admin1_code":"38",
    "gn:asciiname":"Ciftlik",
    "gn:country_code":"TR",
    "gn:dem":996,
    "gn:feature_class":"P",
    "gn:feature_code":"PPL",
    "gn:name":"\u00c7iftlik",
    "gn:population":0,
    "gn:timezone":"Europe/Istanbul",
    "iso:country":"TR",
    "wof:name":"Ciftlik",
    "wof:placetype":"locality"
},
  "geometry": {"coordinates":[35.21667,38.81667],"type":"Point"}
}