{
  "type": "Feature",
  "properties": {
    "gn:admin1_code":"10.0",
    "gn:asciiname":"Ilhankoy",
    "gn:country_code":"TR",
    "gn:dem":5,
    "gn:feature_class":"P",
    "gn:feature_code":"PPL",
    "gn:name":"\u0130lhank\u00f6y",
    "gn:population":0,
    "gn:timezone":"Europe/Istanbul",
    "iso:country":"TR",
    "name:und_x_variant":[
        "\u0130lhan",
        "Herek",
        "\u0130lhank\u00f6y"
    ],
    "wof:name":"Ilhankoy",
    "wof:placetype":"locality"
},
  "geometry": {"coordinates":[27.69598,40.50578],"type":"Point"}
}