{
  "type": "Feature",
  "properties": {
    "gn:admin1_code":"68.0",
    "gn:asciiname":"Imrendi",
    "gn:country_code":"TR",
    "gn:dem":944,
    "gn:feature_class":"P",
    "gn:feature_code":"PPL",
    "gn:name":"Imrendi",
    "gn:population":0,
    "gn:timezone":"Europe/Istanbul",
    "iso:country":"TR",
    "name:und_x_variant":[
        "E\u011frendi",
        "\u0130\u011frendi",
        "Ekrendi",
        "Imrendi"
    ],
    "wof:name":"Imrendi",
    "wof:placetype":"locality"
},
  "geometry": {"coordinates":[32.66882,40.13528],"type":"Point"}
}