{
  "type": "Feature",
  "properties": {
    "gn:admin1_code":"81",
    "gn:asciiname":"Buyukkapili",
    "gn:country_code":"TR",
    "gn:dem":15,
    "gn:feature_class":"P",
    "gn:feature_code":"PPL",
    "gn:name":"B\u00fcy\u00fckkap\u0131l\u0131",
    "gn:population":0,
    "gn:timezone":"Europe/Istanbul",
    "iso:country":"TR",
    "wof:name":"Buyukkapili",
    "wof:placetype":"locality"
},
  "geometry": {"coordinates":[35.56667,36.87233],"type":"Point"}
}