{
  "type": "Feature",
  "properties": {
    "gn:admin1_code":"85",
    "gn:asciiname":"Omerbeyler",
    "gn:country_code":"TR",
    "gn:dem":141,
    "gn:feature_class":"P",
    "gn:feature_code":"PPL",
    "gn:name":"\u00d6merbeyler",
    "gn:population":0,
    "gn:timezone":"Europe/Istanbul",
    "iso:country":"TR",
    "wof:name":"Omerbeyler",
    "wof:placetype":"locality"
},
  "geometry": {"coordinates":[32.19243,41.3965],"type":"Point"}
}