{
  "type": "Feature",
  "properties": {
    "gn:admin1_code":"53.0",
    "gn:asciiname":"Sirtkoy",
    "gn:country_code":"TR",
    "gn:dem":373,
    "gn:feature_class":"P",
    "gn:feature_code":"PPL",
    "gn:name":"S\u0131rtk\u00f6y",
    "gn:population":0,
    "gn:timezone":"Europe/Istanbul",
    "iso:country":"TR",
    "wof:name":"Sirtkoy",
    "wof:placetype":"locality"
},
  "geometry": {"coordinates":[40.80085,41.06232],"type":"Point"}
}