{
  "type": "Feature",
  "properties": {
    "gn:admin1_code":"46.0",
    "gn:asciiname":"Eldelek",
    "gn:country_code":"TR",
    "gn:dem":1159,
    "gn:feature_class":"P",
    "gn:feature_code":"PPL",
    "gn:name":"Eldelek",
    "gn:population":0,
    "gn:timezone":"Europe/Istanbul",
    "iso:country":"TR",
    "wof:name":"Eldelek",
    "wof:placetype":"locality"
},
  "geometry": {"coordinates":[37.23825,38.25863],"type":"Point"}
}