{
  "type": "Feature",
  "properties": {
    "gn:admin1_code":"57.0",
    "gn:asciiname":"Kadilar",
    "gn:country_code":"TR",
    "gn:dem":549,
    "gn:feature_class":"P",
    "gn:feature_code":"PPL",
    "gn:name":"Kad\u0131lar",
    "gn:population":0,
    "gn:timezone":"Europe/Istanbul",
    "iso:country":"TR",
    "wof:name":"Kadilar",
    "wof:placetype":"locality"
},
  "geometry": {"coordinates":[34.75,41.38333],"type":"Point"}
}