{
  "type": "Feature",
  "properties": {
    "gn:admin1_code":"34.0",
    "gn:asciiname":"Aydinli",
    "gn:country_code":"TR",
    "gn:dem":77,
    "gn:feature_class":"P",
    "gn:feature_code":"PPL",
    "gn:name":"Ayd\u0131nl\u0131",
    "gn:population":0,
    "gn:timezone":"Europe/Istanbul",
    "iso:country":"TR",
    "name:tur_x_preferred":[
        "Ayd\u0131nl\u0131"
    ],
    "wof:name":"Aydinli",
    "wof:placetype":"locality"
},
  "geometry": {"coordinates":[29.32992,40.87048],"type":"Point"}
}