{
  "type": "Feature",
  "properties": {
    "gn:admin1_code":"81",
    "gn:asciiname":"Kogukcinar",
    "gn:country_code":"TR",
    "gn:dem":1675,
    "gn:feature_class":"P",
    "gn:feature_code":"PPL",
    "gn:name":"Ko\u011fuk\u00e7\u0131nar",
    "gn:population":0,
    "gn:timezone":"Europe/Istanbul",
    "iso:country":"TR",
    "name:und_x_variant":[
        "Ko\u011fuk\u00e7\u0131nar",
        "Kovuk\u00e7\u0131nar"
    ],
    "wof:name":"Kogukcinar",
    "wof:placetype":"locality"
},
  "geometry": {"coordinates":[35.99943,37.82648],"type":"Point"}
}