{
  "type": "Feature",
  "properties": {
    "gn:admin1_code":"55.0",
    "gn:asciiname":"Avut",
    "gn:country_code":"TR",
    "gn:dem":45,
    "gn:feature_class":"P",
    "gn:feature_code":"PPL",
    "gn:name":"Avut",
    "gn:population":0,
    "gn:timezone":"Europe/Istanbul",
    "iso:country":"TR",
    "wof:name":"Avut",
    "wof:placetype":"locality"
},
  "geometry": {"coordinates":[36.83543,41.12988],"type":"Point"}
}