{
  "type": "Feature",
  "properties": {
    "gn:admin1_code":"20",
    "gn:asciiname":"Narlidere Mevki",
    "gn:country_code":"TR",
    "gn:dem":470,
    "gn:feature_class":"P",
    "gn:feature_code":"PPL",
    "gn:name":"Narl\u0131dere Mevki",
    "gn:population":0,
    "gn:timezone":"Europe/Istanbul",
    "iso:country":"TR",
    "name:tur_x_preferred":[
        "Narl\u0131dere Mevki"
    ],
    "name:tur_x_variant":[
        "Narl\u0131dere",
        "Direbol"
    ],
    "wof:name":"Narlidere Mevki",
    "wof:placetype":"locality"
},
  "geometry": {"coordinates":[28.94378,38.0881],"type":"Point"}
}