{
  "type": "Feature",
  "properties": {
    "gn:admin1_code":"85.0",
    "gn:asciiname":"Yazioren",
    "gn:country_code":"TR",
    "gn:dem":467,
    "gn:feature_class":"P",
    "gn:feature_code":"PPL",
    "gn:name":"Yaz\u0131\u00f6ren",
    "gn:population":0,
    "gn:timezone":"Europe/Istanbul",
    "iso:country":"TR",
    "name:und_x_variant":[
        "Kabag\u00f6z",
        "Kabak\u00f6z",
        "Yaz\u0131\u00f6ren"
    ],
    "wof:name":"Yazioren",
    "wof:placetype":"locality"
},
  "geometry": {"coordinates":[31.81277,41.24478],"type":"Point"}
}