{
  "type": "Feature",
  "properties": {
    "gn:admin1_code":"16",
    "gn:asciiname":"Karincali",
    "gn:country_code":"TR",
    "gn:dem":428,
    "gn:feature_class":"P",
    "gn:feature_code":"PPL",
    "gn:name":"Kar\u0131ncal\u0131",
    "gn:population":2087,
    "gn:timezone":"Europe/Istanbul",
    "iso:country":"TR",
    "name:ceb_x_preferred":[
        "Kar\u0131ncal\u0131"
    ],
    "name:und_x_variant":[
        "Kar\u0131ncal\u0131"
    ],
    "name:vie_x_preferred":[
        "Kar\u0131ncal\u0131"
    ],
    "wof:name":"Karincali",
    "wof:placetype":"locality",
    "wof:population":2087
},
  "geometry": {"coordinates":[28.85894,39.97118],"type":"Point"}
}