{
  "type": "Feature",
  "properties": {
    "gn:admin1_code":"16",
    "gn:asciiname":"Yorucekler",
    "gn:country_code":"TR",
    "gn:dem":347,
    "gn:feature_class":"P",
    "gn:feature_code":"PPL",
    "gn:name":"Y\u00f6r\u00fccekler",
    "gn:population":0,
    "gn:timezone":"Europe/Istanbul",
    "iso:country":"TR",
    "name:und_x_variant":[
        "Y\u00f6r\u00fccekler",
        "Y\u00fcr\u00fccekler"
    ],
    "wof:name":"Yorucekler",
    "wof:placetype":"locality"
},
  "geometry": {"coordinates":[28.89016,39.95588],"type":"Point"}
}