{
  "type": "Feature",
  "properties": {
    "gn:admin1_code":"83",
    "gn:asciiname":"Ballik",
    "gn:country_code":"TR",
    "gn:dem":710,
    "gn:feature_class":"P",
    "gn:feature_code":"PPL",
    "gn:name":"Ball\u0131k",
    "gn:population":0,
    "gn:timezone":"Europe/Istanbul",
    "iso:country":"TR",
    "wof:name":"Ballik",
    "wof:placetype":"locality"
},
  "geometry": {"coordinates":[37.50623,37.32684],"type":"Point"}
}