{
  "type": "Feature",
  "properties": {
    "gn:admin1_code":"32.0",
    "gn:asciiname":"Kirgedigi Yaylasi",
    "gn:country_code":"TR",
    "gn:dem":1862,
    "gn:feature_class":"P",
    "gn:feature_code":"PPL",
    "gn:name":"K\u0131rgedi\u011fi Yaylas\u0131",
    "gn:population":0,
    "gn:timezone":"Europe/Istanbul",
    "iso:country":"TR",
    "wof:name":"Kirgedigi Yaylasi",
    "wof:placetype":"locality"
},
  "geometry": {"coordinates":[32.69297,36.39597],"type":"Point"}
}