{
  "type": "Feature",
  "properties": {
    "gn:admin1_code":"83.0",
    "gn:asciiname":"Hacikoy",
    "gn:cc2":"TR",
    "gn:country_code":"TR",
    "gn:dem":934,
    "gn:feature_class":"P",
    "gn:feature_code":"PPL",
    "gn:name":"Hac\u0131k\u00f6y",
    "gn:population":0,
    "gn:timezone":"Europe/Istanbul",
    "iso:country":"TR",
    "name:rus_x_preferred":[
        "Khadzhik\u00eby"
    ],
    "name:und_x_variant":[
        "Hac\u0131k\u00f6y"
    ],
    "wof:name":"Hacikoy",
    "wof:placetype":"locality"
},
  "geometry": {"coordinates":[37.10333,36.96667],"type":"Point"}
}