{
  "type": "Feature",
  "properties": {
    "gn:admin1_code":"03",
    "gn:asciiname":"Yukari Caybelen",
    "gn:country_code":"TR",
    "gn:dem":1274,
    "gn:feature_class":"P",
    "gn:feature_code":"PPL",
    "gn:name":"Yukar\u0131 \u00c7aybelen",
    "gn:population":0,
    "gn:timezone":"Europe/Istanbul",
    "iso:country":"TR",
    "name:tur_x_preferred":[
        "Yukar\u0131 \u00c7aybelen"
    ],
    "name:und_x_variant":[
        "Yukar\u0131 Ma\u00e7akl\u0131",
        "Yukar\u0131\u00e7aybelen"
    ],
    "wof:name":"Yukari Caybelen",
    "wof:placetype":"locality"
},
  "geometry": {"coordinates":[30.92389,38.83667],"type":"Point"}
}