{
  "type": "Feature",
  "properties": {
    "gn:admin1_code":"03",
    "gn:asciiname":"Cayirbag",
    "gn:cc2":"TR",
    "gn:country_code":"TR",
    "gn:dem":1017,
    "gn:feature_class":"P",
    "gn:feature_code":"PPL",
    "gn:name":"\u00c7ay\u0131rba\u011f",
    "gn:population":0,
    "gn:timezone":"Europe/Istanbul",
    "iso:country":"TR",
    "name:und_x_variant":[
        "Sipsin",
        "\u00c7ay\u0131rba\u011f"
    ],
    "wof:name":"Cayirbag",
    "wof:placetype":"locality"
},
  "geometry": {"coordinates":[30.53167,38.85],"type":"Point"}
}