{
  "type": "Feature",
  "properties": {
    "gn:admin1_code":"52.0",
    "gn:asciiname":"Senaiye",
    "gn:country_code":"TR",
    "gn:dem":422,
    "gn:feature_class":"P",
    "gn:feature_code":"PPL",
    "gn:name":"Senaiye",
    "gn:population":0,
    "gn:timezone":"Europe/Istanbul",
    "iso:country":"TR",
    "name:und_x_variant":[
        "\u00d6v\u00fcnd\u00fck"
    ],
    "wof:name":"Senaiye",
    "wof:placetype":"locality"
},
  "geometry": {"coordinates":[37.85249,40.8893],"type":"Point"}
}