{
  "type": "Feature",
  "properties": {
    "gn:admin1_code":"62",
    "gn:asciiname":"Goneli",
    "gn:country_code":"TR",
    "gn:dem":1776,
    "gn:feature_class":"P",
    "gn:feature_code":"PPL",
    "gn:name":"G\u00f6neli",
    "gn:population":0,
    "gn:timezone":"Europe/Istanbul",
    "iso:country":"TR",
    "name:und_x_variant":[
        "G\u00f6neli",
        "Bayburtlu"
    ],
    "wof:name":"Goneli",
    "wof:placetype":"locality"
},
  "geometry": {"coordinates":[39.84316,39.51651],"type":"Point"}
}