{
  "type": "Feature",
  "properties": {
    "gn:admin1_code":"35",
    "gn:asciiname":"Denizli",
    "gn:country_code":"TR",
    "gn:dem":31,
    "gn:feature_class":"P",
    "gn:feature_code":"PPL",
    "gn:name":"Denizli",
    "gn:population":0,
    "gn:timezone":"Europe/Istanbul",
    "iso:country":"TR",
    "name:tur_x_preferred":[
        "Denizli"
    ],
    "wof:name":"Denizli",
    "wof:placetype":"locality"
},
  "geometry": {"coordinates":[26.76033,38.3795],"type":"Point"}
}