{
  "type": "Feature",
  "properties": {
    "gn:admin1_code":"71",
    "gn:asciiname":"Argithani",
    "gn:country_code":"TR",
    "gn:dem":1094,
    "gn:feature_class":"P",
    "gn:feature_code":"PPLA3",
    "gn:name":"Arg\u0131than\u0131",
    "gn:population":0,
    "gn:timezone":"Europe/Istanbul",
    "iso:country":"TR",
    "name:und_x_variant":[
        "Arg\u0131than",
        "Arg\u0131than\u0131"
    ],
    "wof:name":"Argithani",
    "wof:placetype":"locality"
},
  "geometry": {"coordinates":[31.71452,38.29259],"type":"Point"}
}