{
  "type": "Feature",
  "properties": {
    "gn:admin1_code":"09",
    "gn:asciiname":"Kurukoy",
    "gn:country_code":"TR",
    "gn:dem":90,
    "gn:feature_class":"P",
    "gn:feature_code":"PPL",
    "gn:name":"Kuruk\u00f6y",
    "gn:population":0,
    "gn:timezone":"Europe/Istanbul",
    "iso:country":"TR",
    "name:tur_x_preferred":[
        "Kuruk\u00f6y"
    ],
    "name:tur_x_variant":[
        "Kazanc\u0131"
    ],
    "wof:name":"Kurukoy",
    "wof:placetype":"locality"
},
  "geometry": {"coordinates":[28.07135,37.56098],"type":"Point"}
}