{
  "type": "Feature",
  "properties": {
    "gn:admin1_code":"52.0",
    "gn:asciiname":"Saraykoy",
    "gn:country_code":"TR",
    "gn:dem":250,
    "gn:feature_class":"P",
    "gn:feature_code":"PPL",
    "gn:name":"Sarayk\u00f6y",
    "gn:population":0,
    "gn:timezone":"Europe/Istanbul",
    "iso:country":"TR",
    "name:und_x_variant":[
        "Sarayk\u00f6y",
        "Saray"
    ],
    "wof:name":"Saraykoy",
    "wof:placetype":"locality"
},
  "geometry": {"coordinates":[37.75966,41.03166],"type":"Point"}
}