{
  "type": "Feature",
  "properties": {
    "gn:admin1_code":"25.0",
    "gn:asciiname":"Sogutyani",
    "gn:country_code":"TR",
    "gn:dem":1918,
    "gn:feature_class":"P",
    "gn:feature_code":"PPL",
    "gn:name":"S\u00f6\u011f\u00fctyan\u0131",
    "gn:population":0,
    "gn:timezone":"Europe/Istanbul",
    "iso:country":"TR",
    "name:tur_x_preferred":[
        "S\u00f6\u011f\u00fctyan\u0131"
    ],
    "wof:name":"Sogutyani",
    "wof:placetype":"locality"
},
  "geometry": {"coordinates":[41.39888,40.11842],"type":"Point"}
}