{
  "type": "Feature",
  "properties": {
    "gn:admin1_code":"83.0",
    "gn:asciiname":"Degirmencik",
    "gn:country_code":"TR",
    "gn:dem":580,
    "gn:feature_class":"P",
    "gn:feature_code":"PPL",
    "gn:name":"De\u011firmencik",
    "gn:population":0,
    "gn:timezone":"Europe/Istanbul",
    "iso:country":"TR",
    "name:und_x_variant":[
        "Degirmendzhik",
        "De\u011firmencik"
    ],
    "wof:name":"Degirmencik",
    "wof:placetype":"locality"
},
  "geometry": {"coordinates":[36.61267,37.00297],"type":"Point"}
}