{
  "type": "Feature",
  "properties": {
    "gn:admin1_code":"11.0",
    "gn:asciiname":"Ulucak",
    "gn:country_code":"TR",
    "gn:dem":1051,
    "gn:feature_class":"P",
    "gn:feature_code":"PPL",
    "gn:name":"Ulucak",
    "gn:population":0,
    "gn:timezone":"Europe/Istanbul",
    "iso:country":"TR",
    "name:tur_x_preferred":[
        "Ulucak"
    ],
    "wof:name":"Ulucak",
    "wof:placetype":"locality"
},
  "geometry": {"coordinates":[30.52621,40.27025],"type":"Point"}
}