{
  "type": "Feature",
  "properties": {
    "gn:admin1_code":"13",
    "gn:asciiname":"Bahcedere",
    "gn:country_code":"TR",
    "gn:dem":1774,
    "gn:feature_class":"P",
    "gn:feature_code":"PPL",
    "gn:name":"Bah\u00e7edere",
    "gn:population":0,
    "gn:timezone":"Europe/Istanbul",
    "iso:country":"TR",
    "name:und_x_variant":[
        "Hask\u00fcnd\u00fcrk",
        "Hask\u00fcnd\u00fcr\u00fck",
        "Bah\u00e7edere"
    ],
    "wof:name":"Bahcedere",
    "wof:placetype":"locality"
},
  "geometry": {"coordinates":[42.6381,38.80052],"type":"Point"}
}