{
  "type": "Feature",
  "properties": {
    "gn:admin1_code":"13",
    "gn:asciiname":"Cemalettinkoy",
    "gn:country_code":"TR",
    "gn:dem":2070,
    "gn:feature_class":"P",
    "gn:feature_code":"PPL",
    "gn:name":"Cemalettink\u00f6y",
    "gn:population":0,
    "gn:timezone":"Europe/Istanbul",
    "iso:country":"TR",
    "name:tur_x_preferred":[
        "Cemalettink\u00f6y"
    ],
    "name:und_x_variant":[
        "Cemaleddin",
        "Cemalettin"
    ],
    "wof:name":"Cemalettinkoy",
    "wof:placetype":"locality"
},
  "geometry": {"coordinates":[42.52524,38.82748],"type":"Point"}
}