{
  "type": "Feature",
  "properties": {
    "gn:admin1_code":"37.0",
    "gn:asciiname":"Samanci",
    "gn:country_code":"TR",
    "gn:dem":926,
    "gn:feature_class":"P",
    "gn:feature_code":"PPL",
    "gn:name":"Samanc\u0131",
    "gn:population":0,
    "gn:timezone":"Europe/Istanbul",
    "iso:country":"TR",
    "wof:name":"Samanci",
    "wof:placetype":"locality"
},
  "geometry": {"coordinates":[33.41002,41.67609],"type":"Point"}
}