{
  "type": "Feature",
  "properties": {
    "gn:admin1_code":"86.0",
    "gn:asciiname":"Omeraga",
    "gn:country_code":"TR",
    "gn:dem":2100,
    "gn:feature_class":"P",
    "gn:feature_code":"PPL",
    "gn:name":"\u00d6mera\u011fa",
    "gn:population":0,
    "gn:timezone":"Europe/Istanbul",
    "iso:country":"TR",
    "name:msa_x_preferred":[
        "\u00d6mera\u011fa"
    ],
    "name:tur_x_preferred":[
        "\u00d6mera\u011fa"
    ],
    "name:vie_x_preferred":[
        "\u00d6mera\u011fa"
    ],
    "wof:name":"Omeraga",
    "wof:placetype":"locality"
},
  "geometry": {"coordinates":[42.94703,40.96964000000001],"type":"Point"}
}