{
  "type": "Feature",
  "properties": {
    "gn:admin1_code":"72",
    "gn:asciiname":"Sultancayiri",
    "gn:country_code":"TR",
    "gn:dem":1100,
    "gn:feature_class":"P",
    "gn:feature_code":"PPL",
    "gn:name":"Sultan\u00e7ay\u0131r\u0131",
    "gn:population":0,
    "gn:timezone":"Europe/Istanbul",
    "iso:country":"TR",
    "name:tur_x_preferred":[
        "Sultan\u00e7ay\u0131r\u0131"
    ],
    "wof:name":"Sultancayiri",
    "wof:placetype":"locality"
},
  "geometry": {"coordinates":[40.675,37.39944000000001],"type":"Point"}
}