{
  "type": "Feature",
  "properties": {
    "gn:admin1_code":"90",
    "gn:asciiname":"Deliosman",
    "gn:country_code":"TR",
    "gn:dem":658,
    "gn:feature_class":"P",
    "gn:feature_code":"PPL",
    "gn:name":"Deliosman",
    "gn:population":0,
    "gn:timezone":"Europe/Istanbul",
    "iso:country":"TR",
    "wof:name":"Deliosman",
    "wof:placetype":"locality"
},
  "geometry": {"coordinates":[36.73806,36.8225],"type":"Point"}
}