{
  "type": "Feature",
  "properties": {
    "gn:admin1_code":"72.0",
    "gn:asciiname":"Harmankaya",
    "gn:country_code":"TR",
    "gn:dem":1064,
    "gn:feature_class":"P",
    "gn:feature_code":"PPL",
    "gn:name":"Harmankaya",
    "gn:population":0,
    "gn:timezone":"Europe/Istanbul",
    "iso:country":"TR",
    "name:tur_x_preferred":[
        "Harmankaya"
    ],
    "name:und_x_variant":[
        "Kevarin"
    ],
    "wof:name":"Harmankaya",
    "wof:placetype":"locality"
},
  "geometry": {"coordinates":[40.99489000000001,37.3191],"type":"Point"}
}