{
  "type": "Feature",
  "properties": {
    "gn:admin1_code":"26.0",
    "gn:asciiname":"Aydinci",
    "gn:country_code":"TR",
    "gn:dem":1262,
    "gn:feature_class":"P",
    "gn:feature_code":"PPL",
    "gn:name":"Ayd\u0131nc\u0131",
    "gn:population":0,
    "gn:timezone":"Europe/Istanbul",
    "iso:country":"TR",
    "name:und_x_variant":[
        "Ayd\u0131nc\u0131",
        "Ak\u0131\u015f\u0131k"
    ],
    "wof:name":"Aydinci",
    "wof:placetype":"locality"
},
  "geometry": {"coordinates":[31.41878,39.87193],"type":"Point"}
}