{
  "type": "Feature",
  "properties": {
    "gn:admin1_code":"14",
    "gn:asciiname":"Bulutlar",
    "gn:country_code":"TR",
    "gn:dem":1002,
    "gn:feature_class":"P",
    "gn:feature_code":"PPL",
    "gn:name":"Bulutlar",
    "gn:population":0,
    "gn:timezone":"Europe/Istanbul",
    "iso:country":"TR",
    "wof:name":"Bulutlar",
    "wof:placetype":"locality"
},
  "geometry": {"coordinates":[31.69902,40.80239],"type":"Point"}
}