{
  "type": "Feature",
  "properties": {
    "gn:admin1_code":"55.0",
    "gn:asciiname":"Sarialan",
    "gn:country_code":"TR",
    "gn:dem":686,
    "gn:feature_class":"P",
    "gn:feature_code":"PPL",
    "gn:name":"Sar\u0131alan",
    "gn:population":0,
    "gn:timezone":"Europe/Istanbul",
    "iso:country":"TR",
    "wof:name":"Sarialan",
    "wof:placetype":"locality"
},
  "geometry": {"coordinates":[35.99001,41.02334000000001],"type":"Point"}
}