{
  "type": "Feature",
  "properties": {
    "gn:admin1_code":"52.0",
    "gn:asciiname":"Ugurlu",
    "gn:country_code":"TR",
    "gn:dem":362,
    "gn:feature_class":"P",
    "gn:feature_code":"PPL",
    "gn:name":"U\u011furlu",
    "gn:population":0,
    "gn:timezone":"Europe/Istanbul",
    "iso:country":"TR",
    "wof:name":"Ugurlu",
    "wof:placetype":"locality"
},
  "geometry": {"coordinates":[37.16455,41.00439],"type":"Point"}
}