{
  "type": "Feature",
  "properties": {
    "gn:admin1_code":"46",
    "gn:asciiname":"Sogutdere",
    "gn:country_code":"TR",
    "gn:dem":1706,
    "gn:feature_class":"P",
    "gn:feature_code":"PPL",
    "gn:name":"S\u00f6\u011f\u00fctdere",
    "gn:population":0,
    "gn:timezone":"Europe/Istanbul",
    "iso:country":"TR",
    "name:und_x_variant":[
        "S\u00f6\u011f\u00fctdere K\u00f6y\u00fc",
        "S\u00f6\u011f\u00fctdere"
    ],
    "wof:name":"Sogutdere",
    "wof:placetype":"locality"
},
  "geometry": {"coordinates":[36.86066,38.53783],"type":"Point"}
}