{
  "type": "Feature",
  "properties": {
    "gn:admin1_code":"58",
    "gn:asciiname":"Ilicakoy",
    "gn:country_code":"TR",
    "gn:dem":1425,
    "gn:feature_class":"P",
    "gn:feature_code":"PPL",
    "gn:name":"Il\u0131cak\u00f6y",
    "gn:population":0,
    "gn:timezone":"Europe/Istanbul",
    "iso:country":"TR",
    "name:tur_x_preferred":[
        "Il\u0131cak\u00f6y"
    ],
    "name:und_x_variant":[
        "Il\u0131ca K\u00f6y\u00fc",
        "Il\u0131ca"
    ],
    "wof:name":"Ilicakoy",
    "wof:placetype":"locality"
},
  "geometry": {"coordinates":[36.52028,39.92111],"type":"Point"}
}