{
  "type": "Feature",
  "properties": {
    "gn:admin1_code":"2.0",
    "gn:asciiname":"Bagbasi",
    "gn:country_code":"TR",
    "gn:dem":1038,
    "gn:feature_class":"P",
    "gn:feature_code":"PPL",
    "gn:name":"Ba\u011fba\u015f\u0131",
    "gn:population":0,
    "gn:timezone":"Europe/Istanbul",
    "iso:country":"TR",
    "wof:name":"Bagbasi",
    "wof:placetype":"locality"
},
  "geometry": {"coordinates":[38.73506,37.89941],"type":"Point"}
}