{
  "type": "Feature",
  "properties": {
    "gn:admin1_code":"37.0",
    "gn:asciiname":"Goktas",
    "gn:country_code":"TR",
    "gn:dem":793,
    "gn:feature_class":"P",
    "gn:feature_code":"PPL",
    "gn:name":"G\u00f6kta\u015f",
    "gn:population":0,
    "gn:timezone":"Europe/Istanbul",
    "iso:country":"TR",
    "name:und_x_variant":[
        "G\u00f6kta\u015f K\u00f6y\u00fc",
        "G\u00f6kta\u015f"
    ],
    "wof:name":"Goktas",
    "wof:placetype":"locality"
},
  "geometry": {"coordinates":[33.34084,41.8525],"type":"Point"}
}