{
  "type": "Feature",
  "properties": {
    "gn:admin1_code":"13",
    "gn:asciiname":"Kavak",
    "gn:cc2":"TR",
    "gn:country_code":"TR",
    "gn:dem":1353,
    "gn:feature_class":"P",
    "gn:feature_code":"PPL",
    "gn:name":"Kavak",
    "gn:population":0,
    "gn:timezone":"Europe/Istanbul",
    "iso:country":"TR",
    "name:und_x_variant":[
        "Tap",
        "Huyut",
        "Kavak"
    ],
    "wof:name":"Kavak",
    "wof:placetype":"locality"
},
  "geometry": {"coordinates":[41.81667,38.48333],"type":"Point"}
}