{
  "type": "Feature",
  "properties": {
    "gn:admin1_code":"58",
    "gn:asciiname":"Benlihasan",
    "gn:country_code":"TR",
    "gn:dem":1631,
    "gn:feature_class":"P",
    "gn:feature_code":"PPL",
    "gn:name":"Benlihasan",
    "gn:population":0,
    "gn:timezone":"Europe/Istanbul",
    "iso:country":"TR",
    "name:tur_x_preferred":[
        "Benlihasan"
    ],
    "wof:name":"Benlihasan",
    "wof:placetype":"locality"
},
  "geometry": {"coordinates":[36.26806,39.50198],"type":"Point"}
}