{
  "type": "Feature",
  "properties": {
    "gn:admin1_code":"31.0",
    "gn:asciiname":"Indzhirli",
    "gn:country_code":"TR",
    "gn:dem":596,
    "gn:feature_class":"P",
    "gn:feature_code":"PPL",
    "gn:name":"Indzhirli",
    "gn:population":0,
    "gn:timezone":"Europe/Istanbul",
    "iso:country":"TR",
    "name:und_x_variant":[
        "\u0130ncirli"
    ],
    "wof:name":"Indzhirli",
    "wof:placetype":"locality"
},
  "geometry": {"coordinates":[36.29111,36.5075],"type":"Point"}
}