{
  "type": "Feature",
  "properties": {
    "gn:admin1_code":"37.0",
    "gn:asciiname":"Doganca",
    "gn:country_code":"TR",
    "gn:dem":960,
    "gn:feature_class":"P",
    "gn:feature_code":"PPL",
    "gn:name":"Do\u011fanca",
    "gn:population":0,
    "gn:timezone":"Europe/Istanbul",
    "iso:country":"TR",
    "wof:name":"Doganca",
    "wof:placetype":"locality"
},
  "geometry": {"coordinates":[33.42217,41.29167],"type":"Point"}
}