{
  "type": "Feature",
  "properties": {
    "gn:admin1_code":"38",
    "gn:asciiname":"Tozgun",
    "gn:country_code":"TR",
    "gn:dem":1515,
    "gn:feature_class":"P",
    "gn:feature_code":"PPL",
    "gn:name":"T\u00f6zg\u00fcn",
    "gn:population":0,
    "gn:timezone":"Europe/Istanbul",
    "iso:country":"TR",
    "name:und_x_variant":[
        "Tozg\u00fcm",
        "T\u00f6zg\u00fcn"
    ],
    "wof:name":"Tozgun",
    "wof:placetype":"locality"
},
  "geometry": {"coordinates":[36.12131,38.74692],"type":"Point"}
}