{
  "type": "Feature",
  "properties": {
    "gn:admin1_code":"82.0",
    "gn:asciiname":"Yuva",
    "gn:country_code":"TR",
    "gn:dem":1299,
    "gn:feature_class":"P",
    "gn:feature_code":"PPL",
    "gn:name":"Yuva",
    "gn:population":0,
    "gn:timezone":"Europe/Istanbul",
    "iso:country":"TR",
    "wof:name":"Yuva",
    "wof:placetype":"locality"
},
  "geometry": {"coordinates":[33.03572,40.61848],"type":"Point"}
}