{
  "type": "Feature",
  "properties": {
    "gn:admin1_code":"82.0",
    "gn:asciiname":"Aydinlar",
    "gn:country_code":"TR",
    "gn:dem":1297,
    "gn:feature_class":"P",
    "gn:feature_code":"PPL",
    "gn:name":"Ayd\u0131nlar",
    "gn:population":0,
    "gn:timezone":"Europe/Istanbul",
    "iso:country":"TR",
    "name:und_x_variant":[
        "Ayd\u0131nlar",
        "K\u0131z\u0131llar"
    ],
    "wof:name":"Aydinlar",
    "wof:placetype":"locality"
},
  "geometry": {"coordinates":[32.85,40.85],"type":"Point"}
}