{
  "type": "Feature",
  "properties": {
    "iso:country":"TR",
    "name:eng_x_preferred":[
        "Yaylali"
    ],
    "name:tur_x_preferred":[
        "Yaylal\u0131"
    ],
    "wof:name":"Yaylali",
    "wof:placetype":"neighbourhood"
},
  "geometry": {"coordinates":[29.67183474993906,41.0927908562376],"type":"Point"}
}