{
  "type": "Feature",
  "properties": {
    "gn:admin1_code":"54.0",
    "gn:asciiname":"Aydogan",
    "gn:country_code":"TR",
    "gn:dem":34,
    "gn:feature_class":"P",
    "gn:feature_code":"PPL",
    "gn:name":"Aydo\u011fan",
    "gn:population":0,
    "gn:timezone":"Europe/Istanbul",
    "iso:country":"TR",
    "name:tur_x_preferred":[
        "Aydo\u011fan"
    ],
    "wof:name":"Aydogan",
    "wof:placetype":"locality"
},
  "geometry": {"coordinates":[30.9791,41.01752000000001],"type":"Point"}
}