{
  "type": "Feature",
  "properties": {
    "gn:admin1_code":"71",
    "gn:asciiname":"Yenikoy",
    "gn:country_code":"TR",
    "gn:dem":1079,
    "gn:feature_class":"P",
    "gn:feature_code":"PPL",
    "gn:name":"Yenik\u00f6y",
    "gn:population":0,
    "gn:timezone":"Europe/Istanbul",
    "iso:country":"TR",
    "name:tur_x_preferred":[
        "P\u0131narba\u015f\u0131"
    ],
    "name:tur_x_variant":[
        "P\u0131narba\u015f\u0131 Yaylas\u0131"
    ],
    "name:und_x_variant":[
        "Yenik\u00f6y"
    ],
    "wof:name":"Yenikoy",
    "wof:placetype":"locality"
},
  "geometry": {"coordinates":[32.70647,38.73736],"type":"Point"}
}