{
  "type": "Feature",
  "properties": {
    "gn:admin1_code":"43.0",
    "gn:asciiname":"Ahlatlicesme",
    "gn:country_code":"TR",
    "gn:dem":1145,
    "gn:feature_class":"P",
    "gn:feature_code":"PPL",
    "gn:name":"Ahlatl\u0131\u00e7e\u015fme",
    "gn:population":0,
    "gn:timezone":"Europe/Istanbul",
    "iso:country":"TR",
    "name:tur_x_preferred":[
        "Ahlatl\u0131\u00e7e\u015fme"
    ],
    "wof:name":"Ahlatlicesme",
    "wof:placetype":"locality"
},
  "geometry": {"coordinates":[29.0402,39.14559000000001],"type":"Point"}
}