{
  "type": "Feature",
  "properties": {
    "gn:country":"TR",
    "gn:fcode":"PPL",
    "gn:population":38,
    "iso:country":"TR",
    "name:tur_x_preferred":[
        "Derecik"
    ],
    "name:und_x_variant":[
        "Tavusu"
    ],
    "qs:name":"Derecik",
    "qs:photos_9r":0,
    "qs:photos_sr":0,
    "qs:pop_sr":"1",
    "wof:name":"Derecik",
    "wof:placetype":"locality",
    "wof:population":38
},
  "geometry": {"coordinates":[40.52222,37.52056],"type":"Point"}
}