{
  "type": "Feature",
  "properties": {
    "gn:admin1_code":"68.0",
    "gn:asciiname":"Igmir",
    "gn:country_code":"TR",
    "gn:dem":1128,
    "gn:feature_class":"P",
    "gn:feature_code":"PPL",
    "gn:name":"\u0130\u011fmir",
    "gn:population":0,
    "gn:timezone":"Europe/Istanbul",
    "iso:country":"TR",
    "name:und_x_variant":[
        "\u0130mir",
        "\u0130\u011fmir",
        "\u0130ymir"
    ],
    "wof:name":"Igmir",
    "wof:placetype":"locality"
},
  "geometry": {"coordinates":[32.78384,40.35],"type":"Point"}
}