{
  "type": "Feature",
  "properties": {
    "gn:admin1_code":"80.0",
    "gn:asciiname":"Sufisalim",
    "gn:country_code":"TR",
    "gn:dem":340,
    "gn:feature_class":"P",
    "gn:feature_code":"PPL",
    "gn:name":"Sufisalim",
    "gn:population":0,
    "gn:timezone":"Europe/Istanbul",
    "iso:country":"TR",
    "wof:name":"Sufisalim",
    "wof:placetype":"locality"
},
  "geometry": {"coordinates":[42.35472,37.12722],"type":"Point"}
}