{
  "type": "Feature",
  "properties": {
    "gn:admin1_code":"43",
    "gn:asciiname":"Oreyler",
    "gn:country_code":"TR",
    "gn:dem":820,
    "gn:feature_class":"P",
    "gn:feature_code":"PPL",
    "gn:name":"\u00d6reyler",
    "gn:population":0,
    "gn:timezone":"Europe/Istanbul",
    "iso:country":"TR",
    "name:tur_x_preferred":[
        "\u00d6reyler"
    ],
    "name:tur_x_variant":[
        "\u00c7\u00f6k\u00fcler"
    ],
    "wof:name":"Oreyler",
    "wof:placetype":"locality"
},
  "geometry": {"coordinates":[28.89014,39.11218],"type":"Point"}
}