{
  "type": "Feature",
  "properties": {
    "gn:admin1_code":"5.0",
    "gn:asciiname":"Karsan",
    "gn:country_code":"TR",
    "gn:dem":933,
    "gn:feature_class":"P",
    "gn:feature_code":"PPL",
    "gn:name":"Karsan",
    "gn:population":0,
    "gn:timezone":"Europe/Istanbul",
    "iso:country":"TR",
    "wof:name":"Karsan",
    "wof:placetype":"locality"
},
  "geometry": {"coordinates":[36.19639,40.57906],"type":"Point"}
}