{
  "type": "Feature",
  "properties": {
    "gn:admin1_code":"45",
    "gn:asciiname":"Karakilicli",
    "gn:cc2":"TR",
    "gn:country_code":"TR",
    "gn:dem":425,
    "gn:feature_class":"P",
    "gn:feature_code":"PPL",
    "gn:name":"Karak\u0131l\u0131\u00e7l\u0131",
    "gn:population":0,
    "gn:timezone":"Europe/Istanbul",
    "iso:country":"TR",
    "name:und_x_variant":[
        "Karakilikli",
        "Karak\u0131l\u0131\u00e7l\u0131"
    ],
    "wof:name":"Karakilicli",
    "wof:placetype":"locality"
},
  "geometry": {"coordinates":[27.34333,38.77639],"type":"Point"}
}