{
  "type": "Feature",
  "properties": {
    "gn:admin1_code":"71",
    "gn:asciiname":"Ormanozu",
    "gn:country_code":"TR",
    "gn:dem":1166,
    "gn:feature_class":"P",
    "gn:feature_code":"PPL",
    "gn:name":"Orman\u00f6z\u00fc",
    "gn:population":0,
    "gn:timezone":"Europe/Istanbul",
    "iso:country":"TR",
    "name:und_x_variant":[
        "Puht\u0131",
        "\u015eevketiye",
        "Orman\u00f6z\u00fc"
    ],
    "wof:name":"Ormanozu",
    "wof:placetype":"locality"
},
  "geometry": {"coordinates":[31.90115,38.20173],"type":"Point"}
}