{
  "type": "Feature",
  "properties": {
    "gn:admin1_code":"02",
    "gn:asciiname":"Armutlu",
    "gn:country_code":"TR",
    "gn:dem":1134,
    "gn:feature_class":"P",
    "gn:feature_code":"PPL",
    "gn:name":"Armutlu",
    "gn:population":0,
    "gn:timezone":"Europe/Istanbul",
    "iso:country":"TR",
    "name:ceb_x_preferred":[
        "Armutlu"
    ],
    "name:deu_x_preferred":[
        "Armutlu"
    ],
    "name:kat_x_preferred":[
        "\u10d0\u10e0\u10db\u10e3\u10d3\u10da\u10e3"
    ],
    "name:nld_x_preferred":[
        "Armutlu"
    ],
    "name:swe_x_preferred":[
        "Armutlu"
    ],
    "name:tur_x_preferred":[
        "Armutlu"
    ],
    "name:und_x_variant":[
        "Tayibiye",
        "Taibiye",
        "Armutlu"
    ],
    "wof:name":"Armutlu",
    "wof:placetype":"locality"
},
  "geometry": {"coordinates":[38.3481,37.87655],"type":"Point"}
}