{
  "type": "Feature",
  "properties": {
    "gn:admin1_code":"28.0",
    "gn:asciiname":"Akkoy",
    "gn:country_code":"TR",
    "gn:dem":403,
    "gn:feature_class":"P",
    "gn:feature_code":"PPL",
    "gn:name":"Akk\u00f6y",
    "gn:population":0,
    "gn:timezone":"Europe/Istanbul",
    "iso:country":"TR",
    "name:und_x_variant":[
        "Akk\u00f6y",
        "Sadek\u00f6re"
    ],
    "wof:name":"Akkoy",
    "wof:placetype":"locality"
},
  "geometry": {"coordinates":[39.00655,40.89486],"type":"Point"}
}