{
  "type": "Feature",
  "properties": {
    "gn:admin1_code":"19.0",
    "gn:asciiname":"Burunkoy",
    "gn:country_code":"TR",
    "gn:dem":864,
    "gn:feature_class":"P",
    "gn:feature_code":"PPL",
    "gn:name":"Burunk\u00f6y",
    "gn:population":0,
    "gn:timezone":"Europe/Istanbul",
    "iso:country":"TR",
    "wof:name":"Burunkoy",
    "wof:placetype":"locality"
},
  "geometry": {"coordinates":[34.84699000000001,40.40307],"type":"Point"}
}