{
  "type": "Feature",
  "properties": {
    "gn:admin1_code":"07",
    "gn:asciiname":"Degirmenli",
    "gn:country_code":"TR",
    "gn:dem":49,
    "gn:feature_class":"P",
    "gn:feature_code":"PPL",
    "gn:name":"De\u011firmenli",
    "gn:population":0,
    "gn:timezone":"Europe/Istanbul",
    "iso:country":"TR",
    "name:und_x_variant":[
        "Somak\u00f6y",
        "Homa",
        "De\u011firmenli"
    ],
    "wof:name":"Degirmenli",
    "wof:placetype":"locality"
},
  "geometry": {"coordinates":[31.55327,36.85808],"type":"Point"}
}