{
  "type": "Feature",
  "properties": {
    "gn:admin1_code":"65",
    "gn:asciiname":"Kiziltas",
    "gn:country_code":"TR",
    "gn:dem":1767,
    "gn:feature_class":"P",
    "gn:feature_code":"PPL",
    "gn:name":"K\u0131z\u0131lta\u015f",
    "gn:population":0,
    "gn:timezone":"Europe/Istanbul",
    "iso:country":"TR",
    "name:tur_x_preferred":[
        "K\u0131z\u0131lta\u015f"
    ],
    "wof:name":"Kiziltas",
    "wof:placetype":"locality"
},
  "geometry": {"coordinates":[43.24646,38.30141],"type":"Point"}
}