{
  "type": "Feature",
  "properties": {
    "gn:admin1_code":"38",
    "gn:asciiname":"Hasanci",
    "gn:country_code":"TR",
    "gn:dem":1207,
    "gn:feature_class":"P",
    "gn:feature_code":"PPL",
    "gn:name":"Hasanc\u0131",
    "gn:population":0,
    "gn:timezone":"Europe/Istanbul",
    "iso:country":"TR",
    "wof:name":"Hasanci",
    "wof:placetype":"locality"
},
  "geometry": {"coordinates":[35.52162,38.95763],"type":"Point"}
}