{
  "type": "Feature",
  "properties": {
    "gn:admin1_code":"55.0",
    "gn:asciiname":"Cinaralan",
    "gn:country_code":"TR",
    "gn:dem":288,
    "gn:feature_class":"P",
    "gn:feature_code":"PPL",
    "gn:name":"\u00c7\u0131naralan",
    "gn:population":0,
    "gn:timezone":"Europe/Istanbul",
    "iso:country":"TR",
    "wof:name":"Cinaralan",
    "wof:placetype":"locality"
},
  "geometry": {"coordinates":[36.43224,41.19326],"type":"Point"}
}