{
  "type": "Feature",
  "properties": {
    "gn:admin1_code":"16",
    "gn:asciiname":"Hamadiye",
    "gn:country_code":"TR",
    "gn:dem":879,
    "gn:feature_class":"P",
    "gn:feature_code":"PPL",
    "gn:name":"Hamadiye",
    "gn:population":0,
    "gn:timezone":"Europe/Istanbul",
    "iso:country":"TR",
    "name:tur_x_preferred":[
        "Hamadiye"
    ],
    "wof:name":"Hamadiye",
    "wof:placetype":"locality"
},
  "geometry": {"coordinates":[29.5166,39.96517],"type":"Point"}
}