{
  "type": "Feature",
  "properties": {
    "gn:admin1_code":"83",
    "gn:asciiname":"Yeniceli",
    "gn:country_code":"TR",
    "gn:dem":1024,
    "gn:feature_class":"P",
    "gn:feature_code":"PPL",
    "gn:name":"Yeniceli",
    "gn:population":0,
    "gn:timezone":"Europe/Istanbul",
    "iso:country":"TR",
    "wof:name":"Yeniceli",
    "wof:placetype":"locality"
},
  "geometry": {"coordinates":[36.92244,36.97929],"type":"Point"}
}