{
  "type": "Feature",
  "properties": {
    "gn:admin1_code":"61.0",
    "gn:asciiname":"Bulak",
    "gn:country_code":"TR",
    "gn:dem":453,
    "gn:feature_class":"P",
    "gn:feature_code":"PPL",
    "gn:name":"Bulak",
    "gn:population":0,
    "gn:timezone":"Europe/Istanbul",
    "iso:country":"TR",
    "wof:name":"Bulak",
    "wof:placetype":"locality"
},
  "geometry": {"coordinates":[39.76222,40.96702],"type":"Point"}
}