{
  "type": "Feature",
  "properties": {
    "gn:admin1_code":"58.0",
    "gn:asciiname":"Kavakkoy",
    "gn:country_code":"TR",
    "gn:dem":1383,
    "gn:feature_class":"P",
    "gn:feature_code":"PPL",
    "gn:name":"Kavakk\u00f6y",
    "gn:population":0,
    "gn:timezone":"Europe/Istanbul",
    "iso:country":"TR",
    "name:tur_x_preferred":[
        "Kavakk\u00f6y"
    ],
    "name:tur_x_variant":[
        "Kavak"
    ],
    "wof:name":"Kavakkoy",
    "wof:placetype":"locality"
},
  "geometry": {"coordinates":[37.61276,39.45727],"type":"Point"}
}