{
  "type": "Feature",
  "properties": {
    "gn:admin1_code":"89.0",
    "gn:asciiname":"Yukaridegirmencik",
    "gn:country_code":"TR",
    "gn:dem":868,
    "gn:feature_class":"P",
    "gn:feature_code":"PPL",
    "gn:name":"Yukar\u0131de\u011firmencik",
    "gn:population":0,
    "gn:timezone":"Europe/Istanbul",
    "iso:country":"TR",
    "wof:name":"Yukaridegirmencik",
    "wof:placetype":"locality"
},
  "geometry": {"coordinates":[32.83467,41.29316],"type":"Point"}
}