{
  "type": "Feature",
  "properties": {
    "gn:admin1_code":"09",
    "gn:asciiname":"Isiklar",
    "gn:country_code":"TR",
    "gn:dem":468,
    "gn:feature_class":"P",
    "gn:feature_code":"PPL",
    "gn:name":"I\u015f\u0131klar",
    "gn:population":0,
    "gn:timezone":"Europe/Istanbul",
    "iso:country":"TR",
    "wof:name":"Isiklar",
    "wof:placetype":"locality"
},
  "geometry": {"coordinates":[28.36042,38.05861],"type":"Point"}
}