{
  "type": "Feature",
  "properties": {
    "gn:admin1_code":"48",
    "gn:asciiname":"Kanatlar",
    "gn:country_code":"TR",
    "gn:dem":709,
    "gn:feature_class":"P",
    "gn:feature_code":"PPL",
    "gn:name":"Kanatlar",
    "gn:population":0,
    "gn:timezone":"Europe/Istanbul",
    "iso:country":"TR",
    "name:tur_x_preferred":[
        "G\u00f6lc\u00fck"
    ],
    "name:tur_x_variant":[
        "Kanatlar"
    ],
    "wof:name":"Kanatlar",
    "wof:placetype":"locality"
},
  "geometry": {"coordinates":[28.54049,37.12912],"type":"Point"}
}