{
  "type": "Feature",
  "properties": {
    "gn:admin1_code":"68.0",
    "gn:asciiname":"Kurucay",
    "gn:country_code":"TR",
    "gn:dem":1239,
    "gn:feature_class":"P",
    "gn:feature_code":"PPL",
    "gn:name":"Kuru\u00e7ay",
    "gn:population":0,
    "gn:timezone":"Europe/Istanbul",
    "iso:country":"TR",
    "wof:name":"Kurucay",
    "wof:placetype":"locality"
},
  "geometry": {"coordinates":[32.95956,40.36778],"type":"Point"}
}