{
  "type": "Feature",
  "properties": {
    "gn:admin1_code":"20",
    "gn:asciiname":"Muslugume",
    "gn:country_code":"TR",
    "gn:dem":691,
    "gn:feature_class":"P",
    "gn:feature_code":"PPL",
    "gn:name":"Muslug\u00fcme",
    "gn:population":0,
    "gn:timezone":"Europe/Istanbul",
    "iso:country":"TR",
    "name:tur_x_preferred":[
        "Muslug\u00fcme"
    ],
    "wof:name":"Muslugume",
    "wof:placetype":"locality"
},
  "geometry": {"coordinates":[28.64786,37.43636],"type":"Point"}
}