{
  "type": "Feature",
  "properties": {
    "gn:admin1_code":"65.0",
    "gn:asciiname":"Yalindam",
    "gn:country_code":"TR",
    "gn:dem":2394,
    "gn:feature_class":"P",
    "gn:feature_code":"PPL",
    "gn:name":"Yal\u0131ndam",
    "gn:population":0,
    "gn:timezone":"Europe/Istanbul",
    "iso:country":"TR",
    "name:tur_x_preferred":[
        "Yal\u0131ndam"
    ],
    "wof:name":"Yalindam",
    "wof:placetype":"locality"
},
  "geometry": {"coordinates":[43.39304,39.26134],"type":"Point"}
}