{
  "type": "Feature",
  "properties": {
    "gn:admin1_code":"14",
    "gn:asciiname":"Calca",
    "gn:country_code":"TR",
    "gn:dem":1391,
    "gn:feature_class":"P",
    "gn:feature_code":"PPL",
    "gn:name":"\u00c7al\u00e7a",
    "gn:population":0,
    "gn:timezone":"Europe/Istanbul",
    "iso:country":"TR",
    "name:ceb_x_preferred":[
        "Calca"
    ],
    "name:nld_x_preferred":[
        "Calca"
    ],
    "wof:name":"Calca",
    "wof:placetype":"locality"
},
  "geometry": {"coordinates":[32.54923,40.82157],"type":"Point"}
}