{
  "type": "Feature",
  "properties": {
    "gn:admin1_code":"23",
    "gn:asciiname":"Urunveren",
    "gn:country_code":"TR",
    "gn:dem":1032,
    "gn:feature_class":"P",
    "gn:feature_code":"PPL",
    "gn:name":"\u00dcr\u00fcnveren",
    "gn:population":0,
    "gn:timezone":"Europe/Istanbul",
    "iso:country":"TR",
    "name:tur_x_preferred":[
        "\u00dcr\u00fcnveren"
    ],
    "wof:name":"Urunveren",
    "wof:placetype":"locality"
},
  "geometry": {"coordinates":[39.1618,38.53978],"type":"Point"}
}