{
  "type": "Feature",
  "properties": {
    "gn:admin1_code":"14",
    "gn:asciiname":"Saftalar",
    "gn:country_code":"TR",
    "gn:dem":1040,
    "gn:feature_class":"P",
    "gn:feature_code":"PPL",
    "gn:name":"Saftalar",
    "gn:population":0,
    "gn:timezone":"Europe/Istanbul",
    "iso:country":"TR",
    "wof:name":"Saftalar",
    "wof:placetype":"locality"
},
  "geometry": {"coordinates":[32.31869,40.94422],"type":"Point"}
}