{
  "type": "Feature",
  "properties": {
    "gn:admin1_code":"19.0",
    "gn:asciiname":"Cetmi",
    "gn:country_code":"TR",
    "gn:dem":779,
    "gn:feature_class":"P",
    "gn:feature_code":"PPL",
    "gn:name":"\u00c7etmi",
    "gn:population":0,
    "gn:timezone":"Europe/Istanbul",
    "iso:country":"TR",
    "wof:name":"Cetmi",
    "wof:placetype":"locality"
},
  "geometry": {"coordinates":[34.45598,40.85104000000001],"type":"Point"}
}