{
  "type": "Feature",
  "properties": {
    "gn:admin1_code":"84.0",
    "gn:asciiname":"Kosapinar",
    "gn:country_code":"TR",
    "gn:dem":2015,
    "gn:feature_class":"P",
    "gn:feature_code":"PPL",
    "gn:name":"Ko\u015fap\u0131nar",
    "gn:population":0,
    "gn:timezone":"Europe/Istanbul",
    "iso:country":"TR",
    "name:tur_x_preferred":[
        "Ko\u015fap\u0131nar"
    ],
    "wof:name":"Kosapinar",
    "wof:placetype":"locality"
},
  "geometry": {"coordinates":[42.7531,40.52905],"type":"Point"}
}