{
  "type": "Feature",
  "properties": {
    "gn:admin1_code":"14.0",
    "gn:asciiname":"Sarilar",
    "gn:country_code":"TR",
    "gn:dem":1381,
    "gn:feature_class":"P",
    "gn:feature_code":"PPL",
    "gn:name":"Sar\u0131lar",
    "gn:population":0,
    "gn:timezone":"Europe/Istanbul",
    "iso:country":"TR",
    "wof:name":"Sarilar",
    "wof:placetype":"locality"
},
  "geometry": {"coordinates":[31.05526,40.33129],"type":"Point"}
}