{
  "type": "Feature",
  "properties": {
    "gn:admin1_code":"37.0",
    "gn:asciiname":"Kalayci",
    "gn:country_code":"TR",
    "gn:dem":462,
    "gn:feature_class":"P",
    "gn:feature_code":"PPL",
    "gn:name":"Kalayc\u0131",
    "gn:population":0,
    "gn:timezone":"Europe/Istanbul",
    "iso:country":"TR",
    "wof:name":"Kalayci",
    "wof:placetype":"locality"
},
  "geometry": {"coordinates":[33.31117,41.82784],"type":"Point"}
}