{
  "type": "Feature",
  "properties": {
    "gn:admin1_code":"91",
    "gn:asciiname":"Zindogan",
    "gn:country_code":"TR",
    "gn:dem":472,
    "gn:feature_class":"P",
    "gn:feature_code":"PPL",
    "gn:name":"Zindo\u011fan",
    "gn:population":0,
    "gn:timezone":"Europe/Istanbul",
    "iso:country":"TR",
    "name:und_x_variant":[
        "Zindo\u011fan",
        "G\u00fcm\u00fc\u015f"
    ],
    "wof:name":"Zindogan",
    "wof:placetype":"locality"
},
  "geometry": {"coordinates":[36.50261,37.29949000000001],"type":"Point"}
}