{
  "type": "Feature",
  "properties": {
    "gn:admin1_code":"74",
    "gn:asciiname":"Tekev",
    "gn:country_code":"TR",
    "gn:dem":1634,
    "gn:feature_class":"P",
    "gn:feature_code":"PPL",
    "gn:name":"Tekev",
    "gn:population":0,
    "gn:timezone":"Europe/Istanbul",
    "iso:country":"TR",
    "name:und_x_variant":[
        "K\u0131na\u00e7a",
        "Kanachan",
        "Tekev",
        "Kana\u00e7an"
    ],
    "wof:name":"Tekev",
    "wof:placetype":"locality"
},
  "geometry": {"coordinates":[42.50472,37.86972],"type":"Point"}
}