{
  "type": "Feature",
  "properties": {
    "gn:admin1_code":"72",
    "gn:asciiname":"Kuskaya",
    "gn:country_code":"TR",
    "gn:dem":692,
    "gn:feature_class":"P",
    "gn:feature_code":"PPL",
    "gn:name":"Ku\u015fkaya",
    "gn:population":0,
    "gn:timezone":"Europe/Istanbul",
    "iso:country":"TR",
    "name:tur_x_preferred":[
        "Ku\u015fkaya"
    ],
    "name:und_x_variant":[
        "Aytepe",
        "K\u00fcr\u00fck",
        "Kyuryuk",
        "K\u00fcrr\u00fck\u00e7etto",
        "K\u00fcr\u00fck\u00e7ato"
    ],
    "wof:name":"Kuskaya",
    "wof:placetype":"locality"
},
  "geometry": {"coordinates":[41.02821,37.18425],"type":"Point"}
}