{
  "type": "Feature",
  "properties": {
    "gn:admin1_code":"55.0",
    "gn:asciiname":"Muslubey",
    "gn:country_code":"TR",
    "gn:dem":106,
    "gn:feature_class":"P",
    "gn:feature_code":"PPL",
    "gn:name":"Muslubey",
    "gn:population":0,
    "gn:timezone":"Europe/Istanbul",
    "iso:country":"TR",
    "wof:name":"Muslubey",
    "wof:placetype":"locality"
},
  "geometry": {"coordinates":[36.76009000000001,41.08969],"type":"Point"}
}