{
  "type": "Feature",
  "properties": {
    "gn:admin1_code":"13",
    "gn:asciiname":"Yukari Suphan",
    "gn:country_code":"TR",
    "gn:dem":1904,
    "gn:feature_class":"P",
    "gn:feature_code":"PPL",
    "gn:name":"Yukar\u0131 S\u00fcphan",
    "gn:population":0,
    "gn:timezone":"Europe/Istanbul",
    "iso:country":"TR",
    "name:tur_x_preferred":[
        "Yukar\u0131 S\u00fcphan"
    ],
    "name:und_x_variant":[
        "Yukar\u0131 Subhan",
        "Yukar\u0131s\u00fcphan"
    ],
    "wof:name":"Yukari Suphan",
    "wof:placetype":"locality"
},
  "geometry": {"coordinates":[42.85728,38.82487],"type":"Point"}
}