{
  "type": "Feature",
  "properties": {
    "gn:admin1_code":"43",
    "gn:asciiname":"Ece",
    "gn:country_code":"TR",
    "gn:dem":980,
    "gn:feature_class":"P",
    "gn:feature_code":"PPL",
    "gn:name":"Ece",
    "gn:population":0,
    "gn:timezone":"Europe/Istanbul",
    "iso:country":"TR",
    "name:tur_x_preferred":[
        "Ece"
    ],
    "wof:name":"Ece",
    "wof:placetype":"locality"
},
  "geometry": {"coordinates":[29.37667,39.03302],"type":"Point"}
}