{
  "type": "Feature",
  "properties": {
    "gn:admin1_code":"58",
    "gn:asciiname":"Peyik",
    "gn:country_code":"TR",
    "gn:dem":1626,
    "gn:feature_class":"P",
    "gn:feature_code":"PPL",
    "gn:name":"Peyik",
    "gn:population":0,
    "gn:timezone":"Europe/Istanbul",
    "iso:country":"TR",
    "name:und_x_variant":[
        "G\u00fcl\u00f6ren"
    ],
    "wof:name":"Peyik",
    "wof:placetype":"locality"
},
  "geometry": {"coordinates":[36.14764,39.58019],"type":"Point"}
}