{
  "type": "Feature",
  "properties": {
    "gn:admin1_code":"16.0",
    "gn:asciiname":"Behram",
    "gn:country_code":"TR",
    "gn:dem":68,
    "gn:feature_class":"P",
    "gn:feature_code":"PPL",
    "gn:name":"Behram",
    "gn:population":0,
    "gn:timezone":"Europe/Istanbul",
    "iso:country":"TR",
    "name:und_x_variant":[
        "Behramk\u00f6y"
    ],
    "wof:name":"Behram",
    "wof:placetype":"locality"
},
  "geometry": {"coordinates":[28.44056,40.00056],"type":"Point"}
}