{
  "type": "Feature",
  "properties": {
    "gn:admin1_code":"70",
    "gn:asciiname":"Nikse",
    "gn:country_code":"TR",
    "gn:dem":1778,
    "gn:feature_class":"P",
    "gn:feature_code":"PPL",
    "gn:name":"Nikse",
    "gn:population":0,
    "gn:timezone":"Europe/Istanbul",
    "iso:country":"TR",
    "name:und_x_variant":[
        "Yukar\u0131 Katma"
    ],
    "wof:name":"Nikse",
    "wof:placetype":"locality"
},
  "geometry": {"coordinates":[44.5596,37.39585],"type":"Point"}
}