{
  "type": "Feature",
  "properties": {
    "gn:admin1_code":"19.0",
    "gn:asciiname":"Tuglu",
    "gn:country_code":"TR",
    "gn:dem":782,
    "gn:feature_class":"P",
    "gn:feature_code":"PPL",
    "gn:name":"Tu\u011flu",
    "gn:population":0,
    "gn:timezone":"Europe/Istanbul",
    "iso:country":"TR",
    "wof:name":"Tuglu",
    "wof:placetype":"locality"
},
  "geometry": {"coordinates":[34.31172,40.4312],"type":"Point"}
}