{
  "type": "Feature",
  "properties": {
    "gn:admin1_code":"60.0",
    "gn:asciiname":"Hevekse",
    "gn:country_code":"TR",
    "gn:dem":1390,
    "gn:feature_class":"P",
    "gn:feature_code":"PPL",
    "gn:name":"Hevekse",
    "gn:population":0,
    "gn:timezone":"Europe/Istanbul",
    "iso:country":"TR",
    "name:und_x_variant":[
        "Da\u011f\u00fcst\u00fc"
    ],
    "wof:name":"Hevekse",
    "wof:placetype":"locality"
},
  "geometry": {"coordinates":[37.15917,40.49203],"type":"Point"}
}