{
  "type": "Feature",
  "properties": {
    "gn:admin1_code":"16",
    "gn:asciiname":"Coreler",
    "gn:country_code":"TR",
    "gn:dem":379,
    "gn:feature_class":"P",
    "gn:feature_code":"PPL",
    "gn:name":"\u00c7\u00f6reler",
    "gn:population":0,
    "gn:timezone":"Europe/Istanbul",
    "iso:country":"TR",
    "name:tur_x_preferred":[
        "\u00c7\u00f6reler"
    ],
    "wof:name":"Coreler",
    "wof:placetype":"locality"
},
  "geometry": {"coordinates":[28.94695,39.94455],"type":"Point"}
}