{
  "type": "Feature",
  "properties": {
    "gn:admin1_code":"21",
    "gn:asciiname":"Yillarca",
    "gn:country_code":"TR",
    "gn:dem":821,
    "gn:feature_class":"P",
    "gn:feature_code":"PPL",
    "gn:name":"Y\u0131llarca",
    "gn:population":0,
    "gn:timezone":"Europe/Istanbul",
    "iso:country":"TR",
    "name:tur_x_preferred":[
        "Y\u0131llarca"
    ],
    "wof:name":"Yillarca",
    "wof:placetype":"locality"
},
  "geometry": {"coordinates":[40.14397,37.73779],"type":"Point"}
}