{
  "type": "Feature",
  "properties": {
    "gn:admin1_code":"53",
    "gn:asciiname":"Hosdere",
    "gn:country_code":"TR",
    "gn:dem":195,
    "gn:feature_class":"P",
    "gn:feature_code":"PPL",
    "gn:name":"Ho\u015fdere",
    "gn:population":0,
    "gn:timezone":"Europe/Istanbul",
    "iso:country":"TR",
    "name:tur_x_preferred":[
        "Ho\u015fdere"
    ],
    "name:tur_x_variant":[
        "K\u00f6pr\u00fcba\u015f\u0131"
    ],
    "wof:name":"Hosdere",
    "wof:placetype":"locality"
},
  "geometry": {"coordinates":[41.03891,41.12033],"type":"Point"}
}