{
  "type": "Feature",
  "properties": {
    "gn:country":"TR",
    "gn:fcode":"PPL",
    "gn:population":210,
    "iso:country":"TR",
    "name:und_x_variant":[
        "Sinip"
    ],
    "qs:name":"Sinep",
    "qs:photos_9r":0,
    "qs:photos_sr":0,
    "qs:pop_sr":"2",
    "wof:name":"Sinep",
    "wof:placetype":"locality",
    "wof:population":210
},
  "geometry": {"coordinates":[42.03139,37.97278],"type":"Point"}
}