{
  "type": "Feature",
  "properties": {
    "gn:admin1_code":"87.0",
    "gn:asciiname":"Sarideresi",
    "gn:country_code":"TR",
    "gn:dem":202,
    "gn:feature_class":"P",
    "gn:feature_code":"PPL",
    "gn:name":"Sar\u0131deresi",
    "gn:population":0,
    "gn:timezone":"Europe/Istanbul",
    "iso:country":"TR",
    "name:und_x_variant":[
        "Sar\u0131dere",
        "Sar\u0131deresi"
    ],
    "wof:name":"Sarideresi",
    "wof:placetype":"locality"
},
  "geometry": {"coordinates":[32.59017,41.75616],"type":"Point"}
}