{
  "type": "Feature",
  "properties": {
    "gn:admin1_code":"03",
    "gn:asciiname":"Palaz",
    "gn:country_code":"TR",
    "gn:dem":1312,
    "gn:feature_class":"P",
    "gn:feature_code":"PPL",
    "gn:name":"Palaz",
    "gn:population":0,
    "gn:timezone":"Europe/Istanbul",
    "iso:country":"TR",
    "wof:name":"Palaz",
    "wof:placetype":"locality"
},
  "geometry": {"coordinates":[30.10788,37.95443],"type":"Point"}
}