{
  "type": "Feature",
  "properties": {
    "gn:admin1_code":"65",
    "gn:asciiname":"Karadulda",
    "gn:country_code":"TR",
    "gn:dem":2172,
    "gn:feature_class":"P",
    "gn:feature_code":"PPL",
    "gn:name":"Karadulda",
    "gn:population":0,
    "gn:timezone":"Europe/Istanbul",
    "iso:country":"TR",
    "name:und_x_variant":[
        "Ke\u00e7an",
        "Karadulda"
    ],
    "wof:name":"Karadulda",
    "wof:placetype":"locality"
},
  "geometry": {"coordinates":[44.04285,38.96962],"type":"Point"}
}