{
  "type": "Feature",
  "properties": {
    "gn:admin1_code":"10",
    "gn:asciiname":"Kulat",
    "gn:country_code":"TR",
    "gn:dem":438,
    "gn:feature_class":"P",
    "gn:feature_code":"PPL",
    "gn:name":"Kulat",
    "gn:population":0,
    "gn:timezone":"Europe/Istanbul",
    "iso:country":"TR",
    "name:tur_x_preferred":[
        "Kulat"
    ],
    "wof:name":"Kulat",
    "wof:placetype":"locality"
},
  "geometry": {"coordinates":[28.04806,39.89028],"type":"Point"}
}