{
  "type": "Feature",
  "properties": {
    "iso:country":"TR",
    "name:eng_x_preferred":[
        "Burhaniye"
    ],
    "name:tur_x_preferred":[
        "Burhaniye"
    ],
    "wof:name":"Burhaniye",
    "wof:placetype":"neighbourhood"
},
  "geometry": {"coordinates":[29.05423245266945,41.03072631721739],"type":"Point"}
}