{
  "type": "Feature",
  "properties": {
    "gn:admin1_code":"72",
    "gn:asciiname":"Dura",
    "gn:country_code":"TR",
    "gn:dem":446,
    "gn:feature_class":"P",
    "gn:feature_code":"PPL",
    "gn:name":"Dura",
    "gn:population":0,
    "gn:timezone":"Europe/Istanbul",
    "iso:country":"TR",
    "name:ceb_x_preferred":[
        "Dura"
    ],
    "name:deu_x_preferred":[
        "Dura"
    ],
    "name:fin_x_preferred":[
        "Dura"
    ],
    "name:fra_x_preferred":[
        "Dura"
    ],
    "name:nld_x_preferred":[
        "Dura"
    ],
    "name:por_x_preferred":[
        "Dura"
    ],
    "name:rus_x_preferred":[
        "\u0414\u0443\u0440\u0430"
    ],
    "name:swe_x_preferred":[
        "Dura"
    ],
    "name:tur_x_preferred":[
        "Dura"
    ],
    "name:und_x_variant":[
        "Tel\u00e2c\u0131k"
    ],
    "wof:name":"Dura",
    "wof:placetype":"locality"
},
  "geometry": {"coordinates":[40.49113,37.10909],"type":"Point"}
}