{
  "type": "Feature",
  "properties": {
    "gn:admin1_code":"64",
    "gn:asciiname":"Eminoglu",
    "gn:country_code":"TR",
    "gn:dem":857,
    "gn:feature_class":"P",
    "gn:feature_code":"PPL",
    "gn:name":"Emino\u011flu",
    "gn:population":0,
    "gn:timezone":"Europe/Istanbul",
    "iso:country":"TR",
    "name:tur_x_preferred":[
        "Emino\u011flu"
    ],
    "wof:name":"Eminoglu",
    "wof:placetype":"locality"
},
  "geometry": {"coordinates":[29.09373,38.78466],"type":"Point"}
}