{
  "type": "Feature",
  "properties": {
    "gn:admin1_code":"58",
    "gn:asciiname":"Coksoz",
    "gn:cc2":"TR",
    "gn:country_code":"TR",
    "gn:dem":1763,
    "gn:feature_class":"P",
    "gn:feature_code":"PPL",
    "gn:name":"\u00c7oks\u00f6z",
    "gn:population":0,
    "gn:timezone":"Europe/Istanbul",
    "iso:country":"TR",
    "name:und_x_variant":[
        "\u00c7\u00fcks\u00fczler",
        "\u00c7\u00fcks\u00fczer",
        "\u00c7oks\u00f6z"
    ],
    "wof:name":"Coksoz",
    "wof:placetype":"locality"
},
  "geometry": {"coordinates":[37.95,39.36667],"type":"Point"}
}