{
  "type": "Feature",
  "properties": {
    "gn:admin1_code":"45",
    "gn:asciiname":"Narincali Suleyman",
    "gn:country_code":"TR",
    "gn:dem":904,
    "gn:feature_class":"P",
    "gn:feature_code":"PPL",
    "gn:name":"Nar\u0131ncal\u0131 S\u00fcleyman",
    "gn:population":0,
    "gn:timezone":"Europe/Istanbul",
    "iso:country":"TR",
    "name:tur_x_preferred":[
        "Nar\u0131ncal\u0131 S\u00fcleyman"
    ],
    "name:tur_x_variant":[
        "S\u00fcleymanefendi\u00e7iftli\u011fi"
    ],
    "wof:name":"Narincali Suleyman",
    "wof:placetype":"locality"
},
  "geometry": {"coordinates":[28.77629,38.46798],"type":"Point"}
}