{
  "type": "Feature",
  "properties": {
    "gn:admin1_code":"26",
    "gn:asciiname":"Demirciler",
    "gn:country_code":"TR",
    "gn:dem":263,
    "gn:feature_class":"P",
    "gn:feature_code":"PPL",
    "gn:name":"Demirciler",
    "gn:population":0,
    "gn:timezone":"Europe/Istanbul",
    "iso:country":"TR",
    "name:tur_x_preferred":[
        "Demirciler"
    ],
    "name:und_x_variant":[
        "Sakar\u0131demirciler"
    ],
    "wof:name":"Demirciler",
    "wof:placetype":"locality"
},
  "geometry": {"coordinates":[30.53787,40.0107],"type":"Point"}
}