{
  "type": "Feature",
  "properties": {
    "gn:admin1_code":"23",
    "gn:asciiname":"Matarusagi",
    "gn:cc2":"TR",
    "gn:country_code":"TR",
    "gn:dem":831,
    "gn:feature_class":"P",
    "gn:feature_code":"PPL",
    "gn:name":"Mataru\u015fa\u011f\u0131",
    "gn:population":0,
    "gn:timezone":"Europe/Istanbul",
    "iso:country":"TR",
    "name:und_x_variant":[
        "Metiru\u015fa\u011f\u0131",
        "Mataru\u015fa\u011f\u0131"
    ],
    "wof:name":"Matarusagi",
    "wof:placetype":"locality"
},
  "geometry": {"coordinates":[38.51667,38.66667],"type":"Point"}
}