{
  "type": "Feature",
  "properties": {
    "gn:admin1_code":"40.0",
    "gn:asciiname":"Altinyazi",
    "gn:country_code":"TR",
    "gn:dem":1012,
    "gn:feature_class":"P",
    "gn:feature_code":"PPL",
    "gn:name":"Alt\u0131nyaz\u0131",
    "gn:population":0,
    "gn:timezone":"Europe/Istanbul",
    "iso:country":"TR",
    "wof:name":"Altinyazi",
    "wof:placetype":"locality"
},
  "geometry": {"coordinates":[34.42508,38.99551],"type":"Point"}
}