{
  "type": "Feature",
  "properties": {
    "gn:admin1_code":"93",
    "gn:asciiname":"Cakirlar",
    "gn:country_code":"TR",
    "gn:dem":178,
    "gn:feature_class":"P",
    "gn:feature_code":"PPL",
    "gn:name":"\u00c7ak\u0131rlar",
    "gn:population":0,
    "gn:timezone":"Europe/Istanbul",
    "iso:country":"TR",
    "wof:name":"Cakirlar",
    "wof:placetype":"locality"
},
  "geometry": {"coordinates":[31.20115,40.88384],"type":"Point"}
}