{
  "type": "Feature",
  "properties": {
    "gn:admin1_code":"20",
    "gn:asciiname":"Boztarla",
    "gn:country_code":"TR",
    "gn:dem":788,
    "gn:feature_class":"P",
    "gn:feature_code":"PPL",
    "gn:name":"Boztarla",
    "gn:population":0,
    "gn:timezone":"Europe/Istanbul",
    "iso:country":"TR",
    "wof:name":"Boztarla",
    "wof:placetype":"locality"
},
  "geometry": {"coordinates":[29.18333,37.03333],"type":"Point"}
}