{
  "type": "Feature",
  "properties": {
    "gn:admin1_code":"91.0",
    "gn:asciiname":"Dereobasi",
    "gn:country_code":"TR",
    "gn:dem":126,
    "gn:feature_class":"P",
    "gn:feature_code":"PPL",
    "gn:name":"Dereobas\u0131",
    "gn:population":0,
    "gn:timezone":"Europe/Istanbul",
    "iso:country":"TR",
    "wof:name":"Dereobasi",
    "wof:placetype":"locality"
},
  "geometry": {"coordinates":[36.13406,37.22971],"type":"Point"}
}