{
  "type": "Feature",
  "properties": {
    "gn:admin1_code":"83.0",
    "gn:asciiname":"Karatas",
    "gn:cc2":"TR",
    "gn:country_code":"TR",
    "gn:dem":665,
    "gn:feature_class":"P",
    "gn:feature_code":"PPL",
    "gn:name":"Karata\u015f",
    "gn:population":0,
    "gn:timezone":"Europe/Istanbul",
    "iso:country":"TR",
    "name:ceb_x_preferred":[
        "Karatas"
    ],
    "name:swe_x_preferred":[
        "Karatas"
    ],
    "name:und_x_variant":[
        "Karatash",
        "Karata\u015f"
    ],
    "wof:name":"Karatas",
    "wof:placetype":"locality"
},
  "geometry": {"coordinates":[37.57167000000001,36.89222],"type":"Point"}
}