{
  "type": "Feature",
  "properties": {
    "gn:admin1_code":"10",
    "gn:asciiname":"Demirkapi",
    "gn:cc2":"TR",
    "gn:country_code":"TR",
    "gn:dem":97,
    "gn:feature_class":"P",
    "gn:feature_code":"PPL",
    "gn:name":"Demirkap\u0131",
    "gn:population":0,
    "gn:timezone":"Europe/Istanbul",
    "iso:country":"TR",
    "name:und_x_variant":[
        "Demirkapu K\u00f6y",
        "Demirkapu",
        "Demirkap\u0131"
    ],
    "wof:name":"Demirkapi",
    "wof:placetype":"locality"
},
  "geometry": {"coordinates":[28.08694,39.80944],"type":"Point"}
}