{
  "type": "Feature",
  "properties": {
    "gn:admin1_code":"48",
    "gn:asciiname":"Kecili",
    "gn:country_code":"TR",
    "gn:dem":661,
    "gn:feature_class":"P",
    "gn:feature_code":"PPL",
    "gn:name":"Ke\u00e7ili",
    "gn:population":0,
    "gn:timezone":"Europe/Istanbul",
    "iso:country":"TR",
    "name:tur_x_preferred":[
        "Ke\u00e7ili"
    ],
    "wof:name":"Kecili",
    "wof:placetype":"locality"
},
  "geometry": {"coordinates":[28.06699,37.22527],"type":"Point"}
}