{
  "type": "Feature",
  "properties": {
    "gn:admin1_code":"25.0",
    "gn:asciiname":"Cirins",
    "gn:country_code":"TR",
    "gn:dem":1281,
    "gn:feature_class":"P",
    "gn:feature_code":"PPL",
    "gn:name":"Cirins",
    "gn:population":0,
    "gn:timezone":"Europe/Istanbul",
    "iso:country":"TR",
    "wof:name":"Cirins",
    "wof:placetype":"locality"
},
  "geometry": {"coordinates":[41.47317,40.49571],"type":"Point"}
}