{
  "type": "Feature",
  "properties": {
    "gn:admin1_code":"25.0",
    "gn:asciiname":"Kirklar",
    "gn:country_code":"TR",
    "gn:dem":1892,
    "gn:feature_class":"P",
    "gn:feature_code":"PPL",
    "gn:name":"K\u0131rklar",
    "gn:population":0,
    "gn:timezone":"Europe/Istanbul",
    "iso:country":"TR",
    "name:tur_x_preferred":[
        "K\u0131rklar"
    ],
    "wof:name":"Kirklar",
    "wof:placetype":"locality"
},
  "geometry": {"coordinates":[42.39536,40.01998],"type":"Point"}
}