{
  "type": "Feature",
  "properties": {
    "gn:admin1_code":"54.0",
    "gn:asciiname":"Bezirgan",
    "gn:country_code":"TR",
    "gn:dem":51,
    "gn:feature_class":"P",
    "gn:feature_code":"PPL",
    "gn:name":"Bezirgan",
    "gn:population":0,
    "gn:timezone":"Europe/Istanbul",
    "iso:country":"TR",
    "name:tur_x_preferred":[
        "Bezirgan"
    ],
    "wof:name":"Bezirgan",
    "wof:placetype":"locality"
},
  "geometry": {"coordinates":[31.0021,41.04056],"type":"Point"}
}