{
  "type": "Feature",
  "properties": {
    "gn:admin1_code":"24.0",
    "gn:asciiname":"Adak",
    "gn:country_code":"TR",
    "gn:dem":1368,
    "gn:feature_class":"P",
    "gn:feature_code":"PPL",
    "gn:name":"Adak",
    "gn:population":0,
    "gn:timezone":"Europe/Istanbul",
    "iso:country":"TR",
    "name:und_x_variant":[
        "Pat",
        "Adak"
    ],
    "wof:name":"Adak",
    "wof:placetype":"locality"
},
  "geometry": {"coordinates":[38.65425,39.12165],"type":"Point"}
}