{
  "type": "Feature",
  "properties": {
    "gn:admin1_code":"24.0",
    "gn:asciiname":"Adak",
    "gn:country_code":"TR",
    "gn:dem":1368,
    "gn:feature_class":"P",
    "gn:feature_code":"PPL",
    "gn:name":"Adak",
    "gn:population":0,
    "gn:timezone":"Europe/Istanbul",
    "iso:country":"TR",
    "name:azb_x_preferred":[
        "\u0622\u062f\u0627\u06a9"
    ],
    "name:ben_x_preferred":[
        "\u0986\u09a6\u09be\u0995"
    ],
    "name:bre_x_preferred":[
        "Adak"
    ],
    "name:deu_x_preferred":[
        "Adak"
    ],
    "name:ell_x_preferred":[
        "\u0386\u03bd\u03c4\u03b1\u03ba"
    ],
    "name:fas_x_preferred":[
        "\u0622\u062f\u0627\u06a9"
    ],
    "name:heb_x_preferred":[
        "\u05d4\u05d0\u05d9 \u05d0\u05d3\u05d0\u05e7"
    ],
    "name:hin_x_preferred":[
        "\u0905\u0926\u0915"
    ],
    "name:hun_x_preferred":[
        "Adak"
    ],
    "name:ind_x_preferred":[
        "Adak"
    ],
    "name:ita_x_preferred":[
        "Adak"
    ],
    "name:nld_x_preferred":[
        "Adak"
    ],
    "name:pol_x_preferred":[
        "Adak"
    ],
    "name:tur_x_preferred":[
        "Adak"
    ],
    "name:und_x_variant":[
        "Pat"
    ],
    "name:vie_x_preferred":[
        "\u0110\u1ea3o Adak"
    ],
    "wof:name":"Adak",
    "wof:placetype":"locality"
},
  "geometry": {"coordinates":[38.65425,39.12165],"type":"Point"}
}