{
  "type": "Feature",
  "properties": {
    "gn:admin1_code":"74.0",
    "gn:asciiname":"Yamacli",
    "gn:country_code":"TR",
    "gn:dem":1799,
    "gn:feature_class":"P",
    "gn:feature_code":"PPL",
    "gn:name":"Yama\u00e7l\u0131",
    "gn:population":0,
    "gn:timezone":"Europe/Istanbul",
    "iso:country":"TR",
    "name:tur_x_preferred":[
        "Yama\u00e7l\u0131"
    ],
    "wof:name":"Yamacli",
    "wof:placetype":"locality"
},
  "geometry": {"coordinates":[42.19046,38.18098],"type":"Point"}
}