{
  "type": "Feature",
  "properties": {
    "gn:admin1_code":"14",
    "gn:asciiname":"Kayabasi",
    "gn:country_code":"TR",
    "gn:dem":949,
    "gn:feature_class":"P",
    "gn:feature_code":"PPL",
    "gn:name":"Kayaba\u015f\u0131",
    "gn:population":0,
    "gn:timezone":"Europe/Istanbul",
    "iso:country":"TR",
    "wof:name":"Kayabasi",
    "wof:placetype":"locality"
},
  "geometry": {"coordinates":[31.8643,40.8791],"type":"Point"}
}