{
  "type": "Feature",
  "properties": {
    "gn:admin1_code":"23",
    "gn:asciiname":"Oymaagac",
    "gn:country_code":"TR",
    "gn:dem":1154,
    "gn:feature_class":"P",
    "gn:feature_code":"PPL",
    "gn:name":"Oymaa\u011fa\u00e7",
    "gn:population":0,
    "gn:timezone":"Europe/Istanbul",
    "iso:country":"TR",
    "name:tur_x_preferred":[
        "Oymaa\u011fa\u00e7"
    ],
    "wof:name":"Oymaagac",
    "wof:placetype":"locality"
},
  "geometry": {"coordinates":[39.34069,38.72473],"type":"Point"}
}