{
  "type": "Feature",
  "properties": {
    "gn:admin1_code":"09",
    "gn:asciiname":"Cumayani",
    "gn:country_code":"TR",
    "gn:dem":574,
    "gn:feature_class":"P",
    "gn:feature_code":"PPL",
    "gn:name":"Cumayan\u0131",
    "gn:population":0,
    "gn:timezone":"Europe/Istanbul",
    "iso:country":"TR",
    "name:tur_x_preferred":[
        "Cumayan\u0131"
    ],
    "wof:name":"Cumayani",
    "wof:placetype":"locality"
},
  "geometry": {"coordinates":[28.10284,37.98494],"type":"Point"}
}