{
  "type": "Feature",
  "properties": {
    "gn:admin1_code":"71",
    "gn:asciiname":"Karasinir Mahallesi",
    "gn:country_code":"TR",
    "gn:dem":1122,
    "gn:feature_class":"P",
    "gn:feature_code":"PPL",
    "gn:name":"Karas\u0131n\u0131r Mahallesi",
    "gn:population":0,
    "gn:timezone":"Europe/Istanbul",
    "iso:country":"TR",
    "name:und_x_variant":[
        "Karas\u0131n\u0131r Mahallesi",
        "Karasinir"
    ],
    "wof:name":"Karasinir Mahallesi",
    "wof:placetype":"locality"
},
  "geometry": {"coordinates":[32.71768,37.29923],"type":"Point"}
}