{
  "type": "Feature",
  "properties": {
    "gn:admin1_code":"10",
    "gn:asciiname":"Ahmetliyorugu",
    "gn:country_code":"TR",
    "gn:dem":852,
    "gn:feature_class":"P",
    "gn:feature_code":"PPL",
    "gn:name":"Ahmetliy\u00f6r\u00fc\u011f\u00fc",
    "gn:population":0,
    "gn:timezone":"Europe/Istanbul",
    "iso:country":"TR",
    "name:tur_x_preferred":[
        "Ahmetliy\u00f6r\u00fc\u011f\u00fc"
    ],
    "wof:name":"Ahmetliyorugu",
    "wof:placetype":"locality"
},
  "geometry": {"coordinates":[28.40216,39.25504],"type":"Point"}
}