{
  "type": "Feature",
  "properties": {
    "gn:admin1_code":"35",
    "gn:asciiname":"Tepekoy",
    "gn:country_code":"TR",
    "gn:dem":97,
    "gn:feature_class":"P",
    "gn:feature_code":"PPL",
    "gn:name":"Tepek\u00f6y",
    "gn:population":0,
    "gn:timezone":"Europe/Istanbul",
    "iso:country":"TR",
    "name:tur_x_preferred":[
        "Tepek\u00f6y"
    ],
    "wof:name":"Tepekoy",
    "wof:placetype":"locality"
},
  "geometry": {"coordinates":[27.10713,39.08794],"type":"Point"}
}