{
  "type": "Feature",
  "properties": {
    "gn:admin1_code":"25.0",
    "gn:asciiname":"Oztoprak",
    "gn:country_code":"TR",
    "gn:dem":1384,
    "gn:feature_class":"P",
    "gn:feature_code":"PPL",
    "gn:name":"\u00d6ztoprak",
    "gn:population":0,
    "gn:timezone":"Europe/Istanbul",
    "iso:country":"TR",
    "name:und_x_variant":[
        "\u00d6ztoprak",
        "Muh\u015fin"
    ],
    "wof:name":"Oztoprak",
    "wof:placetype":"locality"
},
  "geometry": {"coordinates":[41.05819,40.52252],"type":"Point"}
}