{
  "type": "Feature",
  "properties": {
    "gn:admin1_code":"63",
    "gn:asciiname":"Yukarihabib",
    "gn:country_code":"TR",
    "gn:dem":540,
    "gn:feature_class":"P",
    "gn:feature_code":"PPL",
    "gn:name":"Yukar\u0131habib",
    "gn:population":0,
    "gn:timezone":"Europe/Istanbul",
    "iso:country":"TR",
    "name:und_x_variant":[
        "Yukar\u0131 Habip",
        "Yukar\u0131habib"
    ],
    "wof:name":"Yukarihabib",
    "wof:placetype":"locality"
},
  "geometry": {"coordinates":[38.0105,37.13481],"type":"Point"}
}