{
  "type": "Feature",
  "properties": {
    "gn:country":"TR",
    "gn:fcode":"PPL",
    "gn:pop":47,
    "iso:country":"TR",
    "name:tur_x_preferred":[
        "Dikmeto\u015f"
    ],
    "name:unk_x_variant":[
        "Dikmetash"
    ],
    "qs:name":"Dikmeta\u015f",
    "qs:photos_9r":0,
    "qs:photos_sr":0,
    "qs:pop_sr":"1",
    "wof:name":"Dikmeta\u015f",
    "wof:placetype":"locality",
    "wof:population":47
},
  "geometry": {"coordinates":[37.67528,36.83694],"type":"Point"}
}