{
  "type": "Feature",
  "properties": {
    "gn:admin1_code":"37.0",
    "gn:asciiname":"Alamabatak",
    "gn:country_code":"TR",
    "gn:dem":585,
    "gn:feature_class":"P",
    "gn:feature_code":"PPL",
    "gn:name":"Alamabatak",
    "gn:population":0,
    "gn:timezone":"Europe/Istanbul",
    "iso:country":"TR",
    "name:und_x_variant":[
        "Alamabatak K\u00f6y",
        "Alamabatak K\u00f6y\u00fc",
        "Alamabatak"
    ],
    "wof:name":"Alamabatak",
    "wof:placetype":"locality"
},
  "geometry": {"coordinates":[34.12627,41.4651],"type":"Point"}
}