{
  "type": "Feature",
  "properties": {
    "gn:admin1_code":"22.0",
    "gn:asciiname":"Muratcali",
    "gn:country_code":"TR",
    "gn:dem":90,
    "gn:feature_class":"P",
    "gn:feature_code":"PPL",
    "gn:name":"Murat\u00e7al\u0131",
    "gn:population":0,
    "gn:timezone":"Europe/Istanbul",
    "iso:country":"TR",
    "wof:name":"Muratcali",
    "wof:placetype":"locality"
},
  "geometry": {"coordinates":[26.61602,41.8052],"type":"Point"}
}