{
  "type": "Feature",
  "properties": {
    "gn:admin1_code":"43.0",
    "gn:asciiname":"Agizoren",
    "gn:country_code":"TR",
    "gn:dem":1094,
    "gn:feature_class":"P",
    "gn:feature_code":"PPL",
    "gn:name":"A\u011f\u0131z\u00f6ren",
    "gn:population":0,
    "gn:timezone":"Europe/Istanbul",
    "iso:country":"TR",
    "name:tur_x_preferred":[
        "A\u011f\u0131z\u00f6ren"
    ],
    "name:tur_x_variant":[
        "Koz\u00f6ren",
        "A\u011fz\u0131\u00f6ren"
    ],
    "wof:name":"Agizoren",
    "wof:placetype":"locality"
},
  "geometry": {"coordinates":[29.82687,39.55434],"type":"Point"}
}