{
  "type": "Feature",
  "properties": {
    "gn:admin1_code":"40",
    "gn:asciiname":"Cebisler",
    "gn:country_code":"TR",
    "gn:dem":864,
    "gn:feature_class":"P",
    "gn:feature_code":"PPL",
    "gn:name":"\u00c7ebi\u015fler",
    "gn:population":0,
    "gn:timezone":"Europe/Istanbul",
    "iso:country":"TR",
    "wof:name":"Cebisler",
    "wof:placetype":"locality"
},
  "geometry": {"coordinates":[33.92932,39.6165],"type":"Point"}
}