{
  "type": "Feature",
  "properties": {
    "gn:admin1_code":"21",
    "gn:asciiname":"Kocakoy",
    "gn:country_code":"TR",
    "gn:dem":668,
    "gn:feature_class":"P",
    "gn:feature_code":"PPL",
    "gn:name":"Kocak\u00f6y",
    "gn:population":0,
    "gn:timezone":"Europe/Istanbul",
    "iso:country":"TR",
    "name:und_x_variant":[
        "Kocak\u00f6y",
        "Azrailan"
    ],
    "wof:name":"Kocakoy",
    "wof:placetype":"locality"
},
  "geometry": {"coordinates":[40.32003,38.07084],"type":"Point"}
}