{
  "type": "Feature",
  "properties": {
    "gn:admin1_code":"13.0",
    "gn:asciiname":"Cagdas",
    "gn:country_code":"TR",
    "gn:dem":1453,
    "gn:feature_class":"P",
    "gn:feature_code":"PPL",
    "gn:name":"\u00c7a\u011fda\u015f",
    "gn:population":0,
    "gn:timezone":"Europe/Istanbul",
    "iso:country":"TR",
    "name:tur_x_preferred":[
        "\u00c7a\u011fda\u015f"
    ],
    "wof:name":"Cagdas",
    "wof:placetype":"locality"
},
  "geometry": {"coordinates":[41.65561,38.55774],"type":"Point"}
}