{
  "type": "Feature",
  "properties": {
    "gn:admin1_code":"78",
    "gn:asciiname":"Osmaniye",
    "gn:country_code":"TR",
    "gn:dem":1007,
    "gn:feature_class":"P",
    "gn:feature_code":"PPL",
    "gn:name":"Osmaniye",
    "gn:population":0,
    "gn:timezone":"Europe/Istanbul",
    "iso:country":"TR",
    "wof:name":"Osmaniye",
    "wof:placetype":"locality"
},
  "geometry": {"coordinates":[33.29975,37.38268],"type":"Point"}
}