{
  "type": "Feature",
  "properties": {
    "gn:admin1_code":"09",
    "gn:asciiname":"Yilmazkoy",
    "gn:country_code":"TR",
    "gn:dem":119,
    "gn:feature_class":"P",
    "gn:feature_code":"PPL",
    "gn:name":"Y\u0131lmazk\u00f6y",
    "gn:population":0,
    "gn:timezone":"Europe/Istanbul",
    "iso:country":"TR",
    "name:tur_x_preferred":[
        "Y\u0131lmazk\u00f6y"
    ],
    "wof:name":"Yilmazkoy",
    "wof:placetype":"locality"
},
  "geometry": {"coordinates":[27.88971,37.85781],"type":"Point"}
}