{
  "type": "Feature",
  "properties": {
    "gn:admin1_code":"71",
    "gn:asciiname":"Yukari Esence",
    "gn:country_code":"TR",
    "gn:dem":1124,
    "gn:feature_class":"P",
    "gn:feature_code":"PPL",
    "gn:name":"Yukar\u0131 Esence",
    "gn:population":0,
    "gn:timezone":"Europe/Istanbul",
    "iso:country":"TR",
    "name:und_x_variant":[
        "Yukar\u0131homa",
        "Yukar\u0131 Esence"
    ],
    "wof:name":"Yukari Esence",
    "wof:placetype":"locality"
},
  "geometry": {"coordinates":[31.84968,37.61445],"type":"Point"}
}