{
  "type": "Feature",
  "properties": {
    "gn:admin1_code":"45",
    "gn:asciiname":"Akcesme",
    "gn:country_code":"TR",
    "gn:dem":631,
    "gn:feature_class":"P",
    "gn:feature_code":"PPL",
    "gn:name":"Ak\u00e7e\u015fme",
    "gn:population":0,
    "gn:timezone":"Europe/Istanbul",
    "iso:country":"TR",
    "name:tur_x_preferred":[
        "Ak\u00e7e\u015fme"
    ],
    "wof:name":"Akcesme",
    "wof:placetype":"locality"
},
  "geometry": {"coordinates":[28.77025,38.88206],"type":"Point"}
}