{
  "type": "Feature",
  "properties": {
    "gn:admin1_code":"72",
    "gn:asciiname":"Dirvan",
    "gn:country_code":"TR",
    "gn:dem":903,
    "gn:feature_class":"P",
    "gn:feature_code":"PPL",
    "gn:name":"Dirvan",
    "gn:population":0,
    "gn:timezone":"Europe/Istanbul",
    "iso:country":"TR",
    "wof:name":"Dirvan",
    "wof:placetype":"locality"
},
  "geometry": {"coordinates":[41.41583,37.31167],"type":"Point"}
}