{
  "type": "Feature",
  "properties": {
    "gn:admin1_code":"70",
    "gn:asciiname":"Alan",
    "gn:country_code":"TR",
    "gn:dem":1959,
    "gn:feature_class":"P",
    "gn:feature_code":"PPL",
    "gn:name":"Alan",
    "gn:population":0,
    "gn:timezone":"Europe/Istanbul",
    "iso:country":"TR",
    "name:und_x_variant":[
        "Halane",
        "Halana",
        "Alan"
    ],
    "wof:name":"Alan",
    "wof:placetype":"locality"
},
  "geometry": {"coordinates":[44.75694,37.29833],"type":"Point"}
}