{
  "type": "Feature",
  "properties": {
    "gn:admin1_code":"69.0",
    "gn:asciiname":"Gungoren",
    "gn:country_code":"TR",
    "gn:dem":1805,
    "gn:feature_class":"P",
    "gn:feature_code":"PPL",
    "gn:name":"G\u00fcng\u00f6ren",
    "gn:population":0,
    "gn:timezone":"Europe/Istanbul",
    "iso:country":"TR",
    "name:und_x_variant":[
        "G\u00fcng\u00f6ren",
        "G\u00fcndo\u011fdu"
    ],
    "wof:name":"Gungoren",
    "wof:placetype":"locality"
},
  "geometry": {"coordinates":[40.05814,40.56101],"type":"Point"}
}