{
  "type": "Feature",
  "properties": {
    "gn:admin1_code":"66",
    "gn:asciiname":"Ozan",
    "gn:country_code":"TR",
    "gn:dem":1218,
    "gn:feature_class":"P",
    "gn:feature_code":"PPL",
    "gn:name":"Ozan",
    "gn:population":0,
    "gn:timezone":"Europe/Istanbul",
    "iso:country":"TR",
    "name:aze_x_preferred":[
        "Ozan"
    ],
    "name:ceb_x_preferred":[
        "Ozan"
    ],
    "name:deu_x_preferred":[
        "Ozan"
    ],
    "name:hun_x_preferred":[
        "Ozan"
    ],
    "name:hye_x_preferred":[
        "\u0555\u0566\u0561\u0576"
    ],
    "name:nld_x_preferred":[
        "Ozan"
    ],
    "name:pol_x_preferred":[
        "Ozan"
    ],
    "name:por_x_preferred":[
        "Ozan"
    ],
    "name:swe_x_preferred":[
        "Ozan"
    ],
    "name:tur_x_preferred":[
        "Ozan"
    ],
    "wof:name":"Ozan",
    "wof:placetype":"locality"
},
  "geometry": {"coordinates":[35.56645,39.6551],"type":"Point"}
}