{
  "type": "Feature",
  "properties": {
    "gn:admin1_code":"45",
    "gn:asciiname":"Lazdegirmeni",
    "gn:country_code":"TR",
    "gn:dem":1269,
    "gn:feature_class":"P",
    "gn:feature_code":"PPL",
    "gn:name":"Lazde\u011firmeni",
    "gn:population":0,
    "gn:timezone":"Europe/Istanbul",
    "iso:country":"TR",
    "wof:name":"Lazdegirmeni",
    "wof:placetype":"locality"
},
  "geometry": {"coordinates":[28.83333,39.08333],"type":"Point"}
}