{
  "type": "Feature",
  "properties": {
    "gn:admin1_code":"60.0",
    "gn:asciiname":"Asagifirindere",
    "gn:country_code":"TR",
    "gn:dem":1412,
    "gn:feature_class":"P",
    "gn:feature_code":"PPL",
    "gn:name":"A\u015fa\u011f\u0131f\u0131r\u0131ndere",
    "gn:population":0,
    "gn:timezone":"Europe/Istanbul",
    "iso:country":"TR",
    "name:und_x_variant":[
        "A\u015fa\u011f\u0131 F\u0131r\u0131ndere K\u00f6y",
        "A\u015fa\u011f\u0131f\u0131r\u0131ndere"
    ],
    "wof:name":"Asagifirindere",
    "wof:placetype":"locality"
},
  "geometry": {"coordinates":[36.70603,40.13838],"type":"Point"}
}