{
  "type": "Feature",
  "properties": {
    "gn:admin1_code":"45",
    "gn:asciiname":"Golbasi",
    "gn:country_code":"TR",
    "gn:dem":762,
    "gn:feature_class":"P",
    "gn:feature_code":"PPL",
    "gn:name":"G\u00f6lba\u015f\u0131",
    "gn:population":0,
    "gn:timezone":"Europe/Istanbul",
    "iso:country":"TR",
    "name:tur_x_preferred":[
        "G\u00f6lba\u015f\u0131"
    ],
    "wof:name":"Golbasi",
    "wof:placetype":"locality"
},
  "geometry": {"coordinates":[28.60185,38.51769],"type":"Point"}
}