{
  "type": "Feature",
  "properties": {
    "gn:admin1_code":"28.0",
    "gn:asciiname":"Balcikbeleni",
    "gn:country_code":"TR",
    "gn:dem":194,
    "gn:feature_class":"P",
    "gn:feature_code":"PPL",
    "gn:name":"Bal\u00e7\u0131kbeleni",
    "gn:population":0,
    "gn:timezone":"Europe/Istanbul",
    "iso:country":"TR",
    "name:tur_x_preferred":[
        "Bal\u00e7\u0131kbeleni"
    ],
    "wof:name":"Balcikbeleni",
    "wof:placetype":"locality"
},
  "geometry": {"coordinates":[38.88876,40.97436],"type":"Point"}
}