{
  "type": "Feature",
  "properties": {
    "gn:admin1_code":"8.0",
    "gn:asciiname":"Kurudere",
    "gn:country_code":"TR",
    "gn:dem":973,
    "gn:feature_class":"P",
    "gn:feature_code":"PPL",
    "gn:name":"Kurudere",
    "gn:population":0,
    "gn:timezone":"Europe/Istanbul",
    "iso:country":"TR",
    "wof:name":"Kurudere",
    "wof:placetype":"locality"
},
  "geometry": {"coordinates":[42.33339,41.2551],"type":"Point"}
}