{
  "type": "Feature",
  "properties": {
    "gn:admin1_code":"65",
    "gn:asciiname":"Doganlar",
    "gn:country_code":"TR",
    "gn:dem":1828,
    "gn:feature_class":"P",
    "gn:feature_code":"PPL",
    "gn:name":"Do\u011fanlar",
    "gn:population":0,
    "gn:timezone":"Europe/Istanbul",
    "iso:country":"TR",
    "name:und_x_variant":[
        "Pertek",
        "Do\u011fanlar"
    ],
    "wof:name":"Doganlar",
    "wof:placetype":"locality"
},
  "geometry": {"coordinates":[43.35158,38.40293],"type":"Point"}
}