{
  "type": "Feature",
  "properties": {
    "gn:admin1_code":"63.0",
    "gn:asciiname":"Saryani",
    "gn:country_code":"TR",
    "gn:dem":490,
    "gn:feature_class":"P",
    "gn:feature_code":"PPL",
    "gn:name":"\u015earyan\u0131",
    "gn:population":0,
    "gn:timezone":"Europe/Istanbul",
    "iso:country":"TR",
    "name:rus_x_preferred":[
        "Shar\u2019yani"
    ],
    "name:tur_x_preferred":[
        "\u015eazyan\u0131"
    ],
    "name:und_x_variant":[
        "Remil",
        "\u015earyan\u0131"
    ],
    "wof:name":"Saryani",
    "wof:placetype":"locality"
},
  "geometry": {"coordinates":[38.44008,36.97581],"type":"Point"}
}