{
  "type": "Feature",
  "properties": {
    "gn:admin1_code":"37.0",
    "gn:asciiname":"Imamkoy",
    "gn:country_code":"TR",
    "gn:dem":1098,
    "gn:feature_class":"P",
    "gn:feature_code":"PPL",
    "gn:name":"\u0130mamk\u00f6y",
    "gn:population":0,
    "gn:timezone":"Europe/Istanbul",
    "iso:country":"TR",
    "wof:name":"Imamkoy",
    "wof:placetype":"locality"
},
  "geometry": {"coordinates":[33.95327,41.31039000000001],"type":"Point"}
}