{
  "type": "Feature",
  "properties": {
    "gn:admin1_code":"46",
    "gn:asciiname":"Kalekaya",
    "gn:country_code":"TR",
    "gn:dem":1050,
    "gn:feature_class":"P",
    "gn:feature_code":"PPL",
    "gn:name":"Kalekaya",
    "gn:population":0,
    "gn:timezone":"Europe/Istanbul",
    "iso:country":"TR",
    "name:tur_x_preferred":[
        "Kalekaya"
    ],
    "name:und_x_variant":[
        "Kalek\u00f6y",
        "Kalekayak\u00f6y\u00fc"
    ],
    "wof:name":"Kalekaya",
    "wof:placetype":"locality"
},
  "geometry": {"coordinates":[36.55781,37.44515],"type":"Point"}
}