{
  "type": "Feature",
  "properties": {
    "gn:admin1_code":"21",
    "gn:asciiname":"Gurbulak",
    "gn:country_code":"TR",
    "gn:dem":1228,
    "gn:feature_class":"P",
    "gn:feature_code":"PPL",
    "gn:name":"G\u00fcrbulak",
    "gn:population":0,
    "gn:timezone":"Europe/Istanbul",
    "iso:country":"TR",
    "name:tur_x_preferred":[
        "G\u00fcrbulak"
    ],
    "wof:name":"Gurbulak",
    "wof:placetype":"locality"
},
  "geometry": {"coordinates":[40.46109000000001,38.43914],"type":"Point"}
}