{
  "type": "Feature",
  "properties": {
    "gn:admin1_code":"31",
    "gn:asciiname":"Besirler",
    "gn:country_code":"TR",
    "gn:dem":196,
    "gn:feature_class":"P",
    "gn:feature_code":"PPL",
    "gn:name":"Besirler",
    "gn:population":0,
    "gn:timezone":"Europe/Istanbul",
    "iso:country":"TR",
    "name:tur_x_preferred":[
        "Besirler"
    ],
    "wof:name":"Besirler",
    "wof:placetype":"locality"
},
  "geometry": {"coordinates":[36.1882,36.36742],"type":"Point"}
}