{
  "type": "Feature",
  "properties": {
    "gn:admin1_code":"89.0",
    "gn:asciiname":"Yurukoren",
    "gn:country_code":"TR",
    "gn:dem":1234,
    "gn:feature_class":"P",
    "gn:feature_code":"PPL",
    "gn:name":"Y\u00fcr\u00fck\u00f6ren",
    "gn:population":0,
    "gn:timezone":"Europe/Istanbul",
    "iso:country":"TR",
    "wof:name":"Yurukoren",
    "wof:placetype":"locality"
},
  "geometry": {"coordinates":[32.87715,40.97193],"type":"Point"}
}