{
  "type": "Feature",
  "properties": {
    "gn:admin1_code":"90",
    "gn:asciiname":"Uzunlu",
    "gn:country_code":"TR",
    "gn:dem":675,
    "gn:feature_class":"P",
    "gn:feature_code":"PPL",
    "gn:name":"Uzunlu",
    "gn:population":0,
    "gn:timezone":"Europe/Istanbul",
    "iso:country":"TR",
    "name:tur_x_preferred":[
        "Uzunlu"
    ],
    "wof:name":"Uzunlu",
    "wof:placetype":"locality"
},
  "geometry": {"coordinates":[37.2166,36.76828],"type":"Point"}
}