{
  "type": "Feature",
  "properties": {
    "gn:admin1_code":"63",
    "gn:asciiname":"Gulus",
    "gn:cc2":"TR",
    "gn:country_code":"TR",
    "gn:dem":1114,
    "gn:feature_class":"P",
    "gn:feature_code":"PPL",
    "gn:name":"G\u00fcl\u00fc\u015f",
    "gn:population":0,
    "gn:timezone":"Europe/Istanbul",
    "iso:country":"TR",
    "name:und_x_variant":[
        "Kelo\u015f",
        "G\u00fcl\u00fc\u015f"
    ],
    "wof:name":"Gulus",
    "wof:placetype":"locality"
},
  "geometry": {"coordinates":[39.61667,37.81667],"type":"Point"}
}