{
  "type": "Feature",
  "properties": {
    "gn:admin1_code":"21.0",
    "gn:asciiname":"Agacgecit",
    "gn:country_code":"TR",
    "gn:dem":669,
    "gn:feature_class":"P",
    "gn:feature_code":"PPL",
    "gn:name":"A\u011fa\u00e7ge\u00e7it",
    "gn:population":0,
    "gn:timezone":"Europe/Istanbul",
    "iso:country":"TR",
    "name:tur_x_preferred":[
        "A\u011fa\u00e7ge\u00e7it"
    ],
    "wof:name":"Agacgecit",
    "wof:placetype":"locality"
},
  "geometry": {"coordinates":[40.17649,37.8744],"type":"Point"}
}