{
  "type": "Feature",
  "properties": {
    "gn:admin1_code":"65",
    "gn:asciiname":"Kasikcilar",
    "gn:country_code":"TR",
    "gn:dem":2076,
    "gn:feature_class":"P",
    "gn:feature_code":"PPL",
    "gn:name":"Ka\u015f\u0131k\u00e7\u0131lar",
    "gn:population":0,
    "gn:timezone":"Europe/Istanbul",
    "iso:country":"TR",
    "name:tur_x_preferred":[
        "Ka\u015f\u0131k\u00e7\u0131lar"
    ],
    "name:und_x_variant":[
        "Ka\u015f\u0131k\u00e7\u0131"
    ],
    "wof:name":"Kasikcilar",
    "wof:placetype":"locality"
},
  "geometry": {"coordinates":[42.85312,38.04904000000001],"type":"Point"}
}