{
  "type": "Feature",
  "properties": {
    "gn:admin1_code":"21",
    "gn:asciiname":"Bostanpinari",
    "gn:country_code":"TR",
    "gn:dem":669,
    "gn:feature_class":"P",
    "gn:feature_code":"PPL",
    "gn:name":"Bostanp\u0131nar\u0131",
    "gn:population":0,
    "gn:timezone":"Europe/Istanbul",
    "iso:country":"TR",
    "name:tur_x_preferred":[
        "Bostanp\u0131nar\u0131"
    ],
    "wof:name":"Bostanpinari",
    "wof:placetype":"locality"
},
  "geometry": {"coordinates":[40.31615,38.08294],"type":"Point"}
}