{
  "type": "Feature",
  "properties": {
    "gn:admin1_code":"69.0",
    "gn:asciiname":"Calik",
    "gn:country_code":"TR",
    "gn:dem":1794,
    "gn:feature_class":"P",
    "gn:feature_code":"PPL",
    "gn:name":"\u00c7al\u0131k",
    "gn:population":0,
    "gn:timezone":"Europe/Istanbul",
    "iso:country":"TR",
    "name:tur_x_preferred":[
        "\u00c7al\u0131k"
    ],
    "wof:name":"Calik",
    "wof:placetype":"locality"
},
  "geometry": {"coordinates":[39.78751,40.35181],"type":"Point"}
}