{
  "type": "Feature",
  "properties": {
    "gn:admin1_code":"52.0",
    "gn:asciiname":"Asagikizilin",
    "gn:country_code":"TR",
    "gn:dem":555,
    "gn:feature_class":"P",
    "gn:feature_code":"PPL",
    "gn:name":"A\u015fa\u011f\u0131k\u0131z\u0131lin",
    "gn:population":0,
    "gn:timezone":"Europe/Istanbul",
    "iso:country":"TR",
    "wof:name":"Asagikizilin",
    "wof:placetype":"locality"
},
  "geometry": {"coordinates":[37.69686,40.80545],"type":"Point"}
}