{
  "type": "Feature",
  "properties": {
    "gn:admin1_code":"11",
    "gn:asciiname":"Osmaniye",
    "gn:cc2":"TR",
    "gn:country_code":"TR",
    "gn:dem":1031,
    "gn:feature_class":"P",
    "gn:feature_code":"PPL",
    "gn:name":"Osmaniye",
    "gn:population":0,
    "gn:timezone":"Europe/Istanbul",
    "iso:country":"TR",
    "name:rus_x_preferred":[
        "\u041e\u0441\u043c\u0430\u043d\u0438\u0435"
    ],
    "name:und_x_variant":[
        "I\u015f\u0131kp\u0131nar",
        "Osmaniye"
    ],
    "wof:name":"Osmaniye",
    "wof:placetype":"locality"
},
  "geometry": {"coordinates":[30.00333,39.66861],"type":"Point"}
}