{
  "type": "Feature",
  "properties": {
    "gn:admin1_code":"21",
    "gn:asciiname":"Kucukkadi",
    "gn:country_code":"TR",
    "gn:dem":725,
    "gn:feature_class":"P",
    "gn:feature_code":"PPL",
    "gn:name":"K\u00fc\u00e7\u00fckkad\u0131",
    "gn:population":0,
    "gn:timezone":"Europe/Istanbul",
    "iso:country":"TR",
    "name:tur_x_preferred":[
        "K\u00fc\u00e7\u00fckkad\u0131"
    ],
    "name:und_x_variant":[
        "K\u00fc\u00e7\u00fck Kad\u0131k\u00f6y"
    ],
    "wof:name":"Kucukkadi",
    "wof:placetype":"locality"
},
  "geometry": {"coordinates":[40.29035,37.96546],"type":"Point"}
}