{
  "type": "Feature",
  "properties": {
    "gn:admin1_code":"37.0",
    "gn:asciiname":"Tascilar",
    "gn:country_code":"TR",
    "gn:dem":1310,
    "gn:feature_class":"P",
    "gn:feature_code":"PPL",
    "gn:name":"Ta\u015f\u00e7\u0131lar",
    "gn:population":0,
    "gn:timezone":"Europe/Istanbul",
    "iso:country":"TR",
    "name:und_x_variant":[
        "\u0130sa",
        "Eserli",
        "Ta\u015f\u00e7\u0131lar"
    ],
    "wof:name":"Tascilar",
    "wof:placetype":"locality"
},
  "geometry": {"coordinates":[34.13715,41.19945],"type":"Point"}
}