{
  "type": "Feature",
  "properties": {
    "gn:admin1_code":"85.0",
    "gn:asciiname":"Yolgecen",
    "gn:country_code":"TR",
    "gn:dem":77,
    "gn:feature_class":"P",
    "gn:feature_code":"PPL",
    "gn:name":"Yolge\u00e7en",
    "gn:population":0,
    "gn:timezone":"Europe/Istanbul",
    "iso:country":"TR",
    "name:und_x_variant":[
        "Balgur",
        "Balkur",
        "Bargur",
        "Yolge\u00e7en"
    ],
    "wof:name":"Yolgecen",
    "wof:placetype":"locality"
},
  "geometry": {"coordinates":[32.15333,41.45233],"type":"Point"}
}