{
  "type": "Feature",
  "properties": {
    "gn:admin1_code":"48",
    "gn:asciiname":"Kuyucak",
    "gn:country_code":"TR",
    "gn:dem":11,
    "gn:feature_class":"P",
    "gn:feature_code":"PPL",
    "gn:name":"Kuyucak",
    "gn:population":0,
    "gn:timezone":"Europe/Istanbul",
    "iso:country":"TR",
    "name:tur_x_preferred":[
        "Kuyucak"
    ],
    "wof:name":"Kuyucak",
    "wof:placetype":"locality"
},
  "geometry": {"coordinates":[27.56568,37.15401],"type":"Point"}
}