{
  "type": "Feature",
  "properties": {
    "gn:admin1_code":"26",
    "gn:asciiname":"Topal Yaylasi",
    "gn:country_code":"TR",
    "gn:dem":785,
    "gn:feature_class":"P",
    "gn:feature_code":"PPL",
    "gn:name":"Topal Yaylas\u0131",
    "gn:population":0,
    "gn:timezone":"Europe/Istanbul",
    "iso:country":"TR",
    "wof:name":"Topal Yaylasi",
    "wof:placetype":"locality"
},
  "geometry": {"coordinates":[31.78074,39.1632],"type":"Point"}
}