{
  "type": "Feature",
  "properties": {
    "gn:admin1_code":"26",
    "gn:asciiname":"Gecek",
    "gn:country_code":"TR",
    "gn:dem":1014,
    "gn:feature_class":"P",
    "gn:feature_code":"PPL",
    "gn:name":"Gecek",
    "gn:population":0,
    "gn:timezone":"Europe/Istanbul",
    "iso:country":"TR",
    "wof:name":"Gecek",
    "wof:placetype":"locality"
},
  "geometry": {"coordinates":[31.76978,39.38161],"type":"Point"}
}