{
  "type": "Feature",
  "properties": {
    "gn:admin1_code":"88.0",
    "gn:asciiname":"Karatas",
    "gn:country_code":"TR",
    "gn:dem":1738,
    "gn:feature_class":"P",
    "gn:feature_code":"PPL",
    "gn:name":"Karata\u015f",
    "gn:population":0,
    "gn:timezone":"Europe/Istanbul",
    "iso:country":"TR",
    "wof:name":"Karatas",
    "wof:placetype":"locality"
},
  "geometry": {"coordinates":[43.50796,39.9939],"type":"Point"}
}