{
  "type": "Feature",
  "properties": {
    "gn:admin1_code":"09",
    "gn:asciiname":"Asagiyakacik",
    "gn:country_code":"TR",
    "gn:dem":686,
    "gn:feature_class":"P",
    "gn:feature_code":"PPL",
    "gn:name":"A\u015fa\u011f\u0131yakac\u0131k",
    "gn:population":0,
    "gn:timezone":"Europe/Istanbul",
    "iso:country":"TR",
    "name:und_x_variant":[
        "A\u015fa\u011f\u0131avra",
        "A\u015fa\u011f\u0131yakac\u0131k"
    ],
    "wof:name":"Asagiyakacik",
    "wof:placetype":"locality"
},
  "geometry": {"coordinates":[28.49143,38.08636],"type":"Point"}
}