{
  "type": "Feature",
  "properties": {
    "gn:admin1_code":"21",
    "gn:asciiname":"Duzalan",
    "gn:country_code":"TR",
    "gn:dem":675,
    "gn:feature_class":"P",
    "gn:feature_code":"PPL",
    "gn:name":"D\u00fczalan",
    "gn:population":0,
    "gn:timezone":"Europe/Istanbul",
    "iso:country":"TR",
    "name:und_x_variant":[
        "D\u00fczalan",
        "Dirrik"
    ],
    "wof:name":"Duzalan",
    "wof:placetype":"locality"
},
  "geometry": {"coordinates":[41.08752,38.00753],"type":"Point"}
}