{
  "type": "Feature",
  "properties": {
    "gn:admin1_code":"31",
    "gn:asciiname":"Derekuyu",
    "gn:country_code":"TR",
    "gn:dem":267,
    "gn:feature_class":"P",
    "gn:feature_code":"PPL",
    "gn:name":"Derekuyu",
    "gn:population":0,
    "gn:timezone":"Europe/Istanbul",
    "iso:country":"TR",
    "name:und_x_variant":[
        "Derekuyu K\u00f6y\u00fc",
        "Derekuyu"
    ],
    "wof:name":"Derekuyu",
    "wof:placetype":"locality"
},
  "geometry": {"coordinates":[36.04596,36.44347],"type":"Point"}
}