{
  "type": "Feature",
  "properties": {
    "gn:admin1_code":"28.0",
    "gn:asciiname":"Hacihueseyin",
    "gn:country_code":"TR",
    "gn:dem":326,
    "gn:feature_class":"P",
    "gn:feature_code":"PPL",
    "gn:name":"Hac\u0131h\u00fcseyin",
    "gn:population":0,
    "gn:timezone":"Europe/Istanbul",
    "iso:country":"TR",
    "name:tur_x_preferred":[
        "Hac\u0131h\u00fcseyin"
    ],
    "name:und_x_variant":[
        "Hacih\u00fcseyin"
    ],
    "wof:name":"Hacihueseyin",
    "wof:placetype":"locality"
},
  "geometry": {"coordinates":[38.91379000000001,40.98601],"type":"Point"}
}