{
  "type": "Feature",
  "properties": {
    "gn:admin1_code":"21",
    "gn:asciiname":"Hevsinan",
    "gn:country_code":"TR",
    "gn:dem":878,
    "gn:feature_class":"P",
    "gn:feature_code":"PPL",
    "gn:name":"Hevsinan",
    "gn:population":0,
    "gn:timezone":"Europe/Istanbul",
    "iso:country":"TR",
    "name:und_x_variant":[
        "\u00c7eman"
    ],
    "wof:name":"Hevsinan",
    "wof:placetype":"locality"
},
  "geometry": {"coordinates":[40.41296,38.30398],"type":"Point"}
}