{
  "type": "Feature",
  "properties": {
    "gn:admin1_code":"26",
    "gn:asciiname":"Asagikuzfindik",
    "gn:country_code":"TR",
    "gn:dem":967,
    "gn:feature_class":"P",
    "gn:feature_code":"PPL",
    "gn:name":"A\u015fa\u011f\u0131kuzf\u0131nd\u0131k",
    "gn:population":0,
    "gn:timezone":"Europe/Istanbul",
    "iso:country":"TR",
    "name:und_x_variant":[
        "Kuzf\u0131nd\u0131k",
        "A\u015fa\u011f\u0131kuzf\u0131nd\u0131k"
    ],
    "wof:name":"Asagikuzfindik",
    "wof:placetype":"locality"
},
  "geometry": {"coordinates":[30.0675,39.69972],"type":"Point"}
}