{
  "type": "Feature",
  "properties": {
    "gn:admin1_code":"59.0",
    "gn:asciiname":"Kizilcaterzi",
    "gn:country_code":"TR",
    "gn:dem":119,
    "gn:feature_class":"P",
    "gn:feature_code":"PPL",
    "gn:name":"K\u0131z\u0131lcaterzi",
    "gn:population":0,
    "gn:timezone":"Europe/Istanbul",
    "iso:country":"TR",
    "wof:name":"Kizilcaterzi",
    "wof:placetype":"locality"
},
  "geometry": {"coordinates":[26.98374,40.58703],"type":"Point"}
}