{
  "type": "Feature",
  "properties": {
    "gn:admin1_code":"71",
    "gn:asciiname":"Ilmen",
    "gn:country_code":"TR",
    "gn:dem":1271,
    "gn:feature_class":"P",
    "gn:feature_code":"PPL",
    "gn:name":"\u0130lmen",
    "gn:population":0,
    "gn:timezone":"Europe/Istanbul",
    "iso:country":"TR",
    "name:tur_x_preferred":[
        "\u0130lmen"
    ],
    "wof:name":"Ilmen",
    "wof:placetype":"locality"
},
  "geometry": {"coordinates":[31.56416,37.98554],"type":"Point"}
}