{
  "type": "Feature",
  "properties": {
    "gn:admin1_code":"79",
    "gn:asciiname":"Sarikaya",
    "gn:country_code":"TR",
    "gn:dem":1124,
    "gn:feature_class":"P",
    "gn:feature_code":"PPL",
    "gn:name":"Sar\u0131kaya",
    "gn:population":0,
    "gn:timezone":"Europe/Istanbul",
    "iso:country":"TR",
    "wof:name":"Sarikaya",
    "wof:placetype":"locality"
},
  "geometry": {"coordinates":[33.30866,39.67166],"type":"Point"}
}