{
  "type": "Feature",
  "properties": {
    "gn:admin1_code":"49.0",
    "gn:asciiname":"Asagi Balozu",
    "gn:country_code":"TR",
    "gn:dem":1654,
    "gn:feature_class":"P",
    "gn:feature_code":"PPL",
    "gn:name":"A\u015fa\u011f\u0131 Bal\u00f6z\u00fc",
    "gn:population":0,
    "gn:timezone":"Europe/Istanbul",
    "iso:country":"TR",
    "name:tur_x_preferred":[
        "A\u015fa\u011f\u0131 Bal\u00f6z\u00fc"
    ],
    "wof:name":"Asagi Balozu",
    "wof:placetype":"locality"
},
  "geometry": {"coordinates":[41.56182,38.63762],"type":"Point"}
}