{
  "type": "Feature",
  "properties": {
    "gn:admin1_code":"53.0",
    "gn:asciiname":"Kaplica",
    "gn:country_code":"TR",
    "gn:dem":692,
    "gn:feature_class":"P",
    "gn:feature_code":"PPL",
    "gn:name":"Kapl\u0131ca",
    "gn:population":0,
    "gn:timezone":"Europe/Istanbul",
    "iso:country":"TR",
    "name:nld_x_preferred":[
        "Kaplica"
    ],
    "name:pol_x_preferred":[
        "Kaplica"
    ],
    "name:ukr_x_preferred":[
        "\u041a\u0430\u043f\u043b\u0438\u0446\u044f"
    ],
    "name:und_x_variant":[
        "Kapl\u0131ca",
        "Hol\u00e7o"
    ],
    "wof:name":"Kaplica",
    "wof:placetype":"locality"
},
  "geometry": {"coordinates":[41.04766,41.01507],"type":"Point"}
}