{
  "type": "Feature",
  "properties": {
    "gn:admin1_code":"37.0",
    "gn:asciiname":"Arfi",
    "gn:country_code":"TR",
    "gn:dem":714,
    "gn:feature_class":"P",
    "gn:feature_code":"PPL",
    "gn:name":"Arfi",
    "gn:population":0,
    "gn:timezone":"Europe/Istanbul",
    "iso:country":"TR",
    "name:und_x_variant":[
        "Yol\u00fcst\u00fc"
    ],
    "wof:name":"Arfi",
    "wof:placetype":"locality"
},
  "geometry": {"coordinates":[33.72957,41.90766],"type":"Point"}
}