{
  "type": "Feature",
  "properties": {
    "gn:admin1_code":"32",
    "gn:asciiname":"Kumkuyu",
    "gn:country_code":"TR",
    "gn:dem":28,
    "gn:feature_class":"P",
    "gn:feature_code":"PPL",
    "gn:name":"Kumkuyu",
    "gn:population":0,
    "gn:timezone":"Europe/Istanbul",
    "iso:country":"TR",
    "wof:name":"Kumkuyu",
    "wof:placetype":"locality"
},
  "geometry": {"coordinates":[34.20878,36.52045],"type":"Point"}
}