{
  "type": "Feature",
  "properties": {
    "gn:admin1_code":"8.0",
    "gn:asciiname":"Cagliyan",
    "gn:country_code":"TR",
    "gn:dem":476,
    "gn:feature_class":"P",
    "gn:feature_code":"PPL",
    "gn:name":"\u00c7a\u011fl\u0131yan",
    "gn:population":0,
    "gn:timezone":"Europe/Istanbul",
    "iso:country":"TR",
    "name:und_x_variant":[
        "\u00c7a\u011fl\u0131yan",
        "U\u015fhum"
    ],
    "wof:name":"Cagliyan",
    "wof:placetype":"locality"
},
  "geometry": {"coordinates":[41.76329000000001,40.95089],"type":"Point"}
}