{
  "type": "Feature",
  "properties": {
    "gn:admin1_code":"63",
    "gn:asciiname":"Karatepe",
    "gn:country_code":"TR",
    "gn:dem":535,
    "gn:feature_class":"P",
    "gn:feature_code":"PPL",
    "gn:name":"Karatepe",
    "gn:population":0,
    "gn:timezone":"Europe/Istanbul",
    "iso:country":"TR",
    "name:tur_x_preferred":[
        "Karatepe"
    ],
    "wof:name":"Karatepe",
    "wof:placetype":"locality"
},
  "geometry": {"coordinates":[39.0163,37.2392],"type":"Point"}
}