{
  "type": "Feature",
  "properties": {
    "gn:admin1_code":"86.0",
    "gn:asciiname":"Yokusdibi",
    "gn:cc2":"TR",
    "gn:country_code":"TR",
    "gn:dem":1913,
    "gn:feature_class":"P",
    "gn:feature_code":"PPL",
    "gn:name":"Yoku\u015fdibi",
    "gn:population":0,
    "gn:timezone":"Europe/Istanbul",
    "iso:country":"TR",
    "name:msa_x_preferred":[
        "Yoku\u015fdibi"
    ],
    "name:tur_x_preferred":[
        "Yoku\u015fdibi"
    ],
    "name:und_x_variant":[
        "Lori",
        "Yoku\u015fdibi"
    ],
    "name:vie_x_preferred":[
        "Yoku\u015fdibi"
    ],
    "wof:name":"Yokusdibi",
    "wof:placetype":"locality"
},
  "geometry": {"coordinates":[42.58333,41.18333],"type":"Point"}
}