{
  "type": "Feature",
  "properties": {
    "gn:admin1_code":"5.0",
    "gn:asciiname":"Cambuku",
    "gn:country_code":"TR",
    "gn:dem":284,
    "gn:feature_class":"P",
    "gn:feature_code":"PPL",
    "gn:name":"\u00c7amb\u00fck\u00fc",
    "gn:population":0,
    "gn:timezone":"Europe/Istanbul",
    "iso:country":"TR",
    "name:und_x_variant":[
        "Me\u011fellib\u00fck\u00fc",
        "\u00c7amb\u00fck\u00fc"
    ],
    "wof:name":"Cambuku",
    "wof:placetype":"locality"
},
  "geometry": {"coordinates":[36.21826,40.73922],"type":"Point"}
}