{
  "type": "Feature",
  "properties": {
    "gn:admin1_code":"33",
    "gn:asciiname":"Kelikan",
    "gn:cc2":"TR",
    "gn:country_code":"TR",
    "gn:dem":1607,
    "gn:feature_class":"P",
    "gn:feature_code":"PPL",
    "gn:name":"Kelikan",
    "gn:population":0,
    "gn:timezone":"Europe/Istanbul",
    "iso:country":"TR",
    "name:ara_x_preferred":[
        "\u0643\u0644\u064a\u0643\u0627\u0646"
    ],
    "name:ceb_x_preferred":[
        "Kel\u012bk\u0101n"
    ],
    "name:fas_x_preferred":[
        "\u06a9\u0644\u06cc\u06a9\u0627\u0646"
    ],
    "name:mzn_x_preferred":[
        "\u06a9\u0644\u06cc\u06a9\u0627\u0646"
    ],
    "name:swe_x_preferred":[
        "Kel\u012bk\u0101n"
    ],
    "name:ukr_x_preferred":[
        "\u041a\u0435\u043b\u0456\u043a\u0430\u043d"
    ],
    "name:und_x_variant":[
        "Kalkan",
        "Kalakan Mahallesi",
        "Kelikan"
    ],
    "wof:name":"Kelikan",
    "wof:placetype":"locality"
},
  "geometry": {"coordinates":[30.68333,37.98333],"type":"Point"}
}