{
  "type": "Feature",
  "properties": {
    "gn:admin1_code":"82.0",
    "gn:asciiname":"Balci",
    "gn:country_code":"TR",
    "gn:dem":1367,
    "gn:feature_class":"P",
    "gn:feature_code":"PPL",
    "gn:name":"Balc\u0131",
    "gn:population":0,
    "gn:timezone":"Europe/Istanbul",
    "iso:country":"TR",
    "wof:name":"Balci",
    "wof:placetype":"locality"
},
  "geometry": {"coordinates":[33.47571,41.04563],"type":"Point"}
}