{
  "type": "Feature",
  "properties": {
    "iso:country":"TR",
    "name:eng_x_preferred":[
        "Zerzavatci"
    ],
    "name:tur_x_preferred":[
        "Zerzavat\u00e7\u0131"
    ],
    "wof:name":"Zerzavatci",
    "wof:placetype":"neighbourhood"
},
  "geometry": {"coordinates":[29.1597441428745,41.12924287404369],"type":"Point"}
}