{
  "type": "Feature",
  "properties": {
    "gn:admin1_code":"19.0",
    "gn:asciiname":"Ecviortakisla",
    "gn:country_code":"TR",
    "gn:dem":1185,
    "gn:feature_class":"P",
    "gn:feature_code":"PPL",
    "gn:name":"Ecviortak\u0131\u015fla",
    "gn:population":0,
    "gn:timezone":"Europe/Istanbul",
    "iso:country":"TR",
    "wof:name":"Ecviortakisla",
    "wof:placetype":"locality"
},
  "geometry": {"coordinates":[34.62369,40.34807],"type":"Point"}
}