{
  "type": "Feature",
  "properties": {
    "gn:admin1_code":"78",
    "gn:asciiname":"Dumlugoze",
    "gn:country_code":"TR",
    "gn:dem":1026,
    "gn:feature_class":"P",
    "gn:feature_code":"PPL",
    "gn:name":"Dumlug\u00f6ze",
    "gn:population":0,
    "gn:timezone":"Europe/Istanbul",
    "iso:country":"TR",
    "name:und_x_variant":[
        "Muzad\u0131",
        "Muzvadi",
        "Dumlug\u00f6ze"
    ],
    "wof:name":"Dumlugoze",
    "wof:placetype":"locality"
},
  "geometry": {"coordinates":[32.55710999999999,36.55278],"type":"Point"}
}