{
  "type": "Feature",
  "properties": {
    "gn:admin1_code":"85",
    "gn:asciiname":"Geris",
    "gn:country_code":"TR",
    "gn:dem":144,
    "gn:feature_class":"P",
    "gn:feature_code":"PPL",
    "gn:name":"Geris",
    "gn:population":0,
    "gn:timezone":"Europe/Istanbul",
    "iso:country":"TR",
    "wof:name":"Geris",
    "wof:placetype":"locality"
},
  "geometry": {"coordinates":[32.11101,41.36712],"type":"Point"}
}