{
  "type": "Feature",
  "properties": {
    "gn:admin1_code":"81",
    "gn:asciiname":"Arslanli",
    "gn:country_code":"TR",
    "gn:dem":58,
    "gn:feature_class":"P",
    "gn:feature_code":"PPL",
    "gn:name":"Arslanl\u0131",
    "gn:population":0,
    "gn:timezone":"Europe/Istanbul",
    "iso:country":"TR",
    "name:und_x_variant":[
        "Arslanl\u0131 K\u00f6y\u00fc",
        "Aslanl\u0131",
        "Arslanl\u0131",
        "Karalar\u00f6z\u00fc"
    ],
    "wof:name":"Arslanli",
    "wof:placetype":"locality"
},
  "geometry": {"coordinates":[35.76667,37.31667],"type":"Point"}
}