{
  "type": "Feature",
  "properties": {
    "gn:admin1_code":"71",
    "gn:asciiname":"Yassioren",
    "gn:country_code":"TR",
    "gn:dem":1321,
    "gn:feature_class":"P",
    "gn:feature_code":"PPL",
    "gn:name":"Yass\u0131\u00f6ren",
    "gn:population":0,
    "gn:timezone":"Europe/Istanbul",
    "iso:country":"TR",
    "name:und_x_variant":[
        "Arap\u00f6z\u00fc",
        "Yass\u0131\u00f6ren"
    ],
    "wof:name":"Yassioren",
    "wof:placetype":"locality"
},
  "geometry": {"coordinates":[31.8886,37.9834],"type":"Point"}
}