{
  "type": "Feature",
  "properties": {
    "gn:admin1_code":"26",
    "gn:asciiname":"Ertugrul",
    "gn:country_code":"TR",
    "gn:dem":868,
    "gn:feature_class":"P",
    "gn:feature_code":"PPL",
    "gn:name":"Ertu\u011frul",
    "gn:population":0,
    "gn:timezone":"Europe/Istanbul",
    "iso:country":"TR",
    "name:und_x_variant":[
        "Yakap\u0131nar",
        "Ertu\u011frul",
        "Ertu\u011frulk\u00f6y"
    ],
    "wof:name":"Ertugrul",
    "wof:placetype":"locality"
},
  "geometry": {"coordinates":[31.58972,39.28778],"type":"Point"}
}