{
  "type": "Feature",
  "properties": {
    "gn:admin1_code":"48",
    "gn:asciiname":"Beyobasi",
    "gn:country_code":"TR",
    "gn:dem":62,
    "gn:feature_class":"P",
    "gn:feature_code":"PPL",
    "gn:name":"Beyobas\u0131",
    "gn:population":0,
    "gn:timezone":"Europe/Istanbul",
    "iso:country":"TR",
    "wof:name":"Beyobasi",
    "wof:placetype":"locality"
},
  "geometry": {"coordinates":[28.77399,36.91114],"type":"Point"}
}