{
  "type": "Feature",
  "properties": {
    "gn:admin1_code":"48",
    "gn:asciiname":"Koylukoba",
    "gn:country_code":"TR",
    "gn:dem":16,
    "gn:feature_class":"P",
    "gn:feature_code":"PPL",
    "gn:name":"K\u00f6yl\u00fckoba",
    "gn:population":0,
    "gn:timezone":"Europe/Istanbul",
    "iso:country":"TR",
    "name:tur_x_preferred":[
        "K\u00f6yl\u00fckoba"
    ],
    "wof:name":"Koylukoba",
    "wof:placetype":"locality"
},
  "geometry": {"coordinates":[28.27268,36.96797],"type":"Point"}
}