{
  "type": "Feature",
  "properties": {
    "gn:country":"TR",
    "gn:fcode":"PPLA2",
    "gn:pop":5423,
    "iso:country":"TR",
    "name:aze_x_preferred":[
        "Saimb\u0259yli"
    ],
    "name:cat_x_preferred":[
        "Saimbeyli"
    ],
    "name:ceb_x_preferred":[
        "Saimbeyli \u0130l\u00e7esi"
    ],
    "name:deu_x_preferred":[
        "Saimbeyli"
    ],
    "name:diq_x_preferred":[
        "Saimbeyli"
    ],
    "name:eng_x_preferred":[
        "Saimbeyli"
    ],
    "name:epo_x_preferred":[
        "Saimbeyli"
    ],
    "name:fas_x_preferred":[
        "\u0633\u0627\u06cc\u0645\u0628\u06cc\u0644\u06cc"
    ],
    "name:fra_x_preferred":[
        "Saimbeyli"
    ],
    "name:hye_x_preferred":[
        "\u0540\u0561\u0573\u0568\u0576"
    ],
    "name:hyw_x_preferred":[
        "\u0540\u0561\u0573\u0568\u0576"
    ],
    "name:kaz_x_preferred":[
        "\u0421\u0430\u0438\u043c\u0431\u0435\u0439\u043b\u0438"
    ],
    "name:lbe_x_preferred":[
        "\u0421\u0430\u0438\u043c\u0431\u0435\u0439\u043b\u0438"
    ],
    "name:mrj_x_preferred":[
        "\u0421\u0430\u0438\u043c\u0431\u0435\u0439\u043b\u0438"
    ],
    "name:msa_x_preferred":[
        "Saimbeyli"
    ],
    "name:nan_x_preferred":[
        "Saimbeyli"
    ],
    "name:nld_x_preferred":[
        "Saimbeyli"
    ],
    "name:nob_x_preferred":[
        "Saimbeyli"
    ],
    "name:pnb_x_preferred":[
        "\u0636\u0644\u0639 \u0633\u0627\u0626\u0628\u06cc\u0644\u06cc"
    ],
    "name:ron_x_preferred":[
        "Saimbeyli"
    ],
    "name:rus_x_preferred":[
        "\u0421\u0430\u0438\u043c\u0431\u0435\u0439\u043b\u0438"
    ],
    "name:swa_x_preferred":[
        "Saimbeyli"
    ],
    "name:tur_x_preferred":[
        "Saimbeyli"
    ],
    "name:unk_x_variant":[
        "Ha\u00e7in"
    ],
    "name:urd_x_preferred":[
        "\u0633\u06cc\u0645\u0628\u06d2\u0644\u06cc"
    ],
    "name:vie_x_preferred":[
        "Saimbeyli"
    ],
    "qs:name":"Saimbeyli",
    "qs:photos_9r":0,
    "qs:photos_sr":0,
    "qs:pop_sr":"5",
    "wd:wordcount":211,
    "wof:name":"Saimbeyli",
    "wof:placetype":"locality",
    "wof:population":5423
},
  "geometry": {"coordinates":[36.09056,37.98632],"type":"Point"}
}