{
  "type": "Feature",
  "properties": {
    "gn:country":"TR",
    "gn:fcode":"PPLA2",
    "gn:pop":5423,
    "iso:country":"TR",
    "name:unk_x_variant":[
        "Ha\u00e7in"
    ],
    "qs:name":"Saimbeyli",
    "qs:photos_9r":0,
    "qs:photos_sr":0,
    "qs:pop_sr":"5",
    "wd:wordcount":211,
    "wof:name":"Saimbeyli",
    "wof:placetype":"locality",
    "wof:population":5423
},
  "geometry": {"coordinates":[36.09056,37.98632],"type":"Point"}
}