{
  "type": "Feature",
  "properties": {
    "iso:country":"TR",
    "wof:name":"Yahya Kemal",
    "wof:placetype":"neighbourhood"
},
  "geometry": {"coordinates":[28.98768488597338,41.08501216043419],"type":"Point"}
}