{
  "type": "Feature",
  "properties": {
    "gn:admin1_code":"63",
    "gn:asciiname":"Savi",
    "gn:cc2":"TR",
    "gn:country_code":"TR",
    "gn:dem":378,
    "gn:feature_class":"P",
    "gn:feature_code":"PPL",
    "gn:name":"\u015eavi",
    "gn:population":0,
    "gn:timezone":"Europe/Istanbul",
    "iso:country":"TR",
    "name:und_x_variant":[
        "Shavi",
        "\u015eao",
        "\u015eavi"
    ],
    "wof:name":"Savi",
    "wof:placetype":"locality"
},
  "geometry": {"coordinates":[38.015,36.93528],"type":"Point"}
}