{
  "type": "Feature",
  "properties": {
    "gn:admin1_code":"38",
    "gn:asciiname":"Emiroren",
    "gn:country_code":"TR",
    "gn:dem":1653,
    "gn:feature_class":"P",
    "gn:feature_code":"PPL",
    "gn:name":"Emir\u00f6ren",
    "gn:population":0,
    "gn:timezone":"Europe/Istanbul",
    "iso:country":"TR",
    "name:und_x_variant":[
        "Emirviran",
        "Emir\u00f6ren"
    ],
    "wof:name":"Emiroren",
    "wof:placetype":"locality"
},
  "geometry": {"coordinates":[36.02877,38.83631],"type":"Point"}
}