{
  "type": "Feature",
  "properties": {
    "gn:admin1_code":"64",
    "gn:asciiname":"Cirpicilar",
    "gn:country_code":"TR",
    "gn:dem":976,
    "gn:feature_class":"P",
    "gn:feature_code":"PPL",
    "gn:name":"\u00c7\u0131rp\u0131c\u0131lar",
    "gn:population":0,
    "gn:timezone":"Europe/Istanbul",
    "iso:country":"TR",
    "wof:name":"Cirpicilar",
    "wof:placetype":"locality"
},
  "geometry": {"coordinates":[29.195,38.56028],"type":"Point"}
}