{
  "type": "Feature",
  "properties": {
    "gn:admin1_code":"68.0",
    "gn:asciiname":"Tilkikoy",
    "gn:country_code":"TR",
    "gn:dem":729,
    "gn:feature_class":"P",
    "gn:feature_code":"PPL",
    "gn:name":"Tilkik\u00f6y",
    "gn:population":0,
    "gn:timezone":"Europe/Istanbul",
    "iso:country":"TR",
    "name:und_x_variant":[
        "Tilki",
        "Tilkik\u00f6y"
    ],
    "wof:name":"Tilkikoy",
    "wof:placetype":"locality"
},
  "geometry": {"coordinates":[33.51468,40.20884],"type":"Point"}
}