{
  "type": "Feature",
  "properties": {
    "gn:admin1_code":"09",
    "gn:asciiname":"Gullubahce",
    "gn:country_code":"TR",
    "gn:dem":26,
    "gn:feature_class":"P",
    "gn:feature_code":"PPL",
    "gn:name":"G\u00fcll\u00fcbah\u00e7e",
    "gn:population":0,
    "gn:timezone":"Europe/Istanbul",
    "iso:country":"TR",
    "name:tur_x_preferred":[
        "G\u00fcll\u00fcbah\u00e7e"
    ],
    "wof:name":"Gullubahce",
    "wof:placetype":"locality"
},
  "geometry": {"coordinates":[27.32038,37.66575],"type":"Point"}
}