{
  "type": "Feature",
  "properties": {
    "gn:admin1_code":"66",
    "gn:asciiname":"Azizlibaglari",
    "gn:country_code":"TR",
    "gn:dem":1151,
    "gn:feature_class":"P",
    "gn:feature_code":"PPL",
    "gn:name":"Azizliba\u011flar\u0131",
    "gn:population":0,
    "gn:timezone":"Europe/Istanbul",
    "iso:country":"TR",
    "name:tur_x_preferred":[
        "Azizliba\u011flar\u0131"
    ],
    "wof:name":"Azizlibaglari",
    "wof:placetype":"locality"
},
  "geometry": {"coordinates":[34.76958,39.74459],"type":"Point"}
}