{
  "type": "Feature",
  "properties": {
    "gn:admin1_code":"65",
    "gn:asciiname":"Sorhac",
    "gn:cc2":"TR",
    "gn:country_code":"TR",
    "gn:dem":2254,
    "gn:feature_class":"P",
    "gn:feature_code":"PPL",
    "gn:name":"Sorha\u00e7",
    "gn:population":0,
    "gn:timezone":"Europe/Istanbul",
    "iso:country":"TR",
    "name:und_x_variant":[
        "Sorho\u00e7",
        "Sorha\u00e7"
    ],
    "wof:name":"Sorhac",
    "wof:placetype":"locality"
},
  "geometry": {"coordinates":[43.96667,37.98333],"type":"Point"}
}