{
  "type": "Feature",
  "properties": {
    "gn:admin1_code":"76",
    "gn:asciiname":"Dilimli",
    "gn:country_code":"TR",
    "gn:dem":617,
    "gn:feature_class":"P",
    "gn:feature_code":"PPL",
    "gn:name":"Dilimli",
    "gn:population":0,
    "gn:timezone":"Europe/Istanbul",
    "iso:country":"TR",
    "name:tur_x_preferred":[
        "Dilimli"
    ],
    "wof:name":"Dilimli",
    "wof:placetype":"locality"
},
  "geometry": {"coordinates":[41.51147,38.08714000000001],"type":"Point"}
}