{
  "type": "Feature",
  "properties": {
    "gn:admin1_code":"52.0",
    "gn:asciiname":"Soken",
    "gn:country_code":"TR",
    "gn:dem":226,
    "gn:feature_class":"P",
    "gn:feature_code":"PPL",
    "gn:name":"S\u00f6ken",
    "gn:population":0,
    "gn:timezone":"Europe/Istanbul",
    "iso:country":"TR",
    "name:tur_x_preferred":[
        "S\u00f6ken"
    ],
    "wof:name":"Soken",
    "wof:placetype":"locality"
},
  "geometry": {"coordinates":[37.51059,40.94466],"type":"Point"}
}