{
  "type": "Feature",
  "properties": {
    "gn:admin1_code":"60.0",
    "gn:asciiname":"Gulpinar",
    "gn:country_code":"TR",
    "gn:dem":659,
    "gn:feature_class":"P",
    "gn:feature_code":"PPL",
    "gn:name":"G\u00fclp\u0131nar",
    "gn:population":0,
    "gn:timezone":"Europe/Istanbul",
    "iso:country":"TR",
    "name:und_x_variant":[
        "G\u00fclp\u0131nar K\u00f6y\u00fc",
        "G\u00fclp\u0131nar"
    ],
    "wof:name":"Gulpinar",
    "wof:placetype":"locality"
},
  "geometry": {"coordinates":[36.39405,40.29984],"type":"Point"}
}