{
  "type": "Feature",
  "properties": {
    "gn:admin1_code":"11",
    "gn:asciiname":"Yukaribogaz",
    "gn:country_code":"TR",
    "gn:dem":763,
    "gn:feature_class":"P",
    "gn:feature_code":"PPL",
    "gn:name":"Yukar\u0131bo\u011faz",
    "gn:population":0,
    "gn:timezone":"Europe/Istanbul",
    "iso:country":"TR",
    "name:tur_x_preferred":[
        "Yukar\u0131bo\u011faz"
    ],
    "wof:name":"Yukaribogaz",
    "wof:placetype":"locality"
},
  "geometry": {"coordinates":[30.60322,40.24354],"type":"Point"}
}