{
  "type": "Feature",
  "properties": {
    "gn:admin1_code":"14.0",
    "gn:asciiname":"Dereboyu",
    "gn:country_code":"TR",
    "gn:dem":1014,
    "gn:feature_class":"P",
    "gn:feature_code":"PPL",
    "gn:name":"Dereboyu",
    "gn:population":0,
    "gn:timezone":"Europe/Istanbul",
    "iso:country":"TR",
    "wof:name":"Dereboyu",
    "wof:placetype":"locality"
},
  "geometry": {"coordinates":[31.5087,40.46746],"type":"Point"}
}