{
  "type": "Feature",
  "properties": {
    "gn:admin1_code":"52.0",
    "gn:asciiname":"Ortakoy",
    "gn:country_code":"TR",
    "gn:dem":670,
    "gn:feature_class":"P",
    "gn:feature_code":"PPL",
    "gn:name":"Ortak\u00f6y",
    "gn:population":0,
    "gn:timezone":"Europe/Istanbul",
    "iso:country":"TR",
    "name:und_x_variant":[
        "Ortak\u00f6y",
        "Erik\u00e7ukuru"
    ],
    "wof:name":"Ortakoy",
    "wof:placetype":"locality"
},
  "geometry": {"coordinates":[37.98181,40.81291],"type":"Point"}
}