{
  "type": "Feature",
  "properties": {
    "gn:admin1_code":"14.0",
    "gn:asciiname":"Catak",
    "gn:cc2":"TR",
    "gn:country_code":"TR",
    "gn:dem":1018,
    "gn:feature_class":"P",
    "gn:feature_code":"PPL",
    "gn:name":"\u00c7atak",
    "gn:population":0,
    "gn:timezone":"Europe/Istanbul",
    "iso:country":"TR",
    "name:und_x_variant":[
        "\u00c7\u0131takk\u00f6y",
        "\u00c7atak"
    ],
    "wof:name":"Catak",
    "wof:placetype":"locality"
},
  "geometry": {"coordinates":[31.53333,40.76667],"type":"Point"}
}