{
  "type": "Feature",
  "properties": {
    "gn:admin1_code":"21",
    "gn:asciiname":"Olgun",
    "gn:country_code":"TR",
    "gn:dem":766,
    "gn:feature_class":"P",
    "gn:feature_code":"PPL",
    "gn:name":"Olgun",
    "gn:population":0,
    "gn:timezone":"Europe/Istanbul",
    "iso:country":"TR",
    "name:tur_x_preferred":[
        "A\u015fa\u011f\u0131cayan"
    ],
    "wof:name":"Olgun",
    "wof:placetype":"locality"
},
  "geometry": {"coordinates":[39.84779,38.08786],"type":"Point"}
}