{
  "type": "Feature",
  "properties": {
    "gn:admin1_code":"93",
    "gn:asciiname":"Alibeyler",
    "gn:country_code":"TR",
    "gn:dem":164,
    "gn:feature_class":"P",
    "gn:feature_code":"PPL",
    "gn:name":"Alibeyler",
    "gn:population":0,
    "gn:timezone":"Europe/Istanbul",
    "iso:country":"TR",
    "wof:name":"Alibeyler",
    "wof:placetype":"locality"
},
  "geometry": {"coordinates":[30.9494,40.7564],"type":"Point"}
}