{
  "type": "Feature",
  "properties": {
    "gn:admin1_code":"68.0",
    "gn:asciiname":"Ikipinar",
    "gn:country_code":"TR",
    "gn:dem":1034,
    "gn:feature_class":"P",
    "gn:feature_code":"PPL",
    "gn:name":"\u0130kip\u0131nar",
    "gn:population":0,
    "gn:timezone":"Europe/Istanbul",
    "iso:country":"TR",
    "name:und_x_variant":[
        "\u0130kip\u0131nar K\u00f6y\u00fc",
        "\u0130kip\u0131nar"
    ],
    "wof:name":"Ikipinar",
    "wof:placetype":"locality"
},
  "geometry": {"coordinates":[32.91213,40.16397],"type":"Point"}
}