{
  "type": "Feature",
  "properties": {
    "gn:admin1_code":"31",
    "gn:asciiname":"Yesiltepe",
    "gn:country_code":"TR",
    "gn:dem":29,
    "gn:feature_class":"P",
    "gn:feature_code":"PPL",
    "gn:name":"Ye\u015filtepe",
    "gn:population":0,
    "gn:timezone":"Europe/Istanbul",
    "iso:country":"TR",
    "name:und_x_variant":[
        "Ye\u015filtepe",
        "\u0130cadiye"
    ],
    "wof:name":"Yesiltepe",
    "wof:placetype":"locality"
},
  "geometry": {"coordinates":[36.12595,36.91677],"type":"Point"}
}