{
  "type": "Feature",
  "properties": {
    "gn:admin1_code":"66",
    "gn:asciiname":"Izibuyuk",
    "gn:country_code":"TR",
    "gn:dem":893,
    "gn:feature_class":"P",
    "gn:feature_code":"PPL",
    "gn:name":"\u0130zib\u00fcy\u00fck",
    "gn:population":0,
    "gn:timezone":"Europe/Istanbul",
    "iso:country":"TR",
    "wof:name":"Izibuyuk",
    "wof:placetype":"locality"
},
  "geometry": {"coordinates":[35.62862,39.8853],"type":"Point"}
}