{
  "type": "Feature",
  "properties": {
    "gn:admin1_code":"5.0",
    "gn:asciiname":"Bayat",
    "gn:country_code":"TR",
    "gn:dem":864,
    "gn:feature_class":"P",
    "gn:feature_code":"PPL",
    "gn:name":"Bayat",
    "gn:population":0,
    "gn:timezone":"Europe/Istanbul",
    "iso:country":"TR",
    "name:tur_x_preferred":[
        "Bayat"
    ],
    "wof:name":"Bayat",
    "wof:placetype":"locality"
},
  "geometry": {"coordinates":[35.61228,40.92465],"type":"Point"}
}