{
  "type": "Feature",
  "properties": {
    "gn:admin1_code":"20",
    "gn:asciiname":"Bahcekoy",
    "gn:country_code":"TR",
    "gn:dem":1123,
    "gn:feature_class":"P",
    "gn:feature_code":"PPL",
    "gn:name":"Bah\u00e7ek\u00f6y",
    "gn:population":0,
    "gn:timezone":"Europe/Istanbul",
    "iso:country":"TR",
    "name:und_x_variant":[
        "Bah\u00e7ak\u00f6y",
        "Bah\u00e7e",
        "Bah\u00e7ek\u00f6y"
    ],
    "wof:name":"Bahcekoy",
    "wof:placetype":"locality"
},
  "geometry": {"coordinates":[29.13836,37.35972],"type":"Point"}
}