{
  "type": "Feature",
  "properties": {
    "gn:admin1_code":"37.0",
    "gn:asciiname":"Cigil",
    "gn:country_code":"TR",
    "gn:dem":771,
    "gn:feature_class":"P",
    "gn:feature_code":"PPL",
    "gn:name":"\u00c7i\u011fil",
    "gn:population":0,
    "gn:timezone":"Europe/Istanbul",
    "iso:country":"TR",
    "wof:name":"Cigil",
    "wof:placetype":"locality"
},
  "geometry": {"coordinates":[33.67523,41.45533],"type":"Point"}
}