{
  "type": "Feature",
  "properties": {
    "gn:admin1_code":"14",
    "gn:asciiname":"Boruncek",
    "gn:country_code":"TR",
    "gn:dem":753,
    "gn:feature_class":"P",
    "gn:feature_code":"PPL",
    "gn:name":"B\u00f6r\u00fcncek",
    "gn:population":0,
    "gn:timezone":"Europe/Istanbul",
    "iso:country":"TR",
    "wof:name":"Boruncek",
    "wof:placetype":"locality"
},
  "geometry": {"coordinates":[31.03013,40.52391],"type":"Point"}
}