{
  "type": "Feature",
  "properties": {
    "gn:admin1_code":"64",
    "gn:asciiname":"Koyunbeyli",
    "gn:country_code":"TR",
    "gn:dem":917,
    "gn:feature_class":"P",
    "gn:feature_code":"PPL",
    "gn:name":"Koyunbeyli",
    "gn:population":0,
    "gn:timezone":"Europe/Istanbul",
    "iso:country":"TR",
    "wof:name":"Koyunbeyli",
    "wof:placetype":"locality"
},
  "geometry": {"coordinates":[29.48528,38.58],"type":"Point"}
}