{
  "type": "Feature",
  "properties": {
    "gn:admin1_code":"14.0",
    "gn:asciiname":"Sogukcam",
    "gn:country_code":"TR",
    "gn:dem":746,
    "gn:feature_class":"P",
    "gn:feature_code":"PPL",
    "gn:name":"So\u011fuk\u00e7am",
    "gn:population":0,
    "gn:timezone":"Europe/Istanbul",
    "iso:country":"TR",
    "name:und_x_variant":[
        "Germenoz",
        "Kermanus",
        "Gernenuz",
        "Germenuz",
        "So\u011fuk\u00e7am"
    ],
    "wof:name":"Sogukcam",
    "wof:placetype":"locality"
},
  "geometry": {"coordinates":[30.82772000000001,40.17041],"type":"Point"}
}