{
  "type": "Feature",
  "properties": {
    "gn:admin1_code":"21",
    "gn:asciiname":"Kalac",
    "gn:country_code":"TR",
    "gn:dem":1008,
    "gn:feature_class":"P",
    "gn:feature_code":"PPL",
    "gn:name":"Kala\u00e7",
    "gn:population":0,
    "gn:timezone":"Europe/Istanbul",
    "iso:country":"TR",
    "name:bos_x_preferred":[
        "Kalac"
    ],
    "name:ceb_x_preferred":[
        "Kalac"
    ],
    "name:deu_x_preferred":[
        "Kalac"
    ],
    "name:fra_x_preferred":[
        "Kalac"
    ],
    "name:hrv_x_preferred":[
        "Kalac"
    ],
    "name:hun_x_preferred":[
        "Kalac"
    ],
    "name:rus_x_preferred":[
        "\u041a\u0430\u043b\u0430\u0446"
    ],
    "name:srp_x_preferred":[
        "\u041a\u0430\u043b\u0430\u0446"
    ],
    "name:swe_x_preferred":[
        "Kalac"
    ],
    "name:tur_x_preferred":[
        "Kala\u00e7"
    ],
    "name:und_x_variant":[
        "Mola"
    ],
    "wof:name":"Kalac",
    "wof:placetype":"locality"
},
  "geometry": {"coordinates":[39.34869000000001,38.13071],"type":"Point"}
}