{
  "type": "Feature",
  "properties": {
    "gn:admin1_code":"25",
    "gn:asciiname":"Yukari Soylemez",
    "gn:country_code":"TR",
    "gn:dem":1917,
    "gn:feature_class":"P",
    "gn:feature_code":"PPL",
    "gn:name":"Yukar\u0131 S\u00f6ylemez",
    "gn:population":0,
    "gn:timezone":"Europe/Istanbul",
    "iso:country":"TR",
    "name:tur_x_preferred":[
        "Yukar\u0131 S\u00f6ylemez"
    ],
    "name:und_x_variant":[
        "Yukar\u0131s\u00f6ylemez"
    ],
    "wof:name":"Yukari Soylemez",
    "wof:placetype":"locality"
},
  "geometry": {"coordinates":[41.85018,39.61143],"type":"Point"}
}