{
  "type": "Feature",
  "properties": {
    "gn:admin1_code":"37.0",
    "gn:asciiname":"Cavuslu",
    "gn:country_code":"TR",
    "gn:dem":1244,
    "gn:feature_class":"P",
    "gn:feature_code":"PPL",
    "gn:name":"\u00c7avu\u015flu",
    "gn:population":0,
    "gn:timezone":"Europe/Istanbul",
    "iso:country":"TR",
    "name:tur_x_preferred":[
        "\u00d6rencik"
    ],
    "name:und_x_variant":[
        "\u00c7avu\u015flu",
        "Topallar"
    ],
    "wof:name":"Cavuslu",
    "wof:placetype":"locality"
},
  "geometry": {"coordinates":[33.8742,41.75684],"type":"Point"}
}