{
  "type": "Feature",
  "properties": {
    "gn:admin1_code":"09",
    "gn:asciiname":"Ozbasi",
    "gn:country_code":"TR",
    "gn:dem":28,
    "gn:feature_class":"P",
    "gn:feature_code":"PPL",
    "gn:name":"\u00d6zba\u015f\u0131",
    "gn:population":0,
    "gn:timezone":"Europe/Istanbul",
    "iso:country":"TR",
    "wof:name":"Ozbasi",
    "wof:placetype":"locality"
},
  "geometry": {"coordinates":[27.42778,37.62833],"type":"Point"}
}