{
  "type": "Feature",
  "properties": {
    "gn:admin1_code":"12",
    "gn:asciiname":"Hasbaglar",
    "gn:country_code":"TR",
    "gn:dem":1560,
    "gn:feature_class":"P",
    "gn:feature_code":"PPL",
    "gn:name":"Hasba\u011flar",
    "gn:population":0,
    "gn:timezone":"Europe/Istanbul",
    "iso:country":"TR",
    "name:tur_x_preferred":[
        "Hasba\u011flar"
    ],
    "wof:name":"Hasbaglar",
    "wof:placetype":"locality"
},
  "geometry": {"coordinates":[40.37285,39.18721],"type":"Point"}
}