{
  "type": "Feature",
  "properties": {
    "gn:admin1_code":"25",
    "gn:asciiname":"Ceperli",
    "gn:country_code":"TR",
    "gn:dem":2120,
    "gn:feature_class":"P",
    "gn:feature_code":"PPL",
    "gn:name":"\u00c7eperli",
    "gn:population":0,
    "gn:timezone":"Europe/Istanbul",
    "iso:country":"TR",
    "name:tur_x_preferred":[
        "\u00c7eperli"
    ],
    "wof:name":"Ceperli",
    "wof:placetype":"locality"
},
  "geometry": {"coordinates":[41.42036,39.88149],"type":"Point"}
}