{
  "type": "Feature",
  "properties": {
    "gn:admin1_code":"13",
    "gn:asciiname":"Karkus",
    "gn:country_code":"TR",
    "gn:dem":1254,
    "gn:feature_class":"P",
    "gn:feature_code":"PPL",
    "gn:name":"Karkus",
    "gn:population":0,
    "gn:timezone":"Europe/Istanbul",
    "iso:country":"TR",
    "name:tur_x_preferred":[
        "Karkus"
    ],
    "name:und_x_variant":[
        "Homa\u00e7"
    ],
    "wof:name":"Karkus",
    "wof:placetype":"locality"
},
  "geometry": {"coordinates":[42.11675,38.26368],"type":"Point"}
}