{
  "type": "Feature",
  "properties": {
    "gn:admin1_code":"13",
    "gn:asciiname":"Pertek",
    "gn:country_code":"TR",
    "gn:dem":1660,
    "gn:feature_class":"P",
    "gn:feature_code":"PPL",
    "gn:name":"Pertek",
    "gn:population":0,
    "gn:timezone":"Europe/Istanbul",
    "iso:country":"TR",
    "name:tur_x_preferred":[
        "\u00c7ay\u0131rl\u0131"
    ],
    "wof:name":"Pertek",
    "wof:placetype":"locality"
},
  "geometry": {"coordinates":[42.59424,38.14587],"type":"Point"}
}