{
  "type": "Feature",
  "properties": {
    "gn:admin1_code":"13",
    "gn:asciiname":"Pertek",
    "gn:country_code":"TR",
    "gn:dem":1660,
    "gn:feature_class":"P",
    "gn:feature_code":"PPL",
    "gn:name":"Pertek",
    "gn:population":0,
    "gn:timezone":"Europe/Istanbul",
    "iso:country":"TR",
    "name:ara_x_preferred":[
        "\u0628\u0631\u062a\u0643"
    ],
    "name:ceb_x_preferred":[
        "Pertek \u0130l\u00e7esi"
    ],
    "name:ckb_x_preferred":[
        "\u067e\u06ce\u0631\u062a\u0627\u06af\u06d5"
    ],
    "name:deu_x_preferred":[
        "Pertek"
    ],
    "name:diq_x_preferred":[
        "P\u00eartage"
    ],
    "name:fas_x_preferred":[
        "\u067e\u0631\u062a\u06a9"
    ],
    "name:fra_x_preferred":[
        "Pertek"
    ],
    "name:hye_x_preferred":[
        "\u0532\u0565\u0580\u0564\u0561\u056f"
    ],
    "name:kur_x_preferred":[
        "P\u00eartag"
    ],
    "name:mrj_x_preferred":[
        "\u041f\u0435\u0440\u0442\u0435\u043a"
    ],
    "name:msa_x_preferred":[
        "Pertek"
    ],
    "name:nld_x_preferred":[
        "Pertek"
    ],
    "name:nno_x_preferred":[
        "Pertek"
    ],
    "name:nor_x_preferred":[
        "Pertek"
    ],
    "name:pnb_x_preferred":[
        "\u0636\u0644\u0639 \u067e\u0631\u062a\u06a9"
    ],
    "name:rus_x_preferred":[
        "\u041f\u0435\u0440\u0442\u0435\u043a"
    ],
    "name:swa_x_preferred":[
        "Pertek"
    ],
    "name:tur_x_preferred":[
        "\u00c7ay\u0131rl\u0131"
    ],
    "name:tur_x_variant":[
        "Pertek"
    ],
    "name:urd_x_preferred":[
        "\u067e\u0631\u062a\u06a9"
    ],
    "name:vie_x_preferred":[
        "Pertek"
    ],
    "name:zho_x_preferred":[
        "\u4f69\u723e\u6cf0\u514b"
    ],
    "wof:name":"Pertek",
    "wof:placetype":"locality"
},
  "geometry": {"coordinates":[42.59424,38.14587],"type":"Point"}
}