{
  "type": "Feature",
  "properties": {
    "gn:admin1_code":"13",
    "gn:asciiname":"Besevler",
    "gn:country_code":"TR",
    "gn:dem":1264,
    "gn:feature_class":"P",
    "gn:feature_code":"PPL",
    "gn:name":"Be\u015fevler",
    "gn:population":0,
    "gn:timezone":"Europe/Istanbul",
    "iso:country":"TR",
    "name:tur_x_preferred":[
        "Be\u015fevler"
    ],
    "name:und_x_variant":[
        "Tago"
    ],
    "wof:name":"Besevler",
    "wof:placetype":"locality"
},
  "geometry": {"coordinates":[41.7197,38.52079000000001],"type":"Point"}
}