{
  "type": "Feature",
  "properties": {
    "gn:admin1_code":"91.0",
    "gn:asciiname":"Ahmetgecitli",
    "gn:country_code":"TR",
    "gn:dem":466,
    "gn:feature_class":"P",
    "gn:feature_code":"PPL",
    "gn:name":"Ahmetge\u00e7itli",
    "gn:population":0,
    "gn:timezone":"Europe/Istanbul",
    "iso:country":"TR",
    "wof:name":"Ahmetgecitli",
    "wof:placetype":"locality"
},
  "geometry": {"coordinates":[36.21966,37.52165],"type":"Point"}
}