{
  "type": "Feature",
  "properties": {
    "gn:admin1_code":"65.0",
    "gn:asciiname":"Hidirmentes",
    "gn:country_code":"TR",
    "gn:dem":2422,
    "gn:feature_class":"P",
    "gn:feature_code":"PPL",
    "gn:name":"H\u0131d\u0131rmentes",
    "gn:population":0,
    "gn:timezone":"Europe/Istanbul",
    "iso:country":"TR",
    "name:tur_x_preferred":[
        "H\u0131d\u0131rmentes"
    ],
    "wof:name":"Hidirmentes",
    "wof:placetype":"locality"
},
  "geometry": {"coordinates":[43.79459,39.17597],"type":"Point"}
}