{
  "type": "Feature",
  "properties": {
    "gn:admin1_code":"72",
    "gn:asciiname":"Yardere",
    "gn:country_code":"TR",
    "gn:dem":720,
    "gn:feature_class":"P",
    "gn:feature_code":"PPL",
    "gn:name":"Yardere",
    "gn:population":0,
    "gn:timezone":"Europe/Istanbul",
    "iso:country":"TR",
    "name:tur_x_preferred":[
        "Yardere"
    ],
    "name:und_x_variant":[
        "Kurdis",
        "Kordis"
    ],
    "wof:name":"Yardere",
    "wof:placetype":"locality"
},
  "geometry": {"coordinates":[40.97886,37.23065],"type":"Point"}
}