{
  "type": "Feature",
  "properties": {
    "gn:admin1_code":"37.0",
    "gn:asciiname":"Velioglu",
    "gn:country_code":"TR",
    "gn:dem":335,
    "gn:feature_class":"P",
    "gn:feature_code":"PPL",
    "gn:name":"Velio\u011flu",
    "gn:population":0,
    "gn:timezone":"Europe/Istanbul",
    "iso:country":"TR",
    "wof:name":"Velioglu",
    "wof:placetype":"locality"
},
  "geometry": {"coordinates":[33.06845999999999,41.86838],"type":"Point"}
}