{
  "type": "Feature",
  "properties": {
    "gn:admin1_code":"37.0",
    "gn:asciiname":"Samanlioren",
    "gn:country_code":"TR",
    "gn:dem":809,
    "gn:feature_class":"P",
    "gn:feature_code":"PPL",
    "gn:name":"Samanl\u0131\u00f6ren",
    "gn:population":0,
    "gn:timezone":"Europe/Istanbul",
    "iso:country":"TR",
    "name:und_x_variant":[
        "Samanl\u0131viran",
        "Samanl\u0131veran",
        "Samanl\u0131\u00f6ren"
    ],
    "wof:name":"Samanlioren",
    "wof:placetype":"locality"
},
  "geometry": {"coordinates":[34.02377,41.53435],"type":"Point"}
}