{
  "type": "Feature",
  "properties": {
    "gn:admin1_code":"63",
    "gn:asciiname":"Ortatepe",
    "gn:country_code":"TR",
    "gn:dem":491,
    "gn:feature_class":"P",
    "gn:feature_code":"PPL",
    "gn:name":"Ortatepe",
    "gn:population":0,
    "gn:timezone":"Europe/Istanbul",
    "iso:country":"TR",
    "name:und_x_variant":[
        "Cernus",
        "Curnus",
        "Ortatepe"
    ],
    "wof:name":"Ortatepe",
    "wof:placetype":"locality"
},
  "geometry": {"coordinates":[38.24695,37.41527],"type":"Point"}
}