{
  "type": "Feature",
  "properties": {
    "gn:admin1_code":"37.0",
    "gn:asciiname":"Dagbeloren",
    "gn:country_code":"TR",
    "gn:dem":1393,
    "gn:feature_class":"P",
    "gn:feature_code":"PPL",
    "gn:name":"Da\u011fbel\u00f6ren",
    "gn:population":0,
    "gn:timezone":"Europe/Istanbul",
    "iso:country":"TR",
    "name:und_x_variant":[
        "Da\u011fbel\u00f6ren",
        "Tellio\u011flu"
    ],
    "wof:name":"Dagbeloren",
    "wof:placetype":"locality"
},
  "geometry": {"coordinates":[34.25878,41.30571],"type":"Point"}
}