{
  "type": "Feature",
  "properties": {
    "gn:admin1_code":"87.0",
    "gn:asciiname":"Cetme",
    "gn:country_code":"TR",
    "gn:dem":729,
    "gn:feature_class":"P",
    "gn:feature_code":"PPL",
    "gn:name":"\u00c7etme",
    "gn:population":0,
    "gn:timezone":"Europe/Istanbul",
    "iso:country":"TR",
    "name:und_x_variant":[
        "\u00c7etme",
        "Darenli"
    ],
    "wof:name":"Cetme",
    "wof:placetype":"locality"
},
  "geometry": {"coordinates":[32.54608,41.69069],"type":"Point"}
}