{
  "type": "Feature",
  "properties": {
    "gn:admin1_code":"17.0",
    "gn:asciiname":"Ahlatliburun",
    "gn:country_code":"TR",
    "gn:dem":149,
    "gn:feature_class":"P",
    "gn:feature_code":"PPL",
    "gn:name":"Ahlatl\u0131burun",
    "gn:population":0,
    "gn:timezone":"Europe/Istanbul",
    "iso:country":"TR",
    "name:tur_x_preferred":[
        "Ahlatl\u0131burun"
    ],
    "wof:name":"Ahlatliburun",
    "wof:placetype":"locality"
},
  "geometry": {"coordinates":[26.87358,40.01295],"type":"Point"}
}