{
  "type": "Feature",
  "properties": {
    "gn:admin1_code":"17.0",
    "gn:asciiname":"Ilyasalani",
    "gn:country_code":"TR",
    "gn:dem":341,
    "gn:feature_class":"P",
    "gn:feature_code":"PPL",
    "gn:name":"Ilyasalan\u0131",
    "gn:population":0,
    "gn:timezone":"Europe/Istanbul",
    "iso:country":"TR",
    "wof:name":"Ilyasalani",
    "wof:placetype":"locality"
},
  "geometry": {"coordinates":[27.4778,40.24524],"type":"Point"}
}