{
  "type": "Feature",
  "properties": {
    "gn:admin1_code":"32.0",
    "gn:asciiname":"Ayvacik",
    "gn:country_code":"TR",
    "gn:dem":544,
    "gn:feature_class":"P",
    "gn:feature_code":"PPL",
    "gn:name":"Ayvac\u0131k",
    "gn:population":0,
    "gn:timezone":"Europe/Istanbul",
    "iso:country":"TR",
    "wof:name":"Ayvacik",
    "wof:placetype":"locality"
},
  "geometry": {"coordinates":[33.3335,36.75303],"type":"Point"}
}