{
  "type": "Feature",
  "properties": {
    "iso:country":"TR",
    "name:eng_x_preferred":[
        "Madenler"
    ],
    "name:tur_x_preferred":[
        "Madenler"
    ],
    "wof:name":"Madenler",
    "wof:placetype":"neighbourhood"
},
  "geometry": {"coordinates":[29.18356901895265,41.01343864865172],"type":"Point"}
}