{
  "type": "Feature",
  "properties": {
    "gn:admin1_code":"79",
    "gn:asciiname":"Karabucak",
    "gn:country_code":"TR",
    "gn:dem":745,
    "gn:feature_class":"P",
    "gn:feature_code":"PPL",
    "gn:name":"Karabucak",
    "gn:population":0,
    "gn:timezone":"Europe/Istanbul",
    "iso:country":"TR",
    "wof:name":"Karabucak",
    "wof:placetype":"locality"
},
  "geometry": {"coordinates":[33.41444,39.50978],"type":"Point"}
}