{
  "type": "Feature",
  "properties": {
    "gn:country":"TR",
    "gn:fcode":"PPL",
    "gn:population":428,
    "iso:country":"TR",
    "name:tur_x_colloquial":[
        "Turan",
        "Turank\u00f6y",
        "Bacas\u0131z K\u00f6y"
    ],
    "name:tur_x_historical":[
        "Bo\u015fnak Karyesi"
    ],
    "name:tur_x_preferred":[
        "Turan"
    ],
    "name:tur_x_variant":[
        "Turank\u00f6y",
        "Bacas\u0131z K\u00f6y",
        "Bo\u015fnak Karyesi"
    ],
    "name:und_x_variant":[
        "Bo\u015fnakk\u00f6y"
    ],
    "qs:name":"Turank\u00f6y",
    "qs:photos_9r":0,
    "qs:photos_sr":0,
    "qs:pop_sr":"2",
    "wof:name":"Turank\u00f6y",
    "wof:placetype":"locality",
    "wof:population":428
},
  "geometry": {"coordinates":[29.34861,40.205],"type":"Point"}
}