{
  "type": "Feature",
  "properties": {
    "gn:admin1_code":"76.0",
    "gn:asciiname":"Akkus",
    "gn:country_code":"TR",
    "gn:dem":872,
    "gn:feature_class":"P",
    "gn:feature_code":"PPL",
    "gn:name":"Akkus",
    "gn:population":0,
    "gn:timezone":"Europe/Istanbul",
    "iso:country":"TR",
    "wof:name":"Akkus",
    "wof:placetype":"locality"
},
  "geometry": {"coordinates":[41.57807,38.19838],"type":"Point"}
}