{
  "type": "Feature",
  "properties": {
    "gn:admin1_code":"32",
    "gn:asciiname":"Kirkayak",
    "gn:country_code":"TR",
    "gn:dem":152,
    "gn:feature_class":"P",
    "gn:feature_code":"PPL",
    "gn:name":"K\u0131rkayak",
    "gn:population":0,
    "gn:timezone":"Europe/Istanbul",
    "iso:country":"TR",
    "name:und_x_variant":[
        "K\u0131rkayak",
        "K\u0131rkyalan"
    ],
    "wof:name":"Kirkayak",
    "wof:placetype":"locality"
},
  "geometry": {"coordinates":[33.31944,36.57233],"type":"Point"}
}