{
  "type": "Feature",
  "properties": {
    "gn:admin1_code":"84.0",
    "gn:asciiname":"Kurugol",
    "gn:country_code":"TR",
    "gn:dem":1981,
    "gn:feature_class":"P",
    "gn:feature_code":"PPL",
    "gn:name":"Kurug\u00f6l",
    "gn:population":0,
    "gn:timezone":"Europe/Istanbul",
    "iso:country":"TR",
    "name:und_x_variant":[
        "G\u00f6lveren",
        "G\u00f6lveran",
        "Kurug\u00f6l"
    ],
    "wof:name":"Kurugol",
    "wof:placetype":"locality"
},
  "geometry": {"coordinates":[43.05258,40.81835],"type":"Point"}
}