{
  "type": "Feature",
  "properties": {
    "gn:admin1_code":"61.0",
    "gn:asciiname":"Zimlakova",
    "gn:country_code":"TR",
    "gn:dem":734,
    "gn:feature_class":"P",
    "gn:feature_code":"PPL",
    "gn:name":"Zimlakova",
    "gn:population":0,
    "gn:timezone":"Europe/Istanbul",
    "iso:country":"TR",
    "name:und_x_variant":[
        "\u00c7aml\u0131ktepe",
        "Zimlakova"
    ],
    "wof:name":"Zimlakova",
    "wof:placetype":"locality"
},
  "geometry": {"coordinates":[39.98333,40.76667],"type":"Point"}
}