{
  "type": "Feature",
  "properties": {
    "gn:admin1_code":"2.0",
    "gn:asciiname":"Guzelsu",
    "gn:country_code":"TR",
    "gn:dem":787,
    "gn:feature_class":"P",
    "gn:feature_code":"PPL",
    "gn:name":"G\u00fczelsu",
    "gn:population":0,
    "gn:timezone":"Europe/Istanbul",
    "iso:country":"TR",
    "wof:name":"Guzelsu",
    "wof:placetype":"locality"
},
  "geometry": {"coordinates":[38.91901,37.87782],"type":"Point"}
}