{
  "type": "Feature",
  "properties": {
    "gn:admin1_code":"90",
    "gn:asciiname":"Mezrea",
    "gn:country_code":"TR",
    "gn:dem":681,
    "gn:feature_class":"P",
    "gn:feature_code":"PPL",
    "gn:name":"Mezrea",
    "gn:population":0,
    "gn:timezone":"Europe/Istanbul",
    "iso:country":"TR",
    "name:und_x_variant":[
        "Murala\u011fa Mezraas\u0131"
    ],
    "wof:name":"Mezrea",
    "wof:placetype":"locality"
},
  "geometry": {"coordinates":[36.91667,36.86667],"type":"Point"}
}