{
  "type": "Feature",
  "properties": {
    "gn:admin1_code":"03",
    "gn:asciiname":"Sinekli Yaylasi",
    "gn:country_code":"TR",
    "gn:dem":1557,
    "gn:feature_class":"P",
    "gn:feature_code":"PPL",
    "gn:name":"Sinekli Yaylas\u0131",
    "gn:population":0,
    "gn:timezone":"Europe/Istanbul",
    "iso:country":"TR",
    "wof:name":"Sinekli Yaylasi",
    "wof:placetype":"locality"
},
  "geometry": {"coordinates":[31.25683,38.89402000000001],"type":"Point"}
}