{
  "type": "Feature",
  "properties": {
    "gn:admin1_code":"55.0",
    "gn:asciiname":"Turkkoyu",
    "gn:country_code":"TR",
    "gn:dem":213,
    "gn:feature_class":"P",
    "gn:feature_code":"PPL",
    "gn:name":"T\u00fcrkk\u00f6y\u00fc",
    "gn:population":0,
    "gn:timezone":"Europe/Istanbul",
    "iso:country":"TR",
    "name:und_x_variant":[
        "T\u00fcrkk\u00f6y",
        "T\u00fcrkk\u00f6y\u00fc"
    ],
    "wof:name":"Turkkoyu",
    "wof:placetype":"locality"
},
  "geometry": {"coordinates":[35.80703,41.48137],"type":"Point"}
}