{
  "type": "Feature",
  "properties": {
    "gn:admin1_code":"69.0",
    "gn:asciiname":"Kabaktepe",
    "gn:country_code":"TR",
    "gn:dem":1671,
    "gn:feature_class":"P",
    "gn:feature_code":"PPL",
    "gn:name":"Kabaktepe",
    "gn:population":0,
    "gn:timezone":"Europe/Istanbul",
    "iso:country":"TR",
    "name:und_x_variant":[
        "\u015eurut",
        "Kabaktepe"
    ],
    "wof:name":"Kabaktepe",
    "wof:placetype":"locality"
},
  "geometry": {"coordinates":[39.6872,40.23309],"type":"Point"}
}