{
  "type": "Feature",
  "properties": {
    "gn:country":"TR",
    "gn:fcode":"PPL",
    "gn:population":1227,
    "iso:country":"TR",
    "name:ceb_x_preferred":[
        "Be\u015fp\u0131nar"
    ],
    "name:che_x_preferred":[
        "\u0411\u0435\u0448\u043f\u0438\u043d\u0430\u0440"
    ],
    "name:deu_x_preferred":[
        "Be\u015fp\u0131nar"
    ],
    "name:eng_x_preferred":[
        "Be\u015fp\u0131nar"
    ],
    "name:hye_x_preferred":[
        "\u054c\u0565\u0564\u057e\u0561\u0576"
    ],
    "name:kur_x_preferred":[
        "Erens"
    ],
    "name:msa_x_preferred":[
        "Be\u015fp\u0131nar"
    ],
    "name:nld_x_preferred":[
        "Be\u015fp\u0131nar"
    ],
    "name:rus_x_preferred":[
        "\u042e\u043a\u0430\u0440\u044b-\u041b\u043e\u0440\u0438"
    ],
    "name:tat_x_preferred":[
        "\u0411\u0435\u0448\u043f\u044b\u043d\u0430\u0440"
    ],
    "name:tur_x_preferred":[
        "Be\u015fp\u0131nar"
    ],
    "name:und_x_variant":[
        "Ba\u015fp\u0131nar"
    ],
    "name:vie_x_preferred":[
        "Be\u015fp\u0131nar"
    ],
    "qs:name":"Be\u015fp\u0131nar",
    "qs:photos_9r":0,
    "qs:photos_sr":0,
    "qs:pop_sr":"3",
    "wd:wordcount":48,
    "wof:name":"Be\u015fp\u0131nar",
    "wof:placetype":"locality",
    "wof:population":1227
},
  "geometry": {"coordinates":[41.60444,37.84389],"type":"Point"}
}