{
  "type": "Feature",
  "properties": {
    "gn:admin1_code":"49",
    "gn:asciiname":"Sakavi",
    "gn:cc2":"TR",
    "gn:country_code":"TR",
    "gn:dem":1261,
    "gn:feature_class":"P",
    "gn:feature_code":"PPL",
    "gn:name":"Sakavi",
    "gn:population":0,
    "gn:timezone":"Europe/Istanbul",
    "iso:country":"TR",
    "name:und_x_variant":[
        "Ak\u00e7an",
        "Sakav",
        "Sakavi"
    ],
    "wof:name":"Sakavi",
    "wof:placetype":"locality"
},
  "geometry": {"coordinates":[41.51667,38.93333],"type":"Point"}
}