{
  "type": "Feature",
  "properties": {
    "gn:admin1_code":"34.0",
    "gn:asciiname":"Sultanbeyli",
    "gn:country_code":"TR",
    "gn:dem":140,
    "gn:feature_class":"P",
    "gn:feature_code":"PPL",
    "gn:name":"Sultanbeyli",
    "gn:population":0,
    "gn:timezone":"Europe/Istanbul",
    "iso:country":"TR",
    "name:tur_x_preferred":[
        "Sultanbeyli"
    ],
    "name:und_x_variant":[
        "Kavakl\u0131"
    ],
    "wof:name":"Sultanbeyli",
    "wof:placetype":"locality"
},
  "geometry": {"coordinates":[29.27001,40.96556],"type":"Point"}
}