{
  "type": "Feature",
  "properties": {
    "gn:admin1_code":"34.0",
    "gn:asciiname":"Sultanbeyli",
    "gn:country_code":"TR",
    "gn:dem":140,
    "gn:feature_class":"P",
    "gn:feature_code":"PPL",
    "gn:name":"Sultanbeyli",
    "gn:population":0,
    "gn:timezone":"Europe/Istanbul",
    "iso:country":"TR",
    "name:ara_x_preferred":[
        "\u0633\u0644\u0637\u0627\u0646 \u0628\u064a\u0644\u064a"
    ],
    "name:ast_x_preferred":[
        "Sultanbeyli"
    ],
    "name:bre_x_preferred":[
        "Sultanbeyli"
    ],
    "name:cat_x_preferred":[
        "Sultanbeyli"
    ],
    "name:ceb_x_preferred":[
        "Sultanbeyli"
    ],
    "name:deu_x_preferred":[
        "Sultanbeyli"
    ],
    "name:diq_x_preferred":[
        "Sultanbeyli"
    ],
    "name:fas_x_preferred":[
        "\u0633\u0644\u0637\u0627\u0646\u200c\u0628\u06cc\u0644\u06cc"
    ],
    "name:fra_x_preferred":[
        "Sultanbeyli"
    ],
    "name:hun_x_preferred":[
        "Sultanbeyli"
    ],
    "name:hye_x_preferred":[
        "\u054d\u0578\u0582\u056c\u0569\u0561\u0576\u0562\u0565\u0575\u056c\u056b"
    ],
    "name:ind_x_preferred":[
        "Sultanbeyli"
    ],
    "name:ita_x_preferred":[
        "Sultanbeyli"
    ],
    "name:jpn_x_preferred":[
        "\u30b9\u30eb\u30bf\u30f3\u30d9\u30a4\u30ea"
    ],
    "name:kur_x_preferred":[
        "Sultanbeyli"
    ],
    "name:lav_x_preferred":[
        "Sultanbejli rajons"
    ],
    "name:lit_x_preferred":[
        "Sultanbeilis"
    ],
    "name:min_x_preferred":[
        "Sultanbeyli"
    ],
    "name:mrj_x_preferred":[
        "\u0421\u0443\u043b\u0442\u0430\u043d\u0431\u0435\u0439\u043b\u0438"
    ],
    "name:msa_x_preferred":[
        "Sultanbeyli"
    ],
    "name:nld_x_preferred":[
        "Sultanbeyli"
    ],
    "name:nor_x_preferred":[
        "Sultanbeyli"
    ],
    "name:pnb_x_preferred":[
        "\u0633\u0644\u0637\u0627\u0646\u0628\u06cc\u0644\u06cc"
    ],
    "name:pol_x_preferred":[
        "Sultanbeyli"
    ],
    "name:por_x_preferred":[
        "Sultanbeyli"
    ],
    "name:ron_x_preferred":[
        "Sultanbeyli"
    ],
    "name:rus_x_preferred":[
        "\u0421\u0443\u043b\u0442\u0430\u043d\u0431\u0435\u0439\u043b\u0438"
    ],
    "name:sco_x_preferred":[
        "Sultanbeyli"
    ],
    "name:spa_x_preferred":[
        "Sultanbeyli"
    ],
    "name:srp_x_preferred":[
        "\u0421\u0443\u043b\u0442\u0430\u043d\u0431\u0435\u0458\u043b\u0438"
    ],
    "name:swa_x_preferred":[
        "Sultanbeyli"
    ],
    "name:tur_x_preferred":[
        "Sultanbeyli"
    ],
    "name:und_x_variant":[
        "Kavakl\u0131"
    ],
    "name:vie_x_preferred":[
        "Sultanbeyli"
    ],
    "name:war_x_preferred":[
        "Sultanbeyli"
    ],
    "wof:name":"Sultanbeyli",
    "wof:placetype":"locality"
},
  "geometry": {"coordinates":[29.27001,40.96556],"type":"Point"}
}