{
  "type": "Feature",
  "properties": {
    "gn:admin1_code":"68.0",
    "gn:asciiname":"Osmansin",
    "gn:country_code":"TR",
    "gn:dem":1180,
    "gn:feature_class":"P",
    "gn:feature_code":"PPL",
    "gn:name":"Osmansin",
    "gn:population":0,
    "gn:timezone":"Europe/Istanbul",
    "iso:country":"TR",
    "wof:name":"Osmansin",
    "wof:placetype":"locality"
},
  "geometry": {"coordinates":[32.25172,40.4316],"type":"Point"}
}