{
  "type": "Feature",
  "properties": {
    "gn:admin1_code":"75",
    "gn:asciiname":"Dogan Tarla",
    "gn:country_code":"TR",
    "gn:dem":1132,
    "gn:feature_class":"P",
    "gn:feature_code":"PPL",
    "gn:name":"Do\u011fan Tarla",
    "gn:population":0,
    "gn:timezone":"Europe/Istanbul",
    "iso:country":"TR",
    "name:und_x_variant":[
        "Do\u011fan Tarla",
        "G\u00f6st\u00fck"
    ],
    "wof:name":"Dogan Tarla",
    "wof:placetype":"locality"
},
  "geometry": {"coordinates":[34.21213,38.36618],"type":"Point"}
}