{
  "type": "Feature",
  "properties": {
    "gn:admin1_code":"49",
    "gn:asciiname":"Karakaya",
    "gn:country_code":"TR",
    "gn:dem":1668,
    "gn:feature_class":"P",
    "gn:feature_code":"PPL",
    "gn:name":"Karakaya",
    "gn:population":0,
    "gn:timezone":"Europe/Istanbul",
    "iso:country":"TR",
    "name:tur_x_preferred":[
        "Karakaya"
    ],
    "name:und_x_variant":[
        "Bitli"
    ],
    "wof:name":"Karakaya",
    "wof:placetype":"locality"
},
  "geometry": {"coordinates":[42.13297,39.04566],"type":"Point"}
}