{
  "type": "Feature",
  "properties": {
    "gn:admin1_code":"81",
    "gn:asciiname":"Yaylaevleri",
    "gn:country_code":"TR",
    "gn:dem":1434,
    "gn:feature_class":"P",
    "gn:feature_code":"PPL",
    "gn:name":"Yaylaevleri",
    "gn:population":0,
    "gn:timezone":"Europe/Istanbul",
    "iso:country":"TR",
    "wof:name":"Yaylaevleri",
    "wof:placetype":"locality"
},
  "geometry": {"coordinates":[36.03333,37.83333],"type":"Point"}
}