{
  "type": "Feature",
  "properties": {
    "gn:admin1_code":"02",
    "gn:asciiname":"Sahverdi",
    "gn:country_code":"TR",
    "gn:dem":1138,
    "gn:feature_class":"P",
    "gn:feature_code":"PPL",
    "gn:name":"\u015eahverdi",
    "gn:population":0,
    "gn:timezone":"Europe/Istanbul",
    "iso:country":"TR",
    "name:und_x_variant":[
        "\u015eehverdi",
        "\u015eahverdi"
    ],
    "wof:name":"Sahverdi",
    "wof:placetype":"locality"
},
  "geometry": {"coordinates":[38.38959000000001,38.00686],"type":"Point"}
}