{
  "type": "Feature",
  "properties": {
    "gn:admin1_code":"21",
    "gn:asciiname":"Kobuk",
    "gn:cc2":"TR",
    "gn:country_code":"TR",
    "gn:dem":841,
    "gn:feature_class":"P",
    "gn:feature_code":"PPL",
    "gn:name":"Kobuk",
    "gn:population":0,
    "gn:timezone":"Europe/Istanbul",
    "iso:country":"TR",
    "name:ara_x_preferred":[
        "\u0643\u0648\u0628\u0648\u0643"
    ],
    "name:ben_x_preferred":[
        "\u0995\u09cb\u09ac\u09c1\u0995"
    ],
    "name:ceb_x_preferred":[
        "Kobuk"
    ],
    "name:deu_x_preferred":[
        "Kobuk"
    ],
    "name:ell_x_preferred":[
        "\u039a\u03bf\u03bc\u03c0\u03bf\u03cd\u03ba"
    ],
    "name:heb_x_preferred":[
        "\u05e7\u05d5\u05d1\u05d5\u05e7"
    ],
    "name:hin_x_preferred":[
        "\u0915\u094b\u092c\u0941\u0915"
    ],
    "name:hun_x_preferred":[
        "Kobuk"
    ],
    "name:ind_x_preferred":[
        "Kobuk"
    ],
    "name:jpn_x_preferred":[
        "\u30b3\u30d6\u30af"
    ],
    "name:kor_x_preferred":[
        "\ucf54\ubd81"
    ],
    "name:pol_x_preferred":[
        "Kobuk"
    ],
    "name:por_x_preferred":[
        "Kobuk"
    ],
    "name:spa_x_preferred":[
        "Kobuk"
    ],
    "name:swe_x_preferred":[
        "Kobuk River"
    ],
    "name:tur_x_preferred":[
        "Kobuk"
    ],
    "name:und_x_variant":[
        "Konik"
    ],
    "name:urd_x_preferred":[
        "\u06a9\u0648\u0628\u0648\u06a9"
    ],
    "name:vie_x_preferred":[
        "S\u00f4ng Kobuk"
    ],
    "wof:name":"Kobuk",
    "wof:placetype":"locality"
},
  "geometry": {"coordinates":[40.16667,37.63333],"type":"Point"}
}