{
  "type": "Feature",
  "properties": {
    "gn:admin1_code":"21",
    "gn:asciiname":"Kobuk",
    "gn:cc2":"TR",
    "gn:country_code":"TR",
    "gn:dem":841,
    "gn:feature_class":"P",
    "gn:feature_code":"PPL",
    "gn:name":"Kobuk",
    "gn:population":0,
    "gn:timezone":"Europe/Istanbul",
    "iso:country":"TR",
    "name:ceb_x_preferred":[
        "Kobuk"
    ],
    "name:deu_x_preferred":[
        "Kobuk"
    ],
    "name:und_x_variant":[
        "Konik"
    ],
    "wof:name":"Kobuk",
    "wof:placetype":"locality"
},
  "geometry": {"coordinates":[40.16667,37.63333],"type":"Point"}
}