{
  "type": "Feature",
  "properties": {
    "gn:admin1_code":"43",
    "gn:asciiname":"Dogaraslan",
    "gn:country_code":"TR",
    "gn:dem":1156,
    "gn:feature_class":"P",
    "gn:feature_code":"PPL",
    "gn:name":"Do\u011faraslan",
    "gn:population":0,
    "gn:timezone":"Europe/Istanbul",
    "iso:country":"TR",
    "name:und_x_variant":[
        "Do\u011farslan",
        "Do\u011faraslan",
        "Do\u011fuarslan",
        "Da\u011farslan"
    ],
    "wof:name":"Dogaraslan",
    "wof:placetype":"locality"
},
  "geometry": {"coordinates":[30.31667,39.18333],"type":"Point"}
}