{
  "type": "Feature",
  "properties": {
    "gn:admin1_code":"21",
    "gn:asciiname":"Sukurlu",
    "gn:country_code":"TR",
    "gn:dem":615,
    "gn:feature_class":"P",
    "gn:feature_code":"PPL",
    "gn:name":"\u015e\u00fck\u00fcrl\u00fc",
    "gn:population":0,
    "gn:timezone":"Europe/Istanbul",
    "iso:country":"TR",
    "name:tur_x_preferred":[
        "\u015e\u00fck\u00fcrl\u00fc"
    ],
    "wof:name":"Sukurlu",
    "wof:placetype":"locality"
},
  "geometry": {"coordinates":[40.34747,37.81096],"type":"Point"}
}