{
  "type": "Feature",
  "properties": {
    "gn:admin1_code":"91.0",
    "gn:asciiname":"Bekereci",
    "gn:country_code":"TR",
    "gn:dem":263,
    "gn:feature_class":"P",
    "gn:feature_code":"PPL",
    "gn:name":"Bekereci",
    "gn:population":0,
    "gn:timezone":"Europe/Istanbul",
    "iso:country":"TR",
    "wof:name":"Bekereci",
    "wof:placetype":"locality"
},
  "geometry": {"coordinates":[36.23269000000001,37.35647],"type":"Point"}
}