{
  "type": "Feature",
  "properties": {
    "iso:country":"TR",
    "name:che_x_preferred":[
        "\u0422\u0435\u043f\u0435\u0431\u0430\u0433\u04c0"
    ],
    "name:eng_x_preferred":[
        "Tepeba\u011f"
    ],
    "name:fas_x_preferred":[
        "\u062a\u067e\u0647\u200c\u0628\u0627\u063a"
    ],
    "name:tat_x_preferred":[
        "\u0422\u0435\u043f\u0435\u0431\u0430\u0433"
    ],
    "name:tur_x_preferred":[
        "Tepeba\u011f"
    ],
    "qs:name":"Tepebag",
    "qs:name_adm0":"Turkey",
    "qs:name_adm1":"Adana",
    "qs:photos":19,
    "qs:photos_1k":4,
    "qs:photos_9k":1,
    "qs:photos_9r":1,
    "qs:photos_all":19,
    "qs:photos_sr":1,
    "qs:placetype":"Suburb",
    "qs:pop_sr":"0",
    "wd:wordcount":1100,
    "wof:name":"Tepebag",
    "wof:placetype":"neighbourhood"
},
  "geometry": {"coordinates":[35.326452,36.986982],"type":"Point"}
}