{
  "type": "Feature",
  "properties": {
    "iso:country":"TR",
    "qs:name":"Tepebag",
    "qs:name_adm0":"Turkey",
    "qs:name_adm1":"Adana",
    "qs:photos":19,
    "qs:photos_1k":4,
    "qs:photos_9k":1,
    "qs:photos_9r":1,
    "qs:photos_all":19,
    "qs:photos_sr":1,
    "qs:placetype":"Suburb",
    "qs:pop_sr":"0",
    "wd:wordcount":1100,
    "wof:name":"Tepebag",
    "wof:placetype":"neighbourhood"
},
  "geometry": {"coordinates":[35.326452,36.986982],"type":"Point"}
}