{
  "type": "Feature",
  "properties": {
    "gn:admin1_code":"32.0",
    "gn:asciiname":"Kermenli",
    "gn:country_code":"TR",
    "gn:dem":141,
    "gn:feature_class":"P",
    "gn:feature_code":"PPL",
    "gn:name":"Kermenli",
    "gn:population":0,
    "gn:timezone":"Europe/Istanbul",
    "iso:country":"TR",
    "wof:name":"Kermenli",
    "wof:placetype":"locality"
},
  "geometry": {"coordinates":[33.49988,36.51526],"type":"Point"}
}