{
  "type": "Feature",
  "properties": {
    "gn:country":"TR",
    "gn:fcode":"PPL",
    "gn:population":225,
    "iso:country":"TR",
    "name:und_x_variant":[
        "Kezer"
    ],
    "qs:name":"P\u0131narca",
    "qs:photos_9r":0,
    "qs:photos_sr":0,
    "qs:pop_sr":"2",
    "wof:name":"P\u0131narca",
    "wof:placetype":"locality",
    "wof:population":225
},
  "geometry": {"coordinates":[41.8525,37.98083],"type":"Point"}
}