{
  "type": "Feature",
  "properties": {
    "gn:admin1_code":"62",
    "gn:asciiname":"Beyce",
    "gn:country_code":"TR",
    "gn:dem":1611,
    "gn:feature_class":"P",
    "gn:feature_code":"PPL",
    "gn:name":"Beyce",
    "gn:population":0,
    "gn:timezone":"Europe/Istanbul",
    "iso:country":"TR",
    "name:und_x_variant":[
        "Piri",
        "Beyce"
    ],
    "wof:name":"Beyce",
    "wof:placetype":"locality"
},
  "geometry": {"coordinates":[39.85934,39.42493],"type":"Point"}
}