{
  "type": "Feature",
  "properties": {
    "gn:admin1_code":"77.0",
    "gn:asciiname":"Zeyli",
    "gn:country_code":"TR",
    "gn:dem":1750,
    "gn:feature_class":"P",
    "gn:feature_code":"PPL",
    "gn:name":"Zeyli",
    "gn:population":0,
    "gn:timezone":"Europe/Istanbul",
    "iso:country":"TR",
    "name:tur_x_preferred":[
        "G\u00fcll\u00fcce"
    ],
    "wof:name":"Zeyli",
    "wof:placetype":"locality"
},
  "geometry": {"coordinates":[40.00605,40.12865],"type":"Point"}
}