{
  "type": "Feature",
  "properties": {
    "gn:admin1_code":"49.0",
    "gn:asciiname":"Tasci",
    "gn:country_code":"TR",
    "gn:dem":1553,
    "gn:feature_class":"P",
    "gn:feature_code":"PPL",
    "gn:name":"Ta\u015fc\u0131",
    "gn:population":0,
    "gn:timezone":"Europe/Istanbul",
    "iso:country":"TR",
    "name:tur_x_preferred":[
        "Ta\u015f\u00e7\u0131"
    ],
    "name:tur_x_variant":[
        "Ta\u015fc\u0131"
    ],
    "wof:name":"Tasci",
    "wof:placetype":"locality"
},
  "geometry": {"coordinates":[41.41752,39.20596],"type":"Point"}
}