{
  "type": "Feature",
  "properties": {
    "gn:admin1_code":"21.0",
    "gn:asciiname":"Malacelik",
    "gn:country_code":"TR",
    "gn:dem":740,
    "gn:feature_class":"P",
    "gn:feature_code":"PPL",
    "gn:name":"Mala\u00e7elik",
    "gn:population":0,
    "gn:timezone":"Europe/Istanbul",
    "iso:country":"TR",
    "wof:name":"Malacelik",
    "wof:placetype":"locality"
},
  "geometry": {"coordinates":[41.03784,38.35569],"type":"Point"}
}