{
  "type": "Feature",
  "properties": {
    "gn:admin1_code":"74",
    "gn:asciiname":"Yediyaprak",
    "gn:country_code":"TR",
    "gn:dem":1012,
    "gn:feature_class":"P",
    "gn:feature_code":"PPL",
    "gn:name":"Yediyaprak",
    "gn:population":0,
    "gn:timezone":"Europe/Istanbul",
    "iso:country":"TR",
    "name:rus_x_preferred":[
        "Khergyul\u2019"
    ],
    "name:und_x_variant":[
        "Herg\u00fcl",
        "Yediyaprak"
    ],
    "wof:name":"Yediyaprak",
    "wof:placetype":"locality"
},
  "geometry": {"coordinates":[42.09495,37.7532],"type":"Point"}
}