{
  "type": "Feature",
  "properties": {
    "gn:admin1_code":"37",
    "gn:asciiname":"Kucuk Mutlu",
    "gn:country_code":"TR",
    "gn:dem":616,
    "gn:feature_class":"P",
    "gn:feature_code":"PPL",
    "gn:name":"K\u00fc\u00e7\u00fck Mutlu",
    "gn:population":0,
    "gn:timezone":"Europe/Istanbul",
    "iso:country":"TR",
    "wof:name":"Kucuk Mutlu",
    "wof:placetype":"locality"
},
  "geometry": {"coordinates":[33.31509,41.88191],"type":"Point"}
}