{
  "type": "Feature",
  "properties": {
    "gn:admin1_code":"10",
    "gn:asciiname":"Haciahmet Pinari",
    "gn:country_code":"TR",
    "gn:dem":852,
    "gn:feature_class":"P",
    "gn:feature_code":"PPL",
    "gn:name":"Hac\u0131ahmet P\u0131nar\u0131",
    "gn:population":0,
    "gn:timezone":"Europe/Istanbul",
    "iso:country":"TR",
    "name:tur_x_preferred":[
        "Hac\u0131ahmet P\u0131nar\u0131"
    ],
    "name:tur_x_variant":[
        "Hac\u0131ahmetler"
    ],
    "wof:name":"Haciahmet Pinari",
    "wof:placetype":"locality"
},
  "geometry": {"coordinates":[28.50155,39.61627],"type":"Point"}
}