{
  "type": "Feature",
  "properties": {
    "gn:admin1_code":"19.0",
    "gn:asciiname":"Karatepe",
    "gn:country_code":"TR",
    "gn:dem":1053,
    "gn:feature_class":"P",
    "gn:feature_code":"PPL",
    "gn:name":"Karatepe",
    "gn:population":0,
    "gn:timezone":"Europe/Istanbul",
    "iso:country":"TR",
    "name:und_x_variant":[
        "Karatepe K\u00f6y\u00fc",
        "Karatepe"
    ],
    "wof:name":"Karatepe",
    "wof:placetype":"locality"
},
  "geometry": {"coordinates":[34.95571,40.01958],"type":"Point"}
}