{
  "type": "Feature",
  "properties": {
    "gn:admin1_code":"21",
    "gn:asciiname":"Kalaba",
    "gn:country_code":"TR",
    "gn:dem":1178,
    "gn:feature_class":"P",
    "gn:feature_code":"PPL",
    "gn:name":"Kalaba",
    "gn:population":0,
    "gn:timezone":"Europe/Istanbul",
    "iso:country":"TR",
    "name:ceb_x_preferred":[
        "Kalaba"
    ],
    "name:deu_x_preferred":[
        "Kalaba"
    ],
    "name:fra_x_preferred":[
        "Kalaba"
    ],
    "name:swe_x_preferred":[
        "Kalaba"
    ],
    "name:tur_x_preferred":[
        "Kalaba"
    ],
    "wof:name":"Kalaba",
    "wof:placetype":"locality"
},
  "geometry": {"coordinates":[40.41781,38.43613],"type":"Point"}
}