{
  "type": "Feature",
  "properties": {
    "gn:admin1_code":"35",
    "gn:admin2_code":"8632427.0",
    "gn:asciiname":"Ildir",
    "gn:country_code":"TR",
    "gn:dem":22,
    "gn:feature_class":"P",
    "gn:feature_code":"PPL",
    "gn:name":"Ild\u0131r",
    "gn:population":0,
    "gn:timezone":"Europe/Istanbul",
    "iso:country":"TR",
    "name:deu_x_preferred":[
        "Ildir"
    ],
    "name:eng_x_preferred":[
        "Ildir"
    ],
    "name:ita_x_preferred":[
        "Ild\u0131r\u0131"
    ],
    "name:msa_x_preferred":[
        "Ild\u0131r\u0131"
    ],
    "name:slk_x_preferred":[
        "Ild\u0131r\u0131"
    ],
    "name:tur_x_preferred":[
        "Ild\u0131r"
    ],
    "name:vie_x_preferred":[
        "Ild\u0131r"
    ],
    "wof:name":"Ildir",
    "wof:placetype":"locality"
},
  "geometry": {"coordinates":[26.47786,38.38262],"type":"Point"}
}