{
  "type": "Feature",
  "properties": {
    "gn:admin1_code":"79",
    "gn:asciiname":"Aydinseyh",
    "gn:country_code":"TR",
    "gn:dem":1107,
    "gn:feature_class":"P",
    "gn:feature_code":"PPL",
    "gn:name":"Ayd\u0131n\u015feyh",
    "gn:population":0,
    "gn:timezone":"Europe/Istanbul",
    "iso:country":"TR",
    "name:und_x_variant":[
        "Ayd\u0131n\u015f\u0131h",
        "Avd\u0131n\u015feyh",
        "Ayd\u0131n\u015feyh"
    ],
    "wof:name":"Aydinseyh",
    "wof:placetype":"locality"
},
  "geometry": {"coordinates":[33.62517,39.99549],"type":"Point"}
}