{
  "type": "Feature",
  "properties": {
    "gn:admin1_code":"83",
    "gn:asciiname":"Akkoc",
    "gn:country_code":"TR",
    "gn:dem":771,
    "gn:feature_class":"P",
    "gn:feature_code":"PPL",
    "gn:name":"Akko\u00e7",
    "gn:population":0,
    "gn:timezone":"Europe/Istanbul",
    "iso:country":"TR",
    "name:und_x_variant":[
        "Akko\u00e7",
        "Mandollu"
    ],
    "wof:name":"Akkoc",
    "wof:placetype":"locality"
},
  "geometry": {"coordinates":[37.79974,37.47467],"type":"Point"}
}