{
  "type": "Feature",
  "properties": {
    "gn:admin1_code":"40",
    "gn:asciiname":"Boyalik",
    "gn:country_code":"TR",
    "gn:dem":1019,
    "gn:feature_class":"P",
    "gn:feature_code":"PPL",
    "gn:name":"Boyal\u0131k",
    "gn:population":0,
    "gn:timezone":"Europe/Istanbul",
    "iso:country":"TR",
    "wof:name":"Boyalik",
    "wof:placetype":"locality"
},
  "geometry": {"coordinates":[33.99885,39.50786],"type":"Point"}
}