{
  "type": "Feature",
  "properties": {
    "gn:admin1_code":"17.0",
    "gn:asciiname":"Kahvetepe",
    "gn:country_code":"TR",
    "gn:dem":43,
    "gn:feature_class":"P",
    "gn:feature_code":"PPL",
    "gn:name":"Kahvetepe",
    "gn:population":0,
    "gn:timezone":"Europe/Istanbul",
    "iso:country":"TR",
    "wof:name":"Kahvetepe",
    "wof:placetype":"locality"
},
  "geometry": {"coordinates":[27.13907,40.21894],"type":"Point"}
}