{
  "type": "Feature",
  "properties": {
    "gn:admin1_code":"60.0",
    "gn:asciiname":"Keslik",
    "gn:country_code":"TR",
    "gn:dem":1148,
    "gn:feature_class":"P",
    "gn:feature_code":"PPL",
    "gn:name":"Ke\u015flik",
    "gn:population":0,
    "gn:timezone":"Europe/Istanbul",
    "iso:country":"TR",
    "wof:name":"Keslik",
    "wof:placetype":"locality"
},
  "geometry": {"coordinates":[36.3853,40.25876],"type":"Point"}
}