{
  "type": "Feature",
  "properties": {
    "gn:admin1_code":"31.0",
    "gn:asciiname":"Kiremitli",
    "gn:country_code":"TR",
    "gn:dem":86,
    "gn:feature_class":"P",
    "gn:feature_code":"PPL",
    "gn:name":"Kiremitli",
    "gn:population":0,
    "gn:timezone":"Europe/Istanbul",
    "iso:country":"TR",
    "name:tur_x_preferred":[
        "Kiremitli"
    ],
    "wof:name":"Kiremitli",
    "wof:placetype":"locality"
},
  "geometry": {"coordinates":[36.45917,36.38944],"type":"Point"}
}