{
  "type": "Feature",
  "properties": {
    "gn:admin1_code":"12",
    "gn:asciiname":"Karadere",
    "gn:country_code":"TR",
    "gn:dem":1146,
    "gn:feature_class":"P",
    "gn:feature_code":"PPL",
    "gn:name":"Karadere",
    "gn:population":0,
    "gn:timezone":"Europe/Istanbul",
    "iso:country":"TR",
    "name:bul_x_preferred":[
        "\u041a\u0430\u0440\u0430 \u0434\u0435\u0440\u0435"
    ],
    "name:ceb_x_preferred":[
        "Karadere"
    ],
    "name:swe_x_preferred":[
        "Karadere"
    ],
    "name:tur_x_preferred":[
        "Karadere"
    ],
    "name:und_x_variant":[
        "G\u00fcnl\u00fck"
    ],
    "wof:name":"Karadere",
    "wof:placetype":"locality"
},
  "geometry": {"coordinates":[40.13591,39.17084000000001],"type":"Point"}
}