{
  "type": "Feature",
  "properties": {
    "gn:admin1_code":"74",
    "gn:asciiname":"Demirdag",
    "gn:cc2":"TR",
    "gn:country_code":"TR",
    "gn:dem":1109,
    "gn:feature_class":"P",
    "gn:feature_code":"PPL",
    "gn:name":"Demirda\u011f",
    "gn:population":0,
    "gn:timezone":"Europe/Istanbul",
    "iso:country":"TR",
    "name:tur_x_preferred":[
        "Demirda\u011f"
    ],
    "name:und_x_variant":[
        "Kilis"
    ],
    "wof:name":"Demirdag",
    "wof:placetype":"locality"
},
  "geometry": {"coordinates":[41.65278,37.89778],"type":"Point"}
}