{
  "type": "Feature",
  "properties": {
    "gn:admin1_code":"28.0",
    "gn:asciiname":"Camli",
    "gn:country_code":"TR",
    "gn:dem":787,
    "gn:feature_class":"P",
    "gn:feature_code":"PPL",
    "gn:name":"\u00c7aml\u0131",
    "gn:population":0,
    "gn:timezone":"Europe/Istanbul",
    "iso:country":"TR",
    "name:tur_x_preferred":[
        "\u00c7aml\u0131"
    ],
    "wof:name":"Camli",
    "wof:placetype":"locality"
},
  "geometry": {"coordinates":[38.43953,40.66721],"type":"Point"}
}