{
  "type": "Feature",
  "properties": {
    "gn:admin1_code":"25.0",
    "gn:asciiname":"Kongur",
    "gn:country_code":"TR",
    "gn:dem":1881,
    "gn:feature_class":"P",
    "gn:feature_code":"PPL",
    "gn:name":"Kongur",
    "gn:population":0,
    "gn:timezone":"Europe/Istanbul",
    "iso:country":"TR",
    "wof:name":"Kongur",
    "wof:placetype":"locality"
},
  "geometry": {"coordinates":[41.85501,39.23962],"type":"Point"}
}