{
  "type": "Feature",
  "properties": {
    "gn:admin1_code":"24",
    "gn:asciiname":"Davarli",
    "gn:country_code":"TR",
    "gn:dem":1684,
    "gn:feature_class":"P",
    "gn:feature_code":"PPL",
    "gn:name":"Davarl\u0131",
    "gn:population":0,
    "gn:timezone":"Europe/Istanbul",
    "iso:country":"TR",
    "name:tur_x_preferred":[
        "Davarl\u0131"
    ],
    "wof:name":"Davarli",
    "wof:placetype":"locality"
},
  "geometry": {"coordinates":[39.3439,39.84345],"type":"Point"}
}