{
  "type": "Feature",
  "properties": {
    "gn:admin1_code":"53.0",
    "gn:asciiname":"Zilkale",
    "gn:country_code":"TR",
    "gn:dem":939,
    "gn:feature_class":"P",
    "gn:feature_code":"PPL",
    "gn:name":"Zilkale",
    "gn:population":0,
    "gn:timezone":"Europe/Istanbul",
    "iso:country":"TR",
    "name:aze_x_preferred":[
        "Zilqala"
    ],
    "name:fas_x_preferred":[
        "\u0632\u06cc\u0631\u0642\u0644\u0639\u0647"
    ],
    "name:hye_x_preferred":[
        "\u0536\u056b\u056c\u0584\u0561\u056c\u0565"
    ],
    "name:spa_x_preferred":[
        "Zilkale"
    ],
    "name:tur_x_preferred":[
        "Zilkale"
    ],
    "name:und_x_variant":[
        "Kolona",
        "Kolana"
    ],
    "wof:name":"Zilkale",
    "wof:placetype":"locality"
},
  "geometry": {"coordinates":[40.95562,40.92486],"type":"Point"}
}