{
  "type": "Feature",
  "properties": {
    "gn:admin1_code":"53.0",
    "gn:asciiname":"Zilkale",
    "gn:country_code":"TR",
    "gn:dem":939,
    "gn:feature_class":"P",
    "gn:feature_code":"PPL",
    "gn:name":"Zilkale",
    "gn:population":0,
    "gn:timezone":"Europe/Istanbul",
    "iso:country":"TR",
    "name:und_x_variant":[
        "Kolona",
        "Kolana",
        "Zilkale"
    ],
    "wof:name":"Zilkale",
    "wof:placetype":"locality"
},
  "geometry": {"coordinates":[40.95562,40.92486],"type":"Point"}
}