{
  "type": "Feature",
  "properties": {
    "gn:admin1_code":"72",
    "gn:asciiname":"Tasit",
    "gn:country_code":"TR",
    "gn:dem":1090,
    "gn:feature_class":"P",
    "gn:feature_code":"PPL",
    "gn:name":"Ta\u015f\u0131t",
    "gn:population":0,
    "gn:timezone":"Europe/Istanbul",
    "iso:country":"TR",
    "name:tur_x_preferred":[
        "Ta\u015f\u0131t"
    ],
    "wof:name":"Tasit",
    "wof:placetype":"locality"
},
  "geometry": {"coordinates":[40.30481,37.41536],"type":"Point"}
}