{
  "type": "Feature",
  "properties": {
    "gn:admin1_code":"03",
    "gn:asciiname":"Devlethan",
    "gn:country_code":"TR",
    "gn:dem":1063,
    "gn:feature_class":"P",
    "gn:feature_code":"PPL",
    "gn:name":"Devlethan",
    "gn:population":0,
    "gn:timezone":"Europe/Istanbul",
    "iso:country":"TR",
    "wof:name":"Devlethan",
    "wof:placetype":"locality"
},
  "geometry": {"coordinates":[29.95969,38.55695],"type":"Point"}
}