{
  "type": "Feature",
  "properties": {
    "gn:admin1_code":"66",
    "gn:asciiname":"Kozan",
    "gn:country_code":"TR",
    "gn:dem":1365,
    "gn:feature_class":"P",
    "gn:feature_code":"PPL",
    "gn:name":"Kozan",
    "gn:population":0,
    "gn:timezone":"Europe/Istanbul",
    "iso:country":"TR",
    "name:bar_x_preferred":[
        "Kozan"
    ],
    "name:ceb_x_preferred":[
        "Kozan"
    ],
    "name:deu_x_preferred":[
        "Kozan"
    ],
    "name:fra_x_preferred":[
        "Kozan"
    ],
    "name:hun_x_preferred":[
        "Kozan"
    ],
    "name:min_x_preferred":[
        "Kozan"
    ],
    "name:nld_x_preferred":[
        "Kozan"
    ],
    "name:swe_x_preferred":[
        "Kozan"
    ],
    "name:tur_x_preferred":[
        "Kozan"
    ],
    "name:und_x_variant":[
        "Kuzan"
    ],
    "name:vie_x_preferred":[
        "Kozan"
    ],
    "wof:name":"Kozan",
    "wof:placetype":"locality"
},
  "geometry": {"coordinates":[35.57181,39.26149],"type":"Point"}
}