{
  "type": "Feature",
  "properties": {
    "gn:admin1_code":"22.0",
    "gn:asciiname":"Turpcular",
    "gn:country_code":"TR",
    "gn:dem":34,
    "gn:feature_class":"P",
    "gn:feature_code":"PPL",
    "gn:name":"Turp\u00e7ular",
    "gn:population":0,
    "gn:timezone":"Europe/Istanbul",
    "iso:country":"TR",
    "name:und_x_variant":[
        "Turupcular",
        "Turp\u00e7ular"
    ],
    "wof:name":"Turpcular",
    "wof:placetype":"locality"
},
  "geometry": {"coordinates":[26.4374,40.94098],"type":"Point"}
}