{
  "type": "Feature",
  "properties": {
    "gn:admin1_code":"70.0",
    "gn:asciiname":"Tatlica",
    "gn:country_code":"TR",
    "gn:dem":2320,
    "gn:feature_class":"P",
    "gn:feature_code":"PPL",
    "gn:name":"Tatl\u0131ca",
    "gn:population":0,
    "gn:timezone":"Europe/Istanbul",
    "iso:country":"TR",
    "wof:name":"Tatlica",
    "wof:placetype":"locality"
},
  "geometry": {"coordinates":[44.21438,37.62591],"type":"Point"}
}