{
  "type": "Feature",
  "properties": {
    "gn:admin1_code":"14.0",
    "gn:asciiname":"Kancilar",
    "gn:country_code":"TR",
    "gn:dem":833,
    "gn:feature_class":"P",
    "gn:feature_code":"PPL",
    "gn:name":"Kanc\u0131lar",
    "gn:population":0,
    "gn:timezone":"Europe/Istanbul",
    "iso:country":"TR",
    "wof:name":"Kancilar",
    "wof:placetype":"locality"
},
  "geometry": {"coordinates":[32.25607,40.94723],"type":"Point"}
}