{
  "type": "Feature",
  "properties": {
    "gn:admin1_code":"16",
    "gn:asciiname":"Yunuslar",
    "gn:country_code":"TR",
    "gn:dem":1007,
    "gn:feature_class":"P",
    "gn:feature_code":"PPL",
    "gn:name":"Yunuslar",
    "gn:population":0,
    "gn:timezone":"Europe/Istanbul",
    "iso:country":"TR",
    "name:tur_x_preferred":[
        "Yunuslar"
    ],
    "wof:name":"Yunuslar",
    "wof:placetype":"locality"
},
  "geometry": {"coordinates":[29.3225,39.81389],"type":"Point"}
}