{
  "type": "Feature",
  "properties": {
    "gn:admin1_code":"16.0",
    "gn:asciiname":"Kurtul",
    "gn:country_code":"TR",
    "gn:dem":77,
    "gn:feature_class":"P",
    "gn:feature_code":"PPL",
    "gn:name":"Kurtul",
    "gn:population":0,
    "gn:timezone":"Europe/Istanbul",
    "iso:country":"TR",
    "name:tur_x_preferred":[
        "Kurtul"
    ],
    "wof:name":"Kurtul",
    "wof:placetype":"locality"
},
  "geometry": {"coordinates":[29.12328,40.36437],"type":"Point"}
}