{
  "type": "Feature",
  "properties": {
    "gn:admin1_code":"48",
    "gn:asciiname":"Beyciler",
    "gn:country_code":"TR",
    "gn:dem":204,
    "gn:feature_class":"P",
    "gn:feature_code":"PPL",
    "gn:name":"Beyciler",
    "gn:population":0,
    "gn:timezone":"Europe/Istanbul",
    "iso:country":"TR",
    "name:tur_x_preferred":[
        "Beyciler"
    ],
    "wof:name":"Beyciler",
    "wof:placetype":"locality"
},
  "geometry": {"coordinates":[27.71977,37.10588],"type":"Point"}
}