{
  "type": "Feature",
  "properties": {
    "gn:admin1_code":"37.0",
    "gn:asciiname":"Konukca",
    "gn:country_code":"TR",
    "gn:dem":972,
    "gn:feature_class":"P",
    "gn:feature_code":"PPL",
    "gn:name":"Konuk\u00e7a",
    "gn:population":0,
    "gn:timezone":"Europe/Istanbul",
    "iso:country":"TR",
    "name:msa_x_preferred":[
        "Konuk\u00e7a"
    ],
    "name:tur_x_preferred":[
        "Konuk\u00e7a"
    ],
    "name:und_x_variant":[
        "Kanukca",
        "Konuk\u00e7a"
    ],
    "name:vie_x_preferred":[
        "Konuk\u00e7a"
    ],
    "wof:name":"Konukca",
    "wof:placetype":"locality"
},
  "geometry": {"coordinates":[33.72306,41.34183],"type":"Point"}
}