{
  "type": "Feature",
  "properties": {
    "gn:admin1_code":"31.0",
    "gn:asciiname":"Yoncaduzu",
    "gn:country_code":"TR",
    "gn:dem":206,
    "gn:feature_class":"P",
    "gn:feature_code":"PPL",
    "gn:name":"Yoncad\u00fcz\u00fc",
    "gn:population":0,
    "gn:timezone":"Europe/Istanbul",
    "iso:country":"TR",
    "name:tur_x_preferred":[
        "Yoncad\u00fcz\u00fc"
    ],
    "name:tur_x_variant":[
        "G\u00fcl\u00fck"
    ],
    "wof:name":"Yoncaduzu",
    "wof:placetype":"locality"
},
  "geometry": {"coordinates":[36.20839,36.97334],"type":"Point"}
}