{
  "type": "Feature",
  "properties": {
    "gn:admin1_code":"38",
    "gn:asciiname":"Cadirkaya",
    "gn:country_code":"TR",
    "gn:dem":1147,
    "gn:feature_class":"P",
    "gn:feature_code":"PPL",
    "gn:name":"\u00c7ad\u0131rkaya",
    "gn:population":0,
    "gn:timezone":"Europe/Istanbul",
    "iso:country":"TR",
    "wof:name":"Cadirkaya",
    "wof:placetype":"locality"
},
  "geometry": {"coordinates":[35.21777,38.16649],"type":"Point"}
}