{
  "type": "Feature",
  "properties": {
    "gn:admin1_code":"5.0",
    "gn:asciiname":"Ikipohrelik",
    "gn:country_code":"TR",
    "gn:dem":883,
    "gn:feature_class":"P",
    "gn:feature_code":"PPL",
    "gn:name":"\u0130kip\u00f6hrelik",
    "gn:population":0,
    "gn:timezone":"Europe/Istanbul",
    "iso:country":"TR",
    "wof:name":"Ikipohrelik",
    "wof:placetype":"locality"
},
  "geometry": {"coordinates":[36.35737,40.8451],"type":"Point"}
}