{
  "type": "Feature",
  "properties": {
    "gn:admin1_code":"09",
    "gn:admin2_code":"8632392",
    "gn:asciiname":"Ovapinari",
    "gn:country_code":"TR",
    "gn:dem":107,
    "gn:feature_class":"P",
    "gn:feature_code":"PPL",
    "gn:name":"Ovap\u0131nar\u0131",
    "gn:population":0,
    "gn:timezone":"Europe/Istanbul",
    "iso:country":"TR",
    "name:tur_x_preferred":[
        "Ovap\u0131nar\u0131"
    ],
    "wof:name":"Ovapinari",
    "wof:placetype":"locality"
},
  "geometry": {"coordinates":[27.84415,37.51089],"type":"Point"}
}