{
  "type": "Feature",
  "properties": {
    "gn:admin1_code":"28.0",
    "gn:asciiname":"Sahinler",
    "gn:country_code":"TR",
    "gn:dem":1357,
    "gn:feature_class":"P",
    "gn:feature_code":"PPL",
    "gn:name":"\u015eahinler",
    "gn:population":0,
    "gn:timezone":"Europe/Istanbul",
    "iso:country":"TR",
    "name:und_x_variant":[
        "\u015eahinler",
        "K\u00f6pekli"
    ],
    "wof:name":"Sahinler",
    "wof:placetype":"locality"
},
  "geometry": {"coordinates":[38.42798,40.1809],"type":"Point"}
}