{
  "type": "Feature",
  "properties": {
    "gn:admin1_code":"49",
    "gn:asciiname":"Erentepe",
    "gn:country_code":"TR",
    "gn:dem":1483,
    "gn:feature_class":"P",
    "gn:feature_code":"PPLA3",
    "gn:name":"Erentepe",
    "gn:population":0,
    "gn:timezone":"Europe/Istanbul",
    "iso:country":"TR",
    "name:und_x_variant":[
        "Liz",
        "Camili",
        "Lis",
        "Erentepe"
    ],
    "wof:name":"Erentepe",
    "wof:placetype":"locality"
},
  "geometry": {"coordinates":[42.04364,39.00893],"type":"Point"}
}