{
  "type": "Feature",
  "properties": {
    "gn:admin1_code":"81",
    "gn:asciiname":"Nergizlik",
    "gn:country_code":"TR",
    "gn:dem":320,
    "gn:feature_class":"P",
    "gn:feature_code":"PPL",
    "gn:name":"Nergizlik",
    "gn:population":0,
    "gn:timezone":"Europe/Istanbul",
    "iso:country":"TR",
    "wof:name":"Nergizlik",
    "wof:placetype":"locality"
},
  "geometry": {"coordinates":[35.04497,37.30598],"type":"Point"}
}