{
  "type": "Feature",
  "properties": {
    "gn:admin1_code":"88",
    "gn:asciiname":"Sogutlu",
    "gn:country_code":"TR",
    "gn:dem":1516,
    "gn:feature_class":"P",
    "gn:feature_code":"PPL",
    "gn:name":"S\u00f6\u011f\u00fctl\u00fc",
    "gn:population":0,
    "gn:timezone":"Europe/Istanbul",
    "iso:country":"TR",
    "wof:name":"Sogutlu",
    "wof:placetype":"locality"
},
  "geometry": {"coordinates":[43.71667,39.93333],"type":"Point"}
}