{
  "type": "Feature",
  "properties": {
    "gn:admin1_code":"35.0",
    "gn:asciiname":"Sutculer",
    "gn:country_code":"TR",
    "gn:dem":261,
    "gn:feature_class":"P",
    "gn:feature_code":"PPL",
    "gn:name":"S\u00fct\u00e7\u00fcler",
    "gn:population":0,
    "gn:timezone":"Europe/Istanbul",
    "iso:country":"TR",
    "wof:name":"Sutculer",
    "wof:placetype":"locality"
},
  "geometry": {"coordinates":[27.46297,38.47235],"type":"Point"}
}