{
  "type": "Feature",
  "properties": {
    "gn:admin1_code":"58",
    "gn:asciiname":"Gazimagara",
    "gn:country_code":"TR",
    "gn:dem":1542,
    "gn:feature_class":"P",
    "gn:feature_code":"PPL",
    "gn:name":"Gazima\u011fara",
    "gn:population":0,
    "gn:timezone":"Europe/Istanbul",
    "iso:country":"TR",
    "wof:name":"Gazimagara",
    "wof:placetype":"locality"
},
  "geometry": {"coordinates":[36.82717,39.34254],"type":"Point"}
}