{
  "type": "Feature",
  "properties": {
    "iso:country":"TR",
    "name:eng_x_preferred":[
        "Fenerkoy"
    ],
    "name:tur_x_preferred":[
        "Fenerk\u00f6y"
    ],
    "name:tur_x_variant":[
        "Fener"
    ],
    "wof:name":"Fenerkoy",
    "wof:placetype":"neighbourhood"
},
  "geometry": {"coordinates":[28.23663751309658,41.15079795931127],"type":"Point"}
}