{
  "type": "Feature",
  "properties": {
    "gn:admin1_code":"04",
    "gn:asciiname":"Arakonak",
    "gn:country_code":"TR",
    "gn:dem":1670,
    "gn:feature_class":"P",
    "gn:feature_code":"PPL",
    "gn:name":"Arakonak",
    "gn:population":0,
    "gn:timezone":"Europe/Istanbul",
    "iso:country":"TR",
    "name:und_x_variant":[
        "K\u00e2sor",
        "Arakonak"
    ],
    "wof:name":"Arakonak",
    "wof:placetype":"locality"
},
  "geometry": {"coordinates":[42.97018,39.78365],"type":"Point"}
}