{
  "type": "Feature",
  "properties": {
    "gn:admin1_code":"02",
    "gn:asciiname":"Gozpinar",
    "gn:country_code":"TR",
    "gn:dem":690,
    "gn:feature_class":"P",
    "gn:feature_code":"PPL",
    "gn:name":"G\u00f6zp\u0131nar",
    "gn:population":0,
    "gn:timezone":"Europe/Istanbul",
    "iso:country":"TR",
    "name:und_x_variant":[
        "H\u0131rso",
        "Hars\u00fck",
        "G\u00f6zp\u0131nar",
        "H\u0131rs\u00fck"
    ],
    "wof:name":"Gozpinar",
    "wof:placetype":"locality"
},
  "geometry": {"coordinates":[39.16131,38.05584],"type":"Point"}
}