{
  "type": "Feature",
  "properties": {
    "gn:admin1_code":"37.0",
    "gn:asciiname":"Catkoy",
    "gn:country_code":"TR",
    "gn:dem":1111,
    "gn:feature_class":"P",
    "gn:feature_code":"PPL",
    "gn:name":"\u00c7atk\u00f6y",
    "gn:population":0,
    "gn:timezone":"Europe/Istanbul",
    "iso:country":"TR",
    "wof:name":"Catkoy",
    "wof:placetype":"locality"
},
  "geometry": {"coordinates":[33.56667,41.84499],"type":"Point"}
}