{
  "type": "Feature",
  "properties": {
    "gn:admin1_code":"10",
    "gn:asciiname":"Karlik",
    "gn:cc2":"TR",
    "gn:country_code":"TR",
    "gn:dem":303,
    "gn:feature_class":"P",
    "gn:feature_code":"PPL",
    "gn:name":"Karl\u0131k",
    "gn:population":0,
    "gn:timezone":"Europe/Istanbul",
    "iso:country":"TR",
    "name:und_x_variant":[
        "Karl\u0131kk\u00f6y",
        "Karl\u0131k"
    ],
    "wof:name":"Karlik",
    "wof:placetype":"locality"
},
  "geometry": {"coordinates":[27.74028,39.90944],"type":"Point"}
}