{
  "type": "Feature",
  "properties": {
    "gn:admin1_code":"04",
    "gn:asciiname":"Korankomu",
    "gn:country_code":"TR",
    "gn:dem":2286,
    "gn:feature_class":"P",
    "gn:feature_code":"PPL",
    "gn:name":"Korankomu",
    "gn:population":0,
    "gn:timezone":"Europe/Istanbul",
    "iso:country":"TR",
    "name:und_x_variant":[
        "G\u00f6z\u00fcpek"
    ],
    "wof:name":"Korankomu",
    "wof:placetype":"locality"
},
  "geometry": {"coordinates":[43.63706,39.42233],"type":"Point"}
}