{
  "type": "Feature",
  "properties": {
    "gn:admin1_code":"61.0",
    "gn:asciiname":"Caferli",
    "gn:country_code":"TR",
    "gn:dem":206,
    "gn:feature_class":"P",
    "gn:feature_code":"PPL",
    "gn:name":"Caferli",
    "gn:population":0,
    "gn:timezone":"Europe/Istanbul",
    "iso:country":"TR",
    "name:tur_x_preferred":[
        "Caferli"
    ],
    "wof:name":"Caferli",
    "wof:placetype":"locality"
},
  "geometry": {"coordinates":[39.2874,41.0234],"type":"Point"}
}