{
  "type": "Feature",
  "properties": {
    "gn:admin1_code":"58.0",
    "gn:asciiname":"Kilic",
    "gn:country_code":"TR",
    "gn:dem":1731,
    "gn:feature_class":"P",
    "gn:feature_code":"PPL",
    "gn:name":"K\u0131l\u0131\u00e7",
    "gn:population":0,
    "gn:timezone":"Europe/Istanbul",
    "iso:country":"TR",
    "name:tur_x_preferred":[
        "K\u0131l\u0131\u00e7"
    ],
    "wof:name":"Kilic",
    "wof:placetype":"locality"
},
  "geometry": {"coordinates":[38.3134,40.03823],"type":"Point"}
}