{
  "type": "Feature",
  "properties": {
    "gn:admin1_code":"58",
    "gn:asciiname":"Maltepe",
    "gn:country_code":"TR",
    "gn:dem":1341,
    "gn:feature_class":"P",
    "gn:feature_code":"PPL",
    "gn:name":"Maltepe",
    "gn:population":0,
    "gn:timezone":"Europe/Istanbul",
    "iso:country":"TR",
    "name:ceb_x_preferred":[
        "Maltepe"
    ],
    "name:deu_x_preferred":[
        "Maltepe"
    ],
    "name:msa_x_preferred":[
        "Maltepe"
    ],
    "name:swe_x_preferred":[
        "Maltepe"
    ],
    "name:tur_x_preferred":[
        "Maltepe"
    ],
    "name:und_x_variant":[
        "Hornovil",
        "Hornevil",
        "Hornavul"
    ],
    "wof:name":"Maltepe",
    "wof:placetype":"locality"
},
  "geometry": {"coordinates":[38.10693,39.48632],"type":"Point"}
}