{
  "type": "Feature",
  "properties": {
    "gn:admin1_code":"89.0",
    "gn:asciiname":"Kutluoren",
    "gn:country_code":"TR",
    "gn:dem":838,
    "gn:feature_class":"P",
    "gn:feature_code":"PPL",
    "gn:name":"Kutlu\u00f6ren",
    "gn:population":0,
    "gn:timezone":"Europe/Istanbul",
    "iso:country":"TR",
    "name:und_x_variant":[
        "Kutluveren",
        "Kutlu\u00f6ren"
    ],
    "wof:name":"Kutluoren",
    "wof:placetype":"locality"
},
  "geometry": {"coordinates":[32.9257,41.5365],"type":"Point"}
}