{
  "type": "Feature",
  "properties": {
    "gn:admin1_code":"23.0",
    "gn:asciiname":"Kocharman",
    "gn:country_code":"TR",
    "gn:dem":1428,
    "gn:feature_class":"P",
    "gn:feature_code":"PPL",
    "gn:name":"Ko\u00e7harman",
    "gn:population":0,
    "gn:timezone":"Europe/Istanbul",
    "iso:country":"TR",
    "name:tur_x_preferred":[
        "Ko\u00e7harman"
    ],
    "name:tur_x_variant":[
        "Kocaharman\u0131"
    ],
    "wof:name":"Kocharman",
    "wof:placetype":"locality"
},
  "geometry": {"coordinates":[38.94373,38.49342],"type":"Point"}
}