{
  "type": "Feature",
  "properties": {
    "gn:admin1_code":"20",
    "gn:asciiname":"Sepetci",
    "gn:country_code":"TR",
    "gn:dem":948,
    "gn:feature_class":"P",
    "gn:feature_code":"PPL",
    "gn:name":"Sepet\u00e7i",
    "gn:population":0,
    "gn:timezone":"Europe/Istanbul",
    "iso:country":"TR",
    "name:tur_x_preferred":[
        "Sepet\u00e7i"
    ],
    "wof:name":"Sepetci",
    "wof:placetype":"locality"
},
  "geometry": {"coordinates":[28.9019,37.27183],"type":"Point"}
}