{
  "type": "Feature",
  "properties": {
    "gn:admin1_code":"17",
    "gn:asciiname":"Umurlar",
    "gn:country_code":"TR",
    "gn:dem":322,
    "gn:feature_class":"P",
    "gn:feature_code":"PPL",
    "gn:name":"Umurlar",
    "gn:population":0,
    "gn:timezone":"Europe/Istanbul",
    "iso:country":"TR",
    "name:tur_x_preferred":[
        "Umurlar"
    ],
    "wof:name":"Umurlar",
    "wof:placetype":"locality"
},
  "geometry": {"coordinates":[27.34929,39.89697],"type":"Point"}
}