{
  "type": "Feature",
  "properties": {
    "gn:admin1_code":"70",
    "gn:asciiname":"Soguksu",
    "gn:country_code":"TR",
    "gn:dem":1847,
    "gn:feature_class":"P",
    "gn:feature_code":"PPL",
    "gn:name":"So\u011fuksu",
    "gn:population":0,
    "gn:timezone":"Europe/Istanbul",
    "iso:country":"TR",
    "wof:name":"Soguksu",
    "wof:placetype":"locality"
},
  "geometry": {"coordinates":[44.59578,37.38303],"type":"Point"}
}