{
  "type": "Feature",
  "properties": {
    "gn:admin1_code":"48",
    "gn:asciiname":"Kozagac",
    "gn:country_code":"TR",
    "gn:dem":737,
    "gn:feature_class":"P",
    "gn:feature_code":"PPL",
    "gn:name":"Koza\u011fa\u00e7",
    "gn:population":0,
    "gn:timezone":"Europe/Istanbul",
    "iso:country":"TR",
    "name:tur_x_preferred":[
        "Koza\u011fa\u00e7"
    ],
    "name:tur_x_variant":[
        "Koza\u011fac\u0131"
    ],
    "wof:name":"Kozagac",
    "wof:placetype":"locality"
},
  "geometry": {"coordinates":[29.15938,36.52506],"type":"Point"}
}