{
  "type": "Feature",
  "properties": {
    "gn:admin1_code":"07",
    "gn:asciiname":"Seyret",
    "gn:country_code":"TR",
    "gn:dem":831,
    "gn:feature_class":"P",
    "gn:feature_code":"PPL",
    "gn:name":"Seyret",
    "gn:population":0,
    "gn:timezone":"Europe/Istanbul",
    "iso:country":"TR",
    "name:und_x_variant":[
        "Seyretk\u00f6y\u00fc",
        "Seyretk\u00f6y",
        "Seyret",
        "G\u00f6k\u00e7e\u00f6ren"
    ],
    "wof:name":"Seyret",
    "wof:placetype":"locality"
},
  "geometry": {"coordinates":[29.54243,36.23901],"type":"Point"}
}