{
  "type": "Feature",
  "properties": {
    "gn:admin1_code":"86.0",
    "gn:asciiname":"Yukaricambaz",
    "gn:country_code":"TR",
    "gn:dem":1921,
    "gn:feature_class":"P",
    "gn:feature_code":"PPL",
    "gn:name":"Yukar\u0131cambaz",
    "gn:population":0,
    "gn:timezone":"Europe/Istanbul",
    "iso:country":"TR",
    "name:und_x_variant":[
        "Yukar\u0131 Canbaz",
        "Yukar\u0131 Canbaz Yayl\u00e2",
        "Yukar\u0131cambaz"
    ],
    "wof:name":"Yukaricambaz",
    "wof:placetype":"locality"
},
  "geometry": {"coordinates":[43.26868,41.12515],"type":"Point"}
}