{
  "type": "Feature",
  "properties": {
    "gn:admin1_code":"19.0",
    "gn:asciiname":"Bagozu",
    "gn:country_code":"TR",
    "gn:dem":611,
    "gn:feature_class":"P",
    "gn:feature_code":"PPL",
    "gn:name":"Ba\u011f\u00f6z\u00fc",
    "gn:population":0,
    "gn:timezone":"Europe/Istanbul",
    "iso:country":"TR",
    "name:tur_x_preferred":[
        "Ba\u011f\u00f6z\u00fc"
    ],
    "name:und_x_variant":[
        "Ba\u011fy\u00fcz\u00fc"
    ],
    "wof:name":"Bagozu",
    "wof:placetype":"locality"
},
  "geometry": {"coordinates":[34.71025,41.14835],"type":"Point"}
}