{
  "type": "Feature",
  "properties": {
    "gn:admin1_code":"65.0",
    "gn:asciiname":"Serametas",
    "gn:country_code":"TR",
    "gn:dem":2087,
    "gn:feature_class":"P",
    "gn:feature_code":"PPL",
    "gn:name":"Serameta\u015f",
    "gn:population":0,
    "gn:timezone":"Europe/Istanbul",
    "iso:country":"TR",
    "name:tur_x_preferred":[
        "Serameta\u015f"
    ],
    "wof:name":"Serametas",
    "wof:placetype":"locality"
},
  "geometry": {"coordinates":[43.91277,39.18865],"type":"Point"}
}