{
  "type": "Feature",
  "properties": {
    "gn:admin1_code":"09",
    "gn:asciiname":"Saki Mahallesi",
    "gn:country_code":"TR",
    "gn:dem":574,
    "gn:feature_class":"P",
    "gn:feature_code":"PPL",
    "gn:name":"Sak\u0131 Mahallesi",
    "gn:population":0,
    "gn:timezone":"Europe/Istanbul",
    "iso:country":"TR",
    "name:tur_x_preferred":[
        "Sak\u0131 Mahallesi"
    ],
    "wof:name":"Saki Mahallesi",
    "wof:placetype":"locality"
},
  "geometry": {"coordinates":[28.51716,37.98746],"type":"Point"}
}