{
  "type": "Feature",
  "properties": {
    "gn:admin1_code":"65",
    "gn:asciiname":"Ekece",
    "gn:country_code":"TR",
    "gn:dem":2636,
    "gn:feature_class":"P",
    "gn:feature_code":"PPL",
    "gn:name":"Ekece",
    "gn:population":0,
    "gn:timezone":"Europe/Istanbul",
    "iso:country":"TR",
    "name:tur_x_preferred":[
        "Ekecek"
    ],
    "wof:name":"Ekece",
    "wof:placetype":"locality"
},
  "geometry": {"coordinates":[43.66015,38.49253],"type":"Point"}
}