{
  "type": "Feature",
  "properties": {
    "gn:admin1_code":"57.0",
    "gn:asciiname":"Beloren",
    "gn:country_code":"TR",
    "gn:dem":143,
    "gn:feature_class":"P",
    "gn:feature_code":"PPL",
    "gn:name":"Bel\u00f6ren",
    "gn:population":0,
    "gn:timezone":"Europe/Istanbul",
    "iso:country":"TR",
    "name:tur_x_preferred":[
        "Bel\u00f6ren"
    ],
    "wof:name":"Beloren",
    "wof:placetype":"locality"
},
  "geometry": {"coordinates":[35.14895,41.8103],"type":"Point"}
}