{
  "type": "Feature",
  "properties": {
    "gn:admin1_code":"44",
    "gn:asciiname":"Karacayir",
    "gn:country_code":"TR",
    "gn:dem":1351,
    "gn:feature_class":"P",
    "gn:feature_code":"PPL",
    "gn:name":"Kara\u00e7ay\u0131r",
    "gn:population":0,
    "gn:timezone":"Europe/Istanbul",
    "iso:country":"TR",
    "name:tur_x_preferred":[
        "Kara\u00e7ay\u0131r"
    ],
    "wof:name":"Karacayir",
    "wof:placetype":"locality"
},
  "geometry": {"coordinates":[37.74401,38.87106],"type":"Point"}
}