{
  "type": "Feature",
  "properties": {
    "gn:admin1_code":"71",
    "gn:asciiname":"Urunlu",
    "gn:country_code":"TR",
    "gn:dem":1011,
    "gn:feature_class":"P",
    "gn:feature_code":"PPL",
    "gn:name":"\u00dcr\u00fcnl\u00fc",
    "gn:population":0,
    "gn:timezone":"Europe/Istanbul",
    "iso:country":"TR",
    "wof:name":"Urunlu",
    "wof:placetype":"locality"
},
  "geometry": {"coordinates":[32.88027,37.55752],"type":"Point"}
}