{
  "type": "Feature",
  "properties": {
    "gn:admin1_code":"07",
    "gn:asciiname":"Yaylakonak",
    "gn:country_code":"TR",
    "gn:dem":776,
    "gn:feature_class":"P",
    "gn:feature_code":"PPL",
    "gn:name":"Yaylakonak",
    "gn:population":0,
    "gn:timezone":"Europe/Istanbul",
    "iso:country":"TR",
    "wof:name":"Yaylakonak",
    "wof:placetype":"locality"
},
  "geometry": {"coordinates":[32.25114,36.51236],"type":"Point"}
}