{
  "type": "Feature",
  "properties": {
    "gn:admin1_code":"5.0",
    "gn:asciiname":"Demirpinar",
    "gn:country_code":"TR",
    "gn:dem":1001,
    "gn:feature_class":"P",
    "gn:feature_code":"PPL",
    "gn:name":"Demirp\u0131nar",
    "gn:population":0,
    "gn:timezone":"Europe/Istanbul",
    "iso:country":"TR",
    "name:und_x_variant":[
        "\u015eamba",
        "Demirp\u0131nar"
    ],
    "wof:name":"Demirpinar",
    "wof:placetype":"locality"
},
  "geometry": {"coordinates":[35.31431,40.74197],"type":"Point"}
}