{
  "type": "Feature",
  "properties": {
    "gn:admin1_code":"48.0",
    "gn:asciiname":"Kurtlar",
    "gn:country_code":"TR",
    "gn:dem":1221,
    "gn:feature_class":"P",
    "gn:feature_code":"PPL",
    "gn:name":"Kurtlar",
    "gn:population":0,
    "gn:timezone":"Europe/Istanbul",
    "iso:country":"TR",
    "name:tur_x_preferred":[
        "Kurtlar"
    ],
    "name:tur_x_variant":[
        "Karag\u00f6z"
    ],
    "wof:name":"Kurtlar",
    "wof:placetype":"locality"
},
  "geometry": {"coordinates":[29.53788,36.86115],"type":"Point"}
}