{
  "type": "Feature",
  "properties": {
    "gn:admin1_code":"68.0",
    "gn:asciiname":"Esenboga",
    "gn:country_code":"TR",
    "gn:dem":942,
    "gn:feature_class":"P",
    "gn:feature_code":"PPL",
    "gn:name":"Esenbo\u011fa",
    "gn:population":0,
    "gn:timezone":"Europe/Istanbul",
    "iso:country":"TR",
    "name:deu_x_preferred":[
        "Esenbo\u011fa"
    ],
    "name:eng_x_preferred":[
        "Esenbo\u011fa"
    ],
    "name:msa_x_preferred":[
        "Esenbo\u011fa"
    ],
    "name:tur_x_preferred":[
        "Esenbo\u011fa"
    ],
    "name:und_x_variant":[
        "Esenbu\u011fa",
        "Esenbo\u011fa"
    ],
    "wof:name":"Esenboga",
    "wof:placetype":"locality"
},
  "geometry": {"coordinates":[32.98525,40.134],"type":"Point"}
}