{
  "type": "Feature",
  "properties": {
    "gn:country":"TR",
    "gn:fcode":"PPL",
    "gn:population":331,
    "iso:country":"TR",
    "name:und_x_variant":[
        "Banih"
    ],
    "qs:name":"Ocakl\u0131",
    "qs:photos_9r":0,
    "qs:photos_sr":0,
    "qs:pop_sr":"2",
    "wof:name":"Ocakl\u0131",
    "wof:placetype":"locality",
    "wof:population":331
},
  "geometry": {"coordinates":[41.82293,37.16299],"type":"Point"}
}