{
  "type": "Feature",
  "properties": {
    "gn:admin1_code":"34",
    "gn:asciiname":"Denizli",
    "gn:country_code":"TR",
    "gn:dem":19,
    "gn:feature_class":"P",
    "gn:feature_code":"PPL",
    "gn:name":"Denizli",
    "gn:population":0,
    "gn:timezone":"Europe/Istanbul",
    "iso:country":"TR",
    "name:tur_x_preferred":[
        "Denizli"
    ],
    "wof:name":"Denizli",
    "wof:placetype":"locality"
},
  "geometry": {"coordinates":[29.78164,41.09648],"type":"Point"}
}