{
  "type": "Feature",
  "properties": {
    "gn:admin1_code":"37.0",
    "gn:asciiname":"Kavak",
    "gn:country_code":"TR",
    "gn:dem":984,
    "gn:feature_class":"P",
    "gn:feature_code":"PPL",
    "gn:name":"Kavak",
    "gn:population":0,
    "gn:timezone":"Europe/Istanbul",
    "iso:country":"TR",
    "name:deu_x_preferred":[
        "Kavak"
    ],
    "name:nld_x_preferred":[
        "Kavak"
    ],
    "name:tur_x_preferred":[
        "Kavak"
    ],
    "wof:name":"Kavak",
    "wof:placetype":"locality"
},
  "geometry": {"coordinates":[34.24764,41.62648],"type":"Point"}
}