{
  "type": "Feature",
  "properties": {
    "gn:admin1_code":"8.0",
    "gn:asciiname":"Kasikci",
    "gn:country_code":"TR",
    "gn:dem":1466,
    "gn:feature_class":"P",
    "gn:feature_code":"PPL",
    "gn:name":"Ka\u015f\u0131k\u00e7\u0131",
    "gn:population":0,
    "gn:timezone":"Europe/Istanbul",
    "iso:country":"TR",
    "wof:name":"Kasikci",
    "wof:placetype":"locality"
},
  "geometry": {"coordinates":[42.14579000000001,41.12721],"type":"Point"}
}