{
  "type": "Feature",
  "properties": {
    "gn:admin1_code":"44",
    "gn:asciiname":"Esencik",
    "gn:country_code":"TR",
    "gn:dem":1266,
    "gn:feature_class":"P",
    "gn:feature_code":"PPL",
    "gn:name":"Esencik",
    "gn:population":0,
    "gn:timezone":"Europe/Istanbul",
    "iso:country":"TR",
    "name:tur_x_preferred":[
        "Esencik"
    ],
    "wof:name":"Esencik",
    "wof:placetype":"locality"
},
  "geometry": {"coordinates":[39.0164,38.09653],"type":"Point"}
}