{
  "type": "Feature",
  "properties": {
    "gn:admin1_code":"39.0",
    "gn:asciiname":"Kucukkaristiran",
    "gn:country_code":"TR",
    "gn:dem":109,
    "gn:feature_class":"P",
    "gn:feature_code":"PPL",
    "gn:name":"K\u00fc\u00e7\u00fckkar\u0131\u015ft\u0131ran",
    "gn:population":0,
    "gn:timezone":"Europe/Istanbul",
    "iso:country":"TR",
    "wof:name":"Kucukkaristiran",
    "wof:placetype":"locality"
},
  "geometry": {"coordinates":[27.53917,41.3325],"type":"Point"}
}