{
  "type": "Feature",
  "properties": {
    "gn:admin1_code":"69.0",
    "gn:asciiname":"Atalar",
    "gn:country_code":"TR",
    "gn:dem":1636,
    "gn:feature_class":"P",
    "gn:feature_code":"PPL",
    "gn:name":"Atalar",
    "gn:population":0,
    "gn:timezone":"Europe/Istanbul",
    "iso:country":"TR",
    "name:tur_x_preferred":[
        "Atalar"
    ],
    "wof:name":"Atalar",
    "wof:placetype":"locality"
},
  "geometry": {"coordinates":[39.44117,40.58878],"type":"Point"}
}