{
  "type": "Feature",
  "properties": {
    "gn:admin1_code":"61.0",
    "gn:asciiname":"Kumburlu",
    "gn:country_code":"TR",
    "gn:dem":481,
    "gn:feature_class":"P",
    "gn:feature_code":"PPL",
    "gn:name":"Kumburlu",
    "gn:population":0,
    "gn:timezone":"Europe/Istanbul",
    "iso:country":"TR",
    "wof:name":"Kumburlu",
    "wof:placetype":"locality"
},
  "geometry": {"coordinates":[39.68069000000001,40.85263],"type":"Point"}
}