{
  "type": "Feature",
  "properties": {
    "gn:admin1_code":"03",
    "gn:asciiname":"Alanyurt",
    "gn:cc2":"TR",
    "gn:country_code":"TR",
    "gn:dem":1419,
    "gn:feature_class":"P",
    "gn:feature_code":"PPL",
    "gn:name":"Alanyurt",
    "gn:population":0,
    "gn:timezone":"Europe/Istanbul",
    "iso:country":"TR",
    "name:tur_x_preferred":[
        "Alanyurt"
    ],
    "name:und_x_variant":[
        "Bavurdu"
    ],
    "wof:name":"Alanyurt",
    "wof:placetype":"locality"
},
  "geometry": {"coordinates":[30.745,39.00111],"type":"Point"}
}