{
  "type": "Feature",
  "properties": {
    "gn:country":"TR",
    "gn:fcode":"PPL",
    "gn:pop":410,
    "iso:country":"TR",
    "name:tur_x_preferred":[
        "\u00c7etinler"
    ],
    "name:unk_x_variant":[
        "Kharemsheddat"
    ],
    "qs:name":"\u00c7etinler",
    "qs:photos_9r":0,
    "qs:photos_sr":0,
    "qs:pop_sr":"2",
    "wof:name":"\u00c7etinler",
    "wof:placetype":"locality",
    "wof:population":410
},
  "geometry": {"coordinates":[40.68283,37.14021],"type":"Point"}
}