{
  "type": "Feature",
  "properties": {
    "gn:country":"TR",
    "gn:fcode":"PPL",
    "gn:population":23161,
    "iso:country":"TR",
    "name:ara_x_preferred":[
        "\u0645\u0648\u062f\u0627\u0646\u064a\u0627"
    ],
    "name:ast_x_preferred":[
        "Mudanya"
    ],
    "name:bul_x_preferred":[
        "\u041c\u0443\u0434\u0430\u043d\u0438\u044f"
    ],
    "name:cat_x_preferred":[
        "Mudanya"
    ],
    "name:ceb_x_preferred":[
        "Mudanya"
    ],
    "name:ces_x_preferred":[
        "Mudanya"
    ],
    "name:che_x_preferred":[
        "\u041c\u0443\u0434\u0430\u043d\u0439\u0430"
    ],
    "name:deu_x_preferred":[
        "Mudanya"
    ],
    "name:diq_x_preferred":[
        "Mudanya"
    ],
    "name:ell_x_preferred":[
        "\u039c\u03bf\u03c5\u03b4\u03b1\u03bd\u03b9\u03ac"
    ],
    "name:eng_x_preferred":[
        "Mudanya"
    ],
    "name:fas_x_preferred":[
        "\u0645\u0648\u062f\u0627\u0646\u06cc\u0627"
    ],
    "name:fra_x_preferred":[
        "Mudanya"
    ],
    "name:hau_x_preferred":[
        "Mudanya"
    ],
    "name:ita_x_preferred":[
        "Distretto di Mudanya"
    ],
    "name:lit_x_preferred":[
        "Mudanja"
    ],
    "name:min_x_preferred":[
        "Mudanya"
    ],
    "name:mrj_x_preferred":[
        "\u041c\u0443\u0434\u0430\u043d\u044c\u044f"
    ],
    "name:msa_x_preferred":[
        "Mudanya"
    ],
    "name:nan_x_preferred":[
        "Mudanya"
    ],
    "name:nld_x_preferred":[
        "Mudanya"
    ],
    "name:nob_x_preferred":[
        "Mudanya"
    ],
    "name:pnb_x_preferred":[
        "\u0636\u0644\u0639 \u0645\u062f\u06cc\u0627\u0646\u0627"
    ],
    "name:pol_x_preferred":[
        "Mudanya"
    ],
    "name:rus_x_preferred":[
        "\u041c\u0443\u0434\u0430\u043d\u044c\u0438"
    ],
    "name:rus_x_variant":[
        "\u041c\u0443\u0434\u0430\u043d\u044c\u044f"
    ],
    "name:slk_x_preferred":[
        "Mudanya"
    ],
    "name:spa_x_preferred":[
        "Mudania"
    ],
    "name:swa_x_preferred":[
        "Mudanya"
    ],
    "name:swe_x_preferred":[
        "Mudanya"
    ],
    "name:tat_x_preferred":[
        "\u041c\u0443\u0434\u0430\u043d\u044c\u044f"
    ],
    "name:tur_x_preferred":[
        "Mudanya"
    ],
    "name:und_x_variant":[
        "Montagnae"
    ],
    "name:urd_x_preferred":[
        "\u0645\u0648\u062f\u0627\u0646\u06cc\u0627"
    ],
    "name:vie_x_preferred":[
        "Mudanya"
    ],
    "name:zho_x_preferred":[
        "\u7a46\u4e39\u96c5"
    ],
    "qs:name":"Mudanya",
    "qs:photos_9r":0,
    "qs:photos_sr":0,
    "qs:pop_sr":"7",
    "wd:wordcount":391,
    "wof:name":"Mudanya",
    "wof:placetype":"locality",
    "wof:population":23161
},
  "geometry": {"coordinates":[28.88222,40.37528],"type":"Point"}
}