{
  "type": "Feature",
  "properties": {
    "gn:admin1_code":"25",
    "gn:asciiname":"Doganbey",
    "gn:country_code":"TR",
    "gn:dem":1665,
    "gn:feature_class":"P",
    "gn:feature_code":"PPL",
    "gn:name":"Do\u011fanbey",
    "gn:population":0,
    "gn:timezone":"Europe/Istanbul",
    "iso:country":"TR",
    "name:und_x_variant":[
        "Do\u011fanbey",
        "G\u00fcvendik"
    ],
    "wof:name":"Doganbey",
    "wof:placetype":"locality"
},
  "geometry": {"coordinates":[42.14463,39.30408],"type":"Point"}
}