{
  "type": "Feature",
  "properties": {
    "gn:admin1_code":"38",
    "gn:asciiname":"Bagpinar",
    "gn:country_code":"TR",
    "gn:dem":1154,
    "gn:feature_class":"P",
    "gn:feature_code":"PPL",
    "gn:name":"Ba\u011fp\u0131nar",
    "gn:population":0,
    "gn:timezone":"Europe/Istanbul",
    "iso:country":"TR",
    "name:und_x_variant":[
        "Espidin",
        "\u0130sp\u0131d\u0131n",
        "Isb\u0131d\u0131n",
        "Ba\u011fp\u0131nar"
    ],
    "wof:name":"Bagpinar",
    "wof:placetype":"locality"
},
  "geometry": {"coordinates":[35.65365,38.81179],"type":"Point"}
}