{
  "type": "Feature",
  "properties": {
    "gn:admin1_code":"68.0",
    "gn:asciiname":"Alan Koy",
    "gn:country_code":"TR",
    "gn:dem":869,
    "gn:feature_class":"P",
    "gn:feature_code":"PPL",
    "gn:name":"Alan K\u00f6y",
    "gn:population":0,
    "gn:timezone":"Europe/Istanbul",
    "iso:country":"TR",
    "name:und_x_variant":[
        "Alan K\u00f6y",
        "Alan"
    ],
    "wof:name":"Alan Koy",
    "wof:placetype":"locality"
},
  "geometry": {"coordinates":[31.21417000000001,40.11056],"type":"Point"}
}