{
  "type": "Feature",
  "properties": {
    "gn:admin1_code":"09",
    "gn:asciiname":"Koyunlar",
    "gn:cc2":"TR",
    "gn:country_code":"TR",
    "gn:dem":754,
    "gn:feature_class":"P",
    "gn:feature_code":"PPL",
    "gn:name":"Koyunlar",
    "gn:population":0,
    "gn:timezone":"Europe/Istanbul",
    "iso:country":"TR",
    "name:und_x_variant":[
        "Koyuncular",
        "Koyunlar"
    ],
    "wof:name":"Koyunlar",
    "wof:placetype":"locality"
},
  "geometry": {"coordinates":[28.22592,37.75504],"type":"Point"}
}