{
  "type": "Feature",
  "properties": {
    "gn:admin1_code":"82.0",
    "gn:asciiname":"Derecati",
    "gn:country_code":"TR",
    "gn:dem":1113,
    "gn:feature_class":"P",
    "gn:feature_code":"PPL",
    "gn:name":"Dere\u00e7at\u0131",
    "gn:population":0,
    "gn:timezone":"Europe/Istanbul",
    "iso:country":"TR",
    "name:und_x_variant":[
        "Hand\u0131r\u0131",
        "Dere\u00e7at\u0131"
    ],
    "wof:name":"Derecati",
    "wof:placetype":"locality"
},
  "geometry": {"coordinates":[33.67363,40.75485],"type":"Point"}
}