{
  "type": "Feature",
  "properties": {
    "gn:admin1_code":"37.0",
    "gn:asciiname":"Asagidikmen",
    "gn:country_code":"TR",
    "gn:dem":574,
    "gn:feature_class":"P",
    "gn:feature_code":"PPL",
    "gn:name":"A\u015fa\u011f\u0131dikmen",
    "gn:population":0,
    "gn:timezone":"Europe/Istanbul",
    "iso:country":"TR",
    "wof:name":"Asagidikmen",
    "wof:placetype":"locality"
},
  "geometry": {"coordinates":[34.10719,40.98653],"type":"Point"}
}