{
  "type": "Feature",
  "properties": {
    "gn:admin1_code":"80.0",
    "gn:asciiname":"Kirkagac",
    "gn:country_code":"TR",
    "gn:dem":709,
    "gn:feature_class":"P",
    "gn:feature_code":"PPL",
    "gn:name":"K\u0131rka\u011fa\u00e7",
    "gn:population":0,
    "gn:timezone":"Europe/Istanbul",
    "iso:country":"TR",
    "name:und_x_variant":[
        "Avine",
        "K\u0131rka\u011fa\u00e7"
    ],
    "wof:name":"Kirkagac",
    "wof:placetype":"locality"
},
  "geometry": {"coordinates":[42.00816,37.48811],"type":"Point"}
}