{
  "type": "Feature",
  "properties": {
    "gn:admin1_code":"86.0",
    "gn:asciiname":"Oragas",
    "gn:country_code":"TR",
    "gn:dem":1774,
    "gn:feature_class":"P",
    "gn:feature_code":"PPL",
    "gn:name":"Oragas",
    "gn:population":0,
    "gn:timezone":"Europe/Istanbul",
    "iso:country":"TR",
    "name:und_x_variant":[
        "\u00c7aya\u011fz\u0131"
    ],
    "wof:name":"Oragas",
    "wof:placetype":"locality"
},
  "geometry": {"coordinates":[42.85136,41.19393],"type":"Point"}
}