{
  "type": "Feature",
  "properties": {
    "gn:admin1_code":"14",
    "gn:asciiname":"Cerkezpinar",
    "gn:country_code":"TR",
    "gn:dem":678,
    "gn:feature_class":"P",
    "gn:feature_code":"PPL",
    "gn:name":"\u00c7erkezp\u0131nar",
    "gn:population":0,
    "gn:timezone":"Europe/Istanbul",
    "iso:country":"TR",
    "wof:name":"Cerkezpinar",
    "wof:placetype":"locality"
},
  "geometry": {"coordinates":[31.97874,40.89921],"type":"Point"}
}