{
  "type": "Feature",
  "properties": {
    "gn:admin1_code":"58.0",
    "gn:asciiname":"Yesimli",
    "gn:country_code":"TR",
    "gn:dem":1429,
    "gn:feature_class":"P",
    "gn:feature_code":"PPL",
    "gn:name":"Ye\u015fimli",
    "gn:population":0,
    "gn:timezone":"Europe/Istanbul",
    "iso:country":"TR",
    "name:tur_x_preferred":[
        "Ye\u015fimli"
    ],
    "wof:name":"Yesimli",
    "wof:placetype":"locality"
},
  "geometry": {"coordinates":[37.70386,40.17947],"type":"Point"}
}