{
  "type": "Feature",
  "properties": {
    "iso:country":"TR",
    "name:tur_x_preferred":[
        "Boyal\u0131k"
    ],
    "wof:name":"Boyalik",
    "wof:placetype":"neighbourhood"
},
  "geometry": {"coordinates":[28.62805065167995,41.26250566059439],"type":"Point"}
}