{
  "type": "Feature",
  "properties": {
    "gn:admin1_code":"11",
    "gn:asciiname":"Duzdag",
    "gn:country_code":"TR",
    "gn:dem":1066,
    "gn:feature_class":"P",
    "gn:feature_code":"PPL",
    "gn:name":"D\u00fczda\u011f",
    "gn:population":0,
    "gn:timezone":"Europe/Istanbul",
    "iso:country":"TR",
    "name:und_x_variant":[
        "D\u00fczda\u011f K\u00f6y\u00fc",
        "D\u00fczda\u011f"
    ],
    "wof:name":"Duzdag",
    "wof:placetype":"locality"
},
  "geometry": {"coordinates":[30.14132,39.93889],"type":"Point"}
}