{
  "type": "Feature",
  "properties": {
    "gn:admin1_code":"25",
    "gn:asciiname":"Yesiloren",
    "gn:country_code":"TR",
    "gn:dem":1999,
    "gn:feature_class":"P",
    "gn:feature_code":"PPL",
    "gn:name":"Ye\u015fil\u00f6ren",
    "gn:population":0,
    "gn:timezone":"Europe/Istanbul",
    "iso:country":"TR",
    "name:tur_x_preferred":[
        "Ye\u015fil\u00f6ren"
    ],
    "wof:name":"Yesiloren",
    "wof:placetype":"locality"
},
  "geometry": {"coordinates":[41.63953,39.675],"type":"Point"}
}