{
  "type": "Feature",
  "properties": {
    "gn:admin1_code":"17",
    "gn:asciiname":"Hacidervisler",
    "gn:country_code":"TR",
    "gn:dem":272,
    "gn:feature_class":"P",
    "gn:feature_code":"PPL",
    "gn:name":"Hac\u0131dervi\u015fler",
    "gn:population":0,
    "gn:timezone":"Europe/Istanbul",
    "iso:country":"TR",
    "wof:name":"Hacidervisler",
    "wof:placetype":"locality"
},
  "geometry": {"coordinates":[26.7375,39.95389],"type":"Point"}
}