{
  "type": "Feature",
  "properties": {
    "gn:admin1_code":"24",
    "gn:asciiname":"Saztepe",
    "gn:country_code":"TR",
    "gn:dem":1151,
    "gn:feature_class":"P",
    "gn:feature_code":"PPL",
    "gn:name":"Saztepe",
    "gn:population":0,
    "gn:timezone":"Europe/Istanbul",
    "iso:country":"TR",
    "name:tur_x_preferred":[
        "Saztepe"
    ],
    "wof:name":"Saztepe",
    "wof:placetype":"locality"
},
  "geometry": {"coordinates":[39.62328,39.69678],"type":"Point"}
}