{
  "type": "Feature",
  "properties": {
    "gn:admin1_code":"10",
    "gn:asciiname":"Deliler",
    "gn:country_code":"TR",
    "gn:dem":309,
    "gn:feature_class":"P",
    "gn:feature_code":"PPL",
    "gn:name":"Deliler",
    "gn:population":0,
    "gn:timezone":"Europe/Istanbul",
    "iso:country":"TR",
    "wof:name":"Deliler",
    "wof:placetype":"locality"
},
  "geometry": {"coordinates":[27.51667,39.85],"type":"Point"}
}