{
  "type": "Feature",
  "properties": {
    "gn:admin1_code":"45",
    "gn:asciiname":"Sehitlioglu",
    "gn:country_code":"TR",
    "gn:dem":416,
    "gn:feature_class":"P",
    "gn:feature_code":"PPL",
    "gn:name":"\u015eehitlio\u011flu",
    "gn:population":0,
    "gn:timezone":"Europe/Istanbul",
    "iso:country":"TR",
    "name:tur_x_preferred":[
        "\u015eehitlio\u011flu"
    ],
    "wof:name":"Sehitlioglu",
    "wof:placetype":"locality"
},
  "geometry": {"coordinates":[28.75602,38.6491],"type":"Point"}
}