{
  "type": "Feature",
  "properties": {
    "gn:country":"TR",
    "gn:fcode":"PPLA2",
    "gn:pop":0,
    "iso:country":"TR",
    "name:eng_x_preferred":[
        "Kaymaz"
    ],
    "name:nld_x_preferred":[
        "Kaymaz"
    ],
    "name:tur_x_preferred":[
        "Kaymaz"
    ],
    "name:vie_x_preferred":[
        "Kaymaz"
    ],
    "qs:name":"Kaymaz",
    "qs:photos_9r":0,
    "qs:photos_sr":0,
    "qs:pop_sr":"0",
    "wd:wordcount":188,
    "wof:name":"Kaymaz",
    "wof:placetype":"locality",
    "wof:population":0
},
  "geometry": {"coordinates":[31.17972,39.51667],"type":"Point"}
}