{
  "type": "Feature",
  "properties": {
    "gn:country":"TR",
    "gn:fcode":"PPLA2",
    "gn:population":0,
    "iso:country":"TR",
    "name:ara_x_preferred":[
        "\u0642\u064a\u0645\u0627\u0632"
    ],
    "name:ceb_x_preferred":[
        "Kaymaz"
    ],
    "name:che_x_preferred":[
        "\u041a\u0430\u0439\u043c\u0430\u0437"
    ],
    "name:eng_x_preferred":[
        "Kaymaz"
    ],
    "name:nld_x_preferred":[
        "Kaymaz"
    ],
    "name:tat_x_preferred":[
        "\u041a\u0430\u0439\u043c\u0430\u0437"
    ],
    "name:tur_x_preferred":[
        "Kaymaz"
    ],
    "name:vie_x_preferred":[
        "Kaymaz"
    ],
    "qs:name":"Kaymaz",
    "qs:photos_9r":0,
    "qs:photos_sr":0,
    "qs:pop_sr":"0",
    "wd:wordcount":188,
    "wof:name":"Kaymaz",
    "wof:placetype":"locality",
    "wof:population":0
},
  "geometry": {"coordinates":[31.17972,39.51667],"type":"Point"}
}