{
  "type": "Feature",
  "properties": {
    "gn:admin1_code":"69.0",
    "gn:asciiname":"Kurtoglu",
    "gn:country_code":"TR",
    "gn:dem":1686,
    "gn:feature_class":"P",
    "gn:feature_code":"PPL",
    "gn:name":"Kurto\u011flu",
    "gn:population":0,
    "gn:timezone":"Europe/Istanbul",
    "iso:country":"TR",
    "name:tur_x_preferred":[
        "Kurto\u011flu"
    ],
    "wof:name":"Kurtoglu",
    "wof:placetype":"locality"
},
  "geometry": {"coordinates":[39.39744,40.30516],"type":"Point"}
}