{
  "type": "Feature",
  "properties": {
    "gn:admin1_code":"52.0",
    "gn:asciiname":"Teynelli",
    "gn:country_code":"TR",
    "gn:dem":190,
    "gn:feature_class":"P",
    "gn:feature_code":"PPL",
    "gn:name":"Teynelli",
    "gn:population":0,
    "gn:timezone":"Europe/Istanbul",
    "iso:country":"TR",
    "name:tur_x_preferred":[
        "Teynelli"
    ],
    "wof:name":"Teynelli",
    "wof:placetype":"locality"
},
  "geometry": {"coordinates":[37.82336,40.93516],"type":"Point"}
}