{
  "type": "Feature",
  "properties": {
    "gn:admin1_code":"43",
    "gn:asciiname":"Kiziluzum",
    "gn:country_code":"TR",
    "gn:dem":774,
    "gn:feature_class":"P",
    "gn:feature_code":"PPL",
    "gn:name":"K\u0131z\u0131l\u00fcz\u00fcm",
    "gn:population":0,
    "gn:timezone":"Europe/Istanbul",
    "iso:country":"TR",
    "wof:name":"Kiziluzum",
    "wof:placetype":"locality"
},
  "geometry": {"coordinates":[29.245,38.89944000000001],"type":"Point"}
}