{
  "type": "Feature",
  "properties": {
    "gn:country":"TR",
    "gn:fcode":"ADM3",
    "gn:population":0,
    "iso:country":"TR",
    "name:afr_x_preferred":[
        "Karak\u00f6y"
    ],
    "name:ara_x_preferred":[
        "\u0642\u0631\u0647 \u0643\u0648\u064a"
    ],
    "name:cat_x_preferred":[
        "Karak\u00f6y"
    ],
    "name:eng_x_preferred":[
        "Karak\u00f6y"
    ],
    "name:fra_x_preferred":[
        "Karak\u00f6y"
    ],
    "name:hun_x_preferred":[
        "Karak\u00f6y"
    ],
    "name:hye_x_preferred":[
        "\u0554\u0561\u0580\u0561\u0584\u0578\u0575"
    ],
    "name:ind_x_preferred":[
        "Karak\u00f6y"
    ],
    "name:ita_x_preferred":[
        "Karak\u00f6y"
    ],
    "name:jpn_x_preferred":[
        "\u30ab\u30e9\u30ad\u30e7\u30a4"
    ],
    "name:mkd_x_preferred":[
        "\u041a\u0430\u0440\u0430\u045c\u043e\u0458"
    ],
    "name:nld_x_preferred":[
        "Karak\u00f6y"
    ],
    "name:por_x_preferred":[
        "Karak\u00f6y"
    ],
    "name:rus_x_preferred":[
        "\u041a\u0430\u0440\u0430\u043a\u0451\u0439"
    ],
    "name:spa_x_preferred":[
        "Karak\u00f6y"
    ],
    "name:tur_x_preferred":[
        "Karak\u00f6y"
    ],
    "name:vie_x_preferred":[
        "S\u0131n\u0131rg\u00f6ren"
    ],
    "name:zho_x_preferred":[
        "\u5361\u62c9\u67ef\u4f0a"
    ],
    "qs:name":"Karak\u00f6y",
    "qs:photos_9r":0,
    "qs:photos_sr":0,
    "qs:pop_sr":"0",
    "wd:wordcount":1332,
    "wof:name":"Karak\u00f6y",
    "wof:placetype":"localadmin",
    "wof:population":0
},
  "geometry": {"coordinates":[28.98,41.0256],"type":"Point"}
}