{
  "type": "Feature",
  "properties": {
    "gn:country":"TR",
    "gn:fcode":"ADM3",
    "gn:pop":0,
    "iso:country":"TR",
    "name:jpn_x_preferred":[
        "\u30ab\u30e9\u30ad\u30e7\u30a4"
    ],
    "name:mkd_x_preferred":[
        "\u041a\u0430\u0440\u0430\u045c\u043e\u0458"
    ],
    "name:zho_x_preferred":[
        "\u5361\u62c9\u67ef\u4f0a"
    ],
    "qs:name":"Karak\u00f6y",
    "qs:photos_9r":0,
    "qs:photos_sr":0,
    "qs:pop_sr":"0",
    "wd:wordcount":1332,
    "wof:name":"Karak\u00f6y",
    "wof:placetype":"localadmin",
    "wof:population":0
},
  "geometry": {"coordinates":[28.98,41.0256],"type":"Point"}
}