{
  "type": "Feature",
  "properties": {
    "gn:admin1_code":"62",
    "gn:asciiname":"Kopuzlar",
    "gn:country_code":"TR",
    "gn:dem":1025,
    "gn:feature_class":"P",
    "gn:feature_code":"PPL",
    "gn:name":"Kopuzlar",
    "gn:population":0,
    "gn:timezone":"Europe/Istanbul",
    "iso:country":"TR",
    "name:und_x_variant":[
        "Kamo\u011flu",
        "Kopuzlar"
    ],
    "wof:name":"Kopuzlar",
    "wof:placetype":"locality"
},
  "geometry": {"coordinates":[39.48988,38.99934],"type":"Point"}
}