{
  "type": "Feature",
  "properties": {
    "gn:admin1_code":"55.0",
    "gn:asciiname":"Asagikizoglu",
    "gn:country_code":"TR",
    "gn:dem":880,
    "gn:feature_class":"P",
    "gn:feature_code":"PPL",
    "gn:name":"A\u015fa\u011f\u0131k\u0131zo\u011flu",
    "gn:population":0,
    "gn:timezone":"Europe/Istanbul",
    "iso:country":"TR",
    "wof:name":"Asagikizoglu",
    "wof:placetype":"locality"
},
  "geometry": {"coordinates":[35.96896,40.90943],"type":"Point"}
}