{
  "type": "Feature",
  "properties": {
    "gn:admin1_code":"31.0",
    "gn:asciiname":"Karsanbey",
    "gn:country_code":"TR",
    "gn:dem":509,
    "gn:feature_class":"P",
    "gn:feature_code":"PPL",
    "gn:name":"Karsanbey",
    "gn:population":0,
    "gn:timezone":"Europe/Istanbul",
    "iso:country":"TR",
    "wof:name":"Karsanbey",
    "wof:placetype":"locality"
},
  "geometry": {"coordinates":[36.18583,36.02361],"type":"Point"}
}