{
  "type": "Feature",
  "properties": {
    "gn:admin1_code":"31",
    "gn:asciiname":"Com",
    "gn:country_code":"TR",
    "gn:dem":377,
    "gn:feature_class":"P",
    "gn:feature_code":"PPL",
    "gn:name":"Com",
    "gn:population":0,
    "gn:timezone":"Europe/Istanbul",
    "iso:country":"TR",
    "name:und_x_variant":[
        "Cam",
        "Cam K\u00f6y",
        "Com",
        "D\u00fczg\u00f6ren"
    ],
    "wof:name":"Com",
    "wof:placetype":"locality"
},
  "geometry": {"coordinates":[36.24664,36.0716],"type":"Point"}
}