{
  "type": "Feature",
  "properties": {
    "gn:admin1_code":"07",
    "gn:asciiname":"Ceceler",
    "gn:country_code":"TR",
    "gn:dem":1387,
    "gn:feature_class":"P",
    "gn:feature_code":"PPL",
    "gn:name":"Ceceler",
    "gn:population":0,
    "gn:timezone":"Europe/Istanbul",
    "iso:country":"TR",
    "wof:name":"Ceceler",
    "wof:placetype":"locality"
},
  "geometry": {"coordinates":[31.83133,37.19581],"type":"Point"}
}