{
  "type": "Feature",
  "properties": {
    "gn:admin1_code":"48",
    "gn:asciiname":"Inisdibi",
    "gn:country_code":"TR",
    "gn:dem":277,
    "gn:feature_class":"P",
    "gn:feature_code":"PPL",
    "gn:name":"\u0130nisdibi",
    "gn:population":0,
    "gn:timezone":"Europe/Istanbul",
    "iso:country":"TR",
    "name:tur_x_preferred":[
        "\u0130nisdibi"
    ],
    "wof:name":"Inisdibi",
    "wof:placetype":"locality"
},
  "geometry": {"coordinates":[28.96263,36.88293],"type":"Point"}
}