{
  "type": "Feature",
  "properties": {
    "iso:country":"TR",
    "name:tur_x_preferred":[
        "\u00c7apa"
    ],
    "wof:name":"Capa",
    "wof:placetype":"neighbourhood"
},
  "geometry": {"coordinates":[28.927939133614,41.01157283834559],"type":"Point"}
}