{
  "type": "Feature",
  "properties": {
    "gn:admin1_code":"55.0",
    "gn:asciiname":"Idrisli",
    "gn:country_code":"TR",
    "gn:dem":699,
    "gn:feature_class":"P",
    "gn:feature_code":"PPL",
    "gn:name":"\u0130drisli",
    "gn:population":0,
    "gn:timezone":"Europe/Istanbul",
    "iso:country":"TR",
    "wof:name":"Idrisli",
    "wof:placetype":"locality"
},
  "geometry": {"coordinates":[35.99293,41.09686],"type":"Point"}
}