{
  "type": "Feature",
  "properties": {
    "gn:admin1_code":"8.0",
    "gn:asciiname":"Cala",
    "gn:country_code":"TR",
    "gn:dem":889,
    "gn:feature_class":"P",
    "gn:feature_code":"PPL",
    "gn:name":"Cala",
    "gn:population":0,
    "gn:timezone":"Europe/Istanbul",
    "iso:country":"TR",
    "name:und_x_variant":[
        "Cala Mahallesi",
        "Cala"
    ],
    "wof:name":"Cala",
    "wof:placetype":"locality"
},
  "geometry": {"coordinates":[41.38894000000001,40.71743],"type":"Point"}
}