{
  "type": "Feature",
  "properties": {
    "gn:admin1_code":"81",
    "gn:asciiname":"Turuclu",
    "gn:country_code":"TR",
    "gn:dem":155,
    "gn:feature_class":"P",
    "gn:feature_code":"PPL",
    "gn:name":"Turu\u00e7lu",
    "gn:population":0,
    "gn:timezone":"Europe/Istanbul",
    "iso:country":"TR",
    "name:und_x_variant":[
        "Toru\u00e7lu",
        "Turu\u00e7lu"
    ],
    "wof:name":"Turuclu",
    "wof:placetype":"locality"
},
  "geometry": {"coordinates":[35.73217,37.43939],"type":"Point"}
}