{
  "type": "Feature",
  "properties": {
    "gn:admin1_code":"17",
    "gn:asciiname":"Tutuler",
    "gn:country_code":"TR",
    "gn:dem":181,
    "gn:feature_class":"P",
    "gn:feature_code":"PPL",
    "gn:name":"T\u00fct\u00fcler",
    "gn:population":0,
    "gn:timezone":"Europe/Istanbul",
    "iso:country":"TR",
    "name:tur_x_preferred":[
        "T\u00fct\u00fcler"
    ],
    "wof:name":"Tutuler",
    "wof:placetype":"locality"
},
  "geometry": {"coordinates":[26.66329,39.83819],"type":"Point"}
}