{
  "type": "Feature",
  "properties": {
    "gn:admin1_code":"32",
    "gn:asciiname":"Copurlu",
    "gn:country_code":"TR",
    "gn:dem":213,
    "gn:feature_class":"P",
    "gn:feature_code":"PPL",
    "gn:name":"\u00c7opurlu",
    "gn:population":0,
    "gn:timezone":"Europe/Istanbul",
    "iso:country":"TR",
    "name:ceb_x_preferred":[
        "\u00c7opurlu"
    ],
    "name:msa_x_preferred":[
        "\u00c7opurlu"
    ],
    "name:und_x_variant":[
        "\u00c7opurlu"
    ],
    "name:vie_x_preferred":[
        "\u00c7opurlu"
    ],
    "wof:name":"Copurlu",
    "wof:placetype":"locality"
},
  "geometry": {"coordinates":[34.56971,36.85799],"type":"Point"}
}