{
  "type": "Feature",
  "properties": {
    "gn:admin1_code":"74",
    "gn:asciiname":"Benekli",
    "gn:country_code":"TR",
    "gn:dem":1646,
    "gn:feature_class":"P",
    "gn:feature_code":"PPL",
    "gn:name":"Benekli",
    "gn:population":0,
    "gn:timezone":"Europe/Istanbul",
    "iso:country":"TR",
    "name:und_x_variant":[
        "Dergin"
    ],
    "wof:name":"Benekli",
    "wof:placetype":"locality"
},
  "geometry": {"coordinates":[42.14554,38.12112],"type":"Point"}
}