{
  "type": "Feature",
  "properties": {
    "gn:admin1_code":"25.0",
    "gn:asciiname":"Arpacayir",
    "gn:country_code":"TR",
    "gn:dem":1984,
    "gn:feature_class":"P",
    "gn:feature_code":"PPL",
    "gn:name":"Arpa\u00e7ay\u0131r",
    "gn:population":0,
    "gn:timezone":"Europe/Istanbul",
    "iso:country":"TR",
    "name:und_x_variant":[
        "Arap\u00e7ay\u0131r",
        "Arpa\u00e7ay\u0131r"
    ],
    "wof:name":"Arpacayir",
    "wof:placetype":"locality"
},
  "geometry": {"coordinates":[42.42855,40.01974000000001],"type":"Point"}
}