{
  "type": "Feature",
  "properties": {
    "gn:admin1_code":"21",
    "gn:asciiname":"Kozikan",
    "gn:cc2":"TR",
    "gn:country_code":"TR",
    "gn:dem":898,
    "gn:feature_class":"P",
    "gn:feature_code":"PPL",
    "gn:name":"Kozik\u00e2n",
    "gn:population":0,
    "gn:timezone":"Europe/Istanbul",
    "iso:country":"TR",
    "name:und_x_variant":[
        "Kozek\u00e2n",
        "Kozik\u00e2n"
    ],
    "wof:name":"Kozikan",
    "wof:placetype":"locality"
},
  "geometry": {"coordinates":[40.66667,38.36667],"type":"Point"}
}