{
  "type": "Feature",
  "properties": {
    "gn:admin1_code":"65",
    "gn:asciiname":"Tinazli",
    "gn:country_code":"TR",
    "gn:dem":1969,
    "gn:feature_class":"P",
    "gn:feature_code":"PPL",
    "gn:name":"T\u0131nazl\u0131",
    "gn:population":0,
    "gn:timezone":"Europe/Istanbul",
    "iso:country":"TR",
    "name:und_x_variant":[
        "\u015eahmaniz",
        "\u015eahmanis",
        "T\u0131nazl\u0131"
    ],
    "wof:name":"Tinazli",
    "wof:placetype":"locality"
},
  "geometry": {"coordinates":[44.13639000000001,38.02417],"type":"Point"}
}