{
  "type": "Feature",
  "properties": {
    "gn:admin1_code":"16",
    "gn:asciiname":"Niluefer",
    "gn:country_code":"TR",
    "gn:dem":69,
    "gn:feature_class":"P",
    "gn:feature_code":"PPLA2",
    "gn:name":"Nil\u00fcfer",
    "gn:population":0,
    "gn:timezone":"Europe/Istanbul",
    "iso:country":"TR",
    "name:eng_x_preferred":[
        "Nilufer"
    ],
    "name:tur_x_preferred":[
        "Nil\u00fcfer"
    ],
    "wof:name":"Niluefer",
    "wof:placetype":"locality"
},
  "geometry": {"coordinates":[28.91567,40.21401],"type":"Point"}
}