{
  "type": "Feature",
  "properties": {
    "gn:admin1_code":"44",
    "gn:asciiname":"Ikinciler",
    "gn:country_code":"TR",
    "gn:dem":1327,
    "gn:feature_class":"P",
    "gn:feature_code":"PPL",
    "gn:name":"\u0130kinciler",
    "gn:population":0,
    "gn:timezone":"Europe/Istanbul",
    "iso:country":"TR",
    "name:und_x_variant":[
        "Geranl\u0131",
        "\u0130kinciler"
    ],
    "wof:name":"Ikinciler",
    "wof:placetype":"locality"
},
  "geometry": {"coordinates":[37.92662,38.29985],"type":"Point"}
}