{
  "type": "Feature",
  "properties": {
    "gn:admin1_code":"50",
    "gn:asciiname":"Karacausagi",
    "gn:country_code":"TR",
    "gn:dem":1448,
    "gn:feature_class":"P",
    "gn:feature_code":"PPL",
    "gn:name":"Karacau\u015fa\u011f\u0131",
    "gn:population":0,
    "gn:timezone":"Europe/Istanbul",
    "iso:country":"TR",
    "wof:name":"Karacausagi",
    "wof:placetype":"locality"
},
  "geometry": {"coordinates":[34.92485,38.91166],"type":"Point"}
}