{
  "type": "Feature",
  "properties": {
    "gn:admin1_code":"4.0",
    "gn:asciiname":"Ortadamla",
    "gn:country_code":"TR",
    "gn:dem":1814,
    "gn:feature_class":"P",
    "gn:feature_code":"PPL",
    "gn:name":"Ortadamla",
    "gn:population":0,
    "gn:timezone":"Europe/Istanbul",
    "iso:country":"TR",
    "name:tur_x_preferred":[
        "Ortadamla"
    ],
    "wof:name":"Ortadamla",
    "wof:placetype":"locality"
},
  "geometry": {"coordinates":[43.04203,39.20274000000001],"type":"Point"}
}