{
  "type": "Feature",
  "properties": {
    "gn:admin1_code":"43",
    "gn:asciiname":"Bercin",
    "gn:country_code":"TR",
    "gn:dem":918,
    "gn:feature_class":"P",
    "gn:feature_code":"PPL",
    "gn:name":"Ber\u00e7in",
    "gn:population":0,
    "gn:timezone":"Europe/Istanbul",
    "iso:country":"TR",
    "name:und_x_variant":[
        "Per\u00e7in",
        "Ber\u00e7in"
    ],
    "wof:name":"Bercin",
    "wof:placetype":"locality"
},
  "geometry": {"coordinates":[29.57348,39.78933],"type":"Point"}
}