{
  "type": "Feature",
  "properties": {
    "gn:admin1_code":"09",
    "gn:asciiname":"Evciler",
    "gn:country_code":"TR",
    "gn:dem":73,
    "gn:feature_class":"P",
    "gn:feature_code":"PPL",
    "gn:name":"Evciler",
    "gn:population":0,
    "gn:timezone":"Europe/Istanbul",
    "iso:country":"TR",
    "name:tur_x_preferred":[
        "Evciler"
    ],
    "wof:name":"Evciler",
    "wof:placetype":"locality"
},
  "geometry": {"coordinates":[28.06171,37.59839],"type":"Point"}
}