{
  "type": "Feature",
  "properties": {
    "gn:admin1_code":"09",
    "gn:asciiname":"Evciler",
    "gn:country_code":"TR",
    "gn:dem":73,
    "gn:feature_class":"P",
    "gn:feature_code":"PPL",
    "gn:name":"Evciler",
    "gn:population":0,
    "gn:timezone":"Europe/Istanbul",
    "iso:country":"TR",
    "name:ceb_x_preferred":[
        "Evciler \u0130l\u00e7esi"
    ],
    "name:deu_x_preferred":[
        "Evciler"
    ],
    "name:diq_x_preferred":[
        "Evciler"
    ],
    "name:fra_x_preferred":[
        "Evciler"
    ],
    "name:hun_x_preferred":[
        "Evciler"
    ],
    "name:mrj_x_preferred":[
        "\u042d\u0432\u0434\u0436\u0438\u043b\u0435\u0440"
    ],
    "name:msa_x_preferred":[
        "Evciler"
    ],
    "name:nor_x_preferred":[
        "Evciler"
    ],
    "name:pnb_x_preferred":[
        "\u0636\u0644\u0639 \u0627\u0648\u0648\u062c\u0644\u0631"
    ],
    "name:ron_x_preferred":[
        "Evciler"
    ],
    "name:swa_x_preferred":[
        "Evciler"
    ],
    "name:tur_x_preferred":[
        "Evciler"
    ],
    "name:urd_x_preferred":[
        "\u0639\u0648\u062c\u06cc\u0644\u0631"
    ],
    "name:vie_x_preferred":[
        "Evciler"
    ],
    "wof:name":"Evciler",
    "wof:placetype":"locality"
},
  "geometry": {"coordinates":[28.06171,37.59839],"type":"Point"}
}