{
  "type": "Feature",
  "properties": {
    "gn:admin1_code":"66",
    "gn:asciiname":"Musalikalesi",
    "gn:country_code":"TR",
    "gn:dem":1113,
    "gn:feature_class":"P",
    "gn:feature_code":"PPL",
    "gn:name":"Mu\u015falikalesi",
    "gn:population":0,
    "gn:timezone":"Europe/Istanbul",
    "iso:country":"TR",
    "name:tur_x_preferred":[
        "Mu\u015falikalesi"
    ],
    "name:und_x_variant":[
        "Mu\u015falikalesi K\u00f6y\u00fc",
        "Mu\u015fal\u0131kalesi",
        "\u00c7al\u0131\u015fkan"
    ],
    "wof:name":"Musalikalesi",
    "wof:placetype":"locality"
},
  "geometry": {"coordinates":[35.83722,39.74028],"type":"Point"}
}