{
  "type": "Feature",
  "properties": {
    "gn:admin1_code":"91",
    "gn:asciiname":"Oksuzlu",
    "gn:country_code":"TR",
    "gn:dem":39,
    "gn:feature_class":"P",
    "gn:feature_code":"PPL",
    "gn:name":"\u00d6ks\u00fczl\u00fc",
    "gn:population":0,
    "gn:timezone":"Europe/Istanbul",
    "iso:country":"TR",
    "wof:name":"Oksuzlu",
    "wof:placetype":"locality"
},
  "geometry": {"coordinates":[35.9704,37.32076],"type":"Point"}
}