{
  "type": "Feature",
  "properties": {
    "gn:admin1_code":"21",
    "gn:asciiname":"Kaynakkoy",
    "gn:country_code":"TR",
    "gn:dem":1023,
    "gn:feature_class":"P",
    "gn:feature_code":"PPL",
    "gn:name":"Kaynakk\u00f6y",
    "gn:population":0,
    "gn:timezone":"Europe/Istanbul",
    "iso:country":"TR",
    "name:tur_x_preferred":[
        "Kaynakk\u00f6y"
    ],
    "name:und_x_variant":[
        "Kaynak"
    ],
    "wof:name":"Kaynakkoy",
    "wof:placetype":"locality"
},
  "geometry": {"coordinates":[39.18049,38.27497],"type":"Point"}
}