{
  "type": "Feature",
  "properties": {
    "gn:admin1_code":"31.0",
    "gn:asciiname":"Golbasi",
    "gn:country_code":"TR",
    "gn:dem":86,
    "gn:feature_class":"P",
    "gn:feature_code":"PPL",
    "gn:name":"G\u00f6lba\u015f\u0131",
    "gn:population":0,
    "gn:timezone":"Europe/Istanbul",
    "iso:country":"TR",
    "name:rus_x_preferred":[
        "G\u00ebl\u2019bashi"
    ],
    "name:und_x_variant":[
        "G\u00f6lba\u015f\u0131 K\u00f6y\u00fc",
        "G\u00f6lba\u015f\u0131"
    ],
    "wof:name":"Golbasi",
    "wof:placetype":"locality"
},
  "geometry": {"coordinates":[36.47449,36.50238],"type":"Point"}
}