{
  "type": "Feature",
  "properties": {
    "iso:country":"TU",
    "name:ceb_x_preferred":[
        "Esfez\u0101r"
    ],
    "name:fas_x_preferred":[
        "\u0627\u0633\u0641\u0632\u0627\u0631"
    ],
    "name:por_x_preferred":[
        "Esfezar"
    ],
    "name:swe_x_preferred":[
        "Esfez\u0101r"
    ],
    "name:tur_x_preferred":[
        "\u0130stanbul K\u00fclt\u00fcr \u00dcniversitesi"
    ],
    "name:und_x_colloquial":[
        "Kultur"
    ],
    "name:und_x_variant":[
        "K\u00fclt\u00fcr"
    ],
    "qs:gn_adm0_cc":"TR",
    "qs:gn_fcode":"PPLX",
    "qs:gn_local":323777,
    "qs:gn_namadm1":"07",
    "qs:gn_name":"K\u00fclt\u00fcr",
    "qs:local_max":1873,
    "qs:local_sum":6541,
    "qs:localhoods":23,
    "qs:name":"K\u00fclt\u00fcr",
    "qs:name_adm0":"Turkey",
    "qs:name_adm1":"Antalya",
    "qs:name_adm2":"Merkez",
    "qs:name_local":"Antalya",
    "qs:photo_max":38,
    "qs:photo_sum":123,
    "qs:placetype":"Suburb",
    "qs:quad_count":13,
    "qs:woe_adm0":23424969,
    "qs:woe_adm1":2347264,
    "qs:woe_adm2":29390627,
    "qs:woe_lau":0,
    "qs:woe_local":2343733,
    "qs:woe_ver":"7.10.0",
    "wof:lang":[
        "unk"
    ],
    "wof:name":"K\u00fclt\u00fcr",
    "wof:placetype":"neighbourhood"
},
  "geometry": {"coordinates":[30.663248,36.902172],"type":"Point"}
}