{
  "type": "Feature",
  "properties": {
    "gn:admin1_code":"65",
    "gn:asciiname":"Pirgarip",
    "gn:country_code":"TR",
    "gn:dem":1966,
    "gn:feature_class":"P",
    "gn:feature_code":"PPL",
    "gn:name":"Pirgarip",
    "gn:population":0,
    "gn:timezone":"Europe/Istanbul",
    "iso:country":"TR",
    "name:tur_x_preferred":[
        "Pirgarip"
    ],
    "wof:name":"Pirgarip",
    "wof:placetype":"locality"
},
  "geometry": {"coordinates":[43.40738,38.76037],"type":"Point"}
}