{
  "type": "Feature",
  "properties": {
    "gn:admin1_code":"60.0",
    "gn:asciiname":"Ideli",
    "gn:country_code":"TR",
    "gn:dem":890,
    "gn:feature_class":"P",
    "gn:feature_code":"PPL",
    "gn:name":"\u0130deli",
    "gn:population":0,
    "gn:timezone":"Europe/Istanbul",
    "iso:country":"TR",
    "wof:name":"Ideli",
    "wof:placetype":"locality"
},
  "geometry": {"coordinates":[36.03333,40.41667],"type":"Point"}
}