{
  "type": "Feature",
  "properties": {
    "gn:admin1_code":"32.0",
    "gn:asciiname":"Tekeli",
    "gn:country_code":"TR",
    "gn:dem":11,
    "gn:feature_class":"P",
    "gn:feature_code":"PPL",
    "gn:name":"Tekeli",
    "gn:population":0,
    "gn:timezone":"Europe/Istanbul",
    "iso:country":"TR",
    "name:deu_x_preferred":[
        "Tekeli"
    ],
    "name:rus_x_preferred":[
        "\u0422\u0435\u043a\u0435\u043b\u0438"
    ],
    "name:tur_x_preferred":[
        "Tekeli"
    ],
    "name:und_x_variant":[
        "Aksaz",
        "Akyaka"
    ],
    "wof:name":"Tekeli",
    "wof:placetype":"locality"
},
  "geometry": {"coordinates":[33.13155,36.13692],"type":"Point"}
}