{
  "type": "Feature",
  "properties": {
    "gn:country":"TR",
    "gn:fcode":"PPL",
    "gn:pop":1140,
    "iso:country":"TR",
    "name:tur_x_preferred":[
        "Bozh\u00fcy\u00fck"
    ],
    "name:unk_x_variant":[
        "Teliba K\u00f6y\u00fc"
    ],
    "qs:name":"Taliban",
    "qs:photos_9r":0,
    "qs:photos_sr":0,
    "qs:pop_sr":"3",
    "wd:wordcount":21784,
    "wof:name":"Taliban",
    "wof:placetype":"locality",
    "wof:population":1140
},
  "geometry": {"coordinates":[41.41221,37.98125],"type":"Point"}
}