{
  "type": "Feature",
  "properties": {
    "gn:admin1_code":"13",
    "gn:asciiname":"Kushane",
    "gn:country_code":"TR",
    "gn:dem":2161,
    "gn:feature_class":"P",
    "gn:feature_code":"PPL",
    "gn:name":"Ku\u015fhane",
    "gn:population":0,
    "gn:timezone":"Europe/Istanbul",
    "iso:country":"TR",
    "name:und_x_variant":[
        "Ku\u015fane",
        "Ku\u015fhane"
    ],
    "wof:name":"Kushane",
    "wof:placetype":"locality"
},
  "geometry": {"coordinates":[42.59825,38.83431],"type":"Point"}
}