{
  "type": "Feature",
  "properties": {
    "gn:admin1_code":"58.0",
    "gn:asciiname":"Absal",
    "gn:country_code":"TR",
    "gn:dem":1684,
    "gn:feature_class":"P",
    "gn:feature_code":"PPL",
    "gn:name":"Absal",
    "gn:population":0,
    "gn:timezone":"Europe/Istanbul",
    "iso:country":"TR",
    "wof:name":"Absal",
    "wof:placetype":"locality"
},
  "geometry": {"coordinates":[37.96667,39.53333],"type":"Point"}
}