{
  "type": "Feature",
  "properties": {
    "gn:admin1_code":"55.0",
    "gn:asciiname":"Boyacili",
    "gn:country_code":"TR",
    "gn:dem":28,
    "gn:feature_class":"P",
    "gn:feature_code":"PPL",
    "gn:name":"Boyac\u0131l\u0131",
    "gn:population":0,
    "gn:timezone":"Europe/Istanbul",
    "iso:country":"TR",
    "wof:name":"Boyacili",
    "wof:placetype":"locality"
},
  "geometry": {"coordinates":[36.7088,41.11696],"type":"Point"}
}