{
  "type": "Feature",
  "properties": {
    "gn:admin1_code":"63.0",
    "gn:asciiname":"Kizilpinar",
    "gn:country_code":"TR",
    "gn:dem":562,
    "gn:feature_class":"P",
    "gn:feature_code":"PPL",
    "gn:name":"K\u0131z\u0131lp\u0131nar",
    "gn:population":0,
    "gn:timezone":"Europe/Istanbul",
    "iso:country":"TR",
    "name:tur_x_preferred":[
        "K\u0131z\u0131lp\u0131nar"
    ],
    "name:und_x_variant":[
        "Kyzylpynarkey"
    ],
    "wof:name":"Kizilpinar",
    "wof:placetype":"locality"
},
  "geometry": {"coordinates":[38.98665,37.26784],"type":"Point"}
}