{
  "type": "Feature",
  "properties": {
    "gn:admin1_code":"63",
    "gn:asciiname":"Kasaba",
    "gn:country_code":"TR",
    "gn:dem":764,
    "gn:feature_class":"P",
    "gn:feature_code":"PPL",
    "gn:name":"Kasaba",
    "gn:population":0,
    "gn:timezone":"Europe/Istanbul",
    "iso:country":"TR",
    "name:tur_x_preferred":[
        "Cerik"
    ],
    "name:und_x_variant":[
        "Kasab\u0131",
        "Kasaba",
        "G\u00f6nc\u00fck"
    ],
    "wof:name":"Kasaba",
    "wof:placetype":"locality"
},
  "geometry": {"coordinates":[39.90954,37.37441],"type":"Point"}
}