{
  "type": "Feature",
  "properties": {
    "gn:admin1_code":"45",
    "gn:asciiname":"Pelitalan",
    "gn:country_code":"TR",
    "gn:dem":473,
    "gn:feature_class":"P",
    "gn:feature_code":"PPL",
    "gn:name":"Pelitalan",
    "gn:population":0,
    "gn:timezone":"Europe/Istanbul",
    "iso:country":"TR",
    "name:tur_x_preferred":[
        "Pelitalan"
    ],
    "wof:name":"Pelitalan",
    "wof:placetype":"locality"
},
  "geometry": {"coordinates":[27.32924,38.85238],"type":"Point"}
}