{
  "type": "Feature",
  "properties": {
    "gn:admin1_code":"24",
    "gn:asciiname":"Yazikoey",
    "gn:country_code":"TR",
    "gn:dem":1563,
    "gn:feature_class":"P",
    "gn:feature_code":"PPL",
    "gn:name":"Yaz\u0131k\u00f6y",
    "gn:population":0,
    "gn:timezone":"Europe/Istanbul",
    "iso:country":"TR",
    "name:und_x_variant":[
        "Yaz\u0131k\u00f6y\u00fc",
        "Yaz\u0131",
        "Yaz\u0131k\u00f6y"
    ],
    "wof:name":"Yazikoey",
    "wof:placetype":"locality"
},
  "geometry": {"coordinates":[38.61493,39.92464],"type":"Point"}
}