{
  "type": "Feature",
  "properties": {
    "gn:admin1_code":"58",
    "gn:asciiname":"Koyunkaya",
    "gn:country_code":"TR",
    "gn:dem":1788,
    "gn:feature_class":"P",
    "gn:feature_code":"PPL",
    "gn:name":"Koyunkaya",
    "gn:population":0,
    "gn:timezone":"Europe/Istanbul",
    "iso:country":"TR",
    "name:und_x_variant":[
        "Koyunkaya K\u00f6y\u00fc",
        "Koyunkaya"
    ],
    "wof:name":"Koyunkaya",
    "wof:placetype":"locality"
},
  "geometry": {"coordinates":[38.2975,39.83893],"type":"Point"}
}