{
  "type": "Feature",
  "properties": {
    "gn:admin1_code":"32",
    "gn:asciiname":"Genzin",
    "gn:country_code":"TR",
    "gn:dem":1070,
    "gn:feature_class":"P",
    "gn:feature_code":"PPL",
    "gn:name":"Genzin",
    "gn:population":0,
    "gn:timezone":"Europe/Istanbul",
    "iso:country":"TR",
    "name:tur_x_preferred":[
        "Ard\u0131\u00e7l\u0131"
    ],
    "name:tur_x_variant":[
        "Genzin"
    ],
    "wof:name":"Genzin",
    "wof:placetype":"locality"
},
  "geometry": {"coordinates":[34.74488,37.23434],"type":"Point"}
}