{
  "type": "Feature",
  "properties": {
    "gn:admin1_code":"37.0",
    "gn:asciiname":"Derekaraagac",
    "gn:country_code":"TR",
    "gn:dem":1211,
    "gn:feature_class":"P",
    "gn:feature_code":"PPL",
    "gn:name":"Derekaraa\u011fa\u00e7",
    "gn:population":0,
    "gn:timezone":"Europe/Istanbul",
    "iso:country":"TR",
    "wof:name":"Derekaraagac",
    "wof:placetype":"locality"
},
  "geometry": {"coordinates":[34.20737,41.34871],"type":"Point"}
}