{
  "type": "Feature",
  "properties": {
    "iso:country":"TR",
    "name:und_x_colloquial":[
        "Cay Yolu"
    ],
    "name:und_x_variant":[
        "\u00c7ay Yolu"
    ],
    "qs:gn_adm0_cc":"TR",
    "qs:gn_local":323786,
    "qs:gn_nam_loc":"Ankara",
    "qs:gn_namadm1":"68",
    "qs:local_max":3835,
    "qs:local_sum":10452,
    "qs:localhoods":37,
    "qs:name":"\u00c7ay Yolu",
    "qs:name_adm0":"Turkey",
    "qs:name_adm1":"Ankara",
    "qs:name_adm2":"Yenimahalle",
    "qs:name_local":"Ankara",
    "qs:photo_max":12,
    "qs:photo_sum":72,
    "qs:placetype":"Suburb",
    "qs:quad_count":22,
    "qs:woe_adm0":23424969,
    "qs:woe_adm1":2347263,
    "qs:woe_adm2":29390874,
    "qs:woe_lau":0,
    "qs:woe_local":2343732,
    "qs:woe_ver":"7.10.0",
    "wof:name":"\u00c7ay Yolu",
    "wof:placetype":"neighbourhood"
},
  "geometry": {"coordinates":[32.705002,39.897446],"type":"Point"}
}