{
  "type": "Feature",
  "properties": {
    "gn:admin1_code":"48",
    "gn:asciiname":"Madenler",
    "gn:country_code":"TR",
    "gn:dem":388,
    "gn:feature_class":"P",
    "gn:feature_code":"PPL",
    "gn:name":"Madenler",
    "gn:population":0,
    "gn:timezone":"Europe/Istanbul",
    "iso:country":"TR",
    "name:tur_x_preferred":[
        "Madenler"
    ],
    "wof:name":"Madenler",
    "wof:placetype":"locality"
},
  "geometry": {"coordinates":[28.1564,37.33704],"type":"Point"}
}