{
  "type": "Feature",
  "properties": {
    "gn:admin1_code":"09",
    "gn:asciiname":"Gelenbe",
    "gn:country_code":"TR",
    "gn:dem":213,
    "gn:feature_class":"P",
    "gn:feature_code":"PPL",
    "gn:name":"Gelenbe",
    "gn:population":0,
    "gn:timezone":"Europe/Istanbul",
    "iso:country":"TR",
    "name:tur_x_preferred":[
        "Gelenbe"
    ],
    "wof:name":"Gelenbe",
    "wof:placetype":"locality"
},
  "geometry": {"coordinates":[28.6835,37.95936],"type":"Point"}
}