{
  "type": "Feature",
  "properties": {
    "gn:admin1_code":"22.0",
    "gn:asciiname":"Sigircili",
    "gn:country_code":"TR",
    "gn:dem":35,
    "gn:feature_class":"P",
    "gn:feature_code":"PPL",
    "gn:name":"S\u0131\u011f\u0131rc\u0131l\u0131",
    "gn:population":0,
    "gn:timezone":"Europe/Istanbul",
    "iso:country":"TR",
    "wof:name":"Sigircili",
    "wof:placetype":"locality"
},
  "geometry": {"coordinates":[26.64878,41.41098],"type":"Point"}
}