{
  "type": "Feature",
  "properties": {
    "gn:admin1_code":"72",
    "gn:asciiname":"Bagarasi",
    "gn:country_code":"TR",
    "gn:dem":1125,
    "gn:feature_class":"P",
    "gn:feature_code":"PPL",
    "gn:name":"Ba\u011faras\u0131",
    "gn:population":0,
    "gn:timezone":"Europe/Istanbul",
    "iso:country":"TR",
    "name:tur_x_preferred":[
        "Ba\u011faras\u0131"
    ],
    "name:und_x_variant":[
        "Ba\u011flararas\u0131"
    ],
    "wof:name":"Bagarasi",
    "wof:placetype":"locality"
},
  "geometry": {"coordinates":[40.23464,37.41304],"type":"Point"}
}