{
  "type": "Feature",
  "properties": {
    "gn:admin1_code":"58",
    "gn:asciiname":"Huyukkoy",
    "gn:country_code":"TR",
    "gn:dem":1451,
    "gn:feature_class":"P",
    "gn:feature_code":"PPL",
    "gn:name":"H\u00fcy\u00fckk\u00f6y",
    "gn:population":0,
    "gn:timezone":"Europe/Istanbul",
    "iso:country":"TR",
    "name:tur_x_preferred":[
        "H\u00fcy\u00fckk\u00f6y"
    ],
    "name:und_x_variant":[
        "H\u00fcy\u00fck K\u00f6y\u00fc",
        "H\u00fcy\u00fck",
        "Eski H\u00fcy\u00fck"
    ],
    "wof:name":"Huyukkoy",
    "wof:placetype":"locality"
},
  "geometry": {"coordinates":[36.19056,39.42161],"type":"Point"}
}