{
  "type": "Feature",
  "properties": {
    "gn:admin1_code":"37.0",
    "gn:asciiname":"Alinoren",
    "gn:country_code":"TR",
    "gn:dem":1233,
    "gn:feature_class":"P",
    "gn:feature_code":"PPL",
    "gn:name":"Al\u0131n\u00f6ren",
    "gn:population":0,
    "gn:timezone":"Europe/Istanbul",
    "iso:country":"TR",
    "name:und_x_variant":[
        "Al\u0131nviren",
        "Al\u0131nveren",
        "Al\u0131n\u00f6ren"
    ],
    "wof:name":"Alinoren",
    "wof:placetype":"locality"
},
  "geometry": {"coordinates":[33.90961,41.81111],"type":"Point"}
}