{
  "type": "Feature",
  "properties": {
    "gn:admin1_code":"24",
    "gn:asciiname":"Enbiya",
    "gn:country_code":"TR",
    "gn:dem":1529,
    "gn:feature_class":"P",
    "gn:feature_code":"PPL",
    "gn:name":"Enbiya",
    "gn:population":0,
    "gn:timezone":"Europe/Istanbul",
    "iso:country":"TR",
    "name:tur_x_preferred":[
        "U\u011furk\u00f6y"
    ],
    "name:und_x_variant":[
        "U\u011fur"
    ],
    "wof:name":"Enbiya",
    "wof:placetype":"locality"
},
  "geometry": {"coordinates":[38.61116,39.65955],"type":"Point"}
}