{
  "type": "Feature",
  "properties": {
    "gn:admin1_code":"07",
    "gn:asciiname":"Bucakkisla",
    "gn:country_code":"TR",
    "gn:dem":966,
    "gn:feature_class":"P",
    "gn:feature_code":"PPL",
    "gn:name":"Bucakk\u0131\u015fla",
    "gn:population":0,
    "gn:timezone":"Europe/Istanbul",
    "iso:country":"TR",
    "wof:name":"Bucakkisla",
    "wof:placetype":"locality"
},
  "geometry": {"coordinates":[31.73943,37.04595],"type":"Point"}
}