{
  "type": "Feature",
  "properties": {
    "gn:admin1_code":"65.0",
    "gn:asciiname":"Yenicavus",
    "gn:country_code":"TR",
    "gn:dem":1884,
    "gn:feature_class":"P",
    "gn:feature_code":"PPL",
    "gn:name":"Yeni\u00e7avu\u015f",
    "gn:population":0,
    "gn:timezone":"Europe/Istanbul",
    "iso:country":"TR",
    "name:tur_x_preferred":[
        "Yeni\u00e7avu\u015f"
    ],
    "wof:name":"Yenicavus",
    "wof:placetype":"locality"
},
  "geometry": {"coordinates":[43.79372,38.66202],"type":"Point"}
}