{
  "type": "Feature",
  "properties": {
    "gn:admin1_code":"48",
    "gn:asciiname":"Tuzabat",
    "gn:country_code":"TR",
    "gn:dem":515,
    "gn:feature_class":"P",
    "gn:feature_code":"PPL",
    "gn:name":"Tuzabat",
    "gn:population":0,
    "gn:timezone":"Europe/Istanbul",
    "iso:country":"TR",
    "name:tur_x_preferred":[
        "Tuzabat"
    ],
    "name:tur_x_variant":[
        "Tuzova"
    ],
    "wof:name":"Tuzabat",
    "wof:placetype":"locality"
},
  "geometry": {"coordinates":[27.87743,37.2953],"type":"Point"}
}