{
  "type": "Feature",
  "properties": {
    "gn:admin1_code":"37.0",
    "gn:asciiname":"Sevincoren",
    "gn:country_code":"TR",
    "gn:dem":928,
    "gn:feature_class":"P",
    "gn:feature_code":"PPL",
    "gn:name":"Sevin\u00e7\u00f6ren",
    "gn:population":0,
    "gn:timezone":"Europe/Istanbul",
    "iso:country":"TR",
    "name:und_x_variant":[
        "Sevin\u00e7veren",
        "Sevin\u00e7\u00f6ren"
    ],
    "wof:name":"Sevincoren",
    "wof:placetype":"locality"
},
  "geometry": {"coordinates":[34.02115999999999,40.93451],"type":"Point"}
}