{
  "type": "Feature",
  "properties": {
    "gn:admin1_code":"54",
    "gn:asciiname":"Kurtbeyler",
    "gn:country_code":"TR",
    "gn:dem":25,
    "gn:feature_class":"P",
    "gn:feature_code":"PPL",
    "gn:name":"Kurtbeyler",
    "gn:population":0,
    "gn:timezone":"Europe/Istanbul",
    "iso:country":"TR",
    "name:tur_x_preferred":[
        "Kurtbeyler"
    ],
    "wof:name":"Kurtbeyler",
    "wof:placetype":"locality"
},
  "geometry": {"coordinates":[30.48305,40.81213],"type":"Point"}
}