{
  "type": "Feature",
  "properties": {
    "gn:admin1_code":"61",
    "gn:asciiname":"Gumusoren",
    "gn:country_code":"TR",
    "gn:dem":156,
    "gn:feature_class":"P",
    "gn:feature_code":"PPL",
    "gn:name":"G\u00fcm\u00fc\u015f\u00f6ren",
    "gn:population":0,
    "gn:timezone":"Europe/Istanbul",
    "iso:country":"TR",
    "name:tur_x_preferred":[
        "G\u00fcm\u00fc\u015f\u00f6ren"
    ],
    "wof:name":"Gumusoren",
    "wof:placetype":"locality"
},
  "geometry": {"coordinates":[40.40649000000001,40.92599000000001],"type":"Point"}
}