{
  "type": "Feature",
  "properties": {
    "gn:admin1_code":"07",
    "gn:asciiname":"Cavdar Yaylasi",
    "gn:country_code":"TR",
    "gn:dem":1214,
    "gn:feature_class":"P",
    "gn:feature_code":"PPL",
    "gn:name":"\u00c7avdar Yaylas\u0131",
    "gn:population":0,
    "gn:timezone":"Europe/Istanbul",
    "iso:country":"TR",
    "wof:name":"Cavdar Yaylasi",
    "wof:placetype":"locality"
},
  "geometry": {"coordinates":[29.51487,36.4526],"type":"Point"}
}