{
  "type": "Feature",
  "properties": {
    "gn:admin1_code":"38",
    "gn:asciiname":"Karadayi",
    "gn:country_code":"TR",
    "gn:dem":1444,
    "gn:feature_class":"P",
    "gn:feature_code":"PPL",
    "gn:name":"Karaday\u0131",
    "gn:population":0,
    "gn:timezone":"Europe/Istanbul",
    "iso:country":"TR",
    "wof:name":"Karadayi",
    "wof:placetype":"locality"
},
  "geometry": {"coordinates":[35.9342,38.6453],"type":"Point"}
}