{
  "type": "Feature",
  "properties": {
    "gn:admin1_code":"48",
    "gn:asciiname":"Belenkavak",
    "gn:country_code":"TR",
    "gn:dem":968,
    "gn:feature_class":"P",
    "gn:feature_code":"PPL",
    "gn:name":"Belenkavak",
    "gn:population":0,
    "gn:timezone":"Europe/Istanbul",
    "iso:country":"TR",
    "name:tur_x_preferred":[
        "Belenkavak"
    ],
    "wof:name":"Belenkavak",
    "wof:placetype":"locality"
},
  "geometry": {"coordinates":[29.17881,36.80362],"type":"Point"}
}