{
  "type": "Feature",
  "properties": {
    "gn:admin1_code":"02",
    "gn:asciiname":"Buyukbag",
    "gn:country_code":"TR",
    "gn:dem":684,
    "gn:feature_class":"P",
    "gn:feature_code":"PPL",
    "gn:name":"B\u00fcy\u00fckba\u011f",
    "gn:population":0,
    "gn:timezone":"Europe/Istanbul",
    "iso:country":"TR",
    "name:tur_x_preferred":[
        "B\u00fcy\u00fckba\u011f"
    ],
    "wof:name":"Buyukbag",
    "wof:placetype":"locality"
},
  "geometry": {"coordinates":[38.71183,37.81833],"type":"Point"}
}