{
  "type": "Feature",
  "properties": {
    "gn:admin1_code":"46",
    "gn:asciiname":"Akcali",
    "gn:country_code":"TR",
    "gn:dem":565,
    "gn:feature_class":"P",
    "gn:feature_code":"PPL",
    "gn:name":"Ak\u00e7al\u0131",
    "gn:population":0,
    "gn:timezone":"Europe/Istanbul",
    "iso:country":"TR",
    "name:tur_x_preferred":[
        "Ak\u00e7al\u0131"
    ],
    "name:und_x_variant":[
        "Akal\u0131",
        "Sar\u0131lar"
    ],
    "wof:name":"Akcali",
    "wof:placetype":"locality"
},
  "geometry": {"coordinates":[36.79594,37.32448],"type":"Point"}
}