{
  "type": "Feature",
  "properties": {
    "gn:admin1_code":"25.0",
    "gn:asciiname":"Ahpini",
    "gn:cc2":"TR",
    "gn:country_code":"TR",
    "gn:dem":2949,
    "gn:feature_class":"P",
    "gn:feature_code":"PPL",
    "gn:name":"Ahpini",
    "gn:population":0,
    "gn:timezone":"Europe/Istanbul",
    "iso:country":"TR",
    "name:und_x_variant":[
        "Ahpini Mahallesi",
        "Ahpini"
    ],
    "wof:name":"Ahpini",
    "wof:placetype":"locality"
},
  "geometry": {"coordinates":[41.16667,40.78333],"type":"Point"}
}