{
  "type": "Feature",
  "properties": {
    "gn:admin1_code":"19.0",
    "gn:asciiname":"Kadimli",
    "gn:country_code":"TR",
    "gn:dem":1540,
    "gn:feature_class":"P",
    "gn:feature_code":"PPL",
    "gn:name":"Kadimli",
    "gn:population":0,
    "gn:timezone":"Europe/Istanbul",
    "iso:country":"TR",
    "wof:name":"Kadimli",
    "wof:placetype":"locality"
},
  "geometry": {"coordinates":[34.46667,41.28333],"type":"Point"}
}