{
  "type": "Feature",
  "properties": {
    "gn:admin1_code":"55.0",
    "gn:asciiname":"Burhaniye",
    "gn:country_code":"TR",
    "gn:dem":637,
    "gn:feature_class":"P",
    "gn:feature_code":"PPL",
    "gn:name":"Burhaniye",
    "gn:population":0,
    "gn:timezone":"Europe/Istanbul",
    "iso:country":"TR",
    "name:ara_x_preferred":[
        "\u0628\u0631\u0647\u0627\u0646\u064a\u0629"
    ],
    "name:bul_x_preferred":[
        "\u0411\u0443\u0440\u0445\u0430\u043d\u0438\u0435"
    ],
    "name:ceb_x_preferred":[
        "Burhaniye \u0130l\u00e7esi"
    ],
    "name:deu_x_preferred":[
        "Burhaniye"
    ],
    "name:fas_x_preferred":[
        "\u0628\u0631\u0647\u0627\u0646\u06cc\u0647"
    ],
    "name:fra_x_preferred":[
        "Burhaniye"
    ],
    "name:gag_x_preferred":[
        "Burhaniye"
    ],
    "name:min_x_preferred":[
        "Burhaniye"
    ],
    "name:mrj_x_preferred":[
        "\u0411\u0443\u0440\u0445\u0430\u043d\u0438\u0435"
    ],
    "name:msa_x_preferred":[
        "Burhaniye"
    ],
    "name:nno_x_preferred":[
        "Burhaniye"
    ],
    "name:nor_x_preferred":[
        "Burhaniye"
    ],
    "name:pol_x_preferred":[
        "Burhaniye"
    ],
    "name:ron_x_preferred":[
        "Burhaniye"
    ],
    "name:rus_x_preferred":[
        "\u0411\u0443\u0440\u0445\u0430\u043d\u0438\u0435"
    ],
    "name:swa_x_preferred":[
        "Burhaniye"
    ],
    "name:tur_x_preferred":[
        "Burhaniye"
    ],
    "name:urd_x_preferred":[
        "\u0628\u0631\u06c1\u0627\u0646\u06cc\u06d2"
    ],
    "name:vie_x_preferred":[
        "Burhaniye"
    ],
    "name:zho_x_preferred":[
        "\u5e03\u723e\u6f22\u5c3c\u8036"
    ],
    "wof:name":"Burhaniye",
    "wof:placetype":"locality"
},
  "geometry": {"coordinates":[35.30121,41.12972],"type":"Point"}
}