{
  "type": "Feature",
  "properties": {
    "gn:admin1_code":"55.0",
    "gn:asciiname":"Burhaniye",
    "gn:country_code":"TR",
    "gn:dem":637,
    "gn:feature_class":"P",
    "gn:feature_code":"PPL",
    "gn:name":"Burhaniye",
    "gn:population":0,
    "gn:timezone":"Europe/Istanbul",
    "iso:country":"TR",
    "name:tur_x_preferred":[
        "Burhaniye"
    ],
    "wof:name":"Burhaniye",
    "wof:placetype":"locality"
},
  "geometry": {"coordinates":[35.30121,41.12972],"type":"Point"}
}