{
  "type": "Feature",
  "properties": {
    "gn:admin1_code":"14.0",
    "gn:asciiname":"Asagiovacik",
    "gn:country_code":"TR",
    "gn:dem":1464,
    "gn:feature_class":"P",
    "gn:feature_code":"PPL",
    "gn:name":"A\u015fa\u011f\u0131ovac\u0131k",
    "gn:population":0,
    "gn:timezone":"Europe/Istanbul",
    "iso:country":"TR",
    "wof:name":"Asagiovacik",
    "wof:placetype":"locality"
},
  "geometry": {"coordinates":[32.38314,40.56263],"type":"Point"}
}