{
  "type": "Feature",
  "properties": {
    "gn:country":"TR",
    "gn:fcode":"PPL",
    "gn:pop":22976,
    "iso:country":"TR",
    "name:ceb_x_preferred":[
        "Kovanc\u0131lar"
    ],
    "name:deu_x_preferred":[
        "Kovanc\u0131lar"
    ],
    "name:diq_x_preferred":[
        "Kovanc\u0131lar"
    ],
    "name:eng_x_preferred":[
        "Kovanc\u0131lar"
    ],
    "name:fas_x_preferred":[
        "\u06a9\u0648\u0627\u0646\u062c\u06cc\u0644\u0627\u0631"
    ],
    "name:fra_x_preferred":[
        "Kovanc\u0131lar"
    ],
    "name:kur_x_preferred":[
        "Qowanciyan"
    ],
    "name:mrj_x_preferred":[
        "\u041a\u043e\u0432\u0430\u043d\u0434\u0436\u044b\u043b\u0430\u0440"
    ],
    "name:msa_x_preferred":[
        "Kovanc\u0131lar"
    ],
    "name:nan_x_preferred":[
        "Kovanc\u0131lar"
    ],
    "name:nld_x_preferred":[
        "Kovanc\u0131lar"
    ],
    "name:nno_x_preferred":[
        "Kovanc\u0131lar"
    ],
    "name:nob_x_preferred":[
        "Kovanc\u0131lar"
    ],
    "name:pnb_x_preferred":[
        "\u0636\u0644\u0639 \u06a9\u0648\u0648\u0627\u0646\u0686\u06cc\u0644\u0627\u0631"
    ],
    "name:rus_x_preferred":[
        "\u041a\u043e\u0432\u0430\u043d\u0434\u0436\u044b\u043b\u0430\u0440"
    ],
    "name:swa_x_preferred":[
        "Kovanc\u0131lar"
    ],
    "name:tur_x_preferred":[
        "Kovanc\u0131lar"
    ],
    "name:urd_x_preferred":[
        "\u06a9\u0648\u0648\u0627\u0646\u062c\u06cc\u0644\u0627\u0631"
    ],
    "name:vie_x_preferred":[
        "Kovanc\u0131lar"
    ],
    "name:zho_x_preferred":[
        "\u79d1\u842c\u54f2\u62c9\u723e"
    ],
    "name:zho_x_variant":[
        "\u6bd4\u96f7\u5409\u514b"
    ],
    "qs:name":"Kovanc\u0131lar",
    "qs:name_adm0":"Turkey",
    "qs:name_adm1":"Elaz\u0131\u011f",
    "qs:photos_9k":1,
    "qs:photos_9r":1,
    "qs:photos_all":2,
    "qs:photos_sr":0,
    "qs:placetype":"Town",
    "qs:pop_sr":"7",
    "wd:wordcount":63,
    "wof:name":"Kovanc\u0131lar",
    "wof:placetype":"locality",
    "wof:population":22976
},
  "geometry": {"coordinates":[39.86806,38.72139],"type":"Point"}
}