{
  "type": "Feature",
  "properties": {
    "gn:admin1_code":"81.0",
    "gn:asciiname":"Agacli",
    "gn:country_code":"TR",
    "gn:dem":33,
    "gn:feature_class":"P",
    "gn:feature_code":"PPL",
    "gn:name":"A\u011fa\u00e7l\u0131",
    "gn:population":0,
    "gn:timezone":"Europe/Istanbul",
    "iso:country":"TR",
    "name:und_x_variant":[
        "A\u011fa\u00e7l\u0131"
    ],
    "wof:name":"Agacli",
    "wof:placetype":"locality"
},
  "geometry": {"coordinates":[35.89465,37.23241],"type":"Point"}
}