{
  "type": "Feature",
  "properties": {
    "gn:admin1_code":"35",
    "gn:asciiname":"Sasalli",
    "gn:country_code":"TR",
    "gn:dem":5,
    "gn:feature_class":"P",
    "gn:feature_code":"PPL",
    "gn:name":"Sasall\u0131",
    "gn:population":0,
    "gn:timezone":"Europe/Istanbul",
    "iso:country":"TR",
    "name:und_x_variant":[
        "Sasall\u0131"
    ],
    "wof:name":"Sasalli",
    "wof:placetype":"locality"
},
  "geometry": {"coordinates":[26.95083,38.49508],"type":"Point"}
}