{
  "type": "Feature",
  "properties": {
    "gn:admin1_code":"35",
    "gn:asciiname":"Yuntdag",
    "gn:country_code":"TR",
    "gn:dem":450,
    "gn:feature_class":"P",
    "gn:feature_code":"PPLA3",
    "gn:name":"Yuntda\u011f",
    "gn:population":0,
    "gn:timezone":"Europe/Istanbul",
    "iso:country":"TR",
    "name:und_x_variant":[
        "\u0130smailli",
        "Yuntda\u011f"
    ],
    "wof:name":"Yuntdag",
    "wof:placetype":"locality"
},
  "geometry": {"coordinates":[27.21361,38.93167],"type":"Point"}
}