{
  "type": "Feature",
  "properties": {
    "gn:admin1_code":"07",
    "gn:asciiname":"Intas",
    "gn:country_code":"TR",
    "gn:dem":1084,
    "gn:feature_class":"P",
    "gn:feature_code":"PPL",
    "gn:name":"\u0130nta\u015f",
    "gn:population":0,
    "gn:timezone":"Europe/Istanbul",
    "iso:country":"TR",
    "name:und_x_variant":[
        "\u0130nta\u015f",
        "K\u0131z\u0131lcak\u00f6y"
    ],
    "wof:name":"Intas",
    "wof:placetype":"locality"
},
  "geometry": {"coordinates":[31.32862,37.30162],"type":"Point"}
}