{
  "type": "Feature",
  "properties": {
    "gn:admin1_code":"73",
    "gn:asciiname":"Emen",
    "gn:country_code":"TR",
    "gn:dem":1066,
    "gn:feature_class":"P",
    "gn:feature_code":"PPL",
    "gn:name":"Emen",
    "gn:population":0,
    "gn:timezone":"Europe/Istanbul",
    "iso:country":"TR",
    "name:bul_x_preferred":[
        "\u0415\u043c\u0435\u043d"
    ],
    "name:kat_x_preferred":[
        "\u10d4\u10db\u10d4\u10dc\u10d8"
    ],
    "name:kaz_x_preferred":[
        "\u042d\u043c\u0435\u043d"
    ],
    "name:msa_x_preferred":[
        "Emen"
    ],
    "name:ron_x_preferred":[
        "Emen"
    ],
    "name:rus_x_preferred":[
        "\u0415\u043c\u0435\u043d"
    ],
    "name:ukr_x_preferred":[
        "\u0404\u043c\u0435\u043d"
    ],
    "wof:name":"Emen",
    "wof:placetype":"locality"
},
  "geometry": {"coordinates":[34.4495,37.81872],"type":"Point"}
}