{
  "type": "Feature",
  "properties": {
    "gn:admin1_code":"73",
    "gn:asciiname":"Emen",
    "gn:country_code":"TR",
    "gn:dem":1066,
    "gn:feature_class":"P",
    "gn:feature_code":"PPL",
    "gn:name":"Emen",
    "gn:population":0,
    "gn:timezone":"Europe/Istanbul",
    "iso:country":"TR",
    "wof:name":"Emen",
    "wof:placetype":"locality"
},
  "geometry": {"coordinates":[34.4495,37.81872],"type":"Point"}
}