{
  "type": "Feature",
  "properties": {
    "gn:admin1_code":"14",
    "gn:asciiname":"Ormanpinar",
    "gn:country_code":"TR",
    "gn:dem":1017,
    "gn:feature_class":"P",
    "gn:feature_code":"PPL",
    "gn:name":"Ormanp\u0131nar",
    "gn:population":0,
    "gn:timezone":"Europe/Istanbul",
    "iso:country":"TR",
    "wof:name":"Ormanpinar",
    "wof:placetype":"locality"
},
  "geometry": {"coordinates":[31.11704000000001,40.43412],"type":"Point"}
}