{
  "type": "Feature",
  "properties": {
    "gn:admin1_code":"24",
    "gn:asciiname":"Kuzkisla",
    "gn:country_code":"TR",
    "gn:dem":1661,
    "gn:feature_class":"P",
    "gn:feature_code":"PPL",
    "gn:name":"Kuzk\u0131\u015fla",
    "gn:population":0,
    "gn:timezone":"Europe/Istanbul",
    "iso:country":"TR",
    "name:und_x_variant":[
        "Kozk\u0131\u015fla K\u00f6y\u00fc",
        "Kozk\u0131\u015fla",
        "Kuzk\u0131\u015fla"
    ],
    "wof:name":"Kuzkisla",
    "wof:placetype":"locality"
},
  "geometry": {"coordinates":[38.61075,39.69822],"type":"Point"}
}