{
  "type": "Feature",
  "properties": {
    "gn:admin1_code":"5.0",
    "gn:asciiname":"Zugu",
    "gn:country_code":"TR",
    "gn:dem":571,
    "gn:feature_class":"P",
    "gn:feature_code":"PPL",
    "gn:name":"Zugu",
    "gn:population":0,
    "gn:timezone":"Europe/Istanbul",
    "iso:country":"TR",
    "name:und_x_variant":[
        "G\u00f6k\u00e7eba\u011f"
    ],
    "wof:name":"Zugu",
    "wof:placetype":"locality"
},
  "geometry": {"coordinates":[35.53337,40.85414],"type":"Point"}
}