{
  "type": "Feature",
  "properties": {
    "gn:admin1_code":"66",
    "gn:asciiname":"Alifakili",
    "gn:country_code":"TR",
    "gn:dem":1221,
    "gn:feature_class":"P",
    "gn:feature_code":"PPL",
    "gn:name":"Alifak\u0131l\u0131",
    "gn:population":0,
    "gn:timezone":"Europe/Istanbul",
    "iso:country":"TR",
    "wof:name":"Alifakili",
    "wof:placetype":"locality"
},
  "geometry": {"coordinates":[35.47662000000001,39.41413],"type":"Point"}
}