{
  "type": "Feature",
  "properties": {
    "gn:admin1_code":"60.0",
    "gn:asciiname":"Alpudere",
    "gn:country_code":"TR",
    "gn:dem":1080,
    "gn:feature_class":"P",
    "gn:feature_code":"PPL",
    "gn:name":"Alpudere",
    "gn:population":0,
    "gn:timezone":"Europe/Istanbul",
    "iso:country":"TR",
    "name:und_x_variant":[
        "Alpuderesi K\u00f6y\u00fc",
        "Alpudere"
    ],
    "wof:name":"Alpudere",
    "wof:placetype":"locality"
},
  "geometry": {"coordinates":[36.08219,40.04783],"type":"Point"}
}