{
  "type": "Feature",
  "properties": {
    "gn:admin1_code":"62",
    "gn:asciiname":"Guzelpinar",
    "gn:country_code":"TR",
    "gn:dem":1451,
    "gn:feature_class":"P",
    "gn:feature_code":"PPL",
    "gn:name":"G\u00fczelp\u0131nar",
    "gn:population":0,
    "gn:timezone":"Europe/Istanbul",
    "iso:country":"TR",
    "name:und_x_variant":[
        "G\u00fczelp\u0131nar"
    ],
    "wof:name":"Guzelpinar",
    "wof:placetype":"locality"
},
  "geometry": {"coordinates":[39.84667,39.17584],"type":"Point"}
}