{
  "type": "Feature",
  "properties": {
    "gn:admin1_code":"82.0",
    "gn:asciiname":"Pinarcik",
    "gn:country_code":"TR",
    "gn:dem":1090,
    "gn:feature_class":"P",
    "gn:feature_code":"PPL",
    "gn:name":"P\u0131narc\u0131k",
    "gn:population":0,
    "gn:timezone":"Europe/Istanbul",
    "iso:country":"TR",
    "name:und_x_variant":[
        "P\u0131narc\u0131k",
        "Doda\u015f"
    ],
    "wof:name":"Pinarcik",
    "wof:placetype":"locality"
},
  "geometry": {"coordinates":[33.3259,40.96038],"type":"Point"}
}