{
  "type": "Feature",
  "properties": {
    "gn:admin1_code":"32",
    "gn:asciiname":"Kumdere",
    "gn:country_code":"TR",
    "gn:dem":143,
    "gn:feature_class":"P",
    "gn:feature_code":"PPL",
    "gn:name":"Kumdere",
    "gn:population":0,
    "gn:timezone":"Europe/Istanbul",
    "iso:country":"TR",
    "name:und_x_variant":[
        "Kocaveliler"
    ],
    "wof:name":"Kumdere",
    "wof:placetype":"locality"
},
  "geometry": {"coordinates":[34.98448,37.07979],"type":"Point"}
}