{
  "type": "Feature",
  "properties": {
    "gn:admin1_code":"70",
    "gn:asciiname":"Halkan",
    "gn:country_code":"TR",
    "gn:dem":1969,
    "gn:feature_class":"P",
    "gn:feature_code":"PPL",
    "gn:name":"Halkan",
    "gn:population":0,
    "gn:timezone":"Europe/Istanbul",
    "iso:country":"TR",
    "name:und_x_variant":[
        "P\u0131narg\u00f6z\u00fc"
    ],
    "wof:name":"Halkan",
    "wof:placetype":"locality"
},
  "geometry": {"coordinates":[44.14288,37.43648],"type":"Point"}
}