{
  "type": "Feature",
  "properties": {
    "gn:admin1_code":"62",
    "gn:asciiname":"Inkoy",
    "gn:country_code":"TR",
    "gn:dem":1447,
    "gn:feature_class":"P",
    "gn:feature_code":"PPL",
    "gn:name":"\u0130nk\u00f6y",
    "gn:population":0,
    "gn:timezone":"Europe/Istanbul",
    "iso:country":"TR",
    "name:und_x_variant":[
        "\u0130nk\u00f6y",
        "\u0130n"
    ],
    "wof:name":"Inkoy",
    "wof:placetype":"locality"
},
  "geometry": {"coordinates":[39.24627,39.05925],"type":"Point"}
}