{
  "type": "Feature",
  "properties": {
    "gn:admin1_code":"21",
    "gn:asciiname":"Kirmatepe",
    "gn:country_code":"TR",
    "gn:dem":869,
    "gn:feature_class":"P",
    "gn:feature_code":"PPL",
    "gn:name":"K\u0131rmatepe",
    "gn:population":0,
    "gn:timezone":"Europe/Istanbul",
    "iso:country":"TR",
    "name:tur_x_preferred":[
        "K\u0131rmatepe"
    ],
    "wof:name":"Kirmatepe",
    "wof:placetype":"locality"
},
  "geometry": {"coordinates":[39.49393,38.08692],"type":"Point"}
}