{
  "type": "Feature",
  "properties": {
    "gn:admin1_code":"48",
    "gn:asciiname":"Gokpinar",
    "gn:country_code":"TR",
    "gn:dem":393,
    "gn:feature_class":"P",
    "gn:feature_code":"PPL",
    "gn:name":"G\u00f6kp\u0131nar",
    "gn:population":0,
    "gn:timezone":"Europe/Istanbul",
    "iso:country":"TR",
    "name:tur_x_preferred":[
        "G\u00f6kp\u0131nar"
    ],
    "wof:name":"Gokpinar",
    "wof:placetype":"locality"
},
  "geometry": {"coordinates":[28.15954,37.27759],"type":"Point"}
}