{
  "type": "Feature",
  "properties": {
    "gn:admin1_code":"69.0",
    "gn:asciiname":"Ugurtasi",
    "gn:country_code":"TR",
    "gn:dem":1899,
    "gn:feature_class":"P",
    "gn:feature_code":"PPL",
    "gn:name":"U\u011furta\u015f\u0131",
    "gn:population":0,
    "gn:timezone":"Europe/Istanbul",
    "iso:country":"TR",
    "name:und_x_variant":[
        "\u0130stavri",
        "U\u011furta\u015f\u0131"
    ],
    "wof:name":"Ugurtasi",
    "wof:placetype":"locality"
},
  "geometry": {"coordinates":[39.51177,40.58197],"type":"Point"}
}