{
  "type": "Feature",
  "properties": {
    "gn:admin1_code":"71",
    "gn:asciiname":"Tolca",
    "gn:country_code":"TR",
    "gn:dem":1130,
    "gn:feature_class":"P",
    "gn:feature_code":"PPL",
    "gn:name":"Tolca",
    "gn:population":0,
    "gn:timezone":"Europe/Istanbul",
    "iso:country":"TR",
    "wof:name":"Tolca",
    "wof:placetype":"locality"
},
  "geometry": {"coordinates":[31.4953,37.91279],"type":"Point"}
}