{
  "type": "Feature",
  "properties": {
    "gn:admin1_code":"55.0",
    "gn:asciiname":"Asagidikencik",
    "gn:country_code":"TR",
    "gn:dem":12,
    "gn:feature_class":"P",
    "gn:feature_code":"PPL",
    "gn:name":"A\u015fa\u011f\u0131dikencik",
    "gn:population":0,
    "gn:timezone":"Europe/Istanbul",
    "iso:country":"TR",
    "wof:name":"Asagidikencik",
    "wof:placetype":"locality"
},
  "geometry": {"coordinates":[36.66361,41.26361],"type":"Point"}
}