{
  "type": "Feature",
  "properties": {
    "gn:admin1_code":"11",
    "gn:asciiname":"Demirkoy",
    "gn:country_code":"TR",
    "gn:dem":630,
    "gn:feature_class":"P",
    "gn:feature_code":"PPL",
    "gn:name":"Demirk\u00f6y",
    "gn:population":0,
    "gn:timezone":"Europe/Istanbul",
    "iso:country":"TR",
    "name:tur_x_preferred":[
        "Demirk\u00f6y"
    ],
    "wof:name":"Demirkoy",
    "wof:placetype":"locality"
},
  "geometry": {"coordinates":[30.00849,40.00272],"type":"Point"}
}