{
  "type": "Feature",
  "properties": {
    "gn:admin1_code":"63",
    "gn:asciiname":"Otlu",
    "gn:country_code":"TR",
    "gn:dem":1027,
    "gn:feature_class":"P",
    "gn:feature_code":"PPL",
    "gn:name":"Otlu",
    "gn:population":0,
    "gn:timezone":"Europe/Istanbul",
    "iso:country":"TR",
    "name:tur_x_preferred":[
        "Otlu"
    ],
    "wof:name":"Otlu",
    "wof:placetype":"locality"
},
  "geometry": {"coordinates":[39.59694,37.67275],"type":"Point"}
}