{
  "type": "Feature",
  "properties": {
    "gn:admin1_code":"14.0",
    "gn:asciiname":"Kuzorenemirler",
    "gn:country_code":"TR",
    "gn:dem":1235,
    "gn:feature_class":"P",
    "gn:feature_code":"PPL",
    "gn:name":"Kuz\u00f6renemirler",
    "gn:population":0,
    "gn:timezone":"Europe/Istanbul",
    "iso:country":"TR",
    "name:ceb_x_preferred":[
        "Kuz\u00f6renemirler"
    ],
    "name:msa_x_preferred":[
        "Kuz\u00f6renemirler"
    ],
    "name:tur_x_preferred":[
        "Kuz\u00f6renemirler"
    ],
    "name:und_x_variant":[
        "Emirler",
        "Kuzviranemirler"
    ],
    "name:vie_x_preferred":[
        "Kuz\u00f6renemirler"
    ],
    "wof:name":"Kuzorenemirler",
    "wof:placetype":"locality"
},
  "geometry": {"coordinates":[31.92873,40.74183],"type":"Point"}
}