{
  "type": "Feature",
  "properties": {
    "gn:admin1_code":"10.0",
    "gn:asciiname":"Eskiziraatli",
    "gn:country_code":"TR",
    "gn:dem":110,
    "gn:feature_class":"P",
    "gn:feature_code":"PPL",
    "gn:name":"Eskiziraatl\u0131",
    "gn:population":0,
    "gn:timezone":"Europe/Istanbul",
    "iso:country":"TR",
    "name:tur_x_preferred":[
        "Eskiziraatl\u0131"
    ],
    "wof:name":"Eskiziraatli",
    "wof:placetype":"locality"
},
  "geometry": {"coordinates":[28.07635,40.29932],"type":"Point"}
}