{
  "type": "Feature",
  "properties": {
    "gn:admin1_code":"25.0",
    "gn:asciiname":"Gulpinar",
    "gn:country_code":"TR",
    "gn:dem":1794,
    "gn:feature_class":"P",
    "gn:feature_code":"PPL",
    "gn:name":"G\u00fclp\u0131nar",
    "gn:population":0,
    "gn:timezone":"Europe/Istanbul",
    "iso:country":"TR",
    "name:tur_x_preferred":[
        "G\u00fclp\u0131nar"
    ],
    "name:und_x_variant":[
        "G\u00f6lp\u0131nar\u0131"
    ],
    "wof:name":"Gulpinar",
    "wof:placetype":"locality"
},
  "geometry": {"coordinates":[41.33485,40.07054],"type":"Point"}
}