{
  "type": "Feature",
  "properties": {
    "gn:admin1_code":"24",
    "gn:asciiname":"Yardere",
    "gn:country_code":"TR",
    "gn:dem":1731,
    "gn:feature_class":"P",
    "gn:feature_code":"PPL",
    "gn:name":"Yardere",
    "gn:population":0,
    "gn:timezone":"Europe/Istanbul",
    "iso:country":"TR",
    "name:tur_x_preferred":[
        "Yardere"
    ],
    "wof:name":"Yardere",
    "wof:placetype":"locality"
},
  "geometry": {"coordinates":[39.03705,39.77148],"type":"Point"}
}