{
  "type": "Feature",
  "properties": {
    "gn:admin1_code":"71",
    "gn:asciiname":"Dinek",
    "gn:country_code":"TR",
    "gn:dem":1194,
    "gn:feature_class":"P",
    "gn:feature_code":"PPLA3",
    "gn:name":"Dinek",
    "gn:population":0,
    "gn:timezone":"Europe/Istanbul",
    "iso:country":"TR",
    "name:ceb_x_preferred":[
        "Dinek"
    ],
    "name:tur_x_preferred":[
        "Dinek"
    ],
    "name:vie_x_preferred":[
        "Dinek"
    ],
    "wof:name":"Dinek",
    "wof:placetype":"locality"
},
  "geometry": {"coordinates":[32.61602,37.32481],"type":"Point"}
}