{
  "type": "Feature",
  "properties": {
    "gn:admin1_code":"25",
    "gn:asciiname":"Kayabogaz",
    "gn:country_code":"TR",
    "gn:dem":2096,
    "gn:feature_class":"P",
    "gn:feature_code":"PPL",
    "gn:name":"Kayabo\u011faz",
    "gn:population":0,
    "gn:timezone":"Europe/Istanbul",
    "iso:country":"TR",
    "name:tur_x_preferred":[
        "Kayabo\u011faz"
    ],
    "name:und_x_variant":[
        "Karabo\u011faz",
        "Ke\u00e7elan"
    ],
    "wof:name":"Kayabogaz",
    "wof:placetype":"locality"
},
  "geometry": {"coordinates":[41.28427,39.51087],"type":"Point"}
}