{
  "type": "Feature",
  "properties": {
    "gn:admin1_code":"82.0",
    "gn:asciiname":"Asagiyanlar",
    "gn:country_code":"TR",
    "gn:dem":788,
    "gn:feature_class":"P",
    "gn:feature_code":"PPL",
    "gn:name":"A\u015fa\u011f\u0131yanlar",
    "gn:population":0,
    "gn:timezone":"Europe/Istanbul",
    "iso:country":"TR",
    "name:und_x_variant":[
        "B\u00fcy\u00fckyanlar",
        "A\u015fa\u011f\u0131yanlar"
    ],
    "wof:name":"Asagiyanlar",
    "wof:placetype":"locality"
},
  "geometry": {"coordinates":[33.5652,40.55724],"type":"Point"}
}