{
  "type": "Feature",
  "properties": {
    "gn:admin1_code":"19.0",
    "gn:asciiname":"Tultepe",
    "gn:country_code":"TR",
    "gn:dem":1368,
    "gn:feature_class":"P",
    "gn:feature_code":"PPL",
    "gn:name":"T\u00fcltepe",
    "gn:population":0,
    "gn:timezone":"Europe/Istanbul",
    "iso:country":"TR",
    "wof:name":"Tultepe",
    "wof:placetype":"locality"
},
  "geometry": {"coordinates":[34.33215,40.92695],"type":"Point"}
}