{
  "type": "Feature",
  "properties": {
    "gn:admin1_code":"2.0",
    "gn:asciiname":"Baglarbasi",
    "gn:country_code":"TR",
    "gn:dem":953,
    "gn:feature_class":"P",
    "gn:feature_code":"PPL",
    "gn:name":"Ba\u011flarba\u015f\u0131",
    "gn:population":0,
    "gn:timezone":"Europe/Istanbul",
    "iso:country":"TR",
    "wof:name":"Baglarbasi",
    "wof:placetype":"locality"
},
  "geometry": {"coordinates":[37.55674000000001,37.7623],"type":"Point"}
}