{
  "type": "Feature",
  "properties": {
    "gn:admin1_code":"82.0",
    "gn:asciiname":"Kulluklu",
    "gn:country_code":"TR",
    "gn:dem":1328,
    "gn:feature_class":"P",
    "gn:feature_code":"PPL",
    "gn:name":"Kulluklu",
    "gn:population":0,
    "gn:timezone":"Europe/Istanbul",
    "iso:country":"TR",
    "wof:name":"Kulluklu",
    "wof:placetype":"locality"
},
  "geometry": {"coordinates":[33.32937,40.51481],"type":"Point"}
}