{
  "type": "Feature",
  "properties": {
    "gn:admin1_code":"58",
    "gn:asciiname":"Yukaribogaz",
    "gn:country_code":"TR",
    "gn:dem":1738,
    "gn:feature_class":"P",
    "gn:feature_code":"PPL",
    "gn:name":"Yukar\u0131bo\u011faz",
    "gn:population":0,
    "gn:timezone":"Europe/Istanbul",
    "iso:country":"TR",
    "wof:name":"Yukaribogaz",
    "wof:placetype":"locality"
},
  "geometry": {"coordinates":[38.23414,39.92011],"type":"Point"}
}