{
  "type": "Feature",
  "properties": {
    "gn:admin1_code":"44",
    "gn:asciiname":"Goltarla",
    "gn:country_code":"TR",
    "gn:dem":1532,
    "gn:feature_class":"P",
    "gn:feature_code":"PPL",
    "gn:name":"G\u00f6ltarla",
    "gn:population":0,
    "gn:timezone":"Europe/Istanbul",
    "iso:country":"TR",
    "wof:name":"Goltarla",
    "wof:placetype":"locality"
},
  "geometry": {"coordinates":[38.14122,37.9761],"type":"Point"}
}