{
  "type": "Feature",
  "properties": {
    "gn:admin1_code":"45",
    "gn:asciiname":"Horozkoy",
    "gn:country_code":"TR",
    "gn:dem":42,
    "gn:feature_class":"P",
    "gn:feature_code":"PPL",
    "gn:name":"Horozk\u00f6y",
    "gn:population":0,
    "gn:timezone":"Europe/Istanbul",
    "iso:country":"TR",
    "name:tur_x_preferred":[
        "Horozk\u00f6y"
    ],
    "name:und_x_variant":[
        "Horoz"
    ],
    "wof:name":"Horozkoy",
    "wof:placetype":"locality"
},
  "geometry": {"coordinates":[27.40262,38.63213],"type":"Point"}
}