{
  "type": "Feature",
  "properties": {
    "gn:admin1_code":"62",
    "gn:asciiname":"Doganalan",
    "gn:country_code":"TR",
    "gn:dem":1504,
    "gn:feature_class":"P",
    "gn:feature_code":"PPL",
    "gn:name":"Do\u011fanalan",
    "gn:population":0,
    "gn:timezone":"Europe/Istanbul",
    "iso:country":"TR",
    "name:tur_x_preferred":[
        "Do\u011fanalan"
    ],
    "wof:name":"Doganalan",
    "wof:placetype":"locality"
},
  "geometry": {"coordinates":[38.80597,39.18089000000001],"type":"Point"}
}