{
  "type": "Feature",
  "properties": {
    "gn:admin1_code":"65",
    "gn:asciiname":"Papan",
    "gn:country_code":"TR",
    "gn:dem":1860,
    "gn:feature_class":"P",
    "gn:feature_code":"PPL",
    "gn:name":"Papan",
    "gn:population":0,
    "gn:timezone":"Europe/Istanbul",
    "iso:country":"TR",
    "name:kir_x_preferred":[
        "\u041f\u0430\u043f\u0430\u043d"
    ],
    "name:uzb_x_preferred":[
        "Papan"
    ],
    "wof:name":"Papan",
    "wof:placetype":"locality"
},
  "geometry": {"coordinates":[43.16667,38.01667],"type":"Point"}
}