{
  "type": "Feature",
  "properties": {
    "gn:admin1_code":"19.0",
    "gn:asciiname":"Orucpinar",
    "gn:cc2":"TR",
    "gn:country_code":"TR",
    "gn:dem":1149,
    "gn:feature_class":"P",
    "gn:feature_code":"PPL",
    "gn:name":"Oru\u00e7p\u0131nar",
    "gn:population":0,
    "gn:timezone":"Europe/Istanbul",
    "iso:country":"TR",
    "name:und_x_variant":[
        "Karada\u011f",
        "Oru\u00e7p\u0131nark\u00f6y"
    ],
    "wof:name":"Orucpinar",
    "wof:placetype":"locality"
},
  "geometry": {"coordinates":[35.18887,40.2811],"type":"Point"}
}