{
  "type": "Feature",
  "properties": {
    "gn:admin1_code":"8.0",
    "gn:asciiname":"Yanikli",
    "gn:country_code":"TR",
    "gn:dem":1270,
    "gn:feature_class":"P",
    "gn:feature_code":"PPL",
    "gn:name":"Yan\u0131kl\u0131",
    "gn:population":0,
    "gn:timezone":"Europe/Istanbul",
    "iso:country":"TR",
    "name:tur_x_preferred":[
        "Yan\u0131kl\u0131"
    ],
    "wof:name":"Yanikli",
    "wof:placetype":"locality"
},
  "geometry": {"coordinates":[42.12054000000001,41.30677],"type":"Point"}
}