{
  "type": "Feature",
  "properties": {
    "gn:admin1_code":"58",
    "gn:asciiname":"Sarikaya",
    "gn:country_code":"TR",
    "gn:dem":877,
    "gn:feature_class":"P",
    "gn:feature_code":"PPL",
    "gn:name":"Sar\u0131kaya",
    "gn:population":0,
    "gn:timezone":"Europe/Istanbul",
    "iso:country":"TR",
    "name:tur_x_preferred":[
        "Sar\u0131kaya"
    ],
    "wof:name":"Sarikaya",
    "wof:placetype":"locality"
},
  "geometry": {"coordinates":[37.71221,40.3149],"type":"Point"}
}