{
  "type": "Feature",
  "properties": {
    "gn:admin1_code":"81",
    "gn:asciiname":"Sakli",
    "gn:country_code":"TR",
    "gn:dem":165,
    "gn:feature_class":"P",
    "gn:feature_code":"PPL",
    "gn:name":"Sakl\u0131",
    "gn:population":0,
    "gn:timezone":"Europe/Istanbul",
    "iso:country":"TR",
    "wof:name":"Sakli",
    "wof:placetype":"locality"
},
  "geometry": {"coordinates":[35.13333,37.23333],"type":"Point"}
}