{
  "type": "Feature",
  "properties": {
    "gn:country":"TR",
    "gn:fcode":"PPLX",
    "gn:pop":0,
    "iso:country":"TR",
    "qs:name":"Bademlidere",
    "qs:name_adm0":"Turkey",
    "qs:name_adm1":"Ankara",
    "qs:photos":8,
    "qs:photos_1k":2,
    "qs:photos_9k":1,
    "qs:photos_9r":1,
    "qs:photos_all":8,
    "qs:photos_sr":1,
    "qs:placetype":"Suburb",
    "qs:pop_sr":"0",
    "wof:name":"Bademlidere",
    "wof:placetype":"neighbourhood",
    "wof:population":0
},
  "geometry": {"coordinates":[32.88774,39.89893],"type":"Point"}
}