{
  "type": "Feature",
  "properties": {
    "gn:admin1_code":"04",
    "gn:asciiname":"Asagi Karahalit",
    "gn:country_code":"TR",
    "gn:dem":1740,
    "gn:feature_class":"P",
    "gn:feature_code":"PPL",
    "gn:name":"A\u015fa\u011f\u0131 Karahalit",
    "gn:population":0,
    "gn:timezone":"Europe/Istanbul",
    "iso:country":"TR",
    "name:tur_x_preferred":[
        "A\u015fa\u011f\u0131 Karahalit"
    ],
    "name:und_x_variant":[
        "A\u015fa\u011f\u0131karahalit"
    ],
    "wof:name":"Asagi Karahalit",
    "wof:placetype":"locality"
},
  "geometry": {"coordinates":[42.84892,39.46571],"type":"Point"}
}