{
  "type": "Feature",
  "properties": {
    "gn:country":"TR",
    "gn:fcode":"PPL",
    "gn:population":1452,
    "iso:country":"TR",
    "name:cat_x_preferred":[
        "Bar\u0131\u015ftepe"
    ],
    "name:ceb_x_preferred":[
        "Bar\u0131\u015ftepe"
    ],
    "name:ces_x_preferred":[
        "Bar\u0131\u015ftepe"
    ],
    "name:dan_x_preferred":[
        "Bar\u0131\u015ftepe"
    ],
    "name:deu_x_preferred":[
        "Bar\u0131\u015ftepe"
    ],
    "name:eng_x_preferred":[
        "Bar\u0131\u015ftepe"
    ],
    "name:eus_x_preferred":[
        "Bar\u0131\u015ftepe"
    ],
    "name:fin_x_preferred":[
        "Bar\u0131\u015ftepe"
    ],
    "name:glg_x_preferred":[
        "Bar\u0131\u015ftepe"
    ],
    "name:hye_x_preferred":[
        "\u054d\u0561\u056c\u0561\u0570"
    ],
    "name:ita_x_preferred":[
        "Bar\u0131\u015ftepe"
    ],
    "name:kur_x_preferred":[
        "Selh\u00ea"
    ],
    "name:nld_x_preferred":[
        "Bar\u0131\u015ftepe"
    ],
    "name:nno_x_preferred":[
        "Bar\u0131\u015ftepe"
    ],
    "name:nob_x_preferred":[
        "Bar\u0131\u015ftepe"
    ],
    "name:oci_x_preferred":[
        "Bar\u0131\u015ftepe"
    ],
    "name:pol_x_preferred":[
        "Bar\u0131\u015ftepe"
    ],
    "name:por_x_preferred":[
        "Bar\u0131\u015ftepe"
    ],
    "name:ron_x_preferred":[
        "Bar\u0131\u015ftepe"
    ],
    "name:sco_x_preferred":[
        "Bar\u0131\u015ftepe"
    ],
    "name:slk_x_preferred":[
        "Bar\u0131\u015ftepe"
    ],
    "name:slv_x_preferred":[
        "Bar\u0131\u015ftepe"
    ],
    "name:spa_x_preferred":[
        "Bar\u0131\u015ftepe"
    ],
    "name:swe_x_preferred":[
        "Bar\u0131\u015ftepe"
    ],
    "name:tgl_x_preferred":[
        "Bar\u0131\u015ftepe"
    ],
    "name:tur_x_preferred":[
        "Bar\u0131\u015ftepe"
    ],
    "name:und_x_variant":[
        "Salkhi"
    ],
    "name:vie_x_preferred":[
        "Bar\u0131\u015ftepe"
    ],
    "name:war_x_preferred":[
        "Bar\u0131\u015ftepe"
    ],
    "qs:name":"Bar\u0131\u015ftepe",
    "qs:photos_9r":0,
    "qs:photos_sr":0,
    "qs:pop_sr":"3",
    "wof:name":"Bar\u0131\u015ftepe",
    "wof:placetype":"locality",
    "wof:population":1452
},
  "geometry": {"coordinates":[41.395,37.48028],"type":"Point"}
}