{
  "type": "Feature",
  "properties": {
    "gn:admin1_code":"46.0",
    "gn:asciiname":"Dedepasa",
    "gn:country_code":"TR",
    "gn:dem":561,
    "gn:feature_class":"P",
    "gn:feature_code":"PPL",
    "gn:name":"Dedepa\u015fa",
    "gn:population":0,
    "gn:timezone":"Europe/Istanbul",
    "iso:country":"TR",
    "name:tur_x_preferred":[
        "Dedepa\u015fa"
    ],
    "wof:name":"Dedepasa",
    "wof:placetype":"locality"
},
  "geometry": {"coordinates":[37.12254,37.33177],"type":"Point"}
}