{
  "type": "Feature",
  "properties": {
    "gn:admin1_code":"13",
    "gn:asciiname":"Uzuntas",
    "gn:country_code":"TR",
    "gn:dem":1744,
    "gn:feature_class":"P",
    "gn:feature_code":"PPL",
    "gn:name":"Uzunta\u015f",
    "gn:population":0,
    "gn:timezone":"Europe/Istanbul",
    "iso:country":"TR",
    "name:tur_x_preferred":[
        "Uzunta\u015f"
    ],
    "name:und_x_variant":[
        "Kavnas",
        "Kindik"
    ],
    "wof:name":"Uzuntas",
    "wof:placetype":"locality"
},
  "geometry": {"coordinates":[42.56487,38.08397],"type":"Point"}
}