{
  "type": "Feature",
  "properties": {
    "gn:admin1_code":"70.0",
    "gn:asciiname":"Pinarli",
    "gn:country_code":"TR",
    "gn:dem":1970,
    "gn:feature_class":"P",
    "gn:feature_code":"PPL",
    "gn:name":"P\u0131narl\u0131",
    "gn:population":0,
    "gn:timezone":"Europe/Istanbul",
    "iso:country":"TR",
    "wof:name":"Pinarli",
    "wof:placetype":"locality"
},
  "geometry": {"coordinates":[43.76546,37.24863],"type":"Point"}
}