{
  "type": "Feature",
  "properties": {
    "gn:admin1_code":"76.0",
    "gn:asciiname":"Akcakisla",
    "gn:country_code":"TR",
    "gn:dem":938,
    "gn:feature_class":"P",
    "gn:feature_code":"PPL",
    "gn:name":"Ak\u00e7ak\u0131\u015fla",
    "gn:population":0,
    "gn:timezone":"Europe/Istanbul",
    "iso:country":"TR",
    "name:tur_x_preferred":[
        "Ak\u00e7ak\u0131\u015fla"
    ],
    "name:und_x_variant":[
        "Ak\u00e7ak\u0131\u1e63la"
    ],
    "wof:name":"Akcakisla",
    "wof:placetype":"locality"
},
  "geometry": {"coordinates":[41.61143,38.26714000000001],"type":"Point"}
}