{
  "type": "Feature",
  "properties": {
    "gn:admin1_code":"68.0",
    "gn:asciiname":"Saatli",
    "gn:country_code":"TR",
    "gn:dem":1007,
    "gn:feature_class":"P",
    "gn:feature_code":"PPL",
    "gn:name":"Saatl\u0131",
    "gn:population":0,
    "gn:timezone":"Europe/Istanbul",
    "iso:country":"TR",
    "wof:name":"Saatli",
    "wof:placetype":"locality"
},
  "geometry": {"coordinates":[32.54626,39.07484],"type":"Point"}
}