{
  "type": "Feature",
  "properties": {
    "gn:admin1_code":"31.0",
    "gn:asciiname":"Azganlik",
    "gn:country_code":"TR",
    "gn:dem":181,
    "gn:feature_class":"P",
    "gn:feature_code":"PPL",
    "gn:name":"Azganl\u0131k",
    "gn:population":0,
    "gn:timezone":"Europe/Istanbul",
    "iso:country":"TR",
    "name:tur_x_preferred":[
        "Azganl\u0131k"
    ],
    "wof:name":"Azganlik",
    "wof:placetype":"locality"
},
  "geometry": {"coordinates":[36.22752,36.69629000000001],"type":"Point"}
}