{
  "type": "Feature",
  "properties": {
    "gn:admin1_code":"63",
    "gn:asciiname":"Arslani",
    "gn:country_code":"TR",
    "gn:dem":623,
    "gn:feature_class":"P",
    "gn:feature_code":"PPL",
    "gn:name":"Arslan\u0131",
    "gn:population":0,
    "gn:timezone":"Europe/Istanbul",
    "iso:country":"TR",
    "name:tur_x_preferred":[
        "Arslan\u0131"
    ],
    "wof:name":"Arslani",
    "wof:placetype":"locality"
},
  "geometry": {"coordinates":[39.16386,37.60974],"type":"Point"}
}