{
  "type": "Feature",
  "properties": {
    "gn:country":"TR",
    "gn:fcode":"PPLA2",
    "gn:population":8415,
    "iso:country":"TR",
    "name:ast_x_preferred":[
        "Ba\u015fmak\u00e7\u0131"
    ],
    "name:cat_x_preferred":[
        "Ba\u015fmak\u00e7\u0131"
    ],
    "name:ceb_x_preferred":[
        "Ba\u015fmak\u00e7\u0131 \u0130l\u00e7esi"
    ],
    "name:che_x_preferred":[
        "\u0411\u0430\u0448\u043c\u0430\u043a\u0447\u0438"
    ],
    "name:deu_x_preferred":[
        "Ba\u015fmak\u00e7\u0131"
    ],
    "name:diq_x_preferred":[
        "Ba\u015fmak\u00e7\u0131"
    ],
    "name:eng_x_preferred":[
        "Ba\u015fmak\u00e7\u0131"
    ],
    "name:eus_x_preferred":[
        "Basmakzi"
    ],
    "name:fas_x_preferred":[
        "\u0628\u0627\u0634\u0645\u0627\u06a9\u0686\u06cc"
    ],
    "name:fin_x_preferred":[
        "Ba\u015fmak\u00e7\u0131"
    ],
    "name:fra_x_preferred":[
        "Ba\u015fmak\u00e7\u0131"
    ],
    "name:ita_x_preferred":[
        "Distretto di Ba\u015fmak\u00e7\u0131"
    ],
    "name:mrj_x_preferred":[
        "\u0411\u0430\u0448\u043c\u0430\u043a\u0447\u044b"
    ],
    "name:msa_x_preferred":[
        "Ba\u015fmak\u00e7\u0131"
    ],
    "name:nan_x_preferred":[
        "Ba\u015fmak\u00e7\u0131"
    ],
    "name:nld_x_preferred":[
        "Ba\u015fmak\u00e7\u0131"
    ],
    "name:nob_x_preferred":[
        "Ba\u015fmak\u00e7\u0131"
    ],
    "name:pnb_x_preferred":[
        "\u0636\u0644\u0639 \u0628\u0627\u0633\u0645\u0627\u06a9\u0634\u06cc"
    ],
    "name:pol_x_preferred":[
        "Ba\u015fmak\u00e7\u0131"
    ],
    "name:ron_x_preferred":[
        "Districtul Ba\u015fmak\u00e7\u0131"
    ],
    "name:spa_x_preferred":[
        "Ba\u015fmak\u00e7\u0131"
    ],
    "name:swa_x_preferred":[
        "Ba\u015fmak\u00e7\u0131"
    ],
    "name:tat_x_preferred":[
        "\u0411\u0430\u0448\u043c\u0430\u043a\u0447\u044b"
    ],
    "name:tur_x_preferred":[
        "Ba\u015fmak\u00e7\u0131"
    ],
    "name:urd_x_preferred":[
        "\u0628\u0627\u0634\u0645\u0627\u06a9\u0686\u06cc"
    ],
    "name:uzb_x_preferred":[
        "Ba\u015fmak\u00e7\u0131"
    ],
    "name:vie_x_preferred":[
        "Ba\u015fmak\u00e7\u0131"
    ],
    "qs:name":"Ba\u015fmak\u00e7\u0131",
    "qs:photos_9r":0,
    "qs:photos_sr":0,
    "qs:pop_sr":"5",
    "wd:wordcount":328,
    "wof:name":"Ba\u015fmak\u00e7\u0131",
    "wof:placetype":"locality",
    "wof:population":8415
},
  "geometry": {"coordinates":[30.01167,37.89722],"type":"Point"}
}