{
  "type": "Feature",
  "properties": {
    "gn:admin1_code":"32.0",
    "gn:asciiname":"Oluoluk",
    "gn:country_code":"TR",
    "gn:dem":865,
    "gn:feature_class":"P",
    "gn:feature_code":"PPL",
    "gn:name":"\u00d6l\u00fcoluk",
    "gn:population":0,
    "gn:timezone":"Europe/Istanbul",
    "iso:country":"TR",
    "wof:name":"Oluoluk",
    "wof:placetype":"locality"
},
  "geometry": {"coordinates":[33.29223,36.26092],"type":"Point"}
}