{
  "type": "Feature",
  "properties": {
    "gn:country":"TR",
    "gn:fcode":"PPLX",
    "gn:population":0,
    "iso:country":"TR",
    "qs:name":"Dikimevi",
    "qs:name_adm0":"Turkey",
    "qs:name_adm1":"Ankara",
    "qs:photos_9r":0,
    "qs:photos_sr":0,
    "qs:placetype":"Suburb",
    "qs:pop_sr":"0",
    "wof:name":"Dikimevi",
    "wof:placetype":"neighbourhood",
    "wof:population":0
},
  "geometry": {"coordinates":[32.87838,39.93245],"type":"Point"}
}