{
  "type": "Feature",
  "properties": {
    "gn:admin1_code":"44",
    "gn:asciiname":"Onatli",
    "gn:cc2":"TR",
    "gn:country_code":"TR",
    "gn:dem":1501,
    "gn:feature_class":"P",
    "gn:feature_code":"PPL",
    "gn:name":"Onatl\u0131",
    "gn:population":0,
    "gn:timezone":"Europe/Istanbul",
    "iso:country":"TR",
    "name:und_x_variant":[
        "Kilise",
        "Kilisek\u00f6y",
        "Onatl\u0131"
    ],
    "wof:name":"Onatli",
    "wof:placetype":"locality"
},
  "geometry": {"coordinates":[38.08333,38.23333],"type":"Point"}
}