{
  "type": "Feature",
  "properties": {
    "gn:admin1_code":"63",
    "gn:asciiname":"Tirkak",
    "gn:country_code":"TR",
    "gn:dem":473,
    "gn:feature_class":"P",
    "gn:feature_code":"PPL",
    "gn:name":"Tirkak",
    "gn:population":0,
    "gn:timezone":"Europe/Istanbul",
    "iso:country":"TR",
    "name:tur_x_preferred":[
        "Tirkak"
    ],
    "name:tur_x_variant":[
        "\u00dcveylik"
    ],
    "name:und_x_variant":[
        "Terfak"
    ],
    "wof:name":"Tirkak",
    "wof:placetype":"locality"
},
  "geometry": {"coordinates":[38.50751,36.93838],"type":"Point"}
}