{
  "type": "Feature",
  "properties": {
    "gn:admin1_code":"09",
    "gn:asciiname":"Beykoy",
    "gn:country_code":"TR",
    "gn:dem":577,
    "gn:feature_class":"P",
    "gn:feature_code":"PPL",
    "gn:name":"Beyk\u00f6y",
    "gn:population":0,
    "gn:timezone":"Europe/Istanbul",
    "iso:country":"TR",
    "name:tur_x_preferred":[
        "Beyk\u00f6y"
    ],
    "name:und_x_variant":[
        "Tekirk\u00f6y",
        "Tekir"
    ],
    "wof:name":"Beykoy",
    "wof:placetype":"locality"
},
  "geometry": {"coordinates":[27.781,37.9635],"type":"Point"}
}