{
  "type": "Feature",
  "properties": {
    "gn:admin1_code":"21",
    "gn:asciiname":"Kemaliye",
    "gn:country_code":"TR",
    "gn:dem":804,
    "gn:feature_class":"P",
    "gn:feature_code":"PPL",
    "gn:name":"Kemaliye",
    "gn:population":0,
    "gn:timezone":"Europe/Istanbul",
    "iso:country":"TR",
    "name:aze_x_preferred":[
        "K\u0259maliy\u0259"
    ],
    "name:bul_x_preferred":[
        "\u041a\u0435\u043c\u0430\u043b\u0438\u0435"
    ],
    "name:cat_x_preferred":[
        "Kemaliye"
    ],
    "name:ceb_x_preferred":[
        "Kemaliye \u0130l\u00e7esi"
    ],
    "name:ckb_x_preferred":[
        "\u0626\u06d5\u06af\u06cc\u0646"
    ],
    "name:deu_x_preferred":[
        "Kemaliye"
    ],
    "name:diq_x_preferred":[
        "Egin"
    ],
    "name:epo_x_preferred":[
        "Kemaliye"
    ],
    "name:fra_x_preferred":[
        "Kemaliye"
    ],
    "name:hye_x_preferred":[
        "\u0531\u056f\u0576"
    ],
    "name:hyw_x_preferred":[
        "\u0531\u056f\u0576"
    ],
    "name:kur_x_preferred":[
        "Eg\u00een"
    ],
    "name:mrj_x_preferred":[
        "\u041a\u0435\u043c\u0430\u043b\u0438\u0435"
    ],
    "name:msa_x_preferred":[
        "Kemaliye"
    ],
    "name:nor_x_preferred":[
        "Kemaliye"
    ],
    "name:pnb_x_preferred":[
        "\u0636\u0644\u0639 \u06a9\u0645\u0627\u0644\u06cc\u06d3"
    ],
    "name:rus_x_preferred":[
        "\u041a\u0435\u043c\u0430\u043b\u0438\u0435"
    ],
    "name:swa_x_preferred":[
        "Kemaliye"
    ],
    "name:tur_x_preferred":[
        "Dersil"
    ],
    "name:tur_x_variant":[
        "Kemaliye"
    ],
    "name:urd_x_preferred":[
        "\u06a9\u06cc\u0645\u0627\u0644\u06cc\u06d2"
    ],
    "name:vie_x_preferred":[
        "Kemaliye"
    ],
    "wof:name":"Kemaliye",
    "wof:placetype":"locality"
},
  "geometry": {"coordinates":[40.79978,38.1941],"type":"Point"}
}