{
  "type": "Feature",
  "properties": {
    "gn:admin1_code":"21",
    "gn:asciiname":"Kemaliye",
    "gn:country_code":"TR",
    "gn:dem":804,
    "gn:feature_class":"P",
    "gn:feature_code":"PPL",
    "gn:name":"Kemaliye",
    "gn:population":0,
    "gn:timezone":"Europe/Istanbul",
    "iso:country":"TR",
    "name:tur_x_preferred":[
        "Dersil"
    ],
    "wof:name":"Kemaliye",
    "wof:placetype":"locality"
},
  "geometry": {"coordinates":[40.79978,38.1941],"type":"Point"}
}