{
  "type": "Feature",
  "properties": {
    "gn:admin1_code":"14",
    "gn:asciiname":"Hanyeri",
    "gn:country_code":"TR",
    "gn:dem":845,
    "gn:feature_class":"P",
    "gn:feature_code":"PPL",
    "gn:name":"Hanyeri",
    "gn:population":0,
    "gn:timezone":"Europe/Istanbul",
    "iso:country":"TR",
    "wof:name":"Hanyeri",
    "wof:placetype":"locality"
},
  "geometry": {"coordinates":[31.47052,40.65447],"type":"Point"}
}