{
  "type": "Feature",
  "properties": {
    "gn:admin1_code":"71",
    "gn:asciiname":"Haciomeroglu",
    "gn:country_code":"TR",
    "gn:dem":1007,
    "gn:feature_class":"P",
    "gn:feature_code":"PPL",
    "gn:name":"Hac\u0131\u00f6mero\u011flu",
    "gn:population":0,
    "gn:timezone":"Europe/Istanbul",
    "iso:country":"TR",
    "name:tur_x_preferred":[
        "Hac\u0131\u00f6mero\u011flu"
    ],
    "wof:name":"Haciomeroglu",
    "wof:placetype":"locality"
},
  "geometry": {"coordinates":[32.33075,38.99151],"type":"Point"}
}