{
  "type": "Feature",
  "properties": {
    "gn:admin1_code":"20",
    "gn:asciiname":"Hacikurtlar",
    "gn:country_code":"TR",
    "gn:dem":1174,
    "gn:feature_class":"P",
    "gn:feature_code":"PPL",
    "gn:name":"Hac\u0131kurtlar",
    "gn:population":0,
    "gn:timezone":"Europe/Istanbul",
    "iso:country":"TR",
    "name:tur_x_preferred":[
        "Hac\u0131kurtlar"
    ],
    "wof:name":"Hacikurtlar",
    "wof:placetype":"locality"
},
  "geometry": {"coordinates":[29.3091,37.18724],"type":"Point"}
}