{
  "type": "Feature",
  "properties": {
    "gn:admin1_code":"54.0",
    "gn:asciiname":"Egricay",
    "gn:country_code":"TR",
    "gn:dem":85,
    "gn:feature_class":"P",
    "gn:feature_code":"PPL",
    "gn:name":"E\u011fri\u00e7ay",
    "gn:population":0,
    "gn:timezone":"Europe/Istanbul",
    "iso:country":"TR",
    "name:tur_x_preferred":[
        "E\u011fri\u00e7ay"
    ],
    "wof:name":"Egricay",
    "wof:placetype":"locality"
},
  "geometry": {"coordinates":[30.07976,40.4696],"type":"Point"}
}