{
  "type": "Feature",
  "properties": {
    "gn:admin1_code":"28.0",
    "gn:asciiname":"Cakilkaya",
    "gn:country_code":"TR",
    "gn:dem":1464,
    "gn:feature_class":"P",
    "gn:feature_code":"PPL",
    "gn:name":"\u00c7ak\u0131lkaya",
    "gn:population":0,
    "gn:timezone":"Europe/Istanbul",
    "iso:country":"TR",
    "name:eng_x_preferred":[
        "\u00c7ak\u0131lkaya"
    ],
    "name:rus_x_preferred":[
        "\u0417\u043e\u0434\u0430\u043c\u0430"
    ],
    "name:und_x_variant":[
        "Zodama",
        "\u00c7ak\u0131ll\u0131kaya",
        "\u00c7ak\u0131lkaya"
    ],
    "wof:name":"Cakilkaya",
    "wof:placetype":"locality"
},
  "geometry": {"coordinates":[38.82927,40.20684],"type":"Point"}
}