{
  "type": "Feature",
  "properties": {
    "gn:admin1_code":"23",
    "gn:asciiname":"Deliktas",
    "gn:country_code":"TR",
    "gn:dem":821,
    "gn:feature_class":"P",
    "gn:feature_code":"PPL",
    "gn:name":"Delikta\u015f",
    "gn:population":0,
    "gn:timezone":"Europe/Istanbul",
    "iso:country":"TR",
    "name:und_x_variant":[
        "Talanusa\u011f\u0131 K\u00f6y\u00fc",
        "Delikta\u015f",
        "Talanu\u015fa\u011f\u0131"
    ],
    "wof:name":"Deliktas",
    "wof:placetype":"locality"
},
  "geometry": {"coordinates":[38.61932,38.47339],"type":"Point"}
}