{
  "type": "Feature",
  "properties": {
    "gn:admin1_code":"66",
    "gn:asciiname":"Karahisartatlisi",
    "gn:country_code":"TR",
    "gn:dem":1170,
    "gn:feature_class":"P",
    "gn:feature_code":"PPL",
    "gn:name":"Karahisartatl\u0131s\u0131",
    "gn:population":0,
    "gn:timezone":"Europe/Istanbul",
    "iso:country":"TR",
    "name:tur_x_preferred":[
        "Karahisartatl\u0131s\u0131"
    ],
    "name:und_x_variant":[
        "Babo",
        "Babu",
        "Karahisartarl\u0131s\u0131"
    ],
    "wof:name":"Karahisartatlisi",
    "wof:placetype":"locality"
},
  "geometry": {"coordinates":[35.64795,39.73177],"type":"Point"}
}