{
  "type": "Feature",
  "properties": {
    "gn:admin1_code":"71",
    "gn:asciiname":"Milyas",
    "gn:country_code":"TR",
    "gn:dem":981,
    "gn:feature_class":"P",
    "gn:feature_code":"PPL",
    "gn:name":"Milyas",
    "gn:population":0,
    "gn:timezone":"Europe/Istanbul",
    "iso:country":"TR",
    "name:deu_x_preferred":[
        "Milyas"
    ],
    "name:ita_x_preferred":[
        "Milias"
    ],
    "name:und_x_variant":[
        "S\u00f6\u011f\u00fctl\u00fc",
        "Milyas"
    ],
    "wof:name":"Milyas",
    "wof:placetype":"locality"
},
  "geometry": {"coordinates":[31.49516,38.39335],"type":"Point"}
}