{
  "type": "Feature",
  "properties": {
    "iso:country":"TR",
    "name:eng_x_preferred":[
        "Alemdag"
    ],
    "name:tur_x_preferred":[
        "Alemda\u011f"
    ],
    "wof:name":"Alemdag",
    "wof:placetype":"neighbourhood"
},
  "geometry": {"coordinates":[29.23981935198187,41.04904371646113],"type":"Point"}
}