{
  "type": "Feature",
  "properties": {
    "gn:admin1_code":"45",
    "gn:asciiname":"Kozluoren",
    "gn:country_code":"TR",
    "gn:dem":555,
    "gn:feature_class":"P",
    "gn:feature_code":"PPL",
    "gn:name":"Kozlu\u00f6ren",
    "gn:population":0,
    "gn:timezone":"Europe/Istanbul",
    "iso:country":"TR",
    "name:tur_x_preferred":[
        "Kozlu\u00f6ren"
    ],
    "name:tur_x_variant":[
        "Tahtac\u0131"
    ],
    "wof:name":"Kozluoren",
    "wof:placetype":"locality"
},
  "geometry": {"coordinates":[27.71753,39.2817],"type":"Point"}
}