{
  "type": "Feature",
  "properties": {
    "gn:admin1_code":"53.0",
    "gn:asciiname":"Soguksu",
    "gn:country_code":"TR",
    "gn:dem":439,
    "gn:feature_class":"P",
    "gn:feature_code":"PPL",
    "gn:name":"So\u011fuksu",
    "gn:population":0,
    "gn:timezone":"Europe/Istanbul",
    "iso:country":"TR",
    "name:und_x_variant":[
        "So\u011fuksu",
        "Samr\u0131"
    ],
    "wof:name":"Soguksu",
    "wof:placetype":"locality"
},
  "geometry": {"coordinates":[40.49001,40.84013],"type":"Point"}
}