{
  "type": "Feature",
  "properties": {
    "gn:admin1_code":"68.0",
    "gn:asciiname":"Sincik",
    "gn:country_code":"TR",
    "gn:dem":1037,
    "gn:feature_class":"P",
    "gn:feature_code":"PPL",
    "gn:name":"Sincik",
    "gn:population":0,
    "gn:timezone":"Europe/Istanbul",
    "iso:country":"TR",
    "name:ceb_x_preferred":[
        "Sincik \u0130l\u00e7esi"
    ],
    "name:ckb_x_preferred":[
        "\u0633\u0646\u062c\u0642"
    ],
    "name:deu_x_preferred":[
        "Sincik"
    ],
    "name:diq_x_preferred":[
        "S\u0131nc\u0131k"
    ],
    "name:fra_x_preferred":[
        "Sincik"
    ],
    "name:hye_x_preferred":[
        "\u054d\u056b\u0576\u057b\u056b\u0584"
    ],
    "name:ita_x_preferred":[
        "Sincik"
    ],
    "name:kur_x_preferred":[
        "Sincik"
    ],
    "name:lbe_x_preferred":[
        "\u0421\u0438\u043d\u0434\u0436\u0438\u043a"
    ],
    "name:mrj_x_preferred":[
        "\u0421\u0438\u043d\u0434\u0436\u0438\u043a"
    ],
    "name:msa_x_preferred":[
        "Sincik"
    ],
    "name:nld_x_preferred":[
        "Sincik"
    ],
    "name:nor_x_preferred":[
        "Sincik"
    ],
    "name:pnb_x_preferred":[
        "\u0636\u0644\u0639 \u0633\u0646\u0633\u06a9"
    ],
    "name:ron_x_preferred":[
        "Sincik"
    ],
    "name:rus_x_preferred":[
        "\u0421\u0438\u043d\u0434\u0436\u0438\u043a"
    ],
    "name:swa_x_preferred":[
        "Sincik"
    ],
    "name:tur_x_preferred":[
        "Sincik"
    ],
    "name:urd_x_preferred":[
        "\u0633\u0646\u062c\u06a9"
    ],
    "name:vie_x_preferred":[
        "Sincik"
    ],
    "wof:name":"Sincik",
    "wof:placetype":"locality"
},
  "geometry": {"coordinates":[32.27911,39.04804],"type":"Point"}
}