{
  "type": "Feature",
  "properties": {
    "gn:admin1_code":"68.0",
    "gn:asciiname":"Sincik",
    "gn:country_code":"TR",
    "gn:dem":1037,
    "gn:feature_class":"P",
    "gn:feature_code":"PPL",
    "gn:name":"Sincik",
    "gn:population":0,
    "gn:timezone":"Europe/Istanbul",
    "iso:country":"TR",
    "wof:name":"Sincik",
    "wof:placetype":"locality"
},
  "geometry": {"coordinates":[32.27911,39.04804],"type":"Point"}
}