{
  "type": "Feature",
  "properties": {
    "gn:admin1_code":"88",
    "gn:asciiname":"Yagli",
    "gn:country_code":"TR",
    "gn:dem":2087,
    "gn:feature_class":"P",
    "gn:feature_code":"PPL",
    "gn:name":"Ya\u011fl\u0131",
    "gn:population":0,
    "gn:timezone":"Europe/Istanbul",
    "iso:country":"TR",
    "name:und_x_variant":[
        "Ya\u011fl\u0131",
        "G\u00fclahmet"
    ],
    "wof:name":"Yagli",
    "wof:placetype":"locality"
},
  "geometry": {"coordinates":[43.72983,39.84434],"type":"Point"}
}