{
  "type": "Feature",
  "properties": {
    "gn:admin1_code":"8.0",
    "gn:asciiname":"Kuvartat",
    "gn:country_code":"TR",
    "gn:dem":1276,
    "gn:feature_class":"P",
    "gn:feature_code":"PPL",
    "gn:name":"Kuvartat",
    "gn:population":0,
    "gn:timezone":"Europe/Istanbul",
    "iso:country":"TR",
    "wof:name":"Kuvartat",
    "wof:placetype":"locality"
},
  "geometry": {"coordinates":[41.37087,40.95058],"type":"Point"}
}