{
  "type": "Feature",
  "properties": {
    "gn:admin1_code":"8.0",
    "gn:asciiname":"Gumusozu",
    "gn:country_code":"TR",
    "gn:dem":1345,
    "gn:feature_class":"P",
    "gn:feature_code":"PPL",
    "gn:name":"G\u00fcm\u00fc\u015f\u00f6z\u00fc",
    "gn:population":0,
    "gn:timezone":"Europe/Istanbul",
    "iso:country":"TR",
    "name:tur_x_preferred":[
        "G\u00fcm\u00fc\u015f\u00f6z\u00fc"
    ],
    "wof:name":"Gumusozu",
    "wof:placetype":"locality"
},
  "geometry": {"coordinates":[41.76773,40.67725],"type":"Point"}
}