{
  "type": "Feature",
  "properties": {
    "gn:admin1_code":"73",
    "gn:asciiname":"Kayirli",
    "gn:country_code":"TR",
    "gn:dem":1445,
    "gn:feature_class":"P",
    "gn:feature_code":"PPL",
    "gn:name":"Kay\u0131rl\u0131",
    "gn:population":0,
    "gn:timezone":"Europe/Istanbul",
    "iso:country":"TR",
    "name:ceb_x_preferred":[
        "Kay\u0131rl\u0131"
    ],
    "name:msa_x_preferred":[
        "Kay\u0131rl\u0131"
    ],
    "name:tur_x_preferred":[
        "Kay\u0131rl\u0131"
    ],
    "name:und_x_variant":[
        "Kay\u0131nl\u0131"
    ],
    "name:vie_x_preferred":[
        "Kay\u0131rl\u0131"
    ],
    "wof:name":"Kayirli",
    "wof:placetype":"locality"
},
  "geometry": {"coordinates":[34.5101,38.31838],"type":"Point"}
}