{
  "type": "Feature",
  "properties": {
    "gn:country":"TR",
    "gn:fcode":"PPL",
    "gn:pop":320,
    "iso:country":"TR",
    "name:ceb_x_preferred":[
        "P\u0131narba\u015f\u0131"
    ],
    "name:deu_x_preferred":[
        "P\u0131narba\u015f\u0131"
    ],
    "name:fra_x_preferred":[
        "P\u0131narba\u015f\u0131"
    ],
    "name:nld_x_preferred":[
        "P\u0131narba\u015f\u0131"
    ],
    "name:swe_x_preferred":[
        "P\u0131narba\u015f\u0131"
    ],
    "name:tur_x_preferred":[
        "P\u0131narba\u015f\u0131"
    ],
    "name:unk_x_variant":[
        "Matar"
    ],
    "qs:name":"P\u0131narba\u015f\u0131",
    "qs:photos_9r":0,
    "qs:photos_sr":0,
    "qs:pop_sr":"2",
    "wd:wordcount":139,
    "wof:name":"P\u0131narba\u015f\u0131",
    "wof:placetype":"locality",
    "wof:population":320
},
  "geometry": {"coordinates":[40.88,37.70833],"type":"Point"}
}