{
  "type": "Feature",
  "properties": {
    "iso:country":"TR",
    "qs:name":"Beyaz\u0131t A\u011fa",
    "qs:name_adm0":"Turkey",
    "qs:name_adm1":"\u0130stanbul",
    "qs:photos":27,
    "qs:photos_1k":5,
    "qs:photos_9k":1,
    "qs:photos_9r":2,
    "qs:photos_all":27,
    "qs:photos_sr":2,
    "qs:placetype":"Suburb",
    "qs:pop_sr":"0",
    "wof:name":"Beyaz\u0131t A\u011fa",
    "wof:placetype":"neighbourhood"
},
  "geometry": {"coordinates":[28.924388,41.019938],"type":"Point"}
}