{
  "type": "Feature",
  "properties": {
    "gn:admin1_code":"74",
    "gn:asciiname":"Guzelbag",
    "gn:country_code":"TR",
    "gn:dem":1557,
    "gn:feature_class":"P",
    "gn:feature_code":"PPL",
    "gn:name":"G\u00fczelba\u011f",
    "gn:population":0,
    "gn:timezone":"Europe/Istanbul",
    "iso:country":"TR",
    "wof:name":"Guzelbag",
    "wof:placetype":"locality"
},
  "geometry": {"coordinates":[42.7625,37.83528],"type":"Point"}
}