{
  "type": "Feature",
  "properties": {
    "gn:admin1_code":"20",
    "gn:asciiname":"Senkoy",
    "gn:country_code":"TR",
    "gn:dem":822,
    "gn:feature_class":"P",
    "gn:feature_code":"PPL",
    "gn:name":"\u015eenk\u00f6y",
    "gn:population":0,
    "gn:timezone":"Europe/Istanbul",
    "iso:country":"TR",
    "name:tur_x_preferred":[
        "\u015eenk\u00f6y"
    ],
    "name:tur_x_variant":[
        "\u00c7\u00f6pl\u00fc"
    ],
    "wof:name":"Senkoy",
    "wof:placetype":"locality"
},
  "geometry": {"coordinates":[29.74045,38.26196],"type":"Point"}
}