{
  "type": "Feature",
  "properties": {
    "gn:admin1_code":"55.0",
    "gn:asciiname":"Mezraa",
    "gn:country_code":"TR",
    "gn:dem":730,
    "gn:feature_class":"P",
    "gn:feature_code":"PPLA3",
    "gn:name":"Mezraa",
    "gn:population":0,
    "gn:timezone":"Europe/Istanbul",
    "iso:country":"TR",
    "name:tur_x_preferred":[
        "Mezraa"
    ],
    "wof:name":"Mezraa",
    "wof:placetype":"locality"
},
  "geometry": {"coordinates":[35.11684,41.19764],"type":"Point"}
}