{
  "type": "Feature",
  "properties": {
    "gn:admin1_code":"39",
    "gn:asciiname":"Yeni Mahalle",
    "gn:country_code":"TR",
    "gn:dem":145,
    "gn:feature_class":"P",
    "gn:feature_code":"PPL",
    "gn:name":"Yeni Mahalle",
    "gn:population":0,
    "gn:timezone":"Europe/Istanbul",
    "iso:country":"TR",
    "name:tur_x_preferred":[
        "Yeni Mahalle"
    ],
    "wof:name":"Yeni Mahalle",
    "wof:placetype":"locality"
},
  "geometry": {"coordinates":[27.98269,41.59684],"type":"Point"}
}