{
  "type": "Feature",
  "properties": {
    "gn:country":"TR",
    "gn:fcode":"PPL",
    "gn:pop":162,
    "iso:country":"TR",
    "name:tur_x_preferred":[
        "Karayi\u011fit"
    ],
    "qs:name":"Karayi\u011fit",
    "qs:photos_9r":0,
    "qs:photos_sr":0,
    "qs:pop_sr":"1",
    "wof:name":"Karayi\u011fit",
    "wof:placetype":"locality",
    "wof:population":162
},
  "geometry": {"coordinates":[40.79639,37.98389],"type":"Point"}
}