{
  "type": "Feature",
  "properties": {
    "gn:admin1_code":"59.0",
    "gn:asciiname":"Safaalan",
    "gn:country_code":"TR",
    "gn:dem":210,
    "gn:feature_class":"P",
    "gn:feature_code":"PPL",
    "gn:name":"Safaalan",
    "gn:population":0,
    "gn:timezone":"Europe/Istanbul",
    "iso:country":"TR",
    "name:und_x_variant":[
        "Fevziye",
        "Safaalan"
    ],
    "wof:name":"Safaalan",
    "wof:placetype":"locality"
},
  "geometry": {"coordinates":[28.09952,41.42623],"type":"Point"}
}