{
  "type": "Feature",
  "properties": {
    "gn:admin1_code":"26",
    "gn:asciiname":"Karakaya",
    "gn:country_code":"TR",
    "gn:dem":1073,
    "gn:feature_class":"P",
    "gn:feature_code":"PPL",
    "gn:name":"Karakaya",
    "gn:population":0,
    "gn:timezone":"Europe/Istanbul",
    "iso:country":"TR",
    "wof:name":"Karakaya",
    "wof:placetype":"locality"
},
  "geometry": {"coordinates":[31.24664000000001,39.51192],"type":"Point"}
}