{
  "type": "Feature",
  "properties": {
    "gn:admin1_code":"10",
    "gn:asciiname":"Guvencetmi",
    "gn:country_code":"TR",
    "gn:dem":340,
    "gn:feature_class":"P",
    "gn:feature_code":"PPL",
    "gn:name":"G\u00fcven\u00e7etmi",
    "gn:population":0,
    "gn:timezone":"Europe/Istanbul",
    "iso:country":"TR",
    "name:und_x_variant":[
        "G\u00fcvem\u00e7etmi",
        "G\u00fcven\u00e7etmi"
    ],
    "wof:name":"Guvencetmi",
    "wof:placetype":"locality"
},
  "geometry": {"coordinates":[28.07479,39.51893],"type":"Point"}
}