{
  "type": "Feature",
  "properties": {
    "gn:admin1_code":"89",
    "gn:asciiname":"Huseyinbeyoglu",
    "gn:country_code":"TR",
    "gn:dem":187,
    "gn:feature_class":"P",
    "gn:feature_code":"PPL",
    "gn:name":"H\u00fcseyinbeyo\u011flu",
    "gn:population":0,
    "gn:timezone":"Europe/Istanbul",
    "iso:country":"TR",
    "wof:name":"Huseyinbeyoglu",
    "wof:placetype":"locality"
},
  "geometry": {"coordinates":[32.35753,41.23581],"type":"Point"}
}