{
  "type": "Feature",
  "properties": {
    "gn:admin1_code":"38",
    "gn:asciiname":"Demircili",
    "gn:country_code":"TR",
    "gn:dem":1679,
    "gn:feature_class":"P",
    "gn:feature_code":"PPL",
    "gn:name":"Demircili",
    "gn:population":0,
    "gn:timezone":"Europe/Istanbul",
    "iso:country":"TR",
    "name:tur_x_preferred":[
        "Demircili"
    ],
    "wof:name":"Demircili",
    "wof:placetype":"locality"
},
  "geometry": {"coordinates":[36.32776,38.59072000000001],"type":"Point"}
}