{
  "type": "Feature",
  "properties": {
    "gn:admin1_code":"86.0",
    "gn:asciiname":"Yaylacik",
    "gn:country_code":"TR",
    "gn:dem":1923,
    "gn:feature_class":"P",
    "gn:feature_code":"PPL",
    "gn:name":"Yaylac\u0131k",
    "gn:population":0,
    "gn:timezone":"Europe/Istanbul",
    "iso:country":"TR",
    "name:und_x_variant":[
        "Yaylac\u0131k"
    ],
    "wof:name":"Yaylacik",
    "wof:placetype":"locality"
},
  "geometry": {"coordinates":[42.71255,41.08609000000001],"type":"Point"}
}