{
  "type": "Feature",
  "properties": {
    "gn:admin1_code":"15",
    "gn:asciiname":"Seydiler",
    "gn:country_code":"TR",
    "gn:dem":1208,
    "gn:feature_class":"P",
    "gn:feature_code":"PPL",
    "gn:name":"Seydiler",
    "gn:population":0,
    "gn:timezone":"Europe/Istanbul",
    "iso:country":"TR",
    "name:und_x_variant":[
        "Seyitler"
    ],
    "wof:name":"Seydiler",
    "wof:placetype":"locality"
},
  "geometry": {"coordinates":[29.81666,37.24431],"type":"Point"}
}