{
  "type": "Feature",
  "properties": {
    "gn:admin1_code":"15",
    "gn:asciiname":"Seydiler",
    "gn:country_code":"TR",
    "gn:dem":1208,
    "gn:feature_class":"P",
    "gn:feature_code":"PPL",
    "gn:name":"Seydiler",
    "gn:population":0,
    "gn:timezone":"Europe/Istanbul",
    "iso:country":"TR",
    "name:ceb_x_preferred":[
        "Seydiler \u0130l\u00e7esi"
    ],
    "name:deu_x_preferred":[
        "Seydiler"
    ],
    "name:fra_x_preferred":[
        "Seydiler"
    ],
    "name:mrj_x_preferred":[
        "\u0421\u0435\u0439\u0434\u0438\u043b\u0435\u0440"
    ],
    "name:msa_x_preferred":[
        "Seydiler"
    ],
    "name:nor_x_preferred":[
        "Seydiler"
    ],
    "name:pnb_x_preferred":[
        "\u0636\u0644\u0639 \u0633\u06cc\u062f\u0644\u0631"
    ],
    "name:swa_x_preferred":[
        "Seydiler"
    ],
    "name:tur_x_preferred":[
        "Seydiler"
    ],
    "name:und_x_variant":[
        "Seyitler"
    ],
    "name:urd_x_preferred":[
        "\u0633\u06cc\u062f\u06cc\u0644\u0631"
    ],
    "name:vie_x_preferred":[
        "Seydiler"
    ],
    "wof:name":"Seydiler",
    "wof:placetype":"locality"
},
  "geometry": {"coordinates":[29.81666,37.24431],"type":"Point"}
}