{
  "type": "Feature",
  "properties": {
    "gn:admin1_code":"60.0",
    "gn:asciiname":"Asagicandir",
    "gn:country_code":"TR",
    "gn:dem":209,
    "gn:feature_class":"P",
    "gn:feature_code":"PPL",
    "gn:name":"A\u015fa\u011f\u0131\u00e7and\u0131r",
    "gn:population":0,
    "gn:timezone":"Europe/Istanbul",
    "iso:country":"TR",
    "wof:name":"Asagicandir",
    "wof:placetype":"locality"
},
  "geometry": {"coordinates":[36.50609,40.70734],"type":"Point"}
}