{
  "type": "Feature",
  "properties": {
    "gn:admin1_code":"17.0",
    "gn:asciiname":"Guveylerobasi",
    "gn:country_code":"TR",
    "gn:dem":383,
    "gn:feature_class":"P",
    "gn:feature_code":"PPL",
    "gn:name":"G\u00fcveylerobas\u0131",
    "gn:population":0,
    "gn:timezone":"Europe/Istanbul",
    "iso:country":"TR",
    "name:und_x_variant":[
        "G\u00fcveyler",
        "G\u00fcveylerobas\u0131"
    ],
    "wof:name":"Guveylerobasi",
    "wof:placetype":"locality"
},
  "geometry": {"coordinates":[27.25286,40.03906],"type":"Point"}
}