{
  "type": "Feature",
  "properties": {
    "gn:admin1_code":"65.0",
    "gn:asciiname":"Kiragi",
    "gn:country_code":"TR",
    "gn:dem":2011,
    "gn:feature_class":"P",
    "gn:feature_code":"PPL",
    "gn:name":"K\u0131rag\u0131",
    "gn:population":0,
    "gn:timezone":"Europe/Istanbul",
    "iso:country":"TR",
    "name:tur_x_preferred":[
        "K\u0131rag\u0131"
    ],
    "wof:name":"Kiragi",
    "wof:placetype":"locality"
},
  "geometry": {"coordinates":[43.80194,38.35143],"type":"Point"}
}