{
  "type": "Feature",
  "properties": {
    "gn:admin1_code":"03",
    "gn:asciiname":"Baskimse",
    "gn:country_code":"TR",
    "gn:dem":1181,
    "gn:feature_class":"P",
    "gn:feature_code":"PPL",
    "gn:name":"Ba\u015fkimse",
    "gn:population":0,
    "gn:timezone":"Europe/Istanbul",
    "iso:country":"TR",
    "wof:name":"Baskimse",
    "wof:placetype":"locality"
},
  "geometry": {"coordinates":[30.20277,38.86335],"type":"Point"}
}