{
  "type": "Feature",
  "properties": {
    "gn:admin1_code":"63",
    "gn:asciiname":"Topac",
    "gn:country_code":"TR",
    "gn:dem":745,
    "gn:feature_class":"P",
    "gn:feature_code":"PPL",
    "gn:name":"Topa\u00e7",
    "gn:population":0,
    "gn:timezone":"Europe/Istanbul",
    "iso:country":"TR",
    "name:tur_x_preferred":[
        "Topa\u00e7"
    ],
    "wof:name":"Topac",
    "wof:placetype":"locality"
},
  "geometry": {"coordinates":[39.23444,37.80944],"type":"Point"}
}