{
  "type": "Feature",
  "properties": {
    "gn:admin1_code":"45.0",
    "gn:asciiname":"Adiloba",
    "gn:country_code":"TR",
    "gn:dem":37,
    "gn:feature_class":"P",
    "gn:feature_code":"PPL",
    "gn:name":"Adiloba",
    "gn:population":0,
    "gn:timezone":"Europe/Istanbul",
    "iso:country":"TR",
    "name:tur_x_preferred":[
        "Adiloba"
    ],
    "wof:name":"Adiloba",
    "wof:placetype":"locality"
},
  "geometry": {"coordinates":[27.55,38.75],"type":"Point"}
}