{
  "type": "Feature",
  "properties": {
    "gn:admin1_code":"89.0",
    "gn:asciiname":"Doganlar",
    "gn:country_code":"TR",
    "gn:dem":872,
    "gn:feature_class":"P",
    "gn:feature_code":"PPL",
    "gn:name":"Do\u011fanlar",
    "gn:population":0,
    "gn:timezone":"Europe/Istanbul",
    "iso:country":"TR",
    "name:und_x_variant":[
        "Do\u011fanlar",
        "Karak\u00f6y"
    ],
    "wof:name":"Doganlar",
    "wof:placetype":"locality"
},
  "geometry": {"coordinates":[32.93136,41.03905],"type":"Point"}
}