{
  "type": "Feature",
  "properties": {
    "gn:admin1_code":"92.0",
    "gn:asciiname":"Fistikli",
    "gn:country_code":"TR",
    "gn:dem":23,
    "gn:feature_class":"P",
    "gn:feature_code":"PPL",
    "gn:name":"F\u0131st\u0131kl\u0131",
    "gn:population":0,
    "gn:timezone":"Europe/Istanbul",
    "iso:country":"TR",
    "wof:name":"Fistikli",
    "wof:placetype":"locality"
},
  "geometry": {"coordinates":[28.89512,40.49226],"type":"Point"}
}