{
  "type": "Feature",
  "properties": {
    "gn:admin1_code":"32",
    "gn:asciiname":"Gozce",
    "gn:country_code":"TR",
    "gn:dem":7,
    "gn:feature_class":"P",
    "gn:feature_code":"PPL",
    "gn:name":"G\u00f6zce",
    "gn:population":0,
    "gn:timezone":"Europe/Istanbul",
    "iso:country":"TR",
    "name:und_x_variant":[
        "G\u00f6zce",
        "\u00c7ad\u0131r"
    ],
    "wof:name":"Gozce",
    "wof:placetype":"locality"
},
  "geometry": {"coordinates":[33.16924,36.13744000000001],"type":"Point"}
}