{
  "type": "Feature",
  "properties": {
    "gn:admin1_code":"09",
    "gn:asciiname":"Bekirler",
    "gn:country_code":"TR",
    "gn:dem":653,
    "gn:feature_class":"P",
    "gn:feature_code":"PPL",
    "gn:name":"Bekirler",
    "gn:population":0,
    "gn:timezone":"Europe/Istanbul",
    "iso:country":"TR",
    "name:tur_x_preferred":[
        "Bekirler"
    ],
    "wof:name":"Bekirler",
    "wof:placetype":"locality"
},
  "geometry": {"coordinates":[28.40462,38.01553],"type":"Point"}
}