{
  "type": "Feature",
  "properties": {
    "gn:admin1_code":"69.0",
    "gn:asciiname":"Demiroren",
    "gn:country_code":"TR",
    "gn:dem":2201,
    "gn:feature_class":"P",
    "gn:feature_code":"PPL",
    "gn:name":"Demir\u00f6ren",
    "gn:population":0,
    "gn:timezone":"Europe/Istanbul",
    "iso:country":"TR",
    "name:und_x_variant":[
        "Demirveren",
        "Demir\u00f6ren"
    ],
    "wof:name":"Demiroren",
    "wof:placetype":"locality"
},
  "geometry": {"coordinates":[39.8482,40.46061],"type":"Point"}
}