{
  "type": "Feature",
  "properties": {
    "gn:admin1_code":"13.0",
    "gn:asciiname":"Catalagzi",
    "gn:country_code":"TR",
    "gn:dem":1932,
    "gn:feature_class":"P",
    "gn:feature_code":"PPL",
    "gn:name":"\u00c7atala\u011fz\u0131",
    "gn:population":0,
    "gn:timezone":"Europe/Istanbul",
    "iso:country":"TR",
    "name:tur_x_preferred":[
        "\u00c7atala\u011fz\u0131"
    ],
    "wof:name":"Catalagzi",
    "wof:placetype":"locality"
},
  "geometry": {"coordinates":[42.43848,38.79566],"type":"Point"}
}