{
  "type": "Feature",
  "properties": {
    "gn:admin1_code":"82.0",
    "gn:asciiname":"Duzankara",
    "gn:country_code":"TR",
    "gn:dem":1171,
    "gn:feature_class":"P",
    "gn:feature_code":"PPL",
    "gn:name":"D\u00fczankara",
    "gn:population":0,
    "gn:timezone":"Europe/Istanbul",
    "iso:country":"TR",
    "wof:name":"Duzankara",
    "wof:placetype":"locality"
},
  "geometry": {"coordinates":[34.0531,40.72174],"type":"Point"}
}