{
  "type": "Feature",
  "properties": {
    "gn:admin1_code":"65",
    "gn:asciiname":"Sagmali",
    "gn:country_code":"TR",
    "gn:dem":2032,
    "gn:feature_class":"P",
    "gn:feature_code":"PPL",
    "gn:name":"Sa\u011fmal\u0131",
    "gn:population":0,
    "gn:timezone":"Europe/Istanbul",
    "iso:country":"TR",
    "name:und_x_variant":[
        "A\u015fa\u011f\u0131no\u015far",
        "A\u015fa\u011f\u0131 Nev\u015far",
        "A\u015fa\u011f\u0131sa\u011fmall\u0131",
        "Sa\u011fmal\u0131"
    ],
    "wof:name":"Sagmali",
    "wof:placetype":"locality"
},
  "geometry": {"coordinates":[44.01505,38.85828],"type":"Point"}
}