{
  "type": "Feature",
  "properties": {
    "gn:admin1_code":"35",
    "gn:asciiname":"Koprubasi",
    "gn:country_code":"TR",
    "gn:dem":68,
    "gn:feature_class":"P",
    "gn:feature_code":"PPL",
    "gn:name":"K\u00f6pr\u00fcba\u015f\u0131",
    "gn:population":0,
    "gn:timezone":"Europe/Istanbul",
    "iso:country":"TR",
    "name:tur_x_preferred":[
        "K\u00f6pr\u00fcba\u015f\u0131"
    ],
    "wof:name":"Koprubasi",
    "wof:placetype":"locality"
},
  "geometry": {"coordinates":[27.05153,38.0594],"type":"Point"}
}