{
  "type": "Feature",
  "properties": {
    "gn:admin1_code":"37.0",
    "gn:asciiname":"Sakizcilar",
    "gn:country_code":"TR",
    "gn:dem":455,
    "gn:feature_class":"P",
    "gn:feature_code":"PPL",
    "gn:name":"Sak\u0131zc\u0131lar",
    "gn:population":0,
    "gn:timezone":"Europe/Istanbul",
    "iso:country":"TR",
    "wof:name":"Sakizcilar",
    "wof:placetype":"locality"
},
  "geometry": {"coordinates":[34.03592,41.87649],"type":"Point"}
}