{
  "type": "Feature",
  "properties": {
    "gn:admin1_code":"12.0",
    "gn:asciiname":"Saridibek",
    "gn:country_code":"TR",
    "gn:dem":1759,
    "gn:feature_class":"P",
    "gn:feature_code":"PPL",
    "gn:name":"Sar\u0131dibek",
    "gn:population":0,
    "gn:timezone":"Europe/Istanbul",
    "iso:country":"TR",
    "name:tur_x_preferred":[
        "Sar\u0131dibek"
    ],
    "wof:name":"Saridibek",
    "wof:placetype":"locality"
},
  "geometry": {"coordinates":[40.65649000000001,39.13873],"type":"Point"}
}