{
  "type": "Feature",
  "properties": {
    "gn:admin1_code":"75",
    "gn:asciiname":"Yagan",
    "gn:country_code":"TR",
    "gn:dem":1153,
    "gn:feature_class":"P",
    "gn:feature_code":"PPL",
    "gn:name":"Ya\u011fan",
    "gn:population":0,
    "gn:timezone":"Europe/Istanbul",
    "iso:country":"TR",
    "name:msa_x_preferred":[
        "Ya\u011fan"
    ],
    "name:tur_x_preferred":[
        "Ya\u011fan"
    ],
    "name:urd_x_preferred":[
        "\u06cc\u0627\u06af\u0627\u0646"
    ],
    "name:vie_x_preferred":[
        "Ya\u011fan"
    ],
    "wof:name":"Yagan",
    "wof:placetype":"locality"
},
  "geometry": {"coordinates":[34.04002,38.53743],"type":"Point"}
}