{
  "type": "Feature",
  "properties": {
    "gn:admin1_code":"65",
    "gn:asciiname":"Yatirli",
    "gn:country_code":"TR",
    "gn:dem":2336,
    "gn:feature_class":"P",
    "gn:feature_code":"PPL",
    "gn:name":"Yat\u0131rl\u0131",
    "gn:population":0,
    "gn:timezone":"Europe/Istanbul",
    "iso:country":"TR",
    "name:und_x_variant":[
        "Hac\u0131ziyaret",
        "Yat\u0131rl\u0131"
    ],
    "wof:name":"Yatirli",
    "wof:placetype":"locality"
},
  "geometry": {"coordinates":[43.7988,39.20676],"type":"Point"}
}