{
  "type": "Feature",
  "properties": {
    "gn:admin1_code":"14",
    "gn:asciiname":"Bolukoren",
    "gn:country_code":"TR",
    "gn:dem":854,
    "gn:feature_class":"P",
    "gn:feature_code":"PPL",
    "gn:name":"B\u00f6l\u00fck\u00f6ren",
    "gn:population":0,
    "gn:timezone":"Europe/Istanbul",
    "iso:country":"TR",
    "wof:name":"Bolukoren",
    "wof:placetype":"locality"
},
  "geometry": {"coordinates":[32.02412,40.95933],"type":"Point"}
}