{
  "type": "Feature",
  "properties": {
    "gn:admin1_code":"44",
    "gn:asciiname":"Kozdere",
    "gn:country_code":"TR",
    "gn:dem":1511,
    "gn:feature_class":"P",
    "gn:feature_code":"PPL",
    "gn:name":"Kozdere",
    "gn:population":0,
    "gn:timezone":"Europe/Istanbul",
    "iso:country":"TR",
    "name:und_x_variant":[
        "Kozdere K\u00f6y\u00fc",
        "Kozdere"
    ],
    "wof:name":"Kozdere",
    "wof:placetype":"locality"
},
  "geometry": {"coordinates":[38.06071,38.90991],"type":"Point"}
}