{
  "type": "Feature",
  "properties": {
    "gn:admin1_code":"22.0",
    "gn:asciiname":"Omeroba",
    "gn:country_code":"TR",
    "gn:dem":351,
    "gn:feature_class":"P",
    "gn:feature_code":"PPL",
    "gn:name":"\u00d6meroba",
    "gn:population":0,
    "gn:timezone":"Europe/Istanbul",
    "iso:country":"TR",
    "name:und_x_variant":[
        "\u00d6meroba",
        "\u00d6merobak\u00f6y"
    ],
    "wof:name":"Omeroba",
    "wof:placetype":"locality"
},
  "geometry": {"coordinates":[26.93059,41.9236],"type":"Point"}
}