{
  "type": "Feature",
  "properties": {
    "gn:admin1_code":"68",
    "gn:asciiname":"Solakusagi",
    "gn:country_code":"TR",
    "gn:dem":1034,
    "gn:feature_class":"P",
    "gn:feature_code":"PPL",
    "gn:name":"Solaku\u015fa\u011f\u0131",
    "gn:population":0,
    "gn:timezone":"Europe/Istanbul",
    "iso:country":"TR",
    "wof:name":"Solakusagi",
    "wof:placetype":"locality"
},
  "geometry": {"coordinates":[33.70185,39.04421],"type":"Point"}
}