{
  "type": "Feature",
  "properties": {
    "gn:admin1_code":"63.0",
    "gn:asciiname":"Celoglu",
    "gn:country_code":"TR",
    "gn:dem":397,
    "gn:feature_class":"P",
    "gn:feature_code":"PPL",
    "gn:name":"\u00c7elo\u011flu",
    "gn:population":0,
    "gn:timezone":"Europe/Istanbul",
    "iso:country":"TR",
    "name:und_x_variant":[
        "Cheloglu",
        "\u00c7alo\u011flu",
        "\u00c7elo\u011flu"
    ],
    "wof:name":"Celoglu",
    "wof:placetype":"locality"
},
  "geometry": {"coordinates":[38.07176,36.87215],"type":"Point"}
}