{
  "type": "Feature",
  "properties": {
    "gn:admin1_code":"24",
    "gn:asciiname":"Harmantepe",
    "gn:country_code":"TR",
    "gn:dem":1477,
    "gn:feature_class":"P",
    "gn:feature_code":"PPL",
    "gn:name":"Harmantepe",
    "gn:population":0,
    "gn:timezone":"Europe/Istanbul",
    "iso:country":"TR",
    "name:und_x_variant":[
        "Ma\u011fiker",
        "Mi\u011fik\u00e2r",
        "Harmantepe"
    ],
    "wof:name":"Harmantepe",
    "wof:placetype":"locality"
},
  "geometry": {"coordinates":[40.08413,39.82778],"type":"Point"}
}