{
  "type": "Feature",
  "properties": {
    "gn:country":"TR",
    "gn:fcode":"PPL",
    "gn:population":379,
    "iso:country":"TR",
    "name:tur_x_preferred":[
        "Ya\u011fmuralan"
    ],
    "qs:name":"Ya\u011fmuralan",
    "qs:photos_9r":0,
    "qs:photos_sr":0,
    "qs:pop_sr":"2",
    "wof:name":"Ya\u011fmuralan",
    "wof:placetype":"locality",
    "wof:population":379
},
  "geometry": {"coordinates":[38.68361,36.74694],"type":"Point"}
}