{
  "type": "Feature",
  "properties": {
    "gn:admin1_code":"2.0",
    "gn:asciiname":"Akbulut",
    "gn:country_code":"TR",
    "gn:dem":664,
    "gn:feature_class":"P",
    "gn:feature_code":"PPL",
    "gn:name":"Akbulut",
    "gn:population":0,
    "gn:timezone":"Europe/Istanbul",
    "iso:country":"TR",
    "wof:name":"Akbulut",
    "wof:placetype":"locality"
},
  "geometry": {"coordinates":[38.38715,37.79711],"type":"Point"}
}