{
  "type": "Feature",
  "properties": {
    "gn:admin1_code":"2.0",
    "gn:asciiname":"Akbulut",
    "gn:country_code":"TR",
    "gn:dem":664,
    "gn:feature_class":"P",
    "gn:feature_code":"PPL",
    "gn:name":"Akbulut",
    "gn:population":0,
    "gn:timezone":"Europe/Istanbul",
    "iso:country":"TR",
    "name:deu_x_preferred":[
        "Akbulut"
    ],
    "name:kor_x_preferred":[
        "\uc544\ud06c\ubd88\ub8e8\ud2b8"
    ],
    "name:nld_x_preferred":[
        "Akbulut"
    ],
    "name:rus_x_preferred":[
        "\u0410\u043a\u0431\u0443\u043b\u0443\u0442"
    ],
    "name:tur_x_preferred":[
        "Akbulut"
    ],
    "wof:name":"Akbulut",
    "wof:placetype":"locality"
},
  "geometry": {"coordinates":[38.38715,37.79711],"type":"Point"}
}