{
  "type": "Feature",
  "properties": {
    "gn:admin1_code":"44.0",
    "gn:asciiname":"Kucukkurne",
    "gn:country_code":"TR",
    "gn:dem":1532,
    "gn:feature_class":"P",
    "gn:feature_code":"PPL",
    "gn:name":"K\u00fc\u00e7\u00fckk\u00fcrne",
    "gn:population":0,
    "gn:timezone":"Europe/Istanbul",
    "iso:country":"TR",
    "name:tur_x_preferred":[
        "K\u00fc\u00e7\u00fckk\u00fcrne"
    ],
    "name:und_x_variant":[
        "K\u00fc\u00e7\u00fckk\u00fcme"
    ],
    "wof:name":"Kucukkurne",
    "wof:placetype":"locality"
},
  "geometry": {"coordinates":[37.85291,38.46213],"type":"Point"}
}