{
  "type": "Feature",
  "properties": {
    "gn:admin1_code":"4.0",
    "gn:asciiname":"Abdikoy",
    "gn:country_code":"TR",
    "gn:dem":1879,
    "gn:feature_class":"P",
    "gn:feature_code":"PPL",
    "gn:name":"Abdik\u00f6y",
    "gn:population":0,
    "gn:timezone":"Europe/Istanbul",
    "iso:country":"TR",
    "name:und_x_variant":[
        "Abdik\u00f6y",
        "Abdi"
    ],
    "wof:name":"Abdikoy",
    "wof:placetype":"locality"
},
  "geometry": {"coordinates":[42.55887,39.72749],"type":"Point"}
}