{
  "type": "Feature",
  "properties": {
    "gn:admin1_code":"26",
    "gn:asciiname":"Yusuflar",
    "gn:country_code":"TR",
    "gn:dem":845,
    "gn:feature_class":"P",
    "gn:feature_code":"PPL",
    "gn:name":"Yusuflar",
    "gn:population":0,
    "gn:timezone":"Europe/Istanbul",
    "iso:country":"TR",
    "name:und_x_variant":[
        "Ak\u00e7inyusuflar",
        "Ak\u00e7in",
        "Yusuflar"
    ],
    "wof:name":"Yusuflar",
    "wof:placetype":"locality"
},
  "geometry": {"coordinates":[30.36779000000001,39.76198],"type":"Point"}
}