{
  "type": "Feature",
  "properties": {
    "gn:admin1_code":"03",
    "gn:asciiname":"Tinaztepe",
    "gn:country_code":"TR",
    "gn:dem":1105,
    "gn:feature_class":"P",
    "gn:feature_code":"PPL",
    "gn:name":"T\u0131naztepe",
    "gn:population":0,
    "gn:timezone":"Europe/Istanbul",
    "iso:country":"TR",
    "wof:name":"Tinaztepe",
    "wof:placetype":"locality"
},
  "geometry": {"coordinates":[30.37833,38.72861],"type":"Point"}
}