{
  "type": "Feature",
  "properties": {
    "gn:admin1_code":"02",
    "gn:asciiname":"Karaagac",
    "gn:country_code":"TR",
    "gn:dem":836,
    "gn:feature_class":"P",
    "gn:feature_code":"PPL",
    "gn:name":"Karaa\u011fa\u00e7",
    "gn:population":0,
    "gn:timezone":"Europe/Istanbul",
    "iso:country":"TR",
    "name:und_x_variant":[
        "Karamusal\u0131",
        "Karamustafa",
        "Karaa\u011fa\u00e7"
    ],
    "wof:name":"Karaagac",
    "wof:placetype":"locality"
},
  "geometry": {"coordinates":[37.91049,37.67573],"type":"Point"}
}