{
  "type": "Feature",
  "properties": {
    "gn:admin1_code":"24",
    "gn:asciiname":"Leventler",
    "gn:country_code":"TR",
    "gn:dem":1790,
    "gn:feature_class":"P",
    "gn:feature_code":"PPL",
    "gn:name":"Leventler",
    "gn:population":0,
    "gn:timezone":"Europe/Istanbul",
    "iso:country":"TR",
    "name:tur_x_preferred":[
        "Leventler"
    ],
    "wof:name":"Leventler",
    "wof:placetype":"locality"
},
  "geometry": {"coordinates":[38.97983,39.96431],"type":"Point"}
}