{
  "type": "Feature",
  "properties": {
    "gn:admin1_code":"20",
    "gn:asciiname":"Kelekci",
    "gn:country_code":"TR",
    "gn:dem":815,
    "gn:feature_class":"P",
    "gn:feature_code":"PPLA3",
    "gn:name":"Kelek\u00e7i",
    "gn:population":0,
    "gn:timezone":"Europe/Istanbul",
    "iso:country":"TR",
    "name:tur_x_preferred":[
        "Kelek\u00e7i"
    ],
    "name:und_x_variant":[
        "Kelkelci"
    ],
    "wof:name":"Kelekci",
    "wof:placetype":"locality"
},
  "geometry": {"coordinates":[29.30425,37.24073],"type":"Point"}
}