{
  "type": "Feature",
  "properties": {
    "gn:admin1_code":"76.0",
    "gn:asciiname":"Bitam",
    "gn:country_code":"TR",
    "gn:dem":728,
    "gn:feature_class":"P",
    "gn:feature_code":"PPL",
    "gn:name":"Bitam",
    "gn:population":0,
    "gn:timezone":"Europe/Istanbul",
    "iso:country":"TR",
    "name:ben_x_preferred":[
        "\u09ac\u09bf\u09a4\u09be\u09ae"
    ],
    "name:bul_x_preferred":[
        "\u0411\u0438\u0442\u0430\u043c"
    ],
    "name:ceb_x_preferred":[
        "Bitam"
    ],
    "name:deu_x_preferred":[
        "Bitam"
    ],
    "name:ell_x_preferred":[
        "\u039c\u03c0\u03b9\u03c4\u03ac\u03bc"
    ],
    "name:fas_x_preferred":[
        "\u0628\u06cc\u062a\u0627\u0645"
    ],
    "name:fra_x_preferred":[
        "Bitam"
    ],
    "name:hin_x_preferred":[
        "\u092c\u093f\u0924\u092e"
    ],
    "name:hun_x_preferred":[
        "Bitam"
    ],
    "name:ind_x_preferred":[
        "Bitam"
    ],
    "name:ita_x_preferred":[
        "Bitam"
    ],
    "name:kor_x_preferred":[
        "\ube44\ud0d0"
    ],
    "name:lit_x_preferred":[
        "Bitamas"
    ],
    "name:nld_x_preferred":[
        "Bitam"
    ],
    "name:nor_x_preferred":[
        "Bitam"
    ],
    "name:pol_x_preferred":[
        "Bitam"
    ],
    "name:por_x_preferred":[
        "Bitam"
    ],
    "name:rus_x_preferred":[
        "\u0411\u0438\u0442\u0430\u043c"
    ],
    "name:spa_x_preferred":[
        "Bitam"
    ],
    "name:swe_x_preferred":[
        "Bitam"
    ],
    "name:tur_x_preferred":[
        "Bitam"
    ],
    "name:ukr_x_preferred":[
        "\u0411\u0456\u0442\u0430\u043c"
    ],
    "name:urd_x_preferred":[
        "\u0628\u06cc\u0679\u0627\u0645"
    ],
    "name:vie_x_preferred":[
        "Bitam"
    ],
    "wof:name":"Bitam",
    "wof:placetype":"locality"
},
  "geometry": {"coordinates":[41.66333,37.80667],"type":"Point"}
}