{
  "type": "Feature",
  "properties": {
    "gn:admin1_code":"63.0",
    "gn:asciiname":"Darik",
    "gn:country_code":"TR",
    "gn:dem":477,
    "gn:feature_class":"P",
    "gn:feature_code":"PPL",
    "gn:name":"Darik",
    "gn:population":0,
    "gn:timezone":"Europe/Istanbul",
    "iso:country":"TR",
    "wof:name":"Darik",
    "wof:placetype":"locality"
},
  "geometry": {"coordinates":[38.445,36.90861],"type":"Point"}
}