{
  "type": "Feature",
  "properties": {
    "gn:admin1_code":"63.0",
    "gn:asciiname":"Darik",
    "gn:country_code":"TR",
    "gn:dem":477,
    "gn:feature_class":"P",
    "gn:feature_code":"PPL",
    "gn:name":"Darik",
    "gn:population":0,
    "gn:timezone":"Europe/Istanbul",
    "iso:country":"TR",
    "name:aze_x_preferred":[
        "\u00d6ks\u00fcz"
    ],
    "name:bul_x_preferred":[
        "\u0414\u0430\u0440\u0438\u043a"
    ],
    "name:fas_x_preferred":[
        "\u062f\u0627\u0631\u06cc\u06a9"
    ],
    "name:hye_x_preferred":[
        "\u0534\u0561\u0580\u056b\u056f"
    ],
    "name:kat_x_preferred":[
        "\u10d3\u10d0\u10e0\u10d8\u10d9\u10d8"
    ],
    "name:spa_x_preferred":[
        "Darik"
    ],
    "wof:name":"Darik",
    "wof:placetype":"locality"
},
  "geometry": {"coordinates":[38.445,36.90861],"type":"Point"}
}