{
  "type": "Feature",
  "properties": {
    "gn:admin1_code":"03",
    "gn:asciiname":"Cayiryazi",
    "gn:cc2":"TR",
    "gn:country_code":"TR",
    "gn:dem":1048,
    "gn:feature_class":"P",
    "gn:feature_code":"PPL",
    "gn:name":"\u00c7ay\u0131ryaz\u0131",
    "gn:population":0,
    "gn:timezone":"Europe/Istanbul",
    "iso:country":"TR",
    "name:und_x_variant":[
        "Geneli",
        "\u00c7ay\u0131ryaz\u0131"
    ],
    "wof:name":"Cayiryazi",
    "wof:placetype":"locality"
},
  "geometry": {"coordinates":[30.74139000000001,38.36806],"type":"Point"}
}