{
  "type": "Feature",
  "properties": {
    "gn:admin1_code":"32",
    "gn:asciiname":"Guzelkoy",
    "gn:country_code":"TR",
    "gn:dem":414,
    "gn:feature_class":"P",
    "gn:feature_code":"PPL",
    "gn:name":"G\u00fczelk\u00f6y",
    "gn:population":0,
    "gn:timezone":"Europe/Istanbul",
    "iso:country":"TR",
    "name:tur_x_preferred":[
        "G\u00fczelk\u00f6y"
    ],
    "wof:name":"Guzelkoy",
    "wof:placetype":"locality"
},
  "geometry": {"coordinates":[33.37344,36.52554],"type":"Point"}
}