{
  "type": "Feature",
  "properties": {
    "gn:admin1_code":"40",
    "gn:asciiname":"Kalekoy",
    "gn:country_code":"TR",
    "gn:dem":1288,
    "gn:feature_class":"P",
    "gn:feature_code":"PPL",
    "gn:name":"Kalek\u00f6y",
    "gn:population":0,
    "gn:timezone":"Europe/Istanbul",
    "iso:country":"TR",
    "wof:name":"Kalekoy",
    "wof:placetype":"locality"
},
  "geometry": {"coordinates":[33.87784,39.36904000000001],"type":"Point"}
}