{
  "type": "Feature",
  "properties": {
    "gn:admin1_code":"23",
    "gn:asciiname":"Keklikkoy",
    "gn:country_code":"TR",
    "gn:dem":1650,
    "gn:feature_class":"P",
    "gn:feature_code":"PPL",
    "gn:name":"Keklikk\u00f6y",
    "gn:population":0,
    "gn:timezone":"Europe/Istanbul",
    "iso:country":"TR",
    "name:und_x_variant":[
        "Keklik",
        "Keklikk\u00f6y"
    ],
    "wof:name":"Keklikkoy",
    "wof:placetype":"locality"
},
  "geometry": {"coordinates":[40.19427,39.11247],"type":"Point"}
}