{
  "type": "Feature",
  "properties": {
    "gn:admin1_code":"86.0",
    "gn:asciiname":"Karakale",
    "gn:country_code":"TR",
    "gn:dem":2139,
    "gn:feature_class":"P",
    "gn:feature_code":"PPL",
    "gn:name":"Karakale",
    "gn:population":0,
    "gn:timezone":"Europe/Istanbul",
    "iso:country":"TR",
    "name:eng_x_preferred":[
        "Karakale"
    ],
    "name:rus_x_preferred":[
        "\u041a\u0430\u0440\u0430\u0433\u0430\u043b\u0435"
    ],
    "wof:name":"Karakale",
    "wof:placetype":"locality"
},
  "geometry": {"coordinates":[42.72306,41.33896],"type":"Point"}
}