{
  "type": "Feature",
  "properties": {
    "gn:admin1_code":"49",
    "gn:asciiname":"Koprucuk",
    "gn:country_code":"TR",
    "gn:dem":1696,
    "gn:feature_class":"P",
    "gn:feature_code":"PPL",
    "gn:name":"K\u00f6pr\u00fcc\u00fck",
    "gn:population":0,
    "gn:timezone":"Europe/Istanbul",
    "iso:country":"TR",
    "name:tur_x_preferred":[
        "K\u00f6pr\u00fcc\u00fck"
    ],
    "wof:name":"Koprucuk",
    "wof:placetype":"locality"
},
  "geometry": {"coordinates":[41.2032,39.27134],"type":"Point"}
}