{
  "type": "Feature",
  "properties": {
    "gn:admin1_code":"31.0",
    "gn:asciiname":"Karagecili",
    "gn:country_code":"TR",
    "gn:dem":293,
    "gn:feature_class":"P",
    "gn:feature_code":"PPL",
    "gn:name":"Karagecili",
    "gn:population":0,
    "gn:timezone":"Europe/Istanbul",
    "iso:country":"TR",
    "name:und_x_variant":[
        "Melek"
    ],
    "wof:name":"Karagecili",
    "wof:placetype":"locality"
},
  "geometry": {"coordinates":[36.08931,36.24368],"type":"Point"}
}