{
  "type": "Feature",
  "properties": {
    "gn:admin1_code":"81",
    "gn:asciiname":"Kirikusagi",
    "gn:country_code":"TR",
    "gn:dem":1464,
    "gn:feature_class":"P",
    "gn:feature_code":"PPL",
    "gn:name":"K\u0131r\u0131ku\u015fag\u0131",
    "gn:population":0,
    "gn:timezone":"Europe/Istanbul",
    "iso:country":"TR",
    "wof:name":"Kirikusagi",
    "wof:placetype":"locality"
},
  "geometry": {"coordinates":[35.98522,37.79941],"type":"Point"}
}