{
  "type": "Feature",
  "properties": {
    "gn:admin1_code":"31.0",
    "gn:asciiname":"Yudzhekyshla",
    "gn:country_code":"TR",
    "gn:dem":195,
    "gn:feature_class":"P",
    "gn:feature_code":"PPL",
    "gn:name":"Yudzhekyshla",
    "gn:population":0,
    "gn:timezone":"Europe/Istanbul",
    "iso:country":"TR",
    "name:und_x_variant":[
        "Y\u00fccek\u0131\u015fla"
    ],
    "wof:name":"Yudzhekyshla",
    "wof:placetype":"locality"
},
  "geometry": {"coordinates":[36.50492,36.66269000000001],"type":"Point"}
}