{
  "type": "Feature",
  "properties": {
    "gn:admin1_code":"80",
    "gn:asciiname":"Ikili",
    "gn:cc2":"TR",
    "gn:country_code":"TR",
    "gn:dem":2316,
    "gn:feature_class":"P",
    "gn:feature_code":"PPL",
    "gn:name":"\u0130kili",
    "gn:population":0,
    "gn:timezone":"Europe/Istanbul",
    "iso:country":"TR",
    "name:und_x_variant":[
        "Simhata",
        "Simkhata",
        "\u0130kili"
    ],
    "wof:name":"Ikili",
    "wof:placetype":"locality"
},
  "geometry": {"coordinates":[43.28611,37.66972],"type":"Point"}
}