{
  "type": "Feature",
  "properties": {
    "gn:admin1_code":"83",
    "gn:asciiname":"Dahni",
    "gn:country_code":"TR",
    "gn:dem":619,
    "gn:feature_class":"P",
    "gn:feature_code":"PPL",
    "gn:name":"Dahni",
    "gn:population":0,
    "gn:timezone":"Europe/Istanbul",
    "iso:country":"TR",
    "name:und_x_variant":[
        "\u00c7avu\u015fba\u015f\u0131"
    ],
    "wof:name":"Dahni",
    "wof:placetype":"locality"
},
  "geometry": {"coordinates":[37.49447,36.82976],"type":"Point"}
}