{
  "type": "Feature",
  "properties": {
    "gn:admin1_code":"11.0",
    "gn:asciiname":"Gokcekaya",
    "gn:country_code":"TR",
    "gn:dem":754,
    "gn:feature_class":"P",
    "gn:feature_code":"PPL",
    "gn:name":"G\u00f6k\u00e7ekaya",
    "gn:population":0,
    "gn:timezone":"Europe/Istanbul",
    "iso:country":"TR",
    "name:tur_x_preferred":[
        "G\u00f6k\u00e7ekaya"
    ],
    "wof:name":"Gokcekaya",
    "wof:placetype":"locality"
},
  "geometry": {"coordinates":[30.39222,40.23503],"type":"Point"}
}