{
  "type": "Feature",
  "properties": {
    "gn:admin1_code":"45",
    "gn:asciiname":"Campinar",
    "gn:country_code":"TR",
    "gn:dem":114,
    "gn:feature_class":"P",
    "gn:feature_code":"PPL",
    "gn:name":"\u00c7amp\u0131nar",
    "gn:population":0,
    "gn:timezone":"Europe/Istanbul",
    "iso:country":"TR",
    "wof:name":"Campinar",
    "wof:placetype":"locality"
},
  "geometry": {"coordinates":[27.74139000000001,38.5775],"type":"Point"}
}