{
  "type": "Feature",
  "properties": {
    "gn:admin1_code":"14",
    "gn:asciiname":"Yesilcele",
    "gn:country_code":"TR",
    "gn:dem":1101,
    "gn:feature_class":"P",
    "gn:feature_code":"PPL",
    "gn:name":"Ye\u015fil\u00e7ele",
    "gn:population":0,
    "gn:timezone":"Europe/Istanbul",
    "iso:country":"TR",
    "name:tur_x_preferred":[
        "Ye\u015fil\u00e7ele"
    ],
    "wof:name":"Yesilcele",
    "wof:placetype":"locality"
},
  "geometry": {"coordinates":[31.70579,40.83422],"type":"Point"}
}