{
  "type": "Feature",
  "properties": {
    "gn:country":"TR",
    "gn:fcode":"PPL",
    "gn:pop":1102,
    "iso:country":"TR",
    "name:baq_x_preferred":[
        "Hamidiye"
    ],
    "name:cat_x_preferred":[
        "Hamidiye"
    ],
    "name:cze_x_preferred":[
        "Hamidiye"
    ],
    "name:dan_x_preferred":[
        "Hamidiye"
    ],
    "name:dut_x_preferred":[
        "Hamidiye"
    ],
    "name:eng_x_preferred":[
        "Hamidiye"
    ],
    "name:fin_x_preferred":[
        "Hamidiye"
    ],
    "name:ger_x_preferred":[
        "Hamidiye"
    ],
    "name:glg_x_preferred":[
        "Hamidiye"
    ],
    "name:ita_x_preferred":[
        "Hamidiye"
    ],
    "name:nno_x_preferred":[
        "Hamidiye"
    ],
    "name:nob_x_preferred":[
        "Hamidiye"
    ],
    "name:oci_x_preferred":[
        "Hamidiye"
    ],
    "name:pol_x_preferred":[
        "Hamidiye"
    ],
    "name:por_x_preferred":[
        "Hamidiye"
    ],
    "name:rum_x_preferred":[
        "Hamidiye"
    ],
    "name:sco_x_preferred":[
        "Hamidiye"
    ],
    "name:slo_x_preferred":[
        "Hamidiye"
    ],
    "name:slv_x_preferred":[
        "Hamidiye"
    ],
    "name:spa_x_preferred":[
        "Hamidiye"
    ],
    "name:swe_x_preferred":[
        "Hamidiye"
    ],
    "name:tgl_x_preferred":[
        "Hamidiye"
    ],
    "name:tur_x_preferred":[
        "Hamidiye"
    ],
    "name:unk_x_variant":[
        "Hamidiye"
    ],
    "name:war_x_preferred":[
        "Hamidiye"
    ],
    "qs:name":"Bal\u00e7\u0131k",
    "qs:photos_9r":0,
    "qs:photos_sr":0,
    "qs:pop_sr":"3",
    "wof:name":"Bal\u00e7\u0131k",
    "wof:placetype":"locality",
    "wof:population":1102
},
  "geometry": {"coordinates":[29.42833,40.8725],"type":"Point"}
}