{
  "type": "Feature",
  "properties": {
    "gn:admin1_code":"38",
    "gn:asciiname":"Kirimusagi",
    "gn:country_code":"TR",
    "gn:dem":1550,
    "gn:feature_class":"P",
    "gn:feature_code":"PPL",
    "gn:name":"K\u0131r\u0131mu\u015fa\u011f\u0131",
    "gn:population":0,
    "gn:timezone":"Europe/Istanbul",
    "iso:country":"TR",
    "wof:name":"Kirimusagi",
    "wof:placetype":"locality"
},
  "geometry": {"coordinates":[36.26667,38.65],"type":"Point"}
}