{
  "type": "Feature",
  "properties": {
    "gn:admin1_code":"60.0",
    "gn:asciiname":"Balikhisar",
    "gn:country_code":"TR",
    "gn:dem":1131,
    "gn:feature_class":"P",
    "gn:feature_code":"PPL",
    "gn:name":"Bal\u0131khisar",
    "gn:population":0,
    "gn:timezone":"Europe/Istanbul",
    "iso:country":"TR",
    "wof:name":"Balikhisar",
    "wof:placetype":"locality"
},
  "geometry": {"coordinates":[35.9543,40.02346],"type":"Point"}
}