{
  "type": "Feature",
  "properties": {
    "gn:admin1_code":"81.0",
    "gn:asciiname":"Otluk",
    "gn:country_code":"TR",
    "gn:dem":209,
    "gn:feature_class":"P",
    "gn:feature_code":"PPL",
    "gn:name":"Otluk",
    "gn:population":0,
    "gn:timezone":"Europe/Istanbul",
    "iso:country":"TR",
    "wof:name":"Otluk",
    "wof:placetype":"locality"
},
  "geometry": {"coordinates":[35.51189,37.30128],"type":"Point"}
}