{
  "type": "Feature",
  "properties": {
    "gn:admin1_code":"37.0",
    "gn:asciiname":"Imamoglu",
    "gn:country_code":"TR",
    "gn:dem":992,
    "gn:feature_class":"P",
    "gn:feature_code":"PPL",
    "gn:name":"\u0130mamo\u011flu",
    "gn:population":0,
    "gn:timezone":"Europe/Istanbul",
    "iso:country":"TR",
    "wof:name":"Imamoglu",
    "wof:placetype":"locality"
},
  "geometry": {"coordinates":[33.61167,41.22416],"type":"Point"}
}