{
  "type": "Feature",
  "properties": {
    "gn:admin1_code":"13.0",
    "gn:asciiname":"Guvendik",
    "gn:country_code":"TR",
    "gn:dem":2004,
    "gn:feature_class":"P",
    "gn:feature_code":"PPL",
    "gn:name":"G\u00fcvendik",
    "gn:population":0,
    "gn:timezone":"Europe/Istanbul",
    "iso:country":"TR",
    "name:tur_x_preferred":[
        "G\u00fcvendik"
    ],
    "wof:name":"Guvendik",
    "wof:placetype":"locality"
},
  "geometry": {"coordinates":[42.53537,38.20119],"type":"Point"}
}