{
  "type": "Feature",
  "properties": {
    "gn:admin1_code":"11.0",
    "gn:asciiname":"Kasikci",
    "gn:country_code":"TR",
    "gn:dem":170,
    "gn:feature_class":"P",
    "gn:feature_code":"PPL",
    "gn:name":"Ka\u015f\u0131k\u00e7\u0131",
    "gn:population":0,
    "gn:timezone":"Europe/Istanbul",
    "iso:country":"TR",
    "name:tur_x_preferred":[
        "Ka\u015f\u0131k\u00e7\u0131"
    ],
    "wof:name":"Kasikci",
    "wof:placetype":"locality"
},
  "geometry": {"coordinates":[30.15316,40.33999],"type":"Point"}
}