{
  "type": "Feature",
  "properties": {
    "gn:admin1_code":"24",
    "gn:asciiname":"Distas",
    "gn:country_code":"TR",
    "gn:dem":1972,
    "gn:feature_class":"P",
    "gn:feature_code":"PPL",
    "gn:name":"Di\u015fta\u015f",
    "gn:population":0,
    "gn:timezone":"Europe/Istanbul",
    "iso:country":"TR",
    "name:und_x_variant":[
        "Di\u015fta\u015f\u0131n",
        "Di\u015fta\u015f K\u00f6y\u00fc",
        "Di\u015fta\u015f"
    ],
    "wof:name":"Distas",
    "wof:placetype":"locality"
},
  "geometry": {"coordinates":[38.73175,39.73915],"type":"Point"}
}