{
  "type": "Feature",
  "properties": {
    "gn:admin1_code":"65.0",
    "gn:asciiname":"Han",
    "gn:country_code":"TR",
    "gn:dem":2307,
    "gn:feature_class":"P",
    "gn:feature_code":"PPL",
    "gn:name":"Han",
    "gn:population":0,
    "gn:timezone":"Europe/Istanbul",
    "iso:country":"TR",
    "name:tur_x_preferred":[
        "Han"
    ],
    "wof:name":"Han",
    "wof:placetype":"locality"
},
  "geometry": {"coordinates":[43.86929,38.89955],"type":"Point"}
}