{
  "type": "Feature",
  "properties": {
    "gn:admin1_code":"13.0",
    "gn:asciiname":"Cakirkaya",
    "gn:country_code":"TR",
    "gn:dem":1883,
    "gn:feature_class":"P",
    "gn:feature_code":"PPL",
    "gn:name":"\u00c7ak\u0131rkaya",
    "gn:population":0,
    "gn:timezone":"Europe/Istanbul",
    "iso:country":"TR",
    "name:tur_x_preferred":[
        "\u00c7ak\u0131rkaya"
    ],
    "wof:name":"Cakirkaya",
    "wof:placetype":"locality"
},
  "geometry": {"coordinates":[42.6372,38.25242],"type":"Point"}
}