{
  "type": "Feature",
  "properties": {
    "gn:admin1_code":"38",
    "gn:asciiname":"Beyazsehir",
    "gn:country_code":"TR",
    "gn:dem":1115,
    "gn:feature_class":"P",
    "gn:feature_code":"PPL",
    "gn:name":"Beyaz\u015fehir",
    "gn:population":0,
    "gn:timezone":"Europe/Istanbul",
    "iso:country":"TR",
    "name:und_x_variant":[
        "Beyaz\u015fehir",
        "Muncusun"
    ],
    "wof:name":"Beyazsehir",
    "wof:placetype":"locality"
},
  "geometry": {"coordinates":[35.59200999999999,38.78109],"type":"Point"}
}