{
  "type": "Feature",
  "properties": {
    "gn:admin1_code":"77.0",
    "gn:asciiname":"Kurucakol",
    "gn:country_code":"TR",
    "gn:dem":1668,
    "gn:feature_class":"P",
    "gn:feature_code":"PPL",
    "gn:name":"Kurucakol",
    "gn:population":0,
    "gn:timezone":"Europe/Istanbul",
    "iso:country":"TR",
    "name:und_x_variant":[
        "Kurcakur",
        "Kurucakol"
    ],
    "wof:name":"Kurucakol",
    "wof:placetype":"locality"
},
  "geometry": {"coordinates":[40.26667,40.23333],"type":"Point"}
}