{
  "type": "Feature",
  "properties": {
    "gn:admin1_code":"17.0",
    "gn:asciiname":"Derekoy",
    "gn:country_code":"TR",
    "gn:dem":225,
    "gn:feature_class":"P",
    "gn:feature_code":"PPL",
    "gn:name":"Derek\u00f6y",
    "gn:population":0,
    "gn:timezone":"Europe/Istanbul",
    "iso:country":"TR",
    "wof:name":"Derekoy",
    "wof:placetype":"locality"
},
  "geometry": {"coordinates":[25.784,40.15086],"type":"Point"}
}