{
  "type": "Feature",
  "properties": {
    "gn:admin1_code":"63.0",
    "gn:asciiname":"Kyuchyuk-Dzhafer",
    "gn:country_code":"TR",
    "gn:dem":384,
    "gn:feature_class":"P",
    "gn:feature_code":"PPL",
    "gn:name":"Kyuchyuk-Dzhafer",
    "gn:population":0,
    "gn:timezone":"Europe/Istanbul",
    "iso:country":"TR",
    "name:und_x_variant":[
        "K\u00fc\u00e7\u00fck Cafer"
    ],
    "wof:name":"Kyuchyuk-Dzhafer",
    "wof:placetype":"locality"
},
  "geometry": {"coordinates":[39.11833,36.97278],"type":"Point"}
}