{
  "type": "Feature",
  "properties": {
    "gn:admin1_code":"37.0",
    "gn:asciiname":"Gokceagac",
    "gn:country_code":"TR",
    "gn:dem":445,
    "gn:feature_class":"P",
    "gn:feature_code":"PPL",
    "gn:name":"G\u00f6k\u00e7ea\u011fa\u00e7",
    "gn:population":0,
    "gn:timezone":"Europe/Istanbul",
    "iso:country":"TR",
    "name:tur_x_preferred":[
        "Nefsig\u00f6k\u00e7ea\u011fa\u00e7 K\u00f6y\u00fc"
    ],
    "name:tur_x_variant":[
        "Nefsig\u00f6k\u00e7ea\u011fa\u00e7 K\u00f6y",
        "Nefsig\u00f6k\u00e7ea\u011fa\u00e7"
    ],
    "name:und_x_variant":[
        "G\u00f6k\u00e7ea\u011fa\u00e7",
        "Kayaba\u015f\u0131"
    ],
    "wof:name":"Gokceagac",
    "wof:placetype":"locality"
},
  "geometry": {"coordinates":[34.50156,41.6376],"type":"Point"}
}