{
  "type": "Feature",
  "properties": {
    "gn:admin1_code":"65.0",
    "gn:asciiname":"Gozaydin",
    "gn:country_code":"TR",
    "gn:dem":2310,
    "gn:feature_class":"P",
    "gn:feature_code":"PPL",
    "gn:name":"G\u00f6zayd\u0131n",
    "gn:population":0,
    "gn:timezone":"Europe/Istanbul",
    "iso:country":"TR",
    "name:tur_x_preferred":[
        "G\u00f6zayd\u0131n"
    ],
    "wof:name":"Gozaydin",
    "wof:placetype":"locality"
},
  "geometry": {"coordinates":[43.95781,37.822],"type":"Point"}
}