{
  "type": "Feature",
  "properties": {
    "gn:admin1_code":"55.0",
    "gn:asciiname":"Dundarli",
    "gn:country_code":"TR",
    "gn:dem":587,
    "gn:feature_class":"P",
    "gn:feature_code":"PPL",
    "gn:name":"D\u00fcndarl\u0131",
    "gn:population":0,
    "gn:timezone":"Europe/Istanbul",
    "iso:country":"TR",
    "name:und_x_variant":[
        "Dinardibi",
        "Dindardibi",
        "D\u00fcndardibi",
        "D\u00fcndarl\u0131"
    ],
    "wof:name":"Dundarli",
    "wof:placetype":"locality"
},
  "geometry": {"coordinates":[35.55166,41.04067],"type":"Point"}
}