{
  "type": "Feature",
  "properties": {
    "gn:admin1_code":"58.0",
    "gn:asciiname":"Diskapi",
    "gn:country_code":"TR",
    "gn:dem":1290,
    "gn:feature_class":"P",
    "gn:feature_code":"PPL",
    "gn:name":"D\u0131\u015fkap\u0131",
    "gn:population":0,
    "gn:timezone":"Europe/Istanbul",
    "iso:country":"TR",
    "wof:name":"Diskapi",
    "wof:placetype":"locality"
},
  "geometry": {"coordinates":[37.4088,39.84717],"type":"Point"}
}