{
  "type": "Feature",
  "properties": {
    "gn:admin1_code":"19.0",
    "gn:asciiname":"Balkaya",
    "gn:country_code":"TR",
    "gn:dem":1139,
    "gn:feature_class":"P",
    "gn:feature_code":"PPL",
    "gn:name":"Balkaya",
    "gn:population":0,
    "gn:timezone":"Europe/Istanbul",
    "iso:country":"TR",
    "name:tur_x_preferred":[
        "Balkaya"
    ],
    "wof:name":"Balkaya",
    "wof:placetype":"locality"
},
  "geometry": {"coordinates":[34.33019,39.96918],"type":"Point"}
}