{
  "type": "Feature",
  "properties": {
    "gn:admin1_code":"60.0",
    "gn:asciiname":"Boyunpinar",
    "gn:country_code":"TR",
    "gn:dem":1296,
    "gn:feature_class":"P",
    "gn:feature_code":"PPL",
    "gn:name":"Boyunp\u0131nar",
    "gn:population":0,
    "gn:timezone":"Europe/Istanbul",
    "iso:country":"TR",
    "name:und_x_variant":[
        "Horun",
        "Boyunp\u0131nar"
    ],
    "wof:name":"Boyunpinar",
    "wof:placetype":"locality"
},
  "geometry": {"coordinates":[36.39621,40.15827],"type":"Point"}
}