{
  "type": "Feature",
  "properties": {
    "gn:admin1_code":"23",
    "gn:asciiname":"Bademli",
    "gn:country_code":"TR",
    "gn:dem":998,
    "gn:feature_class":"P",
    "gn:feature_code":"PPL",
    "gn:name":"Bademli",
    "gn:population":0,
    "gn:timezone":"Europe/Istanbul",
    "iso:country":"TR",
    "name:ceb_x_preferred":[
        "Bademli"
    ],
    "name:tur_x_preferred":[
        "Bademli"
    ],
    "wof:name":"Bademli",
    "wof:placetype":"locality"
},
  "geometry": {"coordinates":[38.66991,39.00717],"type":"Point"}
}