{
  "type": "Feature",
  "properties": {
    "gn:country":"TR",
    "gn:fcode":"PPL",
    "gn:pop":225,
    "iso:country":"TR",
    "name:tur_x_preferred":[
        "Erikli"
    ],
    "name:unk_x_variant":[
        "Alimishmish"
    ],
    "qs:name":"Erikli",
    "qs:photos_9r":0,
    "qs:photos_sr":0,
    "qs:pop_sr":"2",
    "wd:wordcount":81,
    "wof:name":"Erikli",
    "wof:placetype":"locality",
    "wof:population":225
},
  "geometry": {"coordinates":[40.60803,37.22538],"type":"Point"}
}