{
  "type": "Feature",
  "properties": {
    "gn:admin1_code":"21.0",
    "gn:asciiname":"Yunluce",
    "gn:country_code":"TR",
    "gn:dem":913,
    "gn:feature_class":"P",
    "gn:feature_code":"PPL",
    "gn:name":"Y\u00fcnl\u00fcce",
    "gn:population":0,
    "gn:timezone":"Europe/Istanbul",
    "iso:country":"TR",
    "name:tur_x_preferred":[
        "Y\u00fcnl\u00fcce"
    ],
    "wof:name":"Yunluce",
    "wof:placetype":"locality"
},
  "geometry": {"coordinates":[40.72542,38.46784],"type":"Point"}
}