{
  "type": "Feature",
  "properties": {
    "gn:admin1_code":"76",
    "gn:asciiname":"Gunyayla",
    "gn:country_code":"TR",
    "gn:dem":684,
    "gn:feature_class":"P",
    "gn:feature_code":"PPL",
    "gn:name":"G\u00fcnyayla",
    "gn:population":0,
    "gn:timezone":"Europe/Istanbul",
    "iso:country":"TR",
    "name:tur_x_preferred":[
        "G\u00fclyayla"
    ],
    "name:tur_x_variant":[
        "G\u00fcnyayla"
    ],
    "wof:name":"Gunyayla",
    "wof:placetype":"locality"
},
  "geometry": {"coordinates":[41.52209000000001,38.02078],"type":"Point"}
}