{
  "type": "Feature",
  "properties": {
    "gn:admin1_code":"03",
    "gn:asciiname":"Sadikbey",
    "gn:country_code":"TR",
    "gn:dem":1011,
    "gn:feature_class":"P",
    "gn:feature_code":"PPL",
    "gn:name":"Sad\u0131kbey",
    "gn:population":0,
    "gn:timezone":"Europe/Istanbul",
    "iso:country":"TR",
    "wof:name":"Sadikbey",
    "wof:placetype":"locality"
},
  "geometry": {"coordinates":[30.45806,38.805],"type":"Point"}
}