{
  "type": "Feature",
  "properties": {
    "gn:admin1_code":"12",
    "gn:asciiname":"Kurbanli",
    "gn:country_code":"TR",
    "gn:dem":2044,
    "gn:feature_class":"P",
    "gn:feature_code":"PPL",
    "gn:name":"Kurbanl\u0131",
    "gn:population":0,
    "gn:timezone":"Europe/Istanbul",
    "iso:country":"TR",
    "name:tur_x_preferred":[
        "Kurbanl\u0131"
    ],
    "wof:name":"Kurbanli",
    "wof:placetype":"locality"
},
  "geometry": {"coordinates":[40.79266,39.52495],"type":"Point"}
}