{
  "type": "Feature",
  "properties": {
    "gn:admin1_code":"74",
    "gn:asciiname":"Sacayak",
    "gn:country_code":"TR",
    "gn:dem":880,
    "gn:feature_class":"P",
    "gn:feature_code":"PPL",
    "gn:name":"Sa\u00e7ayak",
    "gn:population":0,
    "gn:timezone":"Europe/Istanbul",
    "iso:country":"TR",
    "name:und_x_variant":[
        "Sa\u00e7ayak",
        "Sadi"
    ],
    "wof:name":"Sacayak",
    "wof:placetype":"locality"
},
  "geometry": {"coordinates":[41.92092,38.06153],"type":"Point"}
}