{
  "type": "Feature",
  "properties": {
    "gn:admin1_code":"37.0",
    "gn:asciiname":"Kireccik",
    "gn:country_code":"TR",
    "gn:dem":1162,
    "gn:feature_class":"P",
    "gn:feature_code":"PPL",
    "gn:name":"Kire\u00e7cik",
    "gn:population":0,
    "gn:timezone":"Europe/Istanbul",
    "iso:country":"TR",
    "wof:name":"Kireccik",
    "wof:placetype":"locality"
},
  "geometry": {"coordinates":[33.43333,41.35],"type":"Point"}
}