{
  "type": "Feature",
  "properties": {
    "gn:admin1_code":"58.0",
    "gn:asciiname":"Otmanalan",
    "gn:country_code":"TR",
    "gn:dem":1370,
    "gn:feature_class":"P",
    "gn:feature_code":"PPL",
    "gn:name":"Otmanalan",
    "gn:population":0,
    "gn:timezone":"Europe/Istanbul",
    "iso:country":"TR",
    "name:und_x_variant":[
        "Otmanalan K\u00f6y\u00fc",
        "Otmanaalan",
        "Otmanalan"
    ],
    "wof:name":"Otmanalan",
    "wof:placetype":"locality"
},
  "geometry": {"coordinates":[37.28279000000001,40.11181],"type":"Point"}
}