{
  "type": "Feature",
  "properties": {
    "gn:admin1_code":"60.0",
    "gn:asciiname":"Dalkaya",
    "gn:country_code":"TR",
    "gn:dem":519,
    "gn:feature_class":"P",
    "gn:feature_code":"PPL",
    "gn:name":"Dalkaya",
    "gn:population":0,
    "gn:timezone":"Europe/Istanbul",
    "iso:country":"TR",
    "wof:name":"Dalkaya",
    "wof:placetype":"locality"
},
  "geometry": {"coordinates":[36.85323,40.54608],"type":"Point"}
}