{
  "type": "Feature",
  "properties": {
    "gn:admin1_code":"55.0",
    "gn:asciiname":"Seyhulas",
    "gn:country_code":"TR",
    "gn:dem":31,
    "gn:feature_class":"P",
    "gn:feature_code":"PPL",
    "gn:name":"\u015eeyhula\u015f",
    "gn:population":0,
    "gn:timezone":"Europe/Istanbul",
    "iso:country":"TR",
    "name:und_x_variant":[
        "Su\u011fla\u015f",
        "Sula\u015f",
        "\u015eeyhula\u015f"
    ],
    "wof:name":"Seyhulas",
    "wof:placetype":"locality"
},
  "geometry": {"coordinates":[35.86040999999999,41.4924],"type":"Point"}
}