{
  "type": "Feature",
  "properties": {
    "gn:admin1_code":"73",
    "gn:asciiname":"Yesilburc",
    "gn:country_code":"TR",
    "gn:dem":1380,
    "gn:feature_class":"P",
    "gn:feature_code":"PPL",
    "gn:name":"Ye\u015filbur\u00e7",
    "gn:population":0,
    "gn:timezone":"Europe/Istanbul",
    "iso:country":"TR",
    "name:ceb_x_preferred":[
        "Ye\u015filbur\u00e7"
    ],
    "name:msa_x_preferred":[
        "Ye\u015filbur\u00e7"
    ],
    "name:tur_x_preferred":[
        "Ye\u015filbur\u00e7"
    ],
    "name:und_x_variant":[
        "Dene\u011fri"
    ],
    "name:urd_x_preferred":[
        "\u06cc\u06c1\u0633\u0627\u0644\u0628\u0631\u0633"
    ],
    "name:vie_x_preferred":[
        "Ye\u015filbur\u00e7"
    ],
    "wof:name":"Yesilburc",
    "wof:placetype":"locality"
},
  "geometry": {"coordinates":[34.66998,38.01049],"type":"Point"}
}