{
  "type": "Feature",
  "properties": {
    "gn:admin1_code":"16.0",
    "gn:asciiname":"Kocu",
    "gn:country_code":"TR",
    "gn:dem":687,
    "gn:feature_class":"P",
    "gn:feature_code":"PPL",
    "gn:name":"Ko\u00e7u",
    "gn:population":0,
    "gn:timezone":"Europe/Istanbul",
    "iso:country":"TR",
    "name:und_x_variant":[
        "Ko\u00e7uk\u00f6y",
        "Ko\u00e7u"
    ],
    "wof:name":"Kocu",
    "wof:placetype":"locality"
},
  "geometry": {"coordinates":[28.86006,40.04739],"type":"Point"}
}