{
  "type": "Feature",
  "properties": {
    "gn:admin1_code":"58.0",
    "gn:asciiname":"Yalniztepe",
    "gn:country_code":"TR",
    "gn:dem":1254,
    "gn:feature_class":"P",
    "gn:feature_code":"PPL",
    "gn:name":"Yaln\u0131ztepe",
    "gn:population":0,
    "gn:timezone":"Europe/Istanbul",
    "iso:country":"TR",
    "name:und_x_variant":[
        "C\u00f6rg\u00fc",
        "Yaln\u0131ztepe"
    ],
    "wof:name":"Yalniztepe",
    "wof:placetype":"locality"
},
  "geometry": {"coordinates":[37.9466,40.26899],"type":"Point"}
}