{
  "type": "Feature",
  "properties": {
    "gn:admin1_code":"41.0",
    "gn:asciiname":"Tepetarla",
    "gn:country_code":"TR",
    "gn:dem":42,
    "gn:feature_class":"P",
    "gn:feature_code":"PPL",
    "gn:name":"Tepetarla",
    "gn:population":0,
    "gn:timezone":"Europe/Istanbul",
    "iso:country":"TR",
    "name:tur_x_preferred":[
        "Tepetarla"
    ],
    "name:und_x_variant":[
        "Ramiye",
        "Tepetarla"
    ],
    "wof:name":"Tepetarla",
    "wof:placetype":"locality"
},
  "geometry": {"coordinates":[30.08165,40.72004],"type":"Point"}
}