{
  "type": "Feature",
  "properties": {
    "gn:admin1_code":"62",
    "gn:asciiname":"Ulukale",
    "gn:country_code":"TR",
    "gn:dem":1215,
    "gn:feature_class":"P",
    "gn:feature_code":"PPL",
    "gn:name":"Ulukale",
    "gn:population":0,
    "gn:timezone":"Europe/Istanbul",
    "iso:country":"TR",
    "name:tur_x_preferred":[
        "Ulukale"
    ],
    "wof:name":"Ulukale",
    "wof:placetype":"locality"
},
  "geometry": {"coordinates":[39.04705,39.03444],"type":"Point"}
}