{
  "type": "Feature",
  "properties": {
    "gn:admin1_code":"58",
    "gn:asciiname":"Polatpasa",
    "gn:country_code":"TR",
    "gn:dem":1352,
    "gn:feature_class":"P",
    "gn:feature_code":"PPL",
    "gn:name":"Polatpa\u015fa",
    "gn:population":0,
    "gn:timezone":"Europe/Istanbul",
    "iso:country":"TR",
    "name:tur_x_preferred":[
        "Polatpa\u015fa"
    ],
    "name:und_x_variant":[
        "Tuzla",
        "Tuzluk\u00f6y",
        "Tuzlak\u00f6y"
    ],
    "wof:name":"Polatpasa",
    "wof:placetype":"locality"
},
  "geometry": {"coordinates":[36.50944000000001,39.42778],"type":"Point"}
}