{
  "type": "Feature",
  "properties": {
    "gn:admin1_code":"88",
    "gn:asciiname":"Kuzuguden",
    "gn:country_code":"TR",
    "gn:dem":872,
    "gn:feature_class":"P",
    "gn:feature_code":"PPL",
    "gn:name":"Kuzug\u00fcden",
    "gn:population":0,
    "gn:timezone":"Europe/Istanbul",
    "iso:country":"TR",
    "wof:name":"Kuzuguden",
    "wof:placetype":"locality"
},
  "geometry": {"coordinates":[43.97315,39.98611],"type":"Point"}
}