{
  "type": "Feature",
  "properties": {
    "gn:admin1_code":"64",
    "gn:asciiname":"Cobanlar",
    "gn:country_code":"TR",
    "gn:dem":850,
    "gn:feature_class":"P",
    "gn:feature_code":"PPL",
    "gn:name":"\u00c7obanlar",
    "gn:population":0,
    "gn:timezone":"Europe/Istanbul",
    "iso:country":"TR",
    "name:tur_x_preferred":[
        "\u00c7obanlar"
    ],
    "name:und_x_variant":[
        "\u00c7obank\u00f6y",
        "\u00c7oban"
    ],
    "wof:name":"Cobanlar",
    "wof:placetype":"locality"
},
  "geometry": {"coordinates":[29.04447,38.46431],"type":"Point"}
}