{
  "type": "Feature",
  "properties": {
    "gn:admin1_code":"20",
    "gn:asciiname":"Yazir",
    "gn:country_code":"TR",
    "gn:dem":999,
    "gn:feature_class":"P",
    "gn:feature_code":"PPL",
    "gn:name":"Yaz\u0131r",
    "gn:population":0,
    "gn:timezone":"Europe/Istanbul",
    "iso:country":"TR",
    "wof:name":"Yazir",
    "wof:placetype":"locality"
},
  "geometry": {"coordinates":[29.55956,37.36462],"type":"Point"}
}