{
  "type": "Feature",
  "properties": {
    "gn:admin1_code":"71",
    "gn:asciiname":"Sogutgozu",
    "gn:country_code":"TR",
    "gn:dem":1172,
    "gn:feature_class":"P",
    "gn:feature_code":"PPL",
    "gn:name":"S\u00f6\u011f\u00fct\u011f\u00f6z\u00fc",
    "gn:population":0,
    "gn:timezone":"Europe/Istanbul",
    "iso:country":"TR",
    "name:und_x_variant":[
        "S\u00f6\u011f\u00fct\u011f\u00f6z\u00fc",
        "D\u0131ra\u011fan"
    ],
    "wof:name":"Sogutgozu",
    "wof:placetype":"locality"
},
  "geometry": {"coordinates":[32.1783,38.17801],"type":"Point"}
}