{
  "type": "Feature",
  "properties": {
    "gn:admin1_code":"32",
    "gn:asciiname":"Cicekli",
    "gn:country_code":"TR",
    "gn:dem":8,
    "gn:feature_class":"P",
    "gn:feature_code":"PPL",
    "gn:name":"\u00c7i\u00e7ekli",
    "gn:population":0,
    "gn:timezone":"Europe/Istanbul",
    "iso:country":"TR",
    "name:und_x_variant":[
        "\u00c7i\u00e7ekli",
        "Fireng\u00fcl\u00fcs"
    ],
    "wof:name":"Cicekli",
    "wof:placetype":"locality"
},
  "geometry": {"coordinates":[35.08643,36.87506],"type":"Point"}
}