{
  "type": "Feature",
  "properties": {
    "gn:admin1_code":"43",
    "gn:asciiname":"Allioren",
    "gn:country_code":"TR",
    "gn:dem":1135,
    "gn:feature_class":"P",
    "gn:feature_code":"PPL",
    "gn:name":"All\u0131\u00f6ren",
    "gn:population":0,
    "gn:timezone":"Europe/Istanbul",
    "iso:country":"TR",
    "name:und_x_variant":[
        "Al\u0131nveren",
        "All\u0131\u00f6ren"
    ],
    "wof:name":"Allioren",
    "wof:placetype":"locality"
},
  "geometry": {"coordinates":[29.99946,38.94624],"type":"Point"}
}