{
  "type": "Feature",
  "properties": {
    "gn:admin1_code":"72",
    "gn:asciiname":"Ucevler",
    "gn:country_code":"TR",
    "gn:dem":489,
    "gn:feature_class":"P",
    "gn:feature_code":"PPL",
    "gn:name":"\u00dc\u00e7evler",
    "gn:population":0,
    "gn:timezone":"Europe/Istanbul",
    "iso:country":"TR",
    "name:tur_x_preferred":[
        "\u00dc\u00e7evler"
    ],
    "wof:name":"Ucevler",
    "wof:placetype":"locality"
},
  "geometry": {"coordinates":[40.61807,37.19329000000001],"type":"Point"}
}