{
  "type": "Feature",
  "properties": {
    "gn:admin1_code":"82.0",
    "gn:asciiname":"Dalkoz",
    "gn:country_code":"TR",
    "gn:dem":881,
    "gn:feature_class":"P",
    "gn:feature_code":"PPL",
    "gn:name":"Dalkoz",
    "gn:population":0,
    "gn:timezone":"Europe/Istanbul",
    "iso:country":"TR",
    "wof:name":"Dalkoz",
    "wof:placetype":"locality"
},
  "geometry": {"coordinates":[33.23387,40.951],"type":"Point"}
}