{
  "type": "Feature",
  "properties": {
    "gn:admin1_code":"35",
    "gn:asciiname":"Palamut",
    "gn:country_code":"TR",
    "gn:dem":614,
    "gn:feature_class":"P",
    "gn:feature_code":"PPL",
    "gn:name":"Palamut",
    "gn:population":0,
    "gn:timezone":"Europe/Istanbul",
    "iso:country":"TR",
    "name:ceb_x_preferred":[
        "Palamut"
    ],
    "name:tur_x_preferred":[
        "Palamut"
    ],
    "wof:name":"Palamut",
    "wof:placetype":"locality"
},
  "geometry": {"coordinates":[27.73824,37.96988],"type":"Point"}
}