{
  "type": "Feature",
  "properties": {
    "gn:admin1_code":"85.0",
    "gn:asciiname":"Elmaci",
    "gn:country_code":"TR",
    "gn:dem":334,
    "gn:feature_class":"P",
    "gn:feature_code":"PPL",
    "gn:name":"Elmac\u0131",
    "gn:population":0,
    "gn:timezone":"Europe/Istanbul",
    "iso:country":"TR",
    "wof:name":"Elmaci",
    "wof:placetype":"locality"
},
  "geometry": {"coordinates":[31.6505,41.34234],"type":"Point"}
}