{
  "type": "Feature",
  "properties": {
    "iso:country":"TR",
    "qs:name":"\u0130zzet Pa\u015fa",
    "qs:name_adm0":"Turkey",
    "qs:name_adm1":"\u0130stanbul",
    "qs:photos":17,
    "qs:photos_1k":3,
    "qs:photos_9k":1,
    "qs:photos_9r":1,
    "qs:photos_all":17,
    "qs:photos_sr":1,
    "qs:placetype":"Suburb",
    "qs:pop_sr":"0",
    "wof:name":"\u0130zzet Pa\u015fa",
    "wof:placetype":"neighbourhood"
},
  "geometry": {"coordinates":[28.988842,41.068965],"type":"Point"}
}