{
  "type": "Feature",
  "properties": {
    "gn:admin1_code":"09",
    "gn:asciiname":"Hacikoseler",
    "gn:country_code":"TR",
    "gn:dem":570,
    "gn:feature_class":"P",
    "gn:feature_code":"PPL",
    "gn:name":"Hac\u0131k\u00f6seler",
    "gn:population":0,
    "gn:timezone":"Europe/Istanbul",
    "iso:country":"TR",
    "name:tur_x_preferred":[
        "Hac\u0131k\u00f6seler"
    ],
    "wof:name":"Hacikoseler",
    "wof:placetype":"locality"
},
  "geometry": {"coordinates":[28.13681,37.70629],"type":"Point"}
}