{
  "type": "Feature",
  "properties": {
    "gn:admin1_code":"63",
    "gn:asciiname":"Birhalil",
    "gn:cc2":"TR",
    "gn:country_code":"TR",
    "gn:dem":464,
    "gn:feature_class":"P",
    "gn:feature_code":"PPL",
    "gn:name":"Birhalil",
    "gn:population":0,
    "gn:timezone":"Europe/Istanbul",
    "iso:country":"TR",
    "name:rus_x_preferred":[
        "Birkhalil\u2019"
    ],
    "name:und_x_variant":[
        "Mirhalil",
        "Birhalil"
    ],
    "wof:name":"Birhalil",
    "wof:placetype":"locality"
},
  "geometry": {"coordinates":[38.55611,36.87833],"type":"Point"}
}