{
  "type": "Feature",
  "properties": {
    "gn:admin1_code":"90",
    "gn:asciiname":"Omercik",
    "gn:country_code":"TR",
    "gn:dem":682,
    "gn:feature_class":"P",
    "gn:feature_code":"PPL",
    "gn:name":"\u00d6mercik",
    "gn:population":0,
    "gn:timezone":"Europe/Istanbul",
    "iso:country":"TR",
    "wof:name":"Omercik",
    "wof:placetype":"locality"
},
  "geometry": {"coordinates":[37.22944,36.80934],"type":"Point"}
}