{
  "type": "Feature",
  "properties": {
    "gn:country":"TR",
    "gn:fcode":"PPL",
    "gn:population":15922,
    "iso:country":"TR",
    "name:ast_x_preferred":[
        "Baskil"
    ],
    "name:ceb_x_preferred":[
        "Baskil \u0130l\u00e7esi"
    ],
    "name:che_x_preferred":[
        "\u0411\u0430\u0441\u043a\u0438\u043b"
    ],
    "name:ckb_x_preferred":[
        "\u0628\u0627\u0633\u0642\u06cc\u0644"
    ],
    "name:deu_x_preferred":[
        "Baskil"
    ],
    "name:diq_x_preferred":[
        "Baskil"
    ],
    "name:eng_x_preferred":[
        "Baskil"
    ],
    "name:fas_x_preferred":[
        "\u0628\u0627\u0633\u06a9\u06cc\u0644"
    ],
    "name:fra_x_preferred":[
        "Baskil"
    ],
    "name:kur_x_preferred":[
        "Baskil"
    ],
    "name:mdf_x_preferred":[
        "\u0411\u0430\u0441\u043a\u0438\u043b"
    ],
    "name:mrj_x_preferred":[
        "\u0411\u0430\u0441\u043a\u0438\u043b\u044c"
    ],
    "name:msa_x_preferred":[
        "Baskil"
    ],
    "name:nan_x_preferred":[
        "Baskil"
    ],
    "name:nld_x_preferred":[
        "Baskil"
    ],
    "name:nob_x_preferred":[
        "Baskil"
    ],
    "name:pnb_x_preferred":[
        "\u0636\u0644\u0639 \u0628\u0627\u0633\u06a9\u0644"
    ],
    "name:rus_x_preferred":[
        "\u0411\u0430\u0441\u043a\u0438\u043b\u044c"
    ],
    "name:swa_x_preferred":[
        "Baskil"
    ],
    "name:tat_x_preferred":[
        "\u0411\u0430\u0441\u043a\u0438\u043b"
    ],
    "name:tur_x_preferred":[
        "Baskil"
    ],
    "name:ukr_x_preferred":[
        "\u0411\u0430\u0441\u043a\u0456\u043b"
    ],
    "name:urd_x_preferred":[
        "\u0628\u0627\u0633\u06a9\u0644"
    ],
    "name:vie_x_preferred":[
        "Baskil"
    ],
    "qs:name":"Baskil",
    "qs:name_adm0":"Turkey",
    "qs:name_adm1":"Elaz\u0131\u011f",
    "qs:photos_9k":1,
    "qs:photos_9r":1,
    "qs:photos_all":2,
    "qs:photos_sr":0,
    "qs:placetype":"Town",
    "qs:pop_sr":"6",
    "wd:wordcount":80,
    "wof:name":"Baskil",
    "wof:placetype":"locality",
    "wof:population":15922
},
  "geometry": {"coordinates":[38.82382,38.56791],"type":"Point"}
}