{
  "type": "Feature",
  "properties": {
    "gn:admin1_code":"49",
    "gn:asciiname":"Toklular",
    "gn:country_code":"TR",
    "gn:dem":1626,
    "gn:feature_class":"P",
    "gn:feature_code":"PPL",
    "gn:name":"Toklular",
    "gn:population":0,
    "gn:timezone":"Europe/Istanbul",
    "iso:country":"TR",
    "name:tur_x_preferred":[
        "Toklular"
    ],
    "wof:name":"Toklular",
    "wof:placetype":"locality"
},
  "geometry": {"coordinates":[42.03326,39.18943],"type":"Point"}
}