{
  "type": "Feature",
  "properties": {
    "gn:admin1_code":"87.0",
    "gn:asciiname":"Muratbey",
    "gn:country_code":"TR",
    "gn:dem":96,
    "gn:feature_class":"P",
    "gn:feature_code":"PPL",
    "gn:name":"Muratbey",
    "gn:population":0,
    "gn:timezone":"Europe/Istanbul",
    "iso:country":"TR",
    "wof:name":"Muratbey",
    "wof:placetype":"locality"
},
  "geometry": {"coordinates":[32.37583,41.58383],"type":"Point"}
}