{
  "type": "Feature",
  "properties": {
    "gn:admin1_code":"37.0",
    "gn:asciiname":"Gemiciler",
    "gn:country_code":"TR",
    "gn:dem":112,
    "gn:feature_class":"P",
    "gn:feature_code":"PPL",
    "gn:name":"Gemiciler",
    "gn:population":0,
    "gn:timezone":"Europe/Istanbul",
    "iso:country":"TR",
    "name:und_x_variant":[
        "Evrenye",
        "Gemiciler"
    ],
    "wof:name":"Gemiciler",
    "wof:placetype":"locality"
},
  "geometry": {"coordinates":[33.89028,41.96943],"type":"Point"}
}