{
  "type": "Feature",
  "properties": {
    "gn:country":"TR",
    "gn:fcode":"PPL",
    "gn:pop":0,
    "iso:country":"TR",
    "name:rus_x_preferred":[
        "\u0417\u0438\u043d\u0434\u0436\u0438\u0440\u043b\u0438\u043a\u0443\u044e"
    ],
    "name:tur_x_preferred":[
        "Zincirlikuyu"
    ],
    "name:unk_x_variant":[
        "Hamidiyezincirlikuyu"
    ],
    "qs:name":"Zincirlikuyu",
    "qs:name_adm0":"Turkey",
    "qs:name_adm1":"Eski\u015fehir",
    "qs:photos_9k":1,
    "qs:photos_9r":1,
    "qs:photos_all":4,
    "qs:photos_sr":0,
    "qs:placetype":"Town",
    "qs:pop_sr":"0",
    "wd:wordcount":663,
    "wof:name":"Zincirlikuyu",
    "wof:placetype":"locality",
    "wof:population":0
},
  "geometry": {"coordinates":[30.46972,39.79583],"type":"Point"}
}