{
  "type": "Feature",
  "properties": {
    "gn:admin1_code":"68.0",
    "gn:asciiname":"Evren",
    "gn:country_code":"TR",
    "gn:dem":885,
    "gn:feature_class":"P",
    "gn:feature_code":"PPL",
    "gn:name":"Evren",
    "gn:population":0,
    "gn:timezone":"Europe/Istanbul",
    "iso:country":"TR",
    "name:und_x_variant":[
        "\u00c7\u0131k\u0131na\u011f\u0131l"
    ],
    "wof:name":"Evren",
    "wof:placetype":"locality"
},
  "geometry": {"coordinates":[33.80982,39.02805],"type":"Point"}
}