{
  "type": "Feature",
  "properties": {
    "gn:country":"TR",
    "gn:fcode":"PPL",
    "gn:population":0,
    "iso:country":"TR",
    "name:ara_x_preferred":[
        "\u064a\u062f\u064a \u062a\u0628\u064a\u0647"
    ],
    "name:sco_x_preferred":[
        "Yeditepe"
    ],
    "name:tur_x_preferred":[
        "Diktepe"
    ],
    "name:tur_x_variant":[
        "Yeditepe"
    ],
    "name:urd_x_preferred":[
        "\u06cc\u062f\u06cc \u062a\u067e\u06c1"
    ],
    "name:vie_x_preferred":[
        "Yeditepe"
    ],
    "qs:name":"Yeditepe",
    "qs:name_adm0":"Turkey",
    "qs:name_adm1":"Gaziantep",
    "qs:photos":27,
    "qs:photos_1k":5,
    "qs:photos_9k":1,
    "qs:photos_9r":2,
    "qs:photos_all":27,
    "qs:photos_sr":2,
    "qs:placetype":"Suburb",
    "qs:pop_sr":"0",
    "wd:wordcount":68,
    "wof:name":"Yeditepe",
    "wof:placetype":"neighbourhood",
    "wof:population":0
},
  "geometry": {"coordinates":[38.07677,37.0173],"type":"Point"}
}