{
  "type": "Feature",
  "properties": {
    "gn:country":"TR",
    "gn:fcode":"PPL",
    "gn:pop":0,
    "iso:country":"TR",
    "name:tur_x_preferred":[
        "Diktepe"
    ],
    "qs:name":"Yeditepe",
    "qs:name_adm0":"Turkey",
    "qs:name_adm1":"Gaziantep",
    "qs:photos":27,
    "qs:photos_1k":5,
    "qs:photos_9k":1,
    "qs:photos_9r":2,
    "qs:photos_all":27,
    "qs:photos_sr":2,
    "qs:placetype":"Suburb",
    "qs:pop_sr":"0",
    "wd:wordcount":68,
    "wof:name":"Yeditepe",
    "wof:placetype":"neighbourhood",
    "wof:population":0
},
  "geometry": {"coordinates":[38.07677,37.0173],"type":"Point"}
}