{
  "type": "Feature",
  "properties": {
    "gn:country":"TR",
    "gn:fcode":"PPL",
    "gn:population":75,
    "iso:country":"TR",
    "name:und_x_variant":[
        "Yukar\u0131avte"
    ],
    "qs:name":"\u00c7eltikba\u015f\u0131",
    "qs:photos_9r":0,
    "qs:photos_sr":0,
    "qs:pop_sr":"1",
    "wof:name":"\u00c7eltikba\u015f\u0131",
    "wof:placetype":"locality",
    "wof:population":75
},
  "geometry": {"coordinates":[41.73278,37.74389],"type":"Point"}
}