{
  "type": "Feature",
  "properties": {
    "gn:admin1_code":"83",
    "gn:asciiname":"Gemrik",
    "gn:country_code":"TR",
    "gn:dem":580,
    "gn:feature_class":"P",
    "gn:feature_code":"PPL",
    "gn:name":"Gemrik",
    "gn:population":0,
    "gn:timezone":"Europe/Istanbul",
    "iso:country":"TR",
    "name:tur_x_preferred":[
        "G\u00fcve\u00e7li"
    ],
    "name:tur_x_variant":[
        "Gemrik"
    ],
    "wof:name":"Gemrik",
    "wof:placetype":"locality"
},
  "geometry": {"coordinates":[37.6798,36.85319000000001],"type":"Point"}
}