{
  "type": "Feature",
  "properties": {
    "gn:admin1_code":"70.0",
    "gn:asciiname":"Yayik",
    "gn:country_code":"TR",
    "gn:dem":1684,
    "gn:feature_class":"P",
    "gn:feature_code":"PPL",
    "gn:name":"Yay\u0131k",
    "gn:population":0,
    "gn:timezone":"Europe/Istanbul",
    "iso:country":"TR",
    "wof:name":"Yayik",
    "wof:placetype":"locality"
},
  "geometry": {"coordinates":[43.75104,37.44308],"type":"Point"}
}