{
  "type": "Feature",
  "properties": {
    "gn:admin1_code":"33",
    "gn:asciiname":"Kozluca",
    "gn:country_code":"TR",
    "gn:dem":1115,
    "gn:feature_class":"P",
    "gn:feature_code":"PPL",
    "gn:name":"Kozluca",
    "gn:population":0,
    "gn:timezone":"Europe/Istanbul",
    "iso:country":"TR",
    "wof:name":"Kozluca",
    "wof:placetype":"locality"
},
  "geometry": {"coordinates":[30.24167000000001,37.91639],"type":"Point"}
}