{
  "type": "Feature",
  "properties": {
    "gn:admin1_code":"66",
    "gn:asciiname":"Gudulelmahacili",
    "gn:country_code":"TR",
    "gn:dem":1284,
    "gn:feature_class":"P",
    "gn:feature_code":"PPL",
    "gn:name":"G\u00fcd\u00fclelmahac\u0131l\u0131",
    "gn:population":0,
    "gn:timezone":"Europe/Istanbul",
    "iso:country":"TR",
    "wof:name":"Gudulelmahacili",
    "wof:placetype":"locality"
},
  "geometry": {"coordinates":[34.90825,39.75746],"type":"Point"}
}