{
  "type": "Feature",
  "properties": {
    "gn:admin1_code":"61.0",
    "gn:asciiname":"Guneysu",
    "gn:country_code":"TR",
    "gn:dem":293,
    "gn:feature_class":"P",
    "gn:feature_code":"PPL",
    "gn:name":"G\u00fcneysu",
    "gn:population":0,
    "gn:timezone":"Europe/Istanbul",
    "iso:country":"TR",
    "wof:name":"Guneysu",
    "wof:placetype":"locality"
},
  "geometry": {"coordinates":[39.27308,41.00252],"type":"Point"}
}