{
  "type": "Feature",
  "properties": {
    "gn:admin1_code":"46",
    "gn:asciiname":"Ulutas",
    "gn:country_code":"TR",
    "gn:dem":1040,
    "gn:feature_class":"P",
    "gn:feature_code":"PPL",
    "gn:name":"Uluta\u015f",
    "gn:population":0,
    "gn:timezone":"Europe/Istanbul",
    "iso:country":"TR",
    "name:tur_x_preferred":[
        "Uluta\u015f"
    ],
    "wof:name":"Ulutas",
    "wof:placetype":"locality"
},
  "geometry": {"coordinates":[37.02772,37.60607],"type":"Point"}
}