{
  "type": "Feature",
  "properties": {
    "gn:admin1_code":"39.0",
    "gn:asciiname":"Sislioba",
    "gn:cc2":"TR",
    "gn:country_code":"TR",
    "gn:dem":49,
    "gn:feature_class":"P",
    "gn:feature_code":"PPL",
    "gn:name":"Sislioba",
    "gn:population":0,
    "gn:timezone":"Europe/Istanbul",
    "iso:country":"TR",
    "name:und_x_variant":[
        "Pula\u00e7a",
        "P\u0131la\u00e7a",
        "Rula\u00e7a",
        "Sislioba"
    ],
    "wof:name":"Sislioba",
    "wof:placetype":"locality"
},
  "geometry": {"coordinates":[27.91444000000001,41.96806],"type":"Point"}
}