{
  "type": "Feature",
  "properties": {
    "gn:admin1_code":"31",
    "gn:asciiname":"Karahuyuk",
    "gn:country_code":"TR",
    "gn:dem":89,
    "gn:feature_class":"P",
    "gn:feature_code":"PPL",
    "gn:name":"Karah\u00fcy\u00fck",
    "gn:population":0,
    "gn:timezone":"Europe/Istanbul",
    "iso:country":"TR",
    "name:und_x_variant":[
        "Karah\u00fcy\u00fck",
        "Karacah\u00fcy\u00fck"
    ],
    "wof:name":"Karahuyuk",
    "wof:placetype":"locality"
},
  "geometry": {"coordinates":[36.46436,36.32968],"type":"Point"}
}