{
  "type": "Feature",
  "properties": {
    "gn:admin1_code":"58",
    "gn:asciiname":"Oluktas",
    "gn:cc2":"TR",
    "gn:country_code":"TR",
    "gn:dem":1634,
    "gn:feature_class":"P",
    "gn:feature_code":"PPL",
    "gn:name":"Olukta\u015f",
    "gn:population":0,
    "gn:timezone":"Europe/Istanbul",
    "iso:country":"TR",
    "name:und_x_variant":[
        "K\u00f6t\u00fck\u00f6y",
        "P\u00f6hrenk",
        "Olukta\u015f"
    ],
    "wof:name":"Oluktas",
    "wof:placetype":"locality"
},
  "geometry": {"coordinates":[36.5175,39.17944],"type":"Point"}
}