{
  "type": "Feature",
  "properties": {
    "gn:admin1_code":"65.0",
    "gn:asciiname":"Simkorik",
    "gn:country_code":"TR",
    "gn:dem":1643,
    "gn:feature_class":"P",
    "gn:feature_code":"PPL",
    "gn:name":"Simkorik",
    "gn:population":0,
    "gn:timezone":"Europe/Istanbul",
    "iso:country":"TR",
    "wof:name":"Simkorik",
    "wof:placetype":"locality"
},
  "geometry": {"coordinates":[43.06417,37.99444],"type":"Point"}
}