{
  "type": "Feature",
  "properties": {
    "gn:admin1_code":"71",
    "gn:asciiname":"Eyirler",
    "gn:country_code":"TR",
    "gn:dem":1241,
    "gn:feature_class":"P",
    "gn:feature_code":"PPL",
    "gn:name":"Eyirler",
    "gn:population":0,
    "gn:timezone":"Europe/Istanbul",
    "iso:country":"TR",
    "name:und_x_variant":[
        "E\u011firler"
    ],
    "wof:name":"Eyirler",
    "wof:placetype":"locality"
},
  "geometry": {"coordinates":[31.84488,37.73982],"type":"Point"}
}