{
  "type": "Feature",
  "properties": {
    "gn:admin1_code":"28.0",
    "gn:asciiname":"Aktepe",
    "gn:country_code":"TR",
    "gn:dem":1693,
    "gn:feature_class":"P",
    "gn:feature_code":"PPL",
    "gn:name":"Aktepe",
    "gn:population":0,
    "gn:timezone":"Europe/Istanbul",
    "iso:country":"TR",
    "name:hye_x_preferred":[
        "\u0531\u056f\u0569\u0565\u0583\u0565"
    ],
    "name:tur_x_preferred":[
        "Aktepe"
    ],
    "name:und_x_variant":[
        "Zilk\u00f6y",
        "Zil"
    ],
    "wof:name":"Aktepe",
    "wof:placetype":"locality"
},
  "geometry": {"coordinates":[38.69862,40.32784],"type":"Point"}
}