{
  "type": "Feature",
  "properties": {
    "gn:admin1_code":"74",
    "gn:asciiname":"Kesmetas",
    "gn:country_code":"TR",
    "gn:dem":1575,
    "gn:feature_class":"P",
    "gn:feature_code":"PPL",
    "gn:name":"Kesmeta\u015f",
    "gn:population":0,
    "gn:timezone":"Europe/Istanbul",
    "iso:country":"TR",
    "name:und_x_variant":[
        "Kesmeta\u015f",
        "Halenze"
    ],
    "wof:name":"Kesmetas",
    "wof:placetype":"locality"
},
  "geometry": {"coordinates":[42.20802,38.16059],"type":"Point"}
}