{
  "type": "Feature",
  "properties": {
    "gn:admin1_code":"5.0",
    "gn:asciiname":"Gemibuku",
    "gn:country_code":"TR",
    "gn:dem":281,
    "gn:feature_class":"P",
    "gn:feature_code":"PPL",
    "gn:name":"Gemib\u00fck\u00fc",
    "gn:population":0,
    "gn:timezone":"Europe/Istanbul",
    "iso:country":"TR",
    "name:und_x_variant":[
        "Tombakb\u00fck\u00fc",
        "Gemib\u00fck\u00fc"
    ],
    "wof:name":"Gemibuku",
    "wof:placetype":"locality"
},
  "geometry": {"coordinates":[36.37323,40.74672],"type":"Point"}
}