{
  "type": "Feature",
  "properties": {
    "gn:admin1_code":"10.0",
    "gn:asciiname":"Karsiyaka",
    "gn:country_code":"TR",
    "gn:dem":9,
    "gn:feature_class":"P",
    "gn:feature_code":"PPL",
    "gn:name":"Kar\u015f\u0131yaka",
    "gn:population":0,
    "gn:timezone":"Europe/Istanbul",
    "iso:country":"TR",
    "name:und_x_variant":[
        "Perema",
        "Kar\u015f\u0131yaka"
    ],
    "wof:name":"Karsiyaka",
    "wof:placetype":"locality"
},
  "geometry": {"coordinates":[28.00087000000001,40.44194],"type":"Point"}
}