{
  "type": "Feature",
  "properties": {
    "gn:admin1_code":"37.0",
    "gn:asciiname":"Sorkuncuk",
    "gn:country_code":"TR",
    "gn:dem":1227,
    "gn:feature_class":"P",
    "gn:feature_code":"PPL",
    "gn:name":"Sorkuncuk",
    "gn:population":0,
    "gn:timezone":"Europe/Istanbul",
    "iso:country":"TR",
    "name:und_x_variant":[
        "\u00c7alca"
    ],
    "wof:name":"Sorkuncuk",
    "wof:placetype":"locality"
},
  "geometry": {"coordinates":[33.46353,41.35486],"type":"Point"}
}