{
  "type": "Feature",
  "properties": {
    "gn:admin1_code":"43",
    "gn:asciiname":"Yesilyurt",
    "gn:country_code":"TR",
    "gn:dem":1101,
    "gn:feature_class":"P",
    "gn:feature_code":"PPL",
    "gn:name":"Ye\u015filyurt",
    "gn:population":0,
    "gn:timezone":"Europe/Istanbul",
    "iso:country":"TR",
    "name:tur_x_preferred":[
        "Ye\u015filyurt"
    ],
    "name:und_x_variant":[
        "Ke\u00e7ililer",
        "Ke\u00e7iler",
        "Ke\u00e7iller"
    ],
    "wof:name":"Yesilyurt",
    "wof:placetype":"locality"
},
  "geometry": {"coordinates":[29.93611,38.96306],"type":"Point"}
}