{
  "type": "Feature",
  "properties": {
    "gn:admin1_code":"31",
    "gn:asciiname":"Kazkeli",
    "gn:country_code":"TR",
    "gn:dem":83,
    "gn:feature_class":"P",
    "gn:feature_code":"PPL",
    "gn:name":"Kazkeli",
    "gn:population":0,
    "gn:timezone":"Europe/Istanbul",
    "iso:country":"TR",
    "name:tur_x_preferred":[
        "Kazkeli"
    ],
    "wof:name":"Kazkeli",
    "wof:placetype":"locality"
},
  "geometry": {"coordinates":[36.36386,36.39091],"type":"Point"}
}