{
  "type": "Feature",
  "properties": {
    "gn:admin1_code":"65",
    "gn:asciiname":"Yumruklu",
    "gn:country_code":"TR",
    "gn:dem":2076,
    "gn:feature_class":"P",
    "gn:feature_code":"PPL",
    "gn:name":"Yumruklu",
    "gn:population":0,
    "gn:timezone":"Europe/Istanbul",
    "iso:country":"TR",
    "name:und_x_variant":[
        "Pirmeryem",
        "Yumruklu"
    ],
    "wof:name":"Yumruklu",
    "wof:placetype":"locality"
},
  "geometry": {"coordinates":[44.10234000000001,38.84399000000001],"type":"Point"}
}