{
  "type": "Feature",
  "properties": {
    "gn:admin1_code":"14",
    "gn:asciiname":"Alioglu",
    "gn:country_code":"TR",
    "gn:dem":730,
    "gn:feature_class":"P",
    "gn:feature_code":"PPL",
    "gn:name":"Alio\u011flu",
    "gn:population":0,
    "gn:timezone":"Europe/Istanbul",
    "iso:country":"TR",
    "wof:name":"Alioglu",
    "wof:placetype":"locality"
},
  "geometry": {"coordinates":[32.02188,40.92043],"type":"Point"}
}