{
  "type": "Feature",
  "properties": {
    "gn:admin1_code":"52.0",
    "gn:asciiname":"Hidirbeyli",
    "gn:country_code":"TR",
    "gn:dem":259,
    "gn:feature_class":"P",
    "gn:feature_code":"PPL",
    "gn:name":"H\u0131d\u0131rbeyli",
    "gn:population":0,
    "gn:timezone":"Europe/Istanbul",
    "iso:country":"TR",
    "wof:name":"Hidirbeyli",
    "wof:placetype":"locality"
},
  "geometry": {"coordinates":[37.45188,40.97584000000001],"type":"Point"}
}