{
  "type": "Feature",
  "properties": {
    "gn:admin1_code":"43",
    "gn:asciiname":"Kirankoy",
    "gn:country_code":"TR",
    "gn:dem":987,
    "gn:feature_class":"P",
    "gn:feature_code":"PPL",
    "gn:name":"K\u0131rank\u00f6y",
    "gn:population":0,
    "gn:timezone":"Europe/Istanbul",
    "iso:country":"TR",
    "name:tur_x_preferred":[
        "K\u0131rank\u00f6y"
    ],
    "name:tur_x_variant":[
        "K\u0131ran"
    ],
    "wof:name":"Kirankoy",
    "wof:placetype":"locality"
},
  "geometry": {"coordinates":[29.28495,39.11427],"type":"Point"}
}