{
  "type": "Feature",
  "properties": {
    "gn:admin1_code":"37.0",
    "gn:asciiname":"Kizilcaelma",
    "gn:country_code":"TR",
    "gn:dem":656,
    "gn:feature_class":"P",
    "gn:feature_code":"PPL",
    "gn:name":"K\u0131z\u0131lcaelma",
    "gn:population":0,
    "gn:timezone":"Europe/Istanbul",
    "iso:country":"TR",
    "name:tur_x_preferred":[
        "K\u0131z\u0131lcaelma"
    ],
    "name:tur_x_variant":[
        "De\u011firmenba\u015f\u0131"
    ],
    "wof:name":"Kizilcaelma",
    "wof:placetype":"locality"
},
  "geometry": {"coordinates":[34.02306,41.86443],"type":"Point"}
}