{
  "type": "Feature",
  "properties": {
    "gn:admin1_code":"21",
    "gn:asciiname":"Buyuransu",
    "gn:country_code":"TR",
    "gn:dem":813,
    "gn:feature_class":"P",
    "gn:feature_code":"PPL",
    "gn:name":"Buyuransu",
    "gn:population":0,
    "gn:timezone":"Europe/Istanbul",
    "iso:country":"TR",
    "name:tur_x_preferred":[
        "Buyuransu"
    ],
    "name:und_x_variant":[
        "\u015eenbeko"
    ],
    "wof:name":"Buyuransu",
    "wof:placetype":"locality"
},
  "geometry": {"coordinates":[40.09284,37.79494],"type":"Point"}
}