{
  "type": "Feature",
  "properties": {
    "gn:admin1_code":"8.0",
    "gn:asciiname":"Sehitlik",
    "gn:country_code":"TR",
    "gn:dem":236,
    "gn:feature_class":"P",
    "gn:feature_code":"PPL",
    "gn:name":"\u015eehitlik",
    "gn:population":0,
    "gn:timezone":"Europe/Istanbul",
    "iso:country":"TR",
    "name:und_x_variant":[
        "\u015eehitlik",
        "Sotibar"
    ],
    "wof:name":"Sehitlik",
    "wof:placetype":"locality"
},
  "geometry": {"coordinates":[41.83995,41.17521],"type":"Point"}
}