{
  "type": "Feature",
  "properties": {
    "gn:admin1_code":"31.0",
    "gn:asciiname":"Kamarly",
    "gn:country_code":"TR",
    "gn:dem":156,
    "gn:feature_class":"P",
    "gn:feature_code":"PPL",
    "gn:name":"Kamarly",
    "gn:population":0,
    "gn:timezone":"Europe/Istanbul",
    "iso:country":"TR",
    "name:und_x_variant":[
        "Kamarl\u0131"
    ],
    "wof:name":"Kamarly",
    "wof:placetype":"locality"
},
  "geometry": {"coordinates":[36.34167,36.03833],"type":"Point"}
}