{
  "type": "Feature",
  "properties": {
    "gn:admin1_code":"10.0",
    "gn:asciiname":"Yenice",
    "gn:country_code":"TR",
    "gn:dem":11,
    "gn:feature_class":"P",
    "gn:feature_code":"PPL",
    "gn:name":"Yenice",
    "gn:population":0,
    "gn:timezone":"Europe/Istanbul",
    "iso:country":"TR",
    "name:aze_x_preferred":[
        "Yengic\u0259"
    ],
    "name:bul_x_preferred":[
        "\u0419\u0435\u043d\u0438\u0434\u0436\u0435"
    ],
    "name:ceb_x_preferred":[
        "Yenice"
    ],
    "name:deu_x_preferred":[
        "Yenice"
    ],
    "name:fra_x_preferred":[
        "Yenice"
    ],
    "name:nld_x_preferred":[
        "Yenice"
    ],
    "name:tur_x_preferred":[
        "Yenice"
    ],
    "name:vie_x_preferred":[
        "Yenice"
    ],
    "wof:name":"Yenice",
    "wof:placetype":"locality"
},
  "geometry": {"coordinates":[28.11474,40.38789000000001],"type":"Point"}
}