{
  "type": "Feature",
  "properties": {
    "gn:admin1_code":"58",
    "gn:asciiname":"Huyukluyurt",
    "gn:country_code":"TR",
    "gn:dem":1601,
    "gn:feature_class":"P",
    "gn:feature_code":"PPL",
    "gn:name":"H\u00fcy\u00fckl\u00fcyurt",
    "gn:population":0,
    "gn:timezone":"Europe/Istanbul",
    "iso:country":"TR",
    "wof:name":"Huyukluyurt",
    "wof:placetype":"locality"
},
  "geometry": {"coordinates":[37.13244,39.27947],"type":"Point"}
}