{
  "type": "Feature",
  "properties": {
    "gn:admin1_code":"57.0",
    "gn:asciiname":"Durhacili",
    "gn:country_code":"TR",
    "gn:dem":1253,
    "gn:feature_class":"P",
    "gn:feature_code":"PPL",
    "gn:name":"Durhac\u0131l\u0131",
    "gn:population":0,
    "gn:timezone":"Europe/Istanbul",
    "iso:country":"TR",
    "name:und_x_variant":[
        "Durahac\u0131l\u0131",
        "Durhac\u0131l\u0131"
    ],
    "wof:name":"Durhacili",
    "wof:placetype":"locality"
},
  "geometry": {"coordinates":[34.45646,41.43333],"type":"Point"}
}