{
  "type": "Feature",
  "properties": {
    "gn:admin1_code":"21.0",
    "gn:asciiname":"Harapkurt",
    "gn:cc2":"TR",
    "gn:country_code":"TR",
    "gn:dem":709,
    "gn:feature_class":"P",
    "gn:feature_code":"PPL",
    "gn:name":"Harapk\u00fcrt",
    "gn:population":0,
    "gn:timezone":"Europe/Istanbul",
    "iso:country":"TR",
    "name:tur_x_preferred":[
        "Harapk\u00fcrt"
    ],
    "name:und_x_variant":[
        "G\u00fcndik",
        "Harabk\u00fcrt",
        "Kharapkyurt"
    ],
    "wof:name":"Harapkurt",
    "wof:placetype":"locality"
},
  "geometry": {"coordinates":[40.6125,37.71417],"type":"Point"}
}