{
  "type": "Feature",
  "properties": {
    "gn:admin1_code":"65.0",
    "gn:asciiname":"Guragac",
    "gn:country_code":"TR",
    "gn:dem":1809,
    "gn:feature_class":"P",
    "gn:feature_code":"PPL",
    "gn:name":"G\u00fcra\u011fa\u00e7",
    "gn:population":0,
    "gn:timezone":"Europe/Istanbul",
    "iso:country":"TR",
    "name:tur_x_preferred":[
        "G\u00fcra\u011fa\u00e7"
    ],
    "wof:name":"Guragac",
    "wof:placetype":"locality"
},
  "geometry": {"coordinates":[43.15399,38.03737],"type":"Point"}
}