{
  "type": "Feature",
  "properties": {
    "gn:admin1_code":"17",
    "gn:asciiname":"Merkez",
    "gn:country_code":"TR",
    "gn:dem":11,
    "gn:feature_class":"P",
    "gn:feature_code":"PPLA2",
    "gn:name":"Merkez",
    "gn:population":0,
    "gn:timezone":"Europe/Istanbul",
    "iso:country":"TR",
    "wof:name":"Merkez",
    "wof:placetype":"locality"
},
  "geometry": {"coordinates":[26.42075,40.12954000000001],"type":"Point"}
}