{
  "type": "Feature",
  "properties": {
    "gn:admin1_code":"32.0",
    "gn:asciiname":"Gokcukur",
    "gn:country_code":"TR",
    "gn:dem":185,
    "gn:feature_class":"P",
    "gn:feature_code":"PPL",
    "gn:name":"G\u014dk\u00e7ukur",
    "gn:population":0,
    "gn:timezone":"Europe/Istanbul",
    "iso:country":"TR",
    "wof:name":"Gokcukur",
    "wof:placetype":"locality"
},
  "geometry": {"coordinates":[33.2142,36.16375],"type":"Point"}
}