{
  "type": "Feature",
  "properties": {
    "iso:country":"TR",
    "qs:name":"Yeni",
    "qs:name_adm0":"Turkey",
    "qs:name_adm1":"Kocaeli",
    "qs:photos":1,
    "qs:photos_1k":1,
    "qs:photos_9k":1,
    "qs:photos_9r":1,
    "qs:photos_all":1,
    "qs:photos_sr":1,
    "qs:placetype":"Suburb",
    "qs:pop_sr":"0",
    "wd:wordcount":54,
    "wof:name":"Yeni",
    "wof:placetype":"neighbourhood"
},
  "geometry": {"coordinates":[29.928302,40.763901],"type":"Point"}
}