{
  "type": "Feature",
  "properties": {
    "gn:admin1_code":"68.0",
    "gn:asciiname":"Gokcedere",
    "gn:country_code":"TR",
    "gn:dem":1092,
    "gn:feature_class":"P",
    "gn:feature_code":"PPL",
    "gn:name":"G\u00f6k\u00e7edere",
    "gn:population":0,
    "gn:timezone":"Europe/Istanbul",
    "iso:country":"TR",
    "wof:name":"Gokcedere",
    "wof:placetype":"locality"
},
  "geometry": {"coordinates":[32.99515,40.25869],"type":"Point"}
}