{
  "type": "Feature",
  "properties": {
    "gn:admin1_code":"35",
    "gn:asciiname":"Demircidere",
    "gn:country_code":"TR",
    "gn:dem":271,
    "gn:feature_class":"P",
    "gn:feature_code":"PPL",
    "gn:name":"Demircidere",
    "gn:population":0,
    "gn:timezone":"Europe/Istanbul",
    "iso:country":"TR",
    "wof:name":"Demircidere",
    "wof:placetype":"locality"
},
  "geometry": {"coordinates":[26.9198,39.26472],"type":"Point"}
}