{
  "type": "Feature",
  "properties": {
    "gn:admin1_code":"26",
    "gn:asciiname":"Karapazar",
    "gn:country_code":"TR",
    "gn:dem":1038,
    "gn:feature_class":"P",
    "gn:feature_code":"PPL",
    "gn:name":"Karapazar",
    "gn:population":0,
    "gn:timezone":"Europe/Istanbul",
    "iso:country":"TR",
    "wof:name":"Karapazar",
    "wof:placetype":"locality"
},
  "geometry": {"coordinates":[30.56722,39.59694],"type":"Point"}
}