{
  "type": "Feature",
  "properties": {
    "gn:admin1_code":"49",
    "gn:asciiname":"Asagi Buklu",
    "gn:country_code":"TR",
    "gn:dem":1800,
    "gn:feature_class":"P",
    "gn:feature_code":"PPL",
    "gn:name":"A\u015fa\u011f\u0131 B\u00fckl\u00fc",
    "gn:population":0,
    "gn:timezone":"Europe/Istanbul",
    "iso:country":"TR",
    "name:tur_x_preferred":[
        "A\u015fa\u011f\u0131 B\u00fckl\u00fc"
    ],
    "wof:name":"Asagi Buklu",
    "wof:placetype":"locality"
},
  "geometry": {"coordinates":[41.88748,38.92732],"type":"Point"}
}