{
  "type": "Feature",
  "properties": {
    "gn:admin1_code":"24",
    "gn:asciiname":"Topkapi",
    "gn:country_code":"TR",
    "gn:dem":1074,
    "gn:feature_class":"P",
    "gn:feature_code":"PPL",
    "gn:name":"Topkap\u0131",
    "gn:population":0,
    "gn:timezone":"Europe/Istanbul",
    "iso:country":"TR",
    "name:und_x_variant":[
        "Encitli",
        "En\u00e7iti",
        "Topkap\u0131"
    ],
    "wof:name":"Topkapi",
    "wof:placetype":"locality"
},
  "geometry": {"coordinates":[38.69334,39.08969],"type":"Point"}
}