{
  "type": "Feature",
  "properties": {
    "gn:admin1_code":"11.0",
    "gn:asciiname":"Tarpak",
    "gn:country_code":"TR",
    "gn:dem":257,
    "gn:feature_class":"P",
    "gn:feature_code":"PPL",
    "gn:name":"Tarpak",
    "gn:population":0,
    "gn:timezone":"Europe/Istanbul",
    "iso:country":"TR",
    "name:tur_x_preferred":[
        "Tarpak"
    ],
    "wof:name":"Tarpak",
    "wof:placetype":"locality"
},
  "geometry": {"coordinates":[30.43912000000001,40.03316],"type":"Point"}
}