{
  "type": "Feature",
  "properties": {
    "gn:admin1_code":"69.0",
    "gn:asciiname":"Mahmatli",
    "gn:country_code":"TR",
    "gn:dem":1633,
    "gn:feature_class":"P",
    "gn:feature_code":"PPL",
    "gn:name":"Mahmatl\u0131",
    "gn:population":0,
    "gn:timezone":"Europe/Istanbul",
    "iso:country":"TR",
    "wof:name":"Mahmatli",
    "wof:placetype":"locality"
},
  "geometry": {"coordinates":[39.53114,40.01756],"type":"Point"}
}