{
  "type": "Feature",
  "properties": {
    "gn:admin1_code":"25.0",
    "gn:asciiname":"Baskent",
    "gn:country_code":"TR",
    "gn:dem":2201,
    "gn:feature_class":"P",
    "gn:feature_code":"PPL",
    "gn:name":"Ba\u015fkent",
    "gn:population":0,
    "gn:timezone":"Europe/Istanbul",
    "iso:country":"TR",
    "name:und_x_variant":[
        "Ba\u015fkend",
        "Ba\u015fkent"
    ],
    "wof:name":"Baskent",
    "wof:placetype":"locality"
},
  "geometry": {"coordinates":[41.1001,40.28896],"type":"Point"}
}