{
  "type": "Feature",
  "properties": {
    "gn:admin1_code":"31",
    "gn:asciiname":"Gokgol",
    "gn:country_code":"TR",
    "gn:dem":303,
    "gn:feature_class":"P",
    "gn:feature_code":"PPL",
    "gn:name":"G\u00f6kg\u00f6l",
    "gn:population":0,
    "gn:timezone":"Europe/Istanbul",
    "iso:country":"TR",
    "name:tur_x_preferred":[
        "G\u00f6kg\u00f6l"
    ],
    "wof:name":"Gokgol",
    "wof:placetype":"locality"
},
  "geometry": {"coordinates":[36.24521,36.95496],"type":"Point"}
}