{
  "type": "Feature",
  "properties": {
    "gn:admin1_code":"23",
    "gn:asciiname":"Beyelmasi",
    "gn:country_code":"TR",
    "gn:dem":1063,
    "gn:feature_class":"P",
    "gn:feature_code":"PPL",
    "gn:name":"Beyelmas\u0131",
    "gn:population":0,
    "gn:timezone":"Europe/Istanbul",
    "iso:country":"TR",
    "name:tur_x_preferred":[
        "Beyelmas\u0131"
    ],
    "name:und_x_variant":[
        "Hozakpur",
        "Beylemas\u0131",
        "Hozakbur"
    ],
    "wof:name":"Beyelmasi",
    "wof:placetype":"locality"
},
  "geometry": {"coordinates":[38.69873,38.97458],"type":"Point"}
}