{
  "type": "Feature",
  "properties": {
    "gn:admin1_code":"25",
    "gn:asciiname":"Merhuk",
    "gn:country_code":"TR",
    "gn:dem":2080,
    "gn:feature_class":"P",
    "gn:feature_code":"PPL",
    "gn:name":"Merhuk",
    "gn:population":0,
    "gn:timezone":"Europe/Istanbul",
    "iso:country":"TR",
    "wof:name":"Merhuk",
    "wof:placetype":"locality"
},
  "geometry": {"coordinates":[41.28333,39.55],"type":"Point"}
}