{
  "type": "Feature",
  "properties": {
    "gn:admin1_code":"43",
    "gn:asciiname":"Yeginler",
    "gn:country_code":"TR",
    "gn:dem":1142,
    "gn:feature_class":"P",
    "gn:feature_code":"PPL",
    "gn:name":"Ye\u011finler",
    "gn:population":0,
    "gn:timezone":"Europe/Istanbul",
    "iso:country":"TR",
    "name:und_x_variant":[
        "Ye\u011fenler",
        "Ye\u011finler"
    ],
    "wof:name":"Yeginler",
    "wof:placetype":"locality"
},
  "geometry": {"coordinates":[29.58818,39.10178],"type":"Point"}
}