{
  "type": "Feature",
  "properties": {
    "gn:admin1_code":"04",
    "gn:asciiname":"Celi",
    "gn:country_code":"TR",
    "gn:dem":2300,
    "gn:feature_class":"P",
    "gn:feature_code":"PPL",
    "gn:name":"\u00c7eli",
    "gn:population":0,
    "gn:timezone":"Europe/Istanbul",
    "iso:country":"TR",
    "name:cat_x_preferred":[
        "Celi"
    ],
    "name:deu_x_preferred":[
        "Celi"
    ],
    "name:fra_x_preferred":[
        "Celi"
    ],
    "name:nds_x_preferred":[
        "Celi"
    ],
    "name:tur_x_preferred":[
        "\u00c7eli"
    ],
    "wof:name":"Celi",
    "wof:placetype":"locality"
},
  "geometry": {"coordinates":[43.36667,39.51667],"type":"Point"}
}