{
  "type": "Feature",
  "properties": {
    "gn:admin1_code":"80",
    "gn:asciiname":"Yalaz",
    "gn:country_code":"TR",
    "gn:dem":563,
    "gn:feature_class":"P",
    "gn:feature_code":"PPL",
    "gn:name":"Yalaz",
    "gn:population":0,
    "gn:timezone":"Europe/Istanbul",
    "iso:country":"TR",
    "name:und_x_variant":[
        "Arzanakh",
        "Erzanih",
        "Arzanah",
        "Erzani",
        "Erzanik",
        "Yalaz"
    ],
    "wof:name":"Yalaz",
    "wof:placetype":"locality"
},
  "geometry": {"coordinates":[42.00724,37.41313],"type":"Point"}
}