{
  "type": "Feature",
  "properties": {
    "gn:admin1_code":"32.0",
    "gn:asciiname":"Senyurt",
    "gn:country_code":"TR",
    "gn:dem":1305,
    "gn:feature_class":"P",
    "gn:feature_code":"PPL",
    "gn:name":"\u015eenyurt",
    "gn:population":0,
    "gn:timezone":"Europe/Istanbul",
    "iso:country":"TR",
    "wof:name":"Senyurt",
    "wof:placetype":"locality"
},
  "geometry": {"coordinates":[33.11154000000001,36.44917],"type":"Point"}
}