{
  "type": "Feature",
  "properties": {
    "gn:admin1_code":"82",
    "gn:asciiname":"Ilipinar",
    "gn:country_code":"TR",
    "gn:dem":1225,
    "gn:feature_class":"P",
    "gn:feature_code":"PPL",
    "gn:name":"Il\u0131p\u0131nar",
    "gn:population":0,
    "gn:timezone":"Europe/Istanbul",
    "iso:country":"TR",
    "wof:name":"Ilipinar",
    "wof:placetype":"locality"
},
  "geometry": {"coordinates":[33.11523,40.79688],"type":"Point"}
}