{
  "type": "Feature",
  "properties": {
    "gn:admin1_code":"70.0",
    "gn:asciiname":"Guzelkoy",
    "gn:country_code":"TR",
    "gn:dem":1199,
    "gn:feature_class":"P",
    "gn:feature_code":"PPL",
    "gn:name":"G\u00fczelk\u00f6y",
    "gn:population":0,
    "gn:timezone":"Europe/Istanbul",
    "iso:country":"TR",
    "wof:name":"Guzelkoy",
    "wof:placetype":"locality"
},
  "geometry": {"coordinates":[44.51348,37.26534],"type":"Point"}
}