{
  "type": "Feature",
  "properties": {
    "gn:admin1_code":"08",
    "gn:asciiname":"Akdere",
    "gn:country_code":"TR",
    "gn:dem":179,
    "gn:feature_class":"P",
    "gn:feature_code":"PPL",
    "gn:name":"Akdere",
    "gn:population":0,
    "gn:timezone":"Europe/Istanbul",
    "iso:country":"TR",
    "name:tur_x_preferred":[
        "Akdere"
    ],
    "wof:name":"Akdere",
    "wof:placetype":"locality"
},
  "geometry": {"coordinates":[41.51515,41.45871],"type":"Point"}
}