{
  "type": "Feature",
  "properties": {
    "gn:admin1_code":"81",
    "gn:asciiname":"Aysehoca",
    "gn:country_code":"TR",
    "gn:dem":40,
    "gn:feature_class":"P",
    "gn:feature_code":"PPL",
    "gn:name":"Ay\u015fehoca",
    "gn:population":0,
    "gn:timezone":"Europe/Istanbul",
    "iso:country":"TR",
    "name:deu_x_preferred":[
        "Ay\u015fehoca"
    ],
    "name:msa_x_preferred":[
        "Ay\u015fehoca"
    ],
    "name:tur_x_preferred":[
        "Ay\u015fehoca"
    ],
    "name:und_x_variant":[
        "Ay\u015fehoca"
    ],
    "name:vie_x_preferred":[
        "Ay\u015fehoca"
    ],
    "wof:name":"Aysehoca",
    "wof:placetype":"locality"
},
  "geometry": {"coordinates":[35.85117,37.26378],"type":"Point"}
}