{
  "type": "Feature",
  "properties": {
    "gn:admin1_code":"48",
    "gn:asciiname":"Cilek",
    "gn:country_code":"TR",
    "gn:dem":183,
    "gn:feature_class":"P",
    "gn:feature_code":"PPL",
    "gn:name":"\u00c7ilek",
    "gn:population":0,
    "gn:timezone":"Europe/Istanbul",
    "iso:country":"TR",
    "name:tur_x_preferred":[
        "\u00c7ilek"
    ],
    "wof:name":"Cilek",
    "wof:placetype":"locality"
},
  "geometry": {"coordinates":[27.4963,37.04737],"type":"Point"}
}