{
  "type": "Feature",
  "properties": {
    "gn:admin1_code":"12",
    "gn:asciiname":"Karapolat",
    "gn:country_code":"TR",
    "gn:dem":1460,
    "gn:feature_class":"P",
    "gn:feature_code":"PPL",
    "gn:name":"Karapolat",
    "gn:population":0,
    "gn:timezone":"Europe/Istanbul",
    "iso:country":"TR",
    "name:und_x_variant":[
        "Karapulat",
        "Karapolat"
    ],
    "wof:name":"Karapolat",
    "wof:placetype":"locality"
},
  "geometry": {"coordinates":[40.47844,39.45482],"type":"Point"}
}