{
  "type": "Feature",
  "properties": {
    "gn:admin1_code":"64",
    "gn:asciiname":"Colaklar",
    "gn:country_code":"TR",
    "gn:dem":863,
    "gn:feature_class":"P",
    "gn:feature_code":"PPL",
    "gn:name":"\u00c7olaklar",
    "gn:population":0,
    "gn:timezone":"Europe/Istanbul",
    "iso:country":"TR",
    "name:tur_x_preferred":[
        "\u00c7olaklar"
    ],
    "wof:name":"Colaklar",
    "wof:placetype":"locality"
},
  "geometry": {"coordinates":[28.91107,38.52412],"type":"Point"}
}