{
  "type": "Feature",
  "properties": {
    "gn:country":"TR",
    "gn:fcode":"PPLX",
    "gn:population":0,
    "iso:country":"TR",
    "qs_pg:aaroncc":"TR",
    "qs_pg:gn_country":"TR",
    "qs_pg:gn_fcode":"PPLX",
    "qs_pg:gn_pop":0,
    "qs_pg:name":"\u00c7aglayan",
    "qs_pg:name_adm0":"Turkey",
    "qs_pg:name_adm1":"Antalya",
    "qs_pg:photos":286,
    "qs_pg:photos_1k":58,
    "qs_pg:photos_9k":1,
    "qs_pg:photos_9r":4,
    "qs_pg:photos_all":286,
    "qs_pg:photos_sr":5,
    "qs_pg:pop_sr":0,
    "qs_pg:qs_pg_placetype":"neighbourhood",
    "qs_pg:qs_pg_placetype_gp":"Suburb",
    "qs_pg:woe_adm0":23424969,
    "woe:adm0_id":23424969,
    "woe:name_adm0":"Turkey",
    "woe:name_adm1":"Antalya",
    "woe:placetype":"Suburb",
    "wof:name":"\u00c7aglayan",
    "wof:placetype":"neighbourhood"
},
  "geometry": {"coordinates":[30.7705,36.85332],"type":"Point"}
}