{
  "type": "Feature",
  "properties": {
    "gn:admin1_code":"44",
    "gn:asciiname":"Tosunlu",
    "gn:country_code":"TR",
    "gn:dem":788,
    "gn:feature_class":"P",
    "gn:feature_code":"PPL",
    "gn:name":"Tosunlu",
    "gn:population":0,
    "gn:timezone":"Europe/Istanbul",
    "iso:country":"TR",
    "name:und_x_variant":[
        "Doyumlu",
        "Tosunlu"
    ],
    "wof:name":"Tosunlu",
    "wof:placetype":"locality"
},
  "geometry": {"coordinates":[38.82273,38.22917],"type":"Point"}
}