{
  "type": "Feature",
  "properties": {
    "gn:admin1_code":"89.0",
    "gn:asciiname":"Buyukyayalar",
    "gn:country_code":"TR",
    "gn:dem":922,
    "gn:feature_class":"P",
    "gn:feature_code":"PPL",
    "gn:name":"B\u00fcy\u00fckyayalar",
    "gn:population":0,
    "gn:timezone":"Europe/Istanbul",
    "iso:country":"TR",
    "name:und_x_variant":[
        "Yayalar",
        "Yayalarkebir",
        "B\u00fcy\u00fckyayalar"
    ],
    "wof:name":"Buyukyayalar",
    "wof:placetype":"locality"
},
  "geometry": {"coordinates":[32.47594,40.92961],"type":"Point"}
}