{
  "type": "Feature",
  "properties": {
    "iso:country":"TR",
    "name:eng_x_preferred":[
        "Hasanli"
    ],
    "name:tur_x_preferred":[
        "Hasanl\u0131"
    ],
    "wof:name":"Hasanli",
    "wof:placetype":"neighbourhood"
},
  "geometry": {"coordinates":[29.66564063213745,41.01766908101989],"type":"Point"}
}