{
  "type": "Feature",
  "properties": {
    "gn:admin1_code":"16.0",
    "gn:asciiname":"Karaislah",
    "gn:country_code":"TR",
    "gn:dem":791,
    "gn:feature_class":"P",
    "gn:feature_code":"PPL",
    "gn:name":"Karaislah",
    "gn:population":0,
    "gn:timezone":"Europe/Istanbul",
    "iso:country":"TR",
    "name:tur_x_preferred":[
        "Karaislah"
    ],
    "wof:name":"Karaislah",
    "wof:placetype":"locality"
},
  "geometry": {"coordinates":[29.12289,40.02234],"type":"Point"}
}