{
  "type": "Feature",
  "properties": {
    "gn:admin1_code":"39.0",
    "gn:asciiname":"Yenitasli",
    "gn:country_code":"TR",
    "gn:dem":111,
    "gn:feature_class":"P",
    "gn:feature_code":"PPL",
    "gn:name":"Yenita\u015fl\u0131",
    "gn:population":0,
    "gn:timezone":"Europe/Istanbul",
    "iso:country":"TR",
    "name:tur_x_preferred":[
        "Yenita\u015fl\u0131"
    ],
    "wof:name":"Yenitasli",
    "wof:placetype":"locality"
},
  "geometry": {"coordinates":[27.38936,41.48648],"type":"Point"}
}