{
  "type": "Feature",
  "properties": {
    "gn:admin1_code":"25",
    "gn:asciiname":"Dagcayiri",
    "gn:country_code":"TR",
    "gn:dem":2123,
    "gn:feature_class":"P",
    "gn:feature_code":"PPL",
    "gn:name":"Da\u011f\u00e7ay\u0131r\u0131",
    "gn:population":0,
    "gn:timezone":"Europe/Istanbul",
    "iso:country":"TR",
    "name:tur_x_preferred":[
        "Da\u011f\u00e7ay\u0131r\u0131"
    ],
    "wof:name":"Dagcayiri",
    "wof:placetype":"locality"
},
  "geometry": {"coordinates":[41.78315,39.1976],"type":"Point"}
}