{
  "type": "Feature",
  "properties": {
    "gn:admin1_code":"37.0",
    "gn:asciiname":"Tekkekoy",
    "gn:country_code":"TR",
    "gn:dem":1396,
    "gn:feature_class":"P",
    "gn:feature_code":"PPL",
    "gn:name":"Tekkek\u00f6y",
    "gn:population":0,
    "gn:timezone":"Europe/Istanbul",
    "iso:country":"TR",
    "wof:name":"Tekkekoy",
    "wof:placetype":"locality"
},
  "geometry": {"coordinates":[34.03425,41.21656],"type":"Point"}
}