{
  "type": "Feature",
  "properties": {
    "gn:admin1_code":"66",
    "gn:asciiname":"Dikir",
    "gn:country_code":"TR",
    "gn:dem":1143,
    "gn:feature_class":"P",
    "gn:feature_code":"PPL",
    "gn:name":"Dikir",
    "gn:population":0,
    "gn:timezone":"Europe/Istanbul",
    "iso:country":"TR",
    "name:und_x_variant":[
        "G\u00fcnyaz\u0131"
    ],
    "wof:name":"Dikir",
    "wof:placetype":"locality"
},
  "geometry": {"coordinates":[35.52548,39.87099],"type":"Point"}
}