{
  "type": "Feature",
  "properties": {
    "gn:admin1_code":"72.0",
    "gn:asciiname":"Hirbegura",
    "gn:country_code":"TR",
    "gn:dem":543,
    "gn:feature_class":"P",
    "gn:feature_code":"PPL",
    "gn:name":"H\u0131rbeg\u00fcra",
    "gn:population":0,
    "gn:timezone":"Europe/Istanbul",
    "iso:country":"TR",
    "name:tur_x_preferred":[
        "H\u0131rbeg\u00fcra"
    ],
    "wof:name":"Hirbegura",
    "wof:placetype":"locality"
},
  "geometry": {"coordinates":[40.24677,37.27468],"type":"Point"}
}