{
  "type": "Feature",
  "properties": {
    "gn:admin1_code":"48",
    "gn:asciiname":"Ulupinar",
    "gn:country_code":"TR",
    "gn:dem":260,
    "gn:feature_class":"P",
    "gn:feature_code":"PPL",
    "gn:name":"Ulup\u0131nar",
    "gn:population":0,
    "gn:timezone":"Europe/Istanbul",
    "iso:country":"TR",
    "name:tur_x_preferred":[
        "Ulup\u0131nar"
    ],
    "wof:name":"Ulupinar",
    "wof:placetype":"locality"
},
  "geometry": {"coordinates":[27.83338,37.13702],"type":"Point"}
}