{
  "type": "Feature",
  "properties": {
    "gn:admin1_code":"63",
    "gn:asciiname":"Gecili",
    "gn:country_code":"TR",
    "gn:dem":389,
    "gn:feature_class":"P",
    "gn:feature_code":"PPL",
    "gn:name":"Gecili",
    "gn:population":0,
    "gn:timezone":"Europe/Istanbul",
    "iso:country":"TR",
    "name:und_x_variant":[
        "Kechili",
        "Ke\u00e7ili"
    ],
    "wof:name":"Gecili",
    "wof:placetype":"locality"
},
  "geometry": {"coordinates":[38.77647,36.73472],"type":"Point"}
}