{
  "type": "Feature",
  "properties": {
    "gn:admin1_code":"25.0",
    "gn:asciiname":"Sariyazi",
    "gn:country_code":"TR",
    "gn:dem":1847,
    "gn:feature_class":"P",
    "gn:feature_code":"PPL",
    "gn:name":"Sar\u0131yaz\u0131",
    "gn:population":0,
    "gn:timezone":"Europe/Istanbul",
    "iso:country":"TR",
    "wof:name":"Sariyazi",
    "wof:placetype":"locality"
},
  "geometry": {"coordinates":[41.06667,40.01667],"type":"Point"}
}