{
  "type": "Feature",
  "properties": {
    "gn:admin1_code":"68",
    "gn:asciiname":"Cokoren",
    "gn:country_code":"TR",
    "gn:dem":841,
    "gn:feature_class":"P",
    "gn:feature_code":"PPL",
    "gn:name":"\u00c7ok\u00f6ren",
    "gn:population":0,
    "gn:timezone":"Europe/Istanbul",
    "iso:country":"TR",
    "name:und_x_variant":[
        "\u00c7okviran",
        "\u00c7ok\u00f6ren"
    ],
    "wof:name":"Cokoren",
    "wof:placetype":"locality"
},
  "geometry": {"coordinates":[32.43611,39.65844],"type":"Point"}
}