{
  "type": "Feature",
  "properties": {
    "gn:admin1_code":"12",
    "gn:asciiname":"Amasya",
    "gn:country_code":"TR",
    "gn:dem":2117,
    "gn:feature_class":"P",
    "gn:feature_code":"PPL",
    "gn:name":"Amasya",
    "gn:population":0,
    "gn:timezone":"Europe/Istanbul",
    "iso:country":"TR",
    "wof:name":"Amasya",
    "wof:placetype":"locality"
},
  "geometry": {"coordinates":[41.17583,39.06417],"type":"Point"}
}