{
  "type": "Feature",
  "properties": {
    "gn:admin1_code":"82.0",
    "gn:asciiname":"Yukarioz",
    "gn:country_code":"TR",
    "gn:dem":1250,
    "gn:feature_class":"P",
    "gn:feature_code":"PPL",
    "gn:name":"Yukar\u0131\u00f6z",
    "gn:population":0,
    "gn:timezone":"Europe/Istanbul",
    "iso:country":"TR",
    "name:und_x_variant":[
        "Yukar\u0131badi\u011fin",
        "Yukar\u0131\u00f6z"
    ],
    "wof:name":"Yukarioz",
    "wof:placetype":"locality"
},
  "geometry": {"coordinates":[33.83822,40.81117],"type":"Point"}
}