{
  "type": "Feature",
  "properties": {
    "gn:admin1_code":"2.0",
    "gn:asciiname":"Incirli",
    "gn:country_code":"TR",
    "gn:dem":1264,
    "gn:feature_class":"P",
    "gn:feature_code":"PPL",
    "gn:name":"\u0130ncirli",
    "gn:population":0,
    "gn:timezone":"Europe/Istanbul",
    "iso:country":"TR",
    "wof:name":"Incirli",
    "wof:placetype":"locality"
},
  "geometry": {"coordinates":[38.40665,38.0134],"type":"Point"}
}