{
  "type": "Feature",
  "properties": {
    "iso:country":"TR",
    "name:eng_x_preferred":[
        "Parseller"
    ],
    "name:tur_x_preferred":[
        "Parseller"
    ],
    "wof:name":"Parseller",
    "wof:placetype":"neighbourhood"
},
  "geometry": {"coordinates":[29.15215497116418,41.03027515387065],"type":"Point"}
}