{
  "type": "Feature",
  "properties": {
    "gn:admin1_code":"68",
    "gn:asciiname":"Yenicimsit",
    "gn:country_code":"TR",
    "gn:dem":887,
    "gn:feature_class":"P",
    "gn:feature_code":"PPL",
    "gn:name":"Yeni\u00e7im\u015fit",
    "gn:population":0,
    "gn:timezone":"Europe/Istanbul",
    "iso:country":"TR",
    "name:und_x_variant":[
        "Yeni\u00e7im\u015fit",
        "\u00c7im\u015fit"
    ],
    "wof:name":"Yenicimsit",
    "wof:placetype":"locality"
},
  "geometry": {"coordinates":[32.53664000000001,39.93593],"type":"Point"}
}