{
  "type": "Feature",
  "properties": {
    "gn:admin1_code":"44",
    "gn:asciiname":"Sisman",
    "gn:country_code":"TR",
    "gn:dem":727,
    "gn:feature_class":"P",
    "gn:feature_code":"PPL",
    "gn:name":"\u015ei\u015fman",
    "gn:population":0,
    "gn:timezone":"Europe/Istanbul",
    "iso:country":"TR",
    "name:und_x_variant":[
        "F\u0131rat",
        "\u015ei\u015fman"
    ],
    "wof:name":"Sisman",
    "wof:placetype":"locality"
},
  "geometry": {"coordinates":[38.57512,38.41964],"type":"Point"}
}