{
  "type": "Feature",
  "properties": {
    "gn:admin1_code":"72.0",
    "gn:asciiname":"Telharzem",
    "gn:cc2":"TR",
    "gn:country_code":"TR",
    "gn:dem":539,
    "gn:feature_class":"P",
    "gn:feature_code":"PPL",
    "gn:name":"Telharzem",
    "gn:population":0,
    "gn:timezone":"Europe/Istanbul",
    "iso:country":"TR",
    "name:rus_x_preferred":[
        "Tel\u2019kharzem"
    ],
    "wof:name":"Telharzem",
    "wof:placetype":"locality"
},
  "geometry": {"coordinates":[40.63056,37.2425],"type":"Point"}
}