{
  "type": "Feature",
  "properties": {
    "gn:admin1_code":"23",
    "gn:asciiname":"Akseki",
    "gn:country_code":"TR",
    "gn:dem":1001,
    "gn:feature_class":"P",
    "gn:feature_code":"PPL",
    "gn:name":"Akseki",
    "gn:population":0,
    "gn:timezone":"Europe/Istanbul",
    "iso:country":"TR",
    "name:ceb_x_preferred":[
        "Akseki"
    ],
    "name:deu_x_preferred":[
        "Akseki"
    ],
    "name:diq_x_preferred":[
        "Akseki"
    ],
    "name:fas_x_preferred":[
        "\u0627\u06a9\u0633\u06a9\u06cc"
    ],
    "name:fra_x_preferred":[
        "Akseki"
    ],
    "name:ita_x_preferred":[
        "Akseki"
    ],
    "name:lbe_x_preferred":[
        "\u0410\u043a\u044a\u0441\u0435\u043a\u0438"
    ],
    "name:mrj_x_preferred":[
        "\u0410\u043a\u0441\u0435\u043a\u0438"
    ],
    "name:msa_x_preferred":[
        "Akseki"
    ],
    "name:nor_x_preferred":[
        "Akseki"
    ],
    "name:por_x_preferred":[
        "Akseki"
    ],
    "name:rus_x_preferred":[
        "\u0410\u043a\u0441\u0435\u043a\u0438"
    ],
    "name:swa_x_preferred":[
        "Akseki"
    ],
    "name:tur_x_preferred":[
        "Akseki"
    ],
    "name:und_x_variant":[
        "Apseki",
        "Akseki"
    ],
    "name:urd_x_preferred":[
        "\u0622\u0642\u0633\u06cc\u06a9\u06cc"
    ],
    "name:vie_x_preferred":[
        "Akseki"
    ],
    "wof:name":"Akseki",
    "wof:placetype":"locality"
},
  "geometry": {"coordinates":[39.11609,38.35824],"type":"Point"}
}