{
  "type": "Feature",
  "properties": {
    "gn:admin1_code":"39.0",
    "gn:asciiname":"Demircihalil",
    "gn:country_code":"TR",
    "gn:dem":419,
    "gn:feature_class":"P",
    "gn:feature_code":"PPL",
    "gn:name":"Demircihalil",
    "gn:population":0,
    "gn:timezone":"Europe/Istanbul",
    "iso:country":"TR",
    "name:und_x_variant":[
        "Demircihali"
    ],
    "wof:name":"Demircihalil",
    "wof:placetype":"locality"
},
  "geometry": {"coordinates":[27.30144,41.80655],"type":"Point"}
}