{
  "type": "Feature",
  "properties": {
    "gn:admin1_code":"4.0",
    "gn:asciiname":"Subesigi",
    "gn:country_code":"TR",
    "gn:dem":1722,
    "gn:feature_class":"P",
    "gn:feature_code":"PPL",
    "gn:name":"Sube\u015fi\u011fi",
    "gn:population":0,
    "gn:timezone":"Europe/Istanbul",
    "iso:country":"TR",
    "name:tur_x_preferred":[
        "Sube\u015fi\u011fi"
    ],
    "wof:name":"Subesigi",
    "wof:placetype":"locality"
},
  "geometry": {"coordinates":[43.86355,39.61737],"type":"Point"}
}