{
  "type": "Feature",
  "properties": {
    "gn:admin1_code":"83",
    "gn:asciiname":"Isikli",
    "gn:country_code":"TR",
    "gn:dem":1153,
    "gn:feature_class":"P",
    "gn:feature_code":"PPL",
    "gn:name":"I\u015f\u0131kl\u0131",
    "gn:population":0,
    "gn:timezone":"Europe/Istanbul",
    "iso:country":"TR",
    "name:und_x_variant":[
        "\u00c7arp\u0131n",
        "I\u015f\u0131kl\u0131"
    ],
    "wof:name":"Isikli",
    "wof:placetype":"locality"
},
  "geometry": {"coordinates":[37.19248,37.1453],"type":"Point"}
}