{
  "type": "Feature",
  "properties": {
    "gn:admin1_code":"44",
    "gn:asciiname":"Kapikaya",
    "gn:country_code":"TR",
    "gn:dem":813,
    "gn:feature_class":"P",
    "gn:feature_code":"PPL",
    "gn:name":"Kap\u0131kaya",
    "gn:population":0,
    "gn:timezone":"Europe/Istanbul",
    "iso:country":"TR",
    "name:tur_x_preferred":[
        "Kap\u0131kaya"
    ],
    "wof:name":"Kapikaya",
    "wof:placetype":"locality"
},
  "geometry": {"coordinates":[38.57378,38.36474000000001],"type":"Point"}
}