{
  "type": "Feature",
  "properties": {
    "gn:admin1_code":"52.0",
    "gn:asciiname":"Korucak",
    "gn:country_code":"TR",
    "gn:dem":241,
    "gn:feature_class":"P",
    "gn:feature_code":"PPL",
    "gn:name":"Korucak",
    "gn:population":0,
    "gn:timezone":"Europe/Istanbul",
    "iso:country":"TR",
    "name:und_x_variant":[
        "Kavras",
        "Kavraz",
        "Korucak"
    ],
    "wof:name":"Korucak",
    "wof:placetype":"locality"
},
  "geometry": {"coordinates":[37.5907,40.98721],"type":"Point"}
}