{
  "type": "Feature",
  "properties": {
    "gn:admin1_code":"24",
    "gn:asciiname":"Dogankoey",
    "gn:country_code":"TR",
    "gn:dem":1221,
    "gn:feature_class":"P",
    "gn:feature_code":"PPL",
    "gn:name":"Do\u011fank\u00f6y",
    "gn:population":0,
    "gn:timezone":"Europe/Istanbul",
    "iso:country":"TR",
    "name:tur_x_preferred":[
        "Do\u011fank\u00f6y"
    ],
    "name:und_x_variant":[
        "Do\u011fan"
    ],
    "wof:name":"Dogankoey",
    "wof:placetype":"locality"
},
  "geometry": {"coordinates":[38.6343,39.45319],"type":"Point"}
}