{
  "type": "Feature",
  "properties": {
    "gn:admin1_code":"26",
    "gn:asciiname":"Ballihisar",
    "gn:cc2":"TR",
    "gn:country_code":"TR",
    "gn:dem":942,
    "gn:feature_class":"P",
    "gn:feature_code":"PPL",
    "gn:name":"Ball\u0131hisar",
    "gn:population":0,
    "gn:timezone":"Europe/Istanbul",
    "iso:country":"TR",
    "name:und_x_variant":[
        "Pessinus",
        "Ball\u0131hisar"
    ],
    "wof:name":"Ballihisar",
    "wof:placetype":"locality"
},
  "geometry": {"coordinates":[31.58444,39.33389],"type":"Point"}
}