{
  "type": "Feature",
  "properties": {
    "gn:admin1_code":"14",
    "gn:asciiname":"Asagidedegan",
    "gn:country_code":"TR",
    "gn:dem":1387,
    "gn:feature_class":"P",
    "gn:feature_code":"PPL",
    "gn:name":"A\u015fa\u011f\u0131dede\u011fan",
    "gn:population":0,
    "gn:timezone":"Europe/Istanbul",
    "iso:country":"TR",
    "wof:name":"Asagidedegan",
    "wof:placetype":"locality"
},
  "geometry": {"coordinates":[31.11303,40.62214],"type":"Point"}
}