{
  "type": "Feature",
  "properties": {
    "gn:admin1_code":"04",
    "gn:asciiname":"Kilicgedigi",
    "gn:country_code":"TR",
    "gn:dem":1859,
    "gn:feature_class":"P",
    "gn:feature_code":"PPL",
    "gn:name":"K\u0131l\u0131\u00e7gedi\u011fi",
    "gn:population":0,
    "gn:timezone":"Europe/Istanbul",
    "iso:country":"TR",
    "name:und_x_variant":[
        "Hanik",
        "K\u0131l\u0131\u00e7gedi\u011fi"
    ],
    "wof:name":"Kilicgedigi",
    "wof:placetype":"locality"
},
  "geometry": {"coordinates":[42.7912,39.64784],"type":"Point"}
}