{
  "type": "Feature",
  "properties": {
    "gn:admin1_code":"48",
    "gn:asciiname":"Kizilyaka",
    "gn:country_code":"TR",
    "gn:dem":104,
    "gn:feature_class":"P",
    "gn:feature_code":"PPL",
    "gn:name":"K\u0131z\u0131lyaka",
    "gn:population":0,
    "gn:timezone":"Europe/Istanbul",
    "iso:country":"TR",
    "name:tur_x_preferred":[
        "K\u0131z\u0131lyaka"
    ],
    "name:tur_x_variant":[
        "K\u0131z\u0131lkaya"
    ],
    "wof:name":"Kizilyaka",
    "wof:placetype":"locality"
},
  "geometry": {"coordinates":[28.46073,37.01746],"type":"Point"}
}