{
  "type": "Feature",
  "properties": {
    "gn:admin1_code":"70",
    "gn:asciiname":"Magarabasi",
    "gn:country_code":"TR",
    "gn:dem":948,
    "gn:feature_class":"P",
    "gn:feature_code":"PPL",
    "gn:name":"Ma\u011faraba\u015f\u0131",
    "gn:population":0,
    "gn:timezone":"Europe/Istanbul",
    "iso:country":"TR",
    "wof:name":"Magarabasi",
    "wof:placetype":"locality"
},
  "geometry": {"coordinates":[43.55509,37.27895],"type":"Point"}
}