{
  "type": "Feature",
  "properties": {
    "gn:admin1_code":"21",
    "gn:asciiname":"Bayirbagi",
    "gn:country_code":"TR",
    "gn:dem":819,
    "gn:feature_class":"P",
    "gn:feature_code":"PPL",
    "gn:name":"Bay\u0131rba\u011f\u0131",
    "gn:population":0,
    "gn:timezone":"Europe/Istanbul",
    "iso:country":"TR",
    "name:tur_x_preferred":[
        "Bay\u0131rba\u011f\u0131"
    ],
    "wof:name":"Bayirbagi",
    "wof:placetype":"locality"
},
  "geometry": {"coordinates":[39.53324,38.0994],"type":"Point"}
}