{
  "type": "Feature",
  "properties": {
    "gn:admin1_code":"68",
    "gn:asciiname":"Yenimehmetli",
    "gn:country_code":"TR",
    "gn:dem":932,
    "gn:feature_class":"P",
    "gn:feature_code":"PPLA3",
    "gn:name":"Yenimehmetli",
    "gn:population":0,
    "gn:timezone":"Europe/Istanbul",
    "iso:country":"TR",
    "name:und_x_variant":[
        "Yenimehmet",
        "Yenimehmetli"
    ],
    "wof:name":"Yenimehmetli",
    "wof:placetype":"locality"
},
  "geometry": {"coordinates":[32.16889,39.42],"type":"Point"}
}