{
  "type": "Feature",
  "properties": {
    "gn:admin1_code":"63",
    "gn:asciiname":"Bilesor",
    "gn:country_code":"TR",
    "gn:dem":471,
    "gn:feature_class":"P",
    "gn:feature_code":"PPL",
    "gn:name":"Bilesor",
    "gn:population":0,
    "gn:timezone":"Europe/Istanbul",
    "iso:country":"TR",
    "name:und_x_variant":[
        "Bile\u015fur",
        "Bilesor"
    ],
    "wof:name":"Bilesor",
    "wof:placetype":"locality"
},
  "geometry": {"coordinates":[37.85375,37.2805],"type":"Point"}
}