{
  "type": "Feature",
  "properties": {
    "gn:admin1_code":"76.0",
    "gn:asciiname":"Guvercin",
    "gn:country_code":"TR",
    "gn:dem":735,
    "gn:feature_class":"P",
    "gn:feature_code":"PPL",
    "gn:name":"G\u00fcvercin",
    "gn:population":0,
    "gn:timezone":"Europe/Istanbul",
    "iso:country":"TR",
    "name:tur_x_preferred":[
        "G\u00fcvercin"
    ],
    "name:und_x_variant":[
        "Amso"
    ],
    "wof:name":"Guvercin",
    "wof:placetype":"locality"
},
  "geometry": {"coordinates":[41.17254000000001,37.93428],"type":"Point"}
}