{
  "type": "Feature",
  "properties": {
    "gn:admin1_code":"46",
    "gn:asciiname":"Kuyumcular",
    "gn:country_code":"TR",
    "gn:dem":500,
    "gn:feature_class":"P",
    "gn:feature_code":"PPL",
    "gn:name":"Kuyumcular",
    "gn:population":0,
    "gn:timezone":"Europe/Istanbul",
    "iso:country":"TR",
    "name:und_x_variant":[
        "Yaylakuyumcular"
    ],
    "wof:name":"Kuyumcular",
    "wof:placetype":"locality"
},
  "geometry": {"coordinates":[36.92995,37.42641],"type":"Point"}
}