{
  "type": "Feature",
  "properties": {
    "gn:admin1_code":"79.0",
    "gn:asciiname":"Biyikaydin",
    "gn:country_code":"TR",
    "gn:dem":1078,
    "gn:feature_class":"P",
    "gn:feature_code":"PPL",
    "gn:name":"B\u0131y\u0131kayd\u0131n",
    "gn:population":0,
    "gn:timezone":"Europe/Istanbul",
    "iso:country":"TR",
    "wof:name":"Biyikaydin",
    "wof:placetype":"locality"
},
  "geometry": {"coordinates":[33.76583,40.04667],"type":"Point"}
}