{
  "type": "Feature",
  "properties": {
    "gn:admin1_code":"63",
    "gn:asciiname":"Yaylak",
    "gn:country_code":"TR",
    "gn:dem":510,
    "gn:feature_class":"P",
    "gn:feature_code":"PPLA3",
    "gn:name":"Yaylak",
    "gn:population":0,
    "gn:timezone":"Europe/Istanbul",
    "iso:country":"TR",
    "name:azb_x_preferred":[
        "\u06cc\u0627\u06cc\u0644\u0627\u0642"
    ],
    "name:aze_x_preferred":[
        "Yaylaq"
    ],
    "name:fas_x_preferred":[
        "\u06cc\u06cc\u0644\u0627\u0642"
    ],
    "name:kir_x_preferred":[
        "\u0416\u0430\u0439\u043b\u043e\u043e"
    ],
    "name:por_x_preferred":[
        "Jailoo"
    ],
    "name:rus_x_preferred":[
        "\u0414\u0436\u0430\u0439\u043b\u044f\u0443"
    ],
    "name:spa_x_preferred":[
        "Yailak"
    ],
    "name:tat_x_preferred":[
        "\u0496\u04d9\u0439\u043b\u04d9\u04af"
    ],
    "name:tgk_x_preferred":[
        "\u0410\u0439\u043b\u043e\u049b"
    ],
    "name:tur_x_preferred":[
        "Yaylak"
    ],
    "name:ukr_x_preferred":[
        "\u0414\u0436\u0430\u0439\u043b\u044f\u0443"
    ],
    "name:und_x_variant":[
        "Hevenk",
        "Baziki"
    ],
    "name:uzb_x_preferred":[
        "Yaylov"
    ],
    "wof:name":"Yaylak",
    "wof:placetype":"locality"
},
  "geometry": {"coordinates":[38.33892,37.38268],"type":"Point"}
}