{
  "type": "Feature",
  "properties": {
    "gn:admin1_code":"63",
    "gn:asciiname":"Yaylak",
    "gn:country_code":"TR",
    "gn:dem":510,
    "gn:feature_class":"P",
    "gn:feature_code":"PPLA3",
    "gn:name":"Yaylak",
    "gn:population":0,
    "gn:timezone":"Europe/Istanbul",
    "iso:country":"TR",
    "name:und_x_variant":[
        "Hevenk",
        "Baziki",
        "Yaylak"
    ],
    "wof:name":"Yaylak",
    "wof:placetype":"locality"
},
  "geometry": {"coordinates":[38.33892,37.38268],"type":"Point"}
}