{
  "type": "Feature",
  "properties": {
    "gn:admin1_code":"35.0",
    "gn:asciiname":"Karaorman",
    "gn:country_code":"TR",
    "gn:dem":390,
    "gn:feature_class":"P",
    "gn:feature_code":"PPL",
    "gn:name":"Karaorman",
    "gn:population":0,
    "gn:timezone":"Europe/Istanbul",
    "iso:country":"TR",
    "wof:name":"Karaorman",
    "wof:placetype":"locality"
},
  "geometry": {"coordinates":[27.23155,38.60755],"type":"Point"}
}