{
  "type": "Feature",
  "properties": {
    "gn:admin1_code":"62",
    "gn:asciiname":"Derviscemal",
    "gn:country_code":"TR",
    "gn:dem":1766,
    "gn:feature_class":"P",
    "gn:feature_code":"PPL",
    "gn:name":"Dervi\u015fcemal",
    "gn:population":0,
    "gn:timezone":"Europe/Istanbul",
    "iso:country":"TR",
    "name:tur_x_preferred":[
        "Dervi\u015fcemal"
    ],
    "wof:name":"Derviscemal",
    "wof:placetype":"locality"
},
  "geometry": {"coordinates":[39.2826,39.10027],"type":"Point"}
}