{
  "type": "Feature",
  "properties": {
    "gn:admin1_code":"11.0",
    "gn:asciiname":"Bayat",
    "gn:country_code":"TR",
    "gn:dem":591,
    "gn:feature_class":"P",
    "gn:feature_code":"PPL",
    "gn:name":"Bayat",
    "gn:population":0,
    "gn:timezone":"Europe/Istanbul",
    "iso:country":"TR",
    "name:und_x_variant":[
        "Bayatk\u00f6y"
    ],
    "wof:name":"Bayat",
    "wof:placetype":"locality"
},
  "geometry": {"coordinates":[30.26565,40.18844],"type":"Point"}
}