{
  "type": "Feature",
  "properties": {
    "gn:admin1_code":"11.0",
    "gn:asciiname":"Bayat",
    "gn:country_code":"TR",
    "gn:dem":591,
    "gn:feature_class":"P",
    "gn:feature_code":"PPL",
    "gn:name":"Bayat",
    "gn:population":0,
    "gn:timezone":"Europe/Istanbul",
    "iso:country":"TR",
    "name:ara_x_preferred":[
        "\u0628\u064a\u0627\u062a"
    ],
    "name:aze_x_preferred":[
        "Bayat"
    ],
    "name:deu_x_preferred":[
        "Bayat"
    ],
    "name:eus_x_preferred":[
        "Bayat"
    ],
    "name:fas_x_preferred":[
        "\u0628\u06cc\u0627\u062a"
    ],
    "name:fra_x_preferred":[
        "Bayat"
    ],
    "name:ita_x_preferred":[
        "Bayat"
    ],
    "name:nld_x_preferred":[
        "Bayat"
    ],
    "name:rus_x_preferred":[
        "\u0411\u0430\u044f\u0442\u044b"
    ],
    "name:tur_x_preferred":[
        "Bayat"
    ],
    "name:und_x_variant":[
        "Bayatk\u00f6y"
    ],
    "name:vie_x_preferred":[
        "Bayat"
    ],
    "wof:name":"Bayat",
    "wof:placetype":"locality"
},
  "geometry": {"coordinates":[30.26565,40.18844],"type":"Point"}
}