{
  "type": "Feature",
  "properties": {
    "gn:admin1_code":"13.0",
    "gn:asciiname":"Cavuslar",
    "gn:country_code":"TR",
    "gn:dem":1903,
    "gn:feature_class":"P",
    "gn:feature_code":"PPL",
    "gn:name":"\u00c7avu\u015flar",
    "gn:population":0,
    "gn:timezone":"Europe/Istanbul",
    "iso:country":"TR",
    "name:tur_x_preferred":[
        "\u00c7avu\u015flar"
    ],
    "wof:name":"Cavuslar",
    "wof:placetype":"locality"
},
  "geometry": {"coordinates":[42.53321,38.41427],"type":"Point"}
}