{
  "type": "Feature",
  "properties": {
    "gn:country":"TR",
    "gn:fcode":"PPL",
    "gn:population":811,
    "iso:country":"TR",
    "name:tur_x_preferred":[
        "G\u00f6k\u00e7ep\u0131nar"
    ],
    "name:und_x_variant":[
        "\u00c7ukuryurt"
    ],
    "qs:name":"G\u00f6k\u00e7ep\u0131nar",
    "qs:photos_9r":0,
    "qs:photos_sr":0,
    "qs:pop_sr":"2",
    "wof:name":"G\u00f6k\u00e7ep\u0131nar",
    "wof:placetype":"locality",
    "wof:population":811
},
  "geometry": {"coordinates":[41.51972,37.58972],"type":"Point"}
}