{
  "type": "Feature",
  "properties": {
    "gn:admin1_code":"68",
    "gn:asciiname":"Hacimuratli",
    "gn:country_code":"TR",
    "gn:dem":1068,
    "gn:feature_class":"P",
    "gn:feature_code":"PPL",
    "gn:name":"Hac\u0131muratl\u0131",
    "gn:population":0,
    "gn:timezone":"Europe/Istanbul",
    "iso:country":"TR",
    "wof:name":"Hacimuratli",
    "wof:placetype":"locality"
},
  "geometry": {"coordinates":[32.69888,39.68221],"type":"Point"}
}