{
  "type": "Feature",
  "properties": {
    "gn:admin1_code":"31",
    "gn:asciiname":"Sev",
    "gn:country_code":"TR",
    "gn:dem":493,
    "gn:feature_class":"P",
    "gn:feature_code":"PPL",
    "gn:name":"Sev",
    "gn:population":0,
    "gn:timezone":"Europe/Istanbul",
    "iso:country":"TR",
    "wof:name":"Sev",
    "wof:placetype":"locality"
},
  "geometry": {"coordinates":[36.18333,36.11667],"type":"Point"}
}