{
  "type": "Feature",
  "properties": {
    "gn:admin1_code":"61.0",
    "gn:asciiname":"Fidanbasi",
    "gn:country_code":"TR",
    "gn:dem":704,
    "gn:feature_class":"P",
    "gn:feature_code":"PPL",
    "gn:name":"Fidanba\u015f\u0131",
    "gn:population":0,
    "gn:timezone":"Europe/Istanbul",
    "iso:country":"TR",
    "name:tur_x_preferred":[
        "Fidanba\u015f\u0131"
    ],
    "wof:name":"Fidanbasi",
    "wof:placetype":"locality"
},
  "geometry": {"coordinates":[39.1549,40.93075],"type":"Point"}
}