{
  "type": "Feature",
  "properties": {
    "gn:admin1_code":"03",
    "gn:asciiname":"Sevikli",
    "gn:country_code":"TR",
    "gn:dem":1185,
    "gn:feature_class":"P",
    "gn:feature_code":"PPL",
    "gn:name":"\u015eevikli",
    "gn:population":0,
    "gn:timezone":"Europe/Istanbul",
    "iso:country":"TR",
    "wof:name":"Sevikli",
    "wof:placetype":"locality"
},
  "geometry": {"coordinates":[30.91667,38.43333],"type":"Point"}
}