{
  "type": "Feature",
  "properties": {
    "gn:admin1_code":"73",
    "gn:asciiname":"Duvarli",
    "gn:country_code":"TR",
    "gn:dem":1548,
    "gn:feature_class":"P",
    "gn:feature_code":"PPL",
    "gn:name":"Duvarl\u0131",
    "gn:population":0,
    "gn:timezone":"Europe/Istanbul",
    "iso:country":"TR",
    "name:und_x_variant":[
        "Duvarl\u0131",
        "Divarl\u0131"
    ],
    "wof:name":"Duvarli",
    "wof:placetype":"locality"
},
  "geometry": {"coordinates":[34.46345,38.20767],"type":"Point"}
}