{
  "type": "Feature",
  "properties": {
    "gn:admin1_code":"46",
    "gn:asciiname":"Catova",
    "gn:country_code":"TR",
    "gn:dem":1150,
    "gn:feature_class":"P",
    "gn:feature_code":"PPL",
    "gn:name":"\u00c7atova",
    "gn:population":0,
    "gn:timezone":"Europe/Istanbul",
    "iso:country":"TR",
    "name:und_x_variant":[
        "Maraba",
        "\u00c7atova"
    ],
    "wof:name":"Catova",
    "wof:placetype":"locality"
},
  "geometry": {"coordinates":[37.20345,38.26443],"type":"Point"}
}