{
  "type": "Feature",
  "properties": {
    "gn:admin1_code":"04",
    "gn:asciiname":"Taskin",
    "gn:country_code":"TR",
    "gn:dem":1854,
    "gn:feature_class":"P",
    "gn:feature_code":"PPL",
    "gn:name":"Ta\u015fk\u0131n",
    "gn:population":0,
    "gn:timezone":"Europe/Istanbul",
    "iso:country":"TR",
    "name:tur_x_preferred":[
        "Ta\u015fk\u0131n"
    ],
    "wof:name":"Taskin",
    "wof:placetype":"locality"
},
  "geometry": {"coordinates":[42.83857,39.0447],"type":"Point"}
}