{
  "type": "Feature",
  "properties": {
    "gn:admin1_code":"46",
    "gn:asciiname":"Kaynar",
    "gn:country_code":"TR",
    "gn:dem":1148,
    "gn:feature_class":"P",
    "gn:feature_code":"PPL",
    "gn:name":"Kaynar",
    "gn:population":0,
    "gn:timezone":"Europe/Istanbul",
    "iso:country":"TR",
    "name:tur_x_preferred":[
        "Kaynar"
    ],
    "wof:name":"Kaynar",
    "wof:placetype":"locality"
},
  "geometry": {"coordinates":[36.55405,37.79626],"type":"Point"}
}