{
  "type": "Feature",
  "properties": {
    "gn:admin1_code":"13",
    "gn:asciiname":"Kumbet",
    "gn:country_code":"TR",
    "gn:dem":1715,
    "gn:feature_class":"P",
    "gn:feature_code":"PPL",
    "gn:name":"K\u00fcmbet",
    "gn:population":0,
    "gn:timezone":"Europe/Istanbul",
    "iso:country":"TR",
    "wof:name":"Kumbet",
    "wof:placetype":"locality"
},
  "geometry": {"coordinates":[43.01667,38.93333],"type":"Point"}
}