{
  "type": "Feature",
  "properties": {
    "gn:admin1_code":"16",
    "gn:asciiname":"Suleymaniye",
    "gn:country_code":"TR",
    "gn:dem":438,
    "gn:feature_class":"P",
    "gn:feature_code":"PPL",
    "gn:name":"S\u00fcleymaniye",
    "gn:population":0,
    "gn:timezone":"Europe/Istanbul",
    "iso:country":"TR",
    "name:tur_x_preferred":[
        "S\u00fcleymaniye"
    ],
    "wof:name":"Suleymaniye",
    "wof:placetype":"locality"
},
  "geometry": {"coordinates":[29.67979,40.56877],"type":"Point"}
}