{
  "type": "Feature",
  "properties": {
    "gn:admin1_code":"32",
    "gn:asciiname":"Igdir",
    "gn:country_code":"TR",
    "gn:dem":184,
    "gn:feature_class":"P",
    "gn:feature_code":"PPL",
    "gn:name":"\u0130\u011fdir",
    "gn:population":0,
    "gn:timezone":"Europe/Istanbul",
    "iso:country":"TR",
    "name:und_x_variant":[
        "\u0130\u011fdir"
    ],
    "wof:name":"Igdir",
    "wof:placetype":"locality"
},
  "geometry": {"coordinates":[34.6432,36.9067],"type":"Point"}
}