{
  "type": "Feature",
  "properties": {
    "gn:admin1_code":"39.0",
    "gn:asciiname":"Cesmekolu",
    "gn:country_code":"TR",
    "gn:dem":111,
    "gn:feature_class":"P",
    "gn:feature_code":"PPL",
    "gn:name":"\u00c7e\u015fmekolu",
    "gn:population":0,
    "gn:timezone":"Europe/Istanbul",
    "iso:country":"TR",
    "wof:name":"Cesmekolu",
    "wof:placetype":"locality"
},
  "geometry": {"coordinates":[27.27944,41.53111],"type":"Point"}
}