{
  "type": "Feature",
  "properties": {
    "gn:admin1_code":"37.0",
    "gn:asciiname":"Belen",
    "gn:country_code":"TR",
    "gn:dem":155,
    "gn:feature_class":"P",
    "gn:feature_code":"PPL",
    "gn:name":"Belen",
    "gn:population":0,
    "gn:timezone":"Europe/Istanbul",
    "iso:country":"TR",
    "wof:name":"Belen",
    "wof:placetype":"locality"
},
  "geometry": {"coordinates":[33.5985,41.98132],"type":"Point"}
}