{
  "type": "Feature",
  "properties": {
    "gn:admin1_code":"21",
    "gn:asciiname":"Buyukkadi",
    "gn:country_code":"TR",
    "gn:dem":762,
    "gn:feature_class":"P",
    "gn:feature_code":"PPL",
    "gn:name":"B\u00fcy\u00fckkad\u0131",
    "gn:population":0,
    "gn:timezone":"Europe/Istanbul",
    "iso:country":"TR",
    "name:tur_x_preferred":[
        "B\u00fcy\u00fckkad\u0131"
    ],
    "name:und_x_variant":[
        "B\u00fcy\u00fck Kad\u0131k\u00f6y",
        "B\u00fcy\u00fck Kad\u0131k\u00f6y\u00fc",
        "Kad\u0131"
    ],
    "wof:name":"Buyukkadi",
    "wof:placetype":"locality"
},
  "geometry": {"coordinates":[40.29773,38.01069],"type":"Point"}
}