{
  "type": "Feature",
  "properties": {
    "gn:admin1_code":"13",
    "gn:asciiname":"Suzan",
    "gn:country_code":"TR",
    "gn:dem":1436,
    "gn:feature_class":"P",
    "gn:feature_code":"PPL",
    "gn:name":"Suzan",
    "gn:population":0,
    "gn:timezone":"Europe/Istanbul",
    "iso:country":"TR",
    "name:tur_x_preferred":[
        "D\u00f6k\u00fcta\u015f"
    ],
    "name:tur_x_variant":[
        "D\u00f6k\u00fckta\u015f"
    ],
    "name:und_x_variant":[
        "Obin"
    ],
    "wof:name":"Suzan",
    "wof:placetype":"locality"
},
  "geometry": {"coordinates":[42.63314,37.99739],"type":"Point"}
}