{
  "type": "Feature",
  "properties": {
    "gn:admin1_code":"16",
    "gn:asciiname":"Nalbant",
    "gn:country_code":"TR",
    "gn:dem":863,
    "gn:feature_class":"P",
    "gn:feature_code":"PPL",
    "gn:name":"Nalbant",
    "gn:population":0,
    "gn:timezone":"Europe/Istanbul",
    "iso:country":"TR",
    "name:ceb_x_preferred":[
        "Comuna Nalbant"
    ],
    "name:ita_x_preferred":[
        "Nalbant"
    ],
    "name:msa_x_preferred":[
        "Nalbant"
    ],
    "name:nld_x_preferred":[
        "Nalbant"
    ],
    "name:por_x_preferred":[
        "Nalbant"
    ],
    "name:ron_x_preferred":[
        "Comuna Nalbant"
    ],
    "name:srp_x_preferred":[
        "\u041e\u043f\u0448\u0442\u0438\u043d\u0430 \u041d\u0430\u043b\u0431\u0430\u043d\u0442"
    ],
    "name:tur_x_preferred":[
        "Nalbant"
    ],
    "name:ukr_x_preferred":[
        "\u041d\u0430\u043b\u0431\u0430\u043d\u0442"
    ],
    "name:vie_x_preferred":[
        "Nalbant"
    ],
    "name:zho_x_preferred":[
        "\u7d0d\u723e\u73ed\u7279\u9109"
    ],
    "wof:name":"Nalbant",
    "wof:placetype":"locality"
},
  "geometry": {"coordinates":[29.2119,39.71372],"type":"Point"}
}