{
  "type": "Feature",
  "properties": {
    "gn:admin1_code":"16",
    "gn:asciiname":"Nalbant",
    "gn:country_code":"TR",
    "gn:dem":863,
    "gn:feature_class":"P",
    "gn:feature_code":"PPL",
    "gn:name":"Nalbant",
    "gn:population":0,
    "gn:timezone":"Europe/Istanbul",
    "iso:country":"TR",
    "name:tur_x_preferred":[
        "Nalbant"
    ],
    "wof:name":"Nalbant",
    "wof:placetype":"locality"
},
  "geometry": {"coordinates":[29.2119,39.71372],"type":"Point"}
}