{
  "type": "Feature",
  "properties": {
    "gn:admin1_code":"87",
    "gn:asciiname":"Kelesoglu",
    "gn:country_code":"TR",
    "gn:dem":519,
    "gn:feature_class":"P",
    "gn:feature_code":"PPL",
    "gn:name":"Keleso\u011flu",
    "gn:population":0,
    "gn:timezone":"Europe/Istanbul",
    "iso:country":"TR",
    "wof:name":"Kelesoglu",
    "wof:placetype":"locality"
},
  "geometry": {"coordinates":[32.38445,41.35149000000001],"type":"Point"}
}