{
  "type": "Feature",
  "properties": {
    "gn:admin1_code":"63",
    "gn:asciiname":"Golgen",
    "gn:country_code":"TR",
    "gn:dem":811,
    "gn:feature_class":"P",
    "gn:feature_code":"PPL",
    "gn:name":"G\u00f6lgen",
    "gn:population":0,
    "gn:timezone":"Europe/Istanbul",
    "iso:country":"TR",
    "name:und_x_variant":[
        "G\u00fcll\u00fc",
        "G\u00f6ll\u00fc",
        "G\u00f6lgen"
    ],
    "wof:name":"Golgen",
    "wof:placetype":"locality"
},
  "geometry": {"coordinates":[38.90788,37.43578],"type":"Point"}
}