{
  "type": "Feature",
  "properties": {
    "gn:admin1_code":"55.0",
    "gn:asciiname":"Cuce",
    "gn:country_code":"TR",
    "gn:dem":988,
    "gn:feature_class":"P",
    "gn:feature_code":"PPL",
    "gn:name":"C\u00fcce",
    "gn:population":0,
    "gn:timezone":"Europe/Istanbul",
    "iso:country":"TR",
    "name:hrv_x_preferred":[
        "Cuce"
    ],
    "name:srp_x_preferred":[
        "\u0426\u0443\u0446\u0435"
    ],
    "wof:name":"Cuce",
    "wof:placetype":"locality"
},
  "geometry": {"coordinates":[36.0401,40.88381],"type":"Point"}
}