{
  "type": "Feature",
  "properties": {
    "gn:admin1_code":"31",
    "gn:asciiname":"Saylak",
    "gn:cc2":"TR",
    "gn:country_code":"TR",
    "gn:dem":936,
    "gn:feature_class":"P",
    "gn:feature_code":"PPL",
    "gn:name":"Saylak",
    "gn:population":0,
    "gn:timezone":"Europe/Istanbul",
    "iso:country":"TR",
    "name:und_x_variant":[
        "Seyl\u00e2k",
        "Saylak"
    ],
    "wof:name":"Saylak",
    "wof:placetype":"locality"
},
  "geometry": {"coordinates":[36.38333,36.65],"type":"Point"}
}