{
  "type": "Feature",
  "properties": {
    "gn:admin1_code":"25",
    "gn:asciiname":"Yalindali",
    "gn:country_code":"TR",
    "gn:dem":2072,
    "gn:feature_class":"P",
    "gn:feature_code":"PPL",
    "gn:name":"Yal\u0131ndal\u0131",
    "gn:population":0,
    "gn:timezone":"Europe/Istanbul",
    "iso:country":"TR",
    "name:tur_x_preferred":[
        "Yal\u0131ndal\u0131"
    ],
    "name:und_x_variant":[
        "Yal\u0131ndal",
        "Valekor"
    ],
    "wof:name":"Yalindali",
    "wof:placetype":"locality"
},
  "geometry": {"coordinates":[42.31955,39.54078],"type":"Point"}
}