{
  "type": "Feature",
  "properties": {
    "gn:country":"TR",
    "gn:fcode":"PPL",
    "gn:pop":603,
    "iso:country":"TR",
    "name:unk_x_variant":[
        "Hista"
    ],
    "qs:name":"Ko\u00e7tepe",
    "qs:photos_9r":0,
    "qs:photos_sr":0,
    "qs:pop_sr":"2",
    "wof:name":"Ko\u00e7tepe",
    "wof:placetype":"locality",
    "wof:population":603
},
  "geometry": {"coordinates":[41.86472,37.54278],"type":"Point"}
}