{
  "type": "Feature",
  "properties": {
    "gn:admin1_code":"79",
    "gn:asciiname":"Kilevli",
    "gn:country_code":"TR",
    "gn:dem":1117,
    "gn:feature_class":"P",
    "gn:feature_code":"PPL",
    "gn:name":"K\u0131levli",
    "gn:population":0,
    "gn:timezone":"Europe/Istanbul",
    "iso:country":"TR",
    "wof:name":"Kilevli",
    "wof:placetype":"locality"
},
  "geometry": {"coordinates":[33.76467,39.85801],"type":"Point"}
}