{
  "type": "Feature",
  "properties": {
    "gn:admin1_code":"32",
    "gn:asciiname":"Koruklu",
    "gn:country_code":"TR",
    "gn:dem":1138,
    "gn:feature_class":"P",
    "gn:feature_code":"PPL",
    "gn:name":"Koruklu",
    "gn:population":0,
    "gn:timezone":"Europe/Istanbul",
    "iso:country":"TR",
    "name:tur_x_preferred":[
        "Koruklu"
    ],
    "wof:name":"Koruklu",
    "wof:placetype":"locality"
},
  "geometry": {"coordinates":[33.88333,36.53333],"type":"Point"}
}