{
  "type": "Feature",
  "properties": {
    "gn:admin1_code":"66",
    "gn:asciiname":"Omerli",
    "gn:country_code":"TR",
    "gn:dem":1079,
    "gn:feature_class":"P",
    "gn:feature_code":"PPL",
    "gn:name":"\u00d6merli",
    "gn:population":0,
    "gn:timezone":"Europe/Istanbul",
    "iso:country":"TR",
    "wof:name":"Omerli",
    "wof:placetype":"locality"
},
  "geometry": {"coordinates":[35.11923,39.4792],"type":"Point"}
}