{
  "type": "Feature",
  "properties": {
    "gn:admin1_code":"68.0",
    "gn:asciiname":"Doymusoren",
    "gn:country_code":"TR",
    "gn:dem":1134,
    "gn:feature_class":"P",
    "gn:feature_code":"PPL",
    "gn:name":"Doymu\u015f\u00f6ren",
    "gn:population":0,
    "gn:timezone":"Europe/Istanbul",
    "iso:country":"TR",
    "name:und_x_variant":[
        "Doymu\u015fviran",
        "Doymu\u015f\u00f6ren"
    ],
    "wof:name":"Doymusoren",
    "wof:placetype":"locality"
},
  "geometry": {"coordinates":[32.55675,40.38092],"type":"Point"}
}