{
  "type": "Feature",
  "properties": {
    "gn:admin1_code":"80.0",
    "gn:asciiname":"Sevartepe",
    "gn:country_code":"TR",
    "gn:dem":875,
    "gn:feature_class":"P",
    "gn:feature_code":"PPL",
    "gn:name":"Sevartepe",
    "gn:population":0,
    "gn:timezone":"Europe/Istanbul",
    "iso:country":"TR",
    "name:tur_x_preferred":[
        "Sevartepe"
    ],
    "wof:name":"Sevartepe",
    "wof:placetype":"locality"
},
  "geometry": {"coordinates":[42.74512,37.38217],"type":"Point"}
}