{
  "type": "Feature",
  "properties": {
    "gn:admin1_code":"43",
    "gn:asciiname":"Inli",
    "gn:country_code":"TR",
    "gn:dem":1088,
    "gn:feature_class":"P",
    "gn:feature_code":"PPL",
    "gn:name":"\u0130nli",
    "gn:population":0,
    "gn:timezone":"Europe/Istanbul",
    "iso:country":"TR",
    "wof:name":"Inli",
    "wof:placetype":"locality"
},
  "geometry": {"coordinates":[30.21639,39.47639],"type":"Point"}
}