{
  "type": "Feature",
  "properties": {
    "gn:admin1_code":"66",
    "gn:asciiname":"Igdeli",
    "gn:country_code":"TR",
    "gn:dem":1277,
    "gn:feature_class":"P",
    "gn:feature_code":"PPL",
    "gn:name":"\u0130\u011fdeli",
    "gn:population":0,
    "gn:timezone":"Europe/Istanbul",
    "iso:country":"TR",
    "wof:name":"Igdeli",
    "wof:placetype":"locality"
},
  "geometry": {"coordinates":[35.47723,39.30316],"type":"Point"}
}