{
  "type": "Feature",
  "properties": {
    "gn:admin1_code":"04",
    "gn:asciiname":"Bozoglak",
    "gn:country_code":"TR",
    "gn:dem":1842,
    "gn:feature_class":"P",
    "gn:feature_code":"PPL",
    "gn:name":"Bozo\u011flak",
    "gn:population":0,
    "gn:timezone":"Europe/Istanbul",
    "iso:country":"TR",
    "name:und_x_variant":[
        "Nenecani",
        "Bozo\u011flak"
    ],
    "wof:name":"Bozoglak",
    "wof:placetype":"locality"
},
  "geometry": {"coordinates":[42.98003,39.2409],"type":"Point"}
}