{
  "type": "Feature",
  "properties": {
    "gn:admin1_code":"74.0",
    "gn:asciiname":"Batgel",
    "gn:cc2":"TR",
    "gn:country_code":"TR",
    "gn:dem":530,
    "gn:feature_class":"P",
    "gn:feature_code":"PPL",
    "gn:name":"Batgel",
    "gn:population":0,
    "gn:timezone":"Europe/Istanbul",
    "iso:country":"TR",
    "name:rus_x_preferred":[
        "Batgel\u2019"
    ],
    "name:und_x_variant":[
        "Batlelu",
        "Batgel"
    ],
    "wof:name":"Batgel",
    "wof:placetype":"locality"
},
  "geometry": {"coordinates":[41.85389,37.94944],"type":"Point"}
}