{
  "type": "Feature",
  "properties": {
    "gn:admin1_code":"65.0",
    "gn:asciiname":"Meral",
    "gn:country_code":"TR",
    "gn:dem":2226,
    "gn:feature_class":"P",
    "gn:feature_code":"PPL",
    "gn:name":"Meral",
    "gn:population":0,
    "gn:timezone":"Europe/Istanbul",
    "iso:country":"TR",
    "name:tur_x_preferred":[
        "Meral"
    ],
    "wof:name":"Meral",
    "wof:placetype":"locality"
},
  "geometry": {"coordinates":[43.05824000000001,39.06087],"type":"Point"}
}