{
  "type": "Feature",
  "properties": {
    "gn:admin1_code":"13.0",
    "gn:asciiname":"Elmacik",
    "gn:country_code":"TR",
    "gn:dem":2130,
    "gn:feature_class":"P",
    "gn:feature_code":"PPL",
    "gn:name":"Elmac\u0131k",
    "gn:population":0,
    "gn:timezone":"Europe/Istanbul",
    "iso:country":"TR",
    "name:tur_x_preferred":[
        "Elmal\u0131"
    ],
    "name:tur_x_variant":[
        "Elmac\u0131k"
    ],
    "wof:name":"Elmacik",
    "wof:placetype":"locality"
},
  "geometry": {"coordinates":[42.60918,38.15645],"type":"Point"}
}