{
  "type": "Feature",
  "properties": {
    "gn:admin1_code":"13.0",
    "gn:asciiname":"Koyunlu",
    "gn:country_code":"TR",
    "gn:dem":2139,
    "gn:feature_class":"P",
    "gn:feature_code":"PPL",
    "gn:name":"Koyunlu",
    "gn:population":0,
    "gn:timezone":"Europe/Istanbul",
    "iso:country":"TR",
    "name:tur_x_preferred":[
        "Koyunlu"
    ],
    "wof:name":"Koyunlu",
    "wof:placetype":"locality"
},
  "geometry": {"coordinates":[42.66752,38.16439],"type":"Point"}
}