{
  "type": "Feature",
  "properties": {
    "gn:admin1_code":"28",
    "gn:asciiname":"Esenyurt",
    "gn:country_code":"TR",
    "gn:dem":315,
    "gn:feature_class":"P",
    "gn:feature_code":"PPL",
    "gn:name":"Esenyurt",
    "gn:population":0,
    "gn:timezone":"Europe/Istanbul",
    "iso:country":"TR",
    "name:tur_x_preferred":[
        "Esenyurt"
    ],
    "wof:name":"Esenyurt",
    "wof:placetype":"locality"
},
  "geometry": {"coordinates":[38.99269,40.93488],"type":"Point"}
}