{
  "type": "Feature",
  "properties": {
    "gn:admin1_code":"35",
    "gn:asciiname":"Birgi",
    "gn:country_code":"TR",
    "gn:dem":148,
    "gn:feature_class":"P",
    "gn:feature_code":"PPL",
    "gn:name":"Birgi",
    "gn:population":0,
    "gn:timezone":"Europe/Istanbul",
    "iso:country":"TR",
    "name:tur_x_preferred":[
        "Birgi"
    ],
    "wof:name":"Birgi",
    "wof:placetype":"locality"
},
  "geometry": {"coordinates":[26.55384,38.30201],"type":"Point"}
}