{
  "type": "Feature",
  "properties": {
    "gn:admin1_code":"89.0",
    "gn:asciiname":"Kulat",
    "gn:country_code":"TR",
    "gn:dem":1281,
    "gn:feature_class":"P",
    "gn:feature_code":"PPL",
    "gn:name":"Kulat",
    "gn:population":0,
    "gn:timezone":"Europe/Istanbul",
    "iso:country":"TR",
    "wof:name":"Kulat",
    "wof:placetype":"locality"
},
  "geometry": {"coordinates":[32.54212,41.03376],"type":"Point"}
}