{
  "type": "Feature",
  "properties": {
    "gn:admin1_code":"31",
    "gn:asciiname":"Haciahmetli",
    "gn:country_code":"TR",
    "gn:dem":81,
    "gn:feature_class":"P",
    "gn:feature_code":"PPL",
    "gn:name":"Hac\u0131ahmetli",
    "gn:population":0,
    "gn:timezone":"Europe/Istanbul",
    "iso:country":"TR",
    "name:tur_x_preferred":[
        "Hac\u0131ahmetli"
    ],
    "wof:name":"Haciahmetli",
    "wof:placetype":"locality"
},
  "geometry": {"coordinates":[35.93133,36.37967],"type":"Point"}
}