{
  "type": "Feature",
  "properties": {
    "gn:admin1_code":"81",
    "gn:asciiname":"Agilbogazi",
    "gn:country_code":"TR",
    "gn:dem":372,
    "gn:feature_class":"P",
    "gn:feature_code":"PPL",
    "gn:name":"A\u011f\u0131lbo\u011faz\u0131",
    "gn:population":0,
    "gn:timezone":"Europe/Istanbul",
    "iso:country":"TR",
    "name:deu_x_preferred":[
        "Hac\u0131mirzal\u0131"
    ],
    "name:msa_x_preferred":[
        "Hac\u0131mirzal\u0131"
    ],
    "name:tur_x_preferred":[
        "Hac\u0131mirzal\u0131"
    ],
    "name:und_x_variant":[
        "A\u011f\u0131lbo\u011faz\u0131",
        "Hac\u0131mirzal\u0131"
    ],
    "name:vie_x_preferred":[
        "Hac\u0131mirzal\u0131"
    ],
    "wof:name":"Agilbogazi",
    "wof:placetype":"locality"
},
  "geometry": {"coordinates":[35.82508,37.48287],"type":"Point"}
}