{
  "type": "Feature",
  "properties": {
    "gn:admin1_code":"07",
    "gn:asciiname":"Uzunlar",
    "gn:country_code":"TR",
    "gn:dem":122,
    "gn:feature_class":"P",
    "gn:feature_code":"PPL",
    "gn:name":"Uzunlar",
    "gn:population":0,
    "gn:timezone":"Europe/Istanbul",
    "iso:country":"TR",
    "wof:name":"Uzunlar",
    "wof:placetype":"locality"
},
  "geometry": {"coordinates":[31.64358,36.7271],"type":"Point"}
}