{
  "type": "Feature",
  "properties": {
    "gn:admin1_code":"54.0",
    "gn:asciiname":"Ahmediye",
    "gn:country_code":"TR",
    "gn:dem":47,
    "gn:feature_class":"P",
    "gn:feature_code":"PPL",
    "gn:name":"Ahmediye",
    "gn:population":0,
    "gn:timezone":"Europe/Istanbul",
    "iso:country":"TR",
    "name:tur_x_preferred":[
        "Ahmediye"
    ],
    "wof:name":"Ahmediye",
    "wof:placetype":"locality"
},
  "geometry": {"coordinates":[30.35668,40.67311],"type":"Point"}
}