{
  "type": "Feature",
  "properties": {
    "gn:admin1_code":"10",
    "gn:asciiname":"Yaylabasi",
    "gn:cc2":"TR",
    "gn:country_code":"TR",
    "gn:dem":557,
    "gn:feature_class":"P",
    "gn:feature_code":"PPL",
    "gn:name":"Yaylaba\u015f\u0131",
    "gn:population":0,
    "gn:timezone":"Europe/Istanbul",
    "iso:country":"TR",
    "name:und_x_variant":[
        "Yaylaba\u015f\u0131 K\u00f6y\u00fc",
        "Yaylaba\u015f\u0131"
    ],
    "wof:name":"Yaylabasi",
    "wof:placetype":"locality"
},
  "geometry": {"coordinates":[28.45389,39.78167],"type":"Point"}
}