{
  "type": "Feature",
  "properties": {
    "gn:admin1_code":"91.0",
    "gn:asciiname":"Karagedik",
    "gn:country_code":"TR",
    "gn:dem":115,
    "gn:feature_class":"P",
    "gn:feature_code":"PPL",
    "gn:name":"Karagedik",
    "gn:population":0,
    "gn:timezone":"Europe/Istanbul",
    "iso:country":"TR",
    "wof:name":"Karagedik",
    "wof:placetype":"locality"
},
  "geometry": {"coordinates":[36.27387,37.23008],"type":"Point"}
}