{
  "type": "Feature",
  "properties": {
    "iso:country":"TR",
    "name:eng_x_preferred":[
        "Orhangazi"
    ],
    "name:tur_x_preferred":[
        "Orhangazi"
    ],
    "wof:name":"Orhangazi",
    "wof:placetype":"neighbourhood"
},
  "geometry": {"coordinates":[29.28811344366393,40.94483386914384],"type":"Point"}
}