{
  "type": "Feature",
  "properties": {
    "gn:admin1_code":"8.0",
    "gn:asciiname":"Kalburlu",
    "gn:country_code":"TR",
    "gn:dem":328,
    "gn:feature_class":"P",
    "gn:feature_code":"PPL",
    "gn:name":"Kalburlu",
    "gn:population":0,
    "gn:timezone":"Europe/Istanbul",
    "iso:country":"TR",
    "name:msa_x_preferred":[
        "Kalburlu"
    ],
    "name:tur_x_preferred":[
        "Kalburlu"
    ],
    "name:vie_x_preferred":[
        "Kalburlu"
    ],
    "wof:name":"Kalburlu",
    "wof:placetype":"locality"
},
  "geometry": {"coordinates":[41.88954,41.12913],"type":"Point"}
}