{
  "type": "Feature",
  "properties": {
    "gn:admin1_code":"63.0",
    "gn:asciiname":"Kuruyer",
    "gn:country_code":"TR",
    "gn:dem":370,
    "gn:feature_class":"P",
    "gn:feature_code":"PPL",
    "gn:name":"Kuruyer",
    "gn:population":0,
    "gn:timezone":"Europe/Istanbul",
    "iso:country":"TR",
    "name:tur_x_historical":[
        "A\u015fa\u011f\u0131 H\u00fcmeyre"
    ],
    "name:tur_x_preferred":[
        "Kuruyer"
    ],
    "name:tur_x_variant":[
        "A\u015fa\u011f\u0131 H\u00fcmeyre"
    ],
    "name:und_x_variant":[
        "Ashagy-Khyumeyre"
    ],
    "wof:name":"Kuruyer",
    "wof:placetype":"locality"
},
  "geometry": {"coordinates":[39.025,36.9125],"type":"Point"}
}