{
  "type": "Feature",
  "properties": {
    "gn:admin1_code":"07",
    "gn:asciiname":"Cakirlar",
    "gn:country_code":"TR",
    "gn:dem":45,
    "gn:feature_class":"P",
    "gn:feature_code":"PPLA3",
    "gn:name":"\u00c7ak\u0131rlar",
    "gn:population":0,
    "gn:timezone":"Europe/Istanbul",
    "iso:country":"TR",
    "name:tur_x_preferred":[
        "\u00c7ak\u0131rlar"
    ],
    "wof:name":"Cakirlar",
    "wof:placetype":"locality"
},
  "geometry": {"coordinates":[30.56208,36.87145],"type":"Point"}
}