{
  "type": "Feature",
  "properties": {
    "gn:admin1_code":"61.0",
    "gn:asciiname":"Erenkoy",
    "gn:country_code":"TR",
    "gn:dem":414,
    "gn:feature_class":"P",
    "gn:feature_code":"PPL",
    "gn:name":"Erenk\u00f6y",
    "gn:population":0,
    "gn:timezone":"Europe/Istanbul",
    "iso:country":"TR",
    "name:und_x_variant":[
        "Erenk\u00f6y",
        "Visir"
    ],
    "wof:name":"Erenkoy",
    "wof:placetype":"locality"
},
  "geometry": {"coordinates":[40.2355,40.83888],"type":"Point"}
}