{
  "type": "Feature",
  "properties": {
    "gn:admin1_code":"45",
    "gn:asciiname":"Kaplancukuru",
    "gn:country_code":"TR",
    "gn:dem":962,
    "gn:feature_class":"P",
    "gn:feature_code":"PPL",
    "gn:name":"Kaplancukuru",
    "gn:population":0,
    "gn:timezone":"Europe/Istanbul",
    "iso:country":"TR",
    "name:tur_x_preferred":[
        "Kaplancukuru"
    ],
    "wof:name":"Kaplancukuru",
    "wof:placetype":"locality"
},
  "geometry": {"coordinates":[28.47578,38.31516],"type":"Point"}
}