{
  "type": "Feature",
  "properties": {
    "gn:admin1_code":"82.0",
    "gn:asciiname":"Yukari Colkesen",
    "gn:country_code":"TR",
    "gn:dem":676,
    "gn:feature_class":"P",
    "gn:feature_code":"PPL",
    "gn:name":"Yukar\u0131 \u00c7\u00f6lkesen",
    "gn:population":0,
    "gn:timezone":"Europe/Istanbul",
    "iso:country":"TR",
    "wof:name":"Yukari Colkesen",
    "wof:placetype":"locality"
},
  "geometry": {"coordinates":[33.72611,40.4881],"type":"Point"}
}