{
  "type": "Feature",
  "properties": {
    "gn:country":"TR",
    "gn:fcode":"PPL",
    "gn:pop":757,
    "iso:country":"TR",
    "name:tur_x_preferred":[
        "A\u015fa\u011f\u0131 Oylum"
    ],
    "name:unk_x_variant":[
        "A\u015fa\u011f\u0131parapar"
    ],
    "qs:name":"A\u015fa\u011f\u0131oylum",
    "qs:photos_9r":0,
    "qs:photos_sr":0,
    "qs:pop_sr":"2",
    "wof:name":"A\u015fa\u011f\u0131oylum",
    "wof:placetype":"locality",
    "wof:population":757
},
  "geometry": {"coordinates":[38.54485,36.86391],"type":"Point"}
}