{
  "type": "Feature",
  "properties": {
    "gn:admin1_code":"12",
    "gn:asciiname":"Alpekmez",
    "gn:country_code":"TR",
    "gn:dem":1679,
    "gn:feature_class":"P",
    "gn:feature_code":"PPL",
    "gn:name":"Alpekmez",
    "gn:population":0,
    "gn:timezone":"Europe/Istanbul",
    "iso:country":"TR",
    "name:tur_x_preferred":[
        "\u00c7al\u0131ka\u011f\u0131l"
    ],
    "name:und_x_variant":[
        "\u00c7ak\u0131la\u011f\u0131l",
        "Alpekmez"
    ],
    "wof:name":"Alpekmez",
    "wof:placetype":"locality"
},
  "geometry": {"coordinates":[40.05393,39.29371],"type":"Point"}
}