{
  "type": "Feature",
  "properties": {
    "gn:admin1_code":"23",
    "gn:asciiname":"Salkimli",
    "gn:country_code":"TR",
    "gn:dem":919,
    "gn:feature_class":"P",
    "gn:feature_code":"PPL",
    "gn:name":"Salk\u0131ml\u0131",
    "gn:population":0,
    "gn:timezone":"Europe/Istanbul",
    "iso:country":"TR",
    "name:und_x_variant":[
        "Enkuran",
        "Salk\u0131ml\u0131",
        "Eng\u00fcran"
    ],
    "wof:name":"Salkimli",
    "wof:placetype":"locality"
},
  "geometry": {"coordinates":[39.64251,38.69083],"type":"Point"}
}