{
  "type": "Feature",
  "properties": {
    "gn:admin1_code":"26",
    "gn:asciiname":"Yenikoy Yaylasi",
    "gn:country_code":"TR",
    "gn:dem":1187,
    "gn:feature_class":"P",
    "gn:feature_code":"PPL",
    "gn:name":"Yenik\u00f6y Yaylas\u0131",
    "gn:population":0,
    "gn:timezone":"Europe/Istanbul",
    "iso:country":"TR",
    "name:tur_x_preferred":[
        "Yenik\u00f6y Yaylas\u0131"
    ],
    "name:und_x_variant":[
        "Elekli",
        "Elekliyaylas\u0131"
    ],
    "wof:name":"Yenikoy Yaylasi",
    "wof:placetype":"locality"
},
  "geometry": {"coordinates":[31.44977,39.47464],"type":"Point"}
}