{
  "type": "Feature",
  "properties": {
    "gn:admin1_code":"17.0",
    "gn:asciiname":"Gevicikiri",
    "gn:country_code":"TR",
    "gn:dem":62,
    "gn:feature_class":"P",
    "gn:feature_code":"PPL",
    "gn:name":"Gevicik\u0131r\u0131",
    "gn:population":0,
    "gn:timezone":"Europe/Istanbul",
    "iso:country":"TR",
    "wof:name":"Gevicikiri",
    "wof:placetype":"locality"
},
  "geometry": {"coordinates":[27.16375,40.22161],"type":"Point"}
}