{
  "type": "Feature",
  "properties": {
    "gn:admin1_code":"19.0",
    "gn:asciiname":"Oyaca",
    "gn:country_code":"TR",
    "gn:dem":975,
    "gn:feature_class":"P",
    "gn:feature_code":"PPL",
    "gn:name":"Oyaca",
    "gn:population":0,
    "gn:timezone":"Europe/Istanbul",
    "iso:country":"TR",
    "wof:name":"Oyaca",
    "wof:placetype":"locality"
},
  "geometry": {"coordinates":[34.34394,40.35216],"type":"Point"}
}