{
  "type": "Feature",
  "properties": {
    "gn:admin1_code":"58",
    "gn:asciiname":"Kayabasi",
    "gn:country_code":"TR",
    "gn:dem":1684,
    "gn:feature_class":"P",
    "gn:feature_code":"PPL",
    "gn:name":"Kayaba\u015f\u0131",
    "gn:population":0,
    "gn:timezone":"Europe/Istanbul",
    "iso:country":"TR",
    "name:tur_x_preferred":[
        "Kayaba\u015f\u0131"
    ],
    "wof:name":"Kayabasi",
    "wof:placetype":"locality"
},
  "geometry": {"coordinates":[37.76726,40.14648],"type":"Point"}
}