{
  "type": "Feature",
  "properties": {
    "iso:country":"TR",
    "name:eng_x_preferred":[
        "Imrenli"
    ],
    "name:tur_x_preferred":[
        "\u0130mrenli"
    ],
    "wof:name":"Imrenli",
    "wof:placetype":"neighbourhood"
},
  "geometry": {"coordinates":[29.73806746453862,41.14672759676783],"type":"Point"}
}