{
  "type": "Feature",
  "properties": {
    "gn:admin1_code":"72",
    "gn:asciiname":"Baysun",
    "gn:country_code":"TR",
    "gn:dem":822,
    "gn:feature_class":"P",
    "gn:feature_code":"PPL",
    "gn:name":"Baysun",
    "gn:population":0,
    "gn:timezone":"Europe/Istanbul",
    "iso:country":"TR",
    "name:und_x_variant":[
        "Dinar",
        "Baysun"
    ],
    "wof:name":"Baysun",
    "wof:placetype":"locality"
},
  "geometry": {"coordinates":[41.78039,37.44234],"type":"Point"}
}