{
  "type": "Feature",
  "properties": {
    "gn:admin1_code":"88",
    "gn:asciiname":"Halfeli",
    "gn:country_code":"TR",
    "gn:dem":869,
    "gn:feature_class":"P",
    "gn:feature_code":"PPL",
    "gn:name":"Halfeli",
    "gn:population":0,
    "gn:timezone":"Europe/Istanbul",
    "iso:country":"TR",
    "name:und_x_variant":[
        "Khalfalu",
        "Halfali",
        "Halefli",
        "Halfeli"
    ],
    "wof:name":"Halfeli",
    "wof:placetype":"locality"
},
  "geometry": {"coordinates":[43.98861,39.88806],"type":"Point"}
}