{
  "type": "Feature",
  "properties": {
    "gn:admin1_code":"48",
    "gn:asciiname":"Kayabasi",
    "gn:country_code":"TR",
    "gn:dem":1439,
    "gn:feature_class":"P",
    "gn:feature_code":"PPL",
    "gn:name":"Kayaba\u015f\u0131",
    "gn:population":0,
    "gn:timezone":"Europe/Istanbul",
    "iso:country":"TR",
    "wof:name":"Kayabasi",
    "wof:placetype":"locality"
},
  "geometry": {"coordinates":[29.73169,36.87556],"type":"Point"}
}