{
  "type": "Feature",
  "properties": {
    "gn:admin1_code":"85",
    "gn:asciiname":"Budaklar",
    "gn:country_code":"TR",
    "gn:dem":84,
    "gn:feature_class":"P",
    "gn:feature_code":"PPL",
    "gn:name":"Budaklar",
    "gn:population":0,
    "gn:timezone":"Europe/Istanbul",
    "iso:country":"TR",
    "wof:name":"Budaklar",
    "wof:placetype":"locality"
},
  "geometry": {"coordinates":[32.17437,41.50882],"type":"Point"}
}