{
  "type": "Feature",
  "properties": {
    "gn:country":"TR",
    "gn:fcode":"PPLX",
    "gn:pop":0,
    "iso:country":"TR",
    "name:unk_x_variant":[
        "Zeytin K\u00f6y"
    ],
    "qs:name":"Etiler",
    "qs:name_adm0":"Turkey",
    "qs:name_adm1":"Antalya",
    "qs:photos":1,
    "qs:photos_1k":1,
    "qs:photos_9k":1,
    "qs:photos_9r":1,
    "qs:photos_all":1,
    "qs:photos_sr":1,
    "qs:placetype":"Suburb",
    "qs:pop_sr":"0",
    "wd:wordcount":382,
    "wof:name":"Etiler",
    "wof:placetype":"neighbourhood",
    "wof:population":0
},
  "geometry": {"coordinates":[30.71353,36.90101],"type":"Point"}
}