{
  "type": "Feature",
  "properties": {
    "gn:admin1_code":"87",
    "gn:asciiname":"Pasalilar",
    "gn:country_code":"TR",
    "gn:dem":370,
    "gn:feature_class":"P",
    "gn:feature_code":"PPL",
    "gn:name":"Pa\u015fal\u0131lar",
    "gn:population":0,
    "gn:timezone":"Europe/Istanbul",
    "iso:country":"TR",
    "wof:name":"Pasalilar",
    "wof:placetype":"locality"
},
  "geometry": {"coordinates":[32.61886,41.78062],"type":"Point"}
}