{
  "type": "Feature",
  "properties": {
    "iso:country":"TR",
    "name:eng_x_preferred":[
        "Esenler"
    ],
    "name:tur_x_preferred":[
        "Esenler"
    ],
    "wof:name":"Esenler",
    "wof:placetype":"neighbourhood"
},
  "geometry": {"coordinates":[29.27237780952583,40.88464286951249],"type":"Point"}
}