{
  "type": "Feature",
  "properties": {
    "gn:admin1_code":"74.0",
    "gn:asciiname":"Oglakli",
    "gn:country_code":"TR",
    "gn:dem":1274,
    "gn:feature_class":"P",
    "gn:feature_code":"PPL",
    "gn:name":"O\u011flakl\u0131",
    "gn:population":0,
    "gn:timezone":"Europe/Istanbul",
    "iso:country":"TR",
    "wof:name":"Oglakli",
    "wof:placetype":"locality"
},
  "geometry": {"coordinates":[41.66809,38.24009],"type":"Point"}
}