{
  "type": "Feature",
  "properties": {
    "gn:admin1_code":"73",
    "gn:asciiname":"Fertek",
    "gn:country_code":"TR",
    "gn:dem":1292,
    "gn:feature_class":"P",
    "gn:feature_code":"PPL",
    "gn:name":"Fertek",
    "gn:population":0,
    "gn:timezone":"Europe/Istanbul",
    "iso:country":"TR",
    "name:ceb_x_preferred":[
        "Aykent"
    ],
    "name:tur_x_preferred":[
        "Ayd\u0131nyurt"
    ],
    "name:und_x_variant":[
        "Aykent",
        "Fertek"
    ],
    "wof:name":"Fertek",
    "wof:placetype":"locality"
},
  "geometry": {"coordinates":[34.62214,37.97415],"type":"Point"}
}