{
  "type": "Feature",
  "properties": {
    "gn:admin1_code":"16.0",
    "gn:asciiname":"Guzelyurt",
    "gn:country_code":"TR",
    "gn:dem":681,
    "gn:feature_class":"P",
    "gn:feature_code":"PPL",
    "gn:name":"G\u00fczelyurt",
    "gn:population":0,
    "gn:timezone":"Europe/Istanbul",
    "iso:country":"TR",
    "name:und_x_variant":[
        "\u00dc\u00e7lermezar\u0131",
        "Mamure",
        "Uclar",
        "\u00dc\u00e7ler-Mamure",
        "G\u00fczelyurt"
    ],
    "wof:name":"Guzelyurt",
    "wof:placetype":"locality"
},
  "geometry": {"coordinates":[29.71689000000001,40.0238],"type":"Point"}
}