{
  "type": "Feature",
  "properties": {
    "gn:admin1_code":"68.0",
    "gn:asciiname":"Hidirlar",
    "gn:country_code":"TR",
    "gn:dem":1369,
    "gn:feature_class":"P",
    "gn:feature_code":"PPL",
    "gn:name":"H\u0131d\u0131rlar",
    "gn:population":0,
    "gn:timezone":"Europe/Istanbul",
    "iso:country":"TR",
    "name:und_x_variant":[
        "H\u0131z\u0131rlar",
        "H\u0131d\u0131rlar"
    ],
    "wof:name":"Hidirlar",
    "wof:placetype":"locality"
},
  "geometry": {"coordinates":[32.65349000000001,40.66816],"type":"Point"}
}