{
  "type": "Feature",
  "properties": {
    "gn:admin1_code":"20.0",
    "gn:asciiname":"Ahilli",
    "gn:country_code":"TR",
    "gn:dem":633,
    "gn:feature_class":"P",
    "gn:feature_code":"PPL",
    "gn:name":"Ah\u0131ll\u0131",
    "gn:population":0,
    "gn:timezone":"Europe/Istanbul",
    "iso:country":"TR",
    "name:tur_x_preferred":[
        "Ah\u0131ll\u0131"
    ],
    "wof:name":"Ahilli",
    "wof:placetype":"locality"
},
  "geometry": {"coordinates":[28.84527000000001,37.81791],"type":"Point"}
}