{
  "type": "Feature",
  "properties": {
    "gn:admin1_code":"25.0",
    "gn:asciiname":"Sungubayiri",
    "gn:country_code":"TR",
    "gn:dem":1914,
    "gn:feature_class":"P",
    "gn:feature_code":"PPL",
    "gn:name":"S\u00fcng\u00fcbay\u0131r\u0131",
    "gn:population":0,
    "gn:timezone":"Europe/Istanbul",
    "iso:country":"TR",
    "name:tur_x_preferred":[
        "S\u00fcng\u00fcbay\u0131r\u0131"
    ],
    "wof:name":"Sungubayiri",
    "wof:placetype":"locality"
},
  "geometry": {"coordinates":[42.09563,40.88922],"type":"Point"}
}