{
  "type": "Feature",
  "properties": {
    "gn:admin1_code":"31.0",
    "gn:asciiname":"Yosunkaya",
    "gn:country_code":"TR",
    "gn:dem":830,
    "gn:feature_class":"P",
    "gn:feature_code":"PPL",
    "gn:name":"Yosunkaya",
    "gn:population":0,
    "gn:timezone":"Europe/Istanbul",
    "iso:country":"TR",
    "name:und_x_variant":[
        "Korum"
    ],
    "wof:name":"Yosunkaya",
    "wof:placetype":"locality"
},
  "geometry": {"coordinates":[36.06663,35.9812],"type":"Point"}
}