{
  "type": "Feature",
  "properties": {
    "gn:admin1_code":"26",
    "gn:asciiname":"Belek Mahallesi",
    "gn:country_code":"TR",
    "gn:dem":1230,
    "gn:feature_class":"P",
    "gn:feature_code":"PPL",
    "gn:name":"Belek Mahallesi",
    "gn:population":0,
    "gn:timezone":"Europe/Istanbul",
    "iso:country":"TR",
    "wof:name":"Belek Mahallesi",
    "wof:placetype":"locality"
},
  "geometry": {"coordinates":[31.45694,39.65642],"type":"Point"}
}