{
  "type": "Feature",
  "properties": {
    "gn:admin1_code":"13",
    "gn:asciiname":"Simos",
    "gn:country_code":"TR",
    "gn:dem":1684,
    "gn:feature_class":"P",
    "gn:feature_code":"PPLA3",
    "gn:name":"Simos",
    "gn:population":0,
    "gn:timezone":"Europe/Istanbul",
    "iso:country":"TR",
    "name:und_x_variant":[
        "U\u00e7um",
        "Simos",
        "Sa\u011f\u0131nl\u0131"
    ],
    "wof:name":"Simos",
    "wof:placetype":"locality"
},
  "geometry": {"coordinates":[42.58375,38.05731],"type":"Point"}
}