{
  "type": "Feature",
  "properties": {
    "gn:admin1_code":"41.0",
    "gn:asciiname":"Sarigazi",
    "gn:country_code":"TR",
    "gn:dem":81,
    "gn:feature_class":"P",
    "gn:feature_code":"PPL",
    "gn:name":"Sar\u0131gazi",
    "gn:population":0,
    "gn:timezone":"Europe/Istanbul",
    "iso:country":"TR",
    "name:tur_x_preferred":[
        "Sar\u0131gazi"
    ],
    "name:und_x_variant":[
        "Sar\u0131lar",
        "Kabao\u011flu"
    ],
    "wof:name":"Sarigazi",
    "wof:placetype":"locality"
},
  "geometry": {"coordinates":[30.25527,40.97483],"type":"Point"}
}