{
  "type": "Feature",
  "properties": {
    "gn:admin1_code":"49",
    "gn:asciiname":"Karabey",
    "gn:country_code":"TR",
    "gn:dem":1372,
    "gn:feature_class":"P",
    "gn:feature_code":"PPL",
    "gn:name":"Karabey",
    "gn:population":0,
    "gn:timezone":"Europe/Istanbul",
    "iso:country":"TR",
    "name:tur_x_preferred":[
        "Karabey"
    ],
    "wof:name":"Karabey",
    "wof:placetype":"locality"
},
  "geometry": {"coordinates":[41.18109000000001,38.91573],"type":"Point"}
}