{
  "type": "Feature",
  "properties": {
    "gn:admin1_code":"77.0",
    "gn:asciiname":"Kondolot",
    "gn:country_code":"TR",
    "gn:dem":1889,
    "gn:feature_class":"P",
    "gn:feature_code":"PPL",
    "gn:name":"Kondolot",
    "gn:population":0,
    "gn:timezone":"Europe/Istanbul",
    "iso:country":"TR",
    "name:und_x_variant":[
        "Da\u011f\u00e7at\u0131"
    ],
    "wof:name":"Kondolot",
    "wof:placetype":"locality"
},
  "geometry": {"coordinates":[39.91244,40.40519000000001],"type":"Point"}
}