{
  "type": "Feature",
  "properties": {
    "gn:admin1_code":"09",
    "gn:asciiname":"Yamac",
    "gn:country_code":"TR",
    "gn:dem":360,
    "gn:feature_class":"P",
    "gn:feature_code":"PPL",
    "gn:name":"Yama\u00e7",
    "gn:population":0,
    "gn:timezone":"Europe/Istanbul",
    "iso:country":"TR",
    "name:und_x_variant":[
        "Kayas \u00c7iftli\u011fi",
        "Kaya\u015f",
        "Yama\u00e7"
    ],
    "wof:name":"Yamac",
    "wof:placetype":"locality"
},
  "geometry": {"coordinates":[27.41559,37.79385],"type":"Point"}
}