{
  "type": "Feature",
  "properties": {
    "gn:admin1_code":"49",
    "gn:asciiname":"Azikli",
    "gn:country_code":"TR",
    "gn:dem":1348,
    "gn:feature_class":"P",
    "gn:feature_code":"PPL",
    "gn:name":"Az\u0131kl\u0131",
    "gn:population":0,
    "gn:timezone":"Europe/Istanbul",
    "iso:country":"TR",
    "name:tur_x_preferred":[
        "Az\u0131kl\u0131"
    ],
    "wof:name":"Azikli",
    "wof:placetype":"locality"
},
  "geometry": {"coordinates":[41.73066,38.6444],"type":"Point"}
}