{
  "type": "Feature",
  "properties": {
    "gn:admin1_code":"14",
    "gn:asciiname":"Guneydemirciler",
    "gn:country_code":"TR",
    "gn:dem":1318,
    "gn:feature_class":"P",
    "gn:feature_code":"PPL",
    "gn:name":"G\u00fcneydemirciler",
    "gn:population":0,
    "gn:timezone":"Europe/Istanbul",
    "iso:country":"TR",
    "wof:name":"Guneydemirciler",
    "wof:placetype":"locality"
},
  "geometry": {"coordinates":[32.20969,40.79501],"type":"Point"}
}