{
  "type": "Feature",
  "properties": {
    "gn:country":"TR",
    "gn:fcode":"PPL",
    "gn:population":0,
    "iso:country":"TR",
    "name:min_x_preferred":[
        "Yenikent"
    ],
    "name:tur_x_preferred":[
        "Yenikent"
    ],
    "name:und_x_variant":[
        "Yenik\u00f6y"
    ],
    "qs:name":"Yenikent",
    "qs:name_adm0":"Turkey",
    "qs:name_adm1":"Eski\u015fehir",
    "qs:photos":2,
    "qs:photos_1k":1,
    "qs:photos_9k":1,
    "qs:photos_9r":1,
    "qs:photos_all":2,
    "qs:photos_sr":1,
    "qs:placetype":"Suburb",
    "qs:pop_sr":"0",
    "wd:wordcount":19,
    "wof:name":"Yenikent",
    "wof:placetype":"neighbourhood",
    "wof:population":0
},
  "geometry": {"coordinates":[30.74,39.56917],"type":"Point"}
}