{
  "type": "Feature",
  "properties": {
    "gn:admin1_code":"76.0",
    "gn:asciiname":"Kasyayla",
    "gn:country_code":"TR",
    "gn:dem":1128,
    "gn:feature_class":"P",
    "gn:feature_code":"PPL",
    "gn:name":"Ka\u015fyayla",
    "gn:population":0,
    "gn:timezone":"Europe/Istanbul",
    "iso:country":"TR",
    "name:tur_x_preferred":[
        "Ka\u015fyayla"
    ],
    "wof:name":"Kasyayla",
    "wof:placetype":"locality"
},
  "geometry": {"coordinates":[41.29564,38.4395],"type":"Point"}
}