{
  "type": "Feature",
  "properties": {
    "gn:admin1_code":"10",
    "gn:asciiname":"Emeksiz",
    "gn:country_code":"TR",
    "gn:dem":759,
    "gn:feature_class":"P",
    "gn:feature_code":"PPL",
    "gn:name":"Emeksiz",
    "gn:population":0,
    "gn:timezone":"Europe/Istanbul",
    "iso:country":"TR",
    "name:tur_x_preferred":[
        "Emeksiz"
    ],
    "wof:name":"Emeksiz",
    "wof:placetype":"locality"
},
  "geometry": {"coordinates":[28.82349,39.55871],"type":"Point"}
}