{
  "type": "Feature",
  "properties": {
    "gn:admin1_code":"21",
    "gn:asciiname":"Karalar",
    "gn:country_code":"TR",
    "gn:dem":627,
    "gn:feature_class":"P",
    "gn:feature_code":"PPL",
    "gn:name":"Karalar",
    "gn:population":0,
    "gn:timezone":"Europe/Istanbul",
    "iso:country":"TR",
    "name:und_x_variant":[
        "Karelu",
        "Karalar"
    ],
    "wof:name":"Karalar",
    "wof:placetype":"locality"
},
  "geometry": {"coordinates":[40.49046,37.8004],"type":"Point"}
}