{
  "type": "Feature",
  "properties": {
    "gn:admin1_code":"21",
    "gn:asciiname":"Karalar",
    "gn:country_code":"TR",
    "gn:dem":627,
    "gn:feature_class":"P",
    "gn:feature_code":"PPL",
    "gn:name":"Karalar",
    "gn:population":0,
    "gn:timezone":"Europe/Istanbul",
    "iso:country":"TR",
    "name:aze_x_preferred":[
        "Qaralar"
    ],
    "name:ceb_x_preferred":[
        "Qaralar"
    ],
    "name:ita_x_preferred":[
        "Qaralar"
    ],
    "name:kat_x_preferred":[
        "\u10e7\u10d0\u10e0\u10d0\u10da\u10d0\u10e0\u10d8"
    ],
    "name:swe_x_preferred":[
        "Qaralar"
    ],
    "name:tur_x_preferred":[
        "Karalar"
    ],
    "name:und_x_variant":[
        "Karelu"
    ],
    "wof:name":"Karalar",
    "wof:placetype":"locality"
},
  "geometry": {"coordinates":[40.49046,37.8004],"type":"Point"}
}