{
  "type": "Feature",
  "properties": {
    "gn:admin1_code":"14",
    "gn:asciiname":"Dere",
    "gn:country_code":"TR",
    "gn:dem":974,
    "gn:feature_class":"P",
    "gn:feature_code":"PPL",
    "gn:name":"Dere",
    "gn:population":0,
    "gn:timezone":"Europe/Istanbul",
    "iso:country":"TR",
    "wof:name":"Dere",
    "wof:placetype":"locality"
},
  "geometry": {"coordinates":[31.1623,40.42857],"type":"Point"}
}