{
  "type": "Feature",
  "properties": {
    "gn:admin1_code":"68.0",
    "gn:asciiname":"Akkaynak",
    "gn:country_code":"TR",
    "gn:dem":1008,
    "gn:feature_class":"P",
    "gn:feature_code":"PPL",
    "gn:name":"Akkaynak",
    "gn:population":0,
    "gn:timezone":"Europe/Istanbul",
    "iso:country":"TR",
    "name:und_x_variant":[
        "Dokuztorba",
        "Akkaynak"
    ],
    "wof:name":"Akkaynak",
    "wof:placetype":"locality"
},
  "geometry": {"coordinates":[33.39417,40.169],"type":"Point"}
}