{
  "type": "Feature",
  "properties": {
    "gn:admin1_code":"21.0",
    "gn:asciiname":"Kelesevleri",
    "gn:country_code":"TR",
    "gn:dem":1024,
    "gn:feature_class":"P",
    "gn:feature_code":"PPL",
    "gn:name":"Kele\u015fevleri",
    "gn:population":0,
    "gn:timezone":"Europe/Istanbul",
    "iso:country":"TR",
    "name:tur_x_preferred":[
        "Kele\u015fevleri"
    ],
    "wof:name":"Kelesevleri",
    "wof:placetype":"locality"
},
  "geometry": {"coordinates":[39.32741,38.20454],"type":"Point"}
}