{
  "type": "Feature",
  "properties": {
    "gn:admin1_code":"53.0",
    "gn:asciiname":"Meydankobaca",
    "gn:country_code":"TR",
    "gn:dem":1602,
    "gn:feature_class":"P",
    "gn:feature_code":"PPL",
    "gn:name":"Meydankobaca",
    "gn:population":0,
    "gn:timezone":"Europe/Istanbul",
    "iso:country":"TR",
    "wof:name":"Meydankobaca",
    "wof:placetype":"locality"
},
  "geometry": {"coordinates":[40.93365,40.907],"type":"Point"}
}