{
  "type": "Feature",
  "properties": {
    "gn:admin1_code":"43",
    "gn:asciiname":"Demircioren",
    "gn:country_code":"TR",
    "gn:dem":1070,
    "gn:feature_class":"P",
    "gn:feature_code":"PPL",
    "gn:name":"Demirci\u00f6ren",
    "gn:population":0,
    "gn:timezone":"Europe/Istanbul",
    "iso:country":"TR",
    "name:tur_x_preferred":[
        "Demirciveran"
    ],
    "name:und_x_variant":[
        "Demirci\u00f6ren"
    ],
    "wof:name":"Demircioren",
    "wof:placetype":"locality"
},
  "geometry": {"coordinates":[29.86688,39.45051],"type":"Point"}
}