{
  "type": "Feature",
  "properties": {
    "gn:admin1_code":"78",
    "gn:asciiname":"Civler",
    "gn:country_code":"TR",
    "gn:dem":1363,
    "gn:feature_class":"P",
    "gn:feature_code":"PPL",
    "gn:name":"Civler",
    "gn:population":0,
    "gn:timezone":"Europe/Istanbul",
    "iso:country":"TR",
    "name:tur_x_preferred":[
        "Civler"
    ],
    "wof:name":"Civler",
    "wof:placetype":"locality"
},
  "geometry": {"coordinates":[32.5838,36.66699000000001],"type":"Point"}
}