{
  "type": "Feature",
  "properties": {
    "gn:admin1_code":"49",
    "gn:asciiname":"Hankoy",
    "gn:country_code":"TR",
    "gn:dem":1554,
    "gn:feature_class":"P",
    "gn:feature_code":"PPL",
    "gn:name":"Hank\u00f6y",
    "gn:population":0,
    "gn:timezone":"Europe/Istanbul",
    "iso:country":"TR",
    "name:tur_x_preferred":[
        "Hank\u00f6y"
    ],
    "wof:name":"Hankoy",
    "wof:placetype":"locality"
},
  "geometry": {"coordinates":[42.29579,39.27473],"type":"Point"}
}