{
  "type": "Feature",
  "properties": {
    "gn:admin1_code":"61.0",
    "gn:asciiname":"Fenerkoyu",
    "gn:country_code":"TR",
    "gn:dem":32,
    "gn:feature_class":"P",
    "gn:feature_code":"PPL",
    "gn:name":"Fenerk\u00f6y\u00fc",
    "gn:population":0,
    "gn:timezone":"Europe/Istanbul",
    "iso:country":"TR",
    "wof:name":"Fenerkoyu",
    "wof:placetype":"locality"
},
  "geometry": {"coordinates":[39.40588,41.09965],"type":"Point"}
}