{
  "type": "Feature",
  "properties": {
    "gn:country":"TR",
    "gn:fcode":"PPL",
    "gn:pop":814,
    "iso:country":"TR",
    "name:tur_x_preferred":[
        "Damlac\u0131k"
    ],
    "qs:name":"Damlac\u0131k",
    "qs:photos_9r":0,
    "qs:photos_sr":0,
    "qs:pop_sr":"2",
    "wof:name":"Damlac\u0131k",
    "wof:placetype":"locality",
    "wof:population":814
},
  "geometry": {"coordinates":[40.1025,36.91528],"type":"Point"}
}