{
  "type": "Feature",
  "properties": {
    "gn:admin1_code":"25",
    "gn:asciiname":"Yesiloz",
    "gn:country_code":"TR",
    "gn:dem":1794,
    "gn:feature_class":"P",
    "gn:feature_code":"PPL",
    "gn:name":"Ye\u015fil\u00f6z",
    "gn:population":0,
    "gn:timezone":"Europe/Istanbul",
    "iso:country":"TR",
    "name:tur_x_preferred":[
        "Ye\u015fil\u00f6z"
    ],
    "wof:name":"Yesiloz",
    "wof:placetype":"locality"
},
  "geometry": {"coordinates":[42.27478,39.93385],"type":"Point"}
}