{
  "type": "Feature",
  "properties": {
    "gn:admin1_code":"5.0",
    "gn:asciiname":"Komurocagi",
    "gn:country_code":"TR",
    "gn:dem":1442,
    "gn:feature_class":"P",
    "gn:feature_code":"PPL",
    "gn:name":"K\u00f6m\u00fcroca\u011f\u0131",
    "gn:population":0,
    "gn:timezone":"Europe/Istanbul",
    "iso:country":"TR",
    "wof:name":"Komurocagi",
    "wof:placetype":"locality"
},
  "geometry": {"coordinates":[36.07931,40.63427],"type":"Point"}
}