{
  "type": "Feature",
  "properties": {
    "gn:admin1_code":"45",
    "gn:asciiname":"Sarisey",
    "gn:country_code":"TR",
    "gn:dem":362,
    "gn:feature_class":"P",
    "gn:feature_code":"PPL",
    "gn:name":"Sar\u0131sey",
    "gn:population":0,
    "gn:timezone":"Europe/Istanbul",
    "iso:country":"TR",
    "name:tur_x_preferred":[
        "Sar\u0131sey"
    ],
    "wof:name":"Sarisey",
    "wof:placetype":"locality"
},
  "geometry": {"coordinates":[28.16931,38.64264],"type":"Point"}
}