{
  "type": "Feature",
  "properties": {
    "gn:admin1_code":"07",
    "gn:asciiname":"Fettahli",
    "gn:country_code":"TR",
    "gn:dem":79,
    "gn:feature_class":"P",
    "gn:feature_code":"PPL",
    "gn:name":"Fettahl\u0131",
    "gn:population":0,
    "gn:timezone":"Europe/Istanbul",
    "iso:country":"TR",
    "name:tur_x_preferred":[
        "Fettahl\u0131"
    ],
    "wof:name":"Fettahli",
    "wof:placetype":"locality"
},
  "geometry": {"coordinates":[30.80941,36.98669],"type":"Point"}
}