{
  "type": "Feature",
  "properties": {
    "gn:admin1_code":"22.0",
    "gn:asciiname":"Sehitler",
    "gn:country_code":"TR",
    "gn:dem":111,
    "gn:feature_class":"P",
    "gn:feature_code":"PPL",
    "gn:name":"\u015eehitler",
    "gn:population":0,
    "gn:timezone":"Europe/Istanbul",
    "iso:country":"TR",
    "wof:name":"Sehitler",
    "wof:placetype":"locality"
},
  "geometry": {"coordinates":[26.2926,40.69114],"type":"Point"}
}