{
  "type": "Feature",
  "properties": {
    "gn:admin1_code":"28.0",
    "gn:asciiname":"Saplica",
    "gn:country_code":"TR",
    "gn:dem":1392,
    "gn:feature_class":"P",
    "gn:feature_code":"PPL",
    "gn:name":"\u015eapl\u0131ca",
    "gn:population":0,
    "gn:timezone":"Europe/Istanbul",
    "iso:country":"TR",
    "name:und_x_variant":[
        "Gedehor",
        "Sagl\u0131ca",
        "\u015eapl\u0131ca"
    ],
    "wof:name":"Saplica",
    "wof:placetype":"locality"
},
  "geometry": {"coordinates":[38.44456,40.35658],"type":"Point"}
}