{
  "type": "Feature",
  "properties": {
    "gn:admin1_code":"10",
    "gn:asciiname":"Eseler",
    "gn:country_code":"TR",
    "gn:dem":332,
    "gn:feature_class":"P",
    "gn:feature_code":"PPL",
    "gn:name":"Eseler",
    "gn:population":0,
    "gn:timezone":"Europe/Istanbul",
    "iso:country":"TR",
    "name:tur_x_preferred":[
        "Eseler"
    ],
    "wof:name":"Eseler",
    "wof:placetype":"locality"
},
  "geometry": {"coordinates":[27.20854000000001,39.54915],"type":"Point"}
}