{
  "type": "Feature",
  "properties": {
    "gn:admin1_code":"20",
    "gn:asciiname":"Okuzler",
    "gn:country_code":"TR",
    "gn:dem":1166,
    "gn:feature_class":"P",
    "gn:feature_code":"PPL",
    "gn:name":"\u00d6k\u00fczler",
    "gn:population":0,
    "gn:timezone":"Europe/Istanbul",
    "iso:country":"TR",
    "wof:name":"Okuzler",
    "wof:placetype":"locality"
},
  "geometry": {"coordinates":[29.03371,37.15632],"type":"Point"}
}