{
  "type": "Feature",
  "properties": {
    "gn:admin1_code":"59.0",
    "gn:asciiname":"Cerkezmusellim",
    "gn:cc2":"TR",
    "gn:country_code":"TR",
    "gn:dem":109,
    "gn:feature_class":"P",
    "gn:feature_code":"PPL",
    "gn:name":"\u00c7erkezm\u00fcsellim",
    "gn:population":0,
    "gn:timezone":"Europe/Istanbul",
    "iso:country":"TR",
    "name:und_x_variant":[
        "\u00c7erke\u015f M\u00fcsellim",
        "\u00c7erkezm\u00fcsellim"
    ],
    "wof:name":"Cerkezmusellim",
    "wof:placetype":"locality"
},
  "geometry": {"coordinates":[27.02806,41.275],"type":"Point"}
}