{
  "type": "Feature",
  "properties": {
    "gn:admin1_code":"23",
    "gn:asciiname":"Yukari Canakci",
    "gn:country_code":"TR",
    "gn:dem":1464,
    "gn:feature_class":"P",
    "gn:feature_code":"PPL",
    "gn:name":"Yukar\u0131 \u00c7anak\u00e7\u0131",
    "gn:population":0,
    "gn:timezone":"Europe/Istanbul",
    "iso:country":"TR",
    "name:tur_x_preferred":[
        "Yukar\u0131 \u00c7anak\u00e7\u0131"
    ],
    "name:und_x_variant":[
        "Yukar\u0131\u00e7anak\u00e7\u0131"
    ],
    "wof:name":"Yukari Canakci",
    "wof:placetype":"locality"
},
  "geometry": {"coordinates":[39.27096,38.35369],"type":"Point"}
}