{
  "type": "Feature",
  "properties": {
    "gn:country":"TR",
    "gn:fcode":"PPL",
    "gn:population":587,
    "iso:country":"TR",
    "name:rus_x_preferred":[
        "Nimetk\u00eby"
    ],
    "name:und_x_variant":[
        "Nimet K\u00f6y\u00fc"
    ],
    "qs:name":"Nimet",
    "qs:photos_9r":0,
    "qs:photos_sr":0,
    "qs:pop_sr":"2",
    "wof:name":"Nimet",
    "wof:placetype":"locality",
    "wof:population":587
},
  "geometry": {"coordinates":[38.72917,36.77389],"type":"Point"}
}