{
  "type": "Feature",
  "properties": {
    "gn:country":"TR",
    "gn:fcode":"PPL",
    "gn:pop":2569,
    "iso:country":"TR",
    "name:eng_x_preferred":[
        "Elbeyli"
    ],
    "name:nld_x_preferred":[
        "Elbeyli"
    ],
    "name:tur_x_preferred":[
        "Elbeyli"
    ],
    "name:vie_x_preferred":[
        "Elbeyli"
    ],
    "qs:name":"Elbeyli",
    "qs:photos_9r":0,
    "qs:photos_sr":0,
    "qs:pop_sr":"4",
    "wd:wordcount":116,
    "wof:name":"Elbeyli",
    "wof:placetype":"locality",
    "wof:population":2569
},
  "geometry": {"coordinates":[29.72472,40.48611],"type":"Point"}
}