{
  "type": "Feature",
  "properties": {
    "gn:admin1_code":"82.0",
    "gn:asciiname":"Koprulu",
    "gn:country_code":"TR",
    "gn:dem":1068,
    "gn:feature_class":"P",
    "gn:feature_code":"PPL",
    "gn:name":"K\u00f6pr\u00fcl\u00fc",
    "gn:population":0,
    "gn:timezone":"Europe/Istanbul",
    "iso:country":"TR",
    "wof:name":"Koprulu",
    "wof:placetype":"locality"
},
  "geometry": {"coordinates":[33.28629,40.77919],"type":"Point"}
}