{
  "type": "Feature",
  "properties": {
    "gn:admin1_code":"19.0",
    "gn:asciiname":"Coprasik",
    "gn:country_code":"TR",
    "gn:dem":1077,
    "gn:feature_class":"P",
    "gn:feature_code":"PPL",
    "gn:name":"\u00c7opra\u015f\u0131k",
    "gn:population":0,
    "gn:timezone":"Europe/Istanbul",
    "iso:country":"TR",
    "name:und_x_variant":[
        "\u00c7apra\u015f\u0131k",
        "\u00c7opra\u015f\u0131k"
    ],
    "wof:name":"Coprasik",
    "wof:placetype":"locality"
},
  "geometry": {"coordinates":[35.07784,40.18019],"type":"Point"}
}