{
  "type": "Feature",
  "properties": {
    "gn:admin1_code":"48",
    "gn:asciiname":"Bagdamlari",
    "gn:country_code":"TR",
    "gn:dem":315,
    "gn:feature_class":"P",
    "gn:feature_code":"PPL",
    "gn:name":"Ba\u011fdamlar\u0131",
    "gn:population":0,
    "gn:timezone":"Europe/Istanbul",
    "iso:country":"TR",
    "name:tur_x_preferred":[
        "Ba\u011fdamlar\u0131"
    ],
    "name:tur_x_variant":[
        "Karadam"
    ],
    "wof:name":"Bagdamlari",
    "wof:placetype":"locality"
},
  "geometry": {"coordinates":[27.87154,37.14918],"type":"Point"}
}