{
  "type": "Feature",
  "properties": {
    "gn:admin1_code":"23.0",
    "gn:asciiname":"Yukari Demirli",
    "gn:country_code":"TR",
    "gn:dem":1829,
    "gn:feature_class":"P",
    "gn:feature_code":"PPL",
    "gn:name":"Yukar\u0131 Demirli",
    "gn:population":0,
    "gn:timezone":"Europe/Istanbul",
    "iso:country":"TR",
    "name:und_x_variant":[
        "Yukar\u0131 Demirli",
        "Yukar\u0131 Demirci"
    ],
    "wof:name":"Yukari Demirli",
    "wof:placetype":"locality"
},
  "geometry": {"coordinates":[40.18308,38.8745],"type":"Point"}
}