{
  "type": "Feature",
  "properties": {
    "gn:admin1_code":"54.0",
    "gn:asciiname":"Alanduzu",
    "gn:country_code":"TR",
    "gn:dem":101,
    "gn:feature_class":"P",
    "gn:feature_code":"PPL",
    "gn:name":"Aland\u00fcz\u00fc",
    "gn:population":0,
    "gn:timezone":"Europe/Istanbul",
    "iso:country":"TR",
    "name:tur_x_preferred":[
        "Aland\u00fcz\u00fc"
    ],
    "wof:name":"Alanduzu",
    "wof:placetype":"locality"
},
  "geometry": {"coordinates":[30.28006,40.83606],"type":"Point"}
}