{
  "type": "Feature",
  "properties": {
    "iso:country":"TR",
    "name:eng_x_preferred":[
        "Caddebostan"
    ],
    "name:tur_x_preferred":[
        "Caddebostan"
    ],
    "wof:name":"Caddebostan",
    "wof:placetype":"neighbourhood"
},
  "geometry": {"coordinates":[29.06261547157874,40.96688165259491],"type":"Point"}
}