{
  "type": "Feature",
  "properties": {
    "gn:admin1_code":"16",
    "gn:asciiname":"Yenikizilelma",
    "gn:country_code":"TR",
    "gn:dem":533,
    "gn:feature_class":"P",
    "gn:feature_code":"PPL",
    "gn:name":"Yenik\u0131z\u0131lelma",
    "gn:population":0,
    "gn:timezone":"Europe/Istanbul",
    "iso:country":"TR",
    "name:tur_x_preferred":[
        "Yenik\u0131z\u0131lelma"
    ],
    "wof:name":"Yenikizilelma",
    "wof:placetype":"locality"
},
  "geometry": {"coordinates":[28.63934,39.92086],"type":"Point"}
}