{
  "type": "Feature",
  "properties": {
    "gn:admin1_code":"71",
    "gn:asciiname":"Alankoy",
    "gn:country_code":"TR",
    "gn:dem":1264,
    "gn:feature_class":"P",
    "gn:feature_code":"PPL",
    "gn:name":"Alank\u00f6y",
    "gn:population":0,
    "gn:timezone":"Europe/Istanbul",
    "iso:country":"TR",
    "name:und_x_variant":[
        "Alank\u00f6y\u00fc",
        "Alan",
        "Alank\u00f6y"
    ],
    "wof:name":"Alankoy",
    "wof:placetype":"locality"
},
  "geometry": {"coordinates":[32.40215999999999,37.36185],"type":"Point"}
}