{
  "type": "Feature",
  "properties": {
    "gn:country":"TR",
    "gn:fcode":"PPL",
    "gn:population":1476,
    "iso:country":"TR",
    "name:ceb_x_preferred":[
        "Dedek\u00f6y"
    ],
    "name:tur_x_preferred":[
        "Dedek\u00f6y"
    ],
    "qs:name":"Dedek\u00f6y",
    "qs:photos_9r":0,
    "qs:photos_sr":0,
    "qs:pop_sr":"3",
    "wd:wordcount":20,
    "wof:name":"Dedek\u00f6y",
    "wof:placetype":"locality",
    "wof:population":1476
},
  "geometry": {"coordinates":[35.04249,40.74752],"type":"Point"}
}