{
  "type": "Feature",
  "properties": {
    "gn:admin1_code":"65.0",
    "gn:asciiname":"Kelle",
    "gn:country_code":"TR",
    "gn:dem":2195,
    "gn:feature_class":"P",
    "gn:feature_code":"PPL",
    "gn:name":"Kelle",
    "gn:population":0,
    "gn:timezone":"Europe/Istanbul",
    "iso:country":"TR",
    "name:tur_x_preferred":[
        "Kelle"
    ],
    "wof:name":"Kelle",
    "wof:placetype":"locality"
},
  "geometry": {"coordinates":[43.64587,38.86862],"type":"Point"}
}