{
  "type": "Feature",
  "properties": {
    "gn:admin1_code":"58",
    "gn:asciiname":"Caypinar",
    "gn:cc2":"TR",
    "gn:country_code":"TR",
    "gn:dem":1479,
    "gn:feature_class":"P",
    "gn:feature_code":"PPL",
    "gn:name":"\u00c7ayp\u0131nar",
    "gn:population":0,
    "gn:timezone":"Europe/Istanbul",
    "iso:country":"TR",
    "name:und_x_variant":[
        "Karaibo",
        "\u00c7ayp\u0131nar"
    ],
    "wof:name":"Caypinar",
    "wof:placetype":"locality"
},
  "geometry": {"coordinates":[37.78333,39.75],"type":"Point"}
}