{
  "type": "Feature",
  "properties": {
    "gn:admin1_code":"65",
    "gn:asciiname":"Kecan",
    "gn:country_code":"TR",
    "gn:dem":2426,
    "gn:feature_class":"P",
    "gn:feature_code":"PPL",
    "gn:name":"Ke\u00e7an",
    "gn:population":0,
    "gn:timezone":"Europe/Istanbul",
    "iso:country":"TR",
    "wof:name":"Kecan",
    "wof:placetype":"locality"
},
  "geometry": {"coordinates":[43.61667,39.18333],"type":"Point"}
}