{
  "type": "Feature",
  "properties": {
    "gn:admin1_code":"86.0",
    "gn:asciiname":"Nebioglu",
    "gn:country_code":"TR",
    "gn:dem":2038,
    "gn:feature_class":"P",
    "gn:feature_code":"PPL",
    "gn:name":"Nebio\u011flu",
    "gn:population":0,
    "gn:timezone":"Europe/Istanbul",
    "iso:country":"TR",
    "name:msa_x_preferred":[
        "Nebio\u011flu"
    ],
    "name:tur_x_preferred":[
        "Nebio\u011flu"
    ],
    "name:vie_x_preferred":[
        "Nebio\u011flu"
    ],
    "wof:name":"Nebioglu",
    "wof:placetype":"locality"
},
  "geometry": {"coordinates":[42.92219,40.96731],"type":"Point"}
}