{
  "type": "Feature",
  "properties": {
    "gn:admin1_code":"13",
    "gn:asciiname":"Uzunyar",
    "gn:country_code":"TR",
    "gn:dem":1089,
    "gn:feature_class":"P",
    "gn:feature_code":"PPL",
    "gn:name":"Uzunyar",
    "gn:population":0,
    "gn:timezone":"Europe/Istanbul",
    "iso:country":"TR",
    "name:tur_x_preferred":[
        "Uzunyar"
    ],
    "name:und_x_variant":[
        "Kelh\u00fck"
    ],
    "wof:name":"Uzunyar",
    "wof:placetype":"locality"
},
  "geometry": {"coordinates":[41.80603,38.3401],"type":"Point"}
}