{
  "type": "Feature",
  "properties": {
    "gn:admin1_code":"68.0",
    "gn:asciiname":"Akcatas",
    "gn:country_code":"TR",
    "gn:dem":1235,
    "gn:feature_class":"P",
    "gn:feature_code":"PPL",
    "gn:name":"Ak\u00e7ata\u015f",
    "gn:population":0,
    "gn:timezone":"Europe/Istanbul",
    "iso:country":"TR",
    "wof:name":"Akcatas",
    "wof:placetype":"locality"
},
  "geometry": {"coordinates":[33.3024,40.20185],"type":"Point"}
}