{
  "type": "Feature",
  "properties": {
    "gn:admin1_code":"07",
    "gn:asciiname":"Tilkiler",
    "gn:country_code":"TR",
    "gn:dem":161,
    "gn:feature_class":"P",
    "gn:feature_code":"PPL",
    "gn:name":"Tilkiler",
    "gn:population":0,
    "gn:timezone":"Europe/Istanbul",
    "iso:country":"TR",
    "wof:name":"Tilkiler",
    "wof:placetype":"locality"
},
  "geometry": {"coordinates":[31.48382,36.92522],"type":"Point"}
}