{
  "type": "Feature",
  "properties": {
    "gn:admin1_code":"02",
    "gn:asciiname":"Pinaryayla",
    "gn:country_code":"TR",
    "gn:dem":959,
    "gn:feature_class":"P",
    "gn:feature_code":"PPL",
    "gn:name":"P\u0131naryayla",
    "gn:population":0,
    "gn:timezone":"Europe/Istanbul",
    "iso:country":"TR",
    "name:und_x_variant":[
        "Artan",
        "P\u0131naryayla"
    ],
    "wof:name":"Pinaryayla",
    "wof:placetype":"locality"
},
  "geometry": {"coordinates":[38.45938,37.89676],"type":"Point"}
}