{
  "type": "Feature",
  "properties": {
    "gn:admin1_code":"66",
    "gn:asciiname":"Darica",
    "gn:country_code":"TR",
    "gn:dem":1072,
    "gn:feature_class":"P",
    "gn:feature_code":"PPL",
    "gn:name":"Dar\u0131ca",
    "gn:population":0,
    "gn:timezone":"Europe/Istanbul",
    "iso:country":"TR",
    "name:und_x_variant":[
        "Dar\u0131c\u0131",
        "Dar\u0131ca"
    ],
    "wof:name":"Darica",
    "wof:placetype":"locality"
},
  "geometry": {"coordinates":[35.01902,39.97177],"type":"Point"}
}