{
  "type": "Feature",
  "properties": {
    "gn:country":"TR",
    "gn:fcode":"PPLA2",
    "gn:pop":6450,
    "iso:country":"TR",
    "name:deu_x_preferred":[
        "Dazk\u0131r\u0131"
    ],
    "name:diq_x_preferred":[
        "Dazk\u0131r\u0131"
    ],
    "name:eng_x_preferred":[
        "Dazk\u0131r\u0131"
    ],
    "name:eus_x_preferred":[
        "Dazkere"
    ],
    "name:fra_x_preferred":[
        "Dazk\u0131r\u0131"
    ],
    "name:ita_x_preferred":[
        "Distretto di Dazk\u0131r\u0131"
    ],
    "name:mrj_x_preferred":[
        "\u0414\u0430\u0437\u043a\u044b\u0440\u044b"
    ],
    "name:msa_x_preferred":[
        "Dazk\u0131r\u0131"
    ],
    "name:nan_x_preferred":[
        "Dazk\u0131r\u0131"
    ],
    "name:nld_x_preferred":[
        "Dazk\u0131r\u0131"
    ],
    "name:nob_x_preferred":[
        "Dazk\u0131r\u0131"
    ],
    "name:pnb_x_preferred":[
        "\u0636\u0644\u0639 \u0688\u0627\u0632\u06a9\u0631\u06cc"
    ],
    "name:ron_x_preferred":[
        "Dazk\u0131r\u0131"
    ],
    "name:swa_x_preferred":[
        "Dazk\u0131r\u0131"
    ],
    "name:tur_x_preferred":[
        "Dazk\u0131r\u0131"
    ],
    "name:unk_x_variant":[
        "Tazk\u0131r\u0131"
    ],
    "name:urd_x_preferred":[
        "\u062f\u0627\u0632\u06a9\u06cc\u0631\u06cc"
    ],
    "name:vie_x_preferred":[
        "Dazk\u0131r\u0131"
    ],
    "qs:name":"Dazk\u0131r\u0131",
    "qs:photos_9r":0,
    "qs:photos_sr":0,
    "qs:pop_sr":"5",
    "wd:wordcount":278,
    "wof:name":"Dazk\u0131r\u0131",
    "wof:placetype":"locality",
    "wof:population":6450
},
  "geometry": {"coordinates":[29.86056,37.91861],"type":"Point"}
}