{
  "type": "Feature",
  "properties": {
    "gn:admin1_code":"8.0",
    "gn:asciiname":"Germicek",
    "gn:country_code":"TR",
    "gn:dem":2182,
    "gn:feature_class":"P",
    "gn:feature_code":"PPL",
    "gn:name":"Germicek",
    "gn:population":0,
    "gn:timezone":"Europe/Istanbul",
    "iso:country":"TR",
    "wof:name":"Germicek",
    "wof:placetype":"locality"
},
  "geometry": {"coordinates":[42.33333,40.95],"type":"Point"}
}