{
  "type": "Feature",
  "properties": {
    "gn:admin1_code":"62",
    "gn:asciiname":"Cukurkoy",
    "gn:country_code":"TR",
    "gn:dem":1322,
    "gn:feature_class":"P",
    "gn:feature_code":"PPL",
    "gn:name":"\u00c7ukurk\u00f6y",
    "gn:population":0,
    "gn:timezone":"Europe/Istanbul",
    "iso:country":"TR",
    "name:und_x_variant":[
        "\u00c7ukur",
        "\u00c7ukurk\u00f6y"
    ],
    "wof:name":"Cukurkoy",
    "wof:placetype":"locality"
},
  "geometry": {"coordinates":[39.70121,39.1052],"type":"Point"}
}