{
  "type": "Feature",
  "properties": {
    "iso:country":"TR",
    "name:eng_x_preferred":[
        "Orcunlu"
    ],
    "name:tur_x_preferred":[
        "\u00d6rc\u00fcnl\u00fc"
    ],
    "wof:name":"Orcunlu",
    "wof:placetype":"neighbourhood"
},
  "geometry": {"coordinates":[28.52491433050693,41.22505748319899],"type":"Point"}
}