{
  "type": "Feature",
  "properties": {
    "gn:admin1_code":"45",
    "gn:asciiname":"Zeytinliova",
    "gn:country_code":"TR",
    "gn:dem":236,
    "gn:feature_class":"P",
    "gn:feature_code":"PPLA3",
    "gn:name":"Zeytinliova",
    "gn:population":4905,
    "gn:timezone":"Europe/Istanbul",
    "iso:country":"TR",
    "name:ceb_x_preferred":[
        "Zeytinliova"
    ],
    "name:tur_x_preferred":[
        "Zeytinliova"
    ],
    "name:und_x_variant":[
        "Palamut",
        "Yavak\u00f6y",
        "Yayak\u00f6y",
        "Zeytinliova"
    ],
    "name:vie_x_preferred":[
        "Zeytinliba\u011f"
    ],
    "wof:name":"Zeytinliova",
    "wof:placetype":"locality",
    "wof:population":4905
},
  "geometry": {"coordinates":[27.67635,38.99118],"type":"Point"}
}