{
  "type": "Feature",
  "properties": {
    "gn:admin1_code":"26",
    "gn:asciiname":"Ertem Mahallesi",
    "gn:country_code":"TR",
    "gn:dem":1172,
    "gn:feature_class":"P",
    "gn:feature_code":"PPL",
    "gn:name":"Ertem Mahallesi",
    "gn:population":0,
    "gn:timezone":"Europe/Istanbul",
    "iso:country":"TR",
    "wof:name":"Ertem Mahallesi",
    "wof:placetype":"locality"
},
  "geometry": {"coordinates":[30.80596,39.20572],"type":"Point"}
}