{
  "type": "Feature",
  "properties": {
    "gn:admin1_code":"48",
    "gn:asciiname":"Pasali",
    "gn:country_code":"TR",
    "gn:dem":262,
    "gn:feature_class":"P",
    "gn:feature_code":"PPL",
    "gn:name":"Pa\u015fal\u0131",
    "gn:population":0,
    "gn:timezone":"Europe/Istanbul",
    "iso:country":"TR",
    "wof:name":"Pasali",
    "wof:placetype":"locality"
},
  "geometry": {"coordinates":[29.34081,36.7628],"type":"Point"}
}