{
  "type": "Feature",
  "properties": {
    "gn:admin1_code":"63",
    "gn:asciiname":"Karadzhaviran",
    "gn:country_code":"TR",
    "gn:dem":453,
    "gn:feature_class":"P",
    "gn:feature_code":"PPL",
    "gn:name":"Karadzhaviran",
    "gn:population":0,
    "gn:timezone":"Europe/Istanbul",
    "iso:country":"TR",
    "wof:name":"Karadzhaviran",
    "wof:placetype":"locality"
},
  "geometry": {"coordinates":[39.08961,37.14536],"type":"Point"}
}