{
  "type": "Feature",
  "properties": {
    "gn:admin1_code":"91",
    "gn:asciiname":"Cevdetiye",
    "gn:country_code":"TR",
    "gn:dem":66,
    "gn:feature_class":"P",
    "gn:feature_code":"PPL",
    "gn:name":"Cevdetiye",
    "gn:population":0,
    "gn:timezone":"Europe/Istanbul",
    "iso:country":"TR",
    "name:ceb_x_preferred":[
        "Cevdetiye"
    ],
    "name:fas_x_preferred":[
        "\u062c\u0648\u062f\u062a\u06cc\u0647"
    ],
    "name:vie_x_preferred":[
        "Cevdetiye"
    ],
    "wof:name":"Cevdetiye",
    "wof:placetype":"locality"
},
  "geometry": {"coordinates":[36.19639,37.13667],"type":"Point"}
}