{
  "type": "Feature",
  "properties": {
    "gn:admin1_code":"14.0",
    "gn:asciiname":"Surmeli",
    "gn:country_code":"TR",
    "gn:dem":932,
    "gn:feature_class":"P",
    "gn:feature_code":"PPL",
    "gn:name":"S\u00fcrmeli",
    "gn:population":0,
    "gn:timezone":"Europe/Istanbul",
    "iso:country":"TR",
    "wof:name":"Surmeli",
    "wof:placetype":"locality"
},
  "geometry": {"coordinates":[31.2059,40.54294],"type":"Point"}
}