{
  "type": "Feature",
  "properties": {
    "gn:admin1_code":"10",
    "gn:asciiname":"Karlik",
    "gn:country_code":"TR",
    "gn:dem":220,
    "gn:feature_class":"P",
    "gn:feature_code":"PPL",
    "gn:name":"Karl\u0131k",
    "gn:population":0,
    "gn:timezone":"Europe/Istanbul",
    "iso:country":"TR",
    "name:tur_x_preferred":[
        "Karl\u0131k"
    ],
    "wof:name":"Karlik",
    "wof:placetype":"locality"
},
  "geometry": {"coordinates":[27.73531,39.82742],"type":"Point"}
}