{
  "type": "Feature",
  "properties": {
    "gn:admin1_code":"37.0",
    "gn:asciiname":"Gokoren",
    "gn:country_code":"TR",
    "gn:dem":1055,
    "gn:feature_class":"P",
    "gn:feature_code":"PPL",
    "gn:name":"G\u00f6k\u00f6ren",
    "gn:population":0,
    "gn:timezone":"Europe/Istanbul",
    "iso:country":"TR",
    "name:und_x_variant":[
        "G\u00f6kveran",
        "A\u015fa\u011f\u0131 G\u00f6k\u00f6ren",
        "G\u00f6kveren",
        "G\u00f6k\u00f6ren"
    ],
    "wof:name":"Gokoren",
    "wof:placetype":"locality"
},
  "geometry": {"coordinates":[33.14297,41.45585],"type":"Point"}
}