{
  "type": "Feature",
  "properties": {
    "gn:country":"TR",
    "gn:fcode":"PPL",
    "gn:population":2802,
    "iso:country":"TR",
    "name:ara_x_preferred":[
        "\u062f\u0627\u0631\u0627"
    ],
    "name:bul_x_preferred":[
        "\u0414\u0430\u0440\u0430"
    ],
    "name:cat_x_preferred":[
        "Dara"
    ],
    "name:deu_x_preferred":[
        "Dara-Anastasiupolis"
    ],
    "name:ell_x_preferred":[
        "\u0394\u03ac\u03c1\u03b1\u03c2 \u039c\u03b5\u03c3\u03bf\u03c0\u03bf\u03c4\u03b1\u03bc\u03af\u03b1\u03c2"
    ],
    "name:eng_x_preferred":[
        "Dara"
    ],
    "name:fas_x_preferred":[
        "\u0642\u0644\u0639\u0647 \u062f\u0627\u0631\u0627"
    ],
    "name:fin_x_preferred":[
        "Dara"
    ],
    "name:fra_x_preferred":[
        "Dara"
    ],
    "name:heb_x_preferred":[
        "\u05d3\u05e8\u05d0"
    ],
    "name:hrv_x_preferred":[
        "Dara"
    ],
    "name:hye_x_preferred":[
        "\u0534\u0561\u0580\u0561"
    ],
    "name:ind_x_preferred":[
        "Dara"
    ],
    "name:ita_x_preferred":[
        "Dara"
    ],
    "name:jpn_x_preferred":[
        "\u30c0\u30e9"
    ],
    "name:kur_x_preferred":[
        "Dara"
    ],
    "name:nld_x_preferred":[
        "Dara"
    ],
    "name:pol_x_preferred":[
        "Dara"
    ],
    "name:por_x_preferred":[
        "Dara"
    ],
    "name:rus_x_preferred":[
        "\u0414\u0430\u0440\u0430"
    ],
    "name:spa_x_preferred":[
        "Dara"
    ],
    "name:srp_x_preferred":[
        "\u0414\u0430\u0440\u0430"
    ],
    "name:tur_x_preferred":[
        "O\u011fuz"
    ],
    "name:tur_x_variant":[
        "Dara"
    ],
    "name:ukr_x_preferred":[
        "\u0414\u0430\u0440\u0430"
    ],
    "name:yor_x_preferred":[
        "Dara"
    ],
    "name:zho_x_preferred":[
        "\u8fbe\u62c9_(\u7f8e\u7d22\u4e0d\u8fbe\u7c73\u4e9a)"
    ],
    "qs:name":"O\u011fuz",
    "qs:photos_9r":0,
    "qs:photos_sr":0,
    "qs:pop_sr":"4",
    "wd:wordcount":68,
    "wof:name":"O\u011fuz",
    "wof:placetype":"locality",
    "wof:population":2802
},
  "geometry": {"coordinates":[40.95437,37.17763],"type":"Point"}
}