{
  "type": "Feature",
  "properties": {
    "gn:admin1_code":"10",
    "gn:asciiname":"Cicekpinar",
    "gn:country_code":"TR",
    "gn:dem":160,
    "gn:feature_class":"P",
    "gn:feature_code":"PPL",
    "gn:name":"\u00c7i\u00e7ekp\u0131nar",
    "gn:population":0,
    "gn:timezone":"Europe/Istanbul",
    "iso:country":"TR",
    "name:tur_x_preferred":[
        "\u00c7i\u00e7ekp\u0131nar"
    ],
    "name:und_x_variant":[
        "Nergiz"
    ],
    "wof:name":"Cicekpinar",
    "wof:placetype":"locality"
},
  "geometry": {"coordinates":[27.93263,39.52917],"type":"Point"}
}