{
  "type": "Feature",
  "properties": {
    "gn:admin1_code":"37.0",
    "gn:asciiname":"Kizilcaelma",
    "gn:country_code":"TR",
    "gn:dem":1233,
    "gn:feature_class":"P",
    "gn:feature_code":"PPL",
    "gn:name":"K\u0131z\u0131lcaelma",
    "gn:population":0,
    "gn:timezone":"Europe/Istanbul",
    "iso:country":"TR",
    "wof:name":"Kizilcaelma",
    "wof:placetype":"locality"
},
  "geometry": {"coordinates":[34.12273,41.6651],"type":"Point"}
}