{
  "type": "Feature",
  "properties": {
    "gn:admin1_code":"55",
    "gn:asciiname":"Guldere",
    "gn:country_code":"TR",
    "gn:dem":162,
    "gn:feature_class":"P",
    "gn:feature_code":"PPL",
    "gn:name":"G\u00fcldere",
    "gn:population":0,
    "gn:timezone":"Europe/Istanbul",
    "iso:country":"TR",
    "name:tur_x_preferred":[
        "G\u00fcldere"
    ],
    "wof:name":"Guldere",
    "wof:placetype":"locality"
},
  "geometry": {"coordinates":[36.55978,41.08447],"type":"Point"}
}