{
  "type": "Feature",
  "properties": {
    "gn:admin1_code":"8.0",
    "gn:asciiname":"Bagcilar",
    "gn:country_code":"TR",
    "gn:dem":792,
    "gn:feature_class":"P",
    "gn:feature_code":"PPL",
    "gn:name":"Ba\u011fc\u0131lar",
    "gn:population":0,
    "gn:timezone":"Europe/Istanbul",
    "iso:country":"TR",
    "name:tur_x_preferred":[
        "Ba\u011fc\u0131lar"
    ],
    "wof:name":"Bagcilar",
    "wof:placetype":"locality"
},
  "geometry": {"coordinates":[42.03602,41.22503],"type":"Point"}
}