{
  "type": "Feature",
  "properties": {
    "gn:admin1_code":"63",
    "gn:asciiname":"Asagi Aysuk",
    "gn:country_code":"TR",
    "gn:dem":412,
    "gn:feature_class":"P",
    "gn:feature_code":"PPL",
    "gn:name":"A\u015fa\u011f\u0131 Ay\u015fuk",
    "gn:population":0,
    "gn:timezone":"Europe/Istanbul",
    "iso:country":"TR",
    "name:tur_x_preferred":[
        "A\u015fa\u011f\u0131 Ay\u015fuk"
    ],
    "wof:name":"Asagi Aysuk",
    "wof:placetype":"locality"
},
  "geometry": {"coordinates":[40.09498,36.93482],"type":"Point"}
}