{
  "type": "Feature",
  "properties": {
    "gn:admin1_code":"21",
    "gn:asciiname":"Alancik",
    "gn:country_code":"TR",
    "gn:dem":946,
    "gn:feature_class":"P",
    "gn:feature_code":"PPL",
    "gn:name":"Alanc\u0131k",
    "gn:population":0,
    "gn:timezone":"Europe/Istanbul",
    "iso:country":"TR",
    "name:tur_x_preferred":[
        "Alanc\u0131k"
    ],
    "name:und_x_variant":[
        "G\u00fchan"
    ],
    "wof:name":"Alancik",
    "wof:placetype":"locality"
},
  "geometry": {"coordinates":[40.26748,37.5255],"type":"Point"}
}