{
  "type": "Feature",
  "properties": {
    "gn:admin1_code":"52.0",
    "gn:asciiname":"Kilicli",
    "gn:country_code":"TR",
    "gn:dem":171,
    "gn:feature_class":"P",
    "gn:feature_code":"PPL",
    "gn:name":"K\u0131l\u0131\u00e7l\u0131",
    "gn:population":0,
    "gn:timezone":"Europe/Istanbul",
    "iso:country":"TR",
    "name:und_x_variant":[
        "K\u0131l\u0131\u00e7l\u0131"
    ],
    "wof:name":"Kilicli",
    "wof:placetype":"locality"
},
  "geometry": {"coordinates":[37.55442,40.99314],"type":"Point"}
}