{
  "type": "Feature",
  "properties": {
    "gn:admin1_code":"02",
    "gn:asciiname":"Eskikoy",
    "gn:country_code":"TR",
    "gn:dem":909,
    "gn:feature_class":"P",
    "gn:feature_code":"PPL",
    "gn:name":"Eskik\u00f6y",
    "gn:population":0,
    "gn:timezone":"Europe/Istanbul",
    "iso:country":"TR",
    "wof:name":"Eskikoy",
    "wof:placetype":"locality"
},
  "geometry": {"coordinates":[37.79082,37.66772],"type":"Point"}
}