{
  "type": "Feature",
  "properties": {
    "gn:admin1_code":"72.0",
    "gn:asciiname":"Harbaomer",
    "gn:country_code":"TR",
    "gn:dem":734,
    "gn:feature_class":"P",
    "gn:feature_code":"PPL",
    "gn:name":"Harba\u00f6mer",
    "gn:population":0,
    "gn:timezone":"Europe/Istanbul",
    "iso:country":"TR",
    "wof:name":"Harbaomer",
    "wof:placetype":"locality"
},
  "geometry": {"coordinates":[41.09278,37.19417],"type":"Point"}
}