{
  "type": "Feature",
  "properties": {
    "gn:admin1_code":"89",
    "gn:asciiname":"Demirciler",
    "gn:country_code":"TR",
    "gn:dem":1311,
    "gn:feature_class":"P",
    "gn:feature_code":"PPL",
    "gn:name":"Demirciler",
    "gn:population":0,
    "gn:timezone":"Europe/Istanbul",
    "iso:country":"TR",
    "wof:name":"Demirciler",
    "wof:placetype":"locality"
},
  "geometry": {"coordinates":[32.39596,40.92141],"type":"Point"}
}