{
  "type": "Feature",
  "properties": {
    "gn:admin1_code":"23",
    "gn:asciiname":"Pilavtepe",
    "gn:country_code":"TR",
    "gn:dem":1447,
    "gn:feature_class":"P",
    "gn:feature_code":"PPL",
    "gn:name":"Pilavtepe",
    "gn:population":0,
    "gn:timezone":"Europe/Istanbul",
    "iso:country":"TR",
    "name:tur_x_preferred":[
        "Pilavtepe"
    ],
    "wof:name":"Pilavtepe",
    "wof:placetype":"locality"
},
  "geometry": {"coordinates":[40.17803,39.135],"type":"Point"}
}