{
  "type": "Feature",
  "properties": {
    "gn:admin1_code":"61.0",
    "gn:asciiname":"Keler",
    "gn:country_code":"TR",
    "gn:dem":408,
    "gn:feature_class":"P",
    "gn:feature_code":"PPL",
    "gn:name":"Keler",
    "gn:population":0,
    "gn:timezone":"Europe/Istanbul",
    "iso:country":"TR",
    "name:ces_x_preferred":[
        "Keler"
    ],
    "name:deu_x_preferred":[
        "Keler"
    ],
    "name:und_x_variant":[
        "Keller",
        "Keler"
    ],
    "wof:name":"Keler",
    "wof:placetype":"locality"
},
  "geometry": {"coordinates":[40.43883,40.87488],"type":"Point"}
}