{
  "type": "Feature",
  "properties": {
    "gn:admin1_code":"48",
    "gn:asciiname":"Haciimamlar",
    "gn:country_code":"TR",
    "gn:dem":506,
    "gn:feature_class":"P",
    "gn:feature_code":"PPL",
    "gn:name":"Hac\u0131imamlar",
    "gn:population":0,
    "gn:timezone":"Europe/Istanbul",
    "iso:country":"TR",
    "wof:name":"Haciimamlar",
    "wof:placetype":"locality"
},
  "geometry": {"coordinates":[27.89722,37.44167],"type":"Point"}
}