{
  "type": "Feature",
  "properties": {
    "gn:admin1_code":"71",
    "gn:asciiname":"Yaglibayat",
    "gn:country_code":"TR",
    "gn:dem":1083,
    "gn:feature_class":"P",
    "gn:feature_code":"PPL",
    "gn:name":"Ya\u011fl\u0131bayat",
    "gn:population":0,
    "gn:timezone":"Europe/Istanbul",
    "iso:country":"TR",
    "wof:name":"Yaglibayat",
    "wof:placetype":"locality"
},
  "geometry": {"coordinates":[33.11268,37.97148],"type":"Point"}
}