{
  "type": "Feature",
  "properties": {
    "gn:admin1_code":"31.0",
    "gn:asciiname":"Karaagac",
    "gn:country_code":"TR",
    "gn:dem":21,
    "gn:feature_class":"P",
    "gn:feature_code":"PPL",
    "gn:name":"Karaa\u011fa\u00e7",
    "gn:population":0,
    "gn:timezone":"Europe/Istanbul",
    "iso:country":"TR",
    "name:ceb_x_preferred":[
        "Karaa\u011fa\u00e7"
    ],
    "name:fas_x_preferred":[
        "\u0642\u0631\u0647\u200c\u0622\u063a\u0627\u0686"
    ],
    "name:sco_x_preferred":[
        "Karaa\u011fa\u00e7"
    ],
    "name:tur_x_preferred":[
        "Karaa\u011fa\u00e7"
    ],
    "name:und_x_variant":[
        "Karaa\u011fa\u00e7"
    ],
    "name:urd_x_preferred":[
        "\u0642\u0631\u06c1 \u0622\u063a\u0627\u0686"
    ],
    "name:vie_x_preferred":[
        "Karaa\u011fa\u00e7"
    ],
    "wof:name":"Karaagac",
    "wof:placetype":"locality"
},
  "geometry": {"coordinates":[36.12277,36.55748],"type":"Point"}
}