{
  "type": "Feature",
  "properties": {
    "gn:admin1_code":"41.0",
    "gn:asciiname":"Muallim",
    "gn:country_code":"TR",
    "gn:dem":187,
    "gn:feature_class":"P",
    "gn:feature_code":"PPL",
    "gn:name":"Muallim",
    "gn:population":0,
    "gn:timezone":"Europe/Istanbul",
    "iso:country":"TR",
    "name:und_x_variant":[
        "Muallimler",
        "Muallim"
    ],
    "wof:name":"Muallim",
    "wof:placetype":"locality"
},
  "geometry": {"coordinates":[29.49291,40.79298],"type":"Point"}
}