{
  "type": "Feature",
  "properties": {
    "gn:admin1_code":"22.0",
    "gn:asciiname":"Karasati",
    "gn:country_code":"TR",
    "gn:dem":98,
    "gn:feature_class":"P",
    "gn:feature_code":"PPL",
    "gn:name":"Karasat\u0131",
    "gn:population":0,
    "gn:timezone":"Europe/Istanbul",
    "iso:country":"TR",
    "name:tur_x_preferred":[
        "Karasat\u0131"
    ],
    "wof:name":"Karasati",
    "wof:placetype":"locality"
},
  "geometry": {"coordinates":[26.69374,40.96409],"type":"Point"}
}