{
  "type": "Feature",
  "properties": {
    "gn:admin1_code":"71",
    "gn:asciiname":"Kizilcakir",
    "gn:country_code":"TR",
    "gn:dem":1323,
    "gn:feature_class":"P",
    "gn:feature_code":"PPL",
    "gn:name":"K\u0131z\u0131l\u00e7ak\u0131r",
    "gn:population":0,
    "gn:timezone":"Europe/Istanbul",
    "iso:country":"TR",
    "wof:name":"Kizilcakir",
    "wof:placetype":"locality"
},
  "geometry": {"coordinates":[32.57549,37.17724000000001],"type":"Point"}
}