{
  "type": "Feature",
  "properties": {
    "gn:admin1_code":"25.0",
    "gn:asciiname":"Tutmac",
    "gn:country_code":"TR",
    "gn:dem":1866,
    "gn:feature_class":"P",
    "gn:feature_code":"PPL",
    "gn:name":"Tutma\u00e7",
    "gn:population":0,
    "gn:timezone":"Europe/Istanbul",
    "iso:country":"TR",
    "name:tur_x_preferred":[
        "Tutma\u00e7"
    ],
    "wof:name":"Tutmac",
    "wof:placetype":"locality"
},
  "geometry": {"coordinates":[41.71353,40.43959],"type":"Point"}
}