{
  "type": "Feature",
  "properties": {
    "gn:admin1_code":"26",
    "gn:asciiname":"Yukari Doganoglu",
    "gn:country_code":"TR",
    "gn:dem":887,
    "gn:feature_class":"P",
    "gn:feature_code":"PPL",
    "gn:name":"Yukar\u0131 Do\u011fano\u011flu",
    "gn:population":0,
    "gn:timezone":"Europe/Istanbul",
    "iso:country":"TR",
    "name:und_x_variant":[
        "Yukar\u0131 Do\u011fano\u011flu",
        "Do\u011fano\u011flu"
    ],
    "wof:name":"Yukari Doganoglu",
    "wof:placetype":"locality"
},
  "geometry": {"coordinates":[31.21444,39.82528],"type":"Point"}
}