{
  "type": "Feature",
  "properties": {
    "gn:country":"TR",
    "gn:fcode":"PPL",
    "gn:pop":0,
    "iso:country":"TR",
    "name:deu_x_preferred":[
        "Yeni"
    ],
    "name:eng_x_preferred":[
        "Yeni"
    ],
    "name:rus_x_preferred":[
        "Yenik\u00eby"
    ],
    "name:unk_x_variant":[
        "Hazeylan"
    ],
    "qs:name":"Yeni",
    "qs:name_adm0":"Turkey",
    "qs:name_adm1":"Gaziantep",
    "qs:photos":4,
    "qs:photos_1k":1,
    "qs:photos_9k":1,
    "qs:photos_9r":1,
    "qs:photos_all":4,
    "qs:photos_sr":1,
    "qs:placetype":"Suburb",
    "qs:pop_sr":"0",
    "wd:wordcount":54,
    "wof:name":"Yeni",
    "wof:placetype":"neighbourhood",
    "wof:population":0
},
  "geometry": {"coordinates":[37.00861,36.81083],"type":"Point"}
}