{
  "type": "Feature",
  "properties": {
    "gn:admin1_code":"57.0",
    "gn:asciiname":"Yumakli",
    "gn:country_code":"TR",
    "gn:dem":846,
    "gn:feature_class":"P",
    "gn:feature_code":"PPL",
    "gn:name":"Yumakl\u0131",
    "gn:population":0,
    "gn:timezone":"Europe/Istanbul",
    "iso:country":"TR",
    "wof:name":"Yumakli",
    "wof:placetype":"locality"
},
  "geometry": {"coordinates":[35.27855,41.5214],"type":"Point"}
}