{
  "type": "Feature",
  "properties": {
    "gn:admin1_code":"57.0",
    "gn:asciiname":"Huseyinbey",
    "gn:country_code":"TR",
    "gn:dem":214,
    "gn:feature_class":"P",
    "gn:feature_code":"PPL",
    "gn:name":"H\u00fcseyinbey",
    "gn:population":0,
    "gn:timezone":"Europe/Istanbul",
    "iso:country":"TR",
    "name:tur_x_preferred":[
        "H\u00fcseyinbey"
    ],
    "wof:name":"Huseyinbey",
    "wof:placetype":"locality"
},
  "geometry": {"coordinates":[34.65701,41.92368],"type":"Point"}
}