{
  "type": "Feature",
  "properties": {
    "gn:admin1_code":"07",
    "gn:asciiname":"Kepiralani",
    "gn:country_code":"TR",
    "gn:dem":1052,
    "gn:feature_class":"P",
    "gn:feature_code":"PPL",
    "gn:name":"Kepiralan\u0131",
    "gn:population":0,
    "gn:timezone":"Europe/Istanbul",
    "iso:country":"TR",
    "wof:name":"Kepiralani",
    "wof:placetype":"locality"
},
  "geometry": {"coordinates":[30.38333,36.88333],"type":"Point"}
}