{
  "type": "Feature",
  "properties": {
    "gn:admin1_code":"24",
    "gn:asciiname":"Ekinci",
    "gn:country_code":"TR",
    "gn:dem":1708,
    "gn:feature_class":"P",
    "gn:feature_code":"PPL",
    "gn:name":"Ekinci",
    "gn:population":0,
    "gn:timezone":"Europe/Istanbul",
    "iso:country":"TR",
    "name:deu_x_preferred":[
        "Ekinci"
    ],
    "name:tur_x_preferred":[
        "Evci"
    ],
    "name:tur_x_variant":[
        "Ekinci"
    ],
    "name:und_x_variant":[
        "Gi\u00e7\u00fcrdek",
        "Ekince",
        "Ge\u00e7\u00fcrdek",
        "Ekinci"
    ],
    "wof:name":"Ekinci",
    "wof:placetype":"locality"
},
  "geometry": {"coordinates":[39.30018,39.78901],"type":"Point"}
}