{
  "type": "Feature",
  "properties": {
    "gn:admin1_code":"75",
    "gn:asciiname":"Oguzlar",
    "gn:country_code":"TR",
    "gn:dem":1287,
    "gn:feature_class":"P",
    "gn:feature_code":"PPL",
    "gn:name":"O\u011fuzlar",
    "gn:population":0,
    "gn:timezone":"Europe/Istanbul",
    "iso:country":"TR",
    "name:tur_x_preferred":[
        "O\u011fuzlar"
    ],
    "name:und_x_variant":[
        "\u00c7okyatan",
        "\u00c7atin"
    ],
    "wof:name":"Oguzlar",
    "wof:placetype":"locality"
},
  "geometry": {"coordinates":[33.94127,38.66974],"type":"Point"}
}