{
  "type": "Feature",
  "properties": {
    "gn:admin1_code":"35",
    "gn:asciiname":"Umurcali",
    "gn:country_code":"TR",
    "gn:dem":253,
    "gn:feature_class":"P",
    "gn:feature_code":"PPL",
    "gn:name":"Umurcal\u0131",
    "gn:population":0,
    "gn:timezone":"Europe/Istanbul",
    "iso:country":"TR",
    "name:tur_x_preferred":[
        "Umurcal\u0131"
    ],
    "wof:name":"Umurcali",
    "wof:placetype":"locality"
},
  "geometry": {"coordinates":[28.24498,38.19549],"type":"Point"}
}