{
  "type": "Feature",
  "properties": {
    "gn:admin1_code":"25",
    "gn:asciiname":"Kocyayla",
    "gn:country_code":"TR",
    "gn:dem":2073,
    "gn:feature_class":"P",
    "gn:feature_code":"PPL",
    "gn:name":"Ko\u00e7yayla",
    "gn:population":0,
    "gn:timezone":"Europe/Istanbul",
    "iso:country":"TR",
    "name:und_x_variant":[
        "Ko\u00e7yayla",
        "Hirbesor"
    ],
    "wof:name":"Kocyayla",
    "wof:placetype":"locality"
},
  "geometry": {"coordinates":[41.39975,39.51014],"type":"Point"}
}