{
  "type": "Feature",
  "properties": {
    "gn:admin1_code":"71.0",
    "gn:asciiname":"Uckuyu Mahallesi",
    "gn:country_code":"TR",
    "gn:dem":1029,
    "gn:feature_class":"P",
    "gn:feature_code":"PPL",
    "gn:name":"\u00dc\u00e7kuyu Mahallesi",
    "gn:population":0,
    "gn:timezone":"Europe/Istanbul",
    "iso:country":"TR",
    "wof:name":"Uckuyu Mahallesi",
    "wof:placetype":"locality"
},
  "geometry": {"coordinates":[33.25111,37.99675],"type":"Point"}
}