{
  "type": "Feature",
  "properties": {
    "gn:admin1_code":"16",
    "gn:asciiname":"Yenidanisment",
    "gn:country_code":"TR",
    "gn:dem":536,
    "gn:feature_class":"P",
    "gn:feature_code":"PPL",
    "gn:name":"Yenidani\u015fment",
    "gn:population":0,
    "gn:timezone":"Europe/Istanbul",
    "iso:country":"TR",
    "name:tur_x_preferred":[
        "Yenidani\u015fment"
    ],
    "name:und_x_variant":[
        "Dan\u0131\u015fmentcedit"
    ],
    "wof:name":"Yenidanisment",
    "wof:placetype":"locality"
},
  "geometry": {"coordinates":[28.81667,39.88333],"type":"Point"}
}