{
  "type": "Feature",
  "properties": {
    "gn:admin1_code":"04",
    "gn:asciiname":"Mollaali",
    "gn:country_code":"TR",
    "gn:dem":2045,
    "gn:feature_class":"P",
    "gn:feature_code":"PPL",
    "gn:name":"Mollaali",
    "gn:population":0,
    "gn:timezone":"Europe/Istanbul",
    "iso:country":"TR",
    "name:tur_x_preferred":[
        "Mollaali"
    ],
    "wof:name":"Mollaali",
    "wof:placetype":"locality"
},
  "geometry": {"coordinates":[43.14465,39.94335],"type":"Point"}
}