{
  "type": "Feature",
  "properties": {
    "gn:country":"TR",
    "gn:fcode":"PPL",
    "gn:pop":5073,
    "iso:country":"TR",
    "name:unk_x_variant":[
        "Karakoyun"
    ],
    "qs:name":"Karakoyunlu",
    "qs:name_adm0":"Turkey",
    "qs:name_adm1":"I\u011fd\u0131r",
    "qs:photos_9k":1,
    "qs:photos_9r":1,
    "qs:photos_all":2,
    "qs:photos_sr":0,
    "qs:placetype":"Town",
    "qs:pop_sr":"5",
    "wd:wordcount":285,
    "wof:name":"Karakoyunlu",
    "wof:placetype":"locality",
    "wof:population":5073
},
  "geometry": {"coordinates":[43.63014,39.87036],"type":"Point"}
}