{
  "type": "Feature",
  "properties": {
    "gn:country":"TR",
    "gn:fcode":"PPL",
    "gn:population":5073,
    "iso:country":"TR",
    "name:ast_x_preferred":[
        "Karakoyunlu"
    ],
    "name:aze_x_preferred":[
        "Qaraqoyunlu"
    ],
    "name:che_x_preferred":[
        "\u041a\u0430\u0440\u0430\u043a\u043e\u0439\u0443\u043d\u043b\u0443"
    ],
    "name:ckb_x_preferred":[
        "\u062a\u06ce\u0634\u0628\u06d5\u0631\u0648\u0648\u0646"
    ],
    "name:deu_x_preferred":[
        "Karakoyunlu"
    ],
    "name:eng_x_preferred":[
        "Karakoyunlu"
    ],
    "name:fas_x_preferred":[
        "\u0642\u0631\u0627\u0642\u0648\u06cc\u0648\u0646\u0644\u0648"
    ],
    "name:fin_x_preferred":[
        "Karakoyunlu"
    ],
    "name:fra_x_preferred":[
        "Karakoyunlu"
    ],
    "name:heb_x_preferred":[
        "\u05e7\u05e8\u05d0\u05e7\u05d5\u05d9\u05d5\u05e0\u05dc\u05d5"
    ],
    "name:jpn_x_preferred":[
        "\u30ab\u30e9\u30b3\u30e6\u30cc\u30eb"
    ],
    "name:kur_x_preferred":[
        "T\u00ea\u015fber\u00fbn"
    ],
    "name:lav_x_preferred":[
        "Karakojunlu rajons"
    ],
    "name:mrj_x_preferred":[
        "\u041a\u0430\u0440\u0430\u043a\u043e\u044e\u043d\u043b\u0443"
    ],
    "name:msa_x_preferred":[
        "Karakoyunlu"
    ],
    "name:nan_x_preferred":[
        "Karakoyunlu"
    ],
    "name:nld_x_preferred":[
        "Karakoyunlu"
    ],
    "name:nob_x_preferred":[
        "Karakoyunlu"
    ],
    "name:rus_x_preferred":[
        "\u041a\u0430\u0440\u0430\u043a\u043e\u044e\u043d\u043b\u0443"
    ],
    "name:swa_x_preferred":[
        "Karakoyunlu"
    ],
    "name:tat_x_preferred":[
        "\u041a\u0430\u0440\u0430\u043a\u043e\u044e\u043d\u043b\u0443"
    ],
    "name:tur_x_preferred":[
        "Karakoyunlu"
    ],
    "name:und_x_variant":[
        "Karakoyun"
    ],
    "name:urd_x_preferred":[
        "\u0642\u0631\u06c1 \u06a9\u0648\u06cc\u0648\u0646\u0644\u0648"
    ],
    "name:vie_x_preferred":[
        "Karakoyunlu"
    ],
    "name:zho_x_preferred":[
        "\u963f\u62c9\u666e\u52d2"
    ],
    "qs:name":"Karakoyunlu",
    "qs:name_adm0":"Turkey",
    "qs:name_adm1":"I\u011fd\u0131r",
    "qs:photos_9k":1,
    "qs:photos_9r":1,
    "qs:photos_all":2,
    "qs:photos_sr":0,
    "qs:placetype":"Town",
    "qs:pop_sr":"5",
    "wd:wordcount":285,
    "wof:name":"Karakoyunlu",
    "wof:placetype":"locality",
    "wof:population":5073
},
  "geometry": {"coordinates":[43.63014,39.87036],"type":"Point"}
}