{
  "type": "Feature",
  "properties": {
    "gn:admin1_code":"21.0",
    "gn:asciiname":"Bogazkoy",
    "gn:country_code":"TR",
    "gn:dem":870,
    "gn:feature_class":"P",
    "gn:feature_code":"PPL",
    "gn:name":"Bo\u011fazk\u00f6y",
    "gn:population":0,
    "gn:timezone":"Europe/Istanbul",
    "iso:country":"TR",
    "name:tur_x_preferred":[
        "Bo\u011fazk\u00f6y"
    ],
    "wof:name":"Bogazkoy",
    "wof:placetype":"locality"
},
  "geometry": {"coordinates":[40.18752,38.42325],"type":"Point"}
}