{
  "type": "Feature",
  "properties": {
    "gn:admin1_code":"65.0",
    "gn:asciiname":"Taptas",
    "gn:country_code":"TR",
    "gn:dem":2408,
    "gn:feature_class":"P",
    "gn:feature_code":"PPL",
    "gn:name":"Tapta\u015f",
    "gn:population":0,
    "gn:timezone":"Europe/Istanbul",
    "iso:country":"TR",
    "name:tur_x_preferred":[
        "Tapta\u015f"
    ],
    "wof:name":"Taptas",
    "wof:placetype":"locality"
},
  "geometry": {"coordinates":[42.84488,38.0163],"type":"Point"}
}