{
  "type": "Feature",
  "properties": {
    "gn:admin1_code":"2.0",
    "gn:asciiname":"Akkus",
    "gn:country_code":"TR",
    "gn:dem":796,
    "gn:feature_class":"P",
    "gn:feature_code":"PPL",
    "gn:name":"Akku\u015f",
    "gn:population":0,
    "gn:timezone":"Europe/Istanbul",
    "iso:country":"TR",
    "name:tur_x_preferred":[
        "Akku\u015f"
    ],
    "name:und_x_variant":[
        "\u00d6ren"
    ],
    "wof:name":"Akkus",
    "wof:placetype":"locality"
},
  "geometry": {"coordinates":[38.70965,37.87055],"type":"Point"}
}