{
  "type": "Feature",
  "properties": {
    "gn:admin1_code":"14",
    "gn:asciiname":"Gidiris",
    "gn:country_code":"TR",
    "gn:dem":941,
    "gn:feature_class":"P",
    "gn:feature_code":"PPL",
    "gn:name":"Gidiri\u015f",
    "gn:population":0,
    "gn:timezone":"Europe/Istanbul",
    "iso:country":"TR",
    "wof:name":"Gidiris",
    "wof:placetype":"locality"
},
  "geometry": {"coordinates":[31.84454,40.73796],"type":"Point"}
}