{
  "type": "Feature",
  "properties": {
    "gn:admin1_code":"63.0",
    "gn:asciiname":"Tekneli",
    "gn:cc2":"TR",
    "gn:country_code":"TR",
    "gn:dem":373,
    "gn:feature_class":"P",
    "gn:feature_code":"PPL",
    "gn:name":"Tekneli",
    "gn:population":0,
    "gn:timezone":"Europe/Istanbul",
    "iso:country":"TR",
    "name:tur_x_historical":[
        "Curunabuzeyt"
    ],
    "name:tur_x_preferred":[
        "Tekneli"
    ],
    "name:tur_x_variant":[
        "Curunabuzeyt"
    ],
    "name:und_x_variant":[
        "Curunebuzeyt",
        "Dzhurunebuzeyt"
    ],
    "wof:name":"Tekneli",
    "wof:placetype":"locality"
},
  "geometry": {"coordinates":[39.09722,36.89139],"type":"Point"}
}