{
  "type": "Feature",
  "properties": {
    "gn:country":"TR",
    "gn:fcode":"PPL",
    "gn:pop":0,
    "iso:country":"TR",
    "qs:name":"T\u00fcrk\u00f6z\u00fc",
    "qs:name_adm0":"Turkey",
    "qs:name_adm1":"Bal\u0131kesir",
    "qs:photos_9r":0,
    "qs:photos_sr":0,
    "qs:placetype":"Town",
    "qs:pop_sr":"0",
    "wof:name":"T\u00fcrk\u00f6z\u00fc",
    "wof:placetype":"locality",
    "wof:population":0
},
  "geometry": {"coordinates":[26.83445,39.29095],"type":"Point"}
}