{
  "type": "Feature",
  "properties": {
    "gn:admin1_code":"89",
    "gn:asciiname":"Dereagil",
    "gn:country_code":"TR",
    "gn:dem":991,
    "gn:feature_class":"P",
    "gn:feature_code":"PPL",
    "gn:name":"Derea\u011f\u0131l",
    "gn:population":0,
    "gn:timezone":"Europe/Istanbul",
    "iso:country":"TR",
    "wof:name":"Dereagil",
    "wof:placetype":"locality"
},
  "geometry": {"coordinates":[32.4984,41.01252],"type":"Point"}
}