{
  "type": "Feature",
  "properties": {
    "gn:admin1_code":"55.0",
    "gn:asciiname":"Calkoy",
    "gn:country_code":"TR",
    "gn:dem":295,
    "gn:feature_class":"P",
    "gn:feature_code":"PPL",
    "gn:name":"\u00c7alk\u00f6y",
    "gn:population":0,
    "gn:timezone":"Europe/Istanbul",
    "iso:country":"TR",
    "name:tur_x_preferred":[
        "\u00c7alk\u00f6y"
    ],
    "wof:name":"Calkoy",
    "wof:placetype":"locality"
},
  "geometry": {"coordinates":[35.5045,41.15154],"type":"Point"}
}