{
  "type": "Feature",
  "properties": {
    "gn:admin1_code":"55.0",
    "gn:asciiname":"Karadoruk",
    "gn:country_code":"TR",
    "gn:dem":458,
    "gn:feature_class":"P",
    "gn:feature_code":"PPL",
    "gn:name":"Karadoruk",
    "gn:population":0,
    "gn:timezone":"Europe/Istanbul",
    "iso:country":"TR",
    "name:und_x_variant":[
        "Hamidiye",
        "Karadoruk"
    ],
    "wof:name":"Karadoruk",
    "wof:placetype":"locality"
},
  "geometry": {"coordinates":[35.23704,41.1849],"type":"Point"}
}