{
  "type": "Feature",
  "properties": {
    "gn:admin1_code":"37.0",
    "gn:asciiname":"Alancik",
    "gn:country_code":"TR",
    "gn:dem":794,
    "gn:feature_class":"P",
    "gn:feature_code":"PPL",
    "gn:name":"Alanc\u0131k",
    "gn:population":0,
    "gn:timezone":"Europe/Istanbul",
    "iso:country":"TR",
    "name:tur_x_preferred":[
        "\u00d6rencik"
    ],
    "name:und_x_variant":[
        "Bezez",
        "Alanc\u0131k"
    ],
    "wof:name":"Alancik",
    "wof:placetype":"locality"
},
  "geometry": {"coordinates":[33.19824000000001,41.83512],"type":"Point"}
}