{
  "type": "Feature",
  "properties": {
    "gn:country":"TR",
    "gn:fcode":"PPL",
    "gn:pop":326,
    "iso:country":"TR",
    "name:rus_x_preferred":[
        "Kharbetyul\u2019-Khasani"
    ],
    "name:tur_x_preferred":[
        "Karaman"
    ],
    "name:tur_x_variant":[
        "Harbet\u00fclhasani",
        "Kahraman"
    ],
    "qs:name":"Karaman",
    "qs:photos_9r":0,
    "qs:photos_sr":0,
    "qs:pop_sr":"2",
    "wd:wordcount":664,
    "wof:name":"Karaman",
    "wof:placetype":"locality",
    "wof:population":326
},
  "geometry": {"coordinates":[38.96028,36.98528],"type":"Point"}
}