{
  "type": "Feature",
  "properties": {
    "gn:admin1_code":"31.0",
    "gn:asciiname":"Asagi Burnaz",
    "gn:country_code":"TR",
    "gn:dem":7,
    "gn:feature_class":"P",
    "gn:feature_code":"PPL",
    "gn:name":"A\u015fa\u011f\u0131 Burnaz",
    "gn:population":0,
    "gn:timezone":"Europe/Istanbul",
    "iso:country":"TR",
    "name:und_x_variant":[
        "Yanykdegirmen",
        "Yan\u0131kde\u011firmen",
        "A\u015fa\u011f\u0131 Burnaz"
    ],
    "wof:name":"Asagi Burnaz",
    "wof:placetype":"locality"
},
  "geometry": {"coordinates":[36.07264,36.92747],"type":"Point"}
}