{
  "type": "Feature",
  "properties": {
    "gn:admin1_code":"83.0",
    "gn:asciiname":"Kosk",
    "gn:country_code":"TR",
    "gn:dem":962,
    "gn:feature_class":"P",
    "gn:feature_code":"PPL",
    "gn:name":"K\u00f6\u015fk",
    "gn:population":0,
    "gn:timezone":"Europe/Istanbul",
    "iso:country":"TR",
    "wof:name":"Kosk",
    "wof:placetype":"locality"
},
  "geometry": {"coordinates":[37.61533,37.35144],"type":"Point"}
}