{
  "type": "Feature",
  "properties": {
    "gn:admin1_code":"93",
    "gn:asciiname":"Yukariakcaoren",
    "gn:country_code":"TR",
    "gn:dem":677,
    "gn:feature_class":"P",
    "gn:feature_code":"PPL",
    "gn:name":"Yukar\u0131ak\u00e7a\u00f6ren",
    "gn:population":0,
    "gn:timezone":"Europe/Istanbul",
    "iso:country":"TR",
    "wof:name":"Yukariakcaoren",
    "wof:placetype":"locality"
},
  "geometry": {"coordinates":[31.30565,40.95068],"type":"Point"}
}