{
  "type": "Feature",
  "properties": {
    "gn:admin1_code":"16.0",
    "gn:asciiname":"Tuzakli",
    "gn:country_code":"TR",
    "gn:dem":681,
    "gn:feature_class":"P",
    "gn:feature_code":"PPL",
    "gn:name":"Tuzakl\u0131",
    "gn:population":0,
    "gn:timezone":"Europe/Istanbul",
    "iso:country":"TR",
    "name:tur_x_preferred":[
        "Tuzakl\u0131"
    ],
    "wof:name":"Tuzakli",
    "wof:placetype":"locality"
},
  "geometry": {"coordinates":[28.99989,40.10779],"type":"Point"}
}