{
  "type": "Feature",
  "properties": {
    "gn:admin1_code":"86.0",
    "gn:asciiname":"Yukari Gundes",
    "gn:country_code":"TR",
    "gn:dem":2114,
    "gn:feature_class":"P",
    "gn:feature_code":"PPL",
    "gn:name":"Yukar\u0131 G\u00fcnde\u015f",
    "gn:population":0,
    "gn:timezone":"Europe/Istanbul",
    "iso:country":"TR",
    "name:tur_x_preferred":[
        "Yukar\u0131 G\u00fcnde\u015f"
    ],
    "name:und_x_variant":[
        "Topkaya",
        "Yukar\u0131 G\u00fcnda\u015f",
        "Yukar\u0131g\u00fcnta\u015f",
        "Yukar\u0131 Guyunda",
        "Yukar\u0131g\u00fcnde\u015f"
    ],
    "wof:name":"Yukari Gundes",
    "wof:placetype":"locality"
},
  "geometry": {"coordinates":[42.81725,41.37487],"type":"Point"}
}