{
  "type": "Feature",
  "properties": {
    "gn:admin1_code":"23",
    "gn:asciiname":"Dolkoy",
    "gn:country_code":"TR",
    "gn:dem":1455,
    "gn:feature_class":"P",
    "gn:feature_code":"PPL",
    "gn:name":"Dolk\u00f6y",
    "gn:population":0,
    "gn:timezone":"Europe/Istanbul",
    "iso:country":"TR",
    "name:tur_x_preferred":[
        "Dolk\u00f6y"
    ],
    "wof:name":"Dolkoy",
    "wof:placetype":"locality"
},
  "geometry": {"coordinates":[39.88333,38.51667],"type":"Point"}
}