{
  "type": "Feature",
  "properties": {
    "gn:admin1_code":"4.0",
    "gn:asciiname":"Akdilek",
    "gn:country_code":"TR",
    "gn:dem":1795,
    "gn:feature_class":"P",
    "gn:feature_code":"PPL",
    "gn:name":"Akdilek",
    "gn:population":0,
    "gn:timezone":"Europe/Istanbul",
    "iso:country":"TR",
    "name:und_x_variant":[
        "K\u00f6zk\u00f6y",
        "Akdilek"
    ],
    "wof:name":"Akdilek",
    "wof:placetype":"locality"
},
  "geometry": {"coordinates":[42.96434,39.15825],"type":"Point"}
}