{
  "type": "Feature",
  "properties": {
    "gn:country":"TR",
    "gn:fcode":"PPL",
    "gn:pop":456,
    "iso:country":"TR",
    "name:rus_x_preferred":[
        "Kanig\u00ebzyuk"
    ],
    "name:unk_x_variant":[
        "K\u00e2nig\u00f6z\u00fck"
    ],
    "qs:name":"\u00dc\u00e7p\u0131nar",
    "qs:photos_9r":0,
    "qs:photos_sr":0,
    "qs:pop_sr":"2",
    "wof:name":"\u00dc\u00e7p\u0131nar",
    "wof:placetype":"locality",
    "wof:population":456
},
  "geometry": {"coordinates":[41.70528,37.83556],"type":"Point"}
}