{
  "type": "Feature",
  "properties": {
    "gn:country":"TR",
    "gn:fcode":"PPL",
    "gn:pop":9429,
    "iso:country":"TR",
    "name:deu_x_preferred":[
        "Tortum"
    ],
    "name:eng_x_preferred":[
        "Tortum"
    ],
    "name:epo_x_preferred":[
        "Tortum"
    ],
    "name:fra_x_preferred":[
        "Tortum"
    ],
    "name:hun_x_preferred":[
        "Tortum"
    ],
    "name:hye_x_preferred":[
        "\u0539\u0578\u0580\u0569\u0578\u0582\u0574"
    ],
    "name:ita_x_preferred":[
        "Distretto di Tortum"
    ],
    "name:kat_x_preferred":[
        "\u10d7\u10dd\u10e0\u10d7\u10dd\u10db\u10d8"
    ],
    "name:kur_x_preferred":[
        "Tortim"
    ],
    "name:lbe_x_preferred":[
        "\u0422\u043e\u0440\u0442\u0443\u043c"
    ],
    "name:mrj_x_preferred":[
        "\u0422\u043e\u0440\u0442\u0443\u043c"
    ],
    "name:msa_x_preferred":[
        "Tortum"
    ],
    "name:nan_x_preferred":[
        "Tortum"
    ],
    "name:nld_x_preferred":[
        "Tortum"
    ],
    "name:rus_x_preferred":[
        "\u0422\u043e\u0440\u0442\u0443\u043c"
    ],
    "name:swa_x_preferred":[
        "Tortum"
    ],
    "name:tur_x_preferred":[
        "Tortum"
    ],
    "name:unk_x_variant":[
        "Nihah"
    ],
    "name:urd_x_preferred":[
        "\u062a\u0648\u0631\u062a\u0648\u0645"
    ],
    "name:vie_x_preferred":[
        "Tortum"
    ],
    "qs:name":"Tortum",
    "qs:name_adm0":"Turkey",
    "qs:name_adm1":"Erzurum",
    "qs:photos_9k":1,
    "qs:photos_9r":1,
    "qs:photos_all":16,
    "qs:photos_sr":0,
    "qs:placetype":"Town",
    "qs:pop_sr":"5",
    "wd:wordcount":311,
    "wof:name":"Tortum",
    "wof:placetype":"locality",
    "wof:population":9429
},
  "geometry": {"coordinates":[41.54771,40.2973],"type":"Point"}
}