{
  "type": "Feature",
  "properties": {
    "gn:admin1_code":"60.0",
    "gn:asciiname":"Kabakbogazi",
    "gn:country_code":"TR",
    "gn:dem":1176,
    "gn:feature_class":"P",
    "gn:feature_code":"PPL",
    "gn:name":"Kabakbo\u011faz\u0131",
    "gn:population":0,
    "gn:timezone":"Europe/Istanbul",
    "iso:country":"TR",
    "wof:name":"Kabakbogazi",
    "wof:placetype":"locality"
},
  "geometry": {"coordinates":[36.89364000000001,40.4604],"type":"Point"}
}