{
  "type": "Feature",
  "properties": {
    "gn:admin1_code":"72",
    "gn:asciiname":"Ulucinar",
    "gn:cc2":"TR",
    "gn:country_code":"TR",
    "gn:dem":733,
    "gn:feature_class":"P",
    "gn:feature_code":"PPL",
    "gn:name":"Ulu\u00e7\u0131nar",
    "gn:population":0,
    "gn:timezone":"Europe/Istanbul",
    "iso:country":"TR",
    "name:und_x_variant":[
        "Pirkefan",
        "Brikevan",
        "Birkifan",
        "Ulu\u00e7\u0131nar"
    ],
    "wof:name":"Ulucinar",
    "wof:placetype":"locality"
},
  "geometry": {"coordinates":[41.78583,37.6125],"type":"Point"}
}