{
  "type": "Feature",
  "properties": {
    "gn:admin1_code":"87",
    "gn:asciiname":"Eyupoglu",
    "gn:country_code":"TR",
    "gn:dem":563,
    "gn:feature_class":"P",
    "gn:feature_code":"PPL",
    "gn:name":"Eyupo\u011flu",
    "gn:population":0,
    "gn:timezone":"Europe/Istanbul",
    "iso:country":"TR",
    "name:tur_x_preferred":[
        "Eyupo\u011flu"
    ],
    "name:tur_x_variant":[
        "Hac\u0131eyupo\u011flu"
    ],
    "wof:name":"Eyupoglu",
    "wof:placetype":"locality"
},
  "geometry": {"coordinates":[32.39307,41.38087],"type":"Point"}
}