{
  "type": "Feature",
  "properties": {
    "gn:admin1_code":"32",
    "gn:asciiname":"Cukur",
    "gn:cc2":"TR",
    "gn:country_code":"TR",
    "gn:dem":767,
    "gn:feature_class":"P",
    "gn:feature_code":"PPL",
    "gn:name":"\u00c7ukur",
    "gn:population":0,
    "gn:timezone":"Europe/Istanbul",
    "iso:country":"TR",
    "name:und_x_variant":[
        "\u00c7ukurk\u00f6y",
        "\u00c7ukur"
    ],
    "wof:name":"Cukur",
    "wof:placetype":"locality"
},
  "geometry": {"coordinates":[33.93333,36.48333],"type":"Point"}
}