{
  "type": "Feature",
  "properties": {
    "gn:admin1_code":"83.0",
    "gn:asciiname":"Kornukbanisi",
    "gn:cc2":"TR",
    "gn:country_code":"TR",
    "gn:dem":523,
    "gn:feature_class":"P",
    "gn:feature_code":"PPL",
    "gn:name":"Kornukban\u0131s\u0131",
    "gn:population":0,
    "gn:timezone":"Europe/Istanbul",
    "iso:country":"TR",
    "name:und_x_variant":[
        "Kornukbanysy",
        "Kornukban\u0131s\u0131"
    ],
    "wof:name":"Kornukbanisi",
    "wof:placetype":"locality"
},
  "geometry": {"coordinates":[36.67278,36.90472000000001],"type":"Point"}
}