{
  "type": "Feature",
  "properties": {
    "gn:country":"TR",
    "gn:fcode":"PPL",
    "gn:population":92,
    "iso:country":"TR",
    "name:deu_x_preferred":[
        "Ya\u011fc\u0131lar"
    ],
    "name:eng_x_preferred":[
        "Ya\u011fc\u0131lar"
    ],
    "name:nld_x_preferred":[
        "Ya\u011fc\u0131lar"
    ],
    "name:spa_x_preferred":[
        "Ya\u011fc\u0131lar"
    ],
    "name:tur_x_preferred":[
        "Ya\u011fc\u0131lar"
    ],
    "name:und_x_variant":[
        "Munusu"
    ],
    "qs:name":"Ya\u011fc\u0131lar",
    "qs:photos_9r":0,
    "qs:photos_sr":0,
    "qs:pop_sr":"1",
    "wd:wordcount":57,
    "wof:name":"Ya\u011fc\u0131lar",
    "wof:placetype":"locality",
    "wof:population":92
},
  "geometry": {"coordinates":[37.67278,36.91611],"type":"Point"}
}