{
  "type": "Feature",
  "properties": {
    "gn:admin1_code":"35",
    "gn:asciiname":"Sogutcuk Mahalle",
    "gn:country_code":"TR",
    "gn:dem":74,
    "gn:feature_class":"P",
    "gn:feature_code":"PPL",
    "gn:name":"S\u00f6g\u00fctc\u00fck Mahalle",
    "gn:population":0,
    "gn:timezone":"Europe/Istanbul",
    "iso:country":"TR",
    "name:und_x_variant":[
        "S\u00f6\u011f\u00fctc\u00fck",
        "S\u00f6g\u00fctc\u00fck Mahalle"
    ],
    "wof:name":"Sogutcuk Mahalle",
    "wof:placetype":"locality"
},
  "geometry": {"coordinates":[26.80623,38.64431],"type":"Point"}
}