{
  "type": "Feature",
  "properties": {
    "gn:country":"TR",
    "gn:fcode":"PPLA2",
    "gn:pop":27019,
    "iso:country":"TR",
    "name:chi_x_preferred":[
        "\u963f\u62c9\u8cc8"
    ],
    "name:dut_x_preferred":[
        "Alaca"
    ],
    "name:eng_x_preferred":[
        "Alaca"
    ],
    "name:epo_x_preferred":[
        "Alaca"
    ],
    "name:fre_x_preferred":[
        "Alaca"
    ],
    "name:gag_x_preferred":[
        "Alaca"
    ],
    "name:ger_x_preferred":[
        "Alaca"
    ],
    "name:ita_x_preferred":[
        "Alaca"
    ],
    "name:lit_x_preferred":[
        "Alakas"
    ],
    "name:may_x_preferred":[
        "Alaca"
    ],
    "name:min_x_preferred":[
        "Alaca"
    ],
    "name:mrj_x_preferred":[
        "\u0410\u043b\u0430\u0434\u0436\u0430"
    ],
    "name:nan_x_preferred":[
        "Alaca"
    ],
    "name:nno_x_preferred":[
        "Alaca"
    ],
    "name:per_x_preferred":[
        "\u0622\u0644\u0627\u062c\u0647"
    ],
    "name:rum_x_preferred":[
        "Alaca"
    ],
    "name:swa_x_preferred":[
        "Alaca"
    ],
    "name:tur_x_preferred":[
        "Alaca"
    ],
    "name:unk_x_variant":[
        "H\u00fcseynabat"
    ],
    "name:urd_x_preferred":[
        "\u0622\u0644\u0627\u062c\u0627"
    ],
    "name:vie_x_preferred":[
        "Alaca"
    ],
    "qs:name":"Alaca",
    "qs:photos_9r":0,
    "qs:photos_sr":0,
    "qs:pop_sr":"7",
    "wd:wordcount":118,
    "wof:name":"Alaca",
    "wof:placetype":"locality",
    "wof:population":27019
},
  "geometry": {"coordinates":[34.8425,40.16833],"type":"Point"}
}