{
  "type": "Feature",
  "properties": {
    "gn:country":"TR",
    "gn:fcode":"PPLA2",
    "gn:population":27019,
    "iso:country":"TR",
    "name:ast_x_preferred":[
        "Alaca"
    ],
    "name:azb_x_preferred":[
        "\u0622\u0644\u0627\u062c\u0627"
    ],
    "name:ceb_x_preferred":[
        "Alaca"
    ],
    "name:che_x_preferred":[
        "\u0410\u043b\u0430\u0434\u0436\u0430"
    ],
    "name:deu_x_preferred":[
        "Alaca"
    ],
    "name:diq_x_preferred":[
        "Alaca"
    ],
    "name:eng_x_preferred":[
        "Alaca"
    ],
    "name:epo_x_preferred":[
        "Alaca"
    ],
    "name:fas_x_preferred":[
        "\u0622\u0644\u0627\u062c\u0647"
    ],
    "name:fra_x_preferred":[
        "Alaca"
    ],
    "name:gag_x_preferred":[
        "Alaca"
    ],
    "name:ita_x_preferred":[
        "Alaca"
    ],
    "name:lit_x_preferred":[
        "Alakas"
    ],
    "name:min_x_preferred":[
        "Alaca"
    ],
    "name:mrj_x_preferred":[
        "\u0410\u043b\u0430\u0434\u0436\u0430"
    ],
    "name:msa_x_preferred":[
        "Alaca"
    ],
    "name:nan_x_preferred":[
        "Alaca"
    ],
    "name:nld_x_preferred":[
        "Alaca"
    ],
    "name:nno_x_preferred":[
        "Alaca"
    ],
    "name:nob_x_preferred":[
        "Alaca"
    ],
    "name:ron_x_preferred":[
        "Alaca"
    ],
    "name:rus_x_preferred":[
        "\u0410\u043b\u0430\u0434\u0436\u0430"
    ],
    "name:swa_x_preferred":[
        "Alaca"
    ],
    "name:tat_x_preferred":[
        "\u0410\u043b\u0430\u0497\u0430"
    ],
    "name:tur_x_preferred":[
        "Alaca"
    ],
    "name:und_x_variant":[
        "H\u00fcseynabat"
    ],
    "name:urd_x_preferred":[
        "\u0622\u0644\u0627\u062c\u0627"
    ],
    "name:vie_x_preferred":[
        "Alaca"
    ],
    "name:zho_x_preferred":[
        "\u963f\u62c9\u8cc8"
    ],
    "qs:name":"Alaca",
    "qs:photos_9r":0,
    "qs:photos_sr":0,
    "qs:pop_sr":"7",
    "wd:wordcount":118,
    "wof:name":"Alaca",
    "wof:placetype":"locality",
    "wof:population":27019
},
  "geometry": {"coordinates":[34.8425,40.16833],"type":"Point"}
}