{
  "type": "Feature",
  "properties": {
    "gn:admin1_code":"63.0",
    "gn:asciiname":"Goktepe",
    "gn:country_code":"TR",
    "gn:dem":517,
    "gn:feature_class":"P",
    "gn:feature_code":"PPL",
    "gn:name":"G\u00f6ktepe",
    "gn:population":0,
    "gn:timezone":"Europe/Istanbul",
    "iso:country":"TR",
    "name:tur_x_preferred":[
        "G\u00f6ktepe"
    ],
    "wof:name":"Goktepe",
    "wof:placetype":"locality"
},
  "geometry": {"coordinates":[39.65269,37.15121],"type":"Point"}
}