{
  "type": "Feature",
  "properties": {
    "gn:admin1_code":"71",
    "gn:asciiname":"Kuyubasi",
    "gn:country_code":"TR",
    "gn:dem":943,
    "gn:feature_class":"P",
    "gn:feature_code":"PPL",
    "gn:name":"Kuyuba\u015f\u0131",
    "gn:population":0,
    "gn:timezone":"Europe/Istanbul",
    "iso:country":"TR",
    "name:und_x_variant":[
        "Taahh\u00fctl\u00fc",
        "Kuyuba\u015f\u0131"
    ],
    "wof:name":"Kuyubasi",
    "wof:placetype":"locality"
},
  "geometry": {"coordinates":[32.02144000000001,38.68426],"type":"Point"}
}