{
  "type": "Feature",
  "properties": {
    "gn:admin1_code":"23",
    "gn:asciiname":"Kayaonu",
    "gn:country_code":"TR",
    "gn:dem":1243,
    "gn:feature_class":"P",
    "gn:feature_code":"PPL",
    "gn:name":"Kaya\u00f6n\u00fc",
    "gn:population":0,
    "gn:timezone":"Europe/Istanbul",
    "iso:country":"TR",
    "name:tur_x_preferred":[
        "Kaya\u00f6n\u00fc"
    ],
    "wof:name":"Kayaonu",
    "wof:placetype":"locality"
},
  "geometry": {"coordinates":[39.78033,38.54694],"type":"Point"}
}