{
  "type": "Feature",
  "properties": {
    "gn:admin1_code":"81",
    "gn:asciiname":"Kiziltahta",
    "gn:country_code":"TR",
    "gn:dem":12,
    "gn:feature_class":"P",
    "gn:feature_code":"PPL",
    "gn:name":"K\u0131z\u0131ltahta",
    "gn:population":0,
    "gn:timezone":"Europe/Istanbul",
    "iso:country":"TR",
    "name:ceb_x_preferred":[
        "K\u0131z\u0131ltahta"
    ],
    "name:deu_x_preferred":[
        "K\u0131z\u0131ltahta"
    ],
    "name:msa_x_preferred":[
        "K\u0131z\u0131ltahta"
    ],
    "name:tur_x_preferred":[
        "K\u0131z\u0131ltahta"
    ],
    "name:vie_x_preferred":[
        "K\u0131z\u0131ltahta"
    ],
    "wof:name":"Kiziltahta",
    "wof:placetype":"locality"
},
  "geometry": {"coordinates":[35.47989000000001,36.74882],"type":"Point"}
}