{
  "type": "Feature",
  "properties": {
    "gn:admin1_code":"71",
    "gn:asciiname":"Numunegocmen",
    "gn:country_code":"TR",
    "gn:dem":1050,
    "gn:feature_class":"P",
    "gn:feature_code":"PPL",
    "gn:name":"Numuneg\u00f6\u00e7men",
    "gn:population":0,
    "gn:timezone":"Europe/Istanbul",
    "iso:country":"TR",
    "wof:name":"Numunegocmen",
    "wof:placetype":"locality"
},
  "geometry": {"coordinates":[34.21972,37.79778],"type":"Point"}
}