{
  "type": "Feature",
  "properties": {
    "gn:admin1_code":"70",
    "gn:asciiname":"Taslica",
    "gn:country_code":"TR",
    "gn:dem":2187,
    "gn:feature_class":"P",
    "gn:feature_code":"PPL",
    "gn:name":"Ta\u015fl\u0131ca",
    "gn:population":0,
    "gn:timezone":"Europe/Istanbul",
    "iso:country":"TR",
    "name:und_x_variant":[
        "Navg\u00fcze",
        "Ta\u015fl\u0131ca",
        "Nevg\u00fczan"
    ],
    "wof:name":"Taslica",
    "wof:placetype":"locality"
},
  "geometry": {"coordinates":[43.55662,37.64192],"type":"Point"}
}