{
  "type": "Feature",
  "properties": {
    "gn:admin1_code":"2.0",
    "gn:asciiname":"Siraca",
    "gn:country_code":"TR",
    "gn:dem":728,
    "gn:feature_class":"P",
    "gn:feature_code":"PPL",
    "gn:name":"S\u0131raca",
    "gn:population":0,
    "gn:timezone":"Europe/Istanbul",
    "iso:country":"TR",
    "name:tur_x_preferred":[
        "S\u0131raca"
    ],
    "name:und_x_variant":[
        "Sar\u0131ca"
    ],
    "wof:name":"Siraca",
    "wof:placetype":"locality"
},
  "geometry": {"coordinates":[38.75937,37.85851],"type":"Point"}
}