{
  "type": "Feature",
  "properties": {
    "gn:admin1_code":"63",
    "gn:asciiname":"Gokcetas",
    "gn:country_code":"TR",
    "gn:dem":1222,
    "gn:feature_class":"P",
    "gn:feature_code":"PPL",
    "gn:name":"G\u00f6k\u00e7eta\u015f",
    "gn:population":0,
    "gn:timezone":"Europe/Istanbul",
    "iso:country":"TR",
    "name:tur_x_preferred":[
        "G\u00f6k\u00e7eta\u015f"
    ],
    "wof:name":"Gokcetas",
    "wof:placetype":"locality"
},
  "geometry": {"coordinates":[39.58333,37.83333],"type":"Point"}
}