{
  "type": "Feature",
  "properties": {
    "gn:admin1_code":"13.0",
    "gn:asciiname":"Zeviyagave",
    "gn:country_code":"TR",
    "gn:dem":1898,
    "gn:feature_class":"P",
    "gn:feature_code":"PPL",
    "gn:name":"Zeviyagave",
    "gn:population":0,
    "gn:timezone":"Europe/Istanbul",
    "iso:country":"TR",
    "name:tur_x_preferred":[
        "Zeviyagave"
    ],
    "wof:name":"Zeviyagave",
    "wof:placetype":"locality"
},
  "geometry": {"coordinates":[42.435,38.27459],"type":"Point"}
}