{
  "type": "Feature",
  "properties": {
    "gn:admin1_code":"81.0",
    "gn:asciiname":"Kuyumcular",
    "gn:country_code":"TR",
    "gn:dem":102,
    "gn:feature_class":"P",
    "gn:feature_code":"PPL",
    "gn:name":"Kuyumcular",
    "gn:population":0,
    "gn:timezone":"Europe/Istanbul",
    "iso:country":"TR",
    "wof:name":"Kuyumcular",
    "wof:placetype":"locality"
},
  "geometry": {"coordinates":[35.15355,37.03338],"type":"Point"}
}