{
  "type": "Feature",
  "properties": {
    "gn:admin1_code":"72",
    "gn:asciiname":"Asagicimenli",
    "gn:country_code":"TR",
    "gn:dem":710,
    "gn:feature_class":"P",
    "gn:feature_code":"PPL",
    "gn:name":"A\u015fa\u011f\u0131\u00e7imenli",
    "gn:population":0,
    "gn:timezone":"Europe/Istanbul",
    "iso:country":"TR",
    "name:tur_x_preferred":[
        "A\u015fa\u011f\u0131\u00e7imenli"
    ],
    "name:und_x_variant":[
        "Kanisork",
        "Kanis\u00fcrik",
        "K\u00e2nisorik"
    ],
    "wof:name":"Asagicimenli",
    "wof:placetype":"locality"
},
  "geometry": {"coordinates":[40.45643,37.28993],"type":"Point"}
}