{
  "type": "Feature",
  "properties": {
    "gn:admin1_code":"4.0",
    "gn:asciiname":"Hacisefer",
    "gn:country_code":"TR",
    "gn:dem":1663,
    "gn:feature_class":"P",
    "gn:feature_code":"PPL",
    "gn:name":"Hac\u0131sefer",
    "gn:population":0,
    "gn:timezone":"Europe/Istanbul",
    "iso:country":"TR",
    "name:tur_x_preferred":[
        "Hacisefer"
    ],
    "name:tur_x_variant":[
        "Hac\u0131sefer"
    ],
    "wof:name":"Hacisefer",
    "wof:placetype":"locality"
},
  "geometry": {"coordinates":[43.01742,39.78229],"type":"Point"}
}