{
  "type": "Feature",
  "properties": {
    "gn:admin1_code":"54",
    "gn:asciiname":"Tesvikiye",
    "gn:country_code":"TR",
    "gn:dem":95,
    "gn:feature_class":"P",
    "gn:feature_code":"PPL",
    "gn:name":"Te\u015fvikiye",
    "gn:population":0,
    "gn:timezone":"Europe/Istanbul",
    "iso:country":"TR",
    "name:tur_x_preferred":[
        "Te\u015fvikiye"
    ],
    "wof:name":"Tesvikiye",
    "wof:placetype":"locality"
},
  "geometry": {"coordinates":[30.24292,40.51481],"type":"Point"}
}