{
  "type": "Feature",
  "properties": {
    "gn:admin1_code":"8.0",
    "gn:asciiname":"Tutunculer",
    "gn:country_code":"TR",
    "gn:dem":635,
    "gn:feature_class":"P",
    "gn:feature_code":"PPL",
    "gn:name":"T\u00fct\u00fcnc\u00fcler",
    "gn:population":0,
    "gn:timezone":"Europe/Istanbul",
    "iso:country":"TR",
    "name:tur_x_preferred":[
        "T\u00fct\u00fcnc\u00fcler"
    ],
    "wof:name":"Tutunculer",
    "wof:placetype":"locality"
},
  "geometry": {"coordinates":[41.73803,41.28191],"type":"Point"}
}