{
  "type": "Feature",
  "properties": {
    "gn:admin1_code":"59.0",
    "gn:asciiname":"Umurbey",
    "gn:country_code":"TR",
    "gn:dem":93,
    "gn:feature_class":"P",
    "gn:feature_code":"PPL",
    "gn:name":"Umurbey",
    "gn:population":0,
    "gn:timezone":"Europe/Istanbul",
    "iso:country":"TR",
    "wof:name":"Umurbey",
    "wof:placetype":"locality"
},
  "geometry": {"coordinates":[27.05347,41.05838],"type":"Point"}
}