{
  "type": "Feature",
  "properties": {
    "gn:admin1_code":"33",
    "gn:asciiname":"Golkonak",
    "gn:country_code":"TR",
    "gn:dem":1149,
    "gn:feature_class":"P",
    "gn:feature_code":"PPL",
    "gn:name":"G\u00f6lkonak",
    "gn:population":0,
    "gn:timezone":"Europe/Istanbul",
    "iso:country":"TR",
    "name:und_x_variant":[
        "G\u00f6lkonak",
        "Yenice"
    ],
    "wof:name":"Golkonak",
    "wof:placetype":"locality"
},
  "geometry": {"coordinates":[31.42748,37.70665],"type":"Point"}
}