{
  "type": "Feature",
  "properties": {
    "gn:admin1_code":"04",
    "gn:asciiname":"Darkut",
    "gn:country_code":"TR",
    "gn:dem":1892,
    "gn:feature_class":"P",
    "gn:feature_code":"PPL",
    "gn:name":"Darkut",
    "gn:population":0,
    "gn:timezone":"Europe/Istanbul",
    "iso:country":"TR",
    "wof:name":"Darkut",
    "wof:placetype":"locality"
},
  "geometry": {"coordinates":[42.46667,39.56667],"type":"Point"}
}