{
  "type": "Feature",
  "properties": {
    "gn:admin1_code":"85.0",
    "gn:asciiname":"Haydarli",
    "gn:country_code":"TR",
    "gn:dem":76,
    "gn:feature_class":"P",
    "gn:feature_code":"PPL",
    "gn:name":"Haydarl\u0131",
    "gn:population":0,
    "gn:timezone":"Europe/Istanbul",
    "iso:country":"TR",
    "name:und_x_variant":[
        "Haydarl\u0131",
        "Karacal\u0131"
    ],
    "wof:name":"Haydarli",
    "wof:placetype":"locality"
},
  "geometry": {"coordinates":[31.46341,41.15792],"type":"Point"}
}