{
  "type": "Feature",
  "properties": {
    "gn:admin1_code":"82.0",
    "gn:asciiname":"Egmur",
    "gn:country_code":"TR",
    "gn:dem":1355,
    "gn:feature_class":"P",
    "gn:feature_code":"PPL",
    "gn:name":"E\u011fm\u00fcr",
    "gn:population":0,
    "gn:timezone":"Europe/Istanbul",
    "iso:country":"TR",
    "wof:name":"Egmur",
    "wof:placetype":"locality"
},
  "geometry": {"coordinates":[32.89011,40.8543],"type":"Point"}
}