{
  "type": "Feature",
  "properties": {
    "gn:admin1_code":"93.0",
    "gn:asciiname":"Caykoy",
    "gn:country_code":"TR",
    "gn:dem":171,
    "gn:feature_class":"P",
    "gn:feature_code":"PPL",
    "gn:name":"\u00c7ayk\u00f6y",
    "gn:population":0,
    "gn:timezone":"Europe/Istanbul",
    "iso:country":"TR",
    "name:und_x_variant":[
        "Efteni\u00e7ayk\u00f6y",
        "\u00c7ayk\u00f6y\u00fc",
        "\u00c7ay",
        "\u00c7ayk\u00f6y"
    ],
    "wof:name":"Caykoy",
    "wof:placetype":"locality"
},
  "geometry": {"coordinates":[30.94116,40.7573],"type":"Point"}
}