{
  "type": "Feature",
  "properties": {
    "gn:admin1_code":"70.0",
    "gn:asciiname":"Cigir",
    "gn:country_code":"TR",
    "gn:dem":2379,
    "gn:feature_class":"P",
    "gn:feature_code":"PPL",
    "gn:name":"\u00c7\u0131\u011f\u0131r",
    "gn:population":0,
    "gn:timezone":"Europe/Istanbul",
    "iso:country":"TR",
    "wof:name":"Cigir",
    "wof:placetype":"locality"
},
  "geometry": {"coordinates":[43.60612,37.7265],"type":"Point"}
}