{
  "type": "Feature",
  "properties": {
    "gn:admin1_code":"44",
    "gn:asciiname":"Gevherusagi",
    "gn:country_code":"TR",
    "gn:dem":1341,
    "gn:feature_class":"P",
    "gn:feature_code":"PPL",
    "gn:name":"Gevheru\u015fa\u011f\u0131",
    "gn:population":0,
    "gn:timezone":"Europe/Istanbul",
    "iso:country":"TR",
    "name:tur_x_preferred":[
        "Gevheru\u015fa\u011f\u0131"
    ],
    "wof:name":"Gevherusagi",
    "wof:placetype":"locality"
},
  "geometry": {"coordinates":[39.07624000000001,38.25494000000001],"type":"Point"}
}