{
  "type": "Feature",
  "properties": {
    "gn:admin1_code":"68",
    "gn:asciiname":"Gokler",
    "gn:country_code":"TR",
    "gn:dem":1134,
    "gn:feature_class":"P",
    "gn:feature_code":"PPL",
    "gn:name":"G\u00f6kler",
    "gn:population":0,
    "gn:timezone":"Europe/Istanbul",
    "iso:country":"TR",
    "wof:name":"Gokler",
    "wof:placetype":"locality"
},
  "geometry": {"coordinates":[32.39131,39.94498],"type":"Point"}
}