{
  "type": "Feature",
  "properties": {
    "gn:country":"TR",
    "gn:fcode":"PPL",
    "gn:pop":1002,
    "iso:country":"TR",
    "name:rus_x_preferred":[
        "Tel\u2019sikan"
    ],
    "name:unk_x_variant":[
        "Telsek\u00e2n"
    ],
    "qs:name":"\u00d6zbek",
    "qs:photos_9r":0,
    "qs:photos_sr":0,
    "qs:pop_sr":"3",
    "wd:wordcount":37,
    "wof:name":"\u00d6zbek",
    "wof:placetype":"locality",
    "wof:population":1002
},
  "geometry": {"coordinates":[41.69535,37.17499],"type":"Point"}
}