{
  "type": "Feature",
  "properties": {
    "gn:admin1_code":"02",
    "gn:asciiname":"Asagi Ciftlikkoy",
    "gn:country_code":"TR",
    "gn:dem":814,
    "gn:feature_class":"P",
    "gn:feature_code":"PPL",
    "gn:name":"A\u015fa\u011f\u0131 \u00c7iftlikk\u00f6y",
    "gn:population":0,
    "gn:timezone":"Europe/Istanbul",
    "iso:country":"TR",
    "name:tur_x_preferred":[
        "A\u015fa\u011f\u0131 \u00c7iftlikk\u00f6y"
    ],
    "name:und_x_variant":[
        "A\u015fa\u011f\u0131\u00e7iftlik"
    ],
    "wof:name":"Asagi Ciftlikkoy",
    "wof:placetype":"locality"
},
  "geometry": {"coordinates":[44.58639,39.85333],"type":"Point"}
}