{
  "type": "Feature",
  "properties": {
    "gn:admin1_code":"17.0",
    "gn:asciiname":"Biberler",
    "gn:country_code":"TR",
    "gn:dem":366,
    "gn:feature_class":"P",
    "gn:feature_code":"PPL",
    "gn:name":"Biberler",
    "gn:population":0,
    "gn:timezone":"Europe/Istanbul",
    "iso:country":"TR",
    "wof:name":"Biberler",
    "wof:placetype":"locality"
},
  "geometry": {"coordinates":[26.74149,40.17714],"type":"Point"}
}