{
  "type": "Feature",
  "properties": {
    "gn:admin1_code":"24",
    "gn:asciiname":"Goyne",
    "gn:country_code":"TR",
    "gn:dem":1753,
    "gn:feature_class":"P",
    "gn:feature_code":"PPL",
    "gn:name":"G\u00f6yne",
    "gn:population":0,
    "gn:timezone":"Europe/Istanbul",
    "iso:country":"TR",
    "name:tur_x_preferred":[
        "G\u00f6yne"
    ],
    "wof:name":"Goyne",
    "wof:placetype":"locality"
},
  "geometry": {"coordinates":[39.23426,39.81181],"type":"Point"}
}