{
  "type": "Feature",
  "properties": {
    "gn:admin1_code":"10",
    "gn:asciiname":"Tozagan",
    "gn:country_code":"TR",
    "gn:dem":441,
    "gn:feature_class":"P",
    "gn:feature_code":"PPL",
    "gn:name":"Toza\u011fan",
    "gn:population":0,
    "gn:timezone":"Europe/Istanbul",
    "iso:country":"TR",
    "name:tur_x_preferred":[
        "Tozalan"
    ],
    "name:und_x_variant":[
        "Toza\u011fan"
    ],
    "wof:name":"Tozagan",
    "wof:placetype":"locality"
},
  "geometry": {"coordinates":[28.36844,39.44362],"type":"Point"}
}