{
  "type": "Feature",
  "properties": {
    "gn:admin1_code":"85.0",
    "gn:asciiname":"Osmanbeyler",
    "gn:country_code":"TR",
    "gn:dem":208,
    "gn:feature_class":"P",
    "gn:feature_code":"PPL",
    "gn:name":"Osmanbeyler",
    "gn:population":0,
    "gn:timezone":"Europe/Istanbul",
    "iso:country":"TR",
    "name:und_x_variant":[
        "Osmanbey",
        "Osmanbeyler",
        "\u00d6zp\u0131nar"
    ],
    "wof:name":"Osmanbeyler",
    "wof:placetype":"locality"
},
  "geometry": {"coordinates":[31.90432,41.16234],"type":"Point"}
}