{
  "type": "Feature",
  "properties": {
    "gn:admin1_code":"21",
    "gn:asciiname":"Saltepe",
    "gn:country_code":"TR",
    "gn:dem":790,
    "gn:feature_class":"P",
    "gn:feature_code":"PPL",
    "gn:name":"Saltepe",
    "gn:population":0,
    "gn:timezone":"Europe/Istanbul",
    "iso:country":"TR",
    "name:und_x_variant":[
        "\u00c7ataldut"
    ],
    "wof:name":"Saltepe",
    "wof:placetype":"locality"
},
  "geometry": {"coordinates":[39.21877,38.049],"type":"Point"}
}