{
  "type": "Feature",
  "properties": {
    "gn:admin1_code":"72.0",
    "gn:asciiname":"Esinli",
    "gn:country_code":"TR",
    "gn:dem":997,
    "gn:feature_class":"P",
    "gn:feature_code":"PPL",
    "gn:name":"Esinli",
    "gn:population":0,
    "gn:timezone":"Europe/Istanbul",
    "iso:country":"TR",
    "name:tur_x_preferred":[
        "Esinli"
    ],
    "wof:name":"Esinli",
    "wof:placetype":"locality"
},
  "geometry": {"coordinates":[40.38529000000001,37.39914],"type":"Point"}
}