{
  "type": "Feature",
  "properties": {
    "gn:admin1_code":"83.0",
    "gn:asciiname":"Soybun",
    "gn:cc2":"TR",
    "gn:country_code":"TR",
    "gn:dem":528,
    "gn:feature_class":"P",
    "gn:feature_code":"PPL",
    "gn:name":"Soybun",
    "gn:population":0,
    "gn:timezone":"Europe/Istanbul",
    "iso:country":"TR",
    "name:und_x_variant":[
        "Soybunu",
        "Soybun"
    ],
    "wof:name":"Soybun",
    "wof:placetype":"locality"
},
  "geometry": {"coordinates":[37.63333,36.77361],"type":"Point"}
}