{
  "type": "Feature",
  "properties": {
    "gn:admin1_code":"85",
    "gn:asciiname":"Derekoseler",
    "gn:country_code":"TR",
    "gn:dem":148,
    "gn:feature_class":"P",
    "gn:feature_code":"PPL",
    "gn:name":"Derek\u00f6seler",
    "gn:population":0,
    "gn:timezone":"Europe/Istanbul",
    "iso:country":"TR",
    "wof:name":"Derekoseler",
    "wof:placetype":"locality"
},
  "geometry": {"coordinates":[32.14198,41.35488],"type":"Point"}
}