{
  "type": "Feature",
  "properties": {
    "gn:admin1_code":"3.0",
    "gn:asciiname":"Akkoyunlu",
    "gn:country_code":"TR",
    "gn:dem":975,
    "gn:feature_class":"P",
    "gn:feature_code":"PPL",
    "gn:name":"Akkoyunlu",
    "gn:population":0,
    "gn:timezone":"Europe/Istanbul",
    "iso:country":"TR",
    "wof:name":"Akkoyunlu",
    "wof:placetype":"locality"
},
  "geometry": {"coordinates":[30.06637000000001,37.92729],"type":"Point"}
}