{
  "type": "Feature",
  "properties": {
    "gn:admin1_code":"11",
    "gn:asciiname":"Erikli",
    "gn:country_code":"TR",
    "gn:dem":1226,
    "gn:feature_class":"P",
    "gn:feature_code":"PPL",
    "gn:name":"Erikli",
    "gn:population":0,
    "gn:timezone":"Europe/Istanbul",
    "iso:country":"TR",
    "name:deu_x_preferred":[
        "Erikli"
    ],
    "name:tur_x_preferred":[
        "Erikli"
    ],
    "wof:name":"Erikli",
    "wof:placetype":"locality"
},
  "geometry": {"coordinates":[29.86611,39.84944],"type":"Point"}
}