{
  "type": "Feature",
  "properties": {
    "gn:admin1_code":"58",
    "gn:asciiname":"Kabali",
    "gn:country_code":"TR",
    "gn:dem":1505,
    "gn:feature_class":"P",
    "gn:feature_code":"PPL",
    "gn:name":"Kabal\u0131",
    "gn:population":0,
    "gn:timezone":"Europe/Istanbul",
    "iso:country":"TR",
    "wof:name":"Kabali",
    "wof:placetype":"locality"
},
  "geometry": {"coordinates":[37.47361,39.64861],"type":"Point"}
}