{
  "type": "Feature",
  "properties": {
    "gn:admin1_code":"44",
    "gn:asciiname":"Kes",
    "gn:cc2":"TR",
    "gn:country_code":"TR",
    "gn:dem":2246,
    "gn:feature_class":"P",
    "gn:feature_code":"PPL",
    "gn:name":"Ke\u015f",
    "gn:population":0,
    "gn:timezone":"Europe/Istanbul",
    "iso:country":"TR",
    "name:deu_x_preferred":[
        "Kes"
    ],
    "name:fin_x_preferred":[
        "Kes"
    ],
    "name:nld_x_preferred":[
        "Kes"
    ],
    "name:spa_x_preferred":[
        "Kes"
    ],
    "name:und_x_variant":[
        "Ke\u015f Mezraas\u0131",
        "Ke\u015f"
    ],
    "wof:name":"Kes",
    "wof:placetype":"locality"
},
  "geometry": {"coordinates":[38.01667,39.06667],"type":"Point"}
}