{
  "type": "Feature",
  "properties": {
    "gn:admin1_code":"85.0",
    "gn:asciiname":"Sabirli",
    "gn:country_code":"TR",
    "gn:dem":140,
    "gn:feature_class":"P",
    "gn:feature_code":"PPL",
    "gn:name":"Sab\u0131rl\u0131",
    "gn:population":0,
    "gn:timezone":"Europe/Istanbul",
    "iso:country":"TR",
    "name:und_x_variant":[
        "Tekkeizir",
        "A\u015fa\u011f\u0131tekke",
        "Sab\u0131rl\u0131"
    ],
    "wof:name":"Sabirli",
    "wof:placetype":"locality"
},
  "geometry": {"coordinates":[31.37333,41.15213],"type":"Point"}
}