{
  "type": "Feature",
  "properties": {
    "gn:country":"TR",
    "gn:fcode":"PPL",
    "gn:population":1116,
    "iso:country":"TR",
    "qs:name":"Sevimli",
    "qs:photos_9r":0,
    "qs:photos_sr":0,
    "qs:pop_sr":"3",
    "wof:name":"Sevimli",
    "wof:placetype":"locality",
    "wof:population":1116
},
  "geometry": {"coordinates":[38.91472,36.78778],"type":"Point"}
}