{
  "type": "Feature",
  "properties": {
    "gn:admin1_code":"58.0",
    "gn:asciiname":"Serefiye",
    "gn:country_code":"TR",
    "gn:dem":1547,
    "gn:feature_class":"P",
    "gn:feature_code":"PPLA3",
    "gn:name":"\u015eerefiye",
    "gn:population":0,
    "gn:timezone":"Europe/Istanbul",
    "iso:country":"TR",
    "name:eng_x_preferred":[
        "\u015eerefiye"
    ],
    "name:rus_x_preferred":[
        "\u0428\u0435\u0440\u0435\u0444\u0438\u0435"
    ],
    "name:und_x_variant":[
        "\u015eerefiye"
    ],
    "wof:name":"Serefiye",
    "wof:placetype":"locality"
},
  "geometry": {"coordinates":[37.75624000000001,40.11195],"type":"Point"}
}