{
  "type": "Feature",
  "properties": {
    "gn:admin1_code":"17.0",
    "gn:asciiname":"Bahadirli",
    "gn:country_code":"TR",
    "gn:dem":195,
    "gn:feature_class":"P",
    "gn:feature_code":"PPL",
    "gn:name":"Bahad\u0131rl\u0131",
    "gn:population":0,
    "gn:timezone":"Europe/Istanbul",
    "iso:country":"TR",
    "wof:name":"Bahadirli",
    "wof:placetype":"locality"
},
  "geometry": {"coordinates":[26.91584000000001,40.03263],"type":"Point"}
}