{
  "type": "Feature",
  "properties": {
    "gn:admin1_code":"64",
    "gn:asciiname":"Takmak",
    "gn:cc2":"TR",
    "gn:country_code":"TR",
    "gn:dem":825,
    "gn:feature_class":"P",
    "gn:feature_code":"PPL",
    "gn:name":"Takmak",
    "gn:population":0,
    "gn:timezone":"Europe/Istanbul",
    "iso:country":"TR",
    "name:und_x_variant":[
        "Tokmak",
        "Takmak"
    ],
    "wof:name":"Takmak",
    "wof:placetype":"locality"
},
  "geometry": {"coordinates":[28.97694000000001,38.44861],"type":"Point"}
}