{
  "type": "Feature",
  "properties": {
    "gn:admin1_code":"63",
    "gn:asciiname":"Kesmetas",
    "gn:country_code":"TR",
    "gn:dem":745,
    "gn:feature_class":"P",
    "gn:feature_code":"PPL",
    "gn:name":"Kesmeta\u015f",
    "gn:population":0,
    "gn:timezone":"Europe/Istanbul",
    "iso:country":"TR",
    "name:tur_x_preferred":[
        "Kesmeta\u015f"
    ],
    "name:und_x_variant":[
        "Kurundzhautman"
    ],
    "wof:name":"Kesmetas",
    "wof:placetype":"locality"
},
  "geometry": {"coordinates":[38.60189,37.30694],"type":"Point"}
}