{
  "type": "Feature",
  "properties": {
    "gn:admin1_code":"14",
    "gn:asciiname":"Karabacaklar",
    "gn:country_code":"TR",
    "gn:dem":823,
    "gn:feature_class":"P",
    "gn:feature_code":"PPL",
    "gn:name":"Karabacaklar",
    "gn:population":0,
    "gn:timezone":"Europe/Istanbul",
    "iso:country":"TR",
    "wof:name":"Karabacaklar",
    "wof:placetype":"locality"
},
  "geometry": {"coordinates":[31.85834,40.84482],"type":"Point"}
}