{
  "type": "Feature",
  "properties": {
    "gn:admin1_code":"63.0",
    "gn:asciiname":"Kalemli",
    "gn:country_code":"TR",
    "gn:dem":549,
    "gn:feature_class":"P",
    "gn:feature_code":"PPL",
    "gn:name":"Kalemli",
    "gn:population":0,
    "gn:timezone":"Europe/Istanbul",
    "iso:country":"TR",
    "name:tur_x_preferred":[
        "Kalemli"
    ],
    "wof:name":"Kalemli",
    "wof:placetype":"locality"
},
  "geometry": {"coordinates":[38.98631,37.75982],"type":"Point"}
}