{
  "type": "Feature",
  "properties": {
    "gn:admin1_code":"35",
    "gn:asciiname":"Koseler",
    "gn:country_code":"TR",
    "gn:dem":430,
    "gn:feature_class":"P",
    "gn:feature_code":"PPL",
    "gn:name":"K\u00f6seler",
    "gn:population":0,
    "gn:timezone":"Europe/Istanbul",
    "iso:country":"TR",
    "wof:name":"Koseler",
    "wof:placetype":"locality"
},
  "geometry": {"coordinates":[27.37581,39.01246],"type":"Point"}
}