{
  "type": "Feature",
  "properties": {
    "gn:admin1_code":"04",
    "gn:asciiname":"Dolutas",
    "gn:country_code":"TR",
    "gn:dem":1759,
    "gn:feature_class":"P",
    "gn:feature_code":"PPL",
    "gn:name":"Doluta\u015f",
    "gn:population":0,
    "gn:timezone":"Europe/Istanbul",
    "iso:country":"TR",
    "name:und_x_variant":[
        "Mardo",
        "Doluta\u015f"
    ],
    "wof:name":"Dolutas",
    "wof:placetype":"locality"
},
  "geometry": {"coordinates":[42.67417,39.74786],"type":"Point"}
}