{
  "type": "Feature",
  "properties": {
    "gn:admin1_code":"07",
    "gn:asciiname":"Hatipler",
    "gn:country_code":"TR",
    "gn:dem":41,
    "gn:feature_class":"P",
    "gn:feature_code":"PPL",
    "gn:name":"Hatipler",
    "gn:population":0,
    "gn:timezone":"Europe/Istanbul",
    "iso:country":"TR",
    "wof:name":"Hatipler",
    "wof:placetype":"locality"
},
  "geometry": {"coordinates":[31.41114,36.81131],"type":"Point"}
}