{
  "type": "Feature",
  "properties": {
    "gn:admin1_code":"85.0",
    "gn:asciiname":"Alikoy",
    "gn:country_code":"TR",
    "gn:dem":201,
    "gn:feature_class":"P",
    "gn:feature_code":"PPL",
    "gn:name":"Alik\u00f6y",
    "gn:population":0,
    "gn:timezone":"Europe/Istanbul",
    "iso:country":"TR",
    "wof:name":"Alikoy",
    "wof:placetype":"locality"
},
  "geometry": {"coordinates":[32.03437,41.39777],"type":"Point"}
}