{
  "type": "Feature",
  "properties": {
    "gn:admin1_code":"04",
    "gn:asciiname":"Asagi Kupkiran",
    "gn:country_code":"TR",
    "gn:dem":1622,
    "gn:feature_class":"P",
    "gn:feature_code":"PPL",
    "gn:name":"A\u015fa\u011f\u0131 K\u00fcpk\u0131ran",
    "gn:population":0,
    "gn:timezone":"Europe/Istanbul",
    "iso:country":"TR",
    "name:tur_x_preferred":[
        "A\u015fa\u011f\u0131 K\u00fcpk\u0131ran"
    ],
    "name:und_x_variant":[
        "A\u015fa\u011f\u0131k\u00fcpk\u0131ran"
    ],
    "wof:name":"Asagi Kupkiran",
    "wof:placetype":"locality"
},
  "geometry": {"coordinates":[43.04198,39.70508],"type":"Point"}
}