{
  "type": "Feature",
  "properties": {
    "gn:country":"TR",
    "gn:fcode":"PPL",
    "gn:pop":0,
    "iso:country":"TR",
    "name:tur_x_preferred":[
        "A\u011fa\u00e7l\u0131"
    ],
    "qs:name":"A\u011fa\u00e7l\u0131",
    "qs:name_adm0":"Turkey",
    "qs:name_adm1":"\u0130stanbul",
    "qs:photos_9k":1,
    "qs:photos_9r":1,
    "qs:photos_all":1,
    "qs:photos_sr":0,
    "qs:placetype":"Town",
    "qs:pop_sr":"0",
    "wd:wordcount":49,
    "wof:name":"A\u011fa\u00e7l\u0131",
    "wof:placetype":"locality",
    "wof:population":0
},
  "geometry": {"coordinates":[28.87594,41.2665],"type":"Point"}
}