{
  "type": "Feature",
  "properties": {
    "gn:admin1_code":"5.0",
    "gn:asciiname":"Kuzgece",
    "gn:country_code":"TR",
    "gn:dem":394,
    "gn:feature_class":"P",
    "gn:feature_code":"PPL",
    "gn:name":"Kuzge\u00e7e",
    "gn:population":0,
    "gn:timezone":"Europe/Istanbul",
    "iso:country":"TR",
    "name:und_x_variant":[
        "Kuzkise",
        "Kuzge\u00e7e"
    ],
    "wof:name":"Kuzgece",
    "wof:placetype":"locality"
},
  "geometry": {"coordinates":[36.03269,40.74271],"type":"Point"}
}