{
  "type": "Feature",
  "properties": {
    "gn:admin1_code":"74",
    "gn:asciiname":"Hasinki",
    "gn:country_code":"TR",
    "gn:dem":1141,
    "gn:feature_class":"P",
    "gn:feature_code":"PPL",
    "gn:name":"Hasinki",
    "gn:population":0,
    "gn:timezone":"Europe/Istanbul",
    "iso:country":"TR",
    "name:und_x_variant":[
        "Khasinki",
        "Hesink\u00e2n",
        "\u00d6zpelit",
        "Hasinki",
        "Hes\u0131ngan",
        "Hezink\u00e2n",
        "\u00d6zl\u00fcpelit"
    ],
    "wof:name":"Hasinki",
    "wof:placetype":"locality"
},
  "geometry": {"coordinates":[42.10617,37.6653],"type":"Point"}
}