{
  "type": "Feature",
  "properties": {
    "gn:admin1_code":"85",
    "gn:asciiname":"Bostanci",
    "gn:country_code":"TR",
    "gn:dem":154,
    "gn:feature_class":"P",
    "gn:feature_code":"PPL",
    "gn:name":"Bostanc\u0131",
    "gn:population":0,
    "gn:timezone":"Europe/Istanbul",
    "iso:country":"TR",
    "wof:name":"Bostanci",
    "wof:placetype":"locality"
},
  "geometry": {"coordinates":[32.05991,41.46355],"type":"Point"}
}