{
  "type": "Feature",
  "properties": {
    "gn:admin1_code":"54.0",
    "gn:asciiname":"Resuldivani",
    "gn:country_code":"TR",
    "gn:dem":108,
    "gn:feature_class":"P",
    "gn:feature_code":"PPL",
    "gn:name":"Resuldivan\u0131",
    "gn:population":0,
    "gn:timezone":"Europe/Istanbul",
    "iso:country":"TR",
    "name:tur_x_preferred":[
        "Resuldivan\u0131"
    ],
    "name:und_x_variant":[
        "Camilik\u00f6y"
    ],
    "wof:name":"Resuldivani",
    "wof:placetype":"locality"
},
  "geometry": {"coordinates":[30.3106,40.86787],"type":"Point"}
}