{
  "type": "Feature",
  "properties": {
    "gn:admin1_code":"63.0",
    "gn:asciiname":"Binekli",
    "gn:country_code":"TR",
    "gn:dem":533,
    "gn:feature_class":"P",
    "gn:feature_code":"PPL",
    "gn:name":"Binekli",
    "gn:population":0,
    "gn:timezone":"Europe/Istanbul",
    "iso:country":"TR",
    "name:tur_x_preferred":[
        "Binekli"
    ],
    "wof:name":"Binekli",
    "wof:placetype":"locality"
},
  "geometry": {"coordinates":[38.32057,37.33265],"type":"Point"}
}