{
  "type": "Feature",
  "properties": {
    "gn:admin1_code":"80.0",
    "gn:asciiname":"Kutuklu",
    "gn:country_code":"TR",
    "gn:dem":518,
    "gn:feature_class":"P",
    "gn:feature_code":"PPL",
    "gn:name":"K\u00fct\u00fckl\u00fc",
    "gn:population":0,
    "gn:timezone":"Europe/Istanbul",
    "iso:country":"TR",
    "name:und_x_variant":[
        "K\u00fct\u00fck",
        "K\u00fct\u00fckl\u00fc"
    ],
    "wof:name":"Kutuklu",
    "wof:placetype":"locality"
},
  "geometry": {"coordinates":[42.30608,37.48512],"type":"Point"}
}