{
  "type": "Feature",
  "properties": {
    "gn:admin1_code":"13",
    "gn:asciiname":"Aygirgolu",
    "gn:country_code":"TR",
    "gn:dem":1950,
    "gn:feature_class":"P",
    "gn:feature_code":"PPL",
    "gn:name":"Ayg\u0131rg\u00f6l\u00fc",
    "gn:population":0,
    "gn:timezone":"Europe/Istanbul",
    "iso:country":"TR",
    "name:und_x_variant":[
        "Ayg\u0131rg\u00f6l\u00fck\u00f6y\u00fc",
        "Ayg\u0131rg\u00f6l\u00fc"
    ],
    "wof:name":"Aygirgolu",
    "wof:placetype":"locality"
},
  "geometry": {"coordinates":[42.81984,38.84369],"type":"Point"}
}