{
  "type": "Feature",
  "properties": {
    "gn:admin1_code":"16",
    "gn:asciiname":"Okcular",
    "gn:country_code":"TR",
    "gn:dem":918,
    "gn:feature_class":"P",
    "gn:feature_code":"PPL",
    "gn:name":"Ok\u00e7ular",
    "gn:population":0,
    "gn:timezone":"Europe/Istanbul",
    "iso:country":"TR",
    "name:tur_x_preferred":[
        "Ok\u00e7ular"
    ],
    "wof:name":"Okcular",
    "wof:placetype":"locality"
},
  "geometry": {"coordinates":[29.22584,39.70237],"type":"Point"}
}