{
  "type": "Feature",
  "properties": {
    "gn:admin1_code":"07",
    "gn:asciiname":"Karakolcali",
    "gn:country_code":"TR",
    "gn:dem":102,
    "gn:feature_class":"P",
    "gn:feature_code":"PPL",
    "gn:name":"Karakolcal\u0131",
    "gn:population":0,
    "gn:timezone":"Europe/Istanbul",
    "iso:country":"TR",
    "wof:name":"Karakolcali",
    "wof:placetype":"locality"
},
  "geometry": {"coordinates":[32.07568,36.53722],"type":"Point"}
}