{
  "type": "Feature",
  "properties": {
    "gn:admin1_code":"41.0",
    "gn:asciiname":"Seferkoy",
    "gn:country_code":"TR",
    "gn:dem":274,
    "gn:feature_class":"P",
    "gn:feature_code":"PPL",
    "gn:name":"Seferk\u00f6y",
    "gn:population":0,
    "gn:timezone":"Europe/Istanbul",
    "iso:country":"TR",
    "name:tur_x_preferred":[
        "Seferk\u00f6y"
    ],
    "wof:name":"Seferkoy",
    "wof:placetype":"locality"
},
  "geometry": {"coordinates":[30.0228,40.89557],"type":"Point"}
}