{
  "type": "Feature",
  "properties": {
    "gn:admin1_code":"93",
    "gn:asciiname":"Hasanla",
    "gn:country_code":"TR",
    "gn:dem":389,
    "gn:feature_class":"P",
    "gn:feature_code":"PPL",
    "gn:name":"Hasanla",
    "gn:population":0,
    "gn:timezone":"Europe/Istanbul",
    "iso:country":"TR",
    "wof:name":"Hasanla",
    "wof:placetype":"locality"
},
  "geometry": {"coordinates":[30.96502000000001,40.94586],"type":"Point"}
}