{
  "type": "Feature",
  "properties": {
    "gn:country":"TR",
    "gn:fcode":"PPL",
    "gn:pop":259,
    "iso:country":"TR",
    "name:tur_x_preferred":[
        "Hisarkaya"
    ],
    "name:unk_x_variant":[
        "Kalabozres"
    ],
    "qs:name":"Hisarkaya",
    "qs:photos_9r":0,
    "qs:photos_sr":0,
    "qs:pop_sr":"2",
    "wof:name":"Hisarkaya",
    "wof:placetype":"locality",
    "wof:population":259
},
  "geometry": {"coordinates":[40.90833,37.645],"type":"Point"}
}