{
  "type": "Feature",
  "properties": {
    "gn:admin1_code":"63.0",
    "gn:asciiname":"Turluk",
    "gn:country_code":"TR",
    "gn:dem":397,
    "gn:feature_class":"P",
    "gn:feature_code":"PPL",
    "gn:name":"Turluk",
    "gn:population":0,
    "gn:timezone":"Europe/Istanbul",
    "iso:country":"TR",
    "name:tur_x_preferred":[
        "Turluk"
    ],
    "name:und_x_variant":[
        "Bozkhyuyuk"
    ],
    "wof:name":"Turluk",
    "wof:placetype":"locality"
},
  "geometry": {"coordinates":[38.94169,37.00341],"type":"Point"}
}