{
  "type": "Feature",
  "properties": {
    "gn:admin1_code":"37.0",
    "gn:asciiname":"Kayadibi",
    "gn:country_code":"TR",
    "gn:dem":652,
    "gn:feature_class":"P",
    "gn:feature_code":"PPL",
    "gn:name":"Kayadibi",
    "gn:population":0,
    "gn:timezone":"Europe/Istanbul",
    "iso:country":"TR",
    "name:und_x_variant":[
        "Zetceli"
    ],
    "wof:name":"Kayadibi",
    "wof:placetype":"locality"
},
  "geometry": {"coordinates":[33.68340999999999,41.86324000000001],"type":"Point"}
}