{
  "type": "Feature",
  "properties": {
    "gn:admin1_code":"66",
    "gn:asciiname":"Konurkale",
    "gn:country_code":"TR",
    "gn:dem":687,
    "gn:feature_class":"P",
    "gn:feature_code":"PPL",
    "gn:name":"Konurkale",
    "gn:population":0,
    "gn:timezone":"Europe/Istanbul",
    "iso:country":"TR",
    "name:tur_x_preferred":[
        "Konurkale"
    ],
    "wof:name":"Konurkale",
    "wof:placetype":"locality"
},
  "geometry": {"coordinates":[34.14524,39.78815],"type":"Point"}
}