{
  "type": "Feature",
  "properties": {
    "gn:admin1_code":"14",
    "gn:asciiname":"Tavukcuoglu",
    "gn:country_code":"TR",
    "gn:dem":479,
    "gn:feature_class":"P",
    "gn:feature_code":"PPL",
    "gn:name":"Tavuk\u00e7uo\u011flu",
    "gn:population":0,
    "gn:timezone":"Europe/Istanbul",
    "iso:country":"TR",
    "wof:name":"Tavukcuoglu",
    "wof:placetype":"locality"
},
  "geometry": {"coordinates":[31.97919000000001,40.95107],"type":"Point"}
}