{
  "type": "Feature",
  "properties": {
    "gn:admin1_code":"68",
    "gn:asciiname":"Sekerkoy",
    "gn:country_code":"TR",
    "gn:dem":1015,
    "gn:feature_class":"P",
    "gn:feature_code":"PPL",
    "gn:name":"\u015eekerk\u00f6y",
    "gn:population":0,
    "gn:timezone":"Europe/Istanbul",
    "iso:country":"TR",
    "name:und_x_variant":[
        "\u015eekerk\u00f6y\u00fc",
        "\u015eeker",
        "\u015eekerk\u00f6y"
    ],
    "wof:name":"Sekerkoy",
    "wof:placetype":"locality"
},
  "geometry": {"coordinates":[33.19171,39.15743],"type":"Point"}
}