{
  "type": "Feature",
  "properties": {
    "gn:admin1_code":"17",
    "gn:asciiname":"Gulpinar",
    "gn:country_code":"TR",
    "gn:dem":149,
    "gn:feature_class":"P",
    "gn:feature_code":"PPLA3",
    "gn:name":"G\u00fclp\u0131nar",
    "gn:population":0,
    "gn:timezone":"Europe/Istanbul",
    "iso:country":"TR",
    "name:und_x_variant":[
        "K\u00fcl\u00e2hl\u0131",
        "G\u00f6lp\u0131nar",
        "G\u00fclp\u0131nar"
    ],
    "wof:name":"Gulpinar",
    "wof:placetype":"locality"
},
  "geometry": {"coordinates":[26.12056,39.53278],"type":"Point"}
}