{
  "type": "Feature",
  "properties": {
    "gn:admin1_code":"2.0",
    "gn:asciiname":"Alisar",
    "gn:country_code":"TR",
    "gn:dem":634,
    "gn:feature_class":"P",
    "gn:feature_code":"PPL",
    "gn:name":"Alisar",
    "gn:population":0,
    "gn:timezone":"Europe/Istanbul",
    "iso:country":"TR",
    "wof:name":"Alisar",
    "wof:placetype":"locality"
},
  "geometry": {"coordinates":[38.00947,37.61492],"type":"Point"}
}