{
  "type": "Feature",
  "properties": {
    "gn:admin1_code":"09",
    "gn:asciiname":"Ikizdere",
    "gn:country_code":"TR",
    "gn:dem":160,
    "gn:feature_class":"P",
    "gn:feature_code":"PPL",
    "gn:name":"\u0130kizdere",
    "gn:population":0,
    "gn:timezone":"Europe/Istanbul",
    "iso:country":"TR",
    "name:tur_x_preferred":[
        "\u0130kizdere"
    ],
    "wof:name":"Ikizdere",
    "wof:placetype":"locality"
},
  "geometry": {"coordinates":[27.75473,37.91232],"type":"Point"}
}