{
  "type": "Feature",
  "properties": {
    "gn:admin1_code":"34.0",
    "gn:asciiname":"Basak",
    "gn:country_code":"TR",
    "gn:dem":45,
    "gn:feature_class":"P",
    "gn:feature_code":"PPL",
    "gn:name":"Ba\u015fak",
    "gn:population":0,
    "gn:timezone":"Europe/Istanbul",
    "iso:country":"TR",
    "name:und_x_variant":[
        "S\u0131vask\u00f6y",
        "Ba\u015fak",
        "Sivas",
        "Ba\u015fakk\u00f6y"
    ],
    "wof:name":"Basak",
    "wof:placetype":"locality"
},
  "geometry": {"coordinates":[28.44497,41.33288],"type":"Point"}
}