{
  "type": "Feature",
  "properties": {
    "gn:admin1_code":"54.0",
    "gn:asciiname":"Dikmen",
    "gn:country_code":"TR",
    "gn:dem":819,
    "gn:feature_class":"P",
    "gn:feature_code":"PPL",
    "gn:name":"Dikmen",
    "gn:population":0,
    "gn:timezone":"Europe/Istanbul",
    "iso:country":"TR",
    "name:tur_x_preferred":[
        "Dikmen"
    ],
    "wof:name":"Dikmen",
    "wof:placetype":"locality"
},
  "geometry": {"coordinates":[30.90146,40.69886],"type":"Point"}
}