{
  "type": "Feature",
  "properties": {
    "gn:admin1_code":"26",
    "gn:asciiname":"Sevinc",
    "gn:country_code":"TR",
    "gn:dem":787,
    "gn:elevation":"831.0",
    "gn:feature_class":"P",
    "gn:feature_code":"PPL",
    "gn:name":"Sevin\u00e7",
    "gn:population":1281,
    "gn:timezone":"Europe/Istanbul",
    "iso:country":"TR",
    "name:und_x_variant":[
        "Sevin\u00e7 K\u00f6y",
        "Sevin\u00e7"
    ],
    "wof:name":"Sevinc",
    "wof:placetype":"locality",
    "wof:population":1281
},
  "geometry": {"coordinates":[30.68889,39.78],"type":"Point"}
}