{
  "type": "Feature",
  "properties": {
    "gn:country":"TR",
    "gn:fcode":"PPLA2",
    "gn:pop":35472,
    "iso:country":"TR",
    "name:aze_x_preferred":[
        "X\u0131n\u0131s"
    ],
    "name:ceb_x_preferred":[
        "H\u0131n\u0131s \u0130l\u00e7esi"
    ],
    "name:ckb_x_preferred":[
        "\u062e\u0646\u0648\u0648\u0633"
    ],
    "name:deu_x_preferred":[
        "H\u0131n\u0131s"
    ],
    "name:diq_x_preferred":[
        "X\u0131n\u0131s"
    ],
    "name:eng_x_preferred":[
        "H\u0131n\u0131s"
    ],
    "name:fas_x_preferred":[
        "\u062e\u0646\u0633"
    ],
    "name:fra_x_preferred":[
        "H\u0131n\u0131s"
    ],
    "name:hye_x_preferred":[
        "\u053d\u0576\u0578\u0582\u057d"
    ],
    "name:kur_x_preferred":[
        "Xin\u00fbs"
    ],
    "name:lbe_x_preferred":[
        "\u0425\u044b\u043d\u044b\u0441"
    ],
    "name:mrj_x_preferred":[
        "\u0425\u044b\u043d\u044b\u0441"
    ],
    "name:msa_x_preferred":[
        "H\u0131n\u0131s"
    ],
    "name:nld_x_preferred":[
        "H\u0131n\u0131s"
    ],
    "name:nno_x_preferred":[
        "H\u0131n\u0131s"
    ],
    "name:nob_x_preferred":[
        "H\u0131n\u0131s"
    ],
    "name:ron_x_preferred":[
        "H\u0131n\u0131s"
    ],
    "name:rus_x_preferred":[
        "\u0425\u044b\u043d\u044b\u0441"
    ],
    "name:swa_x_preferred":[
        "H\u0131n\u0131s"
    ],
    "name:tur_x_preferred":[
        "H\u0131n\u0131s"
    ],
    "name:vie_x_preferred":[
        "H\u0131n\u0131s"
    ],
    "name:zho_x_preferred":[
        "\u8d6b\u8a25\u65af"
    ],
    "qs:name":"H\u0131n\u0131s",
    "qs:name_adm0":"Turkey",
    "qs:name_adm1":"Erzurum",
    "qs:photos_9k":1,
    "qs:photos_9r":1,
    "qs:photos_all":1,
    "qs:photos_sr":0,
    "qs:placetype":"Town",
    "qs:pop_sr":"7",
    "wd:wordcount":95,
    "wof:name":"H\u0131n\u0131s",
    "wof:placetype":"locality",
    "wof:population":35472
},
  "geometry": {"coordinates":[41.70222,39.3606],"type":"Point"}
}