{
  "type": "Feature",
  "properties": {
    "gn:admin1_code":"43",
    "gn:asciiname":"Senlik",
    "gn:country_code":"TR",
    "gn:dem":1077,
    "gn:feature_class":"P",
    "gn:feature_code":"PPL",
    "gn:name":"\u015eenlik",
    "gn:population":0,
    "gn:timezone":"Europe/Istanbul",
    "iso:country":"TR",
    "name:und_x_variant":[
        "Abdum",
        "Ablum",
        "\u015eenlik"
    ],
    "wof:name":"Senlik",
    "wof:placetype":"locality"
},
  "geometry": {"coordinates":[29.70645,39.58015],"type":"Point"}
}