{
  "type": "Feature",
  "properties": {
    "gn:admin1_code":"20",
    "gn:asciiname":"Almandamlari",
    "gn:country_code":"TR",
    "gn:dem":536,
    "gn:feature_class":"P",
    "gn:feature_code":"PPL",
    "gn:name":"Almandamlar\u0131",
    "gn:population":0,
    "gn:timezone":"Europe/Istanbul",
    "iso:country":"TR",
    "name:tur_x_preferred":[
        "Almandamlar\u0131"
    ],
    "wof:name":"Almandamlari",
    "wof:placetype":"locality"
},
  "geometry": {"coordinates":[28.81517,38.12242],"type":"Point"}
}