{
  "type": "Feature",
  "properties": {
    "gn:admin1_code":"37.0",
    "gn:asciiname":"Menuk",
    "gn:country_code":"TR",
    "gn:dem":389,
    "gn:feature_class":"P",
    "gn:feature_code":"PPL",
    "gn:name":"Men\u00fck",
    "gn:population":0,
    "gn:timezone":"Europe/Istanbul",
    "iso:country":"TR",
    "wof:name":"Menuk",
    "wof:placetype":"locality"
},
  "geometry": {"coordinates":[32.97935,41.79084],"type":"Point"}
}