{
  "type": "Feature",
  "properties": {
    "gn:country":"TR",
    "gn:fcode":"PPL",
    "gn:pop":2073,
    "iso:country":"TR",
    "name:dut_x_preferred":[
        "Tav\u015fanl\u0131"
    ],
    "name:eng_x_preferred":[
        "Tav\u015fanl\u0131"
    ],
    "name:ger_x_preferred":[
        "Tav\u015fanl\u0131"
    ],
    "name:hun_x_preferred":[
        "Tav\u015fanl\u0131"
    ],
    "name:rum_x_preferred":[
        "Tav\u015fanl\u0131"
    ],
    "name:tur_x_preferred":[
        "Tav\u015fanl\u0131"
    ],
    "name:vie_x_preferred":[
        "Tav\u015fanl\u0131"
    ],
    "qs:name":"Tav\u015fanl\u0131",
    "qs:photos_9r":0,
    "qs:photos_sr":0,
    "qs:pop_sr":"4",
    "wd:wordcount":222,
    "wof:name":"Tav\u015fanl\u0131",
    "wof:placetype":"locality",
    "wof:population":2073
},
  "geometry": {"coordinates":[29.51136,40.81876],"type":"Point"}
}