{
  "type": "Feature",
  "properties": {
    "gn:admin1_code":"65",
    "gn:asciiname":"Kiziloren",
    "gn:country_code":"TR",
    "gn:dem":2105,
    "gn:feature_class":"P",
    "gn:feature_code":"PPL",
    "gn:name":"K\u0131z\u0131l\u00f6ren",
    "gn:population":0,
    "gn:timezone":"Europe/Istanbul",
    "iso:country":"TR",
    "name:tur_x_preferred":[
        "K\u0131z\u0131l\u00f6ren"
    ],
    "name:und_x_variant":[
        "K\u0131z\u0131lviran"
    ],
    "wof:name":"Kiziloren",
    "wof:placetype":"locality"
},
  "geometry": {"coordinates":[43.55613,39.13333],"type":"Point"}
}