{
  "type": "Feature",
  "properties": {
    "gn:admin1_code":"25",
    "gn:asciiname":"Dilek",
    "gn:country_code":"TR",
    "gn:dem":1960,
    "gn:feature_class":"P",
    "gn:feature_code":"PPL",
    "gn:name":"Dilek",
    "gn:population":0,
    "gn:timezone":"Europe/Istanbul",
    "iso:country":"TR",
    "name:tur_x_preferred":[
        "Dilek"
    ],
    "wof:name":"Dilek",
    "wof:placetype":"locality"
},
  "geometry": {"coordinates":[41.77274,39.69679],"type":"Point"}
}