{
  "type": "Feature",
  "properties": {
    "gn:admin1_code":"22.0",
    "gn:asciiname":"Ibriktepe",
    "gn:country_code":"TR",
    "gn:dem":120,
    "gn:feature_class":"P",
    "gn:feature_code":"PPLA3",
    "gn:name":"\u0130briktepe",
    "gn:population":0,
    "gn:timezone":"Europe/Istanbul",
    "iso:country":"TR",
    "name:und_x_variant":[
        "\u0130briktepe"
    ],
    "wof:name":"Ibriktepe",
    "wof:placetype":"locality"
},
  "geometry": {"coordinates":[26.50343,41.01037],"type":"Point"}
}