{
  "type": "Feature",
  "properties": {
    "gn:admin1_code":"83.0",
    "gn:asciiname":"Kefersari",
    "gn:country_code":"TR",
    "gn:dem":537,
    "gn:feature_class":"P",
    "gn:feature_code":"PPL",
    "gn:name":"Kefersar\u0131",
    "gn:population":0,
    "gn:timezone":"Europe/Istanbul",
    "iso:country":"TR",
    "wof:name":"Kefersari",
    "wof:placetype":"locality"
},
  "geometry": {"coordinates":[37.58139,36.74361],"type":"Point"}
}