{
  "type": "Feature",
  "properties": {
    "gn:admin1_code":"09",
    "gn:asciiname":"Kircakli",
    "gn:country_code":"TR",
    "gn:dem":127,
    "gn:feature_class":"P",
    "gn:feature_code":"PPL",
    "gn:name":"K\u0131rcakl\u0131",
    "gn:population":0,
    "gn:timezone":"Europe/Istanbul",
    "iso:country":"TR",
    "name:und_x_variant":[
        "K\u0131rcatl\u0131",
        "K\u0131rcakl\u0131"
    ],
    "wof:name":"Kircakli",
    "wof:placetype":"locality"
},
  "geometry": {"coordinates":[28.37207,37.83443],"type":"Point"}
}