{
  "type": "Feature",
  "properties": {
    "gn:admin1_code":"12",
    "gn:asciiname":"Hacilar",
    "gn:country_code":"TR",
    "gn:dem":1574,
    "gn:feature_class":"P",
    "gn:feature_code":"PPL",
    "gn:name":"Hac\u0131lar",
    "gn:population":0,
    "gn:timezone":"Europe/Istanbul",
    "iso:country":"TR",
    "name:und_x_variant":[
        "Hac\u0131yan",
        "Hac\u0131lar"
    ],
    "wof:name":"Hacilar",
    "wof:placetype":"locality"
},
  "geometry": {"coordinates":[40.82271,39.09868],"type":"Point"}
}