{
  "type": "Feature",
  "properties": {
    "gn:admin1_code":"84.0",
    "gn:asciiname":"Yukari Sallipinar",
    "gn:country_code":"TR",
    "gn:dem":2077,
    "gn:feature_class":"P",
    "gn:feature_code":"PPL",
    "gn:name":"Yukar\u0131 Sall\u0131p\u0131nar",
    "gn:population":0,
    "gn:timezone":"Europe/Istanbul",
    "iso:country":"TR",
    "name:tur_x_preferred":[
        "Yukar\u0131 Sall\u0131p\u0131nar"
    ],
    "name:und_x_variant":[
        "Yukar\u0131salut",
        "Yukar\u0131sall\u0131p\u0131nar"
    ],
    "wof:name":"Yukari Sallipinar",
    "wof:placetype":"locality"
},
  "geometry": {"coordinates":[42.61644,40.43702],"type":"Point"}
}