{
  "type": "Feature",
  "properties": {
    "gn:country":"TR",
    "gn:fcode":"PPL",
    "gn:pop":0,
    "iso:country":"TR",
    "name:ceb_x_preferred":[
        "Kozca\u011f\u0131z"
    ],
    "name:eng_x_preferred":[
        "Kozca\u011f\u0131z"
    ],
    "name:nld_x_preferred":[
        "Kozca\u011f\u0131z"
    ],
    "name:tur_x_preferred":[
        "Kozca\u011f\u0131z"
    ],
    "name:unk_x_variant":[
        "Ahmetler"
    ],
    "name:vie_x_preferred":[
        "Kozca\u011f\u0131z"
    ],
    "qs:name":"Kozca\u011f\u0131z",
    "qs:name_adm0":"Turkey",
    "qs:name_adm1":"Bart\u0131n",
    "qs:photos_9k":1,
    "qs:photos_9r":1,
    "qs:photos_all":8,
    "qs:photos_sr":0,
    "qs:placetype":"Town",
    "qs:pop_sr":"0",
    "wd:wordcount":61,
    "wof:name":"Kozca\u011f\u0131z",
    "wof:placetype":"locality",
    "wof:population":0
},
  "geometry": {"coordinates":[32.33333,41.48333],"type":"Point"}
}