{
  "type": "Feature",
  "properties": {
    "gn:admin1_code":"43",
    "gn:asciiname":"Gulludere",
    "gn:country_code":"TR",
    "gn:dem":1405,
    "gn:feature_class":"P",
    "gn:feature_code":"PPL",
    "gn:name":"G\u00fcll\u00fcdere",
    "gn:population":0,
    "gn:timezone":"Europe/Istanbul",
    "iso:country":"TR",
    "wof:name":"Gulludere",
    "wof:placetype":"locality"
},
  "geometry": {"coordinates":[30.37056,39.4125],"type":"Point"}
}