{
  "type": "Feature",
  "properties": {
    "gn:country":"TR",
    "gn:fcode":"PPL",
    "gn:population":0,
    "iso:country":"TR",
    "name:ceb_x_preferred":[
        "Ye\u015filyurt"
    ],
    "name:deu_x_preferred":[
        "Ye\u015filyurt"
    ],
    "name:diq_x_preferred":[
        "Ye\u015filyurt"
    ],
    "name:eng_x_preferred":[
        "Ye\u015filyurt"
    ],
    "name:nld_x_preferred":[
        "Ye\u015filyurt"
    ],
    "name:por_x_preferred":[
        "Ye\u015filyurt"
    ],
    "name:spa_x_preferred":[
        "Ye\u015filyurt"
    ],
    "name:swe_x_preferred":[
        "Ye\u015filyurt"
    ],
    "name:tur_x_preferred":[
        "Yeniyurt"
    ],
    "name:tur_x_variant":[
        "Yenik\u00f6y",
        "Ye\u015filyurt"
    ],
    "name:uzb_x_preferred":[
        "Ye\u015filyurt"
    ],
    "qs:name":"Yesilyurt",
    "qs:name_adm0":"Turkey",
    "qs:name_adm1":"Adana",
    "qs:photos":53,
    "qs:photos_1k":11,
    "qs:photos_9k":1,
    "qs:photos_9r":2,
    "qs:photos_all":53,
    "qs:photos_sr":2,
    "qs:placetype":"Suburb",
    "qs:pop_sr":"0",
    "wd:wordcount":259,
    "wof:name":"Yesilyurt",
    "wof:placetype":"neighbourhood",
    "wof:population":0
},
  "geometry": {"coordinates":[36.15156,36.88555],"type":"Point"}
}