{
  "type": "Feature",
  "properties": {
    "gn:admin1_code":"14",
    "gn:asciiname":"Kalemler",
    "gn:country_code":"TR",
    "gn:dem":928,
    "gn:feature_class":"P",
    "gn:feature_code":"PPL",
    "gn:name":"Kalemler",
    "gn:population":0,
    "gn:timezone":"Europe/Istanbul",
    "iso:country":"TR",
    "wof:name":"Kalemler",
    "wof:placetype":"locality"
},
  "geometry": {"coordinates":[32.23811,40.91894],"type":"Point"}
}