{
  "type": "Feature",
  "properties": {
    "gn:admin1_code":"70",
    "gn:asciiname":"Cevireli",
    "gn:country_code":"TR",
    "gn:dem":1857,
    "gn:feature_class":"P",
    "gn:feature_code":"PPL",
    "gn:name":"\u00c7evireli",
    "gn:population":0,
    "gn:timezone":"Europe/Istanbul",
    "iso:country":"TR",
    "name:und_x_variant":[
        "G\u00f6rike",
        "\u00c7evireli",
        "K\u00f6vrik"
    ],
    "wof:name":"Cevireli",
    "wof:placetype":"locality"
},
  "geometry": {"coordinates":[44.32478,37.497],"type":"Point"}
}