{
  "type": "Feature",
  "properties": {
    "gn:admin1_code":"37.0",
    "gn:asciiname":"Kostekciler",
    "gn:country_code":"TR",
    "gn:dem":1222,
    "gn:feature_class":"P",
    "gn:feature_code":"PPL",
    "gn:name":"K\u00f6stek\u00e7iler",
    "gn:population":0,
    "gn:timezone":"Europe/Istanbul",
    "iso:country":"TR",
    "wof:name":"Kostekciler",
    "wof:placetype":"locality"
},
  "geometry": {"coordinates":[33.57417,41.80069],"type":"Point"}
}