{
  "type": "Feature",
  "properties": {
    "gn:admin1_code":"63",
    "gn:asciiname":"Erecek",
    "gn:country_code":"TR",
    "gn:dem":432,
    "gn:feature_class":"P",
    "gn:feature_code":"PPL",
    "gn:name":"Erecek",
    "gn:population":0,
    "gn:timezone":"Europe/Istanbul",
    "iso:country":"TR",
    "name:tur_x_preferred":[
        "Erecek"
    ],
    "name:und_x_variant":[
        "Biryakup",
        "Biriyakup"
    ],
    "wof:name":"Erecek",
    "wof:placetype":"locality"
},
  "geometry": {"coordinates":[38.73277,36.8111],"type":"Point"}
}