{
  "type": "Feature",
  "properties": {
    "gn:admin1_code":"89",
    "gn:asciiname":"Hocamatlar",
    "gn:country_code":"TR",
    "gn:dem":859,
    "gn:feature_class":"P",
    "gn:feature_code":"PPL",
    "gn:name":"Hocamatlar",
    "gn:population":0,
    "gn:timezone":"Europe/Istanbul",
    "iso:country":"TR",
    "wof:name":"Hocamatlar",
    "wof:placetype":"locality"
},
  "geometry": {"coordinates":[32.48121,40.92514],"type":"Point"}
}