{
  "type": "Feature",
  "properties": {
    "gn:admin1_code":"57.0",
    "gn:asciiname":"Sofu",
    "gn:country_code":"TR",
    "gn:dem":658,
    "gn:feature_class":"P",
    "gn:feature_code":"PPL",
    "gn:name":"Sofu",
    "gn:population":0,
    "gn:timezone":"Europe/Istanbul",
    "iso:country":"TR",
    "wof:name":"Sofu",
    "wof:placetype":"locality"
},
  "geometry": {"coordinates":[34.68333,41.78333],"type":"Point"}
}