{
  "type": "Feature",
  "properties": {
    "gn:admin1_code":"71",
    "gn:asciiname":"Kundullu",
    "gn:country_code":"TR",
    "gn:dem":1169,
    "gn:feature_class":"P",
    "gn:feature_code":"PPL",
    "gn:name":"Kundullu",
    "gn:population":0,
    "gn:timezone":"Europe/Istanbul",
    "iso:country":"TR",
    "wof:name":"Kundullu",
    "wof:placetype":"locality"
},
  "geometry": {"coordinates":[31.78417,38.47278],"type":"Point"}
}