{
  "type": "Feature",
  "properties": {
    "gn:admin1_code":"50",
    "gn:asciiname":"Kusakli",
    "gn:country_code":"TR",
    "gn:dem":1106,
    "gn:feature_class":"P",
    "gn:feature_code":"PPL",
    "gn:name":"Ku\u015fakl\u0131",
    "gn:population":0,
    "gn:timezone":"Europe/Istanbul",
    "iso:country":"TR",
    "name:cat_x_preferred":[
        "Serisa"
    ],
    "name:deu_x_preferred":[
        "Ku\u015fakl\u0131"
    ],
    "name:fra_x_preferred":[
        "Ku\u015fakl\u0131"
    ],
    "name:glg_x_preferred":[
        "Serisa"
    ],
    "name:hun_x_preferred":[
        "Szarisszasz"
    ],
    "name:tur_x_preferred":[
        "Sarissa"
    ],
    "name:und_x_variant":[
        "Ku\u015fakl\u0131"
    ],
    "wof:name":"Kusakli",
    "wof:placetype":"locality"
},
  "geometry": {"coordinates":[34.61021,39.29174],"type":"Point"}
}