{
  "type": "Feature",
  "properties": {
    "gn:admin1_code":"57.0",
    "gn:asciiname":"Calpinar",
    "gn:country_code":"TR",
    "gn:dem":1134,
    "gn:feature_class":"P",
    "gn:feature_code":"PPL",
    "gn:name":"\u00c7alp\u0131nar",
    "gn:population":0,
    "gn:timezone":"Europe/Istanbul",
    "iso:country":"TR",
    "name:und_x_variant":[
        "\u00c7al\u0131p\u0131nar",
        "Cal\u0131p\u0131nar K\u00f6y",
        "\u00c7al\u0131p\u0131nar K\u00f6y\u00fc",
        "\u00c7alp\u0131nar"
    ],
    "wof:name":"Calpinar",
    "wof:placetype":"locality"
},
  "geometry": {"coordinates":[34.63194,41.30118],"type":"Point"}
}