{
  "type": "Feature",
  "properties": {
    "gn:admin1_code":"68.0",
    "gn:asciiname":"Cukurundere",
    "gn:country_code":"TR",
    "gn:dem":1485,
    "gn:feature_class":"P",
    "gn:feature_code":"PPL",
    "gn:name":"\u00c7ukurundere",
    "gn:population":0,
    "gn:timezone":"Europe/Istanbul",
    "iso:country":"TR",
    "wof:name":"Cukurundere",
    "wof:placetype":"locality"
},
  "geometry": {"coordinates":[32.92691,40.37582],"type":"Point"}
}