{
  "type": "Feature",
  "properties": {
    "gn:admin1_code":"14",
    "gn:asciiname":"Birinci Afsar",
    "gn:country_code":"TR",
    "gn:dem":1191,
    "gn:feature_class":"P",
    "gn:feature_code":"PPL",
    "gn:name":"Birinci Af\u015far",
    "gn:population":0,
    "gn:timezone":"Europe/Istanbul",
    "iso:country":"TR",
    "name:tur_x_preferred":[
        "Birinci Af\u015far"
    ],
    "wof:name":"Birinci Afsar",
    "wof:placetype":"locality"
},
  "geometry": {"coordinates":[32.29768,40.74266],"type":"Point"}
}