{
  "type": "Feature",
  "properties": {
    "gn:country":"TR",
    "gn:fcode":"PPLA2",
    "gn:population":5035,
    "iso:country":"TR",
    "name:ast_x_preferred":[
        "Derebucak"
    ],
    "name:bul_x_preferred":[
        "\u0414\u0435\u0440\u0435\u0431\u0443\u0434\u0436\u0430\u043a"
    ],
    "name:ceb_x_preferred":[
        "Derebucak \u0130l\u00e7esi"
    ],
    "name:che_x_preferred":[
        "\u0414\u0435\u0440\u0435\u0431\u0443\u0434\u0436\u0430\u043a"
    ],
    "name:deu_x_preferred":[
        "Derebucak"
    ],
    "name:diq_x_preferred":[
        "Derebucak"
    ],
    "name:ell_x_preferred":[
        "\u039d\u03c4\u03b5\u03c1\u03b5\u03bc\u03c0\u03bf\u03c5\u03c4\u03b6\u03ac\u03ba"
    ],
    "name:eng_x_preferred":[
        "Derebucak"
    ],
    "name:fas_x_preferred":[
        "\u062f\u0631\u0628\u0648\u062c\u0627\u06a9"
    ],
    "name:fra_x_preferred":[
        "Derebucak"
    ],
    "name:ita_x_preferred":[
        "Distretto di Derebucak"
    ],
    "name:kur_x_preferred":[
        "Derebucak"
    ],
    "name:mrj_x_preferred":[
        "\u0414\u0435\u0440\u0435\u0431\u0443\u0434\u0436\u0430\u043a"
    ],
    "name:msa_x_preferred":[
        "Derebucak"
    ],
    "name:nan_x_preferred":[
        "Derebucak"
    ],
    "name:nld_x_preferred":[
        "Derebucak"
    ],
    "name:nob_x_preferred":[
        "Derebucak"
    ],
    "name:spa_x_preferred":[
        "Derebucak"
    ],
    "name:swa_x_preferred":[
        "Derebucak"
    ],
    "name:tat_x_preferred":[
        "\u0414\u0435\u0440\u0435\u0431\u0443\u0497\u0430\u043a"
    ],
    "name:tur_x_preferred":[
        "Derebucak"
    ],
    "name:urd_x_preferred":[
        "\u062f\u06cc\u0631\u0628\u0648\u062c\u0627\u06a9"
    ],
    "name:vie_x_preferred":[
        "Derebucak"
    ],
    "qs:name":"Derebucak",
    "qs:name_adm0":"Turkey",
    "qs:name_adm1":"Konya",
    "qs:photos_9k":1,
    "qs:photos_9r":2,
    "qs:photos_all":29,
    "qs:photos_sr":0,
    "qs:placetype":"Town",
    "qs:pop_sr":"5",
    "wd:wordcount":148,
    "wof:name":"Derebucak",
    "wof:placetype":"locality",
    "wof:population":5035
},
  "geometry": {"coordinates":[31.50918,37.39179],"type":"Point"}
}