{
  "type": "Feature",
  "properties": {
    "gn:country":"TR",
    "gn:fcode":"PPLA2",
    "gn:pop":5035,
    "iso:country":"TR",
    "name:dut_x_preferred":[
        "Derebucak"
    ],
    "name:eng_x_preferred":[
        "Derebucak"
    ],
    "name:fre_x_preferred":[
        "Derebucak"
    ],
    "name:ger_x_preferred":[
        "Derebucak"
    ],
    "name:ita_x_preferred":[
        "Distretto di Derebucak"
    ],
    "name:kur_x_preferred":[
        "Derebucak"
    ],
    "name:may_x_preferred":[
        "Derebucak"
    ],
    "name:mrj_x_preferred":[
        "\u0414\u0435\u0440\u0435\u0431\u0443\u0434\u0436\u0430\u043a"
    ],
    "name:nan_x_preferred":[
        "Derebucak"
    ],
    "name:spa_x_preferred":[
        "Derebucak"
    ],
    "name:swa_x_preferred":[
        "Derebucak"
    ],
    "name:tur_x_preferred":[
        "Derebucak"
    ],
    "name:urd_x_preferred":[
        "\u062f\u06cc\u0631\u0628\u0648\u062c\u0627\u06a9"
    ],
    "name:vie_x_preferred":[
        "Derebucak"
    ],
    "qs:name":"Derebucak",
    "qs:name_adm0":"Turkey",
    "qs:name_adm1":"Konya",
    "qs:photos_9k":1,
    "qs:photos_9r":2,
    "qs:photos_all":29,
    "qs:photos_sr":0,
    "qs:placetype":"Town",
    "qs:pop_sr":"5",
    "wd:wordcount":148,
    "wof:name":"Derebucak",
    "wof:placetype":"locality",
    "wof:population":5035
},
  "geometry": {"coordinates":[31.50918,37.39179],"type":"Point"}
}