{
  "type": "Feature",
  "properties": {
    "gn:admin1_code":"22.0",
    "gn:asciiname":"Hidiraga",
    "gn:country_code":"TR",
    "gn:dem":76,
    "gn:feature_class":"P",
    "gn:feature_code":"PPL",
    "gn:name":"H\u0131d\u0131ra\u011fa",
    "gn:population":0,
    "gn:timezone":"Europe/Istanbul",
    "iso:country":"TR",
    "name:und_x_variant":[
        "H\u0131z\u0131ra\u011fa",
        "H\u0131d\u0131ra\u011fa"
    ],
    "wof:name":"Hidiraga",
    "wof:placetype":"locality"
},
  "geometry": {"coordinates":[26.65995,41.73686],"type":"Point"}
}