{
  "type": "Feature",
  "properties": {
    "gn:admin1_code":"31",
    "gn:asciiname":"Aknehir",
    "gn:country_code":"TR",
    "gn:dem":35,
    "gn:feature_class":"P",
    "gn:feature_code":"PPL",
    "gn:name":"Aknehir",
    "gn:population":0,
    "gn:timezone":"Europe/Istanbul",
    "iso:country":"TR",
    "name:tur_x_preferred":[
        "Aknehir"
    ],
    "wof:name":"Aknehir",
    "wof:placetype":"locality"
},
  "geometry": {"coordinates":[36.06841,36.09769],"type":"Point"}
}