{
  "type": "Feature",
  "properties": {
    "gn:admin1_code":"61.0",
    "gn:asciiname":"Derindere",
    "gn:country_code":"TR",
    "gn:dem":2117,
    "gn:feature_class":"P",
    "gn:feature_code":"PPL",
    "gn:name":"Derindere",
    "gn:population":0,
    "gn:timezone":"Europe/Istanbul",
    "iso:country":"TR",
    "name:und_x_variant":[
        "Mollaahmet"
    ],
    "wof:name":"Derindere",
    "wof:placetype":"locality"
},
  "geometry": {"coordinates":[40.34926,40.63636],"type":"Point"}
}