{
  "type": "Feature",
  "properties": {
    "gn:admin1_code":"90",
    "gn:asciiname":"Senlikce",
    "gn:cc2":"TR",
    "gn:country_code":"TR",
    "gn:dem":664,
    "gn:feature_class":"P",
    "gn:feature_code":"PPL",
    "gn:name":"\u015eenlik\u00e7e",
    "gn:population":0,
    "gn:timezone":"Europe/Istanbul",
    "iso:country":"TR",
    "name:und_x_variant":[
        "\u015eenik\u00e7e",
        "\u015eenlik\u00e7e"
    ],
    "wof:name":"Senlikce",
    "wof:placetype":"locality"
},
  "geometry": {"coordinates":[36.86722,36.87139000000001],"type":"Point"}
}