{
  "type": "Feature",
  "properties": {
    "gn:admin1_code":"59.0",
    "gn:asciiname":"Bahceagil",
    "gn:country_code":"TR",
    "gn:dem":151,
    "gn:feature_class":"P",
    "gn:feature_code":"PPL",
    "gn:name":"Bah\u00e7ea\u011f\u0131l",
    "gn:population":0,
    "gn:timezone":"Europe/Istanbul",
    "iso:country":"TR",
    "wof:name":"Bahceagil",
    "wof:placetype":"locality"
},
  "geometry": {"coordinates":[27.88611,41.34917],"type":"Point"}
}