{
  "type": "Feature",
  "properties": {
    "gn:admin1_code":"52.0",
    "gn:asciiname":"Kovanli",
    "gn:country_code":"TR",
    "gn:dem":28,
    "gn:feature_class":"P",
    "gn:feature_code":"PPL",
    "gn:name":"Kovanl\u0131",
    "gn:population":0,
    "gn:timezone":"Europe/Istanbul",
    "iso:country":"TR",
    "wof:name":"Kovanli",
    "wof:placetype":"locality"
},
  "geometry": {"coordinates":[37.65718,41.10769000000001],"type":"Point"}
}