{
  "type": "Feature",
  "properties": {
    "gn:admin1_code":"02",
    "gn:asciiname":"Karadut",
    "gn:country_code":"TR",
    "gn:dem":746,
    "gn:feature_class":"P",
    "gn:feature_code":"PPL",
    "gn:name":"Karadut",
    "gn:population":0,
    "gn:timezone":"Europe/Istanbul",
    "iso:country":"TR",
    "name:tur_x_preferred":[
        "Karadut"
    ],
    "wof:name":"Karadut",
    "wof:placetype":"locality"
},
  "geometry": {"coordinates":[38.53947,37.97988],"type":"Point"}
}