{
  "type": "Feature",
  "properties": {
    "gn:country":"TR",
    "gn:fcode":"PPL",
    "gn:pop":12794,
    "iso:country":"TR",
    "name:azb_x_preferred":[
        "\u0633\u0627\u0631\u06cc \u06af\u0648\u0644"
    ],
    "name:ceb_x_preferred":[
        "Sar\u0131g\u00f6l \u0130l\u00e7esi"
    ],
    "name:deu_x_preferred":[
        "Sar\u0131g\u00f6l"
    ],
    "name:eng_x_preferred":[
        "Sar\u0131g\u00f6l"
    ],
    "name:fas_x_preferred":[
        "\u0633\u0627\u0631\u06cc\u200c\u06af\u0644"
    ],
    "name:fra_x_preferred":[
        "Sar\u0131g\u00f6l"
    ],
    "name:ita_x_preferred":[
        "Distretto di Sar\u0131g\u00f6l"
    ],
    "name:mrj_x_preferred":[
        "\u0421\u0430\u0440\u044b\u0433\u04e7\u043b"
    ],
    "name:msa_x_preferred":[
        "Sar\u0131g\u00f6l"
    ],
    "name:nan_x_preferred":[
        "Sar\u0131g\u00f6l"
    ],
    "name:nld_x_preferred":[
        "Sar\u0131g\u00f6l"
    ],
    "name:nno_x_preferred":[
        "Sar\u0131g\u00f6l"
    ],
    "name:nob_x_preferred":[
        "Sar\u0131g\u00f6l"
    ],
    "name:pnb_x_preferred":[
        "\u0636\u0644\u0639 \u0633\u0627\u0631\u06cc\u06af\u0648\u0644"
    ],
    "name:rup_x_preferred":[
        "Sar\u0131g\u00f6l"
    ],
    "name:rus_x_preferred":[
        "\u0421\u0430\u0440\u044b\u0433\u0451\u043b\u044c"
    ],
    "name:swa_x_preferred":[
        "Sar\u0131g\u00f6l"
    ],
    "name:tur_x_preferred":[
        "Sar\u0131g\u00f6l"
    ],
    "name:urd_x_preferred":[
        "\u0633\u0627\u0631\u06cc\u06af\u0644"
    ],
    "name:vie_x_preferred":[
        "Sar\u0131g\u00f6l"
    ],
    "name:zho_x_preferred":[
        "\u85a9\u52d2\u683c\u723e"
    ],
    "qs:name":"Sar\u0131g\u00f6l",
    "qs:name_adm0":"Turkey",
    "qs:name_adm1":"Manisa",
    "qs:photos_9r":0,
    "qs:photos_sr":0,
    "qs:placetype":"Town",
    "qs:pop_sr":"6",
    "wd:wordcount":269,
    "wof:name":"Sar\u0131g\u00f6l",
    "wof:placetype":"locality",
    "wof:population":12794
},
  "geometry": {"coordinates":[28.69663,38.23953],"type":"Point"}
}