{
  "type": "Feature",
  "properties": {
    "gn:admin1_code":"09",
    "gn:asciiname":"Gumus Yenikoy",
    "gn:country_code":"TR",
    "gn:dem":34,
    "gn:feature_class":"P",
    "gn:feature_code":"PPL",
    "gn:name":"G\u00fcm\u00fc\u015f Yenik\u00f6y",
    "gn:population":0,
    "gn:timezone":"Europe/Istanbul",
    "iso:country":"TR",
    "name:tur_x_preferred":[
        "G\u00fcm\u00fc\u015f Yenik\u00f6y"
    ],
    "name:tur_x_variant":[
        "Yenik\u00f6y",
        "G\u00fcm\u00fc\u015fyeni"
    ],
    "wof:name":"Gumus Yenikoy",
    "wof:placetype":"locality"
},
  "geometry": {"coordinates":[27.51712,37.8596],"type":"Point"}
}