{
  "type": "Feature",
  "properties": {
    "gn:admin1_code":"20",
    "gn:asciiname":"Kizilcayar",
    "gn:country_code":"TR",
    "gn:dem":819,
    "gn:feature_class":"P",
    "gn:feature_code":"PPL",
    "gn:name":"K\u0131z\u0131lcayar",
    "gn:population":0,
    "gn:timezone":"Europe/Istanbul",
    "iso:country":"TR",
    "name:tur_x_preferred":[
        "K\u0131z\u0131lcayar"
    ],
    "wof:name":"Kizilcayar",
    "wof:placetype":"locality"
},
  "geometry": {"coordinates":[29.65798,38.20982],"type":"Point"}
}