{
  "type": "Feature",
  "properties": {
    "gn:admin1_code":"49",
    "gn:asciiname":"Guzeltepe",
    "gn:country_code":"TR",
    "gn:dem":1274,
    "gn:feature_class":"P",
    "gn:feature_code":"PPL",
    "gn:name":"G\u00fczeltepe",
    "gn:population":0,
    "gn:timezone":"Europe/Istanbul",
    "iso:country":"TR",
    "name:tur_x_preferred":[
        "G\u00fczeltepe"
    ],
    "name:und_x_variant":[
        "K\u00e2sor"
    ],
    "wof:name":"Guzeltepe",
    "wof:placetype":"locality"
},
  "geometry": {"coordinates":[41.43845,38.7734],"type":"Point"}
}