{
  "type": "Feature",
  "properties": {
    "gn:admin1_code":"74",
    "gn:asciiname":"Guhesin",
    "gn:country_code":"TR",
    "gn:dem":1682,
    "gn:feature_class":"P",
    "gn:feature_code":"PPL",
    "gn:name":"G\u00fche\u015fin",
    "gn:population":0,
    "gn:timezone":"Europe/Istanbul",
    "iso:country":"TR",
    "wof:name":"Guhesin",
    "wof:placetype":"locality"
},
  "geometry": {"coordinates":[42.73667,37.81833],"type":"Point"}
}