{
  "type": "Feature",
  "properties": {
    "iso:country":"TR",
    "name:eng_x_preferred":[
        "Ziverbey"
    ],
    "name:tur_x_preferred":[
        "Ziverbey"
    ],
    "wof:name":"Ziverbey",
    "wof:placetype":"neighbourhood"
},
  "geometry": {"coordinates":[29.04064280427315,40.98971235909637],"type":"Point"}
}