{
  "type": "Feature",
  "properties": {
    "gn:admin1_code":"76.0",
    "gn:asciiname":"Derol",
    "gn:country_code":"TR",
    "gn:dem":747,
    "gn:feature_class":"P",
    "gn:feature_code":"PPL",
    "gn:name":"Derol",
    "gn:population":0,
    "gn:timezone":"Europe/Istanbul",
    "iso:country":"TR",
    "name:tur_x_preferred":[
        "Derol"
    ],
    "wof:name":"Derol",
    "wof:placetype":"locality"
},
  "geometry": {"coordinates":[41.15108,37.71371],"type":"Point"}
}