{
  "type": "Feature",
  "properties": {
    "gn:admin1_code":"12",
    "gn:asciiname":"Ucyaka",
    "gn:country_code":"TR",
    "gn:dem":1527,
    "gn:feature_class":"P",
    "gn:feature_code":"PPL",
    "gn:name":"\u00dc\u00e7yaka",
    "gn:population":0,
    "gn:timezone":"Europe/Istanbul",
    "iso:country":"TR",
    "name:tur_x_preferred":[
        "\u00dc\u00e7yaka"
    ],
    "wof:name":"Ucyaka",
    "wof:placetype":"locality"
},
  "geometry": {"coordinates":[40.44176,38.85375],"type":"Point"}
}