{
  "type": "Feature",
  "properties": {
    "gn:admin1_code":"07",
    "gn:admin2_code":"7732191.0",
    "gn:asciiname":"Kemer",
    "gn:country_code":"TR",
    "gn:dem":1448,
    "gn:feature_class":"P",
    "gn:feature_code":"PPL",
    "gn:name":"Kemer",
    "gn:population":0,
    "gn:timezone":"Europe/Istanbul",
    "iso:country":"TR",
    "wof:name":"Kemer",
    "wof:placetype":"locality"
},
  "geometry": {"coordinates":[31.67249,38.10618],"type":"Point"}
}