{
  "type": "Feature",
  "properties": {
    "gn:admin1_code":"07",
    "gn:admin2_code":"7732191.0",
    "gn:asciiname":"Kemer",
    "gn:country_code":"TR",
    "gn:dem":1448,
    "gn:feature_class":"P",
    "gn:feature_code":"PPL",
    "gn:name":"Kemer",
    "gn:population":0,
    "gn:timezone":"Europe/Istanbul",
    "iso:country":"TR",
    "name:azb_x_preferred":[
        "\u06a9\u0645\u0631"
    ],
    "name:aze_x_preferred":[
        "K\u0259m\u0259r"
    ],
    "name:ceb_x_preferred":[
        "Kemer \u0130l\u00e7esi"
    ],
    "name:ces_x_preferred":[
        "Kemer"
    ],
    "name:deu_x_preferred":[
        "Kemer"
    ],
    "name:epo_x_preferred":[
        "Kemer"
    ],
    "name:est_x_preferred":[
        "Kemer"
    ],
    "name:fas_x_preferred":[
        "\u06a9\u0645\u0631"
    ],
    "name:fin_x_preferred":[
        "Kemer"
    ],
    "name:fra_x_preferred":[
        "Kemer"
    ],
    "name:hun_x_preferred":[
        "Kemer"
    ],
    "name:hye_x_preferred":[
        "\u053f\u0565\u0574\u0565\u0580"
    ],
    "name:ita_x_preferred":[
        "Kemer"
    ],
    "name:kaz_x_preferred":[
        "\u041a\u0435\u043c\u0435\u0440"
    ],
    "name:lbe_x_preferred":[
        "\u041a\u0435\u043c\u0435\u0440"
    ],
    "name:lit_x_preferred":[
        "Kemeras"
    ],
    "name:mkd_x_preferred":[
        "\u041a\u0435\u043c\u0435\u0440"
    ],
    "name:mrj_x_preferred":[
        "\u041a\u0435\u043c\u0435\u0440"
    ],
    "name:msa_x_preferred":[
        "Kemer"
    ],
    "name:nld_x_preferred":[
        "Kemer"
    ],
    "name:nno_x_preferred":[
        "Kemer"
    ],
    "name:nor_x_preferred":[
        "Kemer"
    ],
    "name:pol_x_preferred":[
        "Kemer"
    ],
    "name:ron_x_preferred":[
        "Kemer"
    ],
    "name:rus_x_preferred":[
        "\u041a\u0435\u043c\u0435\u0440"
    ],
    "name:swa_x_preferred":[
        "Kemer"
    ],
    "name:swe_x_preferred":[
        "Kemer"
    ],
    "name:tur_x_preferred":[
        "Kemer"
    ],
    "name:ukr_x_preferred":[
        "\u041a\u0435\u043c\u0435\u0440"
    ],
    "name:urd_x_preferred":[
        "\u06a9\u0645\u0631"
    ],
    "name:vie_x_preferred":[
        "Kemer"
    ],
    "name:zho_x_preferred":[
        "\u51f1\u6885\u723e"
    ],
    "wof:name":"Kemer",
    "wof:placetype":"locality"
},
  "geometry": {"coordinates":[31.67249,38.10618],"type":"Point"}
}