{
  "type": "Feature",
  "properties": {
    "gn:admin1_code":"69.0",
    "gn:asciiname":"Mescitli",
    "gn:country_code":"TR",
    "gn:dem":1119,
    "gn:feature_class":"P",
    "gn:feature_code":"PPL",
    "gn:name":"Mescitli",
    "gn:population":0,
    "gn:timezone":"Europe/Istanbul",
    "iso:country":"TR",
    "name:und_x_variant":[
        "Be\u015fkilise",
        "Mescitli"
    ],
    "wof:name":"Mescitli",
    "wof:placetype":"locality"
},
  "geometry": {"coordinates":[39.42688,40.51143],"type":"Point"}
}