{
  "type": "Feature",
  "properties": {
    "gn:admin1_code":"62",
    "gn:asciiname":"Kervan",
    "gn:country_code":"TR",
    "gn:dem":1193,
    "gn:feature_class":"P",
    "gn:feature_code":"PPL",
    "gn:name":"Kervan",
    "gn:population":0,
    "gn:timezone":"Europe/Istanbul",
    "iso:country":"TR",
    "wof:name":"Kervan",
    "wof:placetype":"locality"
},
  "geometry": {"coordinates":[39.78333,39.33333],"type":"Point"}
}