{
  "type": "Feature",
  "properties": {
    "gn:country":"TR",
    "gn:fcode":"PPL",
    "gn:population":133959,
    "iso:country":"TR",
    "name:deu_x_preferred":[
        "\u0130neg\u00f6l"
    ],
    "name:eng_x_preferred":[
        "\u0130neg\u00f6l"
    ],
    "name:pol_x_preferred":[
        "\u0130neg\u00f6l"
    ],
    "name:tur_x_preferred":[
        "\u0130neg\u00f6l"
    ],
    "qs:name":"Inegeul",
    "qs:photos_9r":0,
    "qs:photos_sr":0,
    "qs:pop_sr":"9",
    "wof:name":"Inegeul",
    "wof:placetype":"locality",
    "wof:population":133959
},
  "geometry": {"coordinates":[29.51333,40.07806],"type":"Point"}
}