{
  "type": "Feature",
  "properties": {
    "gn:admin1_code":"73",
    "gn:asciiname":"Okcu",
    "gn:country_code":"TR",
    "gn:dem":1283,
    "gn:feature_class":"P",
    "gn:feature_code":"PPL",
    "gn:name":"Ok\u00e7u",
    "gn:population":0,
    "gn:timezone":"Europe/Istanbul",
    "iso:country":"TR",
    "name:und_x_variant":[
        "Ok\u00e7a",
        "Ok\u00e7u"
    ],
    "wof:name":"Okcu",
    "wof:placetype":"locality"
},
  "geometry": {"coordinates":[34.54389,37.93741],"type":"Point"}
}