{
  "type": "Feature",
  "properties": {
    "gn:admin1_code":"14",
    "gn:asciiname":"Ciller",
    "gn:country_code":"TR",
    "gn:dem":880,
    "gn:feature_class":"P",
    "gn:feature_code":"PPL",
    "gn:name":"\u00c7iller",
    "gn:population":0,
    "gn:timezone":"Europe/Istanbul",
    "iso:country":"TR",
    "wof:name":"Ciller",
    "wof:placetype":"locality"
},
  "geometry": {"coordinates":[31.28119,40.50262],"type":"Point"}
}