{
  "type": "Feature",
  "properties": {
    "gn:admin1_code":"13.0",
    "gn:asciiname":"Kaganli",
    "gn:country_code":"TR",
    "gn:dem":1910,
    "gn:feature_class":"P",
    "gn:feature_code":"PPL",
    "gn:name":"Ka\u011fanl\u0131",
    "gn:population":0,
    "gn:timezone":"Europe/Istanbul",
    "iso:country":"TR",
    "name:tur_x_preferred":[
        "Ka\u011f\u0131nl\u0131"
    ],
    "name:tur_x_variant":[
        "Ka\u011fanl\u0131"
    ],
    "wof:name":"Kaganli",
    "wof:placetype":"locality"
},
  "geometry": {"coordinates":[42.71624,38.34966],"type":"Point"}
}