{
  "type": "Feature",
  "properties": {
    "gn:admin1_code":"13",
    "gn:asciiname":"Karinca",
    "gn:country_code":"TR",
    "gn:dem":1119,
    "gn:feature_class":"P",
    "gn:feature_code":"PPL",
    "gn:name":"Kar\u0131nca",
    "gn:population":0,
    "gn:timezone":"Europe/Istanbul",
    "iso:country":"TR",
    "name:tur_x_preferred":[
        "Kar\u0131nca"
    ],
    "wof:name":"Karinca",
    "wof:placetype":"locality"
},
  "geometry": {"coordinates":[41.96962,38.272],"type":"Point"}
}