{
  "type": "Feature",
  "properties": {
    "gn:admin1_code":"65.0",
    "gn:asciiname":"Unsal",
    "gn:country_code":"TR",
    "gn:dem":1974,
    "gn:feature_class":"P",
    "gn:feature_code":"PPL",
    "gn:name":"Unsal",
    "gn:population":0,
    "gn:timezone":"Europe/Istanbul",
    "iso:country":"TR",
    "name:tur_x_preferred":[
        "Unsal"
    ],
    "wof:name":"Unsal",
    "wof:placetype":"locality"
},
  "geometry": {"coordinates":[42.84234,38.05225],"type":"Point"}
}