{
  "type": "Feature",
  "properties": {
    "iso:country":"TR",
    "name:eng_x_preferred":[
        "Ihsaniye"
    ],
    "name:tur_x_preferred":[
        "\u0130hsaniye"
    ],
    "wof:name":"Ihsaniye",
    "wof:placetype":"neighbourhood"
},
  "geometry": {"coordinates":[28.36066292034882,41.25534855436361],"type":"Point"}
}