{
  "type": "Feature",
  "properties": {
    "gn:admin1_code":"68",
    "gn:asciiname":"Yukarisebil",
    "gn:country_code":"TR",
    "gn:dem":1059,
    "gn:feature_class":"P",
    "gn:feature_code":"PPL",
    "gn:name":"Yukar\u0131sebil",
    "gn:population":0,
    "gn:timezone":"Europe/Istanbul",
    "iso:country":"TR",
    "name:und_x_variant":[
        "Sebilibal\u00e2",
        "Yukar\u0131sebil"
    ],
    "wof:name":"Yukarisebil",
    "wof:placetype":"locality"
},
  "geometry": {"coordinates":[32.73243,39.17199],"type":"Point"}
}