{
  "type": "Feature",
  "properties": {
    "gn:admin1_code":"17",
    "gn:asciiname":"Namazgah",
    "gn:country_code":"TR",
    "gn:dem":590,
    "gn:feature_class":"P",
    "gn:feature_code":"PPL",
    "gn:name":"Namazg\u00e2h",
    "gn:population":0,
    "gn:timezone":"Europe/Istanbul",
    "iso:country":"TR",
    "name:rus_x_preferred":[
        "\u041d\u0430\u043c\u0430\u0437\u0433\u0430\u0445"
    ],
    "name:tur_x_preferred":[
        "Namazg\u00e2hk\u00f6y"
    ],
    "name:tur_x_variant":[
        "Namaz",
        "Namazgah"
    ],
    "name:und_x_variant":[
        "Namazg\u00e2h"
    ],
    "wof:name":"Namazgah",
    "wof:placetype":"locality"
},
  "geometry": {"coordinates":[27.28867,39.89068],"type":"Point"}
}