{
  "type": "Feature",
  "properties": {
    "gn:admin1_code":"12",
    "gn:asciiname":"Comak",
    "gn:country_code":"TR",
    "gn:dem":1656,
    "gn:feature_class":"P",
    "gn:feature_code":"PPL",
    "gn:name":"\u00c7omak",
    "gn:population":0,
    "gn:timezone":"Europe/Istanbul",
    "iso:country":"TR",
    "name:und_x_variant":[
        "\u00c7omah",
        "\u00c7omak"
    ],
    "wof:name":"Comak",
    "wof:placetype":"locality"
},
  "geometry": {"coordinates":[40.25756,39.35788],"type":"Point"}
}