{
  "type": "Feature",
  "properties": {
    "gn:admin1_code":"70.0",
    "gn:asciiname":"Ormanli",
    "gn:country_code":"TR",
    "gn:dem":1681,
    "gn:feature_class":"P",
    "gn:feature_code":"PPL",
    "gn:name":"Ormanl\u0131",
    "gn:population":0,
    "gn:timezone":"Europe/Istanbul",
    "iso:country":"TR",
    "wof:name":"Ormanli",
    "wof:placetype":"locality"
},
  "geometry": {"coordinates":[43.40948,37.31126],"type":"Point"}
}