{
  "type": "Feature",
  "properties": {
    "gn:admin1_code":"45.0",
    "gn:asciiname":"Akyar",
    "gn:country_code":"TR",
    "gn:dem":631,
    "gn:feature_class":"P",
    "gn:feature_code":"PPL",
    "gn:name":"Akyar",
    "gn:population":0,
    "gn:timezone":"Europe/Istanbul",
    "iso:country":"TR",
    "name:tur_x_preferred":[
        "Akyar"
    ],
    "wof:name":"Akyar",
    "wof:placetype":"locality"
},
  "geometry": {"coordinates":[27.85,38.43333],"type":"Point"}
}