{
  "type": "Feature",
  "properties": {
    "gn:admin1_code":"69.0",
    "gn:asciiname":"Arpali",
    "gn:country_code":"TR",
    "gn:dem":1426,
    "gn:feature_class":"P",
    "gn:feature_code":"PPL",
    "gn:name":"Arpal\u0131",
    "gn:population":0,
    "gn:timezone":"Europe/Istanbul",
    "iso:country":"TR",
    "name:tur_x_preferred":[
        "Arpal\u0131"
    ],
    "wof:name":"Arpali",
    "wof:placetype":"locality"
},
  "geometry": {"coordinates":[39.13751,40.53648],"type":"Point"}
}