{
  "type": "Feature",
  "properties": {
    "gn:admin1_code":"65",
    "gn:asciiname":"Haydarbey",
    "gn:country_code":"TR",
    "gn:dem":1737,
    "gn:feature_class":"P",
    "gn:feature_code":"PPL",
    "gn:name":"Haydarbey",
    "gn:population":0,
    "gn:timezone":"Europe/Istanbul",
    "iso:country":"TR",
    "name:tur_x_preferred":[
        "Haydarbey"
    ],
    "wof:name":"Haydarbey",
    "wof:placetype":"locality"
},
  "geometry": {"coordinates":[43.42268,39.01117],"type":"Point"}
}