{
  "type": "Feature",
  "properties": {
    "gn:admin1_code":"66",
    "gn:asciiname":"Basinayayla",
    "gn:country_code":"TR",
    "gn:dem":1299,
    "gn:feature_class":"P",
    "gn:feature_code":"PPL",
    "gn:name":"Ba\u015f\u0131nayayla",
    "gn:population":0,
    "gn:timezone":"Europe/Istanbul",
    "iso:country":"TR",
    "wof:name":"Basinayayla",
    "wof:placetype":"locality"
},
  "geometry": {"coordinates":[34.78922,39.69686],"type":"Point"}
}