{
  "type": "Feature",
  "properties": {
    "gn:admin1_code":"63.0",
    "gn:asciiname":"Sarpdere",
    "gn:country_code":"TR",
    "gn:dem":611,
    "gn:feature_class":"P",
    "gn:feature_code":"PPL",
    "gn:name":"Sarpdere",
    "gn:population":0,
    "gn:timezone":"Europe/Istanbul",
    "iso:country":"TR",
    "name:tur_x_preferred":[
        "Sarpdere"
    ],
    "wof:name":"Sarpdere",
    "wof:placetype":"locality"
},
  "geometry": {"coordinates":[39.36411,37.04708],"type":"Point"}
}