{
  "type": "Feature",
  "properties": {
    "gn:admin1_code":"38",
    "gn:asciiname":"Bayramhaci",
    "gn:country_code":"TR",
    "gn:dem":984,
    "gn:feature_class":"P",
    "gn:feature_code":"PPL",
    "gn:name":"Bayramhac\u0131",
    "gn:population":0,
    "gn:timezone":"Europe/Istanbul",
    "iso:country":"TR",
    "name:und_x_variant":[
        "Bayramhac\u0131l\u0131",
        "Bayramhac\u0131"
    ],
    "wof:name":"Bayramhaci",
    "wof:placetype":"locality"
},
  "geometry": {"coordinates":[35.00510999999999,38.79264000000001],"type":"Point"}
}