{
  "type": "Feature",
  "properties": {
    "gn:admin1_code":"45",
    "gn:asciiname":"Piyadeler",
    "gn:country_code":"TR",
    "gn:dem":151,
    "gn:feature_class":"P",
    "gn:feature_code":"PPL",
    "gn:name":"Piyadeler",
    "gn:population":0,
    "gn:timezone":"Europe/Istanbul",
    "iso:country":"TR",
    "name:tur_x_preferred":[
        "Piyadeler"
    ],
    "wof:name":"Piyadeler",
    "wof:placetype":"locality"
},
  "geometry": {"coordinates":[28.44005,38.40655],"type":"Point"}
}