{
  "type": "Feature",
  "properties": {
    "gn:admin1_code":"10.0",
    "gn:asciiname":"Hodul",
    "gn:country_code":"TR",
    "gn:dem":565,
    "gn:feature_class":"P",
    "gn:feature_code":"PPL",
    "gn:name":"Hodul",
    "gn:population":0,
    "gn:timezone":"Europe/Istanbul",
    "iso:country":"TR",
    "name:tur_x_preferred":[
        "Hodul"
    ],
    "wof:name":"Hodul",
    "wof:placetype":"locality"
},
  "geometry": {"coordinates":[27.44995,40.1981],"type":"Point"}
}