{
  "type": "Feature",
  "properties": {
    "gn:admin1_code":"04",
    "gn:asciiname":"Topi",
    "gn:country_code":"TR",
    "gn:dem":1582,
    "gn:feature_class":"P",
    "gn:feature_code":"PPL",
    "gn:name":"Topi",
    "gn:population":0,
    "gn:timezone":"Europe/Istanbul",
    "iso:country":"TR",
    "name:heb_x_preferred":[
        "\u05d8\u05d5\u05e4\u05d9"
    ],
    "name:por_x_preferred":[
        "Topi"
    ],
    "name:und_x_variant":[
        "\u0130kig\u00f6z\u00fcm"
    ],
    "wof:name":"Topi",
    "wof:placetype":"locality"
},
  "geometry": {"coordinates":[42.676,39.4777],"type":"Point"}
}