{
  "type": "Feature",
  "properties": {
    "gn:admin1_code":"21",
    "gn:asciiname":"Korha",
    "gn:country_code":"TR",
    "gn:dem":1117,
    "gn:feature_class":"P",
    "gn:feature_code":"PPL",
    "gn:name":"K\u00f6rha",
    "gn:population":0,
    "gn:timezone":"Europe/Istanbul",
    "iso:country":"TR",
    "wof:name":"Korha",
    "wof:placetype":"locality"
},
  "geometry": {"coordinates":[40.56667,38.53333],"type":"Point"}
}