{
  "type": "Feature",
  "properties": {
    "gn:admin1_code":"43",
    "gn:asciiname":"Kayi",
    "gn:country_code":"TR",
    "gn:dem":856,
    "gn:feature_class":"P",
    "gn:feature_code":"PPL",
    "gn:name":"Kay\u0131",
    "gn:population":0,
    "gn:timezone":"Europe/Istanbul",
    "iso:country":"TR",
    "name:und_x_variant":[
        "Kay\u0131",
        "Kay\u0131k\u00f6y"
    ],
    "wof:name":"Kayi",
    "wof:placetype":"locality"
},
  "geometry": {"coordinates":[29.55646,39.52177],"type":"Point"}
}