{
  "type": "Feature",
  "properties": {
    "gn:admin1_code":"55.0",
    "gn:asciiname":"Olyas",
    "gn:country_code":"TR",
    "gn:dem":202,
    "gn:feature_class":"P",
    "gn:feature_code":"PPL",
    "gn:name":"Olyas",
    "gn:population":0,
    "gn:timezone":"Europe/Istanbul",
    "iso:country":"TR",
    "name:und_x_variant":[
        "\u00c7oban\u00f6z\u00fc"
    ],
    "wof:name":"Olyas",
    "wof:placetype":"locality"
},
  "geometry": {"coordinates":[36.25274,41.31076],"type":"Point"}
}