{
  "type": "Feature",
  "properties": {
    "gn:admin1_code":"11.0",
    "gn:asciiname":"Orhaniye",
    "gn:country_code":"TR",
    "gn:dem":480,
    "gn:feature_class":"P",
    "gn:feature_code":"PPL",
    "gn:name":"Orhaniye",
    "gn:population":0,
    "gn:timezone":"Europe/Istanbul",
    "iso:country":"TR",
    "name:tur_x_preferred":[
        "Orhaniye"
    ],
    "wof:name":"Orhaniye",
    "wof:placetype":"locality"
},
  "geometry": {"coordinates":[29.87628,40.33633],"type":"Point"}
}