{
  "type": "Feature",
  "properties": {
    "gn:admin1_code":"62.0",
    "gn:asciiname":"Kockuyusu",
    "gn:country_code":"TR",
    "gn:dem":1066,
    "gn:feature_class":"P",
    "gn:feature_code":"PPL",
    "gn:name":"Ko\u00e7kuyusu",
    "gn:population":0,
    "gn:timezone":"Europe/Istanbul",
    "iso:country":"TR",
    "name:tur_x_preferred":[
        "Ko\u00e7kuyusu"
    ],
    "wof:name":"Kockuyusu",
    "wof:placetype":"locality"
},
  "geometry": {"coordinates":[39.58596,38.9789],"type":"Point"}
}