{
  "type": "Feature",
  "properties": {
    "gn:admin1_code":"16.0",
    "gn:asciiname":"Kurucesme",
    "gn:country_code":"TR",
    "gn:dem":518,
    "gn:feature_class":"P",
    "gn:feature_code":"PPL",
    "gn:name":"Kuru\u00e7e\u015fme",
    "gn:population":0,
    "gn:timezone":"Europe/Istanbul",
    "iso:country":"TR",
    "name:und_x_variant":[
        "Kuru\u00e7e\u015fme K\u00f6y\u00fc",
        "Kuru\u00e7e\u015fme"
    ],
    "wof:name":"Kurucesme",
    "wof:placetype":"locality"
},
  "geometry": {"coordinates":[28.82236,40.12551],"type":"Point"}
}