{
  "type": "Feature",
  "properties": {
    "gn:admin1_code":"17.0",
    "gn:asciiname":"Caltikara",
    "gn:country_code":"TR",
    "gn:dem":238,
    "gn:feature_class":"P",
    "gn:feature_code":"PPL",
    "gn:name":"\u00c7alt\u0131kara",
    "gn:population":0,
    "gn:timezone":"Europe/Istanbul",
    "iso:country":"TR",
    "wof:name":"Caltikara",
    "wof:placetype":"locality"
},
  "geometry": {"coordinates":[26.81369,39.98249000000001],"type":"Point"}
}