{
  "type": "Feature",
  "properties": {
    "gn:admin1_code":"04",
    "gn:asciiname":"Saricavus",
    "gn:country_code":"TR",
    "gn:dem":1421,
    "gn:feature_class":"P",
    "gn:feature_code":"PPL",
    "gn:name":"Sar\u0131\u00e7avu\u015f",
    "gn:population":0,
    "gn:timezone":"Europe/Istanbul",
    "iso:country":"TR",
    "name:und_x_variant":[
        "Girberan",
        "G\u00fclveren",
        "G\u00fcrveren",
        "Sar\u0131\u00e7avu\u015f"
    ],
    "wof:name":"Saricavus",
    "wof:placetype":"locality"
},
  "geometry": {"coordinates":[44.40617,39.42663],"type":"Point"}
}