{
  "type": "Feature",
  "properties": {
    "gn:admin1_code":"28.0",
    "gn:asciiname":"Sahinyuva",
    "gn:country_code":"TR",
    "gn:dem":279,
    "gn:feature_class":"P",
    "gn:feature_code":"PPL",
    "gn:name":"\u015eahinyuva",
    "gn:population":0,
    "gn:timezone":"Europe/Istanbul",
    "iso:country":"TR",
    "name:tur_x_preferred":[
        "\u015eahinyuva"
    ],
    "wof:name":"Sahinyuva",
    "wof:placetype":"locality"
},
  "geometry": {"coordinates":[39.00268,40.95733],"type":"Point"}
}