{
  "type": "Feature",
  "properties": {
    "gn:admin1_code":"80",
    "gn:asciiname":"Kapanli",
    "gn:country_code":"TR",
    "gn:dem":1250,
    "gn:feature_class":"P",
    "gn:feature_code":"PPL",
    "gn:name":"Kapanl\u0131",
    "gn:population":0,
    "gn:timezone":"Europe/Istanbul",
    "iso:country":"TR",
    "name:und_x_variant":[
        "Eyri",
        "\u0130ri",
        "Eri",
        "\u0130rik\u00f6y",
        "Kapanl\u0131"
    ],
    "wof:name":"Kapanli",
    "wof:placetype":"locality"
},
  "geometry": {"coordinates":[42.15023,37.56855],"type":"Point"}
}