{
  "type": "Feature",
  "properties": {
    "gn:admin1_code":"54",
    "gn:asciiname":"Demiracma",
    "gn:country_code":"TR",
    "gn:dem":42,
    "gn:feature_class":"P",
    "gn:feature_code":"PPL",
    "gn:name":"Demira\u00e7ma",
    "gn:population":0,
    "gn:timezone":"Europe/Istanbul",
    "iso:country":"TR",
    "name:tur_x_preferred":[
        "Demira\u00e7ma"
    ],
    "wof:name":"Demiracma",
    "wof:placetype":"locality"
},
  "geometry": {"coordinates":[30.94546,41.04111],"type":"Point"}
}