{
  "type": "Feature",
  "properties": {
    "gn:admin1_code":"85.0",
    "gn:asciiname":"Comlekci",
    "gn:country_code":"TR",
    "gn:dem":302,
    "gn:feature_class":"P",
    "gn:feature_code":"PPL",
    "gn:name":"\u00c7\u00f6mlek\u00e7i",
    "gn:population":0,
    "gn:timezone":"Europe/Istanbul",
    "iso:country":"TR",
    "wof:name":"Comlekci",
    "wof:placetype":"locality"
},
  "geometry": {"coordinates":[31.61801,41.12987],"type":"Point"}
}