{
  "type": "Feature",
  "properties": {
    "gn:admin1_code":"35",
    "gn:asciiname":"Gereli",
    "gn:country_code":"TR",
    "gn:dem":130,
    "gn:feature_class":"P",
    "gn:feature_code":"PPL",
    "gn:name":"Gereli",
    "gn:population":0,
    "gn:timezone":"Europe/Istanbul",
    "iso:country":"TR",
    "name:tur_x_preferred":[
        "Gereli"
    ],
    "wof:name":"Gereli",
    "wof:placetype":"locality"
},
  "geometry": {"coordinates":[28.04741,38.20075],"type":"Point"}
}