{
  "type": "Feature",
  "properties": {
    "gn:admin1_code":"11",
    "gn:asciiname":"Akcapinar",
    "gn:country_code":"TR",
    "gn:dem":927,
    "gn:feature_class":"P",
    "gn:feature_code":"PPL",
    "gn:name":"Ak\u00e7ap\u0131nar",
    "gn:population":0,
    "gn:timezone":"Europe/Istanbul",
    "iso:country":"TR",
    "name:tur_x_preferred":[
        "Ak\u00e7ap\u0131nar"
    ],
    "wof:name":"Akcapinar",
    "wof:placetype":"locality"
},
  "geometry": {"coordinates":[30.05278,39.96014],"type":"Point"}
}