{
  "type": "Feature",
  "properties": {
    "gn:admin1_code":"14",
    "gn:asciiname":"Pasakoy",
    "gn:country_code":"TR",
    "gn:dem":752,
    "gn:feature_class":"P",
    "gn:feature_code":"PPL",
    "gn:name":"Pa\u015fak\u00f6y",
    "gn:population":0,
    "gn:timezone":"Europe/Istanbul",
    "iso:country":"TR",
    "wof:name":"Pasakoy",
    "wof:placetype":"locality"
},
  "geometry": {"coordinates":[31.57405,40.72868],"type":"Point"}
}