{
  "type": "Feature",
  "properties": {
    "gn:admin1_code":"09",
    "gn:admin2_code":"8632399.0",
    "gn:asciiname":"Isabeyli",
    "gn:country_code":"TR",
    "gn:dem":85,
    "gn:feature_class":"P",
    "gn:feature_code":"PPLA3",
    "gn:name":"\u0130sabeyli",
    "gn:population":4649,
    "gn:timezone":"Europe/Istanbul",
    "iso:country":"TR",
    "name:und_x_variant":[
        "\u0130sabeyli"
    ],
    "wof:name":"Isabeyli",
    "wof:placetype":"locality",
    "wof:population":4649
},
  "geometry": {"coordinates":[28.26475,37.90147],"type":"Point"}
}