{
  "type": "Feature",
  "properties": {
    "gn:admin1_code":"41.0",
    "gn:asciiname":"Bayraktar",
    "gn:country_code":"TR",
    "gn:dem":52,
    "gn:feature_class":"P",
    "gn:feature_code":"PPL",
    "gn:name":"Bayraktar",
    "gn:population":0,
    "gn:timezone":"Europe/Istanbul",
    "iso:country":"TR",
    "name:und_x_variant":[
        "Bayrakdar",
        "Bayraktar"
    ],
    "wof:name":"Bayraktar",
    "wof:placetype":"locality"
},
  "geometry": {"coordinates":[30.08923,40.7855],"type":"Point"}
}