{
  "type": "Feature",
  "properties": {
    "gn:admin1_code":"09",
    "gn:asciiname":"Akdam Mahallesi",
    "gn:country_code":"TR",
    "gn:dem":363,
    "gn:feature_class":"P",
    "gn:feature_code":"PPL",
    "gn:name":"Akdam Mahallesi",
    "gn:population":0,
    "gn:timezone":"Europe/Istanbul",
    "iso:country":"TR",
    "name:tur_x_preferred":[
        "Akdam Mahallesi"
    ],
    "wof:name":"Akdam Mahallesi",
    "wof:placetype":"locality"
},
  "geometry": {"coordinates":[28.54801,37.52081],"type":"Point"}
}