{
  "type": "Feature",
  "properties": {
    "gn:admin1_code":"07",
    "gn:asciiname":"Pinargozu",
    "gn:country_code":"TR",
    "gn:dem":840,
    "gn:feature_class":"P",
    "gn:feature_code":"PPL",
    "gn:name":"P\u0131narg\u00f6z\u00fc",
    "gn:population":0,
    "gn:timezone":"Europe/Istanbul",
    "iso:country":"TR",
    "wof:name":"Pinargozu",
    "wof:placetype":"locality"
},
  "geometry": {"coordinates":[31.01639,37.30139000000001],"type":"Point"}
}