{
  "type": "Feature",
  "properties": {
    "gn:admin1_code":"50",
    "gn:asciiname":"Tatlarin",
    "gn:country_code":"TR",
    "gn:dem":1082,
    "gn:feature_class":"P",
    "gn:feature_code":"PPL",
    "gn:name":"Tatlar\u0131n",
    "gn:population":0,
    "gn:timezone":"Europe/Istanbul",
    "iso:country":"TR",
    "name:und_x_variant":[
        "Tatlar\u0131n",
        "ball\u0131k mah",
        "Tatlar\u0131nk\u00f6y"
    ],
    "wof:name":"Tatlarin",
    "wof:placetype":"locality"
},
  "geometry": {"coordinates":[34.47998,38.63621],"type":"Point"}
}