{
  "type": "Feature",
  "properties": {
    "gn:admin1_code":"10",
    "gn:asciiname":"Yazlik",
    "gn:country_code":"TR",
    "gn:dem":405,
    "gn:feature_class":"P",
    "gn:feature_code":"PPL",
    "gn:name":"Yazl\u0131k",
    "gn:population":0,
    "gn:timezone":"Europe/Istanbul",
    "iso:country":"TR",
    "name:und_x_variant":[
        "Hort",
        "Yazl\u0131k"
    ],
    "wof:name":"Yazlik",
    "wof:placetype":"locality"
},
  "geometry": {"coordinates":[27.57689,39.79925],"type":"Point"}
}