{
  "type": "Feature",
  "properties": {
    "gn:admin1_code":"82.0",
    "gn:asciiname":"Goldagi",
    "gn:country_code":"TR",
    "gn:dem":1052,
    "gn:feature_class":"P",
    "gn:feature_code":"PPL",
    "gn:name":"G\u00f6lda\u011f\u0131",
    "gn:population":0,
    "gn:timezone":"Europe/Istanbul",
    "iso:country":"TR",
    "name:und_x_variant":[
        "G\u00f6lda\u011f",
        "G\u00f6lda\u011f K\u00f6y\u00fc",
        "G\u00f6lda\u011f\u0131"
    ],
    "wof:name":"Goldagi",
    "wof:placetype":"locality"
},
  "geometry": {"coordinates":[33.26,40.40126],"type":"Point"}
}