{
  "type": "Feature",
  "properties": {
    "gn:admin1_code":"81.0",
    "gn:asciiname":"Sahil",
    "gn:country_code":"TR",
    "gn:dem":4,
    "gn:feature_class":"P",
    "gn:feature_code":"PPL",
    "gn:name":"Sahil",
    "gn:population":0,
    "gn:timezone":"Europe/Istanbul",
    "iso:country":"TR",
    "name:ceb_x_preferred":[
        "Sahil"
    ],
    "name:fra_x_preferred":[
        "Sahil"
    ],
    "name:rus_x_preferred":[
        "\u0421\u0430\u0445\u0438\u043b"
    ],
    "name:swe_x_preferred":[
        "Sahil"
    ],
    "name:tur_x_preferred":[
        "Sahil"
    ],
    "wof:name":"Sahil",
    "wof:placetype":"locality"
},
  "geometry": {"coordinates":[35.90917,36.86178],"type":"Point"}
}