{
  "type": "Feature",
  "properties": {
    "gn:admin1_code":"26",
    "gn:asciiname":"Kocacobanpinari",
    "gn:country_code":"TR",
    "gn:dem":1267,
    "gn:feature_class":"P",
    "gn:feature_code":"PPL",
    "gn:name":"Koca\u00e7obanp\u0131nar\u0131",
    "gn:population":0,
    "gn:timezone":"Europe/Istanbul",
    "iso:country":"TR",
    "name:und_x_variant":[
        "Koca\u00e7obanp\u0131nar\u0131",
        "Kara\u00e7\u00f6banp\u0131nar\u0131 K\u00f6y\u00fc",
        "Kara\u00e7oban"
    ],
    "wof:name":"Kocacobanpinari",
    "wof:placetype":"locality"
},
  "geometry": {"coordinates":[30.40569,39.92554000000001],"type":"Point"}
}