{
  "type": "Feature",
  "properties": {
    "gn:admin1_code":"66.0",
    "gn:asciiname":"Kucuk Comakli",
    "gn:country_code":"TR",
    "gn:dem":1298,
    "gn:feature_class":"P",
    "gn:feature_code":"PPL",
    "gn:name":"K\u00fc\u00e7\u00fck Comakl\u0131",
    "gn:population":0,
    "gn:timezone":"Europe/Istanbul",
    "iso:country":"TR",
    "wof:name":"Kucuk Comakli",
    "wof:placetype":"locality"
},
  "geometry": {"coordinates":[35.19692,40.04078],"type":"Point"}
}