{
  "type": "Feature",
  "properties": {
    "gn:admin1_code":"17.0",
    "gn:asciiname":"Eselek",
    "gn:country_code":"TR",
    "gn:dem":30,
    "gn:feature_class":"P",
    "gn:feature_code":"PPL",
    "gn:name":"E\u015felek",
    "gn:population":0,
    "gn:timezone":"Europe/Istanbul",
    "iso:country":"TR",
    "name:tur_x_preferred":[
        "E\u015felek"
    ],
    "name:tur_x_variant":[
        "Karaca"
    ],
    "wof:name":"Eselek",
    "wof:placetype":"locality"
},
  "geometry": {"coordinates":[25.94315,40.14122],"type":"Point"}
}