{
  "type": "Feature",
  "properties": {
    "gn:admin1_code":"52.0",
    "gn:asciiname":"Tekkekoy",
    "gn:country_code":"TR",
    "gn:dem":526,
    "gn:feature_class":"P",
    "gn:feature_code":"PPL",
    "gn:name":"Tekkek\u00f6y",
    "gn:population":0,
    "gn:timezone":"Europe/Istanbul",
    "iso:country":"TR",
    "name:tur_x_preferred":[
        "Tekkek\u00f6y"
    ],
    "name:tur_x_variant":[
        "Tekke"
    ],
    "wof:name":"Tekkekoy",
    "wof:placetype":"locality"
},
  "geometry": {"coordinates":[37.32891,40.89204],"type":"Point"}
}