{
  "type": "Feature",
  "properties": {
    "gn:admin1_code":"04",
    "gn:asciiname":"Ozanlar",
    "gn:country_code":"TR",
    "gn:dem":1664,
    "gn:feature_class":"P",
    "gn:feature_code":"PPL",
    "gn:name":"Ozanlar",
    "gn:population":0,
    "gn:timezone":"Europe/Istanbul",
    "iso:country":"TR",
    "name:und_x_variant":[
        "\u0130ranos",
        "Eranos",
        "Ozanlar"
    ],
    "wof:name":"Ozanlar",
    "wof:placetype":"locality"
},
  "geometry": {"coordinates":[43.06708,39.77022],"type":"Point"}
}