{
  "type": "Feature",
  "properties": {
    "gn:admin1_code":"26",
    "gn:asciiname":"Bektaspinari",
    "gn:country_code":"TR",
    "gn:dem":1270,
    "gn:feature_class":"P",
    "gn:feature_code":"PPL",
    "gn:name":"Bekta\u015fp\u0131nar\u0131",
    "gn:population":0,
    "gn:timezone":"Europe/Istanbul",
    "iso:country":"TR",
    "name:und_x_variant":[
        "Mesudiye",
        "Bekta\u015fp\u0131nar",
        "Bekta\u015fp\u0131nar\u0131"
    ],
    "wof:name":"Bektaspinari",
    "wof:placetype":"locality"
},
  "geometry": {"coordinates":[30.52221,39.91281],"type":"Point"}
}