{
  "type": "Feature",
  "properties": {
    "gn:admin1_code":"70",
    "gn:asciiname":"Bagdas",
    "gn:country_code":"TR",
    "gn:dem":2145,
    "gn:feature_class":"P",
    "gn:feature_code":"PPL",
    "gn:name":"Ba\u011fda\u015f",
    "gn:population":0,
    "gn:timezone":"Europe/Istanbul",
    "iso:country":"TR",
    "name:und_x_variant":[
        "Peranis",
        "Ba\u011fda\u015f"
    ],
    "wof:name":"Bagdas",
    "wof:placetype":"locality"
},
  "geometry": {"coordinates":[44.20524,37.70348],"type":"Point"}
}