{
  "type": "Feature",
  "properties": {
    "gn:country":"TR",
    "gn:fcode":"PPL",
    "gn:pop":3466,
    "iso:country":"TR",
    "name:ceb_x_preferred":[
        "Kavakl\u0131dere"
    ],
    "name:deu_x_preferred":[
        "Kavakl\u0131dere"
    ],
    "name:eng_x_preferred":[
        "Kavakl\u0131dere"
    ],
    "name:frr_x_preferred":[
        "Kavakl\u0131dere"
    ],
    "name:nld_x_preferred":[
        "Kavakl\u0131dere"
    ],
    "name:tur_x_preferred":[
        "Kavakl\u0131dere"
    ],
    "name:unk_x_variant":[
        "Kavakdere"
    ],
    "name:vie_x_preferred":[
        "Kavakl\u0131dere"
    ],
    "qs:name":"Kavakl\u0131dere",
    "qs:photos_9r":0,
    "qs:photos_sr":0,
    "qs:pop_sr":"4",
    "wd:wordcount":43,
    "wof:name":"Kavakl\u0131dere",
    "wof:placetype":"locality",
    "wof:population":3466
},
  "geometry": {"coordinates":[28.36276,37.44463],"type":"Point"}
}