{
  "type": "Feature",
  "properties": {
    "gn:admin1_code":"63",
    "gn:asciiname":"Kavan",
    "gn:country_code":"TR",
    "gn:dem":1101,
    "gn:feature_class":"P",
    "gn:feature_code":"PPL",
    "gn:name":"Kavan",
    "gn:population":0,
    "gn:timezone":"Europe/Istanbul",
    "iso:country":"TR",
    "name:bre_x_preferred":[
        "Kavan"
    ],
    "name:ceb_x_preferred":[
        "Kavan"
    ],
    "name:ces_x_preferred":[
        "Kavan"
    ],
    "name:deu_x_preferred":[
        "Kavan"
    ],
    "name:tur_x_preferred":[
        "Kavan"
    ],
    "wof:name":"Kavan",
    "wof:placetype":"locality"
},
  "geometry": {"coordinates":[39.52105,37.80732],"type":"Point"}
}