{
  "type": "Feature",
  "properties": {
    "gn:admin1_code":"86.0",
    "gn:asciiname":"Alacam",
    "gn:country_code":"TR",
    "gn:dem":1804,
    "gn:feature_class":"P",
    "gn:feature_code":"PPL",
    "gn:name":"Ala\u00e7am",
    "gn:population":0,
    "gn:timezone":"Europe/Istanbul",
    "iso:country":"TR",
    "wof:name":"Alacam",
    "wof:placetype":"locality"
},
  "geometry": {"coordinates":[42.81631,41.22028],"type":"Point"}
}