{
  "type": "Feature",
  "properties": {
    "gn:admin1_code":"91",
    "gn:asciiname":"Koseli",
    "gn:country_code":"TR",
    "gn:dem":46,
    "gn:feature_class":"P",
    "gn:feature_code":"PPL",
    "gn:name":"K\u00f6seli",
    "gn:population":0,
    "gn:timezone":"Europe/Istanbul",
    "iso:country":"TR",
    "wof:name":"Koseli",
    "wof:placetype":"locality"
},
  "geometry": {"coordinates":[35.94069000000001,37.42361],"type":"Point"}
}