{
  "type": "Feature",
  "properties": {
    "gn:admin1_code":"43",
    "gn:asciiname":"Sogukcesme",
    "gn:country_code":"TR",
    "gn:dem":1010,
    "gn:feature_class":"P",
    "gn:feature_code":"PPL",
    "gn:name":"So\u011fuk\u00e7e\u015fme",
    "gn:population":0,
    "gn:timezone":"Europe/Istanbul",
    "iso:country":"TR",
    "name:tur_x_preferred":[
        "So\u011fuk\u00e7e\u015fme"
    ],
    "wof:name":"Sogukcesme",
    "wof:placetype":"locality"
},
  "geometry": {"coordinates":[30.05792000000001,39.59107],"type":"Point"}
}