{
  "type": "Feature",
  "properties": {
    "gn:admin1_code":"60.0",
    "gn:asciiname":"Goltepe",
    "gn:country_code":"TR",
    "gn:dem":1633,
    "gn:feature_class":"P",
    "gn:feature_code":"PPL",
    "gn:name":"G\u00f6ltepe",
    "gn:population":0,
    "gn:timezone":"Europe/Istanbul",
    "iso:country":"TR",
    "name:und_x_variant":[
        "G\u00f6ltepe K\u00f6y\u00fc",
        "G\u00f6lk\u00f6y",
        "G\u00f6ltepe"
    ],
    "wof:name":"Goltepe",
    "wof:placetype":"locality"
},
  "geometry": {"coordinates":[37.4222,40.23509],"type":"Point"}
}