{
  "type": "Feature",
  "properties": {
    "gn:admin1_code":"07",
    "gn:asciiname":"Kursunlu",
    "gn:country_code":"TR",
    "gn:dem":146,
    "gn:feature_class":"P",
    "gn:feature_code":"PPL",
    "gn:name":"Kur\u015funlu",
    "gn:population":0,
    "gn:timezone":"Europe/Istanbul",
    "iso:country":"TR",
    "wof:name":"Kursunlu",
    "wof:placetype":"locality"
},
  "geometry": {"coordinates":[30.8096,37.076],"type":"Point"}
}