{
  "type": "Feature",
  "properties": {
    "gn:admin1_code":"8.0",
    "gn:asciiname":"Osmaniye",
    "gn:country_code":"TR",
    "gn:dem":69,
    "gn:feature_class":"P",
    "gn:feature_code":"PPL",
    "gn:name":"Osmaniye",
    "gn:population":0,
    "gn:timezone":"Europe/Istanbul",
    "iso:country":"TR",
    "name:tur_x_preferred":[
        "Osmaniye"
    ],
    "wof:name":"Osmaniye",
    "wof:placetype":"locality"
},
  "geometry": {"coordinates":[41.52934000000001,41.47277],"type":"Point"}
}