{
  "type": "Feature",
  "properties": {
    "gn:country":"TR",
    "gn:fcode":"PPL",
    "gn:population":630,
    "iso:country":"TR",
    "name:und_x_variant":[
        "Ko\u00e7\u015f\u00fckran"
    ],
    "qs:name":"Binatl\u0131",
    "qs:photos_9r":0,
    "qs:photos_sr":0,
    "qs:pop_sr":"2",
    "wof:name":"Binatl\u0131",
    "wof:placetype":"locality",
    "wof:population":630
},
  "geometry": {"coordinates":[38.38235,36.93395],"type":"Point"}
}