{
  "type": "Feature",
  "properties": {
    "gn:admin1_code":"68.0",
    "gn:asciiname":"Bozyaka",
    "gn:country_code":"TR",
    "gn:dem":706,
    "gn:feature_class":"P",
    "gn:feature_code":"PPL",
    "gn:name":"Bozyaka",
    "gn:population":0,
    "gn:timezone":"Europe/Istanbul",
    "iso:country":"TR",
    "wof:name":"Bozyaka",
    "wof:placetype":"locality"
},
  "geometry": {"coordinates":[31.35443,40.25811],"type":"Point"}
}