{
  "type": "Feature",
  "properties": {
    "gn:admin1_code":"28",
    "gn:asciiname":"Bayrambey",
    "gn:country_code":"TR",
    "gn:dem":831,
    "gn:feature_class":"P",
    "gn:feature_code":"PPL",
    "gn:name":"Bayrambey",
    "gn:population":0,
    "gn:timezone":"Europe/Istanbul",
    "iso:country":"TR",
    "name:tur_x_preferred":[
        "Bayrambey"
    ],
    "wof:name":"Bayrambey",
    "wof:placetype":"locality"
},
  "geometry": {"coordinates":[38.74425,40.75133],"type":"Point"}
}