{
  "type": "Feature",
  "properties": {
    "gn:admin1_code":"83",
    "gn:asciiname":"Zincirli",
    "gn:country_code":"TR",
    "gn:dem":492,
    "gn:feature_class":"P",
    "gn:feature_code":"PPL",
    "gn:name":"Zincirli",
    "gn:population":0,
    "gn:timezone":"Europe/Istanbul",
    "iso:country":"TR",
    "name:tur_x_preferred":[
        "Zincirli"
    ],
    "wof:name":"Zincirli",
    "wof:placetype":"locality"
},
  "geometry": {"coordinates":[36.67598,37.10366],"type":"Point"}
}