{
  "type": "Feature",
  "properties": {
    "gn:admin1_code":"10",
    "gn:asciiname":"Kocaseyit",
    "gn:country_code":"TR",
    "gn:dem":418,
    "gn:feature_class":"P",
    "gn:feature_code":"PPL",
    "gn:name":"Kocaseyit",
    "gn:population":0,
    "gn:timezone":"Europe/Istanbul",
    "iso:country":"TR",
    "name:tur_x_preferred":[
        "\u00c7aml\u0131k"
    ],
    "name:tur_x_variant":[
        "Kocaseyit"
    ],
    "wof:name":"Kocaseyit",
    "wof:placetype":"locality"
},
  "geometry": {"coordinates":[27.1853,39.61286],"type":"Point"}
}