{
  "type": "Feature",
  "properties": {
    "gn:admin1_code":"62.0",
    "gn:asciiname":"Gocek",
    "gn:country_code":"TR",
    "gn:dem":986,
    "gn:feature_class":"P",
    "gn:feature_code":"PPL",
    "gn:name":"G\u00f6\u00e7ek",
    "gn:population":0,
    "gn:timezone":"Europe/Istanbul",
    "iso:country":"TR",
    "name:tur_x_preferred":[
        "G\u00f6\u00e7ek"
    ],
    "name:und_x_variant":[
        "G\u00f6k\u00e7ek"
    ],
    "wof:name":"Gocek",
    "wof:placetype":"locality"
},
  "geometry": {"coordinates":[39.68968,39.19114],"type":"Point"}
}