{
  "type": "Feature",
  "properties": {
    "gn:country":"TR",
    "gn:fcode":"PPLA2",
    "gn:population":31488,
    "iso:country":"TR",
    "name:ara_x_preferred":[
        "\u0631\u0623\u0633 \u0627\u0644\u0639\u064a\u0646"
    ],
    "name:ast_x_preferred":[
        "Ceylanp\u0131nar"
    ],
    "name:azb_x_preferred":[
        "\u062c\u0626\u06cc\u0644\u0627\u0646 \u067e\u064a\u0646\u0627\u0631"
    ],
    "name:aze_x_preferred":[
        "Ceyranp\u0131nar"
    ],
    "name:ceb_x_preferred":[
        "Ceylanp\u0131nar \u0130l\u00e7esi"
    ],
    "name:che_x_preferred":[
        "\u0414\u0436\u0435\u0439\u043b\u0430\u043d\u043f\u0438\u043d\u0430\u0440"
    ],
    "name:ckb_x_preferred":[
        "\u0633\u06d5\u0631\u06cc \u06a9\u0627\u0646\u06cc"
    ],
    "name:deu_x_preferred":[
        "Ceylanp\u0131nar"
    ],
    "name:diq_x_preferred":[
        "Ser\u00ea H\u00eani"
    ],
    "name:eng_x_preferred":[
        "Ceylanp\u0131nar"
    ],
    "name:fas_x_preferred":[
        "\u062c\u06cc\u0644\u0627\u0646\u200c\u067e\u06cc\u0646\u0627\u0631"
    ],
    "name:fra_x_preferred":[
        "Ceylanp\u0131nar"
    ],
    "name:gag_x_preferred":[
        "Ceylanp\u0131nar"
    ],
    "name:hye_x_preferred":[
        "\u054c\u0561\u057d-\u0537\u056c-\u0531\u0575\u0576"
    ],
    "name:ita_x_preferred":[
        "Distretto di Ceylanp\u0131nar"
    ],
    "name:kur_x_preferred":[
        "Ser\u00ea Kaniy\u00ea"
    ],
    "name:min_x_preferred":[
        "Ceylanp\u0131nar"
    ],
    "name:mrj_x_preferred":[
        "\u0414\u0436\u0435\u0439\u043b\u0430\u043d\u043f\u044b\u043d\u0430\u0440"
    ],
    "name:msa_x_preferred":[
        "Ceylanp\u0131nar"
    ],
    "name:nan_x_preferred":[
        "Ceylanp\u0131nar"
    ],
    "name:nld_x_preferred":[
        "Ceylanp\u0131nar"
    ],
    "name:nno_x_preferred":[
        "Ceylanp\u0131nar"
    ],
    "name:nob_x_preferred":[
        "Ceylanp\u0131nar"
    ],
    "name:pnb_x_preferred":[
        "\u0636\u0644\u0639 \u062c\u06cc\u0644\u0646\u067e\u06cc\u0646\u0627\u0631"
    ],
    "name:pol_x_preferred":[
        "Ceylanp\u0131nar"
    ],
    "name:ron_x_preferred":[
        "Ceylanp\u0131nar"
    ],
    "name:rus_x_preferred":[
        "\u0414\u0436\u0435\u0439\u043b\u0430\u043d\u043f\u044b\u043d\u0430\u0440"
    ],
    "name:sco_x_preferred":[
        "Ceylanp\u0131nar"
    ],
    "name:swa_x_preferred":[
        "Ceylanp\u0131nar"
    ],
    "name:tat_x_preferred":[
        "\u0496\u0435\u0439\u043b\u0430\u043d\u043f\u044b\u043d\u0430\u0440"
    ],
    "name:tur_x_preferred":[
        "Ceylanp\u0131nar"
    ],
    "name:und_x_variant":[
        "Raselain"
    ],
    "name:urd_x_preferred":[
        "\u0631\u0627\u0633 \u0627\u0644\u0639\u06cc\u0646"
    ],
    "name:vie_x_preferred":[
        "Ceylanp\u0131nar"
    ],
    "name:zho_x_preferred":[
        "\u5091\u4f0a\u862d\u73c0\u7d0d\u723e"
    ],
    "name:zho_x_variant":[
        "\u683c\u5ae9"
    ],
    "qs:name":"Ceylanp\u0131nar",
    "qs:photos_9r":0,
    "qs:photos_sr":0,
    "qs:pop_sr":"7",
    "wd:wordcount":215,
    "wof:name":"Ceylanp\u0131nar",
    "wof:placetype":"locality",
    "wof:population":31488
},
  "geometry": {"coordinates":[40.05,36.84722],"type":"Point"}
}