{
  "type": "Feature",
  "properties": {
    "gn:admin1_code":"74",
    "gn:asciiname":"Karadayi",
    "gn:cc2":"TR",
    "gn:country_code":"TR",
    "gn:dem":1718,
    "gn:feature_class":"P",
    "gn:feature_code":"PPL",
    "gn:name":"Karaday\u0131",
    "gn:population":0,
    "gn:timezone":"Europe/Istanbul",
    "iso:country":"TR",
    "name:und_x_variant":[
        "Pestegevu",
        "Bestak\u00e2bu",
        "Bestakyabu",
        "Karaday\u0131"
    ],
    "wof:name":"Karadayi",
    "wof:placetype":"locality"
},
  "geometry": {"coordinates":[42.84944,37.69083],"type":"Point"}
}