{
  "type": "Feature",
  "properties": {
    "gn:admin1_code":"31",
    "gn:asciiname":"Guvecci",
    "gn:country_code":"TR",
    "gn:dem":564,
    "gn:feature_class":"P",
    "gn:feature_code":"PPL",
    "gn:name":"G\u00fcve\u00e7\u00e7i",
    "gn:population":0,
    "gn:timezone":"Europe/Istanbul",
    "iso:country":"TR",
    "name:und_x_variant":[
        "G\u00fcvec\u0131",
        "G\u00fcve\u00e7\u00e7i"
    ],
    "wof:name":"Guvecci",
    "wof:placetype":"locality"
},
  "geometry": {"coordinates":[36.16145,35.8935],"type":"Point"}
}