{
  "type": "Feature",
  "properties": {
    "gn:admin1_code":"32",
    "gn:asciiname":"Bolatli",
    "gn:country_code":"TR",
    "gn:dem":48,
    "gn:feature_class":"P",
    "gn:feature_code":"PPL",
    "gn:name":"Bolatl\u0131",
    "gn:population":0,
    "gn:timezone":"Europe/Istanbul",
    "iso:country":"TR",
    "name:tur_x_preferred":[
        "Bolatl\u0131"
    ],
    "wof:name":"Bolatli",
    "wof:placetype":"locality"
},
  "geometry": {"coordinates":[34.89922,36.94819],"type":"Point"}
}