{
  "type": "Feature",
  "properties": {
    "gn:admin1_code":"46",
    "gn:asciiname":"Rifatiye",
    "gn:country_code":"TR",
    "gn:dem":1094,
    "gn:feature_class":"P",
    "gn:feature_code":"PPL",
    "gn:name":"Rifatiye",
    "gn:population":0,
    "gn:timezone":"Europe/Istanbul",
    "iso:country":"TR",
    "wof:name":"Rifatiye",
    "wof:placetype":"locality"
},
  "geometry": {"coordinates":[36.29621,37.68264],"type":"Point"}
}