{
  "type": "Feature",
  "properties": {
    "gn:admin1_code":"63",
    "gn:asciiname":"Mehmetcik",
    "gn:country_code":"TR",
    "gn:dem":625,
    "gn:feature_class":"P",
    "gn:feature_code":"PPL",
    "gn:name":"Mehmet\u00e7ik",
    "gn:population":0,
    "gn:timezone":"Europe/Istanbul",
    "iso:country":"TR",
    "name:tur_x_preferred":[
        "Mehmet\u00e7ik"
    ],
    "wof:name":"Mehmetcik",
    "wof:placetype":"locality"
},
  "geometry": {"coordinates":[38.77227,37.19734],"type":"Point"}
}