{
  "type": "Feature",
  "properties": {
    "gn:admin1_code":"55.0",
    "gn:asciiname":"Bakirpinari",
    "gn:country_code":"TR",
    "gn:dem":18,
    "gn:feature_class":"P",
    "gn:feature_code":"PPL",
    "gn:name":"Bak\u0131rp\u0131nar\u0131",
    "gn:population":0,
    "gn:timezone":"Europe/Istanbul",
    "iso:country":"TR",
    "name:und_x_variant":[
        "Bak\u0131rp\u0131nar",
        "Bak\u0131rp\u0131nar\u0131"
    ],
    "wof:name":"Bakirpinari",
    "wof:placetype":"locality"
},
  "geometry": {"coordinates":[35.92167,41.58027],"type":"Point"}
}