{
  "type": "Feature",
  "properties": {
    "gn:admin1_code":"37.0",
    "gn:asciiname":"Kocaagac",
    "gn:country_code":"TR",
    "gn:dem":1170,
    "gn:feature_class":"P",
    "gn:feature_code":"PPL",
    "gn:name":"Kocaa\u011fa\u00e7",
    "gn:population":0,
    "gn:timezone":"Europe/Istanbul",
    "iso:country":"TR",
    "wof:name":"Kocaagac",
    "wof:placetype":"locality"
},
  "geometry": {"coordinates":[33.41667,41.73333],"type":"Point"}
}