{
  "type": "Feature",
  "properties": {
    "gn:admin1_code":"68.0",
    "gn:asciiname":"Kosrelikkizigi",
    "gn:country_code":"TR",
    "gn:dem":1032,
    "gn:feature_class":"P",
    "gn:feature_code":"PPL",
    "gn:name":"K\u00f6srelikk\u0131z\u0131\u011f\u0131",
    "gn:population":0,
    "gn:timezone":"Europe/Istanbul",
    "iso:country":"TR",
    "name:tur_x_preferred":[
        "K\u0131z\u0131k"
    ],
    "name:und_x_variant":[
        "K\u00f6serelikk\u0131z\u0131\u011f\u0131",
        "K\u00f6srelikk\u0131z\u0131",
        "K\u00f6srelikk\u0131z\u0131\u011f\u0131"
    ],
    "wof:name":"Kosrelikkizigi",
    "wof:placetype":"locality"
},
  "geometry": {"coordinates":[32.88992,40.10676],"type":"Point"}
}