{
  "type": "Feature",
  "properties": {
    "gn:admin1_code":"19.0",
    "gn:asciiname":"Teslim",
    "gn:country_code":"TR",
    "gn:dem":962,
    "gn:feature_class":"P",
    "gn:feature_code":"PPL",
    "gn:name":"Teslim",
    "gn:population":0,
    "gn:timezone":"Europe/Istanbul",
    "iso:country":"TR",
    "wof:name":"Teslim",
    "wof:placetype":"locality"
},
  "geometry": {"coordinates":[34.94275,40.38258],"type":"Point"}
}