{
  "type": "Feature",
  "properties": {
    "gn:admin1_code":"52.0",
    "gn:asciiname":"Hurriyet",
    "gn:country_code":"TR",
    "gn:dem":579,
    "gn:feature_class":"P",
    "gn:feature_code":"PPL",
    "gn:name":"H\u00fcrriyet",
    "gn:population":0,
    "gn:timezone":"Europe/Istanbul",
    "iso:country":"TR",
    "name:und_x_variant":[
        "H\u00fcrriyet",
        "E\u011frice"
    ],
    "wof:name":"Hurriyet",
    "wof:placetype":"locality"
},
  "geometry": {"coordinates":[37.96023,40.84304],"type":"Point"}
}