{
  "type": "Feature",
  "properties": {
    "gn:admin1_code":"65.0",
    "gn:asciiname":"Agacoren",
    "gn:country_code":"TR",
    "gn:dem":1806,
    "gn:feature_class":"P",
    "gn:feature_code":"PPL",
    "gn:name":"A\u011fa\u00e7\u00f6ren",
    "gn:population":0,
    "gn:timezone":"Europe/Istanbul",
    "iso:country":"TR",
    "name:tur_x_preferred":[
        "A\u011fa\u00e7\u00f6ren"
    ],
    "wof:name":"Agacoren",
    "wof:placetype":"locality"
},
  "geometry": {"coordinates":[43.31881,39.13347],"type":"Point"}
}