{
  "type": "Feature",
  "properties": {
    "gn:admin1_code":"81",
    "gn:asciiname":"Enizcakiri",
    "gn:country_code":"TR",
    "gn:dem":866,
    "gn:feature_class":"P",
    "gn:feature_code":"PPL",
    "gn:name":"Eniz\u00e7ak\u0131r\u0131",
    "gn:population":0,
    "gn:timezone":"Europe/Istanbul",
    "iso:country":"TR",
    "name:und_x_variant":[
        "Hen\u00fcz\u00e7ak\u0131r\u0131",
        "Eniz\u00e7ak\u0131r\u0131"
    ],
    "wof:name":"Enizcakiri",
    "wof:placetype":"locality"
},
  "geometry": {"coordinates":[35.56667,37.53333],"type":"Point"}
}