{
  "type": "Feature",
  "properties": {
    "gn:admin1_code":"19.0",
    "gn:asciiname":"Boztepe",
    "gn:country_code":"TR",
    "gn:dem":846,
    "gn:feature_class":"P",
    "gn:feature_code":"PPL",
    "gn:name":"Boztepe",
    "gn:population":0,
    "gn:timezone":"Europe/Istanbul",
    "iso:country":"TR",
    "name:und_x_variant":[
        "Boztepe K\u00f6y\u00fc",
        "Boztepe"
    ],
    "wof:name":"Boztepe",
    "wof:placetype":"locality"
},
  "geometry": {"coordinates":[34.29429,40.21588],"type":"Point"}
}