{
  "type": "Feature",
  "properties": {
    "gn:admin1_code":"07",
    "gn:asciiname":"Salur",
    "gn:country_code":"TR",
    "gn:dem":200,
    "gn:feature_class":"P",
    "gn:feature_code":"PPL",
    "gn:name":"Salur",
    "gn:population":0,
    "gn:timezone":"Europe/Istanbul",
    "iso:country":"TR",
    "wof:name":"Salur",
    "wof:placetype":"locality"
},
  "geometry": {"coordinates":[31.4125,36.92861],"type":"Point"}
}