{
  "type": "Feature",
  "properties": {
    "gn:admin1_code":"07",
    "gn:asciiname":"Salur",
    "gn:country_code":"TR",
    "gn:dem":200,
    "gn:feature_class":"P",
    "gn:feature_code":"PPL",
    "gn:name":"Salur",
    "gn:population":0,
    "gn:timezone":"Europe/Istanbul",
    "iso:country":"TR",
    "name:bpy_x_preferred":[
        "\u09b8\u09be\u09b2\u09c1\u09b0"
    ],
    "name:ceb_x_preferred":[
        "S\u0101l\u016br"
    ],
    "name:ita_x_preferred":[
        "Salur"
    ],
    "name:mar_x_preferred":[
        "\u0938\u093e\u0932\u0942\u0930"
    ],
    "name:msa_x_preferred":[
        "Salur"
    ],
    "name:new_x_preferred":[
        "\u0938\u093e\u0932\u0942\u0930\u0941 \u092e\u0923\u094d\u0921\u0932"
    ],
    "name:ori_x_preferred":[
        "\u0b38\u0b3e\u0b32\u0b41\u0b30"
    ],
    "name:por_x_preferred":[
        "Salur"
    ],
    "name:swe_x_preferred":[
        "S\u0101l\u016br"
    ],
    "name:tam_x_preferred":[
        "\u0b9a\u0bbe\u0bb2\u0bc2\u0bb0\u0bcd"
    ],
    "name:tel_x_preferred":[
        "\u0c38\u0c3e\u0c32\u0c42\u0c30\u0c41"
    ],
    "name:urd_x_preferred":[
        "\u0633\u0627\u0644\u0648\u0631"
    ],
    "name:vie_x_preferred":[
        "Salur"
    ],
    "name:zho_x_preferred":[
        "\u8428\u5362\u5c14"
    ],
    "wof:name":"Salur",
    "wof:placetype":"locality"
},
  "geometry": {"coordinates":[31.4125,36.92861],"type":"Point"}
}