{
  "type": "Feature",
  "properties": {
    "gn:admin1_code":"20",
    "gn:asciiname":"Ericek",
    "gn:country_code":"TR",
    "gn:dem":905,
    "gn:feature_class":"P",
    "gn:feature_code":"PPL",
    "gn:name":"Ericek",
    "gn:population":0,
    "gn:timezone":"Europe/Istanbul",
    "iso:country":"TR",
    "name:tur_x_preferred":[
        "Ericek"
    ],
    "wof:name":"Ericek",
    "wof:placetype":"locality"
},
  "geometry": {"coordinates":[28.8107,37.28715],"type":"Point"}
}