{
  "type": "Feature",
  "properties": {
    "gn:admin1_code":"15",
    "gn:asciiname":"Kucukalan",
    "gn:country_code":"TR",
    "gn:dem":1075,
    "gn:feature_class":"P",
    "gn:feature_code":"PPL",
    "gn:name":"K\u00fc\u00e7\u00fckalan",
    "gn:population":0,
    "gn:timezone":"Europe/Istanbul",
    "iso:country":"TR",
    "name:und_x_variant":[
        "Alansa\u011fir",
        "K\u00fc\u00e7\u00fckalan"
    ],
    "wof:name":"Kucukalan",
    "wof:placetype":"locality"
},
  "geometry": {"coordinates":[29.59765,37.24948],"type":"Point"}
}