{
  "type": "Feature",
  "properties": {
    "gn:admin1_code":"64",
    "gn:asciiname":"Manavli",
    "gn:country_code":"TR",
    "gn:dem":761,
    "gn:feature_class":"P",
    "gn:feature_code":"PPL",
    "gn:name":"Manavl\u0131",
    "gn:population":0,
    "gn:timezone":"Europe/Istanbul",
    "iso:country":"TR",
    "wof:name":"Manavli",
    "wof:placetype":"locality"
},
  "geometry": {"coordinates":[28.83596,38.36146],"type":"Point"}
}