{
  "type": "Feature",
  "properties": {
    "gn:admin1_code":"63",
    "gn:asciiname":"Karatasli",
    "gn:country_code":"TR",
    "gn:dem":683,
    "gn:feature_class":"P",
    "gn:feature_code":"PPL",
    "gn:name":"Karata\u015fl\u0131",
    "gn:population":0,
    "gn:timezone":"Europe/Istanbul",
    "iso:country":"TR",
    "name:tur_x_preferred":[
        "Karata\u015fl\u0131"
    ],
    "wof:name":"Karatasli",
    "wof:placetype":"locality"
},
  "geometry": {"coordinates":[39.26667,37.45],"type":"Point"}
}