{
  "type": "Feature",
  "properties": {
    "gn:admin1_code":"44",
    "gn:asciiname":"Ilisuluk",
    "gn:country_code":"TR",
    "gn:dem":1488,
    "gn:feature_class":"P",
    "gn:feature_code":"PPL",
    "gn:name":"Il\u0131suluk",
    "gn:population":0,
    "gn:timezone":"Europe/Istanbul",
    "iso:country":"TR",
    "name:und_x_variant":[
        "Ulusoluk",
        "Il\u0131suluk"
    ],
    "wof:name":"Ilisuluk",
    "wof:placetype":"locality"
},
  "geometry": {"coordinates":[37.6177,38.80636],"type":"Point"}
}