{
  "type": "Feature",
  "properties": {
    "gn:admin1_code":"81.0",
    "gn:asciiname":"Mutlu",
    "gn:country_code":"TR",
    "gn:dem":47,
    "gn:feature_class":"P",
    "gn:feature_code":"PPL",
    "gn:name":"Mutlu",
    "gn:population":0,
    "gn:timezone":"Europe/Istanbul",
    "iso:country":"TR",
    "name:deu_x_preferred":[
        "Mutlu"
    ],
    "wof:name":"Mutlu",
    "wof:placetype":"locality"
},
  "geometry": {"coordinates":[35.38477,37.01069],"type":"Point"}
}