{
  "type": "Feature",
  "properties": {
    "gn:admin1_code":"37.0",
    "gn:asciiname":"Akincilar",
    "gn:country_code":"TR",
    "gn:dem":719,
    "gn:feature_class":"P",
    "gn:feature_code":"PPL",
    "gn:name":"Ak\u0131nc\u0131lar",
    "gn:population":0,
    "gn:timezone":"Europe/Istanbul",
    "iso:country":"TR",
    "name:und_x_variant":[
        "Daprak",
        "Dabrak",
        "Ak\u0131nc\u0131lar"
    ],
    "wof:name":"Akincilar",
    "wof:placetype":"locality"
},
  "geometry": {"coordinates":[33.30321,41.24558],"type":"Point"}
}