{
  "type": "Feature",
  "properties": {
    "gn:admin1_code":"68",
    "gn:asciiname":"Topcayiri",
    "gn:cc2":"TR",
    "gn:country_code":"TR",
    "gn:dem":954,
    "gn:feature_class":"P",
    "gn:feature_code":"PPL",
    "gn:name":"Top\u00e7ay\u0131r\u0131",
    "gn:population":0,
    "gn:timezone":"Europe/Istanbul",
    "iso:country":"TR",
    "name:und_x_variant":[
        "Toy\u00e7ay\u0131r\u0131",
        "Top\u00e7ay\u0131r\u0131"
    ],
    "wof:name":"Topcayiri",
    "wof:placetype":"locality"
},
  "geometry": {"coordinates":[32.45139,39.04083],"type":"Point"}
}