{
  "type": "Feature",
  "properties": {
    "gn:admin1_code":"37.0",
    "gn:asciiname":"Yavuc",
    "gn:country_code":"TR",
    "gn:dem":645,
    "gn:feature_class":"P",
    "gn:feature_code":"PPL",
    "gn:name":"Yavu\u00e7",
    "gn:population":0,
    "gn:timezone":"Europe/Istanbul",
    "iso:country":"TR",
    "name:und_x_variant":[
        "A\u015fa\u011f\u0131 Yavuc",
        "Yavu\u00e7"
    ],
    "wof:name":"Yavuc",
    "wof:placetype":"locality"
},
  "geometry": {"coordinates":[34.03744,41.43444],"type":"Point"}
}