{
  "type": "Feature",
  "properties": {
    "gn:admin1_code":"20",
    "gn:asciiname":"Kizilan",
    "gn:country_code":"TR",
    "gn:dem":683,
    "gn:feature_class":"P",
    "gn:feature_code":"PPL",
    "gn:name":"K\u0131z\u0131lan",
    "gn:population":0,
    "gn:timezone":"Europe/Istanbul",
    "iso:country":"TR",
    "name:tur_x_preferred":[
        "K\u0131z\u0131lan"
    ],
    "name:tur_x_variant":[
        "K\u0131z\u0131lca"
    ],
    "wof:name":"Kizilan",
    "wof:placetype":"locality"
},
  "geometry": {"coordinates":[28.91051,37.22148],"type":"Point"}
}