{
  "type": "Feature",
  "properties": {
    "gn:admin1_code":"09",
    "gn:asciiname":"Kizilca",
    "gn:country_code":"TR",
    "gn:dem":92,
    "gn:feature_class":"P",
    "gn:feature_code":"PPL",
    "gn:name":"K\u0131z\u0131lca",
    "gn:population":0,
    "gn:timezone":"Europe/Istanbul",
    "iso:country":"TR",
    "name:und_x_variant":[
        "K\u0131z\u0131lcak\u00f6y",
        "K\u0131z\u0131lca"
    ],
    "wof:name":"Kizilca",
    "wof:placetype":"locality"
},
  "geometry": {"coordinates":[27.77252,37.86997],"type":"Point"}
}