{
  "type": "Feature",
  "properties": {
    "gn:admin1_code":"07",
    "gn:asciiname":"Erentepe",
    "gn:country_code":"TR",
    "gn:dem":324,
    "gn:feature_class":"P",
    "gn:feature_code":"PPL",
    "gn:name":"Erentepe",
    "gn:population":0,
    "gn:timezone":"Europe/Istanbul",
    "iso:country":"TR",
    "name:und_x_variant":[
        "Ger\u00e7en",
        "Erentepe"
    ],
    "wof:name":"Erentepe",
    "wof:placetype":"locality"
},
  "geometry": {"coordinates":[30.3616,36.41645],"type":"Point"}
}