{
  "type": "Feature",
  "properties": {
    "gn:admin1_code":"46",
    "gn:asciiname":"Asagiulubahce",
    "gn:country_code":"TR",
    "gn:dem":829,
    "gn:feature_class":"P",
    "gn:feature_code":"PPL",
    "gn:name":"A\u015fa\u011f\u0131ulubah\u00e7e",
    "gn:population":0,
    "gn:timezone":"Europe/Istanbul",
    "iso:country":"TR",
    "wof:name":"Asagiulubahce",
    "wof:placetype":"locality"
},
  "geometry": {"coordinates":[37.32429000000001,37.5074],"type":"Point"}
}