{
  "type": "Feature",
  "properties": {
    "gn:admin1_code":"65.0",
    "gn:asciiname":"Kosumlu",
    "gn:country_code":"TR",
    "gn:dem":2259,
    "gn:feature_class":"P",
    "gn:feature_code":"PPL",
    "gn:name":"Ko\u015fumlu",
    "gn:population":0,
    "gn:timezone":"Europe/Istanbul",
    "iso:country":"TR",
    "name:tur_x_preferred":[
        "Ko\u015fumlu"
    ],
    "wof:name":"Kosumlu",
    "wof:placetype":"locality"
},
  "geometry": {"coordinates":[43.53131,37.88701],"type":"Point"}
}