{
  "type": "Feature",
  "properties": {
    "gn:admin1_code":"25",
    "gn:asciiname":"Akcam",
    "gn:country_code":"TR",
    "gn:dem":1921,
    "gn:feature_class":"P",
    "gn:feature_code":"PPL",
    "gn:name":"Ak\u00e7am",
    "gn:population":0,
    "gn:timezone":"Europe/Istanbul",
    "iso:country":"TR",
    "name:und_x_variant":[
        "Ak\u00e7am",
        "Tavus"
    ],
    "wof:name":"Akcam",
    "wof:placetype":"locality"
},
  "geometry": {"coordinates":[41.98172,39.85971],"type":"Point"}
}