{
  "type": "Feature",
  "properties": {
    "gn:admin1_code":"70",
    "gn:asciiname":"Cemcilekan",
    "gn:country_code":"TR",
    "gn:dem":2305,
    "gn:feature_class":"P",
    "gn:feature_code":"PPL",
    "gn:name":"Cemcilekan",
    "gn:population":0,
    "gn:timezone":"Europe/Istanbul",
    "iso:country":"TR",
    "name:und_x_variant":[
        "G\u00fczelk\u00f6y",
        "\u00c7emialakana"
    ],
    "wof:name":"Cemcilekan",
    "wof:placetype":"locality"
},
  "geometry": {"coordinates":[43.69111,37.5699],"type":"Point"}
}