{
  "type": "Feature",
  "properties": {
    "gn:admin1_code":"76",
    "gn:asciiname":"Umurlu",
    "gn:country_code":"TR",
    "gn:dem":980,
    "gn:feature_class":"P",
    "gn:feature_code":"PPL",
    "gn:name":"Umurlu",
    "gn:population":0,
    "gn:timezone":"Europe/Istanbul",
    "iso:country":"TR",
    "name:tur_x_preferred":[
        "Umurlu"
    ],
    "wof:name":"Umurlu",
    "wof:placetype":"locality"
},
  "geometry": {"coordinates":[41.30486,38.31399],"type":"Point"}
}