{
  "type": "Feature",
  "properties": {
    "gn:admin1_code":"8.0",
    "gn:asciiname":"Cukur",
    "gn:country_code":"TR",
    "gn:dem":1204,
    "gn:feature_class":"P",
    "gn:feature_code":"PPL",
    "gn:name":"\u00c7ukur",
    "gn:population":0,
    "gn:timezone":"Europe/Istanbul",
    "iso:country":"TR",
    "name:und_x_variant":[
        "\u00c7ukur",
        "K\u00fc\u00e7\u00fck\u00e7ukur"
    ],
    "wof:name":"Cukur",
    "wof:placetype":"locality"
},
  "geometry": {"coordinates":[42.19665,41.30958],"type":"Point"}
}