{
  "type": "Feature",
  "properties": {
    "gn:admin1_code":"09",
    "gn:asciiname":"Alabayir",
    "gn:country_code":"TR",
    "gn:dem":550,
    "gn:feature_class":"P",
    "gn:feature_code":"PPL",
    "gn:name":"Alabay\u0131r",
    "gn:population":0,
    "gn:timezone":"Europe/Istanbul",
    "iso:country":"TR",
    "name:und_x_variant":[
        "Naz\u0131rpa",
        "Alabay\u0131r"
    ],
    "wof:name":"Alabayir",
    "wof:placetype":"locality"
},
  "geometry": {"coordinates":[28.15761,37.53951],"type":"Point"}
}