{
  "type": "Feature",
  "properties": {
    "gn:admin1_code":"58.0",
    "gn:asciiname":"Zaramagebeli",
    "gn:country_code":"TR",
    "gn:dem":673,
    "gn:feature_class":"P",
    "gn:feature_code":"PPL",
    "gn:name":"Zaramagebeli",
    "gn:population":0,
    "gn:timezone":"Europe/Istanbul",
    "iso:country":"TR",
    "name:und_x_variant":[
        "Yukar\u0131 Gebeli"
    ],
    "wof:name":"Zaramagebeli",
    "wof:placetype":"locality"
},
  "geometry": {"coordinates":[37.71637,40.29366],"type":"Point"}
}