{
  "type": "Feature",
  "properties": {
    "gn:admin1_code":"17.0",
    "gn:asciiname":"Ahmetler",
    "gn:country_code":"TR",
    "gn:dem":167,
    "gn:feature_class":"P",
    "gn:feature_code":"PPL",
    "gn:name":"Ahmetler",
    "gn:population":0,
    "gn:timezone":"Europe/Istanbul",
    "iso:country":"TR",
    "name:und_x_variant":[
        "Ahmedler",
        "Ahmetler"
    ],
    "wof:name":"Ahmetler",
    "wof:placetype":"locality"
},
  "geometry": {"coordinates":[26.92436,40.16323],"type":"Point"}
}