{
  "type": "Feature",
  "properties": {
    "gn:admin1_code":"52",
    "gn:asciiname":"Kocuklu",
    "gn:country_code":"TR",
    "gn:dem":38,
    "gn:feature_class":"P",
    "gn:feature_code":"PPL",
    "gn:name":"Kocuklu",
    "gn:population":0,
    "gn:timezone":"Europe/Istanbul",
    "iso:country":"TR",
    "name:tur_x_preferred":[
        "Kocuklu"
    ],
    "wof:name":"Kocuklu",
    "wof:placetype":"locality"
},
  "geometry": {"coordinates":[37.16678,41.12978],"type":"Point"}
}