{
  "type": "Feature",
  "properties": {
    "gn:admin1_code":"37.0",
    "gn:asciiname":"Ibrahimli",
    "gn:country_code":"TR",
    "gn:dem":1225,
    "gn:feature_class":"P",
    "gn:feature_code":"PPL",
    "gn:name":"\u0130brahimli",
    "gn:population":0,
    "gn:timezone":"Europe/Istanbul",
    "iso:country":"TR",
    "wof:name":"Ibrahimli",
    "wof:placetype":"locality"
},
  "geometry": {"coordinates":[34.06984,41.29436],"type":"Point"}
}