{
  "type": "Feature",
  "properties": {
    "gn:admin1_code":"25.0",
    "gn:asciiname":"Kirecli",
    "gn:country_code":"TR",
    "gn:dem":1754,
    "gn:feature_class":"P",
    "gn:feature_code":"PPL",
    "gn:name":"Kire\u00e7li",
    "gn:population":0,
    "gn:timezone":"Europe/Istanbul",
    "iso:country":"TR",
    "name:eng_x_preferred":[
        "A\u011fasar"
    ],
    "name:rus_x_preferred":[
        "\u0410\u0433\u0430\u0441\u0430\u0440"
    ],
    "name:und_x_variant":[
        "Kire\u00e7li"
    ],
    "wof:name":"Kirecli",
    "wof:placetype":"locality"
},
  "geometry": {"coordinates":[41.58704,40.28097],"type":"Point"}
}