{
  "type": "Feature",
  "properties": {
    "gn:admin1_code":"14.0",
    "gn:asciiname":"Golbasi",
    "gn:country_code":"TR",
    "gn:dem":1088,
    "gn:feature_class":"P",
    "gn:feature_code":"PPL",
    "gn:name":"G\u00f6lba\u015f\u0131",
    "gn:population":0,
    "gn:timezone":"Europe/Istanbul",
    "iso:country":"TR",
    "name:und_x_variant":[
        "G\u00f6lba\u015f\u0131",
        "Kaltak\u00e7\u0131"
    ],
    "wof:name":"Golbasi",
    "wof:placetype":"locality"
},
  "geometry": {"coordinates":[32.02193,40.80372],"type":"Point"}
}