{
  "type": "Feature",
  "properties": {
    "gn:admin1_code":"21",
    "gn:asciiname":"Durak",
    "gn:country_code":"TR",
    "gn:dem":1168,
    "gn:feature_class":"P",
    "gn:feature_code":"PPL",
    "gn:name":"Durak",
    "gn:population":0,
    "gn:timezone":"Europe/Istanbul",
    "iso:country":"TR",
    "name:bel_x_preferred":[
        "\u0414\u0443\u0440\u0430\u043d\u044c"
    ],
    "name:ces_x_preferred":[
        "Dud\u00e1k"
    ],
    "name:deu_x_preferred":[
        "Durak"
    ],
    "name:est_x_preferred":[
        "Turakas"
    ],
    "name:fin_x_preferred":[
        "Durak"
    ],
    "name:fra_x_preferred":[
        "Durak"
    ],
    "name:heb_x_preferred":[
        "\u05d3\u05d5\u05e8\u05d0\u05e7"
    ],
    "name:hye_x_preferred":[
        "\u0534\u0578\u0582\u057c\u0561\u056f"
    ],
    "name:jpn_x_preferred":[
        "\u30c9\u30a5\u30e9\u30fc\u30af"
    ],
    "name:kor_x_preferred":[
        "\ub450\ub77c\ud06c"
    ],
    "name:lav_x_preferred":[
        "C\u016bkas"
    ],
    "name:lit_x_preferred":[
        "Durnius"
    ],
    "name:nld_x_preferred":[
        "Doerak"
    ],
    "name:pol_x_preferred":[
        "Dure\u0144"
    ],
    "name:rus_x_preferred":[
        "\u0414\u0443\u0440\u0430\u043a"
    ],
    "name:spa_x_preferred":[
        "Durak"
    ],
    "name:swe_x_preferred":[
        "Durak"
    ],
    "name:ukr_x_preferred":[
        "\u0414\u0443\u0440\u0435\u043d\u044c"
    ],
    "name:und_x_variant":[
        "Karaderek\u00f6y",
        "Durak",
        "Karadere"
    ],
    "name:vie_x_preferred":[
        "B\u00e0i t\u1ea5n"
    ],
    "name:zho_x_preferred":[
        "\u50bb\u74dc"
    ],
    "wof:name":"Durak",
    "wof:placetype":"locality"
},
  "geometry": {"coordinates":[40.55434,38.49545],"type":"Point"}
}