{
  "type": "Feature",
  "properties": {
    "gn:admin1_code":"21",
    "gn:asciiname":"Durak",
    "gn:country_code":"TR",
    "gn:dem":1168,
    "gn:feature_class":"P",
    "gn:feature_code":"PPL",
    "gn:name":"Durak",
    "gn:population":0,
    "gn:timezone":"Europe/Istanbul",
    "iso:country":"TR",
    "name:und_x_variant":[
        "Karaderek\u00f6y",
        "Durak",
        "Karadere"
    ],
    "wof:name":"Durak",
    "wof:placetype":"locality"
},
  "geometry": {"coordinates":[40.55434,38.49545],"type":"Point"}
}