{
  "type": "Feature",
  "properties": {
    "gn:admin1_code":"21",
    "gn:asciiname":"Basdegirmen",
    "gn:country_code":"TR",
    "gn:dem":617,
    "gn:feature_class":"P",
    "gn:feature_code":"PPL",
    "gn:name":"Ba\u015fde\u011firmen",
    "gn:population":0,
    "gn:timezone":"Europe/Istanbul",
    "iso:country":"TR",
    "name:tur_x_preferred":[
        "Ba\u015fde\u011firmen"
    ],
    "name:und_x_variant":[
        "Kepo"
    ],
    "wof:name":"Basdegirmen",
    "wof:placetype":"locality"
},
  "geometry": {"coordinates":[41.19316,38.13155],"type":"Point"}
}