{
  "type": "Feature",
  "properties": {
    "gn:admin1_code":"81",
    "gn:asciiname":"Boztahta",
    "gn:country_code":"TR",
    "gn:dem":230,
    "gn:feature_class":"P",
    "gn:feature_code":"PPL",
    "gn:name":"Boztahta",
    "gn:population":0,
    "gn:timezone":"Europe/Istanbul",
    "iso:country":"TR",
    "name:deu_x_preferred":[
        "Boztahta"
    ],
    "name:tur_x_preferred":[
        "Boztahta"
    ],
    "wof:name":"Boztahta",
    "wof:placetype":"locality"
},
  "geometry": {"coordinates":[35.46018,37.3694],"type":"Point"}
}