{
  "type": "Feature",
  "properties": {
    "gn:admin1_code":"09",
    "gn:asciiname":"Bagcilli",
    "gn:country_code":"TR",
    "gn:dem":465,
    "gn:feature_class":"P",
    "gn:feature_code":"PPL",
    "gn:name":"Ba\u011fc\u0131ll\u0131",
    "gn:population":0,
    "gn:timezone":"Europe/Istanbul",
    "iso:country":"TR",
    "name:tur_x_preferred":[
        "Ba\u011fc\u0131ll\u0131"
    ],
    "wof:name":"Bagcilli",
    "wof:placetype":"locality"
},
  "geometry": {"coordinates":[28.40602,38.0546],"type":"Point"}
}