{
  "type": "Feature",
  "properties": {
    "gn:admin1_code":"04",
    "gn:asciiname":"Ergecli",
    "gn:country_code":"TR",
    "gn:dem":1959,
    "gn:feature_class":"P",
    "gn:feature_code":"PPL",
    "gn:name":"Erge\u00e7li",
    "gn:population":0,
    "gn:timezone":"Europe/Istanbul",
    "iso:country":"TR",
    "name:tur_x_preferred":[
        "Erge\u00e7li"
    ],
    "name:und_x_variant":[
        "Ka\u011fam",
        "Erke\u00e7li"
    ],
    "wof:name":"Ergecli",
    "wof:placetype":"locality"
},
  "geometry": {"coordinates":[42.8226,39.03349],"type":"Point"}
}