{
  "type": "Feature",
  "properties": {
    "iso:country":"TR",
    "wof:name":"Fetihtepe",
    "wof:placetype":"neighbourhood"
},
  "geometry": {"coordinates":[28.95562807714939,41.04673237390788],"type":"Point"}
}