{
  "type": "Feature",
  "properties": {
    "gn:admin1_code":"76.0",
    "gn:asciiname":"Sikestaniomer",
    "gn:country_code":"TR",
    "gn:dem":734,
    "gn:feature_class":"P",
    "gn:feature_code":"PPL",
    "gn:name":"\u015eikestani\u00f6mer",
    "gn:population":0,
    "gn:timezone":"Europe/Istanbul",
    "iso:country":"TR",
    "wof:name":"Sikestaniomer",
    "wof:placetype":"locality"
},
  "geometry": {"coordinates":[41.50556,37.7625],"type":"Point"}
}