{
  "type": "Feature",
  "properties": {
    "gn:admin1_code":"31.0",
    "gn:asciiname":"Kurtulus",
    "gn:country_code":"TR",
    "gn:dem":84,
    "gn:feature_class":"P",
    "gn:feature_code":"PPL",
    "gn:name":"Kurtulu\u015f",
    "gn:population":0,
    "gn:timezone":"Europe/Istanbul",
    "iso:country":"TR",
    "name:und_x_variant":[
        "Kurtulu\u015f",
        "Tak\u0131nat"
    ],
    "wof:name":"Kurtulus",
    "wof:placetype":"locality"
},
  "geometry": {"coordinates":[36.3713,36.29586],"type":"Point"}
}