{
  "type": "Feature",
  "properties": {
    "gn:admin1_code":"17",
    "gn:asciiname":"Yaylacik",
    "gn:country_code":"TR",
    "gn:dem":372,
    "gn:feature_class":"P",
    "gn:feature_code":"PPL",
    "gn:name":"Yaylac\u0131k",
    "gn:population":0,
    "gn:timezone":"Europe/Istanbul",
    "iso:country":"TR",
    "name:tur_x_preferred":[
        "Yaylac\u0131k"
    ],
    "wof:name":"Yaylacik",
    "wof:placetype":"locality"
},
  "geometry": {"coordinates":[26.28028,39.68194],"type":"Point"}
}