{
  "type": "Feature",
  "properties": {
    "gn:admin1_code":"75",
    "gn:asciiname":"Hatipoglutolu",
    "gn:country_code":"TR",
    "gn:dem":945,
    "gn:feature_class":"P",
    "gn:feature_code":"PPL",
    "gn:name":"Hatipo\u011flutolu",
    "gn:population":0,
    "gn:timezone":"Europe/Istanbul",
    "iso:country":"TR",
    "name:und_x_variant":[
        "Hatipo\u011flutolu"
    ],
    "wof:name":"Hatipoglutolu",
    "wof:placetype":"locality"
},
  "geometry": {"coordinates":[33.91486,38.38256],"type":"Point"}
}