{
  "type": "Feature",
  "properties": {
    "gn:admin1_code":"8.0",
    "gn:asciiname":"Zorlu",
    "gn:country_code":"TR",
    "gn:dem":592,
    "gn:feature_class":"P",
    "gn:feature_code":"PPL",
    "gn:name":"Zorlu",
    "gn:population":0,
    "gn:timezone":"Europe/Istanbul",
    "iso:country":"TR",
    "name:und_x_variant":[
        "Kiremitli"
    ],
    "wof:name":"Zorlu",
    "wof:placetype":"locality"
},
  "geometry": {"coordinates":[41.70849000000001,41.29488],"type":"Point"}
}