{
  "type": "Feature",
  "properties": {
    "gn:admin1_code":"28.0",
    "gn:asciiname":"Kayali",
    "gn:country_code":"TR",
    "gn:dem":1712,
    "gn:feature_class":"P",
    "gn:feature_code":"PPL",
    "gn:name":"Kayal\u0131",
    "gn:population":0,
    "gn:timezone":"Europe/Istanbul",
    "iso:country":"TR",
    "name:und_x_variant":[
        "Gezan\u00e7",
        "Kezan\u00e7",
        "Kayal\u0131"
    ],
    "wof:name":"Kayali",
    "wof:placetype":"locality"
},
  "geometry": {"coordinates":[38.52011,40.1899],"type":"Point"}
}