{
  "type": "Feature",
  "properties": {
    "gn:admin1_code":"48",
    "gn:asciiname":"Buzagiotu",
    "gn:country_code":"TR",
    "gn:dem":55,
    "gn:feature_class":"P",
    "gn:feature_code":"PPL",
    "gn:name":"Buza\u011f\u0131otu",
    "gn:population":0,
    "gn:timezone":"Europe/Istanbul",
    "iso:country":"TR",
    "name:tur_x_preferred":[
        "Buza\u011f\u0131otu"
    ],
    "wof:name":"Buzagiotu",
    "wof:placetype":"locality"
},
  "geometry": {"coordinates":[28.18426,36.92411],"type":"Point"}
}