{
  "type": "Feature",
  "properties": {
    "gn:admin1_code":"45",
    "gn:asciiname":"Cardakli",
    "gn:country_code":"TR",
    "gn:dem":803,
    "gn:feature_class":"P",
    "gn:feature_code":"PPL",
    "gn:name":"\u00c7ardakl\u0131",
    "gn:population":0,
    "gn:timezone":"Europe/Istanbul",
    "iso:country":"TR",
    "name:tur_x_preferred":[
        "\u00c7artak"
    ],
    "name:tur_x_variant":[
        "\u00c7oruk",
        "\u00c7ardakl\u0131"
    ],
    "wof:name":"Cardakli",
    "wof:placetype":"locality"
},
  "geometry": {"coordinates":[28.63684000000001,38.97315],"type":"Point"}
}