{
  "type": "Feature",
  "properties": {
    "gn:admin1_code":"03",
    "gn:asciiname":"Uckuyu",
    "gn:country_code":"TR",
    "gn:dem":1165,
    "gn:feature_class":"P",
    "gn:feature_code":"PPL",
    "gn:name":"\u00dc\u00e7kuyu",
    "gn:population":0,
    "gn:timezone":"Europe/Istanbul",
    "iso:country":"TR",
    "wof:name":"Uckuyu",
    "wof:placetype":"locality"
},
  "geometry": {"coordinates":[31.43472,38.63722],"type":"Point"}
}