{
  "type": "Feature",
  "properties": {
    "gn:admin1_code":"85",
    "gn:asciiname":"Hasbeyler",
    "gn:country_code":"TR",
    "gn:dem":185,
    "gn:feature_class":"P",
    "gn:feature_code":"PPL",
    "gn:name":"Hasbeyler",
    "gn:population":0,
    "gn:timezone":"Europe/Istanbul",
    "iso:country":"TR",
    "wof:name":"Hasbeyler",
    "wof:placetype":"locality"
},
  "geometry": {"coordinates":[31.74199,41.23951],"type":"Point"}
}