{
  "type": "Feature",
  "properties": {
    "gn:admin1_code":"52.0",
    "gn:asciiname":"Ogmaca",
    "gn:country_code":"TR",
    "gn:dem":303,
    "gn:feature_class":"P",
    "gn:feature_code":"PPL",
    "gn:name":"O\u011fmaca",
    "gn:population":0,
    "gn:timezone":"Europe/Istanbul",
    "iso:country":"TR",
    "name:tur_x_preferred":[
        "O\u011fmaca"
    ],
    "wof:name":"Ogmaca",
    "wof:placetype":"locality"
},
  "geometry": {"coordinates":[37.79599,40.97094],"type":"Point"}
}