{
  "type": "Feature",
  "properties": {
    "gn:admin1_code":"77.0",
    "gn:asciiname":"Orta Cimagil",
    "gn:country_code":"TR",
    "gn:dem":1975,
    "gn:feature_class":"P",
    "gn:feature_code":"PPL",
    "gn:name":"Orta \u00c7ima\u011f\u0131l",
    "gn:population":0,
    "gn:timezone":"Europe/Istanbul",
    "iso:country":"TR",
    "name:tur_x_preferred":[
        "Orta \u00c7ima\u011f\u0131l"
    ],
    "name:und_x_variant":[
        "Orta\u00e7ima\u011f\u0131l K\u00f6y\u00fc",
        "Orta\u00e7ima\u011f\u0131l"
    ],
    "wof:name":"Orta Cimagil",
    "wof:placetype":"locality"
},
  "geometry": {"coordinates":[40.59978,40.10737],"type":"Point"}
}