{
  "type": "Feature",
  "properties": {
    "gn:admin1_code":"61.0",
    "gn:asciiname":"Kamislik",
    "gn:country_code":"TR",
    "gn:dem":475,
    "gn:feature_class":"P",
    "gn:feature_code":"PPL",
    "gn:name":"Kam\u0131\u015fl\u0131k",
    "gn:population":0,
    "gn:timezone":"Europe/Istanbul",
    "iso:country":"TR",
    "wof:name":"Kamislik",
    "wof:placetype":"locality"
},
  "geometry": {"coordinates":[39.68698,40.91126],"type":"Point"}
}