{
  "type": "Feature",
  "properties": {
    "gn:admin1_code":"93",
    "gn:asciiname":"Kozak",
    "gn:country_code":"TR",
    "gn:dem":441,
    "gn:feature_class":"P",
    "gn:feature_code":"PPL",
    "gn:name":"Kozak",
    "gn:population":0,
    "gn:timezone":"Europe/Istanbul",
    "iso:country":"TR",
    "wof:name":"Kozak",
    "wof:placetype":"locality"
},
  "geometry": {"coordinates":[30.982,40.94666],"type":"Point"}
}