{
  "type": "Feature",
  "properties": {
    "gn:admin1_code":"65.0",
    "gn:asciiname":"Elmacik",
    "gn:country_code":"TR",
    "gn:dem":1806,
    "gn:feature_class":"P",
    "gn:feature_code":"PPL",
    "gn:name":"Elmac\u0131k",
    "gn:population":0,
    "gn:timezone":"Europe/Istanbul",
    "iso:country":"TR",
    "name:tur_x_preferred":[
        "Elmac\u0131k"
    ],
    "wof:name":"Elmacik",
    "wof:placetype":"locality"
},
  "geometry": {"coordinates":[43.07476,38.08125],"type":"Point"}
}