{
  "type": "Feature",
  "properties": {
    "gn:admin1_code":"16",
    "gn:asciiname":"Camoglu",
    "gn:country_code":"TR",
    "gn:dem":811,
    "gn:feature_class":"P",
    "gn:feature_code":"PPL",
    "gn:name":"\u00c7amo\u011flu",
    "gn:population":0,
    "gn:timezone":"Europe/Istanbul",
    "iso:country":"TR",
    "name:tur_x_preferred":[
        "\u00c7amo\u011flu"
    ],
    "wof:name":"Camoglu",
    "wof:placetype":"locality"
},
  "geometry": {"coordinates":[29.13323,39.71514000000001],"type":"Point"}
}