{
  "type": "Feature",
  "properties": {
    "gn:admin1_code":"2.0",
    "gn:asciiname":"Yamacli",
    "gn:country_code":"TR",
    "gn:dem":886,
    "gn:feature_class":"P",
    "gn:feature_code":"PPL",
    "gn:name":"Yama\u00e7l\u0131",
    "gn:population":0,
    "gn:timezone":"Europe/Istanbul",
    "iso:country":"TR",
    "wof:name":"Yamacli",
    "wof:placetype":"locality"
},
  "geometry": {"coordinates":[38.67142,37.89069],"type":"Point"}
}