{
  "type": "Feature",
  "properties": {
    "gn:admin1_code":"10",
    "gn:asciiname":"Kirmizilar",
    "gn:country_code":"TR",
    "gn:dem":446,
    "gn:feature_class":"P",
    "gn:feature_code":"PPL",
    "gn:name":"K\u0131rm\u0131z\u0131lar",
    "gn:population":0,
    "gn:timezone":"Europe/Istanbul",
    "iso:country":"TR",
    "name:tur_x_preferred":[
        "K\u0131rm\u0131z\u0131lar"
    ],
    "wof:name":"Kirmizilar",
    "wof:placetype":"locality"
},
  "geometry": {"coordinates":[27.7986,39.79792],"type":"Point"}
}