{
  "type": "Feature",
  "properties": {
    "gn:admin1_code":"93",
    "gn:asciiname":"Yorukler",
    "gn:country_code":"TR",
    "gn:dem":642,
    "gn:feature_class":"P",
    "gn:feature_code":"PPL",
    "gn:name":"Y\u00f6r\u00fckler",
    "gn:population":0,
    "gn:timezone":"Europe/Istanbul",
    "iso:country":"TR",
    "wof:name":"Yorukler",
    "wof:placetype":"locality"
},
  "geometry": {"coordinates":[31.41763,40.93876],"type":"Point"}
}