{
  "type": "Feature",
  "properties": {
    "gn:admin1_code":"76.0",
    "gn:asciiname":"Havrik",
    "gn:country_code":"TR",
    "gn:dem":1173,
    "gn:feature_class":"P",
    "gn:feature_code":"PPL",
    "gn:name":"Havr\u0131k",
    "gn:population":0,
    "gn:timezone":"Europe/Istanbul",
    "iso:country":"TR",
    "wof:name":"Havrik",
    "wof:placetype":"locality"
},
  "geometry": {"coordinates":[41.2796,38.31891],"type":"Point"}
}