{
  "type": "Feature",
  "properties": {
    "gn:admin1_code":"10",
    "gn:asciiname":"Kayaeli",
    "gn:country_code":"TR",
    "gn:dem":422,
    "gn:feature_class":"P",
    "gn:feature_code":"PPL",
    "gn:name":"Kayaeli",
    "gn:population":0,
    "gn:timezone":"Europe/Istanbul",
    "iso:country":"TR",
    "name:tur_x_preferred":[
        "Kayaeli"
    ],
    "wof:name":"Kayaeli",
    "wof:placetype":"locality"
},
  "geometry": {"coordinates":[28.31024,39.75547],"type":"Point"}
}