{
  "type": "Feature",
  "properties": {
    "gn:admin1_code":"68",
    "gn:asciiname":"Seyhali",
    "gn:cc2":"TR",
    "gn:country_code":"TR",
    "gn:dem":1005,
    "gn:feature_class":"P",
    "gn:feature_code":"PPL",
    "gn:name":"\u015eeyhali",
    "gn:population":0,
    "gn:timezone":"Europe/Istanbul",
    "iso:country":"TR",
    "name:und_x_variant":[
        "\u015e\u0131hal\u0131",
        "\u015eeyali",
        "\u015eeyhali"
    ],
    "wof:name":"Seyhali",
    "wof:placetype":"locality"
},
  "geometry": {"coordinates":[32.29417,39.49917],"type":"Point"}
}