{
  "type": "Feature",
  "properties": {
    "gn:admin1_code":"14",
    "gn:asciiname":"Cobanlar",
    "gn:country_code":"TR",
    "gn:dem":1352,
    "gn:feature_class":"P",
    "gn:feature_code":"PPL",
    "gn:name":"\u00c7obanlar",
    "gn:population":0,
    "gn:timezone":"Europe/Istanbul",
    "iso:country":"TR",
    "wof:name":"Cobanlar",
    "wof:placetype":"locality"
},
  "geometry": {"coordinates":[31.39159,40.57948],"type":"Point"}
}