{
  "type": "Feature",
  "properties": {
    "gn:admin1_code":"09",
    "gn:asciiname":"Yakacik",
    "gn:country_code":"TR",
    "gn:dem":584,
    "gn:feature_class":"P",
    "gn:feature_code":"PPL",
    "gn:name":"Yakac\u0131k",
    "gn:population":0,
    "gn:timezone":"Europe/Istanbul",
    "iso:country":"TR",
    "name:tur_x_preferred":[
        "Yakac\u0131k"
    ],
    "wof:name":"Yakacik",
    "wof:placetype":"locality"
},
  "geometry": {"coordinates":[27.93007,37.91241],"type":"Point"}
}