{
  "type": "Feature",
  "properties": {
    "gn:admin1_code":"54",
    "gn:asciiname":"Oruclu",
    "gn:country_code":"TR",
    "gn:dem":129,
    "gn:feature_class":"P",
    "gn:feature_code":"PPL",
    "gn:name":"Oru\u00e7lu",
    "gn:population":0,
    "gn:timezone":"Europe/Istanbul",
    "iso:country":"TR",
    "name:tur_x_preferred":[
        "Oru\u00e7lu"
    ],
    "wof:name":"Oruclu",
    "wof:placetype":"locality"
},
  "geometry": {"coordinates":[30.11225,40.50771],"type":"Point"}
}