{
  "type": "Feature",
  "properties": {
    "gn:admin1_code":"35",
    "gn:asciiname":"Ciplakoy",
    "gn:country_code":"TR",
    "gn:dem":27,
    "gn:feature_class":"P",
    "gn:feature_code":"PPL",
    "gn:name":"\u00c7\u0131plak\u00f6y",
    "gn:population":0,
    "gn:timezone":"Europe/Istanbul",
    "iso:country":"TR",
    "name:tur_x_preferred":[
        "\u00c7\u0131plak\u00f6y"
    ],
    "name:tur_x_variant":[
        "Ye\u015filova"
    ],
    "wof:name":"Ciplakoy",
    "wof:placetype":"locality"
},
  "geometry": {"coordinates":[27.56123,38.16674],"type":"Point"}
}