{
  "type": "Feature",
  "properties": {
    "gn:admin1_code":"58",
    "gn:asciiname":"Goller",
    "gn:country_code":"TR",
    "gn:dem":1864,
    "gn:feature_class":"P",
    "gn:feature_code":"PPL",
    "gn:name":"G\u00f6ller",
    "gn:population":0,
    "gn:timezone":"Europe/Istanbul",
    "iso:country":"TR",
    "wof:name":"Goller",
    "wof:placetype":"locality"
},
  "geometry": {"coordinates":[37.65,39.58333],"type":"Point"}
}