{
  "type": "Feature",
  "properties": {
    "gn:admin1_code":"89",
    "gn:asciiname":"Kale",
    "gn:country_code":"TR",
    "gn:dem":492,
    "gn:feature_class":"P",
    "gn:feature_code":"PPL",
    "gn:name":"Kale",
    "gn:population":0,
    "gn:timezone":"Europe/Istanbul",
    "iso:country":"TR",
    "name:tur_x_preferred":[
        "Kale"
    ],
    "name:tur_x_variant":[
        "Ey\u00fcbo\u011flu"
    ],
    "wof:name":"Kale",
    "wof:placetype":"locality"
},
  "geometry": {"coordinates":[32.17829,41.2141],"type":"Point"}
}