{
  "type": "Feature",
  "properties": {
    "gn:admin1_code":"12",
    "gn:asciiname":"Amaric",
    "gn:cc2":"TR",
    "gn:country_code":"TR",
    "gn:dem":1818,
    "gn:feature_class":"P",
    "gn:feature_code":"PPL",
    "gn:name":"Amari\u00e7",
    "gn:population":0,
    "gn:timezone":"Europe/Istanbul",
    "iso:country":"TR",
    "name:und_x_variant":[
        "Mari\u00e7",
        "Ameri\u00e7",
        "Amari\u00e7"
    ],
    "wof:name":"Amaric",
    "wof:placetype":"locality"
},
  "geometry": {"coordinates":[40.43333,39.48333],"type":"Point"}
}