{
  "type": "Feature",
  "properties": {
    "gn:admin1_code":"48",
    "gn:asciiname":"Seyhkavagi",
    "gn:country_code":"TR",
    "gn:dem":1053,
    "gn:feature_class":"P",
    "gn:feature_code":"PPL",
    "gn:name":"\u015eeyhkava\u011f\u0131",
    "gn:population":0,
    "gn:timezone":"Europe/Istanbul",
    "iso:country":"TR",
    "wof:name":"Seyhkavagi",
    "wof:placetype":"locality"
},
  "geometry": {"coordinates":[29.45571,36.46167],"type":"Point"}
}