{
  "type": "Feature",
  "properties": {
    "gn:admin1_code":"75",
    "gn:asciiname":"Tabtik",
    "gn:country_code":"TR",
    "gn:dem":1422,
    "gn:feature_class":"P",
    "gn:feature_code":"PPL",
    "gn:name":"Tabt\u0131k",
    "gn:population":0,
    "gn:timezone":"Europe/Istanbul",
    "iso:country":"TR",
    "name:tur_x_preferred":[
        "Tabt\u0131k"
    ],
    "name:tur_x_variant":[
        "Tapd\u0131k"
    ],
    "wof:name":"Tabtik",
    "wof:placetype":"locality"
},
  "geometry": {"coordinates":[34.12918,38.56321],"type":"Point"}
}