{
  "type": "Feature",
  "properties": {
    "gn:admin1_code":"84.0",
    "gn:asciiname":"Satiroglu",
    "gn:country_code":"TR",
    "gn:dem":2145,
    "gn:feature_class":"P",
    "gn:feature_code":"PPL",
    "gn:name":"\u015eat\u0131ro\u011flu",
    "gn:population":0,
    "gn:timezone":"Europe/Istanbul",
    "iso:country":"TR",
    "name:tur_x_preferred":[
        "\u015eat\u0131ro\u011flu"
    ],
    "name:und_x_variant":[
        "Sat\u0131ro\u011flu"
    ],
    "wof:name":"Satiroglu",
    "wof:placetype":"locality"
},
  "geometry": {"coordinates":[43.28836,40.44323],"type":"Point"}
}