{
  "type": "Feature",
  "properties": {
    "gn:admin1_code":"71",
    "gn:asciiname":"Bademli Yaylasi",
    "gn:country_code":"TR",
    "gn:dem":1005,
    "gn:feature_class":"P",
    "gn:feature_code":"PPL",
    "gn:name":"Bademli Yaylas\u0131",
    "gn:population":0,
    "gn:timezone":"Europe/Istanbul",
    "iso:country":"TR",
    "wof:name":"Bademli Yaylasi",
    "wof:placetype":"locality"
},
  "geometry": {"coordinates":[33.08333,38.18333],"type":"Point"}
}