{
  "type": "Feature",
  "properties": {
    "gn:admin1_code":"62",
    "gn:asciiname":"Asagi Torunoba",
    "gn:country_code":"TR",
    "gn:dem":1399,
    "gn:feature_class":"P",
    "gn:feature_code":"PPL",
    "gn:name":"A\u015fa\u011f\u0131 Torunoba",
    "gn:population":0,
    "gn:timezone":"Europe/Istanbul",
    "iso:country":"TR",
    "name:tur_x_preferred":[
        "A\u015fa\u011f\u0131 Torunoba"
    ],
    "name:und_x_variant":[
        "A\u015fa\u011f\u0131torunoba"
    ],
    "wof:name":"Asagi Torunoba",
    "wof:placetype":"locality"
},
  "geometry": {"coordinates":[39.38825,39.3099],"type":"Point"}
}