{
  "type": "Feature",
  "properties": {
    "gn:admin1_code":"02",
    "gn:asciiname":"Yukari Karakuyu",
    "gn:country_code":"TR",
    "gn:dem":1232,
    "gn:feature_class":"P",
    "gn:feature_code":"PPL",
    "gn:name":"Yukar\u0131 Karakuyu",
    "gn:population":0,
    "gn:timezone":"Europe/Istanbul",
    "iso:country":"TR",
    "name:tur_x_preferred":[
        "Yukar\u0131 Karakuyu"
    ],
    "name:und_x_variant":[
        "Karakuyu K\u00f6y\u00fc",
        "Karakuyu"
    ],
    "wof:name":"Yukari Karakuyu",
    "wof:placetype":"locality"
},
  "geometry": {"coordinates":[37.6512,37.70254],"type":"Point"}
}