{
  "type": "Feature",
  "properties": {
    "gn:admin1_code":"10.0",
    "gn:asciiname":"Calioba",
    "gn:country_code":"TR",
    "gn:dem":79,
    "gn:feature_class":"P",
    "gn:feature_code":"PPL",
    "gn:name":"\u00c7al\u0131oba",
    "gn:population":0,
    "gn:timezone":"Europe/Istanbul",
    "iso:country":"TR",
    "name:tur_x_preferred":[
        "\u00c7al\u0131oba"
    ],
    "wof:name":"Calioba",
    "wof:placetype":"locality"
},
  "geometry": {"coordinates":[27.72732,40.17801],"type":"Point"}
}