{
  "type": "Feature",
  "properties": {
    "gn:admin1_code":"25.0",
    "gn:asciiname":"Zanzak",
    "gn:country_code":"TR",
    "gn:dem":1767,
    "gn:feature_class":"P",
    "gn:feature_code":"PPL",
    "gn:name":"Zanzak",
    "gn:population":0,
    "gn:timezone":"Europe/Istanbul",
    "iso:country":"TR",
    "wof:name":"Zanzak",
    "wof:placetype":"locality"
},
  "geometry": {"coordinates":[42.15,40.13333],"type":"Point"}
}