{
  "type": "Feature",
  "properties": {
    "gn:admin1_code":"45",
    "gn:asciiname":"Baharlar",
    "gn:country_code":"TR",
    "gn:dem":290,
    "gn:feature_class":"P",
    "gn:feature_code":"PPL",
    "gn:name":"Baharlar",
    "gn:population":0,
    "gn:timezone":"Europe/Istanbul",
    "iso:country":"TR",
    "name:tur_x_preferred":[
        "Baharlar"
    ],
    "wof:name":"Baharlar",
    "wof:placetype":"locality"
},
  "geometry": {"coordinates":[28.76278,38.20181],"type":"Point"}
}