{
  "type": "Feature",
  "properties": {
    "gn:admin1_code":"63",
    "gn:asciiname":"Yukari Bostanci",
    "gn:country_code":"TR",
    "gn:dem":553,
    "gn:feature_class":"P",
    "gn:feature_code":"PPL",
    "gn:name":"Yukar\u0131 Bostanc\u0131",
    "gn:population":0,
    "gn:timezone":"Europe/Istanbul",
    "iso:country":"TR",
    "name:tur_x_preferred":[
        "Yukar\u0131 Bostanc\u0131"
    ],
    "name:tur_x_variant":[
        "Yukar\u0131 Bostan"
    ],
    "name:und_x_variant":[
        "Yukar\u0131 Bostanc\u0131k",
        "Bostanc\u0131k"
    ],
    "wof:name":"Yukari Bostanci",
    "wof:placetype":"locality"
},
  "geometry": {"coordinates":[38.3356,37.05401],"type":"Point"}
}