{
  "type": "Feature",
  "properties": {
    "gn:admin1_code":"19.0",
    "gn:asciiname":"Hacibayram",
    "gn:country_code":"TR",
    "gn:dem":685,
    "gn:feature_class":"P",
    "gn:feature_code":"PPL",
    "gn:name":"Hac\u0131bayram",
    "gn:population":0,
    "gn:timezone":"Europe/Istanbul",
    "iso:country":"TR",
    "wof:name":"Hacibayram",
    "wof:placetype":"locality"
},
  "geometry": {"coordinates":[34.35663,40.6243],"type":"Point"}
}