{
  "type": "Feature",
  "properties": {
    "gn:admin1_code":"93",
    "gn:asciiname":"Gunbasi",
    "gn:country_code":"TR",
    "gn:dem":208,
    "gn:feature_class":"P",
    "gn:feature_code":"PPL",
    "gn:name":"G\u00fcnba\u015f\u0131",
    "gn:population":0,
    "gn:timezone":"Europe/Istanbul",
    "iso:country":"TR",
    "wof:name":"Gunbasi",
    "wof:placetype":"locality"
},
  "geometry": {"coordinates":[31.24448,40.84201],"type":"Point"}
}