{
  "type": "Feature",
  "properties": {
    "gn:admin1_code":"10",
    "gn:asciiname":"Tekkeisiklar",
    "gn:country_code":"TR",
    "gn:dem":111,
    "gn:feature_class":"P",
    "gn:feature_code":"PPL",
    "gn:name":"Tekke\u0131\u015f\u0131klar",
    "gn:population":0,
    "gn:timezone":"Europe/Istanbul",
    "iso:country":"TR",
    "name:tur_x_preferred":[
        "Tekke"
    ],
    "name:und_x_variant":[
        "Tekke\u0131\u015f\u0131klar"
    ],
    "wof:name":"Tekkeisiklar",
    "wof:placetype":"locality"
},
  "geometry": {"coordinates":[28.17156,39.71102],"type":"Point"}
}