{
  "type": "Feature",
  "properties": {
    "gn:admin1_code":"14.0",
    "gn:asciiname":"Daghacilar",
    "gn:country_code":"TR",
    "gn:dem":1021,
    "gn:feature_class":"P",
    "gn:feature_code":"PPL",
    "gn:name":"Da\u011fhac\u0131lar",
    "gn:population":0,
    "gn:timezone":"Europe/Istanbul",
    "iso:country":"TR",
    "name:und_x_variant":[
        "Hac\u0131lar",
        "Da\u011fhac\u0131lar"
    ],
    "wof:name":"Daghacilar",
    "wof:placetype":"locality"
},
  "geometry": {"coordinates":[30.96595,40.27471],"type":"Point"}
}