{
  "type": "Feature",
  "properties": {
    "iso:country":"TR",
    "name:tur_x_preferred":[
        "Tayakad\u0131n"
    ],
    "wof:name":"Tayakadin",
    "wof:placetype":"neighbourhood"
},
  "geometry": {"coordinates":[28.69087874725687,41.26861313644749],"type":"Point"}
}