{
  "type": "Feature",
  "properties": {
    "gn:admin1_code":"25.0",
    "gn:asciiname":"Iyidere",
    "gn:country_code":"TR",
    "gn:dem":1901,
    "gn:feature_class":"P",
    "gn:feature_code":"PPL",
    "gn:name":"\u0130yidere",
    "gn:population":0,
    "gn:timezone":"Europe/Istanbul",
    "iso:country":"TR",
    "name:tur_x_preferred":[
        "\u0130yidere"
    ],
    "wof:name":"Iyidere",
    "wof:placetype":"locality"
},
  "geometry": {"coordinates":[40.85102,40.51499],"type":"Point"}
}