{
  "type": "Feature",
  "properties": {
    "gn:admin1_code":"22.0",
    "gn:asciiname":"Yerlisu",
    "gn:country_code":"TR",
    "gn:dem":167,
    "gn:feature_class":"P",
    "gn:feature_code":"PPL",
    "gn:name":"Yerlisu",
    "gn:population":0,
    "gn:timezone":"Europe/Istanbul",
    "iso:country":"TR",
    "name:und_x_variant":[
        "\u00c7ap\u00e7a",
        "Yerlisu"
    ],
    "wof:name":"Yerlisu",
    "wof:placetype":"locality"
},
  "geometry": {"coordinates":[26.72871,40.72687],"type":"Point"}
}