{
  "type": "Feature",
  "properties": {
    "gn:admin1_code":"26.0",
    "gn:asciiname":"Ahirozu",
    "gn:country_code":"TR",
    "gn:dem":1106,
    "gn:feature_class":"P",
    "gn:feature_code":"PPL",
    "gn:name":"Ah\u0131r\u00f6z\u00fc",
    "gn:population":0,
    "gn:timezone":"Europe/Istanbul",
    "iso:country":"TR",
    "name:und_x_variant":[
        "Ah\u0131r\u00f6z\u00fc"
    ],
    "wof:name":"Ahirozu",
    "wof:placetype":"locality"
},
  "geometry": {"coordinates":[31.70083,39.79333],"type":"Point"}
}