{
  "type": "Feature",
  "properties": {
    "gn:admin1_code":"86.0",
    "gn:asciiname":"Dagci",
    "gn:country_code":"TR",
    "gn:dem":2121,
    "gn:feature_class":"P",
    "gn:feature_code":"PPL",
    "gn:name":"Da\u011fc\u0131",
    "gn:population":0,
    "gn:timezone":"Europe/Istanbul",
    "iso:country":"TR",
    "name:und_x_variant":[
        "Tikos",
        "Da\u011fc\u0131"
    ],
    "wof:name":"Dagci",
    "wof:placetype":"locality"
},
  "geometry": {"coordinates":[42.90151,40.89957],"type":"Point"}
}