{
  "type": "Feature",
  "properties": {
    "iso:country":"TU",
    "name:und_x_variant":[
        "Hosnudiye"
    ],
    "qs:gn_adm0_cc":"TR",
    "qs:gn_local":315202,
    "qs:local_max":228,
    "qs:local_sum":472,
    "qs:localhoods":5,
    "qs:name":"Hosnudiye",
    "qs:name_adm0":"Turkey",
    "qs:name_adm1":"Eski\u015fehir",
    "qs:name_adm2":"Merkez",
    "qs:name_local":"Eski\u015fehir",
    "qs:photo_max":26,
    "qs:photo_sum":65,
    "qs:placetype":"Suburb",
    "qs:quad_count":8,
    "qs:woe_adm0":23424969,
    "qs:woe_adm1":2347283,
    "qs:woe_adm2":29390626,
    "qs:woe_lau":0,
    "qs:woe_local":2343980,
    "qs:woe_ver":"7.10.0",
    "wof:lang":[
        "unk"
    ],
    "wof:name":"Hosnudiye",
    "wof:placetype":"neighbourhood"
},
  "geometry": {"coordinates":[30.511046,39.777877],"type":"Point"}
}