{
  "type": "Feature",
  "properties": {
    "gn:admin1_code":"25.0",
    "gn:asciiname":"Kirkdikme",
    "gn:country_code":"TR",
    "gn:dem":1652,
    "gn:feature_class":"P",
    "gn:feature_code":"PPL",
    "gn:name":"K\u0131rkdikme",
    "gn:population":0,
    "gn:timezone":"Europe/Istanbul",
    "iso:country":"TR",
    "name:tur_x_preferred":[
        "K\u0131rkdikme"
    ],
    "wof:name":"Kirkdikme",
    "wof:placetype":"locality"
},
  "geometry": {"coordinates":[41.98881,40.04306],"type":"Point"}
}