{
  "type": "Feature",
  "properties": {
    "gn:admin1_code":"10",
    "gn:asciiname":"Selimiye",
    "gn:country_code":"TR",
    "gn:dem":163,
    "gn:feature_class":"P",
    "gn:feature_code":"PPL",
    "gn:name":"Selimiye",
    "gn:population":0,
    "gn:timezone":"Europe/Istanbul",
    "iso:country":"TR",
    "name:tur_x_preferred":[
        "Selimiye"
    ],
    "wof:name":"Selimiye",
    "wof:placetype":"locality"
},
  "geometry": {"coordinates":[27.93142000000001,39.48047],"type":"Point"}
}