{
  "type": "Feature",
  "properties": {
    "gn:admin1_code":"10",
    "gn:asciiname":"Selimiye",
    "gn:country_code":"TR",
    "gn:dem":163,
    "gn:feature_class":"P",
    "gn:feature_code":"PPL",
    "gn:name":"Selimiye",
    "gn:population":0,
    "gn:timezone":"Europe/Istanbul",
    "iso:country":"TR",
    "name:deu_x_preferred":[
        "Selimiye"
    ],
    "name:ell_x_preferred":[
        "\u03a3\u03b5\u03bb\u03b9\u03bc\u03b9\u03b3\u03b9\u03ad"
    ],
    "name:fra_x_preferred":[
        "Selimiye"
    ],
    "name:tur_x_preferred":[
        "Selimiye"
    ],
    "wof:name":"Selimiye",
    "wof:placetype":"locality"
},
  "geometry": {"coordinates":[27.93142000000001,39.48047],"type":"Point"}
}