{
  "type": "Feature",
  "properties": {
    "gn:admin1_code":"09",
    "gn:asciiname":"Kuyucular",
    "gn:country_code":"TR",
    "gn:dem":76,
    "gn:feature_class":"P",
    "gn:feature_code":"PPL",
    "gn:name":"Kuyucular",
    "gn:population":0,
    "gn:timezone":"Europe/Istanbul",
    "iso:country":"TR",
    "name:ceb_x_preferred":[
        "Kuyucular"
    ],
    "name:msa_x_preferred":[
        "Kuyucular"
    ],
    "name:tur_x_preferred":[
        "Kuyucular"
    ],
    "name:vie_x_preferred":[
        "Kuyucular"
    ],
    "wof:name":"Kuyucular",
    "wof:placetype":"locality"
},
  "geometry": {"coordinates":[28.02062,37.87015],"type":"Point"}
}