{
  "type": "Feature",
  "properties": {
    "gn:admin1_code":"8.0",
    "gn:asciiname":"Catalcam",
    "gn:country_code":"TR",
    "gn:dem":1744,
    "gn:feature_class":"P",
    "gn:feature_code":"PPL",
    "gn:name":"\u00c7atal\u00e7am",
    "gn:population":0,
    "gn:timezone":"Europe/Istanbul",
    "iso:country":"TR",
    "name:und_x_variant":[
        "\u00c7atal\u00e7am",
        "Ye\u015filce"
    ],
    "wof:name":"Catalcam",
    "wof:placetype":"locality"
},
  "geometry": {"coordinates":[42.31954,41.40263],"type":"Point"}
}