{
  "type": "Feature",
  "properties": {
    "gn:admin1_code":"25.0",
    "gn:asciiname":"Azapkoy",
    "gn:country_code":"TR",
    "gn:dem":1622,
    "gn:feature_class":"P",
    "gn:feature_code":"PPL",
    "gn:name":"Azapk\u00f6y",
    "gn:population":0,
    "gn:timezone":"Europe/Istanbul",
    "iso:country":"TR",
    "name:eng_x_preferred":[
        "Azap"
    ],
    "name:rus_x_preferred":[
        "\u0410\u0437\u0430\u043f"
    ],
    "name:und_x_variant":[
        "Azapk\u00f6y",
        "Azzap",
        "Azab"
    ],
    "wof:name":"Azapkoy",
    "wof:placetype":"locality"
},
  "geometry": {"coordinates":[42.09138,40.07018],"type":"Point"}
}