{
  "type": "Feature",
  "properties": {
    "gn:admin1_code":"86.0",
    "gn:asciiname":"Baykent",
    "gn:country_code":"TR",
    "gn:dem":2218,
    "gn:feature_class":"P",
    "gn:feature_code":"PPL",
    "gn:name":"Baykent",
    "gn:population":0,
    "gn:timezone":"Europe/Istanbul",
    "iso:country":"TR",
    "name:und_x_variant":[
        "Vahla",
        "Baykent"
    ],
    "wof:name":"Baykent",
    "wof:placetype":"locality"
},
  "geometry": {"coordinates":[42.64375,41.39851],"type":"Point"}
}