{
  "type": "Feature",
  "properties": {
    "gn:admin1_code":"69.0",
    "gn:asciiname":"Arduc",
    "gn:country_code":"TR",
    "gn:dem":2042,
    "gn:feature_class":"P",
    "gn:feature_code":"PPL",
    "gn:name":"Ardu\u00e7",
    "gn:population":0,
    "gn:timezone":"Europe/Istanbul",
    "iso:country":"TR",
    "name:tur_x_preferred":[
        "Ardu\u00e7"
    ],
    "name:und_x_variant":[
        "Ard\u00fc\u00e7"
    ],
    "wof:name":"Arduc",
    "wof:placetype":"locality"
},
  "geometry": {"coordinates":[39.8308,40.4488],"type":"Point"}
}