{
  "type": "Feature",
  "properties": {
    "gn:admin1_code":"76",
    "gn:asciiname":"Oguz",
    "gn:country_code":"TR",
    "gn:dem":866,
    "gn:feature_class":"P",
    "gn:feature_code":"PPLA3",
    "gn:name":"O\u011fuz",
    "gn:population":0,
    "gn:timezone":"Europe/Istanbul",
    "iso:country":"TR",
    "name:ceb_x_preferred":[
        "Oguz"
    ],
    "name:nld_x_preferred":[
        "Oguz"
    ],
    "name:por_x_preferred":[
        "Oguz"
    ],
    "name:rus_x_preferred":[
        "\u041e\u0433\u0443\u0437"
    ],
    "name:swe_x_preferred":[
        "Oguz"
    ],
    "name:tur_x_preferred":[
        "O\u011fuz"
    ],
    "name:ukr_x_preferred":[
        "\u041e\u0433\u0443\u0437"
    ],
    "name:und_x_variant":[
        "Shimiz",
        "\u015eimiz"
    ],
    "wof:name":"Oguz",
    "wof:placetype":"locality"
},
  "geometry": {"coordinates":[41.37425,37.81487],"type":"Point"}
}