{
  "type": "Feature",
  "properties": {
    "gn:admin1_code":"10",
    "gn:asciiname":"Hacihuseyinler",
    "gn:country_code":"TR",
    "gn:dem":217,
    "gn:feature_class":"P",
    "gn:feature_code":"PPL",
    "gn:name":"Hac\u0131h\u00fcseyinler",
    "gn:population":0,
    "gn:timezone":"Europe/Istanbul",
    "iso:country":"TR",
    "name:tur_x_preferred":[
        "Hac\u0131h\u00fcseyinler"
    ],
    "wof:name":"Hacihuseyinler",
    "wof:placetype":"locality"
},
  "geometry": {"coordinates":[26.90786,39.36012],"type":"Point"}
}