{
  "type": "Feature",
  "properties": {
    "gn:admin1_code":"63",
    "gn:asciiname":"Yaban",
    "gn:country_code":"TR",
    "gn:dem":516,
    "gn:feature_class":"P",
    "gn:feature_code":"PPL",
    "gn:name":"Yaban",
    "gn:population":0,
    "gn:timezone":"Europe/Istanbul",
    "iso:country":"TR",
    "name:fra_x_preferred":[
        "Yaban"
    ],
    "name:tur_x_preferred":[
        "Yenice"
    ],
    "name:tur_x_variant":[
        "Yaban"
    ],
    "wof:name":"Yaban",
    "wof:placetype":"locality"
},
  "geometry": {"coordinates":[39.9316,37.18858],"type":"Point"}
}