{
  "type": "Feature",
  "properties": {
    "gn:admin1_code":"89",
    "gn:asciiname":"Haydarlar",
    "gn:country_code":"TR",
    "gn:dem":1341,
    "gn:feature_class":"P",
    "gn:feature_code":"PPL",
    "gn:name":"Haydarlar",
    "gn:population":0,
    "gn:timezone":"Europe/Istanbul",
    "iso:country":"TR",
    "wof:name":"Haydarlar",
    "wof:placetype":"locality"
},
  "geometry": {"coordinates":[32.79789,40.96358],"type":"Point"}
}