{
  "type": "Feature",
  "properties": {
    "gn:admin1_code":"13.0",
    "gn:asciiname":"Beskaya",
    "gn:country_code":"TR",
    "gn:dem":1572,
    "gn:feature_class":"P",
    "gn:feature_code":"PPL",
    "gn:name":"Be\u015fkaya",
    "gn:population":0,
    "gn:timezone":"Europe/Istanbul",
    "iso:country":"TR",
    "name:tur_x_preferred":[
        "Be\u015fkaya"
    ],
    "wof:name":"Beskaya",
    "wof:placetype":"locality"
},
  "geometry": {"coordinates":[42.13808,38.34213],"type":"Point"}
}