{
  "type": "Feature",
  "properties": {
    "gn:admin1_code":"38",
    "gn:asciiname":"Zek",
    "gn:country_code":"TR",
    "gn:dem":1492,
    "gn:feature_class":"P",
    "gn:feature_code":"PPL",
    "gn:name":"Zek",
    "gn:population":0,
    "gn:timezone":"Europe/Istanbul",
    "iso:country":"TR",
    "name:tur_x_preferred":[
        "Zek"
    ],
    "wof:name":"Zek",
    "wof:placetype":"locality"
},
  "geometry": {"coordinates":[36.06667,38.71667],"type":"Point"}
}