{
  "type": "Feature",
  "properties": {
    "gn:admin1_code":"43",
    "gn:asciiname":"Muradinlar",
    "gn:country_code":"TR",
    "gn:dem":844,
    "gn:feature_class":"P",
    "gn:feature_code":"PPL",
    "gn:name":"Murad\u0131nlar",
    "gn:population":0,
    "gn:timezone":"Europe/Istanbul",
    "iso:country":"TR",
    "name:tur_x_preferred":[
        "Murad\u0131nlar"
    ],
    "wof:name":"Muradinlar",
    "wof:placetype":"locality"
},
  "geometry": {"coordinates":[29.02054,39.11025],"type":"Point"}
}