{
  "type": "Feature",
  "properties": {
    "gn:admin1_code":"58.0",
    "gn:asciiname":"Demiroluk",
    "gn:country_code":"TR",
    "gn:dem":1219,
    "gn:feature_class":"P",
    "gn:feature_code":"PPL",
    "gn:name":"Demiroluk",
    "gn:population":0,
    "gn:timezone":"Europe/Istanbul",
    "iso:country":"TR",
    "wof:name":"Demiroluk",
    "wof:placetype":"locality"
},
  "geometry": {"coordinates":[36.45196,39.57757],"type":"Point"}
}