{
  "type": "Feature",
  "properties": {
    "gn:admin1_code":"49",
    "gn:asciiname":"Ergat",
    "gn:country_code":"TR",
    "gn:dem":1522,
    "gn:feature_class":"P",
    "gn:feature_code":"PPL",
    "gn:name":"Ergat",
    "gn:population":0,
    "gn:timezone":"Europe/Istanbul",
    "iso:country":"TR",
    "name:tur_x_preferred":[
        "Ergat"
    ],
    "wof:name":"Ergat",
    "wof:placetype":"locality"
},
  "geometry": {"coordinates":[41.35,38.51667],"type":"Point"}
}