{
  "type": "Feature",
  "properties": {
    "gn:admin1_code":"48",
    "gn:asciiname":"Gebeler",
    "gn:country_code":"TR",
    "gn:dem":142,
    "gn:feature_class":"P",
    "gn:feature_code":"PPL",
    "gn:name":"Gebeler",
    "gn:population":0,
    "gn:timezone":"Europe/Istanbul",
    "iso:country":"TR",
    "name:tur_x_preferred":[
        "G\u00fcne\u015fli"
    ],
    "name:tur_x_variant":[
        "Gebeler"
    ],
    "wof:name":"Gebeler",
    "wof:placetype":"locality"
},
  "geometry": {"coordinates":[29.38925,36.56887],"type":"Point"}
}