{
  "type": "Feature",
  "properties": {
    "gn:admin1_code":"69",
    "gn:asciiname":"Yeniyol",
    "gn:country_code":"TR",
    "gn:dem":1328,
    "gn:feature_class":"P",
    "gn:feature_code":"PPL",
    "gn:name":"Yeniyol",
    "gn:population":0,
    "gn:timezone":"Europe/Istanbul",
    "iso:country":"TR",
    "name:tur_x_preferred":[
        "Yeniyol"
    ],
    "wof:name":"Yeniyol",
    "wof:placetype":"locality"
},
  "geometry": {"coordinates":[39.62373,40.40019],"type":"Point"}
}