{
  "type": "Feature",
  "properties": {
    "gn:admin1_code":"17",
    "gn:asciiname":"Pinarbasi",
    "gn:country_code":"TR",
    "gn:dem":151,
    "gn:feature_class":"P",
    "gn:feature_code":"PPL",
    "gn:name":"P\u0131narba\u015f\u0131",
    "gn:population":0,
    "gn:timezone":"Europe/Istanbul",
    "iso:country":"TR",
    "wof:name":"Pinarbasi",
    "wof:placetype":"locality"
},
  "geometry": {"coordinates":[26.5475,39.76861],"type":"Point"}
}