{
  "type": "Feature",
  "properties": {
    "gn:admin1_code":"7.0",
    "gn:asciiname":"Akyazi",
    "gn:country_code":"TR",
    "gn:dem":873,
    "gn:feature_class":"P",
    "gn:feature_code":"PPL",
    "gn:name":"Akyaz\u0131",
    "gn:population":0,
    "gn:timezone":"Europe/Istanbul",
    "iso:country":"TR",
    "wof:name":"Akyazi",
    "wof:placetype":"locality"
},
  "geometry": {"coordinates":[29.50444,36.3875],"type":"Point"}
}