{
  "type": "Feature",
  "properties": {
    "gn:admin1_code":"58.0",
    "gn:asciiname":"Durulmus",
    "gn:country_code":"TR",
    "gn:dem":1311,
    "gn:feature_class":"P",
    "gn:feature_code":"PPL",
    "gn:name":"Durulmu\u015f",
    "gn:population":0,
    "gn:timezone":"Europe/Istanbul",
    "iso:country":"TR",
    "name:ceb_x_preferred":[
        "Durulmu\u015f"
    ],
    "name:msa_x_preferred":[
        "Durulmu\u015f"
    ],
    "name:tur_x_preferred":[
        "Durulmu\u015f"
    ],
    "name:und_x_variant":[
        "Durulmu\u015f"
    ],
    "name:vie_x_preferred":[
        "Durulmu\u015f"
    ],
    "wof:name":"Durulmus",
    "wof:placetype":"locality"
},
  "geometry": {"coordinates":[37.31800000000001,39.84058],"type":"Point"}
}