{
  "type": "Feature",
  "properties": {
    "gn:admin1_code":"52",
    "gn:asciiname":"Esentepe",
    "gn:country_code":"TR",
    "gn:dem":431,
    "gn:feature_class":"P",
    "gn:feature_code":"PPL",
    "gn:name":"Esentepe",
    "gn:population":0,
    "gn:timezone":"Europe/Istanbul",
    "iso:country":"TR",
    "name:tur_x_preferred":[
        "Esentepe"
    ],
    "wof:name":"Esentepe",
    "wof:placetype":"locality"
},
  "geometry": {"coordinates":[37.04903,41.08946],"type":"Point"}
}