{
  "type": "Feature",
  "properties": {
    "gn:admin1_code":"81",
    "gn:asciiname":"Terliksiz",
    "gn:country_code":"TR",
    "gn:dem":5,
    "gn:feature_class":"P",
    "gn:feature_code":"PPL",
    "gn:name":"Terliksiz",
    "gn:population":0,
    "gn:timezone":"Europe/Istanbul",
    "iso:country":"TR",
    "name:deu_x_preferred":[
        "Terliksiz"
    ],
    "name:msa_x_preferred":[
        "Terliksiz"
    ],
    "name:tur_x_preferred":[
        "Terliksiz"
    ],
    "name:vie_x_preferred":[
        "Terliksiz"
    ],
    "wof:name":"Terliksiz",
    "wof:placetype":"locality"
},
  "geometry": {"coordinates":[35.33733,36.69235],"type":"Point"}
}