{
  "type": "Feature",
  "properties": {
    "gn:admin1_code":"38.0",
    "gn:asciiname":"Senirkoy",
    "gn:country_code":"TR",
    "gn:dem":1080,
    "gn:feature_class":"P",
    "gn:feature_code":"PPL",
    "gn:name":"Senirk\u00f6y",
    "gn:population":0,
    "gn:timezone":"Europe/Istanbul",
    "iso:country":"TR",
    "name:tur_x_preferred":[
        "Senirk\u00f6y"
    ],
    "name:tur_x_variant":[
        "Serink\u00f6y"
    ],
    "wof:name":"Senirkoy",
    "wof:placetype":"locality"
},
  "geometry": {"coordinates":[35.27519,38.19189],"type":"Point"}
}