{
  "type": "Feature",
  "properties": {
    "gn:admin1_code":"63.0",
    "gn:asciiname":"Gentari",
    "gn:country_code":"TR",
    "gn:dem":358,
    "gn:feature_class":"P",
    "gn:feature_code":"PPL",
    "gn:name":"Gentari",
    "gn:population":0,
    "gn:timezone":"Europe/Istanbul",
    "iso:country":"TR",
    "name:und_x_variant":[
        "Kentari",
        "Gentari",
        "B\u00fcy\u00fccek"
    ],
    "wof:name":"Gentari",
    "wof:placetype":"locality"
},
  "geometry": {"coordinates":[38.99203,36.77937],"type":"Point"}
}