{
  "type": "Feature",
  "properties": {
    "gn:admin1_code":"14.0",
    "gn:asciiname":"Bolucekkaya",
    "gn:country_code":"TR",
    "gn:dem":1137,
    "gn:feature_class":"P",
    "gn:feature_code":"PPL",
    "gn:name":"B\u00f6l\u00fccekkaya",
    "gn:population":0,
    "gn:timezone":"Europe/Istanbul",
    "iso:country":"TR",
    "name:und_x_variant":[
        "B\u00f6l\u00fck\u00e7ekkaya",
        "B\u00f6l\u00fccekaya",
        "B\u00f6l\u00fccekkaya"
    ],
    "wof:name":"Bolucekkaya",
    "wof:placetype":"locality"
},
  "geometry": {"coordinates":[31.83453,40.41515],"type":"Point"}
}