{
  "type": "Feature",
  "properties": {
    "gn:admin1_code":"71",
    "gn:asciiname":"Bulgarpinari",
    "gn:country_code":"TR",
    "gn:dem":1334,
    "gn:feature_class":"P",
    "gn:feature_code":"PPL",
    "gn:name":"Bulgarp\u0131nar\u0131",
    "gn:population":0,
    "gn:timezone":"Europe/Istanbul",
    "iso:country":"TR",
    "name:tur_x_preferred":[
        "Bulgarp\u0131nar\u0131"
    ],
    "name:tur_x_variant":[
        "Mehdili"
    ],
    "wof:name":"Bulgarpinari",
    "wof:placetype":"locality"
},
  "geometry": {"coordinates":[32.1499,38.13632],"type":"Point"}
}