{
  "type": "Feature",
  "properties": {
    "gn:admin1_code":"77.0",
    "gn:asciiname":"Ulucayir",
    "gn:country_code":"TR",
    "gn:dem":1903,
    "gn:feature_class":"P",
    "gn:feature_code":"PPL",
    "gn:name":"Ulu\u00e7ay\u0131r",
    "gn:population":0,
    "gn:timezone":"Europe/Istanbul",
    "iso:country":"TR",
    "name:und_x_variant":[
        "Alm\u0131\u015fka",
        "Ulu\u00e7ay\u0131r"
    ],
    "wof:name":"Ulucayir",
    "wof:placetype":"locality"
},
  "geometry": {"coordinates":[40.33309000000001,40.25298],"type":"Point"}
}