{
  "type": "Feature",
  "properties": {
    "gn:admin1_code":"91",
    "gn:asciiname":"Kesim",
    "gn:country_code":"TR",
    "gn:dem":210,
    "gn:feature_class":"P",
    "gn:feature_code":"PPL",
    "gn:name":"Kesim",
    "gn:population":0,
    "gn:timezone":"Europe/Istanbul",
    "iso:country":"TR",
    "name:tur_x_preferred":[
        "Kesim"
    ],
    "wof:name":"Kesim",
    "wof:placetype":"locality"
},
  "geometry": {"coordinates":[36.2479,37.43485],"type":"Point"}
}