{
  "type": "Feature",
  "properties": {
    "gn:admin1_code":"5.0",
    "gn:asciiname":"Yerkozlu",
    "gn:country_code":"TR",
    "gn:dem":335,
    "gn:feature_class":"P",
    "gn:feature_code":"PPL",
    "gn:name":"Yerkozlu",
    "gn:population":0,
    "gn:timezone":"Europe/Istanbul",
    "iso:country":"TR",
    "wof:name":"Yerkozlu",
    "wof:placetype":"locality"
},
  "geometry": {"coordinates":[36.18478,40.72024],"type":"Point"}
}