{
  "type": "Feature",
  "properties": {
    "gn:admin1_code":"55.0",
    "gn:asciiname":"Gokceagacoymagi",
    "gn:cc2":"TR",
    "gn:country_code":"TR",
    "gn:dem":806,
    "gn:feature_class":"P",
    "gn:feature_code":"PPL",
    "gn:name":"G\u00f6k\u00e7ea\u011fa\u00e7oyma\u011f\u0131",
    "gn:population":0,
    "gn:timezone":"Europe/Istanbul",
    "iso:country":"TR",
    "name:und_x_variant":[
        "Oyma\u011f\u0131k\u00f6k\u00e7ea\u011fa\u00e7",
        "Oyma\u011f\u0131g\u00f6k\u00e7ea\u011fa\u00e7",
        "G\u00f6k\u00e7ea\u011fa\u00e7oyma\u011f\u0131"
    ],
    "wof:name":"Gokceagacoymagi",
    "wof:placetype":"locality"
},
  "geometry": {"coordinates":[35.63333,41.46667],"type":"Point"}
}