{
  "type": "Feature",
  "properties": {
    "gn:admin1_code":"02",
    "gn:asciiname":"Yagizatli",
    "gn:country_code":"TR",
    "gn:dem":866,
    "gn:feature_class":"P",
    "gn:feature_code":"PPL",
    "gn:name":"Ya\u011f\u0131zatl\u0131",
    "gn:population":0,
    "gn:timezone":"Europe/Istanbul",
    "iso:country":"TR",
    "name:und_x_variant":[
        "Bistik\u00e2n",
        "Ya\u011f\u0131zatl\u0131"
    ],
    "wof:name":"Yagizatli",
    "wof:placetype":"locality"
},
  "geometry": {"coordinates":[38.40056,37.99237],"type":"Point"}
}