{
  "type": "Feature",
  "properties": {
    "gn:admin1_code":"66",
    "gn:asciiname":"Karakaya",
    "gn:country_code":"TR",
    "gn:dem":1062,
    "gn:feature_class":"P",
    "gn:feature_code":"PPL",
    "gn:name":"Karakaya",
    "gn:population":0,
    "gn:timezone":"Europe/Istanbul",
    "iso:country":"TR",
    "name:und_x_variant":[
        "Karakaya K\u00f6y\u00fc",
        "Karakaya"
    ],
    "wof:name":"Karakaya",
    "wof:placetype":"locality"
},
  "geometry": {"coordinates":[34.83914,39.57503],"type":"Point"}
}