{
  "type": "Feature",
  "properties": {
    "gn:admin1_code":"85",
    "gn:asciiname":"Karalar",
    "gn:country_code":"TR",
    "gn:dem":174,
    "gn:feature_class":"P",
    "gn:feature_code":"PPL",
    "gn:name":"Karalar",
    "gn:population":0,
    "gn:timezone":"Europe/Istanbul",
    "iso:country":"TR",
    "name:aze_x_preferred":[
        "Qaralar"
    ],
    "name:ceb_x_preferred":[
        "Qaralar"
    ],
    "name:ita_x_preferred":[
        "Qaralar"
    ],
    "name:kat_x_preferred":[
        "\u10e7\u10d0\u10e0\u10d0\u10da\u10d0\u10e0\u10d8"
    ],
    "name:swe_x_preferred":[
        "Qaralar"
    ],
    "name:tur_x_preferred":[
        "Karalar"
    ],
    "wof:name":"Karalar",
    "wof:placetype":"locality"
},
  "geometry": {"coordinates":[32.05928,41.44439000000001],"type":"Point"}
}