{
  "type": "Feature",
  "properties": {
    "gn:admin1_code":"17.0",
    "gn:asciiname":"Calioba Akcakil",
    "gn:country_code":"TR",
    "gn:dem":203,
    "gn:feature_class":"P",
    "gn:feature_code":"PPL",
    "gn:name":"\u00c7al\u0131oba Ak\u00e7ak\u0131l",
    "gn:population":0,
    "gn:timezone":"Europe/Istanbul",
    "iso:country":"TR",
    "name:tur_x_preferred":[
        "\u00c7al\u0131oba Ak\u00e7ak\u0131l"
    ],
    "name:und_x_variant":[
        "Ak\u00e7ak\u0131l"
    ],
    "wof:name":"Calioba Akcakil",
    "wof:placetype":"locality"
},
  "geometry": {"coordinates":[26.69875,39.77125],"type":"Point"}
}