{
  "type": "Feature",
  "properties": {
    "gn:country":"TR",
    "gn:fcode":"PPL",
    "gn:pop":0,
    "iso:country":"TR",
    "name:dut_x_preferred":[
        "\u00d6zvatan"
    ],
    "name:eng_x_preferred":[
        "\u00d6zvatan"
    ],
    "name:fre_x_preferred":[
        "\u00d6zvatan"
    ],
    "name:ger_x_preferred":[
        "\u00d6zvatan"
    ],
    "name:ita_x_preferred":[
        "Distretto di \u00d6zvatan"
    ],
    "name:may_x_preferred":[
        "\u00d6zvatan"
    ],
    "name:mrj_x_preferred":[
        "\u04e6\u0437\u0432\u0430\u0442\u0430\u043d"
    ],
    "name:nan_x_preferred":[
        "\u00d6zvatan"
    ],
    "name:pnb_x_preferred":[
        "\u0636\u0644\u0639 \u0627\u0648\u0632\u0648\u0627\u062a\u0627\u0646"
    ],
    "name:swa_x_preferred":[
        "\u00d6zvatan"
    ],
    "name:tur_x_preferred":[
        "\u00d6zvatan"
    ],
    "name:urd_x_preferred":[
        "\u0627\u0648\u0632\u0648\u0627\u062a\u0627\u0646"
    ],
    "name:vie_x_preferred":[
        "\u00d6zvatan"
    ],
    "qs:name":"\u00d6zvatan",
    "qs:name_adm0":"Turkey",
    "qs:name_adm1":"Kayseri",
    "qs:photos_9r":0,
    "qs:photos_sr":0,
    "qs:placetype":"Town",
    "qs:pop_sr":"0",
    "wd:wordcount":120,
    "wof:name":"\u00d6zvatan",
    "wof:placetype":"locality",
    "wof:population":0
},
  "geometry": {"coordinates":[35.46439,38.85902],"type":"Point"}
}