{
  "type": "Feature",
  "properties": {
    "gn:admin1_code":"60.0",
    "gn:asciiname":"Igdir",
    "gn:country_code":"TR",
    "gn:dem":1129,
    "gn:feature_class":"P",
    "gn:feature_code":"PPL",
    "gn:name":"\u0130\u011fdir",
    "gn:population":0,
    "gn:timezone":"Europe/Istanbul",
    "iso:country":"TR",
    "wof:name":"Igdir",
    "wof:placetype":"locality"
},
  "geometry": {"coordinates":[36.37252,40.06712],"type":"Point"}
}