{
  "type": "Feature",
  "properties": {
    "gn:admin1_code":"74",
    "gn:asciiname":"Yesilcevre",
    "gn:country_code":"TR",
    "gn:dem":857,
    "gn:feature_class":"P",
    "gn:feature_code":"PPL",
    "gn:name":"Ye\u015fil\u00e7evre",
    "gn:population":0,
    "gn:timezone":"Europe/Istanbul",
    "iso:country":"TR",
    "name:tur_x_preferred":[
        "Ye\u015fil\u00e7evre"
    ],
    "name:und_x_variant":[
        "Baykan"
    ],
    "wof:name":"Yesilcevre",
    "wof:placetype":"locality"
},
  "geometry": {"coordinates":[41.74089,38.14501],"type":"Point"}
}