{
  "type": "Feature",
  "properties": {
    "gn:admin1_code":"45",
    "gn:asciiname":"Yurtbasi",
    "gn:country_code":"TR",
    "gn:dem":424,
    "gn:feature_class":"P",
    "gn:feature_code":"PPL",
    "gn:name":"Yurtba\u015f\u0131",
    "gn:population":0,
    "gn:timezone":"Europe/Istanbul",
    "iso:country":"TR",
    "name:tur_x_preferred":[
        "Yurtba\u015f\u0131"
    ],
    "wof:name":"Yurtbasi",
    "wof:placetype":"locality"
},
  "geometry": {"coordinates":[28.81417,38.59056],"type":"Point"}
}