{
  "type": "Feature",
  "properties": {
    "gn:admin1_code":"76",
    "gn:asciiname":"Balpinari",
    "gn:country_code":"TR",
    "gn:dem":1450,
    "gn:feature_class":"P",
    "gn:feature_code":"PPL",
    "gn:name":"Balp\u0131nar\u0131",
    "gn:population":0,
    "gn:timezone":"Europe/Istanbul",
    "iso:country":"TR",
    "name:tur_x_preferred":[
        "Balp\u0131nar\u0131"
    ],
    "wof:name":"Balpinari",
    "wof:placetype":"locality"
},
  "geometry": {"coordinates":[38.738,38.24987],"type":"Point"}
}