{
  "type": "Feature",
  "properties": {
    "gn:admin1_code":"59.0",
    "gn:asciiname":"Orey",
    "gn:country_code":"TR",
    "gn:dem":128,
    "gn:feature_class":"P",
    "gn:feature_code":"PPL",
    "gn:name":"Orey",
    "gn:population":0,
    "gn:timezone":"Europe/Istanbul",
    "iso:country":"TR",
    "name:und_x_variant":[
        "\u00d6renk\u00f6y",
        "\u00d6reyk\u00f6y",
        "Orey"
    ],
    "wof:name":"Orey",
    "wof:placetype":"locality"
},
  "geometry": {"coordinates":[27.00648,41.15023],"type":"Point"}
}