{
  "type": "Feature",
  "properties": {
    "gn:admin1_code":"83.0",
    "gn:asciiname":"Bogazici",
    "gn:country_code":"TR",
    "gn:dem":526,
    "gn:feature_class":"P",
    "gn:feature_code":"PPL",
    "gn:name":"Bo\u011fazi\u00e7i",
    "gn:population":0,
    "gn:timezone":"Europe/Istanbul",
    "iso:country":"TR",
    "name:tur_x_preferred":[
        "Bo\u011fazi\u00e7i"
    ],
    "name:tur_x_variant":[
        "Kurna"
    ],
    "wof:name":"Bogazici",
    "wof:placetype":"locality"
},
  "geometry": {"coordinates":[36.56,36.94278],"type":"Point"}
}