{
  "type": "Feature",
  "properties": {
    "gn:admin1_code":"26",
    "gn:asciiname":"Omerkoy",
    "gn:country_code":"TR",
    "gn:dem":1246,
    "gn:feature_class":"P",
    "gn:feature_code":"PPL",
    "gn:name":"\u00d6merk\u00f6y",
    "gn:population":0,
    "gn:timezone":"Europe/Istanbul",
    "iso:country":"TR",
    "wof:name":"Omerkoy",
    "wof:placetype":"locality"
},
  "geometry": {"coordinates":[31.52597,39.85751],"type":"Point"}
}