{
  "type": "Feature",
  "properties": {
    "gn:admin1_code":"14",
    "gn:asciiname":"Kilavuzlar",
    "gn:country_code":"TR",
    "gn:dem":845,
    "gn:feature_class":"P",
    "gn:feature_code":"PPL",
    "gn:name":"K\u0131lavuzlar",
    "gn:population":0,
    "gn:timezone":"Europe/Istanbul",
    "iso:country":"TR",
    "wof:name":"Kilavuzlar",
    "wof:placetype":"locality"
},
  "geometry": {"coordinates":[30.59602000000001,40.46348],"type":"Point"}
}