{
  "type": "Feature",
  "properties": {
    "gn:admin1_code":"8.0",
    "gn:asciiname":"Ozmal",
    "gn:country_code":"TR",
    "gn:dem":525,
    "gn:feature_class":"P",
    "gn:feature_code":"PPL",
    "gn:name":"\u00d6zmal",
    "gn:population":0,
    "gn:timezone":"Europe/Istanbul",
    "iso:country":"TR",
    "name:tur_x_preferred":[
        "\u00d6zmal"
    ],
    "wof:name":"Ozmal",
    "wof:placetype":"locality"
},
  "geometry": {"coordinates":[41.60702,41.29369000000001],"type":"Point"}
}