{
  "type": "Feature",
  "properties": {
    "gn:admin1_code":"25.0",
    "gn:asciiname":"Salacor",
    "gn:country_code":"TR",
    "gn:dem":2355,
    "gn:feature_class":"P",
    "gn:feature_code":"PPL",
    "gn:name":"Sala\u00e7or",
    "gn:population":0,
    "gn:timezone":"Europe/Istanbul",
    "iso:country":"TR",
    "wof:name":"Salacor",
    "wof:placetype":"locality"
},
  "geometry": {"coordinates":[41.96667,40.95],"type":"Point"}
}