{
  "type": "Feature",
  "properties": {
    "gn:admin1_code":"8.0",
    "gn:asciiname":"Findikli",
    "gn:country_code":"TR",
    "gn:dem":532,
    "gn:feature_class":"P",
    "gn:feature_code":"PPL",
    "gn:name":"F\u0131nd\u0131kl\u0131",
    "gn:population":0,
    "gn:timezone":"Europe/Istanbul",
    "iso:country":"TR",
    "name:eng_x_preferred":[
        "Pehlivan"
    ],
    "name:rus_x_preferred":[
        "\u041f\u0435\u0445\u043b\u0438\u0432\u0430\u043d"
    ],
    "name:und_x_variant":[
        "Beglevan",
        "F\u0131nd\u0131kl\u0131"
    ],
    "wof:name":"Findikli",
    "wof:placetype":"locality"
},
  "geometry": {"coordinates":[41.60887,41.3966],"type":"Point"}
}