{
  "type": "Feature",
  "properties": {
    "gn:admin1_code":"53.0",
    "gn:asciiname":"Sulak",
    "gn:country_code":"TR",
    "gn:dem":268,
    "gn:feature_class":"P",
    "gn:feature_code":"PPL",
    "gn:name":"Sulak",
    "gn:population":0,
    "gn:timezone":"Europe/Istanbul",
    "iso:country":"TR",
    "name:tur_x_preferred":[
        "Sulak"
    ],
    "name:tur_x_variant":[
        "A\u015fa\u011f\u0131zu\u011fu"
    ],
    "wof:name":"Sulak",
    "wof:placetype":"locality"
},
  "geometry": {"coordinates":[41.19774,41.2162],"type":"Point"}
}