{
  "type": "Feature",
  "properties": {
    "gn:admin1_code":"53.0",
    "gn:asciiname":"Sulak",
    "gn:country_code":"TR",
    "gn:dem":268,
    "gn:feature_class":"P",
    "gn:feature_code":"PPL",
    "gn:name":"Sulak",
    "gn:population":0,
    "gn:timezone":"Europe/Istanbul",
    "iso:country":"TR",
    "name:ceb_x_preferred":[
        "Sulak"
    ],
    "name:deu_x_preferred":[
        "Sulak"
    ],
    "name:fas_x_preferred":[
        "\u0633\u0648\u0644\u06a9"
    ],
    "name:hye_x_preferred":[
        "\u054d\u0578\u0582\u056c\u0561\u056f"
    ],
    "name:rus_x_preferred":[
        "\u0421\u0443\u043b\u0430\u043a"
    ],
    "name:swe_x_preferred":[
        "Sulak"
    ],
    "name:tur_x_preferred":[
        "Sulak"
    ],
    "name:tur_x_variant":[
        "A\u015fa\u011f\u0131zu\u011fu"
    ],
    "name:ukr_x_preferred":[
        "\u0421\u0443\u043b\u0430\u043a"
    ],
    "wof:name":"Sulak",
    "wof:placetype":"locality"
},
  "geometry": {"coordinates":[41.19774,41.2162],"type":"Point"}
}