{
  "type": "Feature",
  "properties": {
    "gn:admin1_code":"07",
    "gn:asciiname":"Gebiz",
    "gn:country_code":"TR",
    "gn:dem":58,
    "gn:feature_class":"P",
    "gn:feature_code":"PPLA3",
    "gn:name":"Gebiz",
    "gn:population":0,
    "gn:timezone":"Europe/Istanbul",
    "iso:country":"TR",
    "name:und_x_variant":[
        "Macar",
        "Gebiz"
    ],
    "wof:name":"Gebiz",
    "wof:placetype":"locality"
},
  "geometry": {"coordinates":[30.93778,37.10417],"type":"Point"}
}