{
  "type": "Feature",
  "properties": {
    "gn:admin1_code":"32",
    "gn:asciiname":"Fakilar",
    "gn:country_code":"TR",
    "gn:dem":1066,
    "gn:feature_class":"P",
    "gn:feature_code":"PPL",
    "gn:name":"Fak\u0131lar",
    "gn:population":0,
    "gn:timezone":"Europe/Istanbul",
    "iso:country":"TR",
    "name:ceb_x_preferred":[
        "Fak\u0131lar"
    ],
    "name:msa_x_preferred":[
        "Fak\u0131lar"
    ],
    "name:urd_x_preferred":[
        "\u0641\u0627\u06a9\u06cc\u0644\u0627\u0631"
    ],
    "name:vie_x_preferred":[
        "Fak\u0131lar"
    ],
    "wof:name":"Fakilar",
    "wof:placetype":"locality"
},
  "geometry": {"coordinates":[34.65217,37.1811],"type":"Point"}
}