{
  "type": "Feature",
  "properties": {
    "gn:admin1_code":"71",
    "gn:asciiname":"Calti",
    "gn:country_code":"TR",
    "gn:dem":1062,
    "gn:feature_class":"P",
    "gn:feature_code":"PPL",
    "gn:name":"\u00c7alt\u0131",
    "gn:population":0,
    "gn:timezone":"Europe/Istanbul",
    "iso:country":"TR",
    "wof:name":"Calti",
    "wof:placetype":"locality"
},
  "geometry": {"coordinates":[32.55292,38.10431],"type":"Point"}
}