{
  "type": "Feature",
  "properties": {
    "gn:country":"TR",
    "gn:fcode":"PPL",
    "gn:pop":0,
    "iso:country":"TR",
    "name:unk_x_variant":[
        "\u00c7aml\u0131b\u00fck"
    ],
    "qs:name":"Ara\u00e7",
    "qs:name_adm0":"Turkey",
    "qs:name_adm1":"Kastamonu",
    "qs:photos":4,
    "qs:photos_1k":1,
    "qs:photos_9k":1,
    "qs:photos_9r":1,
    "qs:photos_all":4,
    "qs:photos_sr":1,
    "qs:placetype":"Town",
    "qs:pop_sr":"0",
    "wd:wordcount":173,
    "wof:name":"Ara\u00e7",
    "wof:placetype":"locality",
    "wof:population":0
},
  "geometry": {"coordinates":[33.36351,41.78728],"type":"Point"}
}