{
  "type": "Feature",
  "properties": {
    "gn:country":"TR",
    "gn:fcode":"PPL",
    "gn:population":0,
    "iso:country":"TR",
    "name:ara_x_preferred":[
        "\u0623\u0631\u0627\u0643"
    ],
    "name:arz_x_preferred":[
        "\u0627\u0631\u0627\u0643"
    ],
    "name:ast_x_preferred":[
        "Ara\u00e7"
    ],
    "name:cat_x_preferred":[
        "Ara\u00e7"
    ],
    "name:ceb_x_preferred":[
        "Ara\u00e7"
    ],
    "name:che_x_preferred":[
        "\u0410\u0440\u0430\u0447"
    ],
    "name:deu_x_preferred":[
        "Ara\u00e7"
    ],
    "name:eng_x_preferred":[
        "Ara\u00e7"
    ],
    "name:fas_x_preferred":[
        "\u0622\u0631\u0627\u0686"
    ],
    "name:fra_x_preferred":[
        "Ara\u00e7"
    ],
    "name:lit_x_preferred":[
        "Ara\u010das"
    ],
    "name:mrj_x_preferred":[
        "\u0410\u0440\u0430\u0447"
    ],
    "name:msa_x_preferred":[
        "Ara\u00e7"
    ],
    "name:nan_x_preferred":[
        "Ara\u00e7"
    ],
    "name:nld_x_preferred":[
        "Ara\u00e7"
    ],
    "name:nob_x_preferred":[
        "Ara\u00e7"
    ],
    "name:pnb_x_preferred":[
        "\u0636\u0644\u0639 \u0627\u0631\u0627\u0686"
    ],
    "name:por_x_preferred":[
        "Ara\u00e7"
    ],
    "name:rus_x_preferred":[
        "\u0410\u0440\u0430\u0447"
    ],
    "name:spa_x_preferred":[
        "Ara\u00e7"
    ],
    "name:swa_x_preferred":[
        "Ara\u00e7"
    ],
    "name:tat_x_preferred":[
        "\u0410\u0440\u0430\u0447"
    ],
    "name:tur_x_preferred":[
        "Ara\u00e7"
    ],
    "name:und_x_variant":[
        "\u00c7aml\u0131b\u00fck"
    ],
    "name:urd_x_preferred":[
        "\u0627\u0631\u0627\u0686"
    ],
    "name:vie_x_preferred":[
        "Ara\u00e7"
    ],
    "qs:name":"Ara\u00e7",
    "qs:name_adm0":"Turkey",
    "qs:name_adm1":"Kastamonu",
    "qs:photos":4,
    "qs:photos_1k":1,
    "qs:photos_9k":1,
    "qs:photos_9r":1,
    "qs:photos_all":4,
    "qs:photos_sr":1,
    "qs:placetype":"Town",
    "qs:pop_sr":"0",
    "wd:wordcount":173,
    "wof:name":"Ara\u00e7",
    "wof:placetype":"locality",
    "wof:population":0
},
  "geometry": {"coordinates":[33.36351,41.78728],"type":"Point"}
}