{
  "type": "Feature",
  "properties": {
    "gn:admin1_code":"25.0",
    "gn:asciiname":"Armutlu",
    "gn:country_code":"TR",
    "gn:dem":2009,
    "gn:feature_class":"P",
    "gn:feature_code":"PPL",
    "gn:name":"Armutlu",
    "gn:population":0,
    "gn:timezone":"Europe/Istanbul",
    "iso:country":"TR",
    "name:und_x_variant":[
        "Koblat"
    ],
    "wof:name":"Armutlu",
    "wof:placetype":"locality"
},
  "geometry": {"coordinates":[41.08447,40.46985],"type":"Point"}
}