{
  "type": "Feature",
  "properties": {
    "gn:admin1_code":"37.0",
    "gn:asciiname":"Yesilkoy",
    "gn:country_code":"TR",
    "gn:dem":869,
    "gn:feature_class":"P",
    "gn:feature_code":"PPL",
    "gn:name":"Ye\u015filk\u00f6y",
    "gn:population":0,
    "gn:timezone":"Europe/Istanbul",
    "iso:country":"TR",
    "name:und_x_variant":[
        "Ye\u015filk\u00f6y",
        "E\u011ferciler"
    ],
    "wof:name":"Yesilkoy",
    "wof:placetype":"locality"
},
  "geometry": {"coordinates":[33.28493,41.71516],"type":"Point"}
}