{
  "type": "Feature",
  "properties": {
    "gn:admin1_code":"80",
    "gn:asciiname":"Yenidemir",
    "gn:country_code":"TR",
    "gn:dem":1048,
    "gn:feature_class":"P",
    "gn:feature_code":"PPL",
    "gn:name":"Yenidemir",
    "gn:population":0,
    "gn:timezone":"Europe/Istanbul",
    "iso:country":"TR",
    "name:und_x_variant":[
        "Bunasra",
        "Bulisera",
        "Bunisra",
        "Yenidemir"
    ],
    "wof:name":"Yenidemir",
    "wof:placetype":"locality"
},
  "geometry": {"coordinates":[42.03257,37.46952],"type":"Point"}
}