{
  "type": "Feature",
  "properties": {
    "gn:admin1_code":"71",
    "gn:asciiname":"Dipdede",
    "gn:country_code":"TR",
    "gn:dem":1317,
    "gn:feature_class":"P",
    "gn:feature_code":"PPL",
    "gn:name":"Dipdede",
    "gn:population":0,
    "gn:timezone":"Europe/Istanbul",
    "iso:country":"TR",
    "wof:name":"Dipdede",
    "wof:placetype":"locality"
},
  "geometry": {"coordinates":[32.89509,39.1961],"type":"Point"}
}