{
  "type": "Feature",
  "properties": {
    "gn:admin1_code":"32.0",
    "gn:asciiname":"Topluca",
    "gn:country_code":"TR",
    "gn:dem":530,
    "gn:feature_class":"P",
    "gn:feature_code":"PPL",
    "gn:name":"Topluca",
    "gn:population":0,
    "gn:timezone":"Europe/Istanbul",
    "iso:country":"TR",
    "name:tur_x_preferred":[
        "Topluca"
    ],
    "wof:name":"Topluca",
    "wof:placetype":"locality"
},
  "geometry": {"coordinates":[33.47323,36.71214000000001],"type":"Point"}
}