{
  "type": "Feature",
  "properties": {
    "gn:admin1_code":"37.0",
    "gn:asciiname":"Halkabuk",
    "gn:country_code":"TR",
    "gn:dem":413,
    "gn:feature_class":"P",
    "gn:feature_code":"PPL",
    "gn:name":"Halkab\u00fck",
    "gn:population":0,
    "gn:timezone":"Europe/Istanbul",
    "iso:country":"TR",
    "wof:name":"Halkabuk",
    "wof:placetype":"locality"
},
  "geometry": {"coordinates":[34.52587,41.61196],"type":"Point"}
}