{
  "type": "Feature",
  "properties": {
    "gn:admin1_code":"44",
    "gn:asciiname":"Govuk",
    "gn:country_code":"TR",
    "gn:dem":750,
    "gn:feature_class":"P",
    "gn:feature_code":"PPL",
    "gn:name":"G\u00f6v\u00fck",
    "gn:population":0,
    "gn:timezone":"Europe/Istanbul",
    "iso:country":"TR",
    "name:und_x_variant":[
        "A\u015fa\u011f\u0131 Kovik",
        "G\u00f6v\u00fck",
        "A\u015fa\u011f\u0131 G\u00f6v\u00fck"
    ],
    "wof:name":"Govuk",
    "wof:placetype":"locality"
},
  "geometry": {"coordinates":[38.21934,38.58739],"type":"Point"}
}