{
  "type": "Feature",
  "properties": {
    "gn:admin1_code":"82.0",
    "gn:asciiname":"Akhasan",
    "gn:country_code":"TR",
    "gn:dem":1229,
    "gn:feature_class":"P",
    "gn:feature_code":"PPL",
    "gn:name":"Akhasan",
    "gn:population":0,
    "gn:timezone":"Europe/Istanbul",
    "iso:country":"TR",
    "wof:name":"Akhasan",
    "wof:placetype":"locality"
},
  "geometry": {"coordinates":[32.80538,40.77086],"type":"Point"}
}