{
  "type": "Feature",
  "properties": {
    "gn:admin1_code":"24",
    "gn:asciiname":"Hakbilir",
    "gn:country_code":"TR",
    "gn:dem":1475,
    "gn:feature_class":"P",
    "gn:feature_code":"PPL",
    "gn:name":"Hakbilir",
    "gn:population":0,
    "gn:timezone":"Europe/Istanbul",
    "iso:country":"TR",
    "name:und_x_variant":[
        "Hezerik"
    ],
    "wof:name":"Hakbilir",
    "wof:placetype":"locality"
},
  "geometry": {"coordinates":[38.90411,39.6879],"type":"Point"}
}