{
  "type": "Feature",
  "properties": {
    "gn:admin1_code":"37.0",
    "gn:asciiname":"Subasi",
    "gn:country_code":"TR",
    "gn:dem":753,
    "gn:feature_class":"P",
    "gn:feature_code":"PPL",
    "gn:name":"Suba\u015f\u0131",
    "gn:population":0,
    "gn:timezone":"Europe/Istanbul",
    "iso:country":"TR",
    "wof:name":"Subasi",
    "wof:placetype":"locality"
},
  "geometry": {"coordinates":[33.71184,41.45433],"type":"Point"}
}