{
  "type": "Feature",
  "properties": {
    "gn:admin1_code":"63.0",
    "gn:asciiname":"Guvenli",
    "gn:country_code":"TR",
    "gn:dem":694,
    "gn:feature_class":"P",
    "gn:feature_code":"PPL",
    "gn:name":"G\u00fcvenli",
    "gn:population":0,
    "gn:timezone":"Europe/Istanbul",
    "iso:country":"TR",
    "name:tur_x_preferred":[
        "G\u00fcvenli"
    ],
    "name:und_x_variant":[
        "Anzele"
    ],
    "wof:name":"Guvenli",
    "wof:placetype":"locality"
},
  "geometry": {"coordinates":[39.34026,37.18721],"type":"Point"}
}