{
  "type": "Feature",
  "properties": {
    "gn:admin1_code":"48",
    "gn:asciiname":"Gokcebel",
    "gn:cc2":"TR",
    "gn:country_code":"TR",
    "gn:dem":112,
    "gn:feature_class":"P",
    "gn:feature_code":"PPL",
    "gn:name":"G\u00f6k\u00e7ebel",
    "gn:population":0,
    "gn:timezone":"Europe/Istanbul",
    "iso:country":"TR",
    "name:und_x_variant":[
        "Dirmili",
        "G\u00f6k\u00e7ebel"
    ],
    "wof:name":"Gokcebel",
    "wof:placetype":"locality"
},
  "geometry": {"coordinates":[27.32083,37.10528],"type":"Point"}
}