{
  "type": "Feature",
  "properties": {
    "gn:admin1_code":"62",
    "gn:asciiname":"Dinar",
    "gn:country_code":"TR",
    "gn:dem":978,
    "gn:feature_class":"P",
    "gn:feature_code":"PPL",
    "gn:name":"Dinar",
    "gn:population":0,
    "gn:timezone":"Europe/Istanbul",
    "iso:country":"TR",
    "wof:name":"Dinar",
    "wof:placetype":"locality"
},
  "geometry": {"coordinates":[39.46667,39.03333],"type":"Point"}
}