{
  "type": "Feature",
  "properties": {
    "gn:admin1_code":"85.0",
    "gn:asciiname":"Esenlik",
    "gn:country_code":"TR",
    "gn:dem":176,
    "gn:feature_class":"P",
    "gn:feature_code":"PPL",
    "gn:name":"Esenlik",
    "gn:population":0,
    "gn:timezone":"Europe/Istanbul",
    "iso:country":"TR",
    "name:und_x_variant":[
        "Arapo\u011flu",
        "Esenlik"
    ],
    "wof:name":"Esenlik",
    "wof:placetype":"locality"
},
  "geometry": {"coordinates":[32.03447,41.37788],"type":"Point"}
}