{
  "type": "Feature",
  "properties": {
    "gn:admin1_code":"22.0",
    "gn:asciiname":"Degirmenci",
    "gn:country_code":"TR",
    "gn:dem":45,
    "gn:feature_class":"P",
    "gn:feature_code":"PPL",
    "gn:name":"De\u011firmenci",
    "gn:population":0,
    "gn:timezone":"Europe/Istanbul",
    "iso:country":"TR",
    "wof:name":"Degirmenci",
    "wof:placetype":"locality"
},
  "geometry": {"coordinates":[26.70099,41.31136],"type":"Point"}
}