{
  "type": "Feature",
  "properties": {
    "gn:admin1_code":"62",
    "gn:asciiname":"Caybagi",
    "gn:country_code":"TR",
    "gn:dem":869,
    "gn:feature_class":"P",
    "gn:feature_code":"PPLA3",
    "gn:name":"\u00c7ayba\u011f\u0131",
    "gn:population":0,
    "gn:timezone":"Europe/Istanbul",
    "iso:country":"TR",
    "name:tur_x_preferred":[
        "\u00c7ayba\u011f\u0131"
    ],
    "wof:name":"Caybagi",
    "wof:placetype":"locality"
},
  "geometry": {"coordinates":[39.61057,38.82855],"type":"Point"}
}