{
  "type": "Feature",
  "properties": {
    "gn:admin1_code":"13",
    "gn:asciiname":"Gunkiri",
    "gn:country_code":"TR",
    "gn:dem":1299,
    "gn:feature_class":"P",
    "gn:feature_code":"PPL",
    "gn:name":"G\u00fcnk\u0131r\u0131",
    "gn:population":0,
    "gn:timezone":"Europe/Istanbul",
    "iso:country":"TR",
    "name:tur_x_preferred":[
        "G\u00fcnk\u0131r\u0131"
    ],
    "wof:name":"Gunkiri",
    "wof:placetype":"locality"
},
  "geometry": {"coordinates":[41.96928,38.5892],"type":"Point"}
}