{
  "type": "Feature",
  "properties": {
    "gn:admin1_code":"48",
    "gn:asciiname":"Beyagaci",
    "gn:country_code":"TR",
    "gn:dem":988,
    "gn:feature_class":"P",
    "gn:feature_code":"PPL",
    "gn:name":"Beya\u011fac\u0131",
    "gn:population":0,
    "gn:timezone":"Europe/Istanbul",
    "iso:country":"TR",
    "name:tur_x_preferred":[
        "Beya\u011fac\u0131"
    ],
    "name:tur_x_variant":[
        "Armutlu"
    ],
    "wof:name":"Beyagaci",
    "wof:placetype":"locality"
},
  "geometry": {"coordinates":[29.49424,36.70874],"type":"Point"}
}