{
  "type": "Feature",
  "properties": {
    "gn:admin1_code":"83",
    "gn:asciiname":"Deliosman",
    "gn:country_code":"TR",
    "gn:dem":496,
    "gn:feature_class":"P",
    "gn:feature_code":"PPL",
    "gn:name":"Deliosman",
    "gn:population":0,
    "gn:timezone":"Europe/Istanbul",
    "iso:country":"TR",
    "name:tur_x_preferred":[
        "Deliosman"
    ],
    "name:und_x_variant":[
        "Ko\u00e7anl\u0131",
        "Ruslar"
    ],
    "wof:name":"Deliosman",
    "wof:placetype":"locality"
},
  "geometry": {"coordinates":[36.72624,36.83707],"type":"Point"}
}