{
  "type": "Feature",
  "properties": {
    "gn:admin1_code":"41.0",
    "gn:asciiname":"Cakmaklar",
    "gn:country_code":"TR",
    "gn:dem":289,
    "gn:feature_class":"P",
    "gn:feature_code":"PPL",
    "gn:name":"\u00c7akmaklar",
    "gn:population":0,
    "gn:timezone":"Europe/Istanbul",
    "iso:country":"TR",
    "name:tur_x_preferred":[
        "\u00c7akmaklar"
    ],
    "wof:name":"Cakmaklar",
    "wof:placetype":"locality"
},
  "geometry": {"coordinates":[29.89042,40.97762],"type":"Point"}
}