{
  "type": "Feature",
  "properties": {
    "gn:admin1_code":"81",
    "gn:asciiname":"Kayapinar",
    "gn:country_code":"TR",
    "gn:dem":1472,
    "gn:feature_class":"P",
    "gn:feature_code":"PPL",
    "gn:name":"Kayap\u0131nar",
    "gn:population":0,
    "gn:timezone":"Europe/Istanbul",
    "iso:country":"TR",
    "wof:name":"Kayapinar",
    "wof:placetype":"locality"
},
  "geometry": {"coordinates":[36.26556,38.32833],"type":"Point"}
}