{
  "type": "Feature",
  "properties": {
    "gn:admin1_code":"16.0",
    "gn:asciiname":"Akcapinar",
    "gn:country_code":"TR",
    "gn:dem":88,
    "gn:feature_class":"P",
    "gn:feature_code":"PPL",
    "gn:name":"Ak\u00e7ap\u0131nar",
    "gn:population":0,
    "gn:timezone":"Europe/Istanbul",
    "iso:country":"TR",
    "name:und_x_variant":[
        "Ak\u00e7ap\u0131nar K\u00f6y\u00fc",
        "Ak\u00e7ap\u0131nar"
    ],
    "wof:name":"Akcapinar",
    "wof:placetype":"locality"
},
  "geometry": {"coordinates":[28.65498,40.11265],"type":"Point"}
}