{
  "type": "Feature",
  "properties": {
    "gn:admin1_code":"72.0",
    "gn:asciiname":"Karagol",
    "gn:country_code":"TR",
    "gn:dem":909,
    "gn:feature_class":"P",
    "gn:feature_code":"PPL",
    "gn:name":"Karag\u00f6l",
    "gn:population":0,
    "gn:timezone":"Europe/Istanbul",
    "iso:country":"TR",
    "name:deu_x_preferred":[
        "Deyrkube"
    ],
    "name:msa_x_preferred":[
        "Karag\u00f6l"
    ],
    "name:und_x_variant":[
        "Dirkup"
    ],
    "wof:name":"Karagol",
    "wof:placetype":"locality"
},
  "geometry": {"coordinates":[41.695,37.48972],"type":"Point"}
}