{
  "type": "Feature",
  "properties": {
    "gn:country":"TR",
    "gn:fcode":"PPLA2",
    "gn:population":2403,
    "iso:country":"TR",
    "name:cat_x_preferred":[
        "K\u0131z\u0131l\u00f6ren"
    ],
    "name:ceb_x_preferred":[
        "K\u0131z\u0131l\u00f6ren"
    ],
    "name:deu_x_preferred":[
        "K\u0131z\u0131l\u00f6ren"
    ],
    "name:diq_x_preferred":[
        "K\u0131z\u0131l\u00f6ren"
    ],
    "name:eng_x_preferred":[
        "K\u0131z\u0131l\u00f6ren"
    ],
    "name:fra_x_preferred":[
        "K\u0131z\u0131l\u00f6ren"
    ],
    "name:ita_x_preferred":[
        "Distretto di K\u0131z\u0131l\u00f6ren"
    ],
    "name:mrj_x_preferred":[
        "\u041a\u044b\u0437\u044b\u043b\u04e7\u0440\u0435\u043d"
    ],
    "name:msa_x_preferred":[
        "K\u0131z\u0131l\u00f6ren"
    ],
    "name:nan_x_preferred":[
        "K\u0131z\u0131l\u00f6ren"
    ],
    "name:nld_x_preferred":[
        "K\u0131z\u0131l\u00f6ren"
    ],
    "name:nob_x_preferred":[
        "K\u0131z\u0131l\u00f6ren"
    ],
    "name:pnb_x_preferred":[
        "\u0636\u0644\u0639 \u06a9\u06cc\u0632\u06cc\u0644\u0648\u0631\u0646"
    ],
    "name:ron_x_preferred":[
        "K\u0131z\u0131l\u00f6ren"
    ],
    "name:swa_x_preferred":[
        "K\u0131z\u0131l\u00f6ren"
    ],
    "name:tur_x_preferred":[
        "K\u0131z\u0131l\u00f6ren"
    ],
    "name:und_x_variant":[
        "K\u0131z\u0131lviran"
    ],
    "name:urd_x_preferred":[
        "\u06a9\u06cc\u0632\u06cc\u0644\u0648\u0631\u06cc\u0646"
    ],
    "name:vie_x_preferred":[
        "K\u0131z\u0131l\u00f6ren"
    ],
    "qs:name":"K\u0131z\u0131l\u00f6ren",
    "qs:name_adm0":"Turkey",
    "qs:name_adm1":"Afyonkarahisar",
    "qs:photos_9k":1,
    "qs:photos_9r":1,
    "qs:photos_all":1,
    "qs:photos_sr":0,
    "qs:placetype":"Town",
    "qs:pop_sr":"4",
    "wd:wordcount":132,
    "wof:name":"K\u0131z\u0131l\u00f6ren",
    "wof:placetype":"locality",
    "wof:population":2403
},
  "geometry": {"coordinates":[30.15167,38.25806],"type":"Point"}
}