{
  "type": "Feature",
  "properties": {
    "gn:admin1_code":"12",
    "gn:asciiname":"Senkoy",
    "gn:country_code":"TR",
    "gn:dem":1622,
    "gn:feature_class":"P",
    "gn:feature_code":"PPL",
    "gn:name":"\u015eenk\u00f6y",
    "gn:population":0,
    "gn:timezone":"Europe/Istanbul",
    "iso:country":"TR",
    "name:tur_x_preferred":[
        "\u015eenk\u00f6y"
    ],
    "name:und_x_variant":[
        "\u015een K\u00f6y",
        "\u015een"
    ],
    "wof:name":"Senkoy",
    "wof:placetype":"locality"
},
  "geometry": {"coordinates":[40.53319000000001,39.41135],"type":"Point"}
}