{
  "type": "Feature",
  "properties": {
    "gn:admin1_code":"57.0",
    "gn:asciiname":"Gokdogan",
    "gn:country_code":"TR",
    "gn:dem":182,
    "gn:feature_class":"P",
    "gn:feature_code":"PPL",
    "gn:name":"G\u00f6kdo\u011fan",
    "gn:population":0,
    "gn:timezone":"Europe/Istanbul",
    "iso:country":"TR",
    "name:tur_x_preferred":[
        "G\u00f6kdo\u011fan"
    ],
    "wof:name":"Gokdogan",
    "wof:placetype":"locality"
},
  "geometry": {"coordinates":[35.12869,41.38647],"type":"Point"}
}