{
  "type": "Feature",
  "properties": {
    "gn:admin1_code":"93.0",
    "gn:asciiname":"Yaylatepe",
    "gn:country_code":"TR",
    "gn:dem":900,
    "gn:feature_class":"P",
    "gn:feature_code":"PPL",
    "gn:name":"Yaylatepe",
    "gn:population":0,
    "gn:timezone":"Europe/Istanbul",
    "iso:country":"TR",
    "name:und_x_variant":[
        "Homrus",
        "H\u00fcmr\u00fcs",
        "H\u00fcrm\u00fcs",
        "Yaylatepe"
    ],
    "wof:name":"Yaylatepe",
    "wof:placetype":"locality"
},
  "geometry": {"coordinates":[31.68596,40.98333],"type":"Point"}
}