{
  "type": "Feature",
  "properties": {
    "gn:admin1_code":"40.0",
    "gn:asciiname":"Karabogaz",
    "gn:country_code":"TR",
    "gn:dem":891,
    "gn:feature_class":"P",
    "gn:feature_code":"PPL",
    "gn:name":"Karabo\u011faz",
    "gn:population":0,
    "gn:timezone":"Europe/Istanbul",
    "iso:country":"TR",
    "wof:name":"Karabogaz",
    "wof:placetype":"locality"
},
  "geometry": {"coordinates":[34.14736,38.95375],"type":"Point"}
}