{
  "type": "Feature",
  "properties": {
    "gn:admin1_code":"61.0",
    "gn:asciiname":"Sogukpinar",
    "gn:country_code":"TR",
    "gn:dem":63,
    "gn:feature_class":"P",
    "gn:feature_code":"PPL",
    "gn:name":"So\u011fukp\u0131nar",
    "gn:population":0,
    "gn:timezone":"Europe/Istanbul",
    "iso:country":"TR",
    "name:und_x_variant":[
        "So\u011fukp\u0131nar",
        "Sargona"
    ],
    "wof:name":"Sogukpinar",
    "wof:placetype":"locality"
},
  "geometry": {"coordinates":[40.23363,40.92605],"type":"Point"}
}