{
  "type": "Feature",
  "properties": {
    "gn:admin1_code":"74.0",
    "gn:asciiname":"Ataf",
    "gn:country_code":"TR",
    "gn:dem":1678,
    "gn:feature_class":"P",
    "gn:feature_code":"PPL",
    "gn:name":"Ataf",
    "gn:population":0,
    "gn:timezone":"Europe/Istanbul",
    "iso:country":"TR",
    "wof:name":"Ataf",
    "wof:placetype":"locality"
},
  "geometry": {"coordinates":[42.69306,37.94389],"type":"Point"}
}