{
  "type": "Feature",
  "properties": {
    "gn:admin1_code":"24",
    "gn:asciiname":"Balibey",
    "gn:country_code":"TR",
    "gn:dem":1148,
    "gn:feature_class":"P",
    "gn:feature_code":"PPL",
    "gn:name":"Bal\u0131bey",
    "gn:population":0,
    "gn:timezone":"Europe/Istanbul",
    "iso:country":"TR",
    "name:und_x_variant":[
        "Bal\u0131beyi",
        "Balbey",
        "Bal\u0131bey"
    ],
    "wof:name":"Balibey",
    "wof:placetype":"locality"
},
  "geometry": {"coordinates":[39.56874000000001,39.69626],"type":"Point"}
}