{
  "type": "Feature",
  "properties": {
    "gn:admin1_code":"78",
    "gn:asciiname":"Dokuzyol",
    "gn:country_code":"TR",
    "gn:dem":1129,
    "gn:feature_class":"P",
    "gn:feature_code":"PPL",
    "gn:name":"Dokuzyol",
    "gn:population":0,
    "gn:timezone":"Europe/Istanbul",
    "iso:country":"TR",
    "name:und_x_variant":[
        "Orzala",
        "Dokuzyol"
    ],
    "wof:name":"Dokuzyol",
    "wof:placetype":"locality"
},
  "geometry": {"coordinates":[33.6213,37.30691],"type":"Point"}
}