{
  "type": "Feature",
  "properties": {
    "gn:admin1_code":"24",
    "gn:asciiname":"Kerer",
    "gn:country_code":"TR",
    "gn:dem":1419,
    "gn:feature_class":"P",
    "gn:feature_code":"PPL",
    "gn:name":"Kerer",
    "gn:population":0,
    "gn:timezone":"Europe/Istanbul",
    "iso:country":"TR",
    "name:tur_x_preferred":[
        "Kerer"
    ],
    "wof:name":"Kerer",
    "wof:placetype":"locality"
},
  "geometry": {"coordinates":[39.0533,39.75004000000001],"type":"Point"}
}