{
  "type": "Feature",
  "properties": {
    "gn:admin1_code":"26",
    "gn:asciiname":"Ayvali",
    "gn:country_code":"TR",
    "gn:dem":1028,
    "gn:feature_class":"P",
    "gn:feature_code":"PPL",
    "gn:name":"Ayval\u0131",
    "gn:population":0,
    "gn:timezone":"Europe/Istanbul",
    "iso:country":"TR",
    "wof:name":"Ayvali",
    "wof:placetype":"locality"
},
  "geometry": {"coordinates":[30.62271,39.47679],"type":"Point"}
}