{
  "type": "Feature",
  "properties": {
    "gn:admin1_code":"60.0",
    "gn:admin2_code":"7911035.0",
    "gn:asciiname":"Yesilhisar",
    "gn:country_code":"TR",
    "gn:dem":416,
    "gn:feature_class":"P",
    "gn:feature_code":"PPL",
    "gn:name":"Ye\u015filhisar",
    "gn:population":0,
    "gn:timezone":"Europe/Istanbul",
    "iso:country":"TR",
    "name:tur_x_preferred":[
        "Ye\u015filhisar"
    ],
    "name:und_x_variant":[
        "Aptalkolu",
        "Abdalkolu"
    ],
    "wof:name":"Yesilhisar",
    "wof:placetype":"locality"
},
  "geometry": {"coordinates":[36.88374,40.62786],"type":"Point"}
}