{
  "type": "Feature",
  "properties": {
    "gn:admin1_code":"63.0",
    "gn:asciiname":"Durre",
    "gn:country_code":"TR",
    "gn:dem":509,
    "gn:feature_class":"P",
    "gn:feature_code":"PPL",
    "gn:name":"Durre",
    "gn:population":0,
    "gn:timezone":"Europe/Istanbul",
    "iso:country":"TR",
    "wof:name":"Durre",
    "wof:placetype":"locality"
},
  "geometry": {"coordinates":[38.38219,36.99718],"type":"Point"}
}