{
  "type": "Feature",
  "properties": {
    "gn:admin1_code":"25.0",
    "gn:asciiname":"Yarbasi",
    "gn:country_code":"TR",
    "gn:dem":1899,
    "gn:feature_class":"P",
    "gn:feature_code":"PPL",
    "gn:name":"Yarba\u015f\u0131",
    "gn:population":0,
    "gn:timezone":"Europe/Istanbul",
    "iso:country":"TR",
    "name:und_x_variant":[
        "Yarba\u015f\u0131",
        "Sananes"
    ],
    "wof:name":"Yarbasi",
    "wof:placetype":"locality"
},
  "geometry": {"coordinates":[41.74415,40.42795],"type":"Point"}
}