{
  "type": "Feature",
  "properties": {
    "gn:admin1_code":"66",
    "gn:asciiname":"Poyrazli",
    "gn:country_code":"TR",
    "gn:dem":1164,
    "gn:feature_class":"P",
    "gn:feature_code":"PPL",
    "gn:name":"Poyrazl\u0131",
    "gn:population":0,
    "gn:timezone":"Europe/Istanbul",
    "iso:country":"TR",
    "wof:name":"Poyrazli",
    "wof:placetype":"locality"
},
  "geometry": {"coordinates":[35.11989000000001,39.38316],"type":"Point"}
}