{
  "type": "Feature",
  "properties": {
    "gn:admin1_code":"73",
    "gn:asciiname":"Bekcili",
    "gn:country_code":"TR",
    "gn:dem":1598,
    "gn:feature_class":"P",
    "gn:feature_code":"PPL",
    "gn:name":"Bek\u00e7ili",
    "gn:population":0,
    "gn:timezone":"Europe/Istanbul",
    "iso:country":"TR",
    "wof:name":"Bekcili",
    "wof:placetype":"locality"
},
  "geometry": {"coordinates":[34.93542,37.76667],"type":"Point"}
}