{
  "type": "Feature",
  "properties": {
    "gn:admin1_code":"69.0",
    "gn:asciiname":"Sadikkoy",
    "gn:country_code":"TR",
    "gn:dem":1408,
    "gn:feature_class":"P",
    "gn:feature_code":"PPL",
    "gn:name":"Sad\u0131kk\u00f6y",
    "gn:population":0,
    "gn:timezone":"Europe/Istanbul",
    "iso:country":"TR",
    "name:und_x_variant":[
        "Sad\u0131k",
        "Sad\u0131kk\u00f6y"
    ],
    "wof:name":"Sadikkoy",
    "wof:placetype":"locality"
},
  "geometry": {"coordinates":[38.94307,40.13504],"type":"Point"}
}