{
  "type": "Feature",
  "properties": {
    "gn:admin1_code":"83",
    "gn:asciiname":"Karapolat",
    "gn:country_code":"TR",
    "gn:dem":461,
    "gn:feature_class":"P",
    "gn:feature_code":"PPL",
    "gn:name":"Karapolat",
    "gn:population":0,
    "gn:timezone":"Europe/Istanbul",
    "iso:country":"TR",
    "wof:name":"Karapolat",
    "wof:placetype":"locality"
},
  "geometry": {"coordinates":[36.70781,37.00579000000001],"type":"Point"}
}