{
  "type": "Feature",
  "properties": {
    "gn:country":"TR",
    "iso:country":"TR",
    "name:ara_x_preferred":[
        "\u0623\u063a\u0641\u0627"
    ],
    "name:eng_x_preferred":[
        "A\u011fva"
    ],
    "name:tur_x_preferred":[
        "A\u011fva"
    ],
    "name:vie_x_preferred":[
        "A\u011fva"
    ],
    "qs:name":"A\u011fva",
    "qs:name_adm0":"Turkey",
    "qs:name_adm1":"\u0130stanbul",
    "qs:photos":857,
    "qs:photos_1k":174,
    "qs:photos_9k":4,
    "qs:photos_9r":6,
    "qs:photos_all":857,
    "qs:photos_sr":10,
    "qs:placetype":"Town",
    "qs:pop_sr":"0",
    "wd:wordcount":311,
    "wof:name":"A\u011fva",
    "wof:placetype":"locality"
},
  "geometry": {"coordinates":[29.846999,41.139041],"type":"Point"}
}