{
  "type": "Feature",
  "properties": {
    "gn:admin1_code":"09",
    "gn:asciiname":"Osan Mahallesi",
    "gn:country_code":"TR",
    "gn:dem":66,
    "gn:feature_class":"P",
    "gn:feature_code":"PPL",
    "gn:name":"Osan Mahallesi",
    "gn:population":0,
    "gn:timezone":"Europe/Istanbul",
    "iso:country":"TR",
    "name:tur_x_preferred":[
        "Osan Mahallesi"
    ],
    "wof:name":"Osan Mahallesi",
    "wof:placetype":"locality"
},
  "geometry": {"coordinates":[28.02346,37.63635],"type":"Point"}
}