{
  "type": "Feature",
  "properties": {
    "gn:admin1_code":"35",
    "gn:asciiname":"Yagcilar",
    "gn:country_code":"TR",
    "gn:dem":210,
    "gn:feature_class":"P",
    "gn:feature_code":"PPL",
    "gn:name":"Ya\u011fc\u0131lar",
    "gn:population":0,
    "gn:timezone":"Europe/Istanbul",
    "iso:country":"TR",
    "wof:name":"Yagcilar",
    "wof:placetype":"locality"
},
  "geometry": {"coordinates":[26.68222,38.25917000000001],"type":"Point"}
}