{
  "type": "Feature",
  "properties": {
    "gn:admin1_code":"24",
    "gn:asciiname":"Yalinkas",
    "gn:country_code":"TR",
    "gn:dem":1487,
    "gn:feature_class":"P",
    "gn:feature_code":"PPL",
    "gn:name":"Yal\u0131nka\u015f",
    "gn:population":0,
    "gn:timezone":"Europe/Istanbul",
    "iso:country":"TR",
    "name:tur_x_preferred":[
        "Yal\u0131nka\u015f"
    ],
    "wof:name":"Yalinkas",
    "wof:placetype":"locality"
},
  "geometry": {"coordinates":[40.36727,39.71214000000001],"type":"Point"}
}