{
  "type": "Feature",
  "properties": {
    "gn:admin1_code":"70",
    "gn:asciiname":"Akcadam",
    "gn:country_code":"TR",
    "gn:dem":1836,
    "gn:feature_class":"P",
    "gn:feature_code":"PPL",
    "gn:name":"Ak\u00e7adam",
    "gn:population":0,
    "gn:timezone":"Europe/Istanbul",
    "iso:country":"TR",
    "name:und_x_variant":[
        "Avyan",
        "Ak\u00e7adam",
        "Avupan"
    ],
    "wof:name":"Akcadam",
    "wof:placetype":"locality"
},
  "geometry": {"coordinates":[44.57566,37.73848],"type":"Point"}
}