{
  "type": "Feature",
  "properties": {
    "gn:country":"TR",
    "gn:fcode":"PPL",
    "gn:population":1950,
    "iso:country":"TR",
    "name:ceb_x_preferred":[
        "\u015eenyurt"
    ],
    "name:deu_x_preferred":[
        "\u015eenyurt"
    ],
    "name:eng_x_preferred":[
        "\u015eenyurt"
    ],
    "name:kur_x_preferred":[
        "Dirb\u00eas\u00ee"
    ],
    "name:nld_x_preferred":[
        "\u015eenyurt"
    ],
    "name:pol_x_preferred":[
        "\u015eenyurt"
    ],
    "name:rus_x_preferred":[
        "Shen\u201dyurt"
    ],
    "name:tur_x_preferred":[
        "\u015eenyurt"
    ],
    "name:und_x_variant":[
        "Derbesie"
    ],
    "name:vie_x_preferred":[
        "\u015eenyurt"
    ],
    "qs:name":"\u015eenyurt",
    "qs:photos_9r":0,
    "qs:photos_sr":0,
    "qs:pop_sr":"5",
    "wd:wordcount":177,
    "wof:name":"\u015eenyurt",
    "wof:placetype":"locality",
    "wof:population":1950
},
  "geometry": {"coordinates":[40.64408,37.07886],"type":"Point"}
}