{
  "type": "Feature",
  "properties": {
    "gn:admin1_code":"65",
    "gn:asciiname":"Avcibasi",
    "gn:cc2":"TR",
    "gn:country_code":"TR",
    "gn:dem":2314,
    "gn:feature_class":"P",
    "gn:feature_code":"PPL",
    "gn:name":"Avc\u0131ba\u015f\u0131",
    "gn:population":0,
    "gn:timezone":"Europe/Istanbul",
    "iso:country":"TR",
    "name:und_x_variant":[
        "Seyiran",
        "Segiran",
        "Se\u011firan",
        "Avc\u0131ba\u015f\u0131"
    ],
    "wof:name":"Avcibasi",
    "wof:placetype":"locality"
},
  "geometry": {"coordinates":[43.86667,39.06667],"type":"Point"}
}