{
  "type": "Feature",
  "properties": {
    "gn:admin1_code":"63.0",
    "gn:asciiname":"Hasami",
    "gn:country_code":"TR",
    "gn:dem":486,
    "gn:feature_class":"P",
    "gn:feature_code":"PPL",
    "gn:name":"Hasami",
    "gn:population":0,
    "gn:timezone":"Europe/Istanbul",
    "iso:country":"TR",
    "name:und_x_variant":[
        "Khasami",
        "Hasami"
    ],
    "wof:name":"Hasami",
    "wof:placetype":"locality"
},
  "geometry": {"coordinates":[38.40498,36.92225],"type":"Point"}
}