{
  "type": "Feature",
  "properties": {
    "gn:admin1_code":"65",
    "gn:asciiname":"Dorutay",
    "gn:country_code":"TR",
    "gn:dem":2034,
    "gn:feature_class":"P",
    "gn:feature_code":"PPLA3",
    "gn:name":"Dorutay",
    "gn:population":0,
    "gn:timezone":"Europe/Istanbul",
    "iso:country":"TR",
    "name:und_x_variant":[
        "Ta\u015frumi",
        "Dorutay"
    ],
    "wof:name":"Dorutay",
    "wof:placetype":"locality"
},
  "geometry": {"coordinates":[44.06726,38.79939],"type":"Point"}
}