{
  "type": "Feature",
  "properties": {
    "gn:admin1_code":"66",
    "gn:asciiname":"Arpalik",
    "gn:country_code":"TR",
    "gn:dem":1123,
    "gn:feature_class":"P",
    "gn:feature_code":"PPL",
    "gn:name":"Arpal\u0131k",
    "gn:population":0,
    "gn:timezone":"Europe/Istanbul",
    "iso:country":"TR",
    "name:cat_x_preferred":[
        "Arpalik"
    ],
    "name:slv_x_preferred":[
        "Arpalik"
    ],
    "name:tur_x_preferred":[
        "Arpal\u0131k"
    ],
    "wof:name":"Arpalik",
    "wof:placetype":"locality"
},
  "geometry": {"coordinates":[35.44031,39.51273],"type":"Point"}
}