{
  "type": "Feature",
  "properties": {
    "gn:admin1_code":"45.0",
    "gn:asciiname":"Kiranciftligi",
    "gn:country_code":"TR",
    "gn:dem":181,
    "gn:feature_class":"P",
    "gn:feature_code":"PPL",
    "gn:name":"K\u0131ran\u00e7iftli\u011fi",
    "gn:population":0,
    "gn:timezone":"Europe/Istanbul",
    "iso:country":"TR",
    "name:tur_x_preferred":[
        "K\u0131ran\u00e7iftli\u011fi"
    ],
    "wof:name":"Kiranciftligi",
    "wof:placetype":"locality"
},
  "geometry": {"coordinates":[27.39255,38.74393],"type":"Point"}
}