{
  "type": "Feature",
  "properties": {
    "gn:admin1_code":"23",
    "gn:asciiname":"Okcular",
    "gn:country_code":"TR",
    "gn:dem":1580,
    "gn:feature_class":"P",
    "gn:feature_code":"PPL",
    "gn:name":"Ok\u00e7ular",
    "gn:population":0,
    "gn:timezone":"Europe/Istanbul",
    "iso:country":"TR",
    "name:und_x_variant":[
        "Okc\u0131yan",
        "Ok\u00e7ular"
    ],
    "wof:name":"Okcular",
    "wof:placetype":"locality"
},
  "geometry": {"coordinates":[40.11519000000001,38.85738],"type":"Point"}
}