{
  "type": "Feature",
  "properties": {
    "gn:admin1_code":"21.0",
    "gn:asciiname":"Yukari Darli",
    "gn:country_code":"TR",
    "gn:dem":690,
    "gn:feature_class":"P",
    "gn:feature_code":"PPL",
    "gn:name":"Yukar\u0131 Darl\u0131",
    "gn:population":0,
    "gn:timezone":"Europe/Istanbul",
    "iso:country":"TR",
    "wof:name":"Yukari Darli",
    "wof:placetype":"locality"
},
  "geometry": {"coordinates":[40.47846,38.00751],"type":"Point"}
}