{
  "type": "Feature",
  "properties": {
    "gn:admin1_code":"43",
    "gn:asciiname":"Bayramsah",
    "gn:country_code":"TR",
    "gn:dem":1301,
    "gn:feature_class":"P",
    "gn:feature_code":"PPL",
    "gn:name":"Bayram\u015fah",
    "gn:population":0,
    "gn:timezone":"Europe/Istanbul",
    "iso:country":"TR",
    "wof:name":"Bayramsah",
    "wof:placetype":"locality"
},
  "geometry": {"coordinates":[29.71972,39.36639],"type":"Point"}
}