{
  "type": "Feature",
  "properties": {
    "iso:country":"TR",
    "name:eng_x_preferred":[
        "Kucukbakkalkoy"
    ],
    "name:tur_x_preferred":[
        "K\u00fc\u00e7\u00fckbakkalk\u00f6y"
    ],
    "wof:name":"Kucukbakkalkoy",
    "wof:placetype":"neighbourhood"
},
  "geometry": {"coordinates":[29.11682131996313,40.98182620376132],"type":"Point"}
}