{
  "type": "Feature",
  "properties": {
    "gn:admin1_code":"21",
    "gn:asciiname":"Akyaprak",
    "gn:country_code":"TR",
    "gn:dem":1028,
    "gn:feature_class":"P",
    "gn:feature_code":"PPL",
    "gn:name":"Akyaprak",
    "gn:population":0,
    "gn:timezone":"Europe/Istanbul",
    "iso:country":"TR",
    "name:und_x_variant":[
        "Cimar",
        "Akyaprak",
        "Cumar"
    ],
    "wof:name":"Akyaprak",
    "wof:placetype":"locality"
},
  "geometry": {"coordinates":[41.14779,38.37447],"type":"Point"}
}