{
  "type": "Feature",
  "properties": {
    "gn:admin1_code":"71",
    "gn:asciiname":"Bicer",
    "gn:country_code":"TR",
    "gn:dem":1056,
    "gn:feature_class":"P",
    "gn:feature_code":"PPL",
    "gn:name":"Bi\u00e7er",
    "gn:population":0,
    "gn:timezone":"Europe/Istanbul",
    "iso:country":"TR",
    "wof:name":"Bicer",
    "wof:placetype":"locality"
},
  "geometry": {"coordinates":[32.52668,38.23359],"type":"Point"}
}