{
  "type": "Feature",
  "properties": {
    "gn:admin1_code":"31",
    "gn:asciiname":"Senkoy",
    "gn:country_code":"TR",
    "gn:dem":724,
    "gn:feature_class":"P",
    "gn:feature_code":"PPLA3",
    "gn:name":"\u015eenk\u00f6y",
    "gn:population":0,
    "gn:timezone":"Europe/Istanbul",
    "iso:country":"TR",
    "name:ceb_x_preferred":[
        "\u015eenk\u00f6y"
    ],
    "name:und_x_variant":[
        "\u015eehk\u00f6y",
        "\u015eeyhk\u00f6y",
        "\u015eeyhler",
        "Seyhk\u00f6y\u00fc",
        "\u015eenk\u00f6y"
    ],
    "wof:name":"Senkoy",
    "wof:placetype":"locality"
},
  "geometry": {"coordinates":[36.14366,36.04841],"type":"Point"}
}