{
  "type": "Feature",
  "properties": {
    "gn:admin1_code":"76.0",
    "gn:asciiname":"Kilimli",
    "gn:country_code":"TR",
    "gn:dem":1076,
    "gn:feature_class":"P",
    "gn:feature_code":"PPL",
    "gn:name":"Kilimli",
    "gn:population":0,
    "gn:timezone":"Europe/Istanbul",
    "iso:country":"TR",
    "name:tur_x_preferred":[
        "Kilimli"
    ],
    "wof:name":"Kilimli",
    "wof:placetype":"locality"
},
  "geometry": {"coordinates":[41.36912,38.28817],"type":"Point"}
}