{
  "type": "Feature",
  "properties": {
    "gn:admin1_code":"76.0",
    "gn:asciiname":"Kilimli",
    "gn:country_code":"TR",
    "gn:dem":1076,
    "gn:feature_class":"P",
    "gn:feature_code":"PPL",
    "gn:name":"Kilimli",
    "gn:population":0,
    "gn:timezone":"Europe/Istanbul",
    "iso:country":"TR",
    "name:azb_x_preferred":[
        "\u06a9\u06cc\u0644\u06cc\u0645\u0644\u06cc"
    ],
    "name:ceb_x_preferred":[
        "Kilimli"
    ],
    "name:deu_x_preferred":[
        "Kilimli"
    ],
    "name:fas_x_preferred":[
        "\u06a9\u06cc\u0644\u06cc\u0645\u0644\u06cc"
    ],
    "name:min_x_preferred":[
        "Kilimli"
    ],
    "name:nno_x_preferred":[
        "Kilimli"
    ],
    "name:nor_x_preferred":[
        "Kilimli"
    ],
    "name:tur_x_preferred":[
        "Kilimli"
    ],
    "name:urd_x_preferred":[
        "\u06a9\u06cc\u0644\u06cc\u0645\u0644\u06cc"
    ],
    "name:vie_x_preferred":[
        "Kilimli"
    ],
    "name:zho_x_preferred":[
        "\u57fa\u5229\u59c6\u5229"
    ],
    "wof:name":"Kilimli",
    "wof:placetype":"locality"
},
  "geometry": {"coordinates":[41.36912,38.28817],"type":"Point"}
}