{
  "type": "Feature",
  "properties": {
    "gn:admin1_code":"59.0",
    "gn:asciiname":"Sultankoy",
    "gn:country_code":"TR",
    "gn:dem":27,
    "gn:feature_class":"P",
    "gn:feature_code":"PPL",
    "gn:name":"Sultank\u00f6y",
    "gn:population":2708,
    "gn:timezone":"Europe/Istanbul",
    "iso:country":"TR",
    "name:ceb_x_preferred":[
        "Sultank\u00f6y"
    ],
    "name:fas_x_preferred":[
        "\u0633\u0644\u0637\u0627\u0646\u200c\u06a9\u0648\u06cc"
    ],
    "name:nno_x_preferred":[
        "Sultank\u00f6y"
    ],
    "name:por_x_preferred":[
        "Sultank\u00f6y"
    ],
    "name:urd_x_preferred":[
        "\u0633\u0644\u0637\u0627\u0646 \u06a9\u0648\u0626\u06d2"
    ],
    "name:vie_x_preferred":[
        "Sultank\u00f6y"
    ],
    "name:zho_x_preferred":[
        "\u8607\u723e\u5766\u67ef\u4f0a"
    ],
    "wof:name":"Sultankoy",
    "wof:placetype":"locality",
    "wof:population":2708
},
  "geometry": {"coordinates":[27.98861,41.02139],"type":"Point"}
}