{
  "type": "Feature",
  "properties": {
    "gn:admin1_code":"59.0",
    "gn:asciiname":"Sultankoy",
    "gn:country_code":"TR",
    "gn:dem":27,
    "gn:feature_class":"P",
    "gn:feature_code":"PPL",
    "gn:name":"Sultank\u00f6y",
    "gn:population":2708,
    "gn:timezone":"Europe/Istanbul",
    "iso:country":"TR",
    "name:und_x_variant":[
        "Sultank\u00f6y"
    ],
    "wof:name":"Sultankoy",
    "wof:placetype":"locality",
    "wof:population":2708
},
  "geometry": {"coordinates":[27.98861,41.02139],"type":"Point"}
}