{
  "type": "Feature",
  "properties": {
    "gn:admin1_code":"73",
    "gn:asciiname":"Hasangazi",
    "gn:country_code":"TR",
    "gn:dem":1383,
    "gn:feature_class":"P",
    "gn:feature_code":"PPL",
    "gn:name":"Hasangazi",
    "gn:population":0,
    "gn:timezone":"Europe/Istanbul",
    "iso:country":"TR",
    "wof:name":"Hasangazi",
    "wof:placetype":"locality"
},
  "geometry": {"coordinates":[34.62641,37.54041],"type":"Point"}
}