{
  "type": "Feature",
  "properties": {
    "gn:admin1_code":"65.0",
    "gn:asciiname":"Golesirne",
    "gn:country_code":"TR",
    "gn:dem":2396,
    "gn:feature_class":"P",
    "gn:feature_code":"PPL",
    "gn:name":"G\u00f6lesirne",
    "gn:population":0,
    "gn:timezone":"Europe/Istanbul",
    "iso:country":"TR",
    "name:tur_x_preferred":[
        "G\u00f6lesirne"
    ],
    "wof:name":"Golesirne",
    "wof:placetype":"locality"
},
  "geometry": {"coordinates":[43.94219,38.29715],"type":"Point"}
}