{
  "type": "Feature",
  "properties": {
    "gn:admin1_code":"39.0",
    "gn:asciiname":"Begendik",
    "gn:country_code":"TR",
    "gn:dem":29,
    "gn:feature_class":"P",
    "gn:feature_code":"PPL",
    "gn:name":"Be\u011fendik",
    "gn:population":0,
    "gn:timezone":"Europe/Istanbul",
    "iso:country":"TR",
    "name:und_x_variant":[
        "Stefano",
        "Ayastafanos",
        "Be\u011fendik"
    ],
    "wof:name":"Begendik",
    "wof:placetype":"locality"
},
  "geometry": {"coordinates":[28.02222,41.96247],"type":"Point"}
}