{
  "type": "Feature",
  "properties": {
    "gn:admin1_code":"81",
    "gn:asciiname":"Yagizlar",
    "gn:country_code":"TR",
    "gn:dem":225,
    "gn:feature_class":"P",
    "gn:feature_code":"PPL",
    "gn:name":"Ya\u011f\u0131zlar",
    "gn:population":0,
    "gn:timezone":"Europe/Istanbul",
    "iso:country":"TR",
    "name:und_x_variant":[
        "Ya\u011f\u0131zlar",
        "B\u0131\u00e7\u0131lganl\u0131"
    ],
    "wof:name":"Yagizlar",
    "wof:placetype":"locality"
},
  "geometry": {"coordinates":[35.54597000000001,37.23212],"type":"Point"}
}