{
  "type": "Feature",
  "properties": {
    "gn:admin1_code":"52.0",
    "gn:asciiname":"Doglu",
    "gn:country_code":"TR",
    "gn:dem":347,
    "gn:feature_class":"P",
    "gn:feature_code":"PPL",
    "gn:name":"Do\u011flu",
    "gn:population":0,
    "gn:timezone":"Europe/Istanbul",
    "iso:country":"TR",
    "name:tur_x_preferred":[
        "Do\u011flu"
    ],
    "name:und_x_variant":[
        "Do\u011fulu"
    ],
    "wof:name":"Doglu",
    "wof:placetype":"locality"
},
  "geometry": {"coordinates":[37.77316,40.9091],"type":"Point"}
}