{
  "type": "Feature",
  "properties": {
    "gn:admin1_code":"65",
    "gn:asciiname":"Ismailbaba",
    "gn:country_code":"TR",
    "gn:dem":2181,
    "gn:feature_class":"P",
    "gn:feature_code":"PPL",
    "gn:name":"\u0130smailbaba",
    "gn:population":0,
    "gn:timezone":"Europe/Istanbul",
    "iso:country":"TR",
    "wof:name":"Ismailbaba",
    "wof:placetype":"locality"
},
  "geometry": {"coordinates":[44.09719000000001,39.02169],"type":"Point"}
}