{
  "type": "Feature",
  "properties": {
    "gn:admin1_code":"0.0",
    "gn:asciiname":"Bozkale",
    "gn:country_code":"TR",
    "gn:dem":1854,
    "gn:feature_class":"P",
    "gn:feature_code":"PPL",
    "gn:name":"Bozkale",
    "gn:population":0,
    "gn:timezone":"Europe/Istanbul",
    "iso:country":"TR",
    "wof:name":"Bozkale",
    "wof:placetype":"locality"
},
  "geometry": {"coordinates":[42.97723,40.58906],"type":"Point"}
}