{
  "type": "Feature",
  "properties": {
    "gn:admin1_code":"25",
    "gn:asciiname":"Goksu",
    "gn:country_code":"TR",
    "gn:dem":1823,
    "gn:feature_class":"P",
    "gn:feature_code":"PPLA3",
    "gn:name":"G\u00f6ksu",
    "gn:population":0,
    "gn:timezone":"Europe/Istanbul",
    "iso:country":"TR",
    "name:und_x_variant":[
        "Ko\u00e7an",
        "G\u00f6ksu"
    ],
    "wof:name":"Goksu",
    "wof:placetype":"locality"
},
  "geometry": {"coordinates":[42.15127,39.48906],"type":"Point"}
}