{
  "type": "Feature",
  "properties": {
    "gn:admin1_code":"58",
    "gn:asciiname":"Dikmencik",
    "gn:country_code":"TR",
    "gn:dem":1334,
    "gn:feature_class":"P",
    "gn:feature_code":"PPL",
    "gn:name":"Dikmencik",
    "gn:population":0,
    "gn:timezone":"Europe/Istanbul",
    "iso:country":"TR",
    "wof:name":"Dikmencik",
    "wof:placetype":"locality"
},
  "geometry": {"coordinates":[37.21667,39.75],"type":"Point"}
}