{
  "type": "Feature",
  "properties": {
    "gn:admin1_code":"63",
    "gn:asciiname":"Yuvacik",
    "gn:country_code":"TR",
    "gn:dem":897,
    "gn:feature_class":"P",
    "gn:feature_code":"PPL",
    "gn:name":"Yuvac\u0131k",
    "gn:population":0,
    "gn:timezone":"Europe/Istanbul",
    "iso:country":"TR",
    "name:tur_x_preferred":[
        "Yuvac\u0131k"
    ],
    "wof:name":"Yuvacik",
    "wof:placetype":"locality"
},
  "geometry": {"coordinates":[39.86752,37.43291],"type":"Point"}
}