{
  "type": "Feature",
  "properties": {
    "gn:admin1_code":"68",
    "gn:asciiname":"Ogulbey",
    "gn:country_code":"TR",
    "gn:dem":1098,
    "gn:feature_class":"P",
    "gn:feature_code":"PPL",
    "gn:name":"O\u011fulbey",
    "gn:population":0,
    "gn:timezone":"Europe/Istanbul",
    "iso:country":"TR",
    "name:tur_x_preferred":[
        "\u00c7akal"
    ],
    "name:und_x_variant":[
        "O\u011fulbey"
    ],
    "wof:name":"Ogulbey",
    "wof:placetype":"locality"
},
  "geometry": {"coordinates":[32.82635,39.68666],"type":"Point"}
}