{
  "type": "Feature",
  "properties": {
    "gn:admin1_code":"62",
    "gn:asciiname":"Begendik",
    "gn:country_code":"TR",
    "gn:dem":1513,
    "gn:feature_class":"P",
    "gn:feature_code":"PPL",
    "gn:name":"Be\u011fendik",
    "gn:population":0,
    "gn:timezone":"Europe/Istanbul",
    "iso:country":"TR",
    "wof:name":"Begendik",
    "wof:placetype":"locality"
},
  "geometry": {"coordinates":[39.86922,39.37746],"type":"Point"}
}