{
  "type": "Feature",
  "properties": {
    "gn:admin1_code":"66",
    "gn:asciiname":"Bahariye",
    "gn:country_code":"TR",
    "gn:dem":1065,
    "gn:feature_class":"P",
    "gn:feature_code":"PPL",
    "gn:name":"Bahariye",
    "gn:population":0,
    "gn:timezone":"Europe/Istanbul",
    "iso:country":"TR",
    "wof:name":"Bahariye",
    "wof:placetype":"locality"
},
  "geometry": {"coordinates":[35.20108,39.20327],"type":"Point"}
}