{
  "type": "Feature",
  "properties": {
    "gn:admin1_code":"65.0",
    "gn:asciiname":"Yaman Yurd",
    "gn:country_code":"TR",
    "gn:dem":2243,
    "gn:feature_class":"P",
    "gn:feature_code":"PPL",
    "gn:name":"Y\u0101m\u0101n Y\u016brd",
    "gn:population":0,
    "gn:timezone":"Europe/Istanbul",
    "iso:country":"TR",
    "name:fas_x_preferred":[
        "\u06cc\u0627\u0645\u0627\u0646 \u06cc\u0648\u0631\u062f"
    ],
    "name:fas_x_variant":[
        "Y\u0101m\u0101n Y\u016brd"
    ],
    "wof:name":"Yaman Yurd",
    "wof:placetype":"locality"
},
  "geometry": {"coordinates":[44.2726,38.5449],"type":"Point"}
}