{
  "type": "Feature",
  "properties": {
    "gn:admin1_code":"65",
    "gn:asciiname":"Ulubeyli",
    "gn:country_code":"TR",
    "gn:dem":2007,
    "gn:feature_class":"P",
    "gn:feature_code":"PPL",
    "gn:name":"Ulubeyli",
    "gn:population":0,
    "gn:timezone":"Europe/Istanbul",
    "iso:country":"TR",
    "name:und_x_variant":[
        "Abduvan",
        "Ulubeyli"
    ],
    "wof:name":"Ulubeyli",
    "wof:placetype":"locality"
},
  "geometry": {"coordinates":[42.70762,38.10622],"type":"Point"}
}