{
  "type": "Feature",
  "properties": {
    "gn:admin1_code":"69.0",
    "gn:asciiname":"Dolek",
    "gn:country_code":"TR",
    "gn:dem":1798,
    "gn:feature_class":"P",
    "gn:feature_code":"PPL",
    "gn:name":"D\u00f6lek",
    "gn:population":0,
    "gn:timezone":"Europe/Istanbul",
    "iso:country":"TR",
    "name:tur_x_preferred":[
        "D\u00f6lek"
    ],
    "wof:name":"Dolek",
    "wof:placetype":"locality"
},
  "geometry": {"coordinates":[39.4078,40.05563],"type":"Point"}
}