{
  "type": "Feature",
  "properties": {
    "iso:country":"TR",
    "name:ceb_x_preferred":[
        "Bayram\u00f6ren \u0130l\u00e7esi"
    ],
    "name:deu_x_preferred":[
        "Bayram\u00f6ren"
    ],
    "name:fra_x_preferred":[
        "Bayram\u00f6ren"
    ],
    "name:ita_x_preferred":[
        "Distretto di Bayram\u00f6ren"
    ],
    "name:mrj_x_preferred":[
        "\u0411\u0430\u0439\u0440\u0430\u043c\u04e7\u0440\u0435\u043d"
    ],
    "name:msa_x_preferred":[
        "Bayram\u00f6ren"
    ],
    "name:nld_x_preferred":[
        "Bayram\u00f6ren"
    ],
    "name:nor_x_preferred":[
        "Bayram\u00f6ren"
    ],
    "name:swa_x_preferred":[
        "Bayram\u00f6ren"
    ],
    "name:tur_x_preferred":[
        "Bayram\u00f6ren"
    ],
    "name:und_x_colloquial":[
        "Bayramoren"
    ],
    "name:urd_x_preferred":[
        "\u0628\u06d2\u0631\u0627\u0645\u0648\u0631\u06cc\u0646"
    ],
    "name:vie_x_preferred":[
        "Bayram\u00f6ren"
    ],
    "qs:gn_local":0,
    "qs:local_max":58,
    "qs:local_sum":58,
    "qs:localhoods":1,
    "qs:name":"Bayram\u00f6ren",
    "qs:name_adm0":"Turkey",
    "qs:name_adm1":"Kocaeli",
    "qs:name_adm2":"Gebze",
    "qs:name_local":"Gebze",
    "qs:photo_max":18,
    "qs:photo_sum":58,
    "qs:placetype":"Suburb",
    "qs:quad_count":13,
    "qs:woe_adm0":23424969,
    "qs:woe_adm1":2347296,
    "qs:woe_adm2":29390340,
    "qs:woe_lau":0,
    "qs:woe_local":2344002,
    "qs:woe_ver":"7.10.0",
    "qs_pg:name":"Bayram\u00f6ren",
    "qs_pg:name_adm0":"Turkey",
    "qs_pg:name_adm1":"Kocaeli",
    "qs_pg:photos":56,
    "qs_pg:photos_1k":11,
    "qs_pg:photos_9k":1,
    "qs_pg:photos_9r":2,
    "qs_pg:photos_all":56,
    "qs_pg:photos_sr":2,
    "qs_pg:pop_sr":0,
    "qs_pg:qs_pg_placetype":"neighbourhood",
    "qs_pg:qs_pg_placetype_gp":"Suburb",
    "qs_pg:woe_adm0":23424969,
    "wd:wordcount":98,
    "woe:adm0_id":23424969,
    "woe:name_adm0":"Turkey",
    "woe:name_adm1":"Kocaeli",
    "woe:placetype":"Suburb",
    "wof:lang":[
        "unk"
    ],
    "wof:name":"Bayram\u00f6ren",
    "wof:placetype":"neighbourhood"
},
  "geometry": {"coordinates":[29.422524,40.763972],"type":"Point"}
}