{
  "type": "Feature",
  "properties": {
    "gn:admin1_code":"45",
    "gn:asciiname":"Kecili",
    "gn:country_code":"TR",
    "gn:dem":86,
    "gn:feature_class":"P",
    "gn:feature_code":"PPL",
    "gn:name":"Ke\u00e7ili",
    "gn:population":0,
    "gn:timezone":"Europe/Istanbul",
    "iso:country":"TR",
    "name:und_x_variant":[
        "A\u015fa\u011f\u0131 Ke\u00e7ili",
        "Ke\u00e7ili"
    ],
    "wof:name":"Kecili",
    "wof:placetype":"locality"
},
  "geometry": {"coordinates":[27.34713,38.61459],"type":"Point"}
}