{
  "type": "Feature",
  "properties": {
    "gn:admin1_code":"78",
    "gn:asciiname":"Kizik",
    "gn:country_code":"TR",
    "gn:dem":1010,
    "gn:feature_class":"P",
    "gn:feature_code":"PPL",
    "gn:name":"K\u0131z\u0131k",
    "gn:population":0,
    "gn:timezone":"Europe/Istanbul",
    "iso:country":"TR",
    "name:tur_x_preferred":[
        "K\u0131z\u0131k"
    ],
    "wof:name":"Kizik",
    "wof:placetype":"locality"
},
  "geometry": {"coordinates":[33.28894,37.27642],"type":"Point"}
}