{
  "type": "Feature",
  "properties": {
    "gn:admin1_code":"66",
    "gn:asciiname":"Komusoren",
    "gn:country_code":"TR",
    "gn:dem":800,
    "gn:feature_class":"P",
    "gn:feature_code":"PPL",
    "gn:name":"K\u00f6m\u00fc\u015f\u00f6ren",
    "gn:population":0,
    "gn:timezone":"Europe/Istanbul",
    "iso:country":"TR",
    "name:und_x_variant":[
        "K\u00f6m\u00fc\u015fviran",
        "K\u00f6m\u00fc\u015f\u00f6ren"
    ],
    "wof:name":"Komusoren",
    "wof:placetype":"locality"
},
  "geometry": {"coordinates":[34.5151,39.68744],"type":"Point"}
}