{
  "type": "Feature",
  "properties": {
    "gn:admin1_code":"10.0",
    "gn:asciiname":"Hacimentes",
    "gn:country_code":"TR",
    "gn:dem":52,
    "gn:feature_class":"P",
    "gn:feature_code":"PPL",
    "gn:name":"Hac\u0131mente\u015f",
    "gn:population":0,
    "gn:timezone":"Europe/Istanbul",
    "iso:country":"TR",
    "name:tur_x_preferred":[
        "Hac\u0131mente\u015f"
    ],
    "wof:name":"Hacimentes",
    "wof:placetype":"locality"
},
  "geometry": {"coordinates":[27.76528,40.15879],"type":"Point"}
}