{
  "type": "Feature",
  "properties": {
    "gn:admin1_code":"80",
    "gn:asciiname":"Fistikli",
    "gn:cc2":"TR",
    "gn:country_code":"TR",
    "gn:dem":501,
    "gn:feature_class":"P",
    "gn:feature_code":"PPL",
    "gn:name":"F\u0131st\u0131kl\u0131",
    "gn:population":0,
    "gn:timezone":"Europe/Istanbul",
    "iso:country":"TR",
    "name:und_x_variant":[
        "Kaf\u0131lk\u0131r",
        "Kaf\u0131k\u0131r",
        "Kafylkyr",
        "F\u0131st\u0131kl\u0131"
    ],
    "wof:name":"Fistikli",
    "wof:placetype":"locality"
},
  "geometry": {"coordinates":[42.145,37.32194000000001],"type":"Point"}
}