{
  "type": "Feature",
  "properties": {
    "gn:admin1_code":"45",
    "gn:asciiname":"Candir",
    "gn:country_code":"TR",
    "gn:dem":981,
    "gn:feature_class":"P",
    "gn:feature_code":"PPL",
    "gn:name":"\u00c7and\u0131r",
    "gn:population":0,
    "gn:timezone":"Europe/Istanbul",
    "iso:country":"TR",
    "wof:name":"Candir",
    "wof:placetype":"locality"
},
  "geometry": {"coordinates":[28.75833,38.98444],"type":"Point"}
}