{
  "type": "Feature",
  "properties": {
    "gn:admin1_code":"93.0",
    "gn:asciiname":"Yesilkoy",
    "gn:country_code":"TR",
    "gn:dem":202,
    "gn:feature_class":"P",
    "gn:feature_code":"PPL",
    "gn:name":"Ye\u015filk\u00f6y",
    "gn:population":0,
    "gn:timezone":"Europe/Istanbul",
    "iso:country":"TR",
    "name:und_x_variant":[
        "Vak\u0131f",
        "Ye\u015filk\u00f6y"
    ],
    "wof:name":"Yesilkoy",
    "wof:placetype":"locality"
},
  "geometry": {"coordinates":[31.12333,41.03083],"type":"Point"}
}