{
  "type": "Feature",
  "properties": {
    "gn:admin1_code":"14",
    "gn:asciiname":"Oteyaka",
    "gn:country_code":"TR",
    "gn:dem":1024,
    "gn:feature_class":"P",
    "gn:feature_code":"PPL",
    "gn:name":"\u00d6teyaka",
    "gn:population":0,
    "gn:timezone":"Europe/Istanbul",
    "iso:country":"TR",
    "wof:name":"Oteyaka",
    "wof:placetype":"locality"
},
  "geometry": {"coordinates":[31.87306,40.74264],"type":"Point"}
}