{
  "type": "Feature",
  "properties": {
    "gn:admin1_code":"37.0",
    "gn:asciiname":"Cekic",
    "gn:country_code":"TR",
    "gn:dem":1086,
    "gn:feature_class":"P",
    "gn:feature_code":"PPL",
    "gn:name":"\u00c7eki\u00e7",
    "gn:population":0,
    "gn:timezone":"Europe/Istanbul",
    "iso:country":"TR",
    "name:und_x_variant":[
        "\u00c7ek\u00fc\u00e7",
        "\u00c7eki\u00e7"
    ],
    "wof:name":"Cekic",
    "wof:placetype":"locality"
},
  "geometry": {"coordinates":[34.18655,41.3851],"type":"Point"}
}