{
  "type": "Feature",
  "properties": {
    "gn:admin1_code":"14.0",
    "gn:asciiname":"Beyderesi",
    "gn:country_code":"TR",
    "gn:dem":1131,
    "gn:feature_class":"P",
    "gn:feature_code":"PPL",
    "gn:name":"Beyderesi",
    "gn:population":0,
    "gn:timezone":"Europe/Istanbul",
    "iso:country":"TR",
    "name:und_x_variant":[
        "Beydere",
        "Beyderesi"
    ],
    "wof:name":"Beyderesi",
    "wof:placetype":"locality"
},
  "geometry": {"coordinates":[31.39671,40.50615],"type":"Point"}
}