{
  "type": "Feature",
  "properties": {
    "gn:country":"TR",
    "gn:fcode":"PPL",
    "gn:population":107,
    "iso:country":"TR",
    "name:rus_x_preferred":[
        "Dyumbil\u2019yan"
    ],
    "name:und_x_variant":[
        "D\u00fcmbilyan"
    ],
    "qs:name":"Erdem",
    "qs:photos_9r":0,
    "qs:photos_sr":0,
    "qs:pop_sr":"1",
    "wd:wordcount":120,
    "wof:name":"Erdem",
    "wof:placetype":"locality",
    "wof:population":107
},
  "geometry": {"coordinates":[42.08111,37.21528],"type":"Point"}
}