{
  "type": "Feature",
  "properties": {
    "gn:admin1_code":"23",
    "gn:asciiname":"Saritas",
    "gn:country_code":"TR",
    "gn:dem":1660,
    "gn:feature_class":"P",
    "gn:feature_code":"PPL",
    "gn:name":"Sar\u0131ta\u015f",
    "gn:population":0,
    "gn:timezone":"Europe/Istanbul",
    "iso:country":"TR",
    "name:tur_x_preferred":[
        "Bozarmut Mezraasi"
    ],
    "name:und_x_variant":[
        "Sar\u0131ta\u015f",
        "Bozarmut"
    ],
    "wof:name":"Saritas",
    "wof:placetype":"locality"
},
  "geometry": {"coordinates":[38.94126,38.43374],"type":"Point"}
}