{
  "type": "Feature",
  "properties": {
    "gn:admin1_code":"71",
    "gn:asciiname":"Alahan",
    "gn:country_code":"TR",
    "gn:dem":1025,
    "gn:feature_class":"P",
    "gn:feature_code":"PPL",
    "gn:name":"Alahan",
    "gn:population":0,
    "gn:timezone":"Europe/Istanbul",
    "iso:country":"TR",
    "name:und_x_variant":[
        "Alhan"
    ],
    "wof:name":"Alahan",
    "wof:placetype":"locality"
},
  "geometry": {"coordinates":[33.97812,37.51115],"type":"Point"}
}