{
  "type": "Feature",
  "properties": {
    "gn:admin1_code":"37.0",
    "gn:asciiname":"Yemisli",
    "gn:country_code":"TR",
    "gn:dem":390,
    "gn:feature_class":"P",
    "gn:feature_code":"PPL",
    "gn:name":"Yemi\u015fli",
    "gn:population":0,
    "gn:timezone":"Europe/Istanbul",
    "iso:country":"TR",
    "name:und_x_variant":[
        "Yemi\u015fli",
        "D\u00fczk\u00f6y"
    ],
    "wof:name":"Yemisli",
    "wof:placetype":"locality"
},
  "geometry": {"coordinates":[34.20575,41.89734],"type":"Point"}
}