{
  "type": "Feature",
  "properties": {
    "gn:admin1_code":"11",
    "gn:asciiname":"Aglan",
    "gn:country_code":"TR",
    "gn:dem":805,
    "gn:feature_class":"P",
    "gn:feature_code":"PPL",
    "gn:name":"A\u011flan",
    "gn:population":0,
    "gn:timezone":"Europe/Istanbul",
    "iso:country":"TR",
    "name:tur_x_preferred":[
        "A\u011flan"
    ],
    "wof:name":"Aglan",
    "wof:placetype":"locality"
},
  "geometry": {"coordinates":[29.96711,40.48797],"type":"Point"}
}