{
  "type": "Feature",
  "properties": {
    "gn:admin1_code":"20",
    "gn:asciiname":"Sapcilar",
    "gn:country_code":"TR",
    "gn:dem":762,
    "gn:feature_class":"P",
    "gn:feature_code":"PPL",
    "gn:name":"\u015eap\u00e7\u0131lar",
    "gn:population":0,
    "gn:timezone":"Europe/Istanbul",
    "iso:country":"TR",
    "name:tur_x_preferred":[
        "\u015eap\u00e7\u0131lar"
    ],
    "wof:name":"Sapcilar",
    "wof:placetype":"locality"
},
  "geometry": {"coordinates":[29.44011,38.1087],"type":"Point"}
}