{
  "type": "Feature",
  "properties": {
    "gn:admin1_code":"48",
    "gn:asciiname":"Yakakoy",
    "gn:country_code":"TR",
    "gn:dem":822,
    "gn:feature_class":"P",
    "gn:feature_code":"PPL",
    "gn:name":"Yakak\u00f6y",
    "gn:population":0,
    "gn:timezone":"Europe/Istanbul",
    "iso:country":"TR",
    "name:tur_x_preferred":[
        "Ak\u0131nlar"
    ],
    "name:und_x_variant":[
        "Yakak\u00f6y",
        "Yaka"
    ],
    "wof:name":"Yakakoy",
    "wof:placetype":"locality"
},
  "geometry": {"coordinates":[29.45196,36.56802],"type":"Point"}
}