{
  "type": "Feature",
  "properties": {
    "gn:admin1_code":"79.0",
    "gn:asciiname":"Kuzugudenli",
    "gn:country_code":"TR",
    "gn:dem":972,
    "gn:feature_class":"P",
    "gn:feature_code":"PPL",
    "gn:name":"Kuzug\u00fcdenli",
    "gn:population":0,
    "gn:timezone":"Europe/Istanbul",
    "iso:country":"TR",
    "wof:name":"Kuzugudenli",
    "wof:placetype":"locality"
},
  "geometry": {"coordinates":[33.76994000000001,39.63501],"type":"Point"}
}