{
  "type": "Feature",
  "properties": {
    "gn:admin1_code":"09",
    "gn:asciiname":"Kalfakoy",
    "gn:country_code":"TR",
    "gn:dem":168,
    "gn:feature_class":"P",
    "gn:feature_code":"PPL",
    "gn:name":"Kalfak\u00f6y",
    "gn:population":0,
    "gn:timezone":"Europe/Istanbul",
    "iso:country":"TR",
    "name:tur_x_preferred":[
        "Kalfak\u00f6y"
    ],
    "wof:name":"Kalfakoy",
    "wof:placetype":"locality"
},
  "geometry": {"coordinates":[27.8511,37.87214],"type":"Point"}
}