{
  "type": "Feature",
  "properties": {
    "gn:admin1_code":"8.0",
    "gn:asciiname":"Asagi Maden",
    "gn:country_code":"TR",
    "gn:dem":810,
    "gn:feature_class":"P",
    "gn:feature_code":"PPL",
    "gn:name":"A\u015fa\u011f\u0131 Maden",
    "gn:population":0,
    "gn:timezone":"Europe/Istanbul",
    "iso:country":"TR",
    "name:ceb_x_preferred":[
        "A\u015fa\u011f\u0131 Maden"
    ],
    "name:msa_x_preferred":[
        "A\u015fa\u011f\u0131maden"
    ],
    "name:tur_x_preferred":[
        "A\u015fa\u011f\u0131 Maden"
    ],
    "name:tur_x_variant":[
        "A\u015fa\u011f\u0131maden"
    ],
    "name:und_x_variant":[
        "Maden",
        "A\u015fa\u011f\u0131maden"
    ],
    "name:vie_x_preferred":[
        "A\u015fa\u011f\u0131maden"
    ],
    "wof:name":"Asagi Maden",
    "wof:placetype":"locality"
},
  "geometry": {"coordinates":[41.83282,40.98398],"type":"Point"}
}