{
  "type": "Feature",
  "properties": {
    "gn:admin1_code":"87.0",
    "gn:asciiname":"Kavakli",
    "gn:country_code":"TR",
    "gn:dem":258,
    "gn:feature_class":"P",
    "gn:feature_code":"PPL",
    "gn:name":"Kavakl\u0131",
    "gn:population":0,
    "gn:timezone":"Europe/Istanbul",
    "iso:country":"TR",
    "name:und_x_variant":[
        "Kavakl\u0131",
        "G\u00f6mbez"
    ],
    "wof:name":"Kavakli",
    "wof:placetype":"locality"
},
  "geometry": {"coordinates":[32.68751,41.80521],"type":"Point"}
}