{
  "type": "Feature",
  "properties": {
    "gn:admin1_code":"44",
    "gn:asciiname":"Kizilmagara",
    "gn:country_code":"TR",
    "gn:dem":1718,
    "gn:feature_class":"P",
    "gn:feature_code":"PPL",
    "gn:name":"K\u0131z\u0131lma\u011fara",
    "gn:population":0,
    "gn:timezone":"Europe/Istanbul",
    "iso:country":"TR",
    "name:tur_x_preferred":[
        "K\u0131z\u0131lma\u011fara"
    ],
    "wof:name":"Kizilmagara",
    "wof:placetype":"locality"
},
  "geometry": {"coordinates":[37.77249000000001,38.70627],"type":"Point"}
}