{
  "type": "Feature",
  "properties": {
    "gn:admin1_code":"16",
    "gn:asciiname":"Cekrice",
    "gn:country_code":"TR",
    "gn:dem":53,
    "gn:feature_class":"P",
    "gn:feature_code":"PPL",
    "gn:name":"\u00c7ekrice",
    "gn:population":0,
    "gn:timezone":"Europe/Istanbul",
    "iso:country":"TR",
    "name:tur_x_preferred":[
        "\u00c7ekrice"
    ],
    "wof:name":"Cekrice",
    "wof:placetype":"locality"
},
  "geometry": {"coordinates":[28.78281,40.26873],"type":"Point"}
}