{
  "type": "Feature",
  "properties": {
    "gn:admin1_code":"5.0",
    "gn:asciiname":"Sarikoy",
    "gn:country_code":"TR",
    "gn:dem":713,
    "gn:feature_class":"P",
    "gn:feature_code":"PPL",
    "gn:name":"Sar\u0131k\u00f6y",
    "gn:population":0,
    "gn:timezone":"Europe/Istanbul",
    "iso:country":"TR",
    "name:und_x_variant":[
        "Sar\u0131",
        "Sar\u0131k\u00f6y"
    ],
    "wof:name":"Sarikoy",
    "wof:placetype":"locality"
},
  "geometry": {"coordinates":[35.39778,40.86207],"type":"Point"}
}