{
  "type": "Feature",
  "properties": {
    "gn:admin1_code":"9.0",
    "gn:asciiname":"Ahatlar",
    "gn:country_code":"TR",
    "gn:dem":764,
    "gn:feature_class":"P",
    "gn:feature_code":"PPL",
    "gn:name":"Ahatlar",
    "gn:population":0,
    "gn:timezone":"Europe/Istanbul",
    "iso:country":"TR",
    "name:tur_x_preferred":[
        "Ahatlar"
    ],
    "wof:name":"Ahatlar",
    "wof:placetype":"locality"
},
  "geometry": {"coordinates":[28.09281,37.98632],"type":"Point"}
}