{
  "type": "Feature",
  "properties": {
    "gn:country":"TR",
    "gn:fcode":"PPL",
    "gn:population":65,
    "iso:country":"TR",
    "name:tur_x_preferred":[
        "Deveh\u00f6y\u00fc\u011f\u00fc"
    ],
    "name:und_x_variant":[
        "Deveh\u00fcy\u00fck"
    ],
    "qs:name":"Devekhyuyuk",
    "qs:photos_9r":0,
    "qs:photos_sr":0,
    "qs:pop_sr":"1",
    "wof:name":"Devekhyuyuk",
    "wof:placetype":"locality",
    "wof:population":65
},
  "geometry": {"coordinates":[37.73583,36.75528],"type":"Point"}
}