{
  "type": "Feature",
  "properties": {
    "gn:admin1_code":"44",
    "gn:asciiname":"Bahceli",
    "gn:country_code":"TR",
    "gn:dem":818,
    "gn:feature_class":"P",
    "gn:feature_code":"PPL",
    "gn:name":"Bah\u00e7eli",
    "gn:population":0,
    "gn:timezone":"Europe/Istanbul",
    "iso:country":"TR",
    "name:tur_x_preferred":[
        "Bah\u00e7eli"
    ],
    "wof:name":"Bahceli",
    "wof:placetype":"locality"
},
  "geometry": {"coordinates":[38.43162,38.77349],"type":"Point"}
}