{
  "type": "Feature",
  "properties": {
    "gn:admin1_code":"5.0",
    "gn:asciiname":"Alparslan",
    "gn:country_code":"TR",
    "gn:dem":472,
    "gn:feature_class":"P",
    "gn:feature_code":"PPL",
    "gn:name":"Alparslan",
    "gn:population":0,
    "gn:timezone":"Europe/Istanbul",
    "iso:country":"TR",
    "name:eng_x_preferred":[
        "Alpaslan"
    ],
    "name:rus_x_preferred":[
        "\u0417\u0443\u0434\u0430\u0439"
    ],
    "name:tur_x_preferred":[
        "Alparslan"
    ],
    "name:und_x_variant":[
        "Yolba\u015f\u0131",
        "Zuday"
    ],
    "wof:name":"Alparslan",
    "wof:placetype":"locality"
},
  "geometry": {"coordinates":[36.34222000000001,40.80722],"type":"Point"}
}