{
  "type": "Feature",
  "properties": {
    "gn:admin1_code":"39.0",
    "gn:asciiname":"Celaliye",
    "gn:country_code":"TR",
    "gn:dem":111,
    "gn:feature_class":"P",
    "gn:feature_code":"PPL",
    "gn:name":"Cel\u00e2liye",
    "gn:population":0,
    "gn:timezone":"Europe/Istanbul",
    "iso:country":"TR",
    "name:tur_x_preferred":[
        "Cel\u00e2liye"
    ],
    "wof:name":"Celaliye",
    "wof:placetype":"locality"
},
  "geometry": {"coordinates":[27.36181,41.52866],"type":"Point"}
}