{
  "type": "Feature",
  "properties": {
    "gn:admin1_code":"58.0",
    "gn:asciiname":"Kuvana",
    "gn:country_code":"TR",
    "gn:dem":852,
    "gn:feature_class":"P",
    "gn:feature_code":"PPL",
    "gn:name":"Kuvana",
    "gn:population":0,
    "gn:timezone":"Europe/Istanbul",
    "iso:country":"TR",
    "name:tur_x_preferred":[
        "Yayg\u0131ns\u00f6\u011f\u00fct"
    ],
    "name:und_x_variant":[
        "Kovana",
        "Kuvana",
        "Yag\u0131ns\u00f6\u011f\u00fct"
    ],
    "wof:name":"Kuvana",
    "wof:placetype":"locality"
},
  "geometry": {"coordinates":[38.15959,40.25844],"type":"Point"}
}