{
  "type": "Feature",
  "properties": {
    "iso:country":"TR",
    "name:eng_x_preferred":[
        "Hisarbeyli"
    ],
    "name:tur_x_preferred":[
        "Hisarbeyli"
    ],
    "wof:name":"Hisarbeyli",
    "wof:placetype":"neighbourhood"
},
  "geometry": {"coordinates":[28.47498945492326,41.36748378415326],"type":"Point"}
}