{
  "type": "Feature",
  "properties": {
    "gn:admin1_code":"58",
    "gn:asciiname":"Igdecik",
    "gn:country_code":"TR",
    "gn:dem":1604,
    "gn:feature_class":"P",
    "gn:feature_code":"PPL",
    "gn:name":"\u0130\u011fdecik",
    "gn:population":0,
    "gn:timezone":"Europe/Istanbul",
    "iso:country":"TR",
    "name:tur_x_preferred":[
        "\u0130\u011fdecik"
    ],
    "wof:name":"Igdecik",
    "wof:placetype":"locality"
},
  "geometry": {"coordinates":[36.28831,39.62566],"type":"Point"}
}