{
  "type": "Feature",
  "properties": {
    "gn:admin1_code":"61.0",
    "gn:asciiname":"Asafoliza",
    "gn:cc2":"TR",
    "gn:country_code":"TR",
    "gn:dem":1975,
    "gn:feature_class":"P",
    "gn:feature_code":"PPL",
    "gn:name":"Asafoliza",
    "gn:population":0,
    "gn:timezone":"Europe/Istanbul",
    "iso:country":"TR",
    "name:und_x_variant":[
        "Asofoliza",
        "Asafoliza"
    ],
    "wof:name":"Asafoliza",
    "wof:placetype":"locality"
},
  "geometry": {"coordinates":[40.36667,40.66667],"type":"Point"}
}