{
  "type": "Feature",
  "properties": {
    "gn:admin1_code":"03",
    "gn:asciiname":"Seyhyahsi",
    "gn:country_code":"TR",
    "gn:dem":962,
    "gn:feature_class":"P",
    "gn:feature_code":"PPL",
    "gn:name":"\u015eeyhyah\u015fi",
    "gn:population":0,
    "gn:timezone":"Europe/Istanbul",
    "iso:country":"TR",
    "name:und_x_variant":[
        "\u015eihyah\u015fi",
        "\u015eeyhyah\u015fi"
    ],
    "wof:name":"Seyhyahsi",
    "wof:placetype":"locality"
},
  "geometry": {"coordinates":[29.99014,38.45372],"type":"Point"}
}