{
  "type": "Feature",
  "properties": {
    "gn:admin1_code":"48",
    "gn:asciiname":"Calardi",
    "gn:country_code":"TR",
    "gn:dem":1181,
    "gn:feature_class":"P",
    "gn:feature_code":"PPL",
    "gn:name":"\u00c7alard\u0131",
    "gn:population":0,
    "gn:timezone":"Europe/Istanbul",
    "iso:country":"TR",
    "name:tur_x_preferred":[
        "\u00c7alard\u0131"
    ],
    "name:tur_x_variant":[
        "Yabanc\u0131k"
    ],
    "wof:name":"Calardi",
    "wof:placetype":"locality"
},
  "geometry": {"coordinates":[29.03758,36.88809000000001],"type":"Point"}
}