{
  "type": "Feature",
  "properties": {
    "gn:country":"TR",
    "gn:fcode":"PPL",
    "gn:pop":279,
    "iso:country":"TR",
    "name:unk_x_variant":[
        "Yukar\u0131 Artuvin"
    ],
    "qs:name":"Hertivinler",
    "qs:photos_9r":0,
    "qs:photos_sr":0,
    "qs:pop_sr":"2",
    "wof:name":"Hertivinler",
    "wof:placetype":"locality",
    "wof:population":279
},
  "geometry": {"coordinates":[42.35333,37.92333],"type":"Point"}
}