{
  "type": "Feature",
  "properties": {
    "gn:admin1_code":"10",
    "gn:asciiname":"Kamcili",
    "gn:country_code":"TR",
    "gn:dem":338,
    "gn:feature_class":"P",
    "gn:feature_code":"PPL",
    "gn:name":"Kam\u00e7\u0131l\u0131",
    "gn:population":0,
    "gn:timezone":"Europe/Istanbul",
    "iso:country":"TR",
    "name:und_x_variant":[
        "Kam\u00e7\u0131ll\u0131",
        "Kam\u00e7\u0131l\u0131"
    ],
    "wof:name":"Kamcili",
    "wof:placetype":"locality"
},
  "geometry": {"coordinates":[27.91988,39.82946],"type":"Point"}
}