{
  "type": "Feature",
  "properties": {
    "gn:admin1_code":"24",
    "gn:asciiname":"Elmakoy",
    "gn:country_code":"TR",
    "gn:dem":1317,
    "gn:feature_class":"P",
    "gn:feature_code":"PPL",
    "gn:name":"Elmak\u00f6y",
    "gn:population":0,
    "gn:timezone":"Europe/Istanbul",
    "iso:country":"TR",
    "name:und_x_variant":[
        "Sipiyata\u011f\u0131",
        "Sipyeta\u011f\u0131",
        "Sipyata\u011f\u0131 K\u00f6y\u00fc",
        "Elmak\u00f6y"
    ],
    "wof:name":"Elmakoy",
    "wof:placetype":"locality"
},
  "geometry": {"coordinates":[39.35423,39.78902],"type":"Point"}
}