{
  "type": "Feature",
  "properties": {
    "gn:admin1_code":"8.0",
    "gn:asciiname":"Zeytinlik",
    "gn:country_code":"TR",
    "gn:dem":301,
    "gn:feature_class":"P",
    "gn:feature_code":"PPLA3",
    "gn:name":"Zeytinlik",
    "gn:population":0,
    "gn:timezone":"Europe/Istanbul",
    "iso:country":"TR",
    "name:eng_x_preferred":[
        "Zeytinlik"
    ],
    "name:rus_x_preferred":[
        "\u0417\u0435\u0439\u0442\u0438\u043d\u043b\u0438\u043a"
    ],
    "name:und_x_variant":[
        "Sirya",
        "Zeytinlik"
    ],
    "wof:name":"Zeytinlik",
    "wof:placetype":"locality"
},
  "geometry": {"coordinates":[41.85816,41.11013],"type":"Point"}
}