{
  "type": "Feature",
  "properties": {
    "gn:admin1_code":"10",
    "gn:asciiname":"Yassioren",
    "gn:country_code":"TR",
    "gn:dem":943,
    "gn:feature_class":"P",
    "gn:feature_code":"PPL",
    "gn:name":"Yass\u0131\u00f6ren",
    "gn:population":0,
    "gn:timezone":"Europe/Istanbul",
    "iso:country":"TR",
    "name:und_x_variant":[
        "Yass\u0131viran",
        "Yass\u0131\u00f6ren"
    ],
    "wof:name":"Yassioren",
    "wof:placetype":"locality"
},
  "geometry": {"coordinates":[28.8026,39.42182],"type":"Point"}
}