{
  "type": "Feature",
  "properties": {
    "gn:admin1_code":"65",
    "gn:asciiname":"Bilgili",
    "gn:country_code":"TR",
    "gn:dem":1980,
    "gn:feature_class":"P",
    "gn:feature_code":"PPL",
    "gn:name":"Bilgili",
    "gn:population":0,
    "gn:timezone":"Europe/Istanbul",
    "iso:country":"TR",
    "wof:name":"Bilgili",
    "wof:placetype":"locality"
},
  "geometry": {"coordinates":[42.7754,38.13546],"type":"Point"}
}