{
  "type": "Feature",
  "properties": {
    "gn:admin1_code":"83.0",
    "gn:asciiname":"Kurucahuyuk",
    "gn:country_code":"TR",
    "gn:dem":552,
    "gn:feature_class":"P",
    "gn:feature_code":"PPL",
    "gn:name":"Kurucah\u00fcy\u00fck",
    "gn:population":0,
    "gn:timezone":"Europe/Istanbul",
    "iso:country":"TR",
    "name:tur_x_preferred":[
        "Kurucah\u00f6y\u00fck"
    ],
    "name:und_x_variant":[
        "Kurudzhakhyuyuk",
        "Kurucah\u00fcy\u00fck"
    ],
    "wof:name":"Kurucahuyuk",
    "wof:placetype":"locality"
},
  "geometry": {"coordinates":[37.74275,36.87118],"type":"Point"}
}