{
  "type": "Feature",
  "properties": {
    "gn:admin1_code":"57.0",
    "gn:asciiname":"Yanalak",
    "gn:country_code":"TR",
    "gn:dem":389,
    "gn:feature_class":"P",
    "gn:feature_code":"PPL",
    "gn:name":"Yanalak",
    "gn:population":0,
    "gn:timezone":"Europe/Istanbul",
    "iso:country":"TR",
    "wof:name":"Yanalak",
    "wof:placetype":"locality"
},
  "geometry": {"coordinates":[35.06306,41.45343],"type":"Point"}
}