{
  "type": "Feature",
  "properties": {
    "gn:admin1_code":"81",
    "gn:asciiname":"Incetarla",
    "gn:cc2":"TR",
    "gn:country_code":"TR",
    "gn:dem":25,
    "gn:feature_class":"P",
    "gn:feature_code":"PPL",
    "gn:name":"Incetarla",
    "gn:population":0,
    "gn:timezone":"Europe/Istanbul",
    "iso:country":"TR",
    "name:und_x_variant":[
        "Hasana\u011fa"
    ],
    "wof:name":"Incetarla",
    "wof:placetype":"locality"
},
  "geometry": {"coordinates":[35.86694,37.08889],"type":"Point"}
}