{
  "type": "Feature",
  "properties": {
    "gn:admin1_code":"52.0",
    "gn:asciiname":"Emenkoy",
    "gn:country_code":"TR",
    "gn:dem":400,
    "gn:feature_class":"P",
    "gn:feature_code":"PPL",
    "gn:name":"Emenk\u00f6y",
    "gn:population":0,
    "gn:timezone":"Europe/Istanbul",
    "iso:country":"TR",
    "name:tur_x_preferred":[
        "Emenk\u00f6y"
    ],
    "wof:name":"Emenkoy",
    "wof:placetype":"locality"
},
  "geometry": {"coordinates":[37.99705,40.92132],"type":"Point"}
}