{
  "type": "Feature",
  "properties": {
    "gn:admin1_code":"64",
    "gn:asciiname":"Kusdemir",
    "gn:country_code":"TR",
    "gn:dem":981,
    "gn:feature_class":"P",
    "gn:feature_code":"PPL",
    "gn:name":"Ku\u015fdemir",
    "gn:population":0,
    "gn:timezone":"Europe/Istanbul",
    "iso:country":"TR",
    "wof:name":"Kusdemir",
    "wof:placetype":"locality"
},
  "geometry": {"coordinates":[29.72259,38.74332],"type":"Point"}
}