{
  "type": "Feature",
  "properties": {
    "gn:admin1_code":"31",
    "gn:asciiname":"Sofular",
    "gn:country_code":"TR",
    "gn:dem":507,
    "gn:feature_class":"P",
    "gn:feature_code":"PPL",
    "gn:name":"Sofular",
    "gn:population":0,
    "gn:timezone":"Europe/Istanbul",
    "iso:country":"TR",
    "name:tur_x_preferred":[
        "Sofular"
    ],
    "wof:name":"Sofular",
    "wof:placetype":"locality"
},
  "geometry": {"coordinates":[36.17368,36.1101],"type":"Point"}
}