{
  "type": "Feature",
  "properties": {
    "gn:admin1_code":"65",
    "gn:asciiname":"Gokcedal",
    "gn:country_code":"TR",
    "gn:dem":2175,
    "gn:feature_class":"P",
    "gn:feature_code":"PPL",
    "gn:name":"G\u00f6k\u00e7edal",
    "gn:population":0,
    "gn:timezone":"Europe/Istanbul",
    "iso:country":"TR",
    "wof:name":"Gokcedal",
    "wof:placetype":"locality"
},
  "geometry": {"coordinates":[42.92944,37.98389],"type":"Point"}
}