{
  "type": "Feature",
  "properties": {
    "gn:country":"TR",
    "gn:fcode":"PPL",
    "gn:pop":18937,
    "iso:country":"TR",
    "name:chi_x_preferred":[
        "\u85a9\u62c9\u4f0a\u67ef\u4f0a"
    ],
    "name:dut_x_preferred":[
        "Sarayk\u00f6y"
    ],
    "name:eng_x_preferred":[
        "Sarayk\u00f6y"
    ],
    "name:fas_x_preferred":[
        "\u0633\u0631\u0627\u06cc\u200c\u06a9\u0648\u06cc"
    ],
    "name:fre_x_preferred":[
        "Sarayk\u00f6y"
    ],
    "name:ger_x_preferred":[
        "Sarayk\u00f6y"
    ],
    "name:gre_x_preferred":[
        "\u03a3\u03b1\u03c1\u03ac\u03b9\u03ba\u03b9\u03bf\u03ca"
    ],
    "name:ita_x_preferred":[
        "Distretto di Sarayk\u00f6y"
    ],
    "name:jpn_x_preferred":[
        "\u30b5\u30e9\u30a4\u30b3\u30a4"
    ],
    "name:lit_x_preferred":[
        "Saraik\u0117jus"
    ],
    "name:may_x_preferred":[
        "Sarayk\u00f6y"
    ],
    "name:mrj_x_preferred":[
        "\u0421\u0430\u0440\u0430\u0439\u043a\u04e7\u0439"
    ],
    "name:nan_x_preferred":[
        "Sarayk\u00f6y"
    ],
    "name:nno_x_preferred":[
        "Sarayk\u00f6y"
    ],
    "name:nob_x_preferred":[
        "Sarayk\u00f6y"
    ],
    "name:per_x_preferred":[
        "\u0633\u0631\u0627\u06cc\u200c\u06a9\u0648\u06cc"
    ],
    "name:pnb_x_preferred":[
        "\u0636\u0644\u0639 \u0633\u0627\u0631\u0627\u06a9\u0648\u06d3"
    ],
    "name:sco_x_preferred":[
        "Sarayk\u00f6y"
    ],
    "name:spa_x_preferred":[
        "Sarayk\u00f6y"
    ],
    "name:tur_x_preferred":[
        "Sarayk\u00f6y"
    ],
    "name:unk_x_variant":[
        "Seraikeui"
    ],
    "name:urd_x_preferred":[
        "\u0633\u0631\u0627\u0626\u06d2\u06a9\u0648\u0626\u06d2"
    ],
    "name:vie_x_preferred":[
        "Sarayk\u00f6y"
    ],
    "name:zho_x_preferred":[
        "\u85a9\u62c9\u4f0a\u67ef\u4f0a"
    ],
    "qs:name":"Sarayk\u00f6y",
    "qs:name_adm0":"Turkey",
    "qs:name_adm1":"Denizli",
    "qs:photos_9k":1,
    "qs:photos_9r":1,
    "qs:photos_all":12,
    "qs:photos_sr":0,
    "qs:placetype":"Town",
    "qs:pop_sr":"6",
    "wd:wordcount":403,
    "wof:name":"Sarayk\u00f6y",
    "wof:placetype":"locality",
    "wof:population":18937
},
  "geometry": {"coordinates":[28.92516,37.92448],"type":"Point"}
}