{
  "type": "Feature",
  "properties": {
    "gn:admin1_code":"63",
    "gn:asciiname":"Kyuchyuk-Dzhana",
    "gn:country_code":"TR",
    "gn:dem":390,
    "gn:feature_class":"P",
    "gn:feature_code":"PPL",
    "gn:name":"Kyuchyuk-Dzhana",
    "gn:population":0,
    "gn:timezone":"Europe/Istanbul",
    "iso:country":"TR",
    "name:und_x_variant":[
        "Canasa\u011fir",
        "Kyuchyuk-Dzhana",
        "K\u00fc\u00e7\u00fckd\u00fczl\u00fck"
    ],
    "wof:name":"Kyuchyuk-Dzhana",
    "wof:placetype":"locality"
},
  "geometry": {"coordinates":[39.15083,36.94972],"type":"Point"}
}