{
  "type": "Feature",
  "properties": {
    "gn:admin1_code":"02",
    "gn:asciiname":"Gedik",
    "gn:country_code":"TR",
    "gn:dem":1268,
    "gn:feature_class":"P",
    "gn:feature_code":"PPL",
    "gn:name":"Gedik",
    "gn:population":0,
    "gn:timezone":"Europe/Istanbul",
    "iso:country":"TR",
    "name:und_x_variant":[
        "Dol"
    ],
    "wof:name":"Gedik",
    "wof:placetype":"locality"
},
  "geometry": {"coordinates":[38.35854000000001,37.89756],"type":"Point"}
}