{
  "type": "Feature",
  "properties": {
    "gn:admin1_code":"64",
    "gn:asciiname":"Goceler",
    "gn:country_code":"TR",
    "gn:dem":860,
    "gn:feature_class":"P",
    "gn:feature_code":"PPL",
    "gn:name":"G\u00f6celer",
    "gn:population":0,
    "gn:timezone":"Europe/Istanbul",
    "iso:country":"TR",
    "name:tur_x_preferred":[
        "G\u00f6celer"
    ],
    "name:und_x_variant":[
        "G\u00fcceler Mahallesi",
        "G\u00fcceler"
    ],
    "wof:name":"Goceler",
    "wof:placetype":"locality"
},
  "geometry": {"coordinates":[29.62554,38.39872],"type":"Point"}
}