{
  "type": "Feature",
  "properties": {
    "gn:admin1_code":"89.0",
    "gn:asciiname":"Uzumluk",
    "gn:country_code":"TR",
    "gn:dem":828,
    "gn:feature_class":"P",
    "gn:feature_code":"PPL",
    "gn:name":"\u00dcz\u00fcml\u00fck",
    "gn:population":0,
    "gn:timezone":"Europe/Istanbul",
    "iso:country":"TR",
    "wof:name":"Uzumluk",
    "wof:placetype":"locality"
},
  "geometry": {"coordinates":[33.04317,41.08417],"type":"Point"}
}