{
  "type": "Feature",
  "properties": {
    "gn:country":"TR",
    "gn:fcode":"PPL",
    "gn:population":217,
    "iso:country":"TR",
    "name:und_x_variant":[
        "Bezal"
    ],
    "qs:name":"Ortal\u0131",
    "qs:photos_9r":0,
    "qs:photos_sr":0,
    "qs:pop_sr":"2",
    "wof:name":"Ortal\u0131",
    "wof:placetype":"locality",
    "wof:population":217
},
  "geometry": {"coordinates":[43.21564,37.60725],"type":"Point"}
}