{
  "type": "Feature",
  "properties": {
    "gn:admin1_code":"60.0",
    "gn:asciiname":"Olukalan",
    "gn:cc2":"TR",
    "gn:country_code":"TR",
    "gn:dem":1359,
    "gn:feature_class":"P",
    "gn:feature_code":"PPL",
    "gn:name":"Olukalan",
    "gn:population":0,
    "gn:timezone":"Europe/Istanbul",
    "iso:country":"TR",
    "name:und_x_variant":[
        "Olukalan K\u00f6y\u00fc",
        "Olukalan"
    ],
    "wof:name":"Olukalan",
    "wof:placetype":"locality"
},
  "geometry": {"coordinates":[37.16056,40.65417],"type":"Point"}
}