{
  "type": "Feature",
  "properties": {
    "gn:admin1_code":"61.0",
    "gn:asciiname":"Akkose",
    "gn:country_code":"TR",
    "gn:dem":589,
    "gn:feature_class":"P",
    "gn:feature_code":"PPL",
    "gn:name":"Akk\u00f6se",
    "gn:population":0,
    "gn:timezone":"Europe/Istanbul",
    "iso:country":"TR",
    "name:msa_x_preferred":[
        "Akk\u00f6se"
    ],
    "name:tur_x_preferred":[
        "Akk\u00f6se"
    ],
    "name:und_x_variant":[
        "Zenoakk\u00f6se",
        "Akk\u00f6se"
    ],
    "name:vie_x_preferred":[
        "Akk\u00f6se"
    ],
    "wof:name":"Akkose",
    "wof:placetype":"locality"
},
  "geometry": {"coordinates":[40.27657,40.78979],"type":"Point"}
}