{
  "type": "Feature",
  "properties": {
    "gn:admin1_code":"72",
    "gn:asciiname":"Atalar",
    "gn:country_code":"TR",
    "gn:dem":1068,
    "gn:feature_class":"P",
    "gn:feature_code":"PPL",
    "gn:name":"Atalar",
    "gn:population":0,
    "gn:timezone":"Europe/Istanbul",
    "iso:country":"TR",
    "name:tur_x_preferred":[
        "Atalar"
    ],
    "name:tur_x_variant":[
        "Atak\u00f6y"
    ],
    "name:und_x_variant":[
        "Har\u00fck",
        "Alpata"
    ],
    "wof:name":"Atalar",
    "wof:placetype":"locality"
},
  "geometry": {"coordinates":[40.3575,37.37167],"type":"Point"}
}