{
  "type": "Feature",
  "properties": {
    "gn:admin1_code":"86.0",
    "gn:asciiname":"Senemoglu",
    "gn:country_code":"TR",
    "gn:dem":2069,
    "gn:feature_class":"P",
    "gn:feature_code":"PPL",
    "gn:name":"Senemo\u011flu",
    "gn:population":0,
    "gn:timezone":"Europe/Istanbul",
    "iso:country":"TR",
    "name:und_x_variant":[
        "Senemo\u011flu"
    ],
    "wof:name":"Senemoglu",
    "wof:placetype":"locality"
},
  "geometry": {"coordinates":[42.66204000000001,40.78106],"type":"Point"}
}