{
  "type": "Feature",
  "properties": {
    "gn:admin1_code":"63",
    "gn:asciiname":"Aritir",
    "gn:country_code":"TR",
    "gn:dem":669,
    "gn:feature_class":"P",
    "gn:feature_code":"PPL",
    "gn:name":"Ar\u0131t\u0131r",
    "gn:population":0,
    "gn:timezone":"Europe/Istanbul",
    "iso:country":"TR",
    "name:tur_x_preferred":[
        "Ar\u0131t\u0131r"
    ],
    "wof:name":"Aritir",
    "wof:placetype":"locality"
},
  "geometry": {"coordinates":[39.97272,37.33186],"type":"Point"}
}