{
  "type": "Feature",
  "properties": {
    "gn:admin1_code":"43",
    "gn:asciiname":"Kalkan",
    "gn:country_code":"TR",
    "gn:dem":861,
    "gn:feature_class":"P",
    "gn:feature_code":"PPL",
    "gn:name":"Kalkan",
    "gn:population":0,
    "gn:timezone":"Europe/Istanbul",
    "iso:country":"TR",
    "name:ceb_x_preferred":[
        "Kalkan"
    ],
    "name:deu_x_preferred":[
        "Kalkan"
    ],
    "name:ell_x_preferred":[
        "\u039a\u03b1\u03bb\u03ba\u03ac\u03bd"
    ],
    "name:epo_x_preferred":[
        "Kalkan"
    ],
    "name:fin_x_preferred":[
        "Kalkan"
    ],
    "name:ita_x_preferred":[
        "Kalkan"
    ],
    "name:srp_x_preferred":[
        "\u041a\u0430\u043b\u043a\u0430\u043d"
    ],
    "name:tur_x_preferred":[
        "Kalkan"
    ],
    "name:vie_x_preferred":[
        "Kalkan"
    ],
    "wof:name":"Kalkan",
    "wof:placetype":"locality"
},
  "geometry": {"coordinates":[29.06083,39.08095],"type":"Point"}
}