{
  "type": "Feature",
  "properties": {
    "gn:admin1_code":"55.0",
    "gn:asciiname":"Inalti",
    "gn:country_code":"TR",
    "gn:dem":939,
    "gn:feature_class":"P",
    "gn:feature_code":"PPL",
    "gn:name":"\u0130nalt\u0131",
    "gn:population":0,
    "gn:timezone":"Europe/Istanbul",
    "iso:country":"TR",
    "wof:name":"Inalti",
    "wof:placetype":"locality"
},
  "geometry": {"coordinates":[35.61667,41.21667],"type":"Point"}
}