{
  "type": "Feature",
  "properties": {
    "gn:admin1_code":"60.0",
    "gn:asciiname":"Ustahasan",
    "gn:country_code":"TR",
    "gn:dem":893,
    "gn:feature_class":"P",
    "gn:feature_code":"PPL",
    "gn:name":"Ustahasan",
    "gn:population":0,
    "gn:timezone":"Europe/Istanbul",
    "iso:country":"TR",
    "wof:name":"Ustahasan",
    "wof:placetype":"locality"
},
  "geometry": {"coordinates":[36.99869,40.57298],"type":"Point"}
}