{
  "type": "Feature",
  "properties": {
    "gn:admin1_code":"25",
    "gn:asciiname":"Tosunlu",
    "gn:country_code":"TR",
    "gn:dem":1884,
    "gn:feature_class":"P",
    "gn:feature_code":"PPL",
    "gn:name":"Tosunlu",
    "gn:population":0,
    "gn:timezone":"Europe/Istanbul",
    "iso:country":"TR",
    "name:und_x_variant":[
        "Kandalkomu"
    ],
    "wof:name":"Tosunlu",
    "wof:placetype":"locality"
},
  "geometry": {"coordinates":[40.69828,39.76752000000001],"type":"Point"}
}