{
  "type": "Feature",
  "properties": {
    "gn:admin1_code":"52.0",
    "gn:asciiname":"Yavi",
    "gn:country_code":"TR",
    "gn:dem":198,
    "gn:feature_class":"P",
    "gn:feature_code":"PPL",
    "gn:name":"Yav\u0131",
    "gn:population":0,
    "gn:timezone":"Europe/Istanbul",
    "iso:country":"TR",
    "name:deu_x_preferred":[
        "Yavi"
    ],
    "name:fra_x_preferred":[
        "Yavi"
    ],
    "name:ita_x_preferred":[
        "Yavi"
    ],
    "name:nld_x_preferred":[
        "Yavi"
    ],
    "name:spa_x_preferred":[
        "Yavi"
    ],
    "name:tur_x_preferred":[
        "Yav\u0131"
    ],
    "name:und_x_variant":[
        "Yav\u0131k\u00f6y",
        "Yavk\u00f6y"
    ],
    "wof:name":"Yavi",
    "wof:placetype":"locality"
},
  "geometry": {"coordinates":[37.17183,41.03997],"type":"Point"}
}