{
  "type": "Feature",
  "properties": {
    "gn:admin1_code":"28.0",
    "gn:asciiname":"Hacili",
    "gn:country_code":"TR",
    "gn:dem":1597,
    "gn:feature_class":"P",
    "gn:feature_code":"PPL",
    "gn:name":"Hac\u0131l\u0131",
    "gn:population":0,
    "gn:timezone":"Europe/Istanbul",
    "iso:country":"TR",
    "name:tur_x_preferred":[
        "Hac\u0131l\u0131"
    ],
    "wof:name":"Hacili",
    "wof:placetype":"locality"
},
  "geometry": {"coordinates":[38.80931,40.32475],"type":"Point"}
}