{
  "type": "Feature",
  "properties": {
    "gn:admin1_code":"88.0",
    "gn:asciiname":"Asagi Alican",
    "gn:country_code":"TR",
    "gn:dem":842,
    "gn:feature_class":"P",
    "gn:feature_code":"PPL",
    "gn:name":"A\u015fa\u011f\u0131 Alican",
    "gn:population":0,
    "gn:timezone":"Europe/Istanbul",
    "iso:country":"TR",
    "name:tur_x_preferred":[
        "A\u015fa\u011f\u0131 Alican"
    ],
    "name:und_x_variant":[
        "A\u015fa\u011f\u0131alican"
    ],
    "wof:name":"Asagi Alican",
    "wof:placetype":"locality"
},
  "geometry": {"coordinates":[44.20371,40.02554],"type":"Point"}
}