{
  "type": "Feature",
  "properties": {
    "gn:admin1_code":"71",
    "gn:asciiname":"Satiryayla Damlari",
    "gn:country_code":"TR",
    "gn:dem":1002,
    "gn:feature_class":"P",
    "gn:feature_code":"PPL",
    "gn:name":"\u015eat\u0131ryayla Damlar\u0131",
    "gn:population":0,
    "gn:timezone":"Europe/Istanbul",
    "iso:country":"TR",
    "wof:name":"Satiryayla Damlari",
    "wof:placetype":"locality"
},
  "geometry": {"coordinates":[32.73333,37.83333],"type":"Point"}
}