{
  "type": "Feature",
  "properties": {
    "gn:admin1_code":"88",
    "gn:asciiname":"Enginalan",
    "gn:country_code":"TR",
    "gn:dem":862,
    "gn:feature_class":"P",
    "gn:feature_code":"PPL",
    "gn:name":"Enginalan",
    "gn:population":0,
    "gn:timezone":"Europe/Istanbul",
    "iso:country":"TR",
    "name:und_x_variant":[
        "Pulur",
        "Enginalan"
    ],
    "wof:name":"Enginalan",
    "wof:placetype":"locality"
},
  "geometry": {"coordinates":[44.03146,39.96115],"type":"Point"}
}