{
  "type": "Feature",
  "properties": {
    "gn:admin1_code":"66",
    "gn:asciiname":"Eskioren",
    "gn:country_code":"TR",
    "gn:dem":1022,
    "gn:feature_class":"P",
    "gn:feature_code":"PPL",
    "gn:name":"Eski\u00f6ren",
    "gn:population":0,
    "gn:timezone":"Europe/Istanbul",
    "iso:country":"TR",
    "name:und_x_variant":[
        "Eski\u00f6ren",
        "Eskiveren"
    ],
    "wof:name":"Eskioren",
    "wof:placetype":"locality"
},
  "geometry": {"coordinates":[35.00274,39.18277],"type":"Point"}
}