{
  "type": "Feature",
  "properties": {
    "gn:admin1_code":"48",
    "gn:asciiname":"Bogazagzi",
    "gn:country_code":"TR",
    "gn:dem":246,
    "gn:feature_class":"P",
    "gn:feature_code":"PPL",
    "gn:name":"Bo\u011faza\u011fz\u0131",
    "gn:population":0,
    "gn:timezone":"Europe/Istanbul",
    "iso:country":"TR",
    "name:tur_x_preferred":[
        "Bo\u011faza\u011fz\u0131"
    ],
    "wof:name":"Bogazagzi",
    "wof:placetype":"locality"
},
  "geometry": {"coordinates":[28.6517,36.76085],"type":"Point"}
}