{
  "type": "Feature",
  "properties": {
    "gn:admin1_code":"02",
    "gn:asciiname":"Sariharman",
    "gn:country_code":"TR",
    "gn:dem":656,
    "gn:feature_class":"P",
    "gn:feature_code":"PPL",
    "gn:name":"Sar\u0131harman",
    "gn:population":0,
    "gn:timezone":"Europe/Istanbul",
    "iso:country":"TR",
    "wof:name":"Sariharman",
    "wof:placetype":"locality"
},
  "geometry": {"coordinates":[38.46098,37.71726],"type":"Point"}
}