{
  "type": "Feature",
  "properties": {
    "gn:admin1_code":"60.0",
    "gn:asciiname":"Yagmurlu",
    "gn:country_code":"TR",
    "gn:dem":852,
    "gn:feature_class":"P",
    "gn:feature_code":"PPL",
    "gn:name":"Ya\u011fmurlu",
    "gn:population":0,
    "gn:timezone":"Europe/Istanbul",
    "iso:country":"TR",
    "name:eng_x_preferred":[
        "Ya\u011fmurlu"
    ],
    "name:rus_x_preferred":[
        "\u041e\u0445\u0442\u0430\u043f\u043a\u0435\u044e"
    ],
    "name:und_x_variant":[
        "Ohtap",
        "Ohtapk\u00f6y\u00fc",
        "Ya\u011fmurlu"
    ],
    "wof:name":"Yagmurlu",
    "wof:placetype":"locality"
},
  "geometry": {"coordinates":[36.81208,40.51955],"type":"Point"}
}