{
  "type": "Feature",
  "properties": {
    "gn:admin1_code":"13.0",
    "gn:asciiname":"Kinalikoc",
    "gn:country_code":"TR",
    "gn:dem":1798,
    "gn:feature_class":"P",
    "gn:feature_code":"PPL",
    "gn:name":"K\u0131nal\u0131ko\u00e7",
    "gn:population":0,
    "gn:timezone":"Europe/Istanbul",
    "iso:country":"TR",
    "name:tur_x_preferred":[
        "K\u0131nal\u0131ko\u00e7"
    ],
    "wof:name":"Kinalikoc",
    "wof:placetype":"locality"
},
  "geometry": {"coordinates":[42.36898,38.81364],"type":"Point"}
}