{
  "type": "Feature",
  "properties": {
    "gn:admin1_code":"53.0",
    "gn:asciiname":"Kalecik",
    "gn:country_code":"TR",
    "gn:dem":184,
    "gn:feature_class":"P",
    "gn:feature_code":"PPL",
    "gn:name":"Kalecik",
    "gn:population":0,
    "gn:timezone":"Europe/Istanbul",
    "iso:country":"TR",
    "name:ceb_x_preferred":[
        "Kalecik"
    ],
    "name:deu_x_preferred":[
        "Kalecik"
    ],
    "name:fra_x_preferred":[
        "Kalecik"
    ],
    "name:nld_x_preferred":[
        "Kalecik"
    ],
    "name:por_x_preferred":[
        "Kalecik"
    ],
    "name:swe_x_preferred":[
        "Kalecik"
    ],
    "name:tur_x_preferred":[
        "Kalecik"
    ],
    "wof:name":"Kalecik",
    "wof:placetype":"locality"
},
  "geometry": {"coordinates":[40.39225,40.97547],"type":"Point"}
}