{
  "type": "Feature",
  "properties": {
    "gn:admin1_code":"21",
    "gn:asciiname":"Kubacik",
    "gn:country_code":"TR",
    "gn:dem":660,
    "gn:feature_class":"P",
    "gn:feature_code":"PPL",
    "gn:name":"Kubac\u0131k",
    "gn:population":0,
    "gn:timezone":"Europe/Istanbul",
    "iso:country":"TR",
    "name:tur_x_preferred":[
        "Kubac\u0131k"
    ],
    "wof:name":"Kubacik",
    "wof:placetype":"locality"
},
  "geometry": {"coordinates":[40.31373,37.79146],"type":"Point"}
}