{
  "type": "Feature",
  "properties": {
    "gn:admin1_code":"58",
    "gn:asciiname":"Orenlice",
    "gn:country_code":"TR",
    "gn:dem":1553,
    "gn:feature_class":"P",
    "gn:feature_code":"PPL",
    "gn:name":"\u00d6renlice",
    "gn:population":0,
    "gn:timezone":"Europe/Istanbul",
    "iso:country":"TR",
    "wof:name":"Orenlice",
    "wof:placetype":"locality"
},
  "geometry": {"coordinates":[37.27124,39.44621],"type":"Point"}
}