{
  "type": "Feature",
  "properties": {
    "gn:admin1_code":"87",
    "gn:asciiname":"Danisment",
    "gn:country_code":"TR",
    "gn:dem":268,
    "gn:feature_class":"P",
    "gn:feature_code":"PPL",
    "gn:name":"Dan\u0131\u015fment",
    "gn:population":0,
    "gn:timezone":"Europe/Istanbul",
    "iso:country":"TR",
    "wof:name":"Danisment",
    "wof:placetype":"locality"
},
  "geometry": {"coordinates":[32.69156,41.81989],"type":"Point"}
}