{
  "type": "Feature",
  "properties": {
    "gn:country":"TR",
    "gn:fcode":"PPL",
    "gn:pop":103,
    "iso:country":"TR",
    "name:tur_x_preferred":[
        "Balaban"
    ],
    "name:tur_x_variant":[
        "Seyd\u00fcmen",
        "Se\u011fd\u00fcmen"
    ],
    "name:unk_x_variant":[
        "Seydyumen"
    ],
    "qs:name":"Balaban",
    "qs:photos_9r":0,
    "qs:photos_sr":0,
    "qs:pop_sr":"1",
    "wd:wordcount":49,
    "wof:name":"Balaban",
    "wof:placetype":"locality",
    "wof:population":103
},
  "geometry": {"coordinates":[37.76833,36.80333],"type":"Point"}
}