{
  "type": "Feature",
  "properties": {
    "gn:admin1_code":"68.0",
    "gn:asciiname":"Yavuzlar",
    "gn:country_code":"TR",
    "gn:dem":1307,
    "gn:feature_class":"P",
    "gn:feature_code":"PPL",
    "gn:name":"Yavuzlar",
    "gn:population":0,
    "gn:timezone":"Europe/Istanbul",
    "iso:country":"TR",
    "wof:name":"Yavuzlar",
    "wof:placetype":"locality"
},
  "geometry": {"coordinates":[33.07765999999999,39.87262],"type":"Point"}
}