{
  "type": "Feature",
  "properties": {
    "gn:admin1_code":"08",
    "gn:asciiname":"Ardicli",
    "gn:country_code":"TR",
    "gn:dem":612,
    "gn:feature_class":"P",
    "gn:feature_code":"PPL",
    "gn:name":"Ard\u0131\u00e7l\u0131",
    "gn:population":0,
    "gn:timezone":"Europe/Istanbul",
    "iso:country":"TR",
    "name:tur_x_preferred":[
        "Ard\u0131\u00e7l\u0131"
    ],
    "wof:name":"Ardicli",
    "wof:placetype":"locality"
},
  "geometry": {"coordinates":[41.58427,41.28273],"type":"Point"}
}