{
  "type": "Feature",
  "properties": {
    "gn:admin1_code":"02",
    "gn:asciiname":"Akcakaya",
    "gn:country_code":"TR",
    "gn:dem":1039,
    "gn:feature_class":"P",
    "gn:feature_code":"PPL",
    "gn:name":"Ak\u00e7akaya",
    "gn:population":0,
    "gn:timezone":"Europe/Istanbul",
    "iso:country":"TR",
    "name:und_x_variant":[
        "Ak\u00e7akaya",
        "Pehnik"
    ],
    "wof:name":"Akcakaya",
    "wof:placetype":"locality"
},
  "geometry": {"coordinates":[37.69047,37.7923],"type":"Point"}
}