{
  "type": "Feature",
  "properties": {
    "gn:admin1_code":"35",
    "gn:asciiname":"Kosedere",
    "gn:country_code":"TR",
    "gn:dem":215,
    "gn:feature_class":"P",
    "gn:feature_code":"PPL",
    "gn:name":"K\u00f6sedere",
    "gn:population":0,
    "gn:timezone":"Europe/Istanbul",
    "iso:country":"TR",
    "name:tur_x_preferred":[
        "K\u00f6sedere"
    ],
    "wof:name":"Kosedere",
    "wof:placetype":"locality"
},
  "geometry": {"coordinates":[26.55329,38.54786],"type":"Point"}
}