{
  "type": "Feature",
  "properties": {
    "gn:admin1_code":"70.0",
    "gn:asciiname":"Tava",
    "gn:country_code":"TR",
    "gn:dem":1765,
    "gn:feature_class":"P",
    "gn:feature_code":"PPL",
    "gn:name":"Tava",
    "gn:population":0,
    "gn:timezone":"Europe/Istanbul",
    "iso:country":"TR",
    "wof:name":"Tava",
    "wof:placetype":"locality"
},
  "geometry": {"coordinates":[44.49988,37.2883],"type":"Point"}
}