{
  "type": "Feature",
  "properties": {
    "gn:admin1_code":"17",
    "gn:asciiname":"Huseyinfaki",
    "gn:country_code":"TR",
    "gn:dem":410,
    "gn:feature_class":"P",
    "gn:feature_code":"PPL",
    "gn:name":"H\u00fcseyinfak\u0131",
    "gn:population":0,
    "gn:timezone":"Europe/Istanbul",
    "iso:country":"TR",
    "name:und_x_variant":[
        "H\u00fcseyinfak\u0131",
        "H\u00fcseyinfak\u0131hl\u0131",
        "H\u00fcseyinfak\u0131h",
        "H\u00fcseyin\u00e7ak\u0131"
    ],
    "wof:name":"Huseyinfaki",
    "wof:placetype":"locality"
},
  "geometry": {"coordinates":[26.46194,39.56083],"type":"Point"}
}