{
  "type": "Feature",
  "properties": {
    "gn:admin1_code":"74",
    "gn:asciiname":"Madenkoy",
    "gn:country_code":"TR",
    "gn:dem":1352,
    "gn:feature_class":"P",
    "gn:feature_code":"PPL",
    "gn:name":"Madenk\u00f6y",
    "gn:population":0,
    "gn:timezone":"Europe/Istanbul",
    "iso:country":"TR",
    "name:und_x_variant":[
        "Maden",
        "Madenk\u00f6y"
    ],
    "wof:name":"Madenkoy",
    "wof:placetype":"locality"
},
  "geometry": {"coordinates":[42.15081,38.09189],"type":"Point"}
}