{
  "type": "Feature",
  "properties": {
    "gn:admin1_code":"74",
    "gn:asciiname":"Imren",
    "gn:country_code":"TR",
    "gn:dem":1120,
    "gn:feature_class":"P",
    "gn:feature_code":"PPL",
    "gn:name":"\u0130mren",
    "gn:population":0,
    "gn:timezone":"Europe/Istanbul",
    "iso:country":"TR",
    "name:und_x_variant":[
        "\u0130mren",
        "Kursun\u00e7"
    ],
    "wof:name":"Imren",
    "wof:placetype":"locality"
},
  "geometry": {"coordinates":[42.27434,38.05684],"type":"Point"}
}