{
  "type": "Feature",
  "properties": {
    "gn:admin1_code":"74",
    "gn:asciiname":"Tasdibek",
    "gn:country_code":"TR",
    "gn:dem":747,
    "gn:feature_class":"P",
    "gn:feature_code":"PPL",
    "gn:name":"Ta\u015fdibek",
    "gn:population":0,
    "gn:timezone":"Europe/Istanbul",
    "iso:country":"TR",
    "name:und_x_variant":[
        "\u015eetr\u00fck",
        "Shatryuk",
        "\u015eatr\u00fck",
        "Ta\u015fdibek"
    ],
    "wof:name":"Tasdibek",
    "wof:placetype":"locality"
},
  "geometry": {"coordinates":[41.94467,37.78972],"type":"Point"}
}