{
  "type": "Feature",
  "properties": {
    "gn:admin1_code":"24",
    "gn:asciiname":"Yesilyayla",
    "gn:country_code":"TR",
    "gn:dem":1788,
    "gn:feature_class":"P",
    "gn:feature_code":"PPL",
    "gn:name":"Ye\u015filyayla",
    "gn:population":0,
    "gn:timezone":"Europe/Istanbul",
    "iso:country":"TR",
    "name:und_x_variant":[
        "Ye\u015filyayla",
        "Ikizce"
    ],
    "wof:name":"Yesilyayla",
    "wof:placetype":"locality"
},
  "geometry": {"coordinates":[40.32191,39.91536],"type":"Point"}
}