{
  "type": "Feature",
  "properties": {
    "gn:admin1_code":"84.0",
    "gn:asciiname":"Karahamza",
    "gn:country_code":"TR",
    "gn:dem":1871,
    "gn:feature_class":"P",
    "gn:feature_code":"PPL",
    "gn:name":"Karahamza",
    "gn:population":0,
    "gn:timezone":"Europe/Istanbul",
    "iso:country":"TR",
    "wof:name":"Karahamza",
    "wof:placetype":"locality"
},
  "geometry": {"coordinates":[42.74819,40.43542],"type":"Point"}
}