{
  "type": "Feature",
  "properties": {
    "gn:admin1_code":"14.0",
    "gn:asciiname":"Celtikderesi",
    "gn:country_code":"TR",
    "gn:dem":672,
    "gn:feature_class":"P",
    "gn:feature_code":"PPL",
    "gn:name":"\u00c7eltikderesi",
    "gn:population":0,
    "gn:timezone":"Europe/Istanbul",
    "iso:country":"TR",
    "name:und_x_variant":[
        "\u00c7eltikdere",
        "\u00c7eltikderesik\u00f6y",
        "\u00c7eltik",
        "\u00c7eltikderesi"
    ],
    "wof:name":"Celtikderesi",
    "wof:placetype":"locality"
},
  "geometry": {"coordinates":[31.71141,40.34434],"type":"Point"}
}