{
  "type": "Feature",
  "properties": {
    "gn:admin1_code":"72.0",
    "gn:asciiname":"Leylak",
    "gn:country_code":"TR",
    "gn:dem":1152,
    "gn:feature_class":"P",
    "gn:feature_code":"PPL",
    "gn:name":"Leylak",
    "gn:population":0,
    "gn:timezone":"Europe/Istanbul",
    "iso:country":"TR",
    "name:ceb_x_preferred":[
        "Leylak"
    ],
    "name:fas_x_preferred":[
        "\u0644\u06cc\u0644\u06a9"
    ],
    "name:msa_x_preferred":[
        "Leylak"
    ],
    "name:swe_x_preferred":[
        "Leylak"
    ],
    "name:tur_x_preferred":[
        "Leylak"
    ],
    "wof:name":"Leylak",
    "wof:placetype":"locality"
},
  "geometry": {"coordinates":[40.66625,37.40515],"type":"Point"}
}