{
  "type": "Feature",
  "properties": {
    "gn:admin1_code":"46",
    "gn:asciiname":"Osmanbey",
    "gn:country_code":"TR",
    "gn:dem":476,
    "gn:feature_class":"P",
    "gn:feature_code":"PPL",
    "gn:name":"Osmanbey",
    "gn:population":0,
    "gn:timezone":"Europe/Istanbul",
    "iso:country":"TR",
    "name:tur_x_preferred":[
        "Osmanbey"
    ],
    "wof:name":"Osmanbey",
    "wof:placetype":"locality"
},
  "geometry": {"coordinates":[36.92873,37.51467],"type":"Point"}
}