{
  "type": "Feature",
  "properties": {
    "gn:admin1_code":"61.0",
    "gn:asciiname":"Pazarcik",
    "gn:country_code":"TR",
    "gn:dem":631,
    "gn:feature_class":"P",
    "gn:feature_code":"PPL",
    "gn:name":"Pazarc\u0131k",
    "gn:population":0,
    "gn:timezone":"Europe/Istanbul",
    "iso:country":"TR",
    "wof:name":"Pazarcik",
    "wof:placetype":"locality"
},
  "geometry": {"coordinates":[39.47078,40.92706],"type":"Point"}
}