{
  "type": "Feature",
  "properties": {
    "gn:admin1_code":"21",
    "gn:asciiname":"Solmaz",
    "gn:country_code":"TR",
    "gn:dem":782,
    "gn:feature_class":"P",
    "gn:feature_code":"PPL",
    "gn:name":"Solmaz",
    "gn:population":0,
    "gn:timezone":"Europe/Istanbul",
    "iso:country":"TR",
    "name:tur_x_preferred":[
        "Solmaz"
    ],
    "wof:name":"Solmaz",
    "wof:placetype":"locality"
},
  "geometry": {"coordinates":[40.32425,37.65736],"type":"Point"}
}