{
  "type": "Feature",
  "properties": {
    "gn:admin1_code":"70.0",
    "gn:asciiname":"Senocak",
    "gn:country_code":"TR",
    "gn:dem":1647,
    "gn:feature_class":"P",
    "gn:feature_code":"PPL",
    "gn:name":"Senocak",
    "gn:population":0,
    "gn:timezone":"Europe/Istanbul",
    "iso:country":"TR",
    "wof:name":"Senocak",
    "wof:placetype":"locality"
},
  "geometry": {"coordinates":[43.91212,37.41329],"type":"Point"}
}