{
  "type": "Feature",
  "properties": {
    "gn:admin1_code":"77.0",
    "gn:asciiname":"Gumussu",
    "gn:country_code":"TR",
    "gn:dem":1736,
    "gn:feature_class":"P",
    "gn:feature_code":"PPL",
    "gn:name":"G\u00fcm\u00fc\u015fsu",
    "gn:population":0,
    "gn:timezone":"Europe/Istanbul",
    "iso:country":"TR",
    "name:und_x_variant":[
        "Ahs\u00fcnkler",
        "Ahs\u00fcnk",
        "G\u00fcm\u00fc\u015fsu"
    ],
    "wof:name":"Gumussu",
    "wof:placetype":"locality"
},
  "geometry": {"coordinates":[40.30434,40.22462],"type":"Point"}
}