{
  "type": "Feature",
  "properties": {
    "gn:admin1_code":"64",
    "gn:asciiname":"Hirikveli",
    "gn:country_code":"TR",
    "gn:dem":795,
    "gn:feature_class":"P",
    "gn:feature_code":"PPL",
    "gn:name":"H\u0131r\u0131kveli",
    "gn:population":0,
    "gn:timezone":"Europe/Istanbul",
    "iso:country":"TR",
    "name:tur_x_preferred":[
        "H\u0131r\u0131kveli"
    ],
    "wof:name":"Hirikveli",
    "wof:placetype":"locality"
},
  "geometry": {"coordinates":[28.94168,38.29701],"type":"Point"}
}