{
  "type": "Feature",
  "properties": {
    "gn:admin1_code":"71.0",
    "gn:asciiname":"Acikuyu",
    "gn:country_code":"TR",
    "gn:dem":933,
    "gn:feature_class":"P",
    "gn:feature_code":"PPL",
    "gn:name":"Ac\u0131kuyu",
    "gn:population":0,
    "gn:timezone":"Europe/Istanbul",
    "iso:country":"TR",
    "name:und_x_variant":[
        "Ac\u0131kuyu Yaylas\u0131",
        "Ac\u0131kuyu"
    ],
    "wof:name":"Acikuyu",
    "wof:placetype":"locality"
},
  "geometry": {"coordinates":[32.98829,38.83887],"type":"Point"}
}