{
  "type": "Feature",
  "properties": {
    "gn:admin1_code":"03",
    "gn:asciiname":"Karacaoren",
    "gn:country_code":"TR",
    "gn:dem":1165,
    "gn:feature_class":"P",
    "gn:feature_code":"PPL",
    "gn:name":"Karaca\u00f6ren",
    "gn:population":0,
    "gn:timezone":"Europe/Istanbul",
    "iso:country":"TR",
    "name:und_x_variant":[
        "Karaca\u00f6ren",
        "Karacaviran"
    ],
    "wof:name":"Karacaoren",
    "wof:placetype":"locality"
},
  "geometry": {"coordinates":[30.10736,38.80201],"type":"Point"}
}