{
  "type": "Feature",
  "properties": {
    "gn:admin1_code":"19.0",
    "gn:asciiname":"Mehmetaliciftligi",
    "gn:country_code":"TR",
    "gn:dem":745,
    "gn:feature_class":"P",
    "gn:feature_code":"PPL",
    "gn:name":"Mehmetali\u00e7iftli\u011fi",
    "gn:population":0,
    "gn:timezone":"Europe/Istanbul",
    "iso:country":"TR",
    "wof:name":"Mehmetaliciftligi",
    "wof:placetype":"locality"
},
  "geometry": {"coordinates":[34.27372,40.43041],"type":"Point"}
}