{
  "type": "Feature",
  "properties": {
    "gn:admin1_code":"63",
    "gn:asciiname":"Saribal",
    "gn:country_code":"TR",
    "gn:dem":735,
    "gn:feature_class":"P",
    "gn:feature_code":"PPL",
    "gn:name":"Sar\u0131bal",
    "gn:population":0,
    "gn:timezone":"Europe/Istanbul",
    "iso:country":"TR",
    "name:und_x_variant":[
        "Celabder",
        "\u00c7alapd\u0131r",
        "Sar\u0131bal"
    ],
    "wof:name":"Saribal",
    "wof:placetype":"locality"
},
  "geometry": {"coordinates":[39.59124,37.36357],"type":"Point"}
}