{
  "type": "Feature",
  "properties": {
    "gn:admin1_code":"13",
    "gn:asciiname":"Alatoprak",
    "gn:country_code":"TR",
    "gn:dem":1450,
    "gn:feature_class":"P",
    "gn:feature_code":"PPL",
    "gn:name":"Alatoprak",
    "gn:population":0,
    "gn:timezone":"Europe/Istanbul",
    "iso:country":"TR",
    "name:und_x_variant":[
        "Salansor",
        "Salansur",
        "Salansar",
        "Alatoprak"
    ],
    "wof:name":"Alatoprak",
    "wof:placetype":"locality"
},
  "geometry": {"coordinates":[41.82042,38.42204],"type":"Point"}
}