{
  "type": "Feature",
  "properties": {
    "gn:admin1_code":"81",
    "gn:asciiname":"Narlioren",
    "gn:country_code":"TR",
    "gn:dem":59,
    "gn:feature_class":"P",
    "gn:feature_code":"PPL",
    "gn:name":"Narl\u0131\u00f6ren",
    "gn:population":0,
    "gn:timezone":"Europe/Istanbul",
    "iso:country":"TR",
    "name:deu_x_preferred":[
        "Narl\u0131\u00f6ren"
    ],
    "name:msa_x_preferred":[
        "Narl\u0131\u00f6ren"
    ],
    "name:tur_x_preferred":[
        "Narl\u0131\u00f6ren"
    ],
    "name:vie_x_preferred":[
        "Narl\u0131\u00f6ren"
    ],
    "wof:name":"Narlioren",
    "wof:placetype":"locality"
},
  "geometry": {"coordinates":[35.83029000000001,36.87347000000001],"type":"Point"}
}