{
  "type": "Feature",
  "properties": {
    "gn:admin1_code":"79.0",
    "gn:asciiname":"Yagbasan",
    "gn:country_code":"TR",
    "gn:dem":1008,
    "gn:feature_class":"P",
    "gn:feature_code":"PPL",
    "gn:name":"Ya\u011fbasan",
    "gn:population":0,
    "gn:timezone":"Europe/Istanbul",
    "iso:country":"TR",
    "name:und_x_variant":[
        "Yakuphasan",
        "Ya\u011fbasan"
    ],
    "wof:name":"Yagbasan",
    "wof:placetype":"locality"
},
  "geometry": {"coordinates":[33.62608,40.09301],"type":"Point"}
}