{
  "type": "Feature",
  "properties": {
    "gn:admin1_code":"87",
    "gn:asciiname":"Pinyaller",
    "gn:country_code":"TR",
    "gn:dem":240,
    "gn:feature_class":"P",
    "gn:feature_code":"PPL",
    "gn:name":"Pinyaller",
    "gn:population":0,
    "gn:timezone":"Europe/Istanbul",
    "iso:country":"TR",
    "wof:name":"Pinyaller",
    "wof:placetype":"locality"
},
  "geometry": {"coordinates":[32.44226,41.53171],"type":"Point"}
}