{
  "type": "Feature",
  "properties": {
    "gn:admin1_code":"81.0",
    "gn:asciiname":"Sagdicli",
    "gn:country_code":"TR",
    "gn:dem":14,
    "gn:feature_class":"P",
    "gn:feature_code":"PPL",
    "gn:name":"Sa\u011fd\u0131\u00e7l\u0131",
    "gn:population":0,
    "gn:timezone":"Europe/Istanbul",
    "iso:country":"TR",
    "wof:name":"Sagdicli",
    "wof:placetype":"locality"
},
  "geometry": {"coordinates":[35.44279,36.84475],"type":"Point"}
}