{
  "type": "Feature",
  "properties": {
    "gn:admin1_code":"71",
    "gn:asciiname":"Aladag",
    "gn:country_code":"TR",
    "gn:dem":948,
    "gn:feature_class":"P",
    "gn:feature_code":"PPL",
    "gn:name":"Alada\u011f",
    "gn:population":0,
    "gn:timezone":"Europe/Istanbul",
    "iso:country":"TR",
    "name:und_x_variant":[
        "Bademli",
        "Alada\u011f"
    ],
    "wof:name":"Aladag",
    "wof:placetype":"locality"
},
  "geometry": {"coordinates":[32.6645,37.02284],"type":"Point"}
}