{
  "type": "Feature",
  "properties": {
    "gn:admin1_code":"78",
    "gn:asciiname":"Cavuspinari",
    "gn:country_code":"TR",
    "gn:dem":1104,
    "gn:feature_class":"P",
    "gn:feature_code":"PPL",
    "gn:name":"\u00c7avu\u015fp\u0131nar\u0131",
    "gn:population":0,
    "gn:timezone":"Europe/Istanbul",
    "iso:country":"TR",
    "name:und_x_variant":[
        "Fideric",
        "\u00c7avu\u015fp\u0131nar\u0131"
    ],
    "wof:name":"Cavuspinari",
    "wof:placetype":"locality"
},
  "geometry": {"coordinates":[33.14773,37.12983],"type":"Point"}
}