{
  "type": "Feature",
  "properties": {
    "gn:admin1_code":"24",
    "gn:asciiname":"Cilesiz",
    "gn:country_code":"TR",
    "gn:dem":1215,
    "gn:feature_class":"P",
    "gn:feature_code":"PPL",
    "gn:name":"\u00c7ilesiz",
    "gn:population":0,
    "gn:timezone":"Europe/Istanbul",
    "iso:country":"TR",
    "name:und_x_variant":[
        "Tepte",
        "\u00c7ilesiz"
    ],
    "wof:name":"Cilesiz",
    "wof:placetype":"locality"
},
  "geometry": {"coordinates":[38.52253,39.5391],"type":"Point"}
}