{
  "type": "Feature",
  "properties": {
    "gn:admin1_code":"20",
    "gn:asciiname":"Esenkoy",
    "gn:country_code":"TR",
    "gn:dem":1022,
    "gn:feature_class":"P",
    "gn:feature_code":"PPL",
    "gn:name":"Esenk\u00f6y",
    "gn:population":0,
    "gn:timezone":"Europe/Istanbul",
    "iso:country":"TR",
    "name:tur_x_preferred":[
        "Esenk\u00f6y"
    ],
    "name:tur_x_variant":[
        "Beyk\u00f6y",
        "Esen"
    ],
    "wof:name":"Esenkoy",
    "wof:placetype":"locality"
},
  "geometry": {"coordinates":[29.9153,39.21428],"type":"Point"}
}