{
  "type": "Feature",
  "properties": {
    "gn:admin1_code":"61.0",
    "gn:asciiname":"Karacam",
    "gn:country_code":"TR",
    "gn:dem":1040,
    "gn:feature_class":"P",
    "gn:feature_code":"PPL",
    "gn:name":"Kara\u00e7am",
    "gn:population":0,
    "gn:timezone":"Europe/Istanbul",
    "iso:country":"TR",
    "name:und_x_variant":[
        "Karacakaya",
        "Kamala\u00e7",
        "Kara\u00e7am"
    ],
    "wof:name":"Karacam",
    "wof:placetype":"locality"
},
  "geometry": {"coordinates":[40.21464,40.59455],"type":"Point"}
}