{
  "type": "Feature",
  "properties": {
    "iso:country":"TR",
    "name:eng_x_preferred":[
        "Gollu"
    ],
    "name:tur_x_preferred":[
        "G\u00f6ll\u00fc"
    ],
    "wof:name":"Gollu",
    "wof:placetype":"neighbourhood"
},
  "geometry": {"coordinates":[29.27058022769464,41.17486996166517],"type":"Point"}
}