{
  "type": "Feature",
  "properties": {
    "iso:country":"TR",
    "qs:name":"Habibler",
    "qs:name_adm0":"Turkey",
    "qs:name_adm1":"Antalya",
    "qs:photos":64,
    "qs:photos_1k":13,
    "qs:photos_9k":1,
    "qs:photos_9r":2,
    "qs:photos_all":64,
    "qs:photos_sr":2,
    "qs:placetype":"Town",
    "qs:pop_sr":"0",
    "wof:name":"Habibler",
    "wof:placetype":"locality"
},
  "geometry": {"coordinates":[30.726893,36.963309],"type":"Point"}
}