{
  "type": "Feature",
  "properties": {
    "gn:admin1_code":"66",
    "gn:asciiname":"Karabacak",
    "gn:country_code":"TR",
    "gn:dem":1172,
    "gn:feature_class":"P",
    "gn:feature_code":"PPL",
    "gn:name":"Karabacak",
    "gn:population":0,
    "gn:timezone":"Europe/Istanbul",
    "iso:country":"TR",
    "wof:name":"Karabacak",
    "wof:placetype":"locality"
},
  "geometry": {"coordinates":[35.1921,39.48326],"type":"Point"}
}