{
  "type": "Feature",
  "properties": {
    "iso:country":"TR",
    "name:eng_x_preferred":[
        "Mehmet Akif"
    ],
    "name:tur_x_preferred":[
        "Mehmet Akif"
    ],
    "wof:name":"Mehmet Akif",
    "wof:placetype":"neighbourhood"
},
  "geometry": {"coordinates":[29.13879398726873,41.0085379853801],"type":"Point"}
}