{
  "type": "Feature",
  "properties": {
    "gn:admin1_code":"52.0",
    "gn:asciiname":"Beyalan",
    "gn:country_code":"TR",
    "gn:dem":1482,
    "gn:feature_class":"P",
    "gn:feature_code":"PPL",
    "gn:name":"Beyalan",
    "gn:population":0,
    "gn:timezone":"Europe/Istanbul",
    "iso:country":"TR",
    "name:und_x_variant":[
        "Beyalan Yaylas\u0131"
    ],
    "wof:name":"Beyalan",
    "wof:placetype":"locality"
},
  "geometry": {"coordinates":[37.98333,40.71667],"type":"Point"}
}