{
  "type": "Feature",
  "properties": {
    "gn:country":"TR",
    "gn:fcode":"PPL",
    "gn:pop":2137,
    "iso:country":"TR",
    "qs:name":"Marmara",
    "qs:name_adm0":"Turkey",
    "qs:name_adm1":"Bal\u0131kesir",
    "qs:photos":142,
    "qs:photos_1k":29,
    "qs:photos_9k":1,
    "qs:photos_9r":3,
    "qs:photos_all":142,
    "qs:photos_sr":3,
    "qs:placetype":"Town",
    "qs:pop_sr":"4",
    "wd:wordcount":218,
    "wof:name":"Marmara",
    "wof:placetype":"locality",
    "wof:population":2137
},
  "geometry": {"coordinates":[27.55541,40.58633],"type":"Point"}
}