{
  "type": "Feature",
  "properties": {
    "gn:admin1_code":"45",
    "gn:asciiname":"Ayanlar",
    "gn:country_code":"TR",
    "gn:dem":254,
    "gn:feature_class":"P",
    "gn:feature_code":"PPL",
    "gn:name":"Ayanlar",
    "gn:population":0,
    "gn:timezone":"Europe/Istanbul",
    "iso:country":"TR",
    "name:tur_x_preferred":[
        "Ayanlar"
    ],
    "wof:name":"Ayanlar",
    "wof:placetype":"locality"
},
  "geometry": {"coordinates":[28.04347000000001,38.69733],"type":"Point"}
}