{
  "type": "Feature",
  "properties": {
    "gn:admin1_code":"20",
    "gn:asciiname":"Hayrettinkoy",
    "gn:country_code":"TR",
    "gn:dem":1479,
    "gn:feature_class":"P",
    "gn:feature_code":"PPL",
    "gn:name":"Hayrettink\u00f6y",
    "gn:population":0,
    "gn:timezone":"Europe/Istanbul",
    "iso:country":"TR",
    "name:tur_x_preferred":[
        "Hayrettink\u00f6y"
    ],
    "name:tur_x_variant":[
        "Hayrettin"
    ],
    "wof:name":"Hayrettinkoy",
    "wof:placetype":"locality"
},
  "geometry": {"coordinates":[29.65597,37.94633],"type":"Point"}
}