{
  "type": "Feature",
  "properties": {
    "gn:admin1_code":"62",
    "gn:asciiname":"Karagoz",
    "gn:country_code":"TR",
    "gn:dem":1888,
    "gn:feature_class":"P",
    "gn:feature_code":"PPL",
    "gn:name":"Karag\u00f6z",
    "gn:population":0,
    "gn:timezone":"Europe/Istanbul",
    "iso:country":"TR",
    "name:tur_x_preferred":[
        "Karag\u00f6z"
    ],
    "wof:name":"Karagoz",
    "wof:placetype":"locality"
},
  "geometry": {"coordinates":[39.68328,39.44473],"type":"Point"}
}