{
  "type": "Feature",
  "properties": {
    "gn:admin1_code":"53.0",
    "gn:asciiname":"Ciftlikkoy",
    "gn:country_code":"TR",
    "gn:dem":273,
    "gn:feature_class":"P",
    "gn:feature_code":"PPL",
    "gn:name":"\u00c7iftlikk\u00f6y",
    "gn:population":0,
    "gn:timezone":"Europe/Istanbul",
    "iso:country":"TR",
    "name:tur_x_preferred":[
        "\u00c7iftlikk\u00f6y"
    ],
    "wof:name":"Ciftlikkoy",
    "wof:placetype":"locality"
},
  "geometry": {"coordinates":[40.37808,40.98792],"type":"Point"}
}