{
  "type": "Feature",
  "properties": {
    "gn:admin1_code":"12",
    "gn:asciiname":"Leabasan",
    "gn:country_code":"TR",
    "gn:dem":1229,
    "gn:feature_class":"P",
    "gn:feature_code":"PPL",
    "gn:name":"Leabasan",
    "gn:population":0,
    "gn:timezone":"Europe/Istanbul",
    "iso:country":"TR",
    "wof:name":"Leabasan",
    "wof:placetype":"locality"
},
  "geometry": {"coordinates":[40.61667,38.73333],"type":"Point"}
}