{
  "type": "Feature",
  "properties": {
    "gn:admin1_code":"25",
    "gn:asciiname":"Marufkoy",
    "gn:country_code":"TR",
    "gn:dem":1556,
    "gn:feature_class":"P",
    "gn:feature_code":"PPL",
    "gn:name":"Marufk\u00f6y",
    "gn:population":0,
    "gn:timezone":"Europe/Istanbul",
    "iso:country":"TR",
    "name:tur_x_preferred":[
        "Marufk\u00f6y"
    ],
    "name:und_x_variant":[
        "Muarif",
        "Maruf"
    ],
    "wof:name":"Marufkoy",
    "wof:placetype":"locality"
},
  "geometry": {"coordinates":[41.91372,39.30893],"type":"Point"}
}