{
  "type": "Feature",
  "properties": {
    "gn:admin1_code":"32",
    "gn:asciiname":"Elbeyli",
    "gn:country_code":"TR",
    "gn:dem":1310,
    "gn:feature_class":"P",
    "gn:feature_code":"PPL",
    "gn:name":"Elbeyli",
    "gn:population":0,
    "gn:timezone":"Europe/Istanbul",
    "iso:country":"TR",
    "wof:name":"Elbeyli",
    "wof:placetype":"locality"
},
  "geometry": {"coordinates":[34.01667,36.69665],"type":"Point"}
}