{
  "type": "Feature",
  "properties": {
    "gn:admin1_code":"32",
    "gn:asciiname":"Elbeyli",
    "gn:country_code":"TR",
    "gn:dem":1310,
    "gn:feature_class":"P",
    "gn:feature_code":"PPL",
    "gn:name":"Elbeyli",
    "gn:population":0,
    "gn:timezone":"Europe/Istanbul",
    "iso:country":"TR",
    "name:aze_x_preferred":[
        "Elbeyli"
    ],
    "name:ceb_x_preferred":[
        "Elbeyli \u0130l\u00e7esi"
    ],
    "name:deu_x_preferred":[
        "Elbeyli"
    ],
    "name:epo_x_preferred":[
        "Elbeyli"
    ],
    "name:fra_x_preferred":[
        "Elbeyli"
    ],
    "name:kur_x_preferred":[
        "Eliy\u00ea Mentar\u00ea"
    ],
    "name:mrj_x_preferred":[
        "\u042d\u043b\u0431\u0435\u0439\u043b\u0438"
    ],
    "name:msa_x_preferred":[
        "Elbeyli"
    ],
    "name:nor_x_preferred":[
        "Elbeyli"
    ],
    "name:pnb_x_preferred":[
        "\u0636\u0644\u0639 \u0627\u0644\u0628\u06cc\u0644\u06cc"
    ],
    "name:rus_x_preferred":[
        "\u042d\u043b\u0431\u0435\u0439\u043b\u0438"
    ],
    "name:sco_x_preferred":[
        "Elbeyli"
    ],
    "name:swa_x_preferred":[
        "Elbeyli"
    ],
    "name:tur_x_preferred":[
        "Elbeyli"
    ],
    "name:urd_x_preferred":[
        "\u0627\u0644 \u0628\u06d2\u0644\u06cc"
    ],
    "name:vie_x_preferred":[
        "Elbeyli"
    ],
    "wof:name":"Elbeyli",
    "wof:placetype":"locality"
},
  "geometry": {"coordinates":[34.01667,36.69665],"type":"Point"}
}