{
  "type": "Feature",
  "properties": {
    "gn:admin1_code":"37.0",
    "gn:asciiname":"Omerhani",
    "gn:country_code":"TR",
    "gn:dem":1150,
    "gn:feature_class":"P",
    "gn:feature_code":"PPL",
    "gn:name":"\u00d6merhan\u0131",
    "gn:population":0,
    "gn:timezone":"Europe/Istanbul",
    "iso:country":"TR",
    "wof:name":"Omerhani",
    "wof:placetype":"locality"
},
  "geometry": {"coordinates":[34.21667,41.26667],"type":"Point"}
}