{
  "type": "Feature",
  "properties": {
    "gn:country":"TR",
    "gn:fcode":"PPL",
    "gn:pop":192,
    "iso:country":"TR",
    "name:tur_x_preferred":[
        "G\u00f6kta\u015f"
    ],
    "qs:name":"G\u00f6kta\u015f",
    "qs:photos_9r":0,
    "qs:photos_sr":0,
    "qs:pop_sr":"1",
    "wof:name":"G\u00f6kta\u015f",
    "wof:placetype":"locality",
    "wof:population":192
},
  "geometry": {"coordinates":[39.29028,36.82306],"type":"Point"}
}