{
  "type": "Feature",
  "properties": {
    "gn:admin1_code":"76.0",
    "gn:asciiname":"Yatir",
    "gn:cc2":"TR",
    "gn:country_code":"TR",
    "gn:dem":827,
    "gn:feature_class":"P",
    "gn:feature_code":"PPL",
    "gn:name":"Yat\u0131r",
    "gn:population":0,
    "gn:timezone":"Europe/Istanbul",
    "iso:country":"TR",
    "name:tur_x_preferred":[
        "Yat\u0131r"
    ],
    "name:und_x_variant":[
        "Yatyr"
    ],
    "wof:name":"Yatir",
    "wof:placetype":"locality"
},
  "geometry": {"coordinates":[41.29472,37.8075],"type":"Point"}
}