{
  "type": "Feature",
  "properties": {
    "gn:admin1_code":"23",
    "gn:asciiname":"Karasaz",
    "gn:country_code":"TR",
    "gn:dem":975,
    "gn:feature_class":"P",
    "gn:feature_code":"PPL",
    "gn:name":"Karasaz",
    "gn:population":0,
    "gn:timezone":"Europe/Istanbul",
    "iso:country":"TR",
    "name:kir_x_preferred":[
        "\u041a\u0430\u0440\u0430-\u0421\u0430\u0437"
    ],
    "name:tur_x_preferred":[
        "Karasaz"
    ],
    "name:uzb_x_preferred":[
        "Qora-Soz"
    ],
    "wof:name":"Karasaz",
    "wof:placetype":"locality"
},
  "geometry": {"coordinates":[39.41842000000001,38.57186],"type":"Point"}
}