{
  "type": "Feature",
  "properties": {
    "gn:admin1_code":"93",
    "gn:asciiname":"Hamamustu",
    "gn:country_code":"TR",
    "gn:dem":522,
    "gn:feature_class":"P",
    "gn:feature_code":"PPL",
    "gn:name":"Hamam\u00fcst\u00fc",
    "gn:population":0,
    "gn:timezone":"Europe/Istanbul",
    "iso:country":"TR",
    "wof:name":"Hamamustu",
    "wof:placetype":"locality"
},
  "geometry": {"coordinates":[31.0412,40.74768],"type":"Point"}
}