{
  "type": "Feature",
  "properties": {
    "gn:admin1_code":"45",
    "gn:asciiname":"Malkoca",
    "gn:country_code":"TR",
    "gn:dem":494,
    "gn:feature_class":"P",
    "gn:feature_code":"PPL",
    "gn:name":"Malkoca",
    "gn:population":0,
    "gn:timezone":"Europe/Istanbul",
    "iso:country":"TR",
    "wof:name":"Malkoca",
    "wof:placetype":"locality"
},
  "geometry": {"coordinates":[28.16444000000001,38.80194],"type":"Point"}
}