{
  "type": "Feature",
  "properties": {
    "iso:country":"TR",
    "name:eng_x_preferred":[
        "Kurna"
    ],
    "name:tur_x_preferred":[
        "Kurna"
    ],
    "wof:name":"Kurna",
    "wof:placetype":"neighbourhood"
},
  "geometry": {"coordinates":[29.36478889728244,41.19519024289361],"type":"Point"}
}