{
  "type": "Feature",
  "properties": {
    "gn:admin1_code":"32",
    "gn:asciiname":"Pamucak",
    "gn:country_code":"TR",
    "gn:dem":147,
    "gn:feature_class":"P",
    "gn:feature_code":"PPL",
    "gn:name":"Pamucak",
    "gn:population":0,
    "gn:timezone":"Europe/Istanbul",
    "iso:country":"TR",
    "wof:name":"Pamucak",
    "wof:placetype":"locality"
},
  "geometry": {"coordinates":[33.44459000000001,36.22849],"type":"Point"}
}