{
  "type": "Feature",
  "properties": {
    "iso:country":"TR",
    "wof:name":"Bolluca",
    "wof:placetype":"neighbourhood"
},
  "geometry": {"coordinates":[28.76772586233867,41.19808435008891],"type":"Point"}
}