{
  "type": "Feature",
  "properties": {
    "gn:admin1_code":"19.0",
    "gn:asciiname":"Agaccami",
    "gn:country_code":"TR",
    "gn:dem":1018,
    "gn:feature_class":"P",
    "gn:feature_code":"PPL",
    "gn:name":"A\u011fa\u00e7cami",
    "gn:population":0,
    "gn:timezone":"Europe/Istanbul",
    "iso:country":"TR",
    "name:tur_x_preferred":[
        "A\u011fa\u00e7cami"
    ],
    "wof:name":"Agaccami",
    "wof:placetype":"locality"
},
  "geometry": {"coordinates":[34.6755,40.79853],"type":"Point"}
}