{
  "type": "Feature",
  "properties": {
    "gn:country":"TR",
    "gn:fcode":"PPL",
    "gn:pop":54,
    "iso:country":"TR",
    "name:rus_x_preferred":[
        "Magaradzhikk\u00eby"
    ],
    "name:unk_x_variant":[
        "Ma\u011farac\u0131k K\u00f6y\u00fc"
    ],
    "qs:name":"Ma\u011farac\u0131k",
    "qs:photos_9r":0,
    "qs:photos_sr":0,
    "qs:pop_sr":"1",
    "wof:name":"Ma\u011farac\u0131k",
    "wof:placetype":"locality",
    "wof:population":54
},
  "geometry": {"coordinates":[37.78722,36.97417],"type":"Point"}
}