{
  "type": "Feature",
  "properties": {
    "gn:admin1_code":"37.0",
    "gn:asciiname":"Cebeci",
    "gn:country_code":"TR",
    "gn:dem":1418,
    "gn:feature_class":"P",
    "gn:feature_code":"PPL",
    "gn:name":"Cebeci",
    "gn:population":0,
    "gn:timezone":"Europe/Istanbul",
    "iso:country":"TR",
    "name:tur_x_preferred":[
        "Cebeci"
    ],
    "wof:name":"Cebeci",
    "wof:placetype":"locality"
},
  "geometry": {"coordinates":[34.04239,41.19042],"type":"Point"}
}