{
  "type": "Feature",
  "properties": {
    "gn:admin1_code":"63.0",
    "gn:asciiname":"Buyuk Bardacik",
    "gn:country_code":"TR",
    "gn:dem":543,
    "gn:feature_class":"P",
    "gn:feature_code":"PPL",
    "gn:name":"B\u00fcy\u00fck Bardac\u0131k",
    "gn:population":0,
    "gn:timezone":"Europe/Istanbul",
    "iso:country":"TR",
    "name:tur_x_preferred":[
        "B\u00fcy\u00fck Bardac\u0131k"
    ],
    "name:und_x_variant":[
        "B\u00fcy\u00fckbardac\u0131k"
    ],
    "wof:name":"Buyuk Bardacik",
    "wof:placetype":"locality"
},
  "geometry": {"coordinates":[39.58812,37.0759],"type":"Point"}
}