{
  "type": "Feature",
  "properties": {
    "gn:admin1_code":"89.0",
    "gn:asciiname":"Karahasanlar",
    "gn:country_code":"TR",
    "gn:dem":636,
    "gn:feature_class":"P",
    "gn:feature_code":"PPL",
    "gn:name":"Karahasanlar",
    "gn:population":0,
    "gn:timezone":"Europe/Istanbul",
    "iso:country":"TR",
    "wof:name":"Karahasanlar",
    "wof:placetype":"locality"
},
  "geometry": {"coordinates":[32.58197,40.99783],"type":"Point"}
}