{
  "type": "Feature",
  "properties": {
    "iso:country":"TR",
    "name:cat_x_preferred":[
        "P\u00fcrtela\u015f Hasan Efendi"
    ],
    "name:ceb_x_preferred":[
        "P\u00fcrtela\u015f Hasan Efendi"
    ],
    "name:ces_x_preferred":[
        "P\u00fcrtela\u015f Hasan Efendi"
    ],
    "name:dan_x_preferred":[
        "P\u00fcrtela\u015f Hasan Efendi"
    ],
    "name:deu_x_preferred":[
        "P\u00fcrtela\u015f Hasan Efendi"
    ],
    "name:eng_x_preferred":[
        "P\u00fcrtela\u015f Hasan Efendi"
    ],
    "name:eus_x_preferred":[
        "P\u00fcrtela\u015f Hasan Efendi"
    ],
    "name:fin_x_preferred":[
        "P\u00fcrtela\u015f Hasan Efendi"
    ],
    "name:glg_x_preferred":[
        "P\u00fcrtela\u015f Hasan Efendi"
    ],
    "name:ita_x_preferred":[
        "P\u00fcrtela\u015f Hasan Efendi"
    ],
    "name:nld_x_preferred":[
        "P\u00fcrtela\u015f Hasan Efendi"
    ],
    "name:nno_x_preferred":[
        "P\u00fcrtela\u015f Hasan Efendi"
    ],
    "name:nob_x_preferred":[
        "P\u00fcrtela\u015f Hasan Efendi"
    ],
    "name:oci_x_preferred":[
        "P\u00fcrtela\u015f Hasan Efendi"
    ],
    "name:pol_x_preferred":[
        "P\u00fcrtela\u015f Hasan Efendi"
    ],
    "name:por_x_preferred":[
        "P\u00fcrtela\u015f Hasan Efendi"
    ],
    "name:ron_x_preferred":[
        "P\u00fcrtela\u015f Hasan Efendi"
    ],
    "name:sco_x_preferred":[
        "P\u00fcrtela\u015f Hasan Efendi"
    ],
    "name:slk_x_preferred":[
        "P\u00fcrtela\u015f Hasan Efendi"
    ],
    "name:slv_x_preferred":[
        "P\u00fcrtela\u015f Hasan Efendi"
    ],
    "name:spa_x_preferred":[
        "P\u00fcrtela\u015f Hasan Efendi"
    ],
    "name:swe_x_preferred":[
        "P\u00fcrtela\u015f Hasan Efendi"
    ],
    "name:tgl_x_preferred":[
        "P\u00fcrtela\u015f Hasan Efendi"
    ],
    "name:tur_x_preferred":[
        "P\u00fcrtela\u015f Hasan Efendi"
    ],
    "name:war_x_preferred":[
        "P\u00fcrtela\u015f Hasan Efendi"
    ],
    "wof:name":"Purtelas Hasan Efendi",
    "wof:placetype":"neighbourhood"
},
  "geometry": {"coordinates":[28.98695629420616,41.02979216380393],"type":"Point"}
}