{
  "type": "Feature",
  "properties": {
    "gn:admin1_code":"45",
    "gn:asciiname":"Kizilavlu",
    "gn:country_code":"TR",
    "gn:dem":383,
    "gn:feature_class":"P",
    "gn:feature_code":"PPL",
    "gn:name":"K\u0131z\u0131lavlu",
    "gn:population":0,
    "gn:timezone":"Europe/Istanbul",
    "iso:country":"TR",
    "name:und_x_variant":[
        "K\u0131z\u0131lavlu",
        "K\u0131z\u0131lhavlu"
    ],
    "wof:name":"Kizilavlu",
    "wof:placetype":"locality"
},
  "geometry": {"coordinates":[28.34909,38.57801],"type":"Point"}
}