{
  "type": "Feature",
  "properties": {
    "gn:admin1_code":"20",
    "gn:asciiname":"Vakif",
    "gn:country_code":"TR",
    "gn:dem":984,
    "gn:feature_class":"P",
    "gn:feature_code":"PPL",
    "gn:name":"Vak\u0131f",
    "gn:population":0,
    "gn:timezone":"Europe/Istanbul",
    "iso:country":"TR",
    "name:und_x_variant":[
        "Vak\u0131fk\u00f6y",
        "Vak\u0131f"
    ],
    "wof:name":"Vakif",
    "wof:placetype":"locality"
},
  "geometry": {"coordinates":[28.98291,37.62302],"type":"Point"}
}