{
  "type": "Feature",
  "properties": {
    "gn:admin1_code":"31.0",
    "gn:asciiname":"Konakli",
    "gn:country_code":"TR",
    "gn:dem":155,
    "gn:feature_class":"P",
    "gn:feature_code":"PPL",
    "gn:name":"Konakl\u0131",
    "gn:population":0,
    "gn:timezone":"Europe/Istanbul",
    "iso:country":"TR",
    "name:und_x_variant":[
        "\u00d6zerli",
        "Uzeyirly",
        "\u00dczeyirl\u0131",
        "Konakl\u0131"
    ],
    "wof:name":"Konakli",
    "wof:placetype":"locality"
},
  "geometry": {"coordinates":[36.24946,36.80673],"type":"Point"}
}