{
  "type": "Feature",
  "properties": {
    "gn:admin1_code":"5.0",
    "gn:asciiname":"Findikli",
    "gn:country_code":"TR",
    "gn:dem":421,
    "gn:feature_class":"P",
    "gn:feature_code":"PPL",
    "gn:name":"F\u0131nd\u0131kl\u0131",
    "gn:population":0,
    "gn:timezone":"Europe/Istanbul",
    "iso:country":"TR",
    "wof:name":"Findikli",
    "wof:placetype":"locality"
},
  "geometry": {"coordinates":[35.79372,40.71313],"type":"Point"}
}