{
  "type": "Feature",
  "properties": {
    "gn:admin1_code":"19.0",
    "gn:asciiname":"Abdullah",
    "gn:country_code":"TR",
    "gn:dem":1234,
    "gn:feature_class":"P",
    "gn:feature_code":"PPL",
    "gn:name":"Abdullah",
    "gn:population":0,
    "gn:timezone":"Europe/Istanbul",
    "iso:country":"TR",
    "wof:name":"Abdullah",
    "wof:placetype":"locality"
},
  "geometry": {"coordinates":[34.34647,41.0349],"type":"Point"}
}