{
  "type": "Feature",
  "properties": {
    "gn:admin1_code":"19.0",
    "gn:asciiname":"Abdullah",
    "gn:country_code":"TR",
    "gn:dem":1234,
    "gn:feature_class":"P",
    "gn:feature_code":"PPL",
    "gn:name":"Abdullah",
    "gn:population":0,
    "gn:timezone":"Europe/Istanbul",
    "iso:country":"TR",
    "name:bak_x_preferred":[
        "\u0410\u0431\u0434\u0443\u043b\u043b\u0430"
    ],
    "name:cat_x_preferred":[
        "Abd-Al\u00b7lah"
    ],
    "name:ceb_x_preferred":[
        "Abdullah"
    ],
    "name:che_x_preferred":[
        "\u04c0\u0430\u0431\u0434\u0443\u043b\u043b\u0430\u0445\u04c0"
    ],
    "name:dan_x_preferred":[
        "Abdallah"
    ],
    "name:deu_x_preferred":[
        "Abdullah"
    ],
    "name:fas_x_preferred":[
        "\u0639\u0628\u062f\u0627\u0644\u0644\u0647"
    ],
    "name:heb_x_preferred":[
        "\u05e2\u05d1\u05d3\u05d0\u05dc\u05dc\u05d4"
    ],
    "name:ind_x_preferred":[
        "Abdullah"
    ],
    "name:ita_x_preferred":[
        "Abdullah"
    ],
    "name:jpn_x_preferred":[
        "\u30a2\u30d6\u30c9\u30a5\u30c3\u30e9\u30fc"
    ],
    "name:kaz_x_preferred":[
        "\u0410\u0431\u0434\u0443\u043b\u043b\u0430\u04bb"
    ],
    "name:kor_x_preferred":[
        "\uc555\ub458\ub77c"
    ],
    "name:nld_x_preferred":[
        "Abdullah"
    ],
    "name:por_x_preferred":[
        "Abdullah"
    ],
    "name:rus_x_preferred":[
        "\u0410\u0431\u0434\u0443\u043b\u043b\u0430\u0445"
    ],
    "name:slk_x_preferred":[
        "Abd All\u00e1h"
    ],
    "name:slv_x_preferred":[
        "Abdulah"
    ],
    "name:swe_x_preferred":[
        "Abdallah"
    ],
    "name:tat_x_preferred":[
        "\u0410\u0431\u0434\u0443\u043b\u043b\u0430"
    ],
    "name:tur_x_preferred":[
        "Abdullah"
    ],
    "name:ukr_x_preferred":[
        "\u0410\u0431\u0434\u0443\u043b\u043b\u0430"
    ],
    "name:urd_x_preferred":[
        "\u0639\u0628\u062f \u0627\u0644\u0644\u06c1"
    ],
    "name:zho_x_preferred":[
        "\u963f\u535c\u675c\u62c9"
    ],
    "wof:name":"Abdullah",
    "wof:placetype":"locality"
},
  "geometry": {"coordinates":[34.34647,41.0349],"type":"Point"}
}