{
  "type": "Feature",
  "properties": {
    "gn:admin1_code":"81",
    "gn:asciiname":"Bozguney",
    "gn:country_code":"TR",
    "gn:dem":1490,
    "gn:feature_class":"P",
    "gn:feature_code":"PPL",
    "gn:name":"Bozg\u00fcney",
    "gn:population":0,
    "gn:timezone":"Europe/Istanbul",
    "iso:country":"TR",
    "wof:name":"Bozguney",
    "wof:placetype":"locality"
},
  "geometry": {"coordinates":[36.32444,38.245],"type":"Point"}
}