{
  "type": "Feature",
  "properties": {
    "gn:admin1_code":"45",
    "gn:asciiname":"Sariahmetli",
    "gn:country_code":"TR",
    "gn:dem":530,
    "gn:feature_class":"P",
    "gn:feature_code":"PPL",
    "gn:name":"Sar\u0131ahmetli",
    "gn:population":0,
    "gn:timezone":"Europe/Istanbul",
    "iso:country":"TR",
    "name:tur_x_preferred":[
        "Sar\u0131ahmetli"
    ],
    "wof:name":"Sariahmetli",
    "wof:placetype":"locality"
},
  "geometry": {"coordinates":[27.24654,38.88716],"type":"Point"}
}