{
  "type": "Feature",
  "properties": {
    "gn:admin1_code":"35",
    "gn:asciiname":"Doganbey",
    "gn:country_code":"TR",
    "gn:dem":188,
    "gn:feature_class":"P",
    "gn:feature_code":"PPL",
    "gn:name":"Do\u011fanbey",
    "gn:population":0,
    "gn:timezone":"Europe/Istanbul",
    "iso:country":"TR",
    "name:tur_x_preferred":[
        "Do\u011fanbey Paymal\u0131"
    ],
    "name:und_x_variant":[
        "Ipsil\u0131",
        "Doganbeyli",
        "Ispil",
        "\u0130psil",
        "Do\u011fanbey"
    ],
    "wof:name":"Doganbey",
    "wof:placetype":"locality"
},
  "geometry": {"coordinates":[26.86802,38.0859],"type":"Point"}
}