{
  "type": "Feature",
  "properties": {
    "gn:admin1_code":"07",
    "gn:asciiname":"Tavullar",
    "gn:country_code":"TR",
    "gn:dem":1043,
    "gn:feature_class":"P",
    "gn:feature_code":"PPL",
    "gn:name":"Tavullar",
    "gn:population":0,
    "gn:timezone":"Europe/Istanbul",
    "iso:country":"TR",
    "name:und_x_variant":[
        "Davullar",
        "Tav\u0131llar",
        "Tavullar"
    ],
    "wof:name":"Tavullar",
    "wof:placetype":"locality"
},
  "geometry": {"coordinates":[29.83414,36.66976],"type":"Point"}
}