{
  "type": "Feature",
  "properties": {
    "gn:admin1_code":"63",
    "gn:asciiname":"Egerkiran",
    "gn:cc2":"TR",
    "gn:country_code":"TR",
    "gn:dem":673,
    "gn:feature_class":"P",
    "gn:feature_code":"PPL",
    "gn:name":"E\u011ferk\u0131ran",
    "gn:population":0,
    "gn:timezone":"Europe/Istanbul",
    "iso:country":"TR",
    "name:und_x_variant":[
        "Hatkuru\u00e7",
        "Eyerk\u0131ran",
        "E\u011ferk\u0131ran"
    ],
    "wof:name":"Egerkiran",
    "wof:placetype":"locality"
},
  "geometry": {"coordinates":[39.17139,37.42472],"type":"Point"}
}