{
  "type": "Feature",
  "properties": {
    "gn:admin1_code":"86.0",
    "gn:asciiname":"Akyaka",
    "gn:country_code":"TR",
    "gn:dem":1812,
    "gn:feature_class":"P",
    "gn:feature_code":"PPL",
    "gn:name":"Akyaka",
    "gn:population":0,
    "gn:timezone":"Europe/Istanbul",
    "iso:country":"TR",
    "name:eng_x_preferred":[
        "Akkaya"
    ],
    "name:rus_x_preferred":[
        "\u0410\u043a\u043a\u0430\u044f"
    ],
    "name:tur_x_preferred":[
        "Akyaka"
    ],
    "name:und_x_variant":[
        "Kodishara",
        "Akkaya"
    ],
    "wof:name":"Akyaka",
    "wof:placetype":"locality"
},
  "geometry": {"coordinates":[42.57894,41.08472],"type":"Point"}
}