{
  "type": "Feature",
  "properties": {
    "gn:admin1_code":"66",
    "gn:asciiname":"Cepni",
    "gn:country_code":"TR",
    "gn:dem":927,
    "gn:feature_class":"P",
    "gn:feature_code":"PPL",
    "gn:name":"\u00c7epni",
    "gn:population":0,
    "gn:timezone":"Europe/Istanbul",
    "iso:country":"TR",
    "wof:name":"Cepni",
    "wof:placetype":"locality"
},
  "geometry": {"coordinates":[35.79643,39.9057],"type":"Point"}
}