{
  "type": "Feature",
  "properties": {
    "gn:admin1_code":"61.0",
    "gn:asciiname":"Dikkaya",
    "gn:country_code":"TR",
    "gn:dem":1020,
    "gn:feature_class":"P",
    "gn:feature_code":"PPL",
    "gn:name":"Dikkaya",
    "gn:population":0,
    "gn:timezone":"Europe/Istanbul",
    "iso:country":"TR",
    "name:tur_x_preferred":[
        "Dikkaya"
    ],
    "wof:name":"Dikkaya",
    "wof:placetype":"locality"
},
  "geometry": {"coordinates":[39.49558,40.70312],"type":"Point"}
}