{
  "type": "Feature",
  "properties": {
    "gn:admin1_code":"04",
    "gn:asciiname":"Yayikli",
    "gn:country_code":"TR",
    "gn:dem":1629,
    "gn:feature_class":"P",
    "gn:feature_code":"PPL",
    "gn:name":"Yay\u0131kl\u0131",
    "gn:population":0,
    "gn:timezone":"Europe/Istanbul",
    "iso:country":"TR",
    "name:und_x_variant":[
        "Ohan",
        "Yay\u0131kl\u0131"
    ],
    "wof:name":"Yayikli",
    "wof:placetype":"locality"
},
  "geometry": {"coordinates":[42.82817,39.55269000000001],"type":"Point"}
}