{
  "type": "Feature",
  "properties": {
    "gn:admin1_code":"16.0",
    "gn:asciiname":"Eskisaribey",
    "gn:country_code":"TR",
    "gn:dem":17,
    "gn:feature_class":"P",
    "gn:feature_code":"PPL",
    "gn:name":"Eskisar\u0131bey",
    "gn:population":0,
    "gn:timezone":"Europe/Istanbul",
    "iso:country":"TR",
    "name:tur_x_preferred":[
        "Eskisar\u0131bey"
    ],
    "wof:name":"Eskisaribey",
    "wof:placetype":"locality"
},
  "geometry": {"coordinates":[28.24006,40.13921],"type":"Point"}
}