{
  "type": "Feature",
  "properties": {
    "gn:admin1_code":"43",
    "gn:asciiname":"Saricam",
    "gn:country_code":"TR",
    "gn:dem":946,
    "gn:feature_class":"P",
    "gn:feature_code":"PPL",
    "gn:name":"Sar\u0131\u00e7am",
    "gn:population":0,
    "gn:timezone":"Europe/Istanbul",
    "iso:country":"TR",
    "name:tur_x_preferred":[
        "Sar\u0131\u00e7am"
    ],
    "wof:name":"Saricam",
    "wof:placetype":"locality"
},
  "geometry": {"coordinates":[29.1373,39.04527],"type":"Point"}
}