{
  "type": "Feature",
  "properties": {
    "gn:admin1_code":"58",
    "gn:asciiname":"Asagisazcigaz",
    "gn:country_code":"TR",
    "gn:dem":1422,
    "gn:feature_class":"P",
    "gn:feature_code":"PPL",
    "gn:name":"A\u015fa\u011f\u0131sazc\u0131\u011faz",
    "gn:population":0,
    "gn:timezone":"Europe/Istanbul",
    "iso:country":"TR",
    "name:und_x_variant":[
        "A\u015fa\u011f\u0131 Sazca\u011f\u0131z",
        "A\u015fa\u011f\u0131sazc\u0131\u011faz"
    ],
    "wof:name":"Asagisazcigaz",
    "wof:placetype":"locality"
},
  "geometry": {"coordinates":[37.31436,38.79526],"type":"Point"}
}