{
  "type": "Feature",
  "properties": {
    "gn:country":"TR",
    "gn:fcode":"PPL",
    "gn:pop":670,
    "iso:country":"TR",
    "name:tur_x_preferred":[
        "Yukar\u0131 Balc\u0131lar"
    ],
    "qs:name":"Yukar\u0131balc\u0131lar",
    "qs:photos_9r":0,
    "qs:photos_sr":0,
    "qs:pop_sr":"2",
    "wof:name":"Yukar\u0131balc\u0131lar",
    "wof:placetype":"locality",
    "wof:population":670
},
  "geometry": {"coordinates":[42.61651,37.90754],"type":"Point"}
}