{
  "type": "Feature",
  "properties": {
    "gn:admin1_code":"25.0",
    "gn:asciiname":"Sohturut",
    "gn:country_code":"TR",
    "gn:dem":1771,
    "gn:feature_class":"P",
    "gn:feature_code":"PPL",
    "gn:name":"Sohturut",
    "gn:population":0,
    "gn:timezone":"Europe/Istanbul",
    "iso:country":"TR",
    "wof:name":"Sohturut",
    "wof:placetype":"locality"
},
  "geometry": {"coordinates":[41.45,40.41667],"type":"Point"}
}