{
  "type": "Feature",
  "properties": {
    "gn:admin1_code":"87",
    "gn:asciiname":"Yenihamidiye",
    "gn:country_code":"TR",
    "gn:dem":62,
    "gn:feature_class":"P",
    "gn:feature_code":"PPL",
    "gn:name":"Yenihamidiye",
    "gn:population":0,
    "gn:timezone":"Europe/Istanbul",
    "iso:country":"TR",
    "wof:name":"Yenihamidiye",
    "wof:placetype":"locality"
},
  "geometry": {"coordinates":[32.3371,41.49381],"type":"Point"}
}