{
  "type": "Feature",
  "properties": {
    "gn:admin1_code":"87",
    "gn:asciiname":"Yenihamidiye",
    "gn:country_code":"TR",
    "gn:dem":62,
    "gn:feature_class":"P",
    "gn:feature_code":"PPL",
    "gn:name":"Yenihamidiye",
    "gn:population":0,
    "gn:timezone":"Europe/Istanbul",
    "iso:country":"TR",
    "name:ceb_x_preferred":[
        "Yenihamidiye"
    ],
    "name:msa_x_preferred":[
        "Yenihamidiye"
    ],
    "name:tur_x_preferred":[
        "Yenihamidiye"
    ],
    "name:urd_x_preferred":[
        "\u06cc\u0646\u06be\u0645\u062f\u06cc\u06d2 "
    ],
    "name:vie_x_preferred":[
        "Yenihamidiye"
    ],
    "wof:name":"Yenihamidiye",
    "wof:placetype":"locality"
},
  "geometry": {"coordinates":[32.3371,41.49381],"type":"Point"}
}