{
  "type": "Feature",
  "properties": {
    "gn:admin1_code":"44.0",
    "gn:asciiname":"Akusagi",
    "gn:country_code":"TR",
    "gn:dem":833,
    "gn:feature_class":"P",
    "gn:feature_code":"PPL",
    "gn:name":"Aku\u015fa\u011f\u0131",
    "gn:population":0,
    "gn:timezone":"Europe/Istanbul",
    "iso:country":"TR",
    "wof:name":"Akusagi",
    "wof:placetype":"locality"
},
  "geometry": {"coordinates":[38.4316,38.79149],"type":"Point"}
}