{
  "type": "Feature",
  "properties": {
    "gn:country":"TR",
    "gn:fcode":"PPL",
    "gn:population":119,
    "iso:country":"TR",
    "name:ceb_x_preferred":[
        "Pars"
    ],
    "name:deu_x_preferred":[
        "Pars"
    ],
    "name:fas_x_preferred":[
        "\u067e\u0627\u0631\u0633"
    ],
    "name:fra_x_preferred":[
        "Pars"
    ],
    "name:kur_x_preferred":[
        "Pars"
    ],
    "name:lat_x_preferred":[
        "Pars"
    ],
    "name:tur_x_preferred":[
        "Pars"
    ],
    "name:und_x_variant":[
        "Paris"
    ],
    "qs:name":"Pars",
    "qs:photos_9r":0,
    "qs:photos_sr":0,
    "qs:pop_sr":"1",
    "wd:wordcount":150,
    "wof:name":"Pars",
    "wof:placetype":"locality",
    "wof:population":119
},
  "geometry": {"coordinates":[42.09083,37.77306],"type":"Point"}
}