{
  "type": "Feature",
  "properties": {
    "gn:country":"TR",
    "gn:fcode":"PPL",
    "gn:pop":119,
    "iso:country":"TR",
    "name:unk_x_variant":[
        "Paris"
    ],
    "qs:name":"Pars",
    "qs:photos_9r":0,
    "qs:photos_sr":0,
    "qs:pop_sr":"1",
    "wd:wordcount":150,
    "wof:name":"Pars",
    "wof:placetype":"locality",
    "wof:population":119
},
  "geometry": {"coordinates":[42.09083,37.77306],"type":"Point"}
}