{
  "type": "Feature",
  "properties": {
    "gn:admin1_code":"14.0",
    "gn:asciiname":"Saraycik",
    "gn:country_code":"TR",
    "gn:dem":892,
    "gn:feature_class":"P",
    "gn:feature_code":"PPL",
    "gn:name":"Sarayc\u0131k",
    "gn:population":0,
    "gn:timezone":"Europe/Istanbul",
    "iso:country":"TR",
    "name:und_x_variant":[
        "A\u015fa\u011f\u0131 Sarayc\u0131k",
        "Sarayc\u0131k"
    ],
    "wof:name":"Saraycik",
    "wof:placetype":"locality"
},
  "geometry": {"coordinates":[31.7409,40.73151],"type":"Point"}
}