{
  "type": "Feature",
  "properties": {
    "gn:admin1_code":"13.0",
    "gn:asciiname":"Kanatli",
    "gn:country_code":"TR",
    "gn:dem":2160,
    "gn:feature_class":"P",
    "gn:feature_code":"PPL",
    "gn:name":"Kanatl\u0131",
    "gn:population":0,
    "gn:timezone":"Europe/Istanbul",
    "iso:country":"TR",
    "name:tur_x_preferred":[
        "Kanatl\u0131"
    ],
    "wof:name":"Kanatli",
    "wof:placetype":"locality"
},
  "geometry": {"coordinates":[42.56464,38.19576],"type":"Point"}
}