{
  "type": "Feature",
  "properties": {
    "gn:admin1_code":"43",
    "gn:asciiname":"Avlagi",
    "gn:country_code":"TR",
    "gn:dem":1093,
    "gn:feature_class":"P",
    "gn:feature_code":"PPL",
    "gn:name":"Avla\u011f\u0131",
    "gn:population":0,
    "gn:timezone":"Europe/Istanbul",
    "iso:country":"TR",
    "wof:name":"Avlagi",
    "wof:placetype":"locality"
},
  "geometry": {"coordinates":[29.85,39.16667],"type":"Point"}
}