{
  "type": "Feature",
  "properties": {
    "gn:admin1_code":"48",
    "gn:asciiname":"Camurlar",
    "gn:country_code":"TR",
    "gn:dem":555,
    "gn:feature_class":"P",
    "gn:feature_code":"PPL",
    "gn:name":"\u00c7amurlar",
    "gn:population":0,
    "gn:timezone":"Europe/Istanbul",
    "iso:country":"TR",
    "name:tur_x_preferred":[
        "\u00c7amurlar"
    ],
    "wof:name":"Camurlar",
    "wof:placetype":"locality"
},
  "geometry": {"coordinates":[28.17046,37.44747],"type":"Point"}
}