{
  "type": "Feature",
  "properties": {
    "gn:admin1_code":"60.0",
    "gn:asciiname":"Kavunluk",
    "gn:country_code":"TR",
    "gn:dem":1134,
    "gn:feature_class":"P",
    "gn:feature_code":"PPL",
    "gn:name":"Kavunluk",
    "gn:population":0,
    "gn:timezone":"Europe/Istanbul",
    "iso:country":"TR",
    "wof:name":"Kavunluk",
    "wof:placetype":"locality"
},
  "geometry": {"coordinates":[36.34927,40.03206],"type":"Point"}
}