{
  "type": "Feature",
  "properties": {
    "gn:admin1_code":"37.0",
    "gn:asciiname":"Kizilorencik",
    "gn:country_code":"TR",
    "gn:dem":944,
    "gn:feature_class":"P",
    "gn:feature_code":"PPL",
    "gn:name":"K\u0131z\u0131l\u00f6rencik",
    "gn:population":0,
    "gn:timezone":"Europe/Istanbul",
    "iso:country":"TR",
    "name:und_x_variant":[
        "K\u0131z\u0131l\u00f6rencik",
        "\u00d6rencik"
    ],
    "wof:name":"Kizilorencik",
    "wof:placetype":"locality"
},
  "geometry": {"coordinates":[33.57384,41.49133],"type":"Point"}
}