{
  "type": "Feature",
  "properties": {
    "gn:admin1_code":"17.0",
    "gn:asciiname":"Kepekli",
    "gn:country_code":"TR",
    "gn:dem":126,
    "gn:feature_class":"P",
    "gn:feature_code":"PPL",
    "gn:name":"Kepekli",
    "gn:population":0,
    "gn:timezone":"Europe/Istanbul",
    "iso:country":"TR",
    "wof:name":"Kepekli",
    "wof:placetype":"locality"
},
  "geometry": {"coordinates":[27.50356,40.27361],"type":"Point"}
}