{
  "type": "Feature",
  "properties": {
    "gn:admin1_code":"78",
    "gn:asciiname":"Lale",
    "gn:country_code":"TR",
    "gn:dem":1499,
    "gn:feature_class":"P",
    "gn:feature_code":"PPL",
    "gn:name":"Lale",
    "gn:population":0,
    "gn:timezone":"Europe/Istanbul",
    "iso:country":"TR",
    "name:ceb_x_preferred":[
        "Lale"
    ],
    "name:deu_x_preferred":[
        "Lale"
    ],
    "name:fra_x_preferred":[
        "Lale"
    ],
    "name:glg_x_preferred":[
        "Lale"
    ],
    "name:swe_x_preferred":[
        "Lale"
    ],
    "name:tur_x_preferred":[
        "Lale"
    ],
    "name:und_x_variant":[
        "Lalek\u00f6y",
        "L\u00e2le"
    ],
    "wof:name":"Lale",
    "wof:placetype":"locality"
},
  "geometry": {"coordinates":[33.30097,36.99208],"type":"Point"}
}