{
  "type": "Feature",
  "properties": {
    "gn:admin1_code":"13",
    "gn:asciiname":"Derdis",
    "gn:country_code":"TR",
    "gn:dem":2103,
    "gn:feature_class":"P",
    "gn:feature_code":"PPL",
    "gn:name":"Derdis",
    "gn:population":0,
    "gn:timezone":"Europe/Istanbul",
    "iso:country":"TR",
    "name:tur_x_preferred":[
        "\u00d6rg\u00fcl\u00fc"
    ],
    "wof:name":"Derdis",
    "wof:placetype":"locality"
},
  "geometry": {"coordinates":[42.65089,38.23775],"type":"Point"}
}