{
  "type": "Feature",
  "properties": {
    "gn:admin1_code":"8.0",
    "gn:asciiname":"Carsidibi",
    "gn:country_code":"TR",
    "gn:dem":942,
    "gn:feature_class":"P",
    "gn:feature_code":"PPL",
    "gn:name":"\u00c7ar\u015f\u0131dibi",
    "gn:population":0,
    "gn:timezone":"Europe/Istanbul",
    "iso:country":"TR",
    "name:und_x_variant":[
        "\u00c7ar\u015f\u0131dibi",
        "Sebzeli"
    ],
    "wof:name":"Carsidibi",
    "wof:placetype":"locality"
},
  "geometry": {"coordinates":[42.28245,41.3523],"type":"Point"}
}