{
  "type": "Feature",
  "properties": {
    "gn:admin1_code":"19.0",
    "gn:asciiname":"Kabilkisla",
    "gn:country_code":"TR",
    "gn:dem":928,
    "gn:feature_class":"P",
    "gn:feature_code":"PPL",
    "gn:name":"Kabilk\u0131\u015fla",
    "gn:population":0,
    "gn:timezone":"Europe/Istanbul",
    "iso:country":"TR",
    "wof:name":"Kabilkisla",
    "wof:placetype":"locality"
},
  "geometry": {"coordinates":[34.90723,40.2719],"type":"Point"}
}