{
  "type": "Feature",
  "properties": {
    "gn:admin1_code":"68.0",
    "gn:asciiname":"Gumusyayla",
    "gn:country_code":"TR",
    "gn:dem":1352,
    "gn:feature_class":"P",
    "gn:feature_code":"PPL",
    "gn:name":"G\u00fcm\u00fcsyayla",
    "gn:population":0,
    "gn:timezone":"Europe/Istanbul",
    "iso:country":"TR",
    "name:und_x_variant":[
        "Mirek\u00f6y",
        "Mire",
        "G\u00fcm\u00fcsyayla"
    ],
    "wof:name":"Gumusyayla",
    "wof:placetype":"locality"
},
  "geometry": {"coordinates":[32.88674,40.20909],"type":"Point"}
}