{
  "type": "Feature",
  "properties": {
    "gn:admin1_code":"48",
    "gn:asciiname":"Camurkoy",
    "gn:cc2":"TR",
    "gn:country_code":"TR",
    "gn:dem":100,
    "gn:feature_class":"P",
    "gn:feature_code":"PPL",
    "gn:name":"\u00c7amurk\u00f6y",
    "gn:population":0,
    "gn:timezone":"Europe/Istanbul",
    "iso:country":"TR",
    "name:und_x_variant":[
        "\u00c7amur",
        "\u00c7amurk\u00f6y"
    ],
    "wof:name":"Camurkoy",
    "wof:placetype":"locality"
},
  "geometry": {"coordinates":[29.37778,36.54556],"type":"Point"}
}