{
  "type": "Feature",
  "properties": {
    "gn:admin1_code":"55.0",
    "gn:asciiname":"Kurtler",
    "gn:country_code":"TR",
    "gn:dem":2,
    "gn:feature_class":"P",
    "gn:feature_code":"PPL",
    "gn:name":"K\u00fcrtler",
    "gn:population":0,
    "gn:timezone":"Europe/Istanbul",
    "iso:country":"TR",
    "wof:name":"Kurtler",
    "wof:placetype":"locality"
},
  "geometry": {"coordinates":[35.9743,41.71549],"type":"Point"}
}