{
  "type": "Feature",
  "properties": {
    "gn:admin1_code":"20",
    "gn:asciiname":"Dagdibi",
    "gn:country_code":"TR",
    "gn:dem":1256,
    "gn:feature_class":"P",
    "gn:feature_code":"PPL",
    "gn:name":"Da\u011fdibi",
    "gn:population":0,
    "gn:timezone":"Europe/Istanbul",
    "iso:country":"TR",
    "name:tur_x_preferred":[
        "Da\u011fdibi"
    ],
    "wof:name":"Dagdibi",
    "wof:placetype":"locality"
},
  "geometry": {"coordinates":[29.2841,37.08084],"type":"Point"}
}