{
  "type": "Feature",
  "properties": {
    "gn:admin1_code":"71",
    "gn:asciiname":"Dutlu",
    "gn:country_code":"TR",
    "gn:dem":1500,
    "gn:feature_class":"P",
    "gn:feature_code":"PPL",
    "gn:name":"Dutlu",
    "gn:population":0,
    "gn:timezone":"Europe/Istanbul",
    "iso:country":"TR",
    "wof:name":"Dutlu",
    "wof:placetype":"locality"
},
  "geometry": {"coordinates":[32.34265,37.2999],"type":"Point"}
}