{
  "type": "Feature",
  "properties": {
    "gn:admin1_code":"23",
    "gn:asciiname":"Tasliyayla",
    "gn:country_code":"TR",
    "gn:dem":1272,
    "gn:feature_class":"P",
    "gn:feature_code":"PPL",
    "gn:name":"Ta\u015fl\u0131yayla",
    "gn:population":0,
    "gn:timezone":"Europe/Istanbul",
    "iso:country":"TR",
    "name:und_x_variant":[
        "Avsiye",
        "Ta\u015fl\u0131yayla",
        "Avsiya"
    ],
    "wof:name":"Tasliyayla",
    "wof:placetype":"locality"
},
  "geometry": {"coordinates":[38.9775,38.38163],"type":"Point"}
}