{
  "type": "Feature",
  "properties": {
    "gn:admin1_code":"81",
    "gn:asciiname":"Corlu",
    "gn:country_code":"TR",
    "gn:dem":445,
    "gn:feature_class":"P",
    "gn:feature_code":"PPL",
    "gn:name":"\u00c7orlu",
    "gn:population":0,
    "gn:timezone":"Europe/Istanbul",
    "iso:country":"TR",
    "name:und_x_variant":[
        "\u00c7orlu",
        "Kayac\u0131"
    ],
    "wof:name":"Corlu",
    "wof:placetype":"locality"
},
  "geometry": {"coordinates":[35.14517,37.32618],"type":"Point"}
}