{
  "type": "Feature",
  "properties": {
    "gn:country":"TR",
    "gn:fcode":"PPL",
    "gn:pop":207,
    "iso:country":"TR",
    "name:tur_x_preferred":[
        "\u00c7ay\u0131ralt\u0131"
    ],
    "qs:name":"\u00c7ay\u0131ralt\u0131",
    "qs:photos_9r":0,
    "qs:photos_sr":0,
    "qs:pop_sr":"2",
    "wof:name":"\u00c7ay\u0131ralt\u0131",
    "wof:placetype":"locality",
    "wof:population":207
},
  "geometry": {"coordinates":[37.00722,36.93444],"type":"Point"}
}