{
  "type": "Feature",
  "properties": {
    "gn:admin1_code":"82.0",
    "gn:asciiname":"Kucukyayla",
    "gn:country_code":"TR",
    "gn:dem":1764,
    "gn:feature_class":"P",
    "gn:feature_code":"PPL",
    "gn:name":"K\u00fc\u00e7\u00fckyayla",
    "gn:population":0,
    "gn:timezone":"Europe/Istanbul",
    "iso:country":"TR",
    "wof:name":"Kucukyayla",
    "wof:placetype":"locality"
},
  "geometry": {"coordinates":[33.47935,40.46446],"type":"Point"}
}