{
  "type": "Feature",
  "properties": {
    "gn:admin1_code":"21",
    "gn:asciiname":"Demirli",
    "gn:country_code":"TR",
    "gn:dem":1060,
    "gn:feature_class":"P",
    "gn:feature_code":"PPL",
    "gn:name":"Demirli",
    "gn:population":0,
    "gn:timezone":"Europe/Istanbul",
    "iso:country":"TR",
    "name:und_x_variant":[
        "Dimirli",
        "D\u00fcm\u00fcrl\u00fc",
        "Demirli"
    ],
    "wof:name":"Demirli",
    "wof:placetype":"locality"
},
  "geometry": {"coordinates":[39.73976,37.86794],"type":"Point"}
}