{
  "type": "Feature",
  "properties": {
    "gn:admin1_code":"90.0",
    "gn:asciiname":"Otekioba",
    "gn:country_code":"TR",
    "gn:dem":906,
    "gn:feature_class":"P",
    "gn:feature_code":"PPL",
    "gn:name":"\u00d6tekioba",
    "gn:population":0,
    "gn:timezone":"Europe/Istanbul",
    "iso:country":"TR",
    "wof:name":"Otekioba",
    "wof:placetype":"locality"
},
  "geometry": {"coordinates":[36.93111,36.95194],"type":"Point"}
}