{
  "type": "Feature",
  "properties": {
    "gn:admin1_code":"58",
    "gn:asciiname":"Eskicubuk",
    "gn:country_code":"TR",
    "gn:dem":1189,
    "gn:feature_class":"P",
    "gn:feature_code":"PPL",
    "gn:name":"Eski\u00e7ubuk",
    "gn:population":0,
    "gn:timezone":"Europe/Istanbul",
    "iso:country":"TR",
    "wof:name":"Eskicubuk",
    "wof:placetype":"locality"
},
  "geometry": {"coordinates":[36.15176,39.23175],"type":"Point"}
}