{
  "type": "Feature",
  "properties": {
    "gn:admin1_code":"49",
    "gn:asciiname":"Yaygin",
    "gn:country_code":"TR",
    "gn:dem":1280,
    "gn:feature_class":"P",
    "gn:feature_code":"PPLA3",
    "gn:name":"Yayg\u0131n",
    "gn:population":0,
    "gn:timezone":"Europe/Istanbul",
    "iso:country":"TR",
    "name:und_x_variant":[
        "Mi\u011fdi",
        "Ziyaret",
        "Yayg\u0131n"
    ],
    "wof:name":"Yaygin",
    "wof:placetype":"locality"
},
  "geometry": {"coordinates":[41.30613,38.89748],"type":"Point"}
}