{
  "type": "Feature",
  "properties": {
    "gn:country":"TR",
    "gn:fcode":"PPL",
    "gn:pop":162,
    "iso:country":"TR",
    "name:unk_x_variant":[
        "\u015e\u00fck\u00fcrali"
    ],
    "qs:name":"Shyukyurali",
    "qs:photos_9r":0,
    "qs:photos_sr":0,
    "qs:pop_sr":"1",
    "wof:name":"Shyukyurali",
    "wof:placetype":"locality",
    "wof:population":162
},
  "geometry": {"coordinates":[39.07361,36.88806],"type":"Point"}
}