{
  "type": "Feature",
  "properties": {
    "gn:admin1_code":"10",
    "gn:asciiname":"Habibler",
    "gn:country_code":"TR",
    "gn:dem":464,
    "gn:feature_class":"P",
    "gn:feature_code":"PPL",
    "gn:name":"Habibler",
    "gn:population":0,
    "gn:timezone":"Europe/Istanbul",
    "iso:country":"TR",
    "name:tur_x_preferred":[
        "Habibler"
    ],
    "wof:name":"Habibler",
    "wof:placetype":"locality"
},
  "geometry": {"coordinates":[27.48703,39.69861],"type":"Point"}
}