{
  "type": "Feature",
  "properties": {
    "gn:admin1_code":"54",
    "gn:asciiname":"Isaret",
    "gn:country_code":"TR",
    "gn:dem":48,
    "gn:feature_class":"P",
    "gn:feature_code":"PPL",
    "gn:name":"\u0130\u015faret",
    "gn:population":0,
    "gn:timezone":"Europe/Istanbul",
    "iso:country":"TR",
    "name:tur_x_preferred":[
        "\u0130\u015faret"
    ],
    "wof:name":"Isaret",
    "wof:placetype":"locality"
},
  "geometry": {"coordinates":[30.40271,41.1093],"type":"Point"}
}