{
  "type": "Feature",
  "properties": {
    "gn:admin1_code":"38",
    "gn:asciiname":"Tekneli",
    "gn:country_code":"TR",
    "gn:dem":1752,
    "gn:feature_class":"P",
    "gn:feature_code":"PPL",
    "gn:name":"Tekneli",
    "gn:population":0,
    "gn:timezone":"Europe/Istanbul",
    "iso:country":"TR",
    "name:und_x_variant":[
        "De\u015ftiye",
        "De\u015ftiya",
        "Tekneli"
    ],
    "wof:name":"Tekneli",
    "wof:placetype":"locality"
},
  "geometry": {"coordinates":[36.5541,38.56882],"type":"Point"}
}