{
  "type": "Feature",
  "properties": {
    "gn:admin1_code":"76.0",
    "gn:asciiname":"Okcu",
    "gn:country_code":"TR",
    "gn:dem":662,
    "gn:feature_class":"P",
    "gn:feature_code":"PPL",
    "gn:name":"Ok\u00e7u",
    "gn:population":0,
    "gn:timezone":"Europe/Istanbul",
    "iso:country":"TR",
    "name:tur_x_preferred":[
        "Ok\u00e7u"
    ],
    "wof:name":"Okcu",
    "wof:placetype":"locality"
},
  "geometry": {"coordinates":[41.09828,37.83981],"type":"Point"}
}