{
  "type": "Feature",
  "properties": {
    "gn:admin1_code":"81",
    "gn:asciiname":"Tahiriye",
    "gn:country_code":"TR",
    "gn:dem":49,
    "gn:feature_class":"P",
    "gn:feature_code":"PPL",
    "gn:name":"Tahiriye",
    "gn:population":0,
    "gn:timezone":"Europe/Istanbul",
    "iso:country":"TR",
    "name:und_x_variant":[
        "Tahriye",
        "Tahiriye"
    ],
    "wof:name":"Tahiriye",
    "wof:placetype":"locality"
},
  "geometry": {"coordinates":[35.53333,36.78333],"type":"Point"}
}