{
  "type": "Feature",
  "properties": {
    "gn:admin1_code":"93",
    "gn:asciiname":"Camlibel",
    "gn:country_code":"TR",
    "gn:dem":768,
    "gn:feature_class":"P",
    "gn:feature_code":"PPL",
    "gn:name":"\u00c7aml\u0131bel",
    "gn:population":0,
    "gn:timezone":"Europe/Istanbul",
    "iso:country":"TR",
    "name:und_x_variant":[
        "\u00c7aml\u0131bel",
        "G\u00f6l\u00e7\u00fck"
    ],
    "wof:name":"Camlibel",
    "wof:placetype":"locality"
},
  "geometry": {"coordinates":[31.02311,40.73288],"type":"Point"}
}