{
  "type": "Feature",
  "properties": {
    "iso:country":"TR",
    "name:eng_x_preferred":[
        "Riva"
    ],
    "name:tur_x_preferred":[
        "\u00c7aya\u011fz\u0131"
    ],
    "wof:name":"Riva",
    "wof:placetype":"neighbourhood"
},
  "geometry": {"coordinates":[29.2178229379661,41.223434989115],"type":"Point"}
}