{
  "type": "Feature",
  "properties": {
    "gn:admin1_code":"03",
    "gn:asciiname":"Alcali",
    "gn:country_code":"TR",
    "gn:dem":1314,
    "gn:feature_class":"P",
    "gn:feature_code":"PPL",
    "gn:name":"Alcal\u0131",
    "gn:population":0,
    "gn:timezone":"Europe/Istanbul",
    "iso:country":"TR",
    "wof:name":"Alcali",
    "wof:placetype":"locality"
},
  "geometry": {"coordinates":[30.61894,38.97083],"type":"Point"}
}