{
  "type": "Feature",
  "properties": {
    "gn:admin1_code":"09",
    "gn:asciiname":"Kuplu Mahallesi",
    "gn:country_code":"TR",
    "gn:dem":823,
    "gn:feature_class":"P",
    "gn:feature_code":"PPL",
    "gn:name":"K\u00fcpl\u00fc Mahallesi",
    "gn:population":0,
    "gn:timezone":"Europe/Istanbul",
    "iso:country":"TR",
    "name:tur_x_preferred":[
        "K\u00fcpl\u00fc Mahallesi"
    ],
    "wof:name":"Kuplu Mahallesi",
    "wof:placetype":"locality"
},
  "geometry": {"coordinates":[28.43549,38.04224],"type":"Point"}
}