{
  "type": "Feature",
  "properties": {
    "gn:admin1_code":"62",
    "gn:asciiname":"Kadisirti",
    "gn:country_code":"TR",
    "gn:dem":1762,
    "gn:feature_class":"P",
    "gn:feature_code":"PPL",
    "gn:name":"Kad\u0131s\u0131rt\u0131",
    "gn:population":0,
    "gn:timezone":"Europe/Istanbul",
    "iso:country":"TR",
    "name:und_x_variant":[
        "Merka\u00e7or Mezraas\u0131",
        "Merka\u00e7or",
        "Kad\u0131s\u0131rt\u0131"
    ],
    "wof:name":"Kadisirti",
    "wof:placetype":"locality"
},
  "geometry": {"coordinates":[39.90545,39.36429],"type":"Point"}
}