{
  "type": "Feature",
  "properties": {
    "gn:admin1_code":"20",
    "gn:asciiname":"Gerali",
    "gn:country_code":"TR",
    "gn:dem":190,
    "gn:feature_class":"P",
    "gn:feature_code":"PPL",
    "gn:name":"Gerali",
    "gn:population":0,
    "gn:timezone":"Europe/Istanbul",
    "iso:country":"TR",
    "name:tur_x_preferred":[
        "Gerali"
    ],
    "name:tur_x_variant":[
        "Gereli"
    ],
    "wof:name":"Gerali",
    "wof:placetype":"locality"
},
  "geometry": {"coordinates":[28.91219,37.90096],"type":"Point"}
}