{
  "type": "Feature",
  "properties": {
    "gn:admin1_code":"72",
    "gn:asciiname":"Harami",
    "gn:country_code":"TR",
    "gn:dem":470,
    "gn:feature_class":"P",
    "gn:feature_code":"PPL",
    "gn:name":"Haram\u0131",
    "gn:population":0,
    "gn:timezone":"Europe/Istanbul",
    "iso:country":"TR",
    "name:tur_x_preferred":[
        "Haram\u0131"
    ],
    "wof:name":"Harami",
    "wof:placetype":"locality"
},
  "geometry": {"coordinates":[40.2432,37.16636],"type":"Point"}
}