{
  "type": "Feature",
  "properties": {
    "gn:admin1_code":"60.0",
    "gn:asciiname":"Arslantas",
    "gn:country_code":"TR",
    "gn:dem":1333,
    "gn:feature_class":"P",
    "gn:feature_code":"PPL",
    "gn:name":"Arslanta\u015f",
    "gn:population":0,
    "gn:timezone":"Europe/Istanbul",
    "iso:country":"TR",
    "name:und_x_variant":[
        "Aslanta\u015f",
        "Arslanta\u015f"
    ],
    "wof:name":"Arslantas",
    "wof:placetype":"locality"
},
  "geometry": {"coordinates":[37.5093,40.24799],"type":"Point"}
}