{
  "type": "Feature",
  "properties": {
    "gn:admin1_code":"80.0",
    "gn:asciiname":"Ozveren",
    "gn:country_code":"TR",
    "gn:dem":1150,
    "gn:feature_class":"P",
    "gn:feature_code":"PPL",
    "gn:name":"\u00d6zveren",
    "gn:population":0,
    "gn:timezone":"Europe/Istanbul",
    "iso:country":"TR",
    "name:und_x_variant":[
        "Urochishche Dekhlabi",
        "Dehlabi",
        "\u00d6zveren"
    ],
    "wof:name":"Ozveren",
    "wof:placetype":"locality"
},
  "geometry": {"coordinates":[42.48333,37.49389],"type":"Point"}
}