{
  "type": "Feature",
  "properties": {
    "gn:admin1_code":"45",
    "gn:asciiname":"Killik",
    "gn:country_code":"TR",
    "gn:dem":727,
    "gn:feature_class":"P",
    "gn:feature_code":"PPL",
    "gn:name":"Killik",
    "gn:population":0,
    "gn:timezone":"Europe/Istanbul",
    "iso:country":"TR",
    "name:tur_x_preferred":[
        "Killik"
    ],
    "wof:name":"Killik",
    "wof:placetype":"locality"
},
  "geometry": {"coordinates":[28.86993,38.70146],"type":"Point"}
}