{
  "type": "Feature",
  "properties": {
    "gn:admin1_code":"16.0",
    "gn:asciiname":"Ermiye",
    "gn:country_code":"TR",
    "gn:dem":82,
    "gn:feature_class":"P",
    "gn:feature_code":"PPL",
    "gn:name":"Ermiye",
    "gn:population":0,
    "gn:timezone":"Europe/Istanbul",
    "iso:country":"TR",
    "name:und_x_variant":[
        "G\u00f6k\u00e7e"
    ],
    "wof:name":"Ermiye",
    "wof:placetype":"locality"
},
  "geometry": {"coordinates":[28.79979,40.24516],"type":"Point"}
}