{
  "type": "Feature",
  "properties": {
    "gn:admin1_code":"13",
    "gn:asciiname":"Caliduzu",
    "gn:country_code":"TR",
    "gn:dem":1834,
    "gn:feature_class":"P",
    "gn:feature_code":"PPL",
    "gn:name":"\u00c7al\u0131d\u00fcz\u00fc",
    "gn:population":0,
    "gn:timezone":"Europe/Istanbul",
    "iso:country":"TR",
    "name:tur_x_preferred":[
        "\u00c7al\u0131d\u00fcz\u00fc"
    ],
    "wof:name":"Caliduzu",
    "wof:placetype":"locality"
},
  "geometry": {"coordinates":[42.26664,38.43436],"type":"Point"}
}