{
  "type": "Feature",
  "properties": {
    "gn:admin1_code":"37.0",
    "gn:asciiname":"Incigez",
    "gn:country_code":"TR",
    "gn:dem":1160,
    "gn:feature_class":"P",
    "gn:feature_code":"PPL",
    "gn:name":"\u0130nci\u011fez",
    "gn:population":0,
    "gn:timezone":"Europe/Istanbul",
    "iso:country":"TR",
    "name:und_x_variant":[
        "\u0130nci\u011fez",
        "K\u00fcrtk\u00f6y"
    ],
    "wof:name":"Incigez",
    "wof:placetype":"locality"
},
  "geometry": {"coordinates":[33.48873,41.25807],"type":"Point"}
}