{
  "type": "Feature",
  "properties": {
    "gn:admin1_code":"17.0",
    "gn:asciiname":"Bakacak",
    "gn:country_code":"TR",
    "gn:dem":42,
    "gn:feature_class":"P",
    "gn:feature_code":"PPLA3",
    "gn:name":"Bakacak",
    "gn:population":0,
    "gn:timezone":"Europe/Istanbul",
    "iso:country":"TR",
    "name:und_x_variant":[
        "\u0130pkaiye",
        "\u00c7erkezbakaca\u011f\u0131",
        "Bakacak"
    ],
    "wof:name":"Bakacak",
    "wof:placetype":"locality"
},
  "geometry": {"coordinates":[27.08317000000001,40.20499],"type":"Point"}
}