{
  "type": "Feature",
  "properties": {
    "gn:admin1_code":"43",
    "gn:asciiname":"Sabuncu",
    "gn:country_code":"TR",
    "gn:dem":963,
    "gn:feature_class":"P",
    "gn:feature_code":"PPLA3",
    "gn:name":"Sabuncu",
    "gn:population":0,
    "gn:timezone":"Europe/Istanbul",
    "iso:country":"TR",
    "name:und_x_variant":[
        "Armutlu",
        "Sabuncup\u0131nar",
        "Armuteli",
        "Armudeli",
        "Sabuncu"
    ],
    "wof:name":"Sabuncu",
    "wof:placetype":"locality"
},
  "geometry": {"coordinates":[30.18813,39.56131],"type":"Point"}
}