{
  "type": "Feature",
  "properties": {
    "gn:admin1_code":"48",
    "gn:asciiname":"Mentese",
    "gn:country_code":"TR",
    "gn:dem":641,
    "gn:feature_class":"P",
    "gn:feature_code":"PPLA2",
    "gn:name":"Mente\u015fe",
    "gn:population":0,
    "gn:timezone":"Europe/Istanbul",
    "iso:country":"TR",
    "name:tur_x_preferred":[
        "Mente\u015fe"
    ],
    "name:tur_x_variant":[
        "\u00c7akallar"
    ],
    "wof:name":"Mentese",
    "wof:placetype":"locality"
},
  "geometry": {"coordinates":[28.26667,37.11667],"type":"Point"}
}