{
  "type": "Feature",
  "properties": {
    "gn:admin1_code":"69.0",
    "gn:asciiname":"Ulukoy",
    "gn:country_code":"TR",
    "gn:dem":1019,
    "gn:feature_class":"P",
    "gn:feature_code":"PPL",
    "gn:name":"Uluk\u00f6y",
    "gn:population":0,
    "gn:timezone":"Europe/Istanbul",
    "iso:country":"TR",
    "name:eng_x_preferred":[
        "Uluk\u00f6y"
    ],
    "name:rus_x_preferred":[
        "\u0423\u043b\u0443\u043a\u0435\u0439"
    ],
    "name:und_x_variant":[
        "Yukar\u0131uluk\u00f6y"
    ],
    "wof:name":"Ulukoy",
    "wof:placetype":"locality"
},
  "geometry": {"coordinates":[39.10185,40.70633],"type":"Point"}
}