{
  "type": "Feature",
  "properties": {
    "iso:country":"TR",
    "name:cat_x_preferred":[
        "Kemanke\u015f Karamustafa Pa\u015fa"
    ],
    "name:ceb_x_preferred":[
        "Kemanke\u015f Karamustafa Pa\u015fa"
    ],
    "name:ces_x_preferred":[
        "Kemanke\u015f Karamustafa Pa\u015fa"
    ],
    "name:dan_x_preferred":[
        "Kemanke\u015f Karamustafa Pa\u015fa"
    ],
    "name:deu_x_preferred":[
        "Kemanke\u015f Karamustafa Pa\u015fa"
    ],
    "name:eng_x_preferred":[
        "Kemanke\u015f Karamustafa Pa\u015fa"
    ],
    "name:eus_x_preferred":[
        "Kemanke\u015f Karamustafa Pa\u015fa"
    ],
    "name:fin_x_preferred":[
        "Kemanke\u015f Karamustafa Pa\u015fa"
    ],
    "name:glg_x_preferred":[
        "Kemanke\u015f Karamustafa Pa\u015fa"
    ],
    "name:ita_x_preferred":[
        "Kemanke\u015f Karamustafa Pa\u015fa"
    ],
    "name:nld_x_preferred":[
        "Kemanke\u015f Karamustafa Pa\u015fa"
    ],
    "name:nno_x_preferred":[
        "Kemanke\u015f Karamustafa Pa\u015fa"
    ],
    "name:nob_x_preferred":[
        "Kemanke\u015f Karamustafa Pa\u015fa"
    ],
    "name:oci_x_preferred":[
        "Kemanke\u015f Karamustafa Pa\u015fa"
    ],
    "name:pol_x_preferred":[
        "Kemanke\u015f Karamustafa Pa\u015fa"
    ],
    "name:por_x_preferred":[
        "Kemanke\u015f Karamustafa Pa\u015fa"
    ],
    "name:ron_x_preferred":[
        "Kemanke\u015f Karamustafa Pa\u015fa"
    ],
    "name:sco_x_preferred":[
        "Kemanke\u015f Karamustafa Pa\u015fa"
    ],
    "name:slk_x_preferred":[
        "Kemanke\u015f Karamustafa Pa\u015fa"
    ],
    "name:slv_x_preferred":[
        "Kemanke\u015f Karamustafa Pa\u015fa"
    ],
    "name:spa_x_preferred":[
        "Kemanke\u015f Karamustafa Pa\u015fa"
    ],
    "name:swe_x_preferred":[
        "Kemanke\u015f Karamustafa Pa\u015fa"
    ],
    "name:tgl_x_preferred":[
        "Kemanke\u015f Karamustafa Pa\u015fa"
    ],
    "name:tur_x_preferred":[
        "Kemanke\u015f Karamustafa Pa\u015fa"
    ],
    "name:war_x_preferred":[
        "Kemanke\u015f Karamustafa Pa\u015fa"
    ],
    "qs:name":"Kemanke\u015f Karamustafa Pa\u015fa",
    "qs:name_adm0":"Turkey",
    "qs:name_adm1":"\u0130stanbul",
    "qs:photos":418,
    "qs:photos_1k":85,
    "qs:photos_9k":2,
    "qs:photos_9r":5,
    "qs:photos_all":418,
    "qs:photos_sr":6,
    "qs:placetype":"Suburb",
    "qs:pop_sr":"0",
    "wof:name":"Kemanke\u015f Karamustafa Pa\u015fa",
    "wof:placetype":"neighbourhood"
},
  "geometry": {"coordinates":[28.979187,41.0240545],"type":"Point"}
}