{
  "type": "Feature",
  "properties": {
    "gn:admin1_code":"31.0",
    "gn:asciiname":"Kandum",
    "gn:country_code":"TR",
    "gn:dem":576,
    "gn:feature_class":"P",
    "gn:feature_code":"PPL",
    "gn:name":"Kandum",
    "gn:population":0,
    "gn:timezone":"Europe/Istanbul",
    "iso:country":"TR",
    "wof:name":"Kandum",
    "wof:placetype":"locality"
},
  "geometry": {"coordinates":[36.16639,35.925],"type":"Point"}
}