{
  "type": "Feature",
  "properties": {
    "gn:admin1_code":"62",
    "gn:asciiname":"Demirci",
    "gn:country_code":"TR",
    "gn:dem":866,
    "gn:feature_class":"P",
    "gn:feature_code":"PPL",
    "gn:name":"Demirci",
    "gn:population":0,
    "gn:timezone":"Europe/Istanbul",
    "iso:country":"TR",
    "name:tur_x_preferred":[
        "Demirci"
    ],
    "wof:name":"Demirci",
    "wof:placetype":"locality"
},
  "geometry": {"coordinates":[39.65277,38.83271],"type":"Point"}
}