{
  "type": "Feature",
  "properties": {
    "gn:admin1_code":"14.0",
    "gn:asciiname":"Yanik",
    "gn:country_code":"TR",
    "gn:dem":1082,
    "gn:feature_class":"P",
    "gn:feature_code":"PPL",
    "gn:name":"Yan\u0131k",
    "gn:population":0,
    "gn:timezone":"Europe/Istanbul",
    "iso:country":"TR",
    "name:und_x_variant":[
        "Orta Mahalle",
        "Ortak\u00f6y",
        "Yan\u0131k"
    ],
    "wof:name":"Yanik",
    "wof:placetype":"locality"
},
  "geometry": {"coordinates":[31.40734,40.58608],"type":"Point"}
}