{
  "type": "Feature",
  "properties": {
    "iso:country":"TR",
    "name:eng_x_preferred":[
        "Mimarsinan"
    ],
    "name:tur_x_preferred":[
        "Mimarsinan"
    ],
    "name:tur_x_variant":[
        "Mimarsinan Silivri"
    ],
    "wof:name":"Mimarsinan",
    "wof:placetype":"neighbourhood"
},
  "geometry": {"coordinates":[28.21054497067118,41.07669146965814],"type":"Point"}
}