{
  "type": "Feature",
  "properties": {
    "gn:admin1_code":"13.0",
    "gn:asciiname":"Guzelli",
    "gn:country_code":"TR",
    "gn:dem":1350,
    "gn:feature_class":"P",
    "gn:feature_code":"PPL",
    "gn:name":"G\u00fczelli",
    "gn:population":0,
    "gn:timezone":"Europe/Istanbul",
    "iso:country":"TR",
    "name:tur_x_preferred":[
        "G\u00fczeleli"
    ],
    "name:tur_x_variant":[
        "G\u00fczelli"
    ],
    "wof:name":"Guzelli",
    "wof:placetype":"locality"
},
  "geometry": {"coordinates":[42.0994,38.65709],"type":"Point"}
}