{
  "type": "Feature",
  "properties": {
    "gn:admin1_code":"45",
    "gn:asciiname":"Canakci",
    "gn:country_code":"TR",
    "gn:dem":1002,
    "gn:feature_class":"P",
    "gn:feature_code":"PPL",
    "gn:name":"\u00c7anak\u00e7\u0131",
    "gn:population":0,
    "gn:timezone":"Europe/Istanbul",
    "iso:country":"TR",
    "name:tur_x_preferred":[
        "\u00c7anak\u00e7\u0131"
    ],
    "wof:name":"Canakci",
    "wof:placetype":"locality"
},
  "geometry": {"coordinates":[28.58997,39.08632],"type":"Point"}
}