{
  "type": "Feature",
  "properties": {
    "gn:admin1_code":"41",
    "gn:asciiname":"Selimkoy",
    "gn:country_code":"TR",
    "gn:dem":151,
    "gn:feature_class":"P",
    "gn:feature_code":"PPL",
    "gn:name":"Selimk\u00f6y",
    "gn:population":0,
    "gn:timezone":"Europe/Istanbul",
    "iso:country":"TR",
    "name:tur_x_preferred":[
        "Selimk\u00f6y"
    ],
    "wof:name":"Selimkoy",
    "wof:placetype":"locality"
},
  "geometry": {"coordinates":[30.23873,40.92816],"type":"Point"}
}