{
  "type": "Feature",
  "properties": {
    "gn:admin1_code":"52.0",
    "gn:asciiname":"Arpaalan",
    "gn:country_code":"TR",
    "gn:dem":1598,
    "gn:feature_class":"P",
    "gn:feature_code":"PPL",
    "gn:name":"Arpaalan",
    "gn:population":0,
    "gn:timezone":"Europe/Istanbul",
    "iso:country":"TR",
    "name:und_x_variant":[
        "Arpaalan\u0131 K\u00f6y\u00fc",
        "Arpaalan"
    ],
    "wof:name":"Arpaalan",
    "wof:placetype":"locality"
},
  "geometry": {"coordinates":[37.85856,40.36491],"type":"Point"}
}