{
  "type": "Feature",
  "properties": {
    "gn:admin1_code":"82.0",
    "gn:asciiname":"Karakocas",
    "gn:country_code":"TR",
    "gn:dem":982,
    "gn:feature_class":"P",
    "gn:feature_code":"PPL",
    "gn:name":"Karako\u00e7a\u015f",
    "gn:population":0,
    "gn:timezone":"Europe/Istanbul",
    "iso:country":"TR",
    "wof:name":"Karakocas",
    "wof:placetype":"locality"
},
  "geometry": {"coordinates":[33.36595,40.44714000000001],"type":"Point"}
}