{
  "type": "Feature",
  "properties": {
    "gn:admin1_code":"16",
    "gn:asciiname":"Delice",
    "gn:country_code":"TR",
    "gn:dem":1221,
    "gn:feature_class":"P",
    "gn:feature_code":"PPL",
    "gn:name":"Delice",
    "gn:population":0,
    "gn:timezone":"Europe/Istanbul",
    "iso:country":"TR",
    "name:ceb_x_preferred":[
        "Delice"
    ],
    "name:deu_x_preferred":[
        "Delice"
    ],
    "name:fra_x_preferred":[
        "Delice"
    ],
    "name:mrj_x_preferred":[
        "\u0414\u0435\u043b\u0438\u0434\u0436\u0435"
    ],
    "name:msa_x_preferred":[
        "Delice"
    ],
    "name:nld_x_preferred":[
        "Delice"
    ],
    "name:nor_x_preferred":[
        "Delice"
    ],
    "name:pnb_x_preferred":[
        "\u0636\u0644\u0639 \u0688\u0644\u06cc\u0686\u06d2"
    ],
    "name:swa_x_preferred":[
        "Delice"
    ],
    "name:tur_x_preferred":[
        "Delice"
    ],
    "name:und_x_variant":[
        "Delice K\u00f6y\u00fc",
        "Delice"
    ],
    "name:urd_x_preferred":[
        "\u062f\u0644\u06cc\u062c\u06d2"
    ],
    "name:vie_x_preferred":[
        "Delice"
    ],
    "wof:name":"Delice",
    "wof:placetype":"locality"
},
  "geometry": {"coordinates":[29.17389,39.96623],"type":"Point"}
}