{
  "type": "Feature",
  "properties": {
    "gn:admin1_code":"25",
    "gn:asciiname":"Kadicelal",
    "gn:country_code":"TR",
    "gn:dem":1897,
    "gn:feature_class":"P",
    "gn:feature_code":"PPL",
    "gn:name":"Kad\u0131celal",
    "gn:population":0,
    "gn:timezone":"Europe/Istanbul",
    "iso:country":"TR",
    "name:tur_x_preferred":[
        "Kad\u0131celal"
    ],
    "wof:name":"Kadicelal",
    "wof:placetype":"locality"
},
  "geometry": {"coordinates":[42.09994,39.8871],"type":"Point"}
}