{
  "type": "Feature",
  "properties": {
    "gn:admin1_code":"31.0",
    "gn:asciiname":"Kirmirttepe",
    "gn:country_code":"TR",
    "gn:dem":84,
    "gn:feature_class":"P",
    "gn:feature_code":"PPL",
    "gn:name":"Kirmirttepe",
    "gn:population":0,
    "gn:timezone":"Europe/Istanbul",
    "iso:country":"TR",
    "name:und_x_variant":[
        "Adakanberli"
    ],
    "wof:name":"Kirmirttepe",
    "wof:placetype":"locality"
},
  "geometry": {"coordinates":[36.46411,36.4977],"type":"Point"}
}