{
  "type": "Feature",
  "properties": {
    "gn:admin1_code":"85",
    "gn:asciiname":"Abdurrahmanlar",
    "gn:country_code":"TR",
    "gn:dem":51,
    "gn:feature_class":"P",
    "gn:feature_code":"PPL",
    "gn:name":"Abdurrahmanlar",
    "gn:population":0,
    "gn:timezone":"Europe/Istanbul",
    "iso:country":"TR",
    "wof:name":"Abdurrahmanlar",
    "wof:placetype":"locality"
},
  "geometry": {"coordinates":[32.22781,41.46263],"type":"Point"}
}