{
  "type": "Feature",
  "properties": {
    "gn:admin1_code":"03",
    "gn:asciiname":"Yusufaga",
    "gn:country_code":"TR",
    "gn:dem":912,
    "gn:feature_class":"P",
    "gn:feature_code":"PPL",
    "gn:name":"Yusufa\u011fa",
    "gn:population":0,
    "gn:timezone":"Europe/Istanbul",
    "iso:country":"TR",
    "wof:name":"Yusufaga",
    "wof:placetype":"locality"
},
  "geometry": {"coordinates":[31.16639,39.19639],"type":"Point"}
}