{
  "type": "Feature",
  "properties": {
    "gn:admin1_code":"60.0",
    "gn:asciiname":"Sarikaya",
    "gn:country_code":"TR",
    "gn:dem":1220,
    "gn:feature_class":"P",
    "gn:feature_code":"PPL",
    "gn:name":"Sar\u0131kaya",
    "gn:population":0,
    "gn:timezone":"Europe/Istanbul",
    "iso:country":"TR",
    "name:und_x_variant":[
        "Sar\u0131kaya K\u00f6y\u00fc",
        "Sar\u0131kaya"
    ],
    "wof:name":"Sarikaya",
    "wof:placetype":"locality"
},
  "geometry": {"coordinates":[35.96583,40.42952],"type":"Point"}
}