{
  "type": "Feature",
  "properties": {
    "gn:admin1_code":"87.0",
    "gn:asciiname":"Terkehaliller",
    "gn:country_code":"TR",
    "gn:dem":111,
    "gn:feature_class":"P",
    "gn:feature_code":"PPL",
    "gn:name":"Terkehaliller",
    "gn:population":0,
    "gn:timezone":"Europe/Istanbul",
    "iso:country":"TR",
    "name:ceb_x_preferred":[
        "Terkehaliller"
    ],
    "name:msa_x_preferred":[
        "Terkehaliller"
    ],
    "name:tur_x_preferred":[
        "Terkehaliller"
    ],
    "name:und_x_variant":[
        "Halilo\u011flu"
    ],
    "name:vie_x_preferred":[
        "Terkehaliller"
    ],
    "wof:name":"Terkehaliller",
    "wof:placetype":"locality"
},
  "geometry": {"coordinates":[32.38333,41.56667],"type":"Point"}
}