{
  "type": "Feature",
  "properties": {
    "gn:admin1_code":"58.0",
    "gn:asciiname":"Orentas",
    "gn:country_code":"TR",
    "gn:dem":1701,
    "gn:feature_class":"P",
    "gn:feature_code":"PPL",
    "gn:name":"\u00d6renta\u015f",
    "gn:population":0,
    "gn:timezone":"Europe/Istanbul",
    "iso:country":"TR",
    "wof:name":"Orentas",
    "wof:placetype":"locality"
},
  "geometry": {"coordinates":[37.64086,39.42392],"type":"Point"}
}