{
  "type": "Feature",
  "properties": {
    "gn:admin1_code":"12",
    "gn:asciiname":"Yenibaslar",
    "gn:country_code":"TR",
    "gn:dem":1254,
    "gn:feature_class":"P",
    "gn:feature_code":"PPL",
    "gn:name":"Yeniba\u015flar",
    "gn:population":0,
    "gn:timezone":"Europe/Istanbul",
    "iso:country":"TR",
    "name:tur_x_preferred":[
        "Yeniba\u015flar"
    ],
    "wof:name":"Yenibaslar",
    "wof:placetype":"locality"
},
  "geometry": {"coordinates":[40.68577,38.9972],"type":"Point"}
}