{
  "type": "Feature",
  "properties": {
    "gn:admin1_code":"52.0",
    "gn:asciiname":"Diskaya",
    "gn:country_code":"TR",
    "gn:dem":748,
    "gn:feature_class":"P",
    "gn:feature_code":"PPL",
    "gn:name":"Di\u015fkaya",
    "gn:population":0,
    "gn:timezone":"Europe/Istanbul",
    "iso:country":"TR",
    "name:tur_x_preferred":[
        "Di\u015fkaya"
    ],
    "wof:name":"Diskaya",
    "wof:placetype":"locality"
},
  "geometry": {"coordinates":[37.90446,40.77603],"type":"Point"}
}