{
  "type": "Feature",
  "properties": {
    "gn:admin1_code":"65",
    "gn:asciiname":"Onagil",
    "gn:country_code":"TR",
    "gn:dem":2175,
    "gn:feature_class":"P",
    "gn:feature_code":"PPL",
    "gn:name":"Ona\u011f\u0131l",
    "gn:population":0,
    "gn:timezone":"Europe/Istanbul",
    "iso:country":"TR",
    "name:und_x_variant":[
        "Kotis",
        "K\u00fctis",
        "Ona\u011f\u0131l"
    ],
    "wof:name":"Onagil",
    "wof:placetype":"locality"
},
  "geometry": {"coordinates":[43.25809,38.22671],"type":"Point"}
}