{
  "type": "Feature",
  "properties": {
    "gn:admin1_code":"55.0",
    "gn:asciiname":"Hizarbasi",
    "gn:country_code":"TR",
    "gn:dem":918,
    "gn:feature_class":"P",
    "gn:feature_code":"PPL",
    "gn:name":"H\u0131zarba\u015f\u0131",
    "gn:population":0,
    "gn:timezone":"Europe/Istanbul",
    "iso:country":"TR",
    "wof:name":"Hizarbasi",
    "wof:placetype":"locality"
},
  "geometry": {"coordinates":[36.06996,40.93188],"type":"Point"}
}