{
  "type": "Feature",
  "properties": {
    "gn:admin1_code":"58.0",
    "gn:asciiname":"Hoducek",
    "gn:country_code":"TR",
    "gn:dem":1153,
    "gn:feature_class":"P",
    "gn:feature_code":"PPL",
    "gn:name":"H\u00f6d\u00fccek",
    "gn:population":0,
    "gn:timezone":"Europe/Istanbul",
    "iso:country":"TR",
    "name:tur_x_preferred":[
        "H\u00f6d\u00fccek"
    ],
    "wof:name":"Hoducek",
    "wof:placetype":"locality"
},
  "geometry": {"coordinates":[38.05972,40.27696],"type":"Point"}
}