{
  "type": "Feature",
  "properties": {
    "gn:admin1_code":"68.0",
    "gn:asciiname":"Ilyakut",
    "gn:country_code":"TR",
    "gn:dem":926,
    "gn:feature_class":"P",
    "gn:feature_code":"PPL",
    "gn:name":"\u0130lyakut",
    "gn:population":0,
    "gn:timezone":"Europe/Istanbul",
    "iso:country":"TR",
    "name:und_x_variant":[
        "\u0130lyakut",
        "\u0130lya\u011fut"
    ],
    "wof:name":"Ilyakut",
    "wof:placetype":"locality"
},
  "geometry": {"coordinates":[32.49317,40.06800000000001],"type":"Point"}
}