{
  "type": "Feature",
  "properties": {
    "gn:admin1_code":"72.0",
    "gn:asciiname":"Hayat",
    "gn:country_code":"TR",
    "gn:dem":455,
    "gn:feature_class":"P",
    "gn:feature_code":"PPL",
    "gn:name":"Hayat",
    "gn:population":0,
    "gn:timezone":"Europe/Istanbul",
    "iso:country":"TR",
    "name:tur_x_preferred":[
        "Hayat"
    ],
    "wof:name":"Hayat",
    "wof:placetype":"locality"
},
  "geometry": {"coordinates":[40.14218,37.1277],"type":"Point"}
}