{
  "type": "Feature",
  "properties": {
    "gn:admin1_code":"49",
    "gn:asciiname":"Alinca",
    "gn:country_code":"TR",
    "gn:dem":1623,
    "gn:feature_class":"P",
    "gn:feature_code":"PPL",
    "gn:name":"Al\u0131nca",
    "gn:population":0,
    "gn:timezone":"Europe/Istanbul",
    "iso:country":"TR",
    "name:tur_x_preferred":[
        "Al\u0131nca"
    ],
    "name:und_x_variant":[
        "Kesan"
    ],
    "wof:name":"Alinca",
    "wof:placetype":"locality"
},
  "geometry": {"coordinates":[42.66667,39.16667],"type":"Point"}
}