{
  "type": "Feature",
  "properties": {
    "gn:admin1_code":"52.0",
    "gn:asciiname":"Cataltepe",
    "gn:country_code":"TR",
    "gn:dem":443,
    "gn:feature_class":"P",
    "gn:feature_code":"PPL",
    "gn:name":"\u00c7ataltepe",
    "gn:population":0,
    "gn:timezone":"Europe/Istanbul",
    "iso:country":"TR",
    "name:und_x_variant":[
        "\u00c7ataltepe",
        "Tepek\u00f6y"
    ],
    "wof:name":"Cataltepe",
    "wof:placetype":"locality"
},
  "geometry": {"coordinates":[37.22475,41.0436],"type":"Point"}
}