{
  "type": "Feature",
  "properties": {
    "gn:admin1_code":"45",
    "gn:asciiname":"Yukari Konurca",
    "gn:country_code":"TR",
    "gn:dem":849,
    "gn:feature_class":"P",
    "gn:feature_code":"PPL",
    "gn:name":"Yukar\u0131 Konurca",
    "gn:population":0,
    "gn:timezone":"Europe/Istanbul",
    "iso:country":"TR",
    "name:tur_x_preferred":[
        "Yukar\u0131 Konurca"
    ],
    "wof:name":"Yukari Konurca",
    "wof:placetype":"locality"
},
  "geometry": {"coordinates":[28.56851,38.48022],"type":"Point"}
}