{
  "type": "Feature",
  "properties": {
    "gn:admin1_code":"76.0",
    "gn:asciiname":"Mergi",
    "gn:country_code":"TR",
    "gn:dem":834,
    "gn:feature_class":"P",
    "gn:feature_code":"PPL",
    "gn:name":"Mergi",
    "gn:population":0,
    "gn:timezone":"Europe/Istanbul",
    "iso:country":"TR",
    "wof:name":"Mergi",
    "wof:placetype":"locality"
},
  "geometry": {"coordinates":[41.47467,38.20339],"type":"Point"}
}