{
  "type": "Feature",
  "properties": {
    "gn:admin1_code":"25.0",
    "gn:asciiname":"Haci Ahmet",
    "gn:country_code":"TR",
    "gn:dem":1817,
    "gn:feature_class":"P",
    "gn:feature_code":"PPL",
    "gn:name":"Hac\u0131 Ahmet",
    "gn:population":0,
    "gn:timezone":"Europe/Istanbul",
    "iso:country":"TR",
    "name:tur_x_preferred":[
        "Hac\u0131 Ahmet"
    ],
    "name:und_x_variant":[
        "Ku\u015fburnu",
        "Hac\u0131ahmet",
        "Sanamer",
        "Hac\u0131ahmetli"
    ],
    "wof:name":"Haci Ahmet",
    "wof:placetype":"locality"
},
  "geometry": {"coordinates":[42.13872,40.17482],"type":"Point"}
}