{
  "type": "Feature",
  "properties": {
    "gn:admin1_code":"58",
    "gn:asciiname":"Kucuk Tuzhisar",
    "gn:country_code":"TR",
    "gn:dem":1427,
    "gn:feature_class":"P",
    "gn:feature_code":"PPL",
    "gn:name":"K\u00fc\u00e7\u00fck Tuzhisar",
    "gn:population":0,
    "gn:timezone":"Europe/Istanbul",
    "iso:country":"TR",
    "name:und_x_variant":[
        "K\u00fc\u00e7\u00fck Tuzhisar",
        "Tuzhisar"
    ],
    "wof:name":"Kucuk Tuzhisar",
    "wof:placetype":"locality"
},
  "geometry": {"coordinates":[36.32478,39.10204],"type":"Point"}
}