{
  "type": "Feature",
  "properties": {
    "gn:admin1_code":"57.0",
    "gn:asciiname":"Tasmanli",
    "gn:country_code":"TR",
    "gn:dem":116,
    "gn:feature_class":"P",
    "gn:feature_code":"PPL",
    "gn:name":"Ta\u015fmanl\u0131",
    "gn:population":0,
    "gn:timezone":"Europe/Istanbul",
    "iso:country":"TR",
    "wof:name":"Tasmanli",
    "wof:placetype":"locality"
},
  "geometry": {"coordinates":[35.0521,41.89772],"type":"Point"}
}