{
  "type": "Feature",
  "properties": {
    "gn:admin1_code":"22.0",
    "gn:asciiname":"Hisarli",
    "gn:country_code":"TR",
    "gn:dem":207,
    "gn:feature_class":"P",
    "gn:feature_code":"PPL",
    "gn:name":"Hisarl\u0131",
    "gn:population":0,
    "gn:timezone":"Europe/Istanbul",
    "iso:country":"TR",
    "wof:name":"Hisarli",
    "wof:placetype":"locality"
},
  "geometry": {"coordinates":[26.21106,40.7202],"type":"Point"}
}