{
  "type": "Feature",
  "properties": {
    "gn:admin1_code":"78",
    "gn:asciiname":"Yuvatepe",
    "gn:country_code":"TR",
    "gn:dem":1014,
    "gn:feature_class":"P",
    "gn:feature_code":"PPL",
    "gn:name":"Yuvatepe",
    "gn:population":0,
    "gn:timezone":"Europe/Istanbul",
    "iso:country":"TR",
    "name:und_x_variant":[
        "Mercik",
        "Yuvatepe"
    ],
    "wof:name":"Yuvatepe",
    "wof:placetype":"locality"
},
  "geometry": {"coordinates":[33.12749,37.28723],"type":"Point"}
}