{
  "type": "Feature",
  "properties": {
    "gn:admin1_code":"81",
    "gn:asciiname":"Eyuplu",
    "gn:country_code":"TR",
    "gn:dem":1479,
    "gn:feature_class":"P",
    "gn:feature_code":"PPL",
    "gn:name":"Ey\u00fcpl\u00fc",
    "gn:population":0,
    "gn:timezone":"Europe/Istanbul",
    "iso:country":"TR",
    "wof:name":"Eyuplu",
    "wof:placetype":"locality"
},
  "geometry": {"coordinates":[36.15263,37.92374],"type":"Point"}
}