{
  "type": "Feature",
  "properties": {
    "gn:admin1_code":"45",
    "gn:asciiname":"Payamtarla",
    "gn:country_code":"TR",
    "gn:dem":604,
    "gn:feature_class":"P",
    "gn:feature_code":"PPL",
    "gn:name":"Payamtarla",
    "gn:population":0,
    "gn:timezone":"Europe/Istanbul",
    "iso:country":"TR",
    "wof:name":"Payamtarla",
    "wof:placetype":"locality"
},
  "geometry": {"coordinates":[28.62012,38.13909],"type":"Point"}
}