{
  "type": "Feature",
  "properties": {
    "gn:admin1_code":"32.0",
    "gn:asciiname":"Koyyeri",
    "gn:country_code":"TR",
    "gn:dem":543,
    "gn:feature_class":"P",
    "gn:feature_code":"PPL",
    "gn:name":"K\u00f6yyeri",
    "gn:population":0,
    "gn:timezone":"Europe/Istanbul",
    "iso:country":"TR",
    "wof:name":"Koyyeri",
    "wof:placetype":"locality"
},
  "geometry": {"coordinates":[33.38869,36.21162],"type":"Point"}
}