{
  "type": "Feature",
  "properties": {
    "gn:admin1_code":"72",
    "gn:asciiname":"Tanriyolu",
    "gn:country_code":"TR",
    "gn:dem":957,
    "gn:feature_class":"P",
    "gn:feature_code":"PPL",
    "gn:name":"Tanr\u0131yolu",
    "gn:population":0,
    "gn:timezone":"Europe/Istanbul",
    "iso:country":"TR",
    "name:tur_x_preferred":[
        "Tanr\u0131yolu"
    ],
    "name:und_x_variant":[
        "K\u00fcrr\u00fck"
    ],
    "wof:name":"Tanriyolu",
    "wof:placetype":"locality"
},
  "geometry": {"coordinates":[40.42009,37.43441],"type":"Point"}
}