{
  "type": "Feature",
  "properties": {
    "gn:admin1_code":"45",
    "gn:asciiname":"Kayadibi",
    "gn:country_code":"TR",
    "gn:dem":403,
    "gn:feature_class":"P",
    "gn:feature_code":"PPL",
    "gn:name":"Kayadibi",
    "gn:population":0,
    "gn:timezone":"Europe/Istanbul",
    "iso:country":"TR",
    "wof:name":"Kayadibi",
    "wof:placetype":"locality"
},
  "geometry": {"coordinates":[27.66667,39.08333],"type":"Point"}
}