{
  "type": "Feature",
  "properties": {
    "gn:admin1_code":"17.0",
    "gn:asciiname":"Karadoru",
    "gn:country_code":"TR",
    "gn:dem":642,
    "gn:feature_class":"P",
    "gn:feature_code":"PPL",
    "gn:name":"Karadoru",
    "gn:population":0,
    "gn:timezone":"Europe/Istanbul",
    "iso:country":"TR",
    "name:und_x_variant":[
        "Kurtta\u015f\u0131",
        "Kurtta\u015f\u0131 K\u00f6y",
        "Karadoru"
    ],
    "wof:name":"Karadoru",
    "wof:placetype":"locality"
},
  "geometry": {"coordinates":[27.33562,40.06764],"type":"Point"}
}