{
  "type": "Feature",
  "properties": {
    "gn:admin1_code":"31.0",
    "gn:asciiname":"Kabacinar",
    "gn:country_code":"TR",
    "gn:dem":802,
    "gn:feature_class":"P",
    "gn:feature_code":"PPL",
    "gn:name":"Kaba\u00e7\u0131nar",
    "gn:population":0,
    "gn:timezone":"Europe/Istanbul",
    "iso:country":"TR",
    "name:tur_x_preferred":[
        "Kaba\u00e7\u0131nar"
    ],
    "name:tur_x_variant":[
        "Kabacinar"
    ],
    "wof:name":"Kabacinar",
    "wof:placetype":"locality"
},
  "geometry": {"coordinates":[36.12763,35.91418],"type":"Point"}
}