{
  "type": "Feature",
  "properties": {
    "gn:admin1_code":"92.0",
    "gn:asciiname":"Kapakli",
    "gn:country_code":"TR",
    "gn:dem":6,
    "gn:feature_class":"P",
    "gn:feature_code":"PPL",
    "gn:name":"Kapakl\u0131",
    "gn:population":0,
    "gn:timezone":"Europe/Istanbul",
    "iso:country":"TR",
    "name:tur_x_preferred":[
        "Kapakl\u0131"
    ],
    "wof:name":"Kapakli",
    "wof:placetype":"locality"
},
  "geometry": {"coordinates":[28.96944,40.46361],"type":"Point"}
}