{
  "type": "Feature",
  "properties": {
    "gn:admin1_code":"19.0",
    "gn:asciiname":"Zennun",
    "gn:country_code":"TR",
    "gn:dem":978,
    "gn:feature_class":"P",
    "gn:feature_code":"PPL",
    "gn:name":"Zennun",
    "gn:population":0,
    "gn:timezone":"Europe/Istanbul",
    "iso:country":"TR",
    "name:und_x_variant":[
        "Zennun K\u00f6y\u00fc",
        "S\u00f6\u011f\u00fctyolu"
    ],
    "wof:name":"Zennun",
    "wof:placetype":"locality"
},
  "geometry": {"coordinates":[35.17618,40.50416],"type":"Point"}
}