{
  "type": "Feature",
  "properties": {
    "gn:admin1_code":"61.0",
    "gn:asciiname":"Bozlu",
    "gn:country_code":"TR",
    "gn:dem":516,
    "gn:feature_class":"P",
    "gn:feature_code":"PPL",
    "gn:name":"Bozlu",
    "gn:population":0,
    "gn:timezone":"Europe/Istanbul",
    "iso:country":"TR",
    "name:aze_x_preferred":[
        "Bozlu"
    ],
    "name:kat_x_preferred":[
        "\u10d1\u10dd\u10d6\u10da\u10e3"
    ],
    "wof:name":"Bozlu",
    "wof:placetype":"locality"
},
  "geometry": {"coordinates":[39.22114000000001,41.00338],"type":"Point"}
}