{
  "type": "Feature",
  "properties": {
    "gn:admin1_code":"82.0",
    "gn:asciiname":"Musakoy",
    "gn:country_code":"TR",
    "gn:dem":1023,
    "gn:feature_class":"P",
    "gn:feature_code":"PPL",
    "gn:name":"Musak\u00f6y",
    "gn:population":0,
    "gn:timezone":"Europe/Istanbul",
    "iso:country":"TR",
    "name:und_x_variant":[
        "Musa",
        "Musak\u00f6y"
    ],
    "wof:name":"Musakoy",
    "wof:placetype":"locality"
},
  "geometry": {"coordinates":[33.68048,40.96538],"type":"Point"}
}