{
  "type": "Feature",
  "properties": {
    "gn:admin1_code":"65",
    "gn:asciiname":"Yoldustu",
    "gn:country_code":"TR",
    "gn:dem":2201,
    "gn:feature_class":"P",
    "gn:feature_code":"PPL",
    "gn:name":"Yold\u00fc\u015ft\u00fc",
    "gn:population":0,
    "gn:timezone":"Europe/Istanbul",
    "iso:country":"TR",
    "name:und_x_variant":[
        "Pa\u011faa\u011fni",
        "Yold\u00fc\u015ft\u00fc"
    ],
    "wof:name":"Yoldustu",
    "wof:placetype":"locality"
},
  "geometry": {"coordinates":[43.5523,38.15607],"type":"Point"}
}