{
  "type": "Feature",
  "properties": {
    "gn:admin1_code":"14.0",
    "gn:asciiname":"Albalar",
    "gn:country_code":"TR",
    "gn:dem":1361,
    "gn:feature_class":"P",
    "gn:feature_code":"PPL",
    "gn:name":"Albalar",
    "gn:population":0,
    "gn:timezone":"Europe/Istanbul",
    "iso:country":"TR",
    "name:und_x_variant":[
        "Almac\u0131k",
        "Elmac\u0131lar",
        "Albalar"
    ],
    "wof:name":"Albalar",
    "wof:placetype":"locality"
},
  "geometry": {"coordinates":[31.04339,40.38596],"type":"Point"}
}