{
  "type": "Feature",
  "properties": {
    "gn:admin1_code":"21",
    "gn:asciiname":"Pirhasan",
    "gn:cc2":"TR",
    "gn:country_code":"TR",
    "gn:dem":651,
    "gn:feature_class":"P",
    "gn:feature_code":"PPL",
    "gn:name":"Pirhasan",
    "gn:population":0,
    "gn:timezone":"Europe/Istanbul",
    "iso:country":"TR",
    "name:tur_x_preferred":[
        "Pirhasan"
    ],
    "name:und_x_variant":[
        "Pyrkhasan"
    ],
    "wof:name":"Pirhasan",
    "wof:placetype":"locality"
},
  "geometry": {"coordinates":[40.97111,37.99833],"type":"Point"}
}