{
  "type": "Feature",
  "properties": {
    "gn:admin1_code":"54",
    "gn:asciiname":"Uzuncaorman",
    "gn:country_code":"TR",
    "gn:dem":46,
    "gn:feature_class":"P",
    "gn:feature_code":"PPL",
    "gn:name":"Uzuncaorman",
    "gn:population":0,
    "gn:timezone":"Europe/Istanbul",
    "iso:country":"TR",
    "name:tur_x_preferred":[
        "Uzuncaorman"
    ],
    "wof:name":"Uzuncaorman",
    "wof:placetype":"locality"
},
  "geometry": {"coordinates":[30.66646,40.77044],"type":"Point"}
}