{
  "type": "Feature",
  "properties": {
    "gn:admin1_code":"82.0",
    "gn:asciiname":"Unur",
    "gn:country_code":"TR",
    "gn:dem":1010,
    "gn:feature_class":"P",
    "gn:feature_code":"PPL",
    "gn:name":"\u00dcn\u00fcr",
    "gn:population":0,
    "gn:timezone":"Europe/Istanbul",
    "iso:country":"TR",
    "wof:name":"Unur",
    "wof:placetype":"locality"
},
  "geometry": {"coordinates":[34.00972,40.58991],"type":"Point"}
}