{
  "type": "Feature",
  "properties": {
    "gn:admin1_code":"32",
    "gn:asciiname":"Kocakoy",
    "gn:country_code":"TR",
    "gn:dem":15,
    "gn:feature_class":"P",
    "gn:feature_code":"PPL",
    "gn:name":"Kocak\u00f6y",
    "gn:population":0,
    "gn:timezone":"Europe/Istanbul",
    "iso:country":"TR",
    "name:und_x_variant":[
        "Kocak\u00f6y",
        "Koca"
    ],
    "wof:name":"Kocakoy",
    "wof:placetype":"locality"
},
  "geometry": {"coordinates":[35.02644,36.92696],"type":"Point"}
}