{
  "type": "Feature",
  "properties": {
    "gn:admin1_code":"74.0",
    "gn:asciiname":"Melekoz",
    "gn:cc2":"TR",
    "gn:country_code":"TR",
    "gn:dem":798,
    "gn:feature_class":"P",
    "gn:feature_code":"PPL",
    "gn:name":"Melek\u00f6z",
    "gn:population":0,
    "gn:timezone":"Europe/Istanbul",
    "iso:country":"TR",
    "name:und_x_variant":[
        "Melekez",
        "Mele\u011f\u00f6z",
        "Melek\u00f6z"
    ],
    "wof:name":"Melekoz",
    "wof:placetype":"locality"
},
  "geometry": {"coordinates":[41.89528,37.96778],"type":"Point"}
}