{
  "type": "Feature",
  "properties": {
    "gn:admin1_code":"65",
    "gn:asciiname":"Tepegoren",
    "gn:country_code":"TR",
    "gn:dem":2120,
    "gn:feature_class":"P",
    "gn:feature_code":"PPL",
    "gn:name":"Tepeg\u00f6ren",
    "gn:population":0,
    "gn:timezone":"Europe/Istanbul",
    "iso:country":"TR",
    "name:und_x_variant":[
        "Zeynis",
        "Tepeg\u00f6ren"
    ],
    "wof:name":"Tepegoren",
    "wof:placetype":"locality"
},
  "geometry": {"coordinates":[43.88852,38.35811],"type":"Point"}
}