{
  "type": "Feature",
  "properties": {
    "gn:admin1_code":"40",
    "gn:asciiname":"Safali",
    "gn:country_code":"TR",
    "gn:dem":1019,
    "gn:feature_class":"P",
    "gn:feature_code":"PPL",
    "gn:name":"Safal\u0131",
    "gn:population":0,
    "gn:timezone":"Europe/Istanbul",
    "iso:country":"TR",
    "name:und_x_variant":[
        "Sefal\u0131",
        "Safal\u0131"
    ],
    "wof:name":"Safali",
    "wof:placetype":"locality"
},
  "geometry": {"coordinates":[34.29508,39.63831],"type":"Point"}
}