{
  "type": "Feature",
  "properties": {
    "gn:admin1_code":"19.0",
    "gn:asciiname":"Cendere",
    "gn:country_code":"TR",
    "gn:dem":807,
    "gn:feature_class":"P",
    "gn:feature_code":"PPL",
    "gn:name":"Cendere",
    "gn:population":0,
    "gn:timezone":"Europe/Istanbul",
    "iso:country":"TR",
    "name:und_x_variant":[
        "Cender",
        "Cendere K\u00f6y\u00fc",
        "Da\u011f\u00f6n\u00fc"
    ],
    "wof:name":"Cendere",
    "wof:placetype":"locality"
},
  "geometry": {"coordinates":[34.49016,40.48721],"type":"Point"}
}