{
  "type": "Feature",
  "properties": {
    "gn:admin1_code":"66",
    "gn:asciiname":"Harkasan",
    "gn:country_code":"TR",
    "gn:dem":945,
    "gn:feature_class":"P",
    "gn:feature_code":"PPL",
    "gn:name":"Harka\u015fan",
    "gn:population":0,
    "gn:timezone":"Europe/Istanbul",
    "iso:country":"TR",
    "wof:name":"Harkasan",
    "wof:placetype":"locality"
},
  "geometry": {"coordinates":[34.61360999999999,39.71167],"type":"Point"}
}