{
  "type": "Feature",
  "properties": {
    "gn:admin1_code":"32",
    "gn:asciiname":"Yuksekoluk",
    "gn:country_code":"TR",
    "gn:dem":1387,
    "gn:feature_class":"P",
    "gn:feature_code":"PPL",
    "gn:name":"Y\u00fcksekoluk",
    "gn:population":0,
    "gn:timezone":"Europe/Istanbul",
    "iso:country":"TR",
    "name:tur_x_preferred":[
        "Y\u00fcksekoluk"
    ],
    "wof:name":"Yuksekoluk",
    "wof:placetype":"locality"
},
  "geometry": {"coordinates":[34.40900999999999,36.9958],"type":"Point"}
}