{
  "type": "Feature",
  "properties": {
    "gn:country":"TR",
    "gn:fcode":"PPLA2",
    "gn:population":25826,
    "iso:country":"TR",
    "name:azb_x_preferred":[
        "\u06af\u0648\u0631\u0627\u0648\u06cc\u0645\u0627\u0642"
    ],
    "name:ceb_x_preferred":[
        "G\u00fcroymak"
    ],
    "name:ckb_x_preferred":[
        "\u0686\u0648\u062e\u0648\u0648\u0695"
    ],
    "name:deu_x_preferred":[
        "G\u00fcroymak"
    ],
    "name:diq_x_preferred":[
        "Nor\u015fin"
    ],
    "name:eng_x_preferred":[
        "G\u00fcroymak"
    ],
    "name:fas_x_preferred":[
        "\u06af\u0648\u0631\u0627\u0648\u06cc\u0645\u0627\u0642"
    ],
    "name:fra_x_preferred":[
        "G\u00fcroymak"
    ],
    "name:hye_x_preferred":[
        "\u0549\u0578\u0582\u056d\u0578\u0582\u0580 \u054e\u0565\u0580\u056b\u0576"
    ],
    "name:ita_x_preferred":[
        "Distretto di G\u00fcroymak"
    ],
    "name:kur_x_preferred":[
        "Nor\u015f\u00een"
    ],
    "name:mrj_x_preferred":[
        "\u0413\u04f1\u0440\u043e\u0439\u043c\u0430\u043a"
    ],
    "name:msa_x_preferred":[
        "G\u00fcroymak"
    ],
    "name:msa_x_variant":[
        "Yontukyaz\u0131"
    ],
    "name:nan_x_preferred":[
        "G\u00fcroymak"
    ],
    "name:nld_x_preferred":[
        "G\u00fcroymak"
    ],
    "name:nno_x_preferred":[
        "G\u00fcroymak"
    ],
    "name:nob_x_preferred":[
        "G\u00fcroymak"
    ],
    "name:rus_x_preferred":[
        "\u0413\u044e\u0440\u043e\u0439\u043c\u0430\u043a"
    ],
    "name:swa_x_preferred":[
        "G\u00fcroymak"
    ],
    "name:tur_x_preferred":[
        "G\u00fcroymak"
    ],
    "name:und_x_variant":[
        "\u00c7ukur"
    ],
    "name:urd_x_preferred":[
        "\u06af\u0648\u0631\u0648\u06cc\u0645\u0627\u06a9"
    ],
    "name:vie_x_preferred":[
        "G\u00fcroymak"
    ],
    "name:zho_x_preferred":[
        "\u5c45\u7f85\u4f0a\u99ac\u514b"
    ],
    "qs:name":"G\u00fcroymak",
    "qs:name_adm0":"Turkey",
    "qs:name_adm1":"Bitlis",
    "qs:photos_9r":0,
    "qs:photos_sr":0,
    "qs:placetype":"Town",
    "qs:pop_sr":"7",
    "wd:wordcount":113,
    "wof:name":"G\u00fcroymak",
    "wof:placetype":"locality",
    "wof:population":25826
},
  "geometry": {"coordinates":[42.02811,38.57739],"type":"Point"}
}