{
  "type": "Feature",
  "properties": {
    "gn:admin1_code":"55.0",
    "gn:asciiname":"Sofular",
    "gn:country_code":"TR",
    "gn:dem":843,
    "gn:feature_class":"P",
    "gn:feature_code":"PPL",
    "gn:name":"Sofular",
    "gn:population":0,
    "gn:timezone":"Europe/Istanbul",
    "iso:country":"TR",
    "name:aze_x_preferred":[
        "Sofular"
    ],
    "name:ell_x_preferred":[
        "\u03a3\u03bf\u03c6\u03bf\u03c5\u03bb\u03ac\u03c1"
    ],
    "name:ita_x_preferred":[
        "Sofular"
    ],
    "name:msa_x_preferred":[
        "Sofular"
    ],
    "name:und_x_variant":[
        "\u0130\u011fdi\u015f"
    ],
    "wof:name":"Sofular",
    "wof:placetype":"locality"
},
  "geometry": {"coordinates":[35.78822,41.12627],"type":"Point"}
}