{
  "type": "Feature",
  "properties": {
    "gn:admin1_code":"55.0",
    "gn:asciiname":"Sofular",
    "gn:country_code":"TR",
    "gn:dem":843,
    "gn:feature_class":"P",
    "gn:feature_code":"PPL",
    "gn:name":"Sofular",
    "gn:population":0,
    "gn:timezone":"Europe/Istanbul",
    "iso:country":"TR",
    "name:und_x_variant":[
        "\u0130\u011fdi\u015f",
        "Sofular"
    ],
    "wof:name":"Sofular",
    "wof:placetype":"locality"
},
  "geometry": {"coordinates":[35.78822,41.12627],"type":"Point"}
}