{
  "type": "Feature",
  "properties": {
    "gn:admin1_code":"17.0",
    "gn:asciiname":"Bilaller",
    "gn:country_code":"TR",
    "gn:dem":205,
    "gn:feature_class":"P",
    "gn:feature_code":"PPL",
    "gn:name":"Bilaller",
    "gn:population":0,
    "gn:timezone":"Europe/Istanbul",
    "iso:country":"TR",
    "wof:name":"Bilaller",
    "wof:placetype":"locality"
},
  "geometry": {"coordinates":[26.37246,39.64937000000001],"type":"Point"}
}