{
  "type": "Feature",
  "properties": {
    "gn:admin1_code":"63.0",
    "gn:asciiname":"Erdemler",
    "gn:country_code":"TR",
    "gn:dem":385,
    "gn:feature_class":"P",
    "gn:feature_code":"PPL",
    "gn:name":"Erdemler",
    "gn:population":0,
    "gn:timezone":"Europe/Istanbul",
    "iso:country":"TR",
    "name:tur_x_preferred":[
        "Erdemler"
    ],
    "name:tur_x_variant":[
        "\u0130\u011fde"
    ],
    "wof:name":"Erdemler",
    "wof:placetype":"locality"
},
  "geometry": {"coordinates":[38.86863,36.8212],"type":"Point"}
}