{
  "type": "Feature",
  "properties": {
    "gn:admin1_code":"14",
    "gn:asciiname":"Tilkioglu",
    "gn:country_code":"TR",
    "gn:dem":581,
    "gn:feature_class":"P",
    "gn:feature_code":"PPL",
    "gn:name":"Tilkio\u011flu",
    "gn:population":0,
    "gn:timezone":"Europe/Istanbul",
    "iso:country":"TR",
    "wof:name":"Tilkioglu",
    "wof:placetype":"locality"
},
  "geometry": {"coordinates":[31.94548,40.96027],"type":"Point"}
}