{
  "type": "Feature",
  "properties": {
    "gn:admin1_code":"21",
    "gn:asciiname":"Cay",
    "gn:country_code":"TR",
    "gn:dem":987,
    "gn:feature_class":"P",
    "gn:feature_code":"PPL",
    "gn:name":"\u00c7ay",
    "gn:population":0,
    "gn:timezone":"Europe/Istanbul",
    "iso:country":"TR",
    "name:und_x_variant":[
        "\u00c7ay",
        "\u015eikeftiyankomu"
    ],
    "wof:name":"Cay",
    "wof:placetype":"locality"
},
  "geometry": {"coordinates":[41.00967,38.41074],"type":"Point"}
}