{
  "type": "Feature",
  "properties": {
    "gn:admin1_code":"21",
    "gn:asciiname":"Cay",
    "gn:country_code":"TR",
    "gn:dem":987,
    "gn:feature_class":"P",
    "gn:feature_code":"PPL",
    "gn:name":"\u00c7ay",
    "gn:population":0,
    "gn:timezone":"Europe/Istanbul",
    "iso:country":"TR",
    "name:deu_x_preferred":[
        "Cay"
    ],
    "name:fra_x_preferred":[
        "Caye"
    ],
    "name:hin_x_preferred":[
        "\u092a\u094d\u0930\u0935\u093e\u0932\u0940"
    ],
    "name:ind_x_preferred":[
        "Pulau pasir"
    ],
    "name:ita_x_preferred":[
        "Isola corallina"
    ],
    "name:jpn_x_preferred":[
        "\u30ad\u30fc"
    ],
    "name:lat_x_preferred":[
        "Cayum"
    ],
    "name:nds_x_preferred":[
        "Cay"
    ],
    "name:por_x_preferred":[
        "Cayo"
    ],
    "name:spa_x_preferred":[
        "Cayo"
    ],
    "name:swe_x_preferred":[
        "Cay"
    ],
    "name:tha_x_preferred":[
        "\u0e40\u0e01\u0e32\u0e30\u0e1b\u0e23\u0e34\u0e48\u0e21\u0e19\u0e49\u0e33"
    ],
    "name:und_x_variant":[
        "\u00c7ay",
        "\u015eikeftiyankomu"
    ],
    "name:vie_x_preferred":[
        "C\u1ed3n"
    ],
    "wof:name":"Cay",
    "wof:placetype":"locality"
},
  "geometry": {"coordinates":[41.00967,38.41074],"type":"Point"}
}