{
  "type": "Feature",
  "properties": {
    "gn:admin1_code":"71",
    "gn:asciiname":"Yuzbasioglu Yaylasi",
    "gn:country_code":"TR",
    "gn:dem":1060,
    "gn:feature_class":"P",
    "gn:feature_code":"PPL",
    "gn:name":"Y\u00fczba\u015f\u0131o\u011flu Yaylas\u0131",
    "gn:population":0,
    "gn:timezone":"Europe/Istanbul",
    "iso:country":"TR",
    "name:und_x_variant":[
        "Y\u00fczba\u015f\u0131o\u011flu Yaylas\u0131",
        "Bacanak Yaylas\u0131"
    ],
    "wof:name":"Yuzbasioglu Yaylasi",
    "wof:placetype":"locality"
},
  "geometry": {"coordinates":[33.30344,37.8677],"type":"Point"}
}