{
  "type": "Feature",
  "properties": {
    "gn:admin1_code":"61.0",
    "gn:asciiname":"Hosarli",
    "gn:country_code":"TR",
    "gn:dem":786,
    "gn:feature_class":"P",
    "gn:feature_code":"PPL",
    "gn:name":"Ho\u015farl\u0131",
    "gn:population":0,
    "gn:timezone":"Europe/Istanbul",
    "iso:country":"TR",
    "name:tur_x_preferred":[
        "Ho\u015farl\u0131"
    ],
    "wof:name":"Hosarli",
    "wof:placetype":"locality"
},
  "geometry": {"coordinates":[39.3013,40.94416],"type":"Point"}
}