{
  "type": "Feature",
  "properties": {
    "gn:admin1_code":"66.0",
    "gn:asciiname":"Mollaismail",
    "gn:country_code":"TR",
    "gn:dem":1071,
    "gn:feature_class":"P",
    "gn:feature_code":"PPL",
    "gn:name":"Mollaismail",
    "gn:population":0,
    "gn:timezone":"Europe/Istanbul",
    "iso:country":"TR",
    "name:und_x_variant":[
        "Mollaismailo\u011flu",
        "Mollaismail"
    ],
    "wof:name":"Mollaismail",
    "wof:placetype":"locality"
},
  "geometry": {"coordinates":[35.18266,40.2071],"type":"Point"}
}