{
  "type": "Feature",
  "properties": {
    "gn:admin1_code":"45",
    "gn:asciiname":"Karacalar",
    "gn:country_code":"TR",
    "gn:dem":741,
    "gn:feature_class":"P",
    "gn:feature_code":"PPL",
    "gn:name":"Karacalar",
    "gn:population":0,
    "gn:timezone":"Europe/Istanbul",
    "iso:country":"TR",
    "name:fra_x_preferred":[
        "Karacalar"
    ],
    "name:tur_x_preferred":[
        "Karacalar"
    ],
    "wof:name":"Karacalar",
    "wof:placetype":"locality"
},
  "geometry": {"coordinates":[28.61186,38.4377],"type":"Point"}
}