{
  "type": "Feature",
  "properties": {
    "gn:admin1_code":"69.0",
    "gn:asciiname":"Tamzi",
    "gn:country_code":"TR",
    "gn:dem":1708,
    "gn:feature_class":"P",
    "gn:feature_code":"PPL",
    "gn:name":"Tamz\u0131",
    "gn:population":0,
    "gn:timezone":"Europe/Istanbul",
    "iso:country":"TR",
    "name:tur_x_preferred":[
        "Tamz\u0131"
    ],
    "wof:name":"Tamzi",
    "wof:placetype":"locality"
},
  "geometry": {"coordinates":[39.71559,40.37369],"type":"Point"}
}