{
  "type": "Feature",
  "properties": {
    "gn:admin1_code":"19.0",
    "gn:asciiname":"Orenkaya",
    "gn:country_code":"TR",
    "gn:dem":1138,
    "gn:feature_class":"P",
    "gn:feature_code":"PPL",
    "gn:name":"\u00d6renkaya",
    "gn:population":0,
    "gn:timezone":"Europe/Istanbul",
    "iso:country":"TR",
    "wof:name":"Orenkaya",
    "wof:placetype":"locality"
},
  "geometry": {"coordinates":[34.4876,40.01985],"type":"Point"}
}