{
  "type": "Feature",
  "properties": {
    "gn:admin1_code":"16.0",
    "gn:asciiname":"Toprakdere",
    "gn:country_code":"TR",
    "gn:dem":292,
    "gn:feature_class":"P",
    "gn:feature_code":"PPL",
    "gn:name":"Toprakdere",
    "gn:population":0,
    "gn:timezone":"Europe/Istanbul",
    "iso:country":"TR",
    "name:und_x_variant":[
        "Derek\u00f6y",
        "Toprakderek\u00f6y",
        "Toprakdere"
    ],
    "wof:name":"Toprakdere",
    "wof:placetype":"locality"
},
  "geometry": {"coordinates":[29.75764,40.23477000000001],"type":"Point"}
}