{
  "type": "Feature",
  "properties": {
    "gn:admin1_code":"25.0",
    "gn:asciiname":"Dankar",
    "gn:country_code":"TR",
    "gn:dem":2148,
    "gn:feature_class":"P",
    "gn:feature_code":"PPL",
    "gn:name":"Dankar",
    "gn:population":0,
    "gn:timezone":"Europe/Istanbul",
    "iso:country":"TR",
    "wof:name":"Dankar",
    "wof:placetype":"locality"
},
  "geometry": {"coordinates":[41.35,40.25],"type":"Point"}
}