{
  "type": "Feature",
  "properties": {
    "gn:admin1_code":"28.0",
    "gn:asciiname":"Sancaklitepe",
    "gn:country_code":"TR",
    "gn:dem":384,
    "gn:feature_class":"P",
    "gn:feature_code":"PPL",
    "gn:name":"Sancakl\u0131tepe",
    "gn:population":0,
    "gn:timezone":"Europe/Istanbul",
    "iso:country":"TR",
    "name:tur_x_preferred":[
        "Sancakl\u0131tepe"
    ],
    "wof:name":"Sancaklitepe",
    "wof:placetype":"locality"
},
  "geometry": {"coordinates":[38.57339,40.8921],"type":"Point"}
}