{
  "type": "Feature",
  "properties": {
    "gn:admin1_code":"41",
    "gn:asciiname":"Yenicam",
    "gn:country_code":"TR",
    "gn:dem":117,
    "gn:feature_class":"P",
    "gn:feature_code":"PPL",
    "gn:name":"Yeni\u00e7am",
    "gn:population":0,
    "gn:timezone":"Europe/Istanbul",
    "iso:country":"TR",
    "name:tur_x_preferred":[
        "Yeni\u00e7am"
    ],
    "wof:name":"Yenicam",
    "wof:placetype":"locality"
},
  "geometry": {"coordinates":[30.24334,40.98359],"type":"Point"}
}