{
  "type": "Feature",
  "properties": {
    "gn:admin1_code":"20",
    "gn:asciiname":"Gencerli",
    "gn:cc2":"TR",
    "gn:country_code":"TR",
    "gn:dem":815,
    "gn:feature_class":"P",
    "gn:feature_code":"PPL",
    "gn:name":"Gencerli",
    "gn:population":0,
    "gn:timezone":"Europe/Istanbul",
    "iso:country":"TR",
    "name:und_x_variant":[
        "Gencelli",
        "Gengerli",
        "Gencerli"
    ],
    "wof:name":"Gencerli",
    "wof:placetype":"locality"
},
  "geometry": {"coordinates":[29.85,38.21667],"type":"Point"}
}