{
  "type": "Feature",
  "properties": {
    "gn:admin1_code":"93",
    "gn:asciiname":"Sogukpinar",
    "gn:country_code":"TR",
    "gn:dem":162,
    "gn:feature_class":"P",
    "gn:feature_code":"PPL",
    "gn:name":"So\u011fukp\u0131nar",
    "gn:population":0,
    "gn:timezone":"Europe/Istanbul",
    "iso:country":"TR",
    "wof:name":"Sogukpinar",
    "wof:placetype":"locality"
},
  "geometry": {"coordinates":[31.19104,40.83456],"type":"Point"}
}