{
  "type": "Feature",
  "properties": {
    "gn:admin1_code":"46",
    "gn:asciiname":"Tahirbey",
    "gn:country_code":"TR",
    "gn:dem":1484,
    "gn:feature_class":"P",
    "gn:feature_code":"PPL",
    "gn:name":"Tahirbey",
    "gn:population":0,
    "gn:timezone":"Europe/Istanbul",
    "iso:country":"TR",
    "wof:name":"Tahirbey",
    "wof:placetype":"locality"
},
  "geometry": {"coordinates":[36.46083,38.13444000000001],"type":"Point"}
}