{
  "type": "Feature",
  "properties": {
    "gn:admin1_code":"31",
    "gn:asciiname":"Korkmaz",
    "gn:country_code":"TR",
    "gn:dem":87,
    "gn:feature_class":"P",
    "gn:feature_code":"PPL",
    "gn:name":"Korkmaz",
    "gn:population":0,
    "gn:timezone":"Europe/Istanbul",
    "iso:country":"TR",
    "name:tur_x_preferred":[
        "Korkmaz"
    ],
    "wof:name":"Korkmaz",
    "wof:placetype":"locality"
},
  "geometry": {"coordinates":[36.18069000000001,36.23814],"type":"Point"}
}