{
  "type": "Feature",
  "properties": {
    "gn:admin1_code":"85.0",
    "gn:asciiname":"Yesilada",
    "gn:country_code":"TR",
    "gn:dem":237,
    "gn:feature_class":"P",
    "gn:feature_code":"PPL",
    "gn:name":"Ye\u015filada",
    "gn:population":0,
    "gn:timezone":"Europe/Istanbul",
    "iso:country":"TR",
    "name:und_x_variant":[
        "Kurde\u015fe",
        "Yaylak",
        "Ye\u015filada"
    ],
    "wof:name":"Yesilada",
    "wof:placetype":"locality"
},
  "geometry": {"coordinates":[31.87319,41.09273],"type":"Point"}
}