{
  "type": "Feature",
  "properties": {
    "gn:admin1_code":"63",
    "gn:asciiname":"Gulveren",
    "gn:country_code":"TR",
    "gn:dem":355,
    "gn:feature_class":"P",
    "gn:feature_code":"PPL",
    "gn:name":"G\u00fclveren",
    "gn:population":0,
    "gn:timezone":"Europe/Istanbul",
    "iso:country":"TR",
    "name:rus_x_preferred":[
        "Ashagy-Kharbetil\u2019salim"
    ],
    "name:tur_x_preferred":[
        "G\u00fclveren"
    ],
    "name:und_x_variant":[
        "A\u015fa\u011f\u0131 Harbetil Salim"
    ],
    "wof:name":"Gulveren",
    "wof:placetype":"locality"
},
  "geometry": {"coordinates":[38.96583,36.74639000000001],"type":"Point"}
}