{
  "type": "Feature",
  "properties": {
    "gn:admin1_code":"21",
    "gn:asciiname":"Catakli",
    "gn:country_code":"TR",
    "gn:dem":1032,
    "gn:feature_class":"P",
    "gn:feature_code":"PPL",
    "gn:name":"\u00c7atakl\u0131",
    "gn:population":0,
    "gn:timezone":"Europe/Istanbul",
    "iso:country":"TR",
    "name:tur_x_preferred":[
        "\u00c7atakl\u0131"
    ],
    "wof:name":"Catakli",
    "wof:placetype":"locality"
},
  "geometry": {"coordinates":[39.85327,38.39531],"type":"Point"}
}