{
  "type": "Feature",
  "properties": {
    "gn:admin1_code":"44",
    "gn:asciiname":"Uzuntas",
    "gn:country_code":"TR",
    "gn:dem":1233,
    "gn:feature_class":"P",
    "gn:feature_code":"PPL",
    "gn:name":"Uzunta\u015f",
    "gn:population":0,
    "gn:timezone":"Europe/Istanbul",
    "iso:country":"TR",
    "name:und_x_variant":[
        "Pera\u015f",
        "Uzunta\u015f"
    ],
    "wof:name":"Uzuntas",
    "wof:placetype":"locality"
},
  "geometry": {"coordinates":[38.80066,38.08491],"type":"Point"}
}