{
  "type": "Feature",
  "properties": {
    "gn:admin1_code":"21.0",
    "gn:asciiname":"Karacaviran",
    "gn:country_code":"TR",
    "gn:dem":717,
    "gn:feature_class":"P",
    "gn:feature_code":"PPL",
    "gn:name":"Karacaviran",
    "gn:population":0,
    "gn:timezone":"Europe/Istanbul",
    "iso:country":"TR",
    "name:tur_x_preferred":[
        "Karacaviran"
    ],
    "wof:name":"Karacaviran",
    "wof:placetype":"locality"
},
  "geometry": {"coordinates":[39.56082,38.05366],"type":"Point"}
}