{
  "type": "Feature",
  "properties": {
    "gn:admin1_code":"60.0",
    "gn:asciiname":"Hacipazar",
    "gn:country_code":"TR",
    "gn:dem":262,
    "gn:feature_class":"P",
    "gn:feature_code":"PPL",
    "gn:name":"Hac\u0131pazar",
    "gn:population":0,
    "gn:timezone":"Europe/Istanbul",
    "iso:country":"TR",
    "name:und_x_variant":[
        "Ha\u00e7pazar",
        "Hac\u0131pazar"
    ],
    "wof:name":"Hacipazar",
    "wof:placetype":"locality"
},
  "geometry": {"coordinates":[36.46227,40.71524],"type":"Point"}
}