{
  "type": "Feature",
  "properties": {
    "gn:admin1_code":"19.0",
    "gn:asciiname":"Obektas",
    "gn:country_code":"TR",
    "gn:dem":975,
    "gn:feature_class":"P",
    "gn:feature_code":"PPL",
    "gn:name":"\u00d6bekta\u015f",
    "gn:population":0,
    "gn:timezone":"Europe/Istanbul",
    "iso:country":"TR",
    "name:und_x_variant":[
        "\u00d6bekta\u015f K\u00f6y",
        "\u00d6bekta\u015f K\u00f6y\u00fc",
        "\u00d6bekta\u015f"
    ],
    "wof:name":"Obektas",
    "wof:placetype":"locality"
},
  "geometry": {"coordinates":[34.96898,41.0417],"type":"Point"}
}