{
  "type": "Feature",
  "properties": {
    "gn:admin1_code":"58",
    "gn:asciiname":"Karakoc",
    "gn:country_code":"TR",
    "gn:dem":1443,
    "gn:feature_class":"P",
    "gn:feature_code":"PPL",
    "gn:name":"Karako\u00e7",
    "gn:population":0,
    "gn:timezone":"Europe/Istanbul",
    "iso:country":"TR",
    "wof:name":"Karakoc",
    "wof:placetype":"locality"
},
  "geometry": {"coordinates":[36.48083,39.70313],"type":"Point"}
}