{
  "type": "Feature",
  "properties": {
    "gn:admin1_code":"07",
    "gn:asciiname":"Yenbey",
    "gn:country_code":"TR",
    "gn:dem":475,
    "gn:feature_class":"P",
    "gn:feature_code":"PPL",
    "gn:name":"Yenbey",
    "gn:population":0,
    "gn:timezone":"Europe/Istanbul",
    "iso:country":"TR",
    "wof:name":"Yenbey",
    "wof:placetype":"locality"
},
  "geometry": {"coordinates":[30.42222000000001,36.41528],"type":"Point"}
}