{
  "type": "Feature",
  "properties": {
    "gn:admin1_code":"63.0",
    "gn:asciiname":"Gyulyundzhe",
    "gn:country_code":"TR",
    "gn:dem":451,
    "gn:feature_class":"P",
    "gn:feature_code":"PPL",
    "gn:name":"Gyulyundzhe",
    "gn:population":0,
    "gn:timezone":"Europe/Istanbul",
    "iso:country":"TR",
    "name:und_x_variant":[
        "G\u00fcl\u00fcnce"
    ],
    "wof:name":"Gyulyundzhe",
    "wof:placetype":"locality"
},
  "geometry": {"coordinates":[38.69111,36.80139000000001],"type":"Point"}
}