{
  "type": "Feature",
  "properties": {
    "gn:admin1_code":"85",
    "gn:asciiname":"Ulu",
    "gn:country_code":"TR",
    "gn:dem":527,
    "gn:feature_class":"P",
    "gn:feature_code":"PPL",
    "gn:name":"Ulu",
    "gn:population":0,
    "gn:timezone":"Europe/Istanbul",
    "iso:country":"TR",
    "name:dan_x_preferred":[
        "Ulo"
    ],
    "name:deu_x_preferred":[
        "Ulu"
    ],
    "name:est_x_preferred":[
        "Ulu"
    ],
    "name:fra_x_preferred":[
        "Ulu"
    ],
    "name:hrv_x_preferred":[
        "Ulu"
    ],
    "name:rus_x_preferred":[
        "\u0423\u043b\u0443"
    ],
    "name:tur_x_preferred":[
        "Ulu"
    ],
    "name:ukr_x_preferred":[
        "\u0423\u043b\u0443"
    ],
    "wof:name":"Ulu",
    "wof:placetype":"locality"
},
  "geometry": {"coordinates":[32.01159000000001,41.49165],"type":"Point"}
}