{
  "type": "Feature",
  "properties": {
    "gn:admin1_code":"03",
    "gn:asciiname":"Avdan",
    "gn:country_code":"TR",
    "gn:dem":1057,
    "gn:feature_class":"P",
    "gn:feature_code":"PPL",
    "gn:name":"Avdan",
    "gn:population":0,
    "gn:timezone":"Europe/Istanbul",
    "iso:country":"TR",
    "wof:name":"Avdan",
    "wof:placetype":"locality"
},
  "geometry": {"coordinates":[31.44164,38.93833],"type":"Point"}
}