{
  "type": "Feature",
  "properties": {
    "gn:country":"TR",
    "gn:fcode":"PPLA2",
    "gn:pop":76268,
    "iso:country":"TR",
    "name:ara_x_preferred":[
        "\u0645\u062f\u064a\u0627\u062a"
    ],
    "name:arc_x_preferred":[
        "\u0721\u0715\u071d\u0715"
    ],
    "name:ckb_x_preferred":[
        "\u0645\u062f\u06cc\u0627\u062f"
    ],
    "name:deu_x_preferred":[
        "Midyat"
    ],
    "name:eng_x_preferred":[
        "Midyat"
    ],
    "name:fas_x_preferred":[
        "\u0645\u06cc\u062f\u06cc\u0627\u062a"
    ],
    "name:mrj_x_preferred":[
        "\u041c\u0438\u0434\u044c\u044f\u0442"
    ],
    "name:nld_x_preferred":[
        "Midyat"
    ],
    "name:pnb_x_preferred":[
        "\u0636\u0644\u0639 \u0645\u062f\u06cc\u0627\u062a"
    ],
    "name:pol_x_preferred":[
        "Midyat"
    ],
    "name:rus_x_preferred":[
        "\u041c\u0438\u0434\u044c\u044f\u0442"
    ],
    "name:tur_x_preferred":[
        "Midyat"
    ],
    "name:ukr_x_preferred":[
        "\u041c\u0456\u0434\u044c\u044f\u0442"
    ],
    "name:unk_x_variant":[
        "Estil"
    ],
    "name:zho_x_preferred":[
        "\u7c73\u8fea\u4e9e\u7279"
    ],
    "qs:name":"Midyat",
    "qs:photos_9r":0,
    "qs:photos_sr":0,
    "qs:pop_sr":"8",
    "wd:wordcount":1165,
    "wof:name":"Midyat",
    "wof:placetype":"locality",
    "wof:population":76268
},
  "geometry": {"coordinates":[41.33934,37.4247],"type":"Point"}
}