{
  "type": "Feature",
  "properties": {
    "gn:country":"TR",
    "gn:fcode":"PPLA2",
    "gn:population":76268,
    "iso:country":"TR",
    "name:ara_x_preferred":[
        "\u0645\u062f\u064a\u0627\u062a"
    ],
    "name:arc_x_preferred":[
        "\u0721\u0715\u071d\u0715"
    ],
    "name:azb_x_preferred":[
        "\u0645\u06cc\u062f\u06cc\u0627\u062a"
    ],
    "name:cat_x_preferred":[
        "Midyat"
    ],
    "name:ceb_x_preferred":[
        "Midyat \u0130l\u00e7esi"
    ],
    "name:ckb_x_preferred":[
        "\u0645\u062f\u06cc\u0627\u062f"
    ],
    "name:deu_x_preferred":[
        "Midyat"
    ],
    "name:eng_x_preferred":[
        "Midyat"
    ],
    "name:fas_x_preferred":[
        "\u0645\u06cc\u062f\u06cc\u0627\u062a"
    ],
    "name:fra_x_preferred":[
        "Midyad"
    ],
    "name:gag_x_preferred":[
        "Midyat"
    ],
    "name:hun_x_preferred":[
        "Midyat"
    ],
    "name:hye_x_preferred":[
        "\u0544\u056b\u0564\u056b\u0561\u0564"
    ],
    "name:ita_x_preferred":[
        "Midyat"
    ],
    "name:jpn_x_preferred":[
        "\u30df\u30c7\u30a3\u30e4\u30c3\u30c8"
    ],
    "name:kur_x_preferred":[
        "Midyad"
    ],
    "name:min_x_preferred":[
        "Midyat"
    ],
    "name:mrj_x_preferred":[
        "\u041c\u0438\u0434\u044c\u044f\u0442"
    ],
    "name:msa_x_preferred":[
        "Midyat"
    ],
    "name:nan_x_preferred":[
        "Midyat"
    ],
    "name:nld_x_preferred":[
        "Midyat"
    ],
    "name:nno_x_preferred":[
        "Midyat"
    ],
    "name:nob_x_preferred":[
        "Midyat"
    ],
    "name:pnb_x_preferred":[
        "\u0636\u0644\u0639 \u0645\u062f\u06cc\u0627\u062a"
    ],
    "name:pol_x_preferred":[
        "Midyat"
    ],
    "name:ron_x_preferred":[
        "Midyat"
    ],
    "name:rus_x_preferred":[
        "\u041c\u0438\u0434\u044c\u044f\u0442"
    ],
    "name:spa_x_preferred":[
        "Midyat"
    ],
    "name:swa_x_preferred":[
        "Midyat"
    ],
    "name:swe_x_preferred":[
        "Midyat"
    ],
    "name:tur_x_preferred":[
        "Midyat"
    ],
    "name:tur_x_variant":[
        "Garip\u00e7e"
    ],
    "name:ukr_x_preferred":[
        "\u041c\u0456\u0434\u044c\u044f\u0442"
    ],
    "name:und_x_variant":[
        "Estil"
    ],
    "name:urd_x_preferred":[
        "\u0645\u062f\u06cc\u0627\u062a"
    ],
    "name:vie_x_preferred":[
        "Midyat"
    ],
    "name:zho_x_preferred":[
        "\u7c73\u8fea\u4e9e\u7279"
    ],
    "qs:name":"Midyat",
    "qs:photos_9r":0,
    "qs:photos_sr":0,
    "qs:pop_sr":"8",
    "wd:wordcount":1165,
    "wof:name":"Midyat",
    "wof:placetype":"locality",
    "wof:population":76268
},
  "geometry": {"coordinates":[41.33934,37.4247],"type":"Point"}
}