{
  "type": "Feature",
  "properties": {
    "gn:admin1_code":"43",
    "gn:asciiname":"Emrez",
    "gn:country_code":"TR",
    "gn:dem":1215,
    "gn:feature_class":"P",
    "gn:feature_code":"PPL",
    "gn:name":"Emrez",
    "gn:population":0,
    "gn:timezone":"Europe/Istanbul",
    "iso:country":"TR",
    "name:tur_x_preferred":[
        "Emrez"
    ],
    "wof:name":"Emrez",
    "wof:placetype":"locality"
},
  "geometry": {"coordinates":[29.78196,39.35112],"type":"Point"}
}