{
  "type": "Feature",
  "properties": {
    "gn:admin1_code":"25.0",
    "gn:asciiname":"Sindiran",
    "gn:country_code":"TR",
    "gn:dem":1468,
    "gn:feature_class":"P",
    "gn:feature_code":"PPL",
    "gn:name":"S\u0131nd\u0131ran",
    "gn:population":0,
    "gn:timezone":"Europe/Istanbul",
    "iso:country":"TR",
    "name:und_x_variant":[
        "S\u0131nd\u0131ran",
        "Ekrek"
    ],
    "wof:name":"Sindiran",
    "wof:placetype":"locality"
},
  "geometry": {"coordinates":[42.36283,40.62077],"type":"Point"}
}