{
  "type": "Feature",
  "properties": {
    "gn:admin1_code":"02",
    "gn:asciiname":"Salkimbagi",
    "gn:country_code":"TR",
    "gn:dem":822,
    "gn:feature_class":"P",
    "gn:feature_code":"PPL",
    "gn:name":"Salk\u0131mba\u011f\u0131",
    "gn:population":0,
    "gn:timezone":"Europe/Istanbul",
    "iso:country":"TR",
    "name:und_x_variant":[
        "Alut",
        "Salk\u0131mba\u011f\u0131"
    ],
    "wof:name":"Salkimbagi",
    "wof:placetype":"locality"
},
  "geometry": {"coordinates":[38.58949000000001,37.83386],"type":"Point"}
}