{
  "type": "Feature",
  "properties": {
    "gn:admin1_code":"70",
    "gn:asciiname":"Uckaya",
    "gn:country_code":"TR",
    "gn:dem":1352,
    "gn:feature_class":"P",
    "gn:feature_code":"PPL",
    "gn:name":"\u00dc\u00e7kaya",
    "gn:population":0,
    "gn:timezone":"Europe/Istanbul",
    "iso:country":"TR",
    "name:und_x_variant":[
        "\u00dc\u00e7yan\u0131",
        "\u00dc\u00e7kaya"
    ],
    "wof:name":"Uckaya",
    "wof:placetype":"locality"
},
  "geometry": {"coordinates":[44.30173,37.1192],"type":"Point"}
}