{
  "type": "Feature",
  "properties": {
    "gn:country":"TR",
    "gn:fcode":"PPLA2",
    "gn:pop":70171,
    "iso:country":"TR",
    "name:deu_x_preferred":[
        "Do\u011fubeyaz\u0131t"
    ],
    "name:eng_x_preferred":[
        "Do\u011fubeyaz\u0131t"
    ],
    "name:fas_x_preferred":[
        "\u062f\u063a\u0648 \u0628\u0627\u06cc\u0632\u06cc\u062f"
    ],
    "name:fra_x_preferred":[
        "Do\u011fubeyaz\u0131t"
    ],
    "name:ita_x_preferred":[
        "Dogubayazit"
    ],
    "name:kur_x_preferred":[
        "Baz\u00eed"
    ],
    "name:pol_x_preferred":[
        "Do\u011fubeyaz\u0131t"
    ],
    "name:rus_x_preferred":[
        "\u0414\u043e\u0433\u0443\u0431\u0430\u044f\u0437\u0438\u0442"
    ],
    "name:tur_x_preferred":[
        "Do\u011fubeyaz\u0131t"
    ],
    "name:tur_x_variant":[
        "Do\u011fubayaz\u0131t"
    ],
    "name:unk_x_variant":[
        "Beyaz\u0131t"
    ],
    "qs:name":"Do\u011fubayaz\u0131t",
    "qs:photos_9r":0,
    "qs:photos_sr":0,
    "qs:pop_sr":"8",
    "wd:wordcount":847,
    "wof:name":"Do\u011fubayaz\u0131t",
    "wof:placetype":"locality",
    "wof:population":70171
},
  "geometry": {"coordinates":[44.08417,39.54694],"type":"Point"}
}