{
  "type": "Feature",
  "properties": {
    "gn:country":"TR",
    "gn:fcode":"PPL",
    "gn:pop":0,
    "iso:country":"TR",
    "name:tur_x_preferred":[
        "Kumalan"
    ],
    "name:tur_x_variant":[
        "Alt\u0131nkum"
    ],
    "qs:name":"Alt\u0131nkum",
    "qs:name_adm0":"Turkey",
    "qs:name_adm1":"Antalya",
    "qs:photos":833,
    "qs:photos_1k":169,
    "qs:photos_9k":4,
    "qs:photos_9r":6,
    "qs:photos_all":833,
    "qs:photos_sr":9,
    "qs:placetype":"Town",
    "qs:pop_sr":"0",
    "wd:wordcount":695,
    "wof:name":"Alt\u0131nkum",
    "wof:placetype":"locality",
    "wof:population":0
},
  "geometry": {"coordinates":[30.80083,36.855],"type":"Point"}
}