{
  "type": "Feature",
  "properties": {
    "gn:admin1_code":"25",
    "gn:asciiname":"Tasan",
    "gn:country_code":"TR",
    "gn:dem":2198,
    "gn:feature_class":"P",
    "gn:feature_code":"PPL",
    "gn:name":"Ta\u015fan",
    "gn:population":0,
    "gn:timezone":"Europe/Istanbul",
    "iso:country":"TR",
    "name:und_x_variant":[
        "K\u00fcfri",
        "Ta\u015fan"
    ],
    "wof:name":"Tasan",
    "wof:placetype":"locality"
},
  "geometry": {"coordinates":[42.1875,39.66783],"type":"Point"}
}