{
  "type": "Feature",
  "properties": {
    "gn:admin1_code":"80",
    "gn:asciiname":"Demrin",
    "gn:cc2":"TR",
    "gn:country_code":"TR",
    "gn:dem":373,
    "gn:feature_class":"P",
    "gn:feature_code":"PPL",
    "gn:name":"Demrin",
    "gn:population":0,
    "gn:timezone":"Europe/Istanbul",
    "iso:country":"TR",
    "name:und_x_variant":[
        "Bemrin",
        "Bimrin",
        "Demrin"
    ],
    "wof:name":"Demrin",
    "wof:placetype":"locality"
},
  "geometry": {"coordinates":[42.48083,37.14583],"type":"Point"}
}