{
  "type": "Feature",
  "properties": {
    "iso:country":"TR",
    "name:eng_x_preferred":[
        "Battalgazi"
    ],
    "name:tur_x_preferred":[
        "Battalgazi"
    ],
    "wof:name":"Battalgazi",
    "wof:placetype":"neighbourhood"
},
  "geometry": {"coordinates":[29.26842959586935,40.98078392806175],"type":"Point"}
}