{
  "type": "Feature",
  "properties": {
    "gn:admin1_code":"04",
    "gn:asciiname":"Yukari Akpazar",
    "gn:country_code":"TR",
    "gn:dem":1974,
    "gn:feature_class":"P",
    "gn:feature_code":"PPL",
    "gn:name":"Yukar\u0131 Akpazar",
    "gn:population":0,
    "gn:timezone":"Europe/Istanbul",
    "iso:country":"TR",
    "name:tur_x_preferred":[
        "Yukar\u0131 Akpazar"
    ],
    "name:und_x_variant":[
        "Yukar\u0131akpazar"
    ],
    "wof:name":"Yukari Akpazar",
    "wof:placetype":"locality"
},
  "geometry": {"coordinates":[43.58742,39.56526],"type":"Point"}
}