{
  "type": "Feature",
  "properties": {
    "gn:admin1_code":"83",
    "gn:asciiname":"Kabaklar",
    "gn:country_code":"TR",
    "gn:dem":769,
    "gn:feature_class":"P",
    "gn:feature_code":"PPL",
    "gn:name":"Kabaklar",
    "gn:population":0,
    "gn:timezone":"Europe/Istanbul",
    "iso:country":"TR",
    "name:tur_x_preferred":[
        "Kabaklar"
    ],
    "wof:name":"Kabaklar",
    "wof:placetype":"locality"
},
  "geometry": {"coordinates":[36.57067,37.03347],"type":"Point"}
}