{
  "type": "Feature",
  "properties": {
    "gn:admin1_code":"37.0",
    "gn:asciiname":"Derekoy",
    "gn:country_code":"TR",
    "gn:dem":290,
    "gn:feature_class":"P",
    "gn:feature_code":"PPL",
    "gn:name":"Derek\u00f6y",
    "gn:population":0,
    "gn:timezone":"Europe/Istanbul",
    "iso:country":"TR",
    "name:tur_x_preferred":[
        "Derek\u00f6y"
    ],
    "name:und_x_variant":[
        "Dere",
        "Delfe"
    ],
    "wof:name":"Derekoy",
    "wof:placetype":"locality"
},
  "geometry": {"coordinates":[33.16636,41.79633],"type":"Point"}
}