{
  "type": "Feature",
  "properties": {
    "gn:admin1_code":"21",
    "gn:asciiname":"Kokeziren",
    "gn:country_code":"TR",
    "gn:dem":652,
    "gn:feature_class":"P",
    "gn:feature_code":"PPL",
    "gn:name":"K\u00f6keziren",
    "gn:population":0,
    "gn:timezone":"Europe/Istanbul",
    "iso:country":"TR",
    "name:und_x_variant":[
        "K\u00f6keziren",
        "Mirank\u00e2n"
    ],
    "wof:name":"Kokeziren",
    "wof:placetype":"locality"
},
  "geometry": {"coordinates":[41.14602,38.21682],"type":"Point"}
}