{
  "type": "Feature",
  "properties": {
    "gn:admin1_code":"89",
    "gn:asciiname":"Kahyaoglu",
    "gn:country_code":"TR",
    "gn:dem":431,
    "gn:feature_class":"P",
    "gn:feature_code":"PPL",
    "gn:name":"Kahyao\u011flu",
    "gn:population":0,
    "gn:timezone":"Europe/Istanbul",
    "iso:country":"TR",
    "wof:name":"Kahyaoglu",
    "wof:placetype":"locality"
},
  "geometry": {"coordinates":[32.32177,41.26505],"type":"Point"}
}