{
  "type": "Feature",
  "properties": {
    "gn:admin1_code":"65",
    "gn:asciiname":"Omerova",
    "gn:country_code":"TR",
    "gn:dem":1977,
    "gn:feature_class":"P",
    "gn:feature_code":"PPL",
    "gn:name":"\u00d6merova",
    "gn:population":0,
    "gn:timezone":"Europe/Istanbul",
    "iso:country":"TR",
    "name:tur_x_preferred":[
        "\u00d6merova"
    ],
    "name:und_x_variant":[
        "\u00d6merabat"
    ],
    "wof:name":"Omerova",
    "wof:placetype":"locality"
},
  "geometry": {"coordinates":[44.08176,37.88213],"type":"Point"}
}