{
  "type": "Feature",
  "properties": {
    "gn:admin1_code":"17",
    "gn:asciiname":"Haciyusuflar",
    "gn:country_code":"TR",
    "gn:dem":470,
    "gn:feature_class":"P",
    "gn:feature_code":"PPL",
    "gn:name":"Hac\u0131yusuflar",
    "gn:population":0,
    "gn:timezone":"Europe/Istanbul",
    "iso:country":"TR",
    "name:tur_x_preferred":[
        "Hac\u0131yusuflar"
    ],
    "wof:name":"Haciyusuflar",
    "wof:placetype":"locality"
},
  "geometry": {"coordinates":[27.4495,39.775],"type":"Point"}
}