{
  "type": "Feature",
  "properties": {
    "gn:admin1_code":"89",
    "gn:asciiname":"Ovatekkeonu",
    "gn:country_code":"TR",
    "gn:dem":38,
    "gn:feature_class":"P",
    "gn:feature_code":"PPL",
    "gn:name":"Ovatekke\u00f6n\u00fc",
    "gn:population":0,
    "gn:timezone":"Europe/Istanbul",
    "iso:country":"TR",
    "name:tur_x_preferred":[
        "Ovatekke\u00f6n\u00fc"
    ],
    "wof:name":"Ovatekkeonu",
    "wof:placetype":"locality"
},
  "geometry": {"coordinates":[32.67789,41.8283],"type":"Point"}
}