{
  "type": "Feature",
  "properties": {
    "gn:admin1_code":"14.0",
    "gn:asciiname":"Yeniceseyhler",
    "gn:country_code":"TR",
    "gn:dem":789,
    "gn:feature_class":"P",
    "gn:feature_code":"PPL",
    "gn:name":"Yenice\u015feyhler",
    "gn:population":0,
    "gn:timezone":"Europe/Istanbul",
    "iso:country":"TR",
    "name:und_x_variant":[
        "Yenice\u015f\u0131hlar",
        "Yenicek\u00f6y",
        "Yenice\u015feyhler"
    ],
    "wof:name":"Yeniceseyhler",
    "wof:placetype":"locality"
},
  "geometry": {"coordinates":[31.12176,40.49296],"type":"Point"}
}