{
  "type": "Feature",
  "properties": {
    "gn:admin1_code":"91.0",
    "gn:asciiname":"Atalan",
    "gn:country_code":"TR",
    "gn:dem":302,
    "gn:feature_class":"P",
    "gn:feature_code":"PPL",
    "gn:name":"Atalan",
    "gn:population":0,
    "gn:timezone":"Europe/Istanbul",
    "iso:country":"TR",
    "name:ceb_x_preferred":[
        "Atalan"
    ],
    "name:kur_x_preferred":[
        "Atalan"
    ],
    "name:nld_x_preferred":[
        "Atalan"
    ],
    "name:tur_x_preferred":[
        "Atalan"
    ],
    "name:vie_x_preferred":[
        "Atalan"
    ],
    "wof:name":"Atalan",
    "wof:placetype":"locality"
},
  "geometry": {"coordinates":[36.34563,37.25323],"type":"Point"}
}