{
  "type": "Feature",
  "properties": {
    "gn:admin1_code":"63",
    "gn:asciiname":"Syrryn",
    "gn:country_code":"TR",
    "gn:dem":495,
    "gn:feature_class":"P",
    "gn:feature_code":"PPL",
    "gn:name":"Syrryn",
    "gn:population":0,
    "gn:timezone":"Europe/Istanbul",
    "iso:country":"TR",
    "wof:name":"Syrryn",
    "wof:placetype":"locality"
},
  "geometry": {"coordinates":[38.82539000000001,37.16254],"type":"Point"}
}