{
  "type": "Feature",
  "properties": {
    "gn:admin1_code":"57.0",
    "gn:asciiname":"Yuruk",
    "gn:cc2":"TR",
    "gn:country_code":"TR",
    "gn:dem":493,
    "gn:feature_class":"P",
    "gn:feature_code":"PPL",
    "gn:name":"Y\u00fcr\u00fck",
    "gn:population":0,
    "gn:timezone":"Europe/Istanbul",
    "iso:country":"TR",
    "name:und_x_variant":[
        "Y\u00fcr\u00fck K\u00f6y",
        "Y\u00fcr\u00fck"
    ],
    "wof:name":"Yuruk",
    "wof:placetype":"locality"
},
  "geometry": {"coordinates":[34.96667,41.46667],"type":"Point"}
}