{
  "type": "Feature",
  "properties": {
    "gn:admin1_code":"37.0",
    "gn:asciiname":"Obrucak",
    "gn:country_code":"TR",
    "gn:dem":835,
    "gn:feature_class":"P",
    "gn:feature_code":"PPL",
    "gn:name":"Obrucak",
    "gn:population":0,
    "gn:timezone":"Europe/Istanbul",
    "iso:country":"TR",
    "wof:name":"Obrucak",
    "wof:placetype":"locality"
},
  "geometry": {"coordinates":[33.99586,41.38961],"type":"Point"}
}