{
  "type": "Feature",
  "properties": {
    "gn:admin1_code":"85",
    "gn:asciiname":"Hasanli",
    "gn:country_code":"TR",
    "gn:dem":133,
    "gn:feature_class":"P",
    "gn:feature_code":"PPL",
    "gn:name":"Hasanl\u0131",
    "gn:population":0,
    "gn:timezone":"Europe/Istanbul",
    "iso:country":"TR",
    "wof:name":"Hasanli",
    "wof:placetype":"locality"
},
  "geometry": {"coordinates":[31.44618,41.11269],"type":"Point"}
}