{
  "type": "Feature",
  "properties": {
    "gn:admin1_code":"64",
    "gn:asciiname":"Karakose",
    "gn:country_code":"TR",
    "gn:dem":693,
    "gn:feature_class":"P",
    "gn:feature_code":"PPL",
    "gn:name":"Karak\u00f6se",
    "gn:population":0,
    "gn:timezone":"Europe/Istanbul",
    "iso:country":"TR",
    "name:tur_x_preferred":[
        "Karak\u00f6se"
    ],
    "wof:name":"Karakose",
    "wof:placetype":"locality"
},
  "geometry": {"coordinates":[29.12074,38.73405],"type":"Point"}
}