{
  "type": "Feature",
  "properties": {
    "gn:admin1_code":"76.0",
    "gn:asciiname":"Hanikabhamo",
    "gn:country_code":"TR",
    "gn:dem":797,
    "gn:feature_class":"P",
    "gn:feature_code":"PPL",
    "gn:name":"Hanikabhamo",
    "gn:population":0,
    "gn:timezone":"Europe/Istanbul",
    "iso:country":"TR",
    "name:tur_x_preferred":[
        "Hanikabhamo"
    ],
    "wof:name":"Hanikabhamo",
    "wof:placetype":"locality"
},
  "geometry": {"coordinates":[41.13581,37.69559],"type":"Point"}
}