{
  "type": "Feature",
  "properties": {
    "gn:admin1_code":"71",
    "gn:asciiname":"Ikikuyu",
    "gn:country_code":"TR",
    "gn:dem":1009,
    "gn:feature_class":"P",
    "gn:feature_code":"PPL",
    "gn:name":"\u0130kikuyu",
    "gn:population":0,
    "gn:timezone":"Europe/Istanbul",
    "iso:country":"TR",
    "name:und_x_variant":[
        "\u0130kikuyu Yaylas\u0131",
        "\u0130kikuyu"
    ],
    "wof:name":"Ikikuyu",
    "wof:placetype":"locality"
},
  "geometry": {"coordinates":[33.08333,37.76667],"type":"Point"}
}