{
  "type": "Feature",
  "properties": {
    "gn:admin1_code":"69.0",
    "gn:asciiname":"Arakoy",
    "gn:country_code":"TR",
    "gn:dem":1668,
    "gn:feature_class":"P",
    "gn:feature_code":"PPL",
    "gn:name":"Arak\u00f6y",
    "gn:population":0,
    "gn:timezone":"Europe/Istanbul",
    "iso:country":"TR",
    "name:und_x_variant":[
        "Ara",
        "Arak\u00f6y"
    ],
    "wof:name":"Arakoy",
    "wof:placetype":"locality"
},
  "geometry": {"coordinates":[38.92654,40.22523],"type":"Point"}
}