{
  "type": "Feature",
  "properties": {
    "gn:admin1_code":"09",
    "gn:asciiname":"Kizilguney",
    "gn:country_code":"TR",
    "gn:dem":250,
    "gn:feature_class":"P",
    "gn:feature_code":"PPL",
    "gn:name":"K\u0131z\u0131lg\u00fcney",
    "gn:population":0,
    "gn:timezone":"Europe/Istanbul",
    "iso:country":"TR",
    "name:tur_x_preferred":[
        "K\u0131z\u0131lg\u00fcney"
    ],
    "wof:name":"Kizilguney",
    "wof:placetype":"locality"
},
  "geometry": {"coordinates":[28.04536,37.68843],"type":"Point"}
}