{
  "type": "Feature",
  "properties": {
    "gn:admin1_code":"68",
    "gn:asciiname":"Yaglipinar",
    "gn:country_code":"TR",
    "gn:dem":1056,
    "gn:feature_class":"P",
    "gn:feature_code":"PPL",
    "gn:name":"Ya\u011fl\u0131p\u0131nar",
    "gn:population":0,
    "gn:timezone":"Europe/Istanbul",
    "iso:country":"TR",
    "wof:name":"Yaglipinar",
    "wof:placetype":"locality"
},
  "geometry": {"coordinates":[32.80333,39.65356],"type":"Point"}
}