{
  "type": "Feature",
  "properties": {
    "gn:admin1_code":"93.0",
    "gn:asciiname":"Camkoy",
    "gn:country_code":"TR",
    "gn:dem":154,
    "gn:feature_class":"P",
    "gn:feature_code":"PPL",
    "gn:name":"\u00c7amk\u00f6y",
    "gn:population":0,
    "gn:timezone":"Europe/Istanbul",
    "iso:country":"TR",
    "name:und_x_variant":[
        "\u00c7amk\u00f6y",
        "\u00c7amk\u00f6y\u00fc",
        "\u00c7am"
    ],
    "wof:name":"Camkoy",
    "wof:placetype":"locality"
},
  "geometry": {"coordinates":[31.15975,40.89182],"type":"Point"}
}