{
  "type": "Feature",
  "properties": {
    "gn:admin1_code":"21",
    "gn:asciiname":"Karaburcak",
    "gn:country_code":"TR",
    "gn:dem":1967,
    "gn:feature_class":"P",
    "gn:feature_code":"PPL",
    "gn:name":"Karaburcak",
    "gn:population":0,
    "gn:timezone":"Europe/Istanbul",
    "iso:country":"TR",
    "name:und_x_variant":[
        "G\u00fcznak"
    ],
    "wof:name":"Karaburcak",
    "wof:placetype":"locality"
},
  "geometry": {"coordinates":[41.15847,38.56059000000001],"type":"Point"}
}