{
  "type": "Feature",
  "properties": {
    "gn:admin1_code":"84.0",
    "gn:asciiname":"Tasdere",
    "gn:country_code":"TR",
    "gn:dem":1829,
    "gn:feature_class":"P",
    "gn:feature_code":"PPL",
    "gn:name":"Ta\u015fdere",
    "gn:population":0,
    "gn:timezone":"Europe/Istanbul",
    "iso:country":"TR",
    "name:und_x_variant":[
        "Sosgert",
        "Ta\u015fdere"
    ],
    "wof:name":"Tasdere",
    "wof:placetype":"locality"
},
  "geometry": {"coordinates":[43.58203,40.86462],"type":"Point"}
}