{
  "type": "Feature",
  "properties": {
    "gn:admin1_code":"89",
    "gn:asciiname":"Cotler",
    "gn:country_code":"TR",
    "gn:dem":973,
    "gn:feature_class":"P",
    "gn:feature_code":"PPL",
    "gn:name":"C\u00f6tler",
    "gn:population":0,
    "gn:timezone":"Europe/Istanbul",
    "iso:country":"TR",
    "wof:name":"Cotler",
    "wof:placetype":"locality"
},
  "geometry": {"coordinates":[32.45418,40.93184],"type":"Point"}
}