{
  "type": "Feature",
  "properties": {
    "gn:admin1_code":"44.0",
    "gn:asciiname":"Sutluce",
    "gn:country_code":"TR",
    "gn:dem":761,
    "gn:feature_class":"P",
    "gn:feature_code":"PPL",
    "gn:name":"S\u00fctl\u00fcce",
    "gn:population":0,
    "gn:timezone":"Europe/Istanbul",
    "iso:country":"TR",
    "name:tur_x_preferred":[
        "S\u00fctl\u00fcce"
    ],
    "wof:name":"Sutluce",
    "wof:placetype":"locality"
},
  "geometry": {"coordinates":[38.21753,38.47671],"type":"Point"}
}