{
  "type": "Feature",
  "properties": {
    "gn:admin1_code":"66",
    "gn:asciiname":"Yanik",
    "gn:country_code":"TR",
    "gn:dem":926,
    "gn:feature_class":"P",
    "gn:feature_code":"PPL",
    "gn:name":"Yan\u0131k",
    "gn:population":0,
    "gn:timezone":"Europe/Istanbul",
    "iso:country":"TR",
    "wof:name":"Yanik",
    "wof:placetype":"locality"
},
  "geometry": {"coordinates":[35.82727,39.92862],"type":"Point"}
}