{
  "type": "Feature",
  "properties": {
    "gn:admin1_code":"72.0",
    "gn:asciiname":"Misti",
    "gn:cc2":"TR",
    "gn:country_code":"TR",
    "gn:dem":541,
    "gn:feature_class":"P",
    "gn:feature_code":"PPL",
    "gn:name":"Mi\u015fti",
    "gn:population":0,
    "gn:timezone":"Europe/Istanbul",
    "iso:country":"TR",
    "name:ben_x_preferred":[
        "\u098f\u09b2 \u09ae\u09bf\u09b8\u09cd\u09a4\u09bf"
    ],
    "name:bos_x_preferred":[
        "Misti"
    ],
    "name:cat_x_preferred":[
        "Misti"
    ],
    "name:ceb_x_preferred":[
        "Volc\u00e1n Misti"
    ],
    "name:ces_x_preferred":[
        "El Misti"
    ],
    "name:dan_x_preferred":[
        "Misti"
    ],
    "name:deu_x_preferred":[
        "Misti"
    ],
    "name:epo_x_preferred":[
        "Misti"
    ],
    "name:est_x_preferred":[
        "Misti vulkaan"
    ],
    "name:fra_x_preferred":[
        "Misti"
    ],
    "name:gle_x_preferred":[
        "El Misti"
    ],
    "name:hun_x_preferred":[
        "Misti"
    ],
    "name:ind_x_preferred":[
        "Misti"
    ],
    "name:ita_x_preferred":[
        "El Misti"
    ],
    "name:kat_x_preferred":[
        "\u10db\u10d8\u10e1\u10e2\u10d8"
    ],
    "name:lit_x_preferred":[
        "Misti"
    ],
    "name:mkd_x_preferred":[
        "\u041c\u0438\u0441\u0442\u0438"
    ],
    "name:nld_x_preferred":[
        "Misti"
    ],
    "name:nor_x_preferred":[
        "Misti"
    ],
    "name:oss_x_preferred":[
        "\u042d\u043b\u044c-\u041c\u0438\u0441\u0442\u0438"
    ],
    "name:pol_x_preferred":[
        "El Misti"
    ],
    "name:por_x_preferred":[
        "Misti"
    ],
    "name:que_x_preferred":[
        "Misti"
    ],
    "name:rus_x_preferred":[
        "\u041c\u0438\u0441\u0442\u0438"
    ],
    "name:slk_x_preferred":[
        "El Misti"
    ],
    "name:spa_x_preferred":[
        "Misti"
    ],
    "name:swe_x_preferred":[
        "Misti"
    ],
    "name:tur_x_preferred":[
        "Misti"
    ],
    "name:ukr_x_preferred":[
        "\u0415\u043b\u044c-\u041c\u0456\u0441\u0442\u0456"
    ],
    "name:und_x_variant":[
        "Me\u015fti",
        "Meshti",
        "Mi\u015fti"
    ],
    "name:zho_x_preferred":[
        "\u57c3\u723e\u7c73\u65af\u8482\u706b\u5c71"
    ],
    "wof:name":"Misti",
    "wof:placetype":"locality"
},
  "geometry": {"coordinates":[41.78111,37.64333],"type":"Point"}
}