{
  "type": "Feature",
  "properties": {
    "gn:admin1_code":"72.0",
    "gn:asciiname":"Misti",
    "gn:cc2":"TR",
    "gn:country_code":"TR",
    "gn:dem":541,
    "gn:feature_class":"P",
    "gn:feature_code":"PPL",
    "gn:name":"Mi\u015fti",
    "gn:population":0,
    "gn:timezone":"Europe/Istanbul",
    "iso:country":"TR",
    "name:und_x_variant":[
        "Me\u015fti",
        "Meshti",
        "Mi\u015fti"
    ],
    "wof:name":"Misti",
    "wof:placetype":"locality"
},
  "geometry": {"coordinates":[41.78111,37.64333],"type":"Point"}
}