{
  "type": "Feature",
  "properties": {
    "gn:admin1_code":"03",
    "gn:asciiname":"Elhan",
    "gn:country_code":"TR",
    "gn:dem":937,
    "gn:feature_class":"P",
    "gn:feature_code":"PPL",
    "gn:name":"Elhan",
    "gn:population":0,
    "gn:timezone":"Europe/Istanbul",
    "iso:country":"TR",
    "wof:name":"Elhan",
    "wof:placetype":"locality"
},
  "geometry": {"coordinates":[31.18105,39.03875],"type":"Point"}
}