{
  "type": "Feature",
  "properties": {
    "gn:admin1_code":"21",
    "gn:asciiname":"Siginak",
    "gn:country_code":"TR",
    "gn:dem":855,
    "gn:feature_class":"P",
    "gn:feature_code":"PPL",
    "gn:name":"S\u0131\u011f\u0131nak",
    "gn:population":0,
    "gn:timezone":"Europe/Istanbul",
    "iso:country":"TR",
    "name:tur_x_preferred":[
        "S\u0131\u011f\u0131nak"
    ],
    "wof:name":"Siginak",
    "wof:placetype":"locality"
},
  "geometry": {"coordinates":[40.74649,38.42956],"type":"Point"}
}