{
  "type": "Feature",
  "properties": {
    "gn:admin1_code":"37.0",
    "gn:asciiname":"Akcaseke",
    "gn:country_code":"TR",
    "gn:dem":1118,
    "gn:feature_class":"P",
    "gn:feature_code":"PPL",
    "gn:name":"Ak\u00e7aseke",
    "gn:population":0,
    "gn:timezone":"Europe/Istanbul",
    "iso:country":"TR",
    "name:und_x_variant":[
        "Ak\u00e7aseke",
        "Ak\u00e7akise"
    ],
    "wof:name":"Akcaseke",
    "wof:placetype":"locality"
},
  "geometry": {"coordinates":[33.51521,41.76275],"type":"Point"}
}