{
  "type": "Feature",
  "properties": {
    "gn:admin1_code":"83",
    "gn:asciiname":"Ufacik",
    "gn:country_code":"TR",
    "gn:dem":939,
    "gn:feature_class":"P",
    "gn:feature_code":"PPL",
    "gn:name":"Ufac\u0131k",
    "gn:population":0,
    "gn:timezone":"Europe/Istanbul",
    "iso:country":"TR",
    "name:und_x_variant":[
        "Ufac\u0131k",
        "Ovac\u0131k"
    ],
    "wof:name":"Ufacik",
    "wof:placetype":"locality"
},
  "geometry": {"coordinates":[37.15864000000001,36.98477000000001],"type":"Point"}
}