{
  "type": "Feature",
  "properties": {
    "gn:admin1_code":"04",
    "gn:asciiname":"Ciftepinar",
    "gn:country_code":"TR",
    "gn:dem":1651,
    "gn:feature_class":"P",
    "gn:feature_code":"PPL",
    "gn:name":"\u00c7iftep\u0131nar",
    "gn:population":0,
    "gn:timezone":"Europe/Istanbul",
    "iso:country":"TR",
    "name:und_x_variant":[
        "\u00c7eli",
        "Celik\u00f6m\u00fc",
        "\u00c7iftep\u0131nar"
    ],
    "wof:name":"Ciftepinar",
    "wof:placetype":"locality"
},
  "geometry": {"coordinates":[42.90187,39.73992],"type":"Point"}
}