{
  "type": "Feature",
  "properties": {
    "gn:admin1_code":"48",
    "gn:asciiname":"Siralik",
    "gn:country_code":"TR",
    "gn:dem":16,
    "gn:feature_class":"P",
    "gn:feature_code":"PPL",
    "gn:name":"S\u0131ral\u0131k",
    "gn:population":0,
    "gn:timezone":"Europe/Istanbul",
    "iso:country":"TR",
    "name:tur_x_preferred":[
        "S\u0131ral\u0131k"
    ],
    "wof:name":"Siralik",
    "wof:placetype":"locality"
},
  "geometry": {"coordinates":[27.58979,37.22503],"type":"Point"}
}