{
  "type": "Feature",
  "properties": {
    "gn:admin1_code":"72.0",
    "gn:asciiname":"Hirbeke",
    "gn:country_code":"TR",
    "gn:dem":1009,
    "gn:feature_class":"P",
    "gn:feature_code":"PPL",
    "gn:name":"H\u0131rbeke",
    "gn:population":0,
    "gn:timezone":"Europe/Istanbul",
    "iso:country":"TR",
    "name:tur_x_preferred":[
        "H\u0131rabak\u0131"
    ],
    "name:tur_x_variant":[
        "H\u0131rbeke"
    ],
    "name:und_x_variant":[
        "Kharabaky"
    ],
    "wof:name":"Hirbeke",
    "wof:placetype":"locality"
},
  "geometry": {"coordinates":[41.64944000000001,37.58028],"type":"Point"}
}