{
  "type": "Feature",
  "properties": {
    "gn:admin1_code":"14",
    "gn:asciiname":"Bicakcilar",
    "gn:country_code":"TR",
    "gn:dem":1294,
    "gn:feature_class":"P",
    "gn:feature_code":"PPL",
    "gn:name":"Bi\u00e7ak\u00e7\u0131lar",
    "gn:population":0,
    "gn:timezone":"Europe/Istanbul",
    "iso:country":"TR",
    "wof:name":"Bicakcilar",
    "wof:placetype":"locality"
},
  "geometry": {"coordinates":[32.24151,40.7964],"type":"Point"}
}