{
  "type": "Feature",
  "properties": {
    "gn:admin1_code":"21",
    "gn:asciiname":"Kengerli",
    "gn:country_code":"TR",
    "gn:dem":730,
    "gn:feature_class":"P",
    "gn:feature_code":"PPL",
    "gn:name":"Kengerli",
    "gn:population":0,
    "gn:timezone":"Europe/Istanbul",
    "iso:country":"TR",
    "name:tur_x_preferred":[
        "Kengerli"
    ],
    "name:und_x_variant":[
        "Kengeril"
    ],
    "wof:name":"Kengerli",
    "wof:placetype":"locality"
},
  "geometry": {"coordinates":[40.3573,38.14663],"type":"Point"}
}