{
  "type": "Feature",
  "properties": {
    "gn:admin1_code":"49",
    "gn:asciiname":"Ekinduzu",
    "gn:country_code":"TR",
    "gn:dem":1619,
    "gn:feature_class":"P",
    "gn:feature_code":"PPL",
    "gn:name":"Ekind\u00fcz\u00fc",
    "gn:population":0,
    "gn:timezone":"Europe/Istanbul",
    "iso:country":"TR",
    "name:tur_x_preferred":[
        "Ekind\u00fcz\u00fc"
    ],
    "wof:name":"Ekinduzu",
    "wof:placetype":"locality"
},
  "geometry": {"coordinates":[41.41002,38.61099],"type":"Point"}
}