{
  "type": "Feature",
  "properties": {
    "gn:admin1_code":"10",
    "gn:asciiname":"Canacik",
    "gn:country_code":"TR",
    "gn:dem":422,
    "gn:feature_class":"P",
    "gn:feature_code":"PPL",
    "gn:name":"\u00c7anac\u0131k",
    "gn:population":0,
    "gn:timezone":"Europe/Istanbul",
    "iso:country":"TR",
    "name:tur_x_preferred":[
        "\u00c7anac\u0131k"
    ],
    "wof:name":"Canacik",
    "wof:placetype":"locality"
},
  "geometry": {"coordinates":[27.97,39.87314],"type":"Point"}
}