{
  "type": "Feature",
  "properties": {
    "gn:admin1_code":"70.0",
    "gn:asciiname":"Yesilbayir",
    "gn:country_code":"TR",
    "gn:dem":1476,
    "gn:feature_class":"P",
    "gn:feature_code":"PPL",
    "gn:name":"Ye\u015filbay\u0131r",
    "gn:population":0,
    "gn:timezone":"Europe/Istanbul",
    "iso:country":"TR",
    "wof:name":"Yesilbayir",
    "wof:placetype":"locality"
},
  "geometry": {"coordinates":[44.35,37.28333],"type":"Point"}
}