{
  "type": "Feature",
  "properties": {
    "gn:admin1_code":"43",
    "gn:asciiname":"Enne",
    "gn:country_code":"TR",
    "gn:dem":1026,
    "gn:feature_class":"P",
    "gn:feature_code":"PPL",
    "gn:name":"Enne",
    "gn:population":0,
    "gn:timezone":"Europe/Istanbul",
    "iso:country":"TR",
    "name:und_x_variant":[
        "Annek\u00f6y",
        "Ennek\u00f6y",
        "Enne"
    ],
    "wof:name":"Enne",
    "wof:placetype":"locality"
},
  "geometry": {"coordinates":[29.85623,39.47408],"type":"Point"}
}