{
  "type": "Feature",
  "properties": {
    "gn:admin1_code":"37.0",
    "gn:asciiname":"Asagi Sapaca",
    "gn:cc2":"TR",
    "gn:country_code":"TR",
    "gn:dem":808,
    "gn:feature_class":"P",
    "gn:feature_code":"PPL",
    "gn:name":"A\u015fa\u011f\u0131 Sapaca",
    "gn:population":0,
    "gn:timezone":"Europe/Istanbul",
    "iso:country":"TR",
    "name:und_x_variant":[
        "A\u015fa\u011f\u0131 Sapca",
        "A\u015fa\u011f\u0131 Sapaca"
    ],
    "wof:name":"Asagi Sapaca",
    "wof:placetype":"locality"
},
  "geometry": {"coordinates":[33.88333,41.35],"type":"Point"}
}