{
  "type": "Feature",
  "properties": {
    "gn:admin1_code":"41.0",
    "gn:asciiname":"Mesruriye",
    "gn:country_code":"TR",
    "gn:dem":536,
    "gn:feature_class":"P",
    "gn:feature_code":"PPL",
    "gn:name":"Mesruriye",
    "gn:population":0,
    "gn:timezone":"Europe/Istanbul",
    "iso:country":"TR",
    "name:tur_x_preferred":[
        "Mesruriye"
    ],
    "wof:name":"Mesruriye",
    "wof:placetype":"locality"
},
  "geometry": {"coordinates":[29.77407,40.64107],"type":"Point"}
}