{
  "type": "Feature",
  "properties": {
    "gn:admin1_code":"46.0",
    "gn:asciiname":"Ahmetcik",
    "gn:country_code":"TR",
    "gn:dem":1448,
    "gn:feature_class":"P",
    "gn:feature_code":"PPL",
    "gn:name":"Ahmetcik",
    "gn:population":0,
    "gn:timezone":"Europe/Istanbul",
    "iso:country":"TR",
    "wof:name":"Ahmetcik",
    "wof:placetype":"locality"
},
  "geometry": {"coordinates":[36.65747,38.02541],"type":"Point"}
}