{
  "type": "Feature",
  "properties": {
    "gn:admin1_code":"5.0",
    "gn:asciiname":"Yesilyurt",
    "gn:country_code":"TR",
    "gn:dem":544,
    "gn:feature_class":"P",
    "gn:feature_code":"PPL",
    "gn:name":"Ye\u015filyurt",
    "gn:population":0,
    "gn:timezone":"Europe/Istanbul",
    "iso:country":"TR",
    "name:und_x_variant":[
        "Sepetlioba K\u00f6y\u00fc",
        "Sepetlioba",
        "Ye\u015filyurt"
    ],
    "wof:name":"Yesilyurt",
    "wof:placetype":"locality"
},
  "geometry": {"coordinates":[36.24764,40.82014],"type":"Point"}
}