{
  "type": "Feature",
  "properties": {
    "gn:country":"TR",
    "gn:fcode":"PPL",
    "gn:pop":3073,
    "iso:country":"TR",
    "name:tur_x_preferred":[
        "Hal\u0131dere"
    ],
    "qs:name":"Hal\u0131dere",
    "qs:photos_9r":0,
    "qs:photos_sr":0,
    "qs:pop_sr":"4",
    "wof:name":"Hal\u0131dere",
    "wof:placetype":"locality",
    "wof:population":3073
},
  "geometry": {"coordinates":[29.75223,40.71604],"type":"Point"}
}