{
  "type": "Feature",
  "properties": {
    "gn:admin1_code":"90",
    "gn:asciiname":"Haskanli",
    "gn:cc2":"TR",
    "gn:country_code":"TR",
    "gn:dem":798,
    "gn:feature_class":"P",
    "gn:feature_code":"PPL",
    "gn:name":"Haskanl\u0131",
    "gn:population":0,
    "gn:timezone":"Europe/Istanbul",
    "iso:country":"TR",
    "name:und_x_variant":[
        "Haskanl\u0131 K\u00f6y\u00fc",
        "Haskanl\u0131"
    ],
    "wof:name":"Haskanli",
    "wof:placetype":"locality"
},
  "geometry": {"coordinates":[36.95,36.93333],"type":"Point"}
}