{
  "type": "Feature",
  "properties": {
    "gn:admin1_code":"09",
    "gn:asciiname":"Bourtlenharunu",
    "gn:cc2":"TR",
    "gn:country_code":"TR",
    "gn:dem":603,
    "gn:feature_class":"P",
    "gn:feature_code":"PPL",
    "gn:name":"B\u00f6\u00fcrtlenharunu",
    "gn:population":0,
    "gn:timezone":"Europe/Istanbul",
    "iso:country":"TR",
    "name:und_x_variant":[
        "B\u00f6\u00fcrtlenharumu",
        "B\u00f6\u00fcrtlenharunu"
    ],
    "wof:name":"Bourtlenharunu",
    "wof:placetype":"locality"
},
  "geometry": {"coordinates":[27.73333,37.51667],"type":"Point"}
}