{
  "type": "Feature",
  "properties": {
    "gn:country":"TR",
    "gn:fcode":"PPLA2",
    "gn:pop":23889,
    "iso:country":"TR",
    "name:lbe_x_preferred":[
        "\u041a\u044a\u0430\u0437\u0430\u043d"
    ],
    "name:mrj_x_preferred":[
        "\u041a\u0430\u0437\u0430\u043d"
    ],
    "name:pnb_x_preferred":[
        "\u0636\u0644\u0639 \u06a9\u0627\u0632\u0627\u0646"
    ],
    "name:urd_x_preferred":[
        "\u06a9\u0627\u0632\u0627\u0646\u060c \u0627\u0646\u0642\u0631\u06c1"
    ],
    "qs:name":"Kazan",
    "qs:photos_9r":0,
    "qs:photos_sr":0,
    "qs:pop_sr":"7",
    "wd:wordcount":5558,
    "wof:name":"Kazan",
    "wof:placetype":"locality",
    "wof:population":23889
},
  "geometry": {"coordinates":[32.68389,40.23167],"type":"Point"}
}