{
  "type": "Feature",
  "properties": {
    "gn:admin1_code":"25.0",
    "gn:asciiname":"Cakilli",
    "gn:country_code":"TR",
    "gn:dem":2183,
    "gn:feature_class":"P",
    "gn:feature_code":"PPL",
    "gn:name":"\u00c7ak\u0131ll\u0131",
    "gn:population":0,
    "gn:timezone":"Europe/Istanbul",
    "iso:country":"TR",
    "name:tur_x_preferred":[
        "\u00c7ak\u0131ll\u0131"
    ],
    "name:und_x_variant":[
        "\u00c7ak\u0131l\u0131",
        "Ma\u015fut"
    ],
    "wof:name":"Cakilli",
    "wof:placetype":"locality"
},
  "geometry": {"coordinates":[41.38489000000001,40.34624],"type":"Point"}
}