{
  "type": "Feature",
  "properties": {
    "gn:admin1_code":"23",
    "gn:asciiname":"Degirmenonu",
    "gn:country_code":"TR",
    "gn:dem":998,
    "gn:feature_class":"P",
    "gn:feature_code":"PPL",
    "gn:name":"De\u011firmen\u00f6n\u00fc",
    "gn:population":0,
    "gn:timezone":"Europe/Istanbul",
    "iso:country":"TR",
    "name:und_x_variant":[
        "Zerteri\u00e7",
        "De\u011firmen\u00f6n\u00fc"
    ],
    "wof:name":"Degirmenonu",
    "wof:placetype":"locality"
},
  "geometry": {"coordinates":[39.53978,38.60466],"type":"Point"}
}