{
  "type": "Feature",
  "properties": {
    "gn:country":"TR",
    "gn:fcode":"PPL",
    "gn:population":8385,
    "iso:country":"TR",
    "name:ceb_x_preferred":[
        "Ayd\u0131nc\u0131k"
    ],
    "name:deu_x_preferred":[
        "Ayd\u0131nc\u0131k"
    ],
    "name:eng_x_preferred":[
        "Ayd\u0131nc\u0131k"
    ],
    "name:epo_x_preferred":[
        "Aydincik"
    ],
    "name:fas_x_preferred":[
        "\u0622\u06cc\u062f\u06cc\u0646\u200c\u062c\u06cc\u06a9"
    ],
    "name:fra_x_preferred":[
        "Ayd\u0131nc\u0131k"
    ],
    "name:mrj_x_preferred":[
        "\u0410\u0439\u0434\u044b\u043d\u0434\u0436\u044b\u043a"
    ],
    "name:nld_x_preferred":[
        "Ayd\u0131nc\u0131k"
    ],
    "name:nno_x_preferred":[
        "Ayd\u0131nc\u0131k i Mersin"
    ],
    "name:pnb_x_preferred":[
        "\u0636\u0644\u0639 \u0627\u0626\u06cc\u062f\u0646\u062c\u06a9"
    ],
    "name:rus_x_preferred":[
        "\u0410\u0439\u0434\u044b\u043d\u0434\u0436\u044b\u043a"
    ],
    "name:tur_x_preferred":[
        "Ayd\u0131nc\u0131k"
    ],
    "name:und_x_variant":[
        "Gilindire"
    ],
    "name:vie_x_preferred":[
        "Ayd\u0131nc\u0131k"
    ],
    "name:zho_x_preferred":[
        "\u963f\u4f0a\u767b\u54f2\u514b"
    ],
    "qs:name":"Ayd\u0131nc\u0131k",
    "qs:name_adm0":"Turkey",
    "qs:name_adm1":"Mersin",
    "qs:photos":54,
    "qs:photos_1k":11,
    "qs:photos_9k":1,
    "qs:photos_9r":2,
    "qs:photos_all":54,
    "qs:photos_sr":2,
    "qs:placetype":"Town",
    "qs:pop_sr":"5",
    "wd:wordcount":64,
    "wof:name":"Ayd\u0131nc\u0131k",
    "wof:placetype":"locality",
    "wof:population":8385
},
  "geometry": {"coordinates":[33.32016,36.1437],"type":"Point"}
}