{
  "type": "Feature",
  "properties": {
    "gn:admin1_code":"63.0",
    "gn:asciiname":"Yolyazi",
    "gn:country_code":"TR",
    "gn:dem":648,
    "gn:feature_class":"P",
    "gn:feature_code":"PPL",
    "gn:name":"Yolyaz\u0131",
    "gn:population":0,
    "gn:timezone":"Europe/Istanbul",
    "iso:country":"TR",
    "name:tur_x_preferred":[
        "Yolyaz\u0131"
    ],
    "wof:name":"Yolyazi",
    "wof:placetype":"locality"
},
  "geometry": {"coordinates":[39.47178,37.27601],"type":"Point"}
}