{
  "type": "Feature",
  "properties": {
    "gn:country":"TR",
    "gn:fcode":"PPLA2",
    "gn:pop":11838,
    "iso:country":"TR",
    "name:arm_x_preferred":[
        "\u054f\u0561\u0577\u056f\u0565\u0576\u057f"
    ],
    "name:ava_x_preferred":[
        "\u0422\u0430\u0448\u043a\u0435\u043d\u0442"
    ],
    "name:aze_x_preferred":[
        "Da\u015fk\u0259nd"
    ],
    "name:bul_x_preferred":[
        "\u0422\u0430\u0448\u043a\u0435\u043d\u0442"
    ],
    "name:dut_x_preferred":[
        "Ta\u015fkent"
    ],
    "name:eng_x_preferred":[
        "Ta\u015fkent"
    ],
    "name:fre_x_preferred":[
        "Ta\u015fkent"
    ],
    "name:ger_x_preferred":[
        "Ta\u015fkent"
    ],
    "name:ita_x_preferred":[
        "Distretto di Ta\u015fkent"
    ],
    "name:may_x_preferred":[
        "Ta\u015fkent"
    ],
    "name:mrj_x_preferred":[
        "\u0422\u0430\u0448\u043a\u0435\u043d\u0442"
    ],
    "name:nan_x_preferred":[
        "Ta\u015fkent"
    ],
    "name:nob_x_preferred":[
        "Ta\u015fkent"
    ],
    "name:por_x_preferred":[
        "Ta\u015fkent"
    ],
    "name:rus_x_preferred":[
        "\u0422\u0430\u0448\u043a\u0435\u043d\u0442"
    ],
    "name:srp_x_preferred":[
        "\u0422\u0430\u0448\u043a\u0435\u043d\u0442"
    ],
    "name:swa_x_preferred":[
        "Ta\u015fkent"
    ],
    "name:tur_x_preferred":[
        "Ta\u015fkent"
    ],
    "name:unk_x_variant":[
        "Pirlerkondu"
    ],
    "name:urd_x_preferred":[
        "\u062a\u0627\u0634\u0642\u0646\u062f\u060c \u062a\u0631\u06a9\u06cc"
    ],
    "name:vie_x_preferred":[
        "Ta\u015fkent"
    ],
    "qs:name":"Ta\u015fkent",
    "qs:photos_9r":0,
    "qs:photos_sr":0,
    "qs:pop_sr":"6",
    "wd:wordcount":161,
    "wof:name":"Ta\u015fkent",
    "wof:placetype":"locality",
    "wof:population":11838
},
  "geometry": {"coordinates":[32.49131,36.9243],"type":"Point"}
}