{
  "type": "Feature",
  "properties": {
    "gn:admin1_code":"52.0",
    "gn:asciiname":"Hurriyet",
    "gn:country_code":"TR",
    "gn:dem":1014,
    "gn:feature_class":"P",
    "gn:feature_code":"PPL",
    "gn:name":"H\u00fcrriyet",
    "gn:population":0,
    "gn:timezone":"Europe/Istanbul",
    "iso:country":"TR",
    "name:tur_x_preferred":[
        "H\u00fcrriyet"
    ],
    "wof:name":"Hurriyet",
    "wof:placetype":"locality"
},
  "geometry": {"coordinates":[37.61569,40.73323],"type":"Point"}
}