{
  "type": "Feature",
  "properties": {
    "gn:admin1_code":"12",
    "gn:asciiname":"Elmali",
    "gn:country_code":"TR",
    "gn:dem":1640,
    "gn:feature_class":"P",
    "gn:feature_code":"PPL",
    "gn:name":"Elmal\u0131",
    "gn:population":0,
    "gn:timezone":"Europe/Istanbul",
    "iso:country":"TR",
    "name:und_x_variant":[
        "Almal\u0131",
        "Elmal\u0131"
    ],
    "wof:name":"Elmali",
    "wof:placetype":"locality"
},
  "geometry": {"coordinates":[40.76535,39.02894000000001],"type":"Point"}
}