{
  "type": "Feature",
  "properties": {
    "gn:admin1_code":"62",
    "gn:asciiname":"Pasacik",
    "gn:country_code":"TR",
    "gn:dem":1378,
    "gn:feature_class":"P",
    "gn:feature_code":"PPL",
    "gn:name":"Pa\u015fac\u0131k",
    "gn:population":0,
    "gn:timezone":"Europe/Istanbul",
    "iso:country":"TR",
    "name:tur_x_preferred":[
        "Pa\u015fac\u0131k"
    ],
    "name:und_x_variant":[
        "Pa\u015fa\u00e7\u0131k",
        "Oskih"
    ],
    "wof:name":"Pasacik",
    "wof:placetype":"locality"
},
  "geometry": {"coordinates":[38.97164,39.08306],"type":"Point"}
}