{
  "type": "Feature",
  "properties": {
    "gn:admin1_code":"37.0",
    "gn:asciiname":"Kirisoglu",
    "gn:country_code":"TR",
    "gn:dem":1184,
    "gn:feature_class":"P",
    "gn:feature_code":"PPL",
    "gn:name":"K\u0131r\u0131\u015fo\u011flu",
    "gn:population":0,
    "gn:timezone":"Europe/Istanbul",
    "iso:country":"TR",
    "name:msa_x_preferred":[
        "K\u0131r\u0131\u015fo\u011flu"
    ],
    "name:tur_x_preferred":[
        "K\u0131r\u0131\u015fo\u011flu"
    ],
    "name:und_x_variant":[
        "K\u0131r\u015fo",
        "Kir\u015fu",
        "K\u0131r\u0131\u015fo\u011flu"
    ],
    "name:vie_x_preferred":[
        "K\u0131r\u0131\u015fo\u011flu"
    ],
    "wof:name":"Kirisoglu",
    "wof:placetype":"locality"
},
  "geometry": {"coordinates":[33.64685,41.31484],"type":"Point"}
}