{
  "type": "Feature",
  "properties": {
    "gn:admin1_code":"80.0",
    "gn:asciiname":"Kulac",
    "gn:country_code":"TR",
    "gn:dem":1362,
    "gn:feature_class":"P",
    "gn:feature_code":"PPL",
    "gn:name":"Kula\u00e7",
    "gn:population":0,
    "gn:timezone":"Europe/Istanbul",
    "iso:country":"TR",
    "name:tur_x_preferred":[
        "Kula\u00e7"
    ],
    "wof:name":"Kulac",
    "wof:placetype":"locality"
},
  "geometry": {"coordinates":[42.86667,37.36667],"type":"Point"}
}