{
  "type": "Feature",
  "properties": {
    "gn:admin1_code":"89",
    "gn:asciiname":"Pazarlioglu",
    "gn:country_code":"TR",
    "gn:dem":551,
    "gn:feature_class":"P",
    "gn:feature_code":"PPL",
    "gn:name":"Pazarl\u0131o\u011flu",
    "gn:population":0,
    "gn:timezone":"Europe/Istanbul",
    "iso:country":"TR",
    "name:tur_x_preferred":[
        "Pazarl\u0131o\u011flu"
    ],
    "wof:name":"Pazarlioglu",
    "wof:placetype":"locality"
},
  "geometry": {"coordinates":[32.25761,41.34732],"type":"Point"}
}