{
  "type": "Feature",
  "properties": {
    "gn:admin1_code":"25.0",
    "gn:asciiname":"Yukari Bakracli",
    "gn:country_code":"TR",
    "gn:dem":1681,
    "gn:feature_class":"P",
    "gn:feature_code":"PPL",
    "gn:name":"Yukar\u0131 Bakra\u00e7l\u0131",
    "gn:population":0,
    "gn:timezone":"Europe/Istanbul",
    "iso:country":"TR",
    "name:tur_x_preferred":[
        "Yukar\u0131 Bakra\u00e7l\u0131"
    ],
    "name:und_x_variant":[
        "Yukar\u0131mernis",
        "Yukar\u0131bakra\u00e7l\u0131",
        "Yukar\u0131merinis"
    ],
    "wof:name":"Yukari Bakracli",
    "wof:placetype":"locality"
},
  "geometry": {"coordinates":[42.23968,40.6026],"type":"Point"}
}