{
  "type": "Feature",
  "properties": {
    "gn:admin1_code":"37.0",
    "gn:asciiname":"Calkaya",
    "gn:country_code":"TR",
    "gn:dem":922,
    "gn:feature_class":"P",
    "gn:feature_code":"PPL",
    "gn:name":"\u00c7alkaya",
    "gn:population":0,
    "gn:timezone":"Europe/Istanbul",
    "iso:country":"TR",
    "name:und_x_variant":[
        "Veres",
        "Veray",
        "\u00c7alkaya"
    ],
    "wof:name":"Calkaya",
    "wof:placetype":"locality"
},
  "geometry": {"coordinates":[33.14877,41.61519000000001],"type":"Point"}
}