{
  "type": "Feature",
  "properties": {
    "gn:admin1_code":"10",
    "gn:asciiname":"Subeylidere",
    "gn:country_code":"TR",
    "gn:dem":233,
    "gn:feature_class":"P",
    "gn:feature_code":"PPL",
    "gn:name":"S\u00fcbeylidere",
    "gn:population":0,
    "gn:timezone":"Europe/Istanbul",
    "iso:country":"TR",
    "name:tur_x_preferred":[
        "S\u00fcbeylidere"
    ],
    "wof:name":"Subeylidere",
    "wof:placetype":"locality"
},
  "geometry": {"coordinates":[27.02936,39.40612],"type":"Point"}
}