{
  "type": "Feature",
  "properties": {
    "gn:admin1_code":"21.0",
    "gn:asciiname":"Balcilar",
    "gn:country_code":"TR",
    "gn:dem":1190,
    "gn:feature_class":"P",
    "gn:feature_code":"PPL",
    "gn:name":"Balc\u0131lar",
    "gn:population":0,
    "gn:timezone":"Europe/Istanbul",
    "iso:country":"TR",
    "name:tur_x_preferred":[
        "Balc\u0131lar"
    ],
    "wof:name":"Balcilar",
    "wof:placetype":"locality"
},
  "geometry": {"coordinates":[39.44569,38.24613],"type":"Point"}
}