{
  "type": "Feature",
  "properties": {
    "gn:admin1_code":"44",
    "gn:asciiname":"Tastepe",
    "gn:country_code":"TR",
    "gn:dem":1385,
    "gn:feature_class":"P",
    "gn:feature_code":"PPL",
    "gn:name":"Ta\u015ftepe",
    "gn:population":0,
    "gn:timezone":"Europe/Istanbul",
    "iso:country":"TR",
    "name:und_x_variant":[
        "K\u00f6rmustafa",
        "Elhask\u00f6rmustafa",
        "Alkas K\u00f6r Mustafa",
        "Ta\u015ftepe",
        "Alkas"
    ],
    "wof:name":"Tastepe",
    "wof:placetype":"locality"
},
  "geometry": {"coordinates":[38.72024,38.06879],"type":"Point"}
}