{
  "type": "Feature",
  "properties": {
    "gn:admin1_code":"63",
    "gn:asciiname":"Tuncbilek",
    "gn:country_code":"TR",
    "gn:dem":677,
    "gn:feature_class":"P",
    "gn:feature_code":"PPL",
    "gn:name":"Tun\u00e7bilek",
    "gn:population":0,
    "gn:timezone":"Europe/Istanbul",
    "iso:country":"TR",
    "name:tur_x_preferred":[
        "Tun\u00e7bilek"
    ],
    "wof:name":"Tuncbilek",
    "wof:placetype":"locality"
},
  "geometry": {"coordinates":[39.61432,37.33593],"type":"Point"}
}