{
  "type": "Feature",
  "properties": {
    "gn:admin1_code":"39.0",
    "gn:asciiname":"Karahidir",
    "gn:country_code":"TR",
    "gn:dem":208,
    "gn:feature_class":"P",
    "gn:feature_code":"PPL",
    "gn:name":"Karah\u0131d\u0131r",
    "gn:population":0,
    "gn:timezone":"Europe/Istanbul",
    "iso:country":"TR",
    "wof:name":"Karahidir",
    "wof:placetype":"locality"
},
  "geometry": {"coordinates":[27.18699,41.7224],"type":"Point"}
}