{
  "type": "Feature",
  "properties": {
    "gn:admin1_code":"48",
    "gn:asciiname":"Bahce",
    "gn:country_code":"TR",
    "gn:dem":87,
    "gn:feature_class":"P",
    "gn:feature_code":"PPL",
    "gn:name":"Bah\u00e7e",
    "gn:population":0,
    "gn:timezone":"Europe/Istanbul",
    "iso:country":"TR",
    "name:tur_x_preferred":[
        "Bah\u00e7e"
    ],
    "name:tur_x_variant":[
        "Bah\u00e7ek\u00f6y"
    ],
    "wof:name":"Bahce",
    "wof:placetype":"locality"
},
  "geometry": {"coordinates":[27.76185,37.24774],"type":"Point"}
}