{
  "type": "Feature",
  "properties": {
    "gn:admin1_code":"21",
    "gn:asciiname":"Halkapinar",
    "gn:country_code":"TR",
    "gn:dem":771,
    "gn:feature_class":"P",
    "gn:feature_code":"PPL",
    "gn:name":"Halkap\u0131nar",
    "gn:population":0,
    "gn:timezone":"Europe/Istanbul",
    "iso:country":"TR",
    "name:tur_x_preferred":[
        "Yar\u0131mta\u015f"
    ],
    "name:und_x_variant":[
        "Halkap\u0131nar"
    ],
    "wof:name":"Halkapinar",
    "wof:placetype":"locality"
},
  "geometry": {"coordinates":[40.21419,37.76158],"type":"Point"}
}