{
  "type": "Feature",
  "properties": {
    "gn:admin1_code":"55.0",
    "gn:asciiname":"Gocebe",
    "gn:country_code":"TR",
    "gn:dem":767,
    "gn:feature_class":"P",
    "gn:feature_code":"PPL",
    "gn:name":"G\u00f6\u00e7ebe",
    "gn:population":0,
    "gn:timezone":"Europe/Istanbul",
    "iso:country":"TR",
    "wof:name":"Gocebe",
    "wof:placetype":"locality"
},
  "geometry": {"coordinates":[36.01298,41.14347],"type":"Point"}
}