{
  "type": "Feature",
  "properties": {
    "gn:admin1_code":"87",
    "gn:asciiname":"Fazlioglu",
    "gn:country_code":"TR",
    "gn:dem":441,
    "gn:feature_class":"P",
    "gn:feature_code":"PPL",
    "gn:name":"Fazl\u0131o\u011flu",
    "gn:population":0,
    "gn:timezone":"Europe/Istanbul",
    "iso:country":"TR",
    "wof:name":"Fazlioglu",
    "wof:placetype":"locality"
},
  "geometry": {"coordinates":[32.57776,41.45458],"type":"Point"}
}