{
  "type": "Feature",
  "properties": {
    "gn:admin1_code":"63.0",
    "gn:asciiname":"Holik",
    "gn:country_code":"TR",
    "gn:dem":497,
    "gn:feature_class":"P",
    "gn:feature_code":"PPL",
    "gn:name":"Holik",
    "gn:population":0,
    "gn:timezone":"Europe/Istanbul",
    "iso:country":"TR",
    "name:und_x_variant":[
        "Kholik",
        "Holik",
        "D\u00fczl\u00fcce"
    ],
    "wof:name":"Holik",
    "wof:placetype":"locality"
},
  "geometry": {"coordinates":[38.12401,36.94316],"type":"Point"}
}