{
  "type": "Feature",
  "properties": {
    "gn:admin1_code":"59.0",
    "gn:asciiname":"Soylu",
    "gn:country_code":"TR",
    "gn:dem":94,
    "gn:feature_class":"P",
    "gn:feature_code":"PPL",
    "gn:name":"Soylu",
    "gn:population":0,
    "gn:timezone":"Europe/Istanbul",
    "iso:country":"TR",
    "name:und_x_variant":[
        "S\u0131r\u0131ns\u0131ll\u0131",
        "Soylu"
    ],
    "wof:name":"Soylu",
    "wof:placetype":"locality"
},
  "geometry": {"coordinates":[27.08717,41.012],"type":"Point"}
}