{
  "type": "Feature",
  "properties": {
    "gn:admin1_code":"41.0",
    "gn:asciiname":"Havuzdere",
    "gn:country_code":"TR",
    "gn:dem":200,
    "gn:feature_class":"P",
    "gn:feature_code":"PPL",
    "gn:name":"Havuzdere",
    "gn:population":0,
    "gn:timezone":"Europe/Istanbul",
    "iso:country":"TR",
    "name:tur_x_preferred":[
        "Havuzdere"
    ],
    "wof:name":"Havuzdere",
    "wof:placetype":"locality"
},
  "geometry": {"coordinates":[29.95,40.68333],"type":"Point"}
}