{
  "type": "Feature",
  "properties": {
    "gn:country":"TR",
    "gn:fcode":"PPL",
    "gn:population":3249,
    "iso:country":"TR",
    "name:ara_x_preferred":[
        "\u0642\u0627\u0631\u0627\u0628\u0648\u0631\u0648\u0646"
    ],
    "name:arz_x_preferred":[
        "\u0642\u0627\u0631\u0627\u0628\u0648\u0631\u0648\u0646"
    ],
    "name:ast_x_preferred":[
        "Karaburun"
    ],
    "name:aze_x_preferred":[
        "Qaraburun"
    ],
    "name:bul_x_preferred":[
        "\u041a\u0430\u0440\u0430\u0431\u0443\u0440\u0443\u043d"
    ],
    "name:cat_x_preferred":[
        "Karaburun"
    ],
    "name:ceb_x_preferred":[
        "Karaburun \u0130l\u00e7esi"
    ],
    "name:che_x_preferred":[
        "\u041a\u0430\u0440\u0430\u0431\u0443\u0440\u0443\u043d"
    ],
    "name:deu_x_preferred":[
        "Karaburun"
    ],
    "name:diq_x_preferred":[
        "Karaburun"
    ],
    "name:eng_x_preferred":[
        "Karaburun"
    ],
    "name:epo_x_preferred":[
        "Karaburun"
    ],
    "name:fas_x_preferred":[
        "\u06a9\u0627\u0631\u0627\u0628\u0648\u0631\u0648\u0646"
    ],
    "name:fra_x_preferred":[
        "Karaburun"
    ],
    "name:hun_x_preferred":[
        "Karaburun"
    ],
    "name:ita_x_preferred":[
        "Distretto di Karaburun"
    ],
    "name:jpn_x_preferred":[
        "\u30ab\u30e9\u30d6\u30eb\u30f3"
    ],
    "name:kur_x_preferred":[
        "Karaburun"
    ],
    "name:lit_x_preferred":[
        "Karaburunas"
    ],
    "name:mrj_x_preferred":[
        "\u041a\u0430\u0440\u0430\u0431\u0443\u0440\u0443\u043d"
    ],
    "name:msa_x_preferred":[
        "Karaburun"
    ],
    "name:nan_x_preferred":[
        "Karaburun"
    ],
    "name:nld_x_preferred":[
        "Karaburun"
    ],
    "name:nob_x_preferred":[
        "Karaburun"
    ],
    "name:spa_x_preferred":[
        "Karaburun"
    ],
    "name:swa_x_preferred":[
        "Karaburun"
    ],
    "name:tat_x_preferred":[
        "\u041a\u0430\u0440\u0430\u0431\u0443\u0440\u0443\u043d"
    ],
    "name:tur_x_preferred":[
        "Karaburun"
    ],
    "name:und_x_variant":[
        "Ah\u0131rl\u0131"
    ],
    "name:urd_x_preferred":[
        "\u0642\u0631\u06c1 \u0628\u0648\u0631\u0648\u0646"
    ],
    "name:vie_x_preferred":[
        "Karaburun"
    ],
    "name:zho_x_preferred":[
        "\u5361\u62c9\u5e03\u502b"
    ],
    "qs:name":"Karaburun",
    "qs:photos_9r":0,
    "qs:photos_sr":0,
    "qs:pop_sr":"4",
    "wd:wordcount":1046,
    "wof:name":"Karaburun",
    "wof:placetype":"locality",
    "wof:population":3249
},
  "geometry": {"coordinates":[26.5111,38.63967],"type":"Point"}
}