{
  "type": "Feature",
  "properties": {
    "gn:admin1_code":"60.0",
    "gn:asciiname":"Yeniturac",
    "gn:country_code":"TR",
    "gn:dem":795,
    "gn:feature_class":"P",
    "gn:feature_code":"PPL",
    "gn:name":"Yenitura\u00e7",
    "gn:population":0,
    "gn:timezone":"Europe/Istanbul",
    "iso:country":"TR",
    "name:und_x_variant":[
        "Muhacirtura\u00e7",
        "Yenitura\u00e7"
    ],
    "wof:name":"Yeniturac",
    "wof:placetype":"locality"
},
  "geometry": {"coordinates":[37.24344,40.42224],"type":"Point"}
}