{
  "type": "Feature",
  "properties": {
    "gn:admin1_code":"41.0",
    "gn:asciiname":"Haci",
    "gn:country_code":"TR",
    "gn:dem":300,
    "gn:feature_class":"P",
    "gn:feature_code":"PPL",
    "gn:name":"Hac\u0131",
    "gn:population":0,
    "gn:timezone":"Europe/Istanbul",
    "iso:country":"TR",
    "name:und_x_variant":[
        "Hadji",
        "Hac\u0131yusuflar",
        "Hac\u0131"
    ],
    "wof:name":"Haci",
    "wof:placetype":"locality"
},
  "geometry": {"coordinates":[29.75,40.85],"type":"Point"}
}