{
  "type": "Feature",
  "properties": {
    "gn:admin1_code":"55.0",
    "gn:asciiname":"Corak",
    "gn:country_code":"TR",
    "gn:dem":184,
    "gn:feature_class":"P",
    "gn:feature_code":"PPL",
    "gn:name":"\u00c7orak",
    "gn:population":0,
    "gn:timezone":"Europe/Istanbul",
    "iso:country":"TR",
    "wof:name":"Corak",
    "wof:placetype":"locality"
},
  "geometry": {"coordinates":[36.26871,41.24467],"type":"Point"}
}