{
  "type": "Feature",
  "properties": {
    "gn:admin1_code":"80.0",
    "gn:asciiname":"Cavushan",
    "gn:country_code":"TR",
    "gn:dem":577,
    "gn:feature_class":"P",
    "gn:feature_code":"PPL",
    "gn:name":"\u00c7avu\u015fhan",
    "gn:population":0,
    "gn:timezone":"Europe/Istanbul",
    "iso:country":"TR",
    "name:tur_x_preferred":[
        "\u00c7avu\u015fhan"
    ],
    "wof:name":"Cavushan",
    "wof:placetype":"locality"
},
  "geometry": {"coordinates":[42.29544,37.45933],"type":"Point"}
}