{
  "type": "Feature",
  "properties": {
    "gn:admin1_code":"12.0",
    "gn:asciiname":"Keklikdere",
    "gn:country_code":"TR",
    "gn:dem":1397,
    "gn:feature_class":"P",
    "gn:feature_code":"PPL",
    "gn:name":"Keklikdere",
    "gn:population":0,
    "gn:timezone":"Europe/Istanbul",
    "iso:country":"TR",
    "name:tur_x_preferred":[
        "Keklikdere"
    ],
    "wof:name":"Keklikdere",
    "wof:placetype":"locality"
},
  "geometry": {"coordinates":[40.65373,38.73214],"type":"Point"}
}