{
  "type": "Feature",
  "properties": {
    "gn:admin1_code":"16.0",
    "gn:asciiname":"Imrali",
    "gn:country_code":"TR",
    "gn:dem":9,
    "gn:feature_class":"P",
    "gn:feature_code":"PPL",
    "gn:name":"\u0130mral\u0131",
    "gn:population":0,
    "gn:timezone":"Europe/Istanbul",
    "iso:country":"TR",
    "name:und_x_variant":[
        "Kalolimno",
        "\u0130mral\u0131"
    ],
    "wof:name":"Imrali",
    "wof:placetype":"locality"
},
  "geometry": {"coordinates":[28.54243,40.55569000000001],"type":"Point"}
}