{
  "type": "Feature",
  "properties": {
    "gn:admin1_code":"35",
    "gn:asciiname":"Telekler",
    "gn:country_code":"TR",
    "gn:dem":256,
    "gn:feature_class":"P",
    "gn:feature_code":"PPL",
    "gn:name":"Telekler",
    "gn:population":0,
    "gn:timezone":"Europe/Istanbul",
    "iso:country":"TR",
    "wof:name":"Telekler",
    "wof:placetype":"locality"
},
  "geometry": {"coordinates":[27.2155,38.66302],"type":"Point"}
}