{
  "type": "Feature",
  "properties": {
    "gn:admin1_code":"80.0",
    "gn:asciiname":"Cudiye",
    "gn:cc2":"TR",
    "gn:country_code":"TR",
    "gn:dem":390,
    "gn:feature_class":"P",
    "gn:feature_code":"PPL",
    "gn:name":"Cudiye",
    "gn:population":0,
    "gn:timezone":"Europe/Istanbul",
    "iso:country":"TR",
    "name:und_x_variant":[
        "Dzhudiyet",
        "Cudiyet",
        "Cudiye"
    ],
    "wof:name":"Cudiye",
    "wof:placetype":"locality"
},
  "geometry": {"coordinates":[42.18389000000001,37.30417],"type":"Point"}
}