{
  "type": "Feature",
  "properties": {
    "gn:admin1_code":"69.0",
    "gn:asciiname":"Kusluk",
    "gn:country_code":"TR",
    "gn:dem":1731,
    "gn:feature_class":"P",
    "gn:feature_code":"PPL",
    "gn:name":"Ku\u015fluk",
    "gn:population":0,
    "gn:timezone":"Europe/Istanbul",
    "iso:country":"TR",
    "name:tur_x_preferred":[
        "Ku\u015fluk"
    ],
    "wof:name":"Kusluk",
    "wof:placetype":"locality"
},
  "geometry": {"coordinates":[39.03164,40.54429],"type":"Point"}
}