{
  "type": "Feature",
  "properties": {
    "gn:admin1_code":"13.0",
    "gn:asciiname":"Ocakbasi",
    "gn:country_code":"TR",
    "gn:dem":1621,
    "gn:feature_class":"P",
    "gn:feature_code":"PPL",
    "gn:name":"Ocakba\u015f\u0131",
    "gn:population":0,
    "gn:timezone":"Europe/Istanbul",
    "iso:country":"TR",
    "name:tur_x_preferred":[
        "Ocakba\u015f\u0131"
    ],
    "wof:name":"Ocakbasi",
    "wof:placetype":"locality"
},
  "geometry": {"coordinates":[41.85574,38.33876],"type":"Point"}
}