{
  "type": "Feature",
  "properties": {
    "gn:admin1_code":"68.0",
    "gn:asciiname":"Akcakavak",
    "gn:country_code":"TR",
    "gn:dem":543,
    "gn:feature_class":"P",
    "gn:feature_code":"PPL",
    "gn:name":"Ak\u00e7akavak",
    "gn:population":0,
    "gn:timezone":"Europe/Istanbul",
    "iso:country":"TR",
    "wof:name":"Akcakavak",
    "wof:placetype":"locality"
},
  "geometry": {"coordinates":[32.05495,40.11402],"type":"Point"}
}