{
  "type": "Feature",
  "properties": {
    "gn:admin1_code":"63",
    "gn:asciiname":"Yukari Modan",
    "gn:country_code":"TR",
    "gn:dem":1120,
    "gn:feature_class":"P",
    "gn:feature_code":"PPL",
    "gn:name":"Yukar\u0131 Modan",
    "gn:population":0,
    "gn:timezone":"Europe/Istanbul",
    "iso:country":"TR",
    "name:tur_x_preferred":[
        "Yukar\u0131 Modan"
    ],
    "wof:name":"Yukari Modan",
    "wof:placetype":"locality"
},
  "geometry": {"coordinates":[39.48333,37.88333],"type":"Point"}
}