{
  "type": "Feature",
  "properties": {
    "gn:admin1_code":"03",
    "gn:asciiname":"Belkaracaoren",
    "gn:cc2":"TR",
    "gn:country_code":"TR",
    "gn:dem":1409,
    "gn:feature_class":"P",
    "gn:feature_code":"PPL",
    "gn:name":"Belkaraca\u00f6ren",
    "gn:population":0,
    "gn:timezone":"Europe/Istanbul",
    "iso:country":"TR",
    "name:und_x_variant":[
        "Belkaracaviran",
        "Belkaracaveran",
        "Belkaraca\u00f6ren"
    ],
    "wof:name":"Belkaracaoren",
    "wof:placetype":"locality"
},
  "geometry": {"coordinates":[30.56389,38.6375],"type":"Point"}
}