{
  "type": "Feature",
  "properties": {
    "gn:admin1_code":"21",
    "gn:asciiname":"Kutlualan",
    "gn:country_code":"TR",
    "gn:dem":716,
    "gn:feature_class":"P",
    "gn:feature_code":"PPL",
    "gn:name":"Kutlualan",
    "gn:population":0,
    "gn:timezone":"Europe/Istanbul",
    "iso:country":"TR",
    "name:tur_x_preferred":[
        "Kutlualan"
    ],
    "wof:name":"Kutlualan",
    "wof:placetype":"locality"
},
  "geometry": {"coordinates":[40.70861,38.04842],"type":"Point"}
}