{
  "type": "Feature",
  "properties": {
    "gn:admin1_code":"24",
    "gn:asciiname":"Mollakoy",
    "gn:country_code":"TR",
    "gn:dem":1176,
    "gn:feature_class":"P",
    "gn:feature_code":"PPL",
    "gn:name":"Mollak\u00f6y",
    "gn:population":0,
    "gn:timezone":"Europe/Istanbul",
    "iso:country":"TR",
    "name:tur_x_preferred":[
        "Mollak\u00f6y"
    ],
    "wof:name":"Mollakoy",
    "wof:placetype":"locality"
},
  "geometry": {"coordinates":[39.57828,39.64098],"type":"Point"}
}