{
  "type": "Feature",
  "properties": {
    "gn:admin1_code":"83",
    "gn:asciiname":"Cinarli",
    "gn:country_code":"TR",
    "gn:dem":852,
    "gn:feature_class":"P",
    "gn:feature_code":"PPL",
    "gn:name":"\u00c7\u0131narl\u0131",
    "gn:population":0,
    "gn:timezone":"Europe/Istanbul",
    "iso:country":"TR",
    "name:und_x_variant":[
        "E\u015fek\u00e7\u0131nar",
        "\u00c7\u0131narl\u0131"
    ],
    "wof:name":"Cinarli",
    "wof:placetype":"locality"
},
  "geometry": {"coordinates":[36.80422,36.94382],"type":"Point"}
}