{
  "type": "Feature",
  "properties": {
    "gn:admin1_code":"35",
    "gn:asciiname":"Ozbek",
    "gn:country_code":"TR",
    "gn:dem":559,
    "gn:feature_class":"P",
    "gn:feature_code":"PPL",
    "gn:name":"\u00d6zbek",
    "gn:population":0,
    "gn:timezone":"Europe/Istanbul",
    "iso:country":"TR",
    "name:ceb_x_preferred":[
        "Ozbek"
    ],
    "name:swe_x_preferred":[
        "Ozbek"
    ],
    "name:tur_x_preferred":[
        "\u00d6zbek"
    ],
    "wof:name":"Ozbek",
    "wof:placetype":"locality"
},
  "geometry": {"coordinates":[27.29576,38.52669],"type":"Point"}
}