{
  "type": "Feature",
  "properties": {
    "gn:admin1_code":"48",
    "gn:admin2_code":"7732940.0",
    "gn:asciiname":"Kayakoy",
    "gn:country_code":"TR",
    "gn:dem":145,
    "gn:feature_class":"P",
    "gn:feature_code":"PPL",
    "gn:name":"Kayak\u00f6y",
    "gn:population":0,
    "gn:timezone":"Europe/Istanbul",
    "iso:country":"TR",
    "name:deu_x_preferred":[
        "Kayak\u00f6y"
    ],
    "name:ell_x_preferred":[
        "\u039b\u03b9\u03b2\u03af\u03c3\u03b9"
    ],
    "name:fra_x_preferred":[
        "Kayak\u00f6y"
    ],
    "name:ita_x_preferred":[
        "Kayak\u00f6y"
    ],
    "name:pol_x_preferred":[
        "Kayak\u00f6y"
    ],
    "name:por_x_preferred":[
        "Kayak\u00f6y"
    ],
    "name:swe_x_preferred":[
        "Kayak\u00f6y"
    ],
    "name:tur_x_preferred":[
        "Kayak\u00f6y"
    ],
    "name:und_x_variant":[
        "Kaya"
    ],
    "name:vie_x_preferred":[
        "Kayak\u00f6y"
    ],
    "wof:name":"Kayakoy",
    "wof:placetype":"locality"
},
  "geometry": {"coordinates":[29.08886,36.58141],"type":"Point"}
}