{
  "type": "Feature",
  "properties": {
    "gn:admin1_code":"68",
    "gn:asciiname":"Ergin",
    "gn:country_code":"TR",
    "gn:dem":1050,
    "gn:feature_class":"P",
    "gn:feature_code":"PPL",
    "gn:name":"Ergin",
    "gn:population":0,
    "gn:timezone":"Europe/Istanbul",
    "iso:country":"TR",
    "wof:name":"Ergin",
    "wof:placetype":"locality"
},
  "geometry": {"coordinates":[33.15701,39.64417],"type":"Point"}
}