{
  "type": "Feature",
  "properties": {
    "gn:admin1_code":"09",
    "gn:asciiname":"Doganyurt",
    "gn:country_code":"TR",
    "gn:dem":96,
    "gn:feature_class":"P",
    "gn:feature_code":"PPL",
    "gn:name":"Do\u011fanyurt",
    "gn:population":0,
    "gn:timezone":"Europe/Istanbul",
    "iso:country":"TR",
    "name:tur_x_preferred":[
        "Do\u011fanyurt"
    ],
    "wof:name":"Doganyurt",
    "wof:placetype":"locality"
},
  "geometry": {"coordinates":[27.96818,37.59782],"type":"Point"}
}