{
  "type": "Feature",
  "properties": {
    "gn:admin1_code":"37.0",
    "gn:asciiname":"Siragomu",
    "gn:country_code":"TR",
    "gn:dem":1035,
    "gn:feature_class":"P",
    "gn:feature_code":"PPL",
    "gn:name":"S\u0131rag\u00f6m\u00fc",
    "gn:population":0,
    "gn:timezone":"Europe/Istanbul",
    "iso:country":"TR",
    "name:und_x_variant":[
        "S\u0131rag\u00fcm\u00fc",
        "S\u0131rag\u00f6m\u00fc",
        "Sar\u0131g\u00f6m\u00fc"
    ],
    "wof:name":"Siragomu",
    "wof:placetype":"locality"
},
  "geometry": {"coordinates":[33.30651,41.19204000000001],"type":"Point"}
}