{
  "type": "Feature",
  "properties": {
    "gn:admin1_code":"19.0",
    "gn:asciiname":"Yogunpelit",
    "gn:country_code":"TR",
    "gn:dem":881,
    "gn:feature_class":"P",
    "gn:feature_code":"PPL",
    "gn:name":"Yo\u011funpelit",
    "gn:population":0,
    "gn:timezone":"Europe/Istanbul",
    "iso:country":"TR",
    "name:und_x_variant":[
        "Yo\u011funpelit",
        "Yo\u011fumpelit"
    ],
    "wof:name":"Yogunpelit",
    "wof:placetype":"locality"
},
  "geometry": {"coordinates":[35.02352,40.46667],"type":"Point"}
}