{
  "type": "Feature",
  "properties": {
    "gn:admin1_code":"71",
    "gn:asciiname":"Ortakonak",
    "gn:country_code":"TR",
    "gn:dem":1005,
    "gn:feature_class":"P",
    "gn:feature_code":"PPL",
    "gn:name":"Ortakonak",
    "gn:population":0,
    "gn:timezone":"Europe/Istanbul",
    "iso:country":"TR",
    "name:und_x_variant":[
        "Zivecik",
        "Ortakonak"
    ],
    "wof:name":"Ortakonak",
    "wof:placetype":"locality"
},
  "geometry": {"coordinates":[32.69857,37.96451],"type":"Point"}
}