{
  "type": "Feature",
  "properties": {
    "gn:admin1_code":"50",
    "gn:asciiname":"Cigdem",
    "gn:country_code":"TR",
    "gn:dem":1185,
    "gn:feature_class":"P",
    "gn:feature_code":"PPL",
    "gn:name":"\u00c7i\u011fdem",
    "gn:population":0,
    "gn:timezone":"Europe/Istanbul",
    "iso:country":"TR",
    "name:und_x_variant":[
        "\u00c7i\u011fdem",
        "\u00c7i\u011fdemk\u00f6y"
    ],
    "wof:name":"Cigdem",
    "wof:placetype":"locality"
},
  "geometry": {"coordinates":[34.51992,39.00089000000001],"type":"Point"}
}