{
  "type": "Feature",
  "properties": {
    "gn:admin1_code":"68.0",
    "gn:asciiname":"Uregil",
    "gn:country_code":"TR",
    "gn:dem":862,
    "gn:feature_class":"P",
    "gn:feature_code":"PPL",
    "gn:name":"\u00dcre\u011fil",
    "gn:population":0,
    "gn:timezone":"Europe/Istanbul",
    "iso:country":"TR",
    "name:und_x_variant":[
        "\u00dcrekil",
        "\u00dcre\u011fil"
    ],
    "wof:name":"Uregil",
    "wof:placetype":"locality"
},
  "geometry": {"coordinates":[32.07762,40.26043],"type":"Point"}
}