{
  "type": "Feature",
  "properties": {
    "gn:admin1_code":"25.0",
    "gn:asciiname":"Verintap",
    "gn:country_code":"TR",
    "gn:dem":2042,
    "gn:feature_class":"P",
    "gn:feature_code":"PPL",
    "gn:name":"Verintap",
    "gn:population":0,
    "gn:timezone":"Europe/Istanbul",
    "iso:country":"TR",
    "wof:name":"Verintap",
    "wof:placetype":"locality"
},
  "geometry": {"coordinates":[41.93333,40.26667],"type":"Point"}
}