{
  "type": "Feature",
  "properties": {
    "gn:admin1_code":"68.0",
    "gn:asciiname":"Eskicote",
    "gn:country_code":"TR",
    "gn:dem":1151,
    "gn:feature_class":"P",
    "gn:feature_code":"PPL",
    "gn:name":"Eski\u00e7\u00f6te",
    "gn:population":0,
    "gn:timezone":"Europe/Istanbul",
    "iso:country":"TR",
    "wof:name":"Eskicote",
    "wof:placetype":"locality"
},
  "geometry": {"coordinates":[33.21706,40.21573],"type":"Point"}
}