{
  "type": "Feature",
  "properties": {
    "gn:admin1_code":"62",
    "gn:asciiname":"Daloren",
    "gn:country_code":"TR",
    "gn:dem":1938,
    "gn:feature_class":"P",
    "gn:feature_code":"PPL",
    "gn:name":"Dal\u00f6ren",
    "gn:population":0,
    "gn:timezone":"Europe/Istanbul",
    "iso:country":"TR",
    "name:und_x_variant":[
        "Dal\u00f6ren",
        "Hopik"
    ],
    "wof:name":"Daloren",
    "wof:placetype":"locality"
},
  "geometry": {"coordinates":[39.28727,39.14991],"type":"Point"}
}