{
  "type": "Feature",
  "properties": {
    "gn:admin1_code":"23",
    "gn:asciiname":"Bayindir",
    "gn:country_code":"TR",
    "gn:dem":1214,
    "gn:feature_class":"P",
    "gn:feature_code":"PPL",
    "gn:name":"Bay\u0131nd\u0131r",
    "gn:population":0,
    "gn:timezone":"Europe/Istanbul",
    "iso:country":"TR",
    "name:tur_x_preferred":[
        "Bay\u0131nd\u0131r"
    ],
    "wof:name":"Bayindir",
    "wof:placetype":"locality"
},
  "geometry": {"coordinates":[38.66548,38.8158],"type":"Point"}
}