{
  "type": "Feature",
  "properties": {
    "gn:admin1_code":"43",
    "gn:asciiname":"Yapilcan",
    "gn:country_code":"TR",
    "gn:dem":1022,
    "gn:feature_class":"P",
    "gn:feature_code":"PPL",
    "gn:name":"Yap\u0131lcan",
    "gn:population":0,
    "gn:timezone":"Europe/Istanbul",
    "iso:country":"TR",
    "name:tur_x_preferred":[
        "Yap\u0131lcan"
    ],
    "wof:name":"Yapilcan",
    "wof:placetype":"locality"
},
  "geometry": {"coordinates":[30.16127,39.06518],"type":"Point"}
}