{
  "type": "Feature",
  "properties": {
    "iso:country":"TR",
    "name:eng_x_preferred":[
        "Nisantepe"
    ],
    "name:tur_x_preferred":[
        "Ni\u015fantepe"
    ],
    "wof:name":"Nisantepe",
    "wof:placetype":"neighbourhood"
},
  "geometry": {"coordinates":[29.26093371197083,41.04110314036116],"type":"Point"}
}