{
  "type": "Feature",
  "properties": {
    "gn:country":"TR",
    "gn:fcode":"PPL",
    "gn:population":765,
    "iso:country":"TR",
    "name:cat_x_preferred":[
        "D\u00fczoba"
    ],
    "name:ceb_x_preferred":[
        "D\u00fczoba"
    ],
    "name:ces_x_preferred":[
        "D\u00fczoba"
    ],
    "name:che_x_preferred":[
        "\u0414\u0443\u044c\u0437\u043e\u0431\u0430"
    ],
    "name:dan_x_preferred":[
        "D\u00fczoba"
    ],
    "name:deu_x_preferred":[
        "D\u00fczoba"
    ],
    "name:eng_x_preferred":[
        "D\u00fczoba"
    ],
    "name:eus_x_preferred":[
        "D\u00fczoba"
    ],
    "name:fin_x_preferred":[
        "D\u00fczoba"
    ],
    "name:glg_x_preferred":[
        "D\u00fczoba"
    ],
    "name:ita_x_preferred":[
        "D\u00fczoba"
    ],
    "name:nld_x_preferred":[
        "D\u00fczoba"
    ],
    "name:nno_x_preferred":[
        "D\u00fczoba"
    ],
    "name:nob_x_preferred":[
        "D\u00fczoba"
    ],
    "name:oci_x_preferred":[
        "D\u00fczoba"
    ],
    "name:pol_x_preferred":[
        "D\u00fczoba"
    ],
    "name:por_x_preferred":[
        "D\u00fczoba"
    ],
    "name:ron_x_preferred":[
        "D\u00fczoba"
    ],
    "name:sco_x_preferred":[
        "D\u00fczoba"
    ],
    "name:slk_x_preferred":[
        "D\u00fczoba"
    ],
    "name:slv_x_preferred":[
        "D\u00fczoba"
    ],
    "name:spa_x_preferred":[
        "D\u00fczoba"
    ],
    "name:swe_x_preferred":[
        "D\u00fczoba"
    ],
    "name:tat_x_preferred":[
        "\u0414\u04af\u0437\u043e\u0431\u0430"
    ],
    "name:tgl_x_preferred":[
        "D\u00fczoba"
    ],
    "name:tur_x_preferred":[
        "D\u00fczoba"
    ],
    "name:und_x_variant":[
        "Rish"
    ],
    "name:vie_x_preferred":[
        "D\u00fczoba"
    ],
    "name:war_x_preferred":[
        "D\u00fczoba"
    ],
    "qs:name":"D\u00fczoba",
    "qs:photos_9r":0,
    "qs:photos_sr":0,
    "qs:pop_sr":"2",
    "wof:name":"D\u00fczoba",
    "wof:placetype":"locality",
    "wof:population":765
},
  "geometry": {"coordinates":[41.27248,37.39212],"type":"Point"}
}