{
  "type": "Feature",
  "properties": {
    "gn:admin1_code":"44",
    "gn:asciiname":"Misirdere",
    "gn:country_code":"TR",
    "gn:dem":837,
    "gn:feature_class":"P",
    "gn:feature_code":"PPL",
    "gn:name":"M\u0131s\u0131rdere",
    "gn:population":0,
    "gn:timezone":"Europe/Istanbul",
    "iso:country":"TR",
    "name:tur_x_preferred":[
        "M\u0131s\u0131rdere"
    ],
    "name:und_x_variant":[
        "M\u0131s\u0131rderesi K\u00f6y\u00fc",
        "M\u0131s\u0131rderesi"
    ],
    "wof:name":"Misirdere",
    "wof:placetype":"locality"
},
  "geometry": {"coordinates":[38.11956,38.55896],"type":"Point"}
}