{
  "type": "Feature",
  "properties": {
    "gn:admin1_code":"09",
    "gn:asciiname":"Geyre",
    "gn:country_code":"TR",
    "gn:dem":515,
    "gn:feature_class":"P",
    "gn:feature_code":"PPL",
    "gn:name":"Geyre",
    "gn:population":0,
    "gn:timezone":"Europe/Istanbul",
    "iso:country":"TR",
    "name:ceb_x_preferred":[
        "Geyre"
    ],
    "name:ita_x_preferred":[
        "Geyre"
    ],
    "name:vie_x_preferred":[
        "Geyre"
    ],
    "wof:name":"Geyre",
    "wof:placetype":"locality"
},
  "geometry": {"coordinates":[28.71052,37.70996],"type":"Point"}
}