{
  "type": "Feature",
  "properties": {
    "gn:admin1_code":"82.0",
    "gn:asciiname":"Corekciler",
    "gn:country_code":"TR",
    "gn:dem":933,
    "gn:feature_class":"P",
    "gn:feature_code":"PPL",
    "gn:name":"\u00c7\u00f6rek\u00e7iler",
    "gn:population":0,
    "gn:timezone":"Europe/Istanbul",
    "iso:country":"TR",
    "wof:name":"Corekciler",
    "wof:placetype":"locality"
},
  "geometry": {"coordinates":[33.45867,40.85343],"type":"Point"}
}