{
  "type": "Feature",
  "properties": {
    "gn:admin1_code":"35",
    "gn:asciiname":"Yayla",
    "gn:country_code":"TR",
    "gn:dem":758,
    "gn:feature_class":"P",
    "gn:feature_code":"PPL",
    "gn:name":"Yayla",
    "gn:population":0,
    "gn:timezone":"Europe/Istanbul",
    "iso:country":"TR",
    "name:ceb_x_preferred":[
        "Yayla"
    ],
    "name:swe_x_preferred":[
        "Yayla"
    ],
    "name:tur_x_preferred":[
        "Yayla"
    ],
    "name:uzb_x_preferred":[
        "Yayla"
    ],
    "wof:name":"Yayla",
    "wof:placetype":"locality"
},
  "geometry": {"coordinates":[27.80426,38.00492],"type":"Point"}
}