{
  "type": "Feature",
  "properties": {
    "gn:admin1_code":"93.0",
    "gn:asciiname":"Uckopru",
    "gn:country_code":"TR",
    "gn:dem":236,
    "gn:feature_class":"P",
    "gn:feature_code":"PPL",
    "gn:name":"\u00dc\u00e7k\u00f6pr\u00fc",
    "gn:population":0,
    "gn:timezone":"Europe/Istanbul",
    "iso:country":"TR",
    "name:und_x_variant":[
        "Hac\u0131s\u00fcleyman",
        "S\u00fcleymanbey",
        "Hac\u0131s\u00fcleymanbey",
        "\u00dc\u00e7k\u00f6pr\u00fc",
        "\u00dc\u00e7k\u00f6pr\u00fcbo\u011faz\u0131"
    ],
    "wof:name":"Uckopru",
    "wof:placetype":"locality"
},
  "geometry": {"coordinates":[31.25311,40.79627],"type":"Point"}
}