{
  "type": "Feature",
  "properties": {
    "gn:admin1_code":"11",
    "gn:asciiname":"Tekeciler",
    "gn:country_code":"TR",
    "gn:dem":670,
    "gn:feature_class":"P",
    "gn:feature_code":"PPL",
    "gn:name":"Tekeciler",
    "gn:population":0,
    "gn:timezone":"Europe/Istanbul",
    "iso:country":"TR",
    "name:tur_x_preferred":[
        "Tekeciler"
    ],
    "wof:name":"Tekeciler",
    "wof:placetype":"locality"
},
  "geometry": {"coordinates":[30.39898,40.22034],"type":"Point"}
}