{
  "type": "Feature",
  "properties": {
    "gn:admin1_code":"03",
    "gn:asciiname":"Agizkara Mahallesi",
    "gn:country_code":"TR",
    "gn:dem":1500,
    "gn:feature_class":"P",
    "gn:feature_code":"PPL",
    "gn:name":"A\u011f\u0131zkara Mahallesi",
    "gn:population":0,
    "gn:timezone":"Europe/Istanbul",
    "iso:country":"TR",
    "wof:name":"Agizkara Mahallesi",
    "wof:placetype":"locality"
},
  "geometry": {"coordinates":[30.75962,39.00187],"type":"Point"}
}