{
  "type": "Feature",
  "properties": {
    "gn:admin1_code":"25.0",
    "gn:asciiname":"Kapikale",
    "gn:country_code":"TR",
    "gn:dem":2103,
    "gn:feature_class":"P",
    "gn:feature_code":"PPL",
    "gn:name":"Kap\u0131kale",
    "gn:population":0,
    "gn:timezone":"Europe/Istanbul",
    "iso:country":"TR",
    "name:tur_x_preferred":[
        "Kap\u0131kale"
    ],
    "wof:name":"Kapikale",
    "wof:placetype":"locality"
},
  "geometry": {"coordinates":[40.58682,40.05712],"type":"Point"}
}