{
  "type": "Feature",
  "properties": {
    "gn:admin1_code":"84.0",
    "gn:asciiname":"Dolbentli",
    "gn:country_code":"TR",
    "gn:dem":1861,
    "gn:feature_class":"P",
    "gn:feature_code":"PPL",
    "gn:name":"D\u00f6lbentli",
    "gn:population":0,
    "gn:timezone":"Europe/Istanbul",
    "iso:country":"TR",
    "name:eng_x_preferred":[
        "D\u00f6lbentli"
    ],
    "name:rus_x_preferred":[
        "\u0414\u043e\u043b\u0431\u0430\u043d\u0442\u043b\u0430"
    ],
    "name:und_x_variant":[
        "D\u00fclbentli",
        "D\u00f6lbentli"
    ],
    "wof:name":"Dolbentli",
    "wof:placetype":"locality"
},
  "geometry": {"coordinates":[42.86032,40.41379000000001],"type":"Point"}
}