{
  "type": "Feature",
  "properties": {
    "gn:country":"TR",
    "gn:fcode":"PPL",
    "gn:pop":268,
    "iso:country":"TR",
    "name:tur_x_preferred":[
        "\u00c7akall\u0131"
    ],
    "name:unk_x_variant":[
        "Chakally"
    ],
    "qs:name":"\u00c7akall\u0131",
    "qs:photos_9r":0,
    "qs:photos_sr":0,
    "qs:pop_sr":"2",
    "wof:name":"\u00c7akall\u0131",
    "wof:placetype":"locality",
    "wof:population":268
},
  "geometry": {"coordinates":[40.55639,37.94444],"type":"Point"}
}