{
  "type": "Feature",
  "properties": {
    "gn:admin1_code":"91",
    "gn:asciiname":"Fakiusagi",
    "gn:country_code":"TR",
    "gn:dem":150,
    "gn:feature_class":"P",
    "gn:feature_code":"PPL",
    "gn:name":"Fak\u0131u\u015fa\u011f\u0131",
    "gn:population":0,
    "gn:timezone":"Europe/Istanbul",
    "iso:country":"TR",
    "wof:name":"Fakiusagi",
    "wof:placetype":"locality"
},
  "geometry": {"coordinates":[36.22489,37.0433],"type":"Point"}
}