{
  "type": "Feature",
  "properties": {
    "gn:admin1_code":"82.0",
    "gn:asciiname":"Sacak",
    "gn:country_code":"TR",
    "gn:dem":1186,
    "gn:feature_class":"P",
    "gn:feature_code":"PPL",
    "gn:name":"Sa\u00e7ak",
    "gn:population":0,
    "gn:timezone":"Europe/Istanbul",
    "iso:country":"TR",
    "wof:name":"Sacak",
    "wof:placetype":"locality"
},
  "geometry": {"coordinates":[33.01580999999999,40.78144],"type":"Point"}
}