{
  "type": "Feature",
  "properties": {
    "gn:admin1_code":"24",
    "gn:asciiname":"Damlaca",
    "gn:country_code":"TR",
    "gn:dem":1313,
    "gn:feature_class":"P",
    "gn:feature_code":"PPL",
    "gn:name":"Damlaca",
    "gn:population":0,
    "gn:timezone":"Europe/Istanbul",
    "iso:country":"TR",
    "name:tur_x_preferred":[
        "Damlaca"
    ],
    "wof:name":"Damlaca",
    "wof:placetype":"locality"
},
  "geometry": {"coordinates":[38.76453,39.99252],"type":"Point"}
}