{
  "type": "Feature",
  "properties": {
    "gn:admin1_code":"61.0",
    "gn:asciiname":"Camkonak",
    "gn:country_code":"TR",
    "gn:dem":736,
    "gn:feature_class":"P",
    "gn:feature_code":"PPL",
    "gn:name":"\u00c7amkonak",
    "gn:population":0,
    "gn:timezone":"Europe/Istanbul",
    "iso:country":"TR",
    "wof:name":"Camkonak",
    "wof:placetype":"locality"
},
  "geometry": {"coordinates":[39.67083,40.81083],"type":"Point"}
}