{
  "type": "Feature",
  "properties": {
    "gn:admin1_code":"09",
    "gn:asciiname":"Yukarikayacik",
    "gn:country_code":"TR",
    "gn:dem":872,
    "gn:feature_class":"P",
    "gn:feature_code":"PPL",
    "gn:name":"Yukar\u0131kayac\u0131k",
    "gn:population":0,
    "gn:timezone":"Europe/Istanbul",
    "iso:country":"TR",
    "name:und_x_variant":[
        "Kayac\u0131k",
        "Yukar\u0131kayac\u0131k"
    ],
    "wof:name":"Yukarikayacik",
    "wof:placetype":"locality"
},
  "geometry": {"coordinates":[27.92748,37.92158],"type":"Point"}
}