{
  "type": "Feature",
  "properties": {
    "gn:admin1_code":"07",
    "gn:asciiname":"Nebiler",
    "gn:country_code":"TR",
    "gn:dem":1643,
    "gn:feature_class":"P",
    "gn:feature_code":"PPL",
    "gn:name":"Nebiler",
    "gn:population":0,
    "gn:timezone":"Europe/Istanbul",
    "iso:country":"TR",
    "wof:name":"Nebiler",
    "wof:placetype":"locality"
},
  "geometry": {"coordinates":[30.00972,36.97583],"type":"Point"}
}