{
  "type": "Feature",
  "properties": {
    "gn:admin1_code":"21.0",
    "gn:asciiname":"Agadibek",
    "gn:country_code":"TR",
    "gn:dem":1174,
    "gn:feature_class":"P",
    "gn:feature_code":"PPL",
    "gn:name":"A\u011fadibek",
    "gn:population":0,
    "gn:timezone":"Europe/Istanbul",
    "iso:country":"TR",
    "name:und_x_variant":[
        "K\u0131ll\u0131kan",
        "K\u0131ll\u0131giran",
        "K\u0131ll\u0131k\u0131ran",
        "A\u011fadibek"
    ],
    "wof:name":"Agadibek",
    "wof:placetype":"locality"
},
  "geometry": {"coordinates":[39.66252,38.35072],"type":"Point"}
}