{
  "type": "Feature",
  "properties": {
    "gn:admin1_code":"52",
    "gn:asciiname":"Tuzla",
    "gn:country_code":"TR",
    "gn:dem":925,
    "gn:feature_class":"P",
    "gn:feature_code":"PPL",
    "gn:name":"Tuzla",
    "gn:population":0,
    "gn:timezone":"Europe/Istanbul",
    "iso:country":"TR",
    "name:tur_x_preferred":[
        "Tuzla"
    ],
    "wof:name":"Tuzla",
    "wof:placetype":"locality"
},
  "geometry": {"coordinates":[37.60461,40.8502],"type":"Point"}
}