{
  "type": "Feature",
  "properties": {
    "gn:admin1_code":"37.0",
    "gn:asciiname":"Enilcek",
    "gn:country_code":"TR",
    "gn:dem":1520,
    "gn:feature_class":"P",
    "gn:feature_code":"PPL",
    "gn:name":"Enilcek",
    "gn:population":0,
    "gn:timezone":"Europe/Istanbul",
    "iso:country":"TR",
    "wof:name":"Enilcek",
    "wof:placetype":"locality"
},
  "geometry": {"coordinates":[34.11667,41.26667],"type":"Point"}
}