{
  "type": "Feature",
  "properties": {
    "gn:admin1_code":"48",
    "gn:asciiname":"Alacak",
    "gn:country_code":"TR",
    "gn:dem":217,
    "gn:feature_class":"P",
    "gn:feature_code":"PPL",
    "gn:name":"Alacak",
    "gn:population":0,
    "gn:timezone":"Europe/Istanbul",
    "iso:country":"TR",
    "name:tur_x_preferred":[
        "Alacak"
    ],
    "name:tur_x_variant":[
        "Balc\u0131lar"
    ],
    "wof:name":"Alacak",
    "wof:placetype":"locality"
},
  "geometry": {"coordinates":[28.58081,37.07589],"type":"Point"}
}