{
  "type": "Feature",
  "properties": {
    "gn:admin1_code":"49",
    "gn:asciiname":"Cankurtaran",
    "gn:country_code":"TR",
    "gn:dem":1585,
    "gn:feature_class":"P",
    "gn:feature_code":"PPL",
    "gn:name":"Cankurtaran",
    "gn:population":0,
    "gn:timezone":"Europe/Istanbul",
    "iso:country":"TR",
    "name:tur_x_preferred":[
        "Cankurtaran"
    ],
    "wof:name":"Cankurtaran",
    "wof:placetype":"locality"
},
  "geometry": {"coordinates":[42.08261,39.06176],"type":"Point"}
}