{
  "type": "Feature",
  "properties": {
    "gn:admin1_code":"63",
    "gn:asciiname":"Arican",
    "gn:cc2":"TR",
    "gn:country_code":"TR",
    "gn:dem":351,
    "gn:feature_class":"P",
    "gn:feature_code":"PPL",
    "gn:name":"Ar\u0131can",
    "gn:population":0,
    "gn:timezone":"Europe/Istanbul",
    "iso:country":"TR",
    "name:tur_x_historical":[
        "Z\u00fcneybir"
    ],
    "name:tur_x_preferred":[
        "Ar\u0131can"
    ],
    "name:tur_x_variant":[
        "Z\u00fcneybir"
    ],
    "name:und_x_variant":[
        "Zinibir",
        "Zyuneybir"
    ],
    "wof:name":"Arican",
    "wof:placetype":"locality"
},
  "geometry": {"coordinates":[39.03556,36.73361],"type":"Point"}
}