{
  "type": "Feature",
  "properties": {
    "gn:admin1_code":"64",
    "gn:asciiname":"Karabacakli",
    "gn:country_code":"TR",
    "gn:dem":797,
    "gn:feature_class":"P",
    "gn:feature_code":"PPL",
    "gn:name":"Karabacakl\u0131",
    "gn:population":0,
    "gn:timezone":"Europe/Istanbul",
    "iso:country":"TR",
    "name:tur_x_preferred":[
        "Karabacakl\u0131"
    ],
    "wof:name":"Karabacakli",
    "wof:placetype":"locality"
},
  "geometry": {"coordinates":[28.96339,38.53922],"type":"Point"}
}