{
  "type": "Feature",
  "properties": {
    "gn:admin1_code":"44",
    "gn:asciiname":"Asar",
    "gn:country_code":"TR",
    "gn:dem":990,
    "gn:feature_class":"P",
    "gn:feature_code":"PPL",
    "gn:name":"Asar",
    "gn:population":0,
    "gn:timezone":"Europe/Istanbul",
    "iso:country":"TR",
    "name:ceb_x_preferred":[
        "Asar"
    ],
    "name:deu_x_preferred":[
        "Asar"
    ],
    "name:glg_x_preferred":[
        "Asar"
    ],
    "name:spa_x_preferred":[
        "Asar"
    ],
    "name:swe_x_preferred":[
        "Asar"
    ],
    "wof:name":"Asar",
    "wof:placetype":"locality"
},
  "geometry": {"coordinates":[38.23684,38.68966],"type":"Point"}
}