{
  "type": "Feature",
  "properties": {
    "gn:admin1_code":"23",
    "gn:asciiname":"Kosebayir",
    "gn:country_code":"TR",
    "gn:dem":1517,
    "gn:feature_class":"P",
    "gn:feature_code":"PPL",
    "gn:name":"K\u00f6sebay\u0131r",
    "gn:population":0,
    "gn:timezone":"Europe/Istanbul",
    "iso:country":"TR",
    "name:tur_x_preferred":[
        "K\u00f6sebay\u0131r"
    ],
    "wof:name":"Kosebayir",
    "wof:placetype":"locality"
},
  "geometry": {"coordinates":[39.18224,38.38893],"type":"Point"}
}