{
  "type": "Feature",
  "properties": {
    "gn:admin1_code":"16",
    "gn:asciiname":"Akpinar",
    "gn:country_code":"TR",
    "gn:dem":797,
    "gn:feature_class":"P",
    "gn:feature_code":"PPL",
    "gn:name":"Akp\u0131nar",
    "gn:population":0,
    "gn:timezone":"Europe/Istanbul",
    "iso:country":"TR",
    "name:tur_x_preferred":[
        "Akp\u0131nar"
    ],
    "wof:name":"Akpinar",
    "wof:placetype":"locality"
},
  "geometry": {"coordinates":[29.11865,39.6335],"type":"Point"}
}