{
  "type": "Feature",
  "properties": {
    "gn:country":"TR",
    "gn:fcode":"PPL",
    "gn:population":306,
    "iso:country":"TR",
    "name:ceb_x_preferred":[
        "Atba\u011f\u0131"
    ],
    "name:che_x_preferred":[
        "\u0410\u0442\u0431\u0430\u0433\u04c0\u0438"
    ],
    "name:deu_x_preferred":[
        "Atba\u011f\u0131"
    ],
    "name:eng_x_preferred":[
        "Atba\u011f\u0131"
    ],
    "name:hye_x_preferred":[
        "\u0532\u0561\u0566\u0562\u0578\u0582\u0569"
    ],
    "name:kur_x_preferred":[
        "Bazb\u00fbd"
    ],
    "name:msa_x_preferred":[
        "Atba\u011f\u0131"
    ],
    "name:nld_x_preferred":[
        "Atba\u011f\u0131"
    ],
    "name:tur_x_preferred":[
        "Atba\u011f\u0131"
    ],
    "name:und_x_variant":[
        "Bazburt"
    ],
    "name:vie_x_preferred":[
        "Atba\u011f\u0131"
    ],
    "name:yor_x_preferred":[
        "Atba\u011f\u0131"
    ],
    "qs:name":"Atba\u011f\u0131",
    "qs:photos_9r":0,
    "qs:photos_sr":0,
    "qs:pop_sr":"2",
    "wof:name":"Atba\u011f\u0131",
    "wof:placetype":"locality",
    "wof:population":306
},
  "geometry": {"coordinates":[41.34278,37.83667],"type":"Point"}
}