{
  "type": "Feature",
  "properties": {
    "gn:country":"TR",
    "gn:fcode":"PPL",
    "gn:pop":306,
    "iso:country":"TR",
    "name:eng_x_preferred":[
        "Atba\u011f\u0131"
    ],
    "name:msa_x_preferred":[
        "Atba\u011f\u0131"
    ],
    "name:nld_x_preferred":[
        "Atba\u011f\u0131"
    ],
    "name:tur_x_preferred":[
        "Atba\u011f\u0131"
    ],
    "name:unk_x_variant":[
        "Bazburt"
    ],
    "name:vie_x_preferred":[
        "Atba\u011f\u0131"
    ],
    "qs:name":"Atba\u011f\u0131",
    "qs:photos_9r":0,
    "qs:photos_sr":0,
    "qs:pop_sr":"2",
    "wof:name":"Atba\u011f\u0131",
    "wof:placetype":"locality",
    "wof:population":306
},
  "geometry": {"coordinates":[41.34278,37.83667],"type":"Point"}
}