{
  "type": "Feature",
  "properties": {
    "gn:admin1_code":"71",
    "gn:asciiname":"Aksakli",
    "gn:country_code":"TR",
    "gn:dem":1048,
    "gn:feature_class":"P",
    "gn:feature_code":"PPL",
    "gn:name":"Aksakl\u0131",
    "gn:population":0,
    "gn:timezone":"Europe/Istanbul",
    "iso:country":"TR",
    "name:tur_x_preferred":[
        "Aksakl\u0131"
    ],
    "name:und_x_variant":[
        "A\u011fsakl\u0131k\u00f6y",
        "A\u011fsakl\u0131",
        "Asakl\u0131"
    ],
    "wof:name":"Aksakli",
    "wof:placetype":"locality"
},
  "geometry": {"coordinates":[33.17708,37.93769],"type":"Point"}
}