{
  "type": "Feature",
  "properties": {
    "gn:admin1_code":"35",
    "gn:asciiname":"Gerence Koyu",
    "gn:country_code":"TR",
    "gn:dem":24,
    "gn:feature_class":"P",
    "gn:feature_code":"PPL",
    "gn:name":"Gerence K\u00f6y\u00fc",
    "gn:population":0,
    "gn:timezone":"Europe/Istanbul",
    "iso:country":"TR",
    "name:tur_x_preferred":[
        "Gerence K\u00f6y\u00fc"
    ],
    "wof:name":"Gerence Koyu",
    "wof:placetype":"locality"
},
  "geometry": {"coordinates":[26.51167,38.43464],"type":"Point"}
}