{
  "type": "Feature",
  "properties": {
    "gn:admin1_code":"37.0",
    "gn:asciiname":"Saraclar",
    "gn:country_code":"TR",
    "gn:dem":142,
    "gn:feature_class":"P",
    "gn:feature_code":"PPL",
    "gn:name":"Sara\u00e7lar",
    "gn:population":0,
    "gn:timezone":"Europe/Istanbul",
    "iso:country":"TR",
    "name:und_x_variant":[
        "Sara\u00e7lar",
        "Mayravan"
    ],
    "wof:name":"Saraclar",
    "wof:placetype":"locality"
},
  "geometry": {"coordinates":[34.20107,41.91736],"type":"Point"}
}