{
  "type": "Feature",
  "properties": {
    "gn:admin1_code":"62",
    "gn:asciiname":"Yaylagunu",
    "gn:country_code":"TR",
    "gn:dem":1302,
    "gn:feature_class":"P",
    "gn:feature_code":"PPL",
    "gn:name":"Yaylag\u00fcn\u00fc",
    "gn:population":0,
    "gn:timezone":"Europe/Istanbul",
    "iso:country":"TR",
    "name:tur_x_preferred":[
        "Yaylag\u00fcn\u00fc"
    ],
    "wof:name":"Yaylagunu",
    "wof:placetype":"locality"
},
  "geometry": {"coordinates":[39.30418,39.34164000000001],"type":"Point"}
}