{
  "type": "Feature",
  "properties": {
    "gn:admin1_code":"22.0",
    "gn:asciiname":"Saricaali",
    "gn:country_code":"TR",
    "gn:dem":30,
    "gn:feature_class":"P",
    "gn:feature_code":"PPL",
    "gn:name":"Sar\u0131caali",
    "gn:population":0,
    "gn:timezone":"Europe/Istanbul",
    "iso:country":"TR",
    "name:und_x_variant":[
        "Sar\u0131cal\u0131",
        "Sar\u0131caali"
    ],
    "wof:name":"Saricaali",
    "wof:placetype":"locality"
},
  "geometry": {"coordinates":[26.3817,40.98526],"type":"Point"}
}