{
  "type": "Feature",
  "properties": {
    "gn:admin1_code":"45",
    "gn:asciiname":"Dere Ciflik",
    "gn:country_code":"TR",
    "gn:dem":473,
    "gn:feature_class":"P",
    "gn:feature_code":"PPL",
    "gn:name":"Dere \u00c7iflik",
    "gn:population":0,
    "gn:timezone":"Europe/Istanbul",
    "iso:country":"TR",
    "name:tur_x_preferred":[
        "Dere \u00c7iflik"
    ],
    "wof:name":"Dere Ciflik",
    "wof:placetype":"locality"
},
  "geometry": {"coordinates":[28.22971,38.83186],"type":"Point"}
}