{
  "type": "Feature",
  "properties": {
    "gn:admin1_code":"58",
    "gn:asciiname":"Yaragil",
    "gn:country_code":"TR",
    "gn:dem":1414,
    "gn:feature_class":"P",
    "gn:feature_code":"PPL",
    "gn:name":"Yara\u011f\u0131l",
    "gn:population":0,
    "gn:timezone":"Europe/Istanbul",
    "iso:country":"TR",
    "wof:name":"Yaragil",
    "wof:placetype":"locality"
},
  "geometry": {"coordinates":[37.68333,39.75],"type":"Point"}
}