{
  "type": "Feature",
  "properties": {
    "gn:admin1_code":"68.0",
    "gn:asciiname":"Eski Yayla",
    "gn:country_code":"TR",
    "gn:dem":1117,
    "gn:feature_class":"P",
    "gn:feature_code":"PPL",
    "gn:name":"Eski Yayla",
    "gn:population":0,
    "gn:timezone":"Europe/Istanbul",
    "iso:country":"TR",
    "wof:name":"Eski Yayla",
    "wof:placetype":"locality"
},
  "geometry": {"coordinates":[32.97294,39.71004],"type":"Point"}
}