{
  "type": "Feature",
  "properties": {
    "gn:admin1_code":"28.0",
    "gn:asciiname":"Dikence",
    "gn:country_code":"TR",
    "gn:dem":299,
    "gn:feature_class":"P",
    "gn:feature_code":"PPL",
    "gn:name":"Dikence",
    "gn:population":0,
    "gn:timezone":"Europe/Istanbul",
    "iso:country":"TR",
    "name:und_x_variant":[
        "Tikence",
        "Dikence"
    ],
    "wof:name":"Dikence",
    "wof:placetype":"locality"
},
  "geometry": {"coordinates":[38.67985,40.8832],"type":"Point"}
}