{
  "type": "Feature",
  "properties": {
    "gn:admin1_code":"81.0",
    "gn:asciiname":"Adbulbakiler",
    "gn:country_code":"TR",
    "gn:dem":916,
    "gn:feature_class":"P",
    "gn:feature_code":"PPL",
    "gn:name":"Adb\u00fclbakiler",
    "gn:population":0,
    "gn:timezone":"Europe/Istanbul",
    "iso:country":"TR",
    "wof:name":"Adbulbakiler",
    "wof:placetype":"locality"
},
  "geometry": {"coordinates":[35.13352,37.48411],"type":"Point"}
}