{
  "type": "Feature",
  "properties": {
    "gn:admin1_code":"68.0",
    "gn:asciiname":"Semer",
    "gn:country_code":"TR",
    "gn:dem":1533,
    "gn:feature_class":"P",
    "gn:feature_code":"PPL",
    "gn:name":"Semer",
    "gn:population":0,
    "gn:timezone":"Europe/Istanbul",
    "iso:country":"TR",
    "wof:name":"Semer",
    "wof:placetype":"locality"
},
  "geometry": {"coordinates":[32.89921,40.59057],"type":"Point"}
}