{
  "type": "Feature",
  "properties": {
    "gn:admin1_code":"21",
    "gn:asciiname":"Umurkoy",
    "gn:country_code":"TR",
    "gn:dem":755,
    "gn:feature_class":"P",
    "gn:feature_code":"PPL",
    "gn:name":"Umurk\u00f6y",
    "gn:population":0,
    "gn:timezone":"Europe/Istanbul",
    "iso:country":"TR",
    "name:tur_x_preferred":[
        "Umur"
    ],
    "name:tur_x_variant":[
        "Umurk\u00f6y"
    ],
    "wof:name":"Umurkoy",
    "wof:placetype":"locality"
},
  "geometry": {"coordinates":[40.97158,38.1097],"type":"Point"}
}