{
  "type": "Feature",
  "properties": {
    "gn:admin1_code":"71",
    "gn:asciiname":"Gezkuyu Mahallesi",
    "gn:country_code":"TR",
    "gn:dem":984,
    "gn:feature_class":"P",
    "gn:feature_code":"PPL",
    "gn:name":"Gezkuyu Mahallesi",
    "gn:population":0,
    "gn:timezone":"Europe/Istanbul",
    "iso:country":"TR",
    "name:und_x_variant":[
        "G\u00fcvercinlik Yaylas\u0131"
    ],
    "wof:name":"Gezkuyu Mahallesi",
    "wof:placetype":"locality"
},
  "geometry": {"coordinates":[33.06310999999999,38.32948],"type":"Point"}
}