{
  "type": "Feature",
  "properties": {
    "gn:admin1_code":"59.0",
    "gn:asciiname":"Karacagur",
    "gn:country_code":"TR",
    "gn:dem":114,
    "gn:feature_class":"P",
    "gn:feature_code":"PPL",
    "gn:name":"Karacag\u00fcr",
    "gn:population":0,
    "gn:timezone":"Europe/Istanbul",
    "iso:country":"TR",
    "name:und_x_variant":[
        "Kara\u00e7g\u00fcr",
        "Karacag\u00fcr"
    ],
    "wof:name":"Karacagur",
    "wof:placetype":"locality"
},
  "geometry": {"coordinates":[26.96862,41.04848],"type":"Point"}
}