{
  "type": "Feature",
  "properties": {
    "gn:admin1_code":"31.0",
    "gn:asciiname":"Ortasirt",
    "gn:country_code":"TR",
    "gn:dem":76,
    "gn:feature_class":"P",
    "gn:feature_code":"PPL",
    "gn:name":"Ortas\u0131rt",
    "gn:population":0,
    "gn:timezone":"Europe/Istanbul",
    "iso:country":"TR",
    "name:tur_x_preferred":[
        "Ortas\u0131rt"
    ],
    "wof:name":"Ortasirt",
    "wof:placetype":"locality"
},
  "geometry": {"coordinates":[36.2381,36.77027],"type":"Point"}
}