{
  "type": "Feature",
  "properties": {
    "gn:admin1_code":"78",
    "gn:asciiname":"Agacli Mahallesi",
    "gn:country_code":"TR",
    "gn:dem":1371,
    "gn:feature_class":"P",
    "gn:feature_code":"PPL",
    "gn:name":"A\u011fa\u00e7l\u0131 Mahallesi",
    "gn:population":0,
    "gn:timezone":"Europe/Istanbul",
    "iso:country":"TR",
    "name:und_x_variant":[
        "A\u011fa\u00e7l\u0131 Mahallesi",
        "K\u00fc\u00e7\u00fck Anamas"
    ],
    "wof:name":"Agacli Mahallesi",
    "wof:placetype":"locality"
},
  "geometry": {"coordinates":[33.12245,37.03971],"type":"Point"}
}