{
  "type": "Feature",
  "properties": {
    "gn:admin1_code":"20",
    "gn:asciiname":"Yenidere",
    "gn:country_code":"TR",
    "gn:dem":495,
    "gn:feature_class":"P",
    "gn:feature_code":"PPL",
    "gn:name":"Yenidere",
    "gn:population":0,
    "gn:timezone":"Europe/Istanbul",
    "iso:country":"TR",
    "name:tur_x_preferred":[
        "Yenidere"
    ],
    "wof:name":"Yenidere",
    "wof:placetype":"locality"
},
  "geometry": {"coordinates":[28.67553,37.49305],"type":"Point"}
}