{
  "type": "Feature",
  "properties": {
    "gn:admin1_code":"68.0",
    "gn:asciiname":"Yakupdervis",
    "gn:country_code":"TR",
    "gn:dem":1059,
    "gn:feature_class":"P",
    "gn:feature_code":"PPL",
    "gn:name":"Yakupdervi\u015f",
    "gn:population":0,
    "gn:timezone":"Europe/Istanbul",
    "iso:country":"TR",
    "name:und_x_variant":[
        "Yubduru\u015f",
        "Yakupdervi\u015f"
    ],
    "wof:name":"Yakupdervis",
    "wof:placetype":"locality"
},
  "geometry": {"coordinates":[32.81706,40.26406],"type":"Point"}
}