{
  "type": "Feature",
  "properties": {
    "gn:admin1_code":"5.0",
    "gn:asciiname":"Akkisiler",
    "gn:country_code":"TR",
    "gn:dem":696,
    "gn:feature_class":"P",
    "gn:feature_code":"PPL",
    "gn:name":"Akki\u015filer",
    "gn:population":0,
    "gn:timezone":"Europe/Istanbul",
    "iso:country":"TR",
    "wof:name":"Akkisiler",
    "wof:placetype":"locality"
},
  "geometry": {"coordinates":[36.28947,40.90611],"type":"Point"}
}