{
  "type": "Feature",
  "properties": {
    "gn:admin1_code":"37",
    "gn:asciiname":"Gukcun",
    "gn:country_code":"TR",
    "gn:dem":669,
    "gn:feature_class":"P",
    "gn:feature_code":"PPL",
    "gn:name":"G\u00fck\u00e7\u00fcn",
    "gn:population":0,
    "gn:timezone":"Europe/Istanbul",
    "iso:country":"TR",
    "wof:name":"Gukcun",
    "wof:placetype":"locality"
},
  "geometry": {"coordinates":[33.69779,41.92299000000001],"type":"Point"}
}