{
  "type": "Feature",
  "properties": {
    "gn:admin1_code":"13",
    "gn:asciiname":"Boluklu",
    "gn:country_code":"TR",
    "gn:dem":1842,
    "gn:feature_class":"P",
    "gn:feature_code":"PPL",
    "gn:name":"B\u00f6l\u00fckl\u00fc",
    "gn:population":0,
    "gn:timezone":"Europe/Istanbul",
    "iso:country":"TR",
    "name:tur_x_preferred":[
        "B\u00f6l\u00fckl\u00fc"
    ],
    "name:und_x_variant":[
        "G\u00fcrt"
    ],
    "wof:name":"Boluklu",
    "wof:placetype":"locality"
},
  "geometry": {"coordinates":[42.55144,38.08065],"type":"Point"}
}