{
  "type": "Feature",
  "properties": {
    "gn:admin1_code":"28.0",
    "gn:asciiname":"Kuzan",
    "gn:country_code":"TR",
    "gn:dem":675,
    "gn:feature_class":"P",
    "gn:feature_code":"PPL",
    "gn:name":"Kuzan",
    "gn:population":0,
    "gn:timezone":"Europe/Istanbul",
    "iso:country":"TR",
    "name:und_x_variant":[
        "Kozan",
        "S\u00f6\u011f\u00fcta\u011fz\u0131"
    ],
    "wof:name":"Kuzan",
    "wof:placetype":"locality"
},
  "geometry": {"coordinates":[38.95921,40.80683],"type":"Point"}
}