{
  "type": "Feature",
  "properties": {
    "gn:admin1_code":"61.0",
    "gn:asciiname":"Dolayli",
    "gn:country_code":"TR",
    "gn:dem":356,
    "gn:feature_class":"P",
    "gn:feature_code":"PPL",
    "gn:name":"Dolayl\u0131",
    "gn:population":0,
    "gn:timezone":"Europe/Istanbul",
    "iso:country":"TR",
    "name:tur_x_preferred":[
        "Dolayl\u0131"
    ],
    "wof:name":"Dolayli",
    "wof:placetype":"locality"
},
  "geometry": {"coordinates":[39.75851,40.93579],"type":"Point"}
}