{
  "type": "Feature",
  "properties": {
    "gn:admin1_code":"59.0",
    "gn:asciiname":"Yagci",
    "gn:country_code":"TR",
    "gn:dem":217,
    "gn:feature_class":"P",
    "gn:feature_code":"PPL",
    "gn:name":"Ya\u011fc\u0131",
    "gn:population":0,
    "gn:timezone":"Europe/Istanbul",
    "iso:country":"TR",
    "name:tur_x_preferred":[
        "Ya\u011fc\u0131"
    ],
    "wof:name":"Yagci",
    "wof:placetype":"locality"
},
  "geometry": {"coordinates":[27.43974,41.00033],"type":"Point"}
}