{
  "type": "Feature",
  "properties": {
    "gn:admin1_code":"63.0",
    "gn:asciiname":"Duger",
    "gn:country_code":"TR",
    "gn:dem":609,
    "gn:feature_class":"P",
    "gn:feature_code":"PPL",
    "gn:name":"D\u00fc\u011fer",
    "gn:population":0,
    "gn:timezone":"Europe/Istanbul",
    "iso:country":"TR",
    "name:tur_x_preferred":[
        "D\u00fc\u011fer"
    ],
    "wof:name":"Duger",
    "wof:placetype":"locality"
},
  "geometry": {"coordinates":[38.72022,37.4749],"type":"Point"}
}