{
  "type": "Feature",
  "properties": {
    "gn:admin1_code":"10",
    "gn:asciiname":"Tugludere",
    "gn:cc2":"TR",
    "gn:country_code":"TR",
    "gn:dem":191,
    "gn:feature_class":"P",
    "gn:feature_code":"PPL",
    "gn:name":"Tu\u011fludere",
    "gn:population":0,
    "gn:timezone":"Europe/Istanbul",
    "iso:country":"TR",
    "name:und_x_variant":[
        "Tu\u011fludere K\u00f6y\u00fc",
        "Tu\u011fludere"
    ],
    "wof:name":"Tugludere",
    "wof:placetype":"locality"
},
  "geometry": {"coordinates":[27.03333,39.65],"type":"Point"}
}