{
  "type": "Feature",
  "properties": {
    "gn:country":"TR",
    "gn:fcode":"PPLA2",
    "gn:population":2635,
    "iso:country":"TR",
    "name:bul_x_preferred":[
        "\u0422\u0435\u043d\u0435\u0434\u043e\u0441"
    ],
    "name:ceb_x_preferred":[
        "Bozcaada"
    ],
    "name:deu_x_preferred":[
        "Bozcaada"
    ],
    "name:ell_x_preferred":[
        "\u03a4\u03ad\u03bd\u03b5\u03b4\u03bf\u03c2"
    ],
    "name:eng_x_preferred":[
        "Tenedos"
    ],
    "name:eng_x_variant":[
        "Castro",
        "Bozcaada"
    ],
    "name:fas_x_preferred":[
        "\u062a\u0646\u062f\u0648\u0633"
    ],
    "name:fra_x_preferred":[
        "T\u00e9n\u00e9dos"
    ],
    "name:heb_x_preferred":[
        "\u05d1\u05d5\u05d6\u05d2\u05d0\u05d0\u05d3\u05d4"
    ],
    "name:ita_x_preferred":[
        "Distretto di Tenedo"
    ],
    "name:lit_x_preferred":[
        "Bozkada"
    ],
    "name:lit_x_variant":[
        "Bozd\u017eada"
    ],
    "name:mrj_x_preferred":[
        "\u0411\u043e\u0437\u0434\u0436\u0430\u0430\u0434\u0430"
    ],
    "name:msa_x_preferred":[
        "Bozcaada"
    ],
    "name:nld_x_preferred":[
        "Bozcaada"
    ],
    "name:pnb_x_preferred":[
        "\u0636\u0644\u0639 \u0628\u0648\u0632\u0633\u0627\u0688\u0627"
    ],
    "name:pol_x_preferred":[
        "Bozca"
    ],
    "name:rus_x_preferred":[
        "\u0411\u043e\u0437\u0434\u0436\u0430\u0430\u0434\u0430"
    ],
    "name:slv_x_preferred":[
        "Bozcaada"
    ],
    "name:spa_x_preferred":[
        "T\u00e9nedos"
    ],
    "name:swa_x_preferred":[
        "Bozcaada"
    ],
    "name:tur_x_preferred":[
        "Bozcaada"
    ],
    "name:ukr_x_preferred":[
        "\u0411\u043e\u0437\u0434\u0436\u0430\u0430\u0434\u0430"
    ],
    "name:und_x_variant":[
        "Bo\u011f\u00e7aada"
    ],
    "name:vec_x_preferred":[
        "Tenedo"
    ],
    "name:zho_x_preferred":[
        "\u535a\u8332\u8cc8\u5cf6"
    ],
    "qs:name":"Bozcaada",
    "qs:photos_9r":0,
    "qs:photos_sr":0,
    "qs:pop_sr":"4",
    "wof:name":"Bozcaada",
    "wof:placetype":"locality",
    "wof:population":2635
},
  "geometry": {"coordinates":[26.06972,39.835],"type":"Point"}
}