{
  "type": "Feature",
  "properties": {
    "gn:admin1_code":"66",
    "gn:asciiname":"Caykoy",
    "gn:country_code":"TR",
    "gn:dem":983,
    "gn:feature_class":"P",
    "gn:feature_code":"PPL",
    "gn:name":"\u00c7ayk\u00f6y",
    "gn:population":0,
    "gn:timezone":"Europe/Istanbul",
    "iso:country":"TR",
    "name:und_x_variant":[
        "\u00c7ay",
        "\u00c7ayk\u00f6y"
    ],
    "wof:name":"Caykoy",
    "wof:placetype":"locality"
},
  "geometry": {"coordinates":[34.24079,39.89298],"type":"Point"}
}