{
  "type": "Feature",
  "properties": {
    "gn:admin1_code":"17.0",
    "gn:asciiname":"Alibeyciftligi",
    "gn:country_code":"TR",
    "gn:dem":146,
    "gn:feature_class":"P",
    "gn:feature_code":"PPL",
    "gn:name":"Alibey\u00e7iftli\u011fi",
    "gn:population":0,
    "gn:timezone":"Europe/Istanbul",
    "iso:country":"TR",
    "wof:name":"Alibeyciftligi",
    "wof:placetype":"locality"
},
  "geometry": {"coordinates":[26.87947,39.99554000000001],"type":"Point"}
}