{
  "type": "Feature",
  "properties": {
    "gn:admin1_code":"55.0",
    "gn:asciiname":"Kumcigaz",
    "gn:country_code":"TR",
    "gn:dem":4,
    "gn:feature_class":"P",
    "gn:feature_code":"PPL",
    "gn:name":"Kumc\u0131\u011faz",
    "gn:population":0,
    "gn:timezone":"Europe/Istanbul",
    "iso:country":"TR",
    "name:tur_x_preferred":[
        "Kumc\u0131\u011faz"
    ],
    "name:tur_x_variant":[
        "Kumcu\u011faz"
    ],
    "wof:name":"Kumcigaz",
    "wof:placetype":"locality"
},
  "geometry": {"coordinates":[36.83189,41.33006],"type":"Point"}
}