{
  "type": "Feature",
  "properties": {
    "gn:admin1_code":"25.0",
    "gn:asciiname":"Danisment",
    "gn:country_code":"TR",
    "gn:dem":1701,
    "gn:feature_class":"P",
    "gn:feature_code":"PPL",
    "gn:name":"Dani\u015fment",
    "gn:population":0,
    "gn:timezone":"Europe/Istanbul",
    "iso:country":"TR",
    "name:und_x_variant":[
        "Dani\u015fment",
        "A\u015fa\u011f\u0131dani\u015fment"
    ],
    "wof:name":"Danisment",
    "wof:placetype":"locality"
},
  "geometry": {"coordinates":[42.37586,40.04784],"type":"Point"}
}