{
  "type": "Feature",
  "properties": {
    "gn:admin1_code":"74",
    "gn:asciiname":"Gundogdu",
    "gn:country_code":"TR",
    "gn:dem":803,
    "gn:feature_class":"P",
    "gn:feature_code":"PPL",
    "gn:name":"G\u00fcndo\u011fdu",
    "gn:population":0,
    "gn:timezone":"Europe/Istanbul",
    "iso:country":"TR",
    "name:und_x_variant":[
        "g\u00fcdog",
        "G\u00fcndo\u011fdu",
        "G\u00fcdo\u011f",
        "G\u00fcndo\u011f"
    ],
    "wof:name":"Gundogdu",
    "wof:placetype":"locality"
},
  "geometry": {"coordinates":[41.80062,38.09069],"type":"Point"}
}