{
  "type": "Feature",
  "properties": {
    "gn:country":"TR",
    "gn:fcode":"PPLA2",
    "gn:pop":71729,
    "iso:country":"TR",
    "name:ara_x_preferred":[
        "\u064a\u0648\u0643\u0633\u0643\u0648\u0641\u0627"
    ],
    "name:azb_x_preferred":[
        "\u06cc\u0648\u06a9\u0633\u06a9 \u0627\u0648\u0648\u0627"
    ],
    "name:ckb_x_preferred":[
        "\u06af\u06d5\u06a4\u06d5\u0631"
    ],
    "name:deu_x_preferred":[
        "Y\u00fcksekova"
    ],
    "name:eng_x_preferred":[
        "Y\u00fcksekova"
    ],
    "name:fas_x_preferred":[
        "\u06cc\u0648\u06a9\u200c\u0633\u06a9\u0648\u0627"
    ],
    "name:fra_x_preferred":[
        "Y\u00fcksekova"
    ],
    "name:gag_x_preferred":[
        "Y\u00fcksekova"
    ],
    "name:kur_x_preferred":[
        "Gever"
    ],
    "name:lit_x_preferred":[
        "Juksekova"
    ],
    "name:min_x_preferred":[
        "Y\u00fcksekova"
    ],
    "name:mrj_x_preferred":[
        "\u0419\u04f1\u043a\u0441\u0435\u043a\u043e\u0432\u0430"
    ],
    "name:msa_x_preferred":[
        "Y\u00fcksekova"
    ],
    "name:nan_x_preferred":[
        "Y\u00fcksekova"
    ],
    "name:nld_x_preferred":[
        "Y\u00fcksekova"
    ],
    "name:nno_x_preferred":[
        "Y\u00fcksekova"
    ],
    "name:pnb_x_preferred":[
        "\u0636\u0644\u0639 \u06cc\u06a9\u0633\u06cc\u06a9\u0648\u0648\u0627"
    ],
    "name:pol_x_preferred":[
        "Y\u00fcksekova"
    ],
    "name:rus_x_preferred":[
        "\u042e\u043a\u0441\u0435\u043a\u043e\u0432\u0430"
    ],
    "name:swa_x_preferred":[
        "Y\u00fcksekova"
    ],
    "name:tur_x_preferred":[
        "Y\u00fcksekova"
    ],
    "name:unk_x_variant":[
        "Dize"
    ],
    "name:urd_x_preferred":[
        "\u06cc\u0648\u06a9\u0633\u06cc\u06a9\u0648\u0648\u0627"
    ],
    "name:vie_x_preferred":[
        "Y\u00fcksekova"
    ],
    "name:zho_x_preferred":[
        "\u4e8e\u514b\u585e\u79d1\u74e6"
    ],
    "qs:name":"Y\u00fcksekova",
    "qs:photos_9r":0,
    "qs:photos_sr":0,
    "qs:pop_sr":"8",
    "wd:wordcount":407,
    "wof:name":"Y\u00fcksekova",
    "wof:placetype":"locality",
    "wof:population":71729
},
  "geometry": {"coordinates":[44.28716,37.57362],"type":"Point"}
}