{
  "type": "Feature",
  "properties": {
    "gn:admin1_code":"02",
    "gn:asciiname":"Bostancik",
    "gn:country_code":"TR",
    "gn:dem":585,
    "gn:feature_class":"P",
    "gn:feature_code":"PPL",
    "gn:name":"Bostanc\u0131k",
    "gn:population":0,
    "gn:timezone":"Europe/Istanbul",
    "iso:country":"TR",
    "name:und_x_variant":[
        "Bostanc\u0131k Mezraa",
        "Bostanc\u0131k"
    ],
    "wof:name":"Bostancik",
    "wof:placetype":"locality"
},
  "geometry": {"coordinates":[38.07371,37.61021],"type":"Point"}
}