{
  "type": "Feature",
  "properties": {
    "gn:admin1_code":"8.0",
    "gn:asciiname":"Libi",
    "gn:country_code":"TR",
    "gn:dem":2111,
    "gn:feature_class":"P",
    "gn:feature_code":"PPL",
    "gn:name":"Libi",
    "gn:population":0,
    "gn:timezone":"Europe/Istanbul",
    "iso:country":"TR",
    "wof:name":"Libi",
    "wof:placetype":"locality"
},
  "geometry": {"coordinates":[42.33174,40.93525],"type":"Point"}
}