{
  "type": "Feature",
  "properties": {
    "gn:admin1_code":"84.0",
    "gn:asciiname":"Yalinkaya",
    "gn:country_code":"TR",
    "gn:dem":1905,
    "gn:feature_class":"P",
    "gn:feature_code":"PPL",
    "gn:name":"Yal\u0131nkaya",
    "gn:population":0,
    "gn:timezone":"Europe/Istanbul",
    "iso:country":"TR",
    "name:und_x_variant":[
        "Ta\u015fkof",
        "Yal\u0131nkaya"
    ],
    "wof:name":"Yalinkaya",
    "wof:placetype":"locality"
},
  "geometry": {"coordinates":[43.25844,40.61823],"type":"Point"}
}