{
  "type": "Feature",
  "properties": {
    "gn:admin1_code":"41",
    "gn:asciiname":"Balaban",
    "gn:country_code":"TR",
    "gn:dem":198,
    "gn:feature_class":"P",
    "gn:feature_code":"PPL",
    "gn:name":"Balaban",
    "gn:population":0,
    "gn:timezone":"Europe/Istanbul",
    "iso:country":"TR",
    "name:bel_x_preferred":[
        "\u0411\u0430\u043b\u0430\u0431\u0430\u043d"
    ],
    "name:ceb_x_preferred":[
        "Balaban"
    ],
    "name:deu_x_preferred":[
        "Balaban"
    ],
    "name:fra_x_preferred":[
        "Balaban"
    ],
    "name:heb_x_preferred":[
        "\u05d1\u05dc\u05d1\u05df"
    ],
    "name:hye_x_preferred":[
        "\u0532\u0561\u056c\u0561\u0562\u0561\u0576"
    ],
    "name:ita_x_preferred":[
        "Balaban"
    ],
    "name:pol_x_preferred":[
        "Ba\u0142aban"
    ],
    "name:rus_x_preferred":[
        "\u0411\u0430\u043b\u0430\u0431\u0430\u043d"
    ],
    "name:srp_x_preferred":[
        "\u0411\u0430\u043b\u0430\u0431\u0430\u043d"
    ],
    "name:swe_x_preferred":[
        "Balaban"
    ],
    "name:tat_x_preferred":[
        "\u0411\u0430\u043b\u0430\u0431\u0430\u043d"
    ],
    "name:tur_x_preferred":[
        "Balaban"
    ],
    "name:und_x_variant":[
        "\u00c7\u0131rakl\u0131"
    ],
    "wof:name":"Balaban",
    "wof:placetype":"locality"
},
  "geometry": {"coordinates":[30.03784000000001,41.03408],"type":"Point"}
}