{
  "type": "Feature",
  "properties": {
    "gn:admin1_code":"52.0",
    "gn:asciiname":"Taslica",
    "gn:country_code":"TR",
    "gn:dem":153,
    "gn:feature_class":"P",
    "gn:feature_code":"PPL",
    "gn:name":"Ta\u015fl\u0131ca",
    "gn:population":0,
    "gn:timezone":"Europe/Istanbul",
    "iso:country":"TR",
    "name:tur_x_preferred":[
        "Ta\u015fl\u0131ca"
    ],
    "wof:name":"Taslica",
    "wof:placetype":"locality"
},
  "geometry": {"coordinates":[37.52205,40.97887],"type":"Point"}
}