{
  "type": "Feature",
  "properties": {
    "gn:admin1_code":"17.0",
    "gn:asciiname":"Karacaali",
    "gn:country_code":"TR",
    "gn:dem":43,
    "gn:feature_class":"P",
    "gn:feature_code":"PPL",
    "gn:name":"Karacaali",
    "gn:population":0,
    "gn:timezone":"Europe/Istanbul",
    "iso:country":"TR",
    "wof:name":"Karacaali",
    "wof:placetype":"locality"
},
  "geometry": {"coordinates":[27.11759,40.31425],"type":"Point"}
}