{
  "type": "Feature",
  "properties": {
    "gn:admin1_code":"19.0",
    "gn:asciiname":"Kizilpinar",
    "gn:country_code":"TR",
    "gn:dem":1196,
    "gn:feature_class":"P",
    "gn:feature_code":"PPL",
    "gn:name":"K\u0131z\u0131lp\u0131nar",
    "gn:population":0,
    "gn:timezone":"Europe/Istanbul",
    "iso:country":"TR",
    "name:und_x_variant":[
        "K\u0131z\u0131lp\u0131nar K\u00f6y\u00fc",
        "K\u0131z\u0131lp\u0131nar"
    ],
    "wof:name":"Kizilpinar",
    "wof:placetype":"locality"
},
  "geometry": {"coordinates":[34.76479,40.67531],"type":"Point"}
}