{
  "type": "Feature",
  "properties": {
    "gn:admin1_code":"14",
    "gn:asciiname":"Sungurlar",
    "gn:country_code":"TR",
    "gn:dem":1263,
    "gn:feature_class":"P",
    "gn:feature_code":"PPL",
    "gn:name":"Sungurlar",
    "gn:population":0,
    "gn:timezone":"Europe/Istanbul",
    "iso:country":"TR",
    "wof:name":"Sungurlar",
    "wof:placetype":"locality"
},
  "geometry": {"coordinates":[32.26152,40.78469000000001],"type":"Point"}
}