{
  "type": "Feature",
  "properties": {
    "gn:admin1_code":"61.0",
    "gn:asciiname":"Arpali",
    "gn:country_code":"TR",
    "gn:dem":1858,
    "gn:feature_class":"P",
    "gn:feature_code":"PPL",
    "gn:name":"Arpal\u0131",
    "gn:population":0,
    "gn:timezone":"Europe/Istanbul",
    "iso:country":"TR",
    "name:eng_x_preferred":[
        "Arpal\u0131"
    ],
    "name:rus_x_preferred":[
        "\u0410\u0440\u043f\u0430\u043b\u044b"
    ],
    "name:und_x_variant":[
        "Arpal\u0131"
    ],
    "wof:name":"Arpali",
    "wof:placetype":"locality"
},
  "geometry": {"coordinates":[40.10249,40.63428],"type":"Point"}
}