{
  "type": "Feature",
  "properties": {
    "gn:admin1_code":"85.0",
    "gn:asciiname":"Oguzhan",
    "gn:country_code":"TR",
    "gn:dem":424,
    "gn:feature_class":"P",
    "gn:feature_code":"PPL",
    "gn:name":"O\u011fuzhan",
    "gn:population":0,
    "gn:timezone":"Europe/Istanbul",
    "iso:country":"TR",
    "name:und_x_variant":[
        "Frenk",
        "U\u011fuzhan",
        "Oquzham",
        "O\u011fuzhan"
    ],
    "wof:name":"Oguzhan",
    "wof:placetype":"locality"
},
  "geometry": {"coordinates":[32.01268,41.27885],"type":"Point"}
}