{
  "type": "Feature",
  "properties": {
    "gn:admin1_code":"5.0",
    "gn:asciiname":"Ozfindikli",
    "gn:country_code":"TR",
    "gn:dem":1031,
    "gn:feature_class":"P",
    "gn:feature_code":"PPL",
    "gn:name":"\u00d6zf\u0131nd\u0131kl\u0131",
    "gn:population":0,
    "gn:timezone":"Europe/Istanbul",
    "iso:country":"TR",
    "name:msa_x_preferred":[
        "\u00d6zf\u0131nd\u0131kl\u0131"
    ],
    "name:tur_x_preferred":[
        "\u00d6zf\u0131nd\u0131kl\u0131"
    ],
    "name:und_x_variant":[
        "F\u0131nd\u0131kl\u0131"
    ],
    "name:vie_x_preferred":[
        "\u00d6zf\u0131nd\u0131kl\u0131"
    ],
    "wof:name":"Ozfindikli",
    "wof:placetype":"locality"
},
  "geometry": {"coordinates":[36.10133,40.47938],"type":"Point"}
}