{
  "type": "Feature",
  "properties": {
    "gn:admin1_code":"21",
    "gn:asciiname":"Bozdemir",
    "gn:country_code":"TR",
    "gn:dem":574,
    "gn:feature_class":"P",
    "gn:feature_code":"PPL",
    "gn:name":"Bozdemir",
    "gn:population":0,
    "gn:timezone":"Europe/Istanbul",
    "iso:country":"TR",
    "name:tur_x_preferred":[
        "Bozdemir"
    ],
    "wof:name":"Bozdemir",
    "wof:placetype":"locality"
},
  "geometry": {"coordinates":[40.30374000000001,37.83692],"type":"Point"}
}