{
  "type": "Feature",
  "properties": {
    "gn:admin1_code":"82.0",
    "gn:asciiname":"Doganlar",
    "gn:country_code":"TR",
    "gn:dem":1354,
    "gn:feature_class":"P",
    "gn:feature_code":"PPL",
    "gn:name":"Do\u011fanlar",
    "gn:population":0,
    "gn:timezone":"Europe/Istanbul",
    "iso:country":"TR",
    "name:und_x_variant":[
        "Avreteli",
        "Avrateli",
        "Do\u011fanlar"
    ],
    "wof:name":"Doganlar",
    "wof:placetype":"locality"
},
  "geometry": {"coordinates":[33.19788,40.67395],"type":"Point"}
}