{
  "type": "Feature",
  "properties": {
    "gn:country":"TR",
    "gn:fcode":"PPL",
    "gn:pop":35193,
    "iso:country":"TR",
    "name:ota_x_preferred":[
        "\u0627\u06cc\u0648\u0627\u0644\u0642"
    ],
    "name:rus_x_preferred":[
        "\u0410\u0439\u0432\u0430\u043b\u044b\u043a"
    ],
    "name:unk_x_variant":[
        "Kydoniai"
    ],
    "qs:name":"Ayval\u0131k",
    "qs:name_adm0":"Turkey",
    "qs:name_adm1":"Bal\u0131kesir",
    "qs:photos":1278,
    "qs:photos_1k":259,
    "qs:photos_9k":6,
    "qs:photos_9r":7,
    "qs:photos_all":1278,
    "qs:photos_sr":12,
    "qs:placetype":"Town",
    "qs:pop_sr":"7",
    "wd:wordcount":1801,
    "wof:name":"Ayval\u0131k",
    "wof:placetype":"locality",
    "wof:population":35193
},
  "geometry": {"coordinates":[26.6954,39.31905],"type":"Point"}
}