{
  "type": "Feature",
  "properties": {
    "gn:admin1_code":"69",
    "gn:asciiname":"Kecikaya",
    "gn:country_code":"TR",
    "gn:dem":1610,
    "gn:feature_class":"P",
    "gn:feature_code":"PPL",
    "gn:name":"Ke\u00e7ikaya",
    "gn:population":0,
    "gn:timezone":"Europe/Istanbul",
    "iso:country":"TR",
    "name:tur_x_preferred":[
        "Ke\u00e7ikaya"
    ],
    "wof:name":"Kecikaya",
    "wof:placetype":"locality"
},
  "geometry": {"coordinates":[39.69724,40.37812],"type":"Point"}
}