{
  "type": "Feature",
  "properties": {
    "gn:admin1_code":"74.0",
    "gn:asciiname":"Dueguencueler",
    "gn:country_code":"TR",
    "gn:dem":1494,
    "gn:feature_class":"P",
    "gn:feature_code":"PPL",
    "gn:name":"D\u00fc\u011f\u00fcnc\u00fcler",
    "gn:population":0,
    "gn:timezone":"Europe/Istanbul",
    "iso:country":"TR",
    "name:tur_x_preferred":[
        "D\u00fc\u011f\u00fcnc\u00fcler"
    ],
    "name:und_x_variant":[
        "A\u015fa\u011f\u0131d\u00fc\u011f\u00fcnc\u00fcler"
    ],
    "wof:name":"Dueguencueler",
    "wof:placetype":"locality"
},
  "geometry": {"coordinates":[42.7299,37.84912],"type":"Point"}
}