{
  "type": "Feature",
  "properties": {
    "gn:admin1_code":"87.0",
    "gn:asciiname":"Gurgenpinari",
    "gn:country_code":"TR",
    "gn:dem":15,
    "gn:feature_class":"P",
    "gn:feature_code":"PPL",
    "gn:name":"G\u00fcrgenp\u0131nar\u0131",
    "gn:population":0,
    "gn:timezone":"Europe/Istanbul",
    "iso:country":"TR",
    "name:und_x_variant":[
        "G\u00fcrgenp\u0131nar\u0131"
    ],
    "wof:name":"Gurgenpinari",
    "wof:placetype":"locality"
},
  "geometry": {"coordinates":[32.28,41.64216],"type":"Point"}
}