{
  "type": "Feature",
  "properties": {
    "gn:admin1_code":"31",
    "gn:asciiname":"Hamam",
    "gn:country_code":"TR",
    "gn:dem":107,
    "gn:feature_class":"P",
    "gn:feature_code":"PPL",
    "gn:name":"Hamam",
    "gn:population":0,
    "gn:timezone":"Europe/Istanbul",
    "iso:country":"TR",
    "name:ara_x_preferred":[
        "\u062d\u0645\u0627\u0645"
    ],
    "name:ceb_x_preferred":[
        "Hamam"
    ],
    "name:ces_x_preferred":[
        "Hamam"
    ],
    "name:deu_x_preferred":[
        "Hamam"
    ],
    "name:fas_x_preferred":[
        "\u062d\u0645\u0627\u0645"
    ],
    "name:heb_x_preferred":[
        "\u05d7\u05de\u05d0\u05dd"
    ],
    "name:ita_x_preferred":[
        "Hamam"
    ],
    "name:swe_x_preferred":[
        "Hamam"
    ],
    "name:tur_x_preferred":[
        "Hamam"
    ],
    "name:und_x_variant":[
        "Corcurum",
        "Curcurum",
        "Curcurun"
    ],
    "wof:name":"Hamam",
    "wof:placetype":"locality"
},
  "geometry": {"coordinates":[36.54291,36.39453],"type":"Point"}
}