{
  "type": "Feature",
  "properties": {
    "gn:admin1_code":"31",
    "gn:asciiname":"Hamam",
    "gn:country_code":"TR",
    "gn:dem":107,
    "gn:feature_class":"P",
    "gn:feature_code":"PPL",
    "gn:name":"Hamam",
    "gn:population":0,
    "gn:timezone":"Europe/Istanbul",
    "iso:country":"TR",
    "name:und_x_variant":[
        "Corcurum",
        "Curcurum",
        "Curcurun",
        "Hamam"
    ],
    "wof:name":"Hamam",
    "wof:placetype":"locality"
},
  "geometry": {"coordinates":[36.54291,36.39453],"type":"Point"}
}