{
  "type": "Feature",
  "properties": {
    "gn:admin1_code":"8.0",
    "gn:asciiname":"Caglipinar",
    "gn:country_code":"TR",
    "gn:dem":1635,
    "gn:feature_class":"P",
    "gn:feature_code":"PPL",
    "gn:name":"\u00c7a\u011fl\u0131p\u0131nar",
    "gn:population":0,
    "gn:timezone":"Europe/Istanbul",
    "iso:country":"TR",
    "name:tur_x_preferred":[
        "\u00c7a\u011fl\u0131p\u0131nar"
    ],
    "wof:name":"Caglipinar",
    "wof:placetype":"locality"
},
  "geometry": {"coordinates":[42.3429,41.41724],"type":"Point"}
}