{
  "type": "Feature",
  "properties": {
    "gn:admin1_code":"48",
    "gn:asciiname":"Hacibayramlar",
    "gn:country_code":"TR",
    "gn:dem":313,
    "gn:feature_class":"P",
    "gn:feature_code":"PPL",
    "gn:name":"Hac\u0131bayramlar",
    "gn:population":0,
    "gn:timezone":"Europe/Istanbul",
    "iso:country":"TR",
    "name:tur_x_preferred":[
        "Hac\u0131bayramlar"
    ],
    "wof:name":"Hacibayramlar",
    "wof:placetype":"locality"
},
  "geometry": {"coordinates":[28.04032,37.41663],"type":"Point"}
}