{
  "type": "Feature",
  "properties": {
    "gn:admin1_code":"68",
    "gn:asciiname":"Gures",
    "gn:country_code":"TR",
    "gn:dem":983,
    "gn:feature_class":"P",
    "gn:feature_code":"PPL",
    "gn:name":"G\u00fcre\u015f",
    "gn:population":0,
    "gn:timezone":"Europe/Istanbul",
    "iso:country":"TR",
    "name:ceb_x_preferred":[
        "Gures"
    ],
    "name:fra_x_preferred":[
        "Gures"
    ],
    "name:swe_x_preferred":[
        "Gures"
    ],
    "wof:name":"Gures",
    "wof:placetype":"locality"
},
  "geometry": {"coordinates":[32.19817,39.8195],"type":"Point"}
}