{
  "type": "Feature",
  "properties": {
    "gn:admin1_code":"41",
    "gn:asciiname":"Kirazyali",
    "gn:country_code":"TR",
    "gn:dem":11,
    "gn:feature_class":"P",
    "gn:feature_code":"PPL",
    "gn:name":"Kirazyal\u0131",
    "gn:population":0,
    "gn:timezone":"Europe/Istanbul",
    "iso:country":"TR",
    "name:tur_x_preferred":[
        "Kirazyal\u0131"
    ],
    "wof:name":"Kirazyali",
    "wof:placetype":"locality"
},
  "geometry": {"coordinates":[29.69866,40.77713],"type":"Point"}
}