{
  "type": "Feature",
  "properties": {
    "gn:admin1_code":"87",
    "gn:asciiname":"Hasankadi",
    "gn:country_code":"TR",
    "gn:dem":398,
    "gn:feature_class":"P",
    "gn:feature_code":"PPL",
    "gn:name":"Hasankad\u0131",
    "gn:population":0,
    "gn:timezone":"Europe/Istanbul",
    "iso:country":"TR",
    "name:ceb_x_preferred":[
        "Hasankad\u0131"
    ],
    "wof:name":"Hasankadi",
    "wof:placetype":"locality"
},
  "geometry": {"coordinates":[32.39009,41.34446],"type":"Point"}
}