{
  "type": "Feature",
  "properties": {
    "gn:admin1_code":"10",
    "gn:asciiname":"Buyuksapci",
    "gn:country_code":"TR",
    "gn:dem":653,
    "gn:feature_class":"P",
    "gn:feature_code":"PPL",
    "gn:name":"B\u00fcy\u00fck\u015fap\u00e7\u0131",
    "gn:population":0,
    "gn:timezone":"Europe/Istanbul",
    "iso:country":"TR",
    "name:tur_x_preferred":[
        "B\u00fcy\u00fck\u015fap\u00e7\u0131"
    ],
    "wof:name":"Buyuksapci",
    "wof:placetype":"locality"
},
  "geometry": {"coordinates":[27.31071,39.63055],"type":"Point"}
}