{
  "type": "Feature",
  "properties": {
    "gn:admin1_code":"58.0",
    "gn:asciiname":"Kesiktas",
    "gn:country_code":"TR",
    "gn:dem":1339,
    "gn:feature_class":"P",
    "gn:feature_code":"PPL",
    "gn:name":"Kesikta\u015f",
    "gn:population":0,
    "gn:timezone":"Europe/Istanbul",
    "iso:country":"TR",
    "name:tur_x_preferred":[
        "Kesikta\u015f"
    ],
    "name:und_x_variant":[
        "Kesikka\u015f"
    ],
    "wof:name":"Kesiktas",
    "wof:placetype":"locality"
},
  "geometry": {"coordinates":[38.03288,40.25507],"type":"Point"}
}