{
  "type": "Feature",
  "properties": {
    "gn:admin1_code":"68.0",
    "gn:asciiname":"Akcaoren",
    "gn:country_code":"TR",
    "gn:dem":1025,
    "gn:feature_class":"P",
    "gn:feature_code":"PPL",
    "gn:name":"Ak\u00e7a\u00f6ren",
    "gn:population":0,
    "gn:timezone":"Europe/Istanbul",
    "iso:country":"TR",
    "name:und_x_variant":[
        "Ak\u00e7aviran",
        "Ak\u00e7a\u00f6ren"
    ],
    "wof:name":"Akcaoren",
    "wof:placetype":"locality"
},
  "geometry": {"coordinates":[32.72770999999999,40.27141],"type":"Point"}
}