{
  "type": "Feature",
  "properties": {
    "gn:admin1_code":"63.0",
    "gn:asciiname":"Kuyucak",
    "gn:country_code":"TR",
    "gn:dem":722,
    "gn:feature_class":"P",
    "gn:feature_code":"PPL",
    "gn:name":"Kuyucak",
    "gn:population":0,
    "gn:timezone":"Europe/Istanbul",
    "iso:country":"TR",
    "name:tur_x_preferred":[
        "Kuyucak"
    ],
    "wof:name":"Kuyucak",
    "wof:placetype":"locality"
},
  "geometry": {"coordinates":[38.92254000000001,37.39091],"type":"Point"}
}