{
  "type": "Feature",
  "properties": {
    "gn:admin1_code":"63.0",
    "gn:asciiname":"Kuyucak",
    "gn:country_code":"TR",
    "gn:dem":722,
    "gn:feature_class":"P",
    "gn:feature_code":"PPL",
    "gn:name":"Kuyucak",
    "gn:population":0,
    "gn:timezone":"Europe/Istanbul",
    "iso:country":"TR",
    "name:ceb_x_preferred":[
        "Kuyucak"
    ],
    "name:deu_x_preferred":[
        "Kuyucak"
    ],
    "name:epo_x_preferred":[
        "Kuyucak"
    ],
    "name:fas_x_preferred":[
        "\u06a9\u0648\u06cc\u0648\u062c\u0627\u06a9"
    ],
    "name:fra_x_preferred":[
        "Kuyucak"
    ],
    "name:lbe_x_preferred":[
        "\u041a\u044a\u0443\u044e\u0434\u0436\u0430\u043a\u044c"
    ],
    "name:mrj_x_preferred":[
        "\u041a\u0443\u044e\u0434\u0436\u0430\u043a"
    ],
    "name:msa_x_preferred":[
        "Kuyucak"
    ],
    "name:nno_x_preferred":[
        "Kuyucak"
    ],
    "name:nor_x_preferred":[
        "Kuyucak"
    ],
    "name:swa_x_preferred":[
        "Kuyucak"
    ],
    "name:tur_x_preferred":[
        "Kuyucak"
    ],
    "name:urd_x_preferred":[
        "\u06a9\u0648\u06cc\u0648\u062c\u0627\u06a9"
    ],
    "name:vie_x_preferred":[
        "Kuyucak"
    ],
    "name:zho_x_preferred":[
        "\u5eab\u5c24\u8cc8\u514b"
    ],
    "wof:name":"Kuyucak",
    "wof:placetype":"locality"
},
  "geometry": {"coordinates":[38.92254000000001,37.39091],"type":"Point"}
}