{
  "type": "Feature",
  "properties": {
    "gn:admin1_code":"23",
    "gn:asciiname":"Kirgil",
    "gn:country_code":"TR",
    "gn:dem":1100,
    "gn:feature_class":"P",
    "gn:feature_code":"PPL",
    "gn:name":"K\u0131rg\u0131l",
    "gn:population":0,
    "gn:timezone":"Europe/Istanbul",
    "iso:country":"TR",
    "name:tur_x_preferred":[
        "K\u0131rg\u0131l"
    ],
    "wof:name":"Kirgil",
    "wof:placetype":"locality"
},
  "geometry": {"coordinates":[39.91001,38.91775],"type":"Point"}
}