{
  "type": "Feature",
  "properties": {
    "gn:country":"TR",
    "gn:fcode":"PPL",
    "gn:population":83,
    "iso:country":"TR",
    "qs:name":"G\u00fcve\u00e7li",
    "qs:photos_9r":0,
    "qs:photos_sr":0,
    "qs:pop_sr":"1",
    "wof:name":"G\u00fcve\u00e7li",
    "wof:placetype":"locality",
    "wof:population":83
},
  "geometry": {"coordinates":[37.66889,36.84806],"type":"Point"}
}