{
  "type": "Feature",
  "properties": {
    "gn:country":"TR",
    "gn:fcode":"PPL",
    "gn:population":2194,
    "iso:country":"TR",
    "name:ceb_x_preferred":[
        "Hisark\u00f6y"
    ],
    "name:swe_x_preferred":[
        "Hisark\u00f6y"
    ],
    "name:tur_x_preferred":[
        "Hisark\u00f6y"
    ],
    "name:und_x_variant":[
        "Khisar"
    ],
    "qs:name":"Hisark\u00f6y",
    "qs:photos_9r":0,
    "qs:photos_sr":0,
    "qs:pop_sr":"4",
    "wd:wordcount":70,
    "wof:name":"Hisark\u00f6y",
    "wof:placetype":"locality",
    "wof:population":2194
},
  "geometry": {"coordinates":[41.22799,37.60094],"type":"Point"}
}