{
  "type": "Feature",
  "properties": {
    "gn:admin1_code":"40",
    "gn:asciiname":"Hanyerisarikaya",
    "gn:country_code":"TR",
    "gn:dem":862,
    "gn:feature_class":"P",
    "gn:feature_code":"PPL",
    "gn:name":"Hanyerisar\u0131kaya",
    "gn:population":0,
    "gn:timezone":"Europe/Istanbul",
    "iso:country":"TR",
    "wof:name":"Hanyerisarikaya",
    "wof:placetype":"locality"
},
  "geometry": {"coordinates":[33.8595,39.55127],"type":"Point"}
}