{
  "type": "Feature",
  "properties": {
    "gn:admin1_code":"87",
    "gn:asciiname":"Akcasu",
    "gn:country_code":"TR",
    "gn:dem":226,
    "gn:feature_class":"P",
    "gn:feature_code":"PPL",
    "gn:name":"Ak\u00e7asu",
    "gn:population":0,
    "gn:timezone":"Europe/Istanbul",
    "iso:country":"TR",
    "wof:name":"Akcasu",
    "wof:placetype":"locality"
},
  "geometry": {"coordinates":[32.72296,41.81298],"type":"Point"}
}