{
  "type": "Feature",
  "properties": {
    "gn:admin1_code":"41.0",
    "gn:asciiname":"Lokmanli",
    "gn:country_code":"TR",
    "gn:dem":75,
    "gn:feature_class":"P",
    "gn:feature_code":"PPL",
    "gn:name":"Lokmanl\u0131",
    "gn:population":0,
    "gn:timezone":"Europe/Istanbul",
    "iso:country":"TR",
    "name:tur_x_preferred":[
        "Lokmanl\u0131"
    ],
    "wof:name":"Lokmanli",
    "wof:placetype":"locality"
},
  "geometry": {"coordinates":[30.19756,41.04335],"type":"Point"}
}