{
  "type": "Feature",
  "properties": {
    "gn:admin1_code":"31.0",
    "gn:asciiname":"Pinarbasi",
    "gn:country_code":"TR",
    "gn:dem":751,
    "gn:feature_class":"P",
    "gn:feature_code":"PPL",
    "gn:name":"P\u0131narba\u015f\u0131",
    "gn:population":0,
    "gn:timezone":"Europe/Istanbul",
    "iso:country":"TR",
    "name:und_x_variant":[
        "P\u0131narba\u015f\u0131",
        "K\u0131z\u0131lg\u00f6l"
    ],
    "wof:name":"Pinarbasi",
    "wof:placetype":"locality"
},
  "geometry": {"coordinates":[36.09506,35.97115],"type":"Point"}
}