{
  "type": "Feature",
  "properties": {
    "gn:admin1_code":"23",
    "gn:asciiname":"Kokluce",
    "gn:cc2":"TR",
    "gn:country_code":"TR",
    "gn:dem":1259,
    "gn:feature_class":"P",
    "gn:feature_code":"PPL",
    "gn:name":"K\u00f6kl\u00fcce",
    "gn:population":0,
    "gn:timezone":"Europe/Istanbul",
    "iso:country":"TR",
    "name:und_x_variant":[
        "Kiliban"
    ],
    "wof:name":"Kokluce",
    "wof:placetype":"locality"
},
  "geometry": {"coordinates":[40.16667,38.76667],"type":"Point"}
}