{
  "type": "Feature",
  "properties": {
    "gn:admin1_code":"76.0",
    "gn:asciiname":"Orta",
    "gn:country_code":"TR",
    "gn:dem":598,
    "gn:feature_class":"P",
    "gn:feature_code":"PPL",
    "gn:name":"Orta",
    "gn:population":0,
    "gn:timezone":"Europe/Istanbul",
    "iso:country":"TR",
    "name:cat_x_preferred":[
        "Orta"
    ],
    "name:ceb_x_preferred":[
        "Orta"
    ],
    "name:deu_x_preferred":[
        "Orta"
    ],
    "name:fra_x_preferred":[
        "Orta"
    ],
    "name:mrj_x_preferred":[
        "\u041e\u0440\u0442\u0430"
    ],
    "name:msa_x_preferred":[
        "Orta"
    ],
    "name:nld_x_preferred":[
        "Orta"
    ],
    "name:nor_x_preferred":[
        "Orta"
    ],
    "name:swa_x_preferred":[
        "Orta"
    ],
    "name:tur_x_preferred":[
        "Orta"
    ],
    "name:urd_x_preferred":[
        "\u0627\u0648\u0631\u062a\u0627"
    ],
    "name:vie_x_preferred":[
        "Orta"
    ],
    "wof:name":"Orta",
    "wof:placetype":"locality"
},
  "geometry": {"coordinates":[41.61608,37.79138],"type":"Point"}
}