{
  "type": "Feature",
  "properties": {
    "gn:admin1_code":"76.0",
    "gn:asciiname":"Orta",
    "gn:country_code":"TR",
    "gn:dem":598,
    "gn:feature_class":"P",
    "gn:feature_code":"PPL",
    "gn:name":"Orta",
    "gn:population":0,
    "gn:timezone":"Europe/Istanbul",
    "iso:country":"TR",
    "wof:name":"Orta",
    "wof:placetype":"locality"
},
  "geometry": {"coordinates":[41.61608,37.79138],"type":"Point"}
}