{
  "type": "Feature",
  "properties": {
    "gn:admin1_code":"37.0",
    "gn:asciiname":"Kezagzi",
    "gn:country_code":"TR",
    "gn:dem":542,
    "gn:feature_class":"P",
    "gn:feature_code":"PPL",
    "gn:name":"Keza\u011fz\u0131",
    "gn:population":0,
    "gn:timezone":"Europe/Istanbul",
    "iso:country":"TR",
    "name:und_x_variant":[
        "Koza\u011fz\u0131",
        "Kezaz\u0131",
        "Kaza\u011fz\u0131",
        "Keza\u011fz\u0131"
    ],
    "wof:name":"Kezagzi",
    "wof:placetype":"locality"
},
  "geometry": {"coordinates":[32.91801,41.80616],"type":"Point"}
}