{
  "type": "Feature",
  "properties": {
    "gn:admin1_code":"15",
    "gn:asciiname":"Cuvalli",
    "gn:country_code":"TR",
    "gn:dem":1227,
    "gn:feature_class":"P",
    "gn:feature_code":"PPL",
    "gn:name":"\u00c7uvall\u0131",
    "gn:population":0,
    "gn:timezone":"Europe/Istanbul",
    "iso:country":"TR",
    "wof:name":"Cuvalli",
    "wof:placetype":"locality"
},
  "geometry": {"coordinates":[29.85111,37.5175],"type":"Point"}
}