{
  "type": "Feature",
  "properties": {
    "gn:admin1_code":"80",
    "gn:asciiname":"Cetinkaya",
    "gn:country_code":"TR",
    "gn:dem":661,
    "gn:feature_class":"P",
    "gn:feature_code":"PPL",
    "gn:name":"\u00c7etinkaya",
    "gn:population":0,
    "gn:timezone":"Europe/Istanbul",
    "iso:country":"TR",
    "name:und_x_variant":[
        "Gyuvinan",
        "G\u00fcvinan",
        "\u00c7etinkaya"
    ],
    "wof:name":"Cetinkaya",
    "wof:placetype":"locality"
},
  "geometry": {"coordinates":[41.96115,37.59005],"type":"Point"}
}