{
  "type": "Feature",
  "properties": {
    "gn:admin1_code":"55.0",
    "gn:asciiname":"Kocalar",
    "gn:country_code":"TR",
    "gn:dem":56,
    "gn:feature_class":"P",
    "gn:feature_code":"PPL",
    "gn:name":"Kocalar",
    "gn:population":0,
    "gn:timezone":"Europe/Istanbul",
    "iso:country":"TR",
    "wof:name":"Kocalar",
    "wof:placetype":"locality"
},
  "geometry": {"coordinates":[36.80371,41.11271],"type":"Point"}
}