{
  "type": "Feature",
  "properties": {
    "gn:admin1_code":"43",
    "gn:asciiname":"Tepebasi",
    "gn:country_code":"TR",
    "gn:dem":1027,
    "gn:feature_class":"P",
    "gn:feature_code":"PPL",
    "gn:name":"Tepeba\u015f\u0131",
    "gn:population":0,
    "gn:timezone":"Europe/Istanbul",
    "iso:country":"TR",
    "name:tur_x_preferred":[
        "Tepeba\u015f\u0131"
    ],
    "wof:name":"Tepebasi",
    "wof:placetype":"locality"
},
  "geometry": {"coordinates":[29.01979,39.42894],"type":"Point"}
}