{
  "type": "Feature",
  "properties": {
    "gn:admin1_code":"59.0",
    "gn:asciiname":"Akarca",
    "gn:country_code":"TR",
    "gn:dem":36,
    "gn:feature_class":"P",
    "gn:feature_code":"PPL",
    "gn:name":"Akarca",
    "gn:population":0,
    "gn:timezone":"Europe/Istanbul",
    "iso:country":"TR",
    "name:deu_x_preferred":[
        "Akarca"
    ],
    "name:kur_x_preferred":[
        "Akarca"
    ],
    "name:tur_x_preferred":[
        "Akarca"
    ],
    "wof:name":"Akarca",
    "wof:placetype":"locality"
},
  "geometry": {"coordinates":[26.932,41.3323],"type":"Point"}
}