{
  "type": "Feature",
  "properties": {
    "gn:admin1_code":"45",
    "gn:asciiname":"Bademli",
    "gn:country_code":"TR",
    "gn:dem":603,
    "gn:feature_class":"P",
    "gn:feature_code":"PPL",
    "gn:name":"Bademli",
    "gn:population":0,
    "gn:timezone":"Europe/Istanbul",
    "iso:country":"TR",
    "name:tur_x_preferred":[
        "Bademli"
    ],
    "wof:name":"Bademli",
    "wof:placetype":"locality"
},
  "geometry": {"coordinates":[27.80173,39.24009],"type":"Point"}
}