{
  "type": "Feature",
  "properties": {
    "gn:admin1_code":"25.0",
    "gn:asciiname":"Ballitas",
    "gn:country_code":"TR",
    "gn:dem":2079,
    "gn:feature_class":"P",
    "gn:feature_code":"PPL",
    "gn:name":"Ball\u0131ta\u015f",
    "gn:population":0,
    "gn:timezone":"Europe/Istanbul",
    "iso:country":"TR",
    "name:tur_x_preferred":[
        "Ball\u0131ta\u015f"
    ],
    "wof:name":"Ballitas",
    "wof:placetype":"locality"
},
  "geometry": {"coordinates":[40.72815,40.02202],"type":"Point"}
}