{
  "type": "Feature",
  "properties": {
    "gn:admin1_code":"87",
    "gn:asciiname":"Kiran",
    "gn:country_code":"TR",
    "gn:dem":150,
    "gn:feature_class":"P",
    "gn:feature_code":"PPL",
    "gn:name":"Kiran",
    "gn:population":0,
    "gn:timezone":"Europe/Istanbul",
    "iso:country":"TR",
    "name:ceb_x_preferred":[
        "Kiran"
    ],
    "name:deu_x_preferred":[
        "Kiran"
    ],
    "name:hin_x_preferred":[
        "\u0915\u093f\u0930\u0923"
    ],
    "wof:name":"Kiran",
    "wof:placetype":"locality"
},
  "geometry": {"coordinates":[32.42736,41.52575],"type":"Point"}
}