{
  "type": "Feature",
  "properties": {
    "gn:admin1_code":"86.0",
    "gn:asciiname":"Kalenderdere",
    "gn:country_code":"TR",
    "gn:dem":2122,
    "gn:feature_class":"P",
    "gn:feature_code":"PPL",
    "gn:name":"Kalenderdere",
    "gn:population":0,
    "gn:timezone":"Europe/Istanbul",
    "iso:country":"TR",
    "name:tur_x_preferred":[
        "Kalenderdere"
    ],
    "wof:name":"Kalenderdere",
    "wof:placetype":"locality"
},
  "geometry": {"coordinates":[42.83457,41.35553],"type":"Point"}
}