{
  "type": "Feature",
  "properties": {
    "gn:admin1_code":"61.0",
    "gn:asciiname":"Cilekli",
    "gn:country_code":"TR",
    "gn:dem":397,
    "gn:feature_class":"P",
    "gn:feature_code":"PPL",
    "gn:name":"\u00c7ilekli",
    "gn:population":0,
    "gn:timezone":"Europe/Istanbul",
    "iso:country":"TR",
    "wof:name":"Cilekli",
    "wof:placetype":"locality"
},
  "geometry": {"coordinates":[39.4427,41.01615],"type":"Point"}
}