{
  "type": "Feature",
  "properties": {
    "gn:admin1_code":"14.0",
    "gn:asciiname":"Gokcesaray",
    "gn:cc2":"TR",
    "gn:country_code":"TR",
    "gn:dem":703,
    "gn:feature_class":"P",
    "gn:feature_code":"PPL",
    "gn:name":"G\u00f6k\u00e7esaray",
    "gn:population":0,
    "gn:timezone":"Europe/Istanbul",
    "iso:country":"TR",
    "name:und_x_variant":[
        "M\u00fcstek",
        "G\u00f6k\u00e7esaray"
    ],
    "wof:name":"Gokcesaray",
    "wof:placetype":"locality"
},
  "geometry": {"coordinates":[30.65278,40.44333],"type":"Point"}
}