{
  "type": "Feature",
  "properties": {
    "gn:admin1_code":"03",
    "gn:asciiname":"Dutagaci",
    "gn:country_code":"TR",
    "gn:dem":1202,
    "gn:feature_class":"P",
    "gn:feature_code":"PPL",
    "gn:name":"Duta\u011fac\u0131",
    "gn:population":0,
    "gn:timezone":"Europe/Istanbul",
    "iso:country":"TR",
    "name:und_x_variant":[
        "Duta\u011fac\u0131",
        "Duta\u011fa\u00e7"
    ],
    "wof:name":"Dutagaci",
    "wof:placetype":"locality"
},
  "geometry": {"coordinates":[30.31783,38.44479000000001],"type":"Point"}
}