{
  "type": "Feature",
  "properties": {
    "gn:admin1_code":"87.0",
    "gn:asciiname":"Barkacboz",
    "gn:country_code":"TR",
    "gn:dem":218,
    "gn:feature_class":"P",
    "gn:feature_code":"PPL",
    "gn:name":"Barka\u00e7boz",
    "gn:population":0,
    "gn:timezone":"Europe/Istanbul",
    "iso:country":"TR",
    "name:und_x_variant":[
        "Barka\u00e7boz"
    ],
    "wof:name":"Barkacboz",
    "wof:placetype":"locality"
},
  "geometry": {"coordinates":[32.35158,41.45784],"type":"Point"}
}