{
  "type": "Feature",
  "properties": {
    "gn:admin1_code":"49",
    "gn:asciiname":"Mezrea",
    "gn:country_code":"TR",
    "gn:dem":1975,
    "gn:feature_class":"P",
    "gn:feature_code":"PPL",
    "gn:name":"Mezrea",
    "gn:population":0,
    "gn:timezone":"Europe/Istanbul",
    "iso:country":"TR",
    "name:tur_x_preferred":[
        "Mezrea"
    ],
    "name:und_x_variant":[
        "Kop Mezraas\u0131"
    ],
    "wof:name":"Mezrea",
    "wof:placetype":"locality"
},
  "geometry": {"coordinates":[41.51718,38.63506],"type":"Point"}
}