{
  "type": "Feature",
  "properties": {
    "gn:country":"TR",
    "gn:fcode":"PPL",
    "gn:pop":4889,
    "iso:country":"TR",
    "name:tur_x_preferred":[
        "Kuzeytepe"
    ],
    "name:tur_x_variant":[
        "G\u00fczeltepe"
    ],
    "qs:name":"Kuzeytepe",
    "qs:photos_9r":0,
    "qs:photos_sr":0,
    "qs:pop_sr":"4",
    "wof:name":"Kuzeytepe",
    "wof:placetype":"locality",
    "wof:population":4889
},
  "geometry": {"coordinates":[36.15167,36.26556],"type":"Point"}
}