{
  "type": "Feature",
  "properties": {
    "gn:admin1_code":"63",
    "gn:asciiname":"Buyukgol",
    "gn:country_code":"TR",
    "gn:dem":868,
    "gn:feature_class":"P",
    "gn:feature_code":"PPL",
    "gn:name":"B\u00fcy\u00fckg\u00f6l",
    "gn:population":0,
    "gn:timezone":"Europe/Istanbul",
    "iso:country":"TR",
    "name:tur_x_preferred":[
        "B\u00fcy\u00fckg\u00f6l"
    ],
    "wof:name":"Buyukgol",
    "wof:placetype":"locality"
},
  "geometry": {"coordinates":[39.13333,37.93333],"type":"Point"}
}