{
  "type": "Feature",
  "properties": {
    "gn:admin1_code":"65",
    "gn:asciiname":"Ucgozeler",
    "gn:country_code":"TR",
    "gn:dem":2193,
    "gn:feature_class":"P",
    "gn:feature_code":"PPL",
    "gn:name":"\u00dc\u00e7g\u00f6zeler",
    "gn:population":0,
    "gn:timezone":"Europe/Istanbul",
    "iso:country":"TR",
    "name:und_x_variant":[
        "Ka\u015fim",
        "\u00dc\u00e7g\u00f6zeler"
    ],
    "wof:name":"Ucgozeler",
    "wof:placetype":"locality"
},
  "geometry": {"coordinates":[44.13528,39.08944],"type":"Point"}
}