{
  "type": "Feature",
  "properties": {
    "gn:admin1_code":"72.0",
    "gn:asciiname":"Kucuk Bogaziye",
    "gn:country_code":"TR",
    "gn:dem":382,
    "gn:feature_class":"P",
    "gn:feature_code":"PPL",
    "gn:name":"K\u00fc\u00e7\u00fck Bo\u011faziye",
    "gn:population":0,
    "gn:timezone":"Europe/Istanbul",
    "iso:country":"TR",
    "name:tur_x_preferred":[
        "K\u00fc\u00e7\u00fck Bo\u011faziye"
    ],
    "wof:name":"Kucuk Bogaziye",
    "wof:placetype":"locality"
},
  "geometry": {"coordinates":[40.27103,36.93613],"type":"Point"}
}