{
  "type": "Feature",
  "properties": {
    "gn:admin1_code":"28.0",
    "gn:asciiname":"Alakilise",
    "gn:country_code":"TR",
    "gn:dem":1670,
    "gn:feature_class":"P",
    "gn:feature_code":"PPL",
    "gn:name":"Alakilise",
    "gn:population":0,
    "gn:timezone":"Europe/Istanbul",
    "iso:country":"TR",
    "name:und_x_variant":[
        "Binicio\u011flu",
        "K\u00f6kl\u00fcce"
    ],
    "wof:name":"Alakilise",
    "wof:placetype":"locality"
},
  "geometry": {"coordinates":[38.87922,40.22513],"type":"Point"}
}