{
  "type": "Feature",
  "properties": {
    "gn:admin1_code":"63",
    "gn:asciiname":"Baluca",
    "gn:country_code":"TR",
    "gn:dem":583,
    "gn:feature_class":"P",
    "gn:feature_code":"PPL",
    "gn:name":"B\u0101luc\u0101",
    "gn:population":0,
    "gn:timezone":"Europe/Istanbul",
    "iso:country":"TR",
    "wof:name":"Baluca",
    "wof:placetype":"locality"
},
  "geometry": {"coordinates":[39.08333,37.58333],"type":"Point"}
}