{
  "type": "Feature",
  "properties": {
    "gn:admin1_code":"21",
    "gn:asciiname":"Sabirli",
    "gn:country_code":"TR",
    "gn:dem":1063,
    "gn:feature_class":"P",
    "gn:feature_code":"PPL",
    "gn:name":"Sab\u0131rl\u0131",
    "gn:population":0,
    "gn:timezone":"Europe/Istanbul",
    "iso:country":"TR",
    "name:azb_x_preferred":[
        "\u0635\u0627\u0628\u06cc\u0631\u0644\u06cc"
    ],
    "name:aze_x_preferred":[
        "Sabirli"
    ],
    "name:ceb_x_preferred":[
        "Sabirli"
    ],
    "name:ita_x_preferred":[
        "Sabirli"
    ],
    "name:kat_x_preferred":[
        "\u10e1\u10d0\u10d1\u10d8\u10e0\u10da\u10d8"
    ],
    "name:min_x_preferred":[
        "Sabirli"
    ],
    "name:msa_x_preferred":[
        "Sabirli"
    ],
    "name:swe_x_preferred":[
        "Sabirli"
    ],
    "name:tur_x_preferred":[
        "Sab\u0131rl\u0131"
    ],
    "name:urd_x_preferred":[
        "\u0633\u0628\u0631\u0644\u06cc"
    ],
    "wof:name":"Sabirli",
    "wof:placetype":"locality"
},
  "geometry": {"coordinates":[39.80106,38.30701],"type":"Point"}
}