{
  "type": "Feature",
  "properties": {
    "gn:country":"TR",
    "gn:fcode":"PPL",
    "gn:pop":0,
    "iso:country":"TR",
    "name:ara_x_preferred":[
        "\u0622\u0644\u062a\u064a\u0646\u0648\u0641\u0627"
    ],
    "name:ceb_x_preferred":[
        "Alt\u0131nova \u0130l\u00e7esi"
    ],
    "name:deu_x_preferred":[
        "Alt\u0131nova"
    ],
    "name:diq_x_preferred":[
        "Alt\u0131nova"
    ],
    "name:eng_x_preferred":[
        "Alt\u0131nova"
    ],
    "name:fas_x_preferred":[
        "\u0622\u0644\u062a\u06cc\u0646\u0648\u0627"
    ],
    "name:fra_x_preferred":[
        "Alt\u0131nova"
    ],
    "name:gag_x_preferred":[
        "Alt\u0131nova"
    ],
    "name:mrj_x_preferred":[
        "\u0410\u043b\u0442\u044b\u043d\u043e\u0432\u0430"
    ],
    "name:msa_x_preferred":[
        "Alt\u0131nova"
    ],
    "name:nan_x_preferred":[
        "Alt\u0131nova"
    ],
    "name:nld_x_preferred":[
        "Alt\u0131nova"
    ],
    "name:nno_x_preferred":[
        "Alt\u0131nova"
    ],
    "name:nob_x_preferred":[
        "Alt\u0131nova"
    ],
    "name:rus_x_preferred":[
        "\u0410\u043b\u0442\u044b\u043d\u043e\u0432\u0430"
    ],
    "name:swa_x_preferred":[
        "Alt\u0131nova"
    ],
    "name:tur_x_preferred":[
        "Alt\u0131nova"
    ],
    "name:urd_x_preferred":[
        "\u0627\u0644\u062a\u06cc\u0646\u0648\u0648\u0627"
    ],
    "name:vie_x_preferred":[
        "Alt\u0131nova"
    ],
    "name:zho_x_preferred":[
        "\u963f\u723e\u7279\u8afe\u74e6"
    ],
    "qs:name":"Altinova",
    "qs:name_adm0":"Turkey",
    "qs:name_adm1":"Bursa",
    "qs:photos":2,
    "qs:photos_1k":1,
    "qs:photos_9k":1,
    "qs:photos_9r":1,
    "qs:photos_all":2,
    "qs:photos_sr":1,
    "qs:placetype":"Suburb",
    "qs:pop_sr":"0",
    "wd:wordcount":91,
    "wof:name":"Altinova",
    "wof:placetype":"neighbourhood",
    "wof:population":0
},
  "geometry": {"coordinates":[29.03318,39.56204],"type":"Point"}
}