{
  "type": "Feature",
  "properties": {
    "gn:admin1_code":"89.0",
    "gn:asciiname":"Incekaya",
    "gn:country_code":"TR",
    "gn:dem":676,
    "gn:feature_class":"P",
    "gn:feature_code":"PPL",
    "gn:name":"\u0130ncekaya",
    "gn:population":0,
    "gn:timezone":"Europe/Istanbul",
    "iso:country":"TR",
    "name:und_x_variant":[
        "Gayza",
        "\u0130ncekaya"
    ],
    "wof:name":"Incekaya",
    "wof:placetype":"locality"
},
  "geometry": {"coordinates":[32.67504,41.28261],"type":"Point"}
}