{
  "type": "Feature",
  "properties": {
    "gn:admin1_code":"07",
    "gn:asciiname":"Emisbeleni",
    "gn:country_code":"TR",
    "gn:dem":110,
    "gn:feature_class":"P",
    "gn:feature_code":"PPL",
    "gn:name":"Emi\u015fbeleni",
    "gn:population":0,
    "gn:timezone":"Europe/Istanbul",
    "iso:country":"TR",
    "wof:name":"Emisbeleni",
    "wof:placetype":"locality"
},
  "geometry": {"coordinates":[31.87354,36.61729],"type":"Point"}
}