{
  "type": "Feature",
  "properties": {
    "gn:admin1_code":"52",
    "gn:asciiname":"Tatarcik",
    "gn:country_code":"TR",
    "gn:dem":611,
    "gn:feature_class":"P",
    "gn:feature_code":"PPL",
    "gn:name":"Tatarc\u0131k",
    "gn:population":0,
    "gn:timezone":"Europe/Istanbul",
    "iso:country":"TR",
    "name:tur_x_preferred":[
        "Tatarc\u0131k"
    ],
    "wof:name":"Tatarcik",
    "wof:placetype":"locality"
},
  "geometry": {"coordinates":[37.37202,40.78966],"type":"Point"}
}