{
  "type": "Feature",
  "properties": {
    "gn:admin1_code":"80.0",
    "gn:asciiname":"Maden",
    "gn:country_code":"TR",
    "gn:dem":1077,
    "gn:feature_class":"P",
    "gn:feature_code":"PPL",
    "gn:name":"Maden",
    "gn:population":0,
    "gn:timezone":"Europe/Istanbul",
    "iso:country":"TR",
    "name:tur_x_preferred":[
        "Maden"
    ],
    "wof:name":"Maden",
    "wof:placetype":"locality"
},
  "geometry": {"coordinates":[42.78904,37.47722],"type":"Point"}
}