{
  "type": "Feature",
  "properties": {
    "gn:admin1_code":"84",
    "gn:asciiname":"Kocoglu",
    "gn:country_code":"TR",
    "gn:dem":1876,
    "gn:feature_class":"P",
    "gn:feature_code":"PPL",
    "gn:name":"Ko\u00e7o\u011flu",
    "gn:population":0,
    "gn:timezone":"Europe/Istanbul",
    "iso:country":"TR",
    "name:tur_x_preferred":[
        "Ko\u00e7o\u011flu"
    ],
    "wof:name":"Kocoglu",
    "wof:placetype":"locality"
},
  "geometry": {"coordinates":[42.63252,39.97532],"type":"Point"}
}