{
  "type": "Feature",
  "properties": {
    "gn:admin1_code":"88.0",
    "gn:asciiname":"Yukari Alican",
    "gn:country_code":"TR",
    "gn:dem":842,
    "gn:feature_class":"P",
    "gn:feature_code":"PPL",
    "gn:name":"Yukar\u0131 Alican",
    "gn:population":0,
    "gn:timezone":"Europe/Istanbul",
    "iso:country":"TR",
    "name:tur_x_preferred":[
        "Yukar\u0131 Alican"
    ],
    "name:und_x_variant":[
        "Yakarialican",
        "Yukar\u0131alican"
    ],
    "wof:name":"Yukari Alican",
    "wof:placetype":"locality"
},
  "geometry": {"coordinates":[44.15623,40.01631],"type":"Point"}
}