{
  "type": "Feature",
  "properties": {
    "gn:admin1_code":"04",
    "gn:asciiname":"Damlakaya",
    "gn:country_code":"TR",
    "gn:dem":1641,
    "gn:feature_class":"P",
    "gn:feature_code":"PPL",
    "gn:name":"Damlakaya",
    "gn:population":0,
    "gn:timezone":"Europe/Istanbul",
    "iso:country":"TR",
    "name:und_x_variant":[
        "Meter",
        "Damlakaya"
    ],
    "wof:name":"Damlakaya",
    "wof:placetype":"locality"
},
  "geometry": {"coordinates":[42.71322,39.44811],"type":"Point"}
}