{
  "type": "Feature",
  "properties": {
    "gn:admin1_code":"43",
    "gn:asciiname":"Hidirdivani",
    "gn:country_code":"TR",
    "gn:dem":1081,
    "gn:feature_class":"P",
    "gn:feature_code":"PPL",
    "gn:name":"H\u0131d\u0131rdivan\u0131",
    "gn:population":0,
    "gn:timezone":"Europe/Istanbul",
    "iso:country":"TR",
    "name:und_x_variant":[
        "Divanh\u0131d\u0131r",
        "H\u0131d\u0131rdivan\u0131"
    ],
    "wof:name":"Hidirdivani",
    "wof:placetype":"locality"
},
  "geometry": {"coordinates":[28.98951,39.00521],"type":"Point"}
}