{
  "type": "Feature",
  "properties": {
    "gn:admin1_code":"58",
    "gn:asciiname":"Bahadun",
    "gn:country_code":"TR",
    "gn:dem":1559,
    "gn:feature_class":"P",
    "gn:feature_code":"PPL",
    "gn:name":"Bahadun",
    "gn:population":0,
    "gn:timezone":"Europe/Istanbul",
    "iso:country":"TR",
    "name:und_x_variant":[
        "Bahad\u0131n",
        "Sar\u0131\u00e7ubuk"
    ],
    "wof:name":"Bahadun",
    "wof:placetype":"locality"
},
  "geometry": {"coordinates":[38.19811,39.75191],"type":"Point"}
}