{
  "type": "Feature",
  "properties": {
    "gn:admin1_code":"14.0",
    "gn:asciiname":"Vakifgecitveren",
    "gn:country_code":"TR",
    "gn:dem":742,
    "gn:feature_class":"P",
    "gn:feature_code":"PPL",
    "gn:name":"Vak\u0131fge\u00e7itveren",
    "gn:population":0,
    "gn:timezone":"Europe/Istanbul",
    "iso:country":"TR",
    "name:msa_x_preferred":[
        "Vak\u0131fge\u00e7itveren"
    ],
    "name:tur_x_preferred":[
        "Vak\u0131fge\u00e7itveren"
    ],
    "name:und_x_variant":[
        "Vak\u0131fge\u00e7itviran"
    ],
    "name:vie_x_preferred":[
        "Vak\u0131fge\u00e7itveren"
    ],
    "wof:name":"Vakifgecitveren",
    "wof:placetype":"locality"
},
  "geometry": {"coordinates":[31.6897,40.72742],"type":"Point"}
}