{
  "type": "Feature",
  "properties": {
    "gn:admin1_code":"19.0",
    "gn:asciiname":"Kizilhamza",
    "gn:country_code":"TR",
    "gn:dem":1231,
    "gn:feature_class":"P",
    "gn:feature_code":"PPL",
    "gn:name":"K\u0131z\u0131lhamza",
    "gn:population":0,
    "gn:timezone":"Europe/Istanbul",
    "iso:country":"TR",
    "wof:name":"Kizilhamza",
    "wof:placetype":"locality"
},
  "geometry": {"coordinates":[35.10313,40.2599],"type":"Point"}
}