{
  "type": "Feature",
  "properties": {
    "gn:admin1_code":"84.0",
    "gn:asciiname":"Sehithalit",
    "gn:country_code":"TR",
    "gn:dem":1945,
    "gn:feature_class":"P",
    "gn:feature_code":"PPL",
    "gn:name":"\u015eehithalit",
    "gn:population":0,
    "gn:timezone":"Europe/Istanbul",
    "iso:country":"TR",
    "name:und_x_variant":[
        "\u015eehitali",
        "\u015eehithalit"
    ],
    "wof:name":"Sehithalit",
    "wof:placetype":"locality"
},
  "geometry": {"coordinates":[42.55487,40.18619],"type":"Point"}
}