{
  "type": "Feature",
  "properties": {
    "gn:admin1_code":"68.0",
    "gn:asciiname":"Bukeler",
    "gn:country_code":"TR",
    "gn:dem":1134,
    "gn:feature_class":"P",
    "gn:feature_code":"PPL",
    "gn:name":"B\u00fckeler",
    "gn:population":0,
    "gn:timezone":"Europe/Istanbul",
    "iso:country":"TR",
    "name:und_x_variant":[
        "B\u00f6keler",
        "B\u00fckeler"
    ],
    "wof:name":"Bukeler",
    "wof:placetype":"locality"
},
  "geometry": {"coordinates":[32.33861,40.45188],"type":"Point"}
}