{
  "type": "Feature",
  "properties": {
    "iso:country":"TR",
    "name:tur_x_preferred":[
        "Avc\u0131lar"
    ],
    "wof:name":"Avcilar",
    "wof:placetype":"neighbourhood"
},
  "geometry": {"coordinates":[28.72466744528802,40.98482136979093],"type":"Point"}
}