{
  "type": "Feature",
  "properties": {
    "gn:admin1_code":"52.0",
    "gn:asciiname":"Medreseonu",
    "gn:country_code":"TR",
    "gn:dem":68,
    "gn:feature_class":"P",
    "gn:feature_code":"PPL",
    "gn:name":"Medrese\u00f6n\u00fc",
    "gn:population":0,
    "gn:timezone":"Europe/Istanbul",
    "iso:country":"TR",
    "wof:name":"Medreseonu",
    "wof:placetype":"locality"
},
  "geometry": {"coordinates":[37.62536,41.07319],"type":"Point"}
}