{
  "type": "Feature",
  "properties": {
    "iso:country":"TR",
    "name:ava_x_preferred":[
        "\u0410\u0439\u0440\u0430\u043d\u0434\u0436\u044b"
    ],
    "name:ceb_x_preferred":[
        "Ayranc\u0131 \u0130l\u00e7esi"
    ],
    "name:deu_x_preferred":[
        "Ayranc\u0131"
    ],
    "name:fra_x_preferred":[
        "Ayranc\u0131"
    ],
    "name:mrj_x_preferred":[
        "\u0410\u0439\u0440\u0430\u043d\u0434\u0436\u044b"
    ],
    "name:msa_x_preferred":[
        "Ayranc\u0131"
    ],
    "name:nld_x_preferred":[
        "Ayranc\u0131"
    ],
    "name:nor_x_preferred":[
        "Ayranc\u0131"
    ],
    "name:pnb_x_preferred":[
        "\u0636\u0644\u0639 \u0622\u0626\u06cc\u0631\u0627\u0646\u0686\u06cc"
    ],
    "name:swa_x_preferred":[
        "Ayranc\u0131"
    ],
    "name:tur_x_preferred":[
        "Ayranc\u0131"
    ],
    "name:vie_x_preferred":[
        "Ayranc\u0131"
    ],
    "qs:name":"Ayranc\u0131",
    "qs:name_adm0":"Turkey",
    "qs:name_adm1":"Ankara",
    "qs:photos":44,
    "qs:photos_1k":9,
    "qs:photos_9k":1,
    "qs:photos_9r":2,
    "qs:photos_all":44,
    "qs:photos_sr":2,
    "qs:placetype":"Suburb",
    "qs:pop_sr":"0",
    "wd:wordcount":235,
    "wof:name":"Ayranc\u0131",
    "wof:placetype":"neighbourhood"
},
  "geometry": {"coordinates":[32.846833,39.9009895],"type":"Point"}
}