{
  "type": "Feature",
  "properties": {
    "gn:admin1_code":"32",
    "gn:asciiname":"Eminlik",
    "gn:country_code":"TR",
    "gn:dem":996,
    "gn:feature_class":"P",
    "gn:feature_code":"PPL",
    "gn:name":"Eminlik",
    "gn:population":0,
    "gn:timezone":"Europe/Istanbul",
    "iso:country":"TR",
    "wof:name":"Eminlik",
    "wof:placetype":"locality"
},
  "geometry": {"coordinates":[34.92149000000001,37.24874000000001],"type":"Point"}
}