{
  "type": "Feature",
  "properties": {
    "gn:admin1_code":"02",
    "gn:asciiname":"Ikizce",
    "gn:country_code":"TR",
    "gn:dem":542,
    "gn:feature_class":"P",
    "gn:feature_code":"PPL",
    "gn:name":"\u0130kizce",
    "gn:population":0,
    "gn:timezone":"Europe/Istanbul",
    "iso:country":"TR",
    "name:und_x_variant":[
        "Tomakkebir",
        "Tomak",
        "\u0130kizce"
    ],
    "wof:name":"Ikizce",
    "wof:placetype":"locality"
},
  "geometry": {"coordinates":[38.83877,37.79334],"type":"Point"}
}