{
  "type": "Feature",
  "properties": {
    "gn:admin1_code":"25.0",
    "gn:asciiname":"Uzumbagi",
    "gn:country_code":"TR",
    "gn:dem":1158,
    "gn:feature_class":"P",
    "gn:feature_code":"PPL",
    "gn:name":"\u00dcz\u00fcmba\u011f\u0131",
    "gn:population":0,
    "gn:timezone":"Europe/Istanbul",
    "iso:country":"TR",
    "name:eng_x_preferred":[
        "\u00dcz\u00fcmba\u011f\u0131"
    ],
    "name:rus_x_preferred":[
        "\u0418\u0441\u0430\u0441\u043e\u0440"
    ],
    "name:und_x_variant":[
        "\u0130sasor"
    ],
    "wof:name":"Uzumbagi",
    "wof:placetype":"locality"
},
  "geometry": {"coordinates":[41.34075,40.71872000000001],"type":"Point"}
}