{
  "type": "Feature",
  "properties": {
    "gn:admin1_code":"23.0",
    "gn:asciiname":"Akdemir",
    "gn:country_code":"TR",
    "gn:dem":1446,
    "gn:feature_class":"P",
    "gn:feature_code":"PPL",
    "gn:name":"Akdemir",
    "gn:population":0,
    "gn:timezone":"Europe/Istanbul",
    "iso:country":"TR",
    "name:tur_x_preferred":[
        "Akdemir"
    ],
    "wof:name":"Akdemir",
    "wof:placetype":"locality"
},
  "geometry": {"coordinates":[38.6974,38.62122],"type":"Point"}
}