{
  "type": "Feature",
  "properties": {
    "gn:country":"TR",
    "gn:fcode":"PPL",
    "gn:pop":204,
    "iso:country":"TR",
    "name:unk_x_variant":[
        "\u00c7ankall\u0131"
    ],
    "qs:name":"\u00c7angall\u0131",
    "qs:photos_9r":0,
    "qs:photos_sr":0,
    "qs:pop_sr":"2",
    "wof:name":"\u00c7angall\u0131",
    "wof:placetype":"locality",
    "wof:population":204
},
  "geometry": {"coordinates":[37.55389,36.71278],"type":"Point"}
}