{
  "type": "Feature",
  "properties": {
    "gn:admin1_code":"70.0",
    "gn:asciiname":"Ustunagac",
    "gn:country_code":"TR",
    "gn:dem":1445,
    "gn:feature_class":"P",
    "gn:feature_code":"PPL",
    "gn:name":"\u00dcst\u00fcna\u011fa\u00e7",
    "gn:population":0,
    "gn:timezone":"Europe/Istanbul",
    "iso:country":"TR",
    "wof:name":"Ustunagac",
    "wof:placetype":"locality"
},
  "geometry": {"coordinates":[44.65,37.25],"type":"Point"}
}