{
  "type": "Feature",
  "properties": {
    "gn:admin1_code":"72.0",
    "gn:asciiname":"Ilicak",
    "gn:country_code":"TR",
    "gn:dem":493,
    "gn:feature_class":"P",
    "gn:feature_code":"PPL",
    "gn:name":"Il\u0131cak",
    "gn:population":0,
    "gn:timezone":"Europe/Istanbul",
    "iso:country":"TR",
    "name:rus_x_preferred":[
        "Resmil\u2019khamam"
    ],
    "name:tur_x_preferred":[
        "Il\u0131cak"
    ],
    "name:und_x_variant":[
        "Resmilhamam"
    ],
    "wof:name":"Ilicak",
    "wof:placetype":"locality"
},
  "geometry": {"coordinates":[40.6238,37.17879],"type":"Point"}
}