{
  "type": "Feature",
  "properties": {
    "gn:admin1_code":"12",
    "gn:asciiname":"Karavelyan",
    "gn:country_code":"TR",
    "gn:dem":1568,
    "gn:feature_class":"P",
    "gn:feature_code":"PPL",
    "gn:name":"Karavelyan",
    "gn:population":0,
    "gn:timezone":"Europe/Istanbul",
    "iso:country":"TR",
    "wof:name":"Karavelyan",
    "wof:placetype":"locality"
},
  "geometry": {"coordinates":[40.31667,39.01667],"type":"Point"}
}