{
  "type": "Feature",
  "properties": {
    "gn:country":"TR",
    "gn:fcode":"PPLA2",
    "gn:pop":18691,
    "iso:country":"TR",
    "name:ara_x_preferred":[
        "\u0648\u0627\u0631\u062a\u0648"
    ],
    "name:cat_x_preferred":[
        "Varto"
    ],
    "name:ceb_x_preferred":[
        "Varto"
    ],
    "name:deu_x_preferred":[
        "Varto"
    ],
    "name:diq_x_preferred":[
        "Varto"
    ],
    "name:eng_x_preferred":[
        "Varto"
    ],
    "name:eus_x_preferred":[
        "Varto"
    ],
    "name:fas_x_preferred":[
        "\u0648\u0627\u0631\u0627\u062a\u0648"
    ],
    "name:fra_x_preferred":[
        "Varto"
    ],
    "name:hye_x_preferred":[
        "\u054e\u0561\u0580\u0564\u0578\u0575\u056b \u0563\u0561\u057e\u0561\u057c\u0561\u056f"
    ],
    "name:ita_x_preferred":[
        "Distretto di Varto"
    ],
    "name:jpn_x_preferred":[
        "\u30f4\u30a1\u30eb\u30c8"
    ],
    "name:kur_x_preferred":[
        "Gimgim"
    ],
    "name:mrj_x_preferred":[
        "\u0412\u0430\u0440\u0442\u043e"
    ],
    "name:msa_x_preferred":[
        "Varto"
    ],
    "name:nan_x_preferred":[
        "Varto"
    ],
    "name:nld_x_preferred":[
        "Varto"
    ],
    "name:nno_x_preferred":[
        "Varto"
    ],
    "name:nob_x_preferred":[
        "Varto"
    ],
    "name:pnb_x_preferred":[
        "\u0636\u0644\u0639 \u0648\u0627\u0631\u062a\u0648"
    ],
    "name:rus_x_preferred":[
        "\u0412\u0430\u0440\u0442\u043e"
    ],
    "name:spa_x_preferred":[
        "Varto"
    ],
    "name:swa_x_preferred":[
        "Varto"
    ],
    "name:tur_x_preferred":[
        "Varto"
    ],
    "name:unk_x_variant":[
        "G\u00fcmg\u00fcm"
    ],
    "name:urd_x_preferred":[
        "\u0648\u0627\u0631\u062a\u0648"
    ],
    "name:vie_x_preferred":[
        "Varto"
    ],
    "name:vie_x_variant":[
        "Ak\u0131nc\u0131lar"
    ],
    "name:zho_x_preferred":[
        "\u74e6\u723e\u6258"
    ],
    "qs:name":"Varto",
    "qs:name_adm0":"Turkey",
    "qs:name_adm1":"Mu\u015f",
    "qs:photos_9k":1,
    "qs:photos_9r":1,
    "qs:photos_all":2,
    "qs:photos_sr":0,
    "qs:placetype":"Town",
    "qs:pop_sr":"6",
    "wd:wordcount":403,
    "wof:name":"Varto",
    "wof:placetype":"locality",
    "wof:population":18691
},
  "geometry": {"coordinates":[41.45593,39.17321],"type":"Point"}
}