{
  "type": "Feature",
  "properties": {
    "gn:admin1_code":"03",
    "gn:asciiname":"Ayvali Mahallesi",
    "gn:country_code":"TR",
    "gn:dem":1337,
    "gn:feature_class":"P",
    "gn:feature_code":"PPL",
    "gn:name":"Ayval\u0131 Mahallesi",
    "gn:population":0,
    "gn:timezone":"Europe/Istanbul",
    "iso:country":"TR",
    "wof:name":"Ayvali Mahallesi",
    "wof:placetype":"locality"
},
  "geometry": {"coordinates":[30.93013,38.82355],"type":"Point"}
}