{
  "type": "Feature",
  "properties": {
    "gn:admin1_code":"07",
    "gn:asciiname":"Caltilicukur",
    "gn:country_code":"TR",
    "gn:dem":910,
    "gn:feature_class":"P",
    "gn:feature_code":"PPL",
    "gn:name":"\u00c7alt\u0131l\u0131\u00e7ukur",
    "gn:population":0,
    "gn:timezone":"Europe/Istanbul",
    "iso:country":"TR",
    "name:und_x_variant":[
        "\u00c7alt\u0131l\u0131\u00e7ukur",
        "\u00c7alt\u0131"
    ],
    "wof:name":"Caltilicukur",
    "wof:placetype":"locality"
},
  "geometry": {"coordinates":[31.88315,36.87501],"type":"Point"}
}