{
  "type": "Feature",
  "properties": {
    "gn:country":"TR",
    "gn:fcode":"PPL",
    "gn:population":2984,
    "iso:country":"TR",
    "name:tur_x_preferred":[
        "Uzunba\u011f"
    ],
    "qs:name":"Uzunba\u011f",
    "qs:photos_9r":0,
    "qs:photos_sr":0,
    "qs:pop_sr":"4",
    "wof:name":"Uzunba\u011f",
    "wof:placetype":"locality",
    "wof:population":2984
},
  "geometry": {"coordinates":[36.02472,36.14832],"type":"Point"}
}