{
  "type": "Feature",
  "properties": {
    "gn:admin1_code":"03",
    "gn:asciiname":"Pinarkaya",
    "gn:country_code":"TR",
    "gn:dem":996,
    "gn:feature_class":"P",
    "gn:feature_code":"PPL",
    "gn:name":"P\u0131narkaya",
    "gn:population":0,
    "gn:timezone":"Europe/Istanbul",
    "iso:country":"TR",
    "name:und_x_variant":[
        "Gedil",
        "P\u0131narkaya"
    ],
    "wof:name":"Pinarkaya",
    "wof:placetype":"locality"
},
  "geometry": {"coordinates":[31.07806,38.59025],"type":"Point"}
}