{
  "type": "Feature",
  "properties": {
    "gn:admin1_code":"44",
    "gn:asciiname":"Akbaba",
    "gn:country_code":"TR",
    "gn:dem":1480,
    "gn:feature_class":"P",
    "gn:feature_code":"PPL",
    "gn:name":"Akbaba",
    "gn:population":0,
    "gn:timezone":"Europe/Istanbul",
    "iso:country":"TR",
    "name:deu_x_preferred":[
        "Akbaba"
    ],
    "name:rus_x_preferred":[
        "\u0410\u043a\u0431\u0430\u0431\u0430"
    ],
    "name:tur_x_preferred":[
        "Akbaba"
    ],
    "name:und_x_variant":[
        "\u00c7at\u00f6ren"
    ],
    "wof:name":"Akbaba",
    "wof:placetype":"locality"
},
  "geometry": {"coordinates":[37.66385,38.64982],"type":"Point"}
}