{
  "type": "Feature",
  "properties": {
    "gn:admin1_code":"8.0",
    "gn:asciiname":"Duzenli",
    "gn:country_code":"TR",
    "gn:dem":733,
    "gn:feature_class":"P",
    "gn:feature_code":"PPL",
    "gn:name":"D\u00fczenli",
    "gn:population":0,
    "gn:timezone":"Europe/Istanbul",
    "iso:country":"TR",
    "name:tur_x_preferred":[
        "D\u00fczenli"
    ],
    "wof:name":"Duzenli",
    "wof:placetype":"locality"
},
  "geometry": {"coordinates":[41.89523,41.46311],"type":"Point"}
}