{
  "type": "Feature",
  "properties": {
    "gn:country":"TR",
    "gn:fcode":"PPL",
    "gn:population":3282,
    "iso:country":"TR",
    "name:ast_x_preferred":[
        "Arguvan"
    ],
    "name:ceb_x_preferred":[
        "Arguvan"
    ],
    "name:che_x_preferred":[
        "\u0410\u0440\u0433\u0443\u0432\u0430\u043d"
    ],
    "name:deu_x_preferred":[
        "Arguvan"
    ],
    "name:eng_x_preferred":[
        "Arguvan"
    ],
    "name:fas_x_preferred":[
        "\u0622\u0631\u06af\u0648\u0648\u0627\u0646"
    ],
    "name:fra_x_preferred":[
        "Arguvan"
    ],
    "name:hye_x_preferred":[
        "\u0531\u0580\u0563\u0578\u057e\u0561\u0576"
    ],
    "name:ita_x_preferred":[
        "Distretto di Arguvan"
    ],
    "name:kur_x_preferred":[
        "Erxewan"
    ],
    "name:mrj_x_preferred":[
        "\u0410\u0440\u0433\u0443\u0432\u0430\u043d"
    ],
    "name:msa_x_preferred":[
        "Arguvan"
    ],
    "name:nan_x_preferred":[
        "Arguvan"
    ],
    "name:nld_x_preferred":[
        "Arguvan"
    ],
    "name:nob_x_preferred":[
        "Arguvan"
    ],
    "name:pnb_x_preferred":[
        "\u0636\u0644\u0639 \u0627\u0631\u06af\u0648\u0648\u0627\u0646"
    ],
    "name:rus_x_preferred":[
        "\u0410\u0440\u0433\u0443\u0432\u0430\u043d"
    ],
    "name:swa_x_preferred":[
        "Arguvan"
    ],
    "name:tat_x_preferred":[
        "\u0410\u0440\u0433\u0443\u0432\u0430\u043d"
    ],
    "name:tur_x_preferred":[
        "Arguvan"
    ],
    "name:und_x_variant":[
        "Tahir"
    ],
    "name:urd_x_preferred":[
        "\u0627\u0631\u06af\u0648\u0648\u0627\u0646"
    ],
    "name:vie_x_preferred":[
        "Arguvan"
    ],
    "name:zho_x_preferred":[
        "\u963f\u5c14\u53e4\u4e07"
    ],
    "qs:name":"Arguvan",
    "qs:name_adm0":"Turkey",
    "qs:name_adm1":"Malatya",
    "qs:photos_9k":1,
    "qs:photos_9r":1,
    "qs:photos_all":3,
    "qs:photos_sr":0,
    "qs:placetype":"Town",
    "qs:pop_sr":"4",
    "wd:wordcount":59,
    "wof:name":"Arguvan",
    "wof:placetype":"locality",
    "wof:population":3282
},
  "geometry": {"coordinates":[38.2712,38.76995],"type":"Point"}
}