{
  "type": "Feature",
  "properties": {
    "gn:admin1_code":"10",
    "gn:asciiname":"Celikler",
    "gn:country_code":"TR",
    "gn:dem":723,
    "gn:feature_class":"P",
    "gn:feature_code":"PPL",
    "gn:name":"\u00c7elikler",
    "gn:population":0,
    "gn:timezone":"Europe/Istanbul",
    "iso:country":"TR",
    "name:tur_x_preferred":[
        "\u00c7elikler"
    ],
    "wof:name":"Celikler",
    "wof:placetype":"locality"
},
  "geometry": {"coordinates":[28.68485,39.45122],"type":"Point"}
}