{
  "type": "Feature",
  "properties": {
    "gn:admin1_code":"54.0",
    "gn:asciiname":"Melen",
    "gn:country_code":"TR",
    "gn:dem":22,
    "gn:feature_class":"P",
    "gn:feature_code":"PPL",
    "gn:name":"Melen",
    "gn:population":0,
    "gn:timezone":"Europe/Istanbul",
    "iso:country":"TR",
    "name:tur_x_preferred":[
        "Melen"
    ],
    "wof:name":"Melen",
    "wof:placetype":"locality"
},
  "geometry": {"coordinates":[30.96479,41.04915],"type":"Point"}
}