{
  "type": "Feature",
  "properties": {
    "gn:admin1_code":"20",
    "gn:asciiname":"Yassihuyuk",
    "gn:country_code":"TR",
    "gn:dem":869,
    "gn:feature_class":"P",
    "gn:feature_code":"PPL",
    "gn:name":"Yass\u0131h\u00fcy\u00fck",
    "gn:population":0,
    "gn:timezone":"Europe/Istanbul",
    "iso:country":"TR",
    "name:und_x_variant":[
        "Yass\u0131h\u00fcy\u00fckk\u00f6y",
        "Yass\u0131h\u00fcy\u00fck"
    ],
    "wof:name":"Yassihuyuk",
    "wof:placetype":"locality"
},
  "geometry": {"coordinates":[29.33037,37.51392],"type":"Point"}
}