{
  "type": "Feature",
  "properties": {
    "gn:admin1_code":"58",
    "gn:asciiname":"Cote",
    "gn:country_code":"TR",
    "gn:dem":1045,
    "gn:feature_class":"P",
    "gn:feature_code":"PPL",
    "gn:name":"\u00c7\u00f6te",
    "gn:population":0,
    "gn:timezone":"Europe/Istanbul",
    "iso:country":"TR",
    "name:deu_x_preferred":[
        "Cote"
    ],
    "name:epo_x_preferred":[
        "Kvoto"
    ],
    "name:fra_x_preferred":[
        "Cote"
    ],
    "name:pol_x_preferred":[
        "Cote"
    ],
    "name:swe_x_preferred":[
        "Cote"
    ],
    "wof:name":"Cote",
    "wof:placetype":"locality"
},
  "geometry": {"coordinates":[36.03176,39.90567],"type":"Point"}
}