{
  "type": "Feature",
  "properties": {
    "gn:admin1_code":"31.0",
    "gn:asciiname":"Hidirbey",
    "gn:cc2":"TR",
    "gn:country_code":"TR",
    "gn:dem":132,
    "gn:feature_class":"P",
    "gn:feature_code":"PPL",
    "gn:name":"Hidirbey",
    "gn:population":0,
    "gn:timezone":"Europe/Istanbul",
    "iso:country":"TR",
    "name:und_x_variant":[
        "Khadyrbei",
        "Hidirbey"
    ],
    "wof:name":"Hidirbey",
    "wof:placetype":"locality"
},
  "geometry": {"coordinates":[36.12139000000001,36.20944],"type":"Point"}
}