{
  "type": "Feature",
  "properties": {
    "gn:admin1_code":"16",
    "gn:asciiname":"Has",
    "gn:country_code":"TR",
    "gn:dem":105,
    "gn:feature_class":"P",
    "gn:feature_code":"PPL",
    "gn:name":"Has",
    "gn:population":0,
    "gn:timezone":"Europe/Istanbul",
    "iso:country":"TR",
    "name:tur_x_preferred":[
        "Has"
    ],
    "wof:name":"Has",
    "wof:placetype":"locality"
},
  "geometry": {"coordinates":[28.88484,40.29063],"type":"Point"}
}