{
  "type": "Feature",
  "properties": {
    "gn:admin1_code":"71",
    "gn:asciiname":"Egisse",
    "gn:country_code":"TR",
    "gn:dem":1269,
    "gn:feature_class":"P",
    "gn:feature_code":"PPL",
    "gn:name":"Egisse",
    "gn:population":0,
    "gn:timezone":"Europe/Istanbul",
    "iso:country":"TR",
    "name:und_x_variant":[
        "E\u011fiste",
        "E\u011fitse",
        "Egisse",
        "Ba\u011fba\u015f\u0131"
    ],
    "wof:name":"Egisse",
    "wof:placetype":"locality"
},
  "geometry": {"coordinates":[32.4496,37.0989],"type":"Point"}
}