{
  "type": "Feature",
  "properties": {
    "gn:admin1_code":"15",
    "gn:asciiname":"Eseklik",
    "gn:country_code":"TR",
    "gn:dem":694,
    "gn:feature_class":"P",
    "gn:feature_code":"PPL",
    "gn:name":"E\u015feklik",
    "gn:population":0,
    "gn:timezone":"Europe/Istanbul",
    "iso:country":"TR",
    "wof:name":"Eseklik",
    "wof:placetype":"locality"
},
  "geometry": {"coordinates":[30.74317000000001,37.26709],"type":"Point"}
}