{
  "type": "Feature",
  "properties": {
    "gn:admin1_code":"16.0",
    "gn:asciiname":"Aglasan",
    "gn:country_code":"TR",
    "gn:dem":559,
    "gn:feature_class":"P",
    "gn:feature_code":"PPL",
    "gn:name":"A\u011fla\u015fan",
    "gn:population":0,
    "gn:timezone":"Europe/Istanbul",
    "iso:country":"TR",
    "name:tur_x_preferred":[
        "A\u011fla\u015fan"
    ],
    "wof:name":"Aglasan",
    "wof:placetype":"locality"
},
  "geometry": {"coordinates":[29.28889,40.28266],"type":"Point"}
}