{
  "type": "Feature",
  "properties": {
    "gn:admin1_code":"55.0",
    "gn:asciiname":"Haskoy",
    "gn:cc2":"TR",
    "gn:country_code":"TR",
    "gn:dem":189,
    "gn:feature_class":"P",
    "gn:feature_code":"PPL",
    "gn:name":"Hask\u00f6y",
    "gn:population":0,
    "gn:timezone":"Europe/Istanbul",
    "iso:country":"TR",
    "name:tur_x_preferred":[
        "Asara\u011fa\u00e7"
    ],
    "name:und_x_variant":[
        "Papask\u00f6y",
        "Hask\u00f6y"
    ],
    "wof:name":"Haskoy",
    "wof:placetype":"locality"
},
  "geometry": {"coordinates":[36.36278,41.25389000000001],"type":"Point"}
}