{
  "type": "Feature",
  "properties": {
    "gn:admin1_code":"19.0",
    "gn:asciiname":"Susuzdag",
    "gn:country_code":"TR",
    "gn:dem":1003,
    "gn:feature_class":"P",
    "gn:feature_code":"PPL",
    "gn:name":"Susuzda\u011f",
    "gn:population":0,
    "gn:timezone":"Europe/Istanbul",
    "iso:country":"TR",
    "wof:name":"Susuzdag",
    "wof:placetype":"locality"
},
  "geometry": {"coordinates":[34.51457,40.91778],"type":"Point"}
}