{
  "type": "Feature",
  "properties": {
    "gn:admin1_code":"66",
    "gn:asciiname":"Ortakoy",
    "gn:country_code":"TR",
    "gn:dem":1365,
    "gn:feature_class":"P",
    "gn:feature_code":"PPL",
    "gn:name":"Ortak\u00f6y",
    "gn:population":0,
    "gn:timezone":"Europe/Istanbul",
    "iso:country":"TR",
    "wof:name":"Ortakoy",
    "wof:placetype":"locality"
},
  "geometry": {"coordinates":[36.02666,39.6747],"type":"Point"}
}