{
  "type": "Feature",
  "properties": {
    "gn:admin1_code":"37.0",
    "gn:asciiname":"Imranlar",
    "gn:country_code":"TR",
    "gn:dem":1043,
    "gn:feature_class":"P",
    "gn:feature_code":"PPL",
    "gn:name":"\u0130mranlar",
    "gn:population":0,
    "gn:timezone":"Europe/Istanbul",
    "iso:country":"TR",
    "name:und_x_variant":[
        "\u0130mranl\u0131",
        "\u0130mranlar"
    ],
    "wof:name":"Imranlar",
    "wof:placetype":"locality"
},
  "geometry": {"coordinates":[33.71683,41.67124],"type":"Point"}
}