{
  "type": "Feature",
  "properties": {
    "gn:admin1_code":"71",
    "gn:asciiname":"Hatunsaray",
    "gn:country_code":"TR",
    "gn:dem":1105,
    "gn:feature_class":"P",
    "gn:feature_code":"PPLA3",
    "gn:name":"Hatunsaray",
    "gn:population":0,
    "gn:timezone":"Europe/Istanbul",
    "iso:country":"TR",
    "name:tur_x_preferred":[
        "Hatunsaray"
    ],
    "wof:name":"Hatunsaray",
    "wof:placetype":"locality"
},
  "geometry": {"coordinates":[32.34802,37.58753],"type":"Point"}
}