{
  "type": "Feature",
  "properties": {
    "gn:admin1_code":"17.0",
    "gn:asciiname":"Kizilcaoren",
    "gn:country_code":"TR",
    "gn:dem":168,
    "gn:feature_class":"P",
    "gn:feature_code":"PPL",
    "gn:name":"K\u0131z\u0131lca\u00f6ren",
    "gn:population":0,
    "gn:timezone":"Europe/Istanbul",
    "iso:country":"TR",
    "name:und_x_variant":[
        "Karab\u0131y\u0131koba",
        "K\u0131z\u0131lcaviran Obas\u0131",
        "K\u0131z\u0131lca\u00f6ren"
    ],
    "wof:name":"Kizilcaoren",
    "wof:placetype":"locality"
},
  "geometry": {"coordinates":[26.43702,40.04469],"type":"Point"}
}