{
  "type": "Feature",
  "properties": {
    "gn:admin1_code":"07",
    "gn:asciiname":"Ayiveliler",
    "gn:country_code":"TR",
    "gn:dem":377,
    "gn:feature_class":"P",
    "gn:feature_code":"PPL",
    "gn:name":"Ay\u0131veliler",
    "gn:population":0,
    "gn:timezone":"Europe/Istanbul",
    "iso:country":"TR",
    "wof:name":"Ayiveliler",
    "wof:placetype":"locality"
},
  "geometry": {"coordinates":[29.84185,36.3152],"type":"Point"}
}