{
  "type": "Feature",
  "properties": {
    "gn:admin1_code":"13.0",
    "gn:asciiname":"Selerbey",
    "gn:country_code":"TR",
    "gn:dem":1676,
    "gn:feature_class":"P",
    "gn:feature_code":"PPL",
    "gn:name":"Selerbey",
    "gn:population":0,
    "gn:timezone":"Europe/Istanbul",
    "iso:country":"TR",
    "name:tur_x_preferred":[
        "Selerbey"
    ],
    "wof:name":"Selerbey",
    "wof:placetype":"locality"
},
  "geometry": {"coordinates":[42.1323,38.41338],"type":"Point"}
}