{
  "type": "Feature",
  "properties": {
    "gn:admin1_code":"58.0",
    "gn:asciiname":"Tepebasi",
    "gn:country_code":"TR",
    "gn:dem":1458,
    "gn:feature_class":"P",
    "gn:feature_code":"PPL",
    "gn:name":"Tepeba\u015f\u0131",
    "gn:population":0,
    "gn:timezone":"Europe/Istanbul",
    "iso:country":"TR",
    "wof:name":"Tepebasi",
    "wof:placetype":"locality"
},
  "geometry": {"coordinates":[37.92673,40.31829000000001],"type":"Point"}
}