{
  "type": "Feature",
  "properties": {
    "gn:country":"TR",
    "gn:fcode":"PPLA2",
    "gn:population":4150,
    "iso:country":"TR",
    "name:ast_x_preferred":[
        "Bal\u0131\u015feyh"
    ],
    "name:ceb_x_preferred":[
        "Bal\u0131\u015feyh"
    ],
    "name:che_x_preferred":[
        "\u0411\u0430\u043b\u0438\u0448\u0435\u0439\u0445\u04c0"
    ],
    "name:deu_x_preferred":[
        "Bal\u0131\u015feyh"
    ],
    "name:eng_x_preferred":[
        "Bal\u0131\u015feyh"
    ],
    "name:fas_x_preferred":[
        "\u0628\u0627\u0644\u06cc\u0634\u06cc\u0647"
    ],
    "name:fra_x_preferred":[
        "Bal\u0131\u015feyh"
    ],
    "name:ita_x_preferred":[
        "Distretto di Bal\u0131\u015feyh"
    ],
    "name:mrj_x_preferred":[
        "\u0411\u0430\u043b\u044b\u0448\u0435\u0439\u0445"
    ],
    "name:msa_x_preferred":[
        "Bal\u0131\u015feyh"
    ],
    "name:nan_x_preferred":[
        "Bal\u0131\u015feyh"
    ],
    "name:nld_x_preferred":[
        "Bal\u0131\u015feyh"
    ],
    "name:nob_x_preferred":[
        "Bal\u0131\u015feyh"
    ],
    "name:rus_x_preferred":[
        "\u0411\u0430\u043b\u044b\u0448\u0435\u0439\u0445"
    ],
    "name:spa_x_preferred":[
        "Bal\u0131\u015feyh"
    ],
    "name:swa_x_preferred":[
        "Bal\u0131\u015feyh"
    ],
    "name:tat_x_preferred":[
        "\u0411\u0430\u043b\u044b\u0448\u0435\u0439\u0445"
    ],
    "name:tur_x_preferred":[
        "Bal\u0131\u015feyh"
    ],
    "name:und_x_variant":[
        "Bal\u0131\u015f\u0131h"
    ],
    "name:urd_x_preferred":[
        "\u0628\u0627\u0644\u06cc\u0634\u06cc\u06c1"
    ],
    "name:vie_x_preferred":[
        "Bal\u0131\u015feyh"
    ],
    "qs:name":"Bal\u0131\u015feyh",
    "qs:name_adm0":"Turkey",
    "qs:name_adm1":"K\u0131r\u0131kkale",
    "qs:photos":13,
    "qs:photos_1k":3,
    "qs:photos_9k":1,
    "qs:photos_9r":1,
    "qs:photos_all":13,
    "qs:photos_sr":1,
    "qs:placetype":"Town",
    "qs:pop_sr":"0",
    "wd:wordcount":216,
    "wof:name":"Bal\u0131\u015feyh",
    "wof:placetype":"locality",
    "wof:population":4150
},
  "geometry": {"coordinates":[33.740927,39.914538],"type":"Point"}
}