{
  "type": "Feature",
  "properties": {
    "gn:admin1_code":"31.0",
    "gn:asciiname":"Shakiraga",
    "gn:country_code":"TR",
    "gn:dem":583,
    "gn:feature_class":"P",
    "gn:feature_code":"PPL",
    "gn:name":"Shakiraga",
    "gn:population":0,
    "gn:timezone":"Europe/Istanbul",
    "iso:country":"TR",
    "name:und_x_variant":[
        "\u015eakira\u011fa"
    ],
    "wof:name":"Shakiraga",
    "wof:placetype":"locality"
},
  "geometry": {"coordinates":[36.14694,35.85111],"type":"Point"}
}