{
  "type": "Feature",
  "properties": {
    "gn:admin1_code":"21",
    "gn:asciiname":"Bicer",
    "gn:country_code":"TR",
    "gn:dem":960,
    "gn:feature_class":"P",
    "gn:feature_code":"PPL",
    "gn:name":"Bi\u00e7er",
    "gn:population":0,
    "gn:timezone":"Europe/Istanbul",
    "iso:country":"TR",
    "name:tur_x_preferred":[
        "Bi\u00e7er"
    ],
    "wof:name":"Bicer",
    "wof:placetype":"locality"
},
  "geometry": {"coordinates":[40.01818,38.37228],"type":"Point"}
}