{
  "type": "Feature",
  "properties": {
    "gn:admin1_code":"10",
    "gn:asciiname":"Gunaydin",
    "gn:country_code":"TR",
    "gn:dem":310,
    "gn:feature_class":"P",
    "gn:feature_code":"PPL",
    "gn:name":"G\u00fcnayd\u0131n",
    "gn:population":0,
    "gn:timezone":"Europe/Istanbul",
    "iso:country":"TR",
    "name:tur_x_preferred":[
        "G\u00fcnayd\u0131n"
    ],
    "wof:name":"Gunaydin",
    "wof:placetype":"locality"
},
  "geometry": {"coordinates":[28.08661,39.95949],"type":"Point"}
}