{
  "type": "Feature",
  "properties": {
    "gn:admin1_code":"57.0",
    "gn:asciiname":"Bengubelen",
    "gn:country_code":"TR",
    "gn:dem":749,
    "gn:feature_class":"P",
    "gn:feature_code":"PPL",
    "gn:name":"Beng\u00fcbelen",
    "gn:population":0,
    "gn:timezone":"Europe/Istanbul",
    "iso:country":"TR",
    "wof:name":"Bengubelen",
    "wof:placetype":"locality"
},
  "geometry": {"coordinates":[34.70685,41.4147],"type":"Point"}
}