{
  "type": "Feature",
  "properties": {
    "gn:admin1_code":"46",
    "gn:asciiname":"Yolyani",
    "gn:country_code":"TR",
    "gn:dem":968,
    "gn:feature_class":"P",
    "gn:feature_code":"PPL",
    "gn:name":"Yolyan\u0131",
    "gn:population":0,
    "gn:timezone":"Europe/Istanbul",
    "iso:country":"TR",
    "name:und_x_variant":[
        "Fenk",
        "F\u0131rn\u0131zk\u00f6y",
        "Yolyan\u0131"
    ],
    "wof:name":"Yolyani",
    "wof:placetype":"locality"
},
  "geometry": {"coordinates":[36.63361,37.53682],"type":"Point"}
}