{
  "type": "Feature",
  "properties": {
    "iso:country":"TR",
    "name:tur_x_preferred":[
        "Levaz\u0131m"
    ],
    "wof:name":"Levazim",
    "wof:placetype":"neighbourhood"
},
  "geometry": {"coordinates":[29.01939237139011,41.0627435117609],"type":"Point"}
}