{
  "type": "Feature",
  "properties": {
    "gn:admin1_code":"21",
    "gn:asciiname":"Saydamli",
    "gn:country_code":"TR",
    "gn:dem":1290,
    "gn:feature_class":"P",
    "gn:feature_code":"PPL",
    "gn:name":"Saydaml\u0131",
    "gn:population":0,
    "gn:timezone":"Europe/Istanbul",
    "iso:country":"TR",
    "name:und_x_variant":[
        "Saydaml\u0131",
        "Kon\u00e7ah"
    ],
    "wof:name":"Saydamli",
    "wof:placetype":"locality"
},
  "geometry": {"coordinates":[40.63573,38.54868],"type":"Point"}
}