{
  "type": "Feature",
  "properties": {
    "gn:admin1_code":"84.0",
    "gn:asciiname":"Odalar",
    "gn:country_code":"TR",
    "gn:dem":2144,
    "gn:feature_class":"P",
    "gn:feature_code":"PPL",
    "gn:name":"Odalar",
    "gn:population":0,
    "gn:timezone":"Europe/Istanbul",
    "iso:country":"TR",
    "name:tur_x_preferred":[
        "Odalar"
    ],
    "wof:name":"Odalar",
    "wof:placetype":"locality"
},
  "geometry": {"coordinates":[42.82505,40.14213],"type":"Point"}
}