{
  "type": "Feature",
  "properties": {
    "gn:country":"TR",
    "gn:fcode":"PPL",
    "gn:pop":1571,
    "iso:country":"TR",
    "name:tur_x_preferred":[
        "Kaynakkaya"
    ],
    "qs:name":"Kaynakkaya",
    "qs:photos_9r":0,
    "qs:photos_sr":0,
    "qs:pop_sr":"3",
    "wof:name":"Kaynakkaya",
    "wof:placetype":"locality",
    "wof:population":1571
},
  "geometry": {"coordinates":[40.92983,37.33388],"type":"Point"}
}