{
  "type": "Feature",
  "properties": {
    "gn:admin1_code":"37.0",
    "gn:asciiname":"Degirmencay",
    "gn:country_code":"TR",
    "gn:dem":709,
    "gn:feature_class":"P",
    "gn:feature_code":"PPL",
    "gn:name":"De\u011firmen\u00e7ay",
    "gn:population":0,
    "gn:timezone":"Europe/Istanbul",
    "iso:country":"TR",
    "name:und_x_variant":[
        "Muamlar",
        "Mugamlar",
        "De\u011firmen\u00e7ay"
    ],
    "wof:name":"Degirmencay",
    "wof:placetype":"locality"
},
  "geometry": {"coordinates":[33.18916,41.2385],"type":"Point"}
}