{
  "type": "Feature",
  "properties": {
    "gn:admin1_code":"71",
    "gn:asciiname":"Gokcimen",
    "gn:country_code":"TR",
    "gn:dem":1163,
    "gn:feature_class":"P",
    "gn:feature_code":"PPL",
    "gn:name":"G\u00f6k\u00e7imen",
    "gn:population":0,
    "gn:timezone":"Europe/Istanbul",
    "iso:country":"TR",
    "wof:name":"Gokcimen",
    "wof:placetype":"locality"
},
  "geometry": {"coordinates":[31.79844000000001,37.61607],"type":"Point"}
}