{
  "type": "Feature",
  "properties": {
    "gn:admin1_code":"46",
    "gn:asciiname":"Emiroglu",
    "gn:country_code":"TR",
    "gn:dem":545,
    "gn:feature_class":"P",
    "gn:feature_code":"PPL",
    "gn:name":"Emiro\u011flu",
    "gn:population":0,
    "gn:timezone":"Europe/Istanbul",
    "iso:country":"TR",
    "name:tur_x_preferred":[
        "Emiro\u011flu"
    ],
    "wof:name":"Emiroglu",
    "wof:placetype":"locality"
},
  "geometry": {"coordinates":[37.06125,37.33117],"type":"Point"}
}