{
  "type": "Feature",
  "properties": {
    "iso:country":"TR",
    "name:eng_x_preferred":[
        "Merve"
    ],
    "name:tur_x_preferred":[
        "Merve"
    ],
    "wof:name":"Merve",
    "wof:placetype":"neighbourhood"
},
  "geometry": {"coordinates":[29.2409065412496,41.00695638206279],"type":"Point"}
}