{
  "type": "Feature",
  "properties": {
    "gn:country":"TR",
    "gn:fcode":"PPLA2",
    "gn:pop":112969,
    "iso:country":"TR",
    "name:ara_x_preferred":[
        "\u0623\u0644\u0627\u0646\u064a\u0627"
    ],
    "name:deu_x_preferred":[
        "Alanya"
    ],
    "name:eng_x_preferred":[
        "Alanya"
    ],
    "name:fas_x_preferred":[
        "\u0622\u0644\u0627\u0646\u06cc\u0627"
    ],
    "name:fin_x_preferred":[
        "Alanya"
    ],
    "name:fra_x_preferred":[
        "Alanya"
    ],
    "name:heb_x_preferred":[
        "\u05d0\u05dc\u05e0\u05d9\u05d4"
    ],
    "name:ita_x_preferred":[
        "Alanya"
    ],
    "name:jpn_x_preferred":[
        "\u30a2\u30e9\u30f3\u30e4"
    ],
    "name:kat_x_preferred":[
        "\u10d0\u10da\u10d0\u10dc\u10d8\u10d0"
    ],
    "name:kor_x_preferred":[
        "\uc54c\ub77c\ub2c8\uc544"
    ],
    "name:lav_x_preferred":[
        "Alanja"
    ],
    "name:lbe_x_preferred":[
        "\u0410\u043b\u0430\u043d\u044c\u044f"
    ],
    "name:lit_x_preferred":[
        "Alanija"
    ],
    "name:mrj_x_preferred":[
        "\u0410\u043b\u0430\u043d\u044c\u044f"
    ],
    "name:nld_x_preferred":[
        "Alanya"
    ],
    "name:nor_x_preferred":[
        "Alanya"
    ],
    "name:oss_x_preferred":[
        "\u0410\u043b\u0430\u043d\u044c\u044f"
    ],
    "name:pnb_x_preferred":[
        "\u0627\u0644\u0627\u0646\u06cc\u0627"
    ],
    "name:pol_x_preferred":[
        "Alanya"
    ],
    "name:rus_x_preferred":[
        "\u0410\u043b\u0430\u043d\u0438\u044f"
    ],
    "name:rus_x_variant":[
        "\u0410\u043b\u0430\u043d\u044c\u044f"
    ],
    "name:srp_x_preferred":[
        "\u0410\u043b\u0430\u045a\u0430"
    ],
    "name:swe_x_preferred":[
        "Alanya"
    ],
    "name:tur_x_preferred":[
        "Alanya"
    ],
    "name:ukr_x_preferred":[
        "\u0410\u043b\u0430\u043d\u0456\u044f"
    ],
    "name:unk_x_variant":[
        "Coracesium"
    ],
    "name:zho_x_preferred":[
        "\u963f\u62c9\u5c3c\u4e9a"
    ],
    "qs:name":"Alanya",
    "qs:photos_9r":0,
    "qs:photos_sr":0,
    "qs:pop_sr":"9",
    "wd:wordcount":7869,
    "wof:name":"Alanya",
    "wof:placetype":"locality",
    "wof:population":112969
},
  "geometry": {"coordinates":[31.99982,36.54375],"type":"Point"}
}