{
  "type": "Feature",
  "properties": {
    "gn:admin1_code":"4.0",
    "gn:asciiname":"Gunbeli",
    "gn:country_code":"TR",
    "gn:dem":1607,
    "gn:feature_class":"P",
    "gn:feature_code":"PPL",
    "gn:name":"G\u00fcnbeli",
    "gn:population":0,
    "gn:timezone":"Europe/Istanbul",
    "iso:country":"TR",
    "name:tur_x_preferred":[
        "G\u00fcnbeli"
    ],
    "wof:name":"Gunbeli",
    "wof:placetype":"locality"
},
  "geometry": {"coordinates":[42.69674000000001,39.16277],"type":"Point"}
}