{
  "type": "Feature",
  "properties": {
    "gn:admin1_code":"53.0",
    "gn:asciiname":"Kocakopru",
    "gn:country_code":"TR",
    "gn:dem":88,
    "gn:feature_class":"P",
    "gn:feature_code":"PPL",
    "gn:name":"Kocak\u00f6pr\u00fc",
    "gn:population":0,
    "gn:timezone":"Europe/Istanbul",
    "iso:country":"TR",
    "wof:name":"Kocakopru",
    "wof:placetype":"locality"
},
  "geometry": {"coordinates":[40.903,41.13724000000001],"type":"Point"}
}