{
  "type": "Feature",
  "properties": {
    "gn:admin1_code":"71",
    "gn:asciiname":"Gozlu",
    "gn:country_code":"TR",
    "gn:dem":1016,
    "gn:feature_class":"P",
    "gn:feature_code":"PPL",
    "gn:name":"G\u00f6zl\u00fc",
    "gn:population":0,
    "gn:timezone":"Europe/Istanbul",
    "iso:country":"TR",
    "wof:name":"Gozlu",
    "wof:placetype":"locality"
},
  "geometry": {"coordinates":[32.33583,38.43722],"type":"Point"}
}