{
  "type": "Feature",
  "properties": {
    "gn:admin1_code":"43",
    "gn:asciiname":"Yeniler",
    "gn:country_code":"TR",
    "gn:dem":822,
    "gn:feature_class":"P",
    "gn:feature_code":"PPL",
    "gn:name":"Yeniler",
    "gn:population":0,
    "gn:timezone":"Europe/Istanbul",
    "iso:country":"TR",
    "wof:name":"Yeniler",
    "wof:placetype":"locality"
},
  "geometry": {"coordinates":[28.94246,39.24541],"type":"Point"}
}