{
  "type": "Feature",
  "properties": {
    "gn:country":"TR",
    "gn:fcode":"PPL",
    "gn:population":290,
    "iso:country":"TR",
    "name:und_x_variant":[
        "Dzherrakhi"
    ],
    "qs:name":"Yuval\u0131",
    "qs:photos_9r":0,
    "qs:photos_sr":0,
    "qs:pop_sr":"2",
    "wof:name":"Yuval\u0131",
    "wof:placetype":"locality",
    "wof:population":290
},
  "geometry": {"coordinates":[42.07167,37.39333],"type":"Point"}
}