{
  "type": "Feature",
  "properties": {
    "gn:admin1_code":"48",
    "gn:asciiname":"Pinarayagi",
    "gn:country_code":"TR",
    "gn:dem":547,
    "gn:feature_class":"P",
    "gn:feature_code":"PPL",
    "gn:name":"P\u0131naraya\u011f\u0131",
    "gn:population":0,
    "gn:timezone":"Europe/Istanbul",
    "iso:country":"TR",
    "name:tur_x_preferred":[
        "P\u0131naraya\u011f\u0131"
    ],
    "name:tur_x_variant":[
        "Piral"
    ],
    "wof:name":"Pinarayagi",
    "wof:placetype":"locality"
},
  "geometry": {"coordinates":[28.67666,37.36068],"type":"Point"}
}