{
  "type": "Feature",
  "properties": {
    "gn:admin1_code":"71",
    "gn:asciiname":"Erdogdu",
    "gn:country_code":"TR",
    "gn:dem":1014,
    "gn:feature_class":"P",
    "gn:feature_code":"PPL",
    "gn:name":"Erdo\u011fdu",
    "gn:population":0,
    "gn:timezone":"Europe/Istanbul",
    "iso:country":"TR",
    "name:tur_x_preferred":[
        "Erdo\u011fdu"
    ],
    "wof:name":"Erdogdu",
    "wof:placetype":"locality"
},
  "geometry": {"coordinates":[31.64695,38.39773],"type":"Point"}
}