{
  "type": "Feature",
  "properties": {
    "gn:admin1_code":"03",
    "gn:asciiname":"Yesilyayla",
    "gn:country_code":"TR",
    "gn:dem":1207,
    "gn:feature_class":"P",
    "gn:feature_code":"PPL",
    "gn:name":"Ye\u015filyayla",
    "gn:population":0,
    "gn:timezone":"Europe/Istanbul",
    "iso:country":"TR",
    "wof:name":"Yesilyayla",
    "wof:placetype":"locality"
},
  "geometry": {"coordinates":[30.55665,39.03319000000001],"type":"Point"}
}