{
  "type": "Feature",
  "properties": {
    "gn:admin1_code":"90.0",
    "gn:asciiname":"Tahtalikaradut",
    "gn:cc2":"TR",
    "gn:country_code":"TR",
    "gn:dem":856,
    "gn:feature_class":"P",
    "gn:feature_code":"PPL",
    "gn:name":"Tahtal\u0131karadut",
    "gn:population":0,
    "gn:timezone":"Europe/Istanbul",
    "iso:country":"TR",
    "name:ceb_x_preferred":[
        "Tahtal\u0131karadut"
    ],
    "name:msa_x_preferred":[
        "Tahtal\u0131karadut"
    ],
    "name:tur_x_preferred":[
        "Tahtal\u0131karadut"
    ],
    "name:und_x_variant":[
        "Takhtaly-Karadut",
        "Tahtal\u0131karadut K\u00f6y",
        "Tahtal\u0131karadut"
    ],
    "name:vie_x_preferred":[
        "Tahtal\u0131karadut"
    ],
    "wof:name":"Tahtalikaradut",
    "wof:placetype":"locality"
},
  "geometry": {"coordinates":[36.91833,36.94111],"type":"Point"}
}