{
  "type": "Feature",
  "properties": {
    "gn:admin1_code":"70",
    "gn:asciiname":"Kurum",
    "gn:country_code":"TR",
    "gn:dem":2397,
    "gn:feature_class":"P",
    "gn:feature_code":"PPL",
    "gn:name":"Kurum",
    "gn:population":0,
    "gn:timezone":"Europe/Istanbul",
    "iso:country":"TR",
    "name:und_x_variant":[
        "K\u0131ran",
        "K\u00fcr\u00fcn",
        "Kurum"
    ],
    "wof:name":"Kurum",
    "wof:placetype":"locality"
},
  "geometry": {"coordinates":[44.02326,37.75509],"type":"Point"}
}