{
  "type": "Feature",
  "properties": {
    "gn:admin1_code":"03",
    "gn:asciiname":"Burunkaya",
    "gn:country_code":"TR",
    "gn:dem":1025,
    "gn:feature_class":"P",
    "gn:feature_code":"PPL",
    "gn:name":"Burunkaya",
    "gn:population":0,
    "gn:timezone":"Europe/Istanbul",
    "iso:country":"TR",
    "wof:name":"Burunkaya",
    "wof:placetype":"locality"
},
  "geometry": {"coordinates":[30.25381,38.09248],"type":"Point"}
}