{
  "type": "Feature",
  "properties": {
    "gn:admin1_code":"57.0",
    "gn:asciiname":"Kupluce",
    "gn:country_code":"TR",
    "gn:dem":450,
    "gn:feature_class":"P",
    "gn:feature_code":"PPL",
    "gn:name":"K\u00fcpl\u00fcce",
    "gn:population":0,
    "gn:timezone":"Europe/Istanbul",
    "iso:country":"TR",
    "name:tur_x_preferred":[
        "K\u00fcpl\u00fcce"
    ],
    "wof:name":"Kupluce",
    "wof:placetype":"locality"
},
  "geometry": {"coordinates":[35.36023,41.65928],"type":"Point"}
}