{
  "type": "Feature",
  "properties": {
    "gn:admin1_code":"72.0",
    "gn:asciiname":"Cayonu",
    "gn:country_code":"TR",
    "gn:dem":1008,
    "gn:feature_class":"P",
    "gn:feature_code":"PPL",
    "gn:name":"\u00c7ay\u00f6n\u00fc",
    "gn:population":0,
    "gn:timezone":"Europe/Istanbul",
    "iso:country":"TR",
    "name:tur_x_preferred":[
        "\u00c7ay\u00f6n\u00fc"
    ],
    "wof:name":"Cayonu",
    "wof:placetype":"locality"
},
  "geometry": {"coordinates":[40.39719,37.38486],"type":"Point"}
}