{
  "type": "Feature",
  "properties": {
    "gn:admin1_code":"66",
    "gn:asciiname":"Hacicesmesi",
    "gn:country_code":"TR",
    "gn:dem":1029,
    "gn:feature_class":"P",
    "gn:feature_code":"PPL",
    "gn:name":"Hac\u0131\u00e7e\u015fmesi",
    "gn:population":0,
    "gn:timezone":"Europe/Istanbul",
    "iso:country":"TR",
    "name:und_x_variant":[
        "Hac\u0131\u00e7e\u015fmesik\u00f6y",
        "Had\u0131\u00e7e\u015fmesi",
        "Hac\u0131\u00e7e\u015fmesi"
    ],
    "wof:name":"Hacicesmesi",
    "wof:placetype":"locality"
},
  "geometry": {"coordinates":[34.43344,39.76385],"type":"Point"}
}