{
  "type": "Feature",
  "properties": {
    "gn:admin1_code":"63.0",
    "gn:asciiname":"Ibrik",
    "gn:country_code":"TR",
    "gn:dem":459,
    "gn:feature_class":"P",
    "gn:feature_code":"PPL",
    "gn:name":"\u0130brik",
    "gn:population":0,
    "gn:timezone":"Europe/Istanbul",
    "iso:country":"TR",
    "name:tur_x_preferred":[
        "\u0130brik"
    ],
    "wof:name":"Ibrik",
    "wof:placetype":"locality"
},
  "geometry": {"coordinates":[39.14782,37.10465],"type":"Point"}
}