{
  "type": "Feature",
  "properties": {
    "gn:admin1_code":"63.0",
    "gn:asciiname":"Ibrik",
    "gn:country_code":"TR",
    "gn:dem":459,
    "gn:feature_class":"P",
    "gn:feature_code":"PPL",
    "gn:name":"\u0130brik",
    "gn:population":0,
    "gn:timezone":"Europe/Istanbul",
    "iso:country":"TR",
    "name:bul_x_preferred":[
        "\u0418\u0431\u0440\u0438\u043a"
    ],
    "name:deu_x_preferred":[
        "Ibr\u012bq"
    ],
    "name:kaz_x_preferred":[
        "\u049a\u04b1\u043c\u0430\u043d"
    ],
    "name:kur_x_preferred":[
        "Mis\u00een"
    ],
    "name:srp_x_preferred":[
        "\u0418\u0431\u0440\u0438\u043a"
    ],
    "name:tur_x_preferred":[
        "\u0130brik"
    ],
    "wof:name":"Ibrik",
    "wof:placetype":"locality"
},
  "geometry": {"coordinates":[39.14782,37.10465],"type":"Point"}
}