{
  "type": "Feature",
  "properties": {
    "gn:admin1_code":"65",
    "gn:asciiname":"Davdana",
    "gn:country_code":"TR",
    "gn:dem":2456,
    "gn:feature_class":"P",
    "gn:feature_code":"PPL",
    "gn:name":"Davdana",
    "gn:population":0,
    "gn:timezone":"Europe/Istanbul",
    "iso:country":"TR",
    "name:tur_x_preferred":[
        "Davutabal"
    ],
    "wof:name":"Davdana",
    "wof:placetype":"locality"
},
  "geometry": {"coordinates":[44.26667,38.36667],"type":"Point"}
}