{
  "type": "Feature",
  "properties": {
    "gn:admin1_code":"25.0",
    "gn:asciiname":"Irmakkoy",
    "gn:country_code":"TR",
    "gn:dem":1928,
    "gn:feature_class":"P",
    "gn:feature_code":"PPL",
    "gn:name":"Irmakk\u00f6y",
    "gn:population":0,
    "gn:timezone":"Europe/Istanbul",
    "iso:country":"TR",
    "name:tur_x_preferred":[
        "Irmakk\u00f6y"
    ],
    "name:und_x_variant":[
        "Irmak"
    ],
    "wof:name":"Irmakkoy",
    "wof:placetype":"locality"
},
  "geometry": {"coordinates":[41.11698,40.4851],"type":"Point"}
}