{
  "type": "Feature",
  "properties": {
    "gn:admin1_code":"83",
    "gn:asciiname":"Salkim",
    "gn:country_code":"TR",
    "gn:dem":694,
    "gn:feature_class":"P",
    "gn:feature_code":"PPL",
    "gn:name":"Salk\u0131m",
    "gn:population":0,
    "gn:timezone":"Europe/Istanbul",
    "iso:country":"TR",
    "name:und_x_variant":[
        "Salk\u0131m"
    ],
    "wof:name":"Salkim",
    "wof:placetype":"locality"
},
  "geometry": {"coordinates":[37.69333,37.15087],"type":"Point"}
}