{
  "type": "Feature",
  "properties": {
    "gn:admin1_code":"31.0",
    "gn:asciiname":"Alazi",
    "gn:country_code":"TR",
    "gn:dem":130,
    "gn:feature_class":"P",
    "gn:feature_code":"PPL",
    "gn:name":"Alaz\u0131",
    "gn:population":0,
    "gn:timezone":"Europe/Istanbul",
    "iso:country":"TR",
    "name:und_x_variant":[
        "Kyrgyzavakly",
        "Kirgizavakl\u0131",
        "Alaz\u0131"
    ],
    "wof:name":"Alazi",
    "wof:placetype":"locality"
},
  "geometry": {"coordinates":[36.19123,36.30044],"type":"Point"}
}