{
  "type": "Feature",
  "properties": {
    "gn:admin1_code":"77.0",
    "gn:asciiname":"Guneydere",
    "gn:country_code":"TR",
    "gn:dem":1756,
    "gn:feature_class":"P",
    "gn:feature_code":"PPL",
    "gn:name":"G\u00fcneydere",
    "gn:population":0,
    "gn:timezone":"Europe/Istanbul",
    "iso:country":"TR",
    "name:und_x_variant":[
        "S\u00f6fker",
        "G\u00fcneydere"
    ],
    "wof:name":"Guneydere",
    "wof:placetype":"locality"
},
  "geometry": {"coordinates":[39.8989,40.38174],"type":"Point"}
}