{
  "type": "Feature",
  "properties": {
    "gn:admin1_code":"93.0",
    "gn:asciiname":"Ballar",
    "gn:country_code":"TR",
    "gn:dem":368,
    "gn:feature_class":"P",
    "gn:feature_code":"PPL",
    "gn:name":"Ballar",
    "gn:population":0,
    "gn:timezone":"Europe/Istanbul",
    "iso:country":"TR",
    "name:aze_x_preferred":[
        "Ballar"
    ],
    "name:che_x_preferred":[
        "\u0411\u0430\u043b\u043b\u0430\u0440"
    ],
    "name:kat_x_preferred":[
        "\u10d1\u10d0\u10da\u10d0\u10e0\u10d8"
    ],
    "name:min_x_preferred":[
        "Ballar"
    ],
    "name:msa_x_preferred":[
        "Ballar"
    ],
    "name:rus_x_preferred":[
        "\u0411\u0430\u043b\u043b\u0430\u0440"
    ],
    "name:tur_x_preferred":[
        "Ballar"
    ],
    "wof:name":"Ballar",
    "wof:placetype":"locality"
},
  "geometry": {"coordinates":[31.15214000000001,40.95363],"type":"Point"}
}