{
  "type": "Feature",
  "properties": {
    "gn:admin1_code":"60.0",
    "gn:asciiname":"Asar",
    "gn:country_code":"TR",
    "gn:dem":767,
    "gn:feature_class":"P",
    "gn:feature_code":"PPL",
    "gn:name":"Asar",
    "gn:population":0,
    "gn:timezone":"Europe/Istanbul",
    "iso:country":"TR",
    "name:ceb_x_preferred":[
        "Asar"
    ],
    "name:deu_x_preferred":[
        "Asar"
    ],
    "name:glg_x_preferred":[
        "Asar"
    ],
    "name:spa_x_preferred":[
        "Asar"
    ],
    "name:swe_x_preferred":[
        "Asar"
    ],
    "wof:name":"Asar",
    "wof:placetype":"locality"
},
  "geometry": {"coordinates":[37.08452,40.47036],"type":"Point"}
}