{
  "type": "Feature",
  "properties": {
    "gn:admin1_code":"59.0",
    "gn:asciiname":"Kiliclar",
    "gn:country_code":"TR",
    "gn:dem":82,
    "gn:feature_class":"P",
    "gn:feature_code":"PPL",
    "gn:name":"K\u0131l\u0131\u00e7lar",
    "gn:population":0,
    "gn:timezone":"Europe/Istanbul",
    "iso:country":"TR",
    "wof:name":"Kiliclar",
    "wof:placetype":"locality"
},
  "geometry": {"coordinates":[27.29591,41.24285],"type":"Point"}
}