{
  "type": "Feature",
  "properties": {
    "gn:admin1_code":"87.0",
    "gn:asciiname":"Kabasakaloglu",
    "gn:country_code":"TR",
    "gn:dem":453,
    "gn:feature_class":"P",
    "gn:feature_code":"PPL",
    "gn:name":"Kabasakalo\u011flu",
    "gn:population":0,
    "gn:timezone":"Europe/Istanbul",
    "iso:country":"TR",
    "name:und_x_variant":[
        "Kabasakalo\u011flu",
        "Kad\u0131o\u011flu"
    ],
    "wof:name":"Kabasakaloglu",
    "wof:placetype":"locality"
},
  "geometry": {"coordinates":[32.6006,41.43263],"type":"Point"}
}