{
  "type": "Feature",
  "properties": {
    "gn:admin1_code":"21",
    "gn:asciiname":"Seren",
    "gn:country_code":"TR",
    "gn:dem":1135,
    "gn:feature_class":"P",
    "gn:feature_code":"PPL",
    "gn:name":"Seren",
    "gn:population":0,
    "gn:timezone":"Europe/Istanbul",
    "iso:country":"TR",
    "name:cym_x_preferred":[
        "Seren"
    ],
    "name:fas_x_preferred":[
        "\u0633\u0631\u0646"
    ],
    "name:heb_x_preferred":[
        "\u05e1\u05e8\u05df"
    ],
    "name:nld_x_preferred":[
        "Seren"
    ],
    "name:rus_x_preferred":[
        "\u0421\u0435\u0440\u0435\u043d"
    ],
    "name:ukr_x_preferred":[
        "\u0421\u0435\u0440\u0435\u043d"
    ],
    "name:und_x_variant":[
        "Tavil"
    ],
    "wof:name":"Seren",
    "wof:placetype":"locality"
},
  "geometry": {"coordinates":[40.47731,38.41695],"type":"Point"}
}