{
  "type": "Feature",
  "properties": {
    "gn:admin1_code":"23",
    "gn:asciiname":"Kumlutarla",
    "gn:country_code":"TR",
    "gn:dem":674,
    "gn:feature_class":"P",
    "gn:feature_code":"PPL",
    "gn:name":"Kumlutarla",
    "gn:population":0,
    "gn:timezone":"Europe/Istanbul",
    "iso:country":"TR",
    "name:und_x_variant":[
        "Ataf",
        "Kumlutarla"
    ],
    "wof:name":"Kumlutarla",
    "wof:placetype":"locality"
},
  "geometry": {"coordinates":[38.4825,38.70284],"type":"Point"}
}