{
  "type": "Feature",
  "properties": {
    "gn:admin1_code":"63",
    "gn:asciiname":"Karabahce",
    "gn:country_code":"TR",
    "gn:dem":1260,
    "gn:feature_class":"P",
    "gn:feature_code":"PPL",
    "gn:name":"Karabah\u00e7e",
    "gn:population":0,
    "gn:timezone":"Europe/Istanbul",
    "iso:country":"TR",
    "name:tur_x_preferred":[
        "Karabah\u00e7e"
    ],
    "wof:name":"Karabahce",
    "wof:placetype":"locality"
},
  "geometry": {"coordinates":[39.76464,37.79529],"type":"Point"}
}