{
  "type": "Feature",
  "properties": {
    "gn:admin1_code":"63.0",
    "gn:asciiname":"Buyuk Cafer",
    "gn:country_code":"TR",
    "gn:dem":382,
    "gn:feature_class":"P",
    "gn:feature_code":"PPL",
    "gn:name":"B\u00fcy\u00fck Cafer",
    "gn:population":0,
    "gn:timezone":"Europe/Istanbul",
    "iso:country":"TR",
    "name:und_x_variant":[
        "Byuyuk-Dzhafer",
        "B\u00fcy\u00fck Cafer"
    ],
    "wof:name":"Buyuk Cafer",
    "wof:placetype":"locality"
},
  "geometry": {"coordinates":[39.12222,36.96528],"type":"Point"}
}