{
  "type": "Feature",
  "properties": {
    "gn:admin1_code":"52.0",
    "gn:asciiname":"Herkozu",
    "gn:country_code":"TR",
    "gn:dem":1670,
    "gn:feature_class":"P",
    "gn:feature_code":"PPL",
    "gn:name":"Herk\u00f6z\u00fc",
    "gn:population":0,
    "gn:timezone":"Europe/Istanbul",
    "iso:country":"TR",
    "name:tur_x_preferred":[
        "Herk\u00f6z\u00fc"
    ],
    "wof:name":"Herkozu",
    "wof:placetype":"locality"
},
  "geometry": {"coordinates":[37.96308,40.49974],"type":"Point"}
}