{
  "type": "Feature",
  "properties": {
    "gn:admin1_code":"40",
    "gn:asciiname":"Seyrekkoy",
    "gn:country_code":"TR",
    "gn:dem":1239,
    "gn:feature_class":"P",
    "gn:feature_code":"PPL",
    "gn:name":"Seyrekk\u00f6y",
    "gn:population":0,
    "gn:timezone":"Europe/Istanbul",
    "iso:country":"TR",
    "name:tur_x_preferred":[
        "Seyrekk\u00f6y"
    ],
    "name:tur_x_variant":[
        "Seyrek"
    ],
    "wof:name":"Seyrekkoy",
    "wof:placetype":"locality"
},
  "geometry": {"coordinates":[34.27327,39.44549],"type":"Point"}
}