{
  "type": "Feature",
  "properties": {
    "gn:admin1_code":"45",
    "gn:asciiname":"Kabazli",
    "gn:country_code":"TR",
    "gn:dem":124,
    "gn:feature_class":"P",
    "gn:feature_code":"PPL",
    "gn:name":"Kabazl\u0131",
    "gn:population":0,
    "gn:timezone":"Europe/Istanbul",
    "iso:country":"TR",
    "name:tur_x_preferred":[
        "Kabazl\u0131"
    ],
    "wof:name":"Kabazli",
    "wof:placetype":"locality"
},
  "geometry": {"coordinates":[28.21169,38.46995],"type":"Point"}
}