{
  "type": "Feature",
  "properties": {
    "gn:admin1_code":"71",
    "gn:asciiname":"Buyuk Hasan",
    "gn:country_code":"TR",
    "gn:dem":939,
    "gn:feature_class":"P",
    "gn:feature_code":"PPL",
    "gn:name":"B\u00fcy\u00fck Hasan",
    "gn:population":0,
    "gn:timezone":"Europe/Istanbul",
    "iso:country":"TR",
    "name:und_x_variant":[
        "B\u00fcy\u00fck Hasan",
        "Zeybek Yaylas\u0131"
    ],
    "wof:name":"Buyuk Hasan",
    "wof:placetype":"locality"
},
  "geometry": {"coordinates":[31.81897,38.92248],"type":"Point"}
}