{
  "type": "Feature",
  "properties": {
    "gn:admin1_code":"60.0",
    "gn:asciiname":"Saltik",
    "gn:country_code":"TR",
    "gn:dem":1389,
    "gn:feature_class":"P",
    "gn:feature_code":"PPL",
    "gn:name":"Salt\u0131k",
    "gn:population":0,
    "gn:timezone":"Europe/Istanbul",
    "iso:country":"TR",
    "name:deu_x_preferred":[
        "Salt\u0131k"
    ],
    "name:tgl_x_preferred":[
        "Saltik"
    ],
    "name:und_x_variant":[
        "Salt\u0131k",
        "Karacalar"
    ],
    "wof:name":"Saltik",
    "wof:placetype":"locality"
},
  "geometry": {"coordinates":[36.58395,40.20184],"type":"Point"}
}