{
  "type": "Feature",
  "properties": {
    "gn:admin1_code":"14",
    "gn:asciiname":"Tekkeler",
    "gn:country_code":"TR",
    "gn:dem":1131,
    "gn:feature_class":"P",
    "gn:feature_code":"PPL",
    "gn:name":"Tekkeler",
    "gn:population":0,
    "gn:timezone":"Europe/Istanbul",
    "iso:country":"TR",
    "wof:name":"Tekkeler",
    "wof:placetype":"locality"
},
  "geometry": {"coordinates":[31.45413,40.67097],"type":"Point"}
}