{
  "type": "Feature",
  "properties": {
    "gn:admin1_code":"63",
    "gn:asciiname":"Sucuhan",
    "gn:country_code":"TR",
    "gn:dem":650,
    "gn:feature_class":"P",
    "gn:feature_code":"PPL",
    "gn:name":"Sucuhan",
    "gn:population":0,
    "gn:timezone":"Europe/Istanbul",
    "iso:country":"TR",
    "name:und_x_variant":[
        "Sucihan",
        "Sucuhan",
        "Saruhan"
    ],
    "wof:name":"Sucuhan",
    "wof:placetype":"locality"
},
  "geometry": {"coordinates":[39.16194,37.55731],"type":"Point"}
}