{
  "type": "Feature",
  "properties": {
    "gn:admin1_code":"77.0",
    "gn:asciiname":"Cakirbag",
    "gn:country_code":"TR",
    "gn:dem":1475,
    "gn:feature_class":"P",
    "gn:feature_code":"PPL",
    "gn:name":"\u00c7ak\u0131rba\u011f",
    "gn:population":0,
    "gn:timezone":"Europe/Istanbul",
    "iso:country":"TR",
    "name:eng_x_preferred":[
        "\u00c7ak\u0131rba\u011f"
    ],
    "name:rus_x_preferred":[
        "\u0410\u0431\u0443\u0441\u0442\u0430"
    ],
    "name:und_x_variant":[
        "Abusta"
    ],
    "wof:name":"Cakirbag",
    "wof:placetype":"locality"
},
  "geometry": {"coordinates":[40.4982,40.39444],"type":"Point"}
}