{
  "type": "Feature",
  "properties": {
    "gn:country":"TR",
    "gn:fcode":"PPL",
    "gn:pop":439,
    "iso:country":"TR",
    "name:arg_x_preferred":[
        "Belos"
    ],
    "name:cat_x_preferred":[
        "Bel\u00b7les"
    ],
    "name:fra_x_preferred":[
        "Belli"
    ],
    "name:ita_x_preferred":[
        "Belli"
    ],
    "name:rus_x_preferred":[
        "\u0411\u0435\u043b\u043b\u044b"
    ],
    "name:spa_x_preferred":[
        "Bellos"
    ],
    "name:tur_x_preferred":[
        "Belli"
    ],
    "name:ukr_x_preferred":[
        "\u0411\u0435\u043b\u0438"
    ],
    "name:unk_x_variant":[
        "Zeko"
    ],
    "qs:name":"Belli",
    "qs:photos_9r":0,
    "qs:photos_sr":0,
    "qs:pop_sr":"2",
    "wd:wordcount":1066,
    "wof:name":"Belli",
    "wof:placetype":"locality",
    "wof:population":439
},
  "geometry": {"coordinates":[40.81639,37.91111],"type":"Point"}
}