{
  "type": "Feature",
  "properties": {
    "gn:admin1_code":"52.0",
    "gn:asciiname":"Kemikgeris",
    "gn:country_code":"TR",
    "gn:dem":931,
    "gn:feature_class":"P",
    "gn:feature_code":"PPL",
    "gn:name":"Kemikgeri\u015f",
    "gn:population":0,
    "gn:timezone":"Europe/Istanbul",
    "iso:country":"TR",
    "wof:name":"Kemikgeris",
    "wof:placetype":"locality"
},
  "geometry": {"coordinates":[36.914,40.8232],"type":"Point"}
}