{
  "type": "Feature",
  "properties": {
    "gn:admin1_code":"34.0",
    "gn:asciiname":"Pinarca",
    "gn:country_code":"TR",
    "gn:dem":153,
    "gn:feature_class":"P",
    "gn:feature_code":"PPL",
    "gn:name":"P\u0131narca",
    "gn:population":0,
    "gn:timezone":"Europe/Istanbul",
    "iso:country":"TR",
    "name:tur_x_preferred":[
        "P\u0131narca"
    ],
    "wof:name":"Pinarca",
    "wof:placetype":"locality"
},
  "geometry": {"coordinates":[28.3225,41.27016],"type":"Point"}
}