{
  "type": "Feature",
  "properties": {
    "gn:admin1_code":"63.0",
    "gn:asciiname":"Saburi",
    "gn:country_code":"TR",
    "gn:dem":635,
    "gn:feature_class":"P",
    "gn:feature_code":"PPL",
    "gn:name":"Saburi",
    "gn:population":0,
    "gn:timezone":"Europe/Istanbul",
    "iso:country":"TR",
    "name:est_x_preferred":[
        "Saburi"
    ],
    "name:fra_x_preferred":[
        "Saburi"
    ],
    "name:hye_x_preferred":[
        "\u054d\u0561\u0562\u0578\u0582\u057c\u056b"
    ],
    "name:pol_x_preferred":[
        "Saburi"
    ],
    "name:spa_x_preferred":[
        "Saburi"
    ],
    "name:ukr_x_preferred":[
        "\u0421\u0430\u0431\u0443\u0440\u0456"
    ],
    "name:und_x_variant":[
        "Razvaliny Saburi",
        "Saburi"
    ],
    "name:urd_x_preferred":[
        "\u0635\u0628\u0631\u06cc"
    ],
    "name:vol_x_preferred":[
        "Saburi"
    ],
    "wof:name":"Saburi",
    "wof:placetype":"locality"
},
  "geometry": {"coordinates":[38.24605,36.97806],"type":"Point"}
}