{
  "type": "Feature",
  "properties": {
    "gn:admin1_code":"81.0",
    "gn:asciiname":"Kargakekec",
    "gn:country_code":"TR",
    "gn:dem":121,
    "gn:feature_class":"P",
    "gn:feature_code":"PPL",
    "gn:name":"Kargakeke\u00e7",
    "gn:population":0,
    "gn:timezone":"Europe/Istanbul",
    "iso:country":"TR",
    "wof:name":"Kargakekec",
    "wof:placetype":"locality"
},
  "geometry": {"coordinates":[35.37365,37.12492],"type":"Point"}
}