{
  "type": "Feature",
  "properties": {
    "gn:admin1_code":"88.0",
    "gn:asciiname":"Dipsiz",
    "gn:country_code":"TR",
    "gn:dem":2104,
    "gn:feature_class":"P",
    "gn:feature_code":"PPL",
    "gn:name":"Dipsiz",
    "gn:population":0,
    "gn:timezone":"Europe/Istanbul",
    "iso:country":"TR",
    "wof:name":"Dipsiz",
    "wof:placetype":"locality"
},
  "geometry": {"coordinates":[43.40669000000001,40.04737],"type":"Point"}
}