{
  "type": "Feature",
  "properties": {
    "gn:admin1_code":"70",
    "gn:asciiname":"Kamisli",
    "gn:country_code":"TR",
    "gn:dem":1769,
    "gn:feature_class":"P",
    "gn:feature_code":"PPL",
    "gn:name":"Kam\u0131\u015fl\u0131",
    "gn:population":0,
    "gn:timezone":"Europe/Istanbul",
    "iso:country":"TR",
    "name:und_x_variant":[
        "Kam\u0131\u015fl\u0131"
    ],
    "wof:name":"Kamisli",
    "wof:placetype":"locality"
},
  "geometry": {"coordinates":[43.51741,37.55973],"type":"Point"}
}