{
  "type": "Feature",
  "properties": {
    "gn:admin1_code":"32",
    "gn:asciiname":"Fidikli",
    "gn:country_code":"TR",
    "gn:dem":211,
    "gn:feature_class":"P",
    "gn:feature_code":"PPL",
    "gn:name":"Fidikli",
    "gn:population":0,
    "gn:timezone":"Europe/Istanbul",
    "iso:country":"TR",
    "name:und_x_variant":[
        "Teked\u00fcz\u00fc",
        "Fidikli"
    ],
    "wof:name":"Fidikli",
    "wof:placetype":"locality"
},
  "geometry": {"coordinates":[33.02744000000001,36.13721],"type":"Point"}
}