{
  "type": "Feature",
  "properties": {
    "gn:admin1_code":"04",
    "gn:asciiname":"Gumusyazi",
    "gn:country_code":"TR",
    "gn:dem":1827,
    "gn:feature_class":"P",
    "gn:feature_code":"PPL",
    "gn:name":"G\u00fcm\u00fc\u015fyaz\u0131",
    "gn:population":0,
    "gn:timezone":"Europe/Istanbul",
    "iso:country":"TR",
    "name:und_x_variant":[
        "S\u0131rdo",
        "G\u00fcm\u00fc\u015fyaz\u0131"
    ],
    "wof:name":"Gumusyazi",
    "wof:placetype":"locality"
},
  "geometry": {"coordinates":[43.16166,39.82716],"type":"Point"}
}