{
  "type": "Feature",
  "properties": {
    "gn:admin1_code":"21",
    "gn:asciiname":"Yolbulan",
    "gn:country_code":"TR",
    "gn:dem":969,
    "gn:feature_class":"P",
    "gn:feature_code":"PPL",
    "gn:name":"Yolbulan",
    "gn:population":0,
    "gn:timezone":"Europe/Istanbul",
    "iso:country":"TR",
    "name:tur_x_preferred":[
        "Yolbulan"
    ],
    "wof:name":"Yolbulan",
    "wof:placetype":"locality"
},
  "geometry": {"coordinates":[39.62605,38.22995],"type":"Point"}
}