{
  "type": "Feature",
  "properties": {
    "gn:admin1_code":"21",
    "gn:asciiname":"Armagantasi",
    "gn:country_code":"TR",
    "gn:dem":728,
    "gn:feature_class":"P",
    "gn:feature_code":"PPL",
    "gn:name":"Arma\u011fanta\u015f\u0131",
    "gn:population":0,
    "gn:timezone":"Europe/Istanbul",
    "iso:country":"TR",
    "name:tur_x_preferred":[
        "Ah\u0131rmat"
    ],
    "name:und_x_variant":[
        "Arma\u011fanta\u015f\u0131",
        "\u00c7atalp\u0131nar"
    ],
    "wof:name":"Armagantasi",
    "wof:placetype":"locality"
},
  "geometry": {"coordinates":[39.15802,38.00518],"type":"Point"}
}