{
  "type": "Feature",
  "properties": {
    "gn:admin1_code":"25.0",
    "gn:asciiname":"Hizirilyas",
    "gn:country_code":"TR",
    "gn:dem":1668,
    "gn:feature_class":"P",
    "gn:feature_code":"PPL",
    "gn:name":"H\u0131z\u0131rilyas",
    "gn:population":0,
    "gn:timezone":"Europe/Istanbul",
    "iso:country":"TR",
    "name:tur_x_preferred":[
        "H\u0131z\u0131rilyas"
    ],
    "wof:name":"Hizirilyas",
    "wof:placetype":"locality"
},
  "geometry": {"coordinates":[42.22817,40.13576],"type":"Point"}
}