{
  "type": "Feature",
  "properties": {
    "gn:admin1_code":"74",
    "gn:asciiname":"Akcagedik",
    "gn:country_code":"TR",
    "gn:dem":764,
    "gn:feature_class":"P",
    "gn:feature_code":"PPL",
    "gn:name":"Ak\u00e7agedik",
    "gn:population":0,
    "gn:timezone":"Europe/Istanbul",
    "iso:country":"TR",
    "name:tur_x_preferred":[
        "Ak\u00e7agedik"
    ],
    "name:und_x_variant":[
        "Zokeyt",
        "kurtalan",
        "Zokay\u0131t",
        "Zokayt"
    ],
    "wof:name":"Akcagedik",
    "wof:placetype":"locality"
},
  "geometry": {"coordinates":[41.55922,38.04888],"type":"Point"}
}