{
  "type": "Feature",
  "properties": {
    "gn:admin1_code":"63",
    "gn:asciiname":"Golebakan",
    "gn:country_code":"TR",
    "gn:dem":641,
    "gn:feature_class":"P",
    "gn:feature_code":"PPL",
    "gn:name":"G\u00f6lebakan",
    "gn:population":0,
    "gn:timezone":"Europe/Istanbul",
    "iso:country":"TR",
    "name:tur_x_preferred":[
        "G\u00f6lebakan"
    ],
    "wof:name":"Golebakan",
    "wof:placetype":"locality"
},
  "geometry": {"coordinates":[39.1182,37.4888],"type":"Point"}
}