{
  "type": "Feature",
  "properties": {
    "gn:admin1_code":"44",
    "gn:asciiname":"Yukari Ulupinar",
    "gn:country_code":"TR",
    "gn:dem":1369,
    "gn:feature_class":"P",
    "gn:feature_code":"PPL",
    "gn:name":"Yukar\u0131 Ulup\u0131nar",
    "gn:population":0,
    "gn:timezone":"Europe/Istanbul",
    "iso:country":"TR",
    "name:tur_x_preferred":[
        "Yukar\u0131 Ulup\u0131nar"
    ],
    "name:und_x_variant":[
        "Yukar\u0131ulup\u0131nar",
        "Yukar\u0131setrek"
    ],
    "wof:name":"Yukari Ulupinar",
    "wof:placetype":"locality"
},
  "geometry": {"coordinates":[37.57668,38.39638],"type":"Point"}
}