{
  "type": "Feature",
  "properties": {
    "gn:admin1_code":"21",
    "gn:asciiname":"Kusburnu",
    "gn:country_code":"TR",
    "gn:dem":645,
    "gn:feature_class":"P",
    "gn:feature_code":"PPL",
    "gn:name":"Ku\u015fburnu",
    "gn:population":0,
    "gn:timezone":"Europe/Istanbul",
    "iso:country":"TR",
    "name:tur_x_preferred":[
        "Ku\u015fburnu"
    ],
    "name:und_x_variant":[
        "Erveni"
    ],
    "wof:name":"Kusburnu",
    "wof:placetype":"locality"
},
  "geometry": {"coordinates":[40.36366,37.99459],"type":"Point"}
}