{
  "type": "Feature",
  "properties": {
    "gn:admin1_code":"12",
    "gn:asciiname":"Kutludugun",
    "gn:country_code":"TR",
    "gn:dem":851,
    "gn:feature_class":"P",
    "gn:feature_code":"PPL",
    "gn:name":"Kutlud\u00fc\u011f\u00fcn",
    "gn:population":0,
    "gn:timezone":"Europe/Istanbul",
    "iso:country":"TR",
    "name:tur_x_preferred":[
        "Kutlud\u00fc\u011f\u00fcn"
    ],
    "wof:name":"Kutludugun",
    "wof:placetype":"locality"
},
  "geometry": {"coordinates":[40.28583,38.49139],"type":"Point"}
}