{
  "type": "Feature",
  "properties": {
    "gn:admin1_code":"68",
    "gn:asciiname":"Bursal",
    "gn:country_code":"TR",
    "gn:dem":1115,
    "gn:feature_class":"P",
    "gn:feature_code":"PPL",
    "gn:name":"Bursal",
    "gn:population":0,
    "gn:timezone":"Europe/Istanbul",
    "iso:country":"TR",
    "wof:name":"Bursal",
    "wof:placetype":"locality"
},
  "geometry": {"coordinates":[32.88444,39.79778],"type":"Point"}
}