{
  "type": "Feature",
  "properties": {
    "gn:admin1_code":"84.0",
    "gn:asciiname":"Mescitli",
    "gn:country_code":"TR",
    "gn:dem":1824,
    "gn:feature_class":"P",
    "gn:feature_code":"PPL",
    "gn:name":"Mescitli",
    "gn:population":0,
    "gn:timezone":"Europe/Istanbul",
    "iso:country":"TR",
    "name:tur_x_preferred":[
        "Mescitli"
    ],
    "wof:name":"Mescitli",
    "wof:placetype":"locality"
},
  "geometry": {"coordinates":[42.64351,40.21531],"type":"Point"}
}