{
  "type": "Feature",
  "properties": {
    "gn:admin1_code":"28.0",
    "gn:asciiname":"Altinova",
    "gn:country_code":"TR",
    "gn:dem":1383,
    "gn:feature_class":"P",
    "gn:feature_code":"PPL",
    "gn:name":"Alt\u0131nova",
    "gn:population":0,
    "gn:timezone":"Europe/Istanbul",
    "iso:country":"TR",
    "name:tur_x_preferred":[
        "Alt\u0131nova"
    ],
    "wof:name":"Altinova",
    "wof:placetype":"locality"
},
  "geometry": {"coordinates":[38.63045,40.3551],"type":"Point"}
}