{
  "type": "Feature",
  "properties": {
    "gn:country":"TR",
    "gn:fcode":"PPL",
    "gn:pop":342,
    "iso:country":"TR",
    "name:unk_x_variant":[
        "Zerziya"
    ],
    "qs:name":"S\u0131rmal\u0131",
    "qs:photos_9r":0,
    "qs:photos_sr":0,
    "qs:pop_sr":"2",
    "wof:name":"S\u0131rmal\u0131",
    "wof:placetype":"locality",
    "wof:population":342
},
  "geometry": {"coordinates":[43.21861,37.83833],"type":"Point"}
}