{
  "type": "Feature",
  "properties": {
    "gn:admin1_code":"31.0",
    "gn:asciiname":"Nahirli",
    "gn:country_code":"TR",
    "gn:dem":195,
    "gn:feature_class":"P",
    "gn:feature_code":"PPL",
    "gn:name":"Nah\u0131rl\u0131",
    "gn:population":0,
    "gn:timezone":"Europe/Istanbul",
    "iso:country":"TR",
    "name:und_x_variant":[
        "Nakhyrly",
        "Nah\u0131rl\u0131"
    ],
    "wof:name":"Nahirli",
    "wof:placetype":"locality"
},
  "geometry": {"coordinates":[36.05432,36.10171],"type":"Point"}
}