{
  "type": "Feature",
  "properties": {
    "gn:admin1_code":"24",
    "gn:asciiname":"Gengerli",
    "gn:cc2":"TR",
    "gn:country_code":"TR",
    "gn:dem":1827,
    "gn:feature_class":"P",
    "gn:feature_code":"PPL",
    "gn:name":"Gengerli",
    "gn:population":0,
    "gn:timezone":"Europe/Istanbul",
    "iso:country":"TR",
    "name:und_x_variant":[
        "\u00c7engerli",
        "Gengerli"
    ],
    "wof:name":"Gengerli",
    "wof:placetype":"locality"
},
  "geometry": {"coordinates":[38.88333,39.81667],"type":"Point"}
}