{
  "type": "Feature",
  "properties": {
    "gn:admin1_code":"76.0",
    "gn:asciiname":"Kislacik",
    "gn:country_code":"TR",
    "gn:dem":843,
    "gn:feature_class":"P",
    "gn:feature_code":"PPL",
    "gn:name":"K\u0131\u015flac\u0131k",
    "gn:population":0,
    "gn:timezone":"Europe/Istanbul",
    "iso:country":"TR",
    "wof:name":"Kislacik",
    "wof:placetype":"locality"
},
  "geometry": {"coordinates":[41.37367,37.83721],"type":"Point"}
}