{
  "type": "Feature",
  "properties": {
    "gn:admin1_code":"07",
    "gn:asciiname":"Cenger",
    "gn:country_code":"TR",
    "gn:dem":29,
    "gn:feature_class":"P",
    "gn:feature_code":"PPL",
    "gn:name":"\u00c7enger",
    "gn:population":0,
    "gn:timezone":"Europe/Istanbul",
    "iso:country":"TR",
    "wof:name":"Cenger",
    "wof:placetype":"locality"
},
  "geometry": {"coordinates":[31.62345,36.69013],"type":"Point"}
}