{
  "type": "Feature",
  "properties": {
    "gn:admin1_code":"81",
    "gn:asciiname":"Kurttepe",
    "gn:country_code":"TR",
    "gn:dem":130,
    "gn:feature_class":"P",
    "gn:feature_code":"PPL",
    "gn:name":"Kurttepe",
    "gn:population":0,
    "gn:timezone":"Europe/Istanbul",
    "iso:country":"TR",
    "name:msa_x_preferred":[
        "Kurttepe"
    ],
    "name:tur_x_preferred":[
        "Kurttepe"
    ],
    "wof:name":"Kurttepe",
    "wof:placetype":"locality"
},
  "geometry": {"coordinates":[35.2757,37.05472],"type":"Point"}
}