{
  "type": "Feature",
  "properties": {
    "gn:admin1_code":"25",
    "gn:asciiname":"Merdivenkoy",
    "gn:country_code":"TR",
    "gn:dem":1781,
    "gn:feature_class":"P",
    "gn:feature_code":"PPL",
    "gn:name":"Merdivenk\u00f6y",
    "gn:population":0,
    "gn:timezone":"Europe/Istanbul",
    "iso:country":"TR",
    "name:tur_x_preferred":[
        "Merdivenk\u00f6y"
    ],
    "name:und_x_variant":[
        "Merdiven"
    ],
    "wof:name":"Merdivenkoy",
    "wof:placetype":"locality"
},
  "geometry": {"coordinates":[40.82018,39.88251],"type":"Point"}
}