{
  "type": "Feature",
  "properties": {
    "gn:admin1_code":"68.0",
    "gn:asciiname":"Dibekoren",
    "gn:country_code":"TR",
    "gn:dem":1425,
    "gn:feature_class":"P",
    "gn:feature_code":"PPL",
    "gn:name":"D\u0131bek\u00f6ren",
    "gn:population":0,
    "gn:timezone":"Europe/Istanbul",
    "iso:country":"TR",
    "name:und_x_variant":[
        "Dibekviran",
        "D\u0131bek\u00f6ren"
    ],
    "wof:name":"Dibekoren",
    "wof:placetype":"locality"
},
  "geometry": {"coordinates":[31.89287,40.30665],"type":"Point"}
}