{
  "type": "Feature",
  "properties": {
    "gn:admin1_code":"55",
    "gn:asciiname":"Keskinoglu",
    "gn:country_code":"TR",
    "gn:dem":489,
    "gn:feature_class":"P",
    "gn:feature_code":"PPL",
    "gn:name":"Keskino\u011flu",
    "gn:population":0,
    "gn:timezone":"Europe/Istanbul",
    "iso:country":"TR",
    "name:tur_x_preferred":[
        "Keskino\u011flu"
    ],
    "wof:name":"Keskinoglu",
    "wof:placetype":"locality"
},
  "geometry": {"coordinates":[36.60232,40.98186],"type":"Point"}
}