{
  "type": "Feature",
  "properties": {
    "gn:admin1_code":"22.0",
    "gn:asciiname":"Calikoy",
    "gn:country_code":"TR",
    "gn:dem":112,
    "gn:feature_class":"P",
    "gn:feature_code":"PPL",
    "gn:name":"\u00c7al\u0131k\u00f6y",
    "gn:population":0,
    "gn:timezone":"Europe/Istanbul",
    "iso:country":"TR",
    "wof:name":"Calikoy",
    "wof:placetype":"locality"
},
  "geometry": {"coordinates":[26.59653,41.28651],"type":"Point"}
}