{
  "type": "Feature",
  "properties": {
    "gn:admin1_code":"65",
    "gn:asciiname":"Camlik",
    "gn:country_code":"TR",
    "gn:dem":1887,
    "gn:feature_class":"P",
    "gn:feature_code":"PPL",
    "gn:name":"\u00c7aml\u0131k",
    "gn:population":0,
    "gn:timezone":"Europe/Istanbul",
    "iso:country":"TR",
    "wof:name":"Camlik",
    "wof:placetype":"locality"
},
  "geometry": {"coordinates":[44.0841,37.95864],"type":"Point"}
}