{
  "type": "Feature",
  "properties": {
    "gn:admin1_code":"72.0",
    "gn:asciiname":"Hanyeri",
    "gn:country_code":"TR",
    "gn:dem":487,
    "gn:feature_class":"P",
    "gn:feature_code":"PPL",
    "gn:name":"Hanyeri",
    "gn:population":0,
    "gn:timezone":"Europe/Istanbul",
    "iso:country":"TR",
    "name:tur_x_preferred":[
        "Hanyeri"
    ],
    "name:und_x_variant":[
        "Khansur",
        "Hansur"
    ],
    "wof:name":"Hanyeri",
    "wof:placetype":"locality"
},
  "geometry": {"coordinates":[40.66807,37.10537],"type":"Point"}
}