{
  "type": "Feature",
  "properties": {
    "gn:admin1_code":"60.0",
    "gn:asciiname":"Guzelyayla",
    "gn:country_code":"TR",
    "gn:dem":789,
    "gn:feature_class":"P",
    "gn:feature_code":"PPL",
    "gn:name":"G\u00fczelyayla",
    "gn:population":0,
    "gn:timezone":"Europe/Istanbul",
    "iso:country":"TR",
    "wof:name":"Guzelyayla",
    "wof:placetype":"locality"
},
  "geometry": {"coordinates":[36.86745,40.50666],"type":"Point"}
}