{
  "type": "Feature",
  "properties": {
    "gn:admin1_code":"03",
    "gn:asciiname":"Kargin",
    "gn:cc2":"TR",
    "gn:country_code":"TR",
    "gn:dem":1283,
    "gn:feature_class":"P",
    "gn:feature_code":"PPL",
    "gn:name":"Karg\u0131n",
    "gn:population":0,
    "gn:timezone":"Europe/Istanbul",
    "iso:country":"TR",
    "name:und_x_variant":[
        "Kark\u0131n",
        "Karg\u0131n"
    ],
    "wof:name":"Kargin",
    "wof:placetype":"locality"
},
  "geometry": {"coordinates":[30.35,38.41667],"type":"Point"}
}