{
  "type": "Feature",
  "properties": {
    "gn:admin1_code":"83",
    "gn:asciiname":"Sakcagoz",
    "gn:country_code":"TR",
    "gn:dem":694,
    "gn:feature_class":"P",
    "gn:feature_code":"PPLA3",
    "gn:name":"Sak\u00e7ag\u00f6z",
    "gn:population":0,
    "gn:timezone":"Europe/Istanbul",
    "iso:country":"TR",
    "name:ceb_x_preferred":[
        "Sak\u00e7ag\u00f6z"
    ],
    "name:fas_x_preferred":[
        "\u0633\u0627\u06a9\u0686\u0627\u06af\u0648\u0632\u0647"
    ],
    "name:msa_x_preferred":[
        "Sak\u00e7ag\u00f6z\u00fc"
    ],
    "name:nno_x_preferred":[
        "Sak\u00e7ag\u00f6ze"
    ],
    "name:rus_x_preferred":[
        "\u0421\u0430\u043a\u0447\u0430\u0433\u0451\u0437\u044e"
    ],
    "name:tur_x_preferred":[
        "Sak\u00e7ag\u00f6z\u00fc"
    ],
    "name:und_x_variant":[
        "Keferdiz"
    ],
    "name:urd_x_preferred":[
        "\u0633\u0627\u06a9\u0686\u0627\u06af\u0648\u0632\u0648"
    ],
    "name:vie_x_preferred":[
        "Sak\u00e7ag\u00f6z"
    ],
    "name:zho_x_preferred":[
        "\u85a9\u514b\u6070\u683c\u805a"
    ],
    "wof:name":"Sakcagoz",
    "wof:placetype":"locality"
},
  "geometry": {"coordinates":[36.91632,37.17152],"type":"Point"}
}