{
  "type": "Feature",
  "properties": {
    "gn:admin1_code":"83",
    "gn:asciiname":"Sakcagoz",
    "gn:country_code":"TR",
    "gn:dem":694,
    "gn:feature_class":"P",
    "gn:feature_code":"PPLA3",
    "gn:name":"Sak\u00e7ag\u00f6z",
    "gn:population":0,
    "gn:timezone":"Europe/Istanbul",
    "iso:country":"TR",
    "name:und_x_variant":[
        "Keferdiz",
        "Sak\u00e7ag\u00f6z",
        "Sak\u00e7ag\u00f6z\u00fc",
        "Sak\u00e7ag\u00f6ze"
    ],
    "wof:name":"Sakcagoz",
    "wof:placetype":"locality"
},
  "geometry": {"coordinates":[36.91632,37.17152],"type":"Point"}
}