{
  "type": "Feature",
  "properties": {
    "gn:admin1_code":"81",
    "gn:asciiname":"Dortler",
    "gn:country_code":"TR",
    "gn:dem":109,
    "gn:feature_class":"P",
    "gn:feature_code":"PPL",
    "gn:name":"D\u00f6rtler",
    "gn:population":0,
    "gn:timezone":"Europe/Istanbul",
    "iso:country":"TR",
    "name:tur_x_preferred":[
        "D\u00f6rtler"
    ],
    "wof:name":"Dortler",
    "wof:placetype":"locality"
},
  "geometry": {"coordinates":[35.24837,37.09615],"type":"Point"}
}