{
  "type": "Feature",
  "properties": {
    "gn:admin1_code":"55.0",
    "gn:asciiname":"Arica",
    "gn:country_code":"TR",
    "gn:dem":511,
    "gn:feature_class":"P",
    "gn:feature_code":"PPL",
    "gn:name":"Ar\u0131ca",
    "gn:population":0,
    "gn:timezone":"Europe/Istanbul",
    "iso:country":"TR",
    "name:und_x_variant":[
        "Geriz",
        "Al\u0131ca",
        "Ar\u0131ca"
    ],
    "wof:name":"Arica",
    "wof:placetype":"locality"
},
  "geometry": {"coordinates":[35.3743,41.14158],"type":"Point"}
}