{
  "type": "Feature",
  "properties": {
    "gn:admin1_code":"93",
    "gn:asciiname":"Saziye",
    "gn:country_code":"TR",
    "gn:dem":127,
    "gn:feature_class":"P",
    "gn:feature_code":"PPL",
    "gn:name":"\u015eaziye",
    "gn:population":0,
    "gn:timezone":"Europe/Istanbul",
    "iso:country":"TR",
    "wof:name":"Saziye",
    "wof:placetype":"locality"
},
  "geometry": {"coordinates":[31.0492,40.84408],"type":"Point"}
}