{
  "type": "Feature",
  "properties": {
    "gn:admin1_code":"70",
    "gn:asciiname":"Altinoluk",
    "gn:country_code":"TR",
    "gn:dem":1900,
    "gn:feature_class":"P",
    "gn:feature_code":"PPL",
    "gn:name":"Alt\u0131noluk",
    "gn:population":0,
    "gn:timezone":"Europe/Istanbul",
    "iso:country":"TR",
    "name:und_x_variant":[
        "Elver",
        "Alt\u0131noluk"
    ],
    "wof:name":"Altinoluk",
    "wof:placetype":"locality"
},
  "geometry": {"coordinates":[44.34439,37.55873],"type":"Point"}
}