{
  "type": "Feature",
  "properties": {
    "gn:admin1_code":"48",
    "gn:asciiname":"Kayadere",
    "gn:country_code":"TR",
    "gn:dem":531,
    "gn:feature_class":"P",
    "gn:feature_code":"PPL",
    "gn:name":"Kayadere",
    "gn:population":0,
    "gn:timezone":"Europe/Istanbul",
    "iso:country":"TR",
    "name:und_x_variant":[
        "Kayaderek\u00f6y",
        "Kayadere"
    ],
    "wof:name":"Kayadere",
    "wof:placetype":"locality"
},
  "geometry": {"coordinates":[27.88852,37.22446],"type":"Point"}
}