{
  "type": "Feature",
  "properties": {
    "iso:country":"TR",
    "name:ara_x_preferred":[
        "\u0645\u062d\u0645\u062f \u0639\u0627\u0643\u0641 \u0622\u0631\u0635\u0648\u064a"
    ],
    "name:azb_x_preferred":[
        "\u0645\u062d\u0645\u062f \u0639\u0627\u06a9\u06cc\u0641 \u0627\u0631\u0633\u0648\u06cc"
    ],
    "name:aze_x_preferred":[
        "M\u0259hm\u0259d Akif \u018frsoy"
    ],
    "name:cat_x_preferred":[
        "Mehmet \u00c2kif Ersoy"
    ],
    "name:ces_x_preferred":[
        "Mehmet Akif Ersoy"
    ],
    "name:ckb_x_preferred":[
        "\u0645\u062d\u06d5\u0645\u0645\u06d5\u062f \u0639\u0627\u06a9\u06cc\u0641 \u0626\u06d5\u0631\u0633\u06c6\u06cc"
    ],
    "name:deu_x_preferred":[
        "Mehmet \u00c2kif Ersoy"
    ],
    "name:ell_x_preferred":[
        "\u039c\u03b5\u03c7\u03bc\u03ad\u03c4 \u0391\u03ba\u03af\u03c6 \u0395\u03c1\u03c3\u03cc\u03b9"
    ],
    "name:epo_x_preferred":[
        "Mehmet \u00c2kif Ersoy"
    ],
    "name:fas_x_preferred":[
        "\u0645\u062d\u0645\u062f \u0639\u0627\u06a9\u0641 \u0627\u0631\u0633\u0648\u06cc"
    ],
    "name:fra_x_preferred":[
        "Mehmet Akif Ersoy"
    ],
    "name:hye_x_preferred":[
        "\u0544\u0565\u0570\u0574\u0565\u0564 \u0531\u0584\u056b\u0586 \u0537\u0580\u057d\u0578\u0575"
    ],
    "name:ita_x_preferred":[
        "Mehmet Akif Ersoy"
    ],
    "name:kat_x_preferred":[
        "\u10db\u10d4\u10f0\u10db\u10d4\u10d7 \u10d0\u10e5\u10d8\u10e4 \u10d4\u10e0\u10e1\u10dd\u10d8"
    ],
    "name:kur_x_preferred":[
        "Mehmet Akif Ersoy"
    ],
    "name:nld_x_preferred":[
        "Mehmet Akif Ersoy"
    ],
    "name:pol_x_preferred":[
        "Mehmet \u00c2kif Ersoy"
    ],
    "name:por_x_preferred":[
        "Mehmet \u00c2kif Ersoy"
    ],
    "name:ron_x_preferred":[
        "Mehmet Akif Ersoy"
    ],
    "name:rus_x_preferred":[
        "\u042d\u0440\u0441\u043e\u0439"
    ],
    "name:slk_x_preferred":[
        "Mehmet \u00c2kif Ersoy"
    ],
    "name:spa_x_preferred":[
        "Mehmet Akif Ersoy"
    ],
    "name:sqi_x_preferred":[
        "Mehmet Aqif Ersoj"
    ],
    "name:srp_x_preferred":[
        "\u041c\u0435\u0445\u043c\u0435\u0442 \u0410\u043a\u0438\u0444 \u0415\u0440\u0441\u043e\u0458"
    ],
    "name:swe_x_preferred":[
        "Mehmet Akif Ersoy"
    ],
    "name:tur_x_preferred":[
        "Mehmet \u00c2kif Ersoy"
    ],
    "name:ukr_x_preferred":[
        "\u041c\u0435\u0445\u043c\u0435\u0442 \u0410\u043a\u0456\u0444 \u0415\u0440\u0441\u043e\u0439"
    ],
    "name:urd_x_preferred":[
        "\u0645\u062d\u0645\u062f \u0639\u0627\u06a9\u0641 \u0627\u0631\u0635\u0648\u06cc"
    ],
    "name:uzb_x_preferred":[
        "Akif Mexmet"
    ],
    "wof:name":"Mehmet Akif Ersoy",
    "wof:placetype":"neighbourhood"
},
  "geometry": {"coordinates":[28.71153534334365,41.206436449927],"type":"Point"}
}