{
  "type": "Feature",
  "properties": {
    "iso:country":"TR",
    "wof:name":"Mehmet Akif Ersoy",
    "wof:placetype":"neighbourhood"
},
  "geometry": {"coordinates":[28.71153534334365,41.206436449927],"type":"Point"}
}