{
  "type": "Feature",
  "properties": {
    "gn:admin1_code":"10.0",
    "gn:asciiname":"Cigmis",
    "gn:country_code":"TR",
    "gn:dem":325,
    "gn:feature_class":"P",
    "gn:feature_code":"PPL",
    "gn:name":"\u00c7\u0131\u011fm\u0131\u015f",
    "gn:population":0,
    "gn:timezone":"Europe/Istanbul",
    "iso:country":"TR",
    "name:und_x_variant":[
        "\u00c7\u0131\u011fm\u0131\u015fk\u00f6y",
        "\u00c7\u0131\u011fm\u0131\u015f"
    ],
    "wof:name":"Cigmis",
    "wof:placetype":"locality"
},
  "geometry": {"coordinates":[27.56235,40.15833],"type":"Point"}
}