{
  "type": "Feature",
  "properties": {
    "gn:admin1_code":"49",
    "gn:asciiname":"Alniacik",
    "gn:country_code":"TR",
    "gn:dem":1946,
    "gn:feature_class":"P",
    "gn:feature_code":"PPL",
    "gn:name":"Aln\u0131a\u00e7\u0131k",
    "gn:population":0,
    "gn:timezone":"Europe/Istanbul",
    "iso:country":"TR",
    "name:und_x_variant":[
        "Ser\u00e7uk",
        "Aln\u0131a\u00e7\u0131k"
    ],
    "wof:name":"Alniacik",
    "wof:placetype":"locality"
},
  "geometry": {"coordinates":[41.66202,39.14607],"type":"Point"}
}