{
  "type": "Feature",
  "properties": {
    "gn:admin1_code":"37",
    "gn:asciiname":"Pehlivan",
    "gn:country_code":"TR",
    "gn:dem":682,
    "gn:feature_class":"P",
    "gn:feature_code":"PPL",
    "gn:name":"Pehlivan",
    "gn:population":0,
    "gn:timezone":"Europe/Istanbul",
    "iso:country":"TR",
    "wof:name":"Pehlivan",
    "wof:placetype":"locality"
},
  "geometry": {"coordinates":[33.93119,41.45786],"type":"Point"}
}