{
  "type": "Feature",
  "properties": {
    "gn:admin1_code":"13.0",
    "gn:asciiname":"Sivrice",
    "gn:country_code":"TR",
    "gn:dem":1458,
    "gn:feature_class":"P",
    "gn:feature_code":"PPL",
    "gn:name":"Sivrice",
    "gn:population":0,
    "gn:timezone":"Europe/Istanbul",
    "iso:country":"TR",
    "name:tur_x_preferred":[
        "Sivrice"
    ],
    "wof:name":"Sivrice",
    "wof:placetype":"locality"
},
  "geometry": {"coordinates":[41.84753,38.35082],"type":"Point"}
}