{
  "type": "Feature",
  "properties": {
    "gn:admin1_code":"10",
    "gn:asciiname":"Akpinar",
    "gn:country_code":"TR",
    "gn:dem":439,
    "gn:feature_class":"P",
    "gn:feature_code":"PPL",
    "gn:name":"Akp\u0131nar",
    "gn:population":0,
    "gn:timezone":"Europe/Istanbul",
    "iso:country":"TR",
    "name:tur_x_preferred":[
        "Akp\u0131nar"
    ],
    "wof:name":"Akpinar",
    "wof:placetype":"locality"
},
  "geometry": {"coordinates":[27.63138,39.4638],"type":"Point"}
}