{
  "type": "Feature",
  "properties": {
    "gn:admin1_code":"48",
    "gn:asciiname":"Tahtaci",
    "gn:country_code":"TR",
    "gn:dem":157,
    "gn:feature_class":"P",
    "gn:feature_code":"PPL",
    "gn:name":"Tahtac\u0131",
    "gn:population":0,
    "gn:timezone":"Europe/Istanbul",
    "iso:country":"TR",
    "wof:name":"Tahtaci",
    "wof:placetype":"locality"
},
  "geometry": {"coordinates":[28.48291,36.9887],"type":"Point"}
}