{
  "type": "Feature",
  "properties": {
    "gn:admin1_code":"25.0",
    "gn:asciiname":"Savakli",
    "gn:country_code":"TR",
    "gn:dem":1340,
    "gn:feature_class":"P",
    "gn:feature_code":"PPL",
    "gn:name":"Savakl\u0131",
    "gn:population":0,
    "gn:timezone":"Europe/Istanbul",
    "iso:country":"TR",
    "wof:name":"Savakli",
    "wof:placetype":"locality"
},
  "geometry": {"coordinates":[41.16667,40.63333],"type":"Point"}
}