{
  "type": "Feature",
  "properties": {
    "iso:country":"TR",
    "qs:name":"\u00d6mer Avni",
    "qs:name_adm0":"Turkey",
    "qs:name_adm1":"\u0130stanbul",
    "qs:photos":362,
    "qs:photos_1k":73,
    "qs:photos_9k":2,
    "qs:photos_9r":5,
    "qs:photos_all":362,
    "qs:photos_sr":6,
    "qs:placetype":"Suburb",
    "qs:pop_sr":"0",
    "wof:name":"\u00d6mer Avni",
    "wof:placetype":"neighbourhood"
},
  "geometry": {"coordinates":[28.9950425,41.036793],"type":"Point"}
}