{
  "type": "Feature",
  "properties": {
    "gn:admin1_code":"60.0",
    "gn:asciiname":"Aydinsofu",
    "gn:country_code":"TR",
    "gn:dem":584,
    "gn:feature_class":"P",
    "gn:feature_code":"PPL",
    "gn:name":"Ayd\u0131nsofu",
    "gn:population":0,
    "gn:timezone":"Europe/Istanbul",
    "iso:country":"TR",
    "wof:name":"Aydinsofu",
    "wof:placetype":"locality"
},
  "geometry": {"coordinates":[36.58352,40.60192],"type":"Point"}
}