{
  "type": "Feature",
  "properties": {
    "gn:admin1_code":"43",
    "gn:asciiname":"Baskonak",
    "gn:country_code":"TR",
    "gn:dem":1158,
    "gn:feature_class":"P",
    "gn:feature_code":"PPL",
    "gn:name":"Ba\u015fkonak",
    "gn:population":0,
    "gn:timezone":"Europe/Istanbul",
    "iso:country":"TR",
    "name:tur_x_preferred":[
        "Ba\u015fkonak"
    ],
    "wof:name":"Baskonak",
    "wof:placetype":"locality"
},
  "geometry": {"coordinates":[29.20151,39.09676],"type":"Point"}
}