{
  "type": "Feature",
  "properties": {
    "gn:admin1_code":"21",
    "gn:asciiname":"Asagi Dosemeler",
    "gn:country_code":"TR",
    "gn:dem":826,
    "gn:feature_class":"P",
    "gn:feature_code":"PPL",
    "gn:name":"A\u015fa\u011f\u0131 D\u00f6\u015femeler",
    "gn:population":0,
    "gn:timezone":"Europe/Istanbul",
    "iso:country":"TR",
    "name:tur_x_preferred":[
        "A\u015fa\u011f\u0131 D\u00f6\u015femeler"
    ],
    "name:und_x_variant":[
        "A\u015fa\u011f\u0131d\u00f6\u015feme"
    ],
    "wof:name":"Asagi Dosemeler",
    "wof:placetype":"locality"
},
  "geometry": {"coordinates":[40.12305,38.22253],"type":"Point"}
}