{
  "type": "Feature",
  "properties": {
    "gn:admin1_code":"68.0",
    "gn:asciiname":"Ucbas",
    "gn:country_code":"TR",
    "gn:dem":1066,
    "gn:feature_class":"P",
    "gn:feature_code":"PPL",
    "gn:name":"\u00dc\u00e7ba\u015f",
    "gn:population":0,
    "gn:timezone":"Europe/Istanbul",
    "iso:country":"TR",
    "name:und_x_variant":[
        "\u00dc\u00e7kas",
        "\u00dc\u00e7ba\u015f"
    ],
    "wof:name":"Ucbas",
    "wof:placetype":"locality"
},
  "geometry": {"coordinates":[32.68167,40.40403],"type":"Point"}
}