{
  "type": "Feature",
  "properties": {
    "gn:country":"TR",
    "gn:fcode":"PPL",
    "gn:population":0,
    "iso:country":"TR",
    "name:tur_x_preferred":[
        "K\u0131\u015flak\u00f6y"
    ],
    "name:und_x_variant":[
        "K\u0131\u015fla"
    ],
    "qs:name":"Kisla",
    "qs:name_adm0":"Turkey",
    "qs:name_adm1":"Samsun",
    "qs:photos":1,
    "qs:photos_1k":1,
    "qs:photos_9k":1,
    "qs:photos_9r":1,
    "qs:photos_all":1,
    "qs:photos_sr":1,
    "qs:placetype":"Suburb",
    "qs:pop_sr":"0",
    "wof:name":"Kisla",
    "wof:placetype":"neighbourhood",
    "wof:population":0
},
  "geometry": {"coordinates":[36.4889,41.16884],"type":"Point"}
}