{
  "type": "Feature",
  "properties": {
    "gn:admin1_code":"20",
    "gn:asciiname":"Ishakli",
    "gn:country_code":"TR",
    "gn:dem":823,
    "gn:feature_class":"P",
    "gn:feature_code":"PPLA3",
    "gn:name":"\u0130shakl\u0131",
    "gn:population":0,
    "gn:timezone":"Europe/Istanbul",
    "iso:country":"TR",
    "name:und_x_variant":[
        "\u0130sakl\u0131",
        "\u0130shakl\u0131"
    ],
    "wof:name":"Ishakli",
    "wof:placetype":"locality"
},
  "geometry": {"coordinates":[30.01333,38.19972],"type":"Point"}
}