{
  "type": "Feature",
  "properties": {
    "gn:admin1_code":"60.0",
    "gn:asciiname":"Kuscu",
    "gn:country_code":"TR",
    "gn:dem":1155,
    "gn:feature_class":"P",
    "gn:feature_code":"PPL",
    "gn:name":"Ku\u015f\u00e7u",
    "gn:population":0,
    "gn:timezone":"Europe/Istanbul",
    "iso:country":"TR",
    "wof:name":"Kuscu",
    "wof:placetype":"locality"
},
  "geometry": {"coordinates":[36.17642,40.03789],"type":"Point"}
}