{
  "type": "Feature",
  "properties": {
    "gn:admin1_code":"48",
    "gn:asciiname":"Gevenezdere",
    "gn:country_code":"TR",
    "gn:dem":525,
    "gn:feature_class":"P",
    "gn:feature_code":"PPL",
    "gn:name":"Gevenezdere",
    "gn:population":0,
    "gn:timezone":"Europe/Istanbul",
    "iso:country":"TR",
    "name:und_x_variant":[
        "Gevenesdere",
        "Gevenezdere",
        "Gevenezderek\u00f6y",
        "\u00c7ukur\u00f6z"
    ],
    "wof:name":"Gevenezdere",
    "wof:placetype":"locality"
},
  "geometry": {"coordinates":[28.11278,37.23583],"type":"Point"}
}