{
  "type": "Feature",
  "properties": {
    "gn:admin1_code":"63",
    "gn:asciiname":"Ulugazi",
    "gn:country_code":"TR",
    "gn:dem":571,
    "gn:feature_class":"P",
    "gn:feature_code":"PPL",
    "gn:name":"Ulugazi",
    "gn:population":0,
    "gn:timezone":"Europe/Istanbul",
    "iso:country":"TR",
    "name:und_x_variant":[
        "Ho\u015fin",
        "Uluyazi",
        "Ulugazi"
    ],
    "wof:name":"Ulugazi",
    "wof:placetype":"locality"
},
  "geometry": {"coordinates":[38.86269,37.63001],"type":"Point"}
}