{
  "type": "Feature",
  "properties": {
    "gn:admin1_code":"5.0",
    "gn:asciiname":"Catalcam",
    "gn:country_code":"TR",
    "gn:dem":976,
    "gn:feature_class":"P",
    "gn:feature_code":"PPL",
    "gn:name":"\u00c7atal\u00e7am",
    "gn:population":0,
    "gn:timezone":"Europe/Istanbul",
    "iso:country":"TR",
    "wof:name":"Catalcam",
    "wof:placetype":"locality"
},
  "geometry": {"coordinates":[36.15944,40.60895],"type":"Point"}
}