{
  "type": "Feature",
  "properties": {
    "iso:country":"TR",
    "name:eng_x_preferred":[
        "Silivri"
    ],
    "name:tur_x_preferred":[
        "Silivri"
    ],
    "wof:name":"Silivri",
    "wof:placetype":"neighbourhood"
},
  "geometry": {"coordinates":[28.24155847504523,41.07753258826727],"type":"Point"}
}