{
  "type": "Feature",
  "properties": {
    "gn:country":"TR",
    "gn:fcode":"PPL",
    "gn:pop":504,
    "iso:country":"TR",
    "name:tur_x_preferred":[
        "Evkuran"
    ],
    "name:unk_x_variant":[
        "Dersel\u00e2m"
    ],
    "qs:name":"Evkuran",
    "qs:photos_9r":0,
    "qs:photos_sr":0,
    "qs:pop_sr":"2",
    "wof:name":"Evkuran",
    "wof:placetype":"locality",
    "wof:population":504
},
  "geometry": {"coordinates":[40.9663,37.66003],"type":"Point"}
}