{
  "type": "Feature",
  "properties": {
    "gn:admin1_code":"32",
    "gn:asciiname":"Atalar",
    "gn:country_code":"TR",
    "gn:dem":3,
    "gn:feature_class":"P",
    "gn:feature_code":"PPL",
    "gn:name":"Atalar",
    "gn:population":0,
    "gn:timezone":"Europe/Istanbul",
    "iso:country":"TR",
    "name:tur_x_preferred":[
        "Atalar"
    ],
    "name:tur_x_variant":[
        "Deliminnet"
    ],
    "wof:name":"Atalar",
    "wof:placetype":"locality"
},
  "geometry": {"coordinates":[34.85,36.85],"type":"Point"}
}