{
  "type": "Feature",
  "properties": {
    "iso:country":"TR",
    "name:eng_x_preferred":[
        "Tepeoren"
    ],
    "name:tur_x_preferred":[
        "Tepe\u00f6ren"
    ],
    "wof:name":"Tepeoren",
    "wof:placetype":"neighbourhood"
},
  "geometry": {"coordinates":[29.39005174263508,40.90985884432578],"type":"Point"}
}