{
  "type": "Feature",
  "properties": {
    "gn:admin1_code":"66",
    "gn:asciiname":"Kahyali",
    "gn:country_code":"TR",
    "gn:dem":808,
    "gn:feature_class":"P",
    "gn:feature_code":"PPL",
    "gn:name":"K\u00e2hyal\u0131",
    "gn:population":0,
    "gn:timezone":"Europe/Istanbul",
    "iso:country":"TR",
    "wof:name":"Kahyali",
    "wof:placetype":"locality"
},
  "geometry": {"coordinates":[35.52919,40.00196],"type":"Point"}
}