{
  "type": "Feature",
  "properties": {
    "gn:admin1_code":"19.0",
    "gn:asciiname":"Kadideresi",
    "gn:cc2":"TR",
    "gn:country_code":"TR",
    "gn:dem":798,
    "gn:feature_class":"P",
    "gn:feature_code":"PPL",
    "gn:name":"Kad\u0131deresi",
    "gn:population":0,
    "gn:timezone":"Europe/Istanbul",
    "iso:country":"TR",
    "name:und_x_variant":[
        "Kad\u0131deresi K\u00f6y\u00fc",
        "Kad\u0131deresi"
    ],
    "wof:name":"Kadideresi",
    "wof:placetype":"locality"
},
  "geometry": {"coordinates":[35.06667,40.31667],"type":"Point"}
}