{
  "type": "Feature",
  "properties": {
    "gn:admin1_code":"44",
    "gn:asciiname":"Yalinbudak",
    "gn:country_code":"TR",
    "gn:dem":1468,
    "gn:feature_class":"P",
    "gn:feature_code":"PPL",
    "gn:name":"Yal\u0131nbudak",
    "gn:population":0,
    "gn:timezone":"Europe/Istanbul",
    "iso:country":"TR",
    "name:tur_x_preferred":[
        "Yal\u0131nbudak"
    ],
    "wof:name":"Yalinbudak",
    "wof:placetype":"locality"
},
  "geometry": {"coordinates":[37.98486,38.44523],"type":"Point"}
}