{
  "type": "Feature",
  "properties": {
    "gn:admin1_code":"16.0",
    "gn:asciiname":"Kizil",
    "gn:country_code":"TR",
    "gn:dem":555,
    "gn:feature_class":"P",
    "gn:feature_code":"PPL",
    "gn:name":"K\u0131z\u0131l",
    "gn:population":0,
    "gn:timezone":"Europe/Istanbul",
    "iso:country":"TR",
    "name:ceb_x_preferred":[
        "Kizil"
    ],
    "name:deu_x_preferred":[
        "Kizil"
    ],
    "name:rus_x_preferred":[
        "\u041a\u0438\u0437\u0438\u043b"
    ],
    "name:srp_x_preferred":[
        "\u041a\u0438\u0437\u0438\u043b"
    ],
    "name:swe_x_preferred":[
        "Kizil"
    ],
    "name:ukr_x_preferred":[
        "\u041a\u0438\u0437\u0438\u043b"
    ],
    "name:und_x_variant":[
        "K\u0131z\u0131l",
        "K\u0131z\u0131lk\u00f6y"
    ],
    "wof:name":"Kizil",
    "wof:placetype":"locality"
},
  "geometry": {"coordinates":[29.76657,40.35113],"type":"Point"}
}