{
  "type": "Feature",
  "properties": {
    "gn:admin1_code":"35",
    "gn:asciiname":"Kasikci",
    "gn:country_code":"TR",
    "gn:dem":90,
    "gn:feature_class":"P",
    "gn:feature_code":"PPL",
    "gn:name":"Ka\u015f\u0131k\u00e7\u0131",
    "gn:population":0,
    "gn:timezone":"Europe/Istanbul",
    "iso:country":"TR",
    "wof:name":"Kasikci",
    "wof:placetype":"locality"
},
  "geometry": {"coordinates":[27.22944,39.07194000000001],"type":"Point"}
}