{
  "type": "Feature",
  "properties": {
    "gn:admin1_code":"03",
    "gn:asciiname":"Ortulu",
    "gn:country_code":"TR",
    "gn:dem":1053,
    "gn:feature_class":"P",
    "gn:feature_code":"PPL",
    "gn:name":"\u00d6rt\u00fcl\u00fc",
    "gn:population":0,
    "gn:timezone":"Europe/Istanbul",
    "iso:country":"TR",
    "wof:name":"Ortulu",
    "wof:placetype":"locality"
},
  "geometry": {"coordinates":[29.7818,37.90297],"type":"Point"}
}