{
  "type": "Feature",
  "properties": {
    "gn:admin1_code":"69.0",
    "gn:asciiname":"Yukari Karadere",
    "gn:country_code":"TR",
    "gn:dem":1675,
    "gn:feature_class":"P",
    "gn:feature_code":"PPL",
    "gn:name":"Yukar\u0131 Karadere",
    "gn:population":0,
    "gn:timezone":"Europe/Istanbul",
    "iso:country":"TR",
    "name:tur_x_preferred":[
        "Yukar\u0131 Karadere"
    ],
    "wof:name":"Yukari Karadere",
    "wof:placetype":"locality"
},
  "geometry": {"coordinates":[38.85077,40.58186],"type":"Point"}
}