{
  "type": "Feature",
  "properties": {
    "gn:admin1_code":"45",
    "gn:asciiname":"Iklikci",
    "gn:country_code":"TR",
    "gn:dem":728,
    "gn:feature_class":"P",
    "gn:feature_code":"PPL",
    "gn:name":"Ikl\u0131k\u00e7\u0131",
    "gn:population":0,
    "gn:timezone":"Europe/Istanbul",
    "iso:country":"TR",
    "name:tur_x_preferred":[
        "Ikl\u0131k\u00e7\u0131"
    ],
    "wof:name":"Iklikci",
    "wof:placetype":"locality"
},
  "geometry": {"coordinates":[28.7627,38.95847],"type":"Point"}
}