{
  "type": "Feature",
  "properties": {
    "gn:admin1_code":"64",
    "gn:asciiname":"Esmetas",
    "gn:country_code":"TR",
    "gn:dem":898,
    "gn:feature_class":"P",
    "gn:feature_code":"PPL",
    "gn:name":"E\u015fmeta\u015f",
    "gn:population":0,
    "gn:timezone":"Europe/Istanbul",
    "iso:country":"TR",
    "name:und_x_variant":[
        "E\u015fmeta\u015fk\u00f6y",
        "E\u015fmeta\u015f"
    ],
    "wof:name":"Esmetas",
    "wof:placetype":"locality"
},
  "geometry": {"coordinates":[28.8354,38.32689],"type":"Point"}
}