{
  "type": "Feature",
  "properties": {
    "gn:admin1_code":"85.0",
    "gn:asciiname":"Kokurdan",
    "gn:country_code":"TR",
    "gn:dem":232,
    "gn:feature_class":"P",
    "gn:feature_code":"PPL",
    "gn:name":"Kokurdan",
    "gn:population":0,
    "gn:timezone":"Europe/Istanbul",
    "iso:country":"TR",
    "name:und_x_variant":[
        "Kirimsa",
        "Kokurdan"
    ],
    "wof:name":"Kokurdan",
    "wof:placetype":"locality"
},
  "geometry": {"coordinates":[31.93183,41.47366],"type":"Point"}
}