{
  "type": "Feature",
  "properties": {
    "gn:country":"TR",
    "gn:fcode":"PPL",
    "gn:population":419,
    "iso:country":"TR",
    "name:aze_x_preferred":[
        "Varl\u0131q jurnal\u0131"
    ],
    "name:eng_x_preferred":[
        "Varl\u0131k"
    ],
    "name:fra_x_preferred":[
        "Varl\u0131k"
    ],
    "name:por_x_preferred":[
        "Varl\u0131k"
    ],
    "name:spa_x_preferred":[
        "Varl\u0131k"
    ],
    "name:tur_x_preferred":[
        "Varl\u0131k"
    ],
    "name:und_x_variant":[
        "Gyzhal"
    ],
    "qs:name":"Varl\u0131k",
    "qs:photos_9r":0,
    "qs:photos_sr":0,
    "qs:pop_sr":"2",
    "wd:wordcount":75,
    "wof:name":"Varl\u0131k",
    "wof:placetype":"locality",
    "wof:population":419
},
  "geometry": {"coordinates":[42.03999,37.2325],"type":"Point"}
}