{
  "type": "Feature",
  "properties": {
    "gn:country":"TR",
    "gn:fcode":"PPL",
    "gn:pop":419,
    "iso:country":"TR",
    "name:unk_x_variant":[
        "Gyzhal"
    ],
    "qs:name":"Varl\u0131k",
    "qs:photos_9r":0,
    "qs:photos_sr":0,
    "qs:pop_sr":"2",
    "wd:wordcount":75,
    "wof:name":"Varl\u0131k",
    "wof:placetype":"locality",
    "wof:population":419
},
  "geometry": {"coordinates":[42.03999,37.2325],"type":"Point"}
}