{
  "type": "Feature",
  "properties": {
    "gn:admin1_code":"37.0",
    "gn:asciiname":"Kuzluk",
    "gn:country_code":"TR",
    "gn:dem":655,
    "gn:feature_class":"P",
    "gn:feature_code":"PPL",
    "gn:name":"Kuzluk",
    "gn:population":0,
    "gn:timezone":"Europe/Istanbul",
    "iso:country":"TR",
    "wof:name":"Kuzluk",
    "wof:placetype":"locality"
},
  "geometry": {"coordinates":[33.67525,41.91355],"type":"Point"}
}