{
  "type": "Feature",
  "properties": {
    "gn:admin1_code":"24",
    "gn:asciiname":"Kirikdere",
    "gn:country_code":"TR",
    "gn:dem":982,
    "gn:feature_class":"P",
    "gn:feature_code":"PPL",
    "gn:name":"K\u0131r\u0131kdere",
    "gn:population":0,
    "gn:timezone":"Europe/Istanbul",
    "iso:country":"TR",
    "name:und_x_variant":[
        "K\u0131r\u0131kdere",
        "Ho\u00e7a\u00e7"
    ],
    "wof:name":"Kirikdere",
    "wof:placetype":"locality"
},
  "geometry": {"coordinates":[38.74408,39.49774],"type":"Point"}
}