{
  "type": "Feature",
  "properties": {
    "gn:admin1_code":"13",
    "gn:asciiname":"Cigdemalan",
    "gn:country_code":"TR",
    "gn:dem":1259,
    "gn:feature_class":"P",
    "gn:feature_code":"PPL",
    "gn:name":"\u00c7i\u011fdemalan",
    "gn:population":0,
    "gn:timezone":"Europe/Istanbul",
    "iso:country":"TR",
    "name:tur_x_preferred":[
        "\u00c7i\u011fdemalan"
    ],
    "name:und_x_variant":[
        "Torh"
    ],
    "wof:name":"Cigdemalan",
    "wof:placetype":"locality"
},
  "geometry": {"coordinates":[41.78183,38.27929],"type":"Point"}
}