{
  "type": "Feature",
  "properties": {
    "gn:admin1_code":"44",
    "gn:asciiname":"Seyitusagi",
    "gn:country_code":"TR",
    "gn:dem":1355,
    "gn:feature_class":"P",
    "gn:feature_code":"PPL",
    "gn:name":"Seyitu\u015fa\u011f\u0131",
    "gn:population":0,
    "gn:timezone":"Europe/Istanbul",
    "iso:country":"TR",
    "name:und_x_variant":[
        "A\u015fa\u011f\u0131 Seyitu\u015fa\u011f\u0131",
        "Seyitu\u015fa\u011f\u0131"
    ],
    "wof:name":"Seyitusagi",
    "wof:placetype":"locality"
},
  "geometry": {"coordinates":[38.1785,38.26426],"type":"Point"}
}