{
  "type": "Feature",
  "properties": {
    "gn:admin1_code":"35",
    "gn:asciiname":"Kaplankoy",
    "gn:country_code":"TR",
    "gn:dem":468,
    "gn:feature_class":"P",
    "gn:feature_code":"PPL",
    "gn:name":"Kaplank\u00f6y",
    "gn:population":0,
    "gn:timezone":"Europe/Istanbul",
    "iso:country":"TR",
    "name:tur_x_preferred":[
        "Kaplank\u00f6y"
    ],
    "wof:name":"Kaplankoy",
    "wof:placetype":"locality"
},
  "geometry": {"coordinates":[27.42369,39.28704000000001],"type":"Point"}
}