{
  "type": "Feature",
  "properties": {
    "gn:country":"TR",
    "gn:fcode":"PPL",
    "gn:population":677,
    "iso:country":"TR",
    "name:tur_x_preferred":[
        "Yukar\u0131az\u0131kl\u0131"
    ],
    "name:tur_x_variant":[
        "Yukar\u0131 Az\u0131kl\u0131"
    ],
    "name:und_x_variant":[
        "T\u00fcmik\u00fclya"
    ],
    "qs:name":"Yukar\u0131az\u0131kl\u0131",
    "qs:photos_9r":0,
    "qs:photos_sr":0,
    "qs:pop_sr":"2",
    "wof:name":"Yukar\u0131az\u0131kl\u0131",
    "wof:placetype":"locality",
    "wof:population":677
},
  "geometry": {"coordinates":[40.67644,37.26621],"type":"Point"}
}