{
  "type": "Feature",
  "properties": {
    "gn:admin1_code":"21.0",
    "gn:asciiname":"Batil",
    "gn:cc2":"TR",
    "gn:country_code":"TR",
    "gn:dem":601,
    "gn:feature_class":"P",
    "gn:feature_code":"PPL",
    "gn:name":"Bat\u0131l",
    "gn:population":0,
    "gn:timezone":"Europe/Istanbul",
    "iso:country":"TR",
    "name:ben_x_preferred":[
        "\u09ac\u09be\u09a4\u09bf\u09b2"
    ],
    "name:hin_x_preferred":[
        "\u092c\u0924\u093f\u0932"
    ],
    "name:msa_x_preferred":[
        "Batil"
    ],
    "name:tur_x_preferred":[
        "Bat\u0131l"
    ],
    "name:und_x_variant":[
        "Batyl"
    ],
    "wof:name":"Batil",
    "wof:placetype":"locality"
},
  "geometry": {"coordinates":[40.99361,37.75778],"type":"Point"}
}