{
  "type": "Feature",
  "properties": {
    "gn:admin1_code":"60.0",
    "gn:asciiname":"Cayirkoy",
    "gn:country_code":"TR",
    "gn:dem":1268,
    "gn:feature_class":"P",
    "gn:feature_code":"PPL",
    "gn:name":"\u00c7ay\u0131rk\u00f6y",
    "gn:population":0,
    "gn:timezone":"Europe/Istanbul",
    "iso:country":"TR",
    "name:und_x_variant":[
        "\u00c7ay\u0131r",
        "\u00c7ay\u0131rk\u00f6y"
    ],
    "wof:name":"Cayirkoy",
    "wof:placetype":"locality"
},
  "geometry": {"coordinates":[35.77023,40.34343],"type":"Point"}
}