{
  "type": "Feature",
  "properties": {
    "gn:admin1_code":"14.0",
    "gn:asciiname":"Elmacikdere",
    "gn:country_code":"TR",
    "gn:dem":743,
    "gn:feature_class":"P",
    "gn:feature_code":"PPL",
    "gn:name":"Elmac\u0131kdere",
    "gn:population":0,
    "gn:timezone":"Europe/Istanbul",
    "iso:country":"TR",
    "name:und_x_variant":[
        "Elmac\u0131dere",
        "Derek\u00f6y",
        "Elmac\u0131kdere"
    ],
    "wof:name":"Elmacikdere",
    "wof:placetype":"locality"
},
  "geometry": {"coordinates":[31.13193,40.59885],"type":"Point"}
}