{
  "type": "Feature",
  "properties": {
    "gn:admin1_code":"40",
    "gn:asciiname":"Tatarlar",
    "gn:country_code":"TR",
    "gn:dem":963,
    "gn:feature_class":"P",
    "gn:feature_code":"PPL",
    "gn:name":"Tatarlar",
    "gn:population":0,
    "gn:timezone":"Europe/Istanbul",
    "iso:country":"TR",
    "name:und_x_variant":[
        "G\u00f6ke\u015fme"
    ],
    "wof:name":"Tatarlar",
    "wof:placetype":"locality"
},
  "geometry": {"coordinates":[33.68283,39.47611],"type":"Point"}
}