{
  "type": "Feature",
  "properties": {
    "gn:admin1_code":"90.0",
    "gn:asciiname":"Kyuchyuk-Byykyr",
    "gn:country_code":"TR",
    "gn:dem":492,
    "gn:feature_class":"P",
    "gn:feature_code":"PPL",
    "gn:name":"Kyuchyuk-Byykyr",
    "gn:population":0,
    "gn:timezone":"Europe/Istanbul",
    "iso:country":"TR",
    "name:und_x_variant":[
        "K\u00fc\u00e7\u00fckb\u0131yk\u0131r",
        "Kyuchyuk-Byykyr",
        "K\u00fc\u00e7\u00fckbay\u0131r"
    ],
    "wof:name":"Kyuchyuk-Byykyr",
    "wof:placetype":"locality"
},
  "geometry": {"coordinates":[37.39361,36.65111],"type":"Point"}
}