{
  "type": "Feature",
  "properties": {
    "gn:admin1_code":"32",
    "gn:asciiname":"Derebasi",
    "gn:country_code":"TR",
    "gn:dem":357,
    "gn:feature_class":"P",
    "gn:feature_code":"PPL",
    "gn:name":"Dereba\u015f\u0131",
    "gn:population":0,
    "gn:timezone":"Europe/Istanbul",
    "iso:country":"TR",
    "wof:name":"Derebasi",
    "wof:placetype":"locality"
},
  "geometry": {"coordinates":[33.04511,36.14039],"type":"Point"}
}