{
  "type": "Feature",
  "properties": {
    "gn:admin1_code":"62",
    "gn:asciiname":"Tasitli",
    "gn:country_code":"TR",
    "gn:dem":1381,
    "gn:feature_class":"P",
    "gn:feature_code":"PPL",
    "gn:name":"Ta\u015f\u0131tl\u0131",
    "gn:population":0,
    "gn:timezone":"Europe/Istanbul",
    "iso:country":"TR",
    "name:tur_x_preferred":[
        "Ta\u015f\u0131tl\u0131"
    ],
    "wof:name":"Tasitli",
    "wof:placetype":"locality"
},
  "geometry": {"coordinates":[39.31823,39.17186],"type":"Point"}
}