{
  "type": "Feature",
  "properties": {
    "iso:country":"TR",
    "qs:name":"Osmana\u011fa",
    "qs:name_adm0":"Turkey",
    "qs:name_adm1":"\u0130stanbul",
    "qs:photos":2,
    "qs:photos_1k":1,
    "qs:photos_9k":1,
    "qs:photos_9r":1,
    "qs:photos_all":2,
    "qs:photos_sr":1,
    "qs:placetype":"Suburb",
    "qs:pop_sr":"0",
    "wof:name":"Osmana\u011fa",
    "wof:placetype":"neighbourhood"
},
  "geometry": {"coordinates":[29.023322,40.990818],"type":"Point"}
}