{
  "type": "Feature",
  "properties": {
    "gn:admin1_code":"15",
    "gn:asciiname":"Yumrutas",
    "gn:country_code":"TR",
    "gn:dem":1211,
    "gn:feature_class":"P",
    "gn:feature_code":"PPL",
    "gn:name":"Yumruta\u015f",
    "gn:population":0,
    "gn:timezone":"Europe/Istanbul",
    "iso:country":"TR",
    "wof:name":"Yumrutas",
    "wof:placetype":"locality"
},
  "geometry": {"coordinates":[30.67786,37.60563],"type":"Point"}
}