{
  "type": "Feature",
  "properties": {
    "gn:admin1_code":"32",
    "gn:asciiname":"Kucuk Ziyaret",
    "gn:country_code":"TR",
    "gn:dem":1709,
    "gn:feature_class":"P",
    "gn:feature_code":"PPL",
    "gn:name":"K\u00fc\u00e7\u00fck Ziyaret",
    "gn:population":0,
    "gn:timezone":"Europe/Istanbul",
    "iso:country":"TR",
    "wof:name":"Kucuk Ziyaret",
    "wof:placetype":"locality"
},
  "geometry": {"coordinates":[34.35,37.06667],"type":"Point"}
}