{
  "type": "Feature",
  "properties": {
    "iso:country":"TR",
    "name:tur_x_preferred":[
        "Yass\u0131\u00f6ren"
    ],
    "wof:name":"Yassioren",
    "wof:placetype":"neighbourhood"
},
  "geometry": {"coordinates":[28.59738047023257,41.23402524121917],"type":"Point"}
}