{
  "type": "Feature",
  "properties": {
    "gn:admin1_code":"25.0",
    "gn:asciiname":"Esenyurt",
    "gn:country_code":"TR",
    "gn:dem":1910,
    "gn:feature_class":"P",
    "gn:feature_code":"PPL",
    "gn:name":"Esenyurt",
    "gn:population":0,
    "gn:timezone":"Europe/Istanbul",
    "iso:country":"TR",
    "name:tur_x_preferred":[
        "Esenyurt"
    ],
    "wof:name":"Esenyurt",
    "wof:placetype":"locality"
},
  "geometry": {"coordinates":[40.76496,40.46521],"type":"Point"}
}