{
  "type": "Feature",
  "properties": {
    "gn:admin1_code":"55.0",
    "gn:asciiname":"Lengerli",
    "gn:country_code":"TR",
    "gn:dem":55,
    "gn:feature_class":"P",
    "gn:feature_code":"PPL",
    "gn:name":"Lengerli",
    "gn:population":0,
    "gn:timezone":"Europe/Istanbul",
    "iso:country":"TR",
    "name:und_x_variant":[
        "Kaydalapa",
        "Gayda\u0131apa",
        "Lengerli"
    ],
    "wof:name":"Lengerli",
    "wof:placetype":"locality"
},
  "geometry": {"coordinates":[35.96064000000001,41.51453],"type":"Point"}
}