{
  "type": "Feature",
  "properties": {
    "gn:admin1_code":"86",
    "gn:asciiname":"Demirdover",
    "gn:country_code":"TR",
    "gn:dem":1711,
    "gn:feature_class":"P",
    "gn:feature_code":"PPL",
    "gn:name":"Demird\u00f6ver",
    "gn:population":0,
    "gn:timezone":"Europe/Istanbul",
    "iso:country":"TR",
    "name:tur_x_preferred":[
        "Demird\u00f6ver"
    ],
    "wof:name":"Demirdover",
    "wof:placetype":"locality"
},
  "geometry": {"coordinates":[42.65922,41.49399],"type":"Point"}
}