{
  "type": "Feature",
  "properties": {
    "gn:admin1_code":"77.0",
    "gn:asciiname":"Kazburnu",
    "gn:country_code":"TR",
    "gn:dem":2378,
    "gn:feature_class":"P",
    "gn:feature_code":"PPL",
    "gn:name":"Kazburnu",
    "gn:population":0,
    "gn:timezone":"Europe/Istanbul",
    "iso:country":"TR",
    "wof:name":"Kazburnu",
    "wof:placetype":"locality"
},
  "geometry": {"coordinates":[40.43375,40.46654],"type":"Point"}
}