{
  "type": "Feature",
  "properties": {
    "gn:admin1_code":"80.0",
    "gn:asciiname":"Toptepe",
    "gn:country_code":"TR",
    "gn:dem":2854,
    "gn:feature_class":"P",
    "gn:feature_code":"PPL",
    "gn:name":"Toptepe",
    "gn:population":0,
    "gn:timezone":"Europe/Istanbul",
    "iso:country":"TR",
    "name:tur_x_preferred":[
        "Toptepe"
    ],
    "wof:name":"Toptepe",
    "wof:placetype":"locality"
},
  "geometry": {"coordinates":[43.37989,37.61137],"type":"Point"}
}