{
  "type": "Feature",
  "properties": {
    "gn:country":"TR",
    "gn:fcode":"PPL",
    "gn:pop":283,
    "iso:country":"TR",
    "name:unk_x_variant":[
        "Hemedantahtani"
    ],
    "qs:name":"A\u015fa\u011f\u0131 Hemedan",
    "qs:photos_9r":0,
    "qs:photos_sr":0,
    "qs:pop_sr":"2",
    "wof:name":"A\u015fa\u011f\u0131 Hemedan",
    "wof:placetype":"locality",
    "wof:population":283
},
  "geometry": {"coordinates":[38.68944,36.94056],"type":"Point"}
}