{
  "type": "Feature",
  "properties": {
    "gn:admin1_code":"93",
    "gn:asciiname":"Mezarlik",
    "gn:country_code":"TR",
    "gn:dem":293,
    "gn:feature_class":"P",
    "gn:feature_code":"PPL",
    "gn:name":"Mezarl\u0131k",
    "gn:population":0,
    "gn:timezone":"Europe/Istanbul",
    "iso:country":"TR",
    "wof:name":"Mezarlik",
    "wof:placetype":"locality"
},
  "geometry": {"coordinates":[31.17856,40.94685],"type":"Point"}
}