{
  "type": "Feature",
  "properties": {
    "gn:admin1_code":"83",
    "gn:asciiname":"Yalankoz",
    "gn:country_code":"TR",
    "gn:dem":913,
    "gn:feature_class":"P",
    "gn:feature_code":"PPL",
    "gn:name":"Yalankoz",
    "gn:population":0,
    "gn:timezone":"Europe/Istanbul",
    "iso:country":"TR",
    "name:tur_x_preferred":[
        "Yalankoz"
    ],
    "name:und_x_variant":[
        "Yalang\u00f6z"
    ],
    "wof:name":"Yalankoz",
    "wof:placetype":"locality"
},
  "geometry": {"coordinates":[37.40732,37.22117],"type":"Point"}
}