{
  "type": "Feature",
  "properties": {
    "gn:admin1_code":"85",
    "gn:asciiname":"Gurbuzler",
    "gn:country_code":"TR",
    "gn:dem":396,
    "gn:feature_class":"P",
    "gn:feature_code":"PPL",
    "gn:name":"G\u00fcrb\u00fczler",
    "gn:population":0,
    "gn:timezone":"Europe/Istanbul",
    "iso:country":"TR",
    "name:tur_x_preferred":[
        "G\u00fcrb\u00fczler"
    ],
    "wof:name":"Gurbuzler",
    "wof:placetype":"locality"
},
  "geometry": {"coordinates":[31.96269,41.13344],"type":"Point"}
}