{
  "type": "Feature",
  "properties": {
    "gn:admin1_code":"14",
    "gn:asciiname":"Kayran",
    "gn:country_code":"TR",
    "gn:dem":1535,
    "gn:feature_class":"P",
    "gn:feature_code":"PPL",
    "gn:name":"Kayran",
    "gn:population":0,
    "gn:timezone":"Europe/Istanbul",
    "iso:country":"TR",
    "wof:name":"Kayran",
    "wof:placetype":"locality"
},
  "geometry": {"coordinates":[31.02329000000001,40.32435],"type":"Point"}
}