{
  "type": "Feature",
  "properties": {
    "gn:admin1_code":"25",
    "gn:asciiname":"Golveren",
    "gn:country_code":"TR",
    "gn:dem":2104,
    "gn:feature_class":"P",
    "gn:feature_code":"PPL",
    "gn:name":"G\u00f6lveren",
    "gn:population":0,
    "gn:timezone":"Europe/Istanbul",
    "iso:country":"TR",
    "wof:name":"Golveren",
    "wof:placetype":"locality"
},
  "geometry": {"coordinates":[40.76667,39.78333],"type":"Point"}
}