{
  "type": "Feature",
  "properties": {
    "gn:admin1_code":"62.0",
    "gn:asciiname":"Agzonik",
    "gn:cc2":"TR",
    "gn:country_code":"TR",
    "gn:dem":1301,
    "gn:feature_class":"P",
    "gn:feature_code":"PPL",
    "gn:name":"A\u011fzonik",
    "gn:population":0,
    "gn:timezone":"Europe/Istanbul",
    "iso:country":"TR",
    "name:und_x_variant":[
        "A\u011fzonik Mahallesi",
        "A\u011fzonik"
    ],
    "wof:name":"Agzonik",
    "wof:placetype":"locality"
},
  "geometry": {"coordinates":[39.16667,39.01667],"type":"Point"}
}