{
  "type": "Feature",
  "properties": {
    "iso:country":"TR",
    "name:aze_x_preferred":[
        "\u018fl\u0259mdar"
    ],
    "name:nor_x_preferred":[
        "Alemdar"
    ],
    "name:rus_x_preferred":[
        "\u0410\u043b\u0435\u043c\u0434\u0430\u0440"
    ],
    "name:tur_x_preferred":[
        "Alemdar"
    ],
    "name:und_x_variant":[
        "Alemda\u011f"
    ],
    "qs:gn_adm0_cc":"TR",
    "qs:gn_fcode":"PPL",
    "qs:gn_local":750269,
    "qs:gn_namadm1":"34",
    "qs:gn_name":"Alemdar",
    "qs:local_max":206,
    "qs:local_sum":532,
    "qs:localhoods":7,
    "qs:name":"Alemdar",
    "qs:name_adm0":"Turkey",
    "qs:name_adm1":"Bursa",
    "qs:name_adm2":"Osmangazi",
    "qs:name_local":"Bursa",
    "qs:photo_max":27,
    "qs:photo_sum":29,
    "qs:placetype":"Suburb",
    "qs:quad_count":2,
    "qs:woe_adm0":23424969,
    "qs:woe_adm1":2347273,
    "qs:woe_adm2":29390676,
    "qs:woe_lau":0,
    "qs:woe_local":2343843,
    "qs:woe_ver":"7.10.0",
    "wd:wordcount":62,
    "wof:name":"Alemdar",
    "wof:placetype":"neighbourhood"
},
  "geometry": {"coordinates":[29.039612,40.219021],"type":"Point"}
}