{
  "type": "Feature",
  "properties": {
    "gn:admin1_code":"63",
    "gn:asciiname":"Incirli",
    "gn:country_code":"TR",
    "gn:dem":563,
    "gn:feature_class":"P",
    "gn:feature_code":"PPL",
    "gn:name":"\u0130ncirli",
    "gn:population":0,
    "gn:timezone":"Europe/Istanbul",
    "iso:country":"TR",
    "name:tur_x_preferred":[
        "\u0130ncirli"
    ],
    "wof:name":"Incirli",
    "wof:placetype":"locality"
},
  "geometry": {"coordinates":[39.97995,37.27076],"type":"Point"}
}