{
  "type": "Feature",
  "properties": {
    "gn:admin1_code":"46",
    "gn:asciiname":"Boylu",
    "gn:country_code":"TR",
    "gn:dem":1556,
    "gn:feature_class":"P",
    "gn:feature_code":"PPL",
    "gn:name":"Boylu",
    "gn:population":0,
    "gn:timezone":"Europe/Istanbul",
    "iso:country":"TR",
    "name:und_x_variant":[
        "Tunaboylu"
    ],
    "wof:name":"Boylu",
    "wof:placetype":"locality"
},
  "geometry": {"coordinates":[37.24414,37.71504],"type":"Point"}
}