{
  "type": "Feature",
  "properties": {
    "gn:admin1_code":"05",
    "gn:asciiname":"Kemaliye",
    "gn:country_code":"TR",
    "gn:dem":917,
    "gn:feature_class":"P",
    "gn:feature_code":"PPL",
    "gn:name":"Kemaliye",
    "gn:population":0,
    "gn:timezone":"Europe/Istanbul",
    "iso:country":"TR",
    "name:tur_x_preferred":[
        "Kemaliye"
    ],
    "wof:name":"Kemaliye",
    "wof:placetype":"locality"
},
  "geometry": {"coordinates":[35.70928,40.87383],"type":"Point"}
}