{
  "type": "Feature",
  "properties": {
    "gn:admin1_code":"37.0",
    "gn:asciiname":"Arslanli",
    "gn:country_code":"TR",
    "gn:dem":1338,
    "gn:feature_class":"P",
    "gn:feature_code":"PPL",
    "gn:name":"Arslanl\u0131",
    "gn:population":0,
    "gn:timezone":"Europe/Istanbul",
    "iso:country":"TR",
    "name:und_x_variant":[
        "Aslanl\u0131",
        "Arslanl\u0131"
    ],
    "wof:name":"Arslanli",
    "wof:placetype":"locality"
},
  "geometry": {"coordinates":[34.17248,41.31773],"type":"Point"}
}