{
  "type": "Feature",
  "properties": {
    "gn:admin1_code":"63",
    "gn:asciiname":"Sahinalan",
    "gn:country_code":"TR",
    "gn:dem":375,
    "gn:feature_class":"P",
    "gn:feature_code":"PPL",
    "gn:name":"\u015eahinalan",
    "gn:population":0,
    "gn:timezone":"Europe/Istanbul",
    "iso:country":"TR",
    "name:tur_x_historical":[
        "Vah\u015fiye"
    ],
    "name:tur_x_preferred":[
        "\u015eahinalan"
    ],
    "name:tur_x_variant":[
        "Vah\u015fiye"
    ],
    "name:und_x_variant":[
        "Vakhshiye"
    ],
    "wof:name":"Sahinalan",
    "wof:placetype":"locality"
},
  "geometry": {"coordinates":[38.97306,36.93389000000001],"type":"Point"}
}