{
  "type": "Feature",
  "properties": {
    "gn:admin1_code":"21.0",
    "gn:asciiname":"Bozek",
    "gn:country_code":"TR",
    "gn:dem":754,
    "gn:feature_class":"P",
    "gn:feature_code":"PPL",
    "gn:name":"Bozek",
    "gn:population":0,
    "gn:timezone":"Europe/Istanbul",
    "iso:country":"TR",
    "name:tur_x_preferred":[
        "Baver"
    ],
    "wof:name":"Bozek",
    "wof:placetype":"locality"
},
  "geometry": {"coordinates":[40.07565,38.09925],"type":"Point"}
}