{
  "type": "Feature",
  "properties": {
    "gn:admin1_code":"61.0",
    "gn:asciiname":"Duzluk",
    "gn:country_code":"TR",
    "gn:dem":348,
    "gn:feature_class":"P",
    "gn:feature_code":"PPL",
    "gn:name":"D\u00fczl\u00fck",
    "gn:population":0,
    "gn:timezone":"Europe/Istanbul",
    "iso:country":"TR",
    "name:tur_x_preferred":[
        "D\u00fczl\u00fck"
    ],
    "wof:name":"Duzluk",
    "wof:placetype":"locality"
},
  "geometry": {"coordinates":[39.30621,41.01891],"type":"Point"}
}