{
  "type": "Feature",
  "properties": {
    "gn:admin1_code":"61.0",
    "gn:asciiname":"Duzluk",
    "gn:country_code":"TR",
    "gn:dem":348,
    "gn:feature_class":"P",
    "gn:feature_code":"PPL",
    "gn:name":"D\u00fczl\u00fck",
    "gn:population":0,
    "gn:timezone":"Europe/Istanbul",
    "iso:country":"TR",
    "name:bos_x_preferred":[
        "Duzluk"
    ],
    "name:ceb_x_preferred":[
        "Duzluk"
    ],
    "name:fra_x_preferred":[
        "Duzluk"
    ],
    "name:hrv_x_preferred":[
        "Duzluk"
    ],
    "name:hun_x_preferred":[
        "Duzluk"
    ],
    "name:nld_x_preferred":[
        "Duzluk"
    ],
    "name:slv_x_preferred":[
        "Duzluk"
    ],
    "name:spa_x_preferred":[
        "Duzluk"
    ],
    "name:srp_x_preferred":[
        "\u0414\u0443\u0437\u043b\u0443\u043a"
    ],
    "name:swe_x_preferred":[
        "Duzluk"
    ],
    "name:tur_x_preferred":[
        "D\u00fczl\u00fck"
    ],
    "name:ukr_x_preferred":[
        "\u0414\u0443\u0437\u043b\u0443\u043a"
    ],
    "wof:name":"Duzluk",
    "wof:placetype":"locality"
},
  "geometry": {"coordinates":[39.30621,41.01891],"type":"Point"}
}