{
  "type": "Feature",
  "properties": {
    "gn:admin1_code":"22.0",
    "gn:asciiname":"Arpac",
    "gn:country_code":"TR",
    "gn:dem":117,
    "gn:feature_class":"P",
    "gn:feature_code":"PPL",
    "gn:name":"Arpa\u00e7",
    "gn:population":0,
    "gn:timezone":"Europe/Istanbul",
    "iso:country":"TR",
    "wof:name":"Arpac",
    "wof:placetype":"locality"
},
  "geometry": {"coordinates":[26.88252,41.68919],"type":"Point"}
}