{
  "type": "Feature",
  "properties": {
    "gn:admin1_code":"58",
    "gn:asciiname":"Yakacik",
    "gn:country_code":"TR",
    "gn:dem":1293,
    "gn:feature_class":"P",
    "gn:feature_code":"PPL",
    "gn:name":"Yakac\u0131k",
    "gn:population":0,
    "gn:timezone":"Europe/Istanbul",
    "iso:country":"TR",
    "name:tur_x_preferred":[
        "Yakac\u0131k"
    ],
    "name:tur_x_variant":[
        "Yakac\u0131k\u00e7avu\u015flu"
    ],
    "wof:name":"Yakacik",
    "wof:placetype":"locality"
},
  "geometry": {"coordinates":[36.54956,39.65269],"type":"Point"}
}