{
  "type": "Feature",
  "properties": {
    "gn:admin1_code":"91",
    "gn:asciiname":"Ariklikas",
    "gn:country_code":"TR",
    "gn:dem":594,
    "gn:feature_class":"P",
    "gn:feature_code":"PPL",
    "gn:name":"Ar\u0131kl\u0131ka\u015f",
    "gn:population":0,
    "gn:timezone":"Europe/Istanbul",
    "iso:country":"TR",
    "name:tur_x_preferred":[
        "Ar\u0131kl\u0131ka\u015f"
    ],
    "wof:name":"Ariklikas",
    "wof:placetype":"locality"
},
  "geometry": {"coordinates":[36.51058,37.18909],"type":"Point"}
}