{
  "type": "Feature",
  "properties": {
    "gn:admin1_code":"65",
    "gn:asciiname":"Yatiksirt",
    "gn:country_code":"TR",
    "gn:dem":2010,
    "gn:feature_class":"P",
    "gn:feature_code":"PPL",
    "gn:name":"Yat\u0131ks\u0131rt",
    "gn:population":0,
    "gn:timezone":"Europe/Istanbul",
    "iso:country":"TR",
    "name:und_x_variant":[
        "Mendan",
        "Yat\u0131ks\u0131rt"
    ],
    "wof:name":"Yatiksirt",
    "wof:placetype":"locality"
},
  "geometry": {"coordinates":[43.80052,38.69371],"type":"Point"}
}