{
  "type": "Feature",
  "properties": {
    "gn:admin1_code":"91",
    "gn:asciiname":"Gokmustafali",
    "gn:country_code":"TR",
    "gn:dem":750,
    "gn:feature_class":"P",
    "gn:feature_code":"PPL",
    "gn:name":"G\u00f6kmustafal\u0131",
    "gn:population":0,
    "gn:timezone":"Europe/Istanbul",
    "iso:country":"TR",
    "name:tur_x_preferred":[
        "G\u00f6kmustafal\u0131"
    ],
    "name:und_x_variant":[
        "\u0130maml\u0131",
        "G\u00f6kmustafa K\u00f6y\u00fc",
        "G\u00f6kmustafa"
    ],
    "wof:name":"Gokmustafali",
    "wof:placetype":"locality"
},
  "geometry": {"coordinates":[36.59766,37.18499],"type":"Point"}
}