{
  "type": "Feature",
  "properties": {
    "gn:admin1_code":"81",
    "gn:asciiname":"Catakli",
    "gn:country_code":"TR",
    "gn:dem":42,
    "gn:feature_class":"P",
    "gn:feature_code":"PPL",
    "gn:name":"\u00c7atakl\u0131",
    "gn:population":0,
    "gn:timezone":"Europe/Istanbul",
    "iso:country":"TR",
    "wof:name":"Catakli",
    "wof:placetype":"locality"
},
  "geometry": {"coordinates":[36.05583,37.13028],"type":"Point"}
}