{
  "type": "Feature",
  "properties": {
    "gn:admin1_code":"25",
    "gn:asciiname":"Cayirca",
    "gn:country_code":"TR",
    "gn:dem":1761,
    "gn:feature_class":"P",
    "gn:feature_code":"PPL",
    "gn:name":"\u00c7ay\u0131rca",
    "gn:population":0,
    "gn:timezone":"Europe/Istanbul",
    "iso:country":"TR",
    "name:und_x_variant":[
        "\u00d6zni",
        "\u00c7ay\u0131rca",
        "\u00d6zn\u00fc"
    ],
    "wof:name":"Cayirca",
    "wof:placetype":"locality"
},
  "geometry": {"coordinates":[41.1753,39.99325],"type":"Point"}
}