{
  "type": "Feature",
  "properties": {
    "gn:country":"TR",
    "gn:fcode":"PPL",
    "gn:pop":863,
    "iso:country":"TR",
    "name:tur_x_preferred":[
        "Kaynarca"
    ],
    "qs:name":"Kaynarca",
    "qs:photos_9r":0,
    "qs:photos_sr":0,
    "qs:pop_sr":"2",
    "wd:wordcount":61,
    "wof:name":"Kaynarca",
    "wof:placetype":"locality",
    "wof:population":863
},
  "geometry": {"coordinates":[29.82556,40.41444],"type":"Point"}
}