{
  "type": "Feature",
  "properties": {
    "gn:country":"TR",
    "gn:fcode":"PPL",
    "gn:pop":49,
    "iso:country":"TR",
    "name:tur_x_preferred":[
        "S\u00fctl\u00fcce"
    ],
    "qs:name":"S\u00fctl\u00fcce",
    "qs:photos_9r":0,
    "qs:photos_sr":0,
    "qs:pop_sr":"1",
    "wd:wordcount":28,
    "wof:name":"S\u00fctl\u00fcce",
    "wof:placetype":"locality",
    "wof:population":49
},
  "geometry": {"coordinates":[37.54692,36.84393],"type":"Point"}
}