{
  "type": "Feature",
  "properties": {
    "gn:admin1_code":"68",
    "gn:asciiname":"Yeniyapancarsak",
    "gn:cc2":"TR",
    "gn:country_code":"TR",
    "gn:dem":1078,
    "gn:feature_class":"P",
    "gn:feature_code":"PPL",
    "gn:name":"Yeniyapan\u00e7ar\u015fak",
    "gn:population":0,
    "gn:timezone":"Europe/Istanbul",
    "iso:country":"TR",
    "name:und_x_variant":[
        "Hac\u0131osman\u00e7arsak",
        "Yeniyapan\u00e7ar\u015fak"
    ],
    "wof:name":"Yeniyapancarsak",
    "wof:placetype":"locality"
},
  "geometry": {"coordinates":[32.96889,39.39111],"type":"Point"}
}