{
  "type": "Feature",
  "properties": {
    "gn:admin1_code":"74.0",
    "gn:asciiname":"Kazanli",
    "gn:cc2":"TR",
    "gn:country_code":"TR",
    "gn:dem":551,
    "gn:feature_class":"P",
    "gn:feature_code":"PPL",
    "gn:name":"Kazanl\u0131",
    "gn:population":0,
    "gn:timezone":"Europe/Istanbul",
    "iso:country":"TR",
    "name:und_x_variant":[
        "Bofedzha",
        "Bofeca",
        "Bufe\u00e7a",
        "Kazanl\u0131"
    ],
    "wof:name":"Kazanli",
    "wof:placetype":"locality"
},
  "geometry": {"coordinates":[41.97333,37.80056],"type":"Point"}
}