{
  "type": "Feature",
  "properties": {
    "gn:admin1_code":"17",
    "gn:asciiname":"Cinarpinar",
    "gn:country_code":"TR",
    "gn:dem":485,
    "gn:feature_class":"P",
    "gn:feature_code":"PPL",
    "gn:name":"\u00c7\u0131narp\u0131nar",
    "gn:population":0,
    "gn:timezone":"Europe/Istanbul",
    "iso:country":"TR",
    "name:und_x_variant":[
        "\u00c7\u0131narp\u0131nar",
        "\u00c7\u0131narp\u0131naroba"
    ],
    "wof:name":"Cinarpinar",
    "wof:placetype":"locality"
},
  "geometry": {"coordinates":[26.31928,39.62682],"type":"Point"}
}