{
  "type": "Feature",
  "properties": {
    "gn:admin1_code":"44.0",
    "gn:asciiname":"Kayadibi",
    "gn:country_code":"TR",
    "gn:dem":1124,
    "gn:feature_class":"P",
    "gn:feature_code":"PPL",
    "gn:name":"Kayadibi",
    "gn:population":0,
    "gn:timezone":"Europe/Istanbul",
    "iso:country":"TR",
    "name:tur_x_preferred":[
        "Kayadibi"
    ],
    "wof:name":"Kayadibi",
    "wof:placetype":"locality"
},
  "geometry": {"coordinates":[37.82248,38.47894],"type":"Point"}
}