{
  "type": "Feature",
  "properties": {
    "gn:admin1_code":"45",
    "gn:asciiname":"Halkaavlu",
    "gn:country_code":"TR",
    "gn:dem":543,
    "gn:feature_class":"P",
    "gn:feature_code":"PPL",
    "gn:name":"Halkaavlu",
    "gn:population":0,
    "gn:timezone":"Europe/Istanbul",
    "iso:country":"TR",
    "wof:name":"Halkaavlu",
    "wof:placetype":"locality"
},
  "geometry": {"coordinates":[27.86613,39.26948],"type":"Point"}
}