{
  "type": "Feature",
  "properties": {
    "gn:admin1_code":"83.0",
    "gn:asciiname":"Cinaroba",
    "gn:country_code":"TR",
    "gn:dem":456,
    "gn:feature_class":"P",
    "gn:feature_code":"PPL",
    "gn:name":"\u00c7\u0131naroba",
    "gn:population":0,
    "gn:timezone":"Europe/Istanbul",
    "iso:country":"TR",
    "wof:name":"Cinaroba",
    "wof:placetype":"locality"
},
  "geometry": {"coordinates":[36.65278,36.97472],"type":"Point"}
}