{
  "type": "Feature",
  "properties": {
    "gn:admin1_code":"59.0",
    "gn:asciiname":"Misinli",
    "gn:country_code":"TR",
    "gn:dem":90,
    "gn:feature_class":"P",
    "gn:feature_code":"PPL",
    "gn:name":"Misinli",
    "gn:population":0,
    "gn:timezone":"Europe/Istanbul",
    "iso:country":"TR",
    "wof:name":"Misinli",
    "wof:placetype":"locality"
},
  "geometry": {"coordinates":[27.60861,41.30861],"type":"Point"}
}