{
  "type": "Feature",
  "properties": {
    "gn:admin1_code":"31",
    "gn:asciiname":"Karsi",
    "gn:country_code":"TR",
    "gn:dem":208,
    "gn:feature_class":"P",
    "gn:feature_code":"PPL",
    "gn:name":"Kar\u015f\u0131",
    "gn:population":0,
    "gn:timezone":"Europe/Istanbul",
    "iso:country":"TR",
    "name:tur_x_preferred":[
        "Kar\u015f\u0131"
    ],
    "wof:name":"Karsi",
    "wof:placetype":"locality"
},
  "geometry": {"coordinates":[36.14563,36.27387],"type":"Point"}
}