{
  "type": "Feature",
  "properties": {
    "gn:admin1_code":"55.0",
    "gn:asciiname":"Karakutuk",
    "gn:country_code":"TR",
    "gn:dem":910,
    "gn:feature_class":"P",
    "gn:feature_code":"PPL",
    "gn:name":"Karak\u00fct\u00fck",
    "gn:population":0,
    "gn:timezone":"Europe/Istanbul",
    "iso:country":"TR",
    "wof:name":"Karakutuk",
    "wof:placetype":"locality"
},
  "geometry": {"coordinates":[35.76983,41.27321],"type":"Point"}
}