{
  "type": "Feature",
  "properties": {
    "gn:admin1_code":"65",
    "gn:asciiname":"Ocakli",
    "gn:country_code":"TR",
    "gn:dem":1997,
    "gn:feature_class":"P",
    "gn:feature_code":"PPL",
    "gn:name":"Ocakl\u0131",
    "gn:population":0,
    "gn:timezone":"Europe/Istanbul",
    "iso:country":"TR",
    "name:und_x_variant":[
        "K\u00f6mk\u00f6y",
        "K\u00f6m",
        "Ocakl\u0131"
    ],
    "wof:name":"Ocakli",
    "wof:placetype":"locality"
},
  "geometry": {"coordinates":[43.4298,38.74379],"type":"Point"}
}