{
  "type": "Feature",
  "properties": {
    "gn:admin1_code":"43",
    "gn:asciiname":"Kestel",
    "gn:country_code":"TR",
    "gn:dem":1281,
    "gn:feature_class":"P",
    "gn:feature_code":"PPL",
    "gn:name":"Kestel",
    "gn:population":0,
    "gn:timezone":"Europe/Istanbul",
    "iso:country":"TR",
    "name:rus_x_preferred":[
        "\u041a\u0435\u0441\u0442\u0435\u043b\u044c"
    ],
    "name:swa_x_preferred":[
        "Kestel"
    ],
    "name:tur_x_preferred":[
        "Kestel"
    ],
    "wof:name":"Kestel",
    "wof:placetype":"locality"
},
  "geometry": {"coordinates":[29.21337,39.15034],"type":"Point"}
}