{
  "type": "Feature",
  "properties": {
    "gn:admin1_code":"46",
    "gn:asciiname":"Gupluce",
    "gn:country_code":"TR",
    "gn:dem":1521,
    "gn:feature_class":"P",
    "gn:feature_code":"PPL",
    "gn:name":"G\u00fcpl\u00fcce",
    "gn:population":0,
    "gn:timezone":"Europe/Istanbul",
    "iso:country":"TR",
    "name:und_x_variant":[
        "K\u00fcpl\u00fcce",
        "G\u00fcpl\u00fcce"
    ],
    "wof:name":"Gupluce",
    "wof:placetype":"locality"
},
  "geometry": {"coordinates":[37.17528,38.13218],"type":"Point"}
}