{
  "type": "Feature",
  "properties": {
    "gn:admin1_code":"89",
    "gn:asciiname":"Kasbasi",
    "gn:country_code":"TR",
    "gn:dem":61,
    "gn:feature_class":"P",
    "gn:feature_code":"PPL",
    "gn:name":"Ka\u015fba\u015f\u0131",
    "gn:population":0,
    "gn:timezone":"Europe/Istanbul",
    "iso:country":"TR",
    "name:tur_x_preferred":[
        "Ka\u015fba\u015f\u0131"
    ],
    "wof:name":"Kasbasi",
    "wof:placetype":"locality"
},
  "geometry": {"coordinates":[32.41426,41.6179],"type":"Point"}
}