{
  "type": "Feature",
  "properties": {
    "gn:admin1_code":"74.0",
    "gn:asciiname":"Savaskoy",
    "gn:country_code":"TR",
    "gn:dem":732,
    "gn:feature_class":"P",
    "gn:feature_code":"PPL",
    "gn:name":"Sava\u015fk\u00f6y",
    "gn:population":0,
    "gn:timezone":"Europe/Istanbul",
    "iso:country":"TR",
    "name:tur_x_preferred":[
        "Sava\u015fk\u00f6y"
    ],
    "wof:name":"Savaskoy",
    "wof:placetype":"locality"
},
  "geometry": {"coordinates":[41.92812,37.67638],"type":"Point"}
}