{
  "type": "Feature",
  "properties": {
    "gn:admin1_code":"19.0",
    "gn:asciiname":"Derekargin",
    "gn:country_code":"TR",
    "gn:dem":844,
    "gn:feature_class":"P",
    "gn:feature_code":"PPL",
    "gn:name":"Derekarg\u0131n",
    "gn:population":0,
    "gn:timezone":"Europe/Istanbul",
    "iso:country":"TR",
    "wof:name":"Derekargin",
    "wof:placetype":"locality"
},
  "geometry": {"coordinates":[34.48014000000001,40.76312],"type":"Point"}
}