{
  "type": "Feature",
  "properties": {
    "gn:admin1_code":"09",
    "gn:asciiname":"Kasar",
    "gn:country_code":"TR",
    "gn:dem":194,
    "gn:feature_class":"P",
    "gn:feature_code":"PPL",
    "gn:name":"Kasar",
    "gn:population":0,
    "gn:timezone":"Europe/Istanbul",
    "iso:country":"TR",
    "name:und_x_variant":[
        "Kasark\u00f6y\u00fc"
    ],
    "wof:name":"Kasar",
    "wof:placetype":"locality"
},
  "geometry": {"coordinates":[28.02446,37.74235],"type":"Point"}
}