{
  "type": "Feature",
  "properties": {
    "gn:country":"TR",
    "gn:fcode":"PPLA2",
    "gn:pop":0,
    "iso:country":"TR",
    "name:azb_x_preferred":[
        "\u0642\u0648\u0645\u0644\u0648\u062c\u0627"
    ],
    "name:cat_x_preferred":[
        "Kumluca"
    ],
    "name:dan_x_preferred":[
        "Kumluca"
    ],
    "name:deu_x_preferred":[
        "Kumluca"
    ],
    "name:eng_x_preferred":[
        "Kumluca"
    ],
    "name:epo_x_preferred":[
        "Kumluca"
    ],
    "name:fas_x_preferred":[
        "\u0642\u0648\u0645\u0644\u0648\u062c\u0627"
    ],
    "name:fra_x_preferred":[
        "Kumluca"
    ],
    "name:ita_x_preferred":[
        "Kumluca"
    ],
    "name:lav_x_preferred":[
        "Kumlud\u017ea"
    ],
    "name:lbe_x_preferred":[
        "\u041a\u044a\u0443\u043c\u043b\u0443\u0434\u0436\u0430"
    ],
    "name:lit_x_preferred":[
        "Kumlukas"
    ],
    "name:min_x_preferred":[
        "Kumluca"
    ],
    "name:mkd_x_preferred":[
        "\u041a\u0443\u043c\u043b\u0443\u045f\u0430"
    ],
    "name:mrj_x_preferred":[
        "\u041a\u0443\u043c\u043b\u0443\u0434\u0436\u0430"
    ],
    "name:msa_x_preferred":[
        "Kumluca"
    ],
    "name:nan_x_preferred":[
        "Kumluca"
    ],
    "name:nld_x_preferred":[
        "Kumluca"
    ],
    "name:nno_x_preferred":[
        "Kumluca"
    ],
    "name:nob_x_preferred":[
        "Kumluca"
    ],
    "name:rus_x_preferred":[
        "\u041a\u0443\u043c\u043b\u0443\u0434\u0436\u0430"
    ],
    "name:swa_x_preferred":[
        "Kumluca"
    ],
    "name:tur_x_preferred":[
        "Kumluca"
    ],
    "name:ukr_x_preferred":[
        "\u041a\u0443\u043c\u043b\u0443\u0434\u0436\u0430"
    ],
    "name:urd_x_preferred":[
        "\u06a9\u0648\u0645\u0644\u0648\u062c\u0627"
    ],
    "name:vie_x_preferred":[
        "Kumluca"
    ],
    "name:zho_x_preferred":[
        "\u5eab\u59c6\u76e7\u8cc8"
    ],
    "qs:name":"Kumluca",
    "qs:photos_9r":0,
    "qs:photos_sr":0,
    "qs:pop_sr":"0",
    "wd:wordcount":427,
    "wof:name":"Kumluca",
    "wof:placetype":"locality",
    "wof:population":0
},
  "geometry": {"coordinates":[30.28694,36.37028],"type":"Point"}
}