{
  "type": "Feature",
  "properties": {
    "gn:country":"TR",
    "gn:fcode":"PPLA2",
    "gn:pop":0,
    "iso:country":"TR",
    "qs:name":"Kumluca",
    "qs:photos_9r":0,
    "qs:photos_sr":0,
    "qs:pop_sr":"0",
    "wd:wordcount":427,
    "wof:name":"Kumluca",
    "wof:placetype":"locality",
    "wof:population":0
},
  "geometry": {"coordinates":[30.28694,36.37028],"type":"Point"}
}