{
  "type": "Feature",
  "properties": {
    "gn:admin1_code":"52.0",
    "gn:asciiname":"Kapili",
    "gn:country_code":"TR",
    "gn:dem":895,
    "gn:feature_class":"P",
    "gn:feature_code":"PPL",
    "gn:name":"Kap\u0131l\u0131",
    "gn:population":0,
    "gn:timezone":"Europe/Istanbul",
    "iso:country":"TR",
    "name:und_x_variant":[
        "\u00c7\u0131ng\u0131rt",
        "Kapal\u0131",
        "\u00c7ink\u0131rt",
        "Kap\u0131l\u0131"
    ],
    "wof:name":"Kapili",
    "wof:placetype":"locality"
},
  "geometry": {"coordinates":[36.99525,40.90971],"type":"Point"}
}