{
  "type": "Feature",
  "properties": {
    "gn:admin1_code":"66",
    "gn:asciiname":"Dedefakili",
    "gn:country_code":"TR",
    "gn:dem":1171,
    "gn:feature_class":"P",
    "gn:feature_code":"PPL",
    "gn:name":"Dedefak\u0131l\u0131",
    "gn:population":0,
    "gn:timezone":"Europe/Istanbul",
    "iso:country":"TR",
    "wof:name":"Dedefakili",
    "wof:placetype":"locality"
},
  "geometry": {"coordinates":[35.4343,39.7151],"type":"Point"}
}