{
  "type": "Feature",
  "properties": {
    "gn:admin1_code":"14",
    "gn:asciiname":"Ferdinler",
    "gn:country_code":"TR",
    "gn:dem":779,
    "gn:feature_class":"P",
    "gn:feature_code":"PPL",
    "gn:name":"Ferdinler",
    "gn:population":0,
    "gn:timezone":"Europe/Istanbul",
    "iso:country":"TR",
    "wof:name":"Ferdinler",
    "wof:placetype":"locality"
},
  "geometry": {"coordinates":[31.79479000000001,40.77125],"type":"Point"}
}