{
  "type": "Feature",
  "properties": {
    "gn:admin1_code":"33",
    "gn:asciiname":"Guneykent",
    "gn:country_code":"TR",
    "gn:dem":1255,
    "gn:feature_class":"P",
    "gn:feature_code":"PPL",
    "gn:name":"G\u00fcneykent",
    "gn:population":0,
    "gn:timezone":"Europe/Istanbul",
    "iso:country":"TR",
    "name:und_x_variant":[
        "Geresun",
        "Emirlergiresunu",
        "Geresin",
        "G\u00fcneykent"
    ],
    "wof:name":"Guneykent",
    "wof:placetype":"locality"
},
  "geometry": {"coordinates":[30.39528,37.97138],"type":"Point"}
}