{
  "type": "Feature",
  "properties": {
    "gn:admin1_code":"85",
    "gn:asciiname":"Temenler",
    "gn:country_code":"TR",
    "gn:dem":162,
    "gn:feature_class":"P",
    "gn:feature_code":"PPL",
    "gn:name":"Temenler",
    "gn:population":0,
    "gn:timezone":"Europe/Istanbul",
    "iso:country":"TR",
    "wof:name":"Temenler",
    "wof:placetype":"locality"
},
  "geometry": {"coordinates":[32.06581,41.51819],"type":"Point"}
}