{
  "type": "Feature",
  "properties": {
    "gn:admin1_code":"59.0",
    "gn:asciiname":"Alaybey",
    "gn:country_code":"TR",
    "gn:dem":171,
    "gn:feature_class":"P",
    "gn:feature_code":"PPL",
    "gn:name":"Alaybey",
    "gn:population":0,
    "gn:timezone":"Europe/Istanbul",
    "iso:country":"TR",
    "name:und_x_variant":[
        "Alabey"
    ],
    "wof:name":"Alaybey",
    "wof:placetype":"locality"
},
  "geometry": {"coordinates":[26.99795,40.85912],"type":"Point"}
}