{
  "type": "Feature",
  "properties": {
    "gn:admin1_code":"55.0",
    "gn:asciiname":"Kapihayat",
    "gn:country_code":"TR",
    "gn:dem":920,
    "gn:feature_class":"P",
    "gn:feature_code":"PPL",
    "gn:name":"Kap\u0131hayat",
    "gn:population":0,
    "gn:timezone":"Europe/Istanbul",
    "iso:country":"TR",
    "name:und_x_variant":[
        "Kapuhayat",
        "Kap\u0131hayat"
    ],
    "wof:name":"Kapihayat",
    "wof:placetype":"locality"
},
  "geometry": {"coordinates":[35.87372,41.03412],"type":"Point"}
}