{
  "type": "Feature",
  "properties": {
    "gn:admin1_code":"79",
    "gn:asciiname":"Besler",
    "gn:country_code":"TR",
    "gn:dem":909,
    "gn:feature_class":"P",
    "gn:feature_code":"PPL",
    "gn:name":"Be\u015fler",
    "gn:population":0,
    "gn:timezone":"Europe/Istanbul",
    "iso:country":"TR",
    "name:deu_x_preferred":[
        "Besler"
    ],
    "name:rus_x_preferred":[
        "\u0411\u0435\u0441\u043b\u0435\u0440"
    ],
    "wof:name":"Besler",
    "wof:placetype":"locality"
},
  "geometry": {"coordinates":[33.79284000000001,39.63329],"type":"Point"}
}