{
  "type": "Feature",
  "properties": {
    "gn:admin1_code":"2.0",
    "gn:asciiname":"Korucak",
    "gn:country_code":"TR",
    "gn:dem":1430,
    "gn:feature_class":"P",
    "gn:feature_code":"PPL",
    "gn:name":"Korucak",
    "gn:population":0,
    "gn:timezone":"Europe/Istanbul",
    "iso:country":"TR",
    "name:msa_x_preferred":[
        "Korucak"
    ],
    "name:tur_x_preferred":[
        "Korucak"
    ],
    "name:vie_x_preferred":[
        "Korucak"
    ],
    "wof:name":"Korucak",
    "wof:placetype":"locality"
},
  "geometry": {"coordinates":[38.37667,38.06412],"type":"Point"}
}