{
  "type": "Feature",
  "properties": {
    "gn:admin1_code":"58.0",
    "gn:asciiname":"Calici",
    "gn:country_code":"TR",
    "gn:dem":1508,
    "gn:feature_class":"P",
    "gn:feature_code":"PPL",
    "gn:name":"\u00c7al\u0131c\u0131",
    "gn:population":0,
    "gn:timezone":"Europe/Istanbul",
    "iso:country":"TR",
    "wof:name":"Calici",
    "wof:placetype":"locality"
},
  "geometry": {"coordinates":[37.49489000000001,40.20829000000001],"type":"Point"}
}