{
  "type": "Feature",
  "properties": {
    "gn:admin1_code":"69.0",
    "gn:asciiname":"Demirciler",
    "gn:country_code":"TR",
    "gn:dem":997,
    "gn:feature_class":"P",
    "gn:feature_code":"PPL",
    "gn:name":"Demirciler",
    "gn:population":0,
    "gn:timezone":"Europe/Istanbul",
    "iso:country":"TR",
    "name:tur_x_preferred":[
        "Demirciler"
    ],
    "name:und_x_variant":[
        "Mursal"
    ],
    "wof:name":"Demirciler",
    "wof:placetype":"locality"
},
  "geometry": {"coordinates":[39.11221,40.65038],"type":"Point"}
}