{
  "type": "Feature",
  "properties": {
    "gn:admin1_code":"89.0",
    "gn:asciiname":"Ayanoglu",
    "gn:country_code":"TR",
    "gn:dem":454,
    "gn:feature_class":"P",
    "gn:feature_code":"PPL",
    "gn:name":"Ayano\u011flu",
    "gn:population":0,
    "gn:timezone":"Europe/Istanbul",
    "iso:country":"TR",
    "wof:name":"Ayanoglu",
    "wof:placetype":"locality"
},
  "geometry": {"coordinates":[32.26667,41.23333],"type":"Point"}
}