{
  "type": "Feature",
  "properties": {
    "gn:admin1_code":"62",
    "gn:asciiname":"Karayonca",
    "gn:country_code":"TR",
    "gn:dem":1296,
    "gn:feature_class":"P",
    "gn:feature_code":"PPL",
    "gn:name":"Karayonca",
    "gn:population":0,
    "gn:timezone":"Europe/Istanbul",
    "iso:country":"TR",
    "name:tur_x_preferred":[
        "Karayonca"
    ],
    "wof:name":"Karayonca",
    "wof:placetype":"locality"
},
  "geometry": {"coordinates":[39.10942,39.32384],"type":"Point"}
}