{
  "type": "Feature",
  "properties": {
    "gn:admin1_code":"45",
    "gn:asciiname":"Tatarislam",
    "gn:country_code":"TR",
    "gn:dem":105,
    "gn:feature_class":"P",
    "gn:feature_code":"PPL",
    "gn:name":"Tatarisl\u00e2m",
    "gn:population":0,
    "gn:timezone":"Europe/Istanbul",
    "iso:country":"TR",
    "wof:name":"Tatarislam",
    "wof:placetype":"locality"
},
  "geometry": {"coordinates":[28.11667000000001,38.48333],"type":"Point"}
}