{
  "type": "Feature",
  "properties": {
    "gn:admin1_code":"59.0",
    "gn:asciiname":"Hacikoy",
    "gn:country_code":"TR",
    "gn:dem":231,
    "gn:feature_class":"P",
    "gn:feature_code":"PPL",
    "gn:name":"Hac\u0131k\u00f6y",
    "gn:population":0,
    "gn:timezone":"Europe/Istanbul",
    "iso:country":"TR",
    "name:tur_x_preferred":[
        "Hac\u0131k\u00f6y"
    ],
    "name:tur_x_variant":[
        "Hocak\u00f6y"
    ],
    "wof:name":"Hacikoy",
    "wof:placetype":"locality"
},
  "geometry": {"coordinates":[27.34415,41.01035],"type":"Point"}
}