{
  "type": "Feature",
  "properties": {
    "gn:admin1_code":"40",
    "gn:asciiname":"Alankoy",
    "gn:country_code":"TR",
    "gn:dem":1251,
    "gn:feature_class":"P",
    "gn:feature_code":"PPL",
    "gn:name":"Alank\u00f6y",
    "gn:population":0,
    "gn:timezone":"Europe/Istanbul",
    "iso:country":"TR",
    "name:tur_x_preferred":[
        "Alank\u00f6y"
    ],
    "name:tur_x_variant":[
        "Alan"
    ],
    "wof:name":"Alankoy",
    "wof:placetype":"locality"
},
  "geometry": {"coordinates":[34.21431,39.65842],"type":"Point"}
}