{
  "type": "Feature",
  "properties": {
    "gn:admin1_code":"17.0",
    "gn:asciiname":"Sevketiye",
    "gn:country_code":"TR",
    "gn:dem":7,
    "gn:feature_class":"P",
    "gn:feature_code":"PPL",
    "gn:name":"\u015eevketiye",
    "gn:population":0,
    "gn:timezone":"Europe/Istanbul",
    "iso:country":"TR",
    "wof:name":"Sevketiye",
    "wof:placetype":"locality"
},
  "geometry": {"coordinates":[26.87221,40.39636],"type":"Point"}
}