{
  "type": "Feature",
  "properties": {
    "gn:admin1_code":"82.0",
    "gn:asciiname":"Tuzlu",
    "gn:country_code":"TR",
    "gn:dem":769,
    "gn:feature_class":"P",
    "gn:feature_code":"PPL",
    "gn:name":"Tuzlu",
    "gn:population":0,
    "gn:timezone":"Europe/Istanbul",
    "iso:country":"TR",
    "wof:name":"Tuzlu",
    "wof:placetype":"locality"
},
  "geometry": {"coordinates":[33.67462,40.62305],"type":"Point"}
}