{
  "type": "Feature",
  "properties": {
    "gn:admin1_code":"02",
    "gn:asciiname":"Narun Mezraasi",
    "gn:country_code":"TR",
    "gn:dem":1432,
    "gn:feature_class":"P",
    "gn:feature_code":"PPL",
    "gn:name":"Narun Mezraasi",
    "gn:population":0,
    "gn:timezone":"Europe/Istanbul",
    "iso:country":"TR",
    "name:und_x_variant":[
        "Naran",
        "Narun Mezraas\u0131"
    ],
    "wof:name":"Narun Mezraasi",
    "wof:placetype":"locality"
},
  "geometry": {"coordinates":[38.48333,38.03333],"type":"Point"}
}