{
  "type": "Feature",
  "properties": {
    "gn:country":"TR",
    "gn:fcode":"PPL",
    "gn:pop":1050,
    "iso:country":"TR",
    "name:tur_x_preferred":[
        "Ball\u0131"
    ],
    "qs:name":"Ball\u0131",
    "qs:photos_9r":0,
    "qs:photos_sr":0,
    "qs:pop_sr":"3",
    "wd:wordcount":52,
    "wof:name":"Ball\u0131",
    "wof:placetype":"locality",
    "wof:population":1050
},
  "geometry": {"coordinates":[42.83944,37.41333],"type":"Point"}
}