{
  "type": "Feature",
  "properties": {
    "gn:admin1_code":"55.0",
    "gn:asciiname":"Karantu",
    "gn:country_code":"TR",
    "gn:dem":749,
    "gn:feature_class":"P",
    "gn:feature_code":"PPL",
    "gn:name":"Karantu",
    "gn:population":0,
    "gn:timezone":"Europe/Istanbul",
    "iso:country":"TR",
    "wof:name":"Karantu",
    "wof:placetype":"locality"
},
  "geometry": {"coordinates":[35.9865,41.17836],"type":"Point"}
}