{
  "type": "Feature",
  "properties": {
    "gn:admin1_code":"61.0",
    "gn:asciiname":"Yenice",
    "gn:country_code":"TR",
    "gn:dem":534,
    "gn:feature_class":"P",
    "gn:feature_code":"PPL",
    "gn:name":"Yenice",
    "gn:population":0,
    "gn:timezone":"Europe/Istanbul",
    "iso:country":"TR",
    "name:tur_x_preferred":[
        "Yenice"
    ],
    "wof:name":"Yenice",
    "wof:placetype":"locality"
},
  "geometry": {"coordinates":[40.21199,40.7895],"type":"Point"}
}