{
  "type": "Feature",
  "properties": {
    "gn:admin1_code":"83.0",
    "gn:asciiname":"Yildiz",
    "gn:cc2":"TR",
    "gn:country_code":"TR",
    "gn:dem":699,
    "gn:feature_class":"P",
    "gn:feature_code":"PPL",
    "gn:name":"Y\u0131ld\u0131z",
    "gn:population":0,
    "gn:timezone":"Europe/Istanbul",
    "iso:country":"TR",
    "name:und_x_variant":[
        "Iildyz",
        "Y\u0131ld\u0131z"
    ],
    "wof:name":"Yildiz",
    "wof:placetype":"locality"
},
  "geometry": {"coordinates":[37.37583,36.89083],"type":"Point"}
}