{
  "type": "Feature",
  "properties": {
    "gn:admin1_code":"46",
    "gn:asciiname":"Yapili",
    "gn:country_code":"TR",
    "gn:dem":1734,
    "gn:feature_class":"P",
    "gn:feature_code":"PPL",
    "gn:name":"Yap\u0131l\u0131",
    "gn:population":0,
    "gn:timezone":"Europe/Istanbul",
    "iso:country":"TR",
    "wof:name":"Yapili",
    "wof:placetype":"locality"
},
  "geometry": {"coordinates":[37.21012,38.52694],"type":"Point"}
}