{
  "type": "Feature",
  "properties": {
    "gn:admin1_code":"03",
    "gn:asciiname":"Dadak",
    "gn:country_code":"TR",
    "gn:dem":1307,
    "gn:feature_class":"P",
    "gn:feature_code":"PPL",
    "gn:name":"Dadak",
    "gn:population":0,
    "gn:timezone":"Europe/Istanbul",
    "iso:country":"TR",
    "wof:name":"Dadak",
    "wof:placetype":"locality"
},
  "geometry": {"coordinates":[30.45472,38.59722],"type":"Point"}
}