{
  "type": "Feature",
  "properties": {
    "gn:admin1_code":"25.0",
    "gn:asciiname":"Agveren",
    "gn:cc2":"TR",
    "gn:country_code":"TR",
    "gn:dem":1721,
    "gn:feature_class":"P",
    "gn:feature_code":"PPL",
    "gn:name":"A\u011fveren",
    "gn:population":0,
    "gn:timezone":"Europe/Istanbul",
    "iso:country":"TR",
    "name:und_x_variant":[
        "A\u015fa\u011f\u0131 Akveren",
        "A\u011fveren"
    ],
    "wof:name":"Agveren",
    "wof:placetype":"locality"
},
  "geometry": {"coordinates":[40.61667,39.78333],"type":"Point"}
}