{
  "type": "Feature",
  "properties": {
    "gn:admin1_code":"34",
    "gn:asciiname":"Bozkoca",
    "gn:country_code":"TR",
    "gn:dem":48,
    "gn:feature_class":"P",
    "gn:feature_code":"PPL",
    "gn:name":"Bozkoca",
    "gn:population":0,
    "gn:timezone":"Europe/Istanbul",
    "iso:country":"TR",
    "name:tur_x_preferred":[
        "Bozkoca"
    ],
    "wof:name":"Bozkoca",
    "wof:placetype":"locality"
},
  "geometry": {"coordinates":[29.77359,41.1407],"type":"Point"}
}