{
  "type": "Feature",
  "properties": {
    "gn:admin1_code":"93.0",
    "gn:asciiname":"Hatipliketenciler",
    "gn:country_code":"TR",
    "gn:dem":352,
    "gn:feature_class":"P",
    "gn:feature_code":"PPL",
    "gn:name":"Hatipliketenciler",
    "gn:population":0,
    "gn:timezone":"Europe/Istanbul",
    "iso:country":"TR",
    "name:und_x_variant":[
        "Ketenciler",
        "Hatipli",
        "Hatipliketenciler"
    ],
    "wof:name":"Hatipliketenciler",
    "wof:placetype":"locality"
},
  "geometry": {"coordinates":[31.17582,40.92045],"type":"Point"}
}