{
  "type": "Feature",
  "properties": {
    "gn:admin1_code":"26.0",
    "gn:asciiname":"Akkaya",
    "gn:country_code":"TR",
    "gn:dem":869,
    "gn:feature_class":"P",
    "gn:feature_code":"PPL",
    "gn:name":"Akkaya",
    "gn:population":0,
    "gn:timezone":"Europe/Istanbul",
    "iso:country":"TR",
    "name:und_x_variant":[
        "Akkaya K\u00f6y\u00fc",
        "Akkaya"
    ],
    "wof:name":"Akkaya",
    "wof:placetype":"locality"
},
  "geometry": {"coordinates":[30.31128,39.62052],"type":"Point"}
}