{
  "type": "Feature",
  "properties": {
    "gn:admin1_code":"02",
    "gn:asciiname":"Uzunpinar",
    "gn:country_code":"TR",
    "gn:dem":686,
    "gn:feature_class":"P",
    "gn:feature_code":"PPL",
    "gn:name":"Uzunp\u0131nar",
    "gn:population":0,
    "gn:timezone":"Europe/Istanbul",
    "iso:country":"TR",
    "name:tur_x_preferred":[
        "Uzunp\u0131nar"
    ],
    "wof:name":"Uzunpinar",
    "wof:placetype":"locality"
},
  "geometry": {"coordinates":[38.471,37.79033],"type":"Point"}
}