{
  "type": "Feature",
  "properties": {
    "gn:admin1_code":"89",
    "gn:asciiname":"Tabaklar",
    "gn:country_code":"TR",
    "gn:dem":527,
    "gn:feature_class":"P",
    "gn:feature_code":"PPL",
    "gn:name":"Tabaklar",
    "gn:population":0,
    "gn:timezone":"Europe/Istanbul",
    "iso:country":"TR",
    "name:deu_x_preferred":[
        "Tabaklar"
    ],
    "name:tur_x_preferred":[
        "Tabaklar"
    ],
    "wof:name":"Tabaklar",
    "wof:placetype":"locality"
},
  "geometry": {"coordinates":[32.39941,41.21996],"type":"Point"}
}