{
  "type": "Feature",
  "properties": {
    "gn:country":"TR",
    "gn:fcode":"PPL",
    "gn:population":140,
    "iso:country":"TR",
    "name:eng_x_preferred":[
        "D\u00fczme\u015fe"
    ],
    "name:msa_x_preferred":[
        "D\u00fczme\u015fe"
    ],
    "name:nld_x_preferred":[
        "D\u00fczme\u015fe"
    ],
    "name:tur_x_preferred":[
        "D\u00fczme\u015fe"
    ],
    "name:und_x_variant":[
        "Khavri"
    ],
    "name:vie_x_preferred":[
        "D\u00fczme\u015fe"
    ],
    "qs:name":"Havri",
    "qs:photos_9r":0,
    "qs:photos_sr":0,
    "qs:pop_sr":"1",
    "wof:name":"Havri",
    "wof:placetype":"locality",
    "wof:population":140
},
  "geometry": {"coordinates":[41.43583,37.60222],"type":"Point"}
}