{
  "type": "Feature",
  "properties": {
    "gn:admin1_code":"8.0",
    "gn:asciiname":"Orenli",
    "gn:country_code":"TR",
    "gn:dem":784,
    "gn:feature_class":"P",
    "gn:feature_code":"PPL",
    "gn:name":"\u00d6renli",
    "gn:population":0,
    "gn:timezone":"Europe/Istanbul",
    "iso:country":"TR",
    "name:tur_x_preferred":[
        "\u00d6renli"
    ],
    "wof:name":"Orenli",
    "wof:placetype":"locality"
},
  "geometry": {"coordinates":[41.74275,41.20651],"type":"Point"}
}