{
  "type": "Feature",
  "properties": {
    "gn:admin1_code":"5.0",
    "gn:asciiname":"Kayrak",
    "gn:country_code":"TR",
    "gn:dem":931,
    "gn:feature_class":"P",
    "gn:feature_code":"PPL",
    "gn:name":"Kayrak",
    "gn:population":0,
    "gn:timezone":"Europe/Istanbul",
    "iso:country":"TR",
    "wof:name":"Kayrak",
    "wof:placetype":"locality"
},
  "geometry": {"coordinates":[35.86763,40.52941],"type":"Point"}
}