{
  "type": "Feature",
  "properties": {
    "gn:admin1_code":"34.0",
    "gn:asciiname":"Canakca",
    "gn:country_code":"TR",
    "gn:dem":56,
    "gn:feature_class":"P",
    "gn:feature_code":"PPL",
    "gn:name":"\u00c7anak\u00e7a",
    "gn:population":0,
    "gn:timezone":"Europe/Istanbul",
    "iso:country":"TR",
    "name:tur_x_preferred":[
        "\u00c7anak\u00e7a"
    ],
    "wof:name":"Canakca",
    "wof:placetype":"locality"
},
  "geometry": {"coordinates":[28.49518,41.24666],"type":"Point"}
}