{
  "type": "Feature",
  "properties": {
    "gn:admin1_code":"31.0",
    "gn:asciiname":"Tapybey",
    "gn:country_code":"TR",
    "gn:dem":96,
    "gn:feature_class":"P",
    "gn:feature_code":"PPL",
    "gn:name":"Tapybey",
    "gn:population":0,
    "gn:timezone":"Europe/Istanbul",
    "iso:country":"TR",
    "name:und_x_variant":[
        "Tap\u0131bey"
    ],
    "wof:name":"Tapybey",
    "wof:placetype":"locality"
},
  "geometry": {"coordinates":[36.35566,36.21189],"type":"Point"}
}