{
  "type": "Feature",
  "properties": {
    "gn:admin1_code":"17.0",
    "gn:asciiname":"Ahmetler",
    "gn:country_code":"TR",
    "gn:dem":263,
    "gn:feature_class":"P",
    "gn:feature_code":"PPL",
    "gn:name":"Ahmetler",
    "gn:population":0,
    "gn:timezone":"Europe/Istanbul",
    "iso:country":"TR",
    "name:deu_x_preferred":[
        "Ahmetler"
    ],
    "name:tur_x_preferred":[
        "Ahmetler"
    ],
    "wof:name":"Ahmetler",
    "wof:placetype":"locality"
},
  "geometry": {"coordinates":[26.66667,39.93333],"type":"Point"}
}