{
  "type": "Feature",
  "properties": {
    "gn:admin1_code":"31.0",
    "gn:asciiname":"Yarikkaya",
    "gn:country_code":"TR",
    "gn:dem":310,
    "gn:feature_class":"P",
    "gn:feature_code":"PPL",
    "gn:name":"Yar\u0131kkaya",
    "gn:population":0,
    "gn:timezone":"Europe/Istanbul",
    "iso:country":"TR",
    "name:und_x_variant":[
        "Yar\u0131kkaya",
        "A\u015fa\u011f\u0131 Yar\u0131kkaya"
    ],
    "wof:name":"Yarikkaya",
    "wof:placetype":"locality"
},
  "geometry": {"coordinates":[36.21583,36.56139],"type":"Point"}
}