{
  "type": "Feature",
  "properties": {
    "gn:admin1_code":"21",
    "gn:asciiname":"Bicimli",
    "gn:country_code":"TR",
    "gn:dem":832,
    "gn:feature_class":"P",
    "gn:feature_code":"PPL",
    "gn:name":"Bi\u00e7imli",
    "gn:population":0,
    "gn:timezone":"Europe/Istanbul",
    "iso:country":"TR",
    "name:und_x_variant":[
        "Bi\u00e7imli",
        "Boli\u015f"
    ],
    "wof:name":"Bicimli",
    "wof:placetype":"locality"
},
  "geometry": {"coordinates":[40.67406,38.20858],"type":"Point"}
}