{
  "type": "Feature",
  "properties": {
    "gn:admin1_code":"52.0",
    "gn:asciiname":"Yenikargicak",
    "gn:country_code":"TR",
    "gn:dem":626,
    "gn:feature_class":"P",
    "gn:feature_code":"PPL",
    "gn:name":"Yenikarg\u0131cak",
    "gn:population":0,
    "gn:timezone":"Europe/Istanbul",
    "iso:country":"TR",
    "name:und_x_variant":[
        "Karkucak Muhac\u0131r",
        "Karakucak",
        "Karakucakmuhacir",
        "Yenikarg\u0131cak"
    ],
    "wof:name":"Yenikargicak",
    "wof:placetype":"locality"
},
  "geometry": {"coordinates":[37.31898,40.96323],"type":"Point"}
}