{
  "type": "Feature",
  "properties": {
    "gn:admin1_code":"54.0",
    "gn:asciiname":"Kozan",
    "gn:country_code":"TR",
    "gn:dem":98,
    "gn:feature_class":"P",
    "gn:feature_code":"PPL",
    "gn:name":"Kozan",
    "gn:population":0,
    "gn:timezone":"Europe/Istanbul",
    "iso:country":"TR",
    "name:tur_x_preferred":[
        "Kozan"
    ],
    "wof:name":"Kozan",
    "wof:placetype":"locality"
},
  "geometry": {"coordinates":[30.14336,40.45162],"type":"Point"}
}