{
  "type": "Feature",
  "properties": {
    "gn:admin1_code":"24",
    "gn:asciiname":"Agacsaray",
    "gn:country_code":"TR",
    "gn:dem":1643,
    "gn:feature_class":"P",
    "gn:feature_code":"PPL",
    "gn:name":"A\u011fa\u00e7saray",
    "gn:population":0,
    "gn:timezone":"Europe/Istanbul",
    "iso:country":"TR",
    "name:und_x_variant":[
        "Menk\u00e2r",
        "Minkar",
        "Munkar",
        "A\u011fa\u00e7saray"
    ],
    "wof:name":"Agacsaray",
    "wof:placetype":"locality"
},
  "geometry": {"coordinates":[38.93964,39.73082],"type":"Point"}
}