{
  "type": "Feature",
  "properties": {
    "gn:admin1_code":"88.0",
    "gn:asciiname":"Kazkoparan",
    "gn:country_code":"TR",
    "gn:dem":1796,
    "gn:feature_class":"P",
    "gn:feature_code":"PPL",
    "gn:name":"Kazkoparan",
    "gn:population":0,
    "gn:timezone":"Europe/Istanbul",
    "iso:country":"TR",
    "name:eng_x_preferred":[
        "Kazkoparan"
    ],
    "name:rus_x_preferred":[
        "\u041a\u0430\u0437\u044b\u043a\u043e\u043b\u0430\u0440\u0430\u043d"
    ],
    "name:und_x_variant":[
        "Kozkoparan",
        "Kaz\u0131koparan",
        "Kazkoparan"
    ],
    "wof:name":"Kazkoparan",
    "wof:placetype":"locality"
},
  "geometry": {"coordinates":[43.43669000000001,40.01811],"type":"Point"}
}