{
  "type": "Feature",
  "properties": {
    "gn:admin1_code":"31.0",
    "gn:asciiname":"Syuryudzhyudana",
    "gn:country_code":"TR",
    "gn:dem":27,
    "gn:feature_class":"P",
    "gn:feature_code":"PPL",
    "gn:name":"Syuryudzhyudana",
    "gn:population":0,
    "gn:timezone":"Europe/Istanbul",
    "iso:country":"TR",
    "name:und_x_variant":[
        "S\u00fcr\u00fcc\u00fcdana"
    ],
    "wof:name":"Syuryudzhyudana",
    "wof:placetype":"locality"
},
  "geometry": {"coordinates":[36.0425,36.07583],"type":"Point"}
}