{
  "type": "Feature",
  "properties": {
    "gn:admin1_code":"58.0",
    "gn:asciiname":"Kecikkaya",
    "gn:country_code":"TR",
    "gn:dem":1337,
    "gn:feature_class":"P",
    "gn:feature_code":"PPL",
    "gn:name":"Ke\u00e7ikkaya",
    "gn:population":0,
    "gn:timezone":"Europe/Istanbul",
    "iso:country":"TR",
    "wof:name":"Kecikkaya",
    "wof:placetype":"locality"
},
  "geometry": {"coordinates":[37.83407,39.36274],"type":"Point"}
}