{
  "type": "Feature",
  "properties": {
    "gn:admin1_code":"45",
    "gn:asciiname":"Haciibrahimler",
    "gn:country_code":"TR",
    "gn:dem":796,
    "gn:feature_class":"P",
    "gn:feature_code":"PPL",
    "gn:name":"Hac\u0131ibrahimler",
    "gn:population":0,
    "gn:timezone":"Europe/Istanbul",
    "iso:country":"TR",
    "name:tur_x_preferred":[
        "Hac\u0131ibrahimler"
    ],
    "wof:name":"Haciibrahimler",
    "wof:placetype":"locality"
},
  "geometry": {"coordinates":[28.04647000000001,38.97825],"type":"Point"}
}