{
  "type": "Feature",
  "properties": {
    "gn:admin1_code":"12",
    "gn:asciiname":"Gecitli",
    "gn:country_code":"TR",
    "gn:dem":1866,
    "gn:feature_class":"P",
    "gn:feature_code":"PPL",
    "gn:name":"Ge\u00e7itli",
    "gn:population":0,
    "gn:timezone":"Europe/Istanbul",
    "iso:country":"TR",
    "name:und_x_variant":[
        "Kobik",
        "Kuzik",
        "Ge\u00e7itli",
        "Kub\u0131k"
    ],
    "wof:name":"Gecitli",
    "wof:placetype":"locality"
},
  "geometry": {"coordinates":[41.07596,39.41608],"type":"Point"}
}