{
  "type": "Feature",
  "properties": {
    "gn:admin1_code":"43",
    "gn:asciiname":"Saka",
    "gn:country_code":"TR",
    "gn:dem":964,
    "gn:feature_class":"P",
    "gn:feature_code":"PPL",
    "gn:name":"Saka",
    "gn:population":0,
    "gn:timezone":"Europe/Istanbul",
    "iso:country":"TR",
    "name:amh_x_preferred":[
        "\u1233\u12ab\u12ce\u127d"
    ],
    "name:ara_x_preferred":[
        "\u0633\u0627\u0643\u0627"
    ],
    "name:aze_x_preferred":[
        "Saklar"
    ],
    "name:bak_x_preferred":[
        "\u0421\u0430\u043a\u0442\u0430\u0440"
    ],
    "name:cat_x_preferred":[
        "Saques"
    ],
    "name:ces_x_preferred":[
        "Sakov\u00e9"
    ],
    "name:chv_x_preferred":[
        "\u0421\u0430\u043a\u043a\u0438\u0441\u0435\u043c"
    ],
    "name:deu_x_preferred":[
        "Saken"
    ],
    "name:ell_x_preferred":[
        "\u03a3\u03ac\u03ba\u03b5\u03c2"
    ],
    "name:epo_x_preferred":[
        "Sakaoj"
    ],
    "name:fas_x_preferred":[
        "\u0633\u0627\u06a9\u0627"
    ],
    "name:fra_x_preferred":[
        "Sakas"
    ],
    "name:hun_x_preferred":[
        "Szak\u00e1k"
    ],
    "name:hye_x_preferred":[
        "\u054d\u0561\u056f\u0565\u0580"
    ],
    "name:ind_x_preferred":[
        "Saka"
    ],
    "name:isl_x_preferred":[
        "Sakar"
    ],
    "name:ita_x_preferred":[
        "Saci"
    ],
    "name:kat_x_preferred":[
        "\u10e1\u10d0\u10d9\u10d4\u10d1\u10d8"
    ],
    "name:kaz_x_preferred":[
        "\u0421\u0430\u049b\u0442\u0430\u0440"
    ],
    "name:kir_x_preferred":[
        "\u0421\u0430\u043a\u0442\u0430\u0440"
    ],
    "name:lfn_x_preferred":[
        "Sacas"
    ],
    "name:mal_x_preferred":[
        "\u0d36\u0d15\u0d7c"
    ],
    "name:nld_x_preferred":[
        "Saken"
    ],
    "name:nor_x_preferred":[
        "Saka"
    ],
    "name:oss_x_preferred":[
        "\u0421\u0430\u043a\u0442\u00e6"
    ],
    "name:pnb_x_preferred":[
        "\u0633\u0627\u06a9\u0627"
    ],
    "name:pol_x_preferred":[
        "Sakowie"
    ],
    "name:por_x_preferred":[
        "Sacas"
    ],
    "name:ron_x_preferred":[
        "Saci"
    ],
    "name:rus_x_preferred":[
        "\u0421\u0430\u043a\u0438"
    ],
    "name:sah_x_preferred":[
        "\u0421\u0430\u043a\u0430\u043b\u0430\u0440"
    ],
    "name:slk_x_preferred":[
        "Sakovia"
    ],
    "name:slv_x_preferred":[
        "Saki"
    ],
    "name:spa_x_preferred":[
        "Sacas"
    ],
    "name:swe_x_preferred":[
        "Saka"
    ],
    "name:tam_x_preferred":[
        "\u0b9a\u0b95\u0bb0\u0bcd\u0b95\u0bb3\u0bcd"
    ],
    "name:tat_x_preferred":[
        "Saqlar"
    ],
    "name:tur_x_preferred":[
        "Sakalar"
    ],
    "name:ukr_x_preferred":[
        "\u0421\u0430\u043a\u0438"
    ],
    "name:und_x_variant":[
        "Sakak\u00f6y",
        "B\u00fcy\u00fcksaka"
    ],
    "name:uzb_x_preferred":[
        "Saklar"
    ],
    "name:vie_x_preferred":[
        "Ng\u01b0\u1eddi Saka"
    ],
    "wof:name":"Saka",
    "wof:placetype":"locality"
},
  "geometry": {"coordinates":[30.13889,39.37167],"type":"Point"}
}