{
  "type": "Feature",
  "properties": {
    "gn:admin1_code":"43",
    "gn:asciiname":"Saka",
    "gn:country_code":"TR",
    "gn:dem":964,
    "gn:feature_class":"P",
    "gn:feature_code":"PPL",
    "gn:name":"Saka",
    "gn:population":0,
    "gn:timezone":"Europe/Istanbul",
    "iso:country":"TR",
    "name:und_x_variant":[
        "Sakak\u00f6y",
        "B\u00fcy\u00fcksaka"
    ],
    "wof:name":"Saka",
    "wof:placetype":"locality"
},
  "geometry": {"coordinates":[30.13889,39.37167],"type":"Point"}
}