{
  "type": "Feature",
  "properties": {
    "gn:admin1_code":"90.0",
    "gn:asciiname":"Hacipoglu",
    "gn:country_code":"TR",
    "gn:dem":489,
    "gn:feature_class":"P",
    "gn:feature_code":"PPL",
    "gn:name":"Hac\u0131po\u011flu",
    "gn:population":0,
    "gn:timezone":"Europe/Istanbul",
    "iso:country":"TR",
    "wof:name":"Hacipoglu",
    "wof:placetype":"locality"
},
  "geometry": {"coordinates":[36.95676,36.80095],"type":"Point"}
}