{
  "type": "Feature",
  "properties": {
    "gn:admin1_code":"38",
    "gn:asciiname":"Doganli",
    "gn:country_code":"TR",
    "gn:dem":1410,
    "gn:feature_class":"P",
    "gn:feature_code":"PPL",
    "gn:name":"Do\u011fanl\u0131",
    "gn:population":0,
    "gn:timezone":"Europe/Istanbul",
    "iso:country":"TR",
    "name:und_x_variant":[
        "G\u00f6rdeles",
        "Do\u011fanl\u0131"
    ],
    "wof:name":"Doganli",
    "wof:placetype":"locality"
},
  "geometry": {"coordinates":[35.06797,38.18631],"type":"Point"}
}