{
  "type": "Feature",
  "properties": {
    "gn:admin1_code":"33.0",
    "gn:asciiname":"Akpinar",
    "gn:country_code":"TR",
    "gn:dem":1229,
    "gn:feature_class":"P",
    "gn:feature_code":"PPL",
    "gn:name":"Akp\u0131nar",
    "gn:population":0,
    "gn:timezone":"Europe/Istanbul",
    "iso:country":"TR",
    "name:und_x_variant":[
        "Akp\u0131nar K\u00f6y\u00fc",
        "Akp\u0131nar"
    ],
    "wof:name":"Akpinar",
    "wof:placetype":"locality"
},
  "geometry": {"coordinates":[30.8486,37.84472],"type":"Point"}
}