{
  "type": "Feature",
  "properties": {
    "gn:admin1_code":"63",
    "gn:asciiname":"Huyuklu",
    "gn:country_code":"TR",
    "gn:dem":628,
    "gn:feature_class":"P",
    "gn:feature_code":"PPL",
    "gn:name":"H\u00fcy\u00fckl\u00fc",
    "gn:population":0,
    "gn:timezone":"Europe/Istanbul",
    "iso:country":"TR",
    "name:tur_x_preferred":[
        "H\u00fcy\u00fckl\u00fc"
    ],
    "wof:name":"Huyuklu",
    "wof:placetype":"locality"
},
  "geometry": {"coordinates":[38.71271,37.43438],"type":"Point"}
}