{
  "type": "Feature",
  "properties": {
    "gn:admin1_code":"60.0",
    "gn:asciiname":"Tahtoba",
    "gn:country_code":"TR",
    "gn:dem":1199,
    "gn:feature_class":"P",
    "gn:feature_code":"PPL",
    "gn:name":"Tahtoba",
    "gn:population":0,
    "gn:timezone":"Europe/Istanbul",
    "iso:country":"TR",
    "name:und_x_variant":[
        "Tahtuba",
        "Tahtoba"
    ],
    "wof:name":"Tahtoba",
    "wof:placetype":"locality"
},
  "geometry": {"coordinates":[36.45203,40.20861],"type":"Point"}
}