{
  "type": "Feature",
  "properties": {
    "gn:admin1_code":"71.0",
    "gn:asciiname":"Acikuyu",
    "gn:country_code":"TR",
    "gn:dem":1043,
    "gn:feature_class":"P",
    "gn:feature_code":"PPL",
    "gn:name":"Ac\u0131kuyu",
    "gn:population":0,
    "gn:timezone":"Europe/Istanbul",
    "iso:country":"TR",
    "name:und_x_variant":[
        "Ac\u0131kuyuk\u00f6y\u00fc",
        "Ac\u0131kuyu"
    ],
    "wof:name":"Acikuyu",
    "wof:placetype":"locality"
},
  "geometry": {"coordinates":[34.28100999999999,37.71765],"type":"Point"}
}