{
  "type": "Feature",
  "properties": {
    "gn:admin1_code":"60.0",
    "gn:asciiname":"Oglakci",
    "gn:country_code":"TR",
    "gn:dem":814,
    "gn:feature_class":"P",
    "gn:feature_code":"PPL",
    "gn:name":"O\u011flak\u00e7\u0131",
    "gn:population":0,
    "gn:timezone":"Europe/Istanbul",
    "iso:country":"TR",
    "name:und_x_variant":[
        "Olah\u00e7\u0131",
        "O\u011flak\u00e7\u0131"
    ],
    "wof:name":"Oglakci",
    "wof:placetype":"locality"
},
  "geometry": {"coordinates":[36.58791,40.58982],"type":"Point"}
}