{
  "type": "Feature",
  "properties": {
    "gn:admin1_code":"04",
    "gn:asciiname":"Goller",
    "gn:country_code":"TR",
    "gn:dem":2183,
    "gn:feature_class":"P",
    "gn:feature_code":"PPL",
    "gn:name":"G\u00f6ller",
    "gn:population":0,
    "gn:timezone":"Europe/Istanbul",
    "iso:country":"TR",
    "name:und_x_variant":[
        "G\u00f6llerk\u00f6y\u00fc",
        "G\u00f6ller"
    ],
    "wof:name":"Goller",
    "wof:placetype":"locality"
},
  "geometry": {"coordinates":[44.1979,39.4768],"type":"Point"}
}