{
  "type": "Feature",
  "properties": {
    "gn:admin1_code":"22.0",
    "gn:asciiname":"Begendik",
    "gn:country_code":"TR",
    "gn:dem":134,
    "gn:feature_class":"P",
    "gn:feature_code":"PPL",
    "gn:name":"Be\u011fendik",
    "gn:population":0,
    "gn:timezone":"Europe/Istanbul",
    "iso:country":"TR",
    "name:deu_x_preferred":[
        "Be\u011fendik"
    ],
    "name:und_x_variant":[
        "Beyendik",
        "Be\u011fendik"
    ],
    "wof:name":"Begendik",
    "wof:placetype":"locality"
},
  "geometry": {"coordinates":[26.57533,40.92874000000001],"type":"Point"}
}