{
  "type": "Feature",
  "properties": {
    "gn:admin1_code":"82.0",
    "gn:asciiname":"Arpayeri",
    "gn:country_code":"TR",
    "gn:dem":1256,
    "gn:feature_class":"P",
    "gn:feature_code":"PPL",
    "gn:name":"Arpayeri",
    "gn:population":0,
    "gn:timezone":"Europe/Istanbul",
    "iso:country":"TR",
    "name:und_x_variant":[
        "Arpayeri K\u00f6y\u00fc",
        "Arpayeri"
    ],
    "wof:name":"Arpayeri",
    "wof:placetype":"locality"
},
  "geometry": {"coordinates":[33.7403,40.95909],"type":"Point"}
}