{
  "type": "Feature",
  "properties": {
    "gn:admin1_code":"81",
    "gn:asciiname":"Kasarli",
    "gn:country_code":"TR",
    "gn:dem":756,
    "gn:feature_class":"P",
    "gn:feature_code":"PPL",
    "gn:name":"Kasarl\u0131",
    "gn:population":0,
    "gn:timezone":"Europe/Istanbul",
    "iso:country":"TR",
    "name:und_x_variant":[
        "Kasarl\u0131",
        "Kazanc\u0131"
    ],
    "wof:name":"Kasarli",
    "wof:placetype":"locality"
},
  "geometry": {"coordinates":[35.9683,37.71278],"type":"Point"}
}