{
  "type": "Feature",
  "properties": {
    "gn:admin1_code":"45",
    "gn:asciiname":"Karayahsi",
    "gn:cc2":"TR",
    "gn:country_code":"TR",
    "gn:dem":74,
    "gn:feature_class":"P",
    "gn:feature_code":"PPL",
    "gn:name":"Karayah\u015fi",
    "gn:population":0,
    "gn:timezone":"Europe/Istanbul",
    "iso:country":"TR",
    "name:und_x_variant":[
        "Karaya\u015fl\u0131",
        "Karayah\u015fi"
    ],
    "wof:name":"Karayahsi",
    "wof:placetype":"locality"
},
  "geometry": {"coordinates":[28.05,38.53333],"type":"Point"}
}