{
  "type": "Feature",
  "properties": {
    "gn:admin1_code":"70",
    "gn:asciiname":"Betane",
    "gn:country_code":"TR",
    "gn:dem":2364,
    "gn:feature_class":"P",
    "gn:feature_code":"PPL",
    "gn:name":"Betane",
    "gn:population":0,
    "gn:timezone":"Europe/Istanbul",
    "iso:country":"TR",
    "name:und_x_variant":[
        "Surman"
    ],
    "wof:name":"Betane",
    "wof:placetype":"locality"
},
  "geometry": {"coordinates":[43.72268,37.61065],"type":"Point"}
}