{
  "type": "Feature",
  "properties": {
    "gn:admin1_code":"68",
    "gn:asciiname":"Hacitugrul",
    "gn:country_code":"TR",
    "gn:dem":993,
    "gn:feature_class":"P",
    "gn:feature_code":"PPL",
    "gn:name":"Hac\u0131tu\u011frul",
    "gn:population":0,
    "gn:timezone":"Europe/Istanbul",
    "iso:country":"TR",
    "name:und_x_variant":[
        "Hac\u0131torul",
        "Hac\u0131tu\u011frul"
    ],
    "wof:name":"Hacitugrul",
    "wof:placetype":"locality"
},
  "geometry": {"coordinates":[32.19617,39.72833],"type":"Point"}
}