{
  "type": "Feature",
  "properties": {
    "gn:admin1_code":"72.0",
    "gn:asciiname":"Acikyol",
    "gn:country_code":"TR",
    "gn:dem":629,
    "gn:feature_class":"P",
    "gn:feature_code":"PPL",
    "gn:name":"A\u00e7\u0131kyol",
    "gn:population":0,
    "gn:timezone":"Europe/Istanbul",
    "iso:country":"TR",
    "name:tur_x_preferred":[
        "A\u00e7\u0131kyol"
    ],
    "name:und_x_variant":[
        "Haferi",
        "Khaferi"
    ],
    "wof:name":"Acikyol",
    "wof:placetype":"locality"
},
  "geometry": {"coordinates":[41.1816,37.17667],"type":"Point"}
}