{
  "type": "Feature",
  "properties": {
    "gn:admin1_code":"64",
    "gn:asciiname":"Haskoy",
    "gn:country_code":"TR",
    "gn:dem":785,
    "gn:feature_class":"P",
    "gn:feature_code":"PPL",
    "gn:name":"Hask\u00f6y",
    "gn:population":0,
    "gn:timezone":"Europe/Istanbul",
    "iso:country":"TR",
    "wof:name":"Haskoy",
    "wof:placetype":"locality"
},
  "geometry": {"coordinates":[29.4125,38.36583],"type":"Point"}
}