{
  "type": "Feature",
  "properties": {
    "gn:admin1_code":"17.0",
    "gn:asciiname":"Akcakecili",
    "gn:country_code":"TR",
    "gn:dem":178,
    "gn:feature_class":"P",
    "gn:feature_code":"PPL",
    "gn:name":"Ak\u00e7ake\u00e7ili",
    "gn:population":0,
    "gn:timezone":"Europe/Istanbul",
    "iso:country":"TR",
    "name:tur_x_preferred":[
        "Ak\u00e7ake\u00e7ili"
    ],
    "wof:name":"Akcakecili",
    "wof:placetype":"locality"
},
  "geometry": {"coordinates":[26.20492,39.71247],"type":"Point"}
}