{
  "type": "Feature",
  "properties": {
    "gn:admin1_code":"23",
    "gn:asciiname":"Kokluce",
    "gn:country_code":"TR",
    "gn:dem":1278,
    "gn:feature_class":"P",
    "gn:feature_code":"PPL",
    "gn:name":"K\u00f6kl\u00fcce",
    "gn:population":0,
    "gn:timezone":"Europe/Istanbul",
    "iso:country":"TR",
    "name:tur_x_preferred":[
        "K\u00f6kl\u00fcce"
    ],
    "wof:name":"Kokluce",
    "wof:placetype":"locality"
},
  "geometry": {"coordinates":[40.16218,38.78514000000001],"type":"Point"}
}