{
  "type": "Feature",
  "properties": {
    "gn:admin1_code":"58",
    "gn:asciiname":"Avsaroren",
    "gn:cc2":"TR",
    "gn:country_code":"TR",
    "gn:dem":1620,
    "gn:feature_class":"P",
    "gn:feature_code":"PPL",
    "gn:name":"Av\u015far\u00f6ren",
    "gn:population":0,
    "gn:timezone":"Europe/Istanbul",
    "iso:country":"TR",
    "name:und_x_variant":[
        "Af\u015farveran",
        "Av\u015ferveran",
        "Av\u015farviran",
        "Av\u015faveran",
        "Av\u015far\u00f6ren"
    ],
    "wof:name":"Avsaroren",
    "wof:placetype":"locality"
},
  "geometry": {"coordinates":[37.20556,39.03028],"type":"Point"}
}