{
  "type": "Feature",
  "properties": {
    "gn:admin1_code":"65.0",
    "gn:asciiname":"Cennetdere",
    "gn:country_code":"TR",
    "gn:dem":1629,
    "gn:feature_class":"P",
    "gn:feature_code":"PPL",
    "gn:name":"Cennetdere",
    "gn:population":0,
    "gn:timezone":"Europe/Istanbul",
    "iso:country":"TR",
    "name:tur_x_preferred":[
        "Cennetdere"
    ],
    "wof:name":"Cennetdere",
    "wof:placetype":"locality"
},
  "geometry": {"coordinates":[43.01499,37.88666],"type":"Point"}
}