{
  "type": "Feature",
  "properties": {
    "gn:admin1_code":"24",
    "gn:asciiname":"Yurtbasi",
    "gn:country_code":"TR",
    "gn:dem":1778,
    "gn:feature_class":"P",
    "gn:feature_code":"PPL",
    "gn:name":"Yurtba\u015f\u0131",
    "gn:population":0,
    "gn:timezone":"Europe/Istanbul",
    "iso:country":"TR",
    "name:und_x_variant":[
        "Melik\u015ferif",
        "Yurtba\u015f\u0131"
    ],
    "wof:name":"Yurtbasi",
    "wof:placetype":"locality"
},
  "geometry": {"coordinates":[38.92426,39.9182],"type":"Point"}
}