{
  "type": "Feature",
  "properties": {
    "gn:admin1_code":"38",
    "gn:asciiname":"Dagardi",
    "gn:country_code":"TR",
    "gn:dem":1706,
    "gn:feature_class":"P",
    "gn:feature_code":"PPL",
    "gn:name":"Da\u011fard\u0131",
    "gn:population":0,
    "gn:timezone":"Europe/Istanbul",
    "iso:country":"TR",
    "name:und_x_variant":[
        "Ermin",
        "Da\u011fard\u0131"
    ],
    "wof:name":"Dagardi",
    "wof:placetype":"locality"
},
  "geometry": {"coordinates":[35.80121,38.6969],"type":"Point"}
}