{
  "type": "Feature",
  "properties": {
    "gn:country":"TR",
    "gn:fcode":"PPL",
    "gn:pop":3185,
    "iso:country":"TR",
    "name:unk_x_variant":[
        "\u015eark\u0131mugayre"
    ],
    "qs:name":"G\u00fcneren",
    "qs:photos_9r":0,
    "qs:photos_sr":0,
    "qs:pop_sr":"4",
    "wof:name":"G\u00fcneren",
    "wof:placetype":"locality",
    "wof:population":3185
},
  "geometry": {"coordinates":[39.08861,36.73417],"type":"Point"}
}