{
  "type": "Feature",
  "properties": {
    "gn:admin1_code":"26",
    "gn:asciiname":"Kayaalti Mahalle",
    "gn:country_code":"TR",
    "gn:dem":1160,
    "gn:feature_class":"P",
    "gn:feature_code":"PPL",
    "gn:name":"Kayaalt\u0131 Mahalle",
    "gn:population":0,
    "gn:timezone":"Europe/Istanbul",
    "iso:country":"TR",
    "wof:name":"Kayaalti Mahalle",
    "wof:placetype":"locality"
},
  "geometry": {"coordinates":[30.60825,39.34851],"type":"Point"}
}