{
  "type": "Feature",
  "properties": {
    "gn:admin1_code":"25.0",
    "gn:asciiname":"Kaleboynu",
    "gn:country_code":"TR",
    "gn:dem":1944,
    "gn:feature_class":"P",
    "gn:feature_code":"PPL",
    "gn:name":"Kaleboynu",
    "gn:population":0,
    "gn:timezone":"Europe/Istanbul",
    "iso:country":"TR",
    "name:tur_x_preferred":[
        "Kaleboynu"
    ],
    "wof:name":"Kaleboynu",
    "wof:placetype":"locality"
},
  "geometry": {"coordinates":[41.35728,40.41891],"type":"Point"}
}