{
  "type": "Feature",
  "properties": {
    "gn:admin1_code":"66",
    "gn:asciiname":"Yesilova",
    "gn:country_code":"TR",
    "gn:dem":1073,
    "gn:feature_class":"P",
    "gn:feature_code":"PPL",
    "gn:name":"Ye\u015filova",
    "gn:population":0,
    "gn:timezone":"Europe/Istanbul",
    "iso:country":"TR",
    "name:tur_x_preferred":[
        "Ye\u015filova"
    ],
    "name:tur_x_variant":[
        "Karga"
    ],
    "wof:name":"Yesilova",
    "wof:placetype":"locality"
},
  "geometry": {"coordinates":[35.00995,39.66262],"type":"Point"}
}