{
  "type": "Feature",
  "properties": {
    "gn:country":"TR",
    "gn:fcode":"PPL",
    "gn:population":340,
    "iso:country":"TR",
    "name:tur_x_preferred":[
        "Dilimli"
    ],
    "name:tur_x_variant":[
        "Haca",
        "Dilimli Baraj\u0131"
    ],
    "qs:name":"Dilimli",
    "qs:photos_9r":0,
    "qs:photos_sr":0,
    "qs:pop_sr":"2",
    "wd:wordcount":170,
    "wof:name":"Dilimli",
    "wof:placetype":"locality",
    "wof:population":340
},
  "geometry": {"coordinates":[39.35278,36.93417],"type":"Point"}
}