{
  "type": "Feature",
  "properties": {
    "gn:admin1_code":"5.0",
    "gn:asciiname":"Kapikaya",
    "gn:country_code":"TR",
    "gn:dem":414,
    "gn:feature_class":"P",
    "gn:feature_code":"PPL",
    "gn:name":"Kap\u0131kaya",
    "gn:population":0,
    "gn:timezone":"Europe/Istanbul",
    "iso:country":"TR",
    "name:und_x_variant":[
        "Kapukaya K\u00f6y\u00fc",
        "Kapukaya",
        "Kap\u0131kaya"
    ],
    "wof:name":"Kapikaya",
    "wof:placetype":"locality"
},
  "geometry": {"coordinates":[35.79339,40.58336],"type":"Point"}
}