{
  "type": "Feature",
  "properties": {
    "gn:admin1_code":"59.0",
    "gn:asciiname":"Dogankoy",
    "gn:country_code":"TR",
    "gn:dem":239,
    "gn:feature_class":"P",
    "gn:feature_code":"PPL",
    "gn:name":"Do\u011fank\u00f6y",
    "gn:population":0,
    "gn:timezone":"Europe/Istanbul",
    "iso:country":"TR",
    "name:tur_x_preferred":[
        "Do\u011fanlar"
    ],
    "name:und_x_variant":[
        "Do\u011fank\u00f6y"
    ],
    "wof:name":"Dogankoy",
    "wof:placetype":"locality"
},
  "geometry": {"coordinates":[26.83832,41.07491],"type":"Point"}
}