{
  "type": "Feature",
  "properties": {
    "gn:admin1_code":"26",
    "gn:asciiname":"Belkese",
    "gn:country_code":"TR",
    "gn:dem":1230,
    "gn:feature_class":"P",
    "gn:feature_code":"PPL",
    "gn:name":"Belkese",
    "gn:population":0,
    "gn:timezone":"Europe/Istanbul",
    "iso:country":"TR",
    "wof:name":"Belkese",
    "wof:placetype":"locality"
},
  "geometry": {"coordinates":[30.98903,40.00023],"type":"Point"}
}