{
  "type": "Feature",
  "properties": {
    "gn:admin1_code":"35",
    "gn:asciiname":"Gedik",
    "gn:country_code":"TR",
    "gn:dem":474,
    "gn:feature_class":"P",
    "gn:feature_code":"PPL",
    "gn:name":"Gedik",
    "gn:population":0,
    "gn:timezone":"Europe/Istanbul",
    "iso:country":"TR",
    "name:tur_x_preferred":[
        "Gedik"
    ],
    "wof:name":"Gedik",
    "wof:placetype":"locality"
},
  "geometry": {"coordinates":[28.15055,38.23777000000001],"type":"Point"}
}