{
  "type": "Feature",
  "properties": {
    "gn:admin1_code":"81.0",
    "gn:asciiname":"Salmanli",
    "gn:country_code":"TR",
    "gn:dem":798,
    "gn:feature_class":"P",
    "gn:feature_code":"PPL",
    "gn:name":"Salmanl\u0131",
    "gn:population":0,
    "gn:timezone":"Europe/Istanbul",
    "iso:country":"TR",
    "wof:name":"Salmanli",
    "wof:placetype":"locality"
},
  "geometry": {"coordinates":[35.66103,37.60144],"type":"Point"}
}