{
  "type": "Feature",
  "properties": {
    "gn:admin1_code":"45",
    "gn:asciiname":"Develi",
    "gn:country_code":"TR",
    "gn:dem":61,
    "gn:feature_class":"P",
    "gn:feature_code":"PPL",
    "gn:name":"Develi",
    "gn:population":0,
    "gn:timezone":"Europe/Istanbul",
    "iso:country":"TR",
    "name:ceb_x_preferred":[
        "Develi"
    ],
    "name:deu_x_preferred":[
        "Develi"
    ],
    "name:epo_x_preferred":[
        "Develi"
    ],
    "name:fas_x_preferred":[
        "\u062f\u0648\u0644\u06cc"
    ],
    "name:fra_x_preferred":[
        "Develi"
    ],
    "name:gag_x_preferred":[
        "Develi"
    ],
    "name:min_x_preferred":[
        "Develi"
    ],
    "name:mrj_x_preferred":[
        "\u0414\u0435\u0432\u0435\u043b\u0438"
    ],
    "name:msa_x_preferred":[
        "Develi"
    ],
    "name:nld_x_preferred":[
        "Develi"
    ],
    "name:nno_x_preferred":[
        "Develi"
    ],
    "name:nor_x_preferred":[
        "Develi"
    ],
    "name:pnb_x_preferred":[
        "\u0636\u0644\u0639 \u062f\u06cc\u0648\u0648\u0644\u06cc"
    ],
    "name:pol_x_preferred":[
        "Develi"
    ],
    "name:ron_x_preferred":[
        "Develi"
    ],
    "name:swa_x_preferred":[
        "Develi"
    ],
    "name:tur_x_preferred":[
        "Develi"
    ],
    "name:und_x_variant":[
        "Hocal\u0131k\u00f6y",
        "Hocal\u0131"
    ],
    "name:urd_x_preferred":[
        "\u062f\u06cc\u0648\u06cc\u0644\u06cc"
    ],
    "name:vie_x_preferred":[
        "Develi"
    ],
    "name:zho_x_preferred":[
        "\u4ee3\u97e6\u5229"
    ],
    "wof:name":"Develi",
    "wof:placetype":"locality"
},
  "geometry": {"coordinates":[27.63511,38.70196],"type":"Point"}
}