{
  "type": "Feature",
  "properties": {
    "gn:admin1_code":"45",
    "gn:asciiname":"Develi",
    "gn:country_code":"TR",
    "gn:dem":61,
    "gn:feature_class":"P",
    "gn:feature_code":"PPL",
    "gn:name":"Develi",
    "gn:population":0,
    "gn:timezone":"Europe/Istanbul",
    "iso:country":"TR",
    "name:tur_x_preferred":[
        "Develi"
    ],
    "name:und_x_variant":[
        "Hocal\u0131k\u00f6y",
        "Hocal\u0131"
    ],
    "wof:name":"Develi",
    "wof:placetype":"locality"
},
  "geometry": {"coordinates":[27.63511,38.70196],"type":"Point"}
}