{
  "type": "Feature",
  "properties": {
    "gn:admin1_code":"58",
    "gn:asciiname":"Ikizbasak",
    "gn:country_code":"TR",
    "gn:dem":1134,
    "gn:feature_class":"P",
    "gn:feature_code":"PPL",
    "gn:name":"\u0130kizba\u015fak",
    "gn:population":0,
    "gn:timezone":"Europe/Istanbul",
    "iso:country":"TR",
    "name:und_x_variant":[
        "Fazl\u0131o\u011flu \u00c7iftli\u011fi",
        "Faz\u0131lo\u011flu",
        "Fazl\u0131o\u011flu",
        "\u0130kizba\u015fak"
    ],
    "wof:name":"Ikizbasak",
    "wof:placetype":"locality"
},
  "geometry": {"coordinates":[38.17525,39.28754],"type":"Point"}
}