{
  "type": "Feature",
  "properties": {
    "gn:admin1_code":"92",
    "gn:asciiname":"Cavuscift",
    "gn:country_code":"TR",
    "gn:dem":49,
    "gn:feature_class":"P",
    "gn:feature_code":"PPL",
    "gn:name":"\u00c7avu\u015f\u00e7ift",
    "gn:population":0,
    "gn:timezone":"Europe/Istanbul",
    "iso:country":"TR",
    "name:tur_x_preferred":[
        "\u00c7avu\u015f\u00e7ift"
    ],
    "wof:name":"Cavuscift",
    "wof:placetype":"locality"
},
  "geometry": {"coordinates":[29.47779,40.68653],"type":"Point"}
}