{
  "type": "Feature",
  "properties": {
    "gn:admin1_code":"13",
    "gn:asciiname":"Arpaliseki",
    "gn:country_code":"TR",
    "gn:dem":1312,
    "gn:feature_class":"P",
    "gn:feature_code":"PPL",
    "gn:name":"Arpal\u0131seki",
    "gn:population":0,
    "gn:timezone":"Europe/Istanbul",
    "iso:country":"TR",
    "name:tur_x_preferred":[
        "Arpal\u0131seki"
    ],
    "name:und_x_variant":[
        "Pi\u00e7onk",
        "Pi\u00e7ank",
        "Pi\u00e7unk"
    ],
    "wof:name":"Arpaliseki",
    "wof:placetype":"locality"
},
  "geometry": {"coordinates":[41.79904000000001,38.49682],"type":"Point"}
}