{
  "type": "Feature",
  "properties": {
    "gn:admin1_code":"80.0",
    "gn:asciiname":"Mermistin",
    "gn:country_code":"TR",
    "gn:dem":642,
    "gn:feature_class":"P",
    "gn:feature_code":"PPL",
    "gn:name":"Mermi\u015ftin",
    "gn:population":0,
    "gn:timezone":"Europe/Istanbul",
    "iso:country":"TR",
    "name:tur_x_preferred":[
        "Mermi\u015ftin"
    ],
    "wof:name":"Mermistin",
    "wof:placetype":"locality"
},
  "geometry": {"coordinates":[42.23111,37.35972],"type":"Point"}
}