{
  "type": "Feature",
  "properties": {
    "gn:admin1_code":"16.0",
    "gn:asciiname":"Kayapa",
    "gn:country_code":"TR",
    "gn:dem":176,
    "gn:feature_class":"P",
    "gn:feature_code":"PPL",
    "gn:name":"Kayapa",
    "gn:population":0,
    "gn:timezone":"Europe/Istanbul",
    "iso:country":"TR",
    "name:tur_x_preferred":[
        "Kayapa"
    ],
    "wof:name":"Kayapa",
    "wof:placetype":"locality"
},
  "geometry": {"coordinates":[28.83945,40.17179],"type":"Point"}
}