{
  "type": "Feature",
  "properties": {
    "gn:admin1_code":"21",
    "gn:asciiname":"Okurkoy",
    "gn:country_code":"TR",
    "gn:dem":864,
    "gn:feature_class":"P",
    "gn:feature_code":"PPL",
    "gn:name":"Okurk\u00f6y",
    "gn:population":0,
    "gn:timezone":"Europe/Istanbul",
    "iso:country":"TR",
    "name:tur_x_preferred":[
        "Okurk\u00f6y"
    ],
    "name:und_x_variant":[
        "Okur",
        "Cevzi"
    ],
    "wof:name":"Okurkoy",
    "wof:placetype":"locality"
},
  "geometry": {"coordinates":[40.37891,38.37785],"type":"Point"}
}