{
  "type": "Feature",
  "properties": {
    "gn:admin1_code":"80",
    "gn:asciiname":"Bulmuslar",
    "gn:country_code":"TR",
    "gn:dem":1071,
    "gn:feature_class":"P",
    "gn:feature_code":"PPL",
    "gn:name":"Bulmu\u015flar",
    "gn:population":0,
    "gn:timezone":"Europe/Istanbul",
    "iso:country":"TR",
    "name:und_x_variant":[
        "Khurs",
        "Hors",
        "Fyndyk",
        "Horsan",
        "Hur\u015f",
        "Hurs",
        "Bulmu\u015flar"
    ],
    "wof:name":"Bulmuslar",
    "wof:placetype":"locality"
},
  "geometry": {"coordinates":[42.03795,37.56365],"type":"Point"}
}