{
  "type": "Feature",
  "properties": {
    "gn:admin1_code":"61.0",
    "gn:asciiname":"Gurbulak",
    "gn:country_code":"TR",
    "gn:dem":319,
    "gn:feature_class":"P",
    "gn:feature_code":"PPL",
    "gn:name":"G\u00fcrbulak",
    "gn:population":0,
    "gn:timezone":"Europe/Istanbul",
    "iso:country":"TR",
    "name:tur_x_preferred":[
        "G\u00fcrbulak"
    ],
    "wof:name":"Gurbulak",
    "wof:placetype":"locality"
},
  "geometry": {"coordinates":[39.62648,40.96389],"type":"Point"}
}