{
  "type": "Feature",
  "properties": {
    "gn:admin1_code":"07",
    "gn:asciiname":"Kayaburnu",
    "gn:country_code":"TR",
    "gn:dem":30,
    "gn:feature_class":"P",
    "gn:feature_code":"PPL",
    "gn:name":"Kayaburnu",
    "gn:population":0,
    "gn:timezone":"Europe/Istanbul",
    "iso:country":"TR",
    "wof:name":"Kayaburnu",
    "wof:placetype":"locality"
},
  "geometry": {"coordinates":[31.01533,36.93336],"type":"Point"}
}