{
  "type": "Feature",
  "properties": {
    "gn:admin1_code":"24",
    "gn:asciiname":"Yesilcat",
    "gn:country_code":"TR",
    "gn:dem":1366,
    "gn:feature_class":"P",
    "gn:feature_code":"PPL",
    "gn:name":"Ye\u015fil\u00e7at",
    "gn:population":0,
    "gn:timezone":"Europe/Istanbul",
    "iso:country":"TR",
    "name:und_x_variant":[
        "Ye\u015fil\u00e7at",
        "\u00c7erme"
    ],
    "wof:name":"Yesilcat",
    "wof:placetype":"locality"
},
  "geometry": {"coordinates":[39.33421,39.79898],"type":"Point"}
}