{
  "type": "Feature",
  "properties": {
    "gn:admin1_code":"04",
    "gn:asciiname":"Guvenli",
    "gn:country_code":"TR",
    "gn:dem":2083,
    "gn:feature_class":"P",
    "gn:feature_code":"PPL",
    "gn:name":"G\u00fcvenli",
    "gn:population":0,
    "gn:timezone":"Europe/Istanbul",
    "iso:country":"TR",
    "name:und_x_variant":[
        "\u015eebo",
        "G\u00fcvenli"
    ],
    "wof:name":"Guvenli",
    "wof:placetype":"locality"
},
  "geometry": {"coordinates":[43.0198,39.88793],"type":"Point"}
}