{
  "type": "Feature",
  "properties": {
    "gn:admin1_code":"16",
    "gn:asciiname":"Baliizir",
    "gn:country_code":"TR",
    "gn:dem":876,
    "gn:feature_class":"P",
    "gn:feature_code":"PPL",
    "gn:name":"B\u00e2liizir",
    "gn:population":0,
    "gn:timezone":"Europe/Istanbul",
    "iso:country":"TR",
    "name:tur_x_preferred":[
        "B\u00e2liizir"
    ],
    "wof:name":"Baliizir",
    "wof:placetype":"locality"
},
  "geometry": {"coordinates":[28.7426,39.85419],"type":"Point"}
}