{
  "type": "Feature",
  "properties": {
    "gn:admin1_code":"54.0",
    "gn:asciiname":"Koyyeri",
    "gn:country_code":"TR",
    "gn:dem":113,
    "gn:feature_class":"P",
    "gn:feature_code":"PPL",
    "gn:name":"K\u00f6yyeri",
    "gn:population":0,
    "gn:timezone":"Europe/Istanbul",
    "iso:country":"TR",
    "name:tur_x_preferred":[
        "K\u00f6yyeri"
    ],
    "wof:name":"Koyyeri",
    "wof:placetype":"locality"
},
  "geometry": {"coordinates":[30.91074,40.97962],"type":"Point"}
}