{
  "type": "Feature",
  "properties": {
    "gn:admin1_code":"23.0",
    "gn:asciiname":"Yumakli",
    "gn:country_code":"TR",
    "gn:dem":1416,
    "gn:feature_class":"P",
    "gn:feature_code":"PPL",
    "gn:name":"Yumakl\u0131",
    "gn:population":0,
    "gn:timezone":"Europe/Istanbul",
    "iso:country":"TR",
    "name:tur_x_preferred":[
        "Yumakl\u0131"
    ],
    "wof:name":"Yumakli",
    "wof:placetype":"locality"
},
  "geometry": {"coordinates":[40.35226,38.75766],"type":"Point"}
}