{
  "type": "Feature",
  "properties": {
    "gn:admin1_code":"07",
    "gn:asciiname":"Sahinler",
    "gn:country_code":"TR",
    "gn:dem":466,
    "gn:feature_class":"P",
    "gn:feature_code":"PPL",
    "gn:name":"\u015eahinler",
    "gn:population":0,
    "gn:timezone":"Europe/Istanbul",
    "iso:country":"TR",
    "name:tur_x_preferred":[
        "\u015eahinler"
    ],
    "name:tur_x_variant":[
        "Sahinler"
    ],
    "wof:name":"Sahinler",
    "wof:placetype":"locality"
},
  "geometry": {"coordinates":[32.43187,36.42118],"type":"Point"}
}