{
  "type": "Feature",
  "properties": {
    "gn:admin1_code":"8.0",
    "gn:asciiname":"Senocak",
    "gn:country_code":"TR",
    "gn:dem":1432,
    "gn:feature_class":"P",
    "gn:feature_code":"PPL",
    "gn:name":"\u015eenocak",
    "gn:population":0,
    "gn:timezone":"Europe/Istanbul",
    "iso:country":"TR",
    "name:tur_x_preferred":[
        "\u015eenocak"
    ],
    "wof:name":"Senocak",
    "wof:placetype":"locality"
},
  "geometry": {"coordinates":[42.28474,41.32456],"type":"Point"}
}