{
  "type": "Feature",
  "properties": {
    "gn:admin1_code":"12",
    "gn:asciiname":"Cevizli",
    "gn:country_code":"TR",
    "gn:dem":1568,
    "gn:feature_class":"P",
    "gn:feature_code":"PPL",
    "gn:name":"Cevizli",
    "gn:population":0,
    "gn:timezone":"Europe/Istanbul",
    "iso:country":"TR",
    "name:tur_x_preferred":[
        "Cevizli"
    ],
    "name:und_x_variant":[
        "\u00c7evizli",
        "Pertek"
    ],
    "wof:name":"Cevizli",
    "wof:placetype":"locality"
},
  "geometry": {"coordinates":[40.44355,39.31695],"type":"Point"}
}