{
  "type": "Feature",
  "properties": {
    "gn:admin1_code":"75",
    "gn:asciiname":"Oymaagac",
    "gn:country_code":"TR",
    "gn:dem":1297,
    "gn:feature_class":"P",
    "gn:feature_code":"PPL",
    "gn:name":"Oymaa\u011fa\u00e7",
    "gn:population":0,
    "gn:timezone":"Europe/Istanbul",
    "iso:country":"TR",
    "wof:name":"Oymaagac",
    "wof:placetype":"locality"
},
  "geometry": {"coordinates":[33.86562,38.71631],"type":"Point"}
}