{
  "type": "Feature",
  "properties": {
    "gn:admin1_code":"58.0",
    "gn:asciiname":"Bahceliyurt",
    "gn:country_code":"TR",
    "gn:dem":1913,
    "gn:feature_class":"P",
    "gn:feature_code":"PPL",
    "gn:name":"Bah\u00e7eliyurt",
    "gn:population":0,
    "gn:timezone":"Europe/Istanbul",
    "iso:country":"TR",
    "wof:name":"Bahceliyurt",
    "wof:placetype":"locality"
},
  "geometry": {"coordinates":[37.84687,39.19929000000001],"type":"Point"}
}