{
  "type": "Feature",
  "properties": {
    "gn:admin1_code":"44",
    "gn:asciiname":"Sugecti",
    "gn:cc2":"TR",
    "gn:country_code":"TR",
    "gn:dem":1615,
    "gn:feature_class":"P",
    "gn:feature_code":"PPL",
    "gn:name":"Suge\u00e7ti",
    "gn:population":0,
    "gn:timezone":"Europe/Istanbul",
    "iso:country":"TR",
    "name:und_x_variant":[
        "Arhut",
        "Arhud",
        "Suge\u00e7ti"
    ],
    "wof:name":"Sugecti",
    "wof:placetype":"locality"
},
  "geometry": {"coordinates":[38.26667,39.03333],"type":"Point"}
}