{
  "type": "Feature",
  "properties": {
    "gn:admin1_code":"19",
    "gn:asciiname":"Cevizli",
    "gn:country_code":"TR",
    "gn:dem":845,
    "gn:feature_class":"P",
    "gn:feature_code":"PPL",
    "gn:name":"Cevizli",
    "gn:population":0,
    "gn:timezone":"Europe/Istanbul",
    "iso:country":"TR",
    "name:deu_x_preferred":[
        "Cevizli"
    ],
    "name:tur_x_preferred":[
        "Cevizli"
    ],
    "wof:name":"Cevizli",
    "wof:placetype":"locality"
},
  "geometry": {"coordinates":[34.23693,40.6792],"type":"Point"}
}