{
  "type": "Feature",
  "properties": {
    "gn:admin1_code":"09",
    "gn:asciiname":"Bocekkoy",
    "gn:country_code":"TR",
    "gn:dem":156,
    "gn:feature_class":"P",
    "gn:feature_code":"PPL",
    "gn:name":"B\u00f6cekk\u00f6y",
    "gn:population":0,
    "gn:timezone":"Europe/Istanbul",
    "iso:country":"TR",
    "name:ceb_x_preferred":[
        "B\u00f6cekk\u00f6y"
    ],
    "name:msa_x_preferred":[
        "B\u00f6cek"
    ],
    "name:tur_x_preferred":[
        "B\u00f6cekk\u00f6y"
    ],
    "wof:name":"Bocekkoy",
    "wof:placetype":"locality"
},
  "geometry": {"coordinates":[27.9016,37.72932],"type":"Point"}
}