{
  "type": "Feature",
  "properties": {
    "iso:country":"TR",
    "name:eng_x_preferred":[
        "Omerli"
    ],
    "name:tur_x_preferred":[
        "\u00d6merli"
    ],
    "wof:name":"Omerli",
    "wof:placetype":"neighbourhood"
},
  "geometry": {"coordinates":[29.32891165144749,41.077647736873],"type":"Point"}
}