{
  "type": "Feature",
  "properties": {
    "gn:admin1_code":"39.0",
    "gn:asciiname":"Sakizkoy",
    "gn:country_code":"TR",
    "gn:dem":96,
    "gn:feature_class":"P",
    "gn:feature_code":"PPL",
    "gn:name":"Sak\u0131zk\u00f6y",
    "gn:population":0,
    "gn:timezone":"Europe/Istanbul",
    "iso:country":"TR",
    "name:und_x_variant":[
        "Sak\u0131zk\u00f6y",
        "Sak\u0131z"
    ],
    "wof:name":"Sakizkoy",
    "wof:placetype":"locality"
},
  "geometry": {"coordinates":[27.47417,41.44028],"type":"Point"}
}