{
  "type": "Feature",
  "properties": {
    "gn:admin1_code":"21.0",
    "gn:asciiname":"Agachan",
    "gn:country_code":"TR",
    "gn:dem":911,
    "gn:feature_class":"P",
    "gn:feature_code":"PPL",
    "gn:name":"A\u011fa\u00e7han",
    "gn:population":0,
    "gn:timezone":"Europe/Istanbul",
    "iso:country":"TR",
    "name:und_x_variant":[
        "A\u011fa\u00e7han K\u00f6y\u00fc",
        "A\u011fa\u00e7han"
    ],
    "wof:name":"Agachan",
    "wof:placetype":"locality"
},
  "geometry": {"coordinates":[39.33091,37.97207],"type":"Point"}
}