{
  "type": "Feature",
  "properties": {
    "gn:admin1_code":"52.0",
    "gn:asciiname":"Pelitli",
    "gn:country_code":"TR",
    "gn:dem":759,
    "gn:feature_class":"P",
    "gn:feature_code":"PPL",
    "gn:name":"Pelitli",
    "gn:population":0,
    "gn:timezone":"Europe/Istanbul",
    "iso:country":"TR",
    "name:azb_x_preferred":[
        "\u067e\u0626\u0644\u06cc\u062a\u0644\u06cc"
    ],
    "name:ceb_x_preferred":[
        "Pelitli"
    ],
    "name:fas_x_preferred":[
        "\u067e\u0644\u06cc\u062a\u0644\u06cc"
    ],
    "name:nno_x_preferred":[
        "Pelitli"
    ],
    "name:tur_x_preferred":[
        "Pelitli"
    ],
    "name:urd_x_preferred":[
        "\u067e\u0644\u06cc\u062a\u0644\u06cc"
    ],
    "name:vie_x_preferred":[
        "Pelitli"
    ],
    "name:zho_x_preferred":[
        "\u4f69\u5229\u7279\u5229"
    ],
    "wof:name":"Pelitli",
    "wof:placetype":"locality"
},
  "geometry": {"coordinates":[37.98256,40.77076],"type":"Point"}
}