{
  "type": "Feature",
  "properties": {
    "gn:admin1_code":"52.0",
    "gn:asciiname":"Pelitli",
    "gn:country_code":"TR",
    "gn:dem":759,
    "gn:feature_class":"P",
    "gn:feature_code":"PPL",
    "gn:name":"Pelitli",
    "gn:population":0,
    "gn:timezone":"Europe/Istanbul",
    "iso:country":"TR",
    "name:tur_x_preferred":[
        "Pelitli"
    ],
    "wof:name":"Pelitli",
    "wof:placetype":"locality"
},
  "geometry": {"coordinates":[37.98256,40.77076],"type":"Point"}
}