{
  "type": "Feature",
  "properties": {
    "gn:admin1_code":"80",
    "gn:asciiname":"Evrek",
    "gn:country_code":"TR",
    "gn:dem":1986,
    "gn:feature_class":"P",
    "gn:feature_code":"PPL",
    "gn:name":"Evrek",
    "gn:population":0,
    "gn:timezone":"Europe/Istanbul",
    "iso:country":"TR",
    "name:und_x_variant":[
        "Everek",
        "G\u00f6k\u00e7e"
    ],
    "wof:name":"Evrek",
    "wof:placetype":"locality"
},
  "geometry": {"coordinates":[43.22291,37.65139],"type":"Point"}
}