{
  "type": "Feature",
  "properties": {
    "gn:admin1_code":"52.0",
    "gn:asciiname":"Egrisu Yaylasi",
    "gn:cc2":"TR",
    "gn:country_code":"TR",
    "gn:dem":1429,
    "gn:feature_class":"P",
    "gn:feature_code":"PPL",
    "gn:name":"E\u011frisu Yaylas\u0131",
    "gn:population":0,
    "gn:timezone":"Europe/Istanbul",
    "iso:country":"TR",
    "name:und_x_variant":[
        "E\u011fnea\u011fz\u0131",
        "E\u011frisu Yaylas\u0131"
    ],
    "wof:name":"Egrisu Yaylasi",
    "wof:placetype":"locality"
},
  "geometry": {"coordinates":[37.25,40.68333],"type":"Point"}
}