{
  "type": "Feature",
  "properties": {
    "gn:admin1_code":"61.0",
    "gn:asciiname":"Ishakli",
    "gn:country_code":"TR",
    "gn:dem":622,
    "gn:feature_class":"P",
    "gn:feature_code":"PPL",
    "gn:name":"\u0130shakl\u0131",
    "gn:population":0,
    "gn:timezone":"Europe/Istanbul",
    "iso:country":"TR",
    "name:tur_x_preferred":[
        "\u0130shakl\u0131"
    ],
    "wof:name":"Ishakli",
    "wof:placetype":"locality"
},
  "geometry": {"coordinates":[39.2952,40.98972],"type":"Point"}
}