{
  "type": "Feature",
  "properties": {
    "gn:admin1_code":"58",
    "gn:asciiname":"Herekli",
    "gn:country_code":"TR",
    "gn:dem":1407,
    "gn:feature_class":"P",
    "gn:feature_code":"PPL",
    "gn:name":"Herekli",
    "gn:population":0,
    "gn:timezone":"Europe/Istanbul",
    "iso:country":"TR",
    "name:und_x_variant":[
        "Harekli",
        "Herekli"
    ],
    "wof:name":"Herekli",
    "wof:placetype":"locality"
},
  "geometry": {"coordinates":[36.82389000000001,39.62101],"type":"Point"}
}