{
  "type": "Feature",
  "properties": {
    "gn:admin1_code":"09",
    "gn:asciiname":"Bagarcik",
    "gn:country_code":"TR",
    "gn:dem":605,
    "gn:feature_class":"P",
    "gn:feature_code":"PPL",
    "gn:name":"Ba\u011farc\u0131k",
    "gn:population":0,
    "gn:timezone":"Europe/Istanbul",
    "iso:country":"TR",
    "name:und_x_variant":[
        "Ba\u011fac\u0131k",
        "Ba\u011farc\u0131k"
    ],
    "wof:name":"Bagarcik",
    "wof:placetype":"locality"
},
  "geometry": {"coordinates":[27.63951,37.54493],"type":"Point"}
}