{
  "type": "Feature",
  "properties": {
    "gn:admin1_code":"68.0",
    "gn:asciiname":"Menceler",
    "gn:country_code":"TR",
    "gn:dem":1345,
    "gn:feature_class":"P",
    "gn:feature_code":"PPL",
    "gn:name":"Men\u00e7eler",
    "gn:population":0,
    "gn:timezone":"Europe/Istanbul",
    "iso:country":"TR",
    "wof:name":"Menceler",
    "wof:placetype":"locality"
},
  "geometry": {"coordinates":[31.86932,40.27304],"type":"Point"}
}