{
  "type": "Feature",
  "properties": {
    "gn:admin1_code":"64",
    "gn:asciiname":"Sevindikler",
    "gn:country_code":"TR",
    "gn:dem":847,
    "gn:feature_class":"P",
    "gn:feature_code":"PPL",
    "gn:name":"Sevindikler",
    "gn:population":0,
    "gn:timezone":"Europe/Istanbul",
    "iso:country":"TR",
    "name:tur_x_preferred":[
        "Sevindikler"
    ],
    "wof:name":"Sevindikler",
    "wof:placetype":"locality"
},
  "geometry": {"coordinates":[29.34545,38.50055],"type":"Point"}
}