{
  "type": "Feature",
  "properties": {
    "gn:admin1_code":"89",
    "gn:asciiname":"Cavuslar",
    "gn:country_code":"TR",
    "gn:dem":652,
    "gn:feature_class":"P",
    "gn:feature_code":"PPL",
    "gn:name":"\u00c7avu\u015flar",
    "gn:population":0,
    "gn:timezone":"Europe/Istanbul",
    "iso:country":"TR",
    "wof:name":"Cavuslar",
    "wof:placetype":"locality"
},
  "geometry": {"coordinates":[32.55215,40.99965],"type":"Point"}
}