{
  "type": "Feature",
  "properties": {
    "gn:admin1_code":"4.0",
    "gn:asciiname":"Kazanbey",
    "gn:country_code":"TR",
    "gn:dem":1802,
    "gn:feature_class":"P",
    "gn:feature_code":"PPL",
    "gn:name":"Kazanbey",
    "gn:population":0,
    "gn:timezone":"Europe/Istanbul",
    "iso:country":"TR",
    "name:tur_x_preferred":[
        "Kazan"
    ],
    "name:tur_x_variant":[
        "Kazanbey"
    ],
    "wof:name":"Kazanbey",
    "wof:placetype":"locality"
},
  "geometry": {"coordinates":[42.89384,39.07036],"type":"Point"}
}