{
  "type": "Feature",
  "properties": {
    "gn:admin1_code":"84.0",
    "gn:asciiname":"Ucboluk",
    "gn:country_code":"TR",
    "gn:dem":1502,
    "gn:feature_class":"P",
    "gn:feature_code":"PPL",
    "gn:name":"\u00dc\u00e7b\u00f6l\u00fck",
    "gn:population":0,
    "gn:timezone":"Europe/Istanbul",
    "iso:country":"TR",
    "name:tur_x_preferred":[
        "\u00dc\u00e7b\u00f6l\u00fck"
    ],
    "wof:name":"Ucboluk",
    "wof:placetype":"locality"
},
  "geometry": {"coordinates":[43.52535,40.47859],"type":"Point"}
}