{
  "type": "Feature",
  "properties": {
    "gn:admin1_code":"80.0",
    "gn:asciiname":"Batus",
    "gn:country_code":"TR",
    "gn:dem":576,
    "gn:feature_class":"P",
    "gn:feature_code":"PPL",
    "gn:name":"Batus",
    "gn:population":0,
    "gn:timezone":"Europe/Istanbul",
    "iso:country":"TR",
    "name:tur_x_preferred":[
        "Batus"
    ],
    "wof:name":"Batus",
    "wof:placetype":"locality"
},
  "geometry": {"coordinates":[42.17335,37.37345],"type":"Point"}
}