{
  "type": "Feature",
  "properties": {
    "gn:admin1_code":"39.0",
    "gn:asciiname":"Balaban",
    "gn:cc2":"TR",
    "gn:country_code":"TR",
    "gn:dem":468,
    "gn:feature_class":"P",
    "gn:feature_code":"PPL",
    "gn:name":"Balaban",
    "gn:population":0,
    "gn:timezone":"Europe/Istanbul",
    "iso:country":"TR",
    "name:und_x_variant":[
        "Velika",
        "Balaban"
    ],
    "wof:name":"Balaban",
    "wof:placetype":"locality"
},
  "geometry": {"coordinates":[27.67576,41.83748],"type":"Point"}
}