{
  "type": "Feature",
  "properties": {
    "gn:admin1_code":"54",
    "gn:asciiname":"Altindere",
    "gn:country_code":"TR",
    "gn:dem":48,
    "gn:feature_class":"P",
    "gn:feature_code":"PPL",
    "gn:name":"Alt\u0131ndere",
    "gn:population":0,
    "gn:timezone":"Europe/Istanbul",
    "iso:country":"TR",
    "name:tur_x_preferred":[
        "Alt\u0131ndere"
    ],
    "wof:name":"Altindere",
    "wof:placetype":"locality"
},
  "geometry": {"coordinates":[30.69672000000001,40.68937],"type":"Point"}
}