{
  "type": "Feature",
  "properties": {
    "gn:admin1_code":"63",
    "gn:asciiname":"Yarimtepe",
    "gn:country_code":"TR",
    "gn:dem":653,
    "gn:feature_class":"P",
    "gn:feature_code":"PPL",
    "gn:name":"Yar\u0131mtepe",
    "gn:population":0,
    "gn:timezone":"Europe/Istanbul",
    "iso:country":"TR",
    "name:tur_x_preferred":[
        "Yar\u0131mtepe"
    ],
    "name:und_x_variant":[
        "Yarymtepe"
    ],
    "wof:name":"Yarimtepe",
    "wof:placetype":"locality"
},
  "geometry": {"coordinates":[38.73625,37.29941],"type":"Point"}
}