{
  "type": "Feature",
  "properties": {
    "gn:admin1_code":"72.0",
    "gn:asciiname":"Asagi Cesme",
    "gn:country_code":"TR",
    "gn:dem":1183,
    "gn:feature_class":"P",
    "gn:feature_code":"PPL",
    "gn:name":"A\u015fa\u011f\u0131 \u00c7e\u015fme",
    "gn:population":0,
    "gn:timezone":"Europe/Istanbul",
    "iso:country":"TR",
    "name:tur_x_preferred":[
        "A\u015fa\u011f\u0131 \u00c7e\u015fme"
    ],
    "wof:name":"Asagi Cesme",
    "wof:placetype":"locality"
},
  "geometry": {"coordinates":[40.57888,37.39399],"type":"Point"}
}