{
  "type": "Feature",
  "properties": {
    "gn:admin1_code":"25",
    "gn:asciiname":"Kepenek",
    "gn:country_code":"TR",
    "gn:dem":1928,
    "gn:feature_class":"P",
    "gn:feature_code":"PPL",
    "gn:name":"Kepenek",
    "gn:population":0,
    "gn:timezone":"Europe/Istanbul",
    "iso:country":"TR",
    "name:tur_x_preferred":[
        "Kepenek"
    ],
    "wof:name":"Kepenek",
    "wof:placetype":"locality"
},
  "geometry": {"coordinates":[42.15,39.89067],"type":"Point"}
}