{
  "type": "Feature",
  "properties": {
    "gn:admin1_code":"80.0",
    "gn:asciiname":"Yarimca",
    "gn:country_code":"TR",
    "gn:dem":702,
    "gn:feature_class":"P",
    "gn:feature_code":"PPL",
    "gn:name":"Yar\u0131mca",
    "gn:population":0,
    "gn:timezone":"Europe/Istanbul",
    "iso:country":"TR",
    "name:tur_x_preferred":[
        "Yar\u0131mca"
    ],
    "wof:name":"Yarimca",
    "wof:placetype":"locality"
},
  "geometry": {"coordinates":[42.0201,37.49242],"type":"Point"}
}