{
  "type": "Feature",
  "properties": {
    "gn:admin1_code":"66",
    "gn:asciiname":"Koseyusuflu",
    "gn:country_code":"TR",
    "gn:dem":1201,
    "gn:feature_class":"P",
    "gn:feature_code":"PPL",
    "gn:name":"K\u00f6seyusuflu",
    "gn:population":0,
    "gn:timezone":"Europe/Istanbul",
    "iso:country":"TR",
    "name:und_x_variant":[
        "K\u00f6seyuflu",
        "K\u00f6seyusuflu"
    ],
    "wof:name":"Koseyusuflu",
    "wof:placetype":"locality"
},
  "geometry": {"coordinates":[34.69222,39.78007],"type":"Point"}
}