{
  "type": "Feature",
  "properties": {
    "gn:admin1_code":"93",
    "gn:asciiname":"Kiliseyani",
    "gn:country_code":"TR",
    "gn:dem":1059,
    "gn:feature_class":"P",
    "gn:feature_code":"PPL",
    "gn:name":"Kiliseyan\u0131",
    "gn:population":0,
    "gn:timezone":"Europe/Istanbul",
    "iso:country":"TR",
    "wof:name":"Kiliseyani",
    "wof:placetype":"locality"
},
  "geometry": {"coordinates":[31.46542,40.903],"type":"Point"}
}