{
  "type": "Feature",
  "properties": {
    "gn:admin1_code":"65",
    "gn:asciiname":"Ezik",
    "gn:country_code":"TR",
    "gn:dem":2102,
    "gn:feature_class":"P",
    "gn:feature_code":"PPL",
    "gn:name":"Ezik",
    "gn:population":0,
    "gn:timezone":"Europe/Istanbul",
    "iso:country":"TR",
    "name:tur_x_preferred":[
        "A\u015fa\u011f\u0131 \u00c7\u00f6kek"
    ],
    "name:und_x_variant":[
        "A\u015fa\u011f\u0131\u00e7\u00f6kek"
    ],
    "wof:name":"Ezik",
    "wof:placetype":"locality"
},
  "geometry": {"coordinates":[43.44848,39.13093],"type":"Point"}
}