{
  "type": "Feature",
  "properties": {
    "gn:admin1_code":"65",
    "gn:asciiname":"Taslica",
    "gn:country_code":"TR",
    "gn:dem":2318,
    "gn:feature_class":"P",
    "gn:feature_code":"PPL",
    "gn:name":"Ta\u015fl\u0131ca",
    "gn:population":0,
    "gn:timezone":"Europe/Istanbul",
    "iso:country":"TR",
    "name:und_x_variant":[
        "Ak\u00e7ur\u0131",
        "Ta\u015fl\u0131yaz\u0131",
        "Ta\u015fl\u0131ca"
    ],
    "wof:name":"Taslica",
    "wof:placetype":"locality"
},
  "geometry": {"coordinates":[43.53755,38.01681],"type":"Point"}
}