{
  "type": "Feature",
  "properties": {
    "gn:admin1_code":"54.0",
    "gn:asciiname":"Aktefek",
    "gn:country_code":"TR",
    "gn:dem":46,
    "gn:feature_class":"P",
    "gn:feature_code":"PPL",
    "gn:name":"Aktefek",
    "gn:population":0,
    "gn:timezone":"Europe/Istanbul",
    "iso:country":"TR",
    "name:und_x_variant":[
        "Aktepek",
        "Aktefek"
    ],
    "wof:name":"Aktefek",
    "wof:placetype":"locality"
},
  "geometry": {"coordinates":[30.59427,40.90787],"type":"Point"}
}