{
  "type": "Feature",
  "properties": {
    "gn:admin1_code":"02",
    "gn:asciiname":"Kamisli",
    "gn:country_code":"TR",
    "gn:dem":649,
    "gn:feature_class":"P",
    "gn:feature_code":"PPL",
    "gn:name":"Kam\u0131\u015fl\u0131",
    "gn:population":0,
    "gn:timezone":"Europe/Istanbul",
    "iso:country":"TR",
    "name:tur_x_preferred":[
        "Kam\u0131\u015fl\u0131"
    ],
    "wof:name":"Kamisli",
    "wof:placetype":"locality"
},
  "geometry": {"coordinates":[38.53081,37.67241],"type":"Point"}
}