{
  "type": "Feature",
  "properties": {
    "gn:admin1_code":"57.0",
    "gn:asciiname":"Yenimehmetli",
    "gn:country_code":"TR",
    "gn:dem":586,
    "gn:feature_class":"P",
    "gn:feature_code":"PPL",
    "gn:name":"Yenimehmetli",
    "gn:population":0,
    "gn:timezone":"Europe/Istanbul",
    "iso:country":"TR",
    "name:und_x_variant":[
        "Yi\u011frenmehmetli",
        "Yenimehmetli"
    ],
    "wof:name":"Yenimehmetli",
    "wof:placetype":"locality"
},
  "geometry": {"coordinates":[34.77974,41.39583],"type":"Point"}
}