{
  "type": "Feature",
  "properties": {
    "gn:admin1_code":"16.0",
    "gn:asciiname":"Firekli",
    "gn:country_code":"TR",
    "gn:dem":138,
    "gn:feature_class":"P",
    "gn:feature_code":"PPL",
    "gn:name":"Firekli",
    "gn:population":0,
    "gn:timezone":"Europe/Istanbul",
    "iso:country":"TR",
    "name:und_x_variant":[
        "I\u015f\u0131kl\u0131k\u00f6y",
        "I\u015f\u0131kl\u0131"
    ],
    "wof:name":"Firekli",
    "wof:placetype":"locality"
},
  "geometry": {"coordinates":[28.86848,40.35628],"type":"Point"}
}