{
  "type": "Feature",
  "properties": {
    "gn:admin1_code":"13",
    "gn:asciiname":"Calli",
    "gn:country_code":"TR",
    "gn:dem":1645,
    "gn:feature_class":"P",
    "gn:feature_code":"PPL",
    "gn:name":"\u00c7all\u0131",
    "gn:population":0,
    "gn:timezone":"Europe/Istanbul",
    "iso:country":"TR",
    "name:tur_x_preferred":[
        "\u00c7all\u0131"
    ],
    "name:und_x_variant":[
        "Pert\u00fck"
    ],
    "wof:name":"Calli",
    "wof:placetype":"locality"
},
  "geometry": {"coordinates":[41.94645,38.52635],"type":"Point"}
}