{
  "type": "Feature",
  "properties": {
    "gn:admin1_code":"45",
    "gn:asciiname":"Kozluca",
    "gn:country_code":"TR",
    "gn:dem":819,
    "gn:feature_class":"P",
    "gn:feature_code":"PPL",
    "gn:name":"Kozluca",
    "gn:population":0,
    "gn:timezone":"Europe/Istanbul",
    "iso:country":"TR",
    "name:tur_x_preferred":[
        "Kozluca"
    ],
    "wof:name":"Kozluca",
    "wof:placetype":"locality"
},
  "geometry": {"coordinates":[28.48202,38.31892],"type":"Point"}
}