{
  "type": "Feature",
  "properties": {
    "gn:admin1_code":"31",
    "gn:asciiname":"Cardak Yaylasi",
    "gn:country_code":"TR",
    "gn:dem":1322,
    "gn:feature_class":"P",
    "gn:feature_code":"PPL",
    "gn:name":"Cardak Yaylas\u0131",
    "gn:population":0,
    "gn:timezone":"Europe/Istanbul",
    "iso:country":"TR",
    "name:tur_x_preferred":[
        "Cardak Yaylas\u0131"
    ],
    "wof:name":"Cardak Yaylasi",
    "wof:placetype":"locality"
},
  "geometry": {"coordinates":[36.39096,36.84007],"type":"Point"}
}