{
  "type": "Feature",
  "properties": {
    "gn:admin1_code":"11.0",
    "gn:asciiname":"Ogulpasa",
    "gn:country_code":"TR",
    "gn:dem":797,
    "gn:feature_class":"P",
    "gn:feature_code":"PPL",
    "gn:name":"O\u011fulpa\u015fa",
    "gn:population":0,
    "gn:timezone":"Europe/Istanbul",
    "iso:country":"TR",
    "name:tur_x_preferred":[
        "O\u011fulpa\u015fa"
    ],
    "wof:name":"Ogulpasa",
    "wof:placetype":"locality"
},
  "geometry": {"coordinates":[29.88278,40.46281],"type":"Point"}
}