{
  "type": "Feature",
  "properties": {
    "gn:admin1_code":"21",
    "gn:asciiname":"Baglan",
    "gn:country_code":"TR",
    "gn:dem":915,
    "gn:feature_class":"P",
    "gn:feature_code":"PPL",
    "gn:name":"Ba\u011flan",
    "gn:population":0,
    "gn:timezone":"Europe/Istanbul",
    "iso:country":"TR",
    "name:und_x_variant":[
        "Mizak",
        "M\u00fcsrif",
        "Ba\u011flan",
        "M\u00fc\u015fr\u00fcf"
    ],
    "wof:name":"Baglan",
    "wof:placetype":"locality"
},
  "geometry": {"coordinates":[40.7122,38.32921],"type":"Point"}
}