{
  "type": "Feature",
  "properties": {
    "gn:admin1_code":"21",
    "gn:asciiname":"Baglan",
    "gn:country_code":"TR",
    "gn:dem":915,
    "gn:feature_class":"P",
    "gn:feature_code":"PPL",
    "gn:name":"Ba\u011flan",
    "gn:population":0,
    "gn:timezone":"Europe/Istanbul",
    "iso:country":"TR",
    "name:bre_x_preferred":[
        "Baglan"
    ],
    "name:ceb_x_preferred":[
        "Baglan"
    ],
    "name:cor_x_preferred":[
        "Baglan"
    ],
    "name:cym_x_preferred":[
        "Baglan"
    ],
    "name:deu_x_preferred":[
        "Baglan"
    ],
    "name:est_x_preferred":[
        "Baglan"
    ],
    "name:fra_x_preferred":[
        "Baglan"
    ],
    "name:gla_x_preferred":[
        "Baglan"
    ],
    "name:nld_x_preferred":[
        "Baghlan"
    ],
    "name:rus_x_preferred":[
        "\u0411\u0430\u0433\u043b\u0430\u043d"
    ],
    "name:swe_x_preferred":[
        "Baglan"
    ],
    "name:und_x_variant":[
        "Mizak",
        "M\u00fcsrif",
        "Ba\u011flan",
        "M\u00fc\u015fr\u00fcf"
    ],
    "name:uzb_x_preferred":[
        "Bag\u02bblon"
    ],
    "wof:name":"Baglan",
    "wof:placetype":"locality"
},
  "geometry": {"coordinates":[40.7122,38.32921],"type":"Point"}
}