{
  "type": "Feature",
  "properties": {
    "gn:admin1_code":"68.0",
    "gn:asciiname":"Dedeler",
    "gn:country_code":"TR",
    "gn:dem":1180,
    "gn:feature_class":"P",
    "gn:feature_code":"PPL",
    "gn:name":"Dedeler",
    "gn:population":0,
    "gn:timezone":"Europe/Istanbul",
    "iso:country":"TR",
    "name:tur_x_preferred":[
        "Dedeler"
    ],
    "wof:name":"Dedeler",
    "wof:placetype":"locality"
},
  "geometry": {"coordinates":[33.16367,40.28817],"type":"Point"}
}