{
  "type": "Feature",
  "properties": {
    "gn:admin1_code":"80.0",
    "gn:asciiname":"Sisli",
    "gn:country_code":"TR",
    "gn:dem":778,
    "gn:feature_class":"P",
    "gn:feature_code":"PPL",
    "gn:name":"\u015ei\u015fli",
    "gn:population":0,
    "gn:timezone":"Europe/Istanbul",
    "iso:country":"TR",
    "name:tur_x_preferred":[
        "\u015ei\u015fli"
    ],
    "wof:name":"Sisli",
    "wof:placetype":"locality"
},
  "geometry": {"coordinates":[42.12139000000001,37.46278],"type":"Point"}
}