{
  "type": "Feature",
  "properties": {
    "gn:admin1_code":"38.0",
    "gn:asciiname":"Kutuklu",
    "gn:country_code":"TR",
    "gn:dem":1720,
    "gn:feature_class":"P",
    "gn:feature_code":"PPL",
    "gn:name":"K\u00fct\u00fckl\u00fc",
    "gn:population":0,
    "gn:timezone":"Europe/Istanbul",
    "iso:country":"TR",
    "wof:name":"Kutuklu",
    "wof:placetype":"locality"
},
  "geometry": {"coordinates":[36.25514,38.72565],"type":"Point"}
}