{
  "type": "Feature",
  "properties": {
    "gn:admin1_code":"17.0",
    "gn:asciiname":"Camyurt",
    "gn:country_code":"TR",
    "gn:dem":314,
    "gn:feature_class":"P",
    "gn:feature_code":"PPL",
    "gn:name":"\u00c7amyurt",
    "gn:population":0,
    "gn:timezone":"Europe/Istanbul",
    "iso:country":"TR",
    "wof:name":"Camyurt",
    "wof:placetype":"locality"
},
  "geometry": {"coordinates":[26.83971,40.28365],"type":"Point"}
}