{
  "type": "Feature",
  "properties": {
    "gn:admin1_code":"37.0",
    "gn:asciiname":"Halife",
    "gn:country_code":"TR",
    "gn:dem":919,
    "gn:feature_class":"P",
    "gn:feature_code":"PPL",
    "gn:name":"Halife",
    "gn:population":0,
    "gn:timezone":"Europe/Istanbul",
    "iso:country":"TR",
    "wof:name":"Halife",
    "wof:placetype":"locality"
},
  "geometry": {"coordinates":[33.74668,41.514],"type":"Point"}
}