{
  "type": "Feature",
  "properties": {
    "gn:admin1_code":"82",
    "gn:asciiname":"Kukurt",
    "gn:country_code":"TR",
    "gn:dem":1018,
    "gn:feature_class":"P",
    "gn:feature_code":"PPL",
    "gn:name":"K\u00fck\u00fcrt",
    "gn:population":0,
    "gn:timezone":"Europe/Istanbul",
    "iso:country":"TR",
    "wof:name":"Kukurt",
    "wof:placetype":"locality"
},
  "geometry": {"coordinates":[33.07021,40.91667],"type":"Point"}
}