{
  "type": "Feature",
  "properties": {
    "gn:admin1_code":"45",
    "gn:asciiname":"Armagan",
    "gn:country_code":"TR",
    "gn:dem":559,
    "gn:feature_class":"P",
    "gn:feature_code":"PPL",
    "gn:name":"Arma\u011fan",
    "gn:population":0,
    "gn:timezone":"Europe/Istanbul",
    "iso:country":"TR",
    "name:tur_x_preferred":[
        "Arma\u011fan"
    ],
    "wof:name":"Armagan",
    "wof:placetype":"locality"
},
  "geometry": {"coordinates":[28.53768,38.73296],"type":"Point"}
}