{
  "type": "Feature",
  "properties": {
    "gn:admin1_code":"54",
    "gn:asciiname":"Ugurlu",
    "gn:country_code":"TR",
    "gn:dem":124,
    "gn:feature_class":"P",
    "gn:feature_code":"PPL",
    "gn:name":"U\u011furlu",
    "gn:population":0,
    "gn:timezone":"Europe/Istanbul",
    "iso:country":"TR",
    "name:tur_x_preferred":[
        "U\u011furlu"
    ],
    "wof:name":"Ugurlu",
    "wof:placetype":"locality"
},
  "geometry": {"coordinates":[30.25579,41.07499],"type":"Point"}
}