{
  "type": "Feature",
  "properties": {
    "gn:admin1_code":"82.0",
    "gn:asciiname":"Agaca",
    "gn:country_code":"TR",
    "gn:dem":1252,
    "gn:feature_class":"P",
    "gn:feature_code":"PPL",
    "gn:name":"A\u011faca",
    "gn:population":0,
    "gn:timezone":"Europe/Istanbul",
    "iso:country":"TR",
    "name:und_x_variant":[
        "A\u011fa",
        "A\u011fak\u00f6y",
        "A\u011faca"
    ],
    "wof:name":"Agaca",
    "wof:placetype":"locality"
},
  "geometry": {"coordinates":[32.79057,40.73225],"type":"Point"}
}