{
  "type": "Feature",
  "properties": {
    "gn:admin1_code":"37.0",
    "gn:asciiname":"Seyhkoy",
    "gn:country_code":"TR",
    "gn:dem":962,
    "gn:feature_class":"P",
    "gn:feature_code":"PPL",
    "gn:name":"\u015eeyhk\u00f6y",
    "gn:population":0,
    "gn:timezone":"Europe/Istanbul",
    "iso:country":"TR",
    "name:und_x_variant":[
        "Hac\u0131veli",
        "\u015eeyh",
        "\u015eeyhk\u00f6y"
    ],
    "wof:name":"Seyhkoy",
    "wof:placetype":"locality"
},
  "geometry": {"coordinates":[33.8581,41.27276],"type":"Point"}
}