{
  "type": "Feature",
  "properties": {
    "gn:admin1_code":"32",
    "gn:asciiname":"Mahmutaga",
    "gn:country_code":"TR",
    "gn:dem":22,
    "gn:feature_class":"P",
    "gn:feature_code":"PPL",
    "gn:name":"Mahmuta\u011fa",
    "gn:population":0,
    "gn:timezone":"Europe/Istanbul",
    "iso:country":"TR",
    "name:tur_x_preferred":[
        "Mahmuta\u011fa"
    ],
    "wof:name":"Mahmutaga",
    "wof:placetype":"locality"
},
  "geometry": {"coordinates":[34.96935,36.93625],"type":"Point"}
}