{
  "type": "Feature",
  "properties": {
    "gn:admin1_code":"24",
    "gn:asciiname":"Kismikor",
    "gn:cc2":"TR",
    "gn:country_code":"TR",
    "gn:dem":1389,
    "gn:feature_class":"P",
    "gn:feature_code":"PPL",
    "gn:name":"Kismik\u00f6r",
    "gn:population":0,
    "gn:timezone":"Europe/Istanbul",
    "iso:country":"TR",
    "name:und_x_variant":[
        "K\u0131s\u0131nk\u00f6r",
        "Kismik\u00f6r"
    ],
    "wof:name":"Kismikor",
    "wof:placetype":"locality"
},
  "geometry": {"coordinates":[39.65,39.58333],"type":"Point"}
}