{
  "type": "Feature",
  "properties": {
    "gn:admin1_code":"60.0",
    "gn:asciiname":"Yenidagici",
    "gn:country_code":"TR",
    "gn:dem":1145,
    "gn:feature_class":"P",
    "gn:feature_code":"PPL",
    "gn:name":"Yenida\u011fi\u00e7i",
    "gn:population":0,
    "gn:timezone":"Europe/Istanbul",
    "iso:country":"TR",
    "name:tur_x_preferred":[
        "Yenida\u011fi\u00e7i"
    ],
    "wof:name":"Yenidagici",
    "wof:placetype":"locality"
},
  "geometry": {"coordinates":[35.72646,40.26321],"type":"Point"}
}