{
  "type": "Feature",
  "properties": {
    "gn:admin1_code":"10",
    "gn:asciiname":"Buyukpinar",
    "gn:country_code":"TR",
    "gn:dem":354,
    "gn:feature_class":"P",
    "gn:feature_code":"PPL",
    "gn:name":"B\u00fcy\u00fckp\u0131nar",
    "gn:population":0,
    "gn:timezone":"Europe/Istanbul",
    "iso:country":"TR",
    "name:tur_x_preferred":[
        "B\u00fcy\u00fckp\u0131nar"
    ],
    "wof:name":"Buyukpinar",
    "wof:placetype":"locality"
},
  "geometry": {"coordinates":[27.6937,39.78969],"type":"Point"}
}