{
  "type": "Feature",
  "properties": {
    "gn:admin1_code":"55.0",
    "gn:asciiname":"Komsupinar",
    "gn:cc2":"TR",
    "gn:country_code":"TR",
    "gn:dem":436,
    "gn:feature_class":"P",
    "gn:feature_code":"PPL",
    "gn:name":"Kom\u015fup\u0131nar",
    "gn:population":0,
    "gn:timezone":"Europe/Istanbul",
    "iso:country":"TR",
    "name:und_x_variant":[
        "K\u00f6leyurdu",
        "Kom\u015fup\u0131nar"
    ],
    "wof:name":"Komsupinar",
    "wof:placetype":"locality"
},
  "geometry": {"coordinates":[35.66667,41.43333],"type":"Point"}
}