{
  "type": "Feature",
  "properties": {
    "gn:admin1_code":"10",
    "gn:asciiname":"Bakacak",
    "gn:country_code":"TR",
    "gn:dem":393,
    "gn:feature_class":"P",
    "gn:feature_code":"PPL",
    "gn:name":"Bakacak",
    "gn:population":0,
    "gn:timezone":"Europe/Istanbul",
    "iso:country":"TR",
    "name:tur_x_preferred":[
        "Bakacakk\u00f6y"
    ],
    "wof:name":"Bakacak",
    "wof:placetype":"locality"
},
  "geometry": {"coordinates":[27.72587,39.67618],"type":"Point"}
}