{
  "type": "Feature",
  "properties": {
    "gn:admin1_code":"68",
    "gn:asciiname":"Kirikli",
    "gn:country_code":"TR",
    "gn:dem":1120,
    "gn:feature_class":"P",
    "gn:feature_code":"PPL",
    "gn:name":"K\u0131r\u0131kl\u0131",
    "gn:population":0,
    "gn:timezone":"Europe/Istanbul",
    "iso:country":"TR",
    "name:und_x_variant":[
        "K\u0131r\u0131kl\u0131 \u00c7iftli\u011fi",
        "K\u0131r\u0131kl\u0131"
    ],
    "wof:name":"Kirikli",
    "wof:placetype":"locality"
},
  "geometry": {"coordinates":[32.80442,39.53068],"type":"Point"}
}