{
  "type": "Feature",
  "properties": {
    "gn:admin1_code":"55.0",
    "gn:asciiname":"Kapakli",
    "gn:country_code":"TR",
    "gn:dem":360,
    "gn:feature_class":"P",
    "gn:feature_code":"PPL",
    "gn:name":"Kapakl\u0131",
    "gn:population":0,
    "gn:timezone":"Europe/Istanbul",
    "iso:country":"TR",
    "wof:name":"Kapakli",
    "wof:placetype":"locality"
},
  "geometry": {"coordinates":[36.21135,41.2795],"type":"Point"}
}