{
  "type": "Feature",
  "properties": {
    "gn:admin1_code":"03",
    "gn:asciiname":"Orhaniye",
    "gn:country_code":"TR",
    "gn:dem":1020,
    "gn:feature_class":"P",
    "gn:feature_code":"PPL",
    "gn:name":"Orhaniye",
    "gn:population":0,
    "gn:timezone":"Europe/Istanbul",
    "iso:country":"TR",
    "wof:name":"Orhaniye",
    "wof:placetype":"locality"
},
  "geometry": {"coordinates":[30.89333,38.48611],"type":"Point"}
}