{
  "type": "Feature",
  "properties": {
    "gn:admin1_code":"87",
    "gn:asciiname":"Asagidere",
    "gn:country_code":"TR",
    "gn:dem":265,
    "gn:feature_class":"P",
    "gn:feature_code":"PPL",
    "gn:name":"A\u015fa\u011f\u0131dere",
    "gn:population":0,
    "gn:timezone":"Europe/Istanbul",
    "iso:country":"TR",
    "wof:name":"Asagidere",
    "wof:placetype":"locality"
},
  "geometry": {"coordinates":[32.59249000000001,41.59034000000001],"type":"Point"}
}