{
  "type": "Feature",
  "properties": {
    "gn:admin1_code":"83",
    "gn:asciiname":"Taslica",
    "gn:country_code":"TR",
    "gn:dem":802,
    "gn:feature_class":"P",
    "gn:feature_code":"PPL",
    "gn:name":"Ta\u015fl\u0131ca",
    "gn:population":0,
    "gn:timezone":"Europe/Istanbul",
    "iso:country":"TR",
    "name:und_x_variant":[
        "Ta\u015frumevlek",
        "Urumelek",
        "Ta\u015fl\u0131ca Rumevlek",
        "Ta\u015fl\u0131ca"
    ],
    "wof:name":"Taslica",
    "wof:placetype":"locality"
},
  "geometry": {"coordinates":[37.45582,37.05321],"type":"Point"}
}