{
  "type": "Feature",
  "properties": {
    "gn:admin1_code":"48",
    "gn:asciiname":"Kizilbel",
    "gn:country_code":"TR",
    "gn:dem":778,
    "gn:feature_class":"P",
    "gn:feature_code":"PPL",
    "gn:name":"K\u0131z\u0131lbel",
    "gn:population":0,
    "gn:timezone":"Europe/Istanbul",
    "iso:country":"TR",
    "name:tur_x_preferred":[
        "K\u0131z\u0131lbel"
    ],
    "wof:name":"Kizilbel",
    "wof:placetype":"locality"
},
  "geometry": {"coordinates":[29.24883,36.77471],"type":"Point"}
}