{
  "type": "Feature",
  "properties": {
    "gn:admin1_code":"58.0",
    "gn:asciiname":"Ekincik",
    "gn:country_code":"TR",
    "gn:dem":1666,
    "gn:feature_class":"P",
    "gn:feature_code":"PPL",
    "gn:name":"Ekincik",
    "gn:population":0,
    "gn:timezone":"Europe/Istanbul",
    "iso:country":"TR",
    "wof:name":"Ekincik",
    "wof:placetype":"locality"
},
  "geometry": {"coordinates":[38.40627,39.79364],"type":"Point"}
}