{
  "type": "Feature",
  "properties": {
    "gn:admin1_code":"12.0",
    "gn:asciiname":"Bilaloglu",
    "gn:country_code":"TR",
    "gn:dem":1273,
    "gn:feature_class":"P",
    "gn:feature_code":"PPL",
    "gn:name":"Bilalo\u011flu",
    "gn:population":0,
    "gn:timezone":"Europe/Istanbul",
    "iso:country":"TR",
    "name:tur_x_preferred":[
        "Bilalo\u011flu"
    ],
    "wof:name":"Bilaloglu",
    "wof:placetype":"locality"
},
  "geometry": {"coordinates":[40.39168,38.9235],"type":"Point"}
}