{
  "type": "Feature",
  "properties": {
    "gn:admin1_code":"23",
    "gn:asciiname":"Peltekoy",
    "gn:country_code":"TR",
    "gn:dem":994,
    "gn:feature_class":"P",
    "gn:feature_code":"PPL",
    "gn:name":"Peltek\u00f6y",
    "gn:population":0,
    "gn:timezone":"Europe/Istanbul",
    "iso:country":"TR",
    "name:tur_x_preferred":[
        "Peltek\u00f6y"
    ],
    "name:und_x_variant":[
        "Pelte"
    ],
    "wof:name":"Peltekoy",
    "wof:placetype":"locality"
},
  "geometry": {"coordinates":[39.05524000000001,38.70742],"type":"Point"}
}