{
  "type": "Feature",
  "properties": {
    "gn:admin1_code":"89.0",
    "gn:asciiname":"Beydini",
    "gn:country_code":"TR",
    "gn:dem":960,
    "gn:feature_class":"P",
    "gn:feature_code":"PPL",
    "gn:name":"Beydini",
    "gn:population":0,
    "gn:timezone":"Europe/Istanbul",
    "iso:country":"TR",
    "name:und_x_variant":[
        "Aci\u00f6z",
        "Beydini"
    ],
    "wof:name":"Beydini",
    "wof:placetype":"locality"
},
  "geometry": {"coordinates":[32.83196,41.06734],"type":"Point"}
}