{
  "type": "Feature",
  "properties": {
    "gn:admin1_code":"10",
    "gn:asciiname":"Hisarkoy",
    "gn:country_code":"TR",
    "gn:dem":359,
    "gn:feature_class":"P",
    "gn:feature_code":"PPL",
    "gn:name":"Hisark\u00f6y",
    "gn:population":0,
    "gn:timezone":"Europe/Istanbul",
    "iso:country":"TR",
    "name:und_x_variant":[
        "Hisar",
        "Hisark\u00f6y"
    ],
    "wof:name":"Hisarkoy",
    "wof:placetype":"locality"
},
  "geometry": {"coordinates":[28.28709000000001,39.42957],"type":"Point"}
}