{
  "type": "Feature",
  "properties": {
    "gn:admin1_code":"20",
    "gn:asciiname":"Keceliler",
    "gn:country_code":"TR",
    "gn:dem":517,
    "gn:feature_class":"P",
    "gn:feature_code":"PPL",
    "gn:name":"Ke\u00e7eliler",
    "gn:population":0,
    "gn:timezone":"Europe/Istanbul",
    "iso:country":"TR",
    "wof:name":"Keceliler",
    "wof:placetype":"locality"
},
  "geometry": {"coordinates":[28.75,37.33333],"type":"Point"}
}