{
  "type": "Feature",
  "properties": {
    "gn:admin1_code":"84.0",
    "gn:asciiname":"Esenyayla",
    "gn:country_code":"TR",
    "gn:dem":1492,
    "gn:feature_class":"P",
    "gn:feature_code":"PPL",
    "gn:name":"Esenyayla",
    "gn:population":0,
    "gn:timezone":"Europe/Istanbul",
    "iso:country":"TR",
    "name:und_x_variant":[
        "Uzunkilise",
        "Esenyayla"
    ],
    "wof:name":"Esenyayla",
    "wof:placetype":"locality"
},
  "geometry": {"coordinates":[43.6737,40.73262],"type":"Point"}
}