{
  "type": "Feature",
  "properties": {
    "gn:admin1_code":"35",
    "gn:asciiname":"Armaganlar",
    "gn:country_code":"TR",
    "gn:dem":156,
    "gn:feature_class":"P",
    "gn:feature_code":"PPL",
    "gn:name":"Arma\u011fanlar",
    "gn:population":0,
    "gn:timezone":"Europe/Istanbul",
    "iso:country":"TR",
    "name:tur_x_preferred":[
        "Arma\u011fanlar"
    ],
    "wof:name":"Armaganlar",
    "wof:placetype":"locality"
},
  "geometry": {"coordinates":[27.18524,39.05563],"type":"Point"}
}