{
  "type": "Feature",
  "properties": {
    "gn:admin1_code":"45",
    "gn:asciiname":"Omerler",
    "gn:country_code":"TR",
    "gn:dem":433,
    "gn:feature_class":"P",
    "gn:feature_code":"PPL",
    "gn:name":"\u00d6merler",
    "gn:population":0,
    "gn:timezone":"Europe/Istanbul",
    "iso:country":"TR",
    "wof:name":"Omerler",
    "wof:placetype":"locality"
},
  "geometry": {"coordinates":[28.75314,38.28829],"type":"Point"}
}