{
  "type": "Feature",
  "properties": {
    "gn:admin1_code":"70",
    "gn:asciiname":"Narli",
    "gn:country_code":"TR",
    "gn:dem":895,
    "gn:feature_class":"P",
    "gn:feature_code":"PPL",
    "gn:name":"Narl\u0131",
    "gn:population":0,
    "gn:timezone":"Europe/Istanbul",
    "iso:country":"TR",
    "name:und_x_variant":[
        "Beyad\u0131r",
        "Biyad\u0131r",
        "Narl\u0131"
    ],
    "wof:name":"Narli",
    "wof:placetype":"locality"
},
  "geometry": {"coordinates":[43.59341,37.26661],"type":"Point"}
}