{
  "type": "Feature",
  "properties": {
    "gn:admin1_code":"38",
    "gn:asciiname":"Asmakaya",
    "gn:country_code":"TR",
    "gn:dem":1667,
    "gn:feature_class":"P",
    "gn:feature_code":"PPL",
    "gn:name":"Asmakaya",
    "gn:population":0,
    "gn:timezone":"Europe/Istanbul",
    "iso:country":"TR",
    "name:und_x_variant":[
        "Dizgeme",
        "Asmakaya"
    ],
    "wof:name":"Asmakaya",
    "wof:placetype":"locality"
},
  "geometry": {"coordinates":[35.97966,38.83356],"type":"Point"}
}