{
  "type": "Feature",
  "properties": {
    "gn:admin1_code":"57.0",
    "gn:asciiname":"Derekoy",
    "gn:country_code":"TR",
    "gn:dem":211,
    "gn:feature_class":"P",
    "gn:feature_code":"PPL",
    "gn:name":"Derek\u00f6y",
    "gn:population":0,
    "gn:timezone":"Europe/Istanbul",
    "iso:country":"TR",
    "name:und_x_variant":[
        "Dere",
        "Derek\u00f6y"
    ],
    "wof:name":"Derekoy",
    "wof:placetype":"locality"
},
  "geometry": {"coordinates":[34.63995,41.93185],"type":"Point"}
}