{
  "type": "Feature",
  "properties": {
    "gn:admin1_code":"41.0",
    "gn:asciiname":"Kaymas",
    "gn:country_code":"TR",
    "gn:dem":142,
    "gn:feature_class":"P",
    "gn:feature_code":"PPLA3",
    "gn:name":"Kaymas",
    "gn:population":0,
    "gn:timezone":"Europe/Istanbul",
    "iso:country":"TR",
    "name:und_x_variant":[
        "Araman",
        "Kaymas",
        "Arman",
        "Salmanl\u0131",
        "Kaymaz"
    ],
    "wof:name":"Kaymas",
    "wof:placetype":"locality"
},
  "geometry": {"coordinates":[30.26597000000001,40.9231],"type":"Point"}
}