{
  "type": "Feature",
  "properties": {
    "gn:admin1_code":"20",
    "gn:asciiname":"Karabuk",
    "gn:country_code":"TR",
    "gn:dem":805,
    "gn:feature_class":"P",
    "gn:feature_code":"PPL",
    "gn:name":"Karab\u00fck",
    "gn:population":0,
    "gn:timezone":"Europe/Istanbul",
    "iso:country":"TR",
    "name:tur_x_preferred":[
        "Karab\u00fck"
    ],
    "wof:name":"Karabuk",
    "wof:placetype":"locality"
},
  "geometry": {"coordinates":[29.25912000000001,37.19761],"type":"Point"}
}