{
  "type": "Feature",
  "properties": {
    "iso:country":"TR",
    "name:eng_x_preferred":[
        "\u00c7ukurbostan"
    ],
    "name:tur_x_preferred":[
        "\u00c7ukurbostan"
    ],
    "wof:name":"Cukurbostan",
    "wof:placetype":"neighbourhood"
},
  "geometry": {"coordinates":[28.94979735994405,41.02504276904773],"type":"Point"}
}