{
  "type": "Feature",
  "properties": {
    "gn:admin1_code":"72.0",
    "gn:asciiname":"Bayrac",
    "gn:country_code":"TR",
    "gn:dem":945,
    "gn:feature_class":"P",
    "gn:feature_code":"PPL",
    "gn:name":"Bayra\u00e7",
    "gn:population":0,
    "gn:timezone":"Europe/Istanbul",
    "iso:country":"TR",
    "name:tur_x_preferred":[
        "Bayra\u00e7"
    ],
    "name:und_x_variant":[
        "Urochishche Perdeziyaret",
        "Perdeziyaret"
    ],
    "wof:name":"Bayrac",
    "wof:placetype":"locality"
},
  "geometry": {"coordinates":[41.64694,37.51306],"type":"Point"}
}