{
  "type": "Feature",
  "properties": {
    "gn:admin1_code":"68",
    "gn:asciiname":"Gunalan",
    "gn:country_code":"TR",
    "gn:dem":1211,
    "gn:feature_class":"P",
    "gn:feature_code":"PPL",
    "gn:name":"G\u00fcnalan",
    "gn:population":0,
    "gn:timezone":"Europe/Istanbul",
    "iso:country":"TR",
    "wof:name":"Gunalan",
    "wof:placetype":"locality"
},
  "geometry": {"coordinates":[32.88223,39.62389],"type":"Point"}
}