{
  "type": "Feature",
  "properties": {
    "gn:admin1_code":"37.0",
    "gn:asciiname":"Kanlicadere",
    "gn:cc2":"TR",
    "gn:country_code":"TR",
    "gn:dem":1320,
    "gn:feature_class":"P",
    "gn:feature_code":"PPL",
    "gn:name":"Kanl\u0131cadere",
    "gn:population":0,
    "gn:timezone":"Europe/Istanbul",
    "iso:country":"TR",
    "name:und_x_variant":[
        "Kanl\u0131caderesi",
        "Kanl\u0131cadere"
    ],
    "wof:name":"Kanlicadere",
    "wof:placetype":"locality"
},
  "geometry": {"coordinates":[33.81667,41.76667],"type":"Point"}
}