{
  "type": "Feature",
  "properties": {
    "gn:admin1_code":"79.0",
    "gn:asciiname":"Kiyhalilinceli",
    "gn:country_code":"TR",
    "gn:dem":589,
    "gn:feature_class":"P",
    "gn:feature_code":"PPL",
    "gn:name":"K\u0131yhalilinceli",
    "gn:population":0,
    "gn:timezone":"Europe/Istanbul",
    "iso:country":"TR",
    "wof:name":"Kiyhalilinceli",
    "wof:placetype":"locality"
},
  "geometry": {"coordinates":[33.7823,40.31867],"type":"Point"}
}