{
  "type": "Feature",
  "properties": {
    "gn:admin1_code":"71",
    "gn:asciiname":"Gozpinari",
    "gn:country_code":"TR",
    "gn:dem":1043,
    "gn:feature_class":"P",
    "gn:feature_code":"PPL",
    "gn:name":"G\u00f6zp\u0131nar\u0131",
    "gn:population":0,
    "gn:timezone":"Europe/Istanbul",
    "iso:country":"TR",
    "wof:name":"Gozpinari",
    "wof:placetype":"locality"
},
  "geometry": {"coordinates":[31.65594,38.35543],"type":"Point"}
}