{
  "type": "Feature",
  "properties": {
    "gn:admin1_code":"82.0",
    "gn:asciiname":"Asagioz",
    "gn:country_code":"TR",
    "gn:dem":1222,
    "gn:feature_class":"P",
    "gn:feature_code":"PPL",
    "gn:name":"A\u015fa\u011f\u0131\u00f6z",
    "gn:population":0,
    "gn:timezone":"Europe/Istanbul",
    "iso:country":"TR",
    "name:und_x_variant":[
        "A\u015fa\u011f\u0131badi\u011fin",
        "A\u015fa\u011f\u0131\u00f6z"
    ],
    "wof:name":"Asagioz",
    "wof:placetype":"locality"
},
  "geometry": {"coordinates":[33.88861,40.81784],"type":"Point"}
}