{
  "type": "Feature",
  "properties": {
    "gn:admin1_code":"59.0",
    "gn:asciiname":"Tetekoy",
    "gn:country_code":"TR",
    "gn:dem":138,
    "gn:feature_class":"P",
    "gn:feature_code":"PPL",
    "gn:name":"Tetek\u00f6y",
    "gn:population":0,
    "gn:timezone":"Europe/Istanbul",
    "iso:country":"TR",
    "name:und_x_variant":[
        "Tete",
        "Tetekk\u00f6y",
        "Tetek\u00f6y"
    ],
    "wof:name":"Tetekoy",
    "wof:placetype":"locality"
},
  "geometry": {"coordinates":[26.80003,40.79164],"type":"Point"}
}