{
  "type": "Feature",
  "properties": {
    "gn:admin1_code":"91",
    "gn:asciiname":"Yukaribozkuyu",
    "gn:country_code":"TR",
    "gn:dem":143,
    "gn:feature_class":"P",
    "gn:feature_code":"PPL",
    "gn:name":"Yukar\u0131bozkuyu",
    "gn:population":0,
    "gn:timezone":"Europe/Istanbul",
    "iso:country":"TR",
    "wof:name":"Yukaribozkuyu",
    "wof:placetype":"locality"
},
  "geometry": {"coordinates":[36.12156,37.2725],"type":"Point"}
}