{
  "type": "Feature",
  "properties": {
    "gn:admin1_code":"16",
    "gn:asciiname":"Yenisaribey",
    "gn:country_code":"TR",
    "gn:dem":17,
    "gn:feature_class":"P",
    "gn:feature_code":"PPL",
    "gn:name":"Yenisar\u0131bey",
    "gn:population":0,
    "gn:timezone":"Europe/Istanbul",
    "iso:country":"TR",
    "name:tur_x_preferred":[
        "Yenisar\u0131bey"
    ],
    "wof:name":"Yenisaribey",
    "wof:placetype":"locality"
},
  "geometry": {"coordinates":[28.22388,40.14804],"type":"Point"}
}