{
  "type": "Feature",
  "properties": {
    "gn:admin1_code":"65.0",
    "gn:asciiname":"Kecikiran",
    "gn:country_code":"TR",
    "gn:dem":1684,
    "gn:feature_class":"P",
    "gn:feature_code":"PPL",
    "gn:name":"Ke\u00e7ik\u0131ran",
    "gn:population":0,
    "gn:timezone":"Europe/Istanbul",
    "iso:country":"TR",
    "name:tur_x_preferred":[
        "K\u00fc\u00e7\u00fck K\u0131ran"
    ],
    "name:tur_x_variant":[
        "Ke\u00e7ik\u0131ran"
    ],
    "wof:name":"Kecikiran",
    "wof:placetype":"locality"
},
  "geometry": {"coordinates":[43.63324,38.97208],"type":"Point"}
}