{
  "type": "Feature",
  "properties": {
    "gn:admin1_code":"45",
    "gn:asciiname":"Gumuscay",
    "gn:country_code":"TR",
    "gn:dem":183,
    "gn:feature_class":"P",
    "gn:feature_code":"PPL",
    "gn:name":"G\u00fcm\u00fc\u015f\u00e7ay",
    "gn:population":0,
    "gn:timezone":"Europe/Istanbul",
    "iso:country":"TR",
    "name:tur_x_preferred":[
        "G\u00fcm\u00fc\u015f\u00e7ay"
    ],
    "wof:name":"Gumuscay",
    "wof:placetype":"locality"
},
  "geometry": {"coordinates":[28.64878,38.36287],"type":"Point"}
}