{
  "type": "Feature",
  "properties": {
    "gn:admin1_code":"5.0",
    "gn:asciiname":"Koyuncu",
    "gn:country_code":"TR",
    "gn:dem":502,
    "gn:feature_class":"P",
    "gn:feature_code":"PPL",
    "gn:name":"Koyuncu",
    "gn:population":0,
    "gn:timezone":"Europe/Istanbul",
    "iso:country":"TR",
    "wof:name":"Koyuncu",
    "wof:placetype":"locality"
},
  "geometry": {"coordinates":[35.52795,40.47759],"type":"Point"}
}