{
  "type": "Feature",
  "properties": {
    "gn:admin1_code":"32.0",
    "gn:asciiname":"Sogutozu Yaylasi",
    "gn:country_code":"TR",
    "gn:dem":1453,
    "gn:feature_class":"P",
    "gn:feature_code":"PPL",
    "gn:name":"S\u00f6\u011f\u00fct\u00f6z\u00fc Yaylas\u0131",
    "gn:population":0,
    "gn:timezone":"Europe/Istanbul",
    "iso:country":"TR",
    "wof:name":"Sogutozu Yaylasi",
    "wof:placetype":"locality"
},
  "geometry": {"coordinates":[33.53153,36.78943],"type":"Point"}
}