{
  "type": "Feature",
  "properties": {
    "gn:admin1_code":"03",
    "gn:asciiname":"Balcam",
    "gn:country_code":"TR",
    "gn:dem":1287,
    "gn:feature_class":"P",
    "gn:feature_code":"PPL",
    "gn:name":"Balcam",
    "gn:population":0,
    "gn:timezone":"Europe/Istanbul",
    "iso:country":"TR",
    "wof:name":"Balcam",
    "wof:placetype":"locality"
},
  "geometry": {"coordinates":[31.1928,38.94496],"type":"Point"}
}