{
  "type": "Feature",
  "properties": {
    "gn:admin1_code":"62",
    "gn:asciiname":"Bozaga Karaderbendi",
    "gn:country_code":"TR",
    "gn:dem":1789,
    "gn:feature_class":"P",
    "gn:feature_code":"PPL",
    "gn:name":"Boza\u011fa Karaderbendi",
    "gn:population":0,
    "gn:timezone":"Europe/Istanbul",
    "iso:country":"TR",
    "name:tur_x_preferred":[
        "Boza\u011fa Karaderbendi"
    ],
    "wof:name":"Bozaga Karaderbendi",
    "wof:placetype":"locality"
},
  "geometry": {"coordinates":[39.99563,39.44301],"type":"Point"}
}