{
  "type": "Feature",
  "properties": {
    "gn:admin1_code":"49.0",
    "gn:asciiname":"Yesildal",
    "gn:country_code":"TR",
    "gn:dem":1569,
    "gn:feature_class":"P",
    "gn:feature_code":"PPL",
    "gn:name":"Ye\u015fildal",
    "gn:population":0,
    "gn:timezone":"Europe/Istanbul",
    "iso:country":"TR",
    "name:tur_x_preferred":[
        "Ye\u015fildal"
    ],
    "wof:name":"Yesildal",
    "wof:placetype":"locality"
},
  "geometry": {"coordinates":[41.2518,39.25281],"type":"Point"}
}