{
  "type": "Feature",
  "properties": {
    "gn:admin1_code":"86.0",
    "gn:asciiname":"Kovorenk",
    "gn:country_code":"TR",
    "gn:dem":2056,
    "gn:feature_class":"P",
    "gn:feature_code":"PPL",
    "gn:name":"Kovorenk",
    "gn:population":0,
    "gn:timezone":"Europe/Istanbul",
    "iso:country":"TR",
    "name:und_x_variant":[
        "Karavenk",
        "Kovorenk",
        "Koravenk",
        "K\u00f6pr\u00fcl\u00fc"
    ],
    "wof:name":"Kovorenk",
    "wof:placetype":"locality"
},
  "geometry": {"coordinates":[42.46299000000001,40.88938],"type":"Point"}
}