{
  "type": "Feature",
  "properties": {
    "gn:admin1_code":"33",
    "gn:asciiname":"Sorkuncak",
    "gn:country_code":"TR",
    "gn:dem":1207,
    "gn:feature_class":"P",
    "gn:feature_code":"PPL",
    "gn:name":"Sorkuncak",
    "gn:population":0,
    "gn:timezone":"Europe/Istanbul",
    "iso:country":"TR",
    "name:und_x_variant":[
        "Sorkuncuk",
        "Sorkuncak"
    ],
    "wof:name":"Sorkuncak",
    "wof:placetype":"locality"
},
  "geometry": {"coordinates":[30.92916,37.89167],"type":"Point"}
}