{
  "type": "Feature",
  "properties": {
    "gn:admin1_code":"93",
    "gn:asciiname":"Ciftlikkoy",
    "gn:country_code":"TR",
    "gn:dem":220,
    "gn:feature_class":"P",
    "gn:feature_code":"PPL",
    "gn:name":"\u00c7iftlikk\u00f6y",
    "gn:population":0,
    "gn:timezone":"Europe/Istanbul",
    "iso:country":"TR",
    "name:tur_x_preferred":[
        "\u00c7iftlikk\u00f6y"
    ],
    "name:tur_x_variant":[
        "\u00c7iftlik"
    ],
    "wof:name":"Ciftlikkoy",
    "wof:placetype":"locality"
},
  "geometry": {"coordinates":[31.21563,40.89161],"type":"Point"}
}