{
  "type": "Feature",
  "properties": {
    "gn:admin1_code":"15",
    "gn:asciiname":"Suludere",
    "gn:cc2":"TR",
    "gn:country_code":"TR",
    "gn:dem":942,
    "gn:feature_class":"P",
    "gn:feature_code":"PPL",
    "gn:name":"Suludere",
    "gn:population":0,
    "gn:timezone":"Europe/Istanbul",
    "iso:country":"TR",
    "name:und_x_variant":[
        "Suluderek\u00f6y",
        "Suludere"
    ],
    "wof:name":"Suludere",
    "wof:placetype":"locality"
},
  "geometry": {"coordinates":[30.17667,37.65417],"type":"Point"}
}