{
  "type": "Feature",
  "properties": {
    "gn:admin1_code":"09",
    "gn:asciiname":"Birci",
    "gn:country_code":"TR",
    "gn:dem":625,
    "gn:feature_class":"P",
    "gn:feature_code":"PPL",
    "gn:name":"Birci",
    "gn:population":0,
    "gn:timezone":"Europe/Istanbul",
    "iso:country":"TR",
    "wof:name":"Birci",
    "wof:placetype":"locality"
},
  "geometry": {"coordinates":[27.68417,37.72333],"type":"Point"}
}