{
  "type": "Feature",
  "properties": {
    "gn:admin1_code":"33",
    "gn:asciiname":"Yukari Mahalle",
    "gn:country_code":"TR",
    "gn:dem":1054,
    "gn:feature_class":"P",
    "gn:feature_code":"PPL",
    "gn:name":"Yukar\u0131 Mahalle",
    "gn:population":0,
    "gn:timezone":"Europe/Istanbul",
    "iso:country":"TR",
    "wof:name":"Yukari Mahalle",
    "wof:placetype":"locality"
},
  "geometry": {"coordinates":[30.8617,37.59734],"type":"Point"}
}