{
  "type": "Feature",
  "properties": {
    "gn:admin1_code":"41.0",
    "gn:asciiname":"Hacilar",
    "gn:country_code":"TR",
    "gn:dem":118,
    "gn:feature_class":"P",
    "gn:feature_code":"PPL",
    "gn:name":"Hac\u0131lar",
    "gn:population":0,
    "gn:timezone":"Europe/Istanbul",
    "iso:country":"TR",
    "name:tur_x_preferred":[
        "Hac\u0131lar"
    ],
    "wof:name":"Hacilar",
    "wof:placetype":"locality"
},
  "geometry": {"coordinates":[30.05702,41.04272],"type":"Point"}
}