{
  "type": "Feature",
  "properties": {
    "iso:country":"TR",
    "name:eng_x_preferred":[
        "Kupluce"
    ],
    "name:tur_x_preferred":[
        "K\u00fcpl\u00fcce"
    ],
    "wof:name":"Kupluce",
    "wof:placetype":"neighbourhood"
},
  "geometry": {"coordinates":[29.05165753071957,41.03866814523403],"type":"Point"}
}