{
  "type": "Feature",
  "properties": {
    "gn:admin1_code":"24",
    "gn:asciiname":"Ulukoy",
    "gn:country_code":"TR",
    "gn:dem":1164,
    "gn:feature_class":"P",
    "gn:feature_code":"PPL",
    "gn:name":"Uluk\u00f6y",
    "gn:population":0,
    "gn:timezone":"Europe/Istanbul",
    "iso:country":"TR",
    "name:tur_x_preferred":[
        "Uluk\u00f6y"
    ],
    "wof:name":"Ulukoy",
    "wof:placetype":"locality"
},
  "geometry": {"coordinates":[39.73352,39.62317],"type":"Point"}
}