{
  "type": "Feature",
  "properties": {
    "gn:admin1_code":"35",
    "gn:asciiname":"Cumali",
    "gn:country_code":"TR",
    "gn:dem":345,
    "gn:feature_class":"P",
    "gn:feature_code":"PPL",
    "gn:name":"Cumal\u0131",
    "gn:population":0,
    "gn:timezone":"Europe/Istanbul",
    "iso:country":"TR",
    "name:tur_x_preferred":[
        "Cumal\u0131"
    ],
    "wof:name":"Cumali",
    "wof:placetype":"locality"
},
  "geometry": {"coordinates":[27.46112,38.31779],"type":"Point"}
}