{
  "type": "Feature",
  "properties": {
    "gn:admin1_code":"86",
    "gn:asciiname":"Saymali",
    "gn:country_code":"TR",
    "gn:dem":1912,
    "gn:feature_class":"P",
    "gn:feature_code":"PPL",
    "gn:name":"Saymal\u0131",
    "gn:population":0,
    "gn:timezone":"Europe/Istanbul",
    "iso:country":"TR",
    "name:tur_x_preferred":[
        "Saymal\u0131"
    ],
    "wof:name":"Saymali",
    "wof:placetype":"locality"
},
  "geometry": {"coordinates":[43.18926,41.12483],"type":"Point"}
}