{
  "type": "Feature",
  "properties": {
    "gn:admin1_code":"74",
    "gn:asciiname":"Gizerek",
    "gn:country_code":"TR",
    "gn:dem":970,
    "gn:feature_class":"P",
    "gn:feature_code":"PPL",
    "gn:name":"Gizerek",
    "gn:population":0,
    "gn:timezone":"Europe/Istanbul",
    "iso:country":"TR",
    "name:und_x_variant":[
        "Gezeryuk",
        "Gezer\u00fck",
        "B\u00f6l\u00fckl\u00fc"
    ],
    "wof:name":"Gizerek",
    "wof:placetype":"locality"
},
  "geometry": {"coordinates":[42.12972,37.85278],"type":"Point"}
}