{
  "type": "Feature",
  "properties": {
    "gn:country":"TR",
    "gn:fcode":"PPL",
    "gn:pop":0,
    "iso:country":"TR",
    "name:bul_x_preferred":[
        "\u0415\u043d\u0438 \u0447\u0438\u0444\u043b\u0438\u043a"
    ],
    "name:chi_x_preferred":[
        "\u8036\u5c3c\u5947\u592b\u7279\u5229\u514b"
    ],
    "name:dut_x_preferred":[
        "Yeni\u00e7iftlik"
    ],
    "name:eng_x_preferred":[
        "Yeni\u00e7iftlik"
    ],
    "name:fre_x_preferred":[
        "Yeni\u00e7iftlik"
    ],
    "name:nno_x_preferred":[
        "Yeni\u00e7iftlik"
    ],
    "name:per_x_preferred":[
        "\u06cc\u0626\u0646\u06cc \u0686\u06cc\u0641\u062a\u0644\u06cc\u06a9"
    ],
    "name:por_x_preferred":[
        "Yeni\u00e7iftlik"
    ],
    "name:urd_x_preferred":[
        "\u06cc\u0646\u06cc\u0633\u0627\u0641\u062a\u0644\u06a9"
    ],
    "name:vie_x_preferred":[
        "Yeni\u00e7iftlik"
    ],
    "qs:name":"Yeni\u00e7iftlik",
    "qs:name_adm0":"Turkey",
    "qs:name_adm1":"Tekirda\u011f",
    "qs:photos_9k":1,
    "qs:photos_9r":2,
    "qs:photos_all":38,
    "qs:photos_sr":0,
    "qs:placetype":"Town",
    "qs:pop_sr":"0",
    "wd:elevation":75.0,
    "wd:wordcount":177,
    "wof:name":"Yeni\u00e7iftlik",
    "wof:placetype":"locality",
    "wof:population":0
},
  "geometry": {"coordinates":[27.85222,41.01139],"type":"Point"}
}