{
  "type": "Feature",
  "properties": {
    "gn:admin1_code":"13",
    "gn:asciiname":"Oduncular",
    "gn:country_code":"TR",
    "gn:dem":1881,
    "gn:feature_class":"P",
    "gn:feature_code":"PPL",
    "gn:name":"Oduncular",
    "gn:population":0,
    "gn:timezone":"Europe/Istanbul",
    "iso:country":"TR",
    "name:tur_x_preferred":[
        "Oduncular"
    ],
    "wof:name":"Oduncular",
    "wof:placetype":"locality"
},
  "geometry": {"coordinates":[42.16972,38.56826],"type":"Point"}
}