{
  "type": "Feature",
  "properties": {
    "gn:admin1_code":"55.0",
    "gn:asciiname":"Gundogdu",
    "gn:country_code":"TR",
    "gn:dem":717,
    "gn:feature_class":"P",
    "gn:feature_code":"PPL",
    "gn:name":"G\u00fcndo\u011fdu",
    "gn:population":0,
    "gn:timezone":"Europe/Istanbul",
    "iso:country":"TR",
    "name:und_x_variant":[
        "Bicinci",
        "Ortak\u00f6y",
        "G\u00fcndo\u011fdu"
    ],
    "wof:name":"Gundogdu",
    "wof:placetype":"locality"
},
  "geometry": {"coordinates":[36.25565,41.03706],"type":"Point"}
}