{
  "type": "Feature",
  "properties": {
    "gn:admin1_code":"28",
    "gn:asciiname":"Kucukkoy",
    "gn:country_code":"TR",
    "gn:dem":158,
    "gn:feature_class":"P",
    "gn:feature_code":"PPL",
    "gn:name":"K\u00fc\u00e7\u00fckk\u00f6y",
    "gn:population":0,
    "gn:timezone":"Europe/Istanbul",
    "iso:country":"TR",
    "name:tur_x_preferred":[
        "K\u00fc\u00e7\u00fckk\u00f6y"
    ],
    "wof:name":"Kucukkoy",
    "wof:placetype":"locality"
},
  "geometry": {"coordinates":[38.45311,40.90249],"type":"Point"}
}