{
  "type": "Feature",
  "properties": {
    "gn:admin1_code":"03",
    "gn:asciiname":"Gomu",
    "gn:country_code":"TR",
    "gn:dem":961,
    "gn:feature_class":"P",
    "gn:feature_code":"PPL",
    "gn:name":"G\u00f6m\u00fc",
    "gn:population":0,
    "gn:timezone":"Europe/Istanbul",
    "iso:country":"TR",
    "wof:name":"Gomu",
    "wof:placetype":"locality"
},
  "geometry": {"coordinates":[31.07972,39.05944],"type":"Point"}
}