{
  "type": "Feature",
  "properties": {
    "gn:admin1_code":"16",
    "gn:asciiname":"Eskikoy",
    "gn:country_code":"TR",
    "gn:dem":573,
    "gn:feature_class":"P",
    "gn:feature_code":"PPL",
    "gn:name":"Eskik\u00f6y",
    "gn:population":0,
    "gn:timezone":"Europe/Istanbul",
    "iso:country":"TR",
    "name:und_x_variant":[
        "Eski",
        "Eskik\u00f6y"
    ],
    "wof:name":"Eskikoy",
    "wof:placetype":"locality"
},
  "geometry": {"coordinates":[29.50671,39.99345],"type":"Point"}
}