{
  "type": "Feature",
  "properties": {
    "gn:admin1_code":"63",
    "gn:asciiname":"Kellehan",
    "gn:country_code":"TR",
    "gn:dem":723,
    "gn:feature_class":"P",
    "gn:feature_code":"PPL",
    "gn:name":"Kellehan",
    "gn:population":0,
    "gn:timezone":"Europe/Istanbul",
    "iso:country":"TR",
    "name:und_x_variant":[
        "Evyan\u0131"
    ],
    "wof:name":"Kellehan",
    "wof:placetype":"locality"
},
  "geometry": {"coordinates":[39.07924000000001,37.9522],"type":"Point"}
}