{
  "type": "Feature",
  "properties": {
    "gn:admin1_code":"57.0",
    "gn:asciiname":"Karaoglu",
    "gn:country_code":"TR",
    "gn:dem":263,
    "gn:feature_class":"P",
    "gn:feature_code":"PPL",
    "gn:name":"Karao\u011flu",
    "gn:population":0,
    "gn:timezone":"Europe/Istanbul",
    "iso:country":"TR",
    "name:tur_x_preferred":[
        "Karao\u011flu"
    ],
    "name:und_x_variant":[
        "\u00c7ak\u0131r"
    ],
    "wof:name":"Karaoglu",
    "wof:placetype":"locality"
},
  "geometry": {"coordinates":[34.8547,41.89846],"type":"Point"}
}