{
  "type": "Feature",
  "properties": {
    "gn:admin1_code":"14.0",
    "gn:asciiname":"Karabogazdamlari",
    "gn:country_code":"TR",
    "gn:dem":1157,
    "gn:feature_class":"P",
    "gn:feature_code":"PPL",
    "gn:name":"Karabo\u011fazdamlar\u0131",
    "gn:population":0,
    "gn:timezone":"Europe/Istanbul",
    "iso:country":"TR",
    "wof:name":"Karabogazdamlari",
    "wof:placetype":"locality"
},
  "geometry": {"coordinates":[32.23333,41.01667],"type":"Point"}
}