{
  "type": "Feature",
  "properties": {
    "gn:admin1_code":"69",
    "gn:asciiname":"Oguzkoey",
    "gn:country_code":"TR",
    "gn:dem":1918,
    "gn:feature_class":"P",
    "gn:feature_code":"PPL",
    "gn:name":"O\u011fuzk\u00f6y",
    "gn:population":0,
    "gn:timezone":"Europe/Istanbul",
    "iso:country":"TR",
    "name:tur_x_preferred":[
        "O\u011fuzk\u00f6y"
    ],
    "name:und_x_variant":[
        "U\u011fuz",
        "O\u011fuz"
    ],
    "wof:name":"Oguzkoey",
    "wof:placetype":"locality"
},
  "geometry": {"coordinates":[39.63333,39.96667],"type":"Point"}
}