{
  "type": "Feature",
  "properties": {
    "gn:admin1_code":"48.0",
    "gn:asciiname":"Akgedik",
    "gn:country_code":"TR",
    "gn:dem":461,
    "gn:feature_class":"P",
    "gn:feature_code":"PPL",
    "gn:name":"Akgedik",
    "gn:population":0,
    "gn:timezone":"Europe/Istanbul",
    "iso:country":"TR",
    "name:fas_x_preferred":[
        "\u0627\u06a9\u06af\u062f\u06cc\u06a9"
    ],
    "name:msa_x_preferred":[
        "Akgedik"
    ],
    "name:tur_x_preferred":[
        "Akgedik"
    ],
    "name:vie_x_preferred":[
        "Akgedik"
    ],
    "wof:name":"Akgedik",
    "wof:placetype":"locality"
},
  "geometry": {"coordinates":[28.21298,37.27627],"type":"Point"}
}