{
  "type": "Feature",
  "properties": {
    "gn:admin1_code":"55.0",
    "gn:asciiname":"Cekalan",
    "gn:country_code":"TR",
    "gn:dem":542,
    "gn:feature_class":"P",
    "gn:feature_code":"PPL",
    "gn:name":"\u00c7ekalan",
    "gn:population":0,
    "gn:timezone":"Europe/Istanbul",
    "iso:country":"TR",
    "name:und_x_variant":[
        "\u00c7ekialan",
        "\u00c7ekalan"
    ],
    "wof:name":"Cekalan",
    "wof:placetype":"locality"
},
  "geometry": {"coordinates":[35.59625,41.15764],"type":"Point"}
}