{
  "type": "Feature",
  "properties": {
    "gn:admin1_code":"68.0",
    "gn:asciiname":"Yildirmevci",
    "gn:country_code":"TR",
    "gn:dem":1394,
    "gn:feature_class":"P",
    "gn:feature_code":"PPL",
    "gn:name":"Y\u0131ld\u0131rmevci",
    "gn:population":0,
    "gn:timezone":"Europe/Istanbul",
    "iso:country":"TR",
    "wof:name":"Yildirmevci",
    "wof:placetype":"locality"
},
  "geometry": {"coordinates":[32.87984,40.44804],"type":"Point"}
}