{
  "type": "Feature",
  "properties": {
    "iso:country":"TR",
    "qs:name":"Yildirim",
    "qs:name_adm0":"Turkey",
    "qs:name_adm1":"Bursa",
    "qs:photos":15,
    "qs:photos_1k":3,
    "qs:photos_9k":1,
    "qs:photos_9r":1,
    "qs:photos_all":15,
    "qs:photos_sr":1,
    "qs:placetype":"Suburb",
    "qs:pop_sr":"0",
    "wof:name":"Yildirim",
    "wof:placetype":"neighbourhood"
},
  "geometry": {"coordinates":[29.05861,40.191987],"type":"Point"}
}