{
  "type": "Feature",
  "properties": {
    "gn:admin1_code":"48",
    "gn:asciiname":"Mondume",
    "gn:country_code":"TR",
    "gn:dem":993,
    "gn:feature_class":"P",
    "gn:feature_code":"PPL",
    "gn:name":"M\u00f6nd\u00fcme",
    "gn:population":0,
    "gn:timezone":"Europe/Istanbul",
    "iso:country":"TR",
    "wof:name":"Mondume",
    "wof:placetype":"locality"
},
  "geometry": {"coordinates":[28.51667,37.21667],"type":"Point"}
}