{
  "type": "Feature",
  "properties": {
    "gn:admin1_code":"84.0",
    "gn:asciiname":"Karabag",
    "gn:country_code":"TR",
    "gn:dem":1559,
    "gn:feature_class":"P",
    "gn:feature_code":"PPL",
    "gn:name":"Karaba\u011f",
    "gn:population":0,
    "gn:timezone":"Europe/Istanbul",
    "iso:country":"TR",
    "name:eng_x_preferred":[
        "Karaba\u011f"
    ],
    "name:rus_x_preferred":[
        "\u041a\u0430\u0440\u0430\u0431\u0430\u0433"
    ],
    "name:und_x_variant":[
        "Karada\u011f Yaylas\u0131",
        "Karaba\u011f Yaylas\u0131",
        "Karaba\u011f"
    ],
    "wof:name":"Karabag",
    "wof:placetype":"locality"
},
  "geometry": {"coordinates":[43.16235,40.23318],"type":"Point"}
}