{
  "type": "Feature",
  "properties": {
    "gn:admin1_code":"43",
    "gn:asciiname":"Kupluce",
    "gn:country_code":"TR",
    "gn:dem":1122,
    "gn:feature_class":"P",
    "gn:feature_code":"PPL",
    "gn:name":"K\u00fcpl\u00fcce",
    "gn:population":0,
    "gn:timezone":"Europe/Istanbul",
    "iso:country":"TR",
    "wof:name":"Kupluce",
    "wof:placetype":"locality"
},
  "geometry": {"coordinates":[29.05972,38.99667],"type":"Point"}
}