{
  "type": "Feature",
  "properties": {
    "gn:admin1_code":"68",
    "gn:asciiname":"Hidirseyh",
    "gn:country_code":"TR",
    "gn:dem":858,
    "gn:feature_class":"P",
    "gn:feature_code":"PPL",
    "gn:name":"H\u0131d\u0131r\u015feyh",
    "gn:population":0,
    "gn:timezone":"Europe/Istanbul",
    "iso:country":"TR",
    "name:tur_x_preferred":[
        "H\u0131d\u0131r\u015feyh"
    ],
    "name:und_x_variant":[
        "H\u0131d\u0131r\u015f\u0131h",
        "H\u0131z\u0131r\u015feyh"
    ],
    "wof:name":"Hidirseyh",
    "wof:placetype":"locality"
},
  "geometry": {"coordinates":[32.23722,39.8385],"type":"Point"}
}