{
  "type": "Feature",
  "properties": {
    "gn:admin1_code":"24.0",
    "gn:asciiname":"Akcali",
    "gn:country_code":"TR",
    "gn:dem":1331,
    "gn:feature_class":"P",
    "gn:feature_code":"PPL",
    "gn:name":"Ak\u00e7al\u0131",
    "gn:population":0,
    "gn:timezone":"Europe/Istanbul",
    "iso:country":"TR",
    "name:tur_x_preferred":[
        "Ak\u00e7al\u0131"
    ],
    "wof:name":"Akcali",
    "wof:placetype":"locality"
},
  "geometry": {"coordinates":[38.66706,39.11888],"type":"Point"}
}