{
  "type": "Feature",
  "properties": {
    "gn:admin1_code":"38",
    "gn:asciiname":"Denizovasi",
    "gn:country_code":"TR",
    "gn:dem":1449,
    "gn:feature_class":"P",
    "gn:feature_code":"PPL",
    "gn:name":"Denizovas\u0131",
    "gn:population":0,
    "gn:timezone":"Europe/Istanbul",
    "iso:country":"TR",
    "wof:name":"Denizovasi",
    "wof:placetype":"locality"
},
  "geometry": {"coordinates":[35.51667,38.16667],"type":"Point"}
}