{
  "type": "Feature",
  "properties": {
    "gn:admin1_code":"07",
    "gn:asciiname":"Alikorusu",
    "gn:country_code":"TR",
    "gn:dem":1351,
    "gn:feature_class":"P",
    "gn:feature_code":"PPL",
    "gn:name":"Alikorusu",
    "gn:population":0,
    "gn:timezone":"Europe/Istanbul",
    "iso:country":"TR",
    "wof:name":"Alikorusu",
    "wof:placetype":"locality"
},
  "geometry": {"coordinates":[31.86667000000001,37.11667],"type":"Point"}
}