{
  "type": "Feature",
  "properties": {
    "gn:admin1_code":"63.0",
    "gn:asciiname":"Sagirtas",
    "gn:country_code":"TR",
    "gn:dem":585,
    "gn:feature_class":"P",
    "gn:feature_code":"PPL",
    "gn:name":"Sa\u011f\u0131rta\u015f",
    "gn:population":0,
    "gn:timezone":"Europe/Istanbul",
    "iso:country":"TR",
    "name:tur_x_preferred":[
        "Sa\u011f\u0131rta\u015f"
    ],
    "wof:name":"Sagirtas",
    "wof:placetype":"locality"
},
  "geometry": {"coordinates":[39.541,37.11919],"type":"Point"}
}