{
  "type": "Feature",
  "properties": {
    "gn:admin1_code":"32.0",
    "gn:asciiname":"Malotu",
    "gn:country_code":"TR",
    "gn:dem":754,
    "gn:feature_class":"P",
    "gn:feature_code":"PPL",
    "gn:name":"Malotu",
    "gn:population":0,
    "gn:timezone":"Europe/Istanbul",
    "iso:country":"TR",
    "wof:name":"Malotu",
    "wof:placetype":"locality"
},
  "geometry": {"coordinates":[32.66076,36.08918],"type":"Point"}
}