{
  "type": "Feature",
  "properties": {
    "gn:admin1_code":"55",
    "gn:asciiname":"Camlikale",
    "gn:country_code":"TR",
    "gn:dem":689,
    "gn:feature_class":"P",
    "gn:feature_code":"PPL",
    "gn:name":"\u00c7aml\u0131kale",
    "gn:population":0,
    "gn:timezone":"Europe/Istanbul",
    "iso:country":"TR",
    "name:tur_x_preferred":[
        "\u00c7aml\u0131kale"
    ],
    "wof:name":"Camlikale",
    "wof:placetype":"locality"
},
  "geometry": {"coordinates":[36.49138,40.91593],"type":"Point"}
}