{
  "type": "Feature",
  "properties": {
    "gn:admin1_code":"10",
    "gn:asciiname":"Aslandede",
    "gn:country_code":"TR",
    "gn:dem":573,
    "gn:feature_class":"P",
    "gn:feature_code":"PPL",
    "gn:name":"Aslandede",
    "gn:population":0,
    "gn:timezone":"Europe/Istanbul",
    "iso:country":"TR",
    "name:tur_x_preferred":[
        "Aslandede"
    ],
    "name:und_x_variant":[
        "Doreyl\u0131"
    ],
    "wof:name":"Aslandede",
    "wof:placetype":"locality"
},
  "geometry": {"coordinates":[28.30171,39.21131],"type":"Point"}
}