{
  "type": "Feature",
  "properties": {
    "gn:admin1_code":"77.0",
    "gn:asciiname":"Gezkoy",
    "gn:country_code":"TR",
    "gn:dem":1656,
    "gn:feature_class":"P",
    "gn:feature_code":"PPL",
    "gn:name":"Gezk\u00f6y",
    "gn:population":0,
    "gn:timezone":"Europe/Istanbul",
    "iso:country":"TR",
    "name:und_x_variant":[
        "Gez",
        "Gez K\u00f6y\u00fc",
        "Gezk\u00f6y"
    ],
    "wof:name":"Gezkoy",
    "wof:placetype":"locality"
},
  "geometry": {"coordinates":[40.31102,40.20153],"type":"Point"}
}