{
  "type": "Feature",
  "properties": {
    "gn:admin1_code":"55",
    "gn:asciiname":"Toygar",
    "gn:country_code":"TR",
    "gn:dem":428,
    "gn:feature_class":"P",
    "gn:feature_code":"PPL",
    "gn:name":"Toygar",
    "gn:population":0,
    "gn:timezone":"Europe/Istanbul",
    "iso:country":"TR",
    "name:tur_x_preferred":[
        "Toygar"
    ],
    "wof:name":"Toygar",
    "wof:placetype":"locality"
},
  "geometry": {"coordinates":[36.36874,41.19255],"type":"Point"}
}