{
  "type": "Feature",
  "properties": {
    "gn:admin1_code":"68",
    "gn:asciiname":"Emirler",
    "gn:country_code":"TR",
    "gn:dem":1177,
    "gn:feature_class":"P",
    "gn:feature_code":"PPL",
    "gn:name":"Emirler",
    "gn:population":0,
    "gn:timezone":"Europe/Istanbul",
    "iso:country":"TR",
    "wof:name":"Emirler",
    "wof:placetype":"locality"
},
  "geometry": {"coordinates":[32.9231,39.40966],"type":"Point"}
}