{
  "type": "Feature",
  "properties": {
    "gn:admin1_code":"09",
    "gn:asciiname":"Hamzebali",
    "gn:country_code":"TR",
    "gn:dem":68,
    "gn:feature_class":"P",
    "gn:feature_code":"PPL",
    "gn:name":"Hamzebali",
    "gn:population":0,
    "gn:timezone":"Europe/Istanbul",
    "iso:country":"TR",
    "name:und_x_variant":[
        "Hamzabal\u0131"
    ],
    "wof:name":"Hamzebali",
    "wof:placetype":"locality"
},
  "geometry": {"coordinates":[28.1206,37.80207],"type":"Point"}
}