{
  "type": "Feature",
  "properties": {
    "gn:admin1_code":"07",
    "gn:asciiname":"Ciglik",
    "gn:country_code":"TR",
    "gn:dem":615,
    "gn:feature_class":"P",
    "gn:feature_code":"PPL",
    "gn:name":"\u00c7\u0131\u011fl\u0131k",
    "gn:population":0,
    "gn:timezone":"Europe/Istanbul",
    "iso:country":"TR",
    "wof:name":"Ciglik",
    "wof:placetype":"locality"
},
  "geometry": {"coordinates":[32.52314000000001,36.31343],"type":"Point"}
}