{
  "type": "Feature",
  "properties": {
    "gn:admin1_code":"34.0",
    "gn:asciiname":"Imrendere",
    "gn:country_code":"TR",
    "gn:dem":10,
    "gn:feature_class":"P",
    "gn:feature_code":"PPL",
    "gn:name":"\u0130mrendere",
    "gn:population":0,
    "gn:timezone":"Europe/Istanbul",
    "iso:country":"TR",
    "name:und_x_variant":[
        "\u0130mrendere K\u00f6y\u00fc",
        "\u0130mrendere"
    ],
    "wof:name":"Imrendere",
    "wof:placetype":"locality"
},
  "geometry": {"coordinates":[29.59888,41.14221],"type":"Point"}
}