{
  "type": "Feature",
  "properties": {
    "gn:admin1_code":"59.0",
    "gn:asciiname":"Susuzmusellim",
    "gn:country_code":"TR",
    "gn:dem":98,
    "gn:feature_class":"P",
    "gn:feature_code":"PPLA3",
    "gn:name":"Susuzm\u00fcsellim",
    "gn:population":0,
    "gn:timezone":"Europe/Istanbul",
    "iso:country":"TR",
    "name:tur_x_preferred":[
        "Susuzm\u00fcsellim"
    ],
    "wof:name":"Susuzmusellim",
    "wof:placetype":"locality"
},
  "geometry": {"coordinates":[27.0675,41.09889],"type":"Point"}
}