{
  "type": "Feature",
  "properties": {
    "gn:admin1_code":"64",
    "gn:asciiname":"Aliosmanlar",
    "gn:country_code":"TR",
    "gn:dem":903,
    "gn:feature_class":"P",
    "gn:feature_code":"PPL",
    "gn:name":"Aliosmanlar",
    "gn:population":0,
    "gn:timezone":"Europe/Istanbul",
    "iso:country":"TR",
    "wof:name":"Aliosmanlar",
    "wof:placetype":"locality"
},
  "geometry": {"coordinates":[28.89092,38.2816],"type":"Point"}
}