{
  "type": "Feature",
  "properties": {
    "gn:admin1_code":"61.0",
    "gn:asciiname":"Yildizli",
    "gn:country_code":"TR",
    "gn:dem":159,
    "gn:feature_class":"P",
    "gn:feature_code":"PPL",
    "gn:name":"Y\u0131ld\u0131zl\u0131",
    "gn:population":0,
    "gn:timezone":"Europe/Istanbul",
    "iso:country":"TR",
    "name:und_x_variant":[
        "Y\u0131ld\u0131zl\u0131",
        "Avanos"
    ],
    "wof:name":"Yildizli",
    "wof:placetype":"locality"
},
  "geometry": {"coordinates":[40.06129,40.88952000000001],"type":"Point"}
}