{
  "type": "Feature",
  "properties": {
    "gn:admin1_code":"59",
    "gn:asciiname":"Vakifigdemir",
    "gn:country_code":"TR",
    "gn:dem":228,
    "gn:feature_class":"P",
    "gn:feature_code":"PPL",
    "gn:name":"Vak\u0131f\u0131\u011fdemir",
    "gn:population":0,
    "gn:timezone":"Europe/Istanbul",
    "iso:country":"TR",
    "name:tur_x_preferred":[
        "Vak\u0131f\u0131\u011fdemir"
    ],
    "wof:name":"Vakifigdemir",
    "wof:placetype":"locality"
},
  "geometry": {"coordinates":[27.14283,40.86807],"type":"Point"}
}