{
  "type": "Feature",
  "properties": {
    "gn:admin1_code":"17",
    "gn:asciiname":"Hacikasim",
    "gn:country_code":"TR",
    "gn:dem":206,
    "gn:feature_class":"P",
    "gn:feature_code":"PPL",
    "gn:name":"Hac\u0131kas\u0131m",
    "gn:population":0,
    "gn:timezone":"Europe/Istanbul",
    "iso:country":"TR",
    "wof:name":"Hacikasim",
    "wof:placetype":"locality"
},
  "geometry": {"coordinates":[26.83194,39.97278],"type":"Point"}
}