{
  "type": "Feature",
  "properties": {
    "gn:admin1_code":"86.0",
    "gn:asciiname":"Kolkoy",
    "gn:country_code":"TR",
    "gn:dem":1951,
    "gn:feature_class":"P",
    "gn:feature_code":"PPL",
    "gn:name":"Kolk\u00f6y",
    "gn:population":0,
    "gn:timezone":"Europe/Istanbul",
    "iso:country":"TR",
    "name:und_x_variant":[
        "Kol",
        "Kolk\u00f6y"
    ],
    "wof:name":"Kolkoy",
    "wof:placetype":"locality"
},
  "geometry": {"coordinates":[42.61083,41.44456],"type":"Point"}
}