{
  "type": "Feature",
  "properties": {
    "gn:admin1_code":"58",
    "gn:asciiname":"Ekinbasi",
    "gn:country_code":"TR",
    "gn:dem":1244,
    "gn:feature_class":"P",
    "gn:feature_code":"PPL",
    "gn:name":"Ekinba\u015f\u0131",
    "gn:population":0,
    "gn:timezone":"Europe/Istanbul",
    "iso:country":"TR",
    "name:und_x_variant":[
        "Kilisecik",
        "Ekinba\u015f\u0131"
    ],
    "wof:name":"Ekinbasi",
    "wof:placetype":"locality"
},
  "geometry": {"coordinates":[38.04206,39.42307],"type":"Point"}
}