{
  "type": "Feature",
  "properties": {
    "gn:country":"TR",
    "gn:fcode":"PPL",
    "gn:population":157,
    "iso:country":"TR",
    "qs:name":"Ozanl\u0131",
    "qs:photos_9r":0,
    "qs:photos_sr":0,
    "qs:pop_sr":"1",
    "wof:name":"Ozanl\u0131",
    "wof:placetype":"locality",
    "wof:population":157
},
  "geometry": {"coordinates":[37.14848,36.97504],"type":"Point"}
}