{
  "type": "Feature",
  "properties": {
    "gn:admin1_code":"65",
    "gn:asciiname":"Temrenli",
    "gn:country_code":"TR",
    "gn:dem":2214,
    "gn:feature_class":"P",
    "gn:feature_code":"PPL",
    "gn:name":"Temrenli",
    "gn:population":0,
    "gn:timezone":"Europe/Istanbul",
    "iso:country":"TR",
    "name:und_x_variant":[
        "Ka\u00e7ak",
        "Temrenli"
    ],
    "wof:name":"Temrenli",
    "wof:placetype":"locality"
},
  "geometry": {"coordinates":[44.12889000000001,39.06528],"type":"Point"}
}