{
  "type": "Feature",
  "properties": {
    "gn:admin1_code":"68",
    "gn:asciiname":"Sehitali",
    "gn:country_code":"TR",
    "gn:dem":1080,
    "gn:feature_class":"P",
    "gn:feature_code":"PPL",
    "gn:name":"\u015eehitali",
    "gn:population":0,
    "gn:timezone":"Europe/Istanbul",
    "iso:country":"TR",
    "wof:name":"Sehitali",
    "wof:placetype":"locality"
},
  "geometry": {"coordinates":[32.61038,39.7727],"type":"Point"}
}