{
  "type": "Feature",
  "properties": {
    "gn:admin1_code":"48",
    "gn:asciiname":"Gokbel",
    "gn:country_code":"TR",
    "gn:dem":432,
    "gn:feature_class":"P",
    "gn:feature_code":"PPL",
    "gn:name":"G\u00f6kbel",
    "gn:population":0,
    "gn:timezone":"Europe/Istanbul",
    "iso:country":"TR",
    "name:tur_x_preferred":[
        "G\u00f6kbel"
    ],
    "wof:name":"Gokbel",
    "wof:placetype":"locality"
},
  "geometry": {"coordinates":[27.86343,37.22044],"type":"Point"}
}