{
  "type": "Feature",
  "properties": {
    "gn:country":"TR",
    "gn:fcode":"PPL",
    "gn:pop":24816,
    "iso:country":"TR",
    "name:ara_x_preferred":[
        "\u0633\u0648\u0633\u0648\u0631\u0644\u0648\u0643"
    ],
    "name:aze_x_preferred":[
        "Susurluq"
    ],
    "name:chi_x_preferred":[
        "\u8607\u8607\u723e\u76e7\u514b"
    ],
    "name:dut_x_preferred":[
        "Susurluk"
    ],
    "name:eng_x_preferred":[
        "Susurluk"
    ],
    "name:fre_x_preferred":[
        "Susurluk"
    ],
    "name:ger_x_preferred":[
        "Susurluk"
    ],
    "name:ita_x_preferred":[
        "Distretto di Susurluk"
    ],
    "name:lit_x_preferred":[
        "Susurlukas"
    ],
    "name:may_x_preferred":[
        "Susurluk"
    ],
    "name:min_x_preferred":[
        "Susurluk"
    ],
    "name:mrj_x_preferred":[
        "\u0421\u0443\u0441\u0443\u0440\u043b\u0443\u043a"
    ],
    "name:nan_x_preferred":[
        "Susurluk"
    ],
    "name:nno_x_preferred":[
        "Susurluk"
    ],
    "name:per_x_preferred":[
        "\u0633\u0648\u0633\u0648\u0631\u0644\u0648\u06a9"
    ],
    "name:rus_x_preferred":[
        "\u0421\u0443\u0441\u0443\u0440\u043b\u0443\u043a"
    ],
    "name:swa_x_preferred":[
        "Susurluk"
    ],
    "name:tur_x_preferred":[
        "Susurluk"
    ],
    "name:unk_x_variant":[
        "Susugurlu"
    ],
    "name:urd_x_preferred":[
        "\u0633\u0648\u0633\u0648\u0631\u0644\u0648\u06a9"
    ],
    "name:vie_x_preferred":[
        "Susurluk"
    ],
    "qs:name":"Susurluk",
    "qs:name_adm0":"Turkey",
    "qs:name_adm1":"Bal\u0131kesir",
    "qs:photos_9k":1,
    "qs:photos_9r":1,
    "qs:photos_all":15,
    "qs:photos_sr":0,
    "qs:placetype":"Town",
    "qs:pop_sr":"7",
    "wd:wordcount":233,
    "wof:name":"Susurluk",
    "wof:placetype":"locality",
    "wof:population":24816
},
  "geometry": {"coordinates":[28.15778,39.91361],"type":"Point"}
}