{
  "type": "Feature",
  "properties": {
    "gn:admin1_code":"23",
    "gn:asciiname":"Atikkoy",
    "gn:country_code":"TR",
    "gn:dem":1400,
    "gn:feature_class":"P",
    "gn:feature_code":"PPL",
    "gn:name":"Atikk\u00f6y",
    "gn:population":0,
    "gn:timezone":"Europe/Istanbul",
    "iso:country":"TR",
    "name:tur_x_preferred":[
        "Atikk\u00f6y"
    ],
    "wof:name":"Atikkoy",
    "wof:placetype":"locality"
},
  "geometry": {"coordinates":[40.28817,38.79601],"type":"Point"}
}