{
  "type": "Feature",
  "properties": {
    "gn:admin1_code":"23",
    "gn:asciiname":"Goldere",
    "gn:country_code":"TR",
    "gn:dem":1354,
    "gn:feature_class":"P",
    "gn:feature_code":"PPL",
    "gn:name":"G\u00f6ldere",
    "gn:population":0,
    "gn:timezone":"Europe/Istanbul",
    "iso:country":"TR",
    "name:und_x_variant":[
        "G\u00f6ldere",
        "Karabey"
    ],
    "wof:name":"Goldere",
    "wof:placetype":"locality"
},
  "geometry": {"coordinates":[38.65888,38.70923],"type":"Point"}
}