{
  "type": "Feature",
  "properties": {
    "gn:admin1_code":"21.0",
    "gn:asciiname":"Yokuslu",
    "gn:country_code":"TR",
    "gn:dem":883,
    "gn:feature_class":"P",
    "gn:feature_code":"PPL",
    "gn:name":"Yoku\u015flu",
    "gn:population":0,
    "gn:timezone":"Europe/Istanbul",
    "iso:country":"TR",
    "name:tur_x_preferred":[
        "Yoku\u015flu"
    ],
    "wof:name":"Yokuslu",
    "wof:placetype":"locality"
},
  "geometry": {"coordinates":[40.01713,38.42164],"type":"Point"}
}