{
  "type": "Feature",
  "properties": {
    "gn:admin1_code":"25",
    "gn:asciiname":"Cepi",
    "gn:country_code":"TR",
    "gn:dem":2238,
    "gn:feature_class":"P",
    "gn:feature_code":"PPL",
    "gn:name":"\u00c7epi",
    "gn:population":0,
    "gn:timezone":"Europe/Istanbul",
    "iso:country":"TR",
    "name:und_x_variant":[
        "\u00c7epi",
        "Bayro"
    ],
    "wof:name":"Cepi",
    "wof:placetype":"locality"
},
  "geometry": {"coordinates":[42.1449,39.64736],"type":"Point"}
}