{
  "type": "Feature",
  "properties": {
    "gn:admin1_code":"21.0",
    "gn:asciiname":"Doganli",
    "gn:country_code":"TR",
    "gn:dem":764,
    "gn:feature_class":"P",
    "gn:feature_code":"PPL",
    "gn:name":"Do\u011fanl\u0131",
    "gn:population":0,
    "gn:timezone":"Europe/Istanbul",
    "iso:country":"TR",
    "name:tur_x_preferred":[
        "Do\u011fanl\u0131"
    ],
    "wof:name":"Doganli",
    "wof:placetype":"locality"
},
  "geometry": {"coordinates":[40.31544,38.22767],"type":"Point"}
}