{
  "type": "Feature",
  "properties": {
    "gn:admin1_code":"93.0",
    "gn:asciiname":"Beykoy",
    "gn:country_code":"TR",
    "gn:dem":188,
    "gn:feature_class":"P",
    "gn:feature_code":"PPL",
    "gn:name":"Beyk\u00f6y",
    "gn:population":0,
    "gn:timezone":"Europe/Istanbul",
    "iso:country":"TR",
    "name:und_x_variant":[
        "Beyk\u00f6y"
    ],
    "wof:name":"Beykoy",
    "wof:placetype":"locality"
},
  "geometry": {"coordinates":[31.16056,40.77583],"type":"Point"}
}