{
  "type": "Feature",
  "properties": {
    "gn:admin1_code":"58",
    "gn:asciiname":"Komurkaya",
    "gn:country_code":"TR",
    "gn:dem":1341,
    "gn:feature_class":"P",
    "gn:feature_code":"PPL",
    "gn:name":"K\u00f6m\u00fcrkaya",
    "gn:population":0,
    "gn:timezone":"Europe/Istanbul",
    "iso:country":"TR",
    "name:und_x_variant":[
        "K\u00f6m\u00fcrkaya",
        "Lisanl\u0131"
    ],
    "wof:name":"Komurkaya",
    "wof:placetype":"locality"
},
  "geometry": {"coordinates":[36.22278,39.29556],"type":"Point"}
}