{
  "type": "Feature",
  "properties": {
    "gn:admin1_code":"72",
    "gn:asciiname":"Civili",
    "gn:country_code":"TR",
    "gn:dem":656,
    "gn:feature_class":"P",
    "gn:feature_code":"PPL",
    "gn:name":"\u00c7ivili",
    "gn:population":0,
    "gn:timezone":"Europe/Istanbul",
    "iso:country":"TR",
    "name:tur_x_preferred":[
        "\u00c7ivili"
    ],
    "wof:name":"Civili",
    "wof:placetype":"locality"
},
  "geometry": {"coordinates":[40.06612,37.37141],"type":"Point"}
}