{
  "type": "Feature",
  "properties": {
    "gn:admin1_code":"25.0",
    "gn:asciiname":"Kirazli",
    "gn:country_code":"TR",
    "gn:dem":1376,
    "gn:feature_class":"P",
    "gn:feature_code":"PPL",
    "gn:name":"Kirazl\u0131",
    "gn:population":0,
    "gn:timezone":"Europe/Istanbul",
    "iso:country":"TR",
    "name:eng_x_preferred":[
        "Otha"
    ],
    "name:rus_x_preferred":[
        "\u041e\u0442\u0445\u0430"
    ],
    "name:und_x_variant":[
        "Kirazl\u0131"
    ],
    "wof:name":"Kirazli",
    "wof:placetype":"locality"
},
  "geometry": {"coordinates":[41.66627,40.5807],"type":"Point"}
}