{
  "type": "Feature",
  "properties": {
    "gn:admin1_code":"8.0",
    "gn:asciiname":"Gurgencik",
    "gn:country_code":"TR",
    "gn:dem":456,
    "gn:feature_class":"P",
    "gn:feature_code":"PPL",
    "gn:name":"G\u00fcrgencik",
    "gn:population":0,
    "gn:timezone":"Europe/Istanbul",
    "iso:country":"TR",
    "name:tur_x_preferred":[
        "Koptone"
    ],
    "name:tur_x_variant":[
        "Koptona"
    ],
    "name:und_x_variant":[
        "G\u00fcrgencik",
        "Ortak\u00f6y"
    ],
    "wof:name":"Gurgencik",
    "wof:placetype":"locality"
},
  "geometry": {"coordinates":[41.33772,41.28651],"type":"Point"}
}