{
  "type": "Feature",
  "properties": {
    "gn:admin1_code":"71",
    "gn:asciiname":"Tepe",
    "gn:country_code":"TR",
    "gn:dem":1550,
    "gn:feature_class":"P",
    "gn:feature_code":"PPL",
    "gn:name":"Tepe",
    "gn:population":0,
    "gn:timezone":"Europe/Istanbul",
    "iso:country":"TR",
    "name:bul_x_preferred":[
        "\u0422\u0435\u043f\u0435"
    ],
    "name:ceb_x_preferred":[
        "Tepe"
    ],
    "name:deu_x_preferred":[
        "Tepe"
    ],
    "name:fra_x_preferred":[
        "Tepe"
    ],
    "name:nld_x_preferred":[
        "Tepe"
    ],
    "name:ron_x_preferred":[
        "Tepe"
    ],
    "name:rus_x_preferred":[
        "\u0422\u0435\u043f\u0435"
    ],
    "name:swe_x_preferred":[
        "Tepe"
    ],
    "name:tur_x_preferred":[
        "Tepe"
    ],
    "name:und_x_variant":[
        "Kirligiret",
        "Tepek\u00f6y",
        "Tepe"
    ],
    "wof:name":"Tepe",
    "wof:placetype":"locality"
},
  "geometry": {"coordinates":[32.16388,38.0704],"type":"Point"}
}