{
  "type": "Feature",
  "properties": {
    "gn:admin1_code":"90",
    "gn:asciiname":"Balikli",
    "gn:country_code":"TR",
    "gn:dem":808,
    "gn:feature_class":"P",
    "gn:feature_code":"PPL",
    "gn:name":"Bal\u0131kl\u0131",
    "gn:population":0,
    "gn:timezone":"Europe/Istanbul",
    "iso:country":"TR",
    "name:tur_x_preferred":[
        "Bal\u0131kl\u0131"
    ],
    "wof:name":"Balikli",
    "wof:placetype":"locality"
},
  "geometry": {"coordinates":[36.93253,36.90639],"type":"Point"}
}