{
  "type": "Feature",
  "properties": {
    "gn:admin1_code":"63",
    "gn:asciiname":"Redzholar",
    "gn:country_code":"TR",
    "gn:dem":824,
    "gn:feature_class":"P",
    "gn:feature_code":"PPL",
    "gn:name":"Redzholar",
    "gn:population":0,
    "gn:timezone":"Europe/Istanbul",
    "iso:country":"TR",
    "wof:name":"Redzholar",
    "wof:placetype":"locality"
},
  "geometry": {"coordinates":[38.72797,37.20978],"type":"Point"}
}