{
  "type": "Feature",
  "properties": {
    "gn:country":"TR",
    "gn:fcode":"PPL",
    "gn:population":363,
    "iso:country":"TR",
    "name:tur_x_preferred":[
        "Odak\u00f6y"
    ],
    "qs:name":"Odak\u00f6y",
    "qs:photos_9r":0,
    "qs:photos_sr":0,
    "qs:pop_sr":"2",
    "wof:name":"Odak\u00f6y",
    "wof:placetype":"locality",
    "wof:population":363
},
  "geometry": {"coordinates":[40.21278,36.99222],"type":"Point"}
}