{
  "type": "Feature",
  "properties": {
    "gn:admin1_code":"20",
    "gn:asciiname":"Kocapinar",
    "gn:country_code":"TR",
    "gn:dem":1216,
    "gn:feature_class":"P",
    "gn:feature_code":"PPL",
    "gn:name":"Kocap\u0131nar",
    "gn:population":0,
    "gn:timezone":"Europe/Istanbul",
    "iso:country":"TR",
    "name:tur_x_preferred":[
        "Kocap\u0131nar"
    ],
    "name:tur_x_variant":[
        "Yukar\u0131kara\u00e7ay"
    ],
    "wof:name":"Kocapinar",
    "wof:placetype":"locality"
},
  "geometry": {"coordinates":[29.37144,37.64784],"type":"Point"}
}