{
  "type": "Feature",
  "properties": {
    "gn:admin1_code":"58",
    "gn:asciiname":"Yilanhuyuk",
    "gn:country_code":"TR",
    "gn:dem":1775,
    "gn:feature_class":"P",
    "gn:feature_code":"PPL",
    "gn:name":"Y\u0131lanh\u00fcy\u00fck",
    "gn:population":0,
    "gn:timezone":"Europe/Istanbul",
    "iso:country":"TR",
    "name:und_x_variant":[
        "Y\u0131lanb\u00fcy\u00fck",
        "Y\u0131lanh\u00fcy\u00fck K\u00f6y\u00fc",
        "Y\u0131lanh\u00fcy\u00fck"
    ],
    "wof:name":"Yilanhuyuk",
    "wof:placetype":"locality"
},
  "geometry": {"coordinates":[37.18864,38.85831],"type":"Point"}
}