{
  "type": "Feature",
  "properties": {
    "gn:admin1_code":"35",
    "gn:asciiname":"Zeamet",
    "gn:country_code":"TR",
    "gn:dem":334,
    "gn:feature_class":"P",
    "gn:feature_code":"PPL",
    "gn:name":"Zeamet",
    "gn:population":0,
    "gn:timezone":"Europe/Istanbul",
    "iso:country":"TR",
    "name:tur_x_preferred":[
        "Zeamet"
    ],
    "wof:name":"Zeamet",
    "wof:placetype":"locality"
},
  "geometry": {"coordinates":[27.69008,38.41588],"type":"Point"}
}