{
  "type": "Feature",
  "properties": {
    "gn:admin1_code":"20",
    "gn:asciiname":"Ciftepinarlar",
    "gn:country_code":"TR",
    "gn:dem":937,
    "gn:feature_class":"P",
    "gn:feature_code":"PPL",
    "gn:name":"\u00c7iftep\u0131narlar",
    "gn:population":0,
    "gn:timezone":"Europe/Istanbul",
    "iso:country":"TR",
    "name:tur_x_preferred":[
        "\u00c7iftep\u0131narlar"
    ],
    "wof:name":"Ciftepinarlar",
    "wof:placetype":"locality"
},
  "geometry": {"coordinates":[29.14087,37.14731],"type":"Point"}
}