{
  "type": "Feature",
  "properties": {
    "gn:admin1_code":"81",
    "gn:asciiname":"Guven",
    "gn:country_code":"TR",
    "gn:dem":1118,
    "gn:feature_class":"P",
    "gn:feature_code":"PPL",
    "gn:name":"G\u00fcven",
    "gn:population":0,
    "gn:timezone":"Europe/Istanbul",
    "iso:country":"TR",
    "name:und_x_variant":[
        "G\u00fcven",
        "Kelerba\u015f\u0131"
    ],
    "wof:name":"Guven",
    "wof:placetype":"locality"
},
  "geometry": {"coordinates":[35.36029,37.47369000000001],"type":"Point"}
}