{
  "type": "Feature",
  "properties": {
    "gn:admin1_code":"2.0",
    "gn:asciiname":"Akyurek",
    "gn:country_code":"TR",
    "gn:dem":759,
    "gn:feature_class":"P",
    "gn:feature_code":"PPL",
    "gn:name":"Aky\u00fcrek",
    "gn:population":0,
    "gn:timezone":"Europe/Istanbul",
    "iso:country":"TR",
    "name:tur_x_preferred":[
        "Aky\u00fcrek"
    ],
    "wof:name":"Akyurek",
    "wof:placetype":"locality"
},
  "geometry": {"coordinates":[38.99536,38.02543],"type":"Point"}
}