{
  "type": "Feature",
  "properties": {
    "gn:admin1_code":"25",
    "gn:asciiname":"Alabayir",
    "gn:country_code":"TR",
    "gn:dem":2027,
    "gn:feature_class":"P",
    "gn:feature_code":"PPL",
    "gn:name":"Alabay\u0131r",
    "gn:population":0,
    "gn:timezone":"Europe/Istanbul",
    "iso:country":"TR",
    "name:tur_x_preferred":[
        "Alabay\u0131r"
    ],
    "name:und_x_variant":[
        "Meman",
        "Akbay\u0131r",
        "Maman"
    ],
    "wof:name":"Alabayir",
    "wof:placetype":"locality"
},
  "geometry": {"coordinates":[41.18429,39.54044],"type":"Point"}
}