{
  "type": "Feature",
  "properties": {
    "gn:admin1_code":"31",
    "gn:asciiname":"Kumtepe",
    "gn:country_code":"TR",
    "gn:dem":81,
    "gn:feature_class":"P",
    "gn:feature_code":"PPL",
    "gn:name":"Kumtepe",
    "gn:population":0,
    "gn:timezone":"Europe/Istanbul",
    "iso:country":"TR",
    "name:deu_x_preferred":[
        "Kumtepe"
    ],
    "name:nld_x_preferred":[
        "Kumtepe"
    ],
    "name:rus_x_preferred":[
        "\u041a\u0443\u043c\u0442\u0435\u043f\u0435"
    ],
    "name:spa_x_preferred":[
        "Kum Tepe"
    ],
    "name:tur_x_preferred":[
        "Kumtepe"
    ],
    "wof:name":"Kumtepe",
    "wof:placetype":"locality"
},
  "geometry": {"coordinates":[36.35754,36.3336],"type":"Point"}
}