{
  "type": "Feature",
  "properties": {
    "gn:admin1_code":"45",
    "gn:asciiname":"Horzum Embelli",
    "gn:country_code":"TR",
    "gn:dem":420,
    "gn:feature_class":"P",
    "gn:feature_code":"PPL",
    "gn:name":"Horzum Embelli",
    "gn:population":0,
    "gn:timezone":"Europe/Istanbul",
    "iso:country":"TR",
    "name:tur_x_preferred":[
        "Horzum Embelli"
    ],
    "name:tur_x_variant":[
        "Embelli"
    ],
    "wof:name":"Horzum Embelli",
    "wof:placetype":"locality"
},
  "geometry": {"coordinates":[28.36263,38.37073],"type":"Point"}
}