{
  "type": "Feature",
  "properties": {
    "gn:admin1_code":"81",
    "gn:asciiname":"Igdebel",
    "gn:country_code":"TR",
    "gn:dem":1613,
    "gn:feature_class":"P",
    "gn:feature_code":"PPL",
    "gn:name":"\u0130\u011fdebel",
    "gn:population":0,
    "gn:timezone":"Europe/Istanbul",
    "iso:country":"TR",
    "wof:name":"Igdebel",
    "wof:placetype":"locality"
},
  "geometry": {"coordinates":[36.3694,38.27616],"type":"Point"}
}