{
  "type": "Feature",
  "properties": {
    "gn:admin1_code":"66",
    "gn:asciiname":"Karacokrak",
    "gn:country_code":"TR",
    "gn:dem":1185,
    "gn:feature_class":"P",
    "gn:feature_code":"PPL",
    "gn:name":"Kara\u00e7okrak",
    "gn:population":0,
    "gn:timezone":"Europe/Istanbul",
    "iso:country":"TR",
    "wof:name":"Karacokrak",
    "wof:placetype":"locality"
},
  "geometry": {"coordinates":[35.64861,39.72177],"type":"Point"}
}