{
  "type": "Feature",
  "properties": {
    "gn:admin1_code":"66",
    "gn:asciiname":"Asagicumafakili",
    "gn:country_code":"TR",
    "gn:dem":1203,
    "gn:feature_class":"P",
    "gn:feature_code":"PPL",
    "gn:name":"A\u015fa\u011f\u0131cumafak\u0131l\u0131",
    "gn:population":0,
    "gn:timezone":"Europe/Istanbul",
    "iso:country":"TR",
    "name:und_x_variant":[
        "Cumafak\u0131l\u0131",
        "A\u015fa\u011f\u0131cumafak\u0131l\u0131",
        "Cumafak\u0131l\u0131zir"
    ],
    "wof:name":"Asagicumafakili",
    "wof:placetype":"locality"
},
  "geometry": {"coordinates":[35.16612,39.8806],"type":"Point"}
}