{
  "type": "Feature",
  "properties": {
    "gn:admin1_code":"71",
    "gn:asciiname":"Dinlendik",
    "gn:country_code":"TR",
    "gn:dem":1031,
    "gn:feature_class":"P",
    "gn:feature_code":"PPL",
    "gn:name":"Dinlendik",
    "gn:population":0,
    "gn:timezone":"Europe/Istanbul",
    "iso:country":"TR",
    "wof:name":"Dinlendik",
    "wof:placetype":"locality"
},
  "geometry": {"coordinates":[32.80544,37.47403],"type":"Point"}
}