{
  "type": "Feature",
  "properties": {
    "gn:country":"TR",
    "gn:fcode":"PPL",
    "gn:population":532,
    "iso:country":"TR",
    "name:tur_x_preferred":[
        "Kepezli"
    ],
    "qs:name":"Kepezli",
    "qs:photos_9r":0,
    "qs:photos_sr":0,
    "qs:pop_sr":"2",
    "wof:name":"Kepezli",
    "wof:placetype":"locality",
    "wof:population":532
},
  "geometry": {"coordinates":[39.25333,36.67889],"type":"Point"}
}