{
  "type": "Feature",
  "properties": {
    "gn:admin1_code":"23",
    "gn:asciiname":"Cicekli",
    "gn:country_code":"TR",
    "gn:dem":1223,
    "gn:feature_class":"P",
    "gn:feature_code":"PPL",
    "gn:name":"\u00c7i\u00e7ekli",
    "gn:population":0,
    "gn:timezone":"Europe/Istanbul",
    "iso:country":"TR",
    "name:tur_x_preferred":[
        "\u00c7i\u00e7ekli"
    ],
    "wof:name":"Cicekli",
    "wof:placetype":"locality"
},
  "geometry": {"coordinates":[39.86667,38.43333],"type":"Point"}
}