{
  "type": "Feature",
  "properties": {
    "gn:country":"TR",
    "gn:fcode":"PPL",
    "gn:pop":0,
    "iso:country":"TR",
    "name:unk_x_variant":[
        "Samutlu"
    ],
    "qs:name":"Temelli",
    "qs:name_adm0":"Turkey",
    "qs:name_adm1":"Ankara",
    "qs:photos_9k":1,
    "qs:photos_9r":2,
    "qs:photos_all":42,
    "qs:photos_sr":0,
    "qs:placetype":"Town",
    "qs:pop_sr":"5",
    "wof:name":"Temelli",
    "wof:placetype":"locality",
    "wof:population":0
},
  "geometry": {"coordinates":[32.35528,39.7275],"type":"Point"}
}