{
  "type": "Feature",
  "properties": {
    "gn:admin1_code":"81",
    "gn:asciiname":"Gaffarusagi",
    "gn:country_code":"TR",
    "gn:dem":1735,
    "gn:feature_class":"P",
    "gn:feature_code":"PPL",
    "gn:name":"Gaffaru\u015fa\u011f\u0131",
    "gn:population":0,
    "gn:timezone":"Europe/Istanbul",
    "iso:country":"TR",
    "name:tur_x_preferred":[
        "Gaffaru\u015fa\u011f\u0131"
    ],
    "name:tur_x_variant":[
        "K\u00e2n"
    ],
    "wof:name":"Gaffarusagi",
    "wof:placetype":"locality"
},
  "geometry": {"coordinates":[36.33597,38.22479000000001],"type":"Point"}
}