{
  "type": "Feature",
  "properties": {
    "gn:admin1_code":"26.0",
    "gn:asciiname":"Igdir",
    "gn:country_code":"TR",
    "gn:dem":231,
    "gn:feature_class":"P",
    "gn:feature_code":"PPL",
    "gn:name":"\u0130\u011fdir",
    "gn:population":0,
    "gn:timezone":"Europe/Istanbul",
    "iso:country":"TR",
    "name:und_x_variant":[
        "\u0130ydil",
        "\u0130\u011fdir"
    ],
    "wof:name":"Igdir",
    "wof:placetype":"locality"
},
  "geometry": {"coordinates":[30.64278,40.04757],"type":"Point"}
}