{
  "type": "Feature",
  "properties": {
    "gn:admin1_code":"09",
    "gn:asciiname":"Alhan",
    "gn:country_code":"TR",
    "gn:dem":60,
    "gn:feature_class":"P",
    "gn:feature_code":"PPL",
    "gn:name":"Alhan",
    "gn:population":0,
    "gn:timezone":"Europe/Istanbul",
    "iso:country":"TR",
    "wof:name":"Alhan",
    "wof:placetype":"locality"
},
  "geometry": {"coordinates":[28.16608,37.80965],"type":"Point"}
}