{
  "type": "Feature",
  "properties": {
    "gn:admin1_code":"65.0",
    "gn:asciiname":"Binbasicesmesi",
    "gn:country_code":"TR",
    "gn:dem":2244,
    "gn:feature_class":"P",
    "gn:feature_code":"PPL",
    "gn:name":"Binba\u015f\u0131\u00e7esmesi",
    "gn:population":0,
    "gn:timezone":"Europe/Istanbul",
    "iso:country":"TR",
    "name:tur_x_preferred":[
        "Binba\u015f\u0131\u00e7esmesi"
    ],
    "wof:name":"Binbasicesmesi",
    "wof:placetype":"locality"
},
  "geometry": {"coordinates":[43.84377,38.91607],"type":"Point"}
}