{
  "type": "Feature",
  "properties": {
    "gn:admin1_code":"37.0",
    "gn:asciiname":"Uyukoren",
    "gn:country_code":"TR",
    "gn:dem":1173,
    "gn:feature_class":"P",
    "gn:feature_code":"PPL",
    "gn:name":"\u00dcy\u00fck\u00f6ren",
    "gn:population":0,
    "gn:timezone":"Europe/Istanbul",
    "iso:country":"TR",
    "name:und_x_variant":[
        "\u00d6y\u00fckveren",
        "Uy\u00fckveren",
        "\u00d6y\u00fckviran",
        "Uy\u00fckveran",
        "\u00dcy\u00fck\u00f6ren"
    ],
    "wof:name":"Uyukoren",
    "wof:placetype":"locality"
},
  "geometry": {"coordinates":[33.44745,41.36096],"type":"Point"}
}