{
  "type": "Feature",
  "properties": {
    "gn:admin1_code":"32",
    "gn:asciiname":"Yuksekkoy",
    "gn:country_code":"TR",
    "gn:dem":15,
    "gn:feature_class":"P",
    "gn:feature_code":"PPL",
    "gn:name":"Y\u00fcksekk\u00f6y",
    "gn:population":0,
    "gn:timezone":"Europe/Istanbul",
    "iso:country":"TR",
    "name:und_x_variant":[
        "Y\u00fcksekk\u00f6y",
        "Y\u00fcksek"
    ],
    "wof:name":"Yuksekkoy",
    "wof:placetype":"locality"
},
  "geometry": {"coordinates":[35.04497,36.9339],"type":"Point"}
}