{
  "type": "Feature",
  "properties": {
    "gn:admin1_code":"49",
    "gn:asciiname":"Kolan",
    "gn:country_code":"TR",
    "gn:dem":1468,
    "gn:feature_class":"P",
    "gn:feature_code":"PPL",
    "gn:name":"Kolan",
    "gn:population":0,
    "gn:timezone":"Europe/Istanbul",
    "iso:country":"TR",
    "name:bos_x_preferred":[
        "Kolan"
    ],
    "name:deu_x_preferred":[
        "Kolan"
    ],
    "name:hrv_x_preferred":[
        "Kolan"
    ],
    "name:hun_x_preferred":[
        "Kolan"
    ],
    "name:ita_x_preferred":[
        "Colane"
    ],
    "name:nld_x_preferred":[
        "Kolan"
    ],
    "name:pol_x_preferred":[
        "Gmina Kolan"
    ],
    "name:ron_x_preferred":[
        "Comuna Kolan"
    ],
    "name:slv_x_preferred":[
        "Kolan"
    ],
    "name:srp_x_preferred":[
        "\u041a\u043e\u043b\u0430\u043d"
    ],
    "name:ukr_x_preferred":[
        "\u041a\u043e\u043b\u0430\u043d"
    ],
    "name:und_x_variant":[
        "Karagivi\u00e7"
    ],
    "wof:name":"Kolan",
    "wof:placetype":"locality"
},
  "geometry": {"coordinates":[41.25642,39.20356],"type":"Point"}
}