{
  "type": "Feature",
  "properties": {
    "gn:admin1_code":"49",
    "gn:asciiname":"Kolan",
    "gn:country_code":"TR",
    "gn:dem":1468,
    "gn:feature_class":"P",
    "gn:feature_code":"PPL",
    "gn:name":"Kolan",
    "gn:population":0,
    "gn:timezone":"Europe/Istanbul",
    "iso:country":"TR",
    "name:und_x_variant":[
        "Karagivi\u00e7"
    ],
    "wof:name":"Kolan",
    "wof:placetype":"locality"
},
  "geometry": {"coordinates":[41.25642,39.20356],"type":"Point"}
}