{
  "type": "Feature",
  "properties": {
    "gn:admin1_code":"71",
    "gn:asciiname":"Cayirbasi",
    "gn:country_code":"TR",
    "gn:dem":998,
    "gn:feature_class":"P",
    "gn:feature_code":"PPL",
    "gn:name":"\u00c7ay\u0131rba\u015f\u0131",
    "gn:population":0,
    "gn:timezone":"Europe/Istanbul",
    "iso:country":"TR",
    "wof:name":"Cayirbasi",
    "wof:placetype":"locality"
},
  "geometry": {"coordinates":[32.23917,38.86861],"type":"Point"}
}