{
  "type": "Feature",
  "properties": {
    "gn:admin1_code":"35",
    "gn:asciiname":"Avunduruk",
    "gn:country_code":"TR",
    "gn:dem":314,
    "gn:feature_class":"P",
    "gn:feature_code":"PPL",
    "gn:name":"Avunduruk",
    "gn:population":0,
    "gn:timezone":"Europe/Istanbul",
    "iso:country":"TR",
    "name:tur_x_preferred":[
        "Avunduruk"
    ],
    "wof:name":"Avunduruk",
    "wof:placetype":"locality"
},
  "geometry": {"coordinates":[27.20546,39.21126],"type":"Point"}
}