{
  "type": "Feature",
  "properties": {
    "gn:admin1_code":"76.0",
    "gn:asciiname":"Bacak",
    "gn:country_code":"TR",
    "gn:dem":670,
    "gn:feature_class":"P",
    "gn:feature_code":"PPL",
    "gn:name":"Bacak",
    "gn:population":0,
    "gn:timezone":"Europe/Istanbul",
    "iso:country":"TR",
    "wof:name":"Bacak",
    "wof:placetype":"locality"
},
  "geometry": {"coordinates":[41.23617,38.16071],"type":"Point"}
}