{
  "type": "Feature",
  "properties": {
    "gn:admin1_code":"16.0",
    "gn:asciiname":"Cavus",
    "gn:country_code":"TR",
    "gn:dem":424,
    "gn:feature_class":"P",
    "gn:feature_code":"PPL",
    "gn:name":"\u00c7avus",
    "gn:population":0,
    "gn:timezone":"Europe/Istanbul",
    "iso:country":"TR",
    "name:und_x_variant":[
        "\u00c7avus",
        "\u00c7avu\u015fk\u00f6y"
    ],
    "wof:name":"Cavus",
    "wof:placetype":"locality"
},
  "geometry": {"coordinates":[29.46667,40.16667],"type":"Point"}
}