{
  "type": "Feature",
  "properties": {
    "gn:admin1_code":"38",
    "gn:asciiname":"Buyukkaramanli",
    "gn:country_code":"TR",
    "gn:dem":1509,
    "gn:feature_class":"P",
    "gn:feature_code":"PPL",
    "gn:name":"B\u00fcy\u00fckkaramanl\u0131",
    "gn:population":0,
    "gn:timezone":"Europe/Istanbul",
    "iso:country":"TR",
    "wof:name":"Buyukkaramanli",
    "wof:placetype":"locality"
},
  "geometry": {"coordinates":[36.25,38.61667],"type":"Point"}
}