{
  "type": "Feature",
  "properties": {
    "gn:admin1_code":"10",
    "gn:asciiname":"Piyade",
    "gn:country_code":"TR",
    "gn:dem":679,
    "gn:feature_class":"P",
    "gn:feature_code":"PPL",
    "gn:name":"Piyade",
    "gn:population":0,
    "gn:timezone":"Europe/Istanbul",
    "iso:country":"TR",
    "name:tur_x_preferred":[
        "Piyade"
    ],
    "wof:name":"Piyade",
    "wof:placetype":"locality"
},
  "geometry": {"coordinates":[28.36755,39.70149],"type":"Point"}
}