{
  "type": "Feature",
  "properties": {
    "gn:admin1_code":"25.0",
    "gn:asciiname":"Pinarkoy",
    "gn:country_code":"TR",
    "gn:dem":1973,
    "gn:feature_class":"P",
    "gn:feature_code":"PPL",
    "gn:name":"P\u0131nark\u00f6y",
    "gn:population":0,
    "gn:timezone":"Europe/Istanbul",
    "iso:country":"TR",
    "name:tur_x_preferred":[
        "P\u0131nark\u00f6y"
    ],
    "wof:name":"Pinarkoy",
    "wof:placetype":"locality"
},
  "geometry": {"coordinates":[41.62256,39.31835],"type":"Point"}
}