{
  "type": "Feature",
  "properties": {
    "gn:admin1_code":"77.0",
    "gn:asciiname":"Rustukoy",
    "gn:country_code":"TR",
    "gn:dem":1646,
    "gn:feature_class":"P",
    "gn:feature_code":"PPL",
    "gn:name":"R\u00fc\u015ft\u00fck\u00f6y",
    "gn:population":0,
    "gn:timezone":"Europe/Istanbul",
    "iso:country":"TR",
    "name:ceb_x_preferred":[
        "R\u00fc\u015ft\u00fck\u00f6y"
    ],
    "name:msa_x_preferred":[
        "R\u00fc\u015ft\u00fc"
    ],
    "name:tur_x_preferred":[
        "R\u00fc\u015ft\u00fck\u00f6y"
    ],
    "wof:name":"Rustukoy",
    "wof:placetype":"locality"
},
  "geometry": {"coordinates":[39.97631,40.21945],"type":"Point"}
}