{
  "type": "Feature",
  "properties": {
    "gn:admin1_code":"62",
    "gn:asciiname":"Seyhomerler",
    "gn:country_code":"TR",
    "gn:dem":1347,
    "gn:feature_class":"P",
    "gn:feature_code":"PPL",
    "gn:name":"\u015eeyh\u00f6merler",
    "gn:population":0,
    "gn:timezone":"Europe/Istanbul",
    "iso:country":"TR",
    "wof:name":"Seyhomerler",
    "wof:placetype":"locality"
},
  "geometry": {"coordinates":[39.41667,39.16667],"type":"Point"}
}