{
  "type": "Feature",
  "properties": {
    "gn:admin1_code":"25",
    "gn:asciiname":"Yuzoren",
    "gn:country_code":"TR",
    "gn:dem":1633,
    "gn:feature_class":"P",
    "gn:feature_code":"PPL",
    "gn:name":"Y\u00fcz\u00f6ren",
    "gn:population":0,
    "gn:timezone":"Europe/Istanbul",
    "iso:country":"TR",
    "name:und_x_variant":[
        "Y\u00fcz\u00f6ren",
        "Y\u00fczveren"
    ],
    "wof:name":"Yuzoren",
    "wof:placetype":"locality"
},
  "geometry": {"coordinates":[42.10415,39.98655],"type":"Point"}
}