{
  "type": "Feature",
  "properties": {
    "gn:country":"TR",
    "gn:fcode":"PPL",
    "gn:pop":221,
    "iso:country":"TR",
    "name:rus_x_preferred":[
        "Meskenk\u00eby"
    ],
    "name:tur_x_preferred":[
        "\u00c7amyurt"
    ],
    "name:unk_x_variant":[
        "Mesken"
    ],
    "qs:name":"\u00c7amyurt",
    "qs:photos_9r":0,
    "qs:photos_sr":0,
    "qs:pop_sr":"2",
    "wof:name":"\u00c7amyurt",
    "wof:placetype":"locality",
    "wof:population":221
},
  "geometry": {"coordinates":[41.11111,37.41222],"type":"Point"}
}