{
  "type": "Feature",
  "properties": {
    "gn:admin1_code":"16.0",
    "gn:asciiname":"Korubasi",
    "gn:country_code":"TR",
    "gn:dem":485,
    "gn:feature_class":"P",
    "gn:feature_code":"PPL",
    "gn:name":"Koruba\u015f\u0131",
    "gn:population":0,
    "gn:timezone":"Europe/Istanbul",
    "iso:country":"TR",
    "name:und_x_variant":[
        "Balyoz",
        "Kelemitna",
        "Balyas",
        "Balyuz",
        "Balyaz",
        "Koruba\u015f\u0131"
    ],
    "wof:name":"Korubasi",
    "wof:placetype":"locality"
},
  "geometry": {"coordinates":[28.7501,40.10454],"type":"Point"}
}