{
  "type": "Feature",
  "properties": {
    "gn:admin1_code":"84.0",
    "gn:asciiname":"Ceperli",
    "gn:country_code":"TR",
    "gn:dem":1752,
    "gn:feature_class":"P",
    "gn:feature_code":"PPL",
    "gn:name":"\u00c7eperli",
    "gn:population":0,
    "gn:timezone":"Europe/Istanbul",
    "iso:country":"TR",
    "name:und_x_variant":[
        "K\u0131z\u0131lveren",
        "K\u0131z\u0131lveran",
        "K\u0131z\u0131lviran",
        "\u00c7eperli"
    ],
    "wof:name":"Ceperli",
    "wof:placetype":"locality"
},
  "geometry": {"coordinates":[42.97819000000001,40.1949],"type":"Point"}
}