{
  "type": "Feature",
  "properties": {
    "gn:admin1_code":"71",
    "gn:asciiname":"Cukurkavak",
    "gn:country_code":"TR",
    "gn:dem":1228,
    "gn:feature_class":"P",
    "gn:feature_code":"PPL",
    "gn:name":"\u00c7ukurkavak",
    "gn:population":0,
    "gn:timezone":"Europe/Istanbul",
    "iso:country":"TR",
    "wof:name":"Cukurkavak",
    "wof:placetype":"locality"
},
  "geometry": {"coordinates":[32.50502,37.29745],"type":"Point"}
}