{
  "type": "Feature",
  "properties": {
    "gn:admin1_code":"31.0",
    "gn:asciiname":"Koyunbeyli",
    "gn:country_code":"TR",
    "gn:dem":1101,
    "gn:feature_class":"P",
    "gn:feature_code":"PPL",
    "gn:name":"Koyunbeyli",
    "gn:population":0,
    "gn:timezone":"Europe/Istanbul",
    "iso:country":"TR",
    "name:und_x_variant":[
        "Koyunbeyli Yayla-s\u0131",
        "Koyunbeyli"
    ],
    "wof:name":"Koyunbeyli",
    "wof:placetype":"locality"
},
  "geometry": {"coordinates":[36.33361,36.92833],"type":"Point"}
}