{
  "type": "Feature",
  "properties": {
    "gn:admin1_code":"63.0",
    "gn:asciiname":"Raktel",
    "gn:country_code":"TR",
    "gn:dem":380,
    "gn:feature_class":"P",
    "gn:feature_code":"PPL",
    "gn:name":"Raktel",
    "gn:population":0,
    "gn:timezone":"Europe/Istanbul",
    "iso:country":"TR",
    "wof:name":"Raktel",
    "wof:placetype":"locality"
},
  "geometry": {"coordinates":[38.79389000000001,36.74722],"type":"Point"}
}