{
  "type": "Feature",
  "properties": {
    "gn:admin1_code":"62",
    "gn:asciiname":"Isitma",
    "gn:country_code":"TR",
    "gn:dem":1403,
    "gn:feature_class":"P",
    "gn:feature_code":"PPL",
    "gn:name":"Is\u0131tma",
    "gn:population":0,
    "gn:timezone":"Europe/Istanbul",
    "iso:country":"TR",
    "name:und_x_variant":[
        "Is\u0131tma",
        "Pardi"
    ],
    "wof:name":"Isitma",
    "wof:placetype":"locality"
},
  "geometry": {"coordinates":[39.12756,39.3142],"type":"Point"}
}