{
  "type": "Feature",
  "properties": {
    "gn:admin1_code":"46",
    "gn:asciiname":"Hacieyuplu",
    "gn:country_code":"TR",
    "gn:dem":1264,
    "gn:feature_class":"P",
    "gn:feature_code":"PPL",
    "gn:name":"Hac\u0131ey\u00fcpl\u00fc",
    "gn:population":0,
    "gn:timezone":"Europe/Istanbul",
    "iso:country":"TR",
    "name:und_x_variant":[
        "Hac\u0131eyy\u00fcpl\u00fc",
        "Hac\u0131eyaplu",
        "Hac\u0131eyyoplu",
        "Ha\u00e7ino\u011flu",
        "Hac\u0131ey\u00fcpl\u00fc"
    ],
    "wof:name":"Hacieyuplu",
    "wof:placetype":"locality"
},
  "geometry": {"coordinates":[37.11554,37.71652],"type":"Point"}
}