{
  "type": "Feature",
  "properties": {
    "gn:admin1_code":"76.0",
    "gn:asciiname":"Sinemarik",
    "gn:country_code":"TR",
    "gn:dem":903,
    "gn:feature_class":"P",
    "gn:feature_code":"PPL",
    "gn:name":"Sinemarik",
    "gn:population":0,
    "gn:timezone":"Europe/Istanbul",
    "iso:country":"TR",
    "wof:name":"Sinemarik",
    "wof:placetype":"locality"
},
  "geometry": {"coordinates":[41.37504000000001,38.29809],"type":"Point"}
}