{
  "type": "Feature",
  "properties": {
    "gn:admin1_code":"83",
    "gn:asciiname":"Korhaci Obasi",
    "gn:country_code":"TR",
    "gn:dem":571,
    "gn:feature_class":"P",
    "gn:feature_code":"PPL",
    "gn:name":"K\u00f6rhac\u0131 Obas\u0131",
    "gn:population":0,
    "gn:timezone":"Europe/Istanbul",
    "iso:country":"TR",
    "name:tur_x_preferred":[
        "K\u00f6rhac\u0131 Obas\u0131"
    ],
    "wof:name":"Korhaci Obasi",
    "wof:placetype":"locality"
},
  "geometry": {"coordinates":[37.62983,37.3975],"type":"Point"}
}