{
  "type": "Feature",
  "properties": {
    "gn:admin1_code":"35",
    "gn:asciiname":"Uzunburun",
    "gn:country_code":"TR",
    "gn:dem":67,
    "gn:feature_class":"P",
    "gn:feature_code":"PPL",
    "gn:name":"Uzunburun",
    "gn:population":0,
    "gn:timezone":"Europe/Istanbul",
    "iso:country":"TR",
    "name:ceb_x_preferred":[
        "Uzunburun"
    ],
    "name:msa_x_preferred":[
        "Uzunburun"
    ],
    "wof:name":"Uzunburun",
    "wof:placetype":"locality"
},
  "geometry": {"coordinates":[26.9087,39.03308],"type":"Point"}
}