{
  "type": "Feature",
  "properties": {
    "gn:country":"TR",
    "gn:fcode":"PPL",
    "gn:pop":176,
    "iso:country":"TR",
    "name:rus_x_preferred":[
        "Kersentashk\u00eby"
    ],
    "name:unk_x_variant":[
        "Kersenta\u015f K\u00f6y\u00fc"
    ],
    "qs:name":"Kersenta\u015f",
    "qs:photos_9r":0,
    "qs:photos_sr":0,
    "qs:pop_sr":"1",
    "wof:name":"Kersenta\u015f",
    "wof:placetype":"locality",
    "wof:population":176
},
  "geometry": {"coordinates":[37.68744,36.76083],"type":"Point"}
}