{
  "type": "Feature",
  "properties": {
    "gn:admin1_code":"46",
    "gn:asciiname":"Canbaz",
    "gn:country_code":"TR",
    "gn:dem":1037,
    "gn:feature_class":"P",
    "gn:feature_code":"PPL",
    "gn:name":"Canbaz",
    "gn:population":0,
    "gn:timezone":"Europe/Istanbul",
    "iso:country":"TR",
    "wof:name":"Canbaz",
    "wof:placetype":"locality"
},
  "geometry": {"coordinates":[36.30559,37.67393],"type":"Point"}
}