{
  "type": "Feature",
  "properties": {
    "gn:admin1_code":"16",
    "gn:asciiname":"Tahtakopru",
    "gn:country_code":"TR",
    "gn:dem":578,
    "gn:feature_class":"P",
    "gn:feature_code":"PPLA3",
    "gn:name":"Tahtak\u00f6pr\u00fc",
    "gn:population":1575,
    "gn:timezone":"Europe/Istanbul",
    "iso:country":"TR",
    "name:ceb_x_preferred":[
        "Tahtak\u00f6pr\u00fc"
    ],
    "name:fas_x_preferred":[
        "\u062a\u062e\u062a\u0647\u200c\u06a9\u0648\u067e\u0631\u0648"
    ],
    "wof:name":"Tahtakopru",
    "wof:placetype":"locality",
    "wof:population":1575
},
  "geometry": {"coordinates":[29.65,39.95],"type":"Point"}
}