{
  "type": "Feature",
  "properties": {
    "gn:admin1_code":"16.0",
    "gn:asciiname":"Hotanli",
    "gn:country_code":"TR",
    "gn:dem":11,
    "gn:feature_class":"P",
    "gn:feature_code":"PPL",
    "gn:name":"Hotanl\u0131",
    "gn:population":0,
    "gn:timezone":"Europe/Istanbul",
    "iso:country":"TR",
    "name:tur_x_preferred":[
        "Hotanl\u0131"
    ],
    "wof:name":"Hotanli",
    "wof:placetype":"locality"
},
  "geometry": {"coordinates":[28.31139000000001,40.20889],"type":"Point"}
}