{
  "type": "Feature",
  "properties": {
    "iso:country":"TR",
    "name:baq_x_preferred":[
        "Sancaktepe"
    ],
    "name:cat_x_preferred":[
        "Sancaktepe"
    ],
    "name:cze_x_preferred":[
        "Sancaktepe"
    ],
    "name:dan_x_preferred":[
        "Sancaktepe"
    ],
    "name:dut_x_preferred":[
        "Sancaktepe"
    ],
    "name:eng_x_preferred":[
        "Sancaktepe"
    ],
    "name:fin_x_preferred":[
        "Sancaktepe"
    ],
    "name:ger_x_preferred":[
        "Sancaktepe"
    ],
    "name:glg_x_preferred":[
        "Sancaktepe"
    ],
    "name:ita_x_preferred":[
        "Sancaktepe"
    ],
    "name:nno_x_preferred":[
        "Sancaktepe"
    ],
    "name:nob_x_preferred":[
        "Sancaktepe"
    ],
    "name:oci_x_preferred":[
        "Sancaktepe"
    ],
    "name:pol_x_preferred":[
        "Sancaktepe"
    ],
    "name:por_x_preferred":[
        "Sancaktepe"
    ],
    "name:rum_x_preferred":[
        "Sancaktepe"
    ],
    "name:sco_x_preferred":[
        "Sancaktepe"
    ],
    "name:slo_x_preferred":[
        "Sancaktepe"
    ],
    "name:slv_x_preferred":[
        "Sancaktepe"
    ],
    "name:spa_x_preferred":[
        "Sancaktepe"
    ],
    "name:swe_x_preferred":[
        "Sancaktepe"
    ],
    "name:tgl_x_preferred":[
        "Sancaktepe"
    ],
    "name:tur_x_preferred":[
        "Sancaktepe"
    ],
    "name:war_x_preferred":[
        "Sancaktepe"
    ],
    "wof:name":"Sancaktepe",
    "wof:placetype":"neighbourhood"
},
  "geometry": {"coordinates":[28.8567417075081,41.03915561410327],"type":"Point"}
}