{
  "type": "Feature",
  "properties": {
    "gn:admin1_code":"49",
    "gn:asciiname":"Dirik",
    "gn:country_code":"TR",
    "gn:dem":1488,
    "gn:feature_class":"P",
    "gn:feature_code":"PPL",
    "gn:name":"Dirik",
    "gn:population":0,
    "gn:timezone":"Europe/Istanbul",
    "iso:country":"TR",
    "name:tur_x_preferred":[
        "\u00d6zen\u00e7"
    ],
    "name:tur_x_variant":[
        "\u00d6zben\u00e7"
    ],
    "wof:name":"Dirik",
    "wof:placetype":"locality"
},
  "geometry": {"coordinates":[41.50633,39.11684],"type":"Point"}
}