{
  "type": "Feature",
  "properties": {
    "gn:admin1_code":"63",
    "gn:asciiname":"Uzumkara",
    "gn:country_code":"TR",
    "gn:dem":718,
    "gn:feature_class":"P",
    "gn:feature_code":"PPL",
    "gn:name":"\u00dcz\u00fcmkara",
    "gn:population":0,
    "gn:timezone":"Europe/Istanbul",
    "iso:country":"TR",
    "name:und_x_variant":[
        "\u00dcz\u00fcmkara",
        "\u015eeyhcafer"
    ],
    "wof:name":"Uzumkara",
    "wof:placetype":"locality"
},
  "geometry": {"coordinates":[39.26269,37.34038],"type":"Point"}
}