{
  "type": "Feature",
  "properties": {
    "iso:country":"TR",
    "name:eng_x_preferred":[
        "Ahmediye"
    ],
    "name:tur_x_preferred":[
        "Ahmediye"
    ],
    "wof:name":"Ahmediye",
    "wof:placetype":"neighbourhood"
},
  "geometry": {"coordinates":[28.51715734637203,41.08971195295086],"type":"Point"}
}