{
  "type": "Feature",
  "properties": {
    "iso:country":"TR",
    "wof:name":"Bostan",
    "wof:placetype":"neighbourhood"
},
  "geometry": {"coordinates":[28.97552765976537,41.03870416237962],"type":"Point"}
}