{
  "type": "Feature",
  "properties": {
    "gn:admin1_code":"63.0",
    "gn:asciiname":"Mizayinter",
    "gn:cc2":"TR",
    "gn:country_code":"TR",
    "gn:dem":492,
    "gn:feature_class":"P",
    "gn:feature_code":"PPL",
    "gn:name":"Mizayinter",
    "gn:population":0,
    "gn:timezone":"Europe/Istanbul",
    "iso:country":"TR",
    "name:und_x_variant":[
        "Mizanter",
        "Mizayinter"
    ],
    "wof:name":"Mizayinter",
    "wof:placetype":"locality"
},
  "geometry": {"coordinates":[38.37556,36.91917],"type":"Point"}
}