{
  "type": "Feature",
  "properties": {
    "gn:admin1_code":"61.0",
    "gn:asciiname":"Cakirli",
    "gn:country_code":"TR",
    "gn:dem":510,
    "gn:feature_class":"P",
    "gn:feature_code":"PPL",
    "gn:name":"\u00c7ak\u0131rl\u0131",
    "gn:population":0,
    "gn:timezone":"Europe/Istanbul",
    "iso:country":"TR",
    "name:tur_x_preferred":[
        "\u00c7ak\u0131rl\u0131"
    ],
    "wof:name":"Cakirli",
    "wof:placetype":"locality"
},
  "geometry": {"coordinates":[39.1588,40.99007],"type":"Point"}
}