{
  "type": "Feature",
  "properties": {
    "gn:admin1_code":"91",
    "gn:asciiname":"Buyuktuysuz",
    "gn:country_code":"TR",
    "gn:dem":157,
    "gn:feature_class":"P",
    "gn:feature_code":"PPL",
    "gn:name":"B\u00fcy\u00fckt\u00fcys\u00fcz",
    "gn:population":0,
    "gn:timezone":"Europe/Istanbul",
    "iso:country":"TR",
    "name:und_x_variant":[
        "B\u00fcy\u00fckt\u00fcys\u00fcz",
        "Yazlamazl\u0131"
    ],
    "wof:name":"Buyuktuysuz",
    "wof:placetype":"locality"
},
  "geometry": {"coordinates":[36.09899,37.02805],"type":"Point"}
}