{
  "type": "Feature",
  "properties": {
    "gn:admin1_code":"71",
    "gn:asciiname":"Yavanoglan",
    "gn:country_code":"TR",
    "gn:dem":1028,
    "gn:feature_class":"P",
    "gn:feature_code":"PPL",
    "gn:name":"Yavano\u011flan",
    "gn:population":0,
    "gn:timezone":"Europe/Istanbul",
    "iso:country":"TR",
    "name:und_x_variant":[
        "Yavano\u011flan Yaylas\u0131",
        "Yavano\u011flan"
    ],
    "wof:name":"Yavanoglan",
    "wof:placetype":"locality"
},
  "geometry": {"coordinates":[33.45656,37.89047],"type":"Point"}
}