{
  "type": "Feature",
  "properties": {
    "gn:admin1_code":"85.0",
    "gn:asciiname":"Adatepe",
    "gn:country_code":"TR",
    "gn:dem":858,
    "gn:feature_class":"P",
    "gn:feature_code":"PPL",
    "gn:name":"Adatepe",
    "gn:population":0,
    "gn:timezone":"Europe/Istanbul",
    "iso:country":"TR",
    "name:und_x_variant":[
        "Adatepek\u00f6y",
        "Adatepe"
    ],
    "wof:name":"Adatepe",
    "wof:placetype":"locality"
},
  "geometry": {"coordinates":[31.83947,41.05288],"type":"Point"}
}