{
  "type": "Feature",
  "properties": {
    "gn:country":"TR",
    "gn:fcode":"PPL",
    "gn:population":12947,
    "iso:country":"TR",
    "name:ast_x_preferred":[
        "Saruhanl\u0131"
    ],
    "name:azb_x_preferred":[
        "\u0633\u0627\u0631\u0648\u062e\u0627\u0646\u0644\u06cc"
    ],
    "name:ceb_x_preferred":[
        "Saruhanl\u0131"
    ],
    "name:che_x_preferred":[
        "\u0421\u0430\u0440\u0443\u0445\u04c0\u0430\u043d\u043b\u0438"
    ],
    "name:deu_x_preferred":[
        "Saruhanl\u0131"
    ],
    "name:eng_x_preferred":[
        "Saruhanl\u0131"
    ],
    "name:fas_x_preferred":[
        "\u0633\u0627\u0631\u0648\u0647\u0627\u0646\u200c\u0644\u06cc"
    ],
    "name:fra_x_preferred":[
        "Saruhanl\u0131"
    ],
    "name:gag_x_preferred":[
        "Saruhanl\u0131"
    ],
    "name:ita_x_preferred":[
        "Distretto di Saruhanl\u0131"
    ],
    "name:mrj_x_preferred":[
        "\u0421\u0430\u0440\u0443\u0445\u0430\u043d\u043b\u044b"
    ],
    "name:msa_x_preferred":[
        "Saruhanl\u0131"
    ],
    "name:nan_x_preferred":[
        "Saruhanl\u0131"
    ],
    "name:nld_x_preferred":[
        "Saruhanl\u0131"
    ],
    "name:nno_x_preferred":[
        "Saruhanl\u0131"
    ],
    "name:nob_x_preferred":[
        "Saruhanl\u0131"
    ],
    "name:pnb_x_preferred":[
        "\u0636\u0644\u0639 \u0633\u0627\u0631\u0648\u06c1\u0627\u0646\u0644\u06cc"
    ],
    "name:swa_x_preferred":[
        "Saruhanl\u0131"
    ],
    "name:tat_x_preferred":[
        "\u0421\u0430\u0440\u0443\u0445\u0430\u043d\u043b\u044b"
    ],
    "name:tur_x_preferred":[
        "Saruhanl\u0131"
    ],
    "name:ukr_x_preferred":[
        "\u0421\u0430\u0440\u0443\u0445\u0430\u043d\u043b\u0456"
    ],
    "name:und_x_variant":[
        "Sar\u0131hanl\u0131"
    ],
    "name:urd_x_preferred":[
        "\u0633\u0627\u0631\u0648\u06c1\u0627\u0646\u0644\u06cc"
    ],
    "name:vie_x_preferred":[
        "Saruhanl\u0131"
    ],
    "name:zho_x_preferred":[
        "\u85a9\u9b6f\u6f22\u52d2"
    ],
    "qs:name":"Saruhanl\u0131",
    "qs:photos_9r":0,
    "qs:photos_sr":0,
    "qs:pop_sr":"6",
    "wd:wordcount":221,
    "wof:name":"Saruhanl\u0131",
    "wof:placetype":"locality",
    "wof:population":12947
},
  "geometry": {"coordinates":[27.56811,38.73455],"type":"Point"}
}