{
  "type": "Feature",
  "properties": {
    "gn:admin1_code":"45",
    "gn:asciiname":"Mersindere",
    "gn:country_code":"TR",
    "gn:dem":136,
    "gn:feature_class":"P",
    "gn:feature_code":"PPL",
    "gn:name":"Mersindere",
    "gn:population":0,
    "gn:timezone":"Europe/Istanbul",
    "iso:country":"TR",
    "name:tur_x_preferred":[
        "Mersindere"
    ],
    "name:tur_x_variant":[
        "Mathasandere"
    ],
    "wof:name":"Mersindere",
    "wof:placetype":"locality"
},
  "geometry": {"coordinates":[27.99911,38.50372],"type":"Point"}
}