{
  "type": "Feature",
  "properties": {
    "gn:admin1_code":"58.0",
    "gn:asciiname":"Uzumlu",
    "gn:country_code":"TR",
    "gn:dem":1199,
    "gn:feature_class":"P",
    "gn:feature_code":"PPL",
    "gn:name":"\u00dcz\u00fcml\u00fc",
    "gn:population":0,
    "gn:timezone":"Europe/Istanbul",
    "iso:country":"TR",
    "name:tur_x_preferred":[
        "\u00dcz\u00fcml\u00fc"
    ],
    "wof:name":"Uzumlu",
    "wof:placetype":"locality"
},
  "geometry": {"coordinates":[38.2698,40.18897],"type":"Point"}
}