{
  "type": "Feature",
  "properties": {
    "gn:admin1_code":"81.0",
    "gn:asciiname":"Bayramhacili",
    "gn:country_code":"TR",
    "gn:dem":106,
    "gn:feature_class":"P",
    "gn:feature_code":"PPL",
    "gn:name":"Bayramhac\u0131l\u0131",
    "gn:population":0,
    "gn:timezone":"Europe/Istanbul",
    "iso:country":"TR",
    "wof:name":"Bayramhacili",
    "wof:placetype":"locality"
},
  "geometry": {"coordinates":[35.31634000000001,37.09046],"type":"Point"}
}