{
  "type": "Feature",
  "properties": {
    "gn:admin1_code":"81",
    "gn:asciiname":"Kuytucak",
    "gn:country_code":"TR",
    "gn:dem":882,
    "gn:feature_class":"P",
    "gn:feature_code":"PPL",
    "gn:name":"Kuytucak",
    "gn:population":0,
    "gn:timezone":"Europe/Istanbul",
    "iso:country":"TR",
    "wof:name":"Kuytucak",
    "wof:placetype":"locality"
},
  "geometry": {"coordinates":[35.71,37.59361],"type":"Point"}
}