{
  "type": "Feature",
  "properties": {
    "gn:admin1_code":"65.0",
    "gn:asciiname":"Ongun",
    "gn:country_code":"TR",
    "gn:dem":2177,
    "gn:feature_class":"P",
    "gn:feature_code":"PPL",
    "gn:name":"Ongun",
    "gn:population":0,
    "gn:timezone":"Europe/Istanbul",
    "iso:country":"TR",
    "name:tur_x_preferred":[
        "Ongun"
    ],
    "wof:name":"Ongun",
    "wof:placetype":"locality"
},
  "geometry": {"coordinates":[43.66647,38.42495],"type":"Point"}
}