{
  "type": "Feature",
  "properties": {
    "gn:admin1_code":"45",
    "gn:asciiname":"Ulgar",
    "gn:country_code":"TR",
    "gn:dem":666,
    "gn:feature_class":"P",
    "gn:feature_code":"PPL",
    "gn:name":"Ulgar",
    "gn:population":0,
    "gn:timezone":"Europe/Istanbul",
    "iso:country":"TR",
    "name:tur_x_preferred":[
        "Ulgar"
    ],
    "wof:name":"Ulgar",
    "wof:placetype":"locality"
},
  "geometry": {"coordinates":[28.43617,39.02572],"type":"Point"}
}