{
  "type": "Feature",
  "properties": {
    "gn:admin1_code":"16",
    "gn:asciiname":"Yesiller",
    "gn:country_code":"TR",
    "gn:dem":667,
    "gn:feature_class":"P",
    "gn:feature_code":"PPL",
    "gn:name":"Ye\u015filler",
    "gn:population":0,
    "gn:timezone":"Europe/Istanbul",
    "iso:country":"TR",
    "name:tur_x_preferred":[
        "Ye\u015filler"
    ],
    "wof:name":"Yesiller",
    "wof:placetype":"locality"
},
  "geometry": {"coordinates":[28.8929,39.87845],"type":"Point"}
}