{
  "type": "Feature",
  "properties": {
    "gn:admin1_code":"41.0",
    "gn:asciiname":"Kisalar",
    "gn:country_code":"TR",
    "gn:dem":328,
    "gn:feature_class":"P",
    "gn:feature_code":"PPL",
    "gn:name":"K\u0131salar",
    "gn:population":0,
    "gn:timezone":"Europe/Istanbul",
    "iso:country":"TR",
    "name:tur_x_preferred":[
        "K\u0131salar"
    ],
    "wof:name":"Kisalar",
    "wof:placetype":"locality"
},
  "geometry": {"coordinates":[30.07482000000001,40.8847],"type":"Point"}
}