{
  "type": "Feature",
  "properties": {
    "gn:admin1_code":"35",
    "gn:asciiname":"Kirtepe",
    "gn:country_code":"TR",
    "gn:dem":149,
    "gn:feature_class":"P",
    "gn:feature_code":"PPL",
    "gn:name":"K\u0131rtepe",
    "gn:population":0,
    "gn:timezone":"Europe/Istanbul",
    "iso:country":"TR",
    "name:tur_x_preferred":[
        "K\u0131rtepe"
    ],
    "wof:name":"Kirtepe",
    "wof:placetype":"locality"
},
  "geometry": {"coordinates":[27.88779000000001,38.11066],"type":"Point"}
}