{
  "type": "Feature",
  "properties": {
    "gn:admin1_code":"49",
    "gn:asciiname":"Dumlusu",
    "gn:country_code":"TR",
    "gn:dem":1378,
    "gn:feature_class":"P",
    "gn:feature_code":"PPL",
    "gn:name":"Dumlusu",
    "gn:population":0,
    "gn:timezone":"Europe/Istanbul",
    "iso:country":"TR",
    "name:tur_x_preferred":[
        "Dumlusu"
    ],
    "wof:name":"Dumlusu",
    "wof:placetype":"locality"
},
  "geometry": {"coordinates":[41.53646,39.01526],"type":"Point"}
}