{
  "type": "Feature",
  "properties": {
    "gn:admin1_code":"88.0",
    "gn:asciiname":"Mursitali",
    "gn:country_code":"TR",
    "gn:dem":849,
    "gn:feature_class":"P",
    "gn:feature_code":"PPL",
    "gn:name":"M\u00fcr\u015fitali",
    "gn:population":0,
    "gn:timezone":"Asia/Yerevan",
    "iso:country":"TR",
    "name:tur_x_preferred":[
        "M\u00fcr\u015fitali"
    ],
    "wof:name":"Mursitali",
    "wof:placetype":"locality"
},
  "geometry": {"coordinates":[44.1328,40.02529000000001],"type":"Point"}
}