{
  "type": "Feature",
  "properties": {
    "gn:admin1_code":"66",
    "gn:asciiname":"Konaci",
    "gn:country_code":"TR",
    "gn:dem":1140,
    "gn:feature_class":"P",
    "gn:feature_code":"PPL",
    "gn:name":"Konac\u0131",
    "gn:population":0,
    "gn:timezone":"Europe/Istanbul",
    "iso:country":"TR",
    "wof:name":"Konaci",
    "wof:placetype":"locality"
},
  "geometry": {"coordinates":[35.77195,39.73687],"type":"Point"}
}