{
  "type": "Feature",
  "properties": {
    "gn:admin1_code":"59.0",
    "gn:asciiname":"Kermeyan",
    "gn:country_code":"TR",
    "gn:dem":256,
    "gn:feature_class":"P",
    "gn:feature_code":"PPL",
    "gn:name":"Kermeyan",
    "gn:population":0,
    "gn:timezone":"Europe/Istanbul",
    "iso:country":"TR",
    "name:und_x_variant":[
        "Germeyan",
        "Kermen",
        "Kermeyen",
        "Kermian",
        "Kermeyan"
    ],
    "wof:name":"Kermeyan",
    "wof:placetype":"locality"
},
  "geometry": {"coordinates":[27.1047,40.92761],"type":"Point"}
}