{
  "type": "Feature",
  "properties": {
    "gn:country":"TR",
    "gn:fcode":"PPLX",
    "gn:population":0,
    "iso:country":"TR",
    "name:ceb_x_preferred":[
        "Karatas"
    ],
    "name:swe_x_preferred":[
        "Karatas"
    ],
    "name:und_x_variant":[
        "Mazmahor"
    ],
    "qs:name":"Karatas",
    "qs:name_adm0":"Turkey",
    "qs:name_adm1":"Gaziantep",
    "qs:photos":3,
    "qs:photos_1k":1,
    "qs:photos_9k":1,
    "qs:photos_9r":1,
    "qs:photos_all":3,
    "qs:photos_sr":1,
    "qs:placetype":"Suburb",
    "qs:pop_sr":"0",
    "wd:wordcount":22,
    "wof:name":"Karatas",
    "wof:placetype":"neighbourhood",
    "wof:population":0
},
  "geometry": {"coordinates":[37.35,37.01667],"type":"Point"}
}