{
  "type": "Feature",
  "properties": {
    "gn:admin1_code":"19.0",
    "gn:asciiname":"Yerli",
    "gn:country_code":"TR",
    "gn:dem":577,
    "gn:feature_class":"P",
    "gn:feature_code":"PPL",
    "gn:name":"Yerli",
    "gn:population":0,
    "gn:timezone":"Europe/Istanbul",
    "iso:country":"TR",
    "name:und_x_variant":[
        "Yerli K\u00f6y\u00fc",
        "Yerli"
    ],
    "wof:name":"Yerli",
    "wof:placetype":"locality"
},
  "geometry": {"coordinates":[34.34861,40.58058],"type":"Point"}
}