{
  "type": "Feature",
  "properties": {
    "gn:admin1_code":"37.0",
    "gn:asciiname":"Dereyucek",
    "gn:country_code":"TR",
    "gn:dem":875,
    "gn:feature_class":"P",
    "gn:feature_code":"PPL",
    "gn:name":"Derey\u00fccek",
    "gn:population":0,
    "gn:timezone":"Europe/Istanbul",
    "iso:country":"TR",
    "wof:name":"Dereyucek",
    "wof:placetype":"locality"
},
  "geometry": {"coordinates":[33.33718,41.59983],"type":"Point"}
}