{
  "type": "Feature",
  "properties": {
    "gn:admin1_code":"39.0",
    "gn:asciiname":"Karakoc",
    "gn:country_code":"TR",
    "gn:dem":273,
    "gn:feature_class":"P",
    "gn:feature_code":"PPL",
    "gn:name":"Karako\u00e7",
    "gn:population":0,
    "gn:timezone":"Europe/Istanbul",
    "iso:country":"TR",
    "name:tur_x_preferred":[
        "Karako\u00e7"
    ],
    "wof:name":"Karakoc",
    "wof:placetype":"locality"
},
  "geometry": {"coordinates":[27.2253,41.77434],"type":"Point"}
}