{
  "type": "Feature",
  "properties": {
    "gn:admin1_code":"55.0",
    "gn:asciiname":"Cayirli",
    "gn:country_code":"TR",
    "gn:dem":787,
    "gn:feature_class":"P",
    "gn:feature_code":"PPL",
    "gn:name":"\u00c7ay\u0131rl\u0131",
    "gn:population":0,
    "gn:timezone":"Europe/Istanbul",
    "iso:country":"TR",
    "wof:name":"Cayirli",
    "wof:placetype":"locality"
},
  "geometry": {"coordinates":[35.96044000000001,41.11078],"type":"Point"}
}