{
  "type": "Feature",
  "properties": {
    "gn:admin1_code":"89",
    "gn:asciiname":"Kurtlar",
    "gn:country_code":"TR",
    "gn:dem":276,
    "gn:feature_class":"P",
    "gn:feature_code":"PPL",
    "gn:name":"Kurtlar",
    "gn:population":0,
    "gn:timezone":"Europe/Istanbul",
    "iso:country":"TR",
    "name:tur_x_preferred":[
        "Kurtlar"
    ],
    "wof:name":"Kurtlar",
    "wof:placetype":"locality"
},
  "geometry": {"coordinates":[31.51338,41.17422],"type":"Point"}
}