{
  "type": "Feature",
  "properties": {
    "gn:admin1_code":"09",
    "gn:asciiname":"Sululer",
    "gn:country_code":"TR",
    "gn:dem":573,
    "gn:feature_class":"P",
    "gn:feature_code":"PPL",
    "gn:name":"Sululer",
    "gn:population":0,
    "gn:timezone":"Europe/Istanbul",
    "iso:country":"TR",
    "wof:name":"Sululer",
    "wof:placetype":"locality"
},
  "geometry": {"coordinates":[28.40576,38.07202],"type":"Point"}
}