{
  "type": "Feature",
  "properties": {
    "gn:admin1_code":"09",
    "gn:asciiname":"Malgacmustafa",
    "gn:cc2":"TR",
    "gn:country_code":"TR",
    "gn:dem":408,
    "gn:feature_class":"P",
    "gn:feature_code":"PPL",
    "gn:name":"Malga\u00e7mustafa",
    "gn:population":0,
    "gn:timezone":"Europe/Istanbul",
    "iso:country":"TR",
    "name:und_x_variant":[
        "Malka\u00e7mustafa",
        "Malga\u00e7mustafa"
    ],
    "wof:name":"Malgacmustafa",
    "wof:placetype":"locality"
},
  "geometry": {"coordinates":[28.16697000000001,37.94545],"type":"Point"}
}