{
  "type": "Feature",
  "properties": {
    "gn:admin1_code":"19.0",
    "gn:asciiname":"Madara",
    "gn:country_code":"TR",
    "gn:dem":884,
    "gn:feature_class":"P",
    "gn:feature_code":"PPL",
    "gn:name":"Madara",
    "gn:population":0,
    "gn:timezone":"Europe/Istanbul",
    "iso:country":"TR",
    "name:tur_x_preferred":[
        "S\u00fctl\u00fcce"
    ],
    "name:tur_x_variant":[
        "Madara"
    ],
    "wof:name":"Madara",
    "wof:placetype":"locality"
},
  "geometry": {"coordinates":[34.97306,40.95857],"type":"Point"}
}