{
  "type": "Feature",
  "properties": {
    "gn:admin1_code":"87",
    "gn:asciiname":"Koseoglu",
    "gn:country_code":"TR",
    "gn:dem":51,
    "gn:feature_class":"P",
    "gn:feature_code":"PPL",
    "gn:name":"K\u00f6seo\u011flu",
    "gn:population":0,
    "gn:timezone":"Europe/Istanbul",
    "iso:country":"TR",
    "wof:name":"Koseoglu",
    "wof:placetype":"locality"
},
  "geometry": {"coordinates":[32.34222,41.57244],"type":"Point"}
}