{
  "type": "Feature",
  "properties": {
    "gn:admin1_code":"21",
    "gn:asciiname":"Ozkaya",
    "gn:country_code":"TR",
    "gn:dem":829,
    "gn:feature_class":"P",
    "gn:feature_code":"PPL",
    "gn:name":"\u00d6zkaya",
    "gn:population":0,
    "gn:timezone":"Europe/Istanbul",
    "iso:country":"TR",
    "name:tur_x_preferred":[
        "\u00d6zkaya"
    ],
    "wof:name":"Ozkaya",
    "wof:placetype":"locality"
},
  "geometry": {"coordinates":[40.41289,38.38409],"type":"Point"}
}