{
  "type": "Feature",
  "properties": {
    "gn:admin1_code":"61",
    "gn:asciiname":"Kavakpinar",
    "gn:country_code":"TR",
    "gn:dem":171,
    "gn:feature_class":"P",
    "gn:feature_code":"PPL",
    "gn:name":"Kavakp\u0131nar",
    "gn:population":0,
    "gn:timezone":"Europe/Istanbul",
    "iso:country":"TR",
    "name:tur_x_preferred":[
        "Kavakp\u0131nar"
    ],
    "wof:name":"Kavakpinar",
    "wof:placetype":"locality"
},
  "geometry": {"coordinates":[40.32293,40.91795],"type":"Point"}
}