{
  "type": "Feature",
  "properties": {
    "gn:country":"TR",
    "gn:fcode":"PPLA2",
    "gn:pop":13640,
    "iso:country":"TR",
    "name:unk_x_variant":[
        "Charan"
    ],
    "qs:name":"Harran",
    "qs:photos_9r":0,
    "qs:photos_sr":0,
    "qs:pop_sr":"6",
    "wd:wordcount":3213,
    "wof:name":"Harran",
    "wof:placetype":"locality",
    "wof:population":13640
},
  "geometry": {"coordinates":[39.03139,36.86],"type":"Point"}
}