{
  "type": "Feature",
  "properties": {
    "gn:admin1_code":"92.0",
    "gn:asciiname":"Esenkoy",
    "gn:country_code":"TR",
    "gn:dem":39,
    "gn:feature_class":"P",
    "gn:feature_code":"PPL",
    "gn:name":"Esenk\u00f6y",
    "gn:population":0,
    "gn:timezone":"Europe/Istanbul",
    "iso:country":"TR",
    "name:und_x_variant":[
        "Kat\u0131rl\u0131",
        "Esenk\u00f6y"
    ],
    "wof:name":"Esenkoy",
    "wof:placetype":"locality"
},
  "geometry": {"coordinates":[28.95713,40.61695],"type":"Point"}
}