{
  "type": "Feature",
  "properties": {
    "gn:admin1_code":"39.0",
    "gn:asciiname":"Osmancik",
    "gn:country_code":"TR",
    "gn:dem":131,
    "gn:feature_class":"P",
    "gn:feature_code":"PPL",
    "gn:name":"Osmanc\u0131k",
    "gn:population":0,
    "gn:timezone":"Europe/Istanbul",
    "iso:country":"TR",
    "wof:name":"Osmancik",
    "wof:placetype":"locality"
},
  "geometry": {"coordinates":[27.37773,41.56799],"type":"Point"}
}