{
  "type": "Feature",
  "properties": {
    "gn:admin1_code":"5.0",
    "gn:asciiname":"Kizilkislacik",
    "gn:country_code":"TR",
    "gn:dem":1249,
    "gn:feature_class":"P",
    "gn:feature_code":"PPL",
    "gn:name":"K\u0131z\u0131lk\u0131\u015flac\u0131k",
    "gn:population":0,
    "gn:timezone":"Europe/Istanbul",
    "iso:country":"TR",
    "name:msa_x_preferred":[
        "K\u0131z\u0131lk\u0131\u015flac\u0131k"
    ],
    "name:tur_x_preferred":[
        "K\u0131z\u0131lk\u0131\u015flac\u0131k"
    ],
    "name:und_x_variant":[
        "K\u0131z\u0131lk\u0131\u015flac\u0131k"
    ],
    "name:vie_x_preferred":[
        "K\u0131z\u0131lk\u0131\u015flac\u0131k"
    ],
    "wof:name":"Kizilkislacik",
    "wof:placetype":"locality"
},
  "geometry": {"coordinates":[35.96151,40.76364],"type":"Point"}
}