{
  "type": "Feature",
  "properties": {
    "gn:admin1_code":"74",
    "gn:asciiname":"Yokusbaglari",
    "gn:country_code":"TR",
    "gn:dem":683,
    "gn:feature_class":"P",
    "gn:feature_code":"PPL",
    "gn:name":"Yoku\u015fba\u011flar\u0131",
    "gn:population":0,
    "gn:timezone":"Europe/Istanbul",
    "iso:country":"TR",
    "name:und_x_variant":[
        "S\u00fcs\u00fck",
        "Syusik",
        "S\u00fcsik",
        "Yoku\u015fba\u011flar",
        "Yoku\u015fba\u011flar\u0131"
    ],
    "wof:name":"Yokusbaglari",
    "wof:placetype":"locality"
},
  "geometry": {"coordinates":[41.84615,37.77182],"type":"Point"}
}