{
  "type": "Feature",
  "properties": {
    "gn:admin1_code":"25",
    "gn:asciiname":"Dundarkoy",
    "gn:country_code":"TR",
    "gn:dem":1990,
    "gn:feature_class":"P",
    "gn:feature_code":"PPL",
    "gn:name":"D\u00fcndark\u00f6y",
    "gn:population":0,
    "gn:timezone":"Europe/Istanbul",
    "iso:country":"TR",
    "name:tur_x_preferred":[
        "D\u00fcndark\u00f6y"
    ],
    "name:und_x_variant":[
        "D\u00fcndar"
    ],
    "wof:name":"Dundarkoy",
    "wof:placetype":"locality"
},
  "geometry": {"coordinates":[41.95393,39.50655],"type":"Point"}
}