{
  "type": "Feature",
  "properties": {
    "gn:admin1_code":"17.0",
    "gn:asciiname":"Demirtepe",
    "gn:country_code":"TR",
    "gn:dem":80,
    "gn:feature_class":"P",
    "gn:feature_code":"PPL",
    "gn:name":"Demirtepe",
    "gn:population":0,
    "gn:timezone":"Europe/Istanbul",
    "iso:country":"TR",
    "name:und_x_variant":[
        "Demirtepe K\u00f6y",
        "Demirtepe"
    ],
    "wof:name":"Demirtepe",
    "wof:placetype":"locality"
},
  "geometry": {"coordinates":[26.78911,40.51269],"type":"Point"}
}