{
  "type": "Feature",
  "properties": {
    "gn:admin1_code":"93",
    "gn:asciiname":"Buyukyaylim",
    "gn:country_code":"TR",
    "gn:dem":137,
    "gn:feature_class":"P",
    "gn:feature_code":"PPL",
    "gn:name":"B\u00fcy\u00fckyayl\u0131m",
    "gn:population":0,
    "gn:timezone":"Europe/Istanbul",
    "iso:country":"TR",
    "wof:name":"Buyukyaylim",
    "wof:placetype":"locality"
},
  "geometry": {"coordinates":[30.93175,40.91875],"type":"Point"}
}