{
  "type": "Feature",
  "properties": {
    "gn:admin1_code":"84.0",
    "gn:asciiname":"Camcavus",
    "gn:country_code":"TR",
    "gn:dem":1700,
    "gn:feature_class":"P",
    "gn:feature_code":"PPL",
    "gn:name":"\u00c7am\u00e7avu\u015f",
    "gn:population":0,
    "gn:timezone":"Europe/Istanbul",
    "iso:country":"TR",
    "name:und_x_variant":[
        "\u00c7am\u00e7avu\u015f",
        "Yenik\u00f6y"
    ],
    "wof:name":"Camcavus",
    "wof:placetype":"locality"
},
  "geometry": {"coordinates":[43.15825,40.73082],"type":"Point"}
}