{
  "type": "Feature",
  "properties": {
    "gn:admin1_code":"57.0",
    "gn:asciiname":"Sokucayiri",
    "gn:country_code":"TR",
    "gn:dem":474,
    "gn:feature_class":"P",
    "gn:feature_code":"PPL",
    "gn:name":"S\u00f6k\u00fc\u00e7ay\u0131r\u0131",
    "gn:population":0,
    "gn:timezone":"Europe/Istanbul",
    "iso:country":"TR",
    "name:und_x_variant":[
        "S\u00f6k\u00fc\u00e7ay\u0131r\u0131 K\u00f6y\u00fc",
        "S\u00f6k\u00fc\u00e7ay\u0131r\u0131 K\u00f6y",
        "S\u00f6k\u00fc\u00e7ay\u0131r\u0131"
    ],
    "wof:name":"Sokucayiri",
    "wof:placetype":"locality"
},
  "geometry": {"coordinates":[34.49491,41.86351],"type":"Point"}
}