{
  "type": "Feature",
  "properties": {
    "gn:admin1_code":"35",
    "gn:asciiname":"Karahalili",
    "gn:country_code":"TR",
    "gn:dem":126,
    "gn:feature_class":"P",
    "gn:feature_code":"PPL",
    "gn:name":"Karahalili",
    "gn:population":0,
    "gn:timezone":"Europe/Istanbul",
    "iso:country":"TR",
    "name:tur_x_preferred":[
        "Karahalil"
    ],
    "name:tur_x_variant":[
        "Karahalili"
    ],
    "wof:name":"Karahalili",
    "wof:placetype":"locality"
},
  "geometry": {"coordinates":[27.60662,38.22012],"type":"Point"}
}