{
  "type": "Feature",
  "properties": {
    "gn:admin1_code":"76.0",
    "gn:asciiname":"Gultepe",
    "gn:country_code":"TR",
    "gn:dem":588,
    "gn:feature_class":"P",
    "gn:feature_code":"PPL",
    "gn:name":"G\u00fcltepe",
    "gn:population":0,
    "gn:timezone":"Europe/Istanbul",
    "iso:country":"TR",
    "wof:name":"Gultepe",
    "wof:placetype":"locality"
},
  "geometry": {"coordinates":[41.13543,37.92535],"type":"Point"}
}