{
  "type": "Feature",
  "properties": {
    "gn:admin1_code":"43",
    "gn:asciiname":"Cobanlaryaylasi",
    "gn:country_code":"TR",
    "gn:dem":1603,
    "gn:feature_class":"P",
    "gn:feature_code":"PPL",
    "gn:name":"\u00c7obanlaryaylas\u0131",
    "gn:population":0,
    "gn:timezone":"Europe/Istanbul",
    "iso:country":"TR",
    "wof:name":"Cobanlaryaylasi",
    "wof:placetype":"locality"
},
  "geometry": {"coordinates":[30.32795,39.44892],"type":"Point"}
}