{
  "type": "Feature",
  "properties": {
    "gn:admin1_code":"8.0",
    "gn:asciiname":"Ciritduzu",
    "gn:country_code":"TR",
    "gn:dem":1156,
    "gn:feature_class":"P",
    "gn:feature_code":"PPL",
    "gn:name":"Ciritd\u00fcz\u00fc",
    "gn:population":0,
    "gn:timezone":"Europe/Istanbul",
    "iso:country":"TR",
    "name:tur_x_preferred":[
        "Ciritd\u00fcz\u00fc"
    ],
    "wof:name":"Ciritduzu",
    "wof:placetype":"locality"
},
  "geometry": {"coordinates":[42.38817,41.27997],"type":"Point"}
}