{
  "type": "Feature",
  "properties": {
    "gn:admin1_code":"14",
    "gn:asciiname":"Hatipoglu",
    "gn:country_code":"TR",
    "gn:dem":861,
    "gn:feature_class":"P",
    "gn:feature_code":"PPL",
    "gn:name":"Hatipo\u011flu",
    "gn:population":0,
    "gn:timezone":"Europe/Istanbul",
    "iso:country":"TR",
    "wof:name":"Hatipoglu",
    "wof:placetype":"locality"
},
  "geometry": {"coordinates":[31.91049000000001,40.89877],"type":"Point"}
}