{
  "type": "Feature",
  "properties": {
    "gn:admin1_code":"24",
    "gn:asciiname":"Erdene",
    "gn:country_code":"TR",
    "gn:dem":1292,
    "gn:feature_class":"P",
    "gn:feature_code":"PPL",
    "gn:name":"Erdene",
    "gn:population":0,
    "gn:timezone":"Europe/Istanbul",
    "iso:country":"TR",
    "name:und_x_variant":[
        "Erdeni",
        "Erdene"
    ],
    "wof:name":"Erdene",
    "wof:placetype":"locality"
},
  "geometry": {"coordinates":[39.75071,39.60479],"type":"Point"}
}