{
  "type": "Feature",
  "properties": {
    "gn:admin1_code":"81.0",
    "gn:asciiname":"Yukari Kecili",
    "gn:country_code":"TR",
    "gn:dem":1196,
    "gn:feature_class":"P",
    "gn:feature_code":"PPL",
    "gn:name":"Yukar\u0131 Ke\u00e7ili",
    "gn:population":0,
    "gn:timezone":"Europe/Istanbul",
    "iso:country":"TR",
    "wof:name":"Yukari Kecili",
    "wof:placetype":"locality"
},
  "geometry": {"coordinates":[35.62636,37.76699],"type":"Point"}
}