{
  "type": "Feature",
  "properties": {
    "gn:admin1_code":"09",
    "gn:asciiname":"Karaahmetler",
    "gn:country_code":"TR",
    "gn:dem":283,
    "gn:feature_class":"P",
    "gn:feature_code":"PPL",
    "gn:name":"Karaahmetler",
    "gn:population":0,
    "gn:timezone":"Europe/Istanbul",
    "iso:country":"TR",
    "name:tur_x_preferred":[
        "Karaahmetler"
    ],
    "wof:name":"Karaahmetler",
    "wof:placetype":"locality"
},
  "geometry": {"coordinates":[28.43701,37.69014],"type":"Point"}
}