{
  "type": "Feature",
  "properties": {
    "gn:admin1_code":"58",
    "gn:asciiname":"Banaz",
    "gn:country_code":"TR",
    "gn:dem":1452,
    "gn:feature_class":"P",
    "gn:feature_code":"PPL",
    "gn:name":"Banaz",
    "gn:population":0,
    "gn:timezone":"Europe/Istanbul",
    "iso:country":"TR",
    "name:ceb_x_preferred":[
        "Banaz"
    ],
    "name:deu_x_preferred":[
        "Banaz"
    ],
    "name:ell_x_preferred":[
        "\u039c\u03c0\u03b1\u03bd\u03ac\u03b6"
    ],
    "name:epo_x_preferred":[
        "Banaz"
    ],
    "name:fas_x_preferred":[
        "\u0628\u0627\u0646\u0627\u0632"
    ],
    "name:fra_x_preferred":[
        "Banaz"
    ],
    "name:mrj_x_preferred":[
        "\u0411\u0430\u043d\u0430\u0437"
    ],
    "name:msa_x_preferred":[
        "Banaz"
    ],
    "name:nld_x_preferred":[
        "Banaz"
    ],
    "name:nno_x_preferred":[
        "Banaz"
    ],
    "name:nor_x_preferred":[
        "Banaz"
    ],
    "name:pnb_x_preferred":[
        "\u0636\u0644\u0639 \u0628\u0627\u0646\u0627\u0632"
    ],
    "name:swa_x_preferred":[
        "Banaz"
    ],
    "name:tur_x_preferred":[
        "Banaz"
    ],
    "name:urd_x_preferred":[
        "\u0628\u0627\u0646\u0627\u0632"
    ],
    "name:vie_x_preferred":[
        "Banaz"
    ],
    "name:zho_x_preferred":[
        "\u5df4\u7d0d\u8332"
    ],
    "wof:name":"Banaz",
    "wof:placetype":"locality"
},
  "geometry": {"coordinates":[36.79204,39.99278],"type":"Point"}
}