{
  "type": "Feature",
  "properties": {
    "gn:admin1_code":"68",
    "gn:asciiname":"Eskikoseler",
    "gn:country_code":"TR",
    "gn:dem":936,
    "gn:feature_class":"P",
    "gn:feature_code":"PPL",
    "gn:name":"Eskik\u00f6seler",
    "gn:population":0,
    "gn:timezone":"Europe/Istanbul",
    "iso:country":"TR",
    "name:und_x_variant":[
        "Eskik\u00f6seler",
        "K\u00f6seler"
    ],
    "wof:name":"Eskikoseler",
    "wof:placetype":"locality"
},
  "geometry": {"coordinates":[32.34806,39.60628],"type":"Point"}
}