{
  "type": "Feature",
  "properties": {
    "gn:admin1_code":"89",
    "gn:asciiname":"Eleler",
    "gn:country_code":"TR",
    "gn:dem":951,
    "gn:feature_class":"P",
    "gn:feature_code":"PPL",
    "gn:name":"Eleler",
    "gn:population":0,
    "gn:timezone":"Europe/Istanbul",
    "iso:country":"TR",
    "wof:name":"Eleler",
    "wof:placetype":"locality"
},
  "geometry": {"coordinates":[32.46652,40.92248],"type":"Point"}
}