{
  "type": "Feature",
  "properties": {
    "gn:admin1_code":"72",
    "gn:asciiname":"Kocatepe",
    "gn:country_code":"TR",
    "gn:dem":487,
    "gn:feature_class":"P",
    "gn:feature_code":"PPLA3",
    "gn:name":"Kocatepe",
    "gn:population":0,
    "gn:timezone":"Europe/Istanbul",
    "iso:country":"TR",
    "name:deu_x_preferred":[
        "Kocatepe"
    ],
    "name:tur_x_preferred":[
        "Kocatepe"
    ],
    "name:und_x_variant":[
        "De\u015fi",
        "Me\u015fkinan"
    ],
    "wof:name":"Kocatepe",
    "wof:placetype":"locality"
},
  "geometry": {"coordinates":[40.16104,37.22922],"type":"Point"}
}