{
  "type": "Feature",
  "properties": {
    "gn:admin1_code":"58.0",
    "gn:asciiname":"Utukyurdu",
    "gn:country_code":"TR",
    "gn:dem":1635,
    "gn:feature_class":"P",
    "gn:feature_code":"PPL",
    "gn:name":"\u00dct\u00fckyurdu",
    "gn:population":0,
    "gn:timezone":"Europe/Istanbul",
    "iso:country":"TR",
    "name:und_x_variant":[
        "\u00dct\u00fck",
        "\u00dct\u00fckyurdu"
    ],
    "wof:name":"Utukyurdu",
    "wof:placetype":"locality"
},
  "geometry": {"coordinates":[37.8083,40.01655],"type":"Point"}
}