{
  "type": "Feature",
  "properties": {
    "gn:country":"TR",
    "gn:fcode":"PPL",
    "gn:population":891,
    "iso:country":"TR",
    "name:und_x_variant":[
        "Ammara"
    ],
    "qs:name":"Temelli",
    "qs:photos_9r":0,
    "qs:photos_sr":0,
    "qs:pop_sr":"2",
    "wof:name":"Temelli",
    "wof:placetype":"locality",
    "wof:population":891
},
  "geometry": {"coordinates":[41.84722,37.57556],"type":"Point"}
}