{
  "type": "Feature",
  "properties": {
    "gn:country":"TR",
    "gn:fcode":"PPL",
    "gn:pop":105,
    "iso:country":"TR",
    "name:bul_x_preferred":[
        "\u0410\u0439\u0434\u0435\u043c\u0438\u0440"
    ],
    "name:fra_x_preferred":[
        "A\u00efdemir"
    ],
    "name:kat_x_preferred":[
        "\u10d0\u10d8\u10d3\u10d4\u10db\u10d8\u10e0\u10d8"
    ],
    "name:kaz_x_preferred":[
        "\u0410\u0439\u0434\u0435\u043c\u0438\u0440"
    ],
    "name:msa_x_preferred":[
        "Aydemir"
    ],
    "name:nld_x_preferred":[
        "Aydemir"
    ],
    "name:ron_x_preferred":[
        "Aidemir"
    ],
    "name:rus_x_preferred":[
        "\u0410\u0439\u0434\u0435\u043c\u0438\u0440"
    ],
    "name:ukr_x_preferred":[
        "\u0410\u0439\u0434\u0435\u043c\u0438\u0440"
    ],
    "name:unk_x_variant":[
        "H\u00fcseyniye"
    ],
    "qs:name":"Aydemir",
    "qs:photos_9r":0,
    "qs:photos_sr":0,
    "qs:pop_sr":"1",
    "wd:wordcount":329,
    "wof:name":"Aydemir",
    "wof:placetype":"locality",
    "wof:population":105
},
  "geometry": {"coordinates":[41.75111,37.80861],"type":"Point"}
}