{
  "type": "Feature",
  "properties": {
    "gn:country":"TR",
    "gn:fcode":"PPL",
    "gn:pop":105,
    "iso:country":"TR",
    "name:unk_x_variant":[
        "H\u00fcseyniye"
    ],
    "qs:name":"Aydemir",
    "qs:photos_9r":0,
    "qs:photos_sr":0,
    "qs:pop_sr":"1",
    "wd:wordcount":329,
    "wof:name":"Aydemir",
    "wof:placetype":"locality",
    "wof:population":105
},
  "geometry": {"coordinates":[41.75111,37.80861],"type":"Point"}
}