{
  "type": "Feature",
  "properties": {
    "gn:admin1_code":"49",
    "gn:asciiname":"Yemisen",
    "gn:country_code":"TR",
    "gn:dem":1485,
    "gn:feature_class":"P",
    "gn:feature_code":"PPL",
    "gn:name":"Yemi\u015fen",
    "gn:population":0,
    "gn:timezone":"Europe/Istanbul",
    "iso:country":"TR",
    "name:tur_x_preferred":[
        "Yemi\u015fen"
    ],
    "wof:name":"Yemisen",
    "wof:placetype":"locality"
},
  "geometry": {"coordinates":[42.08977,38.96843],"type":"Point"}
}