{
  "type": "Feature",
  "properties": {
    "gn:admin1_code":"35",
    "gn:asciiname":"Ulukent",
    "gn:country_code":"TR",
    "gn:dem":19,
    "gn:feature_class":"P",
    "gn:feature_code":"PPL",
    "gn:name":"Ulukent",
    "gn:population":0,
    "gn:timezone":"Europe/Istanbul",
    "iso:country":"TR",
    "name:tur_x_preferred":[
        "Ulukent"
    ],
    "name:tur_x_variant":[
        "Ulucak"
    ],
    "wof:name":"Ulukent",
    "wof:placetype":"locality"
},
  "geometry": {"coordinates":[27.04061,38.54474],"type":"Point"}
}