{
  "type": "Feature",
  "properties": {
    "gn:admin1_code":"37.0",
    "gn:asciiname":"Kavalca",
    "gn:country_code":"TR",
    "gn:dem":802,
    "gn:feature_class":"P",
    "gn:feature_code":"PPL",
    "gn:name":"Kavalca",
    "gn:population":0,
    "gn:timezone":"Europe/Istanbul",
    "iso:country":"TR",
    "wof:name":"Kavalca",
    "wof:placetype":"locality"
},
  "geometry": {"coordinates":[33.84323,41.48863],"type":"Point"}
}