{
  "type": "Feature",
  "properties": {
    "gn:admin1_code":"39.0",
    "gn:asciiname":"Emirali",
    "gn:country_code":"TR",
    "gn:dem":137,
    "gn:feature_class":"P",
    "gn:feature_code":"PPL",
    "gn:name":"Emirali",
    "gn:population":0,
    "gn:timezone":"Europe/Istanbul",
    "iso:country":"TR",
    "name:und_x_variant":[
        "\u0130mrall\u0131",
        "Emirali"
    ],
    "wof:name":"Emirali",
    "wof:placetype":"locality"
},
  "geometry": {"coordinates":[27.54683,41.44658],"type":"Point"}
}