{
  "type": "Feature",
  "properties": {
    "gn:admin1_code":"72.0",
    "gn:asciiname":"Kartalkaya",
    "gn:country_code":"TR",
    "gn:dem":611,
    "gn:feature_class":"P",
    "gn:feature_code":"PPL",
    "gn:name":"Kartalkaya",
    "gn:population":0,
    "gn:timezone":"Europe/Istanbul",
    "iso:country":"TR",
    "name:fra_x_preferred":[
        "Kartalkaya"
    ],
    "name:por_x_preferred":[
        "Kartalkaya"
    ],
    "name:spa_x_preferred":[
        "Kartalkaya"
    ],
    "name:tur_x_preferred":[
        "Kartalkaya"
    ],
    "name:und_x_variant":[
        "Liyan"
    ],
    "wof:name":"Kartalkaya",
    "wof:placetype":"locality"
},
  "geometry": {"coordinates":[41.87909000000001,37.56323],"type":"Point"}
}