{
  "type": "Feature",
  "properties": {
    "gn:admin1_code":"12.0",
    "gn:asciiname":"Direkli",
    "gn:country_code":"TR",
    "gn:dem":1362,
    "gn:feature_class":"P",
    "gn:feature_code":"PPL",
    "gn:name":"Direkli",
    "gn:population":0,
    "gn:timezone":"Europe/Istanbul",
    "iso:country":"TR",
    "name:tur_x_preferred":[
        "Direkli"
    ],
    "wof:name":"Direkli",
    "wof:placetype":"locality"
},
  "geometry": {"coordinates":[40.51611,38.68222],"type":"Point"}
}