{
  "type": "Feature",
  "properties": {
    "gn:admin1_code":"21",
    "gn:asciiname":"Kabakaya",
    "gn:country_code":"TR",
    "gn:dem":896,
    "gn:feature_class":"P",
    "gn:feature_code":"PPL",
    "gn:name":"Kabakaya",
    "gn:population":0,
    "gn:timezone":"Europe/Istanbul",
    "iso:country":"TR",
    "name:tur_x_preferred":[
        "Kabakaya"
    ],
    "wof:name":"Kabakaya",
    "wof:placetype":"locality"
},
  "geometry": {"coordinates":[40.73299,38.35491],"type":"Point"}
}