{
  "type": "Feature",
  "properties": {
    "gn:admin1_code":"43",
    "gn:asciiname":"Guney",
    "gn:country_code":"TR",
    "gn:dem":657,
    "gn:feature_class":"P",
    "gn:feature_code":"PPL",
    "gn:name":"G\u00fcney",
    "gn:population":0,
    "gn:timezone":"Europe/Istanbul",
    "iso:country":"TR",
    "name:tur_x_preferred":[
        "G\u00fcney"
    ],
    "wof:name":"Guney",
    "wof:placetype":"locality"
},
  "geometry": {"coordinates":[29.49251,39.72857],"type":"Point"}
}