{
  "type": "Feature",
  "properties": {
    "gn:admin1_code":"57.0",
    "gn:asciiname":"Gokcebel",
    "gn:country_code":"TR",
    "gn:dem":641,
    "gn:feature_class":"P",
    "gn:feature_code":"PPL",
    "gn:name":"G\u00f6k\u00e7ebel",
    "gn:population":0,
    "gn:timezone":"Europe/Istanbul",
    "iso:country":"TR",
    "name:tur_x_preferred":[
        "G\u00f6k\u00e7ebel"
    ],
    "name:und_x_variant":[
        "Terziyeri",
        "Terziyeni"
    ],
    "wof:name":"Gokcebel",
    "wof:placetype":"locality"
},
  "geometry": {"coordinates":[34.773,41.87627],"type":"Point"}
}