{
  "type": "Feature",
  "properties": {
    "gn:admin1_code":"93.0",
    "gn:asciiname":"Eminacmasi",
    "gn:country_code":"TR",
    "gn:dem":642,
    "gn:feature_class":"P",
    "gn:feature_code":"PPL",
    "gn:name":"Emina\u00e7mas\u0131",
    "gn:population":0,
    "gn:timezone":"Europe/Istanbul",
    "iso:country":"TR",
    "wof:name":"Eminacmasi",
    "wof:placetype":"locality"
},
  "geometry": {"coordinates":[31.23623,40.9483],"type":"Point"}
}