{
  "type": "Feature",
  "properties": {
    "gn:admin1_code":"55.0",
    "gn:asciiname":"Gokcedere",
    "gn:country_code":"TR",
    "gn:dem":709,
    "gn:feature_class":"P",
    "gn:feature_code":"PPL",
    "gn:name":"G\u00f6k\u00e7edere",
    "gn:population":0,
    "gn:timezone":"Europe/Istanbul",
    "iso:country":"TR",
    "name:und_x_variant":[
        "G\u00f6vdere",
        "G\u00f6k\u00e7edere"
    ],
    "wof:name":"Gokcedere",
    "wof:placetype":"locality"
},
  "geometry": {"coordinates":[36.42458,41.06513],"type":"Point"}
}