{
  "type": "Feature",
  "properties": {
    "gn:admin1_code":"24",
    "gn:asciiname":"Karaalikomu",
    "gn:cc2":"TR",
    "gn:country_code":"TR",
    "gn:dem":1556,
    "gn:feature_class":"P",
    "gn:feature_code":"PPL",
    "gn:name":"Karaalikomu",
    "gn:population":0,
    "gn:timezone":"Europe/Istanbul",
    "iso:country":"TR",
    "name:und_x_variant":[
        "Kara Al\u0131n\u0131n Komu",
        "Kara Alisuk Komu",
        "Karaalikomu"
    ],
    "wof:name":"Karaalikomu",
    "wof:placetype":"locality"
},
  "geometry": {"coordinates":[40.16667,39.91667],"type":"Point"}
}