{
  "type": "Feature",
  "properties": {
    "gn:admin1_code":"20",
    "gn:asciiname":"Karayayla",
    "gn:country_code":"TR",
    "gn:dem":1389,
    "gn:feature_class":"P",
    "gn:feature_code":"PPL",
    "gn:name":"Karayayla",
    "gn:population":0,
    "gn:timezone":"Europe/Istanbul",
    "iso:country":"TR",
    "wof:name":"Karayayla",
    "wof:placetype":"locality"
},
  "geometry": {"coordinates":[28.96374,37.35584],"type":"Point"}
}