{
  "type": "Feature",
  "properties": {
    "gn:admin1_code":"37.0",
    "gn:asciiname":"Kayalar",
    "gn:country_code":"TR",
    "gn:dem":410,
    "gn:feature_class":"P",
    "gn:feature_code":"PPL",
    "gn:name":"Kayalar",
    "gn:population":0,
    "gn:timezone":"Europe/Istanbul",
    "iso:country":"TR",
    "name:und_x_variant":[
        "Heni"
    ],
    "wof:name":"Kayalar",
    "wof:placetype":"locality"
},
  "geometry": {"coordinates":[34.04663,41.93039],"type":"Point"}
}