{
  "type": "Feature",
  "properties": {
    "gn:admin1_code":"83",
    "gn:asciiname":"Durantas",
    "gn:country_code":"TR",
    "gn:dem":961,
    "gn:feature_class":"P",
    "gn:feature_code":"PPL",
    "gn:name":"Duranta\u015f",
    "gn:population":0,
    "gn:timezone":"Europe/Istanbul",
    "iso:country":"TR",
    "name:und_x_variant":[
        "Duranta\u015f",
        "Zemge"
    ],
    "wof:name":"Durantas",
    "wof:placetype":"locality"
},
  "geometry": {"coordinates":[37.23663,37.02515],"type":"Point"}
}