{
  "type": "Feature",
  "properties": {
    "iso:country":"TU",
    "name:deu_x_preferred":[
        "G\u00fcrsu"
    ],
    "name:fra_x_preferred":[
        "G\u00fcrsu"
    ],
    "name:ita_x_preferred":[
        "Distretto di G\u00fcrsu"
    ],
    "name:min_x_preferred":[
        "G\u00fcrsu"
    ],
    "name:mrj_x_preferred":[
        "\u0413\u04f1\u0440\u0441\u0443"
    ],
    "name:msa_x_preferred":[
        "G\u00fcrsu"
    ],
    "name:nld_x_preferred":[
        "G\u00fcrsu"
    ],
    "name:pnb_x_preferred":[
        "\u0636\u0644\u0639 \u06af\u0631\u0633\u0648"
    ],
    "name:ron_x_preferred":[
        "G\u00fcrsu"
    ],
    "name:rus_x_preferred":[
        "\u0413\u044e\u0440\u0441\u0443"
    ],
    "name:und_x_colloquial":[
        "Gursu"
    ],
    "qs:gn_adm0_cc":"TR",
    "qs:gn_fcode":"PPL",
    "qs:gn_local":323777,
    "qs:gn_namadm1":"07",
    "qs:gn_name":"G\u00fcrsu",
    "qs:local_max":1873,
    "qs:local_sum":6541,
    "qs:localhoods":23,
    "qs:name":"G\u00fcrsu",
    "qs:name_adm0":"Turkey",
    "qs:name_adm1":"Antalya",
    "qs:name_adm2":"Merkez",
    "qs:name_local":"Antalya",
    "qs:photo_max":5,
    "qs:photo_sum":15,
    "qs:placetype":"Suburb",
    "qs:quad_count":5,
    "qs:woe_adm0":23424969,
    "qs:woe_adm1":2347264,
    "qs:woe_adm2":29390627,
    "qs:woe_lau":0,
    "qs:woe_local":2343733,
    "qs:woe_ver":"7.10.0",
    "wd:wordcount":59,
    "wof:lang":[
        "unk"
    ],
    "wof:name":"G\u00fcrsu",
    "wof:placetype":"neighbourhood"
},
  "geometry": {"coordinates":[30.629333,36.858672],"type":"Point"}
}