{
  "type": "Feature",
  "properties": {
    "gn:admin1_code":"78",
    "gn:asciiname":"Uckuyu",
    "gn:country_code":"TR",
    "gn:dem":1373,
    "gn:feature_class":"P",
    "gn:feature_code":"PPL",
    "gn:name":"\u00dc\u00e7kuyu",
    "gn:population":0,
    "gn:timezone":"Europe/Istanbul",
    "iso:country":"TR",
    "name:und_x_variant":[
        "\u00dc\u00e7kuyu",
        "Yass\u0131tepe"
    ],
    "wof:name":"Uckuyu",
    "wof:placetype":"locality"
},
  "geometry": {"coordinates":[33.13845999999999,37.43731],"type":"Point"}
}