{
  "type": "Feature",
  "properties": {
    "gn:admin1_code":"68.0",
    "gn:asciiname":"Tacettin",
    "gn:country_code":"TR",
    "gn:dem":956,
    "gn:feature_class":"P",
    "gn:feature_code":"PPL",
    "gn:name":"Tacettin",
    "gn:population":0,
    "gn:timezone":"Europe/Istanbul",
    "iso:country":"TR",
    "wof:name":"Tacettin",
    "wof:placetype":"locality"
},
  "geometry": {"coordinates":[31.88999,40.01428],"type":"Point"}
}