{
  "type": "Feature",
  "properties": {
    "gn:admin1_code":"48",
    "gn:asciiname":"Turbe",
    "gn:country_code":"TR",
    "gn:dem":328,
    "gn:feature_class":"P",
    "gn:feature_code":"PPL",
    "gn:name":"T\u00fcrbe",
    "gn:population":0,
    "gn:timezone":"Europe/Istanbul",
    "iso:country":"TR",
    "name:deu_x_preferred":[
        "Turbe"
    ],
    "name:tur_x_preferred":[
        "T\u00fcrbe"
    ],
    "wof:name":"Turbe",
    "wof:placetype":"locality"
},
  "geometry": {"coordinates":[28.03725,37.40328],"type":"Point"}
}