{
  "type": "Feature",
  "properties": {
    "gn:admin1_code":"25.0",
    "gn:asciiname":"Basakli",
    "gn:country_code":"TR",
    "gn:dem":1837,
    "gn:feature_class":"P",
    "gn:feature_code":"PPL",
    "gn:name":"Ba\u015fakl\u0131",
    "gn:population":0,
    "gn:timezone":"Europe/Istanbul",
    "iso:country":"TR",
    "name:tur_x_preferred":[
        "Ba\u015fakl\u0131"
    ],
    "wof:name":"Basakli",
    "wof:placetype":"locality"
},
  "geometry": {"coordinates":[41.7996,40.45723],"type":"Point"}
}