{
  "type": "Feature",
  "properties": {
    "gn:admin1_code":"15",
    "gn:asciiname":"Kumluca",
    "gn:country_code":"TR",
    "gn:dem":879,
    "gn:feature_class":"P",
    "gn:feature_code":"PPL",
    "gn:name":"Kumluca",
    "gn:population":0,
    "gn:timezone":"Europe/Istanbul",
    "iso:country":"TR",
    "name:tur_x_preferred":[
        "Kumluca"
    ],
    "wof:name":"Kumluca",
    "wof:placetype":"locality"
},
  "geometry": {"coordinates":[30.03553,37.63674],"type":"Point"}
}