{
  "type": "Feature",
  "properties": {
    "gn:admin1_code":"15",
    "gn:asciiname":"Kumluca",
    "gn:country_code":"TR",
    "gn:dem":879,
    "gn:feature_class":"P",
    "gn:feature_code":"PPL",
    "gn:name":"Kumluca",
    "gn:population":0,
    "gn:timezone":"Europe/Istanbul",
    "iso:country":"TR",
    "name:azb_x_preferred":[
        "\u0642\u0648\u0645\u0644\u0648\u062c\u0627"
    ],
    "name:deu_x_preferred":[
        "Kumluca"
    ],
    "name:epo_x_preferred":[
        "Kumluca"
    ],
    "name:fas_x_preferred":[
        "\u0642\u0648\u0645\u0644\u0648\u062c\u0627"
    ],
    "name:fra_x_preferred":[
        "Kumluca"
    ],
    "name:ita_x_preferred":[
        "Kumluca"
    ],
    "name:lbe_x_preferred":[
        "\u041a\u044a\u0443\u043c\u043b\u0443\u0434\u0436\u0430"
    ],
    "name:min_x_preferred":[
        "Kumluca"
    ],
    "name:mrj_x_preferred":[
        "\u041a\u0443\u043c\u043b\u0443\u0434\u0436\u0430"
    ],
    "name:msa_x_preferred":[
        "Kumluca"
    ],
    "name:nld_x_preferred":[
        "Kumluca"
    ],
    "name:nno_x_preferred":[
        "Kumluca"
    ],
    "name:nor_x_preferred":[
        "Kumluca"
    ],
    "name:rus_x_preferred":[
        "\u041a\u0443\u043c\u043b\u0443\u0434\u0436\u0430"
    ],
    "name:swa_x_preferred":[
        "Kumluca"
    ],
    "name:tur_x_preferred":[
        "Kumluca"
    ],
    "name:ukr_x_preferred":[
        "\u041a\u0443\u043c\u043b\u0443\u0434\u0436\u0430"
    ],
    "name:urd_x_preferred":[
        "\u06a9\u0648\u0645\u0644\u0648\u062c\u0627"
    ],
    "name:vie_x_preferred":[
        "Kumluca"
    ],
    "name:zho_x_preferred":[
        "\u5eab\u59c6\u76e7\u8cc8"
    ],
    "wof:name":"Kumluca",
    "wof:placetype":"locality"
},
  "geometry": {"coordinates":[30.03553,37.63674],"type":"Point"}
}