{
  "type": "Feature",
  "properties": {
    "gn:admin1_code":"20",
    "gn:asciiname":"Akdere",
    "gn:country_code":"TR",
    "gn:dem":765,
    "gn:feature_class":"P",
    "gn:feature_code":"PPL",
    "gn:name":"Akdere",
    "gn:population":0,
    "gn:timezone":"Europe/Istanbul",
    "iso:country":"TR",
    "name:ceb_x_preferred":[
        "Akdere"
    ],
    "name:deu_x_preferred":[
        "Akdere"
    ],
    "name:kat_x_preferred":[
        "\u10d0\u10e6\u10d3\u10d0\u10e0\u10d0"
    ],
    "name:swe_x_preferred":[
        "Akdere"
    ],
    "name:tur_x_preferred":[
        "Akdere"
    ],
    "wof:name":"Akdere",
    "wof:placetype":"locality"
},
  "geometry": {"coordinates":[29.23429,37.19123],"type":"Point"}
}