{
  "type": "Feature",
  "properties": {
    "gn:admin1_code":"68.0",
    "gn:asciiname":"Yalm Yaylasi",
    "gn:country_code":"TR",
    "gn:dem":766,
    "gn:feature_class":"P",
    "gn:feature_code":"PPL",
    "gn:name":"Yalm Yaylas\u0131",
    "gn:population":0,
    "gn:timezone":"Europe/Istanbul",
    "iso:country":"TR",
    "name:und_x_variant":[
        "Yalm Yaylas\u0131",
        "\u00c7ukurk\u00f6y"
    ],
    "wof:name":"Yalm Yaylasi",
    "wof:placetype":"locality"
},
  "geometry": {"coordinates":[33.41667,40.05],"type":"Point"}
}