{
  "type": "Feature",
  "properties": {
    "gn:admin1_code":"17",
    "gn:asciiname":"Kircalar",
    "gn:country_code":"TR",
    "gn:dem":395,
    "gn:feature_class":"P",
    "gn:feature_code":"PPL",
    "gn:name":"K\u0131rcalar",
    "gn:population":0,
    "gn:timezone":"Europe/Istanbul",
    "iso:country":"TR",
    "wof:name":"Kircalar",
    "wof:placetype":"locality"
},
  "geometry": {"coordinates":[26.55,39.61667],"type":"Point"}
}