{
  "type": "Feature",
  "properties": {
    "gn:admin1_code":"77.0",
    "gn:asciiname":"Guder",
    "gn:country_code":"TR",
    "gn:dem":1835,
    "gn:feature_class":"P",
    "gn:feature_code":"PPL",
    "gn:name":"G\u00fcder",
    "gn:population":0,
    "gn:timezone":"Europe/Istanbul",
    "iso:country":"TR",
    "name:orm_x_preferred":[
        "Gudar"
    ],
    "name:tur_x_preferred":[
        "G\u00fcder"
    ],
    "name:zho_x_preferred":[
        "\u53e4\u5fb7\u723e"
    ],
    "wof:name":"Guder",
    "wof:placetype":"locality"
},
  "geometry": {"coordinates":[40.1425,40.1259],"type":"Point"}
}