{
  "type": "Feature",
  "properties": {
    "gn:admin1_code":"46",
    "gn:asciiname":"Hasankoca",
    "gn:country_code":"TR",
    "gn:dem":776,
    "gn:feature_class":"P",
    "gn:feature_code":"PPL",
    "gn:name":"Hasankoca",
    "gn:population":0,
    "gn:timezone":"Europe/Istanbul",
    "iso:country":"TR",
    "name:tur_x_preferred":[
        "Hasankoca"
    ],
    "name:und_x_variant":[
        "Hasanhoca"
    ],
    "wof:name":"Hasankoca",
    "wof:placetype":"locality"
},
  "geometry": {"coordinates":[37.28869,37.46354],"type":"Point"}
}