{
  "type": "Feature",
  "properties": {
    "gn:admin1_code":"03",
    "gn:asciiname":"Dariseki Mahallesi",
    "gn:country_code":"TR",
    "gn:dem":1358,
    "gn:feature_class":"P",
    "gn:feature_code":"PPL",
    "gn:name":"Dar\u0131seki Mahallesi",
    "gn:population":0,
    "gn:timezone":"Europe/Istanbul",
    "iso:country":"TR",
    "wof:name":"Dariseki Mahallesi",
    "wof:placetype":"locality"
},
  "geometry": {"coordinates":[31.14693,38.88248],"type":"Point"}
}