{
  "type": "Feature",
  "properties": {
    "gn:admin1_code":"63.0",
    "gn:asciiname":"Kaymakli",
    "gn:country_code":"TR",
    "gn:dem":462,
    "gn:feature_class":"P",
    "gn:feature_code":"PPL",
    "gn:name":"Kaymakl\u0131",
    "gn:population":0,
    "gn:timezone":"Europe/Istanbul",
    "iso:country":"TR",
    "name:tur_x_preferred":[
        "Kaymakl\u0131"
    ],
    "wof:name":"Kaymakli",
    "wof:placetype":"locality"
},
  "geometry": {"coordinates":[39.50285,36.82769],"type":"Point"}
}