{
  "type": "Feature",
  "properties": {
    "gn:admin1_code":"37.0",
    "gn:asciiname":"Incebel",
    "gn:country_code":"TR",
    "gn:dem":1314,
    "gn:feature_class":"P",
    "gn:feature_code":"PPL",
    "gn:name":"\u0130ncebel",
    "gn:population":0,
    "gn:timezone":"Europe/Istanbul",
    "iso:country":"TR",
    "name:und_x_variant":[
        "Nigel",
        "\u0130ncebel"
    ],
    "wof:name":"Incebel",
    "wof:placetype":"locality"
},
  "geometry": {"coordinates":[34.06885,41.08036],"type":"Point"}
}