{
  "type": "Feature",
  "properties": {
    "gn:admin1_code":"32",
    "gn:asciiname":"Ovacik",
    "gn:country_code":"TR",
    "gn:dem":262,
    "gn:feature_class":"P",
    "gn:feature_code":"PPL",
    "gn:name":"Ovac\u0131k",
    "gn:population":0,
    "gn:timezone":"Europe/Istanbul",
    "iso:country":"TR",
    "name:tur_x_preferred":[
        "Ovac\u0131k"
    ],
    "name:tur_x_variant":[
        "Dibekli"
    ],
    "wof:name":"Ovacik",
    "wof:placetype":"locality"
},
  "geometry": {"coordinates":[33.67008,36.18457],"type":"Point"}
}