{
  "type": "Feature",
  "properties": {
    "gn:admin1_code":"58.0",
    "gn:asciiname":"Gunisik",
    "gn:country_code":"TR",
    "gn:dem":1476,
    "gn:feature_class":"P",
    "gn:feature_code":"PPL",
    "gn:name":"G\u00fcn\u0131\u015f\u0131k",
    "gn:population":0,
    "gn:timezone":"Europe/Istanbul",
    "iso:country":"TR",
    "name:tur_x_preferred":[
        "G\u00fcn\u0131\u015f\u0131k"
    ],
    "wof:name":"Gunisik",
    "wof:placetype":"locality"
},
  "geometry": {"coordinates":[37.8947,40.18998],"type":"Point"}
}