{
  "type": "Feature",
  "properties": {
    "gn:admin1_code":"59.0",
    "gn:asciiname":"Gunduzlu",
    "gn:country_code":"TR",
    "gn:dem":114,
    "gn:feature_class":"P",
    "gn:feature_code":"PPL",
    "gn:name":"G\u00fcnd\u00fczl\u00fc",
    "gn:population":0,
    "gn:timezone":"Europe/Istanbul",
    "iso:country":"TR",
    "wof:name":"Gunduzlu",
    "wof:placetype":"locality"
},
  "geometry": {"coordinates":[27.64285,41.03333],"type":"Point"}
}