{
  "type": "Feature",
  "properties": {
    "gn:admin1_code":"13",
    "gn:asciiname":"Konuksayar",
    "gn:country_code":"TR",
    "gn:dem":1726,
    "gn:feature_class":"P",
    "gn:feature_code":"PPL",
    "gn:name":"Konuksayar",
    "gn:population":0,
    "gn:timezone":"Europe/Istanbul",
    "iso:country":"TR",
    "name:tur_x_preferred":[
        "Konuksayar"
    ],
    "wof:name":"Konuksayar",
    "wof:placetype":"locality"
},
  "geometry": {"coordinates":[42.01657,38.40738],"type":"Point"}
}