{
  "type": "Feature",
  "properties": {
    "gn:admin1_code":"17.0",
    "gn:asciiname":"Ciftlikdere",
    "gn:country_code":"TR",
    "gn:dem":123,
    "gn:feature_class":"P",
    "gn:feature_code":"PPL",
    "gn:name":"\u00c7iftlikdere",
    "gn:population":0,
    "gn:timezone":"Europe/Istanbul",
    "iso:country":"TR",
    "name:und_x_variant":[
        "\u00c7iftlikk\u00f6y",
        "\u00c7iftlik",
        "\u00c7iftlikdere"
    ],
    "wof:name":"Ciftlikdere",
    "wof:placetype":"locality"
},
  "geometry": {"coordinates":[26.53083,40.05684],"type":"Point"}
}