{
  "type": "Feature",
  "properties": {
    "gn:admin1_code":"89",
    "gn:asciiname":"Orenler",
    "gn:country_code":"TR",
    "gn:dem":602,
    "gn:feature_class":"P",
    "gn:feature_code":"PPL",
    "gn:name":"\u00d6renler",
    "gn:population":0,
    "gn:timezone":"Europe/Istanbul",
    "iso:country":"TR",
    "wof:name":"Orenler",
    "wof:placetype":"locality"
},
  "geometry": {"coordinates":[32.31593,41.1298],"type":"Point"}
}