{
  "type": "Feature",
  "properties": {
    "gn:admin1_code":"37.0",
    "gn:asciiname":"Alcilar",
    "gn:country_code":"TR",
    "gn:dem":1206,
    "gn:feature_class":"P",
    "gn:feature_code":"PPL",
    "gn:name":"Al\u00e7\u0131lar",
    "gn:population":0,
    "gn:timezone":"Europe/Istanbul",
    "iso:country":"TR",
    "wof:name":"Alcilar",
    "wof:placetype":"locality"
},
  "geometry": {"coordinates":[33.89058,41.76299],"type":"Point"}
}