{
  "type": "Feature",
  "properties": {
    "iso:country":"TR",
    "qs:name":"Evka-3",
    "qs:name_adm0":"Turkey",
    "qs:name_adm1":"\u0130zmir",
    "qs:photos":56,
    "qs:photos_1k":11,
    "qs:photos_9k":1,
    "qs:photos_9r":2,
    "qs:photos_all":56,
    "qs:photos_sr":2,
    "qs:placetype":"Town",
    "qs:pop_sr":"0",
    "wof:name":"Evka-3",
    "wof:placetype":"locality"
},
  "geometry": {"coordinates":[27.248972,38.4719185],"type":"Point"}
}