{
  "type": "Feature",
  "properties": {
    "gn:country":"TR",
    "gn:fcode":"PPL",
    "gn:population":450,
    "iso:country":"TR",
    "name:ava_x_preferred":[
        "\u0410\u0439\u0434\u044b\u043d\u0442\u0435\u043f\u0435"
    ],
    "name:ceb_x_preferred":[
        "Ayd\u0131ntepe"
    ],
    "name:deu_x_preferred":[
        "Ayd\u0131ntepe"
    ],
    "name:fas_x_preferred":[
        "\u0622\u06cc\u062f\u06cc\u0646\u200c\u062a\u067e\u0647"
    ],
    "name:fra_x_preferred":[
        "Ayd\u0131ntepe"
    ],
    "name:mrj_x_preferred":[
        "\u0410\u0439\u0434\u044b\u043d\u0442\u0435\u043f\u0435"
    ],
    "name:msa_x_preferred":[
        "Ayd\u0131ntepe"
    ],
    "name:nld_x_preferred":[
        "Ayd\u0131ntepe"
    ],
    "name:nor_x_preferred":[
        "Ayd\u0131ntepe"
    ],
    "name:pnb_x_preferred":[
        "\u0636\u0644\u0639 \u0622\u0626\u06cc\u062f\u0646\u0679\u06cc\u067e"
    ],
    "name:rus_x_preferred":[
        "\u0410\u0439\u0434\u044b\u043d\u0442\u0435\u043f\u0435"
    ],
    "name:swa_x_preferred":[
        "Ayd\u0131ntepe"
    ],
    "name:tur_x_preferred":[
        "Ayd\u0131ntepe"
    ],
    "name:und_x_variant":[
        "Tilma\u011fara"
    ],
    "name:urd_x_preferred":[
        "\u0622\u06cc\u062f\u06cc\u0646\u062a\u06cc\u067e\u06d2"
    ],
    "name:vie_x_preferred":[
        "Ayd\u0131ntepe"
    ],
    "qs:name":"Aydintepe",
    "qs:name_adm0":"Turkey",
    "qs:name_adm1":"Gaziantep",
    "qs:photos_9r":0,
    "qs:photos_sr":0,
    "qs:placetype":"Suburb",
    "qs:pop_sr":"2",
    "wd:wordcount":100,
    "wof:name":"Aydintepe",
    "wof:placetype":"neighbourhood",
    "wof:population":450
},
  "geometry": {"coordinates":[37.94333,36.95361],"type":"Point"}
}