{
  "type": "Feature",
  "properties": {
    "gn:country":"TR",
    "gn:fcode":"PPL",
    "gn:pop":450,
    "iso:country":"TR",
    "name:unk_x_variant":[
        "Tilma\u011fara"
    ],
    "qs:name":"Aydintepe",
    "qs:name_adm0":"Turkey",
    "qs:name_adm1":"Gaziantep",
    "qs:photos_9r":0,
    "qs:photos_sr":0,
    "qs:placetype":"Suburb",
    "qs:pop_sr":"2",
    "wd:wordcount":100,
    "wof:name":"Aydintepe",
    "wof:placetype":"neighbourhood",
    "wof:population":450
},
  "geometry": {"coordinates":[37.94333,36.95361],"type":"Point"}
}