{
  "type": "Feature",
  "properties": {
    "gn:admin1_code":"60.0",
    "gn:asciiname":"Tozanlifindicak",
    "gn:country_code":"TR",
    "gn:dem":912,
    "gn:feature_class":"P",
    "gn:feature_code":"PPL",
    "gn:name":"Tozanl\u0131f\u0131nd\u0131cak",
    "gn:population":0,
    "gn:timezone":"Europe/Istanbul",
    "iso:country":"TR",
    "wof:name":"Tozanlifindicak",
    "wof:placetype":"locality"
},
  "geometry": {"coordinates":[37.31916,40.30258],"type":"Point"}
}