{
  "type": "Feature",
  "properties": {
    "gn:admin1_code":"60.0",
    "gn:asciiname":"Yagmur",
    "gn:country_code":"TR",
    "gn:dem":1206,
    "gn:feature_class":"P",
    "gn:feature_code":"PPL",
    "gn:name":"Ya\u011fmur",
    "gn:population":0,
    "gn:timezone":"Europe/Istanbul",
    "iso:country":"TR",
    "wof:name":"Yagmur",
    "wof:placetype":"locality"
},
  "geometry": {"coordinates":[36.25108,40.05181],"type":"Point"}
}