{
  "type": "Feature",
  "properties": {
    "gn:admin1_code":"35",
    "gn:asciiname":"Godence",
    "gn:country_code":"TR",
    "gn:dem":437,
    "gn:feature_class":"P",
    "gn:feature_code":"PPL",
    "gn:name":"G\u00f6dence",
    "gn:population":0,
    "gn:timezone":"Europe/Istanbul",
    "iso:country":"TR",
    "wof:name":"Godence",
    "wof:placetype":"locality"
},
  "geometry": {"coordinates":[26.91894000000001,38.27059000000001],"type":"Point"}
}