{
  "type": "Feature",
  "properties": {
    "iso:country":"TR",
    "name:eng_x_preferred":[
        "Camlibahce"
    ],
    "name:tur_x_preferred":[
        "\u00c7aml\u0131bah\u00e7e"
    ],
    "wof:name":"Camlibahce",
    "wof:placetype":"neighbourhood"
},
  "geometry": {"coordinates":[29.0842417092554,41.14928134139704],"type":"Point"}
}