{
  "type": "Feature",
  "properties": {
    "gn:country":"TR",
    "gn:fcode":"PPL",
    "gn:population":430,
    "iso:country":"TR",
    "name:und_x_variant":[
        "Zivnik"
    ],
    "qs:name":"Di\u015flinar",
    "qs:photos_9r":0,
    "qs:photos_sr":0,
    "qs:pop_sr":"2",
    "wof:name":"Di\u015flinar",
    "wof:placetype":"locality",
    "wof:population":430
},
  "geometry": {"coordinates":[42.31889,37.97167],"type":"Point"}
}