{
  "type": "Feature",
  "properties": {
    "gn:admin1_code":"59.0",
    "gn:asciiname":"Danisment",
    "gn:country_code":"TR",
    "gn:dem":75,
    "gn:feature_class":"P",
    "gn:feature_code":"PPL",
    "gn:name":"Dani\u015fment",
    "gn:population":0,
    "gn:timezone":"Europe/Istanbul",
    "iso:country":"TR",
    "name:und_x_variant":[
        "B\u00fcy\u00fck Dani\u015fmend",
        "Dani\u015fment"
    ],
    "wof:name":"Danisment",
    "wof:placetype":"locality"
},
  "geometry": {"coordinates":[26.95303,41.30325],"type":"Point"}
}