{
  "type": "Feature",
  "properties": {
    "gn:admin1_code":"48",
    "gn:asciiname":"Fadil",
    "gn:country_code":"TR",
    "gn:dem":635,
    "gn:feature_class":"P",
    "gn:feature_code":"PPL",
    "gn:name":"Fad\u0131l",
    "gn:population":0,
    "gn:timezone":"Europe/Istanbul",
    "iso:country":"TR",
    "wof:name":"Fadil",
    "wof:placetype":"locality"
},
  "geometry": {"coordinates":[28.61873,37.29713],"type":"Point"}
}