{
  "type": "Feature",
  "properties": {
    "gn:admin1_code":"80.0",
    "gn:asciiname":"Gyuryuzan",
    "gn:country_code":"TR",
    "gn:dem":451,
    "gn:feature_class":"P",
    "gn:feature_code":"PPL",
    "gn:name":"Gyuryuzan",
    "gn:population":0,
    "gn:timezone":"Europe/Istanbul",
    "iso:country":"TR",
    "name:und_x_variant":[
        "G\u00fcr\u00fczan"
    ],
    "wof:name":"Gyuryuzan",
    "wof:placetype":"locality"
},
  "geometry": {"coordinates":[41.84917,37.44861],"type":"Point"}
}