{
  "type": "Feature",
  "properties": {
    "gn:admin1_code":"54",
    "gn:asciiname":"Nushetiye",
    "gn:country_code":"TR",
    "gn:dem":134,
    "gn:feature_class":"P",
    "gn:feature_code":"PPL",
    "gn:name":"N\u00fcshetiye",
    "gn:population":0,
    "gn:timezone":"Europe/Istanbul",
    "iso:country":"TR",
    "name:tur_x_preferred":[
        "N\u00fcshetiye"
    ],
    "wof:name":"Nushetiye",
    "wof:placetype":"locality"
},
  "geometry": {"coordinates":[30.72128,40.79493],"type":"Point"}
}