{
  "type": "Feature",
  "properties": {
    "gn:admin1_code":"44",
    "gn:asciiname":"Tasevler",
    "gn:country_code":"TR",
    "gn:dem":1346,
    "gn:feature_class":"P",
    "gn:feature_code":"PPL",
    "gn:name":"Ta\u015fevler",
    "gn:population":0,
    "gn:timezone":"Europe/Istanbul",
    "iso:country":"TR",
    "name:tur_x_preferred":[
        "Ta\u015fevler"
    ],
    "wof:name":"Tasevler",
    "wof:placetype":"locality"
},
  "geometry": {"coordinates":[37.73974000000001,38.42693],"type":"Point"}
}