{
  "type": "Feature",
  "properties": {
    "gn:admin1_code":"21",
    "gn:asciiname":"Yukarikaya",
    "gn:country_code":"TR",
    "gn:dem":682,
    "gn:feature_class":"P",
    "gn:feature_code":"PPL",
    "gn:name":"Yukar\u0131kaya",
    "gn:population":0,
    "gn:timezone":"Europe/Istanbul",
    "iso:country":"TR",
    "wof:name":"Yukarikaya",
    "wof:placetype":"locality"
},
  "geometry": {"coordinates":[40.65,38.08333],"type":"Point"}
}