{
  "type": "Feature",
  "properties": {
    "gn:admin1_code":"5.0",
    "gn:asciiname":"Kusburnu",
    "gn:country_code":"TR",
    "gn:dem":1227,
    "gn:feature_class":"P",
    "gn:feature_code":"PPL",
    "gn:name":"Ku\u015fburnu",
    "gn:population":0,
    "gn:timezone":"Europe/Istanbul",
    "iso:country":"TR",
    "wof:name":"Kusburnu",
    "wof:placetype":"locality"
},
  "geometry": {"coordinates":[35.2132,40.96714],"type":"Point"}
}