{
  "type": "Feature",
  "properties": {
    "gn:admin1_code":"07",
    "gn:asciiname":"Yaylali",
    "gn:country_code":"TR",
    "gn:dem":135,
    "gn:feature_class":"P",
    "gn:feature_code":"PPL",
    "gn:name":"Yaylal\u0131",
    "gn:population":0,
    "gn:timezone":"Europe/Istanbul",
    "iso:country":"TR",
    "wof:name":"Yaylali",
    "wof:placetype":"locality"
},
  "geometry": {"coordinates":[32.10590999999999,36.51444],"type":"Point"}
}