{
  "type": "Feature",
  "properties": {
    "gn:admin1_code":"70",
    "gn:asciiname":"Kadikoy",
    "gn:country_code":"TR",
    "gn:dem":1920,
    "gn:feature_class":"P",
    "gn:feature_code":"PPL",
    "gn:name":"Kad\u0131k\u00f6y",
    "gn:population":0,
    "gn:timezone":"Europe/Istanbul",
    "iso:country":"TR",
    "name:und_x_variant":[
        "Kad\u0131k\u00f6y",
        "Kad\u0131k\u00f6\u015fk"
    ],
    "wof:name":"Kadikoy",
    "wof:placetype":"locality"
},
  "geometry": {"coordinates":[44.13793,37.54759],"type":"Point"}
}