{
  "type": "Feature",
  "properties": {
    "gn:admin1_code":"58",
    "gn:asciiname":"Goloren",
    "gn:country_code":"TR",
    "gn:dem":1471,
    "gn:feature_class":"P",
    "gn:feature_code":"PPL",
    "gn:name":"G\u00f6l\u00f6ren",
    "gn:population":0,
    "gn:timezone":"Europe/Istanbul",
    "iso:country":"TR",
    "wof:name":"Goloren",
    "wof:placetype":"locality"
},
  "geometry": {"coordinates":[37.75992,39.41457],"type":"Point"}
}