{
  "type": "Feature",
  "properties": {
    "gn:admin1_code":"13",
    "gn:asciiname":"Alakir",
    "gn:country_code":"TR",
    "gn:dem":1905,
    "gn:feature_class":"P",
    "gn:feature_code":"PPL",
    "gn:name":"Alak\u0131r",
    "gn:population":0,
    "gn:timezone":"Europe/Istanbul",
    "iso:country":"TR",
    "name:tur_x_preferred":[
        "Alak\u0131r"
    ],
    "name:und_x_variant":[
        "Mezik"
    ],
    "wof:name":"Alakir",
    "wof:placetype":"locality"
},
  "geometry": {"coordinates":[42.18335,38.80343],"type":"Point"}
}