{
  "type": "Feature",
  "properties": {
    "gn:admin1_code":"68",
    "gn:asciiname":"Kucukboyalik",
    "gn:country_code":"TR",
    "gn:dem":1099,
    "gn:feature_class":"P",
    "gn:feature_code":"PPL",
    "gn:name":"K\u00fc\u00e7\u00fckboyal\u0131k",
    "gn:population":0,
    "gn:timezone":"Europe/Istanbul",
    "iso:country":"TR",
    "name:und_x_variant":[
        "Boyal\u0131k Sa\u011f\u0131r",
        "K\u00fc\u00e7\u00fckboyal\u0131k"
    ],
    "wof:name":"Kucukboyalik",
    "wof:placetype":"locality"
},
  "geometry": {"coordinates":[33.23977,39.57443],"type":"Point"}
}