{
  "type": "Feature",
  "properties": {
    "gn:admin1_code":"37.0",
    "gn:asciiname":"Kizilcakaya",
    "gn:country_code":"TR",
    "gn:dem":491,
    "gn:feature_class":"P",
    "gn:feature_code":"PPL",
    "gn:name":"K\u0131z\u0131lcakaya",
    "gn:population":0,
    "gn:timezone":"Europe/Istanbul",
    "iso:country":"TR",
    "name:und_x_variant":[
        "K\u0131z\u0131lcakaya K\u00f6y",
        "K\u0131z\u0131lcakaya K\u00f6y\u00fc",
        "K\u0131z\u0131lcakaya"
    ],
    "wof:name":"Kizilcakaya",
    "wof:placetype":"locality"
},
  "geometry": {"coordinates":[34.28398,41.85658],"type":"Point"}
}