{
  "type": "Feature",
  "properties": {
    "gn:admin1_code":"38",
    "gn:asciiname":"Kizik",
    "gn:country_code":"TR",
    "gn:dem":1618,
    "gn:feature_class":"P",
    "gn:feature_code":"PPL",
    "gn:name":"K\u0131z\u0131k",
    "gn:population":0,
    "gn:timezone":"Europe/Istanbul",
    "iso:country":"TR",
    "wof:name":"Kizik",
    "wof:placetype":"locality"
},
  "geometry": {"coordinates":[35.39823,38.4395],"type":"Point"}
}