{
  "type": "Feature",
  "properties": {
    "gn:admin1_code":"72",
    "gn:asciiname":"Balova",
    "gn:country_code":"TR",
    "gn:dem":503,
    "gn:feature_class":"P",
    "gn:feature_code":"PPL",
    "gn:name":"Balova",
    "gn:population":0,
    "gn:timezone":"Europe/Istanbul",
    "iso:country":"TR",
    "name:tur_x_preferred":[
        "Balova"
    ],
    "wof:name":"Balova",
    "wof:placetype":"locality"
},
  "geometry": {"coordinates":[40.23151,37.23864],"type":"Point"}
}