{
  "type": "Feature",
  "properties": {
    "gn:admin1_code":"22.0",
    "gn:asciiname":"Kemalkoy",
    "gn:country_code":"TR",
    "gn:dem":80,
    "gn:feature_class":"P",
    "gn:feature_code":"PPL",
    "gn:name":"Kemalk\u00f6y",
    "gn:population":0,
    "gn:timezone":"Europe/Istanbul",
    "iso:country":"TR",
    "name:tur_x_preferred":[
        "Kemalk\u00f6y"
    ],
    "name:tur_x_variant":[
        "Kemal"
    ],
    "wof:name":"Kemalkoy",
    "wof:placetype":"locality"
},
  "geometry": {"coordinates":[26.39608,41.73559],"type":"Point"}
}