{
  "type": "Feature",
  "properties": {
    "gn:admin1_code":"5.0",
    "gn:asciiname":"Karamagara",
    "gn:country_code":"TR",
    "gn:dem":913,
    "gn:feature_class":"P",
    "gn:feature_code":"PPL",
    "gn:name":"Karama\u011fara",
    "gn:population":0,
    "gn:timezone":"Europe/Istanbul",
    "iso:country":"TR",
    "wof:name":"Karamagara",
    "wof:placetype":"locality"
},
  "geometry": {"coordinates":[35.38596,40.884],"type":"Point"}
}