{
  "type": "Feature",
  "properties": {
    "iso:country":"TR",
    "name:eng_x_preferred":[
        "Osmankoy"
    ],
    "name:tur_x_preferred":[
        "Osmank\u00f6y"
    ],
    "wof:name":"Osmankoy",
    "wof:placetype":"neighbourhood"
},
  "geometry": {"coordinates":[29.73132975210313,41.08206288611464],"type":"Point"}
}