{
  "type": "Feature",
  "properties": {
    "gn:admin1_code":"20",
    "gn:asciiname":"Kapiz",
    "gn:country_code":"TR",
    "gn:dem":955,
    "gn:feature_class":"P",
    "gn:feature_code":"PPL",
    "gn:name":"Kap\u0131z",
    "gn:population":0,
    "gn:timezone":"Europe/Istanbul",
    "iso:country":"TR",
    "wof:name":"Kapiz",
    "wof:placetype":"locality"
},
  "geometry": {"coordinates":[28.89775,37.28028],"type":"Point"}
}