{
  "type": "Feature",
  "properties": {
    "gn:admin1_code":"90",
    "gn:asciiname":"Cakallipinar",
    "gn:country_code":"TR",
    "gn:dem":706,
    "gn:feature_class":"P",
    "gn:feature_code":"PPL",
    "gn:name":"\u00c7akall\u0131p\u0131nar",
    "gn:population":0,
    "gn:timezone":"Europe/Istanbul",
    "iso:country":"TR",
    "name:tur_x_preferred":[
        "\u00c7akall\u0131p\u0131nar"
    ],
    "name:und_x_variant":[
        "\u00c7akalp\u0131nar",
        "\u00c7akal\u0131p\u0131nar"
    ],
    "wof:name":"Cakallipinar",
    "wof:placetype":"locality"
},
  "geometry": {"coordinates":[37.08583,36.78944],"type":"Point"}
}