{
  "type": "Feature",
  "properties": {
    "gn:admin1_code":"60.0",
    "gn:asciiname":"Ekinlik",
    "gn:country_code":"TR",
    "gn:dem":1171,
    "gn:feature_class":"P",
    "gn:feature_code":"PPL",
    "gn:name":"Ekinlik",
    "gn:population":0,
    "gn:timezone":"Europe/Istanbul",
    "iso:country":"TR",
    "name:und_x_variant":[
        "Ak\u0131n",
        "Ahin",
        "Ekinlik"
    ],
    "wof:name":"Ekinlik",
    "wof:placetype":"locality"
},
  "geometry": {"coordinates":[36.44475,40.12717],"type":"Point"}
}