{
  "type": "Feature",
  "properties": {
    "gn:admin1_code":"04",
    "gn:asciiname":"Mollaosmankomu",
    "gn:country_code":"TR",
    "gn:dem":1844,
    "gn:feature_class":"P",
    "gn:feature_code":"PPL",
    "gn:name":"Mollaosmankomu",
    "gn:population":0,
    "gn:timezone":"Europe/Istanbul",
    "iso:country":"TR",
    "wof:name":"Mollaosmankomu",
    "wof:placetype":"locality"
},
  "geometry": {"coordinates":[43.06499,39.88996],"type":"Point"}
}