{
  "type": "Feature",
  "properties": {
    "gn:admin1_code":"76.0",
    "gn:asciiname":"Tepecik",
    "gn:country_code":"TR",
    "gn:dem":1529,
    "gn:feature_class":"P",
    "gn:feature_code":"PPL",
    "gn:name":"Tepecik",
    "gn:population":0,
    "gn:timezone":"Europe/Istanbul",
    "iso:country":"TR",
    "wof:name":"Tepecik",
    "wof:placetype":"locality"
},
  "geometry": {"coordinates":[41.62118,38.30717],"type":"Point"}
}