{
  "type": "Feature",
  "properties": {
    "gn:admin1_code":"52.0",
    "gn:asciiname":"Hoskadem",
    "gn:country_code":"TR",
    "gn:dem":457,
    "gn:feature_class":"P",
    "gn:feature_code":"PPL",
    "gn:name":"Ho\u015fkadem",
    "gn:population":0,
    "gn:timezone":"Europe/Istanbul",
    "iso:country":"TR",
    "wof:name":"Hoskadem",
    "wof:placetype":"locality"
},
  "geometry": {"coordinates":[37.44304,40.73193],"type":"Point"}
}