{
  "type": "Feature",
  "properties": {
    "gn:admin1_code":"70",
    "gn:asciiname":"Dalka",
    "gn:country_code":"TR",
    "gn:dem":1906,
    "gn:feature_class":"P",
    "gn:feature_code":"PPL",
    "gn:name":"Dalka",
    "gn:population":0,
    "gn:timezone":"Europe/Istanbul",
    "iso:country":"TR",
    "name:und_x_variant":[
        "Tekirova",
        "Takrabat",
        "Dalka",
        "Takurabat"
    ],
    "wof:name":"Dalka",
    "wof:placetype":"locality"
},
  "geometry": {"coordinates":[44.07754,37.71641],"type":"Point"}
}