{
  "type": "Feature",
  "properties": {
    "gn:admin1_code":"63.0",
    "gn:asciiname":"Kurucahuyuk",
    "gn:country_code":"TR",
    "gn:dem":518,
    "gn:feature_class":"P",
    "gn:feature_code":"PPL",
    "gn:name":"Kurucah\u00fcy\u00fck",
    "gn:population":0,
    "gn:timezone":"Europe/Istanbul",
    "iso:country":"TR",
    "name:tur_x_preferred":[
        "Kurucah\u00fcy\u00fck"
    ],
    "wof:name":"Kurucahuyuk",
    "wof:placetype":"locality"
},
  "geometry": {"coordinates":[38.09718,37.00784],"type":"Point"}
}