{
  "type": "Feature",
  "properties": {
    "gn:admin1_code":"46",
    "gn:asciiname":"Kumarli",
    "gn:country_code":"TR",
    "gn:dem":1158,
    "gn:feature_class":"P",
    "gn:feature_code":"PPL",
    "gn:name":"Kumarl\u0131",
    "gn:population":0,
    "gn:timezone":"Europe/Istanbul",
    "iso:country":"TR",
    "name:tur_x_preferred":[
        "Kumarl\u0131"
    ],
    "name:und_x_variant":[
        "Kumarl\u0131"
    ],
    "name:vie_x_preferred":[
        "Kumarl\u0131"
    ],
    "wof:name":"Kumarli",
    "wof:placetype":"locality"
},
  "geometry": {"coordinates":[36.53591,37.83944],"type":"Point"}
}