{
  "type": "Feature",
  "properties": {
    "gn:admin1_code":"58",
    "gn:asciiname":"Tatlipinar",
    "gn:country_code":"TR",
    "gn:dem":1634,
    "gn:feature_class":"P",
    "gn:feature_code":"PPL",
    "gn:name":"Tatl\u0131p\u0131nar",
    "gn:population":0,
    "gn:timezone":"Europe/Istanbul",
    "iso:country":"TR",
    "wof:name":"Tatlipinar",
    "wof:placetype":"locality"
},
  "geometry": {"coordinates":[37.57643,39.3877],"type":"Point"}
}