{
  "type": "Feature",
  "properties": {
    "gn:admin1_code":"75",
    "gn:asciiname":"Gollu",
    "gn:country_code":"TR",
    "gn:dem":1204,
    "gn:feature_class":"P",
    "gn:feature_code":"PPL",
    "gn:name":"G\u00f6ll\u00fc",
    "gn:population":0,
    "gn:timezone":"Europe/Istanbul",
    "iso:country":"TR",
    "wof:name":"Gollu",
    "wof:placetype":"locality"
},
  "geometry": {"coordinates":[33.81149,38.83933],"type":"Point"}
}