{
  "type": "Feature",
  "properties": {
    "gn:admin1_code":"48",
    "gn:asciiname":"Hacibedeler",
    "gn:country_code":"TR",
    "gn:dem":396,
    "gn:feature_class":"P",
    "gn:feature_code":"PPL",
    "gn:name":"Hac\u0131bedeler",
    "gn:population":0,
    "gn:timezone":"Europe/Istanbul",
    "iso:country":"TR",
    "name:tur_x_preferred":[
        "Hac\u0131bedeler"
    ],
    "wof:name":"Hacibedeler",
    "wof:placetype":"locality"
},
  "geometry": {"coordinates":[28.04121,37.4306],"type":"Point"}
}