{
  "type": "Feature",
  "properties": {
    "gn:admin1_code":"78",
    "gn:asciiname":"Yazili",
    "gn:country_code":"TR",
    "gn:dem":1055,
    "gn:feature_class":"P",
    "gn:feature_code":"PPL",
    "gn:name":"Yaz\u0131l\u0131",
    "gn:population":0,
    "gn:timezone":"Europe/Istanbul",
    "iso:country":"TR",
    "name:tur_x_preferred":[
        "Yaz\u0131l\u0131"
    ],
    "wof:name":"Yazili",
    "wof:placetype":"locality"
},
  "geometry": {"coordinates":[33.10429,37.15611],"type":"Point"}
}