{
  "type": "Feature",
  "properties": {
    "iso:country":"TR",
    "name:ceb_x_preferred":[
        "Pasa"
    ],
    "name:ita_x_preferred":[
        "Pasa"
    ],
    "name:jav_x_preferred":[
        "Pasa"
    ],
    "name:spa_x_preferred":[
        "Pasa"
    ],
    "name:srp_x_preferred":[
        "Pasa"
    ],
    "name:swe_x_preferred":[
        "Pasa"
    ],
    "name:tur_x_preferred":[
        "Pa\u015fa"
    ],
    "wof:name":"Pasa",
    "wof:placetype":"neighbourhood"
},
  "geometry": {"coordinates":[28.9744812584193,41.05418919131718],"type":"Point"}
}