{
  "type": "Feature",
  "properties": {
    "gn:country":"TR",
    "gn:fcode":"PPL",
    "gn:population":309,
    "iso:country":"TR",
    "name:rus_x_preferred":[
        "Yarymtepek\u00eby"
    ],
    "name:und_x_variant":[
        "Yarun Tepe"
    ],
    "qs:name":"Yar\u0131mtepe",
    "qs:photos_9r":0,
    "qs:photos_sr":0,
    "qs:pop_sr":"2",
    "wof:name":"Yar\u0131mtepe",
    "wof:placetype":"locality",
    "wof:population":309
},
  "geometry": {"coordinates":[37.71472,36.93722],"type":"Point"}
}