{
  "type": "Feature",
  "properties": {
    "gn:admin1_code":"68.0",
    "gn:asciiname":"Yukarihuyuk",
    "gn:country_code":"TR",
    "gn:dem":1245,
    "gn:feature_class":"P",
    "gn:feature_code":"PPL",
    "gn:name":"Yukar\u0131h\u00fcy\u00fck",
    "gn:population":0,
    "gn:timezone":"Europe/Istanbul",
    "iso:country":"TR",
    "name:und_x_variant":[
        "H\u00fcy\u00fckb\u00e2l\u00e2",
        "Yukar\u0131h\u00fcy\u00fck"
    ],
    "wof:name":"Yukarihuyuk",
    "wof:placetype":"locality"
},
  "geometry": {"coordinates":[32.34303,40.35557],"type":"Point"}
}