{
  "type": "Feature",
  "properties": {
    "gn:admin1_code":"85",
    "gn:asciiname":"Kayikcilar",
    "gn:country_code":"TR",
    "gn:dem":30,
    "gn:feature_class":"P",
    "gn:feature_code":"PPL",
    "gn:name":"Kay\u0131k\u00e7\u0131lar",
    "gn:population":0,
    "gn:timezone":"Europe/Istanbul",
    "iso:country":"TR",
    "wof:name":"Kayikcilar",
    "wof:placetype":"locality"
},
  "geometry": {"coordinates":[32.08982,41.38894000000001],"type":"Point"}
}