{
  "type": "Feature",
  "properties": {
    "gn:admin1_code":"21",
    "gn:asciiname":"Gezerli",
    "gn:country_code":"TR",
    "gn:dem":850,
    "gn:feature_class":"P",
    "gn:feature_code":"PPL",
    "gn:name":"Gezerli",
    "gn:population":0,
    "gn:timezone":"Europe/Istanbul",
    "iso:country":"TR",
    "name:tur_x_preferred":[
        "Musa"
    ],
    "name:und_x_variant":[
        "Musan",
        "Gezerli"
    ],
    "wof:name":"Gezerli",
    "wof:placetype":"locality"
},
  "geometry": {"coordinates":[40.00744,38.18461],"type":"Point"}
}