{
  "type": "Feature",
  "properties": {
    "gn:admin1_code":"10",
    "gn:asciiname":"Koyluce",
    "gn:country_code":"TR",
    "gn:dem":147,
    "gn:feature_class":"P",
    "gn:feature_code":"PPL",
    "gn:name":"K\u00f6yl\u00fcce",
    "gn:population":0,
    "gn:timezone":"Europe/Istanbul",
    "iso:country":"TR",
    "name:tur_x_preferred":[
        "K\u00f6yl\u00fcce"
    ],
    "wof:name":"Koyluce",
    "wof:placetype":"locality"
},
  "geometry": {"coordinates":[27.16667,39.54667],"type":"Point"}
}