{
  "type": "Feature",
  "properties": {
    "gn:admin1_code":"81.0",
    "gn:asciiname":"Kilicikli",
    "gn:country_code":"TR",
    "gn:dem":620,
    "gn:feature_class":"P",
    "gn:feature_code":"PPL",
    "gn:name":"K\u0131l\u0131\u00e7\u0131kl\u0131",
    "gn:population":0,
    "gn:timezone":"Europe/Istanbul",
    "iso:country":"TR",
    "wof:name":"Kilicikli",
    "wof:placetype":"locality"
},
  "geometry": {"coordinates":[35.96725,37.65046],"type":"Point"}
}