{
  "type": "Feature",
  "properties": {
    "gn:admin1_code":"25",
    "gn:asciiname":"Karaseyh",
    "gn:country_code":"TR",
    "gn:dem":2182,
    "gn:feature_class":"P",
    "gn:feature_code":"PPL",
    "gn:name":"Kara\u015feyh",
    "gn:population":0,
    "gn:timezone":"Europe/Istanbul",
    "iso:country":"TR",
    "name:tur_x_preferred":[
        "Kara\u015feyh"
    ],
    "wof:name":"Karaseyh",
    "wof:placetype":"locality"
},
  "geometry": {"coordinates":[41.12172,39.67077000000001],"type":"Point"}
}