{
  "type": "Feature",
  "properties": {
    "gn:admin1_code":"07",
    "gn:asciiname":"Gedikbasi",
    "gn:country_code":"TR",
    "gn:dem":804,
    "gn:feature_class":"P",
    "gn:feature_code":"PPL",
    "gn:name":"Gedikba\u015f\u0131",
    "gn:population":0,
    "gn:timezone":"Europe/Istanbul",
    "iso:country":"TR",
    "wof:name":"Gedikbasi",
    "wof:placetype":"locality"
},
  "geometry": {"coordinates":[29.75626,36.42828],"type":"Point"}
}