{
  "type": "Feature",
  "properties": {
    "iso:country":"TR",
    "qs:name":"\u00d6zt\u00fcrk",
    "qs:name_adm0":"Turkey",
    "qs:name_adm1":"Ankara",
    "qs:photos":196,
    "qs:photos_1k":40,
    "qs:photos_9k":1,
    "qs:photos_9r":4,
    "qs:photos_all":196,
    "qs:photos_sr":4,
    "qs:placetype":"Suburb",
    "qs:pop_sr":"0",
    "wd:wordcount":280,
    "wof:name":"\u00d6zt\u00fcrk",
    "wof:placetype":"neighbourhood"
},
  "geometry": {"coordinates":[32.8580005,39.9439295],"type":"Point"}
}