{
  "type": "Feature",
  "properties": {
    "gn:admin1_code":"38",
    "gn:asciiname":"Yarimtepe",
    "gn:country_code":"TR",
    "gn:dem":1554,
    "gn:feature_class":"P",
    "gn:feature_code":"PPL",
    "gn:name":"Yar\u0131mtepe",
    "gn:population":0,
    "gn:timezone":"Europe/Istanbul",
    "iso:country":"TR",
    "name:und_x_variant":[
        "Yar\u0131mtepe",
        "Alt\u0131parmak"
    ],
    "wof:name":"Yarimtepe",
    "wof:placetype":"locality"
},
  "geometry": {"coordinates":[36.17095,38.68528],"type":"Point"}
}