{
  "type": "Feature",
  "properties": {
    "iso:country":"TR",
    "name:eng_x_preferred":[
        "Basak"
    ],
    "name:tur_x_preferred":[
        "Ba\u015fak"
    ],
    "wof:name":"Basak",
    "wof:placetype":"neighbourhood"
},
  "geometry": {"coordinates":[28.44500591932917,41.33079996530549],"type":"Point"}
}