{
  "type": "Feature",
  "properties": {
    "gn:admin1_code":"52",
    "gn:asciiname":"Sirinkoy",
    "gn:country_code":"TR",
    "gn:dem":885,
    "gn:feature_class":"P",
    "gn:feature_code":"PPL",
    "gn:name":"\u015eirink\u00f6y",
    "gn:population":0,
    "gn:timezone":"Europe/Istanbul",
    "iso:country":"TR",
    "name:tur_x_preferred":[
        "\u015eirink\u00f6y"
    ],
    "wof:name":"Sirinkoy",
    "wof:placetype":"locality"
},
  "geometry": {"coordinates":[37.62246,40.85632],"type":"Point"}
}