{
  "type": "Feature",
  "properties": {
    "gn:admin1_code":"21",
    "gn:asciiname":"Ciftlicevre",
    "gn:country_code":"TR",
    "gn:dem":654,
    "gn:feature_class":"P",
    "gn:feature_code":"PPL",
    "gn:name":"\u00c7iftli\u00e7evre",
    "gn:population":0,
    "gn:timezone":"Europe/Istanbul",
    "iso:country":"TR",
    "name:und_x_variant":[
        "\u00c7iftli\u00e7evre",
        "Alya"
    ],
    "wof:name":"Ciftlicevre",
    "wof:placetype":"locality"
},
  "geometry": {"coordinates":[41.17582,38.23607],"type":"Point"}
}