{
  "type": "Feature",
  "properties": {
    "gn:admin1_code":"81",
    "gn:asciiname":"Catalhuyuk",
    "gn:country_code":"TR",
    "gn:dem":33,
    "gn:feature_class":"P",
    "gn:feature_code":"PPL",
    "gn:name":"\u00c7atalh\u00fcy\u00fck",
    "gn:population":0,
    "gn:timezone":"Europe/Istanbul",
    "iso:country":"TR",
    "name:und_x_variant":[
        "\u00c7atalh\u00f6y\u00fc\u011f\u00fc",
        "\u00c7atalh\u00fcy\u00fck"
    ],
    "wof:name":"Catalhuyuk",
    "wof:placetype":"locality"
},
  "geometry": {"coordinates":[35.81685,37.19718],"type":"Point"}
}