{
  "type": "Feature",
  "properties": {
    "gn:admin1_code":"81",
    "gn:asciiname":"Soysalli",
    "gn:cc2":"TR",
    "gn:country_code":"TR",
    "gn:dem":77,
    "gn:feature_class":"P",
    "gn:feature_code":"PPL",
    "gn:name":"Soysall\u0131",
    "gn:population":0,
    "gn:timezone":"Europe/Istanbul",
    "iso:country":"TR",
    "name:und_x_variant":[
        "Soysal\u0131",
        "Soysall\u0131"
    ],
    "wof:name":"Soysalli",
    "wof:placetype":"locality"
},
  "geometry": {"coordinates":[35.66917,37.14306],"type":"Point"}
}