{
  "type": "Feature",
  "properties": {
    "gn:admin1_code":"16.0",
    "gn:asciiname":"Cardak",
    "gn:country_code":"TR",
    "gn:dem":240,
    "gn:feature_class":"P",
    "gn:feature_code":"PPL",
    "gn:name":"\u00c7ardak",
    "gn:population":0,
    "gn:timezone":"Europe/Istanbul",
    "iso:country":"TR",
    "name:tur_x_preferred":[
        "\u00c7ardak"
    ],
    "wof:name":"Cardak",
    "wof:placetype":"locality"
},
  "geometry": {"coordinates":[29.52811,40.25477],"type":"Point"}
}