{
  "type": "Feature",
  "properties": {
    "gn:admin1_code":"4.0",
    "gn:asciiname":"Esnemez",
    "gn:country_code":"TR",
    "gn:dem":1959,
    "gn:feature_class":"P",
    "gn:feature_code":"PPL",
    "gn:name":"Esnemez",
    "gn:population":0,
    "gn:timezone":"Europe/Istanbul",
    "iso:country":"TR",
    "name:tur_x_preferred":[
        "Esnemez"
    ],
    "wof:name":"Esnemez",
    "wof:placetype":"locality"
},
  "geometry": {"coordinates":[43.90723,39.4648],"type":"Point"}
}