{
  "type": "Feature",
  "properties": {
    "gn:admin1_code":"04",
    "gn:asciiname":"Bozyayla",
    "gn:cc2":"TR",
    "gn:country_code":"TR",
    "gn:dem":2085,
    "gn:feature_class":"P",
    "gn:feature_code":"PPL",
    "gn:name":"Bozyayla",
    "gn:population":0,
    "gn:timezone":"Europe/Istanbul",
    "iso:country":"TR",
    "name:und_x_variant":[
        "Kariler",
        "Bozyayla"
    ],
    "wof:name":"Bozyayla",
    "wof:placetype":"locality"
},
  "geometry": {"coordinates":[44.01667,39.71667],"type":"Point"}
}