{
  "type": "Feature",
  "properties": {
    "gn:admin1_code":"31.0",
    "gn:asciiname":"Kizgonce",
    "gn:country_code":"TR",
    "gn:dem":715,
    "gn:feature_class":"P",
    "gn:feature_code":"PPL",
    "gn:name":"K\u0131zgonce",
    "gn:population":0,
    "gn:timezone":"Europe/Istanbul",
    "iso:country":"TR",
    "name:tur_x_preferred":[
        "K\u0131zgonce"
    ],
    "wof:name":"Kizgonce",
    "wof:placetype":"locality"
},
  "geometry": {"coordinates":[36.29806,36.73417],"type":"Point"}
}