{
  "type": "Feature",
  "properties": {
    "gn:admin1_code":"63",
    "gn:asciiname":"Kochisar",
    "gn:country_code":"TR",
    "gn:dem":525,
    "gn:feature_class":"P",
    "gn:feature_code":"PPL",
    "gn:name":"Ko\u00e7hisar",
    "gn:population":0,
    "gn:timezone":"Europe/Istanbul",
    "iso:country":"TR",
    "name:tur_x_preferred":[
        "Ko\u00e7hisar"
    ],
    "wof:name":"Kochisar",
    "wof:placetype":"locality"
},
  "geometry": {"coordinates":[38.19556,37.36639],"type":"Point"}
}