{
  "type": "Feature",
  "properties": {
    "gn:admin1_code":"04",
    "gn:asciiname":"Cakirbey",
    "gn:country_code":"TR",
    "gn:dem":1767,
    "gn:feature_class":"P",
    "gn:feature_code":"PPL",
    "gn:name":"\u00c7ak\u0131rbey",
    "gn:population":0,
    "gn:timezone":"Europe/Istanbul",
    "iso:country":"TR",
    "name:tur_x_preferred":[
        "\u00c7ak\u0131rbey"
    ],
    "wof:name":"Cakirbey",
    "wof:placetype":"locality"
},
  "geometry": {"coordinates":[42.94658,39.27639],"type":"Point"}
}