{
  "type": "Feature",
  "properties": {
    "gn:admin1_code":"81",
    "gn:asciiname":"Orendere",
    "gn:country_code":"TR",
    "gn:dem":567,
    "gn:feature_class":"P",
    "gn:feature_code":"PPL",
    "gn:name":"\u00d6rendere",
    "gn:population":0,
    "gn:timezone":"Europe/Istanbul",
    "iso:country":"TR",
    "name:und_x_variant":[
        "\u00d6rendere",
        "Dere"
    ],
    "wof:name":"Orendere",
    "wof:placetype":"locality"
},
  "geometry": {"coordinates":[35.77434,37.55342],"type":"Point"}
}