{
  "type": "Feature",
  "properties": {
    "gn:admin1_code":"58",
    "gn:asciiname":"Alisanagili",
    "gn:country_code":"TR",
    "gn:dem":1832,
    "gn:feature_class":"P",
    "gn:feature_code":"PPL",
    "gn:name":"Ali\u015fana\u011f\u0131l\u0131",
    "gn:population":0,
    "gn:timezone":"Europe/Istanbul",
    "iso:country":"TR",
    "name:tur_x_preferred":[
        "Ali\u015fana\u011f\u0131l\u0131"
    ],
    "wof:name":"Alisanagili",
    "wof:placetype":"locality"
},
  "geometry": {"coordinates":[37.82584,39.75262],"type":"Point"}
}