{
  "type": "Feature",
  "properties": {
    "gn:admin1_code":"8.0",
    "gn:asciiname":"Incirli",
    "gn:country_code":"TR",
    "gn:dem":310,
    "gn:feature_class":"P",
    "gn:feature_code":"PPL",
    "gn:name":"\u0130ncirli",
    "gn:population":0,
    "gn:timezone":"Europe/Istanbul",
    "iso:country":"TR",
    "name:tur_x_preferred":[
        "\u0130ncirli"
    ],
    "wof:name":"Incirli",
    "wof:placetype":"locality"
},
  "geometry": {"coordinates":[41.71271,41.31878],"type":"Point"}
}