{
  "type": "Feature",
  "properties": {
    "gn:admin1_code":"07",
    "gn:asciiname":"Degirmenlik",
    "gn:country_code":"TR",
    "gn:dem":1217,
    "gn:feature_class":"P",
    "gn:feature_code":"PPL",
    "gn:name":"De\u011firmenlik",
    "gn:population":0,
    "gn:timezone":"Europe/Istanbul",
    "iso:country":"TR",
    "name:und_x_variant":[
        "De\u011firmenlikk\u00f6y\u00fc",
        "De\u011firmenlik"
    ],
    "wof:name":"Degirmenlik",
    "wof:placetype":"locality"
},
  "geometry": {"coordinates":[31.77889,37.27641],"type":"Point"}
}