{
  "type": "Feature",
  "properties": {
    "gn:admin1_code":"11.0",
    "gn:asciiname":"Ericek",
    "gn:country_code":"TR",
    "gn:dem":402,
    "gn:feature_class":"P",
    "gn:feature_code":"PPL",
    "gn:name":"Ericek",
    "gn:population":0,
    "gn:timezone":"Europe/Istanbul",
    "iso:country":"TR",
    "name:tur_x_preferred":[
        "Ericek"
    ],
    "wof:name":"Ericek",
    "wof:placetype":"locality"
},
  "geometry": {"coordinates":[29.99048,40.42942],"type":"Point"}
}