{
  "type": "Feature",
  "properties": {
    "gn:admin1_code":"76",
    "gn:asciiname":"Malagir",
    "gn:country_code":"TR",
    "gn:dem":590,
    "gn:feature_class":"P",
    "gn:feature_code":"PPL",
    "gn:name":"Malagir",
    "gn:population":0,
    "gn:timezone":"Europe/Istanbul",
    "iso:country":"TR",
    "wof:name":"Malagir",
    "wof:placetype":"locality"
},
  "geometry": {"coordinates":[41.21667,38.08333],"type":"Point"}
}