{
  "type": "Feature",
  "properties": {
    "gn:admin1_code":"33",
    "gn:asciiname":"Alisarnicli",
    "gn:country_code":"TR",
    "gn:dem":1203,
    "gn:feature_class":"P",
    "gn:feature_code":"PPL",
    "gn:name":"Alisarn\u0131\u00e7l\u0131",
    "gn:population":0,
    "gn:timezone":"Europe/Istanbul",
    "iso:country":"TR",
    "wof:name":"Alisarnicli",
    "wof:placetype":"locality"
},
  "geometry": {"coordinates":[30.92533,37.70484],"type":"Point"}
}