{
  "type": "Feature",
  "properties": {
    "gn:admin1_code":"25.0",
    "gn:asciiname":"Akdag",
    "gn:country_code":"TR",
    "gn:dem":1861,
    "gn:feature_class":"P",
    "gn:feature_code":"PPL",
    "gn:name":"Akda\u011f",
    "gn:population":0,
    "gn:timezone":"Europe/Istanbul",
    "iso:country":"TR",
    "name:und_x_variant":[
        "A\u011fda\u011f",
        "A\u011fda\u015f",
        "Akda\u011f"
    ],
    "wof:name":"Akdag",
    "wof:placetype":"locality"
},
  "geometry": {"coordinates":[41.34866,40.10282],"type":"Point"}
}