{
  "type": "Feature",
  "properties": {
    "gn:admin1_code":"54",
    "gn:asciiname":"Yuvalidere",
    "gn:country_code":"TR",
    "gn:dem":46,
    "gn:feature_class":"P",
    "gn:feature_code":"PPL",
    "gn:name":"Yuval\u0131dere",
    "gn:population":0,
    "gn:timezone":"Europe/Istanbul",
    "iso:country":"TR",
    "name:tur_x_preferred":[
        "Yuval\u0131dere"
    ],
    "wof:name":"Yuvalidere",
    "wof:placetype":"locality"
},
  "geometry": {"coordinates":[30.62669,41.0033],"type":"Point"}
}