{
  "type": "Feature",
  "properties": {
    "gn:admin1_code":"21.0",
    "gn:asciiname":"Sahanedirik",
    "gn:cc2":"TR",
    "gn:country_code":"TR",
    "gn:dem":540,
    "gn:feature_class":"P",
    "gn:feature_code":"PPL",
    "gn:name":"\u015eahanedirik",
    "gn:population":0,
    "gn:timezone":"Europe/Istanbul",
    "iso:country":"TR",
    "name:tur_x_preferred":[
        "\u015eahanedirik"
    ],
    "name:und_x_variant":[
        "Shakhanedirik"
    ],
    "wof:name":"Sahanedirik",
    "wof:placetype":"locality"
},
  "geometry": {"coordinates":[41.085,37.92139],"type":"Point"}
}