{
  "type": "Feature",
  "properties": {
    "gn:admin1_code":"76.0",
    "gn:asciiname":"Parmakkapi",
    "gn:country_code":"TR",
    "gn:dem":682,
    "gn:feature_class":"P",
    "gn:feature_code":"PPL",
    "gn:name":"Parmakkap\u0131",
    "gn:population":0,
    "gn:timezone":"Europe/Istanbul",
    "iso:country":"TR",
    "name:tur_x_preferred":[
        "Parmakkap\u0131"
    ],
    "wof:name":"Parmakkapi",
    "wof:placetype":"locality"
},
  "geometry": {"coordinates":[41.26075,38.12212],"type":"Point"}
}