{
  "type": "Feature",
  "properties": {
    "gn:admin1_code":"54.0",
    "gn:asciiname":"Kizilcikorman",
    "gn:country_code":"TR",
    "gn:dem":29,
    "gn:feature_class":"P",
    "gn:feature_code":"PPL",
    "gn:name":"K\u0131z\u0131lc\u0131korman",
    "gn:population":0,
    "gn:timezone":"Europe/Istanbul",
    "iso:country":"TR",
    "name:tur_x_preferred":[
        "K\u0131z\u0131lc\u0131korman"
    ],
    "wof:name":"Kizilcikorman",
    "wof:placetype":"locality"
},
  "geometry": {"coordinates":[30.5856,40.75863],"type":"Point"}
}