{
  "type": "Feature",
  "properties": {
    "gn:admin1_code":"91",
    "gn:asciiname":"Kullu",
    "gn:country_code":"TR",
    "gn:dem":1111,
    "gn:feature_class":"P",
    "gn:feature_code":"PPL",
    "gn:name":"K\u00fcll\u00fc",
    "gn:population":0,
    "gn:timezone":"Europe/Istanbul",
    "iso:country":"TR",
    "name:tur_x_preferred":[
        "K\u00fcll\u00fc"
    ],
    "wof:name":"Kullu",
    "wof:placetype":"locality"
},
  "geometry": {"coordinates":[36.39953,36.9363],"type":"Point"}
}