{
  "type": "Feature",
  "properties": {
    "gn:admin1_code":"75",
    "gn:asciiname":"Yalman",
    "gn:country_code":"TR",
    "gn:dem":1304,
    "gn:feature_class":"P",
    "gn:feature_code":"PPL",
    "gn:name":"Yalman",
    "gn:population":0,
    "gn:timezone":"Europe/Istanbul",
    "iso:country":"TR",
    "name:msa_x_preferred":[
        "Yalman"
    ],
    "name:urd_x_preferred":[
        "\u06cc\u0644\u0645\u0627\u0646"
    ],
    "name:vie_x_preferred":[
        "Yalman"
    ],
    "wof:name":"Yalman",
    "wof:placetype":"locality"
},
  "geometry": {"coordinates":[34.39694,38.53328],"type":"Point"}
}