{
  "type": "Feature",
  "properties": {
    "gn:admin1_code":"28.0",
    "gn:asciiname":"Alisar",
    "gn:country_code":"TR",
    "gn:dem":1516,
    "gn:feature_class":"P",
    "gn:feature_code":"PPL",
    "gn:name":"Ali\u015far",
    "gn:population":0,
    "gn:timezone":"Europe/Istanbul",
    "iso:country":"TR",
    "name:tur_x_preferred":[
        "Ali\u015far"
    ],
    "wof:name":"Alisar",
    "wof:placetype":"locality"
},
  "geometry": {"coordinates":[38.58672,40.30185],"type":"Point"}
}