{
  "type": "Feature",
  "properties": {
    "gn:admin1_code":"35",
    "gn:asciiname":"Suleymanli",
    "gn:country_code":"TR",
    "gn:dem":36,
    "gn:feature_class":"P",
    "gn:feature_code":"PPL",
    "gn:name":"S\u00fcleymanl\u0131",
    "gn:population":0,
    "gn:timezone":"Europe/Istanbul",
    "iso:country":"TR",
    "name:und_x_variant":[
        "S\u00fcleymanlar",
        "S\u00fcleymanl\u0131"
    ],
    "wof:name":"Suleymanli",
    "wof:placetype":"locality"
},
  "geometry": {"coordinates":[27.17855,38.63775],"type":"Point"}
}