{
  "type": "Feature",
  "properties": {
    "gn:admin1_code":"62",
    "gn:asciiname":"Dallibahce",
    "gn:country_code":"TR",
    "gn:dem":1313,
    "gn:feature_class":"P",
    "gn:feature_code":"PPLA3",
    "gn:name":"Dall\u0131bah\u00e7e",
    "gn:population":0,
    "gn:timezone":"Europe/Istanbul",
    "iso:country":"TR",
    "name:und_x_variant":[
        "\u0130resi",
        "Dall\u0131bah\u00e7e"
    ],
    "wof:name":"Dallibahce",
    "wof:placetype":"locality"
},
  "geometry": {"coordinates":[39.87929000000001,39.13321],"type":"Point"}
}