{
  "type": "Feature",
  "properties": {
    "gn:admin1_code":"46",
    "gn:asciiname":"Cakirdere",
    "gn:country_code":"TR",
    "gn:dem":765,
    "gn:feature_class":"P",
    "gn:feature_code":"PPL",
    "gn:name":"\u00c7ak\u0131rdere",
    "gn:population":0,
    "gn:timezone":"Europe/Istanbul",
    "iso:country":"TR",
    "name:tur_x_preferred":[
        "\u00c7ak\u0131rdere"
    ],
    "wof:name":"Cakirdere",
    "wof:placetype":"locality"
},
  "geometry": {"coordinates":[36.84818,37.73377],"type":"Point"}
}