{
  "type": "Feature",
  "properties": {
    "gn:admin1_code":"28.0",
    "gn:asciiname":"Mursal",
    "gn:country_code":"TR",
    "gn:dem":456,
    "gn:feature_class":"P",
    "gn:feature_code":"PPL",
    "gn:name":"Mursal",
    "gn:population":0,
    "gn:timezone":"Europe/Istanbul",
    "iso:country":"TR",
    "name:aze_x_preferred":[
        "M\u00fcrs\u0259l"
    ],
    "name:und_x_variant":[
        "M\u00fcrsel",
        "Mursal"
    ],
    "wof:name":"Mursal",
    "wof:placetype":"locality"
},
  "geometry": {"coordinates":[38.92086,40.89983],"type":"Point"}
}