{
  "type": "Feature",
  "properties": {
    "gn:admin1_code":"37",
    "gn:asciiname":"Yukarikuyucak",
    "gn:country_code":"TR",
    "gn:dem":911,
    "gn:feature_class":"P",
    "gn:feature_code":"PPL",
    "gn:name":"Yukar\u0131kuyucak",
    "gn:population":0,
    "gn:timezone":"Europe/Istanbul",
    "iso:country":"TR",
    "name:tur_x_preferred":[
        "Yukar\u0131kuyucak"
    ],
    "wof:name":"Yukarikuyucak",
    "wof:placetype":"locality"
},
  "geometry": {"coordinates":[33.8056,41.3647],"type":"Point"}
}