{
  "type": "Feature",
  "properties": {
    "gn:admin1_code":"41",
    "gn:asciiname":"Ornek",
    "gn:country_code":"TR",
    "gn:dem":429,
    "gn:feature_class":"P",
    "gn:feature_code":"PPL",
    "gn:name":"\u00d6rnek",
    "gn:population":0,
    "gn:timezone":"Europe/Istanbul",
    "iso:country":"TR",
    "name:tur_x_preferred":[
        "\u00d6rnek"
    ],
    "wof:name":"Ornek",
    "wof:placetype":"locality"
},
  "geometry": {"coordinates":[30.01606,40.65499000000001],"type":"Point"}
}