{
  "type": "Feature",
  "properties": {
    "gn:admin1_code":"52.0",
    "gn:asciiname":"Kumanlar",
    "gn:country_code":"TR",
    "gn:dem":464,
    "gn:feature_class":"P",
    "gn:feature_code":"PPL",
    "gn:name":"Kumanlar",
    "gn:population":0,
    "gn:timezone":"Europe/Istanbul",
    "iso:country":"TR",
    "name:tur_x_preferred":[
        "Kumanlar"
    ],
    "wof:name":"Kumanlar",
    "wof:placetype":"locality"
},
  "geometry": {"coordinates":[37.76168,40.81467],"type":"Point"}
}