{
  "type": "Feature",
  "properties": {
    "gn:admin1_code":"89.0",
    "gn:asciiname":"Karaagac",
    "gn:country_code":"TR",
    "gn:dem":1073,
    "gn:feature_class":"P",
    "gn:feature_code":"PPL",
    "gn:name":"Karaa\u011fa\u00e7",
    "gn:population":0,
    "gn:timezone":"Europe/Istanbul",
    "iso:country":"TR",
    "wof:name":"Karaagac",
    "wof:placetype":"locality"
},
  "geometry": {"coordinates":[32.49234000000001,41.06752],"type":"Point"}
}