{
  "type": "Feature",
  "properties": {
    "gn:admin1_code":"49",
    "gn:asciiname":"Boyuncuk",
    "gn:country_code":"TR",
    "gn:dem":1326,
    "gn:feature_class":"P",
    "gn:feature_code":"PPL",
    "gn:name":"Boyuncuk",
    "gn:population":0,
    "gn:timezone":"Europe/Istanbul",
    "iso:country":"TR",
    "name:und_x_variant":[
        "\u015eeyhyusuf",
        "Boyuncuk"
    ],
    "wof:name":"Boyuncuk",
    "wof:placetype":"locality"
},
  "geometry": {"coordinates":[41.58662,38.84711],"type":"Point"}
}