{
  "type": "Feature",
  "properties": {
    "gn:admin1_code":"68.0",
    "gn:asciiname":"Haydarlar",
    "gn:country_code":"TR",
    "gn:dem":1222,
    "gn:feature_class":"P",
    "gn:feature_code":"PPL",
    "gn:name":"Haydarlar",
    "gn:population":0,
    "gn:timezone":"Europe/Istanbul",
    "iso:country":"TR",
    "wof:name":"Haydarlar",
    "wof:placetype":"locality"
},
  "geometry": {"coordinates":[31.93489000000001,40.27751],"type":"Point"}
}