{
  "type": "Feature",
  "properties": {
    "gn:admin1_code":"8.0",
    "gn:asciiname":"Balli",
    "gn:country_code":"TR",
    "gn:dem":1760,
    "gn:feature_class":"P",
    "gn:feature_code":"PPL",
    "gn:name":"Ball\u0131",
    "gn:population":0,
    "gn:timezone":"Europe/Istanbul",
    "iso:country":"TR",
    "name:tur_x_preferred":[
        "Ball\u0131"
    ],
    "wof:name":"Balli",
    "wof:placetype":"locality"
},
  "geometry": {"coordinates":[42.17858,41.01366],"type":"Point"}
}