{
  "type": "Feature",
  "properties": {
    "gn:admin1_code":"89",
    "gn:asciiname":"Taslik",
    "gn:country_code":"TR",
    "gn:dem":1209,
    "gn:feature_class":"P",
    "gn:feature_code":"PPL",
    "gn:name":"Ta\u015fl\u0131k",
    "gn:population":0,
    "gn:timezone":"Europe/Istanbul",
    "iso:country":"TR",
    "wof:name":"Taslik",
    "wof:placetype":"locality"
},
  "geometry": {"coordinates":[32.52783,40.87958],"type":"Point"}
}