{
  "type": "Feature",
  "properties": {
    "gn:admin1_code":"69.0",
    "gn:asciiname":"Salyazi",
    "gn:country_code":"TR",
    "gn:dem":1739,
    "gn:feature_class":"P",
    "gn:feature_code":"PPL",
    "gn:name":"Salyaz\u0131",
    "gn:population":0,
    "gn:timezone":"Europe/Istanbul",
    "iso:country":"TR",
    "name:eng_x_preferred":[
        "Salyaz\u0131"
    ],
    "name:rus_x_preferred":[
        "\u041f\u043e\u0441\u0443\u0441"
    ],
    "name:und_x_variant":[
        "Posus",
        "Salyaz\u0131"
    ],
    "wof:name":"Salyazi",
    "wof:placetype":"locality"
},
  "geometry": {"coordinates":[39.81353,40.25828],"type":"Point"}
}