{
  "type": "Feature",
  "properties": {
    "gn:admin1_code":"58",
    "gn:asciiname":"Timsi",
    "gn:country_code":"TR",
    "gn:dem":1462,
    "gn:feature_class":"P",
    "gn:feature_code":"PPL",
    "gn:name":"Timsi",
    "gn:population":0,
    "gn:timezone":"Europe/Istanbul",
    "iso:country":"TR",
    "name:und_x_variant":[
        "Timisi",
        "Timsi",
        "Bay\u0131r\u00fcst\u00fc"
    ],
    "wof:name":"Timsi",
    "wof:placetype":"locality"
},
  "geometry": {"coordinates":[38.15401,39.25398],"type":"Point"}
}