{
  "type": "Feature",
  "properties": {
    "gn:admin1_code":"65",
    "gn:asciiname":"Sabunsatan",
    "gn:country_code":"TR",
    "gn:dem":2271,
    "gn:feature_class":"P",
    "gn:feature_code":"PPL",
    "gn:name":"Sabunsatan",
    "gn:population":0,
    "gn:timezone":"Europe/Istanbul",
    "iso:country":"TR",
    "wof:name":"Sabunsatan",
    "wof:placetype":"locality"
},
  "geometry": {"coordinates":[43.71965,39.15142],"type":"Point"}
}