{
  "type": "Feature",
  "properties": {
    "gn:admin1_code":"66.0",
    "gn:asciiname":"Zaimgecidi",
    "gn:country_code":"TR",
    "gn:dem":1006,
    "gn:feature_class":"P",
    "gn:feature_code":"PPL",
    "gn:name":"Zaimge\u00e7idi",
    "gn:population":0,
    "gn:timezone":"Europe/Istanbul",
    "iso:country":"TR",
    "wof:name":"Zaimgecidi",
    "wof:placetype":"locality"
},
  "geometry": {"coordinates":[35.81306,39.81917],"type":"Point"}
}