{
  "type": "Feature",
  "properties": {
    "gn:admin1_code":"04",
    "gn:asciiname":"Yukari Kosk",
    "gn:country_code":"TR",
    "gn:dem":1780,
    "gn:feature_class":"P",
    "gn:feature_code":"PPL",
    "gn:name":"Yukar\u0131 K\u00f6\u015fk",
    "gn:population":0,
    "gn:timezone":"Europe/Istanbul",
    "iso:country":"TR",
    "name:tur_x_preferred":[
        "Yukar\u0131 K\u00f6\u015fk"
    ],
    "name:und_x_variant":[
        "Yukar\u0131k\u00f6\u015fk",
        "K\u00f6\u015fkk\u00f6y",
        "K\u00f6\u015fk"
    ],
    "wof:name":"Yukari Kosk",
    "wof:placetype":"locality"
},
  "geometry": {"coordinates":[42.84845,39.56456],"type":"Point"}
}