{
  "type": "Feature",
  "properties": {
    "gn:admin1_code":"21",
    "gn:asciiname":"Bagacik",
    "gn:country_code":"TR",
    "gn:dem":816,
    "gn:feature_class":"P",
    "gn:feature_code":"PPL",
    "gn:name":"Ba\u011fac\u0131k",
    "gn:population":0,
    "gn:timezone":"Europe/Istanbul",
    "iso:country":"TR",
    "name:tur_x_preferred":[
        "Ba\u011fac\u0131k"
    ],
    "name:und_x_variant":[
        "Ba\u011fc\u0131k"
    ],
    "wof:name":"Bagacik",
    "wof:placetype":"locality"
},
  "geometry": {"coordinates":[40.4244,37.64645],"type":"Point"}
}