{
  "type": "Feature",
  "properties": {
    "gn:admin1_code":"62.0",
    "gn:asciiname":"Adakoy",
    "gn:country_code":"TR",
    "gn:dem":1278,
    "gn:feature_class":"P",
    "gn:feature_code":"PPL",
    "gn:name":"Adak\u00f6y",
    "gn:population":0,
    "gn:timezone":"Europe/Istanbul",
    "iso:country":"TR",
    "name:tur_x_preferred":[
        "Adak\u00f6y"
    ],
    "name:und_x_variant":[
        "Ada"
    ],
    "wof:name":"Adakoy",
    "wof:placetype":"locality"
},
  "geometry": {"coordinates":[39.11225,39.34244],"type":"Point"}
}