{
  "type": "Feature",
  "properties": {
    "gn:admin1_code":"58.0",
    "gn:asciiname":"Aktas",
    "gn:country_code":"TR",
    "gn:dem":1669,
    "gn:feature_class":"P",
    "gn:feature_code":"PPL",
    "gn:name":"Akta\u015f",
    "gn:population":0,
    "gn:timezone":"Europe/Istanbul",
    "iso:country":"TR",
    "wof:name":"Aktas",
    "wof:placetype":"locality"
},
  "geometry": {"coordinates":[37.49056,39.58111],"type":"Point"}
}