{
  "type": "Feature",
  "properties": {
    "gn:admin1_code":"35",
    "gn:asciiname":"Yazibasi",
    "gn:cc2":"TR",
    "gn:country_code":"TR",
    "gn:dem":114,
    "gn:feature_class":"P",
    "gn:feature_code":"PPL",
    "gn:name":"Yaz\u0131ba\u015f\u0131",
    "gn:population":0,
    "gn:timezone":"Europe/Istanbul",
    "iso:country":"TR",
    "name:und_x_variant":[
        "Hortuna",
        "Yaz\u0131ba\u015f\u0131"
    ],
    "wof:name":"Yazibasi",
    "wof:placetype":"locality"
},
  "geometry": {"coordinates":[27.32167,38.24083],"type":"Point"}
}