{
  "type": "Feature",
  "properties": {
    "gn:admin1_code":"25",
    "gn:asciiname":"Kirimkaya",
    "gn:country_code":"TR",
    "gn:dem":1603,
    "gn:feature_class":"P",
    "gn:feature_code":"PPL",
    "gn:name":"K\u0131r\u0131mkaya",
    "gn:population":0,
    "gn:timezone":"Europe/Istanbul",
    "iso:country":"TR",
    "name:tur_x_preferred":[
        "K\u0131r\u0131mkaya"
    ],
    "wof:name":"Kirimkaya",
    "wof:placetype":"locality"
},
  "geometry": {"coordinates":[42.16102,39.3653],"type":"Point"}
}