{
  "type": "Feature",
  "properties": {
    "gn:admin1_code":"37.0",
    "gn:asciiname":"Yunus",
    "gn:country_code":"TR",
    "gn:dem":1206,
    "gn:feature_class":"P",
    "gn:feature_code":"PPL",
    "gn:name":"Yunus",
    "gn:population":0,
    "gn:timezone":"Europe/Istanbul",
    "iso:country":"TR",
    "name:cat_x_preferred":[
        "Yunus"
    ],
    "name:deu_x_preferred":[
        "Yunus"
    ],
    "name:fra_x_preferred":[
        "Yunus"
    ],
    "name:jpn_x_preferred":[
        "\u30e6\u30fc\u30cc\u30b9"
    ],
    "name:nld_x_preferred":[
        "Yunus"
    ],
    "wof:name":"Yunus",
    "wof:placetype":"locality"
},
  "geometry": {"coordinates":[34.19843,41.33176],"type":"Point"}
}