{
  "type": "Feature",
  "properties": {
    "gn:admin1_code":"72",
    "gn:asciiname":"Bekciler",
    "gn:cc2":"TR",
    "gn:country_code":"TR",
    "gn:dem":567,
    "gn:feature_class":"P",
    "gn:feature_code":"PPL",
    "gn:name":"Bek\u00e7iler",
    "gn:population":0,
    "gn:timezone":"Europe/Istanbul",
    "iso:country":"TR",
    "name:tur_x_preferred":[
        "Bek\u00e7iler"
    ],
    "name:und_x_variant":[
        "Razvaliny Birizaraf",
        "Birizaraf"
    ],
    "wof:name":"Bekciler",
    "wof:placetype":"locality"
},
  "geometry": {"coordinates":[40.87528,37.18],"type":"Point"}
}