{
  "type": "Feature",
  "properties": {
    "gn:admin1_code":"81",
    "gn:asciiname":"Yellibel",
    "gn:country_code":"TR",
    "gn:dem":231,
    "gn:feature_class":"P",
    "gn:feature_code":"PPL",
    "gn:name":"Yellibel",
    "gn:population":0,
    "gn:timezone":"Europe/Istanbul",
    "iso:country":"TR",
    "wof:name":"Yellibel",
    "wof:placetype":"locality"
},
  "geometry": {"coordinates":[35.73333,36.86667],"type":"Point"}
}