{
  "type": "Feature",
  "properties": {
    "gn:admin1_code":"68",
    "gn:asciiname":"Fevziye",
    "gn:country_code":"TR",
    "gn:dem":1200,
    "gn:feature_class":"P",
    "gn:feature_code":"PPL",
    "gn:name":"Fevziye",
    "gn:population":0,
    "gn:timezone":"Europe/Istanbul",
    "iso:country":"TR",
    "wof:name":"Fevziye",
    "wof:placetype":"locality"
},
  "geometry": {"coordinates":[32.59918,39.74811],"type":"Point"}
}