{
  "type": "Feature",
  "properties": {
    "gn:admin1_code":"10",
    "gn:asciiname":"Kestanelik",
    "gn:country_code":"TR",
    "gn:dem":8,
    "gn:feature_class":"P",
    "gn:feature_code":"PPL",
    "gn:name":"Kestanelik",
    "gn:population":0,
    "gn:timezone":"Europe/Istanbul",
    "iso:country":"TR",
    "name:tur_x_preferred":[
        "Kestanelik"
    ],
    "wof:name":"Kestanelik",
    "wof:placetype":"locality"
},
  "geometry": {"coordinates":[27.98918,40.48688],"type":"Point"}
}