{
  "type": "Feature",
  "properties": {
    "gn:admin1_code":"35",
    "gn:asciiname":"Mursalli",
    "gn:country_code":"TR",
    "gn:dem":220,
    "gn:feature_class":"P",
    "gn:feature_code":"PPL",
    "gn:name":"Mursall\u0131",
    "gn:population":0,
    "gn:timezone":"Europe/Istanbul",
    "iso:country":"TR",
    "name:tur_x_preferred":[
        "Mursall\u0131"
    ],
    "wof:name":"Mursalli",
    "wof:placetype":"locality"
},
  "geometry": {"coordinates":[27.98375,38.26947],"type":"Point"}
}