{
  "type": "Feature",
  "properties": {
    "gn:admin1_code":"12",
    "gn:asciiname":"Eldirek",
    "gn:country_code":"TR",
    "gn:dem":1418,
    "gn:feature_class":"P",
    "gn:feature_code":"PPL",
    "gn:name":"Eldirek",
    "gn:population":0,
    "gn:timezone":"Europe/Istanbul",
    "iso:country":"TR",
    "wof:name":"Eldirek",
    "wof:placetype":"locality"
},
  "geometry": {"coordinates":[40.61667,38.63333],"type":"Point"}
}