{
  "type": "Feature",
  "properties": {
    "gn:admin1_code":"66",
    "gn:asciiname":"Yunalani",
    "gn:country_code":"TR",
    "gn:dem":1149,
    "gn:feature_class":"P",
    "gn:feature_code":"PPL",
    "gn:name":"Y\u00fcnalan\u0131",
    "gn:population":0,
    "gn:timezone":"Europe/Istanbul",
    "iso:country":"TR",
    "wof:name":"Yunalani",
    "wof:placetype":"locality"
},
  "geometry": {"coordinates":[35.68861,39.83216],"type":"Point"}
}