{
  "type": "Feature",
  "properties": {
    "gn:admin1_code":"60.0",
    "gn:asciiname":"Acipinar",
    "gn:country_code":"TR",
    "gn:dem":1242,
    "gn:feature_class":"P",
    "gn:feature_code":"PPL",
    "gn:name":"Ac\u0131p\u0131nar",
    "gn:population":0,
    "gn:timezone":"Europe/Istanbul",
    "iso:country":"TR",
    "wof:name":"Acipinar",
    "wof:placetype":"locality"
},
  "geometry": {"coordinates":[36.80044,40.46543],"type":"Point"}
}