{
  "type": "Feature",
  "properties": {
    "gn:admin1_code":"25",
    "gn:asciiname":"Duruca",
    "gn:country_code":"TR",
    "gn:dem":1954,
    "gn:feature_class":"P",
    "gn:feature_code":"PPL",
    "gn:name":"Duruca",
    "gn:population":0,
    "gn:timezone":"Europe/Istanbul",
    "iso:country":"TR",
    "name:und_x_variant":[
        "\u0130sakomu"
    ],
    "wof:name":"Duruca",
    "wof:placetype":"locality"
},
  "geometry": {"coordinates":[42.2425,39.64736],"type":"Point"}
}