{
  "type": "Feature",
  "properties": {
    "gn:admin1_code":"23.0",
    "gn:asciiname":"Beydegirmeni",
    "gn:country_code":"TR",
    "gn:dem":1286,
    "gn:feature_class":"P",
    "gn:feature_code":"PPL",
    "gn:name":"Beyde\u011firmeni",
    "gn:population":0,
    "gn:timezone":"Europe/Istanbul",
    "iso:country":"TR",
    "name:tur_x_preferred":[
        "Beyde\u011firmeni"
    ],
    "name:und_x_variant":[
        "Beyde\u011fermeni"
    ],
    "wof:name":"Beydegirmeni",
    "wof:placetype":"locality"
},
  "geometry": {"coordinates":[38.80792,38.69215],"type":"Point"}
}