{
  "type": "Feature",
  "properties": {
    "gn:admin1_code":"75.0",
    "gn:asciiname":"Gumusdugun Yaylasi",
    "gn:country_code":"TR",
    "gn:dem":1078,
    "gn:feature_class":"P",
    "gn:feature_code":"PPL",
    "gn:name":"G\u00fcm\u00fc\u015fd\u00fc\u011f\u00fcn Yaylas\u0131",
    "gn:population":0,
    "gn:timezone":"Europe/Istanbul",
    "iso:country":"TR",
    "wof:name":"Gumusdugun Yaylasi",
    "wof:placetype":"locality"
},
  "geometry": {"coordinates":[33.91592,38.15317],"type":"Point"}
}