{
  "type": "Feature",
  "properties": {
    "gn:admin1_code":"65",
    "gn:asciiname":"Bugulukaynak",
    "gn:country_code":"TR",
    "gn:dem":2035,
    "gn:feature_class":"P",
    "gn:feature_code":"PPL",
    "gn:name":"Bu\u011fulukaynak",
    "gn:population":0,
    "gn:timezone":"Europe/Istanbul",
    "iso:country":"TR",
    "name:und_x_variant":[
        "Dergezin",
        "Bu\u011fulukaynak"
    ],
    "wof:name":"Bugulukaynak",
    "wof:placetype":"locality"
},
  "geometry": {"coordinates":[43.96585,39.01523],"type":"Point"}
}