{
  "type": "Feature",
  "properties": {
    "gn:admin1_code":"10",
    "gn:asciiname":"Comezler",
    "gn:country_code":"TR",
    "gn:dem":441,
    "gn:feature_class":"P",
    "gn:feature_code":"PPL",
    "gn:name":"\u00c7\u00f6mezler",
    "gn:population":0,
    "gn:timezone":"Europe/Istanbul",
    "iso:country":"TR",
    "name:tur_x_preferred":[
        "\u00c7\u00f6mezler"
    ],
    "wof:name":"Comezler",
    "wof:placetype":"locality"
},
  "geometry": {"coordinates":[28.23245,39.62102],"type":"Point"}
}