{
  "type": "Feature",
  "properties": {
    "gn:admin1_code":"53.0",
    "gn:asciiname":"Yucehisar",
    "gn:country_code":"TR",
    "gn:dem":253,
    "gn:feature_class":"P",
    "gn:feature_code":"PPL",
    "gn:name":"Y\u00fccehisar",
    "gn:population":0,
    "gn:timezone":"Europe/Istanbul",
    "iso:country":"TR",
    "name:und_x_variant":[
        "Lamgo",
        "Y\u00fccehisar"
    ],
    "wof:name":"Yucehisar",
    "wof:placetype":"locality"
},
  "geometry": {"coordinates":[40.91309,41.11788],"type":"Point"}
}