{
  "type": "Feature",
  "properties": {
    "gn:admin1_code":"63.0",
    "gn:asciiname":"Gayda",
    "gn:country_code":"TR",
    "gn:dem":359,
    "gn:feature_class":"P",
    "gn:feature_code":"PPL",
    "gn:name":"Gayda",
    "gn:population":0,
    "gn:timezone":"Europe/Istanbul",
    "iso:country":"TR",
    "name:tur_x_preferred":[
        "\u00d6nc\u00fcler"
    ],
    "name:tur_x_variant":[
        "Gayda"
    ],
    "wof:name":"Gayda",
    "wof:placetype":"locality"
},
  "geometry": {"coordinates":[38.99256,36.84114],"type":"Point"}
}