{
  "type": "Feature",
  "properties": {
    "gn:admin1_code":"58.0",
    "gn:asciiname":"Alisir",
    "gn:country_code":"TR",
    "gn:dem":1630,
    "gn:feature_class":"P",
    "gn:feature_code":"PPL",
    "gn:name":"Ali\u015fir",
    "gn:population":0,
    "gn:timezone":"Europe/Istanbul",
    "iso:country":"TR",
    "name:tur_x_preferred":[
        "Ali\u015fir"
    ],
    "wof:name":"Alisir",
    "wof:placetype":"locality"
},
  "geometry": {"coordinates":[37.79084,40.11813],"type":"Point"}
}