{
  "type": "Feature",
  "properties": {
    "gn:admin1_code":"38.0",
    "gn:asciiname":"Otebatan",
    "gn:country_code":"TR",
    "gn:dem":1202,
    "gn:feature_class":"P",
    "gn:feature_code":"PPL",
    "gn:name":"\u00d6tebatan",
    "gn:population":0,
    "gn:timezone":"Europe/Istanbul",
    "iso:country":"TR",
    "wof:name":"Otebatan",
    "wof:placetype":"locality"
},
  "geometry": {"coordinates":[35.2513,38.61426],"type":"Point"}
}