{
  "type": "Feature",
  "properties": {
    "gn:admin1_code":"21",
    "gn:asciiname":"Yenievler",
    "gn:country_code":"TR",
    "gn:dem":629,
    "gn:feature_class":"P",
    "gn:feature_code":"PPL",
    "gn:name":"Yenievler",
    "gn:population":0,
    "gn:timezone":"Europe/Istanbul",
    "iso:country":"TR",
    "name:tur_x_preferred":[
        "Yenievler"
    ],
    "name:und_x_variant":[
        "Sememi",
        "\u015eemami",
        "\u015eemani"
    ],
    "wof:name":"Yenievler",
    "wof:placetype":"locality"
},
  "geometry": {"coordinates":[40.48936,37.91447],"type":"Point"}
}