{
  "type": "Feature",
  "properties": {
    "gn:admin1_code":"17.0",
    "gn:asciiname":"Burhanli",
    "gn:country_code":"TR",
    "gn:dem":10,
    "gn:feature_class":"P",
    "gn:feature_code":"PPL",
    "gn:name":"Burhanl\u0131",
    "gn:population":0,
    "gn:timezone":"Europe/Istanbul",
    "iso:country":"TR",
    "wof:name":"Burhanli",
    "wof:placetype":"locality"
},
  "geometry": {"coordinates":[26.56086,40.30742],"type":"Point"}
}