{
  "type": "Feature",
  "properties": {
    "gn:admin1_code":"66",
    "gn:asciiname":"Beyvelioglu",
    "gn:country_code":"TR",
    "gn:dem":1056,
    "gn:feature_class":"P",
    "gn:feature_code":"PPL",
    "gn:name":"Beyvelio\u011flu",
    "gn:population":0,
    "gn:timezone":"Europe/Istanbul",
    "iso:country":"TR",
    "name:und_x_variant":[
        "Beyveli",
        "Beyvelio\u011flu"
    ],
    "wof:name":"Beyvelioglu",
    "wof:placetype":"locality"
},
  "geometry": {"coordinates":[34.66492,39.76196],"type":"Point"}
}