{
  "type": "Feature",
  "properties": {
    "iso:country":"TR",
    "name:eng_x_preferred":[
        "Esensehir"
    ],
    "name:tur_x_preferred":[
        "Esen\u015fehir"
    ],
    "wof:name":"Esensehir",
    "wof:placetype":"neighbourhood"
},
  "geometry": {"coordinates":[29.16600232920573,41.0079550627356],"type":"Point"}
}