{
  "type": "Feature",
  "properties": {
    "gn:admin1_code":"71.0",
    "gn:asciiname":"Kuzukuyusu",
    "gn:country_code":"TR",
    "gn:dem":1020,
    "gn:feature_class":"P",
    "gn:feature_code":"PPL",
    "gn:name":"Kuzukuyusu",
    "gn:population":0,
    "gn:timezone":"Europe/Istanbul",
    "iso:country":"TR",
    "wof:name":"Kuzukuyusu",
    "wof:placetype":"locality"
},
  "geometry": {"coordinates":[33.963,37.70135],"type":"Point"}
}