{
  "type": "Feature",
  "properties": {
    "gn:admin1_code":"61.0",
    "gn:asciiname":"Osmanbaba",
    "gn:country_code":"TR",
    "gn:dem":323,
    "gn:feature_class":"P",
    "gn:feature_code":"PPL",
    "gn:name":"Osmanbaba",
    "gn:population":0,
    "gn:timezone":"Europe/Istanbul",
    "iso:country":"TR",
    "wof:name":"Osmanbaba",
    "wof:placetype":"locality"
},
  "geometry": {"coordinates":[39.6026,40.98421],"type":"Point"}
}