{
  "type": "Feature",
  "properties": {
    "gn:admin1_code":"17",
    "gn:asciiname":"Nevruz",
    "gn:country_code":"TR",
    "gn:dem":293,
    "gn:feature_class":"P",
    "gn:feature_code":"PPL",
    "gn:name":"Nevruz",
    "gn:population":0,
    "gn:timezone":"Europe/Istanbul",
    "iso:country":"TR",
    "wof:name":"Nevruz",
    "wof:placetype":"locality"
},
  "geometry": {"coordinates":[27.27083,39.95222],"type":"Point"}
}