{
  "type": "Feature",
  "properties": {
    "gn:admin1_code":"19.0",
    "gn:asciiname":"Kaleli",
    "gn:country_code":"TR",
    "gn:dem":1420,
    "gn:feature_class":"P",
    "gn:feature_code":"PPL",
    "gn:name":"Kaleli",
    "gn:population":0,
    "gn:timezone":"Europe/Istanbul",
    "iso:country":"TR",
    "wof:name":"Kaleli",
    "wof:placetype":"locality"
},
  "geometry": {"coordinates":[34.57384,40.80451],"type":"Point"}
}