{
  "type": "Feature",
  "properties": {
    "gn:admin1_code":"45",
    "gn:asciiname":"Sahinkaya",
    "gn:country_code":"TR",
    "gn:dem":523,
    "gn:feature_class":"P",
    "gn:feature_code":"PPL",
    "gn:name":"\u015eahinkaya",
    "gn:population":0,
    "gn:timezone":"Europe/Istanbul",
    "iso:country":"TR",
    "name:tur_x_preferred":[
        "\u015eahinkaya"
    ],
    "name:tur_x_variant":[
        "Kirank\u0131\u015fla"
    ],
    "wof:name":"Sahinkaya",
    "wof:placetype":"locality"
},
  "geometry": {"coordinates":[28.09022,38.85823],"type":"Point"}
}