{
  "type": "Feature",
  "properties": {
    "gn:admin1_code":"03",
    "gn:asciiname":"Alpaslan",
    "gn:country_code":"TR",
    "gn:dem":1125,
    "gn:feature_class":"P",
    "gn:feature_code":"PPL",
    "gn:name":"Alpaslan",
    "gn:population":0,
    "gn:timezone":"Europe/Istanbul",
    "iso:country":"TR",
    "name:deu_x_preferred":[
        "Alpaslan"
    ],
    "name:und_x_variant":[
        "Alparslan",
        "Alpaslan"
    ],
    "wof:name":"Alpaslan",
    "wof:placetype":"locality"
},
  "geometry": {"coordinates":[30.40611,38.2075],"type":"Point"}
}