{
  "type": "Feature",
  "properties": {
    "gn:admin1_code":"82.0",
    "gn:asciiname":"Asiklar",
    "gn:country_code":"TR",
    "gn:dem":704,
    "gn:feature_class":"P",
    "gn:feature_code":"PPL",
    "gn:name":"A\u015f\u0131klar",
    "gn:population":0,
    "gn:timezone":"Europe/Istanbul",
    "iso:country":"TR",
    "wof:name":"Asiklar",
    "wof:placetype":"locality"
},
  "geometry": {"coordinates":[34.07093,40.59988],"type":"Point"}
}