{
  "type": "Feature",
  "properties": {
    "gn:admin1_code":"58",
    "gn:asciiname":"Karapinar",
    "gn:country_code":"TR",
    "gn:dem":1790,
    "gn:feature_class":"P",
    "gn:feature_code":"PPL",
    "gn:name":"Karap\u0131nar",
    "gn:population":0,
    "gn:timezone":"Europe/Istanbul",
    "iso:country":"TR",
    "name:und_x_variant":[
        "Karap\u0131nar Mezraas\u0131",
        "Karap\u0131nar"
    ],
    "wof:name":"Karapinar",
    "wof:placetype":"locality"
},
  "geometry": {"coordinates":[37.00226,38.68635],"type":"Point"}
}