{
  "type": "Feature",
  "properties": {
    "gn:country":"TR",
    "gn:fcode":"PPLA2",
    "gn:population":0,
    "iso:country":"TR",
    "name:ara_x_preferred":[
        "\u0623\u063a\u0644\u064a"
    ],
    "name:ast_x_preferred":[
        "A\u011fl\u0131"
    ],
    "name:ceb_x_preferred":[
        "A\u011fl\u0131 \u0130l\u00e7esi"
    ],
    "name:che_x_preferred":[
        "\u0410\u0433\u04c0\u043b\u0438"
    ],
    "name:deu_x_preferred":[
        "A\u011fl\u0131"
    ],
    "name:eng_x_preferred":[
        "A\u011fl\u0131"
    ],
    "name:fas_x_preferred":[
        "\u0622\u063a\u0644\u06cc"
    ],
    "name:fra_x_preferred":[
        "A\u011fl\u0131"
    ],
    "name:ita_x_preferred":[
        "Distretto di A\u011fl\u0131"
    ],
    "name:mrj_x_preferred":[
        "\u0410\u0433\u043b\u044b"
    ],
    "name:msa_x_preferred":[
        "A\u011fl\u0131"
    ],
    "name:nan_x_preferred":[
        "A\u011fl\u0131"
    ],
    "name:nld_x_preferred":[
        "A\u011fl\u0131"
    ],
    "name:nob_x_preferred":[
        "A\u011fl\u0131"
    ],
    "name:pnb_x_preferred":[
        "\u0636\u0644\u0639 \u0627\u06af\u0644\u06cc"
    ],
    "name:swa_x_preferred":[
        "A\u011fl\u0131"
    ],
    "name:tat_x_preferred":[
        "\u0410\u0433\u043b\u044b"
    ],
    "name:tur_x_preferred":[
        "A\u011fl\u0131"
    ],
    "name:tur_x_variant":[
        "Kuruo\u011flu",
        "A\u011f\u0131lpazar\u0131"
    ],
    "name:und_x_variant":[
        "A\u011fl\u0131k\u00f6y"
    ],
    "name:urd_x_preferred":[
        "\u0622\u063a\u0644\u06cc"
    ],
    "name:vie_x_preferred":[
        "A\u011fl\u0131"
    ],
    "qs:name":"A\u011f\u0131l",
    "qs:photos_9r":0,
    "qs:photos_sr":0,
    "qs:pop_sr":"0",
    "wof:name":"A\u011f\u0131l",
    "wof:placetype":"locality",
    "wof:population":0
},
  "geometry": {"coordinates":[33.55383,41.68602],"type":"Point"}
}