{
  "type": "Feature",
  "properties": {
    "gn:admin1_code":"48",
    "gn:asciiname":"Haliller",
    "gn:country_code":"TR",
    "gn:dem":646,
    "gn:feature_class":"P",
    "gn:feature_code":"PPL",
    "gn:name":"Haliller",
    "gn:population":0,
    "gn:timezone":"Europe/Istanbul",
    "iso:country":"TR",
    "name:tur_x_preferred":[
        "Haliller"
    ],
    "wof:name":"Haliller",
    "wof:placetype":"locality"
},
  "geometry": {"coordinates":[28.3693,37.13802],"type":"Point"}
}