{
  "type": "Feature",
  "properties": {
    "gn:country":"TR",
    "gn:fcode":"PPL",
    "gn:population":50303,
    "iso:country":"TR",
    "name:bel_x_preferred":[
        "\u0413\u043e\u0440\u0430\u0434 \u0422\u0430\u0440\u0431\u0430\u043b\u044b"
    ],
    "name:cat_x_preferred":[
        "Torbal\u0131"
    ],
    "name:ceb_x_preferred":[
        "Torbal\u0131"
    ],
    "name:deu_x_preferred":[
        "Torbal\u0131"
    ],
    "name:eng_x_preferred":[
        "Torbal\u0131"
    ],
    "name:fra_x_preferred":[
        "Torbal\u0131"
    ],
    "name:hun_x_preferred":[
        "Torbal\u0131"
    ],
    "name:ita_x_preferred":[
        "Distretto di Torbal\u0131"
    ],
    "name:lit_x_preferred":[
        "Torbalis"
    ],
    "name:min_x_preferred":[
        "Torbal\u0131"
    ],
    "name:mrj_x_preferred":[
        "\u0422\u043e\u0440\u0431\u0430\u043b\u044b"
    ],
    "name:msa_x_preferred":[
        "Torbal\u0131"
    ],
    "name:nan_x_preferred":[
        "Torbal\u0131"
    ],
    "name:nld_x_preferred":[
        "Torbal\u0131"
    ],
    "name:nob_x_preferred":[
        "Torbal\u0131"
    ],
    "name:pol_x_preferred":[
        "Torbal\u0131"
    ],
    "name:rus_x_preferred":[
        "\u0422\u043e\u0440\u0431\u0430\u043b\u044b"
    ],
    "name:srp_x_preferred":[
        "\u0422\u043e\u0440\u0431\u0430\u043b\u0438"
    ],
    "name:swa_x_preferred":[
        "Torbal\u0131"
    ],
    "name:tur_x_preferred":[
        "Tepek\u00f6y"
    ],
    "name:tur_x_variant":[
        "Torbal\u0131"
    ],
    "name:urd_x_preferred":[
        "\u062a\u0648\u0631\u0628\u0627\u0644\u06cc"
    ],
    "name:vie_x_preferred":[
        "Torbal\u0131"
    ],
    "qs:name":"Torbal\u0131",
    "qs:name_adm0":"Turkey",
    "qs:name_adm1":"\u0130zmir",
    "qs:photos":32,
    "qs:photos_1k":6,
    "qs:photos_9k":1,
    "qs:photos_9r":2,
    "qs:photos_all":32,
    "qs:photos_sr":2,
    "qs:placetype":"Town",
    "qs:pop_sr":"8",
    "wd:wordcount":132,
    "wof:name":"Torbal\u0131",
    "wof:placetype":"locality",
    "wof:population":50303
},
  "geometry": {"coordinates":[27.36223,38.1519],"type":"Point"}
}