{
  "type": "Feature",
  "properties": {
    "gn:country":"TR",
    "gn:fcode":"PPL",
    "gn:pop":749,
    "iso:country":"TR",
    "name:rus_x_preferred":[
        "Kyuchyuk-Medintel\u2019far"
    ],
    "name:unk_x_variant":[
        "K\u00fc\u00e7\u00fckmedinet\u00fclfar"
    ],
    "qs:name":"Sugeldi",
    "qs:photos_9r":0,
    "qs:photos_sr":0,
    "qs:pop_sr":"2",
    "wof:name":"Sugeldi",
    "wof:placetype":"locality",
    "wof:population":749
},
  "geometry": {"coordinates":[39.04333,36.81361],"type":"Point"}
}