{
  "type": "Feature",
  "properties": {
    "gn:admin1_code":"32",
    "gn:asciiname":"Kargipinar",
    "gn:country_code":"TR",
    "gn:dem":32,
    "gn:feature_class":"P",
    "gn:feature_code":"PPL",
    "gn:name":"Karg\u0131p\u0131nar",
    "gn:population":0,
    "gn:timezone":"Europe/Istanbul",
    "iso:country":"TR",
    "name:und_x_variant":[
        "Kargap\u0131nar\u0131k\u00f6y",
        "Kargap\u0131nar\u0131",
        "Karg\u0131p\u0131nar"
    ],
    "wof:name":"Kargipinar",
    "wof:placetype":"locality"
},
  "geometry": {"coordinates":[34.40871,36.67665],"type":"Point"}
}