{
  "type": "Feature",
  "properties": {
    "gn:admin1_code":"07",
    "gn:asciiname":"Alacesme",
    "gn:country_code":"TR",
    "gn:dem":848,
    "gn:feature_class":"P",
    "gn:feature_code":"PPL",
    "gn:name":"Ala\u00e7e\u015fme",
    "gn:population":0,
    "gn:timezone":"Europe/Istanbul",
    "iso:country":"TR",
    "wof:name":"Alacesme",
    "wof:placetype":"locality"
},
  "geometry": {"coordinates":[31.73657,36.96849],"type":"Point"}
}