{
  "type": "Feature",
  "properties": {
    "gn:admin1_code":"35",
    "gn:asciiname":"Kecikoy",
    "gn:country_code":"TR",
    "gn:dem":551,
    "gn:feature_class":"P",
    "gn:feature_code":"PPL",
    "gn:name":"Ke\u00e7ik\u00f6y",
    "gn:population":0,
    "gn:timezone":"Europe/Istanbul",
    "iso:country":"TR",
    "wof:name":"Kecikoy",
    "wof:placetype":"locality"
},
  "geometry": {"coordinates":[27.58333,38.28333],"type":"Point"}
}