{
  "type": "Feature",
  "properties": {
    "gn:admin1_code":"12",
    "gn:asciiname":"Kucuk Tekoren",
    "gn:country_code":"TR",
    "gn:dem":1178,
    "gn:feature_class":"P",
    "gn:feature_code":"PPL",
    "gn:name":"K\u00fc\u00e7\u00fck Tek\u00f6ren",
    "gn:population":0,
    "gn:timezone":"Europe/Istanbul",
    "iso:country":"TR",
    "name:und_x_variant":[
        "K\u00fc\u00e7\u00fcktekviran",
        "K\u00fc\u00e7\u00fck Tek\u00f6ren"
    ],
    "wof:name":"Kucuk Tekoren",
    "wof:placetype":"locality"
},
  "geometry": {"coordinates":[40.49773,38.85901],"type":"Point"}
}