{
  "type": "Feature",
  "properties": {
    "gn:admin1_code":"10",
    "gn:asciiname":"Kalburcu",
    "gn:country_code":"TR",
    "gn:dem":185,
    "gn:feature_class":"P",
    "gn:feature_code":"PPL",
    "gn:name":"Kalburcu",
    "gn:population":0,
    "gn:timezone":"Europe/Istanbul",
    "iso:country":"TR",
    "name:tur_x_preferred":[
        "Kalburcu"
    ],
    "wof:name":"Kalburcu",
    "wof:placetype":"locality"
},
  "geometry": {"coordinates":[28.13083,39.56398],"type":"Point"}
}