{
  "type": "Feature",
  "properties": {
    "gn:admin1_code":"48",
    "gn:asciiname":"Tasdibi",
    "gn:country_code":"TR",
    "gn:dem":384,
    "gn:feature_class":"P",
    "gn:feature_code":"PPL",
    "gn:name":"Ta\u015fdibi",
    "gn:population":0,
    "gn:timezone":"Europe/Istanbul",
    "iso:country":"TR",
    "name:tur_x_preferred":[
        "Ta\u015fdibi"
    ],
    "wof:name":"Tasdibi",
    "wof:placetype":"locality"
},
  "geometry": {"coordinates":[28.97761,36.88413],"type":"Point"}
}