{
  "type": "Feature",
  "properties": {
    "gn:admin1_code":"4.0",
    "gn:asciiname":"Anakaya",
    "gn:country_code":"TR",
    "gn:dem":1645,
    "gn:feature_class":"P",
    "gn:feature_code":"PPL",
    "gn:name":"Anakaya",
    "gn:population":0,
    "gn:timezone":"Europe/Istanbul",
    "iso:country":"TR",
    "name:tur_x_preferred":[
        "Anakaya"
    ],
    "wof:name":"Anakaya",
    "wof:placetype":"locality"
},
  "geometry": {"coordinates":[42.92952,39.74088],"type":"Point"}
}