{
  "type": "Feature",
  "properties": {
    "gn:admin1_code":"62",
    "gn:asciiname":"Saritas",
    "gn:country_code":"TR",
    "gn:dem":1209,
    "gn:feature_class":"P",
    "gn:feature_code":"PPL",
    "gn:name":"Sar\u0131ta\u015f",
    "gn:population":0,
    "gn:timezone":"Europe/Istanbul",
    "iso:country":"TR",
    "name:und_x_variant":[
        "Sar\u0131ta\u015f",
        "Ha\u00e7ili"
    ],
    "wof:name":"Saritas",
    "wof:placetype":"locality"
},
  "geometry": {"coordinates":[39.50481,39.26309000000001],"type":"Point"}
}