{
  "type": "Feature",
  "properties": {
    "gn:admin1_code":"64",
    "gn:asciiname":"Eskikoy",
    "gn:country_code":"TR",
    "gn:dem":1059,
    "gn:feature_class":"P",
    "gn:feature_code":"PPL",
    "gn:name":"Eskik\u00f6y",
    "gn:population":0,
    "gn:timezone":"Europe/Istanbul",
    "iso:country":"TR",
    "name:tur_x_preferred":[
        "Eskik\u00f6y"
    ],
    "wof:name":"Eskikoy",
    "wof:placetype":"locality"
},
  "geometry": {"coordinates":[29.43505,38.8184],"type":"Point"}
}