{
  "type": "Feature",
  "properties": {
    "gn:admin1_code":"8.0",
    "gn:asciiname":"Akarsu",
    "gn:country_code":"TR",
    "gn:dem":1267,
    "gn:feature_class":"P",
    "gn:feature_code":"PPL",
    "gn:name":"Akarsu",
    "gn:population":0,
    "gn:timezone":"Europe/Istanbul",
    "iso:country":"TR",
    "name:tur_x_preferred":[
        "Akarsu"
    ],
    "wof:name":"Akarsu",
    "wof:placetype":"locality"
},
  "geometry": {"coordinates":[42.13082,41.1098],"type":"Point"}
}