{
  "type": "Feature",
  "properties": {
    "gn:admin1_code":"35",
    "gn:asciiname":"Dagkizilca",
    "gn:country_code":"TR",
    "gn:dem":264,
    "gn:feature_class":"P",
    "gn:feature_code":"PPLA3",
    "gn:name":"Da\u011fk\u0131z\u0131lca",
    "gn:population":0,
    "gn:timezone":"Europe/Istanbul",
    "iso:country":"TR",
    "name:tur_x_preferred":[
        "Da\u011fk\u0131z\u0131lca"
    ],
    "wof:name":"Dagkizilca",
    "wof:placetype":"locality"
},
  "geometry": {"coordinates":[27.39081,38.311],"type":"Point"}
}