{
  "type": "Feature",
  "properties": {
    "gn:admin1_code":"65",
    "gn:asciiname":"Degirmigol",
    "gn:country_code":"TR",
    "gn:dem":2214,
    "gn:feature_class":"P",
    "gn:feature_code":"PPL",
    "gn:name":"De\u011firmig\u00f6l",
    "gn:population":0,
    "gn:timezone":"Europe/Istanbul",
    "iso:country":"TR",
    "name:und_x_variant":[
        "Mil\u00e2nengiz",
        "De\u011firmig\u00f6l"
    ],
    "wof:name":"Degirmigol",
    "wof:placetype":"locality"
},
  "geometry": {"coordinates":[44.1588,38.58651],"type":"Point"}
}