{
  "type": "Feature",
  "properties": {
    "gn:admin1_code":"09",
    "gn:asciiname":"Sercekoy",
    "gn:country_code":"TR",
    "gn:dem":42,
    "gn:feature_class":"P",
    "gn:feature_code":"PPL",
    "gn:name":"Ser\u00e7ek\u00f6y",
    "gn:population":0,
    "gn:timezone":"Europe/Istanbul",
    "iso:country":"TR",
    "name:und_x_variant":[
        "Ser\u00e7e",
        "Ser\u00e7ek\u00f6y"
    ],
    "wof:name":"Sercekoy",
    "wof:placetype":"locality"
},
  "geometry": {"coordinates":[27.93318,37.84496],"type":"Point"}
}