{
  "type": "Feature",
  "properties": {
    "gn:admin1_code":"09",
    "gn:asciiname":"Sercekoy",
    "gn:country_code":"TR",
    "gn:dem":42,
    "gn:feature_class":"P",
    "gn:feature_code":"PPL",
    "gn:name":"Ser\u00e7ek\u00f6y",
    "gn:population":0,
    "gn:timezone":"Europe/Istanbul",
    "iso:country":"TR",
    "name:ceb_x_preferred":[
        "Ser\u00e7ek\u00f6y"
    ],
    "name:fas_x_preferred":[
        "\u0633\u0631\u0686\u0647\u200c\u06a9\u0648\u06cc"
    ],
    "name:msa_x_preferred":[
        "Ser\u00e7ek\u00f6y"
    ],
    "name:tur_x_preferred":[
        "Ser\u00e7ek\u00f6y"
    ],
    "name:und_x_variant":[
        "Ser\u00e7e"
    ],
    "name:vie_x_preferred":[
        "Ser\u00e7ek\u00f6y"
    ],
    "wof:name":"Sercekoy",
    "wof:placetype":"locality"
},
  "geometry": {"coordinates":[27.93318,37.84496],"type":"Point"}
}