{
  "type": "Feature",
  "properties": {
    "gn:admin1_code":"37.0",
    "gn:asciiname":"Karcilar",
    "gn:country_code":"TR",
    "gn:dem":826,
    "gn:feature_class":"P",
    "gn:feature_code":"PPL",
    "gn:name":"Karc\u0131lar",
    "gn:population":0,
    "gn:timezone":"Europe/Istanbul",
    "iso:country":"TR",
    "name:und_x_variant":[
        "Karc\u0131lar",
        "Ramibey"
    ],
    "wof:name":"Karcilar",
    "wof:placetype":"locality"
},
  "geometry": {"coordinates":[33.13154,41.17158],"type":"Point"}
}