{
  "type": "Feature",
  "properties": {
    "gn:admin1_code":"11.0",
    "gn:asciiname":"Akcasu",
    "gn:country_code":"TR",
    "gn:dem":200,
    "gn:feature_class":"P",
    "gn:feature_code":"PPL",
    "gn:name":"Ak\u00e7asu",
    "gn:population":0,
    "gn:timezone":"Europe/Istanbul",
    "iso:country":"TR",
    "name:tur_x_preferred":[
        "Ak\u00e7asu"
    ],
    "wof:name":"Akcasu",
    "wof:placetype":"locality"
},
  "geometry": {"coordinates":[30.30728,40.08516],"type":"Point"}
}