{
  "type": "Feature",
  "properties": {
    "gn:admin1_code":"76.0",
    "gn:asciiname":"Bolucek",
    "gn:country_code":"TR",
    "gn:dem":1016,
    "gn:feature_class":"P",
    "gn:feature_code":"PPL",
    "gn:name":"B\u00f6l\u00fccek",
    "gn:population":0,
    "gn:timezone":"Europe/Istanbul",
    "iso:country":"TR",
    "wof:name":"Bolucek",
    "wof:placetype":"locality"
},
  "geometry": {"coordinates":[41.31859,38.25172],"type":"Point"}
}