{
  "type": "Feature",
  "properties": {
    "gn:admin1_code":"83",
    "gn:asciiname":"Dostalli",
    "gn:country_code":"TR",
    "gn:dem":802,
    "gn:feature_class":"P",
    "gn:feature_code":"PPL",
    "gn:name":"Dostall\u0131",
    "gn:population":0,
    "gn:timezone":"Europe/Istanbul",
    "iso:country":"TR",
    "wof:name":"Dostalli",
    "wof:placetype":"locality"
},
  "geometry": {"coordinates":[37.01667,37.05],"type":"Point"}
}