{
  "type": "Feature",
  "properties": {
    "gn:admin1_code":"89.0",
    "gn:asciiname":"Cileklik",
    "gn:country_code":"TR",
    "gn:dem":994,
    "gn:feature_class":"P",
    "gn:feature_code":"PPL",
    "gn:name":"\u00c7ileklik",
    "gn:population":0,
    "gn:timezone":"Europe/Istanbul",
    "iso:country":"TR",
    "name:und_x_variant":[
        "\u00c7ilekli",
        "\u00c7ileklik"
    ],
    "wof:name":"Cileklik",
    "wof:placetype":"locality"
},
  "geometry": {"coordinates":[32.78333,41.36667],"type":"Point"}
}