{
  "type": "Feature",
  "properties": {
    "gn:admin1_code":"90",
    "gn:asciiname":"Kuzuini",
    "gn:cc2":"TR",
    "gn:country_code":"TR",
    "gn:dem":715,
    "gn:feature_class":"P",
    "gn:feature_code":"PPL",
    "gn:name":"Kuzuini",
    "gn:population":0,
    "gn:timezone":"Europe/Istanbul",
    "iso:country":"TR",
    "name:und_x_variant":[
        "Kuzeyne",
        "Kuzuini"
    ],
    "wof:name":"Kuzuini",
    "wof:placetype":"locality"
},
  "geometry": {"coordinates":[37.07639,36.77306],"type":"Point"}
}