{
  "type": "Feature",
  "properties": {
    "gn:admin1_code":"10",
    "gn:asciiname":"Sarica",
    "gn:country_code":"TR",
    "gn:dem":272,
    "gn:feature_class":"P",
    "gn:feature_code":"PPL",
    "gn:name":"Sar\u0131ca",
    "gn:population":0,
    "gn:timezone":"Europe/Istanbul",
    "iso:country":"TR",
    "name:und_x_variant":[
        "Sar\u0131cak\u00f6y\u00fc",
        "Sar\u0131ca"
    ],
    "wof:name":"Sarica",
    "wof:placetype":"locality"
},
  "geometry": {"coordinates":[27.49001,39.62412],"type":"Point"}
}