{
  "type": "Feature",
  "properties": {
    "gn:country":"TR",
    "gn:fcode":"PPL",
    "gn:pop":563,
    "iso:country":"TR",
    "name:tur_x_preferred":[
        "K\u0131say\u0131r"
    ],
    "name:unk_x_variant":[
        "\u00d6renl\u0131"
    ],
    "qs:name":"Oranl\u0131",
    "qs:photos_9r":0,
    "qs:photos_sr":0,
    "qs:pop_sr":"2",
    "wof:name":"Oranl\u0131",
    "wof:placetype":"locality",
    "wof:population":563
},
  "geometry": {"coordinates":[39.27763,36.97661],"type":"Point"}
}