{
  "type": "Feature",
  "properties": {
    "gn:admin1_code":"21",
    "gn:asciiname":"Bogaz",
    "gn:country_code":"TR",
    "gn:dem":946,
    "gn:feature_class":"P",
    "gn:feature_code":"PPL",
    "gn:name":"Bo\u011faz",
    "gn:population":0,
    "gn:timezone":"Europe/Istanbul",
    "iso:country":"TR",
    "name:tur_x_preferred":[
        "Bo\u011faz"
    ],
    "wof:name":"Bogaz",
    "wof:placetype":"locality"
},
  "geometry": {"coordinates":[39.96183,38.43879],"type":"Point"}
}