{
  "type": "Feature",
  "properties": {
    "gn:admin1_code":"21",
    "gn:asciiname":"Bogaz",
    "gn:country_code":"TR",
    "gn:dem":946,
    "gn:feature_class":"P",
    "gn:feature_code":"PPL",
    "gn:name":"Bo\u011faz",
    "gn:population":0,
    "gn:timezone":"Europe/Istanbul",
    "iso:country":"TR",
    "name:bul_x_preferred":[
        "\u0411\u043e\u0433\u0430\u0437\u0438"
    ],
    "name:ceb_x_preferred":[
        "Bog\u00e1zi"
    ],
    "name:deu_x_preferred":[
        "Bogazi/Bo\u011faz"
    ],
    "name:ell_x_preferred":[
        "\u039c\u03c0\u03bf\u03b3\u03ac\u03b6"
    ],
    "name:pol_x_preferred":[
        "Bogazi"
    ],
    "name:slk_x_preferred":[
        "Bogaz"
    ],
    "name:swe_x_preferred":[
        "Bog\u00e1zi"
    ],
    "name:tur_x_preferred":[
        "Bo\u011faz"
    ],
    "wof:name":"Bogaz",
    "wof:placetype":"locality"
},
  "geometry": {"coordinates":[39.96183,38.43879],"type":"Point"}
}