{
  "type": "Feature",
  "properties": {
    "gn:admin1_code":"24",
    "gn:asciiname":"Kockar",
    "gn:country_code":"TR",
    "gn:dem":1290,
    "gn:feature_class":"P",
    "gn:feature_code":"PPL",
    "gn:name":"Ko\u00e7kar",
    "gn:population":0,
    "gn:timezone":"Europe/Istanbul",
    "iso:country":"TR",
    "name:und_x_variant":[
        "Ko\u00e7kar",
        "Hudu"
    ],
    "wof:name":"Kockar",
    "wof:placetype":"locality"
},
  "geometry": {"coordinates":[38.92195,39.55529],"type":"Point"}
}