{
  "type": "Feature",
  "properties": {
    "gn:admin1_code":"07",
    "gn:asciiname":"Boztepe",
    "gn:country_code":"TR",
    "gn:dem":13,
    "gn:feature_class":"P",
    "gn:feature_code":"PPL",
    "gn:name":"Boztepe",
    "gn:population":0,
    "gn:timezone":"Europe/Istanbul",
    "iso:country":"TR",
    "name:ceb_x_preferred":[
        "Boztepe"
    ],
    "name:deu_x_preferred":[
        "Boztepe"
    ],
    "name:fra_x_preferred":[
        "Boztepe"
    ],
    "name:nld_x_preferred":[
        "Boztepe"
    ],
    "name:tur_x_preferred":[
        "Boztepe"
    ],
    "wof:name":"Boztepe",
    "wof:placetype":"locality"
},
  "geometry": {"coordinates":[30.90722,36.91278],"type":"Point"}
}