{
  "type": "Feature",
  "properties": {
    "gn:admin1_code":"91.0",
    "gn:asciiname":"Ciceklidere",
    "gn:country_code":"TR",
    "gn:dem":1296,
    "gn:feature_class":"P",
    "gn:feature_code":"PPL",
    "gn:name":"\u00c7i\u00e7eklidere",
    "gn:population":0,
    "gn:timezone":"Europe/Istanbul",
    "iso:country":"TR",
    "wof:name":"Ciceklidere",
    "wof:placetype":"locality"
},
  "geometry": {"coordinates":[36.09818,37.60481],"type":"Point"}
}