{
  "type": "Feature",
  "properties": {
    "gn:admin1_code":"16",
    "gn:asciiname":"Osmaniye",
    "gn:country_code":"TR",
    "gn:dem":634,
    "gn:feature_class":"P",
    "gn:feature_code":"PPL",
    "gn:name":"Osmaniye",
    "gn:population":0,
    "gn:timezone":"Europe/Istanbul",
    "iso:country":"TR",
    "name:tur_x_preferred":[
        "Osmaniye"
    ],
    "wof:name":"Osmaniye",
    "wof:placetype":"locality"
},
  "geometry": {"coordinates":[29.25385,40.14854],"type":"Point"}
}