{
  "type": "Feature",
  "properties": {
    "gn:admin1_code":"28.0",
    "gn:asciiname":"Gundogdu",
    "gn:country_code":"TR",
    "gn:dem":1325,
    "gn:feature_class":"P",
    "gn:feature_code":"PPL",
    "gn:name":"G\u00fcndo\u011fdu",
    "gn:population":0,
    "gn:timezone":"Europe/Istanbul",
    "iso:country":"TR",
    "name:und_x_variant":[
        "Karak\u00f6y",
        "G\u00fcndo\u011fdu"
    ],
    "wof:name":"Gundogdu",
    "wof:placetype":"locality"
},
  "geometry": {"coordinates":[38.39409000000001,40.18388],"type":"Point"}
}