{
  "type": "Feature",
  "properties": {
    "gn:admin1_code":"37",
    "gn:asciiname":"Yukariguney",
    "gn:country_code":"TR",
    "gn:dem":674,
    "gn:feature_class":"P",
    "gn:feature_code":"PPL",
    "gn:name":"Yukar\u0131g\u00fcney",
    "gn:population":0,
    "gn:timezone":"Europe/Istanbul",
    "iso:country":"TR",
    "wof:name":"Yukariguney",
    "wof:placetype":"locality"
},
  "geometry": {"coordinates":[33.00836,41.16234],"type":"Point"}
}