{
  "type": "Feature",
  "properties": {
    "gn:admin1_code":"10",
    "gn:asciiname":"Temasalik",
    "gn:country_code":"TR",
    "gn:dem":53,
    "gn:feature_class":"P",
    "gn:feature_code":"PPL",
    "gn:name":"Tema\u015fal\u0131k",
    "gn:population":0,
    "gn:timezone":"Europe/Istanbul",
    "iso:country":"TR",
    "name:tur_x_preferred":[
        "Tema\u015fal\u0131k"
    ],
    "wof:name":"Temasalik",
    "wof:placetype":"locality"
},
  "geometry": {"coordinates":[27.0938,39.57296],"type":"Point"}
}