{
  "type": "Feature",
  "properties": {
    "gn:admin1_code":"23",
    "gn:asciiname":"Alayagmur",
    "gn:country_code":"TR",
    "gn:dem":902,
    "gn:feature_class":"P",
    "gn:feature_code":"PPL",
    "gn:name":"Alaya\u011fmur",
    "gn:population":0,
    "gn:timezone":"Europe/Istanbul",
    "iso:country":"TR",
    "name:und_x_variant":[
        "Alayamur",
        "Alaya\u011fmur"
    ],
    "wof:name":"Alayagmur",
    "wof:placetype":"locality"
},
  "geometry": {"coordinates":[39.86991,38.8871],"type":"Point"}
}