{
  "type": "Feature",
  "properties": {
    "gn:admin1_code":"91",
    "gn:asciiname":"Narkisla",
    "gn:country_code":"TR",
    "gn:dem":52,
    "gn:feature_class":"P",
    "gn:feature_code":"PPL",
    "gn:name":"Nark\u0131\u015fla",
    "gn:population":0,
    "gn:timezone":"Europe/Istanbul",
    "iso:country":"TR",
    "name:und_x_variant":[
        "Nark\u0131\u015fla",
        "Narl\u0131k\u0131\u015fla"
    ],
    "wof:name":"Narkisla",
    "wof:placetype":"locality"
},
  "geometry": {"coordinates":[36.03939,37.33468],"type":"Point"}
}