{
  "type": "Feature",
  "properties": {
    "gn:admin1_code":"46.0",
    "gn:asciiname":"Acielma",
    "gn:country_code":"TR",
    "gn:dem":1795,
    "gn:feature_class":"P",
    "gn:feature_code":"PPL",
    "gn:name":"Ac\u0131elma",
    "gn:population":0,
    "gn:timezone":"Europe/Istanbul",
    "iso:country":"TR",
    "name:tur_x_preferred":[
        "Ac\u0131elma"
    ],
    "wof:name":"Acielma",
    "wof:placetype":"locality"
},
  "geometry": {"coordinates":[36.40334,37.99713],"type":"Point"}
}