{
  "type": "Feature",
  "properties": {
    "gn:admin1_code":"23.0",
    "gn:asciiname":"Guneytepe",
    "gn:country_code":"TR",
    "gn:dem":1295,
    "gn:feature_class":"P",
    "gn:feature_code":"PPL",
    "gn:name":"G\u00fcneytepe",
    "gn:population":0,
    "gn:timezone":"Europe/Istanbul",
    "iso:country":"TR",
    "name:tur_x_preferred":[
        "G\u00fcneytepe"
    ],
    "wof:name":"Guneytepe",
    "wof:placetype":"locality"
},
  "geometry": {"coordinates":[38.89568,38.70742],"type":"Point"}
}