{
  "type": "Feature",
  "properties": {
    "gn:country":"TR",
    "gn:fcode":"PPL",
    "gn:pop":0,
    "iso:country":"TR",
    "name:unk_x_variant":[
        "Araplar"
    ],
    "qs:name":"Mutlu",
    "qs:name_adm0":"Turkey",
    "qs:name_adm1":"Manisa",
    "qs:photos":3,
    "qs:photos_1k":1,
    "qs:photos_9k":1,
    "qs:photos_9r":1,
    "qs:photos_all":3,
    "qs:photos_sr":1,
    "qs:placetype":"Suburb",
    "qs:pop_sr":"0",
    "wd:wordcount":80,
    "wof:name":"Mutlu",
    "wof:placetype":"neighbourhood",
    "wof:population":0
},
  "geometry": {"coordinates":[26.77444,39.30194],"type":"Point"}
}