{
  "type": "Feature",
  "properties": {
    "gn:admin1_code":"13",
    "gn:asciiname":"Yukari Yolak",
    "gn:country_code":"TR",
    "gn:dem":1180,
    "gn:feature_class":"P",
    "gn:feature_code":"PPL",
    "gn:name":"Yukar\u0131 Yolak",
    "gn:population":0,
    "gn:timezone":"Europe/Istanbul",
    "iso:country":"TR",
    "name:tur_x_preferred":[
        "Yukar\u0131 Yolak"
    ],
    "wof:name":"Yukari Yolak",
    "wof:placetype":"locality"
},
  "geometry": {"coordinates":[42.07849,38.25441],"type":"Point"}
}