{
  "type": "Feature",
  "properties": {
    "gn:admin1_code":"35",
    "gn:asciiname":"Cirpi",
    "gn:country_code":"TR",
    "gn:dem":21,
    "gn:feature_class":"P",
    "gn:feature_code":"PPLA3",
    "gn:name":"\u00c7\u0131rp\u0131",
    "gn:population":0,
    "gn:timezone":"Europe/Istanbul",
    "iso:country":"TR",
    "name:und_x_variant":[
        "\u00c7\u0131rp\u0131k\u00f6y",
        "\u00c7\u0131rp\u0131"
    ],
    "wof:name":"Cirpi",
    "wof:placetype":"locality"
},
  "geometry": {"coordinates":[27.4975,38.16444],"type":"Point"}
}