{
  "type": "Feature",
  "properties": {
    "gn:admin1_code":"44",
    "gn:asciiname":"Tarlacik",
    "gn:country_code":"TR",
    "gn:dem":1140,
    "gn:feature_class":"P",
    "gn:feature_code":"PPL",
    "gn:name":"Tarlac\u0131k",
    "gn:population":0,
    "gn:timezone":"Europe/Istanbul",
    "iso:country":"TR",
    "name:und_x_variant":[
        "K\u0131z\u0131k",
        "Tarlac\u0131k"
    ],
    "wof:name":"Tarlacik",
    "wof:placetype":"locality"
},
  "geometry": {"coordinates":[38.24057,38.74808],"type":"Point"}
}