{
  "type": "Feature",
  "properties": {
    "gn:admin1_code":"85",
    "gn:asciiname":"Memis",
    "gn:country_code":"TR",
    "gn:dem":822,
    "gn:feature_class":"P",
    "gn:feature_code":"PPL",
    "gn:name":"Memis",
    "gn:population":0,
    "gn:timezone":"Europe/Istanbul",
    "iso:country":"TR",
    "wof:name":"Memis",
    "wof:placetype":"locality"
},
  "geometry": {"coordinates":[31.84543,41.05682],"type":"Point"}
}