{
  "type": "Feature",
  "properties": {
    "gn:admin1_code":"54",
    "gn:asciiname":"Egrioglu",
    "gn:country_code":"TR",
    "gn:dem":149,
    "gn:feature_class":"P",
    "gn:feature_code":"PPL",
    "gn:name":"E\u011frio\u011flu",
    "gn:population":0,
    "gn:timezone":"Europe/Istanbul",
    "iso:country":"TR",
    "name:tur_x_preferred":[
        "E\u011frio\u011flu"
    ],
    "wof:name":"Egrioglu",
    "wof:placetype":"locality"
},
  "geometry": {"coordinates":[30.2908,40.98819],"type":"Point"}
}