{
  "type": "Feature",
  "properties": {
    "gn:admin1_code":"22.0",
    "gn:asciiname":"Suleymandanisment",
    "gn:country_code":"TR",
    "gn:dem":386,
    "gn:feature_class":"P",
    "gn:feature_code":"PPL",
    "gn:name":"S\u00fcleymandani\u015fment",
    "gn:population":0,
    "gn:timezone":"Europe/Istanbul",
    "iso:country":"TR",
    "wof:name":"Suleymandanisment",
    "wof:placetype":"locality"
},
  "geometry": {"coordinates":[26.88866,41.89634],"type":"Point"}
}