{
  "type": "Feature",
  "properties": {
    "gn:admin1_code":"71",
    "gn:asciiname":"Baskaraoren",
    "gn:country_code":"TR",
    "gn:dem":1108,
    "gn:feature_class":"P",
    "gn:feature_code":"PPL",
    "gn:name":"Ba\u015fkara\u00f6ren",
    "gn:population":0,
    "gn:timezone":"Europe/Istanbul",
    "iso:country":"TR",
    "name:und_x_variant":[
        "Ba\u015fkara\u00f6ren",
        "Ba\u015fkaraviran"
    ],
    "wof:name":"Baskaraoren",
    "wof:placetype":"locality"
},
  "geometry": {"coordinates":[32.0783,37.3983],"type":"Point"}
}