{
  "type": "Feature",
  "properties": {
    "gn:admin1_code":"58.0",
    "gn:asciiname":"Kayi",
    "gn:country_code":"TR",
    "gn:dem":1286,
    "gn:feature_class":"P",
    "gn:feature_code":"PPL",
    "gn:name":"Kay\u0131",
    "gn:population":0,
    "gn:timezone":"Europe/Istanbul",
    "iso:country":"TR",
    "name:tur_x_preferred":[
        "Kay\u0131"
    ],
    "wof:name":"Kayi",
    "wof:placetype":"locality"
},
  "geometry": {"coordinates":[38.42143,40.06807],"type":"Point"}
}