{
  "type": "Feature",
  "properties": {
    "gn:admin1_code":"35",
    "gn:asciiname":"Alankiyi",
    "gn:country_code":"TR",
    "gn:dem":683,
    "gn:feature_class":"P",
    "gn:feature_code":"PPL",
    "gn:name":"Alank\u0131y\u0131",
    "gn:population":0,
    "gn:timezone":"Europe/Istanbul",
    "iso:country":"TR",
    "wof:name":"Alankiyi",
    "wof:placetype":"locality"
},
  "geometry": {"coordinates":[27.62889,38.28583],"type":"Point"}
}