{
  "type": "Feature",
  "properties": {
    "gn:admin1_code":"58",
    "gn:asciiname":"Mursal",
    "gn:country_code":"TR",
    "gn:dem":1865,
    "gn:feature_class":"P",
    "gn:feature_code":"PPLA3",
    "gn:name":"Mursal",
    "gn:population":0,
    "gn:timezone":"Europe/Istanbul",
    "iso:country":"TR",
    "name:und_x_variant":[
        "Vaz\u0131ldan",
        "M\u00fcrsel",
        "Mursal"
    ],
    "wof:name":"Mursal",
    "wof:placetype":"locality"
},
  "geometry": {"coordinates":[37.95694,39.16778],"type":"Point"}
}