{
  "type": "Feature",
  "properties": {
    "gn:admin1_code":"68.0",
    "gn:asciiname":"Kurtkovan",
    "gn:country_code":"TR",
    "gn:dem":1256,
    "gn:feature_class":"P",
    "gn:feature_code":"PPL",
    "gn:name":"Kurtkovan",
    "gn:population":0,
    "gn:timezone":"Europe/Istanbul",
    "iso:country":"TR",
    "name:und_x_variant":[
        "Kurtko\u011fan"
    ],
    "wof:name":"Kurtkovan",
    "wof:placetype":"locality"
},
  "geometry": {"coordinates":[31.88519,40.2592],"type":"Point"}
}