{
  "type": "Feature",
  "properties": {
    "gn:admin1_code":"54.0",
    "gn:asciiname":"Ilica",
    "gn:country_code":"TR",
    "gn:dem":503,
    "gn:feature_class":"P",
    "gn:feature_code":"PPL",
    "gn:name":"Il\u0131ca",
    "gn:population":0,
    "gn:timezone":"Europe/Istanbul",
    "iso:country":"TR",
    "name:ceb_x_preferred":[
        "Ilica"
    ],
    "name:fra_x_preferred":[
        "Ilica"
    ],
    "name:swe_x_preferred":[
        "Ilica"
    ],
    "name:und_x_variant":[
        "Il\u0131ca",
        "Il\u0131cak\u00f6y"
    ],
    "wof:name":"Ilica",
    "wof:placetype":"locality"
},
  "geometry": {"coordinates":[30.38597,40.45485],"type":"Point"}
}