{
  "type": "Feature",
  "properties": {
    "gn:admin1_code":"61.0",
    "gn:asciiname":"Simenli",
    "gn:country_code":"TR",
    "gn:dem":954,
    "gn:feature_class":"P",
    "gn:feature_code":"PPL",
    "gn:name":"Simenli",
    "gn:population":0,
    "gn:timezone":"Europe/Istanbul",
    "iso:country":"TR",
    "name:tur_x_preferred":[
        "Simenli"
    ],
    "wof:name":"Simenli",
    "wof:placetype":"locality"
},
  "geometry": {"coordinates":[39.20129,40.86032],"type":"Point"}
}