{
  "type": "Feature",
  "properties": {
    "gn:admin1_code":"13",
    "gn:asciiname":"Kayabasi",
    "gn:country_code":"TR",
    "gn:dem":1557,
    "gn:feature_class":"P",
    "gn:feature_code":"PPL",
    "gn:name":"Kayaba\u015f\u0131",
    "gn:population":0,
    "gn:timezone":"Europe/Istanbul",
    "iso:country":"TR",
    "name:tur_x_preferred":[
        "Kayaba\u015f\u0131"
    ],
    "name:und_x_variant":[
        "\u00c7elikan"
    ],
    "wof:name":"Kayabasi",
    "wof:placetype":"locality"
},
  "geometry": {"coordinates":[42.13329,38.34768],"type":"Point"}
}