{
  "type": "Feature",
  "properties": {
    "gn:admin1_code":"61.0",
    "gn:asciiname":"Manasor",
    "gn:cc2":"TR",
    "gn:country_code":"TR",
    "gn:dem":1882,
    "gn:feature_class":"P",
    "gn:feature_code":"PPL",
    "gn:name":"Manasor",
    "gn:population":0,
    "gn:timezone":"Europe/Istanbul",
    "iso:country":"TR",
    "name:und_x_variant":[
        "Mana\u015for Mahallesi",
        "Manasor"
    ],
    "wof:name":"Manasor",
    "wof:placetype":"locality"
},
  "geometry": {"coordinates":[40.36667,40.68333],"type":"Point"}
}