{
  "type": "Feature",
  "properties": {
    "gn:admin1_code":"31.0",
    "gn:asciiname":"Dalyan Koy",
    "gn:cc2":"TR",
    "gn:country_code":"TR",
    "gn:dem":101,
    "gn:feature_class":"P",
    "gn:feature_code":"PPL",
    "gn:name":"Dalyan K\u00f6y",
    "gn:population":0,
    "gn:timezone":"Europe/Istanbul",
    "iso:country":"TR",
    "name:rus_x_preferred":[
        "Dal\u2019yank\u00eby"
    ],
    "name:und_x_variant":[
        "Dalyan K\u00f6y"
    ],
    "wof:name":"Dalyan Koy",
    "wof:placetype":"locality"
},
  "geometry": {"coordinates":[36.20222,36.3025],"type":"Point"}
}