{
  "type": "Feature",
  "properties": {
    "gn:admin1_code":"82",
    "gn:asciiname":"Akguney",
    "gn:country_code":"TR",
    "gn:dem":1005,
    "gn:feature_class":"P",
    "gn:feature_code":"PPL",
    "gn:name":"Akg\u00fcney",
    "gn:population":0,
    "gn:timezone":"Europe/Istanbul",
    "iso:country":"TR",
    "wof:name":"Akguney",
    "wof:placetype":"locality"
},
  "geometry": {"coordinates":[33.16557,40.92748],"type":"Point"}
}