{
  "type": "Feature",
  "properties": {
    "gn:admin1_code":"17",
    "gn:asciiname":"Bekten",
    "gn:country_code":"TR",
    "gn:dem":300,
    "gn:feature_class":"P",
    "gn:feature_code":"PPL",
    "gn:name":"Bekten",
    "gn:population":0,
    "gn:timezone":"Europe/Istanbul",
    "iso:country":"TR",
    "wof:name":"Bekten",
    "wof:placetype":"locality"
},
  "geometry": {"coordinates":[27.27768,39.99464],"type":"Point"}
}