{
  "type": "Feature",
  "properties": {
    "gn:admin1_code":"31.0",
    "gn:asciiname":"Eseli",
    "gn:country_code":"TR",
    "gn:dem":175,
    "gn:feature_class":"P",
    "gn:feature_code":"PPL",
    "gn:name":"Eseli",
    "gn:population":0,
    "gn:timezone":"Europe/Istanbul",
    "iso:country":"TR",
    "name:tur_x_preferred":[
        "Eseli"
    ],
    "wof:name":"Eseli",
    "wof:placetype":"locality"
},
  "geometry": {"coordinates":[36.20278,36.96194000000001],"type":"Point"}
}