{
  "type": "Feature",
  "properties": {
    "gn:admin1_code":"46",
    "gn:asciiname":"Doganli Karahasan",
    "gn:country_code":"TR",
    "gn:dem":750,
    "gn:feature_class":"P",
    "gn:feature_code":"PPL",
    "gn:name":"Do\u011fanl\u0131 Karahasan",
    "gn:population":0,
    "gn:timezone":"Europe/Istanbul",
    "iso:country":"TR",
    "name:tur_x_preferred":[
        "Do\u011fanl\u0131 Karahasan"
    ],
    "name:und_x_variant":[
        "Karahasan",
        "Do\u011fanl\u0131karahasan"
    ],
    "wof:name":"Doganli Karahasan",
    "wof:placetype":"locality"
},
  "geometry": {"coordinates":[37.14365,37.4769],"type":"Point"}
}