{
  "type": "Feature",
  "properties": {
    "gn:admin1_code":"55.0",
    "gn:asciiname":"Elaldi",
    "gn:country_code":"TR",
    "gn:dem":910,
    "gn:feature_class":"P",
    "gn:feature_code":"PPL",
    "gn:name":"Elald\u0131",
    "gn:population":0,
    "gn:timezone":"Europe/Istanbul",
    "iso:country":"TR",
    "wof:name":"Elaldi",
    "wof:placetype":"locality"
},
  "geometry": {"coordinates":[35.44607,41.05039],"type":"Point"}
}