{
  "type": "Feature",
  "properties": {
    "gn:admin1_code":"61.0",
    "gn:asciiname":"Fevziye",
    "gn:country_code":"TR",
    "gn:dem":381,
    "gn:feature_class":"P",
    "gn:feature_code":"PPL",
    "gn:name":"Fevziye",
    "gn:population":0,
    "gn:timezone":"Europe/Istanbul",
    "iso:country":"TR",
    "wof:name":"Fevziye",
    "wof:placetype":"locality"
},
  "geometry": {"coordinates":[39.27472,40.97232],"type":"Point"}
}