{
  "type": "Feature",
  "properties": {
    "gn:country":"TR",
    "gn:fcode":"PPL",
    "gn:population":0,
    "iso:country":"TR",
    "name:ceb_x_preferred":[
        "\u00c7ankaya"
    ],
    "name:nld_x_preferred":[
        "\u00c7ankaya"
    ],
    "name:tur_x_preferred":[
        "\u00c7ankaya"
    ],
    "qs:name":"\u00c7ankaya",
    "qs:name_adm0":"Turkey",
    "qs:name_adm1":"\u0130zmir",
    "qs:photos":3,
    "qs:photos_1k":1,
    "qs:photos_9k":1,
    "qs:photos_9r":1,
    "qs:photos_all":3,
    "qs:photos_sr":1,
    "qs:placetype":"Suburb",
    "qs:pop_sr":"0",
    "wof:name":"\u00c7ankaya",
    "wof:placetype":"neighbourhood",
    "wof:population":0
},
  "geometry": {"coordinates":[27.14063,38.42443],"type":"Point"}
}