{
  "type": "Feature",
  "properties": {
    "gn:admin1_code":"75.0",
    "gn:asciiname":"Akcakent",
    "gn:country_code":"TR",
    "gn:dem":1366,
    "gn:feature_class":"P",
    "gn:feature_code":"PPL",
    "gn:name":"Ak\u00e7akent",
    "gn:population":0,
    "gn:timezone":"Europe/Istanbul",
    "iso:country":"TR",
    "name:und_x_variant":[
        "Akcakentk\u00f6y\u00fc",
        "Ak\u00e7akent"
    ],
    "wof:name":"Akcakent",
    "wof:placetype":"locality"
},
  "geometry": {"coordinates":[34.08992,38.08397],"type":"Point"}
}