{
  "type": "Feature",
  "properties": {
    "gn:admin1_code":"16.0",
    "gn:asciiname":"Akincilar",
    "gn:country_code":"TR",
    "gn:dem":406,
    "gn:feature_class":"P",
    "gn:feature_code":"PPL",
    "gn:name":"Ak\u0131nc\u0131lar",
    "gn:population":0,
    "gn:timezone":"Europe/Istanbul",
    "iso:country":"TR",
    "name:und_x_variant":[
        "Kadimi",
        "Ak\u0131nc\u0131lar"
    ],
    "wof:name":"Akincilar",
    "wof:placetype":"locality"
},
  "geometry": {"coordinates":[29.39568,40.11205],"type":"Point"}
}