{
  "type": "Feature",
  "properties": {
    "gn:admin1_code":"11",
    "gn:asciiname":"Kapanalan",
    "gn:country_code":"TR",
    "gn:dem":866,
    "gn:feature_class":"P",
    "gn:feature_code":"PPL",
    "gn:name":"Kapanalan",
    "gn:population":0,
    "gn:timezone":"Europe/Istanbul",
    "iso:country":"TR",
    "name:und_x_variant":[
        "Kapanalan K\u00f6y\u00fc",
        "Kapanalan"
    ],
    "wof:name":"Kapanalan",
    "wof:placetype":"locality"
},
  "geometry": {"coordinates":[29.95694,39.85109],"type":"Point"}
}