{
  "type": "Feature",
  "properties": {
    "gn:admin1_code":"76",
    "gn:asciiname":"Ulasli",
    "gn:country_code":"TR",
    "gn:dem":725,
    "gn:feature_class":"P",
    "gn:feature_code":"PPL",
    "gn:name":"Ula\u015fl\u0131",
    "gn:population":0,
    "gn:timezone":"Europe/Istanbul",
    "iso:country":"TR",
    "name:tur_x_preferred":[
        "Ula\u015fl\u0131"
    ],
    "wof:name":"Ulasli",
    "wof:placetype":"locality"
},
  "geometry": {"coordinates":[41.3204,38.17663],"type":"Point"}
}