{
  "type": "Feature",
  "properties": {
    "gn:admin1_code":"35",
    "gn:asciiname":"Yolustu",
    "gn:cc2":"TR",
    "gn:country_code":"TR",
    "gn:dem":128,
    "gn:feature_class":"P",
    "gn:feature_code":"PPL",
    "gn:name":"Yol\u00fcst\u00fc",
    "gn:population":0,
    "gn:timezone":"Europe/Istanbul",
    "iso:country":"TR",
    "name:und_x_variant":[
        "Bezdeg\u00fcme",
        "Yol\u00fcst\u00fc"
    ],
    "wof:name":"Yolustu",
    "wof:placetype":"locality"
},
  "geometry": {"coordinates":[28.02639000000001,38.2125],"type":"Point"}
}