{
  "type": "Feature",
  "properties": {
    "gn:country":"TR",
    "gn:fcode":"PPL",
    "gn:population":285,
    "iso:country":"TR",
    "name:und_x_variant":[
        "Rudzhum"
    ],
    "qs:name":"Yediyol",
    "qs:photos_9r":0,
    "qs:photos_sr":0,
    "qs:pop_sr":"2",
    "wof:name":"Yediyol",
    "wof:placetype":"locality",
    "wof:population":285
},
  "geometry": {"coordinates":[38.79639,36.86528],"type":"Point"}
}