{
  "type": "Feature",
  "properties": {
    "gn:admin1_code":"61.0",
    "gn:asciiname":"Tasalan",
    "gn:country_code":"TR",
    "gn:dem":799,
    "gn:feature_class":"P",
    "gn:feature_code":"PPL",
    "gn:name":"Ta\u015falan",
    "gn:population":0,
    "gn:timezone":"Europe/Istanbul",
    "iso:country":"TR",
    "wof:name":"Tasalan",
    "wof:placetype":"locality"
},
  "geometry": {"coordinates":[39.68816,40.81366],"type":"Point"}
}