{
  "type": "Feature",
  "properties": {
    "gn:admin1_code":"10",
    "gn:asciiname":"Yakupkoy",
    "gn:country_code":"TR",
    "gn:dem":169,
    "gn:feature_class":"P",
    "gn:feature_code":"PPL",
    "gn:name":"Yakupk\u00f6y",
    "gn:population":0,
    "gn:timezone":"Europe/Istanbul",
    "iso:country":"TR",
    "name:tur_x_preferred":[
        "Yakupk\u00f6y"
    ],
    "wof:name":"Yakupkoy",
    "wof:placetype":"locality"
},
  "geometry": {"coordinates":[28.13382,39.97241],"type":"Point"}
}