{
  "type": "Feature",
  "properties": {
    "gn:admin1_code":"63",
    "gn:asciiname":"Egridzhe",
    "gn:country_code":"TR",
    "gn:dem":484,
    "gn:feature_class":"P",
    "gn:feature_code":"PPL",
    "gn:name":"Egridzhe",
    "gn:population":0,
    "gn:timezone":"Europe/Istanbul",
    "iso:country":"TR",
    "wof:name":"Egridzhe",
    "wof:placetype":"locality"
},
  "geometry": {"coordinates":[39.11021,37.19299],"type":"Point"}
}