{
  "type": "Feature",
  "properties": {
    "gn:admin1_code":"21",
    "gn:asciiname":"Sakalli",
    "gn:country_code":"TR",
    "gn:dem":1052,
    "gn:feature_class":"P",
    "gn:feature_code":"PPL",
    "gn:name":"Sakall\u0131",
    "gn:population":0,
    "gn:timezone":"Europe/Istanbul",
    "iso:country":"TR",
    "name:tur_x_preferred":[
        "Sakall\u0131"
    ],
    "wof:name":"Sakalli",
    "wof:placetype":"locality"
},
  "geometry": {"coordinates":[39.88457,37.84651],"type":"Point"}
}