{
  "type": "Feature",
  "properties": {
    "gn:admin1_code":"35",
    "gn:asciiname":"Cobanlar",
    "gn:country_code":"TR",
    "gn:dem":579,
    "gn:feature_class":"P",
    "gn:feature_code":"PPL",
    "gn:name":"\u00c7obanlar",
    "gn:population":0,
    "gn:timezone":"Europe/Istanbul",
    "iso:country":"TR",
    "wof:name":"Cobanlar",
    "wof:placetype":"locality"
},
  "geometry": {"coordinates":[27.24103,39.30686],"type":"Point"}
}