{
  "type": "Feature",
  "properties": {
    "gn:admin1_code":"87",
    "gn:asciiname":"Serenli",
    "gn:country_code":"TR",
    "gn:dem":163,
    "gn:feature_class":"P",
    "gn:feature_code":"PPL",
    "gn:name":"Serenli",
    "gn:population":0,
    "gn:timezone":"Europe/Istanbul",
    "iso:country":"TR",
    "wof:name":"Serenli",
    "wof:placetype":"locality"
},
  "geometry": {"coordinates":[32.44951,41.7357],"type":"Point"}
}