{
  "type": "Feature",
  "properties": {
    "gn:admin1_code":"31",
    "gn:asciiname":"Yukari Demircidibi",
    "gn:country_code":"TR",
    "gn:dem":951,
    "gn:feature_class":"P",
    "gn:feature_code":"PPL",
    "gn:name":"Yukar\u0131 Demircidibi",
    "gn:population":0,
    "gn:timezone":"Europe/Istanbul",
    "iso:country":"TR",
    "name:und_x_variant":[
        "Yukar\u0131 Demircidibi",
        "Demircidibi"
    ],
    "wof:name":"Yukari Demircidibi",
    "wof:placetype":"locality"
},
  "geometry": {"coordinates":[36.27641,36.64502],"type":"Point"}
}