{
  "type": "Feature",
  "properties": {
    "gn:admin1_code":"03",
    "gn:asciiname":"Kulak",
    "gn:country_code":"TR",
    "gn:dem":1318,
    "gn:feature_class":"P",
    "gn:feature_code":"PPL",
    "gn:name":"Kulak",
    "gn:population":0,
    "gn:timezone":"Europe/Istanbul",
    "iso:country":"TR",
    "wof:name":"Kulak",
    "wof:placetype":"locality"
},
  "geometry": {"coordinates":[30.58861,38.38306],"type":"Point"}
}