{
  "type": "Feature",
  "properties": {
    "gn:admin1_code":"25.0",
    "gn:asciiname":"Guneysu",
    "gn:country_code":"TR",
    "gn:dem":1486,
    "gn:feature_class":"P",
    "gn:feature_code":"PPL",
    "gn:name":"G\u00fcneysu",
    "gn:population":0,
    "gn:timezone":"Europe/Istanbul",
    "iso:country":"TR",
    "name:und_x_variant":[
        "G\u00fcneysu",
        "M\u0131rkans"
    ],
    "wof:name":"Guneysu",
    "wof:placetype":"locality"
},
  "geometry": {"coordinates":[40.59629,40.4244],"type":"Point"}
}