{
  "type": "Feature",
  "properties": {
    "gn:country":"TR",
    "gn:fcode":"PPL",
    "gn:population":5327,
    "iso:country":"TR",
    "name:ara_x_preferred":[
        "\u0645\u0627\u0646\u064a\u0627\u0633"
    ],
    "name:ast_x_preferred":[
        "Manyas"
    ],
    "name:cat_x_preferred":[
        "Manyas"
    ],
    "name:ceb_x_preferred":[
        "Manyas \u0130l\u00e7esi"
    ],
    "name:che_x_preferred":[
        "\u041c\u0430\u043d\u0439\u0430\u0441"
    ],
    "name:deu_x_preferred":[
        "Manyas"
    ],
    "name:eng_x_preferred":[
        "Manyas"
    ],
    "name:fas_x_preferred":[
        "\u0645\u0627\u0646\u06cc\u0627\u0633"
    ],
    "name:fra_x_preferred":[
        "Manyas"
    ],
    "name:hun_x_preferred":[
        "Manyas"
    ],
    "name:ita_x_preferred":[
        "Distretto di Manyas"
    ],
    "name:mrj_x_preferred":[
        "\u041c\u0430\u043d\u044c\u044f\u0441"
    ],
    "name:msa_x_preferred":[
        "Manyas"
    ],
    "name:nan_x_preferred":[
        "Manyas"
    ],
    "name:nld_x_preferred":[
        "Manyas"
    ],
    "name:nob_x_preferred":[
        "Manyas"
    ],
    "name:rus_x_preferred":[
        "\u041c\u0430\u043d\u044c\u044f\u0441"
    ],
    "name:swa_x_preferred":[
        "Manyas"
    ],
    "name:tat_x_preferred":[
        "\u041c\u0430\u043d\u044c\u044f\u0441"
    ],
    "name:tur_x_preferred":[
        "Manyas"
    ],
    "name:ukr_x_preferred":[
        "\u041c\u0430\u043d\u044c\u044f\u0441"
    ],
    "name:und_x_variant":[
        "Maltepe"
    ],
    "name:urd_x_preferred":[
        "\u0645\u0627\u0646\u06cc\u0627\u0633"
    ],
    "name:vie_x_preferred":[
        "Manyas"
    ],
    "qs:name":"Manyas",
    "qs:name_adm0":"Turkey",
    "qs:name_adm1":"Bal\u0131kesir",
    "qs:photos_9k":1,
    "qs:photos_9r":1,
    "qs:photos_all":1,
    "qs:photos_sr":0,
    "qs:placetype":"Town",
    "qs:pop_sr":"5",
    "wd:wordcount":69,
    "wof:name":"Manyas",
    "wof:placetype":"locality",
    "wof:population":5327
},
  "geometry": {"coordinates":[27.97,40.04639],"type":"Point"}
}