{
  "type": "Feature",
  "properties": {
    "gn:admin1_code":"44",
    "gn:asciiname":"Kazanc",
    "gn:country_code":"TR",
    "gn:dem":975,
    "gn:feature_class":"P",
    "gn:feature_code":"PPL",
    "gn:name":"Kazan\u00e7",
    "gn:population":0,
    "gn:timezone":"Europe/Istanbul",
    "iso:country":"TR",
    "name:und_x_variant":[
        "Horan",
        "Kazan\u00e7"
    ],
    "wof:name":"Kazanc",
    "wof:placetype":"locality"
},
  "geometry": {"coordinates":[38.55351,38.78645],"type":"Point"}
}