{
  "type": "Feature",
  "properties": {
    "gn:admin1_code":"58",
    "gn:asciiname":"Dumluca",
    "gn:country_code":"TR",
    "gn:dem":1717,
    "gn:feature_class":"P",
    "gn:feature_code":"PPL",
    "gn:name":"Dumluca",
    "gn:population":0,
    "gn:timezone":"Europe/Istanbul",
    "iso:country":"TR",
    "name:und_x_variant":[
        "Dumbuca",
        "Dumluca"
    ],
    "wof:name":"Dumluca",
    "wof:placetype":"locality"
},
  "geometry": {"coordinates":[38.00886,39.35615],"type":"Point"}
}