{
  "type": "Feature",
  "properties": {
    "gn:admin1_code":"91.0",
    "gn:asciiname":"Goztepe",
    "gn:country_code":"TR",
    "gn:dem":215,
    "gn:feature_class":"P",
    "gn:feature_code":"PPL",
    "gn:name":"G\u00f6ztepe",
    "gn:population":0,
    "gn:timezone":"Europe/Istanbul",
    "iso:country":"TR",
    "wof:name":"Goztepe",
    "wof:placetype":"locality"
},
  "geometry": {"coordinates":[36.24271,37.35242],"type":"Point"}
}