{
  "type": "Feature",
  "properties": {
    "gn:admin1_code":"58",
    "gn:asciiname":"Gozecik",
    "gn:country_code":"TR",
    "gn:dem":1366,
    "gn:feature_class":"P",
    "gn:feature_code":"PPL",
    "gn:name":"G\u00f6zecik",
    "gn:population":0,
    "gn:timezone":"Europe/Istanbul",
    "iso:country":"TR",
    "name:tur_x_preferred":[
        "G\u00f6zecik"
    ],
    "wof:name":"Gozecik",
    "wof:placetype":"locality"
},
  "geometry": {"coordinates":[38.12355,39.25062],"type":"Point"}
}