{
  "type": "Feature",
  "properties": {
    "gn:admin1_code":"50",
    "gn:asciiname":"Ogulkaya",
    "gn:country_code":"TR",
    "gn:dem":942,
    "gn:feature_class":"P",
    "gn:feature_code":"PPL",
    "gn:name":"O\u011fulkaya",
    "gn:population":0,
    "gn:timezone":"Europe/Istanbul",
    "iso:country":"TR",
    "name:und_x_variant":[
        "O\u011fulkaya",
        "Cirikler"
    ],
    "wof:name":"Ogulkaya",
    "wof:placetype":"locality"
},
  "geometry": {"coordinates":[34.36991,38.74815],"type":"Point"}
}