{
  "type": "Feature",
  "properties": {
    "gn:admin1_code":"25",
    "gn:asciiname":"Kirikpinar",
    "gn:country_code":"TR",
    "gn:dem":1786,
    "gn:feature_class":"P",
    "gn:feature_code":"PPL",
    "gn:name":"K\u0131r\u0131kp\u0131nar",
    "gn:population":0,
    "gn:timezone":"Europe/Istanbul",
    "iso:country":"TR",
    "name:tur_x_preferred":[
        "K\u0131r\u0131kp\u0131nar"
    ],
    "name:und_x_variant":[
        "K\u0131rkp\u0131nar",
        "Mirgehil"
    ],
    "wof:name":"Kirikpinar",
    "wof:placetype":"locality"
},
  "geometry": {"coordinates":[42.44181,39.60829],"type":"Point"}
}