{
  "type": "Feature",
  "properties": {
    "gn:admin1_code":"14",
    "gn:asciiname":"Ayazlar",
    "gn:country_code":"TR",
    "gn:dem":769,
    "gn:feature_class":"P",
    "gn:feature_code":"PPL",
    "gn:name":"Ayazlar",
    "gn:population":0,
    "gn:timezone":"Europe/Istanbul",
    "iso:country":"TR",
    "wof:name":"Ayazlar",
    "wof:placetype":"locality"
},
  "geometry": {"coordinates":[31.79799,40.7753],"type":"Point"}
}