{
  "type": "Feature",
  "properties": {
    "gn:admin1_code":"57.0",
    "gn:asciiname":"Dagkoy",
    "gn:country_code":"TR",
    "gn:dem":762,
    "gn:feature_class":"P",
    "gn:feature_code":"PPL",
    "gn:name":"Da\u011fk\u00f6y",
    "gn:population":0,
    "gn:timezone":"Europe/Istanbul",
    "iso:country":"TR",
    "name:tur_x_preferred":[
        "Da\u011fk\u00f6y"
    ],
    "wof:name":"Dagkoy",
    "wof:placetype":"locality"
},
  "geometry": {"coordinates":[35.23042,41.54686],"type":"Point"}
}