{
  "type": "Feature",
  "properties": {
    "gn:admin1_code":"34",
    "gn:asciiname":"Sinekli",
    "gn:country_code":"TR",
    "gn:dem":136,
    "gn:feature_class":"P",
    "gn:feature_code":"PPL",
    "gn:name":"Sinekli",
    "gn:population":0,
    "gn:timezone":"Europe/Istanbul",
    "iso:country":"TR",
    "name:tur_x_preferred":[
        "Sinekli"
    ],
    "wof:name":"Sinekli",
    "wof:placetype":"locality"
},
  "geometry": {"coordinates":[29.67136,41.07771],"type":"Point"}
}