{
  "type": "Feature",
  "properties": {
    "gn:admin1_code":"35",
    "gn:asciiname":"Kaplan",
    "gn:country_code":"TR",
    "gn:dem":553,
    "gn:feature_class":"P",
    "gn:feature_code":"PPL",
    "gn:name":"Kaplan",
    "gn:population":0,
    "gn:timezone":"Europe/Istanbul",
    "iso:country":"TR",
    "name:und_x_variant":[
        "Kaplank\u00f6y",
        "Kaplan"
    ],
    "wof:name":"Kaplan",
    "wof:placetype":"locality"
},
  "geometry": {"coordinates":[26.95969,39.23587],"type":"Point"}
}