{
  "type": "Feature",
  "properties": {
    "gn:admin1_code":"35",
    "gn:asciiname":"Kaplan",
    "gn:country_code":"TR",
    "gn:dem":553,
    "gn:feature_class":"P",
    "gn:feature_code":"PPL",
    "gn:name":"Kaplan",
    "gn:population":0,
    "gn:timezone":"Europe/Istanbul",
    "iso:country":"TR",
    "name:ceb_x_preferred":[
        "Kaplan"
    ],
    "name:ces_x_preferred":[
        "Kaplan"
    ],
    "name:deu_x_preferred":[
        "Kaplan"
    ],
    "name:fas_x_preferred":[
        "\u06a9\u0627\u067e\u0644\u0627\u0646"
    ],
    "name:fin_x_preferred":[
        "Kaplan"
    ],
    "name:fra_x_preferred":[
        "Kaplan"
    ],
    "name:heb_x_preferred":[
        "\u05e7\u05e4\u05dc\u05df"
    ],
    "name:ita_x_preferred":[
        "Kaplan"
    ],
    "name:jpn_x_preferred":[
        "\u30ab\u30d7\u30e9\u30f3"
    ],
    "name:kor_x_preferred":[
        "\uce90\ud50c\ub7f0"
    ],
    "name:nld_x_preferred":[
        "Kaplan"
    ],
    "name:pol_x_preferred":[
        "Kaplan"
    ],
    "name:por_x_preferred":[
        "Kaplan"
    ],
    "name:ron_x_preferred":[
        "Kaplan"
    ],
    "name:rus_x_preferred":[
        "\u041a\u0430\u043f\u043b\u0430\u043d"
    ],
    "name:slk_x_preferred":[
        "Kaplan"
    ],
    "name:slv_x_preferred":[
        "Kaplan"
    ],
    "name:spa_x_preferred":[
        "Kaplan"
    ],
    "name:swe_x_preferred":[
        "Kaplan"
    ],
    "name:tur_x_preferred":[
        "Kaplan"
    ],
    "name:ukr_x_preferred":[
        "\u041a\u0430\u043f\u043b\u0430\u043d"
    ],
    "name:und_x_variant":[
        "Kaplank\u00f6y"
    ],
    "wof:name":"Kaplan",
    "wof:placetype":"locality"
},
  "geometry": {"coordinates":[26.95969,39.23587],"type":"Point"}
}