{
  "type": "Feature",
  "properties": {
    "gn:admin1_code":"45",
    "gn:asciiname":"Bagcili",
    "gn:country_code":"TR",
    "gn:dem":349,
    "gn:feature_class":"P",
    "gn:feature_code":"PPL",
    "gn:name":"Bagcili",
    "gn:population":0,
    "gn:timezone":"Europe/Istanbul",
    "iso:country":"TR",
    "name:tur_x_preferred":[
        "Bagcili"
    ],
    "name:und_x_variant":[
        "Ya\u011fc\u0131l\u0131",
        "Ya\u011fc\u0131"
    ],
    "wof:name":"Bagcili",
    "wof:placetype":"locality"
},
  "geometry": {"coordinates":[27.66385,39.32917],"type":"Point"}
}