{
  "type": "Feature",
  "properties": {
    "gn:admin1_code":"71",
    "gn:asciiname":"Huseyinler",
    "gn:country_code":"TR",
    "gn:dem":1334,
    "gn:feature_class":"P",
    "gn:feature_code":"PPL",
    "gn:name":"H\u00fcseyinler",
    "gn:population":0,
    "gn:timezone":"Europe/Istanbul",
    "iso:country":"TR",
    "wof:name":"Huseyinler",
    "wof:placetype":"locality"
},
  "geometry": {"coordinates":[31.91727,37.68511],"type":"Point"}
}