{
  "type": "Feature",
  "properties": {
    "gn:admin1_code":"23",
    "gn:asciiname":"Balan",
    "gn:country_code":"TR",
    "gn:dem":1161,
    "gn:feature_class":"P",
    "gn:feature_code":"PPL",
    "gn:name":"Balan",
    "gn:population":0,
    "gn:timezone":"Europe/Istanbul",
    "iso:country":"TR",
    "name:bul_x_preferred":[
        "\u0411\u0430\u043b\u0430\u043d"
    ],
    "name:cat_x_preferred":[
        "Balan"
    ],
    "name:ceb_x_preferred":[
        "Balan"
    ],
    "name:ces_x_preferred":[
        "Balan"
    ],
    "name:deu_x_preferred":[
        "Balan"
    ],
    "name:epo_x_preferred":[
        "Balan"
    ],
    "name:fas_x_preferred":[
        "\u0628\u0627\u0644\u0627\u0646"
    ],
    "name:fra_x_preferred":[
        "Balan"
    ],
    "name:heb_x_preferred":[
        "\u05d1\u05dc\u05df"
    ],
    "name:hun_x_preferred":[
        "Balan"
    ],
    "name:ita_x_preferred":[
        "Balan"
    ],
    "name:nds_x_preferred":[
        "Balan"
    ],
    "name:nld_x_preferred":[
        "Balan"
    ],
    "name:pol_x_preferred":[
        "Balan"
    ],
    "name:por_x_preferred":[
        "Balan"
    ],
    "name:ron_x_preferred":[
        "Balan"
    ],
    "name:rus_x_preferred":[
        "\u0411\u0430\u043b\u0430\u043d"
    ],
    "name:scn_x_preferred":[
        "Balan"
    ],
    "name:slk_x_preferred":[
        "Balan"
    ],
    "name:spa_x_preferred":[
        "Balan"
    ],
    "name:srp_x_preferred":[
        "\u0411\u0430\u043b\u0430\u043d"
    ],
    "name:swe_x_preferred":[
        "Balan"
    ],
    "name:tur_x_preferred":[
        "G\u00f6lk\u00f6y"
    ],
    "name:ukr_x_preferred":[
        "\u0411\u0430\u043b\u0430\u043d"
    ],
    "name:und_x_variant":[
        "G\u00f6k\u00e7e"
    ],
    "wof:name":"Balan",
    "wof:placetype":"locality"
},
  "geometry": {"coordinates":[39.07124,38.55293],"type":"Point"}
}