{
  "type": "Feature",
  "properties": {
    "gn:admin1_code":"8.0",
    "gn:asciiname":"Saribulut",
    "gn:country_code":"TR",
    "gn:dem":2220,
    "gn:feature_class":"P",
    "gn:feature_code":"PPL",
    "gn:name":"Sar\u0131bulut",
    "gn:population":0,
    "gn:timezone":"Europe/Istanbul",
    "iso:country":"TR",
    "wof:name":"Saribulut",
    "wof:placetype":"locality"
},
  "geometry": {"coordinates":[41.33935,40.9751],"type":"Point"}
}