{
  "type": "Feature",
  "properties": {
    "gn:admin1_code":"43",
    "gn:asciiname":"Cayca",
    "gn:country_code":"TR",
    "gn:dem":977,
    "gn:feature_class":"P",
    "gn:feature_code":"PPL",
    "gn:name":"\u00c7ayca",
    "gn:population":0,
    "gn:timezone":"Europe/Istanbul",
    "iso:country":"TR",
    "name:tur_x_preferred":[
        "\u00c7ayca"
    ],
    "wof:name":"Cayca",
    "wof:placetype":"locality"
},
  "geometry": {"coordinates":[30.14517,39.42244],"type":"Point"}
}