{
  "type": "Feature",
  "properties": {
    "gn:admin1_code":"57.0",
    "gn:asciiname":"Demirkoy",
    "gn:country_code":"TR",
    "gn:dem":138,
    "gn:feature_class":"P",
    "gn:feature_code":"PPL",
    "gn:name":"Demirk\u00f6y",
    "gn:population":0,
    "gn:timezone":"Europe/Istanbul",
    "iso:country":"TR",
    "name:tur_x_preferred":[
        "Demirk\u00f6y"
    ],
    "name:tur_x_variant":[
        "Demirci"
    ],
    "wof:name":"Demirkoy",
    "wof:placetype":"locality"
},
  "geometry": {"coordinates":[35.06591,41.94115],"type":"Point"}
}