{
  "type": "Feature",
  "properties": {
    "gn:admin1_code":"25.0",
    "gn:asciiname":"Duzkoy",
    "gn:country_code":"TR",
    "gn:dem":1941,
    "gn:feature_class":"P",
    "gn:feature_code":"PPL",
    "gn:name":"D\u00fczk\u00f6y",
    "gn:population":0,
    "gn:timezone":"Europe/Istanbul",
    "iso:country":"TR",
    "name:tur_x_preferred":[
        "D\u00fczk\u00f6y"
    ],
    "wof:name":"Duzkoy",
    "wof:placetype":"locality"
},
  "geometry": {"coordinates":[41.0012,40.55766],"type":"Point"}
}