{
  "type": "Feature",
  "properties": {
    "gn:admin1_code":"32",
    "gn:asciiname":"Tasobasi",
    "gn:country_code":"TR",
    "gn:dem":260,
    "gn:feature_class":"P",
    "gn:feature_code":"PPL",
    "gn:name":"Ta\u015fobas\u0131",
    "gn:population":0,
    "gn:timezone":"Europe/Istanbul",
    "iso:country":"TR",
    "name:ceb_x_preferred":[
        "Ta\u015fobas\u0131"
    ],
    "name:msa_x_preferred":[
        "Ta\u015fobas\u0131"
    ],
    "name:tur_x_preferred":[
        "Ta\u015fobas\u0131"
    ],
    "name:vie_x_preferred":[
        "Ta\u015fobas\u0131"
    ],
    "wof:name":"Tasobasi",
    "wof:placetype":"locality"
},
  "geometry": {"coordinates":[34.92961,37.09005],"type":"Point"}
}