{
  "type": "Feature",
  "properties": {
    "gn:admin1_code":"21",
    "gn:asciiname":"Kagitli",
    "gn:country_code":"TR",
    "gn:dem":739,
    "gn:feature_class":"P",
    "gn:feature_code":"PPL",
    "gn:name":"Ka\u011f\u0131tl\u0131",
    "gn:population":0,
    "gn:timezone":"Europe/Istanbul",
    "iso:country":"TR",
    "name:tur_x_preferred":[
        "Ka\u011f\u0131tl\u0131"
    ],
    "name:und_x_variant":[
        "K\u00e2atl\u0131",
        "K\u00e2\u011f\u0131dl\u0131"
    ],
    "wof:name":"Kagitli",
    "wof:placetype":"locality"
},
  "geometry": {"coordinates":[40.52384,38.03519],"type":"Point"}
}