{
  "type": "Feature",
  "properties": {
    "gn:admin1_code":"80.0",
    "gn:asciiname":"Bazgyur",
    "gn:country_code":"TR",
    "gn:dem":807,
    "gn:feature_class":"P",
    "gn:feature_code":"PPL",
    "gn:name":"Bazgyur",
    "gn:population":0,
    "gn:timezone":"Europe/Istanbul",
    "iso:country":"TR",
    "name:und_x_variant":[
        "Bazg\u00fcr"
    ],
    "wof:name":"Bazgyur",
    "wof:placetype":"locality"
},
  "geometry": {"coordinates":[41.64,37.38611],"type":"Point"}
}