{
  "type": "Feature",
  "properties": {
    "gn:admin1_code":"62",
    "gn:asciiname":"Hasangazi",
    "gn:country_code":"TR",
    "gn:dem":1732,
    "gn:feature_class":"P",
    "gn:feature_code":"PPL",
    "gn:name":"Hasangazi",
    "gn:population":0,
    "gn:timezone":"Europe/Istanbul",
    "iso:country":"TR",
    "name:ceb_x_preferred":[
        "Hasangazi"
    ],
    "name:msa_x_preferred":[
        "Hasangazi"
    ],
    "name:tur_x_preferred":[
        "Hasangazi"
    ],
    "name:und_x_variant":[
        "Hasangazi Mezraas\u0131",
        "Hasangazi"
    ],
    "name:vie_x_preferred":[
        "Hasangazi"
    ],
    "wof:name":"Hasangazi",
    "wof:placetype":"locality"
},
  "geometry": {"coordinates":[40.00304000000001,39.46022],"type":"Point"}
}