{
  "type": "Feature",
  "properties": {
    "gn:admin1_code":"10",
    "gn:asciiname":"Tepeoba",
    "gn:country_code":"TR",
    "gn:dem":159,
    "gn:feature_class":"P",
    "gn:feature_code":"PPL",
    "gn:name":"Tepeoba",
    "gn:population":0,
    "gn:timezone":"Europe/Istanbul",
    "iso:country":"TR",
    "name:tur_x_preferred":[
        "Tepeoba"
    ],
    "wof:name":"Tepeoba",
    "wof:placetype":"locality"
},
  "geometry": {"coordinates":[27.10657,39.60314],"type":"Point"}
}