{
  "type": "Feature",
  "properties": {
    "gn:admin1_code":"84",
    "gn:asciiname":"Cukurayva",
    "gn:country_code":"TR",
    "gn:dem":1804,
    "gn:feature_class":"P",
    "gn:feature_code":"PPL",
    "gn:name":"\u00c7ukurayva",
    "gn:population":0,
    "gn:timezone":"Europe/Istanbul",
    "iso:country":"TR",
    "name:tur_x_preferred":[
        "\u00c7ukurayva"
    ],
    "wof:name":"Cukurayva",
    "wof:placetype":"locality"
},
  "geometry": {"coordinates":[42.9282,40.24602],"type":"Point"}
}