{
  "type": "Feature",
  "properties": {
    "gn:admin1_code":"32",
    "gn:asciiname":"Kotekler",
    "gn:country_code":"TR",
    "gn:dem":1342,
    "gn:feature_class":"P",
    "gn:feature_code":"PPL",
    "gn:name":"K\u00f6tekler",
    "gn:population":0,
    "gn:timezone":"Europe/Istanbul",
    "iso:country":"TR",
    "name:und_x_variant":[
        "\u00c7ar\u0131klaryaylas\u0131",
        "\u00c7ar\u0131klar",
        "K\u00f6tekler"
    ],
    "wof:name":"Kotekler",
    "wof:placetype":"locality"
},
  "geometry": {"coordinates":[33.01285,36.37434],"type":"Point"}
}