{
  "type": "Feature",
  "properties": {
    "gn:admin1_code":"58",
    "gn:asciiname":"Selimiye",
    "gn:country_code":"TR",
    "gn:dem":1684,
    "gn:feature_class":"P",
    "gn:feature_code":"PPL",
    "gn:name":"Selimiye",
    "gn:population":0,
    "gn:timezone":"Europe/Istanbul",
    "iso:country":"TR",
    "name:deu_x_preferred":[
        "Selimiye"
    ],
    "name:ell_x_preferred":[
        "\u03a3\u03b5\u03bb\u03b9\u03bc\u03b9\u03b3\u03b9\u03ad"
    ],
    "name:fra_x_preferred":[
        "Selimiye"
    ],
    "name:tur_x_preferred":[
        "Selimiye"
    ],
    "name:und_x_variant":[
        "Alikamber",
        "Alikanber"
    ],
    "wof:name":"Selimiye",
    "wof:placetype":"locality"
},
  "geometry": {"coordinates":[37.68733,39.65324],"type":"Point"}
}