{
  "type": "Feature",
  "properties": {
    "gn:admin1_code":"25",
    "gn:asciiname":"Bellitas",
    "gn:country_code":"TR",
    "gn:dem":1578,
    "gn:feature_class":"P",
    "gn:feature_code":"PPL",
    "gn:name":"Bellita\u015f",
    "gn:population":0,
    "gn:timezone":"Europe/Istanbul",
    "iso:country":"TR",
    "name:und_x_variant":[
        "Harami",
        "Bellita\u015f"
    ],
    "wof:name":"Bellitas",
    "wof:placetype":"locality"
},
  "geometry": {"coordinates":[41.84012,39.30902],"type":"Point"}
}