{
  "type": "Feature",
  "properties": {
    "gn:admin1_code":"39.0",
    "gn:asciiname":"Hasbuga",
    "gn:country_code":"TR",
    "gn:dem":201,
    "gn:feature_class":"P",
    "gn:feature_code":"PPL",
    "gn:name":"Hasbu\u011fa",
    "gn:population":0,
    "gn:timezone":"Europe/Istanbul",
    "iso:country":"TR",
    "name:und_x_variant":[
        "Hasbo\u011fa",
        "Hasbu\u011fa"
    ],
    "wof:name":"Hasbuga",
    "wof:placetype":"locality"
},
  "geometry": {"coordinates":[27.74027,41.51713],"type":"Point"}
}