{
  "type": "Feature",
  "properties": {
    "gn:admin1_code":"28.0",
    "gn:asciiname":"Boncukcukur",
    "gn:country_code":"TR",
    "gn:dem":638,
    "gn:feature_class":"P",
    "gn:feature_code":"PPL",
    "gn:name":"Boncuk\u00e7ukur",
    "gn:population":0,
    "gn:timezone":"Europe/Istanbul",
    "iso:country":"TR",
    "name:tur_x_preferred":[
        "Boncuk\u00e7ukur"
    ],
    "wof:name":"Boncukcukur",
    "wof:placetype":"locality"
},
  "geometry": {"coordinates":[38.80722,40.77744000000001],"type":"Point"}
}