{
  "type": "Feature",
  "properties": {
    "iso:country":"TR",
    "name:tur_x_preferred":[
        "\u0130skenderpa\u015fa"
    ],
    "wof:name":"Iskenderpasa",
    "wof:placetype":"neighbourhood"
},
  "geometry": {"coordinates":[28.94924789654225,41.01370011531093],"type":"Point"}
}