{
  "type": "Feature",
  "properties": {
    "gn:admin1_code":"83.0",
    "gn:asciiname":"Byuyuk-Kyrach",
    "gn:country_code":"TR",
    "gn:dem":503,
    "gn:feature_class":"P",
    "gn:feature_code":"PPL",
    "gn:name":"Byuyuk-Kyrach",
    "gn:population":0,
    "gn:timezone":"Europe/Istanbul",
    "iso:country":"TR",
    "name:und_x_variant":[
        "B\u00fcy\u00fckk\u0131ra\u00e7"
    ],
    "wof:name":"Byuyuk-Kyrach",
    "wof:placetype":"locality"
},
  "geometry": {"coordinates":[37.79361,36.79139],"type":"Point"}
}