{
  "type": "Feature",
  "properties": {
    "gn:admin1_code":"09",
    "gn:asciiname":"Acisu",
    "gn:country_code":"TR",
    "gn:dem":113,
    "gn:feature_class":"P",
    "gn:feature_code":"PPL",
    "gn:name":"Ac\u0131su",
    "gn:population":0,
    "gn:timezone":"Europe/Istanbul",
    "iso:country":"TR",
    "name:tur_x_preferred":[
        "Ac\u0131su"
    ],
    "wof:name":"Acisu",
    "wof:placetype":"locality"
},
  "geometry": {"coordinates":[27.98919,37.56621],"type":"Point"}
}