{
  "type": "Feature",
  "properties": {
    "gn:admin1_code":"17.0",
    "gn:asciiname":"Tepekoy",
    "gn:country_code":"TR",
    "gn:dem":285,
    "gn:feature_class":"P",
    "gn:feature_code":"PPL",
    "gn:name":"Tepek\u00f6y",
    "gn:population":0,
    "gn:timezone":"Europe/Istanbul",
    "iso:country":"TR",
    "name:und_x_variant":[
        "A\u011fritye",
        "Tepek\u00f6y"
    ],
    "wof:name":"Tepekoy",
    "wof:placetype":"locality"
},
  "geometry": {"coordinates":[25.83339,40.19046],"type":"Point"}
}