{
  "type": "Feature",
  "properties": {
    "gn:admin1_code":"21.0",
    "gn:asciiname":"Astal",
    "gn:country_code":"TR",
    "gn:dem":884,
    "gn:feature_class":"P",
    "gn:feature_code":"PPL",
    "gn:name":"Astal",
    "gn:population":0,
    "gn:timezone":"Europe/Istanbul",
    "iso:country":"TR",
    "name:ita_x_preferred":[
        "Astal"
    ],
    "name:jpn_x_preferred":[
        "\u8f1d\u6c34\u6676\u4f1d\u8aac\u30a2\u30b9\u30bf\u30eb"
    ],
    "wof:name":"Astal",
    "wof:placetype":"locality"
},
  "geometry": {"coordinates":[40.80092,38.51743],"type":"Point"}
}