{
  "type": "Feature",
  "properties": {
    "gn:admin1_code":"73",
    "gn:asciiname":"Pinarcik",
    "gn:country_code":"TR",
    "gn:dem":1529,
    "gn:feature_class":"P",
    "gn:feature_code":"PPL",
    "gn:name":"P\u0131narc\u0131k",
    "gn:population":0,
    "gn:timezone":"Europe/Istanbul",
    "iso:country":"TR",
    "name:und_x_variant":[
        "Germegen",
        "P\u0131narc\u0131k"
    ],
    "wof:name":"Pinarcik",
    "wof:placetype":"locality"
},
  "geometry": {"coordinates":[34.67607,38.13513],"type":"Point"}
}