{
  "type": "Feature",
  "properties": {
    "gn:admin1_code":"25.0",
    "gn:asciiname":"Gokcedere",
    "gn:country_code":"TR",
    "gn:dem":1499,
    "gn:feature_class":"P",
    "gn:feature_code":"PPL",
    "gn:name":"G\u00f6k\u00e7edere",
    "gn:population":0,
    "gn:timezone":"Europe/Istanbul",
    "iso:country":"TR",
    "name:tur_x_preferred":[
        "G\u00f6k\u00e7edere"
    ],
    "wof:name":"Gokcedere",
    "wof:placetype":"locality"
},
  "geometry": {"coordinates":[41.98938,40.6114],"type":"Point"}
}