{
  "type": "Feature",
  "properties": {
    "gn:admin1_code":"5.0",
    "gn:asciiname":"Alabedir",
    "gn:country_code":"TR",
    "gn:dem":609,
    "gn:feature_class":"P",
    "gn:feature_code":"PPL",
    "gn:name":"Alabedir",
    "gn:population":0,
    "gn:timezone":"Europe/Istanbul",
    "iso:country":"TR",
    "wof:name":"Alabedir",
    "wof:placetype":"locality"
},
  "geometry": {"coordinates":[35.6527,40.69122],"type":"Point"}
}