{
  "type": "Feature",
  "properties": {
    "gn:admin1_code":"58",
    "gn:asciiname":"Cakilpinar",
    "gn:country_code":"TR",
    "gn:dem":1622,
    "gn:feature_class":"P",
    "gn:feature_code":"PPL",
    "gn:name":"\u00c7ak\u0131lp\u0131nar",
    "gn:population":0,
    "gn:timezone":"Europe/Istanbul",
    "iso:country":"TR",
    "name:und_x_variant":[
        "\u00c7a\u011f\u0131lt\u0131p\u0131nar",
        "\u00c7enillip\u0131nar K\u00f6y\u00fc",
        "Celillip\u0131nar",
        "\u00c7enillip\u0131nar",
        "\u00c7ak\u0131lp\u0131nar"
    ],
    "wof:name":"Cakilpinar",
    "wof:placetype":"locality"
},
  "geometry": {"coordinates":[37.25391,39.48716],"type":"Point"}
}