{
  "type": "Feature",
  "properties": {
    "gn:admin1_code":"55.0",
    "gn:asciiname":"Guvenli",
    "gn:country_code":"TR",
    "gn:dem":578,
    "gn:feature_class":"P",
    "gn:feature_code":"PPL",
    "gn:name":"G\u00fcvenli",
    "gn:population":0,
    "gn:timezone":"Europe/Istanbul",
    "iso:country":"TR",
    "name:tur_x_preferred":[
        "G\u00fcvenli"
    ],
    "name:tur_x_variant":[
        "Adilli"
    ],
    "wof:name":"Guvenli",
    "wof:placetype":"locality"
},
  "geometry": {"coordinates":[35.6382,41.511],"type":"Point"}
}