{
  "type": "Feature",
  "properties": {
    "gn:admin1_code":"65",
    "gn:asciiname":"Guroluk",
    "gn:country_code":"TR",
    "gn:dem":2261,
    "gn:feature_class":"P",
    "gn:feature_code":"PPL",
    "gn:name":"G\u00fcroluk",
    "gn:population":0,
    "gn:timezone":"Europe/Istanbul",
    "iso:country":"TR",
    "name:und_x_variant":[
        "Eliveyan",
        "Elelyan",
        "G\u00fcroluk"
    ],
    "wof:name":"Guroluk",
    "wof:placetype":"locality"
},
  "geometry": {"coordinates":[44.03917,38.08278],"type":"Point"}
}