{
  "type": "Feature",
  "properties": {
    "iso:country":"TR",
    "name:eng_x_preferred":[
        "Yolcati"
    ],
    "name:tur_x_preferred":[
        "Yolcat\u0131"
    ],
    "wof:name":"Yolcati",
    "wof:placetype":"neighbourhood"
},
  "geometry": {"coordinates":[28.12677417656862,41.13121249400463],"type":"Point"}
}