{
  "type": "Feature",
  "properties": {
    "gn:admin1_code":"82.0",
    "gn:asciiname":"Yaylaoren",
    "gn:country_code":"TR",
    "gn:dem":988,
    "gn:feature_class":"P",
    "gn:feature_code":"PPL",
    "gn:name":"Yayla\u00f6ren",
    "gn:population":0,
    "gn:timezone":"Europe/Istanbul",
    "iso:country":"TR",
    "name:und_x_variant":[
        "Bucura",
        "Yayla\u00f6ren"
    ],
    "wof:name":"Yaylaoren",
    "wof:placetype":"locality"
},
  "geometry": {"coordinates":[33.50259,40.89564],"type":"Point"}
}