{
  "type": "Feature",
  "properties": {
    "gn:admin1_code":"91",
    "gn:asciiname":"Yukari Karadere",
    "gn:country_code":"TR",
    "gn:dem":951,
    "gn:feature_class":"P",
    "gn:feature_code":"PPL",
    "gn:name":"Yukar\u0131 Karadere",
    "gn:population":0,
    "gn:timezone":"Europe/Istanbul",
    "iso:country":"TR",
    "name:tur_x_preferred":[
        "Yukar\u0131 Karadere"
    ],
    "name:und_x_variant":[
        "Yukar\u0131 Kardere",
        "Yukar\u0131 Karderesi",
        "Yukar\u0131karadere"
    ],
    "wof:name":"Yukari Karadere",
    "wof:placetype":"locality"
},
  "geometry": {"coordinates":[36.633,37.23018],"type":"Point"}
}