{
  "type": "Feature",
  "properties": {
    "gn:admin1_code":"19.0",
    "gn:asciiname":"Kabakci",
    "gn:country_code":"TR",
    "gn:dem":1422,
    "gn:feature_class":"P",
    "gn:feature_code":"PPL",
    "gn:name":"Kabak\u00e7\u0131",
    "gn:population":0,
    "gn:timezone":"Europe/Istanbul",
    "iso:country":"TR",
    "name:tur_x_preferred":[
        "Kabak\u00e7\u0131"
    ],
    "name:und_x_variant":[
        "Pelit Yaylas\u0131"
    ],
    "wof:name":"Kabakci",
    "wof:placetype":"locality"
},
  "geometry": {"coordinates":[34.33603,41.1441],"type":"Point"}
}