{
  "type": "Feature",
  "properties": {
    "gn:admin1_code":"25.0",
    "gn:asciiname":"Saksi",
    "gn:country_code":"TR",
    "gn:dem":1826,
    "gn:feature_class":"P",
    "gn:feature_code":"PPL",
    "gn:name":"Saks\u0131",
    "gn:population":0,
    "gn:timezone":"Europe/Istanbul",
    "iso:country":"TR",
    "name:und_x_variant":[
        "Saks\u0131",
        "Pertek"
    ],
    "wof:name":"Saksi",
    "wof:placetype":"locality"
},
  "geometry": {"coordinates":[41.47369000000001,40.00206],"type":"Point"}
}