{
  "type": "Feature",
  "properties": {
    "gn:admin1_code":"58.0",
    "gn:asciiname":"Haciilyas",
    "gn:country_code":"TR",
    "gn:dem":1268,
    "gn:feature_class":"P",
    "gn:feature_code":"PPL",
    "gn:name":"Hac\u0131ilyas",
    "gn:population":0,
    "gn:timezone":"Europe/Istanbul",
    "iso:country":"TR",
    "name:tur_x_preferred":[
        "Hac\u0131ilyas"
    ],
    "name:und_x_variant":[
        "Haci\u0131lyas"
    ],
    "wof:name":"Haciilyas",
    "wof:placetype":"locality"
},
  "geometry": {"coordinates":[37.86404,40.31293],"type":"Point"}
}