{
  "type": "Feature",
  "properties": {
    "gn:admin1_code":"59.0",
    "gn:asciiname":"Hore",
    "gn:country_code":"TR",
    "gn:dem":10,
    "gn:feature_class":"P",
    "gn:feature_code":"PPL",
    "gn:name":"Hore",
    "gn:population":0,
    "gn:timezone":"Europe/Istanbul",
    "iso:country":"TR",
    "name:und_x_variant":[
        "Hora",
        "Ho\u015fg\u00f6r",
        "Hore",
        "Ho\u015fk\u00f6y"
    ],
    "wof:name":"Hore",
    "wof:placetype":"locality"
},
  "geometry": {"coordinates":[27.31392,40.71289],"type":"Point"}
}