{
  "type": "Feature",
  "properties": {
    "gn:admin1_code":"41.0",
    "gn:asciiname":"Pirceler",
    "gn:country_code":"TR",
    "gn:dem":184,
    "gn:feature_class":"P",
    "gn:feature_code":"PPL",
    "gn:name":"Pirceler",
    "gn:population":0,
    "gn:timezone":"Europe/Istanbul",
    "iso:country":"TR",
    "name:tur_x_preferred":[
        "Pirceler"
    ],
    "wof:name":"Pirceler",
    "wof:placetype":"locality"
},
  "geometry": {"coordinates":[30.08627000000001,40.89685],"type":"Point"}
}