{
  "type": "Feature",
  "properties": {
    "gn:admin1_code":"21",
    "gn:asciiname":"Tasdam",
    "gn:country_code":"TR",
    "gn:dem":775,
    "gn:feature_class":"P",
    "gn:feature_code":"PPL",
    "gn:name":"Ta\u015fdam",
    "gn:population":0,
    "gn:timezone":"Europe/Istanbul",
    "iso:country":"TR",
    "name:und_x_variant":[
        "Satyan",
        "Ta\u015fdam",
        "Satiyan"
    ],
    "wof:name":"Tasdam",
    "wof:placetype":"locality"
},
  "geometry": {"coordinates":[40.02266,38.14196],"type":"Point"}
}