{
  "type": "Feature",
  "properties": {
    "gn:admin1_code":"32",
    "gn:asciiname":"Alanyali",
    "gn:country_code":"TR",
    "gn:dem":1331,
    "gn:feature_class":"P",
    "gn:feature_code":"PPL",
    "gn:name":"Alanyal\u0131",
    "gn:population":0,
    "gn:timezone":"Europe/Istanbul",
    "iso:country":"TR",
    "name:tur_x_preferred":[
        "Alanyal\u0131"
    ],
    "name:tur_x_variant":[
        "Alaiye"
    ],
    "wof:name":"Alanyali",
    "wof:placetype":"locality"
},
  "geometry": {"coordinates":[34.51239,37.09045],"type":"Point"}
}