{
  "type": "Feature",
  "properties": {
    "gn:admin1_code":"71.0",
    "gn:asciiname":"Yesiltekke",
    "gn:country_code":"TR",
    "gn:dem":1411,
    "gn:feature_class":"P",
    "gn:feature_code":"PPL",
    "gn:name":"Ye\u015filtekke",
    "gn:population":0,
    "gn:timezone":"Europe/Istanbul",
    "iso:country":"TR",
    "name:tur_x_preferred":[
        "Ye\u015filtekke"
    ],
    "name:und_x_variant":[
        "\u00c7ukur \u00c7imentekke",
        "Ak\u00e7akaya"
    ],
    "wof:name":"Yesiltekke",
    "wof:placetype":"locality"
},
  "geometry": {"coordinates":[32.21191,37.50222],"type":"Point"}
}