{
  "type": "Feature",
  "properties": {
    "gn:admin1_code":"81",
    "gn:asciiname":"Dikilitas",
    "gn:country_code":"TR",
    "gn:dem":95,
    "gn:feature_class":"P",
    "gn:feature_code":"PPL",
    "gn:name":"Dikilita\u015f",
    "gn:population":0,
    "gn:timezone":"Europe/Istanbul",
    "iso:country":"TR",
    "name:und_x_variant":[
        "Ortak\u00f6y",
        "Dikili",
        "Dikilita\u015f"
    ],
    "wof:name":"Dikilitas",
    "wof:placetype":"locality"
},
  "geometry": {"coordinates":[35.714,37.36256],"type":"Point"}
}