{
  "type": "Feature",
  "properties": {
    "gn:admin1_code":"19.0",
    "gn:asciiname":"Tugcu",
    "gn:country_code":"TR",
    "gn:dem":792,
    "gn:feature_class":"P",
    "gn:feature_code":"PPL",
    "gn:name":"Tu\u011fcu",
    "gn:population":0,
    "gn:timezone":"Europe/Istanbul",
    "iso:country":"TR",
    "wof:name":"Tugcu",
    "wof:placetype":"locality"
},
  "geometry": {"coordinates":[34.32155,40.18726],"type":"Point"}
}