{
  "type": "Feature",
  "properties": {
    "gn:admin1_code":"45",
    "gn:asciiname":"Akkecili",
    "gn:country_code":"TR",
    "gn:dem":626,
    "gn:feature_class":"P",
    "gn:feature_code":"PPL",
    "gn:name":"Akke\u00e7ili",
    "gn:population":0,
    "gn:timezone":"Europe/Istanbul",
    "iso:country":"TR",
    "name:tur_x_preferred":[
        "Akke\u00e7ili"
    ],
    "name:tur_x_variant":[
        "Macarlar"
    ],
    "wof:name":"Akkecili",
    "wof:placetype":"locality"
},
  "geometry": {"coordinates":[28.16566,38.69212],"type":"Point"}
}