{
  "type": "Feature",
  "properties": {
    "gn:admin1_code":"40.0",
    "gn:asciiname":"Yukari Kizilcaali",
    "gn:country_code":"TR",
    "gn:dem":815,
    "gn:feature_class":"P",
    "gn:feature_code":"PPL",
    "gn:name":"Yukar\u0131 K\u0131z\u0131lcaal\u0131",
    "gn:population":0,
    "gn:timezone":"Europe/Istanbul",
    "iso:country":"TR",
    "wof:name":"Yukari Kizilcaali",
    "wof:placetype":"locality"
},
  "geometry": {"coordinates":[34.23798,39.70474],"type":"Point"}
}