{
  "type": "Feature",
  "properties": {
    "gn:admin1_code":"55.0",
    "gn:asciiname":"Darbogaz",
    "gn:country_code":"TR",
    "gn:dem":360,
    "gn:feature_class":"P",
    "gn:feature_code":"PPL",
    "gn:name":"Darbo\u011faz",
    "gn:population":0,
    "gn:timezone":"Europe/Istanbul",
    "iso:country":"TR",
    "name:und_x_variant":[
        "Darbo\u011fazk\u00f6y\u00fc",
        "Darbo\u011faz"
    ],
    "wof:name":"Darbogaz",
    "wof:placetype":"locality"
},
  "geometry": {"coordinates":[35.9072,41.4353],"type":"Point"}
}