{
  "type": "Feature",
  "properties": {
    "gn:admin1_code":"07",
    "gn:asciiname":"Beldibi",
    "gn:country_code":"TR",
    "gn:dem":521,
    "gn:feature_class":"P",
    "gn:feature_code":"PPL",
    "gn:name":"Beldibi",
    "gn:population":0,
    "gn:timezone":"Europe/Istanbul",
    "iso:country":"TR",
    "name:tur_x_preferred":[
        "Beldibi"
    ],
    "wof:name":"Beldibi",
    "wof:placetype":"locality"
},
  "geometry": {"coordinates":[32.31432,36.44878],"type":"Point"}
}