{
  "type": "Feature",
  "properties": {
    "gn:admin1_code":"63.0",
    "gn:asciiname":"Ekili",
    "gn:country_code":"TR",
    "gn:dem":519,
    "gn:feature_class":"P",
    "gn:feature_code":"PPL",
    "gn:name":"Ekili",
    "gn:population":0,
    "gn:timezone":"Europe/Istanbul",
    "iso:country":"TR",
    "name:tur_x_preferred":[
        "Ekili"
    ],
    "wof:name":"Ekili",
    "wof:placetype":"locality"
},
  "geometry": {"coordinates":[38.40729,37.02448],"type":"Point"}
}