{
  "type": "Feature",
  "properties": {
    "gn:admin1_code":"14.0",
    "gn:asciiname":"Kesenozu",
    "gn:country_code":"TR",
    "gn:dem":806,
    "gn:feature_class":"P",
    "gn:feature_code":"PPL",
    "gn:name":"Kesen\u00f6z\u00fc",
    "gn:population":0,
    "gn:timezone":"Europe/Istanbul",
    "iso:country":"TR",
    "name:und_x_variant":[
        "K\u00f6sen\u00f6z\u00fc",
        "K\u00f6\u015f\u00f6z\u00fc",
        "Kesen\u00f6z\u00fc"
    ],
    "wof:name":"Kesenozu",
    "wof:placetype":"locality"
},
  "geometry": {"coordinates":[31.54712,40.30917],"type":"Point"}
}