{
  "type": "Feature",
  "properties": {
    "gn:admin1_code":"28.0",
    "gn:asciiname":"Babapinar",
    "gn:country_code":"TR",
    "gn:dem":1572,
    "gn:feature_class":"P",
    "gn:feature_code":"PPL",
    "gn:name":"Babap\u0131nar",
    "gn:population":0,
    "gn:timezone":"Europe/Istanbul",
    "iso:country":"TR",
    "name:und_x_variant":[
        "Parak",
        "Babap\u0131nar"
    ],
    "wof:name":"Babapinar",
    "wof:placetype":"locality"
},
  "geometry": {"coordinates":[38.76605,40.34547],"type":"Point"}
}