{
  "type": "Feature",
  "properties": {
    "gn:admin1_code":"44",
    "gn:asciiname":"Bozan",
    "gn:country_code":"TR",
    "gn:dem":1205,
    "gn:feature_class":"P",
    "gn:feature_code":"PPL",
    "gn:name":"Bozan",
    "gn:population":0,
    "gn:timezone":"Europe/Istanbul",
    "iso:country":"TR",
    "name:ceb_x_preferred":[
        "Bozan"
    ],
    "name:und_x_variant":[
        "Pozan",
        "Bozan"
    ],
    "wof:name":"Bozan",
    "wof:placetype":"locality"
},
  "geometry": {"coordinates":[38.22835,38.83156],"type":"Point"}
}