{
  "type": "Feature",
  "properties": {
    "gn:admin1_code":"64",
    "gn:asciiname":"Hamambogazi",
    "gn:country_code":"TR",
    "gn:dem":952,
    "gn:feature_class":"P",
    "gn:feature_code":"PPL",
    "gn:name":"Hamambo\u011faz\u0131",
    "gn:population":0,
    "gn:timezone":"Europe/Istanbul",
    "iso:country":"TR",
    "wof:name":"Hamambogazi",
    "wof:placetype":"locality"
},
  "geometry": {"coordinates":[29.82092,38.77767],"type":"Point"}
}