{
  "type": "Feature",
  "properties": {
    "gn:admin1_code":"48",
    "gn:asciiname":"Kafaca",
    "gn:country_code":"TR",
    "gn:dem":496,
    "gn:feature_class":"P",
    "gn:feature_code":"PPL",
    "gn:name":"Kafaca",
    "gn:population":0,
    "gn:timezone":"Europe/Istanbul",
    "iso:country":"TR",
    "name:und_x_variant":[
        "Karaca"
    ],
    "wof:name":"Kafaca",
    "wof:placetype":"locality"
},
  "geometry": {"coordinates":[28.23428,37.2208],"type":"Point"}
}