{
  "type": "Feature",
  "properties": {
    "gn:country":"TR",
    "gn:fcode":"PPLA2",
    "gn:pop":0,
    "iso:country":"TR",
    "name:unk_x_variant":[
        "Hocacihan"
    ],
    "qs:name":"Sel\u00e7uklu",
    "qs:photos_9r":0,
    "qs:photos_sr":0,
    "qs:pop_sr":"0",
    "wd:wordcount":195,
    "wof:name":"Sel\u00e7uklu",
    "wof:placetype":"locality",
    "wof:population":0
},
  "geometry": {"coordinates":[32.49222,37.8842],"type":"Point"}
}