{
  "type": "Feature",
  "properties": {
    "gn:country":"TR",
    "gn:fcode":"PPLA2",
    "gn:pop":0,
    "iso:country":"TR",
    "name:deu_x_preferred":[
        "Sel\u00e7uklu"
    ],
    "name:diq_x_preferred":[
        "Sel\u00e7uklu"
    ],
    "name:eng_x_preferred":[
        "Sel\u00e7uklu"
    ],
    "name:fas_x_preferred":[
        "\u0633\u0644\u062c\u0648\u0642\u200c\u0644\u0648"
    ],
    "name:fra_x_preferred":[
        "Sel\u00e7uklu"
    ],
    "name:lit_x_preferred":[
        "Sel\u010duklu"
    ],
    "name:mrj_x_preferred":[
        "\u0421\u0435\u043b\u044c\u0447\u0443\u043a\u043b\u0443"
    ],
    "name:msa_x_preferred":[
        "Sel\u00e7uklu"
    ],
    "name:nan_x_preferred":[
        "Sel\u00e7uklu"
    ],
    "name:nld_x_preferred":[
        "Sel\u00e7uklu"
    ],
    "name:nob_x_preferred":[
        "Sel\u00e7uklu"
    ],
    "name:rus_x_preferred":[
        "\u0421\u0435\u043b\u044c\u0447\u0443\u043a\u043b\u0443"
    ],
    "name:swa_x_preferred":[
        "Sel\u00e7uklu"
    ],
    "name:swe_x_preferred":[
        "Sel\u00e7uklu"
    ],
    "name:tur_x_preferred":[
        "Sel\u00e7uklu"
    ],
    "name:unk_x_variant":[
        "Hocacihan"
    ],
    "name:urd_x_preferred":[
        "\u0633\u06cc\u0644\u0686\u0648\u06a9\u0644\u0648"
    ],
    "name:vie_x_preferred":[
        "Sel\u00e7uklu"
    ],
    "qs:name":"Sel\u00e7uklu",
    "qs:photos_9r":0,
    "qs:photos_sr":0,
    "qs:pop_sr":"0",
    "wd:wordcount":195,
    "wof:name":"Sel\u00e7uklu",
    "wof:placetype":"locality",
    "wof:population":0
},
  "geometry": {"coordinates":[32.49222,37.8842],"type":"Point"}
}