{
  "type": "Feature",
  "properties": {
    "gn:admin1_code":"14",
    "gn:asciiname":"Seyrek",
    "gn:country_code":"TR",
    "gn:dem":672,
    "gn:feature_class":"P",
    "gn:feature_code":"PPL",
    "gn:name":"Seyrek",
    "gn:population":0,
    "gn:timezone":"Europe/Istanbul",
    "iso:country":"TR",
    "wof:name":"Seyrek",
    "wof:placetype":"locality"
},
  "geometry": {"coordinates":[31.97114,41.0065],"type":"Point"}
}