{
  "type": "Feature",
  "properties": {
    "gn:admin1_code":"85.0",
    "gn:asciiname":"Yazicik",
    "gn:country_code":"TR",
    "gn:dem":323,
    "gn:feature_class":"P",
    "gn:feature_code":"PPL",
    "gn:name":"Yaz\u0131c\u0131k",
    "gn:population":0,
    "gn:timezone":"Europe/Istanbul",
    "iso:country":"TR",
    "name:und_x_variant":[
        "Dirgine",
        "Yaz\u0131c\u0131k"
    ],
    "wof:name":"Yazicik",
    "wof:placetype":"locality"
},
  "geometry": {"coordinates":[31.90861,41.03083],"type":"Point"}
}