{
  "type": "Feature",
  "properties": {
    "gn:admin1_code":"19.0",
    "gn:asciiname":"Topuz",
    "gn:country_code":"TR",
    "gn:dem":969,
    "gn:feature_class":"P",
    "gn:feature_code":"PPL",
    "gn:name":"Topuz",
    "gn:population":0,
    "gn:timezone":"Europe/Istanbul",
    "iso:country":"TR",
    "wof:name":"Topuz",
    "wof:placetype":"locality"
},
  "geometry": {"coordinates":[34.32517,40.37478],"type":"Point"}
}