{
  "type": "Feature",
  "properties": {
    "gn:admin1_code":"35",
    "gn:asciiname":"Balaban",
    "gn:country_code":"TR",
    "gn:dem":482,
    "gn:feature_class":"P",
    "gn:feature_code":"PPL",
    "gn:name":"Balaban",
    "gn:population":0,
    "gn:timezone":"Europe/Istanbul",
    "iso:country":"TR",
    "name:tur_x_preferred":[
        "Balaban"
    ],
    "wof:name":"Balaban",
    "wof:placetype":"locality"
},
  "geometry": {"coordinates":[27.20309,38.95425],"type":"Point"}
}