{
  "type": "Feature",
  "properties": {
    "gn:admin1_code":"58",
    "gn:asciiname":"Sogutagil",
    "gn:country_code":"TR",
    "gn:dem":1504,
    "gn:feature_class":"P",
    "gn:feature_code":"PPL",
    "gn:name":"S\u00f6\u011f\u00fcta\u011f\u0131l",
    "gn:population":0,
    "gn:timezone":"Europe/Istanbul",
    "iso:country":"TR",
    "name:und_x_variant":[
        "S\u00f6\u011f\u00fcta\u011f\u0131l",
        "S\u00f6\u011f\u00fctl\u00fcg\u00f6l"
    ],
    "wof:name":"Sogutagil",
    "wof:placetype":"locality"
},
  "geometry": {"coordinates":[37.75,39.93333],"type":"Point"}
}