{
  "type": "Feature",
  "properties": {
    "gn:admin1_code":"81.0",
    "gn:asciiname":"Sehit",
    "gn:country_code":"TR",
    "gn:dem":528,
    "gn:feature_class":"P",
    "gn:feature_code":"PPL",
    "gn:name":"\u015eehit",
    "gn:population":0,
    "gn:timezone":"Europe/Istanbul",
    "iso:country":"TR",
    "wof:name":"Sehit",
    "wof:placetype":"locality"
},
  "geometry": {"coordinates":[35.49847000000001,37.51287],"type":"Point"}
}