{
  "type": "Feature",
  "properties": {
    "gn:admin1_code":"89.0",
    "gn:asciiname":"Kapakli",
    "gn:country_code":"TR",
    "gn:dem":669,
    "gn:feature_class":"P",
    "gn:feature_code":"PPL",
    "gn:name":"Kapakl\u0131",
    "gn:population":0,
    "gn:timezone":"Europe/Istanbul",
    "iso:country":"TR",
    "name:tur_x_preferred":[
        "Kapakl\u0131"
    ],
    "name:und_x_variant":[
        "D\u00fczk\u00f6y",
        "D\u00fcz",
        "Kapal\u0131"
    ],
    "wof:name":"Kapakli",
    "wof:placetype":"locality"
},
  "geometry": {"coordinates":[32.72758,41.14903],"type":"Point"}
}