{
  "type": "Feature",
  "properties": {
    "gn:admin1_code":"84.0",
    "gn:asciiname":"Bogazkoy",
    "gn:country_code":"TR",
    "gn:dem":1699,
    "gn:feature_class":"P",
    "gn:feature_code":"PPL",
    "gn:name":"Bo\u011fazk\u00f6y",
    "gn:population":0,
    "gn:timezone":"Europe/Istanbul",
    "iso:country":"TR",
    "name:eng_x_preferred":[
        "Bo\u011fazk\u00f6y"
    ],
    "name:rus_x_preferred":[
        "\u0411\u043e\u0433\u0430\u0437\u043a\u0435\u0439"
    ],
    "name:und_x_variant":[
        "Melikk\u00f6y\u00fc",
        "Melikk\u00f6y",
        "Melik\u00f6y"
    ],
    "wof:name":"Bogazkoy",
    "wof:placetype":"locality"
},
  "geometry": {"coordinates":[43.11578,40.70218],"type":"Point"}
}