{
  "type": "Feature",
  "properties": {
    "gn:admin1_code":"20",
    "gn:asciiname":"Ova",
    "gn:country_code":"TR",
    "gn:dem":841,
    "gn:feature_class":"P",
    "gn:feature_code":"PPL",
    "gn:name":"Ova",
    "gn:population":0,
    "gn:timezone":"Europe/Istanbul",
    "iso:country":"TR",
    "name:tur_x_preferred":[
        "Ova"
    ],
    "wof:name":"Ova",
    "wof:placetype":"locality"
},
  "geometry": {"coordinates":[28.73641,37.41354000000001],"type":"Point"}
}