{
  "type": "Feature",
  "properties": {
    "gn:admin1_code":"61.0",
    "gn:asciiname":"Pelitcik",
    "gn:country_code":"TR",
    "gn:dem":955,
    "gn:feature_class":"P",
    "gn:feature_code":"PPL",
    "gn:name":"Pelit\u00e7ik",
    "gn:population":0,
    "gn:timezone":"Europe/Istanbul",
    "iso:country":"TR",
    "name:tur_x_preferred":[
        "Pelit\u00e7ik"
    ],
    "name:und_x_variant":[
        "Pehli\u00e7ukur"
    ],
    "wof:name":"Pelitcik",
    "wof:placetype":"locality"
},
  "geometry": {"coordinates":[39.17393,40.9044],"type":"Point"}
}