{
  "type": "Feature",
  "properties": {
    "iso:country":"TR",
    "name:und_x_preferred":[
        "Milli Egemenlik"
    ],
    "name:unk_x_variant":[
        "Milli Egemenlik"
    ],
    "qs:gn_adm0_cc":"TR",
    "qs:gn_local":304854,
    "qs:gn_nam_loc":"Manavgat, Manavgat, Antalya, TR",
    "qs:gn_namadm1":"07",
    "qs:local_max":2066,
    "qs:local_sum":2652,
    "qs:localhoods":5,
    "qs:name":"Milli Egemenlik",
    "qs:name_adm0":"Turkey",
    "qs:name_adm1":"Antalya",
    "qs:name_adm2":"Manavgat",
    "qs:name_local":"Manavgat",
    "qs:photo_max":29,
    "qs:photo_sum":42,
    "qs:placetype":"Suburb",
    "qs:quad_count":5,
    "qs:woe_adm0":23424969,
    "qs:woe_adm1":2347264,
    "qs:woe_adm2":29390553,
    "qs:woe_lau":0,
    "qs:woe_local":2344249,
    "qs:woe_ver":"7.10.0",
    "wof:lang":[
        "unk"
    ],
    "wof:name":"Milli Egemenlik",
    "wof:placetype":"neighbourhood"
},
  "geometry": {"coordinates":[31.455296,36.811903],"type":"Point"}
}