{
  "type": "Feature",
  "properties": {
    "gn:admin1_code":"10",
    "gn:asciiname":"Hacibozlar",
    "gn:country_code":"TR",
    "gn:dem":831,
    "gn:feature_class":"P",
    "gn:feature_code":"PPL",
    "gn:name":"Hac\u0131bozlar",
    "gn:population":0,
    "gn:timezone":"Europe/Istanbul",
    "iso:country":"TR",
    "name:tur_x_preferred":[
        "Hac\u0131bozlar"
    ],
    "name:tur_x_variant":[
        "Hac\u0131bozan"
    ],
    "wof:name":"Hacibozlar",
    "wof:placetype":"locality"
},
  "geometry": {"coordinates":[27.01124,39.32459],"type":"Point"}
}