{
  "type": "Feature",
  "properties": {
    "gn:admin1_code":"45",
    "gn:asciiname":"Golgedik",
    "gn:country_code":"TR",
    "gn:dem":324,
    "gn:feature_class":"P",
    "gn:feature_code":"PPL",
    "gn:name":"G\u00f6lgedik",
    "gn:population":0,
    "gn:timezone":"Europe/Istanbul",
    "iso:country":"TR",
    "name:tur_x_preferred":[
        "G\u00f6lgedik"
    ],
    "wof:name":"Golgedik",
    "wof:placetype":"locality"
},
  "geometry": {"coordinates":[28.59371,38.22582],"type":"Point"}
}