{
  "type": "Feature",
  "properties": {
    "gn:admin1_code":"35",
    "gn:asciiname":"Cenikler",
    "gn:country_code":"TR",
    "gn:dem":309,
    "gn:feature_class":"P",
    "gn:feature_code":"PPL",
    "gn:name":"\u00c7enikler",
    "gn:population":0,
    "gn:timezone":"Europe/Istanbul",
    "iso:country":"TR",
    "name:tur_x_preferred":[
        "\u00c7enikler"
    ],
    "wof:name":"Cenikler",
    "wof:placetype":"locality"
},
  "geometry": {"coordinates":[27.73163,38.24336],"type":"Point"}
}