{
  "type": "Feature",
  "properties": {
    "gn:admin1_code":"35",
    "gn:asciiname":"Tastepe",
    "gn:country_code":"TR",
    "gn:dem":242,
    "gn:feature_class":"P",
    "gn:feature_code":"PPL",
    "gn:name":"Ta\u015ftepe",
    "gn:population":0,
    "gn:timezone":"Europe/Istanbul",
    "iso:country":"TR",
    "name:tur_x_preferred":[
        "Ta\u015ftepe"
    ],
    "wof:name":"Tastepe",
    "wof:placetype":"locality"
},
  "geometry": {"coordinates":[27.46741,39.10652],"type":"Point"}
}