{
  "type": "Feature",
  "properties": {
    "gn:admin1_code":"09",
    "gn:asciiname":"Hacipasalar",
    "gn:country_code":"TR",
    "gn:dem":467,
    "gn:feature_class":"P",
    "gn:feature_code":"PPL",
    "gn:name":"Hac\u0131pa\u015falar",
    "gn:population":0,
    "gn:timezone":"Europe/Istanbul",
    "iso:country":"TR",
    "wof:name":"Hacipasalar",
    "wof:placetype":"locality"
},
  "geometry": {"coordinates":[28.18651,37.50242],"type":"Point"}
}