{
  "type": "Feature",
  "properties": {
    "gn:admin1_code":"43",
    "gn:asciiname":"Yagcik",
    "gn:country_code":"TR",
    "gn:dem":722,
    "gn:feature_class":"P",
    "gn:feature_code":"PPL",
    "gn:name":"Ya\u011fc\u0131k",
    "gn:population":0,
    "gn:timezone":"Europe/Istanbul",
    "iso:country":"TR",
    "name:tur_x_preferred":[
        "Ya\u011fc\u0131k"
    ],
    "wof:name":"Yagcik",
    "wof:placetype":"locality"
},
  "geometry": {"coordinates":[29.22087,39.35228],"type":"Point"}
}