{
  "type": "Feature",
  "properties": {
    "gn:admin1_code":"32",
    "gn:asciiname":"Sogut Yaylasi",
    "gn:country_code":"TR",
    "gn:dem":1384,
    "gn:feature_class":"P",
    "gn:feature_code":"PPL",
    "gn:name":"S\u00f6\u011f\u00fct Yaylas\u0131",
    "gn:population":0,
    "gn:timezone":"Europe/Istanbul",
    "iso:country":"TR",
    "name:und_x_variant":[
        "S\u00f6v\u00fct",
        "S\u00f6\u011f\u00fct",
        "S\u00f6\u011f\u00fct Yaylas\u0131"
    ],
    "wof:name":"Sogut Yaylasi",
    "wof:placetype":"locality"
},
  "geometry": {"coordinates":[33.15714000000001,36.27655],"type":"Point"}
}