{
  "type": "Feature",
  "properties": {
    "gn:admin1_code":"86.0",
    "gn:asciiname":"Cataldere",
    "gn:country_code":"TR",
    "gn:dem":1934,
    "gn:feature_class":"P",
    "gn:feature_code":"PPL",
    "gn:name":"\u00c7ataldere",
    "gn:population":0,
    "gn:timezone":"Europe/Istanbul",
    "iso:country":"TR",
    "name:und_x_variant":[
        "Konzulut",
        "Kunzulut",
        "\u00c7ataldere"
    ],
    "wof:name":"Cataldere",
    "wof:placetype":"locality"
},
  "geometry": {"coordinates":[42.61201,41.19964],"type":"Point"}
}