{
  "type": "Feature",
  "properties": {
    "gn:admin1_code":"61.0",
    "gn:asciiname":"Yaniktas",
    "gn:country_code":"TR",
    "gn:dem":340,
    "gn:feature_class":"P",
    "gn:feature_code":"PPL",
    "gn:name":"Yan\u0131kta\u015f",
    "gn:population":0,
    "gn:timezone":"Europe/Istanbul",
    "iso:country":"TR",
    "name:tur_x_preferred":[
        "Yan\u0131kta\u015f"
    ],
    "wof:name":"Yaniktas",
    "wof:placetype":"locality"
},
  "geometry": {"coordinates":[40.31626,40.90381],"type":"Point"}
}