{
  "type": "Feature",
  "properties": {
    "gn:admin1_code":"65",
    "gn:asciiname":"Varcuni",
    "gn:cc2":"TR",
    "gn:country_code":"TR",
    "gn:dem":2340,
    "gn:feature_class":"P",
    "gn:feature_code":"PPL",
    "gn:name":"Varcuni",
    "gn:population":0,
    "gn:timezone":"Europe/Istanbul",
    "iso:country":"TR",
    "name:und_x_variant":[
        "Vardzhuni",
        "Varcuni"
    ],
    "wof:name":"Varcuni",
    "wof:placetype":"locality"
},
  "geometry": {"coordinates":[43.24861,37.90722],"type":"Point"}
}