{
  "type": "Feature",
  "properties": {
    "gn:admin1_code":"65.0",
    "gn:asciiname":"Gorecek",
    "gn:country_code":"TR",
    "gn:dem":2003,
    "gn:feature_class":"P",
    "gn:feature_code":"PPL",
    "gn:name":"G\u00f6recek",
    "gn:population":0,
    "gn:timezone":"Europe/Istanbul",
    "iso:country":"TR",
    "name:tur_x_preferred":[
        "G\u00f6recek"
    ],
    "wof:name":"Gorecek",
    "wof:placetype":"locality"
},
  "geometry": {"coordinates":[43.74503,39.08288],"type":"Point"}
}