{
  "type": "Feature",
  "properties": {
    "gn:admin1_code":"81",
    "gn:asciiname":"Isikli",
    "gn:country_code":"TR",
    "gn:dem":75,
    "gn:feature_class":"P",
    "gn:feature_code":"PPL",
    "gn:name":"I\u015f\u0131kl\u0131",
    "gn:population":0,
    "gn:timezone":"Europe/Istanbul",
    "iso:country":"TR",
    "name:deu_x_preferred":[
        "I\u015f\u0131kl\u0131"
    ],
    "name:msa_x_preferred":[
        "I\u015f\u0131kl\u0131"
    ],
    "name:tur_x_preferred":[
        "I\u015f\u0131kl\u0131"
    ],
    "name:und_x_variant":[
        "I\u015f\u0131kl\u0131"
    ],
    "name:vie_x_preferred":[
        "I\u015f\u0131kl\u0131"
    ],
    "wof:name":"Isikli",
    "wof:placetype":"locality"
},
  "geometry": {"coordinates":[35.80406,37.36832],"type":"Point"}
}