{
  "type": "Feature",
  "properties": {
    "gn:country":"TR",
    "gn:fcode":"PPL",
    "gn:pop":430,
    "iso:country":"TR",
    "name:unk_x_variant":[
        "Sehrince"
    ],
    "qs:name":"Serince",
    "qs:photos_9r":0,
    "qs:photos_sr":0,
    "qs:pop_sr":"2",
    "wof:name":"Serince",
    "wof:placetype":"locality",
    "wof:population":430
},
  "geometry": {"coordinates":[38.95611,36.86639],"type":"Point"}
}