{
  "type": "Feature",
  "properties": {
    "gn:admin1_code":"25",
    "gn:asciiname":"Tellitepe",
    "gn:country_code":"TR",
    "gn:dem":1715,
    "gn:feature_class":"P",
    "gn:feature_code":"PPL",
    "gn:name":"Tellitepe",
    "gn:population":0,
    "gn:timezone":"Europe/Istanbul",
    "iso:country":"TR",
    "name:tur_x_preferred":[
        "Tellitepe"
    ],
    "wof:name":"Tellitepe",
    "wof:placetype":"locality"
},
  "geometry": {"coordinates":[41.74136,39.26781],"type":"Point"}
}