{
  "type": "Feature",
  "properties": {
    "gn:admin1_code":"09",
    "gn:asciiname":"Dageymiri",
    "gn:country_code":"TR",
    "gn:dem":692,
    "gn:feature_class":"P",
    "gn:feature_code":"PPL",
    "gn:name":"Da\u011feymiri",
    "gn:population":0,
    "gn:timezone":"Europe/Istanbul",
    "iso:country":"TR",
    "name:ceb_x_preferred":[
        "Da\u011feymiri"
    ],
    "name:msa_x_preferred":[
        "Da\u011feymiri"
    ],
    "name:tur_x_preferred":[
        "Da\u011feymiri"
    ],
    "name:und_x_variant":[
        "Da\u011femiri",
        "Da\u011feymiri"
    ],
    "name:vie_x_preferred":[
        "Da\u011feymiri"
    ],
    "wof:name":"Dageymiri",
    "wof:placetype":"locality"
},
  "geometry": {"coordinates":[27.83982,37.91145],"type":"Point"}
}