{
  "type": "Feature",
  "properties": {
    "gn:admin1_code":"25.0",
    "gn:asciiname":"Akoren",
    "gn:country_code":"TR",
    "gn:dem":2012,
    "gn:feature_class":"P",
    "gn:feature_code":"PPL",
    "gn:name":"Ak\u00f6ren",
    "gn:population":0,
    "gn:timezone":"Europe/Istanbul",
    "iso:country":"TR",
    "name:tur_x_preferred":[
        "Ak\u00f6ren"
    ],
    "wof:name":"Akoren",
    "wof:placetype":"locality"
},
  "geometry": {"coordinates":[40.59623,39.76483],"type":"Point"}
}