{
  "type": "Feature",
  "properties": {
    "gn:country":"TR",
    "iso:country":"TR",
    "qs:name":"Sariana",
    "qs:name_adm0":"Turkey",
    "qs:name_adm1":"Mu\u011fla",
    "qs:photos":56,
    "qs:photos_1k":11,
    "qs:photos_9k":1,
    "qs:photos_9r":2,
    "qs:photos_all":56,
    "qs:photos_sr":2,
    "qs:placetype":"Town",
    "qs:pop_sr":"0",
    "wof:name":"Sariana",
    "wof:placetype":"locality"
},
  "geometry": {"coordinates":[28.306531,36.81911],"type":"Point"}
}