{
  "type": "Feature",
  "properties": {
    "gn:admin1_code":"14",
    "gn:asciiname":"Gozler",
    "gn:country_code":"TR",
    "gn:dem":1086,
    "gn:feature_class":"P",
    "gn:feature_code":"PPL",
    "gn:name":"G\u00f6zler",
    "gn:population":0,
    "gn:timezone":"Europe/Istanbul",
    "iso:country":"TR",
    "wof:name":"Gozler",
    "wof:placetype":"locality"
},
  "geometry": {"coordinates":[30.70732000000001,40.34598],"type":"Point"}
}