{
  "type": "Feature",
  "properties": {
    "gn:admin1_code":"79",
    "gn:asciiname":"Yeniyapan",
    "gn:country_code":"TR",
    "gn:dem":985,
    "gn:feature_class":"P",
    "gn:feature_code":"PPL",
    "gn:name":"Yeniyapan",
    "gn:population":0,
    "gn:timezone":"Europe/Istanbul",
    "iso:country":"TR",
    "name:tur_x_preferred":[
        "Yeniyapan"
    ],
    "wof:name":"Yeniyapan",
    "wof:placetype":"locality"
},
  "geometry": {"coordinates":[33.54197,39.68738],"type":"Point"}
}