{
  "type": "Feature",
  "properties": {
    "gn:admin1_code":"16",
    "gn:asciiname":"Pasapinar",
    "gn:country_code":"TR",
    "gn:dem":118,
    "gn:feature_class":"P",
    "gn:feature_code":"PPL",
    "gn:name":"Pa\u015fap\u0131nar",
    "gn:population":0,
    "gn:timezone":"Europe/Istanbul",
    "iso:country":"TR",
    "name:tur_x_preferred":[
        "Pa\u015fap\u0131nar"
    ],
    "wof:name":"Pasapinar",
    "wof:placetype":"locality"
},
  "geometry": {"coordinates":[29.45983,40.38915],"type":"Point"}
}