{
  "type": "Feature",
  "properties": {
    "gn:admin1_code":"12.0",
    "gn:asciiname":"Saribudak",
    "gn:country_code":"TR",
    "gn:dem":1110,
    "gn:feature_class":"P",
    "gn:feature_code":"PPL",
    "gn:name":"Sar\u0131budak",
    "gn:population":0,
    "gn:timezone":"Europe/Istanbul",
    "iso:country":"TR",
    "name:tur_x_preferred":[
        "Sar\u0131budak"
    ],
    "wof:name":"Saribudak",
    "wof:placetype":"locality"
},
  "geometry": {"coordinates":[40.31985,38.5211],"type":"Point"}
}