{
  "type": "Feature",
  "properties": {
    "gn:admin1_code":"65.0",
    "gn:asciiname":"Dagoren",
    "gn:country_code":"TR",
    "gn:dem":2214,
    "gn:feature_class":"P",
    "gn:feature_code":"PPL",
    "gn:name":"Da\u011f\u00f6ren",
    "gn:population":0,
    "gn:timezone":"Europe/Istanbul",
    "iso:country":"TR",
    "name:tur_x_preferred":[
        "Da\u011f\u00f6ren"
    ],
    "wof:name":"Dagoren",
    "wof:placetype":"locality"
},
  "geometry": {"coordinates":[43.77396,38.78004],"type":"Point"}
}