{
  "type": "Feature",
  "properties": {
    "gn:admin1_code":"73",
    "gn:asciiname":"Beyaz Kislakci",
    "gn:country_code":"TR",
    "gn:dem":1358,
    "gn:feature_class":"P",
    "gn:feature_code":"PPL",
    "gn:name":"Beyaz K\u0131\u015flak\u00e7\u0131",
    "gn:population":0,
    "gn:timezone":"Europe/Istanbul",
    "iso:country":"TR",
    "name:tur_x_preferred":[
        "Beyaz K\u0131\u015flak\u00e7\u0131"
    ],
    "name:und_x_variant":[
        "Beynamaz K\u0131\u015flakc\u0131s\u0131 K\u00f6y\u00fc",
        "Beynamazk\u0131\u015flac\u0131k",
        "Beynamazk\u0131\u015flakc\u0131s\u0131"
    ],
    "wof:name":"Beyaz Kislakci",
    "wof:placetype":"locality"
},
  "geometry": {"coordinates":[34.97614,37.67807],"type":"Point"}
}