{
  "type": "Feature",
  "properties": {
    "gn:admin1_code":"33",
    "gn:asciiname":"Koturnek",
    "gn:cc2":"TR",
    "gn:country_code":"TR",
    "gn:dem":1156,
    "gn:feature_class":"P",
    "gn:feature_code":"PPL",
    "gn:name":"K\u00f6t\u00fcrnek",
    "gn:population":0,
    "gn:timezone":"Europe/Istanbul",
    "iso:country":"TR",
    "name:und_x_variant":[
        "K\u00f6t\u00fcrenk",
        "K\u00f6t\u00fcrnek"
    ],
    "wof:name":"Koturnek",
    "wof:placetype":"locality"
},
  "geometry": {"coordinates":[31.13333,38.16667],"type":"Point"}
}