{
  "type": "Feature",
  "properties": {
    "gn:admin1_code":"82.0",
    "gn:asciiname":"Gurmec",
    "gn:country_code":"TR",
    "gn:dem":1091,
    "gn:feature_class":"P",
    "gn:feature_code":"PPL",
    "gn:name":"G\u00fcrme\u00e7",
    "gn:population":0,
    "gn:timezone":"Europe/Istanbul",
    "iso:country":"TR",
    "wof:name":"Gurmec",
    "wof:placetype":"locality"
},
  "geometry": {"coordinates":[34.01064,40.65825],"type":"Point"}
}