{
  "type": "Feature",
  "properties": {
    "gn:admin1_code":"93",
    "gn:asciiname":"Hidirli",
    "gn:country_code":"TR",
    "gn:dem":667,
    "gn:feature_class":"P",
    "gn:feature_code":"PPL",
    "gn:name":"H\u0131d\u0131rl\u0131",
    "gn:population":0,
    "gn:timezone":"Europe/Istanbul",
    "iso:country":"TR",
    "wof:name":"Hidirli",
    "wof:placetype":"locality"
},
  "geometry": {"coordinates":[30.91268,40.7886],"type":"Point"}
}