{
  "type": "Feature",
  "properties": {
    "gn:admin1_code":"35",
    "gn:asciiname":"Urfali",
    "gn:country_code":"TR",
    "gn:dem":11,
    "gn:feature_class":"P",
    "gn:feature_code":"PPL",
    "gn:name":"Urfal\u0131",
    "gn:population":0,
    "gn:timezone":"Europe/Istanbul",
    "iso:country":"TR",
    "wof:name":"Urfali",
    "wof:placetype":"locality"
},
  "geometry": {"coordinates":[27.46667,38.05],"type":"Point"}
}