{
  "type": "Feature",
  "properties": {
    "gn:admin1_code":"87",
    "gn:asciiname":"Demirci",
    "gn:country_code":"TR",
    "gn:dem":248,
    "gn:feature_class":"P",
    "gn:feature_code":"PPL",
    "gn:name":"Demirci",
    "gn:population":0,
    "gn:timezone":"Europe/Istanbul",
    "iso:country":"TR",
    "name:azb_x_preferred":[
        "\u062f\u0645\u06cc\u0631\u062c\u06cc"
    ],
    "name:ceb_x_preferred":[
        "Demirci \u0130l\u00e7esi"
    ],
    "name:deu_x_preferred":[
        "Demirci"
    ],
    "name:fas_x_preferred":[
        "\u062f\u0645\u06cc\u0631\u062c\u06cc"
    ],
    "name:fra_x_preferred":[
        "Demirci"
    ],
    "name:mrj_x_preferred":[
        "\u0414\u0435\u043c\u0438\u0440\u0434\u0436\u0438"
    ],
    "name:msa_x_preferred":[
        "Demirci"
    ],
    "name:nno_x_preferred":[
        "Demirci"
    ],
    "name:nor_x_preferred":[
        "Demirci"
    ],
    "name:pnb_x_preferred":[
        "\u0636\u0644\u0639 \u062f\u0645\u0631\u062c\u06cc"
    ],
    "name:ron_x_preferred":[
        "Demirci"
    ],
    "name:swa_x_preferred":[
        "Demirci"
    ],
    "name:tur_x_preferred":[
        "Demirci"
    ],
    "name:urd_x_preferred":[
        "\u062f\u06cc\u0645\u06cc\u0631\u062c\u06cc"
    ],
    "name:vie_x_preferred":[
        "Demirci"
    ],
    "name:zho_x_preferred":[
        "\u4ee3\u7c73\u723e\u5409"
    ],
    "wof:name":"Demirci",
    "wof:placetype":"locality"
},
  "geometry": {"coordinates":[32.70306,41.59599],"type":"Point"}
}