{
  "type": "Feature",
  "properties": {
    "gn:admin1_code":"87",
    "gn:asciiname":"Demirci",
    "gn:country_code":"TR",
    "gn:dem":248,
    "gn:feature_class":"P",
    "gn:feature_code":"PPL",
    "gn:name":"Demirci",
    "gn:population":0,
    "gn:timezone":"Europe/Istanbul",
    "iso:country":"TR",
    "wof:name":"Demirci",
    "wof:placetype":"locality"
},
  "geometry": {"coordinates":[32.70306,41.59599],"type":"Point"}
}