{
  "type": "Feature",
  "properties": {
    "gn:admin1_code":"65",
    "gn:asciiname":"Hasanabat",
    "gn:country_code":"TR",
    "gn:dem":2321,
    "gn:feature_class":"P",
    "gn:feature_code":"PPL",
    "gn:name":"Hasanabat",
    "gn:population":0,
    "gn:timezone":"Europe/Istanbul",
    "iso:country":"TR",
    "wof:name":"Hasanabat",
    "wof:placetype":"locality"
},
  "geometry": {"coordinates":[43.96167,37.96361],"type":"Point"}
}