{
  "type": "Feature",
  "properties": {
    "gn:admin1_code":"85",
    "gn:asciiname":"Rahmanoglu",
    "gn:country_code":"TR",
    "gn:dem":498,
    "gn:feature_class":"P",
    "gn:feature_code":"PPL",
    "gn:name":"Rahmano\u011flu",
    "gn:population":0,
    "gn:timezone":"Europe/Istanbul",
    "iso:country":"TR",
    "wof:name":"Rahmanoglu",
    "wof:placetype":"locality"
},
  "geometry": {"coordinates":[31.76767000000001,41.08177],"type":"Point"}
}