{
  "type": "Feature",
  "properties": {
    "gn:admin1_code":"35",
    "gn:asciiname":"Mersinli",
    "gn:country_code":"TR",
    "gn:dem":641,
    "gn:feature_class":"P",
    "gn:feature_code":"PPL",
    "gn:name":"Mersinli",
    "gn:population":0,
    "gn:timezone":"Europe/Istanbul",
    "iso:country":"TR",
    "name:tur_x_preferred":[
        "Mersinli"
    ],
    "wof:name":"Mersinli",
    "wof:placetype":"locality"
},
  "geometry": {"coordinates":[27.52826,38.2589],"type":"Point"}
}