{
  "type": "Feature",
  "properties": {
    "gn:admin1_code":"57.0",
    "gn:asciiname":"Cukurhan",
    "gn:country_code":"TR",
    "gn:dem":931,
    "gn:feature_class":"P",
    "gn:feature_code":"PPL",
    "gn:name":"\u00c7ukurhan",
    "gn:population":0,
    "gn:timezone":"Europe/Istanbul",
    "iso:country":"TR",
    "name:tur_x_preferred":[
        "\u00c7ukurhan K\u00f6y\u00fc"
    ],
    "name:und_x_variant":[
        "\u00c7ukurhan K\u00f6y",
        "\u00c7ukurhan"
    ],
    "wof:name":"Cukurhan",
    "wof:placetype":"locality"
},
  "geometry": {"coordinates":[34.94651,41.5896],"type":"Point"}
}