{
  "type": "Feature",
  "properties": {
    "gn:admin1_code":"55",
    "gn:asciiname":"Erenkoy",
    "gn:country_code":"TR",
    "gn:dem":777,
    "gn:feature_class":"P",
    "gn:feature_code":"PPL",
    "gn:name":"Erenk\u00f6y",
    "gn:population":0,
    "gn:timezone":"Europe/Istanbul",
    "iso:country":"TR",
    "name:tur_x_preferred":[
        "Erenk\u00f6y"
    ],
    "wof:name":"Erenkoy",
    "wof:placetype":"locality"
},
  "geometry": {"coordinates":[36.35357,41.14516],"type":"Point"}
}