{
  "type": "Feature",
  "properties": {
    "gn:admin1_code":"63",
    "gn:asciiname":"Tanriverdi",
    "gn:country_code":"TR",
    "gn:dem":817,
    "gn:feature_class":"P",
    "gn:feature_code":"PPL",
    "gn:name":"Tanr\u0131verdi",
    "gn:population":0,
    "gn:timezone":"Europe/Istanbul",
    "iso:country":"TR",
    "name:tur_x_preferred":[
        "Tanr\u0131verdi"
    ],
    "wof:name":"Tanriverdi",
    "wof:placetype":"locality"
},
  "geometry": {"coordinates":[39.61569,37.42846],"type":"Point"}
}