{
  "type": "Feature",
  "properties": {
    "gn:admin1_code":"17.0",
    "gn:asciiname":"Pazarli",
    "gn:country_code":"TR",
    "gn:dem":175,
    "gn:feature_class":"P",
    "gn:feature_code":"PPL",
    "gn:name":"Pazarl\u0131",
    "gn:population":0,
    "gn:timezone":"Europe/Istanbul",
    "iso:country":"TR",
    "wof:name":"Pazarli",
    "wof:placetype":"locality"
},
  "geometry": {"coordinates":[26.4967,40.3151],"type":"Point"}
}