{
  "type": "Feature",
  "properties": {
    "gn:admin1_code":"13",
    "gn:asciiname":"Alancik",
    "gn:country_code":"TR",
    "gn:dem":1307,
    "gn:feature_class":"P",
    "gn:feature_code":"PPL",
    "gn:name":"Alanc\u0131k",
    "gn:population":0,
    "gn:timezone":"Europe/Istanbul",
    "iso:country":"TR",
    "name:tur_x_preferred":[
        "Alanc\u0131k"
    ],
    "name:und_x_variant":[
        "Nuvala\u00e7oma"
    ],
    "wof:name":"Alancik",
    "wof:placetype":"locality"
},
  "geometry": {"coordinates":[42.32492,38.13698],"type":"Point"}
}