{
  "type": "Feature",
  "properties": {
    "gn:admin1_code":"13.0",
    "gn:asciiname":"Serinci",
    "gn:country_code":"TR",
    "gn:dem":1554,
    "gn:feature_class":"P",
    "gn:feature_code":"PPL",
    "gn:name":"Serinci",
    "gn:population":0,
    "gn:timezone":"Europe/Istanbul",
    "iso:country":"TR",
    "name:tur_x_preferred":[
        "Serinci"
    ],
    "wof:name":"Serinci",
    "wof:placetype":"locality"
},
  "geometry": {"coordinates":[41.6687,38.56287],"type":"Point"}
}