{
  "type": "Feature",
  "properties": {
    "gn:admin1_code":"16",
    "gn:asciiname":"Taskopru",
    "gn:country_code":"TR",
    "gn:dem":30,
    "gn:feature_class":"P",
    "gn:feature_code":"PPL",
    "gn:name":"Ta\u015fk\u00f6pr\u00fc",
    "gn:population":0,
    "gn:timezone":"Europe/Istanbul",
    "iso:country":"TR",
    "name:und_x_variant":[
        "Ta\u015fk\u00f6pr\u00fc K\u00f6y\u00fc",
        "Ta\u015fk\u00f6pr\u00fc"
    ],
    "wof:name":"Taskopru",
    "wof:placetype":"locality"
},
  "geometry": {"coordinates":[28.21366,40.00029],"type":"Point"}
}