{
  "type": "Feature",
  "properties": {
    "gn:admin1_code":"72",
    "gn:asciiname":"Basak",
    "gn:country_code":"TR",
    "gn:dem":451,
    "gn:feature_class":"P",
    "gn:feature_code":"PPL",
    "gn:name":"Ba\u015fak",
    "gn:population":0,
    "gn:timezone":"Europe/Istanbul",
    "iso:country":"TR",
    "name:ceb_x_preferred":[
        "Basak"
    ],
    "name:ita_x_preferred":[
        "Basak"
    ],
    "name:swe_x_preferred":[
        "Basak"
    ],
    "name:tur_x_preferred":[
        "Ba\u015fak"
    ],
    "name:und_x_variant":[
        "Sinnare",
        "S\u0131nnara",
        "Sinara"
    ],
    "wof:name":"Basak",
    "wof:placetype":"locality"
},
  "geometry": {"coordinates":[40.39814000000001,37.14058],"type":"Point"}
}