{
  "type": "Feature",
  "properties": {
    "gn:admin1_code":"14",
    "gn:asciiname":"Fakilar",
    "gn:country_code":"TR",
    "gn:dem":964,
    "gn:feature_class":"P",
    "gn:feature_code":"PPL",
    "gn:name":"Fak\u0131lar",
    "gn:population":0,
    "gn:timezone":"Europe/Istanbul",
    "iso:country":"TR",
    "wof:name":"Fakilar",
    "wof:placetype":"locality"
},
  "geometry": {"coordinates":[31.8588,40.73817],"type":"Point"}
}