{
  "type": "Feature",
  "properties": {
    "gn:country":"TR",
    "gn:fcode":"PPL",
    "gn:population":3925,
    "iso:country":"TR",
    "name:tur_x_preferred":[
        "G\u00fcm\u00fc\u015fg\u00f6ze"
    ],
    "qs:name":"G\u00fcm\u00fc\u015fg\u00f6ze",
    "qs:photos_9r":0,
    "qs:photos_sr":0,
    "qs:pop_sr":"4",
    "wd:wordcount":45,
    "wof:name":"G\u00fcm\u00fc\u015fg\u00f6ze",
    "wof:placetype":"locality",
    "wof:population":3925
},
  "geometry": {"coordinates":[36.1387,36.15487],"type":"Point"}
}