{
  "type": "Feature",
  "properties": {
    "gn:admin1_code":"21",
    "gn:asciiname":"Gurbeyli",
    "gn:country_code":"TR",
    "gn:dem":876,
    "gn:feature_class":"P",
    "gn:feature_code":"PPL",
    "gn:name":"G\u00fcrbeyli",
    "gn:population":0,
    "gn:timezone":"Europe/Istanbul",
    "iso:country":"TR",
    "name:tur_x_preferred":[
        "G\u00fcrbeyli"
    ],
    "name:und_x_variant":[
        "\u015eeyhan"
    ],
    "wof:name":"Gurbeyli",
    "wof:placetype":"locality"
},
  "geometry": {"coordinates":[40.71099,38.45343],"type":"Point"}
}