{
  "type": "Feature",
  "properties": {
    "gn:admin1_code":"76",
    "gn:asciiname":"Bekirhan",
    "gn:country_code":"TR",
    "gn:dem":645,
    "gn:feature_class":"P",
    "gn:feature_code":"PPLA3",
    "gn:name":"Bekirhan",
    "gn:population":0,
    "gn:timezone":"Europe/Istanbul",
    "iso:country":"TR",
    "name:ceb_x_preferred":[
        "Bekirhan"
    ],
    "name:tur_x_preferred":[
        "Bekirhan"
    ],
    "name:und_x_variant":[
        "\u015eelmo",
        "K\u00e2nihani"
    ],
    "wof:name":"Bekirhan",
    "wof:placetype":"locality"
},
  "geometry": {"coordinates":[41.29351,38.14086],"type":"Point"}
}