{
  "type": "Feature",
  "properties": {
    "gn:admin1_code":"46",
    "gn:asciiname":"Hombur",
    "gn:country_code":"TR",
    "gn:dem":1549,
    "gn:feature_class":"P",
    "gn:feature_code":"PPL",
    "gn:name":"Hombur",
    "gn:population":0,
    "gn:timezone":"Europe/Istanbul",
    "iso:country":"TR",
    "name:und_x_variant":[
        "Honbur",
        "Hombur"
    ],
    "wof:name":"Hombur",
    "wof:placetype":"locality"
},
  "geometry": {"coordinates":[37.20558,37.762],"type":"Point"}
}