{
  "type": "Feature",
  "properties": {
    "gn:admin1_code":"22.0",
    "gn:asciiname":"Sirpsindigi",
    "gn:country_code":"TR",
    "gn:dem":197,
    "gn:feature_class":"P",
    "gn:feature_code":"PPLA3",
    "gn:name":"S\u0131rps\u0131nd\u0131\u011f\u0131",
    "gn:population":0,
    "gn:timezone":"Europe/Istanbul",
    "iso:country":"TR",
    "name:und_x_variant":[
        "Sarayakp\u0131nar",
        "S\u0131rps\u0131nd\u0131\u011f\u0131"
    ],
    "wof:name":"Sirpsindigi",
    "wof:placetype":"locality"
},
  "geometry": {"coordinates":[26.47888,41.78124],"type":"Point"}
}