{
  "type": "Feature",
  "properties": {
    "gn:admin1_code":"37.0",
    "gn:asciiname":"Yunuslar",
    "gn:country_code":"TR",
    "gn:dem":546,
    "gn:feature_class":"P",
    "gn:feature_code":"PPL",
    "gn:name":"Yunuslar",
    "gn:population":0,
    "gn:timezone":"Europe/Istanbul",
    "iso:country":"TR",
    "wof:name":"Yunuslar",
    "wof:placetype":"locality"
},
  "geometry": {"coordinates":[34.25607,41.84882],"type":"Point"}
}