{
  "type": "Feature",
  "properties": {
    "gn:admin1_code":"64",
    "gn:asciiname":"Hamamdere",
    "gn:country_code":"TR",
    "gn:dem":748,
    "gn:feature_class":"P",
    "gn:feature_code":"PPL",
    "gn:name":"Hamamdere",
    "gn:population":0,
    "gn:timezone":"Europe/Istanbul",
    "iso:country":"TR",
    "name:tur_x_preferred":[
        "Hamamdere"
    ],
    "wof:name":"Hamamdere",
    "wof:placetype":"locality"
},
  "geometry": {"coordinates":[28.96699000000001,38.61033],"type":"Point"}
}