{
  "type": "Feature",
  "properties": {
    "gn:admin1_code":"68.0",
    "gn:asciiname":"Dortkonak",
    "gn:country_code":"TR",
    "gn:dem":1267,
    "gn:feature_class":"P",
    "gn:feature_code":"PPL",
    "gn:name":"D\u00f6rtkonak",
    "gn:population":0,
    "gn:timezone":"Europe/Istanbul",
    "iso:country":"TR",
    "wof:name":"Dortkonak",
    "wof:placetype":"locality"
},
  "geometry": {"coordinates":[32.32707,40.50826],"type":"Point"}
}