{
  "type": "Feature",
  "properties": {
    "gn:admin1_code":"84",
    "gn:asciiname":"Ortakale",
    "gn:country_code":"TR",
    "gn:dem":1817,
    "gn:feature_class":"P",
    "gn:feature_code":"PPL",
    "gn:name":"Ortakale",
    "gn:population":0,
    "gn:timezone":"Europe/Istanbul",
    "iso:country":"TR",
    "name:und_x_variant":[
        "K\u00fc\u00e7\u00fck Ortakale"
    ],
    "wof:name":"Ortakale",
    "wof:placetype":"locality"
},
  "geometry": {"coordinates":[42.60004,39.97156],"type":"Point"}
}