{
  "type": "Feature",
  "properties": {
    "gn:admin1_code":"17.0",
    "gn:asciiname":"Bayatlar",
    "gn:country_code":"TR",
    "gn:dem":252,
    "gn:feature_class":"P",
    "gn:feature_code":"PPL",
    "gn:name":"Bayatlar",
    "gn:population":0,
    "gn:timezone":"Europe/Istanbul",
    "iso:country":"TR",
    "wof:name":"Bayatlar",
    "wof:placetype":"locality"
},
  "geometry": {"coordinates":[27.32216,39.84047],"type":"Point"}
}