{
  "type": "Feature",
  "properties": {
    "gn:admin1_code":"64",
    "gn:asciiname":"Calyenice",
    "gn:country_code":"TR",
    "gn:dem":750,
    "gn:feature_class":"P",
    "gn:feature_code":"PPL",
    "gn:name":"\u00c7alyenice",
    "gn:population":0,
    "gn:timezone":"Europe/Istanbul",
    "iso:country":"TR",
    "name:tur_x_preferred":[
        "\u00c7alyenice"
    ],
    "name:tur_x_variant":[
        "Yenice"
    ],
    "wof:name":"Calyenice",
    "wof:placetype":"locality"
},
  "geometry": {"coordinates":[29.37741,38.32927],"type":"Point"}
}