{
  "type": "Feature",
  "properties": {
    "gn:admin1_code":"21",
    "gn:asciiname":"Sogkulak",
    "gn:country_code":"TR",
    "gn:dem":758,
    "gn:feature_class":"P",
    "gn:feature_code":"PPL",
    "gn:name":"So\u011fkulak",
    "gn:population":0,
    "gn:timezone":"Europe/Istanbul",
    "iso:country":"TR",
    "name:und_x_variant":[
        "So\u011fkulak",
        "Karadibek"
    ],
    "wof:name":"Sogkulak",
    "wof:placetype":"locality"
},
  "geometry": {"coordinates":[39.94334,38.00661],"type":"Point"}
}