{
  "type": "Feature",
  "properties": {
    "gn:admin1_code":"64",
    "gn:asciiname":"Cigerdede",
    "gn:country_code":"TR",
    "gn:dem":1100,
    "gn:feature_class":"P",
    "gn:feature_code":"PPL",
    "gn:name":"Ci\u011ferdede",
    "gn:population":0,
    "gn:timezone":"Europe/Istanbul",
    "iso:country":"TR",
    "name:tur_x_preferred":[
        "Ci\u011ferdede"
    ],
    "wof:name":"Cigerdede",
    "wof:placetype":"locality"
},
  "geometry": {"coordinates":[29.37855,38.73439000000001],"type":"Point"}
}