{
  "type": "Feature",
  "properties": {
    "gn:admin1_code":"84.0",
    "gn:asciiname":"Buyukakuzum",
    "gn:country_code":"TR",
    "gn:dem":1497,
    "gn:feature_class":"P",
    "gn:feature_code":"PPL",
    "gn:name":"B\u00fcy\u00fckak\u00fcz\u00fcm",
    "gn:population":0,
    "gn:timezone":"Europe/Istanbul",
    "iso:country":"TR",
    "name:und_x_variant":[
        "\u0130sl\u00e2mak\u00fcz\u00fcm",
        "B\u00fcy\u00fckak\u00fcz\u00fcm"
    ],
    "wof:name":"Buyukakuzum",
    "wof:placetype":"locality"
},
  "geometry": {"coordinates":[43.66667,40.73333],"type":"Point"}
}