{
  "type": "Feature",
  "properties": {
    "gn:admin1_code":"14.0",
    "gn:asciiname":"Demirciler",
    "gn:country_code":"TR",
    "gn:dem":809,
    "gn:feature_class":"P",
    "gn:feature_code":"PPL",
    "gn:name":"Demirciler",
    "gn:population":0,
    "gn:timezone":"Europe/Istanbul",
    "iso:country":"TR",
    "wof:name":"Demirciler",
    "wof:placetype":"locality"
},
  "geometry": {"coordinates":[31.67833,40.69515],"type":"Point"}
}