{
  "type": "Feature",
  "properties": {
    "gn:admin1_code":"63",
    "gn:asciiname":"Ciftlikoy",
    "gn:country_code":"TR",
    "gn:dem":410,
    "gn:feature_class":"P",
    "gn:feature_code":"PPL",
    "gn:name":"\u00c7iftlik\u00f6y",
    "gn:population":0,
    "gn:timezone":"Europe/Istanbul",
    "iso:country":"TR",
    "name:tur_x_preferred":[
        "\u00c7iftlik\u00f6y"
    ],
    "wof:name":"Ciftlikoy",
    "wof:placetype":"locality"
},
  "geometry": {"coordinates":[37.9296,37.10336],"type":"Point"}
}