{
  "type": "Feature",
  "properties": {
    "gn:admin1_code":"90",
    "gn:asciiname":"Tanburali",
    "gn:country_code":"TR",
    "gn:dem":792,
    "gn:feature_class":"P",
    "gn:feature_code":"PPL",
    "gn:name":"Tanbural\u0131",
    "gn:population":0,
    "gn:timezone":"Europe/Istanbul",
    "iso:country":"TR",
    "wof:name":"Tanburali",
    "wof:placetype":"locality"
},
  "geometry": {"coordinates":[37.10667,36.76528],"type":"Point"}
}