{
  "type": "Feature",
  "properties": {
    "gn:admin1_code":"03",
    "gn:asciiname":"Cayhisar",
    "gn:country_code":"TR",
    "gn:dem":1264,
    "gn:feature_class":"P",
    "gn:feature_code":"PPL",
    "gn:name":"\u00c7ayhisar",
    "gn:population":0,
    "gn:timezone":"Europe/Istanbul",
    "iso:country":"TR",
    "wof:name":"Cayhisar",
    "wof:placetype":"locality"
},
  "geometry": {"coordinates":[30.175,38.72722],"type":"Point"}
}