{
  "type": "Feature",
  "properties": {
    "gn:admin1_code":"38",
    "gn:asciiname":"Dikilitas",
    "gn:country_code":"TR",
    "gn:dem":1696,
    "gn:feature_class":"P",
    "gn:feature_code":"PPL",
    "gn:name":"Dikilita\u015f",
    "gn:population":0,
    "gn:timezone":"Europe/Istanbul",
    "iso:country":"TR",
    "name:und_x_variant":[
        "Dikilita\u015f K\u00f6y\u00fc",
        "Dikilita\u015f"
    ],
    "wof:name":"Dikilitas",
    "wof:placetype":"locality"
},
  "geometry": {"coordinates":[36.85055,39.00835],"type":"Point"}
}