{
  "type": "Feature",
  "properties": {
    "gn:admin1_code":"45",
    "gn:asciiname":"Pinarlar",
    "gn:country_code":"TR",
    "gn:dem":939,
    "gn:feature_class":"P",
    "gn:feature_code":"PPL",
    "gn:name":"P\u0131narlar",
    "gn:population":0,
    "gn:timezone":"Europe/Istanbul",
    "iso:country":"TR",
    "name:und_x_variant":[
        "P\u0131narlark\u00f6y",
        "P\u0131narlar"
    ],
    "wof:name":"Pinarlar",
    "wof:placetype":"locality"
},
  "geometry": {"coordinates":[28.91176,38.89145],"type":"Point"}
}