{
  "type": "Feature",
  "properties": {
    "gn:admin1_code":"43",
    "gn:asciiname":"Yazlica",
    "gn:country_code":"TR",
    "gn:dem":1063,
    "gn:feature_class":"P",
    "gn:feature_code":"PPL",
    "gn:name":"Yazl\u0131ca",
    "gn:population":0,
    "gn:timezone":"Europe/Istanbul",
    "iso:country":"TR",
    "name:tur_x_preferred":[
        "Yazl\u0131ca"
    ],
    "wof:name":"Yazlica",
    "wof:placetype":"locality"
},
  "geometry": {"coordinates":[30.04728,39.61137],"type":"Point"}
}