{
  "type": "Feature",
  "properties": {
    "gn:admin1_code":"37.0",
    "gn:asciiname":"Asagiarslanli",
    "gn:country_code":"TR",
    "gn:dem":1040,
    "gn:feature_class":"P",
    "gn:feature_code":"PPL",
    "gn:name":"A\u015fa\u011f\u0131arslanl\u0131",
    "gn:population":0,
    "gn:timezone":"Europe/Istanbul",
    "iso:country":"TR",
    "name:tur_x_preferred":[
        "A\u015fa\u011f\u0131arslan"
    ],
    "name:und_x_variant":[
        "A\u015fa\u011f\u0131arslanl\u0131"
    ],
    "wof:name":"Asagiarslanli",
    "wof:placetype":"locality"
},
  "geometry": {"coordinates":[33.6785,41.62734],"type":"Point"}
}