{
  "type": "Feature",
  "properties": {
    "gn:admin1_code":"85",
    "gn:asciiname":"Sarnaz",
    "gn:country_code":"TR",
    "gn:dem":458,
    "gn:feature_class":"P",
    "gn:feature_code":"PPL",
    "gn:name":"Sarnaz",
    "gn:population":0,
    "gn:timezone":"Europe/Istanbul",
    "iso:country":"TR",
    "wof:name":"Sarnaz",
    "wof:placetype":"locality"
},
  "geometry": {"coordinates":[31.8366,41.11953],"type":"Point"}
}