{
  "type": "Feature",
  "properties": {
    "gn:admin1_code":"63.0",
    "gn:asciiname":"Harmanalan",
    "gn:cc2":"TR",
    "gn:country_code":"TR",
    "gn:dem":578,
    "gn:feature_class":"P",
    "gn:feature_code":"PPL",
    "gn:name":"Harmanalan",
    "gn:population":0,
    "gn:timezone":"Europe/Istanbul",
    "iso:country":"TR",
    "name:und_x_variant":[
        "Tilharman",
        "Aliveran",
        "Kharmanalan",
        "Harmanalan"
    ],
    "wof:name":"Harmanalan",
    "wof:placetype":"locality"
},
  "geometry": {"coordinates":[38.28111,36.98611],"type":"Point"}
}