{
  "type": "Feature",
  "properties": {
    "gn:admin1_code":"48",
    "gn:asciiname":"Aktanbelen",
    "gn:country_code":"TR",
    "gn:dem":110,
    "gn:feature_class":"P",
    "gn:feature_code":"PPL",
    "gn:name":"Aktanbelen",
    "gn:population":0,
    "gn:timezone":"Europe/Istanbul",
    "iso:country":"TR",
    "name:tur_x_preferred":[
        "Aktanbelen"
    ],
    "wof:name":"Aktanbelen",
    "wof:placetype":"locality"
},
  "geometry": {"coordinates":[29.31108,36.47379],"type":"Point"}
}