{
  "type": "Feature",
  "properties": {
    "gn:admin1_code":"25",
    "gn:asciiname":"Yesilova",
    "gn:country_code":"TR",
    "gn:dem":1985,
    "gn:feature_class":"P",
    "gn:feature_code":"PPL",
    "gn:name":"Ye\u015filova",
    "gn:population":0,
    "gn:timezone":"Europe/Istanbul",
    "iso:country":"TR",
    "name:tur_x_preferred":[
        "Ye\u015filova"
    ],
    "wof:name":"Yesilova",
    "wof:placetype":"locality"
},
  "geometry": {"coordinates":[40.81086,40.19891],"type":"Point"}
}