{
  "type": "Feature",
  "properties": {
    "gn:admin1_code":"16.0",
    "gn:asciiname":"Incirlipinar",
    "gn:country_code":"TR",
    "gn:dem":39,
    "gn:feature_class":"P",
    "gn:feature_code":"PPL",
    "gn:name":"\u0130ncirlip\u0131nar",
    "gn:population":0,
    "gn:timezone":"Europe/Istanbul",
    "iso:country":"TR",
    "name:tur_x_preferred":[
        "\u0130ncip\u0131nar"
    ],
    "name:tur_x_variant":[
        "\u0130ncirlip\u0131nar"
    ],
    "name:und_x_variant":[
        "Yaveyli",
        "\u0130ncilip\u0131nar"
    ],
    "wof:name":"Incirlipinar",
    "wof:placetype":"locality"
},
  "geometry": {"coordinates":[28.47333,40.09194],"type":"Point"}
}