{
  "type": "Feature",
  "properties": {
    "gn:country":"TR",
    "gn:fcode":"PPL",
    "gn:pop":449,
    "iso:country":"TR",
    "name:tur_x_preferred":[
        "Korukcu"
    ],
    "name:tur_x_variant":[
        "Koruk\u00e7u"
    ],
    "name:unk_x_variant":[
        "Korukchu"
    ],
    "qs:name":"Korukcu",
    "qs:photos_9r":0,
    "qs:photos_sr":0,
    "qs:pop_sr":"2",
    "wof:name":"Korukcu",
    "wof:placetype":"locality",
    "wof:population":449
},
  "geometry": {"coordinates":[40.73333,37.83333],"type":"Point"}
}