{
  "type": "Feature",
  "properties": {
    "gn:admin1_code":"63.0",
    "gn:asciiname":"Divrigi",
    "gn:country_code":"TR",
    "gn:dem":565,
    "gn:feature_class":"P",
    "gn:feature_code":"PPL",
    "gn:name":"D\u0131vr\u0131\u011f\u0131",
    "gn:population":0,
    "gn:timezone":"Europe/Istanbul",
    "iso:country":"TR",
    "name:tur_x_preferred":[
        "D\u0131vr\u0131\u011f\u0131"
    ],
    "wof:name":"Divrigi",
    "wof:placetype":"locality"
},
  "geometry": {"coordinates":[38.10909,37.02784000000001],"type":"Point"}
}