{
  "type": "Feature",
  "properties": {
    "iso:country":"TR",
    "name:und_x_variant":[
        "Hizirbey"
    ],
    "qs:gn_adm0_cc":"TR",
    "qs:gn_local":738648,
    "qs:local_max":64,
    "qs:local_sum":64,
    "qs:localhoods":1,
    "qs:name":"Hizirbey",
    "qs:name_adm0":"Turkey",
    "qs:name_adm1":"Trabzon",
    "qs:name_adm2":"Merkez",
    "qs:name_local":"Trabzon",
    "qs:photo_max":22,
    "qs:photo_sum":64,
    "qs:placetype":"Suburb",
    "qs:quad_count":5,
    "qs:woe_adm0":23424969,
    "qs:woe_adm1":2347312,
    "qs:woe_adm2":29390575,
    "qs:woe_lau":0,
    "qs:woe_local":2344452,
    "qs:woe_ver":"7.10.0",
    "wof:name":"Hizirbey",
    "wof:placetype":"neighbourhood"
},
  "geometry": {"coordinates":[39.712272,41.009148],"type":"Point"}
}