{
  "type": "Feature",
  "properties": {
    "gn:admin1_code":"26",
    "gn:asciiname":"Tasoluk",
    "gn:country_code":"TR",
    "gn:dem":1533,
    "gn:feature_class":"P",
    "gn:feature_code":"PPL",
    "gn:name":"Ta\u015foluk",
    "gn:population":0,
    "gn:timezone":"Europe/Istanbul",
    "iso:country":"TR",
    "wof:name":"Tasoluk",
    "wof:placetype":"locality"
},
  "geometry": {"coordinates":[30.38681,39.39164],"type":"Point"}
}