{
  "type": "Feature",
  "properties": {
    "gn:admin1_code":"55.0",
    "gn:asciiname":"Eynekaraca",
    "gn:country_code":"TR",
    "gn:dem":958,
    "gn:feature_class":"P",
    "gn:feature_code":"PPL",
    "gn:name":"Eynekaraca",
    "gn:population":0,
    "gn:timezone":"Europe/Istanbul",
    "iso:country":"TR",
    "wof:name":"Eynekaraca",
    "wof:placetype":"locality"
},
  "geometry": {"coordinates":[35.79472,40.91887],"type":"Point"}
}