{
  "type": "Feature",
  "properties": {
    "iso:country":"TR",
    "wof:name":"Mehmet Akif",
    "wof:placetype":"neighbourhood"
},
  "geometry": {"coordinates":[28.80478550460841,41.05624443258972],"type":"Point"}
}