{
  "type": "Feature",
  "properties": {
    "gn:admin1_code":"58",
    "gn:asciiname":"Canakci",
    "gn:country_code":"TR",
    "gn:dem":1351,
    "gn:feature_class":"P",
    "gn:feature_code":"PPL",
    "gn:name":"\u00c7anak\u00e7\u0131",
    "gn:population":0,
    "gn:timezone":"Europe/Istanbul",
    "iso:country":"TR",
    "wof:name":"Canakci",
    "wof:placetype":"locality"
},
  "geometry": {"coordinates":[36.37732000000001,39.58073],"type":"Point"}
}