{
  "type": "Feature",
  "properties": {
    "gn:admin1_code":"43",
    "gn:asciiname":"Ilicikviran",
    "gn:country_code":"TR",
    "gn:dem":1089,
    "gn:feature_class":"P",
    "gn:feature_code":"PPL",
    "gn:name":"Ilicikviran",
    "gn:population":0,
    "gn:timezone":"Europe/Istanbul",
    "iso:country":"TR",
    "name:tur_x_preferred":[
        "Ilicikviran"
    ],
    "name:tur_x_variant":[
        "\u0130l\u00e7ik\u00f6ren"
    ],
    "name:und_x_variant":[
        "\u0130lcikviran"
    ],
    "wof:name":"Ilicikviran",
    "wof:placetype":"locality"
},
  "geometry": {"coordinates":[29.60383,39.14158],"type":"Point"}
}