{
  "type": "Feature",
  "properties": {
    "gn:country":"TR",
    "gn:fcode":"PPL",
    "gn:pop":272,
    "iso:country":"TR",
    "name:unk_x_variant":[
        "Mikhrap"
    ],
    "qs:name":"Mihrap",
    "qs:photos_9r":0,
    "qs:photos_sr":0,
    "qs:pop_sr":"2",
    "wof:name":"Mihrap",
    "wof:placetype":"locality",
    "wof:population":272
},
  "geometry": {"coordinates":[37.86778,36.93333],"type":"Point"}
}