{
  "type": "Feature",
  "properties": {
    "gn:admin1_code":"17.0",
    "gn:asciiname":"Adatepe",
    "gn:country_code":"TR",
    "gn:dem":28,
    "gn:feature_class":"P",
    "gn:feature_code":"PPL",
    "gn:name":"Adatepe",
    "gn:population":0,
    "gn:timezone":"Europe/Istanbul",
    "iso:country":"TR",
    "name:aze_x_preferred":[
        "Adat\u0259p\u0259"
    ],
    "name:ceb_x_preferred":[
        "Adatepe"
    ],
    "name:tur_x_preferred":[
        "Adatepe"
    ],
    "name:und_x_variant":[
        "Adatepek\u00f6y\u00fc"
    ],
    "wof:name":"Adatepe",
    "wof:placetype":"locality"
},
  "geometry": {"coordinates":[26.79066,40.39437],"type":"Point"}
}