{
  "type": "Feature",
  "properties": {
    "gn:admin1_code":"59.0",
    "gn:asciiname":"Karakavak",
    "gn:country_code":"TR",
    "gn:dem":39,
    "gn:feature_class":"P",
    "gn:feature_code":"PPL",
    "gn:name":"Karakavak",
    "gn:population":0,
    "gn:timezone":"Europe/Istanbul",
    "iso:country":"TR",
    "name:tur_x_preferred":[
        "Karakavak"
    ],
    "wof:name":"Karakavak",
    "wof:placetype":"locality"
},
  "geometry": {"coordinates":[27.07224,41.32716],"type":"Point"}
}