{
  "type": "Feature",
  "properties": {
    "gn:admin1_code":"93",
    "gn:asciiname":"Sirt",
    "gn:country_code":"TR",
    "gn:dem":384,
    "gn:feature_class":"P",
    "gn:feature_code":"PPL",
    "gn:name":"S\u0131rt",
    "gn:population":0,
    "gn:timezone":"Europe/Istanbul",
    "iso:country":"TR",
    "wof:name":"Sirt",
    "wof:placetype":"locality"
},
  "geometry": {"coordinates":[30.94019,40.80686],"type":"Point"}
}