{
  "type": "Feature",
  "properties": {
    "gn:admin1_code":"89.0",
    "gn:asciiname":"Samlar",
    "gn:country_code":"TR",
    "gn:dem":837,
    "gn:feature_class":"P",
    "gn:feature_code":"PPL",
    "gn:name":"\u015eamlar",
    "gn:population":0,
    "gn:timezone":"Europe/Istanbul",
    "iso:country":"TR",
    "wof:name":"Samlar",
    "wof:placetype":"locality"
},
  "geometry": {"coordinates":[32.8475,41.10333],"type":"Point"}
}