{
  "type": "Feature",
  "properties": {
    "gn:admin1_code":"21.0",
    "gn:asciiname":"Abali",
    "gn:country_code":"TR",
    "gn:dem":1058,
    "gn:feature_class":"P",
    "gn:feature_code":"PPL",
    "gn:name":"Abal\u0131",
    "gn:population":0,
    "gn:timezone":"Europe/Istanbul",
    "iso:country":"TR",
    "name:ara_x_preferred":[
        "\u0622\u0628\u0639\u0644\u064a"
    ],
    "name:azb_x_preferred":[
        "\u0622\u0628\u0639\u0644\u06cc"
    ],
    "name:bul_x_preferred":[
        "\u0410\u0431\u0430\u043b\u0438"
    ],
    "name:fas_x_preferred":[
        "\u0622\u0628\u0639\u0644\u06cc"
    ],
    "name:mlg_x_preferred":[
        "Abali"
    ],
    "name:tur_x_preferred":[
        "Abal\u0131"
    ],
    "name:tur_x_variant":[
        "Abali"
    ],
    "wof:name":"Abali",
    "wof:placetype":"locality"
},
  "geometry": {"coordinates":[40.54224,38.51654],"type":"Point"}
}