{
  "type": "Feature",
  "properties": {
    "gn:admin1_code":"21.0",
    "gn:asciiname":"Abali",
    "gn:country_code":"TR",
    "gn:dem":1058,
    "gn:feature_class":"P",
    "gn:feature_code":"PPL",
    "gn:name":"Abal\u0131",
    "gn:population":0,
    "gn:timezone":"Europe/Istanbul",
    "iso:country":"TR",
    "name:tur_x_preferred":[
        "Abal\u0131"
    ],
    "wof:name":"Abali",
    "wof:placetype":"locality"
},
  "geometry": {"coordinates":[40.54224,38.51654],"type":"Point"}
}