{
  "type": "Feature",
  "properties": {
    "gn:admin1_code":"8.0",
    "gn:asciiname":"Elmali",
    "gn:country_code":"TR",
    "gn:dem":1010,
    "gn:feature_class":"P",
    "gn:feature_code":"PPL",
    "gn:name":"Elmal\u0131",
    "gn:population":0,
    "gn:timezone":"Europe/Istanbul",
    "iso:country":"TR",
    "wof:name":"Elmali",
    "wof:placetype":"locality"
},
  "geometry": {"coordinates":[42.31949,41.26232],"type":"Point"}
}