{
  "type": "Feature",
  "properties": {
    "gn:admin1_code":"35",
    "gn:admin2_code":"8632420.0",
    "gn:asciiname":"Cinardibi",
    "gn:country_code":"TR",
    "gn:dem":708,
    "gn:feature_class":"P",
    "gn:feature_code":"PPL",
    "gn:name":"\u00c7\u0131nardibi",
    "gn:population":0,
    "gn:timezone":"Europe/Istanbul",
    "iso:country":"TR",
    "name:rus_x_preferred":[
        "\u041e\u0441\u043c\u0430\u043d\u0438\u0435"
    ],
    "name:tur_x_preferred":[
        "\u00c7\u0131nardibi"
    ],
    "name:tur_x_variant":[
        "Kavakalan",
        "Osmaniye"
    ],
    "wof:name":"Cinardibi",
    "wof:placetype":"locality"
},
  "geometry": {"coordinates":[27.51919,38.29128],"type":"Point"}
}