{
  "type": "Feature",
  "properties": {
    "iso:country":"TR",
    "name:ara_x_preferred":[
        "\u0645\u0637\u0627\u0631 \u0643\u0648\u062a\u0627\u0647\u064a\u0627"
    ],
    "name:ceb_x_preferred":[
        "K\u00fctahya Airport"
    ],
    "name:eng_x_preferred":[
        "K\u00fctahya Air Base"
    ],
    "name:jpn_x_preferred":[
        "\u30ad\u30e5\u30bf\u30d2\u30e4\u7a7a\u8ecd\u57fa\u5730"
    ],
    "name:msa_x_preferred":[
        "Pengkalan Udara Kutahya"
    ],
    "name:tur_x_preferred":[
        "K\u00fctahya Askeri Havaalan\u0131"
    ],
    "oa:elevation_ft":"3026",
    "oa:type":"small_airport",
    "woe:hierarchy":{
        "country_id":23424969,
        "county_id":29390571,
        "planet_id":1,
        "state_id":2347297
    },
    "wof:name":"Kutahya Airport",
    "wof:placetype":"campus"
},
  "geometry": {"coordinates":[30.01666667,39.42666667],"type":"Point"}
}