{
  "type": "Feature",
  "properties": {
    "gn:admin1_code":"10",
    "gn:asciiname":"Yagcilar",
    "gn:country_code":"TR",
    "gn:dem":364,
    "gn:feature_class":"P",
    "gn:feature_code":"PPLA3",
    "gn:name":"Ya\u011fc\u0131lar",
    "gn:population":0,
    "gn:timezone":"Europe/Istanbul",
    "iso:country":"TR",
    "name:tur_x_preferred":[
        "Ya\u011fc\u0131lar"
    ],
    "wof:name":"Yagcilar",
    "wof:placetype":"locality"
},
  "geometry": {"coordinates":[28.38109,39.41712],"type":"Point"}
}