{
  "type": "Feature",
  "properties": {
    "gn:admin1_code":"12",
    "gn:asciiname":"Mollaibrahim",
    "gn:country_code":"TR",
    "gn:dem":1245,
    "gn:feature_class":"P",
    "gn:feature_code":"PPL",
    "gn:name":"Mollaibrahim",
    "gn:population":0,
    "gn:timezone":"Europe/Istanbul",
    "iso:country":"TR",
    "name:tur_x_preferred":[
        "Mollaibrahim"
    ],
    "wof:name":"Mollaibrahim",
    "wof:placetype":"locality"
},
  "geometry": {"coordinates":[40.23562,38.62804000000001],"type":"Point"}
}