{
  "type": "Feature",
  "properties": {
    "gn:admin1_code":"84.0",
    "gn:asciiname":"Atcilar",
    "gn:country_code":"TR",
    "gn:dem":1602,
    "gn:feature_class":"P",
    "gn:feature_code":"PPL",
    "gn:name":"Atc\u0131lar",
    "gn:population":0,
    "gn:timezone":"Europe/Istanbul",
    "iso:country":"TR",
    "name:tur_x_preferred":[
        "Atc\u0131lar"
    ],
    "name:und_x_variant":[
        "At\u00e7\u0131lar"
    ],
    "wof:name":"Atcilar",
    "wof:placetype":"locality"
},
  "geometry": {"coordinates":[43.3566,40.77331],"type":"Point"}
}