{
  "type": "Feature",
  "properties": {
    "gn:admin1_code":"32",
    "gn:asciiname":"Sogucak",
    "gn:country_code":"TR",
    "gn:dem":870,
    "gn:feature_class":"P",
    "gn:feature_code":"PPL",
    "gn:name":"So\u011fucak",
    "gn:population":0,
    "gn:timezone":"Europe/Istanbul",
    "iso:country":"TR",
    "name:tur_x_preferred":[
        "So\u011fucak"
    ],
    "name:tur_x_variant":[
        "K\u00f6rtahta"
    ],
    "wof:name":"Sogucak",
    "wof:placetype":"locality"
},
  "geometry": {"coordinates":[34.54722,36.97065],"type":"Point"}
}