{
  "type": "Feature",
  "properties": {
    "gn:admin1_code":"02",
    "gn:asciiname":"Konacik",
    "gn:country_code":"TR",
    "gn:dem":772,
    "gn:feature_class":"P",
    "gn:feature_code":"PPL",
    "gn:name":"Konac\u0131k",
    "gn:population":0,
    "gn:timezone":"Europe/Istanbul",
    "iso:country":"TR",
    "name:tur_x_preferred":[
        "Konac\u0131k"
    ],
    "wof:name":"Konacik",
    "wof:placetype":"locality"
},
  "geometry": {"coordinates":[39.21527,38.11718],"type":"Point"}
}