{
  "type": "Feature",
  "properties": {
    "gn:admin1_code":"09",
    "gn:asciiname":"Haydarli",
    "gn:country_code":"TR",
    "gn:dem":18,
    "gn:feature_class":"P",
    "gn:feature_code":"PPL",
    "gn:name":"Haydarl\u0131",
    "gn:population":0,
    "gn:timezone":"Europe/Istanbul",
    "iso:country":"TR",
    "name:tur_x_preferred":[
        "Haydarl\u0131"
    ],
    "wof:name":"Haydarli",
    "wof:placetype":"locality"
},
  "geometry": {"coordinates":[27.56831,37.73377],"type":"Point"}
}