{
  "type": "Feature",
  "properties": {
    "gn:admin1_code":"21.0",
    "gn:asciiname":"Inkaya",
    "gn:country_code":"TR",
    "gn:dem":791,
    "gn:feature_class":"P",
    "gn:feature_code":"PPL",
    "gn:name":"\u0130nkaya",
    "gn:population":0,
    "gn:timezone":"Europe/Istanbul",
    "iso:country":"TR",
    "name:tur_x_preferred":[
        "\u0130nkaya"
    ],
    "wof:name":"Inkaya",
    "wof:placetype":"locality"
},
  "geometry": {"coordinates":[41.04469,38.34592],"type":"Point"}
}