{
  "type": "Feature",
  "properties": {
    "gn:admin1_code":"89.0",
    "gn:asciiname":"Mehterler",
    "gn:country_code":"TR",
    "gn:dem":901,
    "gn:feature_class":"P",
    "gn:feature_code":"PPL",
    "gn:name":"Mehterler",
    "gn:population":0,
    "gn:timezone":"Europe/Istanbul",
    "iso:country":"TR",
    "name:und_x_variant":[
        "Tilkio\u011flu"
    ],
    "wof:name":"Mehterler",
    "wof:placetype":"locality"
},
  "geometry": {"coordinates":[32.7736,41.0278],"type":"Point"}
}