{
  "type": "Feature",
  "properties": {
    "gn:admin1_code":"09",
    "gn:asciiname":"Gokyaka",
    "gn:country_code":"TR",
    "gn:dem":161,
    "gn:feature_class":"P",
    "gn:feature_code":"PPL",
    "gn:name":"G\u00f6kyaka",
    "gn:population":0,
    "gn:timezone":"Europe/Istanbul",
    "iso:country":"TR",
    "name:tur_x_preferred":[
        "G\u00f6kyaka"
    ],
    "wof:name":"Gokyaka",
    "wof:placetype":"locality"
},
  "geometry": {"coordinates":[27.92916,37.63669],"type":"Point"}
}