{
  "type": "Feature",
  "properties": {
    "gn:admin1_code":"54.0",
    "gn:asciiname":"Daricayiri",
    "gn:cc2":"TR",
    "gn:country_code":"TR",
    "gn:dem":17,
    "gn:feature_class":"P",
    "gn:feature_code":"PPL",
    "gn:name":"Dar\u0131\u00e7ay\u0131r\u0131",
    "gn:population":0,
    "gn:timezone":"Europe/Istanbul",
    "iso:country":"TR",
    "name:und_x_variant":[
        "Dar\u0131\u00e7ay\u0131r",
        "Dar\u0131\u00e7ay\u0131r\u0131"
    ],
    "wof:name":"Daricayiri",
    "wof:placetype":"locality"
},
  "geometry": {"coordinates":[30.64222,41.03861],"type":"Point"}
}