{
  "type": "Feature",
  "properties": {
    "gn:admin1_code":"65.0",
    "gn:asciiname":"Girdil",
    "gn:country_code":"TR",
    "gn:dem":2126,
    "gn:feature_class":"P",
    "gn:feature_code":"PPL",
    "gn:name":"Girdil",
    "gn:population":0,
    "gn:timezone":"Europe/Istanbul",
    "iso:country":"TR",
    "name:tur_x_preferred":[
        "Girdil"
    ],
    "wof:name":"Girdil",
    "wof:placetype":"locality"
},
  "geometry": {"coordinates":[44.11716,38.73486],"type":"Point"}
}