{
  "type": "Feature",
  "properties": {
    "gn:admin1_code":"17.0",
    "gn:asciiname":"Ayitdere",
    "gn:country_code":"TR",
    "gn:dem":61,
    "gn:feature_class":"P",
    "gn:feature_code":"PPL",
    "gn:name":"Ay\u0131tdere",
    "gn:population":0,
    "gn:timezone":"Europe/Istanbul",
    "iso:country":"TR",
    "name:und_x_variant":[
        "Ay\u0131tdere K\u00f6y\u00fc",
        "Ay\u0131tdere"
    ],
    "wof:name":"Ayitdere",
    "wof:placetype":"locality"
},
  "geometry": {"coordinates":[27.05217,40.36303],"type":"Point"}
}