{
  "type": "Feature",
  "properties": {
    "gn:admin1_code":"59.0",
    "gn:asciiname":"Kocaali",
    "gn:cc2":"TR",
    "gn:country_code":"TR",
    "gn:dem":205,
    "gn:feature_class":"P",
    "gn:feature_code":"PPL",
    "gn:name":"Kocaali",
    "gn:population":0,
    "gn:timezone":"Europe/Istanbul",
    "iso:country":"TR",
    "name:ceb_x_preferred":[
        "Kocaali \u0130l\u00e7esi"
    ],
    "name:deu_x_preferred":[
        "Kocaali"
    ],
    "name:fas_x_preferred":[
        "\u06a9\u0648\u062c\u0627\u0644\u06cc"
    ],
    "name:fra_x_preferred":[
        "Kocaali"
    ],
    "name:gag_x_preferred":[
        "Kocaali"
    ],
    "name:lrc_x_preferred":[
        "\u06a9\u0648\u062c\u0627\u0644\u06cc"
    ],
    "name:mrj_x_preferred":[
        "\u041a\u043e\u0434\u0436\u0430\u0430\u043b\u0438"
    ],
    "name:msa_x_preferred":[
        "Kocaali"
    ],
    "name:nno_x_preferred":[
        "Kocaali"
    ],
    "name:nor_x_preferred":[
        "Kocaali"
    ],
    "name:pnb_x_preferred":[
        "\u0636\u0644\u0639 \u06a9\u0648\u062c\u0627\u0644\u06cc"
    ],
    "name:swa_x_preferred":[
        "Kocaali"
    ],
    "name:tur_x_preferred":[
        "Kocaali"
    ],
    "name:und_x_variant":[
        "Kocaeli",
        "Kocal\u0131",
        "Kocaalik\u00f6y\u00fc"
    ],
    "name:urd_x_preferred":[
        "\u06a9\u0648\u0686\u0627\u0644\u06cc"
    ],
    "name:vie_x_preferred":[
        "Kocaali"
    ],
    "name:zho_x_preferred":[
        "\u79d1\u8cc8\u963f\u91cc"
    ],
    "wof:name":"Kocaali",
    "wof:placetype":"locality"
},
  "geometry": {"coordinates":[27.00167,40.60861],"type":"Point"}
}