{
  "type": "Feature",
  "properties": {
    "gn:admin1_code":"59.0",
    "gn:asciiname":"Kocaali",
    "gn:cc2":"TR",
    "gn:country_code":"TR",
    "gn:dem":205,
    "gn:feature_class":"P",
    "gn:feature_code":"PPL",
    "gn:name":"Kocaali",
    "gn:population":0,
    "gn:timezone":"Europe/Istanbul",
    "iso:country":"TR",
    "name:und_x_variant":[
        "Kocaeli",
        "Kocal\u0131",
        "Kocaalik\u00f6y\u00fc",
        "Kocaali"
    ],
    "wof:name":"Kocaali",
    "wof:placetype":"locality"
},
  "geometry": {"coordinates":[27.00167,40.60861],"type":"Point"}
}