{
  "type": "Feature",
  "properties": {
    "gn:admin1_code":"90",
    "gn:asciiname":"Karbeyaz",
    "gn:country_code":"TR",
    "gn:dem":620,
    "gn:feature_class":"P",
    "gn:feature_code":"PPL",
    "gn:name":"Karbeyaz",
    "gn:population":0,
    "gn:timezone":"Europe/Istanbul",
    "iso:country":"TR",
    "name:ceb_x_preferred":[
        "Yi\u011fityolu"
    ],
    "name:tur_x_preferred":[
        "Karbeyaz"
    ],
    "name:vie_x_preferred":[
        "Karbeyaz"
    ],
    "wof:name":"Karbeyaz",
    "wof:placetype":"locality"
},
  "geometry": {"coordinates":[36.96028,36.86355],"type":"Point"}
}