{
  "type": "Feature",
  "properties": {
    "gn:admin1_code":"37",
    "gn:asciiname":"Besoren",
    "gn:country_code":"TR",
    "gn:dem":656,
    "gn:feature_class":"P",
    "gn:feature_code":"PPL",
    "gn:name":"Be\u015f\u00f6ren",
    "gn:population":0,
    "gn:timezone":"Europe/Istanbul",
    "iso:country":"TR",
    "wof:name":"Besoren",
    "wof:placetype":"locality"
},
  "geometry": {"coordinates":[33.63021,41.87523],"type":"Point"}
}