{
  "type": "Feature",
  "properties": {
    "gn:admin1_code":"17.0",
    "gn:asciiname":"Sehitlik",
    "gn:country_code":"TR",
    "gn:dem":143,
    "gn:feature_class":"P",
    "gn:feature_code":"PPL",
    "gn:name":"\u015eehitlik",
    "gn:population":0,
    "gn:timezone":"Europe/Istanbul",
    "iso:country":"TR",
    "name:und_x_variant":[
        "Sehillik",
        "\u015eehitlik"
    ],
    "wof:name":"Sehitlik",
    "wof:placetype":"locality"
},
  "geometry": {"coordinates":[26.82994,40.54195],"type":"Point"}
}