{
  "type": "Feature",
  "properties": {
    "gn:admin1_code":"43",
    "gn:asciiname":"Goceri",
    "gn:country_code":"TR",
    "gn:dem":1144,
    "gn:feature_class":"P",
    "gn:feature_code":"PPL",
    "gn:name":"G\u00f6\u00e7eri",
    "gn:population":0,
    "gn:timezone":"Europe/Istanbul",
    "iso:country":"TR",
    "wof:name":"Goceri",
    "wof:placetype":"locality"
},
  "geometry": {"coordinates":[30.27889,39.27083],"type":"Point"}
}