{
  "type": "Feature",
  "properties": {
    "gn:admin1_code":"10",
    "gn:asciiname":"Celebiler",
    "gn:country_code":"TR",
    "gn:dem":324,
    "gn:feature_class":"P",
    "gn:feature_code":"PPL",
    "gn:name":"Celebiler",
    "gn:population":0,
    "gn:timezone":"Europe/Istanbul",
    "iso:country":"TR",
    "name:tur_x_preferred":[
        "Celebiler"
    ],
    "wof:name":"Celebiler",
    "wof:placetype":"locality"
},
  "geometry": {"coordinates":[28.17762,39.29635],"type":"Point"}
}