{
  "type": "Feature",
  "properties": {
    "gn:admin1_code":"52.0",
    "gn:asciiname":"Musakirik",
    "gn:country_code":"TR",
    "gn:dem":1154,
    "gn:feature_class":"P",
    "gn:feature_code":"PPL",
    "gn:name":"Musak\u0131r\u0131k",
    "gn:population":0,
    "gn:timezone":"Europe/Istanbul",
    "iso:country":"TR",
    "wof:name":"Musakirik",
    "wof:placetype":"locality"
},
  "geometry": {"coordinates":[37.96252,40.75506],"type":"Point"}
}