{
  "type": "Feature",
  "properties": {
    "gn:admin1_code":"31",
    "gn:asciiname":"Haymeseki",
    "gn:country_code":"TR",
    "gn:dem":218,
    "gn:feature_class":"P",
    "gn:feature_code":"PPL",
    "gn:name":"Haymeseki",
    "gn:population":0,
    "gn:timezone":"Europe/Istanbul",
    "iso:country":"TR",
    "name:tur_x_preferred":[
        "Haymeseki"
    ],
    "name:tur_x_variant":[
        "Haymaseki"
    ],
    "name:und_x_variant":[
        "Haymoseki",
        "Haymanseki"
    ],
    "wof:name":"Haymeseki",
    "wof:placetype":"locality"
},
  "geometry": {"coordinates":[35.8772,36.35067],"type":"Point"}
}