{
  "type": "Feature",
  "properties": {
    "gn:country":"TR",
    "gn:fcode":"PPL",
    "gn:pop":161,
    "iso:country":"TR",
    "name:cat_x_preferred":[
        "Belentepe"
    ],
    "name:ces_x_preferred":[
        "Belentepe"
    ],
    "name:dan_x_preferred":[
        "Belentepe"
    ],
    "name:deu_x_preferred":[
        "Belentepe"
    ],
    "name:eng_x_preferred":[
        "Belentepe"
    ],
    "name:eus_x_preferred":[
        "Belentepe"
    ],
    "name:fin_x_preferred":[
        "Belentepe"
    ],
    "name:fra_x_preferred":[
        "Belentepe"
    ],
    "name:glg_x_preferred":[
        "Belentepe"
    ],
    "name:ind_x_preferred":[
        "Belentepe"
    ],
    "name:ita_x_preferred":[
        "Belentepe"
    ],
    "name:nld_x_preferred":[
        "Belentepe"
    ],
    "name:nno_x_preferred":[
        "Belentepe"
    ],
    "name:nob_x_preferred":[
        "Belentepe"
    ],
    "name:oci_x_preferred":[
        "Belentepe"
    ],
    "name:pol_x_preferred":[
        "Belentepe"
    ],
    "name:por_x_preferred":[
        "Belentepe"
    ],
    "name:ron_x_preferred":[
        "Belentepe"
    ],
    "name:sco_x_preferred":[
        "Belentepe"
    ],
    "name:slk_x_preferred":[
        "Belentepe"
    ],
    "name:slv_x_preferred":[
        "Belentepe"
    ],
    "name:spa_x_preferred":[
        "Belentepe"
    ],
    "name:swe_x_preferred":[
        "Belentepe"
    ],
    "name:tgl_x_preferred":[
        "Belentepe"
    ],
    "name:tur_x_preferred":[
        "Belentepe"
    ],
    "name:vie_x_preferred":[
        "Belentepe"
    ],
    "name:war_x_preferred":[
        "Belentepe"
    ],
    "qs:name":"Belentepe",
    "qs:photos_9r":0,
    "qs:photos_sr":0,
    "qs:pop_sr":"1",
    "wof:name":"Belentepe",
    "wof:placetype":"locality",
    "wof:population":161
},
  "geometry": {"coordinates":[37.03417,36.96306],"type":"Point"}
}