{
  "type": "Feature",
  "properties": {
    "gn:admin1_code":"31",
    "gn:asciiname":"Tomruk",
    "gn:country_code":"TR",
    "gn:dem":27,
    "gn:feature_class":"P",
    "gn:feature_code":"PPL",
    "gn:name":"Tomruk",
    "gn:population":0,
    "gn:timezone":"Europe/Istanbul",
    "iso:country":"TR",
    "name:tur_x_preferred":[
        "Tomruk"
    ],
    "wof:name":"Tomruk",
    "wof:placetype":"locality"
},
  "geometry": {"coordinates":[35.81513,36.2594],"type":"Point"}
}