{
  "type": "Feature",
  "properties": {
    "gn:admin1_code":"09",
    "gn:asciiname":"Ortakci",
    "gn:country_code":"TR",
    "gn:dem":227,
    "gn:feature_class":"P",
    "gn:feature_code":"PPL",
    "gn:name":"Ortak\u00e7\u0131",
    "gn:population":0,
    "gn:timezone":"Europe/Istanbul",
    "iso:country":"TR",
    "name:tur_x_preferred":[
        "Ortak\u00e7\u0131"
    ],
    "wof:name":"Ortakci",
    "wof:placetype":"locality"
},
  "geometry": {"coordinates":[28.72318,37.97381],"type":"Point"}
}