{
  "type": "Feature",
  "properties": {
    "gn:admin1_code":"38",
    "gn:asciiname":"Kirkpinar",
    "gn:country_code":"TR",
    "gn:dem":1694,
    "gn:feature_class":"P",
    "gn:feature_code":"PPL",
    "gn:name":"K\u0131rkp\u0131nar",
    "gn:population":0,
    "gn:timezone":"Europe/Istanbul",
    "iso:country":"TR",
    "name:und_x_variant":[
        "K\u0131rkp\u0131nar K\u00f6y\u00fc",
        "K\u0131rkp\u0131nar"
    ],
    "wof:name":"Kirkpinar",
    "wof:placetype":"locality"
},
  "geometry": {"coordinates":[36.77579,38.95343],"type":"Point"}
}