{
  "type": "Feature",
  "properties": {
    "gn:admin1_code":"52.0",
    "gn:asciiname":"Fatih",
    "gn:country_code":"TR",
    "gn:dem":511,
    "gn:feature_class":"P",
    "gn:feature_code":"PPL",
    "gn:name":"Fatih",
    "gn:population":0,
    "gn:timezone":"Europe/Istanbul",
    "iso:country":"TR",
    "name:afr_x_preferred":[
        "Fatih"
    ],
    "name:ara_x_preferred":[
        "\u0627\u0644\u0641\u0627\u062a\u062d"
    ],
    "name:ast_x_preferred":[
        "Fatih"
    ],
    "name:ava_x_preferred":[
        "\u0424\u0430\u0442\u0438\u0445\u0406"
    ],
    "name:aze_x_preferred":[
        "Fateh"
    ],
    "name:bos_x_preferred":[
        "Fatih"
    ],
    "name:bul_x_preferred":[
        "\u0424\u0430\u0442\u0438\u0445"
    ],
    "name:cat_x_preferred":[
        "Fatih"
    ],
    "name:ceb_x_preferred":[
        "Fatih"
    ],
    "name:deu_x_preferred":[
        "Fatih"
    ],
    "name:diq_x_preferred":[
        "Fatih"
    ],
    "name:ell_x_preferred":[
        "\u03a6\u03b1\u03c4\u03af\u03c7"
    ],
    "name:fas_x_preferred":[
        "\u0641\u0627\u062a\u062d"
    ],
    "name:fra_x_preferred":[
        "Fatih"
    ],
    "name:hun_x_preferred":[
        "Fatih"
    ],
    "name:hye_x_preferred":[
        "\u0556\u0561\u0569\u056b\u0570"
    ],
    "name:ind_x_preferred":[
        "Fatih"
    ],
    "name:ita_x_preferred":[
        "Fatih"
    ],
    "name:kor_x_preferred":[
        "\ud30c\ud2f0\ud750"
    ],
    "name:lat_x_preferred":[
        "Fatih"
    ],
    "name:lav_x_preferred":[
        "Fatihas rajons"
    ],
    "name:mkd_x_preferred":[
        "\u0424\u0430\u0442\u0438\u0445"
    ],
    "name:mrj_x_preferred":[
        "\u0424\u0430\u0442\u0438\u0445"
    ],
    "name:msa_x_preferred":[
        "Fatih"
    ],
    "name:nld_x_preferred":[
        "Fatih"
    ],
    "name:nor_x_preferred":[
        "Fatih"
    ],
    "name:oss_x_preferred":[
        "\u0424\u0430\u0442\u0438\u0445"
    ],
    "name:pnb_x_preferred":[
        "\u0641\u0627\u062a\u062d"
    ],
    "name:por_x_preferred":[
        "Fatih"
    ],
    "name:rus_x_preferred":[
        "\u0424\u0430\u0442\u0438\u0445"
    ],
    "name:sco_x_preferred":[
        "Fatih"
    ],
    "name:spa_x_preferred":[
        "Fatih"
    ],
    "name:swa_x_preferred":[
        "Fatih"
    ],
    "name:tur_x_preferred":[
        "Fatih"
    ],
    "name:ukr_x_preferred":[
        "\u0424\u0430\u0442\u0456\u0445"
    ],
    "name:und_x_variant":[
        "Havzikara",
        "\u00c7ay\u0131rl\u0131"
    ],
    "name:urd_x_preferred":[
        "\u0636\u0644\u0639 \u0641\u0627\u062a\u062d"
    ],
    "name:vie_x_preferred":[
        "Fatih"
    ],
    "name:zho_x_preferred":[
        "\u6cd5\u8482\u8d6b"
    ],
    "wof:name":"Fatih",
    "wof:placetype":"locality"
},
  "geometry": {"coordinates":[37.19171,40.93227],"type":"Point"}
}