{
  "type": "Feature",
  "properties": {
    "gn:admin1_code":"52.0",
    "gn:asciiname":"Fatih",
    "gn:country_code":"TR",
    "gn:dem":511,
    "gn:feature_class":"P",
    "gn:feature_code":"PPL",
    "gn:name":"Fatih",
    "gn:population":0,
    "gn:timezone":"Europe/Istanbul",
    "iso:country":"TR",
    "name:tur_x_preferred":[
        "Fatih"
    ],
    "name:und_x_variant":[
        "Havzikara",
        "\u00c7ay\u0131rl\u0131"
    ],
    "wof:name":"Fatih",
    "wof:placetype":"locality"
},
  "geometry": {"coordinates":[37.19171,40.93227],"type":"Point"}
}