{
  "type": "Feature",
  "properties": {
    "gn:country":"TR",
    "gn:fcode":"PPL",
    "gn:pop":0,
    "iso:country":"TR",
    "qs:name":"Cumhuriyet",
    "qs:name_adm0":"Turkey",
    "qs:name_adm1":"Samsun",
    "qs:photos":4,
    "qs:photos_1k":1,
    "qs:photos_9k":1,
    "qs:photos_9r":1,
    "qs:photos_all":4,
    "qs:photos_sr":1,
    "qs:placetype":"Suburb",
    "qs:pop_sr":"0",
    "wd:wordcount":1126,
    "wof:name":"Cumhuriyet",
    "wof:placetype":"neighbourhood",
    "wof:population":0
},
  "geometry": {"coordinates":[36.6884,41.2035],"type":"Point"}
}