{
  "type": "Feature",
  "properties": {
    "gn:country":"TR",
    "gn:fcode":"PPL",
    "gn:population":0,
    "iso:country":"TR",
    "name:ara_x_preferred":[
        "\u062c\u0645\u0647\u0648\u0631\u064a\u062a"
    ],
    "name:aze_x_preferred":[
        "Cumhuriyet"
    ],
    "name:bre_x_preferred":[
        "Cumhuriyet"
    ],
    "name:deu_x_preferred":[
        "Cumhuriyet"
    ],
    "name:ell_x_preferred":[
        "\u03a4\u03b6\u03bf\u03c5\u03bc\u03c7\u03bf\u03c5\u03c1\u03b9\u03ad\u03c4"
    ],
    "name:eng_x_preferred":[
        "Cumhuriyet"
    ],
    "name:fas_x_preferred":[
        "\u062c\u0645\u0647\u0648\u0631\u06cc\u062a"
    ],
    "name:fin_x_preferred":[
        "Cumhuriyet"
    ],
    "name:fra_x_preferred":[
        "Cumhuriyet"
    ],
    "name:heb_x_preferred":[
        "Cumhuriyet"
    ],
    "name:hun_x_preferred":[
        "Cumhuriyet"
    ],
    "name:hye_x_preferred":[
        "\u054b\u0578\u0582\u0574\u0570\u0578\u0582\u0580\u056b\u0575\u0565\u0569"
    ],
    "name:ita_x_preferred":[
        "Cumhuriyet"
    ],
    "name:jpn_x_preferred":[
        "\u30c1\u30e5\u30e0\u30d5\u30ea\u30a8\u30c3\u30c8"
    ],
    "name:kur_x_preferred":[
        "Cumhuriyet"
    ],
    "name:nld_x_preferred":[
        "Cumhuriyet"
    ],
    "name:nno_x_preferred":[
        "Cumhuriyet"
    ],
    "name:por_x_preferred":[
        "Cumhuriyet"
    ],
    "name:ron_x_preferred":[
        "Cumhuriyet"
    ],
    "name:rus_x_preferred":[
        "Cumhuriyet"
    ],
    "name:spa_x_preferred":[
        "Cumhuriyet"
    ],
    "name:srp_x_preferred":[
        "\u040f\u0443\u043c\u0445\u0443\u0440\u0438\u0458\u0435\u0442"
    ],
    "name:tur_x_preferred":[
        "Cumhuriyet"
    ],
    "name:ukr_x_preferred":[
        "\u041a\u0443\u043c\u0445\u0443\u0440\u0456\u0454\u0442"
    ],
    "name:vie_x_preferred":[
        "Cumhuriyet"
    ],
    "name:zho_x_preferred":[
        "\u5171\u548c"
    ],
    "qs:name":"Cumhuriyet",
    "qs:name_adm0":"Turkey",
    "qs:name_adm1":"Samsun",
    "qs:photos":4,
    "qs:photos_1k":1,
    "qs:photos_9k":1,
    "qs:photos_9r":1,
    "qs:photos_all":4,
    "qs:photos_sr":1,
    "qs:placetype":"Suburb",
    "qs:pop_sr":"0",
    "wd:wordcount":1126,
    "wof:name":"Cumhuriyet",
    "wof:placetype":"neighbourhood",
    "wof:population":0
},
  "geometry": {"coordinates":[36.6884,41.2035],"type":"Point"}
}