{
  "type": "Feature",
  "properties": {
    "gn:admin1_code":"4.0",
    "gn:asciiname":"Cicek",
    "gn:country_code":"TR",
    "gn:dem":2085,
    "gn:feature_class":"P",
    "gn:feature_code":"PPL",
    "gn:name":"\u00c7i\u00e7ek",
    "gn:population":0,
    "gn:timezone":"Europe/Istanbul",
    "iso:country":"TR",
    "name:tur_x_preferred":[
        "\u00c7i\u00e7ek"
    ],
    "wof:name":"Cicek",
    "wof:placetype":"locality"
},
  "geometry": {"coordinates":[42.72281,39.00599],"type":"Point"}
}