{
  "type": "Feature",
  "properties": {
    "gn:admin1_code":"32.0",
    "gn:asciiname":"Sariagac",
    "gn:country_code":"TR",
    "gn:dem":207,
    "gn:feature_class":"P",
    "gn:feature_code":"PPL",
    "gn:name":"Sar\u0131a\u011fa\u00e7",
    "gn:population":0,
    "gn:timezone":"Europe/Istanbul",
    "iso:country":"TR",
    "name:ceb_x_preferred":[
        "Sar\u0131a\u011fa\u00e7"
    ],
    "name:msa_x_preferred":[
        "Sar\u0131a\u011fa\u00e7"
    ],
    "name:vie_x_preferred":[
        "Sar\u0131a\u011fa\u00e7"
    ],
    "wof:name":"Sariagac",
    "wof:placetype":"locality"
},
  "geometry": {"coordinates":[32.85475,36.21608],"type":"Point"}
}