{
  "type": "Feature",
  "properties": {
    "gn:admin1_code":"14",
    "gn:asciiname":"Gokceler",
    "gn:country_code":"TR",
    "gn:dem":1231,
    "gn:feature_class":"P",
    "gn:feature_code":"PPL",
    "gn:name":"G\u00f6k\u00e7eler",
    "gn:population":0,
    "gn:timezone":"Europe/Istanbul",
    "iso:country":"TR",
    "wof:name":"Gokceler",
    "wof:placetype":"locality"
},
  "geometry": {"coordinates":[32.30101,40.80332],"type":"Point"}
}