{
  "type": "Feature",
  "properties": {
    "gn:admin1_code":"48",
    "gn:asciiname":"Muratlar",
    "gn:country_code":"TR",
    "gn:dem":616,
    "gn:feature_class":"P",
    "gn:feature_code":"PPL",
    "gn:name":"Muratlar",
    "gn:population":0,
    "gn:timezone":"Europe/Istanbul",
    "iso:country":"TR",
    "name:tur_x_preferred":[
        "Muratlar"
    ],
    "wof:name":"Muratlar",
    "wof:placetype":"locality"
},
  "geometry": {"coordinates":[28.62784000000001,37.26137],"type":"Point"}
}