{
  "type": "Feature",
  "properties": {
    "gn:admin1_code":"21.0",
    "gn:asciiname":"Horsel",
    "gn:country_code":"TR",
    "gn:dem":857,
    "gn:feature_class":"P",
    "gn:feature_code":"PPL",
    "gn:name":"Horsel",
    "gn:population":0,
    "gn:timezone":"Europe/Istanbul",
    "iso:country":"TR",
    "name:tur_x_preferred":[
        "Horsel"
    ],
    "wof:name":"Horsel",
    "wof:placetype":"locality"
},
  "geometry": {"coordinates":[40.39417,38.49194],"type":"Point"}
}