{
  "type": "Feature",
  "properties": {
    "gn:admin1_code":"81",
    "gn:asciiname":"Akoluk",
    "gn:country_code":"TR",
    "gn:dem":1440,
    "gn:feature_class":"P",
    "gn:feature_code":"PPL",
    "gn:name":"Akoluk",
    "gn:population":0,
    "gn:timezone":"Europe/Istanbul",
    "iso:country":"TR",
    "wof:name":"Akoluk",
    "wof:placetype":"locality"
},
  "geometry": {"coordinates":[36.01533,37.77724],"type":"Point"}
}