{
  "type": "Feature",
  "properties": {
    "gn:admin1_code":"93.0",
    "gn:asciiname":"Acma",
    "gn:country_code":"TR",
    "gn:dem":134,
    "gn:feature_class":"P",
    "gn:feature_code":"PPL",
    "gn:name":"A\u00e7ma",
    "gn:population":0,
    "gn:timezone":"Europe/Istanbul",
    "iso:country":"TR",
    "name:und_x_variant":[
        "Eftenia\u00e7ma",
        "A\u00e7ma"
    ],
    "wof:name":"Acma",
    "wof:placetype":"locality"
},
  "geometry": {"coordinates":[31.00193,40.76279],"type":"Point"}
}