{
  "type": "Feature",
  "properties": {
    "gn:admin1_code":"21",
    "gn:asciiname":"Hasanoren",
    "gn:country_code":"TR",
    "gn:dem":804,
    "gn:feature_class":"P",
    "gn:feature_code":"PPL",
    "gn:name":"Hasan\u00f6ren",
    "gn:population":0,
    "gn:timezone":"Europe/Istanbul",
    "iso:country":"TR",
    "wof:name":"Hasanoren",
    "wof:placetype":"locality"
},
  "geometry": {"coordinates":[39.74744000000001,38.04138],"type":"Point"}
}