{
  "type": "Feature",
  "properties": {
    "gn:admin1_code":"48",
    "gn:asciiname":"Kayabasi",
    "gn:country_code":"TR",
    "gn:dem":430,
    "gn:feature_class":"P",
    "gn:feature_code":"PPL",
    "gn:name":"Kayaba\u015f\u0131",
    "gn:population":0,
    "gn:timezone":"Europe/Istanbul",
    "iso:country":"TR",
    "name:tur_x_preferred":[
        "Kayaba\u015f\u0131"
    ],
    "wof:name":"Kayabasi",
    "wof:placetype":"locality"
},
  "geometry": {"coordinates":[27.88686,37.35765],"type":"Point"}
}