{
  "type": "Feature",
  "properties": {
    "gn:admin1_code":"17.0",
    "gn:asciiname":"Kemerdere",
    "gn:country_code":"TR",
    "gn:dem":124,
    "gn:feature_class":"P",
    "gn:feature_code":"PPL",
    "gn:name":"Kemerdere",
    "gn:population":0,
    "gn:timezone":"Europe/Istanbul",
    "iso:country":"TR",
    "wof:name":"Kemerdere",
    "wof:placetype":"locality"
},
  "geometry": {"coordinates":[26.35933,39.93254],"type":"Point"}
}