{
  "type": "Feature",
  "properties": {
    "gn:admin1_code":"38",
    "gn:asciiname":"Komurkoy",
    "gn:country_code":"TR",
    "gn:dem":1511,
    "gn:feature_class":"P",
    "gn:feature_code":"PPL",
    "gn:name":"K\u00f6m\u00fcrk\u00f6y",
    "gn:population":0,
    "gn:timezone":"Europe/Istanbul",
    "iso:country":"TR",
    "name:tur_x_preferred":[
        "K\u00f6m\u00fcrk\u00f6y"
    ],
    "name:und_x_variant":[
        "Gem\u00fcr",
        "K\u00f6m\u00fcr"
    ],
    "wof:name":"Komurkoy",
    "wof:placetype":"locality"
},
  "geometry": {"coordinates":[35.74975999999999,38.50451],"type":"Point"}
}