{
  "type": "Feature",
  "properties": {
    "gn:admin1_code":"62",
    "gn:asciiname":"Kadosa",
    "gn:cc2":"TR",
    "gn:country_code":"TR",
    "gn:dem":1127,
    "gn:feature_class":"P",
    "gn:feature_code":"PPL",
    "gn:name":"Kadosa",
    "gn:population":0,
    "gn:timezone":"Europe/Istanbul",
    "iso:country":"TR",
    "name:und_x_variant":[
        "Kadaso",
        "Kadosa"
    ],
    "wof:name":"Kadosa",
    "wof:placetype":"locality"
},
  "geometry": {"coordinates":[39.58333,38.88333],"type":"Point"}
}