{
  "type": "Feature",
  "properties": {
    "iso:country":"TR",
    "name:eng_x_preferred":[
        "Anadolu Feneri"
    ],
    "name:tur_x_preferred":[
        "Anadolu Feneri"
    ],
    "name:tur_x_variant":[
        "Anadolufeneri"
    ],
    "wof:name":"Anadolu Feneri",
    "wof:placetype":"neighbourhood"
},
  "geometry": {"coordinates":[29.15385043263367,41.21603201205557],"type":"Point"}
}