{
  "type": "Feature",
  "properties": {
    "gn:admin1_code":"48",
    "gn:asciiname":"Kayacik",
    "gn:country_code":"TR",
    "gn:dem":17,
    "gn:feature_class":"P",
    "gn:feature_code":"PPL",
    "gn:name":"Kayac\u0131k",
    "gn:population":0,
    "gn:timezone":"Europe/Istanbul",
    "iso:country":"TR",
    "name:tur_x_preferred":[
        "Kayac\u0131k"
    ],
    "wof:name":"Kayacik",
    "wof:placetype":"locality"
},
  "geometry": {"coordinates":[28.79256,36.69588],"type":"Point"}
}