{
  "type": "Feature",
  "properties": {
    "gn:admin1_code":"52.0",
    "gn:asciiname":"Buhari",
    "gn:country_code":"TR",
    "gn:dem":272,
    "gn:feature_class":"P",
    "gn:feature_code":"PPL",
    "gn:name":"Buhari",
    "gn:population":0,
    "gn:timezone":"Europe/Istanbul",
    "iso:country":"TR",
    "wof:name":"Buhari",
    "wof:placetype":"locality"
},
  "geometry": {"coordinates":[37.62915,41.01334],"type":"Point"}
}