{
  "type": "Feature",
  "properties": {
    "gn:admin1_code":"39.0",
    "gn:asciiname":"Ciftlikkoy",
    "gn:country_code":"TR",
    "gn:dem":59,
    "gn:feature_class":"P",
    "gn:feature_code":"PPL",
    "gn:name":"\u00c7iftlikk\u00f6y",
    "gn:population":0,
    "gn:timezone":"Europe/Istanbul",
    "iso:country":"TR",
    "wof:name":"Ciftlikkoy",
    "wof:placetype":"locality"
},
  "geometry": {"coordinates":[27.47252000000001,41.29049000000001],"type":"Point"}
}