{
  "type": "Feature",
  "properties": {
    "gn:admin1_code":"93",
    "gn:asciiname":"Beren",
    "gn:country_code":"TR",
    "gn:dem":660,
    "gn:feature_class":"P",
    "gn:feature_code":"PPL",
    "gn:name":"Beren",
    "gn:population":0,
    "gn:timezone":"Europe/Istanbul",
    "iso:country":"TR",
    "wof:name":"Beren",
    "wof:placetype":"locality"
},
  "geometry": {"coordinates":[31.4436,40.92524],"type":"Point"}
}