{
  "type": "Feature",
  "properties": {
    "gn:admin1_code":"93",
    "gn:asciiname":"Beren",
    "gn:country_code":"TR",
    "gn:dem":660,
    "gn:feature_class":"P",
    "gn:feature_code":"PPL",
    "gn:name":"Beren",
    "gn:population":0,
    "gn:timezone":"Europe/Istanbul",
    "iso:country":"TR",
    "name:bos_x_preferred":[
        "Beren"
    ],
    "name:bul_x_preferred":[
        "\u0411\u0435\u0440\u0435\u043d"
    ],
    "name:cat_x_preferred":[
        "Beren"
    ],
    "name:ces_x_preferred":[
        "Beren"
    ],
    "name:fas_x_preferred":[
        "\u0628\u0631\u0646"
    ],
    "name:fin_x_preferred":[
        "Beren"
    ],
    "name:fra_x_preferred":[
        "Beren Erchamion"
    ],
    "name:hun_x_preferred":[
        "Beren"
    ],
    "name:ita_x_preferred":[
        "Beren"
    ],
    "name:jpn_x_preferred":[
        "\u30d9\u30ec\u30f3"
    ],
    "name:nld_x_preferred":[
        "Beren Erchamion"
    ],
    "name:nno_x_preferred":[
        "Beren"
    ],
    "name:nor_x_preferred":[
        "Beren"
    ],
    "name:pol_x_preferred":[
        "Beren"
    ],
    "name:ron_x_preferred":[
        "Beren"
    ],
    "name:rus_x_preferred":[
        "\u0411\u0435\u0440\u0435\u043d"
    ],
    "name:spa_x_preferred":[
        "Beren"
    ],
    "name:swe_x_preferred":[
        "Beren"
    ],
    "name:tha_x_preferred":[
        "\u0e40\u0e1a\u0e40\u0e23\u0e19"
    ],
    "name:tur_x_preferred":[
        "Beren"
    ],
    "wof:name":"Beren",
    "wof:placetype":"locality"
},
  "geometry": {"coordinates":[31.4436,40.92524],"type":"Point"}
}