{
  "type": "Feature",
  "properties": {
    "gn:admin1_code":"19.0",
    "gn:asciiname":"Suluklu",
    "gn:country_code":"TR",
    "gn:dem":823,
    "gn:feature_class":"P",
    "gn:feature_code":"PPL",
    "gn:name":"S\u00fcl\u00fckl\u00fc",
    "gn:population":0,
    "gn:timezone":"Europe/Istanbul",
    "iso:country":"TR",
    "wof:name":"Suluklu",
    "wof:placetype":"locality"
},
  "geometry": {"coordinates":[35.33396,40.58013],"type":"Point"}
}