{
  "type": "Feature",
  "properties": {
    "gn:admin1_code":"57.0",
    "gn:asciiname":"Eglence",
    "gn:country_code":"TR",
    "gn:dem":367,
    "gn:feature_class":"P",
    "gn:feature_code":"PPL",
    "gn:name":"E\u011flence",
    "gn:population":0,
    "gn:timezone":"Europe/Istanbul",
    "iso:country":"TR",
    "name:und_x_variant":[
        "Eylence",
        "E\u011flence"
    ],
    "wof:name":"Eglence",
    "wof:placetype":"locality"
},
  "geometry": {"coordinates":[34.74607,41.55432],"type":"Point"}
}