{
  "type": "Feature",
  "properties": {
    "gn:admin1_code":"19.0",
    "gn:asciiname":"Kuylus",
    "gn:country_code":"TR",
    "gn:dem":935,
    "gn:feature_class":"P",
    "gn:feature_code":"PPL",
    "gn:name":"Kuylus",
    "gn:population":0,
    "gn:timezone":"Europe/Istanbul",
    "iso:country":"TR",
    "wof:name":"Kuylus",
    "wof:placetype":"locality"
},
  "geometry": {"coordinates":[34.91133,40.12926],"type":"Point"}
}