{
  "type": "Feature",
  "properties": {
    "gn:admin1_code":"88.0",
    "gn:asciiname":"Kiznefer",
    "gn:country_code":"TR",
    "gn:dem":2134,
    "gn:feature_class":"P",
    "gn:feature_code":"PPL",
    "gn:name":"K\u0131znefer",
    "gn:population":0,
    "gn:timezone":"Europe/Istanbul",
    "iso:country":"TR",
    "name:tur_x_preferred":[
        "K\u0131znefer"
    ],
    "wof:name":"Kiznefer",
    "wof:placetype":"locality"
},
  "geometry": {"coordinates":[43.34303,40.02898],"type":"Point"}
}