{
  "type": "Feature",
  "properties": {
    "gn:admin1_code":"34.0",
    "gn:asciiname":"Kalemkoey",
    "gn:country_code":"TR",
    "gn:dem":90,
    "gn:feature_class":"P",
    "gn:feature_code":"PPL",
    "gn:name":"Kalemk\u00f6y",
    "gn:population":0,
    "gn:timezone":"Europe/Istanbul",
    "iso:country":"TR",
    "wof:name":"Kalemkoey",
    "wof:placetype":"locality"
},
  "geometry": {"coordinates":[29.84518,41.08794],"type":"Point"}
}