{
  "type": "Feature",
  "properties": {
    "gn:admin1_code":"8.0",
    "gn:asciiname":"Taslica",
    "gn:country_code":"TR",
    "gn:dem":565,
    "gn:feature_class":"P",
    "gn:feature_code":"PPL",
    "gn:name":"Ta\u015fl\u0131ca",
    "gn:population":0,
    "gn:timezone":"Europe/Istanbul",
    "iso:country":"TR",
    "name:und_x_variant":[
        "Ba\u015fhat\u0131la",
        "Ta\u015fl\u0131ca"
    ],
    "wof:name":"Taslica",
    "wof:placetype":"locality"
},
  "geometry": {"coordinates":[41.7155,41.17449000000001],"type":"Point"}
}