{
  "type": "Feature",
  "properties": {
    "gn:admin1_code":"57.0",
    "gn:asciiname":"Taypakli",
    "gn:country_code":"TR",
    "gn:dem":339,
    "gn:feature_class":"P",
    "gn:feature_code":"PPL",
    "gn:name":"Taypakl\u0131",
    "gn:population":0,
    "gn:timezone":"Europe/Istanbul",
    "iso:country":"TR",
    "name:und_x_variant":[
        "Taypakl\u0131 K\u00f6y\u00fc",
        "Taypakl\u0131"
    ],
    "wof:name":"Taypakli",
    "wof:placetype":"locality"
},
  "geometry": {"coordinates":[35.00603,41.84337],"type":"Point"}
}