{
  "type": "Feature",
  "properties": {
    "gn:admin1_code":"50",
    "gn:asciiname":"Karakaya",
    "gn:country_code":"TR",
    "gn:dem":1152,
    "gn:feature_class":"P",
    "gn:feature_code":"PPL",
    "gn:name":"Karakaya",
    "gn:population":0,
    "gn:timezone":"Europe/Istanbul",
    "iso:country":"TR",
    "wof:name":"Karakaya",
    "wof:placetype":"locality"
},
  "geometry": {"coordinates":[35.03333,38.71667],"type":"Point"}
}