{
  "type": "Feature",
  "properties": {
    "gn:admin1_code":"74",
    "gn:asciiname":"Mecma",
    "gn:country_code":"TR",
    "gn:dem":1754,
    "gn:feature_class":"P",
    "gn:feature_code":"PPL",
    "gn:name":"Mecma",
    "gn:population":0,
    "gn:timezone":"Europe/Istanbul",
    "iso:country":"TR",
    "wof:name":"Mecma",
    "wof:placetype":"locality"
},
  "geometry": {"coordinates":[42.71667,37.96667],"type":"Point"}
}