{
  "type": "Feature",
  "properties": {
    "gn:admin1_code":"37.0",
    "gn:asciiname":"Salicioglu",
    "gn:country_code":"TR",
    "gn:dem":833,
    "gn:feature_class":"P",
    "gn:feature_code":"PPL",
    "gn:name":"Sal\u0131c\u0131o\u011flu",
    "gn:population":0,
    "gn:timezone":"Europe/Istanbul",
    "iso:country":"TR",
    "name:und_x_variant":[
        "Sal\u0131c\u0131o\u011flu",
        "Sac\u0131o\u011flu"
    ],
    "wof:name":"Salicioglu",
    "wof:placetype":"locality"
},
  "geometry": {"coordinates":[33.7709,41.86592],"type":"Point"}
}