{
  "type": "Feature",
  "properties": {
    "gn:admin1_code":"23",
    "gn:asciiname":"Sefkat",
    "gn:country_code":"TR",
    "gn:dem":1488,
    "gn:feature_class":"P",
    "gn:feature_code":"PPL",
    "gn:name":"Sefkat",
    "gn:population":0,
    "gn:timezone":"Europe/Istanbul",
    "iso:country":"TR",
    "name:und_x_variant":[
        "\u015eevkat",
        "\u015eafakat",
        "Sefkat",
        "\u015eefakat",
        "\u015eafkat",
        "Sefekat",
        "\u015eef\u00e7at"
    ],
    "wof:name":"Sefkat",
    "wof:placetype":"locality"
},
  "geometry": {"coordinates":[38.87601,38.58765],"type":"Point"}
}