{
  "type": "Feature",
  "properties": {
    "gn:admin1_code":"11.0",
    "gn:asciiname":"Tongurlar",
    "gn:country_code":"TR",
    "gn:dem":657,
    "gn:feature_class":"P",
    "gn:feature_code":"PPL",
    "gn:name":"Tongurlar",
    "gn:population":0,
    "gn:timezone":"Europe/Istanbul",
    "iso:country":"TR",
    "name:und_x_variant":[
        "Donkurlar",
        "Tongurlar"
    ],
    "wof:name":"Tongurlar",
    "wof:placetype":"locality"
},
  "geometry": {"coordinates":[30.35182,40.30737],"type":"Point"}
}