{
  "type": "Feature",
  "properties": {
    "gn:admin1_code":"52.0",
    "gn:asciiname":"Beypinari",
    "gn:country_code":"TR",
    "gn:dem":1313,
    "gn:feature_class":"P",
    "gn:feature_code":"PPL",
    "gn:name":"Beyp\u0131nar\u0131",
    "gn:population":0,
    "gn:timezone":"Europe/Istanbul",
    "iso:country":"TR",
    "name:tur_x_preferred":[
        "Beyp\u0131nar\u0131"
    ],
    "name:und_x_variant":[
        "D\u00fczda\u011f",
        "Yakac\u0131k"
    ],
    "wof:name":"Beypinari",
    "wof:placetype":"locality"
},
  "geometry": {"coordinates":[37.25236,40.70413],"type":"Point"}
}