{
  "type": "Feature",
  "properties": {
    "gn:admin1_code":"90",
    "gn:asciiname":"Vahvin",
    "gn:country_code":"TR",
    "gn:dem":513,
    "gn:feature_class":"P",
    "gn:feature_code":"PPL",
    "gn:name":"Vahvin",
    "gn:population":0,
    "gn:timezone":"Europe/Istanbul",
    "iso:country":"TR",
    "name:und_x_variant":[
        "Vahrin",
        "Vahvin",
        "Ya\u011f\u0131zk\u00f6y"
    ],
    "wof:name":"Vahvin",
    "wof:placetype":"locality"
},
  "geometry": {"coordinates":[37.34411,36.68397],"type":"Point"}
}