{
  "type": "Feature",
  "properties": {
    "gn:admin1_code":"48",
    "gn:asciiname":"Kemer",
    "gn:country_code":"TR",
    "gn:dem":141,
    "gn:feature_class":"P",
    "gn:feature_code":"PPLA3",
    "gn:name":"Kemer",
    "gn:population":0,
    "gn:timezone":"Europe/Istanbul",
    "iso:country":"TR",
    "name:deu_x_preferred":[
        "Kemer"
    ],
    "name:eng_x_preferred":[
        "Kemer"
    ],
    "name:fra_x_preferred":[
        "Kemer"
    ],
    "name:tur_x_preferred":[
        "Kemer"
    ],
    "wof:name":"Kemer",
    "wof:placetype":"locality"
},
  "geometry": {"coordinates":[29.3591,36.6481],"type":"Point"}
}