{
  "type": "Feature",
  "properties": {
    "gn:admin1_code":"61.0",
    "gn:asciiname":"Aydinli",
    "gn:country_code":"TR",
    "gn:dem":477,
    "gn:feature_class":"P",
    "gn:feature_code":"PPL",
    "gn:name":"Ayd\u0131nl\u0131",
    "gn:population":0,
    "gn:timezone":"Europe/Istanbul",
    "iso:country":"TR",
    "wof:name":"Aydinli",
    "wof:placetype":"locality"
},
  "geometry": {"coordinates":[39.6902,40.92595],"type":"Point"}
}