{
  "type": "Feature",
  "properties": {
    "gn:admin1_code":"44",
    "gn:asciiname":"Polat",
    "gn:country_code":"TR",
    "gn:dem":1276,
    "gn:feature_class":"P",
    "gn:feature_code":"PPL",
    "gn:name":"Polat",
    "gn:population":0,
    "gn:timezone":"Europe/Istanbul",
    "iso:country":"TR",
    "name:nld_x_preferred":[
        "Polat"
    ],
    "name:tur_x_preferred":[
        "Polat"
    ],
    "wof:name":"Polat",
    "wof:placetype":"locality"
},
  "geometry": {"coordinates":[37.85256,38.15745],"type":"Point"}
}