{
  "type": "Feature",
  "properties": {
    "gn:admin1_code":"19.0",
    "gn:asciiname":"Ertugrulkoy",
    "gn:country_code":"TR",
    "gn:dem":922,
    "gn:feature_class":"P",
    "gn:feature_code":"PPL",
    "gn:name":"Ertu\u011frulk\u00f6y",
    "gn:population":0,
    "gn:timezone":"Europe/Istanbul",
    "iso:country":"TR",
    "name:tur_x_preferred":[
        "Ertu\u011frulk\u00f6y"
    ],
    "name:tur_x_variant":[
        "Ertu\u011frul"
    ],
    "wof:name":"Ertugrulkoy",
    "wof:placetype":"locality"
},
  "geometry": {"coordinates":[34.673,40.38072],"type":"Point"}
}