{
  "type": "Feature",
  "properties": {
    "gn:admin1_code":"77.0",
    "gn:asciiname":"Cayiryolu",
    "gn:country_code":"TR",
    "gn:dem":1648,
    "gn:feature_class":"P",
    "gn:feature_code":"PPL",
    "gn:name":"\u00c7ay\u0131ryolu",
    "gn:population":0,
    "gn:timezone":"Europe/Istanbul",
    "iso:country":"TR",
    "name:tur_x_preferred":[
        "\u00c7ay\u0131ryolu"
    ],
    "name:vie_x_preferred":[
        "\u00c7ay\u0131ryolu"
    ],
    "wof:name":"Cayiryolu",
    "wof:placetype":"locality"
},
  "geometry": {"coordinates":[39.91028,40.25567],"type":"Point"}
}