{
  "type": "Feature",
  "properties": {
    "gn:admin1_code":"79",
    "gn:asciiname":"Tatlicak",
    "gn:country_code":"TR",
    "gn:dem":708,
    "gn:feature_class":"P",
    "gn:feature_code":"PPL",
    "gn:name":"Tatl\u0131cak",
    "gn:population":0,
    "gn:timezone":"Europe/Istanbul",
    "iso:country":"TR",
    "wof:name":"Tatlicak",
    "wof:placetype":"locality"
},
  "geometry": {"coordinates":[34.01667,39.83155],"type":"Point"}
}