{
  "type": "Feature",
  "properties": {
    "gn:admin1_code":"17.0",
    "gn:asciiname":"Tevfikiye",
    "gn:country_code":"TR",
    "gn:dem":50,
    "gn:feature_class":"P",
    "gn:feature_code":"PPL",
    "gn:name":"Tevfikiye",
    "gn:population":0,
    "gn:timezone":"Europe/Istanbul",
    "iso:country":"TR",
    "wof:name":"Tevfikiye",
    "wof:placetype":"locality"
},
  "geometry": {"coordinates":[27.2719,40.24368],"type":"Point"}
}