{
  "type": "Feature",
  "properties": {
    "gn:country":"TR",
    "gn:fcode":"PPL",
    "gn:population":834,
    "iso:country":"TR",
    "name:ceb_x_preferred":[
        "Demirlip\u0131nar"
    ],
    "name:che_x_preferred":[
        "\u0414\u0435\u043c\u0438\u0440\u043b\u0438\u043b\u0438\u043f\u0438\u043d\u0430\u0440"
    ],
    "name:deu_x_preferred":[
        "Demirlip\u0131nar"
    ],
    "name:eng_x_preferred":[
        "Demirlip\u0131nar"
    ],
    "name:kur_x_preferred":[
        "Mozgelan"
    ],
    "name:msa_x_preferred":[
        "Demirlip\u0131nar"
    ],
    "name:nld_x_preferred":[
        "Demirlip\u0131nar"
    ],
    "name:tur_x_preferred":[
        "Demirlip\u0131nar"
    ],
    "name:und_x_variant":[
        "M\u00f6zgelan"
    ],
    "name:vie_x_preferred":[
        "Demirlip\u0131nar"
    ],
    "qs:name":"Demirlip\u0131nar",
    "qs:photos_9r":0,
    "qs:photos_sr":0,
    "qs:pop_sr":"2",
    "wd:wordcount":36,
    "wof:name":"Demirlip\u0131nar",
    "wof:placetype":"locality",
    "wof:population":834
},
  "geometry": {"coordinates":[41.17583,37.96111],"type":"Point"}
}