{
  "type": "Feature",
  "properties": {
    "gn:admin1_code":"32",
    "gn:asciiname":"Ozturkmenli",
    "gn:country_code":"TR",
    "gn:dem":599,
    "gn:feature_class":"P",
    "gn:feature_code":"PPL",
    "gn:name":"\u00d6zt\u00fcrkmenli",
    "gn:population":0,
    "gn:timezone":"Europe/Istanbul",
    "iso:country":"TR",
    "name:tur_x_preferred":[
        "\u00d6zt\u00fcrkmenli"
    ],
    "wof:name":"Ozturkmenli",
    "wof:placetype":"locality"
},
  "geometry": {"coordinates":[34.00928,36.4683],"type":"Point"}
}