{
  "type": "Feature",
  "properties": {
    "gn:admin1_code":"43",
    "gn:asciiname":"Mecidiye",
    "gn:cc2":"TR",
    "gn:country_code":"TR",
    "gn:dem":1176,
    "gn:feature_class":"P",
    "gn:feature_code":"PPL",
    "gn:name":"Mecidiye",
    "gn:population":0,
    "gn:timezone":"Europe/Istanbul",
    "iso:country":"TR",
    "name:und_x_variant":[
        "Uzunp\u0131nar",
        "Mecdiye",
        "Uyuzp\u0131nar",
        "Mecidiye"
    ],
    "wof:name":"Mecidiye",
    "wof:placetype":"locality"
},
  "geometry": {"coordinates":[30.075,38.98083],"type":"Point"}
}