{
  "type": "Feature",
  "properties": {
    "gn:admin1_code":"25",
    "gn:asciiname":"Dedeoren",
    "gn:country_code":"TR",
    "gn:dem":1658,
    "gn:feature_class":"P",
    "gn:feature_code":"PPL",
    "gn:name":"Dede\u00f6ren",
    "gn:population":0,
    "gn:timezone":"Europe/Istanbul",
    "iso:country":"TR",
    "name:und_x_variant":[
        "Dedeveren",
        "Dedeveran",
        "Dede\u00f6ren",
        "Dedeviran"
    ],
    "wof:name":"Dedeoren",
    "wof:placetype":"locality"
},
  "geometry": {"coordinates":[41.94991,39.36782],"type":"Point"}
}