{
  "type": "Feature",
  "properties": {
    "gn:admin1_code":"49",
    "gn:asciiname":"Eskiyol",
    "gn:country_code":"TR",
    "gn:dem":1668,
    "gn:feature_class":"P",
    "gn:feature_code":"PPL",
    "gn:name":"Eskiyol",
    "gn:population":0,
    "gn:timezone":"Europe/Istanbul",
    "iso:country":"TR",
    "name:tur_x_preferred":[
        "Eskiyol"
    ],
    "name:tur_x_variant":[
        "A\u015fa\u011f\u0131derince"
    ],
    "wof:name":"Eskiyol",
    "wof:placetype":"locality"
},
  "geometry": {"coordinates":[42.04782,39.22554],"type":"Point"}
}