{
  "type": "Feature",
  "properties": {
    "gn:admin1_code":"22",
    "gn:asciiname":"Korucu",
    "gn:country_code":"TR",
    "gn:dem":132,
    "gn:feature_class":"P",
    "gn:feature_code":"PPL",
    "gn:name":"Korucu",
    "gn:population":0,
    "gn:timezone":"Europe/Istanbul",
    "iso:country":"TR",
    "name:tur_x_preferred":[
        "Korucu"
    ],
    "wof:name":"Korucu",
    "wof:placetype":"locality"
},
  "geometry": {"coordinates":[26.65483,41.79104],"type":"Point"}
}