{
  "type": "Feature",
  "properties": {
    "gn:admin1_code":"87.0",
    "gn:asciiname":"Hisar",
    "gn:country_code":"TR",
    "gn:dem":301,
    "gn:feature_class":"P",
    "gn:feature_code":"PPL",
    "gn:name":"Hisar",
    "gn:population":0,
    "gn:timezone":"Europe/Istanbul",
    "iso:country":"TR",
    "name:ara_x_preferred":[
        "\u062d\u0635\u0627\u0631"
    ],
    "name:aze_x_preferred":[
        "Hisar"
    ],
    "name:bih_x_preferred":[
        "\u0939\u093f\u0938\u093e\u0930"
    ],
    "name:bpy_x_preferred":[
        "\u09b9\u09bf\u09b8\u09be\u09b0"
    ],
    "name:bul_x_preferred":[
        "\u0425\u0438\u0441\u0430\u0440"
    ],
    "name:cat_x_preferred":[
        "Hisar"
    ],
    "name:ceb_x_preferred":[
        "Hisar"
    ],
    "name:deu_x_preferred":[
        "Hisar"
    ],
    "name:new_x_preferred":[
        "\u0939\u093f\u0938\u093e\u0930"
    ],
    "name:nld_x_preferred":[
        "Hisar"
    ],
    "name:pol_x_preferred":[
        "Hisar"
    ],
    "name:rus_x_preferred":[
        "\u0425\u0438\u0441\u0430\u0440"
    ],
    "name:srp_x_preferred":[
        "\u0425\u0438\u0441\u0430\u0440"
    ],
    "name:swe_x_preferred":[
        "Hisar"
    ],
    "name:tur_x_preferred":[
        "Hisar"
    ],
    "name:und_x_variant":[
        "Hisark\u00f6y",
        "Hisar"
    ],
    "wof:name":"Hisar",
    "wof:placetype":"locality"
},
  "geometry": {"coordinates":[32.54721,41.45085],"type":"Point"}
}