{
  "type": "Feature",
  "properties": {
    "gn:admin1_code":"20",
    "gn:asciiname":"Osmaniye",
    "gn:country_code":"TR",
    "gn:dem":272,
    "gn:feature_class":"P",
    "gn:feature_code":"PPL",
    "gn:name":"Osmaniye",
    "gn:population":0,
    "gn:timezone":"Europe/Istanbul",
    "iso:country":"TR",
    "name:tur_x_preferred":[
        "Osmaniye"
    ],
    "name:tur_x_variant":[
        "Mecidiye"
    ],
    "wof:name":"Osmaniye",
    "wof:placetype":"locality"
},
  "geometry": {"coordinates":[28.91268,38.03673],"type":"Point"}
}