{
  "type": "Feature",
  "properties": {
    "gn:admin1_code":"54.0",
    "gn:asciiname":"Hacilar",
    "gn:country_code":"TR",
    "gn:dem":24,
    "gn:feature_class":"P",
    "gn:feature_code":"PPL",
    "gn:name":"Hac\u0131lar",
    "gn:population":0,
    "gn:timezone":"Europe/Istanbul",
    "iso:country":"TR",
    "name:cat_x_preferred":[
        "Cultura Hacilar"
    ],
    "name:dan_x_preferred":[
        "Hacilar"
    ],
    "name:deu_x_preferred":[
        "Hac\u0131lar H\u00f6y\u00fck"
    ],
    "name:fin_x_preferred":[
        "Hacilar"
    ],
    "name:glg_x_preferred":[
        "Hacilar"
    ],
    "name:heb_x_preferred":[
        "\u05d4\u05d2'\u05d9\u05dc\u05e8"
    ],
    "name:hrv_x_preferred":[
        "Hacilar"
    ],
    "name:hun_x_preferred":[
        "Hacilar"
    ],
    "name:ita_x_preferred":[
        "Hagilar"
    ],
    "name:kat_x_preferred":[
        "\u10f0\u10d0\u10ef\u10d8\u10da\u10d0\u10e0\u10d8"
    ],
    "name:lat_x_preferred":[
        "Hac\u0131lar"
    ],
    "name:pol_x_preferred":[
        "Hacilar"
    ],
    "name:por_x_preferred":[
        "Hac\u0131lar H\u00f6y\u00fck"
    ],
    "name:rus_x_preferred":[
        "\u0425\u0430\u0434\u0436\u0438\u043b\u0430\u0440"
    ],
    "name:slk_x_preferred":[
        "Hacilar"
    ],
    "name:spa_x_preferred":[
        "Cultura Hacilar"
    ],
    "name:swe_x_preferred":[
        "Hacilar"
    ],
    "name:tur_x_preferred":[
        "Hac\u0131lar"
    ],
    "name:tur_x_variant":[
        "Hac\u0131lar H\u00f6y\u00fck"
    ],
    "name:ukr_x_preferred":[
        "\u0425\u0430\u0434\u0436\u0438\u043b\u0430\u0440"
    ],
    "wof:name":"Hacilar",
    "wof:placetype":"locality"
},
  "geometry": {"coordinates":[30.51158,40.80373],"type":"Point"}
}