{
  "type": "Feature",
  "properties": {
    "gn:admin1_code":"28.0",
    "gn:asciiname":"Torcan",
    "gn:country_code":"TR",
    "gn:dem":452,
    "gn:feature_class":"P",
    "gn:feature_code":"PPL",
    "gn:name":"Torcan",
    "gn:population":0,
    "gn:timezone":"Europe/Istanbul",
    "iso:country":"TR",
    "name:tur_x_preferred":[
        "Torcan"
    ],
    "name:und_x_variant":[
        "Torcam"
    ],
    "wof:name":"Torcan",
    "wof:placetype":"locality"
},
  "geometry": {"coordinates":[38.13516,40.8343],"type":"Point"}
}