{
  "type": "Feature",
  "properties": {
    "gn:admin1_code":"58",
    "gn:asciiname":"Gumustepe",
    "gn:country_code":"TR",
    "gn:dem":1253,
    "gn:feature_class":"P",
    "gn:feature_code":"PPL",
    "gn:name":"G\u00fcm\u00fc\u015ftepe",
    "gn:population":0,
    "gn:timezone":"Europe/Istanbul",
    "iso:country":"TR",
    "wof:name":"Gumustepe",
    "wof:placetype":"locality"
},
  "geometry": {"coordinates":[36.39413,39.30708],"type":"Point"}
}