{
  "type": "Feature",
  "properties": {
    "gn:admin1_code":"04",
    "gn:asciiname":"Dagdelen",
    "gn:country_code":"TR",
    "gn:dem":2262,
    "gn:feature_class":"P",
    "gn:feature_code":"PPL",
    "gn:name":"Da\u011fdelen",
    "gn:population":0,
    "gn:timezone":"Europe/Istanbul",
    "iso:country":"TR",
    "name:und_x_variant":[
        "Kanl\u0131k\u00f6y",
        "Da\u011fdaler",
        "Da\u011fdeler",
        "Da\u011fdelen"
    ],
    "wof:name":"Dagdelen",
    "wof:placetype":"locality"
},
  "geometry": {"coordinates":[44.16461,39.42096],"type":"Point"}
}