{
  "type": "Feature",
  "properties": {
    "gn:admin1_code":"72",
    "gn:asciiname":"Denktas",
    "gn:country_code":"TR",
    "gn:dem":469,
    "gn:feature_class":"P",
    "gn:feature_code":"PPL",
    "gn:name":"Denkta\u015f",
    "gn:population":0,
    "gn:timezone":"Europe/Istanbul",
    "iso:country":"TR",
    "name:tur_x_preferred":[
        "Denkta\u015f"
    ],
    "name:und_x_variant":[
        "Gayd\u00fck"
    ],
    "wof:name":"Denktas",
    "wof:placetype":"locality"
},
  "geometry": {"coordinates":[40.10163,37.2036],"type":"Point"}
}