{
  "type": "Feature",
  "properties": {
    "gn:admin1_code":"74.0",
    "gn:asciiname":"Tahik",
    "gn:cc2":"TR",
    "gn:country_code":"TR",
    "gn:dem":899,
    "gn:feature_class":"P",
    "gn:feature_code":"PPL",
    "gn:name":"Tahik",
    "gn:population":0,
    "gn:timezone":"Europe/Istanbul",
    "iso:country":"TR",
    "name:und_x_variant":[
        "Takhik",
        "Tahik"
    ],
    "wof:name":"Tahik",
    "wof:placetype":"locality"
},
  "geometry": {"coordinates":[42.0375,37.80167],"type":"Point"}
}