{
  "type": "Feature",
  "properties": {
    "gn:admin1_code":"21",
    "gn:asciiname":"Goktepe",
    "gn:country_code":"TR",
    "gn:dem":730,
    "gn:feature_class":"P",
    "gn:feature_code":"PPL",
    "gn:name":"G\u00f6ktepe",
    "gn:population":0,
    "gn:timezone":"Europe/Istanbul",
    "iso:country":"TR",
    "name:tur_x_preferred":[
        "G\u00f6ktepe"
    ],
    "wof:name":"Goktepe",
    "wof:placetype":"locality"
},
  "geometry": {"coordinates":[40.38403,37.69504000000001],"type":"Point"}
}