{
  "type": "Feature",
  "properties": {
    "gn:admin1_code":"80",
    "gn:asciiname":"Ayranci",
    "gn:country_code":"TR",
    "gn:dem":2205,
    "gn:feature_class":"P",
    "gn:feature_code":"PPL",
    "gn:name":"Ayranc\u0131",
    "gn:population":0,
    "gn:timezone":"Europe/Istanbul",
    "iso:country":"TR",
    "name:tur_x_preferred":[
        "Ayranc\u0131"
    ],
    "wof:name":"Ayranci",
    "wof:placetype":"locality"
},
  "geometry": {"coordinates":[43.01446,37.69416],"type":"Point"}
}