{
  "type": "Feature",
  "properties": {
    "iso:country":"TR",
    "wof:name":"Esenyurt",
    "wof:placetype":"neighbourhood"
},
  "geometry": {"coordinates":[28.67677389702038,41.03270699570101],"type":"Point"}
}