{
  "type": "Feature",
  "properties": {
    "gn:admin1_code":"71",
    "gn:asciiname":"Dolhanlar",
    "gn:country_code":"TR",
    "gn:dem":1465,
    "gn:feature_class":"P",
    "gn:feature_code":"PPL",
    "gn:name":"Dolhanlar",
    "gn:population":0,
    "gn:timezone":"Europe/Istanbul",
    "iso:country":"TR",
    "wof:name":"Dolhanlar",
    "wof:placetype":"locality"
},
  "geometry": {"coordinates":[32.29855,37.02971],"type":"Point"}
}