{
  "type": "Feature",
  "properties": {
    "gn:admin1_code":"49",
    "gn:asciiname":"Ziyaret",
    "gn:country_code":"TR",
    "gn:dem":1280,
    "gn:feature_class":"P",
    "gn:feature_code":"PPL",
    "gn:name":"Ziyaret",
    "gn:population":0,
    "gn:timezone":"Europe/Istanbul",
    "iso:country":"TR",
    "name:ceb_x_preferred":[
        "Ziyaret"
    ],
    "name:deu_x_preferred":[
        "Ziyaret"
    ],
    "name:kur_x_preferred":[
        "Ziyaret"
    ],
    "name:tur_x_preferred":[
        "Ziyaret"
    ],
    "name:und_x_variant":[
        "Ziyaretk\u00f6y"
    ],
    "wof:name":"Ziyaret",
    "wof:placetype":"locality"
},
  "geometry": {"coordinates":[41.26656,38.8892],"type":"Point"}
}