{
  "type": "Feature",
  "properties": {
    "gn:admin1_code":"14",
    "gn:asciiname":"Yunuslar",
    "gn:country_code":"TR",
    "gn:dem":1182,
    "gn:feature_class":"P",
    "gn:feature_code":"PPL",
    "gn:name":"Yunuslar",
    "gn:population":0,
    "gn:timezone":"Europe/Istanbul",
    "iso:country":"TR",
    "wof:name":"Yunuslar",
    "wof:placetype":"locality"
},
  "geometry": {"coordinates":[32.0941,40.77583],"type":"Point"}
}