{
  "type": "Feature",
  "properties": {
    "gn:admin1_code":"83.0",
    "gn:asciiname":"Kayacik",
    "gn:cc2":"TR",
    "gn:country_code":"TR",
    "gn:dem":596,
    "gn:feature_class":"P",
    "gn:feature_code":"PPL",
    "gn:name":"Kayac\u0131k",
    "gn:population":0,
    "gn:timezone":"Europe/Istanbul",
    "iso:country":"TR",
    "name:und_x_variant":[
        "Kayadzhik",
        "Kayac\u0131k"
    ],
    "wof:name":"Kayacik",
    "wof:placetype":"locality"
},
  "geometry": {"coordinates":[37.56861,36.82611],"type":"Point"}
}