{
  "type": "Feature",
  "properties": {
    "gn:admin1_code":"64",
    "gn:asciiname":"Pinarbasi",
    "gn:country_code":"TR",
    "gn:dem":937,
    "gn:feature_class":"P",
    "gn:feature_code":"PPL",
    "gn:name":"P\u0131narba\u015f\u0131",
    "gn:population":0,
    "gn:timezone":"Europe/Istanbul",
    "iso:country":"TR",
    "name:tur_x_preferred":[
        "P\u0131narba\u015f\u0131"
    ],
    "wof:name":"Pinarbasi",
    "wof:placetype":"locality"
},
  "geometry": {"coordinates":[29.68511,38.47961],"type":"Point"}
}