{
  "type": "Feature",
  "properties": {
    "gn:admin1_code":"43",
    "gn:asciiname":"Aykirikci",
    "gn:cc2":"TR",
    "gn:country_code":"TR",
    "gn:dem":1030,
    "gn:feature_class":"P",
    "gn:feature_code":"PPL",
    "gn:name":"Ayk\u0131r\u0131k\u00e7\u0131",
    "gn:population":0,
    "gn:timezone":"Europe/Istanbul",
    "iso:country":"TR",
    "name:und_x_variant":[
        "Ayk\u0131r\u0131c\u0131",
        "Ayk\u0131r\u0131k\u00e7\u0131"
    ],
    "wof:name":"Aykirikci",
    "wof:placetype":"locality"
},
  "geometry": {"coordinates":[30.15722,39.12806],"type":"Point"}
}