{
  "type": "Feature",
  "properties": {
    "gn:admin1_code":"40",
    "gn:asciiname":"Omerkahya",
    "gn:country_code":"TR",
    "gn:dem":1133,
    "gn:feature_class":"P",
    "gn:feature_code":"PPL",
    "gn:name":"\u00d6merk\u00e2hya",
    "gn:population":0,
    "gn:timezone":"Europe/Istanbul",
    "iso:country":"TR",
    "wof:name":"Omerkahya",
    "wof:placetype":"locality"
},
  "geometry": {"coordinates":[33.66053,39.40188],"type":"Point"}
}