{
  "type": "Feature",
  "properties": {
    "gn:admin1_code":"72.0",
    "gn:asciiname":"Diyarinkari",
    "gn:cc2":"TR",
    "gn:country_code":"TR",
    "gn:dem":921,
    "gn:feature_class":"P",
    "gn:feature_code":"PPL",
    "gn:name":"Diyarinkari",
    "gn:population":0,
    "gn:timezone":"Europe/Istanbul",
    "iso:country":"TR",
    "name:tur_x_preferred":[
        "Diyarinkari"
    ],
    "name:und_x_variant":[
        "G\u00fcnd\u00fcseyitali"
    ],
    "wof:name":"Diyarinkari",
    "wof:placetype":"locality"
},
  "geometry": {"coordinates":[41.59722,37.525],"type":"Point"}
}