{
  "type": "Feature",
  "properties": {
    "gn:admin1_code":"19.0",
    "gn:asciiname":"Seki",
    "gn:country_code":"TR",
    "gn:dem":592,
    "gn:feature_class":"P",
    "gn:feature_code":"PPL",
    "gn:name":"Seki",
    "gn:population":0,
    "gn:timezone":"Europe/Istanbul",
    "iso:country":"TR",
    "name:ceb_x_preferred":[
        "Seki"
    ],
    "name:deu_x_preferred":[
        "Seki"
    ],
    "name:fra_x_preferred":[
        "Seki"
    ],
    "name:ita_x_preferred":[
        "Seki"
    ],
    "name:nld_x_preferred":[
        "Seki"
    ],
    "name:pol_x_preferred":[
        "Seki"
    ],
    "name:por_x_preferred":[
        "Seki"
    ],
    "name:rus_x_preferred":[
        "\u0421\u044d\u043a\u0438"
    ],
    "name:swe_x_preferred":[
        "Seki"
    ],
    "name:tur_x_preferred":[
        "Seki"
    ],
    "name:ukr_x_preferred":[
        "\u0421\u0435\u043a\u0456"
    ],
    "wof:name":"Seki",
    "wof:placetype":"locality"
},
  "geometry": {"coordinates":[34.89728,41.23997],"type":"Point"}
}