{
  "type": "Feature",
  "properties": {
    "gn:admin1_code":"57",
    "gn:asciiname":"Gumusova",
    "gn:country_code":"TR",
    "gn:dem":459,
    "gn:feature_class":"P",
    "gn:feature_code":"PPL",
    "gn:name":"G\u00fcm\u00fc\u015fova",
    "gn:population":0,
    "gn:timezone":"Europe/Istanbul",
    "iso:country":"TR",
    "name:tur_x_preferred":[
        "G\u00fcm\u00fc\u015fova"
    ],
    "wof:name":"Gumusova",
    "wof:placetype":"locality"
},
  "geometry": {"coordinates":[35.47294,41.30702],"type":"Point"}
}