{
  "type": "Feature",
  "properties": {
    "gn:country":"TR",
    "gn:fcode":"PPL",
    "gn:population":1243,
    "iso:country":"TR",
    "name:tur_x_preferred":[
        "Dorumali"
    ],
    "qs:name":"Dorumali",
    "qs:photos_9r":0,
    "qs:photos_sr":0,
    "qs:pop_sr":"3",
    "wof:name":"Dorumali",
    "wof:placetype":"locality",
    "wof:population":1243
},
  "geometry": {"coordinates":[38.85306,36.805],"type":"Point"}
}