{
  "type": "Feature",
  "properties": {
    "gn:admin1_code":"71",
    "gn:asciiname":"Meselik",
    "gn:country_code":"TR",
    "gn:dem":1169,
    "gn:feature_class":"P",
    "gn:feature_code":"PPL",
    "gn:name":"Me\u015felik",
    "gn:population":0,
    "gn:timezone":"Europe/Istanbul",
    "iso:country":"TR",
    "wof:name":"Meselik",
    "wof:placetype":"locality"
},
  "geometry": {"coordinates":[31.75528,38.86167],"type":"Point"}
}