{
  "type": "Feature",
  "properties": {
    "gn:admin1_code":"20",
    "gn:asciiname":"Citak",
    "gn:country_code":"TR",
    "gn:dem":826,
    "gn:feature_class":"P",
    "gn:feature_code":"PPL",
    "gn:name":"\u00c7\u0131tak",
    "gn:population":0,
    "gn:timezone":"Europe/Istanbul",
    "iso:country":"TR",
    "wof:name":"Citak",
    "wof:placetype":"locality"
},
  "geometry": {"coordinates":[29.64694,38.13556],"type":"Point"}
}