{
  "type": "Feature",
  "properties": {
    "gn:admin1_code":"72.0",
    "gn:asciiname":"Seyderi",
    "gn:country_code":"TR",
    "gn:dem":1026,
    "gn:feature_class":"P",
    "gn:feature_code":"PPL",
    "gn:name":"Seyderi",
    "gn:population":0,
    "gn:timezone":"Europe/Istanbul",
    "iso:country":"TR",
    "wof:name":"Seyderi",
    "wof:placetype":"locality"
},
  "geometry": {"coordinates":[41.42361,37.20806],"type":"Point"}
}