{
  "type": "Feature",
  "properties": {
    "gn:admin1_code":"71",
    "gn:asciiname":"Bayram Ciftligi",
    "gn:country_code":"TR",
    "gn:dem":1233,
    "gn:feature_class":"P",
    "gn:feature_code":"PPL",
    "gn:name":"Bayram \u00c7iftli\u011fi",
    "gn:population":0,
    "gn:timezone":"Europe/Istanbul",
    "iso:country":"TR",
    "wof:name":"Bayram Ciftligi",
    "wof:placetype":"locality"
},
  "geometry": {"coordinates":[31.88333,37.83333],"type":"Point"}
}