{
  "type": "Feature",
  "properties": {
    "gn:admin1_code":"19.0",
    "gn:asciiname":"Karnikara",
    "gn:country_code":"TR",
    "gn:dem":1142,
    "gn:feature_class":"P",
    "gn:feature_code":"PPL",
    "gn:name":"Karn\u0131kara",
    "gn:population":0,
    "gn:timezone":"Europe/Istanbul",
    "iso:country":"TR",
    "wof:name":"Karnikara",
    "wof:placetype":"locality"
},
  "geometry": {"coordinates":[35.0332,40.03818],"type":"Point"}
}