{
  "type": "Feature",
  "properties": {
    "gn:admin1_code":"19.0",
    "gn:asciiname":"Yukaribespinar",
    "gn:country_code":"TR",
    "gn:dem":713,
    "gn:feature_class":"P",
    "gn:feature_code":"PPL",
    "gn:name":"Yukar\u0131be\u015fp\u0131nar",
    "gn:population":0,
    "gn:timezone":"Europe/Istanbul",
    "iso:country":"TR",
    "name:und_x_variant":[
        "Be\u015fp\u0131nar\u0131b\u00e2l\u00e2",
        "Yukar\u0131be\u015fp\u0131nar"
    ],
    "wof:name":"Yukaribespinar",
    "wof:placetype":"locality"
},
  "geometry": {"coordinates":[34.24692,40.17589],"type":"Point"}
}