{
  "type": "Feature",
  "properties": {
    "gn:admin1_code":"21",
    "gn:asciiname":"Avut",
    "gn:country_code":"TR",
    "gn:dem":1136,
    "gn:feature_class":"P",
    "gn:feature_code":"PPL",
    "gn:name":"Avut",
    "gn:population":0,
    "gn:timezone":"Europe/Istanbul",
    "iso:country":"TR",
    "name:und_x_variant":[
        "A\u015fa\u011f\u0131 Avut",
        "Avut"
    ],
    "wof:name":"Avut",
    "wof:placetype":"locality"
},
  "geometry": {"coordinates":[39.21963,38.29796],"type":"Point"}
}