{
  "type": "Feature",
  "properties": {
    "gn:admin1_code":"62",
    "gn:asciiname":"Tacekrek",
    "gn:country_code":"TR",
    "gn:dem":1519,
    "gn:feature_class":"P",
    "gn:feature_code":"PPL",
    "gn:name":"Tacekrek",
    "gn:population":0,
    "gn:timezone":"Europe/Istanbul",
    "iso:country":"TR",
    "name:und_x_variant":[
        "Ta\u00e7kirek",
        "Ta\u015fgevi\u00e7"
    ],
    "wof:name":"Tacekrek",
    "wof:placetype":"locality"
},
  "geometry": {"coordinates":[39.15,39.08333],"type":"Point"}
}