{
  "type": "Feature",
  "properties": {
    "gn:admin1_code":"53",
    "gn:asciiname":"Kurtulus",
    "gn:country_code":"TR",
    "gn:dem":211,
    "gn:feature_class":"P",
    "gn:feature_code":"PPL",
    "gn:name":"Kurtulu\u015f",
    "gn:population":0,
    "gn:timezone":"Europe/Istanbul",
    "iso:country":"TR",
    "name:tur_x_preferred":[
        "Kurtulu\u015f"
    ],
    "wof:name":"Kurtulus",
    "wof:placetype":"locality"
},
  "geometry": {"coordinates":[41.02598,41.15904000000001],"type":"Point"}
}