{
  "type": "Feature",
  "properties": {
    "gn:admin1_code":"10",
    "gn:asciiname":"Kazimiye",
    "gn:country_code":"TR",
    "gn:dem":607,
    "gn:feature_class":"P",
    "gn:feature_code":"PPL",
    "gn:name":"Kaz\u0131miye",
    "gn:population":0,
    "gn:timezone":"Europe/Istanbul",
    "iso:country":"TR",
    "name:tur_x_preferred":[
        "Kaz\u0131miye"
    ],
    "wof:name":"Kazimiye",
    "wof:placetype":"locality"
},
  "geometry": {"coordinates":[28.82832,39.59782],"type":"Point"}
}