{
  "type": "Feature",
  "properties": {
    "gn:admin1_code":"83",
    "gn:asciiname":"Alagoz",
    "gn:country_code":"TR",
    "gn:dem":807,
    "gn:feature_class":"P",
    "gn:feature_code":"PPL",
    "gn:name":"Alag\u00f6z",
    "gn:population":0,
    "gn:timezone":"Europe/Istanbul",
    "iso:country":"TR",
    "name:und_x_variant":[
        "Alag\u00f6z",
        "Alag\u00f6zbanisi"
    ],
    "wof:name":"Alagoz",
    "wof:placetype":"locality"
},
  "geometry": {"coordinates":[36.55,36.91667],"type":"Point"}
}