{
  "type": "Feature",
  "properties": {
    "gn:admin1_code":"72",
    "gn:asciiname":"Cekem",
    "gn:country_code":"TR",
    "gn:dem":502,
    "gn:feature_class":"P",
    "gn:feature_code":"PPL",
    "gn:name":"\u00c7ekem",
    "gn:population":0,
    "gn:timezone":"Europe/Istanbul",
    "iso:country":"TR",
    "wof:name":"Cekem",
    "wof:placetype":"locality"
},
  "geometry": {"coordinates":[40.2025,37.24049],"type":"Point"}
}