{
  "type": "Feature",
  "properties": {
    "gn:admin1_code":"60.0",
    "gn:asciiname":"Esence",
    "gn:country_code":"TR",
    "gn:dem":936,
    "gn:feature_class":"P",
    "gn:feature_code":"PPL",
    "gn:name":"Esence",
    "gn:population":0,
    "gn:timezone":"Europe/Istanbul",
    "iso:country":"TR",
    "wof:name":"Esence",
    "wof:placetype":"locality"
},
  "geometry": {"coordinates":[37.00354,40.55365],"type":"Point"}
}