{
  "type": "Feature",
  "properties": {
    "gn:admin1_code":"86.0",
    "gn:asciiname":"Budakli",
    "gn:country_code":"TR",
    "gn:dem":2077,
    "gn:feature_class":"P",
    "gn:feature_code":"PPL",
    "gn:name":"Budakl\u0131",
    "gn:population":0,
    "gn:timezone":"Europe/Istanbul",
    "iso:country":"TR",
    "name:tur_x_preferred":[
        "Budakl\u0131"
    ],
    "wof:name":"Budakli",
    "wof:placetype":"locality"
},
  "geometry": {"coordinates":[42.53374,40.95699000000001],"type":"Point"}
}