{
  "type": "Feature",
  "properties": {
    "gn:admin1_code":"10",
    "gn:asciiname":"Yorukkisla",
    "gn:country_code":"TR",
    "gn:dem":188,
    "gn:feature_class":"P",
    "gn:feature_code":"PPL",
    "gn:name":"Y\u00f6r\u00fckk\u0131sla",
    "gn:population":0,
    "gn:timezone":"Europe/Istanbul",
    "iso:country":"TR",
    "name:tur_x_preferred":[
        "Y\u00f6r\u00fckk\u0131sla"
    ],
    "wof:name":"Yorukkisla",
    "wof:placetype":"locality"
},
  "geometry": {"coordinates":[27.78505,39.53147],"type":"Point"}
}