{
  "type": "Feature",
  "properties": {
    "gn:admin1_code":"74",
    "gn:asciiname":"Yarimtepe",
    "gn:country_code":"TR",
    "gn:dem":1306,
    "gn:feature_class":"P",
    "gn:feature_code":"PPL",
    "gn:name":"Yar\u0131mtepe",
    "gn:population":0,
    "gn:timezone":"Europe/Istanbul",
    "iso:country":"TR",
    "name:tur_x_preferred":[
        "Yar\u0131mtepe"
    ],
    "wof:name":"Yarimtepe",
    "wof:placetype":"locality"
},
  "geometry": {"coordinates":[42.22396,38.07169],"type":"Point"}
}