{
  "type": "Feature",
  "properties": {
    "gn:admin1_code":"26",
    "gn:asciiname":"Osmaniye",
    "gn:country_code":"TR",
    "gn:dem":786,
    "gn:feature_class":"P",
    "gn:feature_code":"PPL",
    "gn:name":"Osmaniye",
    "gn:population":0,
    "gn:timezone":"Europe/Istanbul",
    "iso:country":"TR",
    "name:ceb_x_preferred":[
        "Osmaniye"
    ],
    "name:heb_x_preferred":[
        "\u05d0\u05d5\u05e1\u05de\u05e0\u05d9\u05d9\u05d4"
    ],
    "name:tur_x_preferred":[
        "Osmaniye"
    ],
    "name:vie_x_preferred":[
        "Osmaniye"
    ],
    "wof:name":"Osmaniye",
    "wof:placetype":"locality"
},
  "geometry": {"coordinates":[30.90833,39.84194],"type":"Point"}
}