{
  "type": "Feature",
  "properties": {
    "gn:admin1_code":"65",
    "gn:asciiname":"Tasliyazi",
    "gn:country_code":"TR",
    "gn:dem":2152,
    "gn:feature_class":"P",
    "gn:feature_code":"PPL",
    "gn:name":"Ta\u015fl\u0131yaz\u0131",
    "gn:population":0,
    "gn:timezone":"Europe/Istanbul",
    "iso:country":"TR",
    "name:und_x_variant":[
        "Ah\u00e7orik",
        "Ak\u00e7uri",
        "Akchury",
        "Ta\u015fl\u0131yaz\u0131"
    ],
    "wof:name":"Tasliyazi",
    "wof:placetype":"locality"
},
  "geometry": {"coordinates":[43.28684000000001,37.96673],"type":"Point"}
}