{
  "type": "Feature",
  "properties": {
    "gn:admin1_code":"71",
    "gn:asciiname":"Altinoz",
    "gn:country_code":"TR",
    "gn:dem":931,
    "gn:feature_class":"P",
    "gn:feature_code":"PPL",
    "gn:name":"Alt\u0131n\u00f6z",
    "gn:population":0,
    "gn:timezone":"Europe/Istanbul",
    "iso:country":"TR",
    "name:und_x_variant":[
        "Alt\u0131n\u00f6z",
        "Orta\u015fu\u015fe"
    ],
    "wof:name":"Altinoz",
    "wof:placetype":"locality"
},
  "geometry": {"coordinates":[32.09847,38.88047],"type":"Point"}
}