{
  "type": "Feature",
  "properties": {
    "gn:admin1_code":"82.0",
    "gn:asciiname":"Dogantepe",
    "gn:country_code":"TR",
    "gn:dem":877,
    "gn:feature_class":"P",
    "gn:feature_code":"PPL",
    "gn:name":"Do\u011fantepe",
    "gn:population":0,
    "gn:timezone":"Europe/Istanbul",
    "iso:country":"TR",
    "name:und_x_variant":[
        "Kavra",
        "Do\u011fantepe"
    ],
    "wof:name":"Dogantepe",
    "wof:placetype":"locality"
},
  "geometry": {"coordinates":[33.63815,40.56595],"type":"Point"}
}