{
  "type": "Feature",
  "properties": {
    "gn:admin1_code":"74",
    "gn:asciiname":"Mezraivarabin",
    "gn:country_code":"TR",
    "gn:dem":2174,
    "gn:feature_class":"P",
    "gn:feature_code":"PPL",
    "gn:name":"Mezraivarabin",
    "gn:population":0,
    "gn:timezone":"Europe/Istanbul",
    "iso:country":"TR",
    "name:und_x_variant":[
        "Mezre-\u0130varabin",
        "Mezrevarabin",
        "Mezraivarabin"
    ],
    "wof:name":"Mezraivarabin",
    "wof:placetype":"locality"
},
  "geometry": {"coordinates":[42.45,38.03333],"type":"Point"}
}