{
  "type": "Feature",
  "properties": {
    "gn:admin1_code":"12",
    "gn:asciiname":"Catak",
    "gn:country_code":"TR",
    "gn:dem":1780,
    "gn:feature_class":"P",
    "gn:feature_code":"PPL",
    "gn:name":"\u00c7atak",
    "gn:population":0,
    "gn:timezone":"Europe/Istanbul",
    "iso:country":"TR",
    "wof:name":"Catak",
    "wof:placetype":"locality"
},
  "geometry": {"coordinates":[41.1543,39.16624],"type":"Point"}
}