{
  "type": "Feature",
  "properties": {
    "gn:admin1_code":"63",
    "gn:asciiname":"Cevher",
    "gn:country_code":"TR",
    "gn:dem":410,
    "gn:feature_class":"P",
    "gn:feature_code":"PPL",
    "gn:name":"Cevher",
    "gn:population":0,
    "gn:timezone":"Europe/Istanbul",
    "iso:country":"TR",
    "name:tur_x_preferred":[
        "Cevher"
    ],
    "wof:name":"Cevher",
    "wof:placetype":"locality"
},
  "geometry": {"coordinates":[39.21422000000001,36.70628],"type":"Point"}
}