{
  "type": "Feature",
  "properties": {
    "gn:admin1_code":"82.0",
    "gn:asciiname":"Sazak",
    "gn:country_code":"TR",
    "gn:dem":1033,
    "gn:feature_class":"P",
    "gn:feature_code":"PPL",
    "gn:name":"Sazak",
    "gn:population":0,
    "gn:timezone":"Europe/Istanbul",
    "iso:country":"TR",
    "wof:name":"Sazak",
    "wof:placetype":"locality"
},
  "geometry": {"coordinates":[33.08218,40.99794],"type":"Point"}
}