{
  "type": "Feature",
  "properties": {
    "gn:admin1_code":"13.0",
    "gn:asciiname":"Yapagi",
    "gn:country_code":"TR",
    "gn:dem":2538,
    "gn:feature_class":"P",
    "gn:feature_code":"PPL",
    "gn:name":"Yapa\u011f\u0131",
    "gn:population":0,
    "gn:timezone":"Europe/Istanbul",
    "iso:country":"TR",
    "name:tur_x_preferred":[
        "Yapa\u011f\u0131"
    ],
    "wof:name":"Yapagi",
    "wof:placetype":"locality"
},
  "geometry": {"coordinates":[42.58409,38.20705],"type":"Point"}
}