{
  "type": "Feature",
  "properties": {
    "gn:admin1_code":"09",
    "gn:asciiname":"Akyenikoy",
    "gn:country_code":"TR",
    "gn:dem":51,
    "gn:feature_class":"P",
    "gn:feature_code":"PPL",
    "gn:name":"Akyenik\u00f6y",
    "gn:population":0,
    "gn:timezone":"Europe/Istanbul",
    "iso:country":"TR",
    "name:tur_x_preferred":[
        "Akyenik\u00f6y"
    ],
    "name:tur_x_variant":[
        "Yenik\u00f6y"
    ],
    "wof:name":"Akyenikoy",
    "wof:placetype":"locality"
},
  "geometry": {"coordinates":[27.30317,37.49472],"type":"Point"}
}