{
  "type": "Feature",
  "properties": {
    "gn:admin1_code":"12",
    "gn:asciiname":"Horhor",
    "gn:country_code":"TR",
    "gn:dem":1240,
    "gn:feature_class":"P",
    "gn:feature_code":"PPL",
    "gn:name":"Horhor",
    "gn:population":0,
    "gn:timezone":"Europe/Istanbul",
    "iso:country":"TR",
    "wof:name":"Horhor",
    "wof:placetype":"locality"
},
  "geometry": {"coordinates":[40.41667,39.21667],"type":"Point"}
}