{
  "type": "Feature",
  "properties": {
    "gn:country":"TR",
    "gn:fcode":"PPL",
    "gn:pop":265,
    "iso:country":"TR",
    "name:cat_x_preferred":[
        "\u00dc\u00e7k\u00f6y"
    ],
    "name:ceb_x_preferred":[
        "\u00dc\u00e7k\u00f6y"
    ],
    "name:ces_x_preferred":[
        "\u00dc\u00e7k\u00f6y"
    ],
    "name:dan_x_preferred":[
        "\u00dc\u00e7k\u00f6y"
    ],
    "name:deu_x_preferred":[
        "\u00dc\u00e7k\u00f6y"
    ],
    "name:eng_x_preferred":[
        "\u00dc\u00e7k\u00f6y"
    ],
    "name:eus_x_preferred":[
        "\u00dc\u00e7k\u00f6y"
    ],
    "name:fin_x_preferred":[
        "\u00dc\u00e7k\u00f6y"
    ],
    "name:glg_x_preferred":[
        "\u00dc\u00e7k\u00f6y"
    ],
    "name:ita_x_preferred":[
        "\u00dc\u00e7k\u00f6y"
    ],
    "name:kur_x_preferred":[
        "Xirb\u00ea El\u00ee"
    ],
    "name:nld_x_preferred":[
        "\u00dc\u00e7k\u00f6y"
    ],
    "name:nno_x_preferred":[
        "\u00dc\u00e7k\u00f6y"
    ],
    "name:nob_x_preferred":[
        "\u00dc\u00e7k\u00f6y"
    ],
    "name:oci_x_preferred":[
        "\u00dc\u00e7k\u00f6y"
    ],
    "name:pol_x_preferred":[
        "\u00dc\u00e7k\u00f6y"
    ],
    "name:por_x_preferred":[
        "\u00dc\u00e7k\u00f6y"
    ],
    "name:ron_x_preferred":[
        "\u00dc\u00e7k\u00f6y"
    ],
    "name:sco_x_preferred":[
        "\u00dc\u00e7k\u00f6y"
    ],
    "name:slk_x_preferred":[
        "\u00dc\u00e7k\u00f6y"
    ],
    "name:slv_x_preferred":[
        "\u00dc\u00e7k\u00f6y"
    ],
    "name:spa_x_preferred":[
        "\u00dc\u00e7k\u00f6y"
    ],
    "name:swe_x_preferred":[
        "\u00dc\u00e7k\u00f6y"
    ],
    "name:tgl_x_preferred":[
        "\u00dc\u00e7k\u00f6y"
    ],
    "name:tur_x_preferred":[
        "U\u00e7k\u00f6y"
    ],
    "name:tur_x_variant":[
        "\u00dc\u00e7k\u00f6y"
    ],
    "name:vie_x_preferred":[
        "\u00dc\u00e7k\u00f6y"
    ],
    "name:war_x_preferred":[
        "\u00dc\u00e7k\u00f6y"
    ],
    "qs:name":"U\u00e7k\u00f6y",
    "qs:photos_9r":0,
    "qs:photos_sr":0,
    "qs:pop_sr":"2",
    "wof:name":"U\u00e7k\u00f6y",
    "wof:placetype":"locality",
    "wof:population":265
},
  "geometry": {"coordinates":[41.43603,37.25824],"type":"Point"}
}