{
  "type": "Feature",
  "properties": {
    "gn:admin1_code":"52.0",
    "gn:asciiname":"Durali",
    "gn:country_code":"TR",
    "gn:dem":654,
    "gn:feature_class":"P",
    "gn:feature_code":"PPL",
    "gn:name":"Durali",
    "gn:population":0,
    "gn:timezone":"Europe/Istanbul",
    "iso:country":"TR",
    "wof:name":"Durali",
    "wof:placetype":"locality"
},
  "geometry": {"coordinates":[37.33919,40.77453],"type":"Point"}
}