{
  "type": "Feature",
  "properties": {
    "gn:admin1_code":"52.0",
    "gn:asciiname":"Kurudere",
    "gn:country_code":"TR",
    "gn:dem":374,
    "gn:feature_class":"P",
    "gn:feature_code":"PPL",
    "gn:name":"Kurudere",
    "gn:population":0,
    "gn:timezone":"Europe/Istanbul",
    "iso:country":"TR",
    "wof:name":"Kurudere",
    "wof:placetype":"locality"
},
  "geometry": {"coordinates":[37.11186,41.03514000000001],"type":"Point"}
}