{
  "type": "Feature",
  "properties": {
    "gn:admin1_code":"14.0",
    "gn:asciiname":"Karacadagdemirci",
    "gn:country_code":"TR",
    "gn:dem":1269,
    "gn:feature_class":"P",
    "gn:feature_code":"PPL",
    "gn:name":"Karacada\u011fdemirci",
    "gn:population":0,
    "gn:timezone":"Europe/Istanbul",
    "iso:country":"TR",
    "name:ceb_x_preferred":[
        "Karacada\u011fdemirci"
    ],
    "name:hif_x_preferred":[
        "Karacada\u011fdemirciler"
    ],
    "name:msa_x_preferred":[
        "Karacada\u011fdemirciler"
    ],
    "name:tur_x_preferred":[
        "Karacada\u011fdemirciler"
    ],
    "name:und_x_variant":[
        "Karacada\u011fdemirciler",
        "Karacada\u011f Demircler",
        "Karacada\u011fdemirci"
    ],
    "name:vie_x_preferred":[
        "Karacada\u011fdemirciler"
    ],
    "wof:name":"Karacadagdemirci",
    "wof:placetype":"locality"
},
  "geometry": {"coordinates":[32.45189,40.83754],"type":"Point"}
}