{
  "type": "Feature",
  "properties": {
    "gn:admin1_code":"63",
    "gn:asciiname":"Sekir",
    "gn:country_code":"TR",
    "gn:dem":638,
    "gn:feature_class":"P",
    "gn:feature_code":"PPL",
    "gn:name":"Sekir",
    "gn:population":0,
    "gn:timezone":"Europe/Istanbul",
    "iso:country":"TR",
    "name:und_x_variant":[
        "K\u00f6rkuyu K\u00f6y\u00fc",
        "K\u00f6rkuyu K\u00f6y"
    ],
    "wof:name":"Sekir",
    "wof:placetype":"locality"
},
  "geometry": {"coordinates":[38.18722,36.99833],"type":"Point"}
}