{
  "type": "Feature",
  "properties": {
    "gn:admin1_code":"48",
    "gn:asciiname":"Zorlar",
    "gn:country_code":"TR",
    "gn:dem":150,
    "gn:feature_class":"P",
    "gn:feature_code":"PPL",
    "gn:name":"Zorlar",
    "gn:population":0,
    "gn:timezone":"Europe/Istanbul",
    "iso:country":"TR",
    "name:und_x_variant":[
        "Zorlark\u00f6y",
        "Zorlar"
    ],
    "wof:name":"Zorlar",
    "wof:placetype":"locality"
},
  "geometry": {"coordinates":[29.32958,36.63987],"type":"Point"}
}