{
  "type": "Feature",
  "properties": {
    "gn:admin1_code":"38",
    "gn:asciiname":"Melikoren",
    "gn:country_code":"TR",
    "gn:dem":1368,
    "gn:feature_class":"P",
    "gn:feature_code":"PPL",
    "gn:name":"Melik\u00f6ren",
    "gn:population":0,
    "gn:timezone":"Europe/Istanbul",
    "iso:country":"TR",
    "name:und_x_variant":[
        "Melikviran",
        "Melik\u00f6ren"
    ],
    "wof:name":"Melikoren",
    "wof:placetype":"locality"
},
  "geometry": {"coordinates":[36.0318,38.46618],"type":"Point"}
}