{
  "type": "Feature",
  "properties": {
    "gn:admin1_code":"58.0",
    "gn:asciiname":"Imirhan",
    "gn:country_code":"TR",
    "gn:dem":1297,
    "gn:feature_class":"P",
    "gn:feature_code":"PPL",
    "gn:name":"\u0130mirhan",
    "gn:population":0,
    "gn:timezone":"Europe/Istanbul",
    "iso:country":"TR",
    "wof:name":"Imirhan",
    "wof:placetype":"locality"
},
  "geometry": {"coordinates":[37.74644,39.4547],"type":"Point"}
}