{
  "type": "Feature",
  "properties": {
    "gn:country":"TR",
    "gn:fcode":"PPL",
    "gn:pop":11000,
    "iso:country":"TR",
    "name:azb_x_preferred":[
        "\u0627\u0626\u0634\u0645\u0647"
    ],
    "name:chi_x_preferred":[
        "\u57c3\u4ec0\u6885"
    ],
    "name:dut_x_preferred":[
        "E\u015fme"
    ],
    "name:eng_x_preferred":[
        "E\u015fme"
    ],
    "name:epo_x_preferred":[
        "E\u015fme"
    ],
    "name:fre_x_preferred":[
        "E\u015fme"
    ],
    "name:ger_x_preferred":[
        "E\u015fme"
    ],
    "name:ita_x_preferred":[
        "Distretto di E\u015fme"
    ],
    "name:may_x_preferred":[
        "E\u015fme"
    ],
    "name:mrj_x_preferred":[
        "\u042d\u0448\u043c\u0435"
    ],
    "name:nan_x_preferred":[
        "E\u015fme"
    ],
    "name:nno_x_preferred":[
        "E\u015fme"
    ],
    "name:nob_x_preferred":[
        "E\u015fme"
    ],
    "name:ota_x_preferred":[
        "\u0627\u0634\u0645\u0647"
    ],
    "name:per_x_preferred":[
        "\u0627\u0634\u0645\u0647"
    ],
    "name:pnb_x_preferred":[
        "\u0636\u0644\u0639 \u0627\u0634\u0645\u06d2"
    ],
    "name:rus_x_preferred":[
        "\u042d\u0448\u043c\u0435"
    ],
    "name:swa_x_preferred":[
        "E\u015fme"
    ],
    "name:tur_x_preferred":[
        "E\u015fme"
    ],
    "name:urd_x_preferred":[
        "\u0627\u0634\u0645\u06d2"
    ],
    "name:vie_x_preferred":[
        "E\u015fme"
    ],
    "qs:name":"E\u015fme",
    "qs:name_adm0":"Turkey",
    "qs:name_adm1":"U\u015fak",
    "qs:photos_9r":0,
    "qs:photos_sr":0,
    "qs:placetype":"Town",
    "qs:pop_sr":"6",
    "wd:wordcount":103,
    "wof:name":"E\u015fme",
    "wof:placetype":"locality",
    "wof:population":11000
},
  "geometry": {"coordinates":[28.96905,38.39976],"type":"Point"}
}