{
  "type": "Feature",
  "properties": {
    "gn:admin1_code":"16",
    "gn:asciiname":"Kosenhoroz",
    "gn:country_code":"TR",
    "gn:dem":211,
    "gn:feature_class":"P",
    "gn:feature_code":"PPL",
    "gn:name":"K\u00f6senhoroz",
    "gn:population":0,
    "gn:timezone":"Europe/Istanbul",
    "iso:country":"TR",
    "name:tur_x_preferred":[
        "K\u00f6senhoroz"
    ],
    "wof:name":"Kosenhoroz",
    "wof:placetype":"locality"
},
  "geometry": {"coordinates":[28.52766,39.92706],"type":"Point"}
}