{
  "type": "Feature",
  "properties": {
    "gn:admin1_code":"58.0",
    "gn:asciiname":"Bogazkoy",
    "gn:country_code":"TR",
    "gn:dem":1191,
    "gn:feature_class":"P",
    "gn:feature_code":"PPL",
    "gn:name":"Bo\u011fazk\u00f6y",
    "gn:population":0,
    "gn:timezone":"Europe/Istanbul",
    "iso:country":"TR",
    "name:und_x_variant":[
        "K\u00e2rul",
        "K\u00e2rol",
        "Bo\u011fazk\u00f6y"
    ],
    "wof:name":"Bogazkoy",
    "wof:placetype":"locality"
},
  "geometry": {"coordinates":[38.52432,40.08695],"type":"Point"}
}