{
  "type": "Feature",
  "properties": {
    "gn:admin1_code":"19.0",
    "gn:asciiname":"Damyani",
    "gn:country_code":"TR",
    "gn:dem":1163,
    "gn:feature_class":"P",
    "gn:feature_code":"PPL",
    "gn:name":"Damyan\u0131",
    "gn:population":0,
    "gn:timezone":"Europe/Istanbul",
    "iso:country":"TR",
    "wof:name":"Damyani",
    "wof:placetype":"locality"
},
  "geometry": {"coordinates":[34.09763,40.74901],"type":"Point"}
}