{
  "type": "Feature",
  "properties": {
    "gn:admin1_code":"80.0",
    "gn:asciiname":"Orencik",
    "gn:country_code":"TR",
    "gn:dem":552,
    "gn:feature_class":"P",
    "gn:feature_code":"PPL",
    "gn:name":"\u00d6rencik",
    "gn:population":0,
    "gn:timezone":"Europe/Istanbul",
    "iso:country":"TR",
    "name:tur_x_preferred":[
        "\u00d6rencik"
    ],
    "wof:name":"Orencik",
    "wof:placetype":"locality"
},
  "geometry": {"coordinates":[42.07656,37.26636],"type":"Point"}
}