{
  "type": "Feature",
  "properties": {
    "gn:admin1_code":"46.0",
    "gn:asciiname":"Bunduk",
    "gn:country_code":"TR",
    "gn:dem":1283,
    "gn:feature_class":"P",
    "gn:feature_code":"PPL",
    "gn:name":"Bunduk",
    "gn:population":0,
    "gn:timezone":"Europe/Istanbul",
    "iso:country":"TR",
    "name:und_x_variant":[
        "Bundukk\u00f6y\u00fc",
        "Akg\u00fcm\u00fc\u015f"
    ],
    "wof:name":"Bunduk",
    "wof:placetype":"locality"
},
  "geometry": {"coordinates":[36.54078,37.73375],"type":"Point"}
}