{
  "type": "Feature",
  "properties": {
    "gn:admin1_code":"50",
    "gn:asciiname":"Inalli",
    "gn:country_code":"TR",
    "gn:dem":1207,
    "gn:feature_class":"P",
    "gn:feature_code":"PPL",
    "gn:name":"\u0130nall\u0131",
    "gn:population":0,
    "gn:timezone":"Europe/Istanbul",
    "iso:country":"TR",
    "wof:name":"Inalli",
    "wof:placetype":"locality"
},
  "geometry": {"coordinates":[34.50885,38.57878],"type":"Point"}
}