{
  "type": "Feature",
  "properties": {
    "gn:admin1_code":"81",
    "gn:asciiname":"Narlik",
    "gn:country_code":"TR",
    "gn:dem":49,
    "gn:feature_class":"P",
    "gn:feature_code":"PPL",
    "gn:name":"Narl\u0131k",
    "gn:population":0,
    "gn:timezone":"Europe/Istanbul",
    "iso:country":"TR",
    "name:und_x_variant":[
        "Tahtal\u0131",
        "Narl\u0131k"
    ],
    "wof:name":"Narlik",
    "wof:placetype":"locality"
},
  "geometry": {"coordinates":[35.85183,36.9145],"type":"Point"}
}