{
  "type": "Feature",
  "properties": {
    "gn:admin1_code":"60.0",
    "gn:asciiname":"Edekoy",
    "gn:country_code":"TR",
    "gn:dem":698,
    "gn:feature_class":"P",
    "gn:feature_code":"PPL",
    "gn:name":"Edek\u00f6y",
    "gn:population":0,
    "gn:timezone":"Europe/Istanbul",
    "iso:country":"TR",
    "name:und_x_variant":[
        "\u0130de",
        "Ede",
        "Edek\u00f6y"
    ],
    "wof:name":"Edekoy",
    "wof:placetype":"locality"
},
  "geometry": {"coordinates":[35.99253,40.32846],"type":"Point"}
}