{
  "type": "Feature",
  "properties": {
    "gn:admin1_code":"4.0",
    "gn:asciiname":"Yukari Damla",
    "gn:country_code":"TR",
    "gn:dem":1872,
    "gn:feature_class":"P",
    "gn:feature_code":"PPL",
    "gn:name":"Yukar\u0131 Damla",
    "gn:population":0,
    "gn:timezone":"Europe/Istanbul",
    "iso:country":"TR",
    "name:tur_x_preferred":[
        "Yukar\u0131damla"
    ],
    "name:tur_x_variant":[
        "Yukar\u0131 Damla"
    ],
    "wof:name":"Yukari Damla",
    "wof:placetype":"locality"
},
  "geometry": {"coordinates":[43.06073,39.21467],"type":"Point"}
}