{
  "type": "Feature",
  "properties": {
    "gn:admin1_code":"10",
    "gn:asciiname":"Karapurcek",
    "gn:country_code":"TR",
    "gn:dem":40,
    "gn:feature_class":"P",
    "gn:feature_code":"PPL",
    "gn:name":"Karap\u00fcr\u00e7ek",
    "gn:population":0,
    "gn:timezone":"Europe/Istanbul",
    "iso:country":"TR",
    "name:tur_x_preferred":[
        "Karap\u00fcr\u00e7ek"
    ],
    "wof:name":"Karapurcek",
    "wof:placetype":"locality"
},
  "geometry": {"coordinates":[28.22083,39.97222],"type":"Point"}
}