{
  "type": "Feature",
  "properties": {
    "gn:admin1_code":"37.0",
    "gn:asciiname":"Altikulac",
    "gn:country_code":"TR",
    "gn:dem":308,
    "gn:feature_class":"P",
    "gn:feature_code":"PPL",
    "gn:name":"Alt\u0131kula\u00e7",
    "gn:population":0,
    "gn:timezone":"Europe/Istanbul",
    "iso:country":"TR",
    "wof:name":"Altikulac",
    "wof:placetype":"locality"
},
  "geometry": {"coordinates":[34.08917,41.95727],"type":"Point"}
}