{
  "type": "Feature",
  "properties": {
    "gn:admin1_code":"10",
    "gn:asciiname":"Avunduk",
    "gn:country_code":"TR",
    "gn:dem":405,
    "gn:feature_class":"P",
    "gn:feature_code":"PPL",
    "gn:name":"Avunduk",
    "gn:population":0,
    "gn:timezone":"Europe/Istanbul",
    "iso:country":"TR",
    "name:tur_x_preferred":[
        "Avunduk"
    ],
    "wof:name":"Avunduk",
    "wof:placetype":"locality"
},
  "geometry": {"coordinates":[27.0339,39.41089],"type":"Point"}
}