{
  "type": "Feature",
  "properties": {
    "gn:admin1_code":"15",
    "gn:asciiname":"Onacak",
    "gn:country_code":"TR",
    "gn:dem":1203,
    "gn:feature_class":"P",
    "gn:feature_code":"PPL",
    "gn:name":"Onacak",
    "gn:population":0,
    "gn:timezone":"Europe/Istanbul",
    "iso:country":"TR",
    "wof:name":"Onacak",
    "wof:placetype":"locality"
},
  "geometry": {"coordinates":[29.92288,37.663],"type":"Point"}
}