{
  "type": "Feature",
  "properties": {
    "gn:admin1_code":"14",
    "gn:asciiname":"Yagbaslar",
    "gn:country_code":"TR",
    "gn:dem":1221,
    "gn:feature_class":"P",
    "gn:feature_code":"PPL",
    "gn:name":"Ya\u011fba\u015flar",
    "gn:population":0,
    "gn:timezone":"Europe/Istanbul",
    "iso:country":"TR",
    "wof:name":"Yagbaslar",
    "wof:placetype":"locality"
},
  "geometry": {"coordinates":[31.99312,40.68878],"type":"Point"}
}