{
  "type": "Feature",
  "properties": {
    "gn:admin1_code":"24",
    "gn:asciiname":"Harmantepe",
    "gn:country_code":"TR",
    "gn:dem":1495,
    "gn:feature_class":"P",
    "gn:feature_code":"PPL",
    "gn:name":"Harmantepe",
    "gn:population":0,
    "gn:timezone":"Europe/Istanbul",
    "iso:country":"TR",
    "wof:name":"Harmantepe",
    "wof:placetype":"locality"
},
  "geometry": {"coordinates":[40.08333,39.83333],"type":"Point"}
}