{
  "type": "Feature",
  "properties": {
    "gn:admin1_code":"58",
    "gn:asciiname":"Kizilcakisla",
    "gn:country_code":"TR",
    "gn:dem":1273,
    "gn:feature_class":"P",
    "gn:feature_code":"PPL",
    "gn:name":"K\u0131z\u0131lcak\u0131\u015fla",
    "gn:population":0,
    "gn:timezone":"Europe/Istanbul",
    "iso:country":"TR",
    "name:und_x_variant":[
        "K\u0131z\u0131lcak\u0131\u015fla K\u00f6y\u00fc",
        "K\u0131z\u0131lcak\u0131\u015fla"
    ],
    "wof:name":"Kizilcakisla",
    "wof:placetype":"locality"
},
  "geometry": {"coordinates":[36.32434,39.29371],"type":"Point"}
}