{
  "type": "Feature",
  "properties": {
    "gn:admin1_code":"54.0",
    "gn:asciiname":"Magara",
    "gn:cc2":"TR",
    "gn:country_code":"TR",
    "gn:dem":43,
    "gn:feature_class":"P",
    "gn:feature_code":"PPL",
    "gn:name":"Ma\u011fara",
    "gn:population":0,
    "gn:timezone":"Europe/Istanbul",
    "iso:country":"TR",
    "name:und_x_variant":[
        "Ma\u011farak\u00f6y",
        "Ma\u011fara"
    ],
    "wof:name":"Magara",
    "wof:placetype":"locality"
},
  "geometry": {"coordinates":[30.59528,40.91806],"type":"Point"}
}