{
  "type": "Feature",
  "properties": {
    "gn:admin1_code":"16.0",
    "gn:asciiname":"Sule",
    "gn:country_code":"TR",
    "gn:dem":578,
    "gn:feature_class":"P",
    "gn:feature_code":"PPL",
    "gn:name":"S\u00fcle",
    "gn:population":0,
    "gn:timezone":"Europe/Istanbul",
    "iso:country":"TR",
    "name:und_x_variant":[
        "S\u00fclek\u00f6y",
        "S\u00fcle"
    ],
    "wof:name":"Sule",
    "wof:placetype":"locality"
},
  "geometry": {"coordinates":[29.39986,40.03993],"type":"Point"}
}