{
  "type": "Feature",
  "properties": {
    "gn:admin1_code":"14.0",
    "gn:asciiname":"Yukaridedegan",
    "gn:country_code":"TR",
    "gn:dem":989,
    "gn:feature_class":"P",
    "gn:feature_code":"PPL",
    "gn:name":"Yukar\u0131dede\u011fan",
    "gn:population":0,
    "gn:timezone":"Europe/Istanbul",
    "iso:country":"TR",
    "name:und_x_variant":[
        "Dedek\u00e2n",
        "Yukar\u0131dede\u011fan",
        "Dedeken"
    ],
    "wof:name":"Yukaridedegan",
    "wof:placetype":"locality"
},
  "geometry": {"coordinates":[31.1431,40.6242],"type":"Point"}
}