{
  "type": "Feature",
  "properties": {
    "gn:country":"TR",
    "gn:fcode":"PPL",
    "gn:pop":21327,
    "iso:country":"TR",
    "name:azb_x_preferred":[
        "\u0686\u06cc\u0646\u0647"
    ],
    "name:deu_x_preferred":[
        "\u00c7ine"
    ],
    "name:eng_x_preferred":[
        "\u00c7ine"
    ],
    "name:epo_x_preferred":[
        "\u00c7ine"
    ],
    "name:fas_x_preferred":[
        "\u0686\u06cc\u0646\u0647"
    ],
    "name:fra_x_preferred":[
        "\u00c7ine"
    ],
    "name:ita_x_preferred":[
        "Distretto di \u00c7ine"
    ],
    "name:lbe_x_preferred":[
        "\u0427\u0438\u043d\u0435"
    ],
    "name:lit_x_preferred":[
        "\u010cin\u0117"
    ],
    "name:min_x_preferred":[
        "\u00c7ine"
    ],
    "name:mrj_x_preferred":[
        "\u0427\u0438\u043d\u0435"
    ],
    "name:msa_x_preferred":[
        "\u00c7ine"
    ],
    "name:nan_x_preferred":[
        "\u00c7ine"
    ],
    "name:nld_x_preferred":[
        "\u00c7ine"
    ],
    "name:nno_x_preferred":[
        "\u00c7ine"
    ],
    "name:swa_x_preferred":[
        "\u00c7ine"
    ],
    "name:tur_x_preferred":[
        "\u00c7ine"
    ],
    "name:unk_x_variant":[
        "Hanakp\u0131nar"
    ],
    "name:urd_x_preferred":[
        "\u0686\u06cc\u0646\u06d2"
    ],
    "name:vie_x_preferred":[
        "\u00c7ine"
    ],
    "name:zho_x_preferred":[
        "\u5947\u5167"
    ],
    "qs:name":"\u00c7ine",
    "qs:photos_9r":0,
    "qs:photos_sr":0,
    "qs:pop_sr":"7",
    "wd:wordcount":278,
    "wof:name":"\u00c7ine",
    "wof:placetype":"locality",
    "wof:population":21327
},
  "geometry": {"coordinates":[28.06139,37.61167],"type":"Point"}
}