{
  "type": "Feature",
  "properties": {
    "gn:admin1_code":"65.0",
    "gn:asciiname":"Isinli",
    "gn:country_code":"TR",
    "gn:dem":2059,
    "gn:feature_class":"P",
    "gn:feature_code":"PPL",
    "gn:name":"I\u015f\u0131nl\u0131",
    "gn:population":0,
    "gn:timezone":"Europe/Istanbul",
    "iso:country":"TR",
    "name:tur_x_preferred":[
        "I\u015f\u0131nl\u0131"
    ],
    "wof:name":"Isinli",
    "wof:placetype":"locality"
},
  "geometry": {"coordinates":[43.10586,38.0389],"type":"Point"}
}