{
  "type": "Feature",
  "properties": {
    "gn:admin1_code":"88.0",
    "gn:asciiname":"Bostanli",
    "gn:country_code":"TR",
    "gn:dem":2167,
    "gn:feature_class":"P",
    "gn:feature_code":"PPL",
    "gn:name":"Bostanl\u0131",
    "gn:population":0,
    "gn:timezone":"Europe/Istanbul",
    "iso:country":"TR",
    "name:und_x_variant":[
        "Ha\u015feri",
        "Bostanl\u0131"
    ],
    "wof:name":"Bostanli",
    "wof:placetype":"locality"
},
  "geometry": {"coordinates":[43.37655,40.03135],"type":"Point"}
}