{
  "type": "Feature",
  "properties": {
    "gn:admin1_code":"31",
    "gn:asciiname":"Gulcihan",
    "gn:country_code":"TR",
    "gn:dem":6,
    "gn:feature_class":"P",
    "gn:feature_code":"PPL",
    "gn:name":"G\u00fclcihan",
    "gn:population":0,
    "gn:timezone":"Europe/Istanbul",
    "iso:country":"TR",
    "name:tur_x_preferred":[
        "G\u00fclcihan"
    ],
    "wof:name":"Gulcihan",
    "wof:placetype":"locality"
},
  "geometry": {"coordinates":[35.95436,36.4631],"type":"Point"}
}