{
  "type": "Feature",
  "properties": {
    "gn:admin1_code":"16",
    "gn:asciiname":"Yazlica",
    "gn:country_code":"TR",
    "gn:dem":1042,
    "gn:feature_class":"P",
    "gn:feature_code":"PPL",
    "gn:name":"Yazl\u0131ca",
    "gn:population":0,
    "gn:timezone":"Europe/Istanbul",
    "iso:country":"TR",
    "name:tur_x_preferred":[
        "Yazl\u0131ca"
    ],
    "name:und_x_variant":[
        "Karas\u0131"
    ],
    "wof:name":"Yazlica",
    "wof:placetype":"locality"
},
  "geometry": {"coordinates":[29.07582,39.94754],"type":"Point"}
}