{
  "type": "Feature",
  "properties": {
    "gn:admin1_code":"8.0",
    "gn:asciiname":"Kobak",
    "gn:country_code":"TR",
    "gn:dem":512,
    "gn:feature_class":"P",
    "gn:feature_code":"PPL",
    "gn:name":"Kobak",
    "gn:population":0,
    "gn:timezone":"Europe/Istanbul",
    "iso:country":"TR",
    "name:und_x_variant":[
        "Ba\u015fk\u00f6y",
        "Kobak"
    ],
    "wof:name":"Kobak",
    "wof:placetype":"locality"
},
  "geometry": {"coordinates":[41.3944,41.27571],"type":"Point"}
}