{
  "type": "Feature",
  "properties": {
    "gn:admin1_code":"2.0",
    "gn:asciiname":"Karahasan",
    "gn:country_code":"TR",
    "gn:dem":947,
    "gn:feature_class":"P",
    "gn:feature_code":"PPL",
    "gn:name":"Karahasan",
    "gn:population":0,
    "gn:timezone":"Europe/Istanbul",
    "iso:country":"TR",
    "wof:name":"Karahasan",
    "wof:placetype":"locality"
},
  "geometry": {"coordinates":[37.58964,37.82989],"type":"Point"}
}