{
  "type": "Feature",
  "properties": {
    "gn:admin1_code":"32",
    "gn:asciiname":"Elmapinar",
    "gn:country_code":"TR",
    "gn:dem":1422,
    "gn:feature_class":"P",
    "gn:feature_code":"PPL",
    "gn:name":"Elmap\u0131nar",
    "gn:population":0,
    "gn:timezone":"Europe/Istanbul",
    "iso:country":"TR",
    "name:und_x_variant":[
        "Navadl\u0131",
        "Elmap\u0131nar"
    ],
    "wof:name":"Elmapinar",
    "wof:placetype":"locality"
},
  "geometry": {"coordinates":[33.42587,36.89337],"type":"Point"}
}