{
  "type": "Feature",
  "properties": {
    "gn:admin1_code":"55.0",
    "gn:asciiname":"Terzili",
    "gn:country_code":"TR",
    "gn:dem":159,
    "gn:feature_class":"P",
    "gn:feature_code":"PPL",
    "gn:name":"Terzili",
    "gn:population":0,
    "gn:timezone":"Europe/Istanbul",
    "iso:country":"TR",
    "wof:name":"Terzili",
    "wof:placetype":"locality"
},
  "geometry": {"coordinates":[35.80761,41.4502],"type":"Point"}
}