{
  "type": "Feature",
  "properties": {
    "gn:admin1_code":"20",
    "gn:asciiname":"Belenkoy",
    "gn:country_code":"TR",
    "gn:dem":994,
    "gn:feature_class":"P",
    "gn:feature_code":"PPL",
    "gn:name":"Belenk\u00f6y",
    "gn:population":0,
    "gn:timezone":"Europe/Istanbul",
    "iso:country":"TR",
    "name:tur_x_preferred":[
        "Belenk\u00f6y"
    ],
    "wof:name":"Belenkoy",
    "wof:placetype":"locality"
},
  "geometry": {"coordinates":[28.74468,37.43604000000001],"type":"Point"}
}