{
  "type": "Feature",
  "properties": {
    "gn:admin1_code":"25.0",
    "gn:asciiname":"Vartinik",
    "gn:country_code":"TR",
    "gn:dem":2037,
    "gn:feature_class":"P",
    "gn:feature_code":"PPL",
    "gn:name":"Vartinik",
    "gn:population":0,
    "gn:timezone":"Europe/Istanbul",
    "iso:country":"TR",
    "name:eng_x_preferred":[
        "Vartinik"
    ],
    "name:rus_x_preferred":[
        "\u0412\u0430\u0440\u0442\u0438\u043d\u0438\u043a"
    ],
    "wof:name":"Vartinik",
    "wof:placetype":"locality"
},
  "geometry": {"coordinates":[40.66667,40.25],"type":"Point"}
}