{
  "type": "Feature",
  "properties": {
    "gn:admin1_code":"28.0",
    "gn:asciiname":"Caglayan",
    "gn:country_code":"TR",
    "gn:dem":870,
    "gn:feature_class":"P",
    "gn:feature_code":"PPL",
    "gn:name":"\u00c7a\u011flayan",
    "gn:population":0,
    "gn:timezone":"Europe/Istanbul",
    "iso:country":"TR",
    "name:tur_x_preferred":[
        "\u00c7a\u011flayan"
    ],
    "wof:name":"Caglayan",
    "wof:placetype":"locality"
},
  "geometry": {"coordinates":[39.12174,40.8359],"type":"Point"}
}