{
  "type": "Feature",
  "properties": {
    "gn:admin1_code":"25",
    "gn:asciiname":"Kahramanlar",
    "gn:country_code":"TR",
    "gn:dem":1781,
    "gn:feature_class":"P",
    "gn:feature_code":"PPL",
    "gn:name":"Kahramanlar",
    "gn:population":0,
    "gn:timezone":"Europe/Istanbul",
    "iso:country":"TR",
    "name:tur_x_preferred":[
        "Kahramanlar"
    ],
    "name:und_x_variant":[
        "Garan",
        "Karaz",
        "Karamanlar"
    ],
    "wof:name":"Kahramanlar",
    "wof:placetype":"locality"
},
  "geometry": {"coordinates":[41.11605,39.99232],"type":"Point"}
}