{
  "type": "Feature",
  "properties": {
    "gn:admin1_code":"46",
    "gn:asciiname":"Altas",
    "gn:country_code":"TR",
    "gn:dem":1128,
    "gn:feature_class":"P",
    "gn:feature_code":"PPL",
    "gn:name":"Alta\u015f",
    "gn:population":0,
    "gn:timezone":"Europe/Istanbul",
    "iso:country":"TR",
    "wof:name":"Altas",
    "wof:placetype":"locality"
},
  "geometry": {"coordinates":[36.97936,38.17044],"type":"Point"}
}