{
  "type": "Feature",
  "properties": {
    "gn:admin1_code":"21.0",
    "gn:asciiname":"Sevkenar",
    "gn:country_code":"TR",
    "gn:dem":990,
    "gn:feature_class":"P",
    "gn:feature_code":"PPL",
    "gn:name":"Sevkenar",
    "gn:population":0,
    "gn:timezone":"Europe/Istanbul",
    "iso:country":"TR",
    "wof:name":"Sevkenar",
    "wof:placetype":"locality"
},
  "geometry": {"coordinates":[41.17681,38.41586],"type":"Point"}
}