{
  "type": "Feature",
  "properties": {
    "gn:admin1_code":"60.0",
    "gn:asciiname":"Seyhnusrettin",
    "gn:country_code":"TR",
    "gn:dem":655,
    "gn:feature_class":"P",
    "gn:feature_code":"PPL",
    "gn:name":"\u015eeyhnusrettin",
    "gn:population":0,
    "gn:timezone":"Europe/Istanbul",
    "iso:country":"TR",
    "name:und_x_variant":[
        "\u015eeyhnusrattin",
        "\u015eeyhnusraddin",
        "\u015eeyhnusrettin"
    ],
    "wof:name":"Seyhnusrettin",
    "wof:placetype":"locality"
},
  "geometry": {"coordinates":[35.93875999999999,40.26295],"type":"Point"}
}