{
  "type": "Feature",
  "properties": {
    "gn:country":"TR",
    "gn:fcode":"PPL",
    "gn:population":596,
    "iso:country":"TR",
    "name:eng_x_preferred":[
        "Danal\u0131"
    ],
    "name:kur_x_preferred":[
        "Zercil"
    ],
    "name:msa_x_preferred":[
        "Danal\u0131"
    ],
    "name:nld_x_preferred":[
        "Danal\u0131"
    ],
    "name:rus_x_preferred":[
        "Zerdzhil\u2019"
    ],
    "name:tur_x_preferred":[
        "Danal\u0131"
    ],
    "name:vie_x_preferred":[
        "Danal\u0131"
    ],
    "qs:name":"Danal\u0131",
    "qs:photos_9r":0,
    "qs:photos_sr":0,
    "qs:pop_sr":"2",
    "wof:name":"Danal\u0131",
    "wof:placetype":"locality",
    "wof:population":596
},
  "geometry": {"coordinates":[41.25833,37.88278],"type":"Point"}
}