{
  "type": "Feature",
  "properties": {
    "gn:admin1_code":"77.0",
    "gn:asciiname":"Bayrampasa",
    "gn:country_code":"TR",
    "gn:dem":1715,
    "gn:feature_class":"P",
    "gn:feature_code":"PPL",
    "gn:name":"Bayrampa\u015fa",
    "gn:population":0,
    "gn:timezone":"Europe/Istanbul",
    "iso:country":"TR",
    "name:und_x_variant":[
        "Hi\u011fn\u0131",
        "Bayrampa\u015fa"
    ],
    "wof:name":"Bayrampasa",
    "wof:placetype":"locality"
},
  "geometry": {"coordinates":[39.82211,40.17357],"type":"Point"}
}