{
  "type": "Feature",
  "properties": {
    "gn:admin1_code":"20",
    "gn:asciiname":"Asagi Capak",
    "gn:cc2":"TR",
    "gn:country_code":"TR",
    "gn:dem":1401,
    "gn:feature_class":"P",
    "gn:feature_code":"PPL",
    "gn:name":"A\u015fa\u011f\u0131 \u00c7apak",
    "gn:population":0,
    "gn:timezone":"Europe/Istanbul",
    "iso:country":"TR",
    "name:und_x_variant":[
        "\u00c7apak",
        "A\u015fa\u011f\u0131 \u00c7apak"
    ],
    "wof:name":"Asagi Capak",
    "wof:placetype":"locality"
},
  "geometry": {"coordinates":[29.86667000000001,39.43333],"type":"Point"}
}