{
  "type": "Feature",
  "properties": {
    "gn:admin1_code":"82.0",
    "gn:asciiname":"Taslitarla",
    "gn:country_code":"TR",
    "gn:dem":1577,
    "gn:feature_class":"P",
    "gn:feature_code":"PPL",
    "gn:name":"Ta\u015fl\u0131tarla",
    "gn:population":0,
    "gn:timezone":"Europe/Istanbul",
    "iso:country":"TR",
    "wof:name":"Taslitarla",
    "wof:placetype":"locality"
},
  "geometry": {"coordinates":[32.95999,40.54611],"type":"Point"}
}