{
  "type": "Feature",
  "properties": {
    "gn:admin1_code":"81",
    "gn:asciiname":"Kestel",
    "gn:country_code":"TR",
    "gn:dem":23,
    "gn:feature_class":"P",
    "gn:feature_code":"PPL",
    "gn:name":"Kestel",
    "gn:population":0,
    "gn:timezone":"Europe/Istanbul",
    "iso:country":"TR",
    "name:rus_x_preferred":[
        "\u041a\u0435\u0441\u0442\u0435\u043b\u044c"
    ],
    "name:swa_x_preferred":[
        "Kestel"
    ],
    "name:tur_x_preferred":[
        "Kestel"
    ],
    "name:und_x_variant":[
        "Kestel \u00c7iftli\u011fi"
    ],
    "wof:name":"Kestel",
    "wof:placetype":"locality"
},
  "geometry": {"coordinates":[35.11865,36.97057],"type":"Point"}
}