{
  "type": "Feature",
  "properties": {
    "gn:admin1_code":"17.0",
    "gn:asciiname":"Comakli",
    "gn:country_code":"TR",
    "gn:dem":112,
    "gn:feature_class":"P",
    "gn:feature_code":"PPL",
    "gn:name":"\u00c7omakl\u0131",
    "gn:population":0,
    "gn:timezone":"Europe/Istanbul",
    "iso:country":"TR",
    "wof:name":"Comakli",
    "wof:placetype":"locality"
},
  "geometry": {"coordinates":[27.13797000000001,40.04457],"type":"Point"}
}