{
  "type": "Feature",
  "properties": {
    "gn:admin1_code":"19.0",
    "gn:asciiname":"Hacilarhani",
    "gn:country_code":"TR",
    "gn:dem":1135,
    "gn:feature_class":"P",
    "gn:feature_code":"PPL",
    "gn:name":"Hac\u0131larhan\u0131",
    "gn:population":0,
    "gn:timezone":"Europe/Istanbul",
    "iso:country":"TR",
    "name:und_x_variant":[
        "\u00c7erke\u015f",
        "Hac\u0131larhan\u0131\u00e7erkes",
        "T\u00fcrkhac\u0131larhan\u0131 K\u00f6y\u00fc",
        "Hac\u0131larhan\u0131\u00e7erkez",
        "Hac\u0131lar Han",
        "Hac\u0131larkan\u0131",
        "Hac\u0131larhan\u0131"
    ],
    "wof:name":"Hacilarhani",
    "wof:placetype":"locality"
},
  "geometry": {"coordinates":[34.57553,40.28607],"type":"Point"}
}