{
  "type": "Feature",
  "properties": {
    "gn:admin1_code":"66",
    "gn:asciiname":"Hatip",
    "gn:country_code":"TR",
    "gn:dem":829,
    "gn:feature_class":"P",
    "gn:feature_code":"PPL",
    "gn:name":"Hatip",
    "gn:population":0,
    "gn:timezone":"Europe/Istanbul",
    "iso:country":"TR",
    "wof:name":"Hatip",
    "wof:placetype":"locality"
},
  "geometry": {"coordinates":[34.5096,39.74586],"type":"Point"}
}