{
  "type": "Feature",
  "properties": {
    "gn:admin1_code":"81",
    "gn:asciiname":"Dedepinari",
    "gn:country_code":"TR",
    "gn:dem":15,
    "gn:feature_class":"P",
    "gn:feature_code":"PPL",
    "gn:name":"Dedep\u0131nar\u0131",
    "gn:population":0,
    "gn:timezone":"Europe/Istanbul",
    "iso:country":"TR",
    "wof:name":"Dedepinari",
    "wof:placetype":"locality"
},
  "geometry": {"coordinates":[35.48155999999999,36.92746],"type":"Point"}
}