{
  "type": "Feature",
  "properties": {
    "gn:admin1_code":"55",
    "gn:asciiname":"Tefekli",
    "gn:country_code":"TR",
    "gn:dem":270,
    "gn:feature_class":"P",
    "gn:feature_code":"PPL",
    "gn:name":"Tefekli",
    "gn:population":0,
    "gn:timezone":"Europe/Istanbul",
    "iso:country":"TR",
    "name:tur_x_preferred":[
        "Tefekli"
    ],
    "wof:name":"Tefekli",
    "wof:placetype":"locality"
},
  "geometry": {"coordinates":[35.66532,41.55648],"type":"Point"}
}