{
  "type": "Feature",
  "properties": {
    "gn:admin1_code":"82.0",
    "gn:asciiname":"Asagi Meydan",
    "gn:country_code":"TR",
    "gn:dem":1197,
    "gn:feature_class":"P",
    "gn:feature_code":"PPL",
    "gn:name":"A\u015fa\u011f\u0131 Meydan",
    "gn:population":0,
    "gn:timezone":"Europe/Istanbul",
    "iso:country":"TR",
    "wof:name":"Asagi Meydan",
    "wof:placetype":"locality"
},
  "geometry": {"coordinates":[33.65145,40.96582],"type":"Point"}
}