{
  "type": "Feature",
  "properties": {
    "gn:admin1_code":"31",
    "gn:asciiname":"Demen",
    "gn:country_code":"TR",
    "gn:dem":511,
    "gn:feature_class":"P",
    "gn:feature_code":"PPL",
    "gn:name":"Demen",
    "gn:population":0,
    "gn:timezone":"Europe/Istanbul",
    "iso:country":"TR",
    "name:deu_x_preferred":[
        "Demen"
    ],
    "name:epo_x_preferred":[
        "Demen"
    ],
    "name:fas_x_preferred":[
        "\u062f\u0645\u0646"
    ],
    "name:fra_x_preferred":[
        "Demen"
    ],
    "name:hun_x_preferred":[
        "Demen"
    ],
    "name:ita_x_preferred":[
        "Demen"
    ],
    "name:kaz_x_preferred":[
        "\u0414\u0435\u043c\u0435\u043d"
    ],
    "name:kir_x_preferred":[
        "\u0414\u0435\u043c\u0435\u043d"
    ],
    "name:mkd_x_preferred":[
        "\u0414\u0435\u043c\u0435\u043d"
    ],
    "name:msa_x_preferred":[
        "Demen"
    ],
    "name:nld_x_preferred":[
        "Demen"
    ],
    "name:pol_x_preferred":[
        "Demen"
    ],
    "name:por_x_preferred":[
        "Demen"
    ],
    "name:ron_x_preferred":[
        "Demen"
    ],
    "name:rus_x_preferred":[
        "\u0414\u0435\u043c\u0435\u043d"
    ],
    "name:spa_x_preferred":[
        "Demen"
    ],
    "name:srp_x_preferred":[
        "\u0414\u0435\u043c\u0435\u043d"
    ],
    "name:tgl_x_preferred":[
        "Demen"
    ],
    "name:tur_x_preferred":[
        "Demen"
    ],
    "name:ukr_x_preferred":[
        "\u0414\u0435\u043c\u0435\u043d"
    ],
    "name:uzb_x_preferred":[
        "Demen"
    ],
    "name:vie_x_preferred":[
        "Demen"
    ],
    "name:vol_x_preferred":[
        "Demen"
    ],
    "name:war_x_preferred":[
        "Demen"
    ],
    "wof:name":"Demen",
    "wof:placetype":"locality"
},
  "geometry": {"coordinates":[36.24768,36.64333],"type":"Point"}
}