{
  "type": "Feature",
  "properties": {
    "gn:admin1_code":"31",
    "gn:asciiname":"Demen",
    "gn:country_code":"TR",
    "gn:dem":511,
    "gn:feature_class":"P",
    "gn:feature_code":"PPL",
    "gn:name":"Demen",
    "gn:population":0,
    "gn:timezone":"Europe/Istanbul",
    "iso:country":"TR",
    "name:tur_x_preferred":[
        "Demen"
    ],
    "wof:name":"Demen",
    "wof:placetype":"locality"
},
  "geometry": {"coordinates":[36.24768,36.64333],"type":"Point"}
}