{
  "type": "Feature",
  "properties": {
    "gn:admin1_code":"49",
    "gn:asciiname":"Yukarikoy",
    "gn:country_code":"TR",
    "gn:dem":1769,
    "gn:feature_class":"P",
    "gn:feature_code":"PPL",
    "gn:name":"Yukar\u0131k\u00f6y",
    "gn:population":0,
    "gn:timezone":"Europe/Istanbul",
    "iso:country":"TR",
    "name:tur_x_preferred":[
        "Yukar\u0131k\u00f6y"
    ],
    "name:und_x_variant":[
        "Ha\u00e7l\u0131"
    ],
    "wof:name":"Yukarikoy",
    "wof:placetype":"locality"
},
  "geometry": {"coordinates":[42.24752,38.98539],"type":"Point"}
}