{
  "type": "Feature",
  "properties": {
    "gn:admin1_code":"41.0",
    "gn:asciiname":"Alefli",
    "gn:country_code":"TR",
    "gn:dem":159,
    "gn:feature_class":"P",
    "gn:feature_code":"PPL",
    "gn:name":"Alefli",
    "gn:population":0,
    "gn:timezone":"Europe/Istanbul",
    "iso:country":"TR",
    "name:tur_x_preferred":[
        "Alefli"
    ],
    "name:und_x_variant":[
        "Durakl\u0131"
    ],
    "wof:name":"Alefli",
    "wof:placetype":"locality"
},
  "geometry": {"coordinates":[30.27115,40.95898],"type":"Point"}
}