{
  "type": "Feature",
  "properties": {
    "gn:admin1_code":"68.0",
    "gn:asciiname":"Olucak",
    "gn:country_code":"TR",
    "gn:dem":1508,
    "gn:feature_class":"P",
    "gn:feature_code":"PPL",
    "gn:name":"Olucak",
    "gn:population":0,
    "gn:timezone":"Europe/Istanbul",
    "iso:country":"TR",
    "name:und_x_variant":[
        "Y\u0131ld\u0131r\u0131mmu\u015famaha",
        "Mu\u015fameha",
        "Olucak"
    ],
    "wof:name":"Olucak",
    "wof:placetype":"locality"
},
  "geometry": {"coordinates":[32.82715,40.48236],"type":"Point"}
}