{
  "type": "Feature",
  "properties": {
    "gn:admin1_code":"17.0",
    "gn:asciiname":"Arabakonagi",
    "gn:country_code":"TR",
    "gn:dem":222,
    "gn:feature_class":"P",
    "gn:feature_code":"PPL",
    "gn:name":"Arabakona\u011f\u0131",
    "gn:population":0,
    "gn:timezone":"Europe/Istanbul",
    "iso:country":"TR",
    "wof:name":"Arabakonagi",
    "wof:placetype":"locality"
},
  "geometry": {"coordinates":[27.00073,40.27427],"type":"Point"}
}