{
  "type": "Feature",
  "properties": {
    "gn:admin1_code":"09",
    "gn:asciiname":"Simselli",
    "gn:country_code":"TR",
    "gn:dem":573,
    "gn:feature_class":"P",
    "gn:feature_code":"PPL",
    "gn:name":"\u015eim\u015felli",
    "gn:population":0,
    "gn:timezone":"Europe/Istanbul",
    "iso:country":"TR",
    "name:tur_x_preferred":[
        "\u015eim\u015felli"
    ],
    "wof:name":"Simselli",
    "wof:placetype":"locality"
},
  "geometry": {"coordinates":[28.34423,38.00668],"type":"Point"}
}