{
  "type": "Feature",
  "properties": {
    "gn:admin1_code":"68.0",
    "gn:asciiname":"Faikbey",
    "gn:country_code":"TR",
    "gn:dem":1249,
    "gn:feature_class":"P",
    "gn:feature_code":"PPL",
    "gn:name":"Faikbey",
    "gn:population":0,
    "gn:timezone":"Europe/Istanbul",
    "iso:country":"TR",
    "wof:name":"Faikbey",
    "wof:placetype":"locality"
},
  "geometry": {"coordinates":[33.21491,39.24478],"type":"Point"}
}