{
  "type": "Feature",
  "properties": {
    "gn:admin1_code":"85",
    "gn:asciiname":"Osmankahya",
    "gn:country_code":"TR",
    "gn:dem":422,
    "gn:feature_class":"P",
    "gn:feature_code":"PPL",
    "gn:name":"Osmankahya",
    "gn:population":0,
    "gn:timezone":"Europe/Istanbul",
    "iso:country":"TR",
    "wof:name":"Osmankahya",
    "wof:placetype":"locality"
},
  "geometry": {"coordinates":[32.04776,41.25044000000001],"type":"Point"}
}