{
  "type": "Feature",
  "properties": {
    "gn:admin1_code":"14.0",
    "gn:asciiname":"Dere",
    "gn:country_code":"TR",
    "gn:dem":1358,
    "gn:feature_class":"P",
    "gn:feature_code":"PPL",
    "gn:name":"Dere",
    "gn:population":0,
    "gn:timezone":"Europe/Istanbul",
    "iso:country":"TR",
    "name:und_x_variant":[
        "Tepekebem",
        "Tepegebem",
        "Dere"
    ],
    "wof:name":"Dere",
    "wof:placetype":"locality"
},
  "geometry": {"coordinates":[31.41667,40.45],"type":"Point"}
}