{
  "type": "Feature",
  "properties": {
    "gn:admin1_code":"44",
    "gn:asciiname":"Ayvali",
    "gn:country_code":"TR",
    "gn:dem":1239,
    "gn:feature_class":"P",
    "gn:feature_code":"PPL",
    "gn:name":"Ayval\u0131",
    "gn:population":0,
    "gn:timezone":"Europe/Istanbul",
    "iso:country":"TR",
    "name:tur_x_preferred":[
        "Ayval\u0131"
    ],
    "wof:name":"Ayvali",
    "wof:placetype":"locality"
},
  "geometry": {"coordinates":[37.61457,38.73183],"type":"Point"}
}