{
  "type": "Feature",
  "properties": {
    "gn:admin1_code":"20",
    "gn:asciiname":"Kizilcasogut",
    "gn:country_code":"TR",
    "gn:dem":827,
    "gn:feature_class":"P",
    "gn:feature_code":"PPL",
    "gn:name":"K\u0131z\u0131lcas\u00f6\u011f\u00fct",
    "gn:population":0,
    "gn:timezone":"Europe/Istanbul",
    "iso:country":"TR",
    "name:tur_x_preferred":[
        "K\u0131z\u0131lcas\u00f6\u011f\u00fct"
    ],
    "wof:name":"Kizilcasogut",
    "wof:placetype":"locality"
},
  "geometry": {"coordinates":[29.73572,38.28435],"type":"Point"}
}