{
  "type": "Feature",
  "properties": {
    "gn:admin1_code":"32",
    "gn:asciiname":"Cavusir",
    "gn:country_code":"TR",
    "gn:dem":3,
    "gn:feature_class":"P",
    "gn:feature_code":"PPL",
    "gn:name":"\u00c7avu\u015fir",
    "gn:population":0,
    "gn:timezone":"Europe/Istanbul",
    "iso:country":"TR",
    "name:tur_x_preferred":[
        "\u00c7avu\u015fir"
    ],
    "name:tur_x_variant":[
        "\u00c7avu\u015fbuca\u011f\u0131"
    ],
    "wof:name":"Cavusir",
    "wof:placetype":"locality"
},
  "geometry": {"coordinates":[33.91667,36.31667],"type":"Point"}
}