{
  "type": "Feature",
  "properties": {
    "gn:admin1_code":"55.0",
    "gn:asciiname":"Bazlamac",
    "gn:country_code":"TR",
    "gn:dem":107,
    "gn:feature_class":"P",
    "gn:feature_code":"PPL",
    "gn:name":"Bazlama\u00e7",
    "gn:population":0,
    "gn:timezone":"Europe/Istanbul",
    "iso:country":"TR",
    "name:eng_x_preferred":[
        "Bazlama\u00e7"
    ],
    "name:rus_x_preferred":[
        "\u0411\u0430\u0437\u043b\u0430\u043c\u0430\u0447"
    ],
    "wof:name":"Bazlamac",
    "wof:placetype":"locality"
},
  "geometry": {"coordinates":[36.95639,41.1275],"type":"Point"}
}