{
  "type": "Feature",
  "properties": {
    "gn:admin1_code":"80.0",
    "gn:asciiname":"Karakol",
    "gn:country_code":"TR",
    "gn:dem":449,
    "gn:feature_class":"P",
    "gn:feature_code":"PPL",
    "gn:name":"Karakol",
    "gn:population":0,
    "gn:timezone":"Europe/Istanbul",
    "iso:country":"TR",
    "name:und_x_variant":[
        "G\u00fcm\u00fc\u015fkaya"
    ],
    "wof:name":"Karakol",
    "wof:placetype":"locality"
},
  "geometry": {"coordinates":[41.83139,37.64528],"type":"Point"}
}