{
  "type": "Feature",
  "properties": {
    "gn:admin1_code":"21",
    "gn:asciiname":"Bereketli",
    "gn:country_code":"TR",
    "gn:dem":782,
    "gn:feature_class":"P",
    "gn:feature_code":"PPL",
    "gn:name":"Bereketli",
    "gn:population":0,
    "gn:timezone":"Europe/Istanbul",
    "iso:country":"TR",
    "name:und_x_variant":[
        "Zengetil",
        "Bereketli"
    ],
    "wof:name":"Bereketli",
    "wof:placetype":"locality"
},
  "geometry": {"coordinates":[39.81838,38.13519],"type":"Point"}
}