{
  "type": "Feature",
  "properties": {
    "gn:admin1_code":"63",
    "gn:asciiname":"Magara",
    "gn:country_code":"TR",
    "gn:dem":771,
    "gn:feature_class":"P",
    "gn:feature_code":"PPL",
    "gn:name":"Ma\u011fara",
    "gn:population":0,
    "gn:timezone":"Europe/Istanbul",
    "iso:country":"TR",
    "name:und_x_variant":[
        "Ma\u011fara",
        "Sar\u0131magar",
        "Sar\u0131ma\u011fara",
        "Sarymagara"
    ],
    "wof:name":"Magara",
    "wof:placetype":"locality"
},
  "geometry": {"coordinates":[38.70262,37.21162],"type":"Point"}
}