{
  "type": "Feature",
  "properties": {
    "gn:admin1_code":"55.0",
    "gn:asciiname":"Yaylakoy",
    "gn:country_code":"TR",
    "gn:dem":421,
    "gn:feature_class":"P",
    "gn:feature_code":"PPL",
    "gn:name":"Yaylak\u00f6y",
    "gn:population":0,
    "gn:timezone":"Europe/Istanbul",
    "iso:country":"TR",
    "name:und_x_variant":[
        "Yaylak\u00f6y",
        "Sar\u0131lark\u00f6y\u00fc"
    ],
    "wof:name":"Yaylakoy",
    "wof:placetype":"locality"
},
  "geometry": {"coordinates":[36.39916,41.06123],"type":"Point"}
}