{
  "type": "Feature",
  "properties": {
    "gn:admin1_code":"21",
    "gn:asciiname":"Hizlipinari",
    "gn:country_code":"TR",
    "gn:dem":758,
    "gn:feature_class":"P",
    "gn:feature_code":"PPL",
    "gn:name":"H\u0131zl\u0131p\u0131nar\u0131",
    "gn:population":0,
    "gn:timezone":"Europe/Istanbul",
    "iso:country":"TR",
    "name:tur_x_preferred":[
        "H\u0131zl\u0131p\u0131nar\u0131"
    ],
    "wof:name":"Hizlipinari",
    "wof:placetype":"locality"
},
  "geometry": {"coordinates":[40.46667,38.13333],"type":"Point"}
}