{
  "type": "Feature",
  "properties": {
    "gn:admin1_code":"59.0",
    "gn:asciiname":"Caylakoy",
    "gn:country_code":"TR",
    "gn:dem":140,
    "gn:feature_class":"P",
    "gn:feature_code":"PPL",
    "gn:name":"\u00c7aylak\u00f6y",
    "gn:population":0,
    "gn:timezone":"Europe/Istanbul",
    "iso:country":"TR",
    "name:tur_x_preferred":[
        "\u00c7aylak\u00f6y"
    ],
    "name:tur_x_variant":[
        "\u00c7ayla"
    ],
    "wof:name":"Caylakoy",
    "wof:placetype":"locality"
},
  "geometry": {"coordinates":[27.88638,41.39907],"type":"Point"}
}