{
  "type": "Feature",
  "properties": {
    "gn:admin1_code":"68",
    "gn:asciiname":"Kerpickoy",
    "gn:country_code":"TR",
    "gn:dem":1021,
    "gn:feature_class":"P",
    "gn:feature_code":"PPL",
    "gn:name":"Kerpi\u00e7k\u00f6y",
    "gn:population":0,
    "gn:timezone":"Europe/Istanbul",
    "iso:country":"TR",
    "name:tur_x_preferred":[
        "Kerpi\u00e7k\u00f6y"
    ],
    "name:tur_x_variant":[
        "Kerpi\u00e7"
    ],
    "wof:name":"Kerpickoy",
    "wof:placetype":"locality"
},
  "geometry": {"coordinates":[32.57667,39.07194000000001],"type":"Point"}
}