{
  "type": "Feature",
  "properties": {
    "gn:admin1_code":"12",
    "gn:asciiname":"Erentepe",
    "gn:country_code":"TR",
    "gn:dem":1485,
    "gn:feature_class":"P",
    "gn:feature_code":"PPL",
    "gn:name":"Erentepe",
    "gn:population":0,
    "gn:timezone":"Europe/Istanbul",
    "iso:country":"TR",
    "name:und_x_variant":[
        "\u015einek"
    ],
    "wof:name":"Erentepe",
    "wof:placetype":"locality"
},
  "geometry": {"coordinates":[40.46579000000001,38.80723],"type":"Point"}
}