{
  "type": "Feature",
  "properties": {
    "gn:country":"TR",
    "gn:fcode":"PPL",
    "gn:population":0,
    "iso:country":"TR",
    "name:und_x_variant":[
        "Sammezras\u0131"
    ],
    "qs:name":"Sammezraas\u0131",
    "qs:name_adm0":"Turkey",
    "qs:name_adm1":"Gaziantep",
    "qs:photos":127,
    "qs:photos_1k":26,
    "qs:photos_9k":1,
    "qs:photos_9r":3,
    "qs:photos_all":127,
    "qs:photos_sr":3,
    "qs:placetype":"Town",
    "qs:pop_sr":"0",
    "wof:name":"Sammezraas\u0131",
    "wof:placetype":"locality",
    "wof:population":0
},
  "geometry": {"coordinates":[37.28799,37.13668],"type":"Point"}
}