{
  "type": "Feature",
  "properties": {
    "gn:admin1_code":"68",
    "gn:asciiname":"Igciler",
    "gn:country_code":"TR",
    "gn:dem":892,
    "gn:feature_class":"P",
    "gn:feature_code":"PPL",
    "gn:name":"\u0130\u011fciler",
    "gn:population":0,
    "gn:timezone":"Europe/Istanbul",
    "iso:country":"TR",
    "wof:name":"Igciler",
    "wof:placetype":"locality"
},
  "geometry": {"coordinates":[32.05925,39.55398],"type":"Point"}
}