{
  "type": "Feature",
  "properties": {
    "gn:country":"TR",
    "gn:fcode":"PPL",
    "gn:population":119,
    "iso:country":"TR",
    "name:und_x_variant":[
        "\u0130nk\u0131l\u00e2p"
    ],
    "qs:name":"Inkylyap",
    "qs:photos_9r":0,
    "qs:photos_sr":0,
    "qs:pop_sr":"1",
    "wof:name":"Inkylyap",
    "wof:placetype":"locality",
    "wof:population":119
},
  "geometry": {"coordinates":[37.56139,36.73583],"type":"Point"}
}