{
  "type": "Feature",
  "properties": {
    "gn:admin1_code":"52.0",
    "gn:asciiname":"Bascardak",
    "gn:country_code":"TR",
    "gn:dem":801,
    "gn:feature_class":"P",
    "gn:feature_code":"PPL",
    "gn:name":"Ba\u015f\u00e7ardak",
    "gn:population":0,
    "gn:timezone":"Europe/Istanbul",
    "iso:country":"TR",
    "name:tur_x_preferred":[
        "Ba\u015f\u00e7ardak"
    ],
    "wof:name":"Bascardak",
    "wof:placetype":"locality"
},
  "geometry": {"coordinates":[37.76173,40.73379],"type":"Point"}
}