{
  "type": "Feature",
  "properties": {
    "gn:admin1_code":"54.0",
    "gn:asciiname":"Harmantepe",
    "gn:country_code":"TR",
    "gn:dem":192,
    "gn:feature_class":"P",
    "gn:feature_code":"PPL",
    "gn:name":"Harmantepe",
    "gn:population":0,
    "gn:timezone":"Europe/Istanbul",
    "iso:country":"TR",
    "name:tur_x_preferred":[
        "Harmantepe"
    ],
    "wof:name":"Harmantepe",
    "wof:placetype":"locality"
},
  "geometry": {"coordinates":[30.81099,40.77007],"type":"Point"}
}