{
  "type": "Feature",
  "properties": {
    "gn:admin1_code":"72",
    "gn:asciiname":"Yazioren",
    "gn:cc2":"TR",
    "gn:country_code":"TR",
    "gn:dem":978,
    "gn:feature_class":"P",
    "gn:feature_code":"PPL",
    "gn:name":"Yaz\u0131\u00f6ren",
    "gn:population":0,
    "gn:timezone":"Europe/Istanbul",
    "iso:country":"TR",
    "name:tur_x_preferred":[
        "Yaz\u0131\u00f6ren"
    ],
    "name:und_x_variant":[
        "Divan",
        "Deyvan"
    ],
    "wof:name":"Yazioren",
    "wof:placetype":"locality"
},
  "geometry": {"coordinates":[41.65139,37.54028],"type":"Point"}
}