{
  "type": "Feature",
  "properties": {
    "gn:admin1_code":"66",
    "gn:asciiname":"Koruk",
    "gn:country_code":"TR",
    "gn:dem":1176,
    "gn:feature_class":"P",
    "gn:feature_code":"PPL",
    "gn:name":"K\u00f6r\u00fck",
    "gn:population":0,
    "gn:timezone":"Europe/Istanbul",
    "iso:country":"TR",
    "name:und_x_variant":[
        "Gevr\u00f6k",
        "K\u00f6r\u00fck"
    ],
    "wof:name":"Koruk",
    "wof:placetype":"locality"
},
  "geometry": {"coordinates":[35.68822,39.7151],"type":"Point"}
}