{
  "type": "Feature",
  "properties": {
    "gn:admin1_code":"72.0",
    "gn:asciiname":"Yukari Ilica",
    "gn:country_code":"TR",
    "gn:dem":584,
    "gn:feature_class":"P",
    "gn:feature_code":"PPL",
    "gn:name":"Yukar\u0131 Il\u0131ca",
    "gn:population":0,
    "gn:timezone":"Europe/Istanbul",
    "iso:country":"TR",
    "name:tur_x_preferred":[
        "Yukar\u0131 Il\u0131ca"
    ],
    "wof:name":"Yukari Ilica",
    "wof:placetype":"locality"
},
  "geometry": {"coordinates":[40.28884,37.30369],"type":"Point"}
}