{
  "type": "Feature",
  "properties": {
    "gn:admin1_code":"81",
    "gn:asciiname":"Kucukcildirim",
    "gn:country_code":"TR",
    "gn:dem":12,
    "gn:feature_class":"P",
    "gn:feature_code":"PPL",
    "gn:name":"K\u00fc\u00e7\u00fck\u00e7\u0131ld\u0131r\u0131m",
    "gn:population":0,
    "gn:timezone":"Europe/Istanbul",
    "iso:country":"TR",
    "name:und_x_variant":[
        "K\u00fc\u00e7\u00fck\u00e7\u0131ld\u0131r\u0131m",
        "Hac\u0131habibli"
    ],
    "wof:name":"Kucukcildirim",
    "wof:placetype":"locality"
},
  "geometry": {"coordinates":[35.1491,36.92669],"type":"Point"}
}