{
  "type": "Feature",
  "properties": {
    "gn:admin1_code":"24",
    "gn:asciiname":"Yesilcay",
    "gn:country_code":"TR",
    "gn:dem":1409,
    "gn:feature_class":"P",
    "gn:feature_code":"PPL",
    "gn:name":"Ye\u015fil\u00e7ay",
    "gn:population":0,
    "gn:timezone":"Europe/Istanbul",
    "iso:country":"TR",
    "name:und_x_variant":[
        "E\u011frek",
        "Ekrek",
        "Ye\u015fil\u00e7ay"
    ],
    "wof:name":"Yesilcay",
    "wof:placetype":"locality"
},
  "geometry": {"coordinates":[39.35691,39.7196],"type":"Point"}
}