{
  "type": "Feature",
  "properties": {
    "gn:admin1_code":"48",
    "gn:asciiname":"Keciler",
    "gn:country_code":"TR",
    "gn:dem":152,
    "gn:feature_class":"P",
    "gn:feature_code":"PPL",
    "gn:name":"Ke\u00e7iler",
    "gn:population":0,
    "gn:timezone":"Europe/Istanbul",
    "iso:country":"TR",
    "name:tur_x_preferred":[
        "Ke\u00e7iler"
    ],
    "wof:name":"Keciler",
    "wof:placetype":"locality"
},
  "geometry": {"coordinates":[29.09687000000001,36.58634],"type":"Point"}
}