{
  "type": "Feature",
  "properties": {
    "gn:admin1_code":"81",
    "gn:asciiname":"Avcipinari",
    "gn:country_code":"TR",
    "gn:dem":1674,
    "gn:feature_class":"P",
    "gn:feature_code":"PPL",
    "gn:name":"Avc\u0131p\u0131nar\u0131",
    "gn:population":0,
    "gn:timezone":"Europe/Istanbul",
    "iso:country":"TR",
    "name:und_x_variant":[
        "Evcip\u0131nar",
        "Avc\u0131p\u0131nar\u0131",
        "Avganc\u0131k"
    ],
    "wof:name":"Avcipinari",
    "wof:placetype":"locality"
},
  "geometry": {"coordinates":[36.18333,38.08333],"type":"Point"}
}