{
  "type": "Feature",
  "properties": {
    "gn:admin1_code":"79.0",
    "gn:asciiname":"Hidirseyh",
    "gn:country_code":"TR",
    "gn:dem":1031,
    "gn:feature_class":"P",
    "gn:feature_code":"PPL",
    "gn:name":"H\u0131d\u0131r\u015feyh",
    "gn:population":0,
    "gn:timezone":"Europe/Istanbul",
    "iso:country":"TR",
    "wof:name":"Hidirseyh",
    "wof:placetype":"locality"
},
  "geometry": {"coordinates":[33.6605,40.02233],"type":"Point"}
}