{
  "type": "Feature",
  "properties": {
    "gn:admin1_code":"09",
    "gn:asciiname":"Tasoluk",
    "gn:country_code":"TR",
    "gn:dem":849,
    "gn:feature_class":"P",
    "gn:feature_code":"PPL",
    "gn:name":"Ta\u015foluk",
    "gn:population":0,
    "gn:timezone":"Europe/Istanbul",
    "iso:country":"TR",
    "name:tur_x_preferred":[
        "Ta\u015foluk"
    ],
    "wof:name":"Tasoluk",
    "wof:placetype":"locality"
},
  "geometry": {"coordinates":[28.64498,38.04751],"type":"Point"}
}