{
  "type": "Feature",
  "properties": {
    "gn:admin1_code":"03",
    "gn:asciiname":"Camlikoy",
    "gn:country_code":"TR",
    "gn:dem":1399,
    "gn:feature_class":"P",
    "gn:feature_code":"PPL",
    "gn:name":"\u00c7aml\u0131k\u00f6y",
    "gn:population":0,
    "gn:timezone":"Europe/Istanbul",
    "iso:country":"TR",
    "name:tur_x_preferred":[
        "\u00c7aml\u0131k\u00f6y"
    ],
    "name:tur_x_variant":[
        "\u00c7aml\u0131"
    ],
    "wof:name":"Camlikoy",
    "wof:placetype":"locality"
},
  "geometry": {"coordinates":[30.13342,37.95624],"type":"Point"}
}