{
  "type": "Feature",
  "properties": {
    "gn:admin1_code":"21",
    "gn:asciiname":"Yenisehir",
    "gn:country_code":"TR",
    "gn:dem":766,
    "gn:feature_class":"P",
    "gn:feature_code":"PPLA2",
    "gn:name":"Yeni\u015fehir",
    "gn:population":0,
    "gn:timezone":"Europe/Istanbul",
    "iso:country":"TR",
    "name:tur_x_preferred":[
        "Yeni\u015fehir"
    ],
    "wof:name":"Yenisehir",
    "wof:placetype":"locality"
},
  "geometry": {"coordinates":[40.13801,37.94146],"type":"Point"}
}