{
  "type": "Feature",
  "properties": {
    "gn:admin1_code":"17",
    "gn:asciiname":"Koyunevi",
    "gn:country_code":"TR",
    "gn:dem":316,
    "gn:feature_class":"P",
    "gn:feature_code":"PPL",
    "gn:name":"Koyunevi",
    "gn:population":0,
    "gn:timezone":"Europe/Istanbul",
    "iso:country":"TR",
    "name:tur_x_preferred":[
        "Koyunevi"
    ],
    "wof:name":"Koyunevi",
    "wof:placetype":"locality"
},
  "geometry": {"coordinates":[26.18147,39.49202],"type":"Point"}
}