{
  "type": "Feature",
  "properties": {
    "gn:admin1_code":"17",
    "gn:asciiname":"Cinarkoy",
    "gn:country_code":"TR",
    "gn:dem":65,
    "gn:feature_class":"P",
    "gn:feature_code":"PPL",
    "gn:name":"\u00c7\u0131nark\u00f6y",
    "gn:population":0,
    "gn:timezone":"Europe/Istanbul",
    "iso:country":"TR",
    "name:tur_x_preferred":[
        "\u00c7\u0131nark\u00f6y"
    ],
    "wof:name":"Cinarkoy",
    "wof:placetype":"locality"
},
  "geometry": {"coordinates":[26.35052,39.74291],"type":"Point"}
}