{
  "type": "Feature",
  "properties": {
    "gn:admin1_code":"21.0",
    "gn:asciiname":"Damar",
    "gn:country_code":"TR",
    "gn:dem":899,
    "gn:feature_class":"P",
    "gn:feature_code":"PPL",
    "gn:name":"Damar",
    "gn:population":0,
    "gn:timezone":"Europe/Istanbul",
    "iso:country":"TR",
    "name:tur_x_preferred":[
        "Damar"
    ],
    "wof:name":"Damar",
    "wof:placetype":"locality"
},
  "geometry": {"coordinates":[40.69656,38.45138],"type":"Point"}
}