{
  "type": "Feature",
  "properties": {
    "gn:admin1_code":"45",
    "gn:asciiname":"Caber Konakli",
    "gn:country_code":"TR",
    "gn:dem":223,
    "gn:feature_class":"P",
    "gn:feature_code":"PPL",
    "gn:name":"Caber Konakl\u0131",
    "gn:population":0,
    "gn:timezone":"Europe/Istanbul",
    "iso:country":"TR",
    "name:tur_x_preferred":[
        "Caber Konakl\u0131"
    ],
    "name:tur_x_variant":[
        "Caberkamara",
        "Kamera"
    ],
    "wof:name":"Caber Konakli",
    "wof:placetype":"locality"
},
  "geometry": {"coordinates":[28.67329,38.35454],"type":"Point"}
}