{
  "type": "Feature",
  "properties": {
    "gn:admin1_code":"21",
    "gn:asciiname":"Kirkkasik",
    "gn:country_code":"TR",
    "gn:dem":770,
    "gn:feature_class":"P",
    "gn:feature_code":"PPL",
    "gn:name":"K\u0131rkka\u015f\u0131k",
    "gn:population":0,
    "gn:timezone":"Europe/Istanbul",
    "iso:country":"TR",
    "name:tur_x_preferred":[
        "K\u0131r\u0131kka\u015f\u0131k"
    ],
    "name:tur_x_variant":[
        "K\u0131rkka\u015f\u0131k"
    ],
    "wof:name":"Kirkkasik",
    "wof:placetype":"locality"
},
  "geometry": {"coordinates":[40.6849,38.17785],"type":"Point"}
}