{
  "type": "Feature",
  "properties": {
    "gn:admin1_code":"58",
    "gn:asciiname":"Belpinar",
    "gn:country_code":"TR",
    "gn:dem":1272,
    "gn:feature_class":"P",
    "gn:feature_code":"PPL",
    "gn:name":"Belp\u0131nar",
    "gn:population":0,
    "gn:timezone":"Europe/Istanbul",
    "iso:country":"TR",
    "name:und_x_variant":[
        "Belp\u0131nar",
        "Belp\u0131nar\u0131 K\u00f6y\u00fc"
    ],
    "wof:name":"Belpinar",
    "wof:placetype":"locality"
},
  "geometry": {"coordinates":[36.07391,39.92116],"type":"Point"}
}