{
  "type": "Feature",
  "properties": {
    "gn:admin1_code":"25.0",
    "gn:asciiname":"Zihik",
    "gn:country_code":"TR",
    "gn:dem":1010,
    "gn:feature_class":"P",
    "gn:feature_code":"PPL",
    "gn:name":"Zihik",
    "gn:population":0,
    "gn:timezone":"Europe/Istanbul",
    "iso:country":"TR",
    "wof:name":"Zihik",
    "wof:placetype":"locality"
},
  "geometry": {"coordinates":[41.65,40.65],"type":"Point"}
}