{
  "type": "Feature",
  "properties": {
    "gn:admin1_code":"84.0",
    "gn:asciiname":"Cardakcati",
    "gn:country_code":"TR",
    "gn:dem":1709,
    "gn:feature_class":"P",
    "gn:feature_code":"PPL",
    "gn:name":"\u00c7ardak\u00e7at\u0131",
    "gn:population":0,
    "gn:timezone":"Europe/Istanbul",
    "iso:country":"TR",
    "name:und_x_variant":[
        "C\u00f6r\u00fck",
        "\u00c7\u00fcr\u00fck",
        "\u00c7ardak\u00e7at\u0131"
    ],
    "wof:name":"Cardakcati",
    "wof:placetype":"locality"
},
  "geometry": {"coordinates":[42.70847,40.09363],"type":"Point"}
}