{
  "type": "Feature",
  "properties": {
    "gn:admin1_code":"12",
    "gn:asciiname":"Kaynak",
    "gn:country_code":"TR",
    "gn:dem":1938,
    "gn:feature_class":"P",
    "gn:feature_code":"PPL",
    "gn:name":"Kaynak",
    "gn:population":0,
    "gn:timezone":"Europe/Istanbul",
    "iso:country":"TR",
    "name:und_x_variant":[
        "Kavrak",
        "Kaynak"
    ],
    "wof:name":"Kaynak",
    "wof:placetype":"locality"
},
  "geometry": {"coordinates":[40.91219,39.24531],"type":"Point"}
}