{
  "type": "Feature",
  "properties": {
    "gn:admin1_code":"21",
    "gn:asciiname":"Ziyaret",
    "gn:country_code":"TR",
    "gn:dem":1026,
    "gn:feature_class":"P",
    "gn:feature_code":"PPL",
    "gn:name":"Ziyaret",
    "gn:population":0,
    "gn:timezone":"Europe/Istanbul",
    "iso:country":"TR",
    "name:ceb_x_preferred":[
        "Ziyaret"
    ],
    "name:deu_x_preferred":[
        "Ziyaret"
    ],
    "name:kur_x_preferred":[
        "Ziyaret"
    ],
    "name:tur_x_preferred":[
        "Ziyaret"
    ],
    "wof:name":"Ziyaret",
    "wof:placetype":"locality"
},
  "geometry": {"coordinates":[40.56299,38.33309000000001],"type":"Point"}
}