{
  "type": "Feature",
  "properties": {
    "gn:admin1_code":"54",
    "gn:asciiname":"Hallac",
    "gn:country_code":"TR",
    "gn:dem":57,
    "gn:feature_class":"P",
    "gn:feature_code":"PPL",
    "gn:name":"Halla\u00e7",
    "gn:population":0,
    "gn:timezone":"Europe/Istanbul",
    "iso:country":"TR",
    "name:tur_x_preferred":[
        "Halla\u00e7k\u00f6y"
    ],
    "name:tur_x_variant":[
        "Halla\u00e7"
    ],
    "wof:name":"Hallac",
    "wof:placetype":"locality"
},
  "geometry": {"coordinates":[30.65121,40.81799],"type":"Point"}
}