{
  "type": "Feature",
  "properties": {
    "gn:admin1_code":"71",
    "gn:asciiname":"Ugurlu",
    "gn:country_code":"TR",
    "gn:dem":1461,
    "gn:feature_class":"P",
    "gn:feature_code":"PPL",
    "gn:name":"U\u011furlu",
    "gn:population":0,
    "gn:timezone":"Europe/Istanbul",
    "iso:country":"TR",
    "wof:name":"Ugurlu",
    "wof:placetype":"locality"
},
  "geometry": {"coordinates":[31.67253,37.41618],"type":"Point"}
}