{
  "type": "Feature",
  "properties": {
    "gn:admin1_code":"63",
    "gn:asciiname":"Sugorundu",
    "gn:cc2":"TR",
    "gn:country_code":"TR",
    "gn:dem":519,
    "gn:feature_class":"P",
    "gn:feature_code":"PPL",
    "gn:name":"Sug\u00f6r\u00fcnd\u00fc",
    "gn:population":0,
    "gn:timezone":"Europe/Istanbul",
    "iso:country":"TR",
    "name:und_x_variant":[
        "Sahrin\u00e7s\u00fcbeyh",
        "Sug\u00f6r\u00fcnd\u00fc"
    ],
    "wof:name":"Sugorundu",
    "wof:placetype":"locality"
},
  "geometry": {"coordinates":[39.71667,37.15],"type":"Point"}
}