{
  "type": "Feature",
  "properties": {
    "gn:admin1_code":"58.0",
    "gn:asciiname":"Akcaagil",
    "gn:country_code":"TR",
    "gn:dem":836,
    "gn:feature_class":"P",
    "gn:feature_code":"PPL",
    "gn:name":"Ak\u00e7aa\u011f\u0131l",
    "gn:population":0,
    "gn:timezone":"Europe/Istanbul",
    "iso:country":"TR",
    "name:und_x_variant":[
        "Ak\u00e7a\u011f\u0131l",
        "A\u011fcaa\u011f\u0131l",
        "Ak\u00e7aa\u011f\u0131l K\u00f6y\u00fc",
        "Ak\u00e7aa\u011f\u0131l"
    ],
    "wof:name":"Akcaagil",
    "wof:placetype":"locality"
},
  "geometry": {"coordinates":[38.06423,40.20978],"type":"Point"}
}