{
  "type": "Feature",
  "properties": {
    "gn:country":"TR",
    "gn:fcode":"PPL",
    "gn:population":17080,
    "iso:country":"TR",
    "name:ceb_x_preferred":[
        "Banaz"
    ],
    "name:deu_x_preferred":[
        "Banaz"
    ],
    "name:ell_x_preferred":[
        "\u039c\u03c0\u03b1\u03bd\u03ac\u03b6"
    ],
    "name:eng_x_preferred":[
        "Banaz"
    ],
    "name:epo_x_preferred":[
        "Banaz"
    ],
    "name:fas_x_preferred":[
        "\u0628\u0627\u0646\u0627\u0632"
    ],
    "name:fra_x_preferred":[
        "Banaz"
    ],
    "name:ita_x_preferred":[
        "Distretto di Banaz"
    ],
    "name:lit_x_preferred":[
        "Banasas"
    ],
    "name:mrj_x_preferred":[
        "\u0411\u0430\u043d\u0430\u0437"
    ],
    "name:msa_x_preferred":[
        "Banaz"
    ],
    "name:nan_x_preferred":[
        "Banaz"
    ],
    "name:nld_x_preferred":[
        "Banaz"
    ],
    "name:nno_x_preferred":[
        "Banaz"
    ],
    "name:nob_x_preferred":[
        "Banaz"
    ],
    "name:pnb_x_preferred":[
        "\u0636\u0644\u0639 \u0628\u0627\u0646\u0627\u0632"
    ],
    "name:swa_x_preferred":[
        "Banaz"
    ],
    "name:tur_x_preferred":[
        "Banaz"
    ],
    "name:und_x_variant":[
        "\u0130slamk\u00f6y"
    ],
    "name:urd_x_preferred":[
        "\u0628\u0627\u0646\u0627\u0632"
    ],
    "name:vie_x_preferred":[
        "Banaz"
    ],
    "name:zho_x_preferred":[
        "\u5df4\u7d0d\u8332"
    ],
    "qs:name":"Banaz",
    "qs:name_adm0":"Turkey",
    "qs:name_adm1":"U\u015fak",
    "qs:photos_9k":1,
    "qs:photos_9r":1,
    "qs:photos_all":1,
    "qs:photos_sr":0,
    "qs:placetype":"Town",
    "qs:pop_sr":"6",
    "wd:wordcount":354,
    "wof:name":"Banaz",
    "wof:placetype":"locality",
    "wof:population":17080
},
  "geometry": {"coordinates":[29.75194,38.73707],"type":"Point"}
}