{
  "type": "Feature",
  "properties": {
    "gn:admin1_code":"46",
    "gn:asciiname":"Sahintepe",
    "gn:country_code":"TR",
    "gn:dem":861,
    "gn:feature_class":"P",
    "gn:feature_code":"PPL",
    "gn:name":"\u015eahintepe",
    "gn:population":0,
    "gn:timezone":"Europe/Istanbul",
    "iso:country":"TR",
    "name:tur_x_preferred":[
        "\u015eahintepe"
    ],
    "wof:name":"Sahintepe",
    "wof:placetype":"locality"
},
  "geometry": {"coordinates":[37.32017000000001,37.5446],"type":"Point"}
}