{
  "type": "Feature",
  "properties": {
    "gn:admin1_code":"40.0",
    "gn:asciiname":"Yukarihaciahmetli",
    "gn:country_code":"TR",
    "gn:dem":1294,
    "gn:feature_class":"P",
    "gn:feature_code":"PPL",
    "gn:name":"Yukar\u0131hac\u0131ahmetli",
    "gn:population":0,
    "gn:timezone":"Europe/Istanbul",
    "iso:country":"TR",
    "wof:name":"Yukarihaciahmetli",
    "wof:placetype":"locality"
},
  "geometry": {"coordinates":[34.27148,39.55774],"type":"Point"}
}