{
  "type": "Feature",
  "properties": {
    "gn:admin1_code":"68.0",
    "gn:asciiname":"Erdemli",
    "gn:country_code":"TR",
    "gn:dem":805,
    "gn:feature_class":"P",
    "gn:feature_code":"PPL",
    "gn:name":"Erdemli",
    "gn:population":0,
    "gn:timezone":"Europe/Istanbul",
    "iso:country":"TR",
    "name:und_x_variant":[
        "B\u00fcy\u00fck Erdemli"
    ],
    "wof:name":"Erdemli",
    "wof:placetype":"locality"
},
  "geometry": {"coordinates":[33.37613,39.45007],"type":"Point"}
}