{
  "type": "Feature",
  "properties": {
    "gn:country":"TR",
    "gn:fcode":"PPL",
    "gn:population":182,
    "iso:country":"TR",
    "name:tur_x_preferred":[
        "Yaz\u0131r"
    ],
    "name:und_x_variant":[
        "Yazyr"
    ],
    "qs:name":"Yaz\u0131r",
    "qs:photos_9r":0,
    "qs:photos_sr":0,
    "qs:pop_sr":"1",
    "wd:wordcount":73,
    "wof:name":"Yaz\u0131r",
    "wof:placetype":"locality",
    "wof:population":182
},
  "geometry": {"coordinates":[37.92944,36.88],"type":"Point"}
}