{
  "type": "Feature",
  "properties": {
    "gn:admin1_code":"13",
    "gn:asciiname":"Cokekyazi",
    "gn:country_code":"TR",
    "gn:dem":1605,
    "gn:feature_class":"P",
    "gn:feature_code":"PPL",
    "gn:name":"\u00c7\u00f6kekyaz\u0131",
    "gn:population":0,
    "gn:timezone":"Europe/Istanbul",
    "iso:country":"TR",
    "name:tur_x_preferred":[
        "\u00c7\u00f6kekyaz\u0131"
    ],
    "name:und_x_variant":[
        "\u00c7\u00f6kezyaz\u0131"
    ],
    "wof:name":"Cokekyazi",
    "wof:placetype":"locality"
},
  "geometry": {"coordinates":[42.38333,38.26667],"type":"Point"}
}