{
  "type": "Feature",
  "properties": {
    "gn:admin1_code":"45",
    "gn:asciiname":"Hocalar",
    "gn:country_code":"TR",
    "gn:dem":781,
    "gn:feature_class":"P",
    "gn:feature_code":"PPL",
    "gn:name":"Hocalar",
    "gn:population":0,
    "gn:timezone":"Europe/Istanbul",
    "iso:country":"TR",
    "name:ceb_x_preferred":[
        "Hocalar"
    ],
    "name:deu_x_preferred":[
        "Hocalar"
    ],
    "name:diq_x_preferred":[
        "Hocalar"
    ],
    "name:fra_x_preferred":[
        "Hocalar"
    ],
    "name:mrj_x_preferred":[
        "\u0425\u043e\u0434\u0436\u0430\u043b\u0430\u0440"
    ],
    "name:msa_x_preferred":[
        "Hocalar"
    ],
    "name:nld_x_preferred":[
        "Hocalar"
    ],
    "name:nor_x_preferred":[
        "Hocalar"
    ],
    "name:pnb_x_preferred":[
        "\u0636\u0644\u0639 \u06c1\u0648\u062c\u0627\u0644\u0631"
    ],
    "name:ron_x_preferred":[
        "Hocalar"
    ],
    "name:swa_x_preferred":[
        "Hocalar"
    ],
    "name:tur_x_preferred":[
        "Hocalar"
    ],
    "name:urd_x_preferred":[
        "\u06c1\u0648\u062c\u0627\u0644\u0627\u0631"
    ],
    "name:vie_x_preferred":[
        "Hocalar"
    ],
    "wof:name":"Hocalar",
    "wof:placetype":"locality"
},
  "geometry": {"coordinates":[28.73168,38.396],"type":"Point"}
}