{
  "type": "Feature",
  "properties": {
    "gn:admin1_code":"45",
    "gn:asciiname":"Hocalar",
    "gn:country_code":"TR",
    "gn:dem":781,
    "gn:feature_class":"P",
    "gn:feature_code":"PPL",
    "gn:name":"Hocalar",
    "gn:population":0,
    "gn:timezone":"Europe/Istanbul",
    "iso:country":"TR",
    "wof:name":"Hocalar",
    "wof:placetype":"locality"
},
  "geometry": {"coordinates":[28.73168,38.396],"type":"Point"}
}