{
  "type": "Feature",
  "properties": {
    "gn:admin1_code":"37.0",
    "gn:asciiname":"Sahip",
    "gn:country_code":"TR",
    "gn:dem":1129,
    "gn:feature_class":"P",
    "gn:feature_code":"PPL",
    "gn:name":"Sahip",
    "gn:population":0,
    "gn:timezone":"Europe/Istanbul",
    "iso:country":"TR",
    "wof:name":"Sahip",
    "wof:placetype":"locality"
},
  "geometry": {"coordinates":[33.7063,41.21825],"type":"Point"}
}