{
  "type": "Feature",
  "properties": {
    "gn:admin1_code":"45",
    "gn:asciiname":"Belen",
    "gn:country_code":"TR",
    "gn:dem":503,
    "gn:feature_class":"P",
    "gn:feature_code":"PPL",
    "gn:name":"Belen",
    "gn:population":0,
    "gn:timezone":"Europe/Istanbul",
    "iso:country":"TR",
    "name:tur_x_preferred":[
        "Belen"
    ],
    "wof:name":"Belen",
    "wof:placetype":"locality"
},
  "geometry": {"coordinates":[27.51667,39.38333],"type":"Point"}
}