{
  "type": "Feature",
  "properties": {
    "gn:admin1_code":"5.0",
    "gn:asciiname":"Sebinkarahisar",
    "gn:country_code":"TR",
    "gn:dem":917,
    "gn:feature_class":"P",
    "gn:feature_code":"PPL",
    "gn:name":"\u015eebinkarahisar",
    "gn:population":0,
    "gn:timezone":"Europe/Istanbul",
    "iso:country":"TR",
    "name:und_x_variant":[
        "\u015eebinkarahisar",
        "A\u011fyar"
    ],
    "wof:name":"Sebinkarahisar",
    "wof:placetype":"locality"
},
  "geometry": {"coordinates":[35.42054,40.28333],"type":"Point"}
}