{
  "type": "Feature",
  "properties": {
    "gn:admin1_code":"60.0",
    "gn:asciiname":"Buzkoy",
    "gn:country_code":"TR",
    "gn:dem":341,
    "gn:feature_class":"P",
    "gn:feature_code":"PPL",
    "gn:name":"Buzk\u00f6y",
    "gn:population":0,
    "gn:timezone":"Europe/Istanbul",
    "iso:country":"TR",
    "name:eng_x_preferred":[
        "Buzk\u00f6y"
    ],
    "name:rus_x_preferred":[
        "\u0411\u0443\u0437\u043a\u0435\u0439"
    ],
    "name:und_x_variant":[
        "Buz",
        "Buzk\u00f6y"
    ],
    "wof:name":"Buzkoy",
    "wof:placetype":"locality"
},
  "geometry": {"coordinates":[36.81929,40.63607],"type":"Point"}
}