{
  "type": "Feature",
  "properties": {
    "gn:admin1_code":"82.0",
    "gn:asciiname":"Kiyisin",
    "gn:country_code":"TR",
    "gn:dem":1281,
    "gn:feature_class":"P",
    "gn:feature_code":"PPL",
    "gn:name":"K\u0131y\u0131s\u0131n",
    "gn:population":0,
    "gn:timezone":"Europe/Istanbul",
    "iso:country":"TR",
    "name:und_x_variant":[
        "K\u0131y\u0131s\u0131n",
        "K\u0131z\u0131lsin"
    ],
    "wof:name":"Kiyisin",
    "wof:placetype":"locality"
},
  "geometry": {"coordinates":[33.60539,40.82834],"type":"Point"}
}