{
  "type": "Feature",
  "properties": {
    "gn:admin1_code":"22",
    "gn:asciiname":"Sultansah",
    "gn:country_code":"TR",
    "gn:dem":120,
    "gn:feature_class":"P",
    "gn:feature_code":"PPL",
    "gn:name":"Sultan\u015fah",
    "gn:population":0,
    "gn:timezone":"Europe/Istanbul",
    "iso:country":"TR",
    "name:tur_x_preferred":[
        "Sultan\u015fah"
    ],
    "wof:name":"Sultansah",
    "wof:placetype":"locality"
},
  "geometry": {"coordinates":[26.8859,41.2497],"type":"Point"}
}