{
  "type": "Feature",
  "properties": {
    "gn:admin1_code":"25.0",
    "gn:asciiname":"Tortumkale",
    "gn:country_code":"TR",
    "gn:dem":1434,
    "gn:feature_class":"P",
    "gn:feature_code":"PPL",
    "gn:name":"Tortumkale",
    "gn:population":0,
    "gn:timezone":"Europe/Istanbul",
    "iso:country":"TR",
    "name:tur_x_preferred":[
        "Tortumkale"
    ],
    "wof:name":"Tortumkale",
    "wof:placetype":"locality"
},
  "geometry": {"coordinates":[41.47143,40.34293],"type":"Point"}
}