{
  "type": "Feature",
  "properties": {
    "gn:admin1_code":"65.0",
    "gn:asciiname":"Yalinduz",
    "gn:country_code":"TR",
    "gn:dem":1660,
    "gn:feature_class":"P",
    "gn:feature_code":"PPL",
    "gn:name":"Yal\u0131nd\u00fcz",
    "gn:population":0,
    "gn:timezone":"Europe/Istanbul",
    "iso:country":"TR",
    "name:tur_x_preferred":[
        "Yal\u0131nd\u00fcz"
    ],
    "wof:name":"Yalinduz",
    "wof:placetype":"locality"
},
  "geometry": {"coordinates":[43.72059,38.94737],"type":"Point"}
}