{
  "type": "Feature",
  "properties": {
    "gn:admin1_code":"68",
    "gn:asciiname":"Ozyurt",
    "gn:country_code":"TR",
    "gn:dem":837,
    "gn:feature_class":"P",
    "gn:feature_code":"PPL",
    "gn:name":"\u00d6zyurt",
    "gn:population":0,
    "gn:timezone":"Europe/Istanbul",
    "iso:country":"TR",
    "wof:name":"Ozyurt",
    "wof:placetype":"locality"
},
  "geometry": {"coordinates":[32.06542,39.21187000000001],"type":"Point"}
}