{
  "type": "Feature",
  "properties": {
    "gn:admin1_code":"44",
    "gn:asciiname":"Ikizce",
    "gn:country_code":"TR",
    "gn:dem":1056,
    "gn:feature_class":"P",
    "gn:feature_code":"PPL",
    "gn:name":"\u0130kizce",
    "gn:population":0,
    "gn:timezone":"Europe/Istanbul",
    "iso:country":"TR",
    "name:tur_x_preferred":[
        "\u0130kizce"
    ],
    "wof:name":"Ikizce",
    "wof:placetype":"locality"
},
  "geometry": {"coordinates":[38.19815,38.29668],"type":"Point"}
}