{
  "type": "Feature",
  "properties": {
    "gn:country":"TR",
    "gn:fcode":"PPLA2",
    "gn:pop":5131,
    "iso:country":"TR",
    "name:ceb_x_preferred":[
        "Beylikova"
    ],
    "name:deu_x_preferred":[
        "Beylikova"
    ],
    "name:diq_x_preferred":[
        "Beylikova"
    ],
    "name:eng_x_preferred":[
        "Beylikova"
    ],
    "name:fra_x_preferred":[
        "Beylikova"
    ],
    "name:mrj_x_preferred":[
        "\u0411\u0435\u0439\u043b\u0438\u043a\u043e\u0432\u0430"
    ],
    "name:msa_x_preferred":[
        "Beylikova"
    ],
    "name:nan_x_preferred":[
        "Beylikova"
    ],
    "name:nld_x_preferred":[
        "Beylikova"
    ],
    "name:nob_x_preferred":[
        "Beylikova"
    ],
    "name:rus_x_preferred":[
        "\u0411\u0435\u0439\u043b\u0438\u043a\u043e\u0432\u0430"
    ],
    "name:swa_x_preferred":[
        "Beylikova"
    ],
    "name:tur_x_preferred":[
        "Beylikova"
    ],
    "name:unk_x_variant":[
        "Beylikova"
    ],
    "name:urd_x_preferred":[
        "\u0628\u06d2\u0644\u06cc\u06a9\u0648\u0648\u0627"
    ],
    "name:vie_x_preferred":[
        "Beylikova"
    ],
    "qs:name":"Beylikah\u0131r",
    "qs:name_adm0":"Turkey",
    "qs:name_adm1":"Eski\u015fehir",
    "qs:photos_9k":1,
    "qs:photos_9r":1,
    "qs:photos_all":25,
    "qs:photos_sr":0,
    "qs:placetype":"Town",
    "qs:pop_sr":"5",
    "wof:name":"Beylikah\u0131r",
    "wof:placetype":"locality",
    "wof:population":5131
},
  "geometry": {"coordinates":[31.20556,39.68694],"type":"Point"}
}