{
  "type": "Feature",
  "properties": {
    "gn:admin1_code":"21.0",
    "gn:asciiname":"Konuksever",
    "gn:country_code":"TR",
    "gn:dem":887,
    "gn:feature_class":"P",
    "gn:feature_code":"PPL",
    "gn:name":"Konuksever",
    "gn:population":0,
    "gn:timezone":"Europe/Istanbul",
    "iso:country":"TR",
    "name:tur_x_preferred":[
        "Konuksever"
    ],
    "wof:name":"Konuksever",
    "wof:placetype":"locality"
},
  "geometry": {"coordinates":[39.53863,38.10953],"type":"Point"}
}