{
  "type": "Feature",
  "properties": {
    "gn:admin1_code":"93",
    "gn:asciiname":"Buyukacma",
    "gn:country_code":"TR",
    "gn:dem":183,
    "gn:feature_class":"P",
    "gn:feature_code":"PPL",
    "gn:name":"B\u00fcy\u00fcka\u00e7ma",
    "gn:population":0,
    "gn:timezone":"Europe/Istanbul",
    "iso:country":"TR",
    "wof:name":"Buyukacma",
    "wof:placetype":"locality"
},
  "geometry": {"coordinates":[31.1749,40.787],"type":"Point"}
}