{
  "type": "Feature",
  "properties": {
    "gn:admin1_code":"48",
    "gn:asciiname":"Golturkbuku",
    "gn:country_code":"TR",
    "gn:dem":5,
    "gn:feature_class":"P",
    "gn:feature_code":"PPL",
    "gn:name":"G\u00f6lt\u00fcrkb\u00fck\u00fc",
    "gn:population":0,
    "gn:timezone":"Europe/Istanbul",
    "iso:country":"TR",
    "name:tur_x_preferred":[
        "G\u00f6lt\u00fcrkb\u00fck\u00fc"
    ],
    "name:tur_x_variant":[
        "G\u00f6lk\u00f6y"
    ],
    "wof:name":"Golturkbuku",
    "wof:placetype":"locality"
},
  "geometry": {"coordinates":[27.38558,37.11646],"type":"Point"}
}