{
  "type": "Feature",
  "properties": {
    "gn:admin1_code":"21.0",
    "gn:asciiname":"Kelekci",
    "gn:country_code":"TR",
    "gn:dem":839,
    "gn:feature_class":"P",
    "gn:feature_code":"PPL",
    "gn:name":"Kelek\u00e7i",
    "gn:population":0,
    "gn:timezone":"Europe/Istanbul",
    "iso:country":"TR",
    "name:tur_x_preferred":[
        "Kelek\u00e7i"
    ],
    "wof:name":"Kelekci",
    "wof:placetype":"locality"
},
  "geometry": {"coordinates":[40.20186,38.43402],"type":"Point"}
}