{
  "type": "Feature",
  "properties": {
    "gn:admin1_code":"75",
    "gn:asciiname":"Karacaoren",
    "gn:country_code":"TR",
    "gn:dem":1211,
    "gn:feature_class":"P",
    "gn:feature_code":"PPL",
    "gn:name":"Karaca\u00f6ren",
    "gn:population":0,
    "gn:timezone":"Europe/Istanbul",
    "iso:country":"TR",
    "name:und_x_variant":[
        "Karacaviran",
        "Karaca\u00f6ren"
    ],
    "wof:name":"Karacaoren",
    "wof:placetype":"locality"
},
  "geometry": {"coordinates":[34.06269,38.12878],"type":"Point"}
}