{
  "type": "Feature",
  "properties": {
    "gn:admin1_code":"37",
    "gn:asciiname":"Tunuslar",
    "gn:country_code":"TR",
    "gn:dem":1157,
    "gn:feature_class":"P",
    "gn:feature_code":"PPL",
    "gn:name":"Tunuslar",
    "gn:population":0,
    "gn:timezone":"Europe/Istanbul",
    "iso:country":"TR",
    "wof:name":"Tunuslar",
    "wof:placetype":"locality"
},
  "geometry": {"coordinates":[33.51967,41.62363],"type":"Point"}
}