{
  "type": "Feature",
  "properties": {
    "gn:admin1_code":"37.0",
    "gn:asciiname":"Karaman",
    "gn:country_code":"TR",
    "gn:dem":636,
    "gn:feature_class":"P",
    "gn:feature_code":"PPL",
    "gn:name":"Karaman",
    "gn:population":0,
    "gn:timezone":"Europe/Istanbul",
    "iso:country":"TR",
    "wof:name":"Karaman",
    "wof:placetype":"locality"
},
  "geometry": {"coordinates":[33.65634,41.82384],"type":"Point"}
}