{
  "type": "Feature",
  "properties": {
    "gn:admin1_code":"82.0",
    "gn:asciiname":"Bozatli",
    "gn:country_code":"TR",
    "gn:dem":1185,
    "gn:feature_class":"P",
    "gn:feature_code":"PPL",
    "gn:name":"Bozatl\u0131",
    "gn:population":0,
    "gn:timezone":"Europe/Istanbul",
    "iso:country":"TR",
    "name:und_x_variant":[
        "\u015e\u0131hlar",
        "Bozatl\u0131"
    ],
    "wof:name":"Bozatli",
    "wof:placetype":"locality"
},
  "geometry": {"coordinates":[33.6631,40.97334],"type":"Point"}
}