{
  "type": "Feature",
  "properties": {
    "gn:admin1_code":"21",
    "gn:asciiname":"Desta",
    "gn:country_code":"TR",
    "gn:dem":1409,
    "gn:feature_class":"P",
    "gn:feature_code":"PPL",
    "gn:name":"Desta",
    "gn:population":0,
    "gn:timezone":"Europe/Istanbul",
    "iso:country":"TR",
    "name:deu_x_preferred":[
        "Desta"
    ],
    "name:und_x_variant":[
        "Tiyakus",
        "Desta",
        "Tiyak\u0131s"
    ],
    "wof:name":"Desta",
    "wof:placetype":"locality"
},
  "geometry": {"coordinates":[40.92312,38.54841],"type":"Point"}
}