{
  "type": "Feature",
  "properties": {
    "gn:admin1_code":"26",
    "gn:asciiname":"Koltan",
    "gn:country_code":"TR",
    "gn:dem":928,
    "gn:feature_class":"P",
    "gn:feature_code":"PPL",
    "gn:name":"Koltan",
    "gn:population":0,
    "gn:timezone":"Europe/Istanbul",
    "iso:country":"TR",
    "wof:name":"Koltan",
    "wof:placetype":"locality"
},
  "geometry": {"coordinates":[31.63784,39.54189],"type":"Point"}
}