{
  "type": "Feature",
  "properties": {
    "gn:admin1_code":"68",
    "gn:asciiname":"Girmec",
    "gn:country_code":"TR",
    "gn:dem":892,
    "gn:feature_class":"P",
    "gn:feature_code":"PPL",
    "gn:name":"Girme\u00e7",
    "gn:population":0,
    "gn:timezone":"Europe/Istanbul",
    "iso:country":"TR",
    "wof:name":"Girmec",
    "wof:placetype":"locality"
},
  "geometry": {"coordinates":[32.27929,39.81514],"type":"Point"}
}