{
  "type": "Feature",
  "properties": {
    "gn:admin1_code":"45",
    "gn:asciiname":"Altinkoy",
    "gn:country_code":"TR",
    "gn:dem":681,
    "gn:feature_class":"P",
    "gn:feature_code":"PPL",
    "gn:name":"Alt\u0131nk\u00f6y",
    "gn:population":0,
    "gn:timezone":"Europe/Istanbul",
    "iso:country":"TR",
    "name:tur_x_preferred":[
        "Alt\u0131nk\u00f6y"
    ],
    "wof:name":"Altinkoy",
    "wof:placetype":"locality"
},
  "geometry": {"coordinates":[28.93805,38.74567],"type":"Point"}
}