{
  "type": "Feature",
  "properties": {
    "gn:admin1_code":"68.0",
    "gn:asciiname":"Orenkoy",
    "gn:country_code":"TR",
    "gn:dem":1280,
    "gn:feature_class":"P",
    "gn:feature_code":"PPL",
    "gn:name":"\u00d6renk\u00f6y",
    "gn:population":0,
    "gn:timezone":"Europe/Istanbul",
    "iso:country":"TR",
    "name:und_x_variant":[
        "Virank\u00f6y",
        "\u00d6renk\u00f6y"
    ],
    "wof:name":"Orenkoy",
    "wof:placetype":"locality"
},
  "geometry": {"coordinates":[32.47168,40.53682],"type":"Point"}
}