{
  "type": "Feature",
  "properties": {
    "gn:admin1_code":"37.0",
    "gn:asciiname":"Kizilcam",
    "gn:cc2":"TR",
    "gn:country_code":"TR",
    "gn:dem":1058,
    "gn:feature_class":"P",
    "gn:feature_code":"PPL",
    "gn:name":"K\u0131z\u0131l\u00e7am",
    "gn:population":0,
    "gn:timezone":"Europe/Istanbul",
    "iso:country":"TR",
    "name:und_x_variant":[
        "K\u0131z\u0131l\u00e7amdere",
        "K\u0131z\u0131l\u00e7am"
    ],
    "wof:name":"Kizilcam",
    "wof:placetype":"locality"
},
  "geometry": {"coordinates":[33.56667,41.16667],"type":"Point"}
}