{
  "type": "Feature",
  "properties": {
    "gn:admin1_code":"38",
    "gn:asciiname":"Subasi",
    "gn:country_code":"TR",
    "gn:dem":1379,
    "gn:feature_class":"P",
    "gn:feature_code":"PPL",
    "gn:name":"Suba\u015f\u0131",
    "gn:population":0,
    "gn:timezone":"Europe/Istanbul",
    "iso:country":"TR",
    "name:und_x_variant":[
        "Esk\u00fcbi",
        "\u00dcsk\u00fcb\u00fc",
        "\u00dcsg\u00fcb\u00fc",
        "Suba\u015f\u0131"
    ],
    "wof:name":"Subasi",
    "wof:placetype":"locality"
},
  "geometry": {"coordinates":[35.73582000000001,38.78866],"type":"Point"}
}