{
  "type": "Feature",
  "properties": {
    "gn:admin1_code":"86.0",
    "gn:asciiname":"Binbasar",
    "gn:country_code":"TR",
    "gn:dem":2133,
    "gn:feature_class":"P",
    "gn:feature_code":"PPL",
    "gn:name":"Binba\u015far",
    "gn:population":0,
    "gn:timezone":"Europe/Istanbul",
    "iso:country":"TR",
    "name:msa_x_preferred":[
        "Binba\u015far"
    ],
    "name:tur_x_preferred":[
        "Binba\u015far"
    ],
    "name:und_x_variant":[
        "Mor\u0131kan",
        "Binba\u015far",
        "Murk\u00e2n",
        "Murikan"
    ],
    "name:vie_x_preferred":[
        "Binba\u015far"
    ],
    "wof:name":"Binbasar",
    "wof:placetype":"locality"
},
  "geometry": {"coordinates":[42.97213,40.99408],"type":"Point"}
}