{
  "type": "Feature",
  "properties": {
    "gn:admin1_code":"14.0",
    "gn:asciiname":"Turnakoy",
    "gn:country_code":"TR",
    "gn:dem":865,
    "gn:feature_class":"P",
    "gn:feature_code":"PPL",
    "gn:name":"Turnak\u00f6y",
    "gn:population":0,
    "gn:timezone":"Europe/Istanbul",
    "iso:country":"TR",
    "name:und_x_variant":[
        "Turnak\u00f6y",
        "Turna"
    ],
    "wof:name":"Turnakoy",
    "wof:placetype":"locality"
},
  "geometry": {"coordinates":[31.92301,40.89996],"type":"Point"}
}