{
  "type": "Feature",
  "properties": {
    "gn:admin1_code":"37.0",
    "gn:asciiname":"Karacam",
    "gn:country_code":"TR",
    "gn:dem":1268,
    "gn:feature_class":"P",
    "gn:feature_code":"PPL",
    "gn:name":"Kara\u00e7am",
    "gn:population":0,
    "gn:timezone":"Europe/Istanbul",
    "iso:country":"TR",
    "name:tur_x_preferred":[
        "Kara\u00e7am"
    ],
    "wof:name":"Karacam",
    "wof:placetype":"locality"
},
  "geometry": {"coordinates":[33.88152,41.72409],"type":"Point"}
}