{
  "type": "Feature",
  "properties": {
    "gn:admin1_code":"68",
    "gn:asciiname":"Musular",
    "gn:country_code":"TR",
    "gn:dem":1126,
    "gn:feature_class":"P",
    "gn:feature_code":"PPL",
    "gn:name":"Musular",
    "gn:population":0,
    "gn:timezone":"Europe/Istanbul",
    "iso:country":"TR",
    "wof:name":"Musular",
    "wof:placetype":"locality"
},
  "geometry": {"coordinates":[33.61675,39.02753],"type":"Point"}
}