{
  "type": "Feature",
  "properties": {
    "iso:country":"TR",
    "name:ara_x_preferred":[
        "\u0627\u0645\u0631\u064a \u0627\u064a\u062f\u064a\u0646"
    ],
    "name:aze_x_preferred":[
        "\u018fmr\u0259 Ayd\u0131n"
    ],
    "name:deu_x_preferred":[
        "Emre Ayd\u0131n"
    ],
    "name:diq_x_preferred":[
        "Emre Ayd\u0131n"
    ],
    "name:ell_x_preferred":[
        "\u0395\u03bc\u03c1\u03ad \u0391\u03b9\u03bd\u03c4\u03af\u03bd"
    ],
    "name:fas_x_preferred":[
        "\u0627\u0645\u0631\u0647 \u0622\u06cc\u062f\u06cc\u0646"
    ],
    "name:fra_x_preferred":[
        "Emre Ayd\u0131n"
    ],
    "name:hun_x_preferred":[
        "Emre Ayd\u0131n"
    ],
    "name:isl_x_preferred":[
        "Emre Ayd\u0131n"
    ],
    "name:spa_x_preferred":[
        "Emre Ayd\u0131n"
    ],
    "name:und_x_variant":[
        "Aydin Evler"
    ],
    "qs:gn_adm0_cc":"TR",
    "qs:gn_local":304854,
    "qs:gn_nam_loc":"Manavgat, Manavgat, Antalya, TR",
    "qs:gn_namadm1":"07",
    "qs:local_max":2066,
    "qs:local_sum":2652,
    "qs:localhoods":5,
    "qs:name":"Aydin Evler",
    "qs:name_adm0":"Turkey",
    "qs:name_adm1":"Antalya",
    "qs:name_adm2":"Manavgat",
    "qs:name_local":"Manavgat",
    "qs:photo_max":29,
    "qs:photo_sum":79,
    "qs:placetype":"Suburb",
    "qs:quad_count":11,
    "qs:woe_adm0":23424969,
    "qs:woe_adm1":2347264,
    "qs:woe_adm2":29390553,
    "qs:woe_lau":0,
    "qs:woe_local":2344249,
    "qs:woe_ver":"7.10.0",
    "wof:lang":[
        "unk"
    ],
    "wof:name":"Aydin Evler",
    "wof:placetype":"neighbourhood"
},
  "geometry": {"coordinates":[31.417122,36.773953],"type":"Point"}
}