{
  "type": "Feature",
  "properties": {
    "gn:admin1_code":"58.0",
    "gn:asciiname":"Hubyar",
    "gn:country_code":"TR",
    "gn:dem":1767,
    "gn:feature_class":"P",
    "gn:feature_code":"PPL",
    "gn:name":"Hubyar",
    "gn:population":0,
    "gn:timezone":"Europe/Istanbul",
    "iso:country":"TR",
    "name:tur_x_preferred":[
        "Hubyar"
    ],
    "name:tur_x_variant":[
        "Uzunbelen"
    ],
    "wof:name":"Hubyar",
    "wof:placetype":"locality"
},
  "geometry": {"coordinates":[37.4472,40.17775],"type":"Point"}
}