{
  "type": "Feature",
  "properties": {
    "gn:admin1_code":"63",
    "gn:asciiname":"Mirdzhanki",
    "gn:country_code":"TR",
    "gn:dem":680,
    "gn:feature_class":"P",
    "gn:feature_code":"PPL",
    "gn:name":"Mirdzhanki",
    "gn:population":0,
    "gn:timezone":"Europe/Istanbul",
    "iso:country":"TR",
    "wof:name":"Mirdzhanki",
    "wof:placetype":"locality"
},
  "geometry": {"coordinates":[38.61196,37.04996],"type":"Point"}
}