{
  "type": "Feature",
  "properties": {
    "gn:admin1_code":"14",
    "gn:asciiname":"Dedeler",
    "gn:country_code":"TR",
    "gn:dem":875,
    "gn:feature_class":"P",
    "gn:feature_code":"PPL",
    "gn:name":"Dedeler",
    "gn:population":0,
    "gn:timezone":"Europe/Istanbul",
    "iso:country":"TR",
    "name:tur_x_preferred":[
        "Dedeler"
    ],
    "wof:name":"Dedeler",
    "wof:placetype":"locality"
},
  "geometry": {"coordinates":[31.8795,40.78492],"type":"Point"}
}