{
  "type": "Feature",
  "properties": {
    "gn:admin1_code":"52.0",
    "gn:asciiname":"Senbolluk",
    "gn:country_code":"TR",
    "gn:dem":633,
    "gn:feature_class":"P",
    "gn:feature_code":"PPL",
    "gn:name":"\u015eenbolluk",
    "gn:population":0,
    "gn:timezone":"Europe/Istanbul",
    "iso:country":"TR",
    "name:und_x_variant":[
        "\u015eentepe",
        "\u015eenbolluk"
    ],
    "wof:name":"Senbolluk",
    "wof:placetype":"locality"
},
  "geometry": {"coordinates":[36.99082,41.02939],"type":"Point"}
}