{
  "type": "Feature",
  "properties": {
    "gn:admin1_code":"53.0",
    "gn:asciiname":"Sirinkoy",
    "gn:country_code":"TR",
    "gn:dem":105,
    "gn:feature_class":"P",
    "gn:feature_code":"PPL",
    "gn:name":"\u015eirink\u00f6y",
    "gn:population":0,
    "gn:timezone":"Europe/Istanbul",
    "iso:country":"TR",
    "wof:name":"Sirinkoy",
    "wof:placetype":"locality"
},
  "geometry": {"coordinates":[40.71492,41.05534],"type":"Point"}
}