{
  "type": "Feature",
  "properties": {
    "gn:admin1_code":"60.0",
    "gn:asciiname":"Eskidir",
    "gn:country_code":"TR",
    "gn:dem":466,
    "gn:feature_class":"P",
    "gn:feature_code":"PPL",
    "gn:name":"Eskidir",
    "gn:population":0,
    "gn:timezone":"Europe/Istanbul",
    "iso:country":"TR",
    "name:eng_x_preferred":[
        "G\u00fcr\u00e7e\u015fme"
    ],
    "name:rus_x_preferred":[
        "\u042d\u0441\u043a\u0438\u0434\u0438\u0440"
    ],
    "name:und_x_variant":[
        "Yaprakl\u0131",
        "Eskidir"
    ],
    "wof:name":"Eskidir",
    "wof:placetype":"locality"
},
  "geometry": {"coordinates":[36.80418,40.57509],"type":"Point"}
}