{
  "type": "Feature",
  "properties": {
    "gn:country":"TR",
    "gn:fcode":"PPL",
    "gn:pop":684,
    "iso:country":"TR",
    "name:unk_x_variant":[
        "Bishi"
    ],
    "qs:name":"Bola\u011fa\u00e7",
    "qs:photos_9r":0,
    "qs:photos_sr":0,
    "qs:pop_sr":"2",
    "wof:name":"Bola\u011fa\u00e7",
    "wof:placetype":"locality",
    "wof:population":684
},
  "geometry": {"coordinates":[43.05139,37.50981],"type":"Point"}
}