{
  "type": "Feature",
  "properties": {
    "gn:admin1_code":"12",
    "gn:asciiname":"Kalekoy",
    "gn:country_code":"TR",
    "gn:dem":1151,
    "gn:feature_class":"P",
    "gn:feature_code":"PPL",
    "gn:name":"Kalek\u00f6y",
    "gn:population":0,
    "gn:timezone":"Europe/Istanbul",
    "iso:country":"TR",
    "name:tur_x_preferred":[
        "Kalek\u00f6y"
    ],
    "wof:name":"Kalekoy",
    "wof:placetype":"locality"
},
  "geometry": {"coordinates":[41.05194,38.79401],"type":"Point"}
}