{
  "type": "Feature",
  "properties": {
    "gn:admin1_code":"10",
    "gn:asciiname":"Dugunculer",
    "gn:country_code":"TR",
    "gn:dem":694,
    "gn:feature_class":"P",
    "gn:feature_code":"PPL",
    "gn:name":"D\u00fc\u011f\u00fcnc\u00fcler",
    "gn:population":0,
    "gn:timezone":"Europe/Istanbul",
    "iso:country":"TR",
    "name:tur_x_preferred":[
        "D\u00fc\u011f\u00fcnc\u00fcler"
    ],
    "wof:name":"Dugunculer",
    "wof:placetype":"locality"
},
  "geometry": {"coordinates":[28.53485,39.26012],"type":"Point"}
}