{
  "type": "Feature",
  "properties": {
    "gn:admin1_code":"24",
    "gn:asciiname":"Turnacayiri",
    "gn:country_code":"TR",
    "gn:dem":2160,
    "gn:feature_class":"P",
    "gn:feature_code":"PPL",
    "gn:name":"Turna\u00e7ay\u0131r\u0131",
    "gn:population":0,
    "gn:timezone":"Europe/Istanbul",
    "iso:country":"TR",
    "name:tur_x_preferred":[
        "Turna\u00e7ay\u0131r\u0131"
    ],
    "wof:name":"Turnacayiri",
    "wof:placetype":"locality"
},
  "geometry": {"coordinates":[39.72174,39.85948],"type":"Point"}
}