{
  "type": "Feature",
  "properties": {
    "gn:admin1_code":"57.0",
    "gn:asciiname":"Bostancili",
    "gn:country_code":"TR",
    "gn:dem":44,
    "gn:feature_class":"P",
    "gn:feature_code":"PPL",
    "gn:name":"Bostanc\u0131l\u0131",
    "gn:population":0,
    "gn:timezone":"Europe/Istanbul",
    "iso:country":"TR",
    "name:und_x_variant":[
        "Bostanc\u0131l",
        "Bostanc\u0131l\u0131"
    ],
    "wof:name":"Bostancili",
    "wof:placetype":"locality"
},
  "geometry": {"coordinates":[35.10507,42.01981],"type":"Point"}
}