{
  "type": "Feature",
  "properties": {
    "gn:admin1_code":"39.0",
    "gn:asciiname":"Sogucak",
    "gn:country_code":"TR",
    "gn:dem":280,
    "gn:feature_class":"P",
    "gn:feature_code":"PPL",
    "gn:name":"So\u011fucak",
    "gn:population":0,
    "gn:timezone":"Europe/Istanbul",
    "iso:country":"TR",
    "name:tur_x_preferred":[
        "So\u011fucak"
    ],
    "wof:name":"Sogucak",
    "wof:placetype":"locality"
},
  "geometry": {"coordinates":[27.65689,41.63954],"type":"Point"}
}