{
  "type": "Feature",
  "properties": {
    "gn:admin1_code":"37.0",
    "gn:asciiname":"Ahlar",
    "gn:country_code":"TR",
    "gn:dem":492,
    "gn:feature_class":"P",
    "gn:feature_code":"PPL",
    "gn:name":"Ahlar",
    "gn:population":0,
    "gn:timezone":"Europe/Istanbul",
    "iso:country":"TR",
    "wof:name":"Ahlar",
    "wof:placetype":"locality"
},
  "geometry": {"coordinates":[33.0245,41.676],"type":"Point"}
}