{
  "type": "Feature",
  "properties": {
    "gn:admin1_code":"39.0",
    "gn:asciiname":"Korukoy",
    "gn:country_code":"TR",
    "gn:dem":449,
    "gn:feature_class":"P",
    "gn:feature_code":"PPL",
    "gn:name":"Koruk\u00f6y",
    "gn:population":0,
    "gn:timezone":"Europe/Istanbul",
    "iso:country":"TR",
    "wof:name":"Korukoy",
    "wof:placetype":"locality"
},
  "geometry": {"coordinates":[27.32451,41.85756],"type":"Point"}
}