{
  "type": "Feature",
  "properties": {
    "gn:admin1_code":"09",
    "gn:asciiname":"Hacihidirlar",
    "gn:country_code":"TR",
    "gn:dem":611,
    "gn:feature_class":"P",
    "gn:feature_code":"PPL",
    "gn:name":"Hac\u0131h\u0131d\u0131rlar",
    "gn:population":0,
    "gn:timezone":"Europe/Istanbul",
    "iso:country":"TR",
    "name:tur_x_preferred":[
        "Hac\u0131h\u0131d\u0131rlar"
    ],
    "wof:name":"Hacihidirlar",
    "wof:placetype":"locality"
},
  "geometry": {"coordinates":[28.67315,37.78186],"type":"Point"}
}