{
  "type": "Feature",
  "properties": {
    "gn:admin1_code":"76.0",
    "gn:asciiname":"Arikaya",
    "gn:country_code":"TR",
    "gn:dem":710,
    "gn:feature_class":"P",
    "gn:feature_code":"PPL",
    "gn:name":"Ar\u0131kaya",
    "gn:population":0,
    "gn:timezone":"Europe/Istanbul",
    "iso:country":"TR",
    "name:tur_x_preferred":[
        "Ar\u0131kaya"
    ],
    "wof:name":"Arikaya",
    "wof:placetype":"locality"
},
  "geometry": {"coordinates":[41.53905,38.07128],"type":"Point"}
}