{
  "type": "Feature",
  "properties": {
    "gn:admin1_code":"66",
    "gn:asciiname":"Terzili",
    "gn:country_code":"TR",
    "gn:dem":854,
    "gn:feature_class":"P",
    "gn:feature_code":"PPL",
    "gn:name":"Terzili",
    "gn:population":0,
    "gn:timezone":"Europe/Istanbul",
    "iso:country":"TR",
    "wof:name":"Terzili",
    "wof:placetype":"locality"
},
  "geometry": {"coordinates":[34.1849,39.89097],"type":"Point"}
}