{
  "type": "Feature",
  "properties": {
    "gn:admin1_code":"24.0",
    "gn:asciiname":"Ucoren",
    "gn:country_code":"TR",
    "gn:dem":1548,
    "gn:feature_class":"P",
    "gn:feature_code":"PPL",
    "gn:name":"\u00dc\u00e7\u00f6ren",
    "gn:population":0,
    "gn:timezone":"Europe/Istanbul",
    "iso:country":"TR",
    "name:tur_x_preferred":[
        "\u00dc\u00e7\u00f6ren"
    ],
    "wof:name":"Ucoren",
    "wof:placetype":"locality"
},
  "geometry": {"coordinates":[38.78029,40.04339],"type":"Point"}
}