{
  "type": "Feature",
  "properties": {
    "gn:admin1_code":"48",
    "gn:asciiname":"Yesilbelde",
    "gn:country_code":"TR",
    "gn:dem":171,
    "gn:feature_class":"P",
    "gn:feature_code":"PPL",
    "gn:name":"Ye\u015filbelde",
    "gn:population":0,
    "gn:timezone":"Europe/Istanbul",
    "iso:country":"TR",
    "name:tur_x_preferred":[
        "Ye\u015filbelde"
    ],
    "wof:name":"Yesilbelde",
    "wof:placetype":"locality"
},
  "geometry": {"coordinates":[28.22268,36.886],"type":"Point"}
}