{
  "type": "Feature",
  "properties": {
    "gn:admin1_code":"09",
    "gn:asciiname":"Yazidere",
    "gn:country_code":"TR",
    "gn:dem":28,
    "gn:feature_class":"P",
    "gn:feature_code":"PPL",
    "gn:name":"Yaz\u0131dere",
    "gn:population":0,
    "gn:timezone":"Europe/Istanbul",
    "iso:country":"TR",
    "name:tur_x_preferred":[
        "Yaz\u0131dere"
    ],
    "wof:name":"Yazidere",
    "wof:placetype":"locality"
},
  "geometry": {"coordinates":[27.7316,37.82045],"type":"Point"}
}