{
  "type": "Feature",
  "properties": {
    "gn:admin1_code":"80",
    "gn:asciiname":"Guvabervari",
    "gn:cc2":"TR",
    "gn:country_code":"TR",
    "gn:dem":2126,
    "gn:feature_class":"P",
    "gn:feature_code":"PPL",
    "gn:name":"Guvabervari",
    "gn:population":0,
    "gn:timezone":"Europe/Istanbul",
    "iso:country":"TR",
    "name:und_x_variant":[
        "Gavatrebas\u0131",
        "Guvabevari",
        "Guvabervari"
    ],
    "wof:name":"Guvabervari",
    "wof:placetype":"locality"
},
  "geometry": {"coordinates":[43.2725,37.62667],"type":"Point"}
}