{
  "type": "Feature",
  "properties": {
    "gn:admin1_code":"23",
    "gn:asciiname":"Hopik",
    "gn:country_code":"TR",
    "gn:dem":1195,
    "gn:feature_class":"P",
    "gn:feature_code":"PPL",
    "gn:name":"Hopik",
    "gn:population":0,
    "gn:timezone":"Europe/Istanbul",
    "iso:country":"TR",
    "wof:name":"Hopik",
    "wof:placetype":"locality"
},
  "geometry": {"coordinates":[39.93333,39.08333],"type":"Point"}
}