{
  "type": "Feature",
  "properties": {
    "gn:admin1_code":"16",
    "gn:asciiname":"Derecik",
    "gn:country_code":"TR",
    "gn:dem":712,
    "gn:feature_class":"P",
    "gn:feature_code":"PPL",
    "gn:name":"Derecik",
    "gn:population":0,
    "gn:timezone":"Europe/Istanbul",
    "iso:country":"TR",
    "name:tur_x_preferred":[
        "Derecik"
    ],
    "wof:name":"Derecik",
    "wof:placetype":"locality"
},
  "geometry": {"coordinates":[28.92766,39.75016],"type":"Point"}
}