{
  "type": "Feature",
  "properties": {
    "gn:admin1_code":"32",
    "gn:asciiname":"Uctepe",
    "gn:country_code":"TR",
    "gn:dem":232,
    "gn:feature_class":"P",
    "gn:feature_code":"PPL",
    "gn:name":"\u00dc\u00e7tepe",
    "gn:population":0,
    "gn:timezone":"Europe/Istanbul",
    "iso:country":"TR",
    "name:tur_x_preferred":[
        "\u00dc\u00e7tepe"
    ],
    "wof:name":"Uctepe",
    "wof:placetype":"locality"
},
  "geometry": {"coordinates":[34.23629,36.59058],"type":"Point"}
}