{
  "type": "Feature",
  "properties": {
    "gn:admin1_code":"35",
    "gn:asciiname":"Mordogan",
    "gn:country_code":"TR",
    "gn:dem":8,
    "gn:feature_class":"P",
    "gn:feature_code":"PPLA3",
    "gn:name":"Mordo\u011fan",
    "gn:population":0,
    "gn:timezone":"Europe/Istanbul",
    "iso:country":"TR",
    "name:und_x_variant":[
        "Iskele",
        "Mordu\u011fan",
        "K\u00fc\u00e7\u00fck Mordo\u011fan",
        "Mordo\u011fan \u0130skelesi",
        "Murda\u011fan",
        "Murdo\u011fan",
        "M\u00fcrdu\u011fan",
        "Mordo\u011fan"
    ],
    "wof:name":"Mordogan",
    "wof:placetype":"locality"
},
  "geometry": {"coordinates":[26.62447,38.51648],"type":"Point"}
}