{
  "type": "Feature",
  "properties": {
    "gn:admin1_code":"8.0",
    "gn:asciiname":"Camili",
    "gn:country_code":"TR",
    "gn:dem":455,
    "gn:feature_class":"P",
    "gn:feature_code":"PPLA3",
    "gn:name":"Camili",
    "gn:population":0,
    "gn:timezone":"Europe/Istanbul",
    "iso:country":"TR",
    "name:ceb_x_preferred":[
        "Camili"
    ],
    "name:swe_x_preferred":[
        "Camili"
    ],
    "name:tur_x_preferred":[
        "Camili"
    ],
    "name:und_x_variant":[
        "Ma\u00e7ahel"
    ],
    "wof:name":"Camili",
    "wof:placetype":"locality"
},
  "geometry": {"coordinates":[41.89825,41.47838],"type":"Point"}
}