{
  "type": "Feature",
  "properties": {
    "gn:admin1_code":"03",
    "gn:asciiname":"Killicli",
    "gn:country_code":"TR",
    "gn:dem":1176,
    "gn:feature_class":"P",
    "gn:feature_code":"PPL",
    "gn:name":"K\u0131ll\u0131\u00e7l\u0131",
    "gn:population":0,
    "gn:timezone":"Europe/Istanbul",
    "iso:country":"TR",
    "wof:name":"Killicli",
    "wof:placetype":"locality"
},
  "geometry": {"coordinates":[31.05,39.13333],"type":"Point"}
}