{
  "type": "Feature",
  "properties": {
    "gn:admin1_code":"45",
    "gn:asciiname":"Yukari Gulluce",
    "gn:country_code":"TR",
    "gn:dem":476,
    "gn:feature_class":"P",
    "gn:feature_code":"PPL",
    "gn:name":"Yukar\u0131 G\u00fcll\u00fcce",
    "gn:population":0,
    "gn:timezone":"Europe/Istanbul",
    "iso:country":"TR",
    "name:tur_x_preferred":[
        "Yukar\u0131 G\u00fcll\u00fcce"
    ],
    "name:und_x_variant":[
        "Yukar\u0131tefen"
    ],
    "wof:name":"Yukari Gulluce",
    "wof:placetype":"locality"
},
  "geometry": {"coordinates":[28.77139,38.7425],"type":"Point"}
}