{
  "type": "Feature",
  "properties": {
    "gn:admin1_code":"24",
    "gn:asciiname":"Camurdere",
    "gn:country_code":"TR",
    "gn:dem":1619,
    "gn:feature_class":"P",
    "gn:feature_code":"PPL",
    "gn:name":"\u00c7amurdere",
    "gn:population":0,
    "gn:timezone":"Europe/Istanbul",
    "iso:country":"TR",
    "name:und_x_variant":[
        "\u00c7amurdere K\u00f6y\u00fc",
        "\u00c7amurdere"
    ],
    "wof:name":"Camurdere",
    "wof:placetype":"locality"
},
  "geometry": {"coordinates":[39.95594000000001,39.82129000000001],"type":"Point"}
}