{
  "type": "Feature",
  "properties": {
    "gn:admin1_code":"31.0",
    "gn:asciiname":"Mustafa",
    "gn:country_code":"TR",
    "gn:dem":75,
    "gn:feature_class":"P",
    "gn:feature_code":"PPL",
    "gn:name":"Mustafa",
    "gn:population":0,
    "gn:timezone":"Europe/Istanbul",
    "iso:country":"TR",
    "name:ara_x_preferred":[
        "\u0645\u0635\u0637\u0641\u0649"
    ],
    "name:deu_x_preferred":[
        "Mustafa"
    ],
    "name:ell_x_preferred":[
        "\u039c\u03bf\u03c5\u03c3\u03c4\u03b1\u03c6\u03ac"
    ],
    "name:fas_x_preferred":[
        "\u0645\u0635\u0637\u0641\u06cc"
    ],
    "name:fra_x_preferred":[
        "Moustapha"
    ],
    "name:heb_x_preferred":[
        "\u05de\u05d5\u05e1\u05d8\u05e4\u05d0"
    ],
    "name:ita_x_preferred":[
        "Mustafa"
    ],
    "name:lat_x_preferred":[
        "Mustapha"
    ],
    "name:nor_x_preferred":[
        "Mustafa"
    ],
    "name:spa_x_preferred":[
        "Mustaf\u00e1"
    ],
    "name:sqi_x_preferred":[
        "Mustafa"
    ],
    "name:swe_x_preferred":[
        "Mustafa"
    ],
    "name:tur_x_preferred":[
        "Mustafa"
    ],
    "name:tur_x_variant":[
        "Mustaba"
    ],
    "wof:name":"Mustafa",
    "wof:placetype":"locality"
},
  "geometry": {"coordinates":[36.11343,36.11978],"type":"Point"}
}