{
  "type": "Feature",
  "properties": {
    "gn:admin1_code":"13.0",
    "gn:asciiname":"Bayramalan",
    "gn:country_code":"TR",
    "gn:dem":1526,
    "gn:feature_class":"P",
    "gn:feature_code":"PPL",
    "gn:name":"Bayramalan",
    "gn:population":0,
    "gn:timezone":"Europe/Istanbul",
    "iso:country":"TR",
    "name:tur_x_preferred":[
        "Bayramalan"
    ],
    "wof:name":"Bayramalan",
    "wof:placetype":"locality"
},
  "geometry": {"coordinates":[42.12853,38.33984],"type":"Point"}
}