{
  "type": "Feature",
  "properties": {
    "gn:admin1_code":"52.0",
    "gn:asciiname":"Karagoz",
    "gn:country_code":"TR",
    "gn:dem":1199,
    "gn:feature_class":"P",
    "gn:feature_code":"PPL",
    "gn:name":"Karag\u00f6z",
    "gn:population":0,
    "gn:timezone":"Europe/Istanbul",
    "iso:country":"TR",
    "wof:name":"Karagoz",
    "wof:placetype":"locality"
},
  "geometry": {"coordinates":[37.63333,40.66667],"type":"Point"}
}