{
  "type": "Feature",
  "properties": {
    "gn:admin1_code":"23",
    "gn:asciiname":"Dibekli",
    "gn:country_code":"TR",
    "gn:dem":1066,
    "gn:feature_class":"P",
    "gn:feature_code":"PPL",
    "gn:name":"Dibekli",
    "gn:population":0,
    "gn:timezone":"Europe/Istanbul",
    "iso:country":"TR",
    "name:tur_x_preferred":[
        "Dibekli"
    ],
    "wof:name":"Dibekli",
    "wof:placetype":"locality"
},
  "geometry": {"coordinates":[38.61805,38.88748],"type":"Point"}
}