{
  "type": "Feature",
  "properties": {
    "gn:admin1_code":"26",
    "gn:asciiname":"Dikmen",
    "gn:cc2":"TR",
    "gn:country_code":"TR",
    "gn:dem":850,
    "gn:feature_class":"P",
    "gn:feature_code":"PPL",
    "gn:name":"Dikmen",
    "gn:population":0,
    "gn:timezone":"Europe/Istanbul",
    "iso:country":"TR",
    "name:und_x_variant":[
        "Yaral\u0131",
        "Nasriye",
        "Dikmen"
    ],
    "wof:name":"Dikmen",
    "wof:placetype":"locality"
},
  "geometry": {"coordinates":[31.28778,39.35417],"type":"Point"}
}