{
  "type": "Feature",
  "properties": {
    "gn:admin1_code":"34",
    "gn:asciiname":"Eskidegirmenkoy",
    "gn:country_code":"TR",
    "gn:dem":83,
    "gn:feature_class":"P",
    "gn:feature_code":"PPL",
    "gn:name":"Eskide\u011firmenk\u00f6y",
    "gn:population":0,
    "gn:timezone":"Europe/Istanbul",
    "iso:country":"TR",
    "name:tur_x_preferred":[
        "Eskide\u011firmenk\u00f6y"
    ],
    "wof:name":"Eskidegirmenkoy",
    "wof:placetype":"locality"
},
  "geometry": {"coordinates":[28.02753,41.07183],"type":"Point"}
}