{
  "type": "Feature",
  "properties": {
    "gn:admin1_code":"91.0",
    "gn:asciiname":"Karaincir",
    "gn:country_code":"TR",
    "gn:dem":198,
    "gn:feature_class":"P",
    "gn:feature_code":"PPL",
    "gn:name":"Karaincir",
    "gn:population":0,
    "gn:timezone":"Europe/Istanbul",
    "iso:country":"TR",
    "wof:name":"Karaincir",
    "wof:placetype":"locality"
},
  "geometry": {"coordinates":[36.15759,37.26078],"type":"Point"}
}