{
  "type": "Feature",
  "properties": {
    "gn:admin1_code":"04",
    "gn:asciiname":"Asagi Tavla",
    "gn:country_code":"TR",
    "gn:dem":1507,
    "gn:feature_class":"P",
    "gn:feature_code":"PPL",
    "gn:name":"A\u015fa\u011f\u0131 Tavla",
    "gn:population":0,
    "gn:timezone":"Europe/Istanbul",
    "iso:country":"TR",
    "name:und_x_variant":[
        "Yukar\u0131 Tavla",
        "A\u015fa\u011f\u0131 Tavla",
        "Tavla"
    ],
    "wof:name":"Asagi Tavla",
    "wof:placetype":"locality"
},
  "geometry": {"coordinates":[44.25972,39.5025],"type":"Point"}
}