{
  "type": "Feature",
  "properties": {
    "gn:admin1_code":"2.0",
    "gn:asciiname":"Yukari Akcali",
    "gn:country_code":"TR",
    "gn:dem":647,
    "gn:feature_class":"P",
    "gn:feature_code":"PPL",
    "gn:name":"Yukar\u0131 Ak\u00e7al\u0131",
    "gn:population":0,
    "gn:timezone":"Europe/Istanbul",
    "iso:country":"TR",
    "name:tur_x_preferred":[
        "Yukar\u0131 Ak\u00e7al\u0131"
    ],
    "wof:name":"Yukari Akcali",
    "wof:placetype":"locality"
},
  "geometry": {"coordinates":[38.93636,38.00141],"type":"Point"}
}