{
  "type": "Feature",
  "properties": {
    "gn:admin1_code":"41",
    "gn:asciiname":"Cirakli",
    "gn:country_code":"TR",
    "gn:dem":261,
    "gn:feature_class":"P",
    "gn:feature_code":"PPL",
    "gn:name":"\u00c7\u0131rakl\u0131",
    "gn:population":0,
    "gn:timezone":"Europe/Istanbul",
    "iso:country":"TR",
    "name:tur_x_preferred":[
        "\u00c7\u0131rakl\u0131"
    ],
    "wof:name":"Cirakli",
    "wof:placetype":"locality"
},
  "geometry": {"coordinates":[29.80726,40.90208],"type":"Point"}
}