{
  "type": "Feature",
  "properties": {
    "gn:admin1_code":"09",
    "gn:asciiname":"Abak",
    "gn:country_code":"TR",
    "gn:dem":120,
    "gn:feature_class":"P",
    "gn:feature_code":"PPL",
    "gn:name":"Abak",
    "gn:population":0,
    "gn:timezone":"Europe/Istanbul",
    "iso:country":"TR",
    "name:ceb_x_preferred":[
        "Abak"
    ],
    "name:deu_x_preferred":[
        "Abak"
    ],
    "name:fas_x_preferred":[
        "\u0622\u0628\u0627\u06a9"
    ],
    "name:fra_x_preferred":[
        "Abak"
    ],
    "name:hau_x_preferred":[
        "Abak"
    ],
    "name:ita_x_preferred":[
        "Abak"
    ],
    "name:spa_x_preferred":[
        "Abak"
    ],
    "name:tur_x_preferred":[
        "Abak"
    ],
    "name:tur_x_variant":[
        "Dibabak",
        "Dipabak"
    ],
    "name:yor_x_preferred":[
        "Abak"
    ],
    "wof:name":"Abak",
    "wof:placetype":"locality"
},
  "geometry": {"coordinates":[27.86555,37.60974],"type":"Point"}
}