{
  "type": "Feature",
  "properties": {
    "gn:admin1_code":"44",
    "gn:asciiname":"Kizilyatak",
    "gn:country_code":"TR",
    "gn:dem":1768,
    "gn:feature_class":"P",
    "gn:feature_code":"PPL",
    "gn:name":"K\u0131z\u0131lyatak",
    "gn:population":0,
    "gn:timezone":"Europe/Istanbul",
    "iso:country":"TR",
    "wof:name":"Kizilyatak",
    "wof:placetype":"locality"
},
  "geometry": {"coordinates":[37.84043,38.71139],"type":"Point"}
}