{
  "type": "Feature",
  "properties": {
    "gn:admin1_code":"45",
    "gn:asciiname":"Sazoba",
    "gn:cc2":"TR",
    "gn:country_code":"TR",
    "gn:dem":75,
    "gn:feature_class":"P",
    "gn:feature_code":"PPL",
    "gn:name":"Sazoba",
    "gn:population":0,
    "gn:timezone":"Europe/Istanbul",
    "iso:country":"TR",
    "name:und_x_variant":[
        "Sazk\u00f6y",
        "Sazoba"
    ],
    "wof:name":"Sazoba",
    "wof:placetype":"locality"
},
  "geometry": {"coordinates":[27.79194,38.79861],"type":"Point"}
}