{
  "type": "Feature",
  "properties": {
    "gn:admin1_code":"13.0",
    "gn:asciiname":"Cemihacimehmet",
    "gn:country_code":"TR",
    "gn:dem":1292,
    "gn:feature_class":"P",
    "gn:feature_code":"PPL",
    "gn:name":"Cemihacimehmet",
    "gn:population":0,
    "gn:timezone":"Europe/Istanbul",
    "iso:country":"TR",
    "wof:name":"Cemihacimehmet",
    "wof:placetype":"locality"
},
  "geometry": {"coordinates":[42.60333,37.98917],"type":"Point"}
}