{
  "type": "Feature",
  "properties": {
    "gn:admin1_code":"64",
    "gn:asciiname":"Ortabag",
    "gn:country_code":"TR",
    "gn:dem":556,
    "gn:feature_class":"P",
    "gn:feature_code":"PPL",
    "gn:name":"Ortaba\u011f",
    "gn:population":0,
    "gn:timezone":"Europe/Istanbul",
    "iso:country":"TR",
    "wof:name":"Ortabag",
    "wof:placetype":"locality"
},
  "geometry": {"coordinates":[28.86729,38.6363],"type":"Point"}
}