{
  "type": "Feature",
  "properties": {
    "gn:admin1_code":"63",
    "gn:asciiname":"Sumanli",
    "gn:country_code":"TR",
    "gn:dem":703,
    "gn:feature_class":"P",
    "gn:feature_code":"PPL",
    "gn:name":"Sumanl\u0131",
    "gn:population":0,
    "gn:timezone":"Europe/Istanbul",
    "iso:country":"TR",
    "name:tur_x_preferred":[
        "Sumanl\u0131"
    ],
    "wof:name":"Sumanli",
    "wof:placetype":"locality"
},
  "geometry": {"coordinates":[38.87185,37.52671],"type":"Point"}
}