{
  "type": "Feature",
  "properties": {
    "gn:admin1_code":"19.0",
    "gn:asciiname":"Boyaci",
    "gn:country_code":"TR",
    "gn:dem":1138,
    "gn:feature_class":"P",
    "gn:feature_code":"PPL",
    "gn:name":"Boyac\u0131",
    "gn:population":0,
    "gn:timezone":"Europe/Istanbul",
    "iso:country":"TR",
    "name:tur_x_preferred":[
        "Boyac\u0131"
    ],
    "wof:name":"Boyaci",
    "wof:placetype":"locality"
},
  "geometry": {"coordinates":[35.29143,40.45302],"type":"Point"}
}