{
  "type": "Feature",
  "properties": {
    "gn:admin1_code":"74",
    "gn:asciiname":"Karaca",
    "gn:country_code":"TR",
    "gn:dem":1045,
    "gn:feature_class":"P",
    "gn:feature_code":"PPL",
    "gn:name":"Karaca",
    "gn:population":0,
    "gn:timezone":"Europe/Istanbul",
    "iso:country":"TR",
    "name:aze_x_preferred":[
        "Qaraca"
    ],
    "name:ceb_x_preferred":[
        "Karaca"
    ],
    "name:deu_x_preferred":[
        "Karaca"
    ],
    "name:fra_x_preferred":[
        "Karaca"
    ],
    "name:swe_x_preferred":[
        "Karaca"
    ],
    "name:tur_x_preferred":[
        "Karaca"
    ],
    "name:und_x_variant":[
        "Tasil"
    ],
    "wof:name":"Karaca",
    "wof:placetype":"locality"
},
  "geometry": {"coordinates":[42.03417,38.12146],"type":"Point"}
}