{
  "type": "Feature",
  "properties": {
    "gn:admin1_code":"81",
    "gn:asciiname":"Karakuyu",
    "gn:country_code":"TR",
    "gn:dem":1251,
    "gn:feature_class":"P",
    "gn:feature_code":"PPL",
    "gn:name":"Karakuyu",
    "gn:population":0,
    "gn:timezone":"Europe/Istanbul",
    "iso:country":"TR",
    "wof:name":"Karakuyu",
    "wof:placetype":"locality"
},
  "geometry": {"coordinates":[36.20058,37.86124],"type":"Point"}
}