{
  "type": "Feature",
  "properties": {
    "gn:admin1_code":"55.0",
    "gn:asciiname":"Asagisusuz",
    "gn:country_code":"TR",
    "gn:dem":803,
    "gn:feature_class":"P",
    "gn:feature_code":"PPL",
    "gn:name":"A\u015fa\u011f\u0131susuz",
    "gn:population":0,
    "gn:timezone":"Europe/Istanbul",
    "iso:country":"TR",
    "name:tur_x_preferred":[
        "A\u015fa\u011f\u0131susuz"
    ],
    "wof:name":"Asagisusuz",
    "wof:placetype":"locality"
},
  "geometry": {"coordinates":[35.70211,40.93335],"type":"Point"}
}