{
  "type": "Feature",
  "properties": {
    "gn:admin1_code":"16",
    "gn:asciiname":"Deliceguney",
    "gn:country_code":"TR",
    "gn:dem":605,
    "gn:feature_class":"P",
    "gn:feature_code":"PPL",
    "gn:name":"Deliceg\u00fcney",
    "gn:population":0,
    "gn:timezone":"Europe/Istanbul",
    "iso:country":"TR",
    "name:tur_x_preferred":[
        "Deliceg\u00fcney"
    ],
    "wof:name":"Deliceguney",
    "wof:placetype":"locality"
},
  "geometry": {"coordinates":[29.01029,39.65079],"type":"Point"}
}