{
  "type": "Feature",
  "properties": {
    "gn:admin1_code":"83",
    "gn:asciiname":"Kavsak",
    "gn:country_code":"TR",
    "gn:dem":894,
    "gn:feature_class":"P",
    "gn:feature_code":"PPL",
    "gn:name":"Kav\u015fak",
    "gn:population":0,
    "gn:timezone":"Europe/Istanbul",
    "iso:country":"TR",
    "name:tur_x_preferred":[
        "Kav\u015fak"
    ],
    "wof:name":"Kavsak",
    "wof:placetype":"locality"
},
  "geometry": {"coordinates":[37.14048,37.00999],"type":"Point"}
}