{
  "type": "Feature",
  "properties": {
    "iso:country":"TR",
    "name:eng_x_preferred":[
        "Adem Yavuz"
    ],
    "name:tur_x_preferred":[
        "Adem Yavuz"
    ],
    "wof:name":"Adem Yavuz",
    "wof:placetype":"neighbourhood"
},
  "geometry": {"coordinates":[29.15450101116296,41.02103719416315],"type":"Point"}
}