{
  "type": "Feature",
  "properties": {
    "gn:admin1_code":"04",
    "gn:asciiname":"Sogukpinar",
    "gn:country_code":"TR",
    "gn:dem":1601,
    "gn:feature_class":"P",
    "gn:feature_code":"PPL",
    "gn:name":"So\u011fukp\u0131nar",
    "gn:population":0,
    "gn:timezone":"Europe/Istanbul",
    "iso:country":"TR",
    "name:und_x_variant":[
        "Mu\u015fyan",
        "So\u011fukp\u0131nar"
    ],
    "wof:name":"Sogukpinar",
    "wof:placetype":"locality"
},
  "geometry": {"coordinates":[42.57517,39.4901],"type":"Point"}
}