{
  "type": "Feature",
  "properties": {
    "gn:admin1_code":"57.0",
    "gn:asciiname":"Karacaygoleti",
    "gn:country_code":"TR",
    "gn:dem":848,
    "gn:feature_class":"P",
    "gn:feature_code":"PPL",
    "gn:name":"Kara\u00e7ayg\u00f6leti",
    "gn:population":0,
    "gn:timezone":"Europe/Istanbul",
    "iso:country":"TR",
    "name:und_x_variant":[
        "Kara\u00e7amg\u00f6leti",
        "Kara\u00e7ayg\u00f6leti"
    ],
    "wof:name":"Karacaygoleti",
    "wof:placetype":"locality"
},
  "geometry": {"coordinates":[34.82901,41.28961],"type":"Point"}
}