{
  "type": "Feature",
  "properties": {
    "gn:admin1_code":"49",
    "gn:asciiname":"Erencik",
    "gn:country_code":"TR",
    "gn:dem":1330,
    "gn:feature_class":"P",
    "gn:feature_code":"PPL",
    "gn:name":"Erencik",
    "gn:population":0,
    "gn:timezone":"Europe/Istanbul",
    "iso:country":"TR",
    "name:tur_x_preferred":[
        "Erencik"
    ],
    "name:und_x_variant":[
        "Eldik"
    ],
    "wof:name":"Erencik",
    "wof:placetype":"locality"
},
  "geometry": {"coordinates":[41.4384,38.90619],"type":"Point"}
}