{
  "type": "Feature",
  "properties": {
    "gn:admin1_code":"74.0",
    "gn:asciiname":"Savas",
    "gn:country_code":"TR",
    "gn:dem":937,
    "gn:feature_class":"P",
    "gn:feature_code":"PPL",
    "gn:name":"Sava\u015f",
    "gn:population":0,
    "gn:timezone":"Europe/Istanbul",
    "iso:country":"TR",
    "name:bug_x_preferred":[
        "Savas"
    ],
    "name:ceb_x_preferred":[
        "Savas"
    ],
    "name:deu_x_preferred":[
        "Savas"
    ],
    "name:eus_x_preferred":[
        "Savas"
    ],
    "name:fra_x_preferred":[
        "Savas"
    ],
    "name:frp_x_preferred":[
        "Sav\u00e2s"
    ],
    "name:hun_x_preferred":[
        "Savas"
    ],
    "name:hye_x_preferred":[
        "\u054d\u0561\u057e\u0561"
    ],
    "name:ita_x_preferred":[
        "Savas"
    ],
    "name:lat_x_preferred":[
        "Savas"
    ],
    "name:lmo_x_preferred":[
        "Savas"
    ],
    "name:mlg_x_preferred":[
        "Savas"
    ],
    "name:msa_x_preferred":[
        "Savas"
    ],
    "name:nld_x_preferred":[
        "Savas"
    ],
    "name:oci_x_preferred":[
        "Savas"
    ],
    "name:pms_x_preferred":[
        "Savas"
    ],
    "name:pol_x_preferred":[
        "Savas"
    ],
    "name:por_x_preferred":[
        "Savas"
    ],
    "name:ron_x_preferred":[
        "Savas"
    ],
    "name:rus_x_preferred":[
        "\u0421\u0430\u0432\u0430"
    ],
    "name:slk_x_preferred":[
        "Savas"
    ],
    "name:spa_x_preferred":[
        "Savas"
    ],
    "name:sqi_x_preferred":[
        "Savas"
    ],
    "name:swe_x_preferred":[
        "Savas"
    ],
    "name:ukr_x_preferred":[
        "\u0421\u0430\u0432\u0430"
    ],
    "name:vie_x_preferred":[
        "Savas"
    ],
    "name:vol_x_preferred":[
        "Savas"
    ],
    "name:war_x_preferred":[
        "Savas"
    ],
    "name:zho_x_preferred":[
        "\u8428\u74e6"
    ],
    "wof:name":"Savas",
    "wof:placetype":"locality"
},
  "geometry": {"coordinates":[41.95426,37.66246],"type":"Point"}
}