{
  "type": "Feature",
  "properties": {
    "gn:admin1_code":"04",
    "gn:asciiname":"Alacahan",
    "gn:country_code":"TR",
    "gn:dem":1552,
    "gn:feature_class":"P",
    "gn:feature_code":"PPL",
    "gn:name":"Alacahan",
    "gn:population":0,
    "gn:timezone":"Europe/Istanbul",
    "iso:country":"TR",
    "name:tur_x_preferred":[
        "Alacahan"
    ],
    "wof:name":"Alacahan",
    "wof:placetype":"locality"
},
  "geometry": {"coordinates":[42.5584,39.40029000000001],"type":"Point"}
}