{
  "type": "Feature",
  "properties": {
    "gn:admin1_code":"32",
    "gn:asciiname":"Bahcedere",
    "gn:country_code":"TR",
    "gn:dem":123,
    "gn:feature_class":"P",
    "gn:feature_code":"PPL",
    "gn:name":"Bah\u00e7edere",
    "gn:population":0,
    "gn:timezone":"Europe/Istanbul",
    "iso:country":"TR",
    "name:tur_x_preferred":[
        "Bah\u00e7edere"
    ],
    "name:und_x_variant":[
        "Bah\u00e7ek\u00f6y",
        "Beh\u00e7ederesi K\u00f6y",
        "Bah\u00e7ederesi"
    ],
    "wof:name":"Bahcedere",
    "wof:placetype":"locality"
},
  "geometry": {"coordinates":[33.86891,36.36289],"type":"Point"}
}