{
  "type": "Feature",
  "properties": {
    "gn:admin1_code":"14",
    "gn:asciiname":"Eyvazler",
    "gn:country_code":"TR",
    "gn:dem":1350,
    "gn:feature_class":"P",
    "gn:feature_code":"PPL",
    "gn:name":"Eyvazler",
    "gn:population":0,
    "gn:timezone":"Europe/Istanbul",
    "iso:country":"TR",
    "wof:name":"Eyvazler",
    "wof:placetype":"locality"
},
  "geometry": {"coordinates":[31.54598,40.45383],"type":"Point"}
}