{
  "type": "Feature",
  "properties": {
    "gn:admin1_code":"63",
    "gn:asciiname":"Haraptar",
    "gn:cc2":"TR",
    "gn:country_code":"TR",
    "gn:dem":451,
    "gn:feature_class":"P",
    "gn:feature_code":"PPL",
    "gn:name":"Haraptar",
    "gn:population":0,
    "gn:timezone":"Europe/Istanbul",
    "iso:country":"TR",
    "name:und_x_variant":[
        "Harabdar",
        "Kharaptar",
        "Harapdar",
        "Haraptar"
    ],
    "wof:name":"Haraptar",
    "wof:placetype":"locality"
},
  "geometry": {"coordinates":[38.8125,36.97333],"type":"Point"}
}