{
  "type": "Feature",
  "properties": {
    "gn:admin1_code":"82.0",
    "gn:asciiname":"Imamlar",
    "gn:country_code":"TR",
    "gn:dem":1257,
    "gn:feature_class":"P",
    "gn:feature_code":"PPL",
    "gn:name":"\u0130mamlar",
    "gn:population":0,
    "gn:timezone":"Europe/Istanbul",
    "iso:country":"TR",
    "wof:name":"Imamlar",
    "wof:placetype":"locality"
},
  "geometry": {"coordinates":[33.1519,41.00694],"type":"Point"}
}