{
  "type": "Feature",
  "properties": {
    "gn:admin1_code":"80",
    "gn:asciiname":"Selcik",
    "gn:country_code":"TR",
    "gn:dem":755,
    "gn:feature_class":"P",
    "gn:feature_code":"PPL",
    "gn:name":"Selcik",
    "gn:population":0,
    "gn:timezone":"Europe/Istanbul",
    "iso:country":"TR",
    "name:tur_x_preferred":[
        "Selcik"
    ],
    "name:und_x_variant":[
        "Deredef\u015f",
        "Diredef\u015f",
        "Diredefsh",
        "Sel\u00e7ik"
    ],
    "wof:name":"Selcik",
    "wof:placetype":"locality"
},
  "geometry": {"coordinates":[42.58417,37.30583],"type":"Point"}
}