{
  "type": "Feature",
  "properties": {
    "gn:admin1_code":"5.0",
    "gn:asciiname":"Kuzalan",
    "gn:country_code":"TR",
    "gn:dem":979,
    "gn:feature_class":"P",
    "gn:feature_code":"PPL",
    "gn:name":"Kuzalan",
    "gn:population":0,
    "gn:timezone":"Europe/Istanbul",
    "iso:country":"TR",
    "name:und_x_variant":[
        "Kozalan",
        "Kuzalan"
    ],
    "wof:name":"Kuzalan",
    "wof:placetype":"locality"
},
  "geometry": {"coordinates":[35.1336,40.91716],"type":"Point"}
}