{
  "type": "Feature",
  "properties": {
    "gn:admin1_code":"58",
    "gn:asciiname":"Sarac",
    "gn:country_code":"TR",
    "gn:dem":1215,
    "gn:feature_class":"P",
    "gn:feature_code":"PPL",
    "gn:name":"Sara\u00e7",
    "gn:population":0,
    "gn:timezone":"Europe/Istanbul",
    "iso:country":"TR",
    "name:tur_x_preferred":[
        "Sa\u011f\u0131rkavak"
    ],
    "name:und_x_variant":[
        "Sara\u00e7 K\u00f6y\u00fc",
        "Sara\u00e7",
        "Sara\u00e7k\u00f6y"
    ],
    "wof:name":"Sarac",
    "wof:placetype":"locality"
},
  "geometry": {"coordinates":[36.19817000000001,39.33006],"type":"Point"}
}