{
  "type": "Feature",
  "properties": {
    "gn:country":"TR",
    "gn:fcode":"PPL",
    "gn:population":8648,
    "iso:country":"TR",
    "name:tur_x_preferred":[
        "Bah\u00e7ecik"
    ],
    "name:und_x_variant":[
        "Bagchejik"
    ],
    "qs:name":"Bah\u00e7ecik",
    "qs:photos_9r":0,
    "qs:photos_sr":0,
    "qs:pop_sr":"5",
    "wd:wordcount":80,
    "wof:name":"Bah\u00e7ecik",
    "wof:placetype":"locality",
    "wof:population":8648
},
  "geometry": {"coordinates":[29.89706,40.67136],"type":"Point"}
}