{
  "type": "Feature",
  "properties": {
    "gn:admin1_code":"64",
    "gn:asciiname":"Ortaburun",
    "gn:country_code":"TR",
    "gn:dem":713,
    "gn:feature_class":"P",
    "gn:feature_code":"PPL",
    "gn:name":"Ortaburun",
    "gn:population":0,
    "gn:timezone":"Europe/Istanbul",
    "iso:country":"TR",
    "name:tur_x_preferred":[
        "Ortaburun"
    ],
    "wof:name":"Ortaburun",
    "wof:placetype":"locality"
},
  "geometry": {"coordinates":[29.19246,38.81493],"type":"Point"}
}