{
  "type": "Feature",
  "properties": {
    "gn:admin1_code":"78",
    "gn:asciiname":"Gormeli",
    "gn:country_code":"TR",
    "gn:dem":857,
    "gn:feature_class":"P",
    "gn:feature_code":"PPL",
    "gn:name":"G\u00f6rmeli",
    "gn:population":0,
    "gn:timezone":"Europe/Istanbul",
    "iso:country":"TR",
    "name:ceb_x_preferred":[
        "\u00dc\u00e7b\u00f6l\u00fck"
    ],
    "name:deu_x_preferred":[
        "G\u00f6rmeli"
    ],
    "name:epo_x_preferred":[
        "G\u00f6rmeli"
    ],
    "name:fra_x_preferred":[
        "G\u00f6rmeli"
    ],
    "name:msa_x_preferred":[
        "G\u00f6rmeli"
    ],
    "name:ota_x_preferred":[
        "\u06a9\u0648\u0631\u0645\u0644"
    ],
    "name:spa_x_preferred":[
        "G\u00f6rmeli"
    ],
    "name:tur_x_preferred":[
        "G\u00f6rmeli"
    ],
    "name:und_x_variant":[
        "K\u00f6rmel",
        "G\u00f6rmelk\u00f6y",
        "G\u00f6rmel"
    ],
    "name:vie_x_preferred":[
        "G\u00f6rmeli"
    ],
    "wof:name":"Gormeli",
    "wof:placetype":"locality"
},
  "geometry": {"coordinates":[32.97724,36.54512],"type":"Point"}
}