{
  "type": "Feature",
  "properties": {
    "gn:admin1_code":"38",
    "gn:asciiname":"Muncusun",
    "gn:country_code":"TR",
    "gn:dem":1217,
    "gn:feature_class":"P",
    "gn:feature_code":"PPLA3",
    "gn:name":"Muncusun",
    "gn:population":0,
    "gn:timezone":"Europe/Istanbul",
    "iso:country":"TR",
    "name:und_x_variant":[
        "G\u00fcne\u015fli",
        "Muncusun"
    ],
    "wof:name":"Muncusun",
    "wof:placetype":"locality"
},
  "geometry": {"coordinates":[35.62743,38.90253],"type":"Point"}
}