{
  "type": "Feature",
  "properties": {
    "gn:admin1_code":"85",
    "gn:asciiname":"Dingiller",
    "gn:country_code":"TR",
    "gn:dem":97,
    "gn:feature_class":"P",
    "gn:feature_code":"PPL",
    "gn:name":"Dingiller",
    "gn:population":0,
    "gn:timezone":"Europe/Istanbul",
    "iso:country":"TR",
    "wof:name":"Dingiller",
    "wof:placetype":"locality"
},
  "geometry": {"coordinates":[31.56969,41.35916],"type":"Point"}
}