{
  "type": "Feature",
  "properties": {
    "gn:admin1_code":"31.0",
    "gn:admin2_code":"438418.0",
    "gn:asciiname":"Kalinsan",
    "gn:country_code":"TR",
    "gn:dem":351,
    "gn:feature_class":"P",
    "gn:feature_code":"PPL",
    "gn:name":"Kal\u0131nsan",
    "gn:population":20,
    "gn:timezone":"Europe/Istanbul",
    "iso:country":"TR",
    "name:tur_x_historical":[
        "Kuleyzen"
    ],
    "name:tur_x_preferred":[
        "Kuleyzen"
    ],
    "name:und_x_variant":[
        "Kalynsan",
        "Kal\u0131nsan"
    ],
    "wof:name":"Kalinsan",
    "wof:placetype":"locality",
    "wof:population":20
},
  "geometry": {"coordinates":[36.26724,36.09256],"type":"Point"}
}