{
  "type": "Feature",
  "properties": {
    "gn:admin1_code":"10",
    "gn:asciiname":"Ayvaldere",
    "gn:country_code":"TR",
    "gn:dem":54,
    "gn:feature_class":"P",
    "gn:feature_code":"PPL",
    "gn:name":"Ayvaldere",
    "gn:population":0,
    "gn:timezone":"Europe/Istanbul",
    "iso:country":"TR",
    "name:tur_x_preferred":[
        "Ayvaldere"
    ],
    "wof:name":"Ayvaldere",
    "wof:placetype":"locality"
},
  "geometry": {"coordinates":[27.64596,40.23637],"type":"Point"}
}