{
  "type": "Feature",
  "properties": {
    "gn:admin1_code":"19.0",
    "gn:asciiname":"Buyukgulucek",
    "gn:country_code":"TR",
    "gn:dem":1131,
    "gn:feature_class":"P",
    "gn:feature_code":"PPL",
    "gn:name":"B\u00fcy\u00fckg\u00fcl\u00fccek",
    "gn:population":0,
    "gn:timezone":"Europe/Istanbul",
    "iso:country":"TR",
    "name:und_x_variant":[
        "B\u00fcy\u00fck G\u00fcll\u00fccek",
        "B\u00fcy\u00fckg\u00fcl\u00fccek"
    ],
    "wof:name":"Buyukgulucek",
    "wof:placetype":"locality"
},
  "geometry": {"coordinates":[34.75175,40.34568],"type":"Point"}
}