{
  "type": "Feature",
  "properties": {
    "gn:admin1_code":"37.0",
    "gn:asciiname":"Nanepinari",
    "gn:country_code":"TR",
    "gn:dem":233,
    "gn:feature_class":"P",
    "gn:feature_code":"PPL",
    "gn:name":"Nanep\u0131nar\u0131",
    "gn:population":0,
    "gn:timezone":"Europe/Istanbul",
    "iso:country":"TR",
    "name:und_x_variant":[
        "Nenep\u0131nar\u0131",
        "Nanep\u0131nar",
        "Nanepunar\u0131",
        "Nanep\u0131nar\u0131"
    ],
    "wof:name":"Nanepinari",
    "wof:placetype":"locality"
},
  "geometry": {"coordinates":[32.82151,41.83583],"type":"Point"}
}