{
  "type": "Feature",
  "properties": {
    "gn:admin1_code":"43.0",
    "gn:asciiname":"Kumluyurt",
    "gn:country_code":"TR",
    "gn:dem":1104,
    "gn:feature_class":"P",
    "gn:feature_code":"PPL",
    "gn:name":"Kumluyurt",
    "gn:population":0,
    "gn:timezone":"Europe/Istanbul",
    "iso:country":"TR",
    "name:und_x_variant":[
        "Ahileryaylas\u0131",
        "Ah\u0131laryaylas\u0131"
    ],
    "wof:name":"Kumluyurt",
    "wof:placetype":"locality"
},
  "geometry": {"coordinates":[30.26163,39.28795],"type":"Point"}
}