{
  "type": "Feature",
  "properties": {
    "gn:admin1_code":"17",
    "gn:asciiname":"Kalabakbasi",
    "gn:country_code":"TR",
    "gn:dem":287,
    "gn:feature_class":"P",
    "gn:feature_code":"PPL",
    "gn:name":"Kalabakba\u015f\u0131",
    "gn:population":0,
    "gn:timezone":"Europe/Istanbul",
    "iso:country":"TR",
    "wof:name":"Kalabakbasi",
    "wof:placetype":"locality"
},
  "geometry": {"coordinates":[27.24287,39.77387],"type":"Point"}
}