{
  "type": "Feature",
  "properties": {
    "gn:admin1_code":"15",
    "gn:asciiname":"Sazak",
    "gn:country_code":"TR",
    "gn:dem":991,
    "gn:feature_class":"P",
    "gn:feature_code":"PPL",
    "gn:name":"Sazak",
    "gn:population":0,
    "gn:timezone":"Europe/Istanbul",
    "iso:country":"TR",
    "name:deu_x_preferred":[
        "Sazak"
    ],
    "name:nld_x_preferred":[
        "Sazak"
    ],
    "name:tur_x_preferred":[
        "Sazak"
    ],
    "wof:name":"Sazak",
    "wof:placetype":"locality"
},
  "geometry": {"coordinates":[29.9165,37.56071],"type":"Point"}
}