{
  "type": "Feature",
  "properties": {
    "gn:admin1_code":"65",
    "gn:asciiname":"Hasanbey",
    "gn:country_code":"TR",
    "gn:dem":2104,
    "gn:feature_class":"P",
    "gn:feature_code":"PPL",
    "gn:name":"Hasanbey",
    "gn:population":0,
    "gn:timezone":"Europe/Istanbul",
    "iso:country":"TR",
    "name:tur_x_preferred":[
        "Hasanbey"
    ],
    "wof:name":"Hasanbey",
    "wof:placetype":"locality"
},
  "geometry": {"coordinates":[43.99625,37.91513],"type":"Point"}
}