{
  "type": "Feature",
  "properties": {
    "gn:admin1_code":"49.0",
    "gn:asciiname":"Karakutuk",
    "gn:country_code":"TR",
    "gn:dem":1316,
    "gn:feature_class":"P",
    "gn:feature_code":"PPL",
    "gn:name":"Karak\u00fct\u00fck",
    "gn:population":0,
    "gn:timezone":"Europe/Istanbul",
    "iso:country":"TR",
    "name:tur_x_preferred":[
        "Karak\u00fct\u00fck"
    ],
    "wof:name":"Karakutuk",
    "wof:placetype":"locality"
},
  "geometry": {"coordinates":[41.76734,38.63509000000001],"type":"Point"}
}