{
  "type": "Feature",
  "properties": {
    "gn:admin1_code":"24",
    "gn:asciiname":"Uluyamac",
    "gn:country_code":"TR",
    "gn:dem":1421,
    "gn:feature_class":"P",
    "gn:feature_code":"PPL",
    "gn:name":"Uluyama\u00e7",
    "gn:population":0,
    "gn:timezone":"Europe/Istanbul",
    "iso:country":"TR",
    "name:und_x_variant":[
        "Sergevil",
        "Uluyama\u00e7"
    ],
    "wof:name":"Uluyamac",
    "wof:placetype":"locality"
},
  "geometry": {"coordinates":[38.7028,39.41846],"type":"Point"}
}