{
  "type": "Feature",
  "properties": {
    "gn:admin1_code":"46",
    "gn:asciiname":"Alkayaoglu",
    "gn:country_code":"TR",
    "gn:dem":1863,
    "gn:feature_class":"P",
    "gn:feature_code":"PPL",
    "gn:name":"Alkayao\u011flu",
    "gn:population":0,
    "gn:timezone":"Europe/Istanbul",
    "iso:country":"TR",
    "wof:name":"Alkayaoglu",
    "wof:placetype":"locality"
},
  "geometry": {"coordinates":[37.09005,38.53433],"type":"Point"}
}