{
  "type": "Feature",
  "properties": {
    "gn:admin1_code":"32.0",
    "gn:asciiname":"Sarisu",
    "gn:country_code":"TR",
    "gn:dem":126,
    "gn:feature_class":"P",
    "gn:feature_code":"PPL",
    "gn:name":"Sar\u0131su",
    "gn:population":0,
    "gn:timezone":"Europe/Istanbul",
    "iso:country":"TR",
    "wof:name":"Sarisu",
    "wof:placetype":"locality"
},
  "geometry": {"coordinates":[33.18375,36.13838],"type":"Point"}
}