{
  "type": "Feature",
  "properties": {
    "gn:admin1_code":"13.0",
    "gn:asciiname":"Dogrular",
    "gn:country_code":"TR",
    "gn:dem":1785,
    "gn:feature_class":"P",
    "gn:feature_code":"PPL",
    "gn:name":"Do\u011frular",
    "gn:population":0,
    "gn:timezone":"Europe/Istanbul",
    "iso:country":"TR",
    "name:tur_x_preferred":[
        "Do\u011frular"
    ],
    "wof:name":"Dogrular",
    "wof:placetype":"locality"
},
  "geometry": {"coordinates":[42.56736,38.12613],"type":"Point"}
}