{
  "type": "Feature",
  "properties": {
    "gn:admin1_code":"11.0",
    "gn:asciiname":"Buyukelmali",
    "gn:country_code":"TR",
    "gn:dem":839,
    "gn:feature_class":"P",
    "gn:feature_code":"PPL",
    "gn:name":"B\u00fcy\u00fckelmal\u0131",
    "gn:population":0,
    "gn:timezone":"Europe/Istanbul",
    "iso:country":"TR",
    "name:und_x_variant":[
        "Elmal\u0131kebir",
        "B\u00fcy\u00fckelmal\u0131"
    ],
    "wof:name":"Buyukelmali",
    "wof:placetype":"locality"
},
  "geometry": {"coordinates":[29.79922,40.05381],"type":"Point"}
}