{
  "type": "Feature",
  "properties": {
    "gn:admin1_code":"4.0",
    "gn:asciiname":"Yenitelceker",
    "gn:country_code":"TR",
    "gn:dem":1561,
    "gn:feature_class":"P",
    "gn:feature_code":"PPL",
    "gn:name":"Yenitel\u00e7eker",
    "gn:population":0,
    "gn:timezone":"Europe/Istanbul",
    "iso:country":"TR",
    "wof:name":"Yenitelceker",
    "wof:placetype":"locality"
},
  "geometry": {"coordinates":[44.24951,39.48266],"type":"Point"}
}