{
  "type": "Feature",
  "properties": {
    "gn:admin1_code":"21.0",
    "gn:asciiname":"Karpuzlu",
    "gn:country_code":"TR",
    "gn:dem":601,
    "gn:feature_class":"P",
    "gn:feature_code":"PPL",
    "gn:name":"Karpuzlu",
    "gn:population":0,
    "gn:timezone":"Europe/Istanbul",
    "iso:country":"TR",
    "name:ceb_x_preferred":[
        "Karpuzlu"
    ],
    "name:deu_x_preferred":[
        "Karpuzlu"
    ],
    "name:epo_x_preferred":[
        "Karpuzlu"
    ],
    "name:fas_x_preferred":[
        "\u06a9\u0627\u0631\u067e\u0648\u0632\u0644\u0648"
    ],
    "name:fra_x_preferred":[
        "Karpuzlu"
    ],
    "name:lbe_x_preferred":[
        "\u041a\u044a\u0430\u0440\u043f\u0443\u0437\u043b\u0443"
    ],
    "name:mrj_x_preferred":[
        "\u041a\u0430\u0440\u043f\u0443\u0437\u043b\u0443"
    ],
    "name:msa_x_preferred":[
        "Karpuzlu"
    ],
    "name:nld_x_preferred":[
        "Karpuzlu"
    ],
    "name:nor_x_preferred":[
        "Karpuzlu"
    ],
    "name:swa_x_preferred":[
        "Karpuzlu"
    ],
    "name:tur_x_preferred":[
        "\u00c7ankl\u0131"
    ],
    "name:tur_x_variant":[
        "\u00c7ar\u0131kl\u0131",
        "Karpuzlu"
    ],
    "name:urd_x_preferred":[
        "\u06a9\u0627\u0631\u067e\u0648\u0632\u0644\u0648"
    ],
    "name:vie_x_preferred":[
        "Karpuzlu"
    ],
    "wof:name":"Karpuzlu",
    "wof:placetype":"locality"
},
  "geometry": {"coordinates":[40.23452,37.83838],"type":"Point"}
}