{
  "type": "Feature",
  "properties": {
    "gn:admin1_code":"21.0",
    "gn:asciiname":"Karpuzlu",
    "gn:country_code":"TR",
    "gn:dem":601,
    "gn:feature_class":"P",
    "gn:feature_code":"PPL",
    "gn:name":"Karpuzlu",
    "gn:population":0,
    "gn:timezone":"Europe/Istanbul",
    "iso:country":"TR",
    "name:tur_x_preferred":[
        "\u00c7ankl\u0131"
    ],
    "name:tur_x_variant":[
        "\u00c7ar\u0131kl\u0131"
    ],
    "wof:name":"Karpuzlu",
    "wof:placetype":"locality"
},
  "geometry": {"coordinates":[40.23452,37.83838],"type":"Point"}
}