{
  "type": "Feature",
  "properties": {
    "gn:admin1_code":"53.0",
    "gn:asciiname":"Akkaya",
    "gn:cc2":"TR",
    "gn:country_code":"TR",
    "gn:dem":381,
    "gn:feature_class":"P",
    "gn:feature_code":"PPL",
    "gn:name":"Akkaya",
    "gn:population":0,
    "gn:timezone":"Europe/Istanbul",
    "iso:country":"TR",
    "name:deu_x_preferred":[
        "Akkaya"
    ],
    "name:tur_x_preferred":[
        "Akkaya"
    ],
    "name:und_x_variant":[
        "Pilarcivat",
        "Pilergivat"
    ],
    "wof:name":"Akkaya",
    "wof:placetype":"locality"
},
  "geometry": {"coordinates":[41.01972,41.12889000000001],"type":"Point"}
}