{
  "type": "Feature",
  "properties": {
    "gn:admin1_code":"20",
    "gn:asciiname":"Cindere",
    "gn:cc2":"TR",
    "gn:country_code":"TR",
    "gn:dem":762,
    "gn:feature_class":"P",
    "gn:feature_code":"PPL",
    "gn:name":"\u00c7indere",
    "gn:population":0,
    "gn:timezone":"Europe/Istanbul",
    "iso:country":"TR",
    "name:und_x_variant":[
        "\u00c7indire",
        "\u00c7indere"
    ],
    "wof:name":"Cindere",
    "wof:placetype":"locality"
},
  "geometry": {"coordinates":[29.06306,38.10722],"type":"Point"}
}