{
  "type": "Feature",
  "properties": {
    "gn:admin1_code":"22.0",
    "gn:asciiname":"Ceribasi",
    "gn:country_code":"TR",
    "gn:dem":65,
    "gn:feature_class":"P",
    "gn:feature_code":"PPL",
    "gn:name":"\u00c7eriba\u015f\u0131",
    "gn:population":0,
    "gn:timezone":"Europe/Istanbul",
    "iso:country":"TR",
    "name:und_x_variant":[
        "Cerikba\u015f\u0131",
        "\u00c7eriba\u015f\u0131"
    ],
    "wof:name":"Ceribasi",
    "wof:placetype":"locality"
},
  "geometry": {"coordinates":[26.25545,40.66455],"type":"Point"}
}