{
  "type": "Feature",
  "properties": {
    "gn:admin1_code":"78",
    "gn:asciiname":"Islihisar",
    "gn:country_code":"TR",
    "gn:dem":1023,
    "gn:feature_class":"P",
    "gn:feature_code":"PPL",
    "gn:name":"\u0130slihisar",
    "gn:population":0,
    "gn:timezone":"Europe/Istanbul",
    "iso:country":"TR",
    "name:tur_x_preferred":[
        "\u0130slihisar"
    ],
    "wof:name":"Islihisar",
    "wof:placetype":"locality"
},
  "geometry": {"coordinates":[33.01342,37.36472],"type":"Point"}
}