{
  "type": "Feature",
  "properties": {
    "gn:admin1_code":"07",
    "gn:asciiname":"Savrun",
    "gn:country_code":"TR",
    "gn:dem":321,
    "gn:feature_class":"P",
    "gn:feature_code":"PPL",
    "gn:name":"Savrun",
    "gn:population":0,
    "gn:timezone":"Europe/Istanbul",
    "iso:country":"TR",
    "name:und_x_variant":[
        "G\u00fcz\u00f6ren"
    ],
    "wof:name":"Savrun",
    "wof:placetype":"locality"
},
  "geometry": {"coordinates":[30.31179,36.46282],"type":"Point"}
}