{
  "type": "Feature",
  "properties": {
    "gn:admin1_code":"35",
    "gn:asciiname":"Belevi",
    "gn:country_code":"TR",
    "gn:dem":15,
    "gn:feature_class":"P",
    "gn:feature_code":"PPL",
    "gn:name":"Belevi",
    "gn:population":2174,
    "gn:timezone":"Europe/Istanbul",
    "iso:country":"TR",
    "name:ceb_x_preferred":[
        "Belevi"
    ],
    "name:tur_x_preferred":[
        "Belevi"
    ],
    "name:vie_x_preferred":[
        "Belevi"
    ],
    "wof:name":"Belevi",
    "wof:placetype":"locality",
    "wof:population":2174
},
  "geometry": {"coordinates":[27.45028,38.015],"type":"Point"}
}