{
  "type": "Feature",
  "properties": {
    "gn:admin1_code":"37.0",
    "gn:asciiname":"Araklar",
    "gn:country_code":"TR",
    "gn:dem":541,
    "gn:feature_class":"P",
    "gn:feature_code":"PPL",
    "gn:name":"Araklar",
    "gn:population":0,
    "gn:timezone":"Europe/Istanbul",
    "iso:country":"TR",
    "wof:name":"Araklar",
    "wof:placetype":"locality"
},
  "geometry": {"coordinates":[34.25,41.56667],"type":"Point"}
}