{
  "type": "Feature",
  "properties": {
    "gn:admin1_code":"60.0",
    "gn:asciiname":"Bakimli",
    "gn:cc2":"TR",
    "gn:country_code":"TR",
    "gn:dem":1205,
    "gn:feature_class":"P",
    "gn:feature_code":"PPL",
    "gn:name":"Bak\u0131ml\u0131",
    "gn:population":0,
    "gn:timezone":"Europe/Istanbul",
    "iso:country":"TR",
    "name:und_x_variant":[
        "Mamu",
        "Mamo",
        "Bak\u0131ml\u0131"
    ],
    "wof:name":"Bakimli",
    "wof:placetype":"locality"
},
  "geometry": {"coordinates":[36.80611,40.37639],"type":"Point"}
}