{
  "type": "Feature",
  "properties": {
    "gn:admin1_code":"20",
    "gn:asciiname":"Tekkekoy",
    "gn:country_code":"TR",
    "gn:dem":1140,
    "gn:feature_class":"P",
    "gn:feature_code":"PPL",
    "gn:name":"Tekkek\u00f6y",
    "gn:population":0,
    "gn:timezone":"Europe/Istanbul",
    "iso:country":"TR",
    "name:tur_x_preferred":[
        "Tekkek\u00f6y"
    ],
    "wof:name":"Tekkekoy",
    "wof:placetype":"locality"
},
  "geometry": {"coordinates":[29.16434000000001,37.61582],"type":"Point"}
}