{
  "type": "Feature",
  "properties": {
    "gn:admin1_code":"69.0",
    "gn:asciiname":"Camli",
    "gn:country_code":"TR",
    "gn:dem":1354,
    "gn:feature_class":"P",
    "gn:feature_code":"PPL",
    "gn:name":"\u00c7aml\u0131",
    "gn:population":0,
    "gn:timezone":"Europe/Istanbul",
    "iso:country":"TR",
    "name:tur_x_preferred":[
        "\u00c7aml\u0131"
    ],
    "name:und_x_variant":[
        "\u00c7aml\u0131k\u00f6y"
    ],
    "wof:name":"Camli",
    "wof:placetype":"locality"
},
  "geometry": {"coordinates":[39.48227,40.40296],"type":"Point"}
}