{
  "type": "Feature",
  "properties": {
    "gn:admin1_code":"75",
    "gn:asciiname":"Yenipinar",
    "gn:country_code":"TR",
    "gn:dem":1549,
    "gn:feature_class":"P",
    "gn:feature_code":"PPL",
    "gn:name":"Yenip\u0131nar",
    "gn:population":0,
    "gn:timezone":"Europe/Istanbul",
    "iso:country":"TR",
    "wof:name":"Yenipinar",
    "wof:placetype":"locality"
},
  "geometry": {"coordinates":[34.25318,38.17279],"type":"Point"}
}