{
  "type": "Feature",
  "properties": {
    "gn:admin1_code":"76.0",
    "gn:asciiname":"Gyundyuk",
    "gn:country_code":"TR",
    "gn:dem":865,
    "gn:feature_class":"P",
    "gn:feature_code":"PPL",
    "gn:name":"Gyundyuk",
    "gn:population":0,
    "gn:timezone":"Europe/Istanbul",
    "iso:country":"TR",
    "name:tur_x_preferred":[
        "Ye\u015fil\u00f6z"
    ],
    "name:und_x_variant":[
        "G\u00fcnd\u00fck"
    ],
    "wof:name":"Gyundyuk",
    "wof:placetype":"locality"
},
  "geometry": {"coordinates":[41.20277,37.96851],"type":"Point"}
}