{
  "type": "Feature",
  "properties": {
    "gn:admin1_code":"52.0",
    "gn:asciiname":"Yemisli",
    "gn:country_code":"TR",
    "gn:dem":234,
    "gn:feature_class":"P",
    "gn:feature_code":"PPL",
    "gn:name":"Yemi\u015fli",
    "gn:population":0,
    "gn:timezone":"Europe/Istanbul",
    "iso:country":"TR",
    "name:tur_x_preferred":[
        "Yemi\u015fli"
    ],
    "wof:name":"Yemisli",
    "wof:placetype":"locality"
},
  "geometry": {"coordinates":[37.8525,40.94139000000001],"type":"Point"}
}