{
  "type": "Feature",
  "properties": {
    "gn:admin1_code":"58",
    "gn:asciiname":"Kumyurt",
    "gn:country_code":"TR",
    "gn:dem":1251,
    "gn:feature_class":"P",
    "gn:feature_code":"PPL",
    "gn:name":"Kumyurt",
    "gn:population":0,
    "gn:timezone":"Europe/Istanbul",
    "iso:country":"TR",
    "wof:name":"Kumyurt",
    "wof:placetype":"locality"
},
  "geometry": {"coordinates":[36.83333,39.71667],"type":"Point"}
}