{
  "type": "Feature",
  "properties": {
    "gn:admin1_code":"26.0",
    "gn:asciiname":"Akcaoren",
    "gn:country_code":"TR",
    "gn:dem":646,
    "gn:feature_class":"P",
    "gn:feature_code":"PPL",
    "gn:name":"Ak\u00e7a\u00f6ren",
    "gn:population":0,
    "gn:timezone":"Europe/Istanbul",
    "iso:country":"TR",
    "wof:name":"Akcaoren",
    "wof:placetype":"locality"
},
  "geometry": {"coordinates":[31.31543,40.03484],"type":"Point"}
}