{
  "type": "Feature",
  "properties": {
    "gn:admin1_code":"81",
    "gn:asciiname":"Gazi",
    "gn:country_code":"TR",
    "gn:dem":45,
    "gn:feature_class":"P",
    "gn:feature_code":"PPL",
    "gn:name":"Gazi",
    "gn:population":0,
    "gn:timezone":"Europe/Istanbul",
    "iso:country":"TR",
    "name:und_x_variant":[
        "Gazik\u00f6y",
        "Gazi"
    ],
    "wof:name":"Gazi",
    "wof:placetype":"locality"
},
  "geometry": {"coordinates":[35.85239,37.29578],"type":"Point"}
}