{
  "type": "Feature",
  "properties": {
    "gn:admin1_code":"25",
    "gn:asciiname":"Dervisali",
    "gn:country_code":"TR",
    "gn:dem":2021,
    "gn:feature_class":"P",
    "gn:feature_code":"PPL",
    "gn:name":"Dervi\u015fali",
    "gn:population":0,
    "gn:timezone":"Europe/Istanbul",
    "iso:country":"TR",
    "name:tur_x_preferred":[
        "Dervi\u015fali"
    ],
    "name:und_x_variant":[
        "Devri\u015fali",
        "\u0130brahimkomu"
    ],
    "wof:name":"Dervisali",
    "wof:placetype":"locality"
},
  "geometry": {"coordinates":[41.63901,39.4673],"type":"Point"}
}