{
  "type": "Feature",
  "properties": {
    "gn:admin1_code":"16",
    "gn:asciiname":"Kapaklioluk",
    "gn:country_code":"TR",
    "gn:dem":313,
    "gn:feature_class":"P",
    "gn:feature_code":"PPL",
    "gn:name":"Kapakl\u0131oluk",
    "gn:population":0,
    "gn:timezone":"Europe/Istanbul",
    "iso:country":"TR",
    "name:tur_x_preferred":[
        "Kapakl\u0131o\u011flu"
    ],
    "name:tur_x_variant":[
        "Kapakl\u0131oluk"
    ],
    "wof:name":"Kapaklioluk",
    "wof:placetype":"locality"
},
  "geometry": {"coordinates":[28.49882,40.01621],"type":"Point"}
}