{
  "type": "Feature",
  "properties": {
    "gn:admin1_code":"17",
    "gn:asciiname":"Turkmenli",
    "gn:country_code":"TR",
    "gn:dem":99,
    "gn:feature_class":"P",
    "gn:feature_code":"PPL",
    "gn:name":"T\u00fcrkmenli",
    "gn:population":0,
    "gn:timezone":"Europe/Istanbul",
    "iso:country":"TR",
    "wof:name":"Turkmenli",
    "wof:placetype":"locality"
},
  "geometry": {"coordinates":[26.49667,39.76667],"type":"Point"}
}