{
  "type": "Feature",
  "properties": {
    "gn:admin1_code":"66",
    "gn:asciiname":"Ibrahimhacili",
    "gn:country_code":"TR",
    "gn:dem":977,
    "gn:feature_class":"P",
    "gn:feature_code":"PPL",
    "gn:name":"\u0130brahimhac\u0131l\u0131",
    "gn:population":0,
    "gn:timezone":"Europe/Istanbul",
    "iso:country":"TR",
    "wof:name":"Ibrahimhacili",
    "wof:placetype":"locality"
},
  "geometry": {"coordinates":[34.9515,39.45614000000001],"type":"Point"}
}