{
  "type": "Feature",
  "properties": {
    "gn:admin1_code":"85",
    "gn:asciiname":"Kocak",
    "gn:country_code":"TR",
    "gn:dem":587,
    "gn:feature_class":"P",
    "gn:feature_code":"PPL",
    "gn:name":"Kocak",
    "gn:population":0,
    "gn:timezone":"Europe/Istanbul",
    "iso:country":"TR",
    "wof:name":"Kocak",
    "wof:placetype":"locality"
},
  "geometry": {"coordinates":[32.05888,41.20094],"type":"Point"}
}