{
  "type": "Feature",
  "properties": {
    "gn:admin1_code":"78",
    "gn:asciiname":"Muratdede",
    "gn:country_code":"TR",
    "gn:dem":1264,
    "gn:feature_class":"P",
    "gn:feature_code":"PPL",
    "gn:name":"Muratdede",
    "gn:population":0,
    "gn:timezone":"Europe/Istanbul",
    "iso:country":"TR",
    "name:und_x_variant":[
        "Masdat",
        "Mastat",
        "Muratdede"
    ],
    "wof:name":"Muratdede",
    "wof:placetype":"locality"
},
  "geometry": {"coordinates":[32.82402,37.15969000000001],"type":"Point"}
}