{
  "type": "Feature",
  "properties": {
    "gn:admin1_code":"21",
    "gn:asciiname":"Pekmezciler",
    "gn:country_code":"TR",
    "gn:dem":893,
    "gn:feature_class":"P",
    "gn:feature_code":"PPL",
    "gn:name":"Pekmezciler",
    "gn:population":0,
    "gn:timezone":"Europe/Istanbul",
    "iso:country":"TR",
    "name:tur_x_preferred":[
        "Pekmezciler"
    ],
    "wof:name":"Pekmezciler",
    "wof:placetype":"locality"
},
  "geometry": {"coordinates":[40.06618,38.30799],"type":"Point"}
}