{
  "type": "Feature",
  "properties": {
    "gn:admin1_code":"74",
    "gn:asciiname":"Celikli",
    "gn:country_code":"TR",
    "gn:dem":1007,
    "gn:feature_class":"P",
    "gn:feature_code":"PPL",
    "gn:name":"\u00c7elikli",
    "gn:population":0,
    "gn:timezone":"Europe/Istanbul",
    "iso:country":"TR",
    "name:und_x_variant":[
        "\u00c7elikli",
        "Bak\u0131n"
    ],
    "wof:name":"Celikli",
    "wof:placetype":"locality"
},
  "geometry": {"coordinates":[41.65884000000001,38.0888],"type":"Point"}
}