{
  "type": "Feature",
  "properties": {
    "gn:admin1_code":"21",
    "gn:asciiname":"Guzelbasi",
    "gn:country_code":"TR",
    "gn:dem":838,
    "gn:feature_class":"P",
    "gn:feature_code":"PPL",
    "gn:name":"G\u00fczelba\u015f\u0131",
    "gn:population":0,
    "gn:timezone":"Europe/Istanbul",
    "iso:country":"TR",
    "name:und_x_variant":[
        "G\u00fczelba\u015f\u0131",
        "G\u00fcnova"
    ],
    "wof:name":"Guzelbasi",
    "wof:placetype":"locality"
},
  "geometry": {"coordinates":[39.54674,37.94787],"type":"Point"}
}