{
  "type": "Feature",
  "properties": {
    "gn:admin1_code":"88",
    "gn:asciiname":"Yukari Carikci",
    "gn:country_code":"TR",
    "gn:dem":874,
    "gn:feature_class":"P",
    "gn:feature_code":"PPL",
    "gn:name":"Yukar\u0131 \u00c7ar\u0131k\u00e7\u0131",
    "gn:population":0,
    "gn:timezone":"Europe/Istanbul",
    "iso:country":"TR",
    "name:tur_x_preferred":[
        "Yukar\u0131 \u00c7ar\u0131k\u00e7\u0131"
    ],
    "name:und_x_variant":[
        "Yukar\u0131\u00e7ar\u0131k\u00e7\u0131"
    ],
    "wof:name":"Yukari Carikci",
    "wof:placetype":"locality"
},
  "geometry": {"coordinates":[43.93755,39.96256],"type":"Point"}
}