{
  "type": "Feature",
  "properties": {
    "gn:admin1_code":"37.0",
    "gn:asciiname":"Mencugez",
    "gn:country_code":"TR",
    "gn:dem":1003,
    "gn:feature_class":"P",
    "gn:feature_code":"PPL",
    "gn:name":"Menc\u00fc\u011fez",
    "gn:population":0,
    "gn:timezone":"Europe/Istanbul",
    "iso:country":"TR",
    "wof:name":"Mencugez",
    "wof:placetype":"locality"
},
  "geometry": {"coordinates":[34.10332,41.39372],"type":"Point"}
}