{
  "type": "Feature",
  "properties": {
    "gn:admin1_code":"43",
    "gn:asciiname":"Sapcidede",
    "gn:country_code":"TR",
    "gn:dem":1026,
    "gn:feature_class":"P",
    "gn:feature_code":"PPL",
    "gn:name":"\u015eap\u00e7\u0131dede",
    "gn:population":0,
    "gn:timezone":"Europe/Istanbul",
    "iso:country":"TR",
    "name:tur_x_preferred":[
        "\u015eap\u00e7\u0131dede"
    ],
    "wof:name":"Sapcidede",
    "wof:placetype":"locality"
},
  "geometry": {"coordinates":[29.34037,39.57758],"type":"Point"}
}