{
  "type": "Feature",
  "properties": {
    "gn:country":"TR",
    "gn:fcode":"PPL",
    "gn:pop":0,
    "iso:country":"TR",
    "name:ara_x_preferred":[
        "\u0633\u0643\u0627\u0631\u064a\u0627"
    ],
    "name:bel_x_preferred":[
        "\u0421\u0430\u043a\u0430\u0440\u2019\u044f"
    ],
    "name:ceb_x_preferred":[
        "Sakarya"
    ],
    "name:ces_x_preferred":[
        "Sakarya"
    ],
    "name:deu_x_preferred":[
        "Sakarya"
    ],
    "name:diq_x_preferred":[
        "Sakarya"
    ],
    "name:fra_x_preferred":[
        "Sakarya"
    ],
    "name:heb_x_preferred":[
        "\u05e1\u05e7\u05e8\u05d9\u05d4"
    ],
    "name:msa_x_preferred":[
        "Sakarya"
    ],
    "name:nld_x_preferred":[
        "Sakarya"
    ],
    "name:pol_x_preferred":[
        "Sakarya"
    ],
    "name:por_x_preferred":[
        "Sacaria"
    ],
    "name:rus_x_preferred":[
        "\u0421\u0430\u043a\u0430\u0440\u044c\u044f"
    ],
    "name:slk_x_preferred":[
        "Sakarya"
    ],
    "name:swa_x_preferred":[
        "Sakarya"
    ],
    "name:tur_x_preferred":[
        "Sakarya"
    ],
    "name:unk_x_variant":[
        "K\u0131rm\u0131t"
    ],
    "qs:name":"Sakarya",
    "qs:name_adm0":"Turkey",
    "qs:name_adm1":"Adana",
    "qs:photos":5,
    "qs:photos_1k":1,
    "qs:photos_9k":1,
    "qs:photos_9r":1,
    "qs:photos_all":5,
    "qs:photos_sr":1,
    "qs:placetype":"Suburb",
    "qs:pop_sr":"0",
    "wd:wordcount":77,
    "wof:name":"Sakarya",
    "wof:placetype":"neighbourhood",
    "wof:population":0
},
  "geometry": {"coordinates":[35.68843,37.17852],"type":"Point"}
}