{
  "type": "Feature",
  "properties": {
    "gn:admin1_code":"13",
    "gn:asciiname":"Develik",
    "gn:country_code":"TR",
    "gn:dem":2002,
    "gn:feature_class":"P",
    "gn:feature_code":"PPL",
    "gn:name":"Develik",
    "gn:population":0,
    "gn:timezone":"Europe/Istanbul",
    "iso:country":"TR",
    "name:tur_x_preferred":[
        "Develik"
    ],
    "wof:name":"Develik",
    "wof:placetype":"locality"
},
  "geometry": {"coordinates":[42.51402,38.90566],"type":"Point"}
}