{
  "type": "Feature",
  "properties": {
    "gn:admin1_code":"55",
    "gn:asciiname":"Fener",
    "gn:country_code":"TR",
    "gn:dem":7,
    "gn:feature_class":"P",
    "gn:feature_code":"PPL",
    "gn:name":"Fener",
    "gn:population":0,
    "gn:timezone":"Europe/Istanbul",
    "iso:country":"TR",
    "name:afr_x_preferred":[
        "Fener"
    ],
    "name:ara_x_preferred":[
        "\u0641\u0646\u0627\u0631"
    ],
    "name:bul_x_preferred":[
        "\u0424\u0435\u043d\u0435\u0440"
    ],
    "name:cat_x_preferred":[
        "Fener"
    ],
    "name:deu_x_preferred":[
        "Fener"
    ],
    "name:ell_x_preferred":[
        "\u03a6\u03b1\u03bd\u03ac\u03c1\u03b9"
    ],
    "name:fas_x_preferred":[
        "\u0641\u0646\u0627\u0631"
    ],
    "name:fra_x_preferred":[
        "Phanar"
    ],
    "name:ind_x_preferred":[
        "Fener"
    ],
    "name:ita_x_preferred":[
        "Fener"
    ],
    "name:lat_x_preferred":[
        "Phanarium"
    ],
    "name:nld_x_preferred":[
        "Fener"
    ],
    "name:nor_x_preferred":[
        "Fener"
    ],
    "name:pol_x_preferred":[
        "Fanarion"
    ],
    "name:por_x_preferred":[
        "Fener"
    ],
    "name:ron_x_preferred":[
        "Fanar"
    ],
    "name:rus_x_preferred":[
        "\u0424\u0435\u043d\u0435\u0440"
    ],
    "name:spa_x_preferred":[
        "Fanar"
    ],
    "name:tur_x_preferred":[
        "Fener"
    ],
    "name:ukr_x_preferred":[
        "\u0424\u0435\u043d\u0435\u0440"
    ],
    "name:zho_x_preferred":[
        "\u82ac\u5185\u5c14"
    ],
    "wof:name":"Fener",
    "wof:placetype":"locality"
},
  "geometry": {"coordinates":[35.9068,41.68417],"type":"Point"}
}