{
  "type": "Feature",
  "properties": {
    "gn:admin1_code":"55",
    "gn:asciiname":"Fener",
    "gn:country_code":"TR",
    "gn:dem":7,
    "gn:feature_class":"P",
    "gn:feature_code":"PPL",
    "gn:name":"Fener",
    "gn:population":0,
    "gn:timezone":"Europe/Istanbul",
    "iso:country":"TR",
    "name:tur_x_preferred":[
        "Fener"
    ],
    "wof:name":"Fener",
    "wof:placetype":"locality"
},
  "geometry": {"coordinates":[35.9068,41.68417],"type":"Point"}
}