{
  "type": "Feature",
  "properties": {
    "gn:admin1_code":"34.0",
    "gn:asciiname":"Aydinlar",
    "gn:country_code":"TR",
    "gn:dem":191,
    "gn:feature_class":"P",
    "gn:feature_code":"PPL",
    "gn:name":"Ayd\u0131nlar",
    "gn:population":0,
    "gn:timezone":"Europe/Istanbul",
    "iso:country":"TR",
    "name:und_x_variant":[
        "Alaton",
        "Ayd\u0131nlar"
    ],
    "wof:name":"Aydinlar",
    "wof:placetype":"locality"
},
  "geometry": {"coordinates":[28.20394000000001,41.37473],"type":"Point"}
}