{
  "type": "Feature",
  "properties": {
    "gn:admin1_code":"28.0",
    "gn:asciiname":"Bahceli",
    "gn:country_code":"TR",
    "gn:dem":302,
    "gn:feature_class":"P",
    "gn:feature_code":"PPL",
    "gn:name":"Bah\u00e7eli",
    "gn:population":0,
    "gn:timezone":"Europe/Istanbul",
    "iso:country":"TR",
    "name:und_x_variant":[
        "Nusratl\u0131gegraz",
        "Gegraz",
        "Nusrakl\u0131",
        "Nusrall\u0131",
        "Bah\u00e7eli"
    ],
    "wof:name":"Bahceli",
    "wof:placetype":"locality"
},
  "geometry": {"coordinates":[38.45978,40.73122],"type":"Point"}
}