{
  "type": "Feature",
  "properties": {
    "gn:admin1_code":"12",
    "gn:asciiname":"Maltepe",
    "gn:country_code":"TR",
    "gn:dem":1604,
    "gn:feature_class":"P",
    "gn:feature_code":"PPL",
    "gn:name":"Maltepe",
    "gn:population":0,
    "gn:timezone":"Europe/Istanbul",
    "iso:country":"TR",
    "name:tur_x_preferred":[
        "Maltepe"
    ],
    "wof:name":"Maltepe",
    "wof:placetype":"locality"
},
  "geometry": {"coordinates":[40.48314,39.34093],"type":"Point"}
}