{
  "type": "Feature",
  "properties": {
    "gn:admin1_code":"43",
    "gn:asciiname":"Yavu",
    "gn:country_code":"TR",
    "gn:dem":773,
    "gn:feature_class":"P",
    "gn:feature_code":"PPL",
    "gn:name":"Yavu",
    "gn:population":0,
    "gn:timezone":"Europe/Istanbul",
    "iso:country":"TR",
    "name:tur_x_preferred":[
        "Yavu"
    ],
    "name:und_x_variant":[
        "Yavik\u00f6y"
    ],
    "wof:name":"Yavu",
    "wof:placetype":"locality"
},
  "geometry": {"coordinates":[28.95584,39.31897],"type":"Point"}
}