{
  "type": "Feature",
  "properties": {
    "gn:admin1_code":"82.0",
    "gn:asciiname":"Haydar",
    "gn:country_code":"TR",
    "gn:dem":862,
    "gn:feature_class":"P",
    "gn:feature_code":"PPL",
    "gn:name":"Haydar",
    "gn:population":0,
    "gn:timezone":"Europe/Istanbul",
    "iso:country":"TR",
    "wof:name":"Haydar",
    "wof:placetype":"locality"
},
  "geometry": {"coordinates":[33.94412,40.5656],"type":"Point"}
}