{
  "type": "Feature",
  "properties": {
    "gn:admin1_code":"16.0",
    "gn:asciiname":"Hayirlar",
    "gn:country_code":"TR",
    "gn:dem":20,
    "gn:feature_class":"P",
    "gn:feature_code":"PPL",
    "gn:name":"Hay\u0131rlar",
    "gn:population":0,
    "gn:timezone":"Europe/Istanbul",
    "iso:country":"TR",
    "name:tur_x_preferred":[
        "Hay\u0131rlar"
    ],
    "wof:name":"Hayirlar",
    "wof:placetype":"locality"
},
  "geometry": {"coordinates":[28.44728,40.28969],"type":"Point"}
}