{
  "type": "Feature",
  "properties": {
    "gn:admin1_code":"48",
    "gn:asciiname":"Ulas",
    "gn:country_code":"TR",
    "gn:dem":211,
    "gn:feature_class":"P",
    "gn:feature_code":"PPL",
    "gn:name":"Ula\u015f",
    "gn:population":0,
    "gn:timezone":"Europe/Istanbul",
    "iso:country":"TR",
    "name:tur_x_preferred":[
        "Ula\u015f"
    ],
    "wof:name":"Ulas",
    "wof:placetype":"locality"
},
  "geometry": {"coordinates":[27.83169,37.21541],"type":"Point"}
}