{
  "type": "Feature",
  "properties": {
    "gn:admin1_code":"8.0",
    "gn:asciiname":"Besagil",
    "gn:country_code":"TR",
    "gn:dem":623,
    "gn:feature_class":"P",
    "gn:feature_code":"PPL",
    "gn:name":"Be\u015fa\u011f\u0131l",
    "gn:population":0,
    "gn:timezone":"Europe/Istanbul",
    "iso:country":"TR",
    "name:und_x_variant":[
        "Ba\u015fa\u011f\u0131l",
        "Be\u015fa\u011f\u0131l"
    ],
    "wof:name":"Besagil",
    "wof:placetype":"locality"
},
  "geometry": {"coordinates":[41.80596,41.264],"type":"Point"}
}