{
  "type": "Feature",
  "properties": {
    "gn:admin1_code":"4.0",
    "gn:asciiname":"Duzagil",
    "gn:country_code":"TR",
    "gn:dem":1827,
    "gn:feature_class":"P",
    "gn:feature_code":"PPL",
    "gn:name":"D\u00fcza\u011f\u0131l",
    "gn:population":0,
    "gn:timezone":"Europe/Istanbul",
    "iso:country":"TR",
    "name:tur_x_preferred":[
        "D\u00fcza\u011f\u0131l"
    ],
    "wof:name":"Duzagil",
    "wof:placetype":"locality"
},
  "geometry": {"coordinates":[42.59304,39.73106],"type":"Point"}
}