{
  "type": "Feature",
  "properties": {
    "gn:admin1_code":"19.0",
    "gn:asciiname":"Halilar",
    "gn:country_code":"TR",
    "gn:dem":412,
    "gn:feature_class":"P",
    "gn:feature_code":"PPL",
    "gn:name":"Hal\u0131lar",
    "gn:population":0,
    "gn:timezone":"Europe/Istanbul",
    "iso:country":"TR",
    "wof:name":"Halilar",
    "wof:placetype":"locality"
},
  "geometry": {"coordinates":[34.43647,41.13569],"type":"Point"}
}