{
  "type": "Feature",
  "properties": {
    "gn:admin1_code":"70",
    "gn:asciiname":"Akyildiz",
    "gn:country_code":"TR",
    "gn:dem":2013,
    "gn:feature_class":"P",
    "gn:feature_code":"PPL",
    "gn:name":"Aky\u0131ldiz",
    "gn:population":0,
    "gn:timezone":"Europe/Istanbul",
    "iso:country":"TR",
    "name:und_x_variant":[
        "Rireni",
        "Aky\u0131ldiz",
        "Zereni"
    ],
    "wof:name":"Akyildiz",
    "wof:placetype":"locality"
},
  "geometry": {"coordinates":[44.03526,37.73638],"type":"Point"}
}