{
  "type": "Feature",
  "properties": {
    "iso:country":"TR",
    "name:eng_x_preferred":[
        "Topagaci"
    ],
    "name:tur_x_preferred":[
        "Topa\u011fac\u0131"
    ],
    "wof:name":"Topagaci",
    "wof:placetype":"neighbourhood"
},
  "geometry": {"coordinates":[29.10537722240814,41.04956708522594],"type":"Point"}
}