{
  "type": "Feature",
  "properties": {
    "gn:admin1_code":"14.0",
    "gn:asciiname":"Aktaskurtlar",
    "gn:country_code":"TR",
    "gn:dem":1226,
    "gn:feature_class":"P",
    "gn:feature_code":"PPL",
    "gn:name":"Akta\u015fkurtlar",
    "gn:population":0,
    "gn:timezone":"Europe/Istanbul",
    "iso:country":"TR",
    "wof:name":"Aktaskurtlar",
    "wof:placetype":"locality"
},
  "geometry": {"coordinates":[32.51899,40.84304],"type":"Point"}
}