{
  "type": "Feature",
  "properties": {
    "gn:admin1_code":"23",
    "gn:asciiname":"Tohumlu",
    "gn:country_code":"TR",
    "gn:dem":1196,
    "gn:feature_class":"P",
    "gn:feature_code":"PPL",
    "gn:name":"Tohumlu",
    "gn:population":0,
    "gn:timezone":"Europe/Istanbul",
    "iso:country":"TR",
    "name:tur_x_preferred":[
        "Tohumlu"
    ],
    "wof:name":"Tohumlu",
    "wof:placetype":"locality"
},
  "geometry": {"coordinates":[39.12145,38.56649],"type":"Point"}
}