{
  "type": "Feature",
  "properties": {
    "gn:admin1_code":"25",
    "gn:asciiname":"Yesilkaya",
    "gn:country_code":"TR",
    "gn:dem":1872,
    "gn:feature_class":"P",
    "gn:feature_code":"PPL",
    "gn:name":"Ye\u015filkaya",
    "gn:population":0,
    "gn:timezone":"Europe/Istanbul",
    "iso:country":"TR",
    "name:tur_x_preferred":[
        "Ye\u015filkaya"
    ],
    "wof:name":"Yesilkaya",
    "wof:placetype":"locality"
},
  "geometry": {"coordinates":[42.33141,40.54916],"type":"Point"}
}