{
  "type": "Feature",
  "properties": {
    "gn:admin1_code":"21",
    "gn:asciiname":"Mullafiyat",
    "gn:cc2":"TR",
    "gn:country_code":"TR",
    "gn:dem":650,
    "gn:feature_class":"P",
    "gn:feature_code":"PPL",
    "gn:name":"M\u00fcllafiyat",
    "gn:population":0,
    "gn:timezone":"Europe/Istanbul",
    "iso:country":"TR",
    "name:tur_x_preferred":[
        "M\u00fcllafiyat"
    ],
    "name:und_x_variant":[
        "Myullafiyat",
        "Mollafiyat",
        "Mullafeyat",
        "Mollafeyyat"
    ],
    "wof:name":"Mullafiyat",
    "wof:placetype":"locality"
},
  "geometry": {"coordinates":[40.66889000000001,37.95361],"type":"Point"}
}