{
  "type": "Feature",
  "properties": {
    "gn:admin1_code":"14.0",
    "gn:asciiname":"Yeniakcakavak",
    "gn:country_code":"TR",
    "gn:dem":699,
    "gn:feature_class":"P",
    "gn:feature_code":"PPL",
    "gn:name":"Yeniak\u00e7akavak",
    "gn:population":0,
    "gn:timezone":"Europe/Istanbul",
    "iso:country":"TR",
    "name:ceb_x_preferred":[
        "Yeniak\u00e7akavak"
    ],
    "name:msa_x_preferred":[
        "Yeniak\u00e7akavak"
    ],
    "name:tur_x_preferred":[
        "Yeniak\u00e7akavak"
    ],
    "name:urd_x_preferred":[
        "\u06cc\u0646\u0627\u06a9\u0633\u0627\u06a9\u0648\u06a9"
    ],
    "name:vie_x_preferred":[
        "Yeniak\u00e7akavak"
    ],
    "wof:name":"Yeniakcakavak",
    "wof:placetype":"locality"
},
  "geometry": {"coordinates":[31.68542,40.75095],"type":"Point"}
}