{
  "type": "Feature",
  "properties": {
    "gn:admin1_code":"14.0",
    "gn:asciiname":"Yeniakcakavak",
    "gn:country_code":"TR",
    "gn:dem":699,
    "gn:feature_class":"P",
    "gn:feature_code":"PPL",
    "gn:name":"Yeniak\u00e7akavak",
    "gn:population":0,
    "gn:timezone":"Europe/Istanbul",
    "iso:country":"TR",
    "name:und_x_variant":[
        "Yeniak\u00e7akavak"
    ],
    "wof:name":"Yeniakcakavak",
    "wof:placetype":"locality"
},
  "geometry": {"coordinates":[31.68542,40.75095],"type":"Point"}
}