{
  "type": "Feature",
  "properties": {
    "gn:admin1_code":"93",
    "gn:asciiname":"Arabaci",
    "gn:country_code":"TR",
    "gn:dem":88,
    "gn:feature_class":"P",
    "gn:feature_code":"PPL",
    "gn:name":"Arabac\u0131",
    "gn:population":0,
    "gn:timezone":"Europe/Istanbul",
    "iso:country":"TR",
    "wof:name":"Arabaci",
    "wof:placetype":"locality"
},
  "geometry": {"coordinates":[31.09182,41.04644],"type":"Point"}
}