{
  "type": "Feature",
  "properties": {
    "gn:admin1_code":"07",
    "gn:asciiname":"Inalkoy",
    "gn:cc2":"TR",
    "gn:country_code":"TR",
    "gn:dem":421,
    "gn:feature_class":"P",
    "gn:feature_code":"PPL",
    "gn:name":"\u0130nalk\u00f6y",
    "gn:population":0,
    "gn:timezone":"Europe/Istanbul",
    "iso:country":"TR",
    "name:und_x_variant":[
        "\u0130nal",
        "\u0130nalk\u00f6y"
    ],
    "wof:name":"Inalkoy",
    "wof:placetype":"locality"
},
  "geometry": {"coordinates":[32.53972,36.13417000000001],"type":"Point"}
}