{
  "type": "Feature",
  "properties": {
    "gn:admin1_code":"79.0",
    "gn:asciiname":"Karakoseli",
    "gn:country_code":"TR",
    "gn:dem":615,
    "gn:feature_class":"P",
    "gn:feature_code":"PPL",
    "gn:name":"Karak\u00f6seli",
    "gn:population":0,
    "gn:timezone":"Europe/Istanbul",
    "iso:country":"TR",
    "name:und_x_variant":[
        "Karak\u00f6se",
        "Karak\u00f6seli"
    ],
    "wof:name":"Karakoseli",
    "wof:placetype":"locality"
},
  "geometry": {"coordinates":[34.05187,40.17798],"type":"Point"}
}