{
  "type": "Feature",
  "properties": {
    "gn:admin1_code":"89",
    "gn:asciiname":"Bulduk",
    "gn:country_code":"TR",
    "gn:dem":1219,
    "gn:feature_class":"P",
    "gn:feature_code":"PPL",
    "gn:name":"Bulduk",
    "gn:population":0,
    "gn:timezone":"Europe/Istanbul",
    "iso:country":"TR",
    "name:aze_x_preferred":[
        "Bulduq"
    ],
    "name:nld_x_preferred":[
        "Bulduk"
    ],
    "name:tur_x_preferred":[
        "Bulduk"
    ],
    "wof:name":"Bulduk",
    "wof:placetype":"locality"
},
  "geometry": {"coordinates":[32.56658,40.83999],"type":"Point"}
}