{
  "type": "Feature",
  "properties": {
    "gn:admin1_code":"89.0",
    "gn:asciiname":"Deresoplan",
    "gn:country_code":"TR",
    "gn:dem":1116,
    "gn:feature_class":"P",
    "gn:feature_code":"PPL",
    "gn:name":"Deresoplan",
    "gn:population":0,
    "gn:timezone":"Europe/Istanbul",
    "iso:country":"TR",
    "wof:name":"Deresoplan",
    "wof:placetype":"locality"
},
  "geometry": {"coordinates":[32.55114,40.87053],"type":"Point"}
}