{
  "type": "Feature",
  "properties": {
    "gn:admin1_code":"37.0",
    "gn:asciiname":"Koccagiz",
    "gn:country_code":"TR",
    "gn:dem":1313,
    "gn:feature_class":"P",
    "gn:feature_code":"PPL",
    "gn:name":"Ko\u00e7ca\u011f\u0131z",
    "gn:population":0,
    "gn:timezone":"Europe/Istanbul",
    "iso:country":"TR",
    "wof:name":"Koccagiz",
    "wof:placetype":"locality"
},
  "geometry": {"coordinates":[34.29176,41.68962],"type":"Point"}
}