{
  "type": "Feature",
  "properties": {
    "gn:admin1_code":"32",
    "gn:asciiname":"Celtikci",
    "gn:country_code":"TR",
    "gn:dem":32,
    "gn:feature_class":"P",
    "gn:feature_code":"PPL",
    "gn:name":"\u00c7eltik\u00e7i",
    "gn:population":0,
    "gn:timezone":"Europe/Istanbul",
    "iso:country":"TR",
    "name:tur_x_preferred":[
        "\u00c7eltik\u00e7i"
    ],
    "wof:name":"Celtikci",
    "wof:placetype":"locality"
},
  "geometry": {"coordinates":[32.84829000000001,36.09114],"type":"Point"}
}