{
  "type": "Feature",
  "properties": {
    "gn:admin1_code":"71",
    "gn:asciiname":"Baslamis",
    "gn:country_code":"TR",
    "gn:dem":1512,
    "gn:feature_class":"P",
    "gn:feature_code":"PPL",
    "gn:name":"Ba\u015flam\u0131\u015f",
    "gn:population":0,
    "gn:timezone":"Europe/Istanbul",
    "iso:country":"TR",
    "wof:name":"Baslamis",
    "wof:placetype":"locality"
},
  "geometry": {"coordinates":[31.66432,37.98582],"type":"Point"}
}