{
  "type": "Feature",
  "properties": {
    "gn:admin1_code":"71",
    "gn:asciiname":"Bagyurdu",
    "gn:country_code":"TR",
    "gn:dem":1341,
    "gn:feature_class":"P",
    "gn:feature_code":"PPL",
    "gn:name":"Ba\u011fyurdu",
    "gn:population":0,
    "gn:timezone":"Europe/Istanbul",
    "iso:country":"TR",
    "name:und_x_variant":[
        "Ba\u011fyurdu",
        "Sobran"
    ],
    "wof:name":"Bagyurdu",
    "wof:placetype":"locality"
},
  "geometry": {"coordinates":[32.21038,37.27461],"type":"Point"}
}