{
  "type": "Feature",
  "properties": {
    "gn:admin1_code":"19.0",
    "gn:asciiname":"Senemoglu",
    "gn:country_code":"TR",
    "gn:dem":576,
    "gn:feature_class":"P",
    "gn:feature_code":"PPL",
    "gn:name":"Senemo\u011flu",
    "gn:population":0,
    "gn:timezone":"Europe/Istanbul",
    "iso:country":"TR",
    "name:tur_x_preferred":[
        "Senemo\u011flu"
    ],
    "name:tur_x_variant":[
        "Sirkeo\u011fluk\u00f6y",
        "Sirko\u011flu",
        "Sirkeo\u011flu"
    ],
    "wof:name":"Senemoglu",
    "wof:placetype":"locality"
},
  "geometry": {"coordinates":[35.35942,40.31665],"type":"Point"}
}