{
  "type": "Feature",
  "properties": {
    "iso:country":"TR",
    "name:eng_x_preferred":[
        "Eyup Sultan"
    ],
    "name:tur_x_preferred":[
        "Ey\u00fcp Sultan"
    ],
    "wof:name":"Eyup Sultan",
    "wof:placetype":"neighbourhood"
},
  "geometry": {"coordinates":[29.22362595394156,40.98341892039884],"type":"Point"}
}