{
  "type": "Feature",
  "properties": {
    "gn:admin1_code":"35",
    "gn:asciiname":"Payamli",
    "gn:country_code":"TR",
    "gn:dem":514,
    "gn:feature_class":"P",
    "gn:feature_code":"PPL",
    "gn:name":"Payaml\u0131",
    "gn:population":0,
    "gn:timezone":"Europe/Istanbul",
    "iso:country":"TR",
    "name:tur_x_preferred":[
        "Payaml\u0131"
    ],
    "wof:name":"Payamli",
    "wof:placetype":"locality"
},
  "geometry": {"coordinates":[26.92532000000001,38.31807],"type":"Point"}
}