{
  "type": "Feature",
  "properties": {
    "gn:admin1_code":"81",
    "gn:asciiname":"Buyuk Burhaniye",
    "gn:country_code":"TR",
    "gn:dem":65,
    "gn:feature_class":"P",
    "gn:feature_code":"PPL",
    "gn:name":"B\u00fcy\u00fck Burhaniye",
    "gn:population":0,
    "gn:timezone":"Europe/Istanbul",
    "iso:country":"TR",
    "name:tur_x_preferred":[
        "\u015eahmeran"
    ],
    "name:und_x_variant":[
        "Yilankaleks",
        "Y\u0131lankale K\u00f6y\u00fc",
        "Y\u0131lankale",
        "B\u00fcy\u00fck Burhaniye"
    ],
    "wof:name":"Buyuk Burhaniye",
    "wof:placetype":"locality"
},
  "geometry": {"coordinates":[35.68872,37.05513],"type":"Point"}
}