{
  "type": "Feature",
  "properties": {
    "gn:admin1_code":"81",
    "gn:asciiname":"Buyuk Burhaniye",
    "gn:country_code":"TR",
    "gn:dem":65,
    "gn:feature_class":"P",
    "gn:feature_code":"PPL",
    "gn:name":"B\u00fcy\u00fck Burhaniye",
    "gn:population":0,
    "gn:timezone":"Europe/Istanbul",
    "iso:country":"TR",
    "name:deu_x_preferred":[
        "Y\u0131lankale"
    ],
    "name:ell_x_preferred":[
        "\u0393\u03b9\u03bb\u03ac\u03bd\u03ba\u03b1\u03bb\u03b5"
    ],
    "name:hye_x_preferred":[
        "\u053c\u0587\u0578\u0576\u056f\u056c\u0561"
    ],
    "name:hyw_x_preferred":[
        "\u053c\u0565\u0582\u0578\u0576\u056f\u056c\u0561"
    ],
    "name:mkd_x_preferred":[
        "\u0417\u0430\u043c\u043e\u043a \u043d\u0430 \u0437\u043c\u0438\u0438"
    ],
    "name:tur_x_preferred":[
        "\u015eahmeran"
    ],
    "name:tur_x_variant":[
        "Y\u0131lankale"
    ],
    "name:und_x_variant":[
        "Yilankaleks",
        "Y\u0131lankale K\u00f6y\u00fc",
        "B\u00fcy\u00fck Burhaniye"
    ],
    "wof:name":"Buyuk Burhaniye",
    "wof:placetype":"locality"
},
  "geometry": {"coordinates":[35.68872,37.05513],"type":"Point"}
}