{
  "type": "Feature",
  "properties": {
    "gn:admin1_code":"14.0",
    "gn:asciiname":"Geris",
    "gn:country_code":"TR",
    "gn:dem":1016,
    "gn:feature_class":"P",
    "gn:feature_code":"PPL",
    "gn:name":"Geri\u015f",
    "gn:population":0,
    "gn:timezone":"Europe/Istanbul",
    "iso:country":"TR",
    "name:und_x_variant":[
        "Keri\u015f",
        "Geri\u015f"
    ],
    "wof:name":"Geris",
    "wof:placetype":"locality"
},
  "geometry": {"coordinates":[31.81296,40.36447],"type":"Point"}
}