{
  "type": "Feature",
  "properties": {
    "gn:admin1_code":"21",
    "gn:asciiname":"Yaprakkoy",
    "gn:country_code":"TR",
    "gn:dem":1073,
    "gn:feature_class":"P",
    "gn:feature_code":"PPL",
    "gn:name":"Yaprakk\u00f6y",
    "gn:population":0,
    "gn:timezone":"Europe/Istanbul",
    "iso:country":"TR",
    "name:tur_x_preferred":[
        "Yaprakk\u00f6y"
    ],
    "name:und_x_variant":[
        "Yaprak"
    ],
    "wof:name":"Yaprakkoy",
    "wof:placetype":"locality"
},
  "geometry": {"coordinates":[40.74517,38.48789],"type":"Point"}
}