{
  "type": "Feature",
  "properties": {
    "gn:admin1_code":"46",
    "gn:asciiname":"Gaziler",
    "gn:country_code":"TR",
    "gn:dem":1284,
    "gn:feature_class":"P",
    "gn:feature_code":"PPL",
    "gn:name":"Gaziler",
    "gn:population":0,
    "gn:timezone":"Europe/Istanbul",
    "iso:country":"TR",
    "name:tur_x_preferred":[
        "Gaziler"
    ],
    "wof:name":"Gaziler",
    "wof:placetype":"locality"
},
  "geometry": {"coordinates":[37.09783,37.99635],"type":"Point"}
}