{
  "type": "Feature",
  "properties": {
    "gn:admin1_code":"68.0",
    "gn:asciiname":"Kocalar",
    "gn:country_code":"TR",
    "gn:dem":1067,
    "gn:feature_class":"P",
    "gn:feature_code":"PPL",
    "gn:name":"Kocalar",
    "gn:population":0,
    "gn:timezone":"Europe/Istanbul",
    "iso:country":"TR",
    "wof:name":"Kocalar",
    "wof:placetype":"locality"
},
  "geometry": {"coordinates":[32.52422,40.30756],"type":"Point"}
}