{
  "type": "Feature",
  "properties": {
    "gn:admin1_code":"28.0",
    "gn:asciiname":"Alidede",
    "gn:country_code":"TR",
    "gn:dem":535,
    "gn:feature_class":"P",
    "gn:feature_code":"PPL",
    "gn:name":"Alidede",
    "gn:population":0,
    "gn:timezone":"Europe/Istanbul",
    "iso:country":"TR",
    "name:und_x_variant":[
        "\u015e\u0131hl\u0131"
    ],
    "wof:name":"Alidede",
    "wof:placetype":"locality"
},
  "geometry": {"coordinates":[38.11262,40.89223],"type":"Point"}
}