{
  "type": "Feature",
  "properties": {
    "gn:admin1_code":"63",
    "gn:asciiname":"Kislak",
    "gn:country_code":"TR",
    "gn:dem":1098,
    "gn:feature_class":"P",
    "gn:feature_code":"PPL",
    "gn:name":"K\u0131\u015flak",
    "gn:population":0,
    "gn:timezone":"Europe/Istanbul",
    "iso:country":"TR",
    "name:tur_x_preferred":[
        "K\u0131\u015flak"
    ],
    "wof:name":"Kislak",
    "wof:placetype":"locality"
},
  "geometry": {"coordinates":[39.61667,37.75],"type":"Point"}
}