{
  "type": "Feature",
  "properties": {
    "gn:admin1_code":"65.0",
    "gn:asciiname":"Asagi Dalli",
    "gn:country_code":"TR",
    "gn:dem":2298,
    "gn:feature_class":"P",
    "gn:feature_code":"PPL",
    "gn:name":"A\u015fa\u011f\u0131 Dall\u0131",
    "gn:population":0,
    "gn:timezone":"Europe/Istanbul",
    "iso:country":"TR",
    "name:tur_x_preferred":[
        "A\u015fa\u011f\u0131 Dall\u0131"
    ],
    "wof:name":"Asagi Dalli",
    "wof:placetype":"locality"
},
  "geometry": {"coordinates":[43.86922,37.85067],"type":"Point"}
}