{
  "type": "Feature",
  "properties": {
    "gn:admin1_code":"57.0",
    "gn:asciiname":"Cove",
    "gn:country_code":"TR",
    "gn:dem":868,
    "gn:feature_class":"P",
    "gn:feature_code":"PPL",
    "gn:name":"\u00c7\u00f6ve",
    "gn:population":0,
    "gn:timezone":"Europe/Istanbul",
    "iso:country":"TR",
    "name:ara_x_preferred":[
        "\u0634\u0631\u0645"
    ],
    "name:aze_x_preferred":[
        "Buxta"
    ],
    "name:bel_x_preferred":[
        "\u0411\u0443\u0445\u0442\u0430"
    ],
    "name:deu_x_preferred":[
        "Cala"
    ],
    "name:est_x_preferred":[
        "Abajas"
    ],
    "name:fas_x_preferred":[
        "\u062e\u0644\u06cc\u062c \u06a9\u0648\u0686\u06a9"
    ],
    "name:glg_x_preferred":[
        "Enseada"
    ],
    "name:grn_x_preferred":[
        "Paranakua"
    ],
    "name:hye_x_preferred":[
        "\u053d\u0578\u0580\u0577"
    ],
    "name:isl_x_preferred":[
        "Vogur"
    ],
    "name:kat_x_preferred":[
        "\u10e3\u10d1\u10d4"
    ],
    "name:kaz_x_preferred":[
        "\u0411\u0443\u043c\u0430"
    ],
    "name:kbd_x_preferred":[
        "\u0425\u044b\u043b\u044a\u044d"
    ],
    "name:kur_x_preferred":[
        "Kendavik"
    ],
    "name:lat_x_preferred":[
        "Crecca"
    ],
    "name:lit_x_preferred":[
        "U\u017eut\u0117kis"
    ],
    "name:mal_x_preferred":[
        "\u0d15\u0d4b\u0d35\u0d4d"
    ],
    "name:mhr_x_preferred":[
        "\u0411\u0443\u0445\u0442\u043e"
    ],
    "name:nld_x_preferred":[
        "Cala"
    ],
    "name:por_x_preferred":[
        "Enseada"
    ],
    "name:rus_x_preferred":[
        "\u0411\u0443\u0445\u0442\u0430"
    ],
    "name:spa_x_preferred":[
        "Ensenada"
    ],
    "name:sun_x_preferred":[
        "Tanjung"
    ],
    "name:tat_x_preferred":[
        "\u0411\u0443\u0445\u0442\u0430"
    ],
    "name:ukr_x_preferred":[
        "\u0411\u0443\u0445\u0442\u0430"
    ],
    "name:und_x_variant":[
        "\u00c7\u00f6\u011fe",
        "\u00c7\u00f6vek\u00f6y",
        "\u00c7\u00f6ve"
    ],
    "name:uzb_x_preferred":[
        "Buxta"
    ],
    "name:vie_x_preferred":[
        "V\u1ecbnh nh\u1ecf"
    ],
    "wof:name":"Cove",
    "wof:placetype":"locality"
},
  "geometry": {"coordinates":[35.24595,41.31907],"type":"Point"}
}