{
  "type": "Feature",
  "properties": {
    "gn:admin1_code":"57.0",
    "gn:asciiname":"Cove",
    "gn:country_code":"TR",
    "gn:dem":868,
    "gn:feature_class":"P",
    "gn:feature_code":"PPL",
    "gn:name":"\u00c7\u00f6ve",
    "gn:population":0,
    "gn:timezone":"Europe/Istanbul",
    "iso:country":"TR",
    "name:und_x_variant":[
        "\u00c7\u00f6\u011fe",
        "\u00c7\u00f6vek\u00f6y",
        "\u00c7\u00f6ve"
    ],
    "wof:name":"Cove",
    "wof:placetype":"locality"
},
  "geometry": {"coordinates":[35.24595,41.31907],"type":"Point"}
}