{
  "type": "Feature",
  "properties": {
    "gn:country":"TR",
    "gn:fcode":"PPLA2",
    "gn:pop":15919,
    "iso:country":"TR",
    "name:dut_x_preferred":[
        "Senirkent"
    ],
    "name:eng_x_preferred":[
        "Senirkent"
    ],
    "name:fre_x_preferred":[
        "Senirkent"
    ],
    "name:ger_x_preferred":[
        "Senirkent"
    ],
    "name:ita_x_preferred":[
        "Distretto di Senirkent"
    ],
    "name:lit_x_preferred":[
        "Senirkentas"
    ],
    "name:may_x_preferred":[
        "Senirkent"
    ],
    "name:mrj_x_preferred":[
        "\u0421\u0435\u043d\u0438\u0440\u043a\u0435\u043d\u0442"
    ],
    "name:nan_x_preferred":[
        "Senirkent"
    ],
    "name:rus_x_preferred":[
        "\u0421\u0435\u043d\u0438\u0440\u043a\u0435\u043d\u0442"
    ],
    "name:swa_x_preferred":[
        "Senirkent"
    ],
    "name:tur_x_preferred":[
        "Senirkent"
    ],
    "name:unk_x_variant":[
        "Senikent"
    ],
    "name:urd_x_preferred":[
        "\u0633\u06cc\u0646\u06cc\u0631\u0642\u0646\u062f"
    ],
    "name:vie_x_preferred":[
        "Senirkent"
    ],
    "qs:name":"Senirkent",
    "qs:photos_9r":0,
    "qs:photos_sr":0,
    "qs:pop_sr":"6",
    "wd:wordcount":75,
    "wof:name":"Senirkent",
    "wof:placetype":"locality",
    "wof:population":15919
},
  "geometry": {"coordinates":[30.54861,38.10444],"type":"Point"}
}