{
  "type": "Feature",
  "properties": {
    "gn:admin1_code":"54.0",
    "gn:asciiname":"Sekiharman",
    "gn:country_code":"TR",
    "gn:dem":540,
    "gn:feature_class":"P",
    "gn:feature_code":"PPL",
    "gn:name":"Sekiharman",
    "gn:population":0,
    "gn:timezone":"Europe/Istanbul",
    "iso:country":"TR",
    "name:und_x_variant":[
        "Sakiharman",
        "Sekiharman"
    ],
    "wof:name":"Sekiharman",
    "wof:placetype":"locality"
},
  "geometry": {"coordinates":[30.16579,40.38914000000001],"type":"Point"}
}