{
  "type": "Feature",
  "properties": {
    "gn:admin1_code":"38",
    "gn:asciiname":"Obruk",
    "gn:country_code":"TR",
    "gn:dem":1465,
    "gn:feature_class":"P",
    "gn:feature_code":"PPL",
    "gn:name":"Obruk",
    "gn:population":0,
    "gn:timezone":"Europe/Istanbul",
    "iso:country":"TR",
    "wof:name":"Obruk",
    "wof:placetype":"locality"
},
  "geometry": {"coordinates":[35.59157000000001,39.00827],"type":"Point"}
}