{
  "type": "Feature",
  "properties": {
    "gn:admin1_code":"15",
    "gn:asciiname":"Yuregil",
    "gn:country_code":"TR",
    "gn:dem":842,
    "gn:feature_class":"P",
    "gn:feature_code":"PPL",
    "gn:name":"Y\u00fcre\u011fil",
    "gn:population":0,
    "gn:timezone":"Europe/Istanbul",
    "iso:country":"TR",
    "wof:name":"Yuregil",
    "wof:placetype":"locality"
},
  "geometry": {"coordinates":[30.33333,37.36667],"type":"Point"}
}