{
  "type": "Feature",
  "properties": {
    "gn:admin1_code":"62",
    "gn:asciiname":"Ayazpinar",
    "gn:country_code":"TR",
    "gn:dem":927,
    "gn:feature_class":"P",
    "gn:feature_code":"PPL",
    "gn:name":"Ayazp\u0131nar",
    "gn:population":0,
    "gn:timezone":"Europe/Istanbul",
    "iso:country":"TR",
    "name:und_x_variant":[
        "Titinik",
        "Titinin",
        "Ayazp\u0131nar"
    ],
    "wof:name":"Ayazpinar",
    "wof:placetype":"locality"
},
  "geometry": {"coordinates":[39.05868,38.92564],"type":"Point"}
}