{
  "type": "Feature",
  "properties": {
    "gn:admin1_code":"76",
    "gn:asciiname":"Yigitler",
    "gn:country_code":"TR",
    "gn:dem":1295,
    "gn:feature_class":"P",
    "gn:feature_code":"PPL",
    "gn:name":"Yi\u011fitler",
    "gn:population":0,
    "gn:timezone":"Europe/Istanbul",
    "iso:country":"TR",
    "name:tur_x_preferred":[
        "Yi\u011fitli"
    ],
    "name:tur_x_variant":[
        "Yi\u011fitler"
    ],
    "wof:name":"Yigitler",
    "wof:placetype":"locality"
},
  "geometry": {"coordinates":[41.42392,38.37856],"type":"Point"}
}