{
  "type": "Feature",
  "properties": {
    "gn:admin1_code":"60.0",
    "gn:asciiname":"Taslihuyuk",
    "gn:country_code":"TR",
    "gn:dem":567,
    "gn:feature_class":"P",
    "gn:feature_code":"PPL",
    "gn:name":"Ta\u015fl\u0131h\u00fcy\u00fck",
    "gn:population":0,
    "gn:timezone":"Europe/Istanbul",
    "iso:country":"TR",
    "name:und_x_variant":[
        "Ta\u015fl\u0131h\u00fcy\u00fck K\u00f6y\u00fc",
        "Ta\u015fh\u00fcy\u00fck",
        "Ta\u015fl\u0131h\u00fcy\u00fck"
    ],
    "wof:name":"Taslihuyuk",
    "wof:placetype":"locality"
},
  "geometry": {"coordinates":[36.07855,40.27872],"type":"Point"}
}