{
  "type": "Feature",
  "properties": {
    "gn:admin1_code":"49",
    "gn:asciiname":"Dallioz",
    "gn:country_code":"TR",
    "gn:dem":1438,
    "gn:feature_class":"P",
    "gn:feature_code":"PPL",
    "gn:name":"Dall\u0131\u00f6z",
    "gn:population":0,
    "gn:timezone":"Europe/Istanbul",
    "iso:country":"TR",
    "name:tur_x_preferred":[
        "Dall\u0131\u00f6z"
    ],
    "name:und_x_variant":[
        "Dal\u0131\u00f6z"
    ],
    "wof:name":"Dallioz",
    "wof:placetype":"locality"
},
  "geometry": {"coordinates":[41.38293,39.14477],"type":"Point"}
}