{
  "type": "Feature",
  "properties": {
    "gn:admin1_code":"85",
    "gn:asciiname":"Deliler",
    "gn:country_code":"TR",
    "gn:dem":89,
    "gn:feature_class":"P",
    "gn:feature_code":"PPL",
    "gn:name":"Deliler",
    "gn:population":0,
    "gn:timezone":"Europe/Istanbul",
    "iso:country":"TR",
    "wof:name":"Deliler",
    "wof:placetype":"locality"
},
  "geometry": {"coordinates":[31.54534,41.2833],"type":"Point"}
}