{
  "type": "Feature",
  "properties": {
    "gn:admin1_code":"10",
    "gn:asciiname":"Yolcupinar",
    "gn:country_code":"TR",
    "gn:dem":559,
    "gn:feature_class":"P",
    "gn:feature_code":"PPL",
    "gn:name":"Yolcup\u0131nar",
    "gn:population":0,
    "gn:timezone":"Europe/Istanbul",
    "iso:country":"TR",
    "name:tur_x_preferred":[
        "Yolcup\u0131nar"
    ],
    "wof:name":"Yolcupinar",
    "wof:placetype":"locality"
},
  "geometry": {"coordinates":[27.54885,39.47231],"type":"Point"}
}