{
  "type": "Feature",
  "properties": {
    "gn:admin1_code":"25.0",
    "gn:asciiname":"Pokot",
    "gn:cc2":"TR",
    "gn:country_code":"TR",
    "gn:dem":1665,
    "gn:feature_class":"P",
    "gn:feature_code":"PPL",
    "gn:name":"Pokot",
    "gn:population":0,
    "gn:timezone":"Europe/Istanbul",
    "iso:country":"TR",
    "name:und_x_variant":[
        "Pokut Mahallesi"
    ],
    "wof:name":"Pokot",
    "wof:placetype":"locality"
},
  "geometry": {"coordinates":[41.01892,40.65968],"type":"Point"}
}