{
  "type": "Feature",
  "properties": {
    "gn:admin1_code":"60.0",
    "gn:asciiname":"Gokcesuleymanli",
    "gn:country_code":"TR",
    "gn:dem":1362,
    "gn:feature_class":"P",
    "gn:feature_code":"PPL",
    "gn:name":"G\u00f6k\u00e7es\u00fcleymanl\u0131",
    "gn:population":0,
    "gn:timezone":"Europe/Istanbul",
    "iso:country":"TR",
    "wof:name":"Gokcesuleymanli",
    "wof:placetype":"locality"
},
  "geometry": {"coordinates":[37.52268,40.49314],"type":"Point"}
}