{
  "type": "Feature",
  "properties": {
    "gn:admin1_code":"71",
    "gn:asciiname":"Uzerlitkepeyayla",
    "gn:country_code":"TR",
    "gn:dem":931,
    "gn:feature_class":"P",
    "gn:feature_code":"PPL",
    "gn:name":"\u00dczerlitkepeyayla",
    "gn:population":0,
    "gn:timezone":"Europe/Istanbul",
    "iso:country":"TR",
    "wof:name":"Uzerlitkepeyayla",
    "wof:placetype":"locality"
},
  "geometry": {"coordinates":[32.99375999999999,38.71899000000001],"type":"Point"}
}