{
  "type": "Feature",
  "properties": {
    "gn:admin1_code":"72",
    "gn:asciiname":"Sagiran",
    "gn:cc2":"TR",
    "gn:country_code":"TR",
    "gn:dem":663,
    "gn:feature_class":"P",
    "gn:feature_code":"PPL",
    "gn:name":"Sagiran",
    "gn:population":0,
    "gn:timezone":"Europe/Istanbul",
    "iso:country":"TR",
    "name:tur_x_preferred":[
        "Sagiran"
    ],
    "name:und_x_variant":[
        "S\u0131\u011f\u0131ran",
        "Sekiran"
    ],
    "wof:name":"Sagiran",
    "wof:placetype":"locality"
},
  "geometry": {"coordinates":[40.69333,37.70306],"type":"Point"}
}