{
  "type": "Feature",
  "properties": {
    "gn:admin1_code":"68.0",
    "gn:asciiname":"Karadana",
    "gn:country_code":"TR",
    "gn:dem":1050,
    "gn:feature_class":"P",
    "gn:feature_code":"PPL",
    "gn:name":"Karadana",
    "gn:population":0,
    "gn:timezone":"Europe/Istanbul",
    "iso:country":"TR",
    "wof:name":"Karadana",
    "wof:placetype":"locality"
},
  "geometry": {"coordinates":[33.15784,40.25801],"type":"Point"}
}