{
  "type": "Feature",
  "properties": {
    "gn:admin1_code":"12",
    "gn:asciiname":"Dolucay",
    "gn:country_code":"TR",
    "gn:dem":1697,
    "gn:feature_class":"P",
    "gn:feature_code":"PPL",
    "gn:name":"Dolu\u00e7ay",
    "gn:population":0,
    "gn:timezone":"Europe/Istanbul",
    "iso:country":"TR",
    "name:tur_x_preferred":[
        "Dolu\u00e7ay"
    ],
    "wof:name":"Dolucay",
    "wof:placetype":"locality"
},
  "geometry": {"coordinates":[40.63046,39.15727],"type":"Point"}
}