{
  "type": "Feature",
  "properties": {
    "gn:admin1_code":"21.0",
    "gn:asciiname":"Cirali",
    "gn:country_code":"TR",
    "gn:dem":897,
    "gn:feature_class":"P",
    "gn:feature_code":"PPL",
    "gn:name":"\u00c7\u0131ral\u0131",
    "gn:population":0,
    "gn:timezone":"Europe/Istanbul",
    "iso:country":"TR",
    "name:tur_x_preferred":[
        "\u00c7\u0131ral\u0131"
    ],
    "name:und_x_variant":[
        "\u00c7\u0131rali"
    ],
    "wof:name":"Cirali",
    "wof:placetype":"locality"
},
  "geometry": {"coordinates":[40.79651,38.4353],"type":"Point"}
}