{
  "type": "Feature",
  "properties": {
    "gn:country":"TR",
    "gn:fcode":"PPL",
    "gn:population":155,
    "iso:country":"TR",
    "name:kat_x_preferred":[
        "\u10e3\u10da\u10e3\u10d3\u10d8\u10e3\u10d6\u10d8"
    ],
    "name:msa_x_preferred":[
        "Uludyuz"
    ],
    "name:und_x_variant":[
        "Kharat"
    ],
    "qs:name":"Ulud\u00fcz",
    "qs:photos_9r":0,
    "qs:photos_sr":0,
    "qs:pop_sr":"1",
    "wd:wordcount":39,
    "wof:name":"Ulud\u00fcz",
    "wof:placetype":"locality",
    "wof:population":155
},
  "geometry": {"coordinates":[38.52111,36.95028],"type":"Point"}
}