{
  "type": "Feature",
  "properties": {
    "gn:admin1_code":"89",
    "gn:asciiname":"Dere",
    "gn:country_code":"TR",
    "gn:dem":404,
    "gn:feature_class":"P",
    "gn:feature_code":"PPL",
    "gn:name":"Dere",
    "gn:population":0,
    "gn:timezone":"Europe/Istanbul",
    "iso:country":"TR",
    "wof:name":"Dere",
    "wof:placetype":"locality"
},
  "geometry": {"coordinates":[32.33647,41.25389000000001],"type":"Point"}
}