{
  "type": "Feature",
  "properties": {
    "gn:admin1_code":"58.0",
    "gn:asciiname":"Gohertas",
    "gn:country_code":"TR",
    "gn:dem":1523,
    "gn:feature_class":"P",
    "gn:feature_code":"PPL",
    "gn:name":"G\u00f6herta\u015f",
    "gn:population":0,
    "gn:timezone":"Europe/Istanbul",
    "iso:country":"TR",
    "name:und_x_variant":[
        "G\u00fcherta\u015f",
        "G\u00fcheta\u015f K\u00f6y\u00fc",
        "G\u00f6herta\u015f"
    ],
    "wof:name":"Gohertas",
    "wof:placetype":"locality"
},
  "geometry": {"coordinates":[37.6968,40.1367],"type":"Point"}
}