{
  "type": "Feature",
  "properties": {
    "gn:admin1_code":"81",
    "gn:asciiname":"Camlarca",
    "gn:country_code":"TR",
    "gn:dem":1092,
    "gn:feature_class":"P",
    "gn:feature_code":"PPL",
    "gn:name":"\u00c7amlarca",
    "gn:population":0,
    "gn:timezone":"Europe/Istanbul",
    "iso:country":"TR",
    "name:deu_x_preferred":[
        "\u00c7amlarca"
    ],
    "name:msa_x_preferred":[
        "\u00c7amlarca"
    ],
    "name:tur_x_preferred":[
        "\u00c7amlarca"
    ],
    "name:vie_x_preferred":[
        "\u00c7amlarca"
    ],
    "wof:name":"Camlarca",
    "wof:placetype":"locality"
},
  "geometry": {"coordinates":[36.02036,37.70419],"type":"Point"}
}