{
  "type": "Feature",
  "properties": {
    "gn:admin1_code":"63",
    "gn:asciiname":"Bakirtas",
    "gn:country_code":"TR",
    "gn:dem":408,
    "gn:feature_class":"P",
    "gn:feature_code":"PPL",
    "gn:name":"Bak\u0131rta\u015f",
    "gn:population":0,
    "gn:timezone":"Europe/Istanbul",
    "iso:country":"TR",
    "name:tur_x_preferred":[
        "Bak\u0131rta\u015f"
    ],
    "name:und_x_variant":[
        "Shikhrykh"
    ],
    "wof:name":"Bakirtas",
    "wof:placetype":"locality"
},
  "geometry": {"coordinates":[39.17724000000001,37.0204],"type":"Point"}
}