{
  "type": "Feature",
  "properties": {
    "gn:admin1_code":"72.0",
    "gn:asciiname":"Yukari Ocak",
    "gn:country_code":"TR",
    "gn:dem":1006,
    "gn:feature_class":"P",
    "gn:feature_code":"PPL",
    "gn:name":"Yukar\u0131 Ocak",
    "gn:population":0,
    "gn:timezone":"Europe/Istanbul",
    "iso:country":"TR",
    "name:tur_x_preferred":[
        "Yukar\u0131 Ocak"
    ],
    "name:und_x_variant":[
        "Yukar\u0131k\u00fcri",
        "Yukary-Kyuri"
    ],
    "wof:name":"Yukari Ocak",
    "wof:placetype":"locality"
},
  "geometry": {"coordinates":[40.61603,37.5326],"type":"Point"}
}