{
  "type": "Feature",
  "properties": {
    "gn:admin1_code":"14",
    "gn:asciiname":"Nazirlar",
    "gn:country_code":"TR",
    "gn:dem":784,
    "gn:feature_class":"P",
    "gn:feature_code":"PPL",
    "gn:name":"Naz\u0131rlar",
    "gn:population":0,
    "gn:timezone":"Europe/Istanbul",
    "iso:country":"TR",
    "wof:name":"Nazirlar",
    "wof:placetype":"locality"
},
  "geometry": {"coordinates":[32.13902,40.91181],"type":"Point"}
}