{
  "type": "Feature",
  "properties": {
    "gn:admin1_code":"81",
    "gn:asciiname":"Kepeztepe",
    "gn:country_code":"TR",
    "gn:dem":323,
    "gn:feature_class":"P",
    "gn:feature_code":"PPL",
    "gn:name":"Kepeztepe",
    "gn:population":0,
    "gn:timezone":"Europe/Istanbul",
    "iso:country":"TR",
    "name:tur_x_preferred":[
        "Kepeztepe"
    ],
    "wof:name":"Kepeztepe",
    "wof:placetype":"locality"
},
  "geometry": {"coordinates":[35.37546,37.18631],"type":"Point"}
}