{
  "type": "Feature",
  "properties": {
    "gn:admin1_code":"20",
    "gn:asciiname":"Suleymanli",
    "gn:country_code":"TR",
    "gn:dem":1175,
    "gn:feature_class":"P",
    "gn:feature_code":"PPL",
    "gn:name":"S\u00fcleymanl\u0131",
    "gn:population":0,
    "gn:timezone":"Europe/Istanbul",
    "iso:country":"TR",
    "name:tur_x_preferred":[
        "S\u00fcleymanl\u0131"
    ],
    "name:tur_x_variant":[
        "S\u00fcleymaniye"
    ],
    "wof:name":"Suleymanli",
    "wof:placetype":"locality"
},
  "geometry": {"coordinates":[28.76807,38.05031],"type":"Point"}
}