{
  "type": "Feature",
  "properties": {
    "gn:admin1_code":"63",
    "gn:asciiname":"Seyhcoban",
    "gn:country_code":"TR",
    "gn:dem":466,
    "gn:feature_class":"P",
    "gn:feature_code":"PPL",
    "gn:name":"\u015eeyh\u00e7oban",
    "gn:population":0,
    "gn:timezone":"Europe/Istanbul",
    "iso:country":"TR",
    "name:und_x_variant":[
        "\u015eeyh\u00e7oban",
        "\u015e\u0131h\u00e7oban",
        "Shikhchoban"
    ],
    "wof:name":"Seyhcoban",
    "wof:placetype":"locality"
},
  "geometry": {"coordinates":[38.85209,37.14571],"type":"Point"}
}