{
  "type": "Feature",
  "properties": {
    "gn:admin1_code":"64",
    "gn:asciiname":"Bekirli",
    "gn:country_code":"TR",
    "gn:dem":850,
    "gn:feature_class":"P",
    "gn:feature_code":"PPL",
    "gn:name":"Bekirli",
    "gn:population":0,
    "gn:timezone":"Europe/Istanbul",
    "iso:country":"TR",
    "name:tur_x_preferred":[
        "Bekirli"
    ],
    "wof:name":"Bekirli",
    "wof:placetype":"locality"
},
  "geometry": {"coordinates":[28.92833,38.50327],"type":"Point"}
}