{
  "type": "Feature",
  "properties": {
    "gn:admin1_code":"65",
    "gn:asciiname":"Yukari Balcikli",
    "gn:country_code":"TR",
    "gn:dem":2139,
    "gn:feature_class":"P",
    "gn:feature_code":"PPL",
    "gn:name":"Yukar\u0131 Bal\u00e7\u0131kl\u0131",
    "gn:population":0,
    "gn:timezone":"Europe/Istanbul",
    "iso:country":"TR",
    "name:tur_x_preferred":[
        "Yukar\u0131 Bal\u00e7\u0131kl\u0131"
    ],
    "wof:name":"Yukari Balcikli",
    "wof:placetype":"locality"
},
  "geometry": {"coordinates":[44.14336,38.9204],"type":"Point"}
}