{
  "type": "Feature",
  "properties": {
    "gn:admin1_code":"76.0",
    "gn:asciiname":"Danaci",
    "gn:country_code":"TR",
    "gn:dem":556,
    "gn:feature_class":"P",
    "gn:feature_code":"PPL",
    "gn:name":"Danac\u0131",
    "gn:population":0,
    "gn:timezone":"Europe/Istanbul",
    "iso:country":"TR",
    "wof:name":"Danaci",
    "wof:placetype":"locality"
},
  "geometry": {"coordinates":[41.61888,37.75726],"type":"Point"}
}