{
  "type": "Feature",
  "properties": {
    "gn:admin1_code":"11.0",
    "gn:asciiname":"Derecikoren",
    "gn:country_code":"TR",
    "gn:dem":488,
    "gn:feature_class":"P",
    "gn:feature_code":"PPL",
    "gn:name":"Derecik\u00f6ren",
    "gn:population":0,
    "gn:timezone":"Europe/Istanbul",
    "iso:country":"TR",
    "name:und_x_variant":[
        "Derecikviren",
        "Derecikviran",
        "Derecik\u00f6ren"
    ],
    "wof:name":"Derecikoren",
    "wof:placetype":"locality"
},
  "geometry": {"coordinates":[30.19884,40.30275],"type":"Point"}
}