{
  "type": "Feature",
  "properties": {
    "gn:admin1_code":"54",
    "gn:asciiname":"Topcu",
    "gn:country_code":"TR",
    "gn:dem":39,
    "gn:feature_class":"P",
    "gn:feature_code":"PPL",
    "gn:name":"Top\u00e7u",
    "gn:population":0,
    "gn:timezone":"Europe/Istanbul",
    "iso:country":"TR",
    "name:tur_x_preferred":[
        "Top\u00e7u"
    ],
    "wof:name":"Topcu",
    "wof:placetype":"locality"
},
  "geometry": {"coordinates":[30.33447,41.05136],"type":"Point"}
}