{
  "type": "Feature",
  "properties": {
    "gn:admin1_code":"35",
    "gn:asciiname":"Arpaseki",
    "gn:country_code":"TR",
    "gn:dem":394,
    "gn:feature_class":"P",
    "gn:feature_code":"PPL",
    "gn:name":"Arpaseki",
    "gn:population":0,
    "gn:timezone":"Europe/Istanbul",
    "iso:country":"TR",
    "name:tur_x_preferred":[
        "Arpaseki"
    ],
    "wof:name":"Arpaseki",
    "wof:placetype":"locality"
},
  "geometry": {"coordinates":[27.49016,39.09703],"type":"Point"}
}