{
  "type": "Feature",
  "properties": {
    "gn:admin1_code":"10",
    "gn:asciiname":"Koyuneri",
    "gn:country_code":"TR",
    "gn:dem":158,
    "gn:feature_class":"P",
    "gn:feature_code":"PPL",
    "gn:name":"Koyuneri",
    "gn:population":0,
    "gn:timezone":"Europe/Istanbul",
    "iso:country":"TR",
    "name:tur_x_preferred":[
        "Koyuneri"
    ],
    "wof:name":"Koyuneri",
    "wof:placetype":"locality"
},
  "geometry": {"coordinates":[27.65879,39.92291],"type":"Point"}
}