{
  "type": "Feature",
  "properties": {
    "gn:admin1_code":"40",
    "gn:asciiname":"Ciftliksarikaya",
    "gn:country_code":"TR",
    "gn:dem":1290,
    "gn:feature_class":"P",
    "gn:feature_code":"PPL",
    "gn:name":"\u00c7iftliksar\u0131kaya",
    "gn:population":0,
    "gn:timezone":"Europe/Istanbul",
    "iso:country":"TR",
    "name:und_x_variant":[
        "Yeniyapansar\u0131kaya",
        "Sar\u0131kaya",
        "\u00c7iftliksar\u0131kaya"
    ],
    "wof:name":"Ciftliksarikaya",
    "wof:placetype":"locality"
},
  "geometry": {"coordinates":[34.01667,39.39574],"type":"Point"}
}