{
  "type": "Feature",
  "properties": {
    "gn:admin1_code":"09",
    "gn:asciiname":"Karadut",
    "gn:country_code":"TR",
    "gn:dem":285,
    "gn:feature_class":"P",
    "gn:feature_code":"PPL",
    "gn:name":"Karadut",
    "gn:population":0,
    "gn:timezone":"Europe/Istanbul",
    "iso:country":"TR",
    "name:und_x_variant":[
        "Karadutk\u00f6y",
        "Karadut"
    ],
    "wof:name":"Karadut",
    "wof:placetype":"locality"
},
  "geometry": {"coordinates":[27.58921,37.72602],"type":"Point"}
}