{
  "type": "Feature",
  "properties": {
    "gn:admin1_code":"55.0",
    "gn:asciiname":"Buyukalan",
    "gn:country_code":"TR",
    "gn:dem":995,
    "gn:feature_class":"P",
    "gn:feature_code":"PPL",
    "gn:name":"B\u00fcy\u00fckalan",
    "gn:population":0,
    "gn:timezone":"Europe/Istanbul",
    "iso:country":"TR",
    "name:und_x_variant":[
        "B\u00fcy\u00fckalan",
        "C\u00fcremen"
    ],
    "wof:name":"Buyukalan",
    "wof:placetype":"locality"
},
  "geometry": {"coordinates":[36.12969,40.91567],"type":"Point"}
}