{
  "type": "Feature",
  "properties": {
    "gn:admin1_code":"09",
    "gn:asciiname":"Sarikemer",
    "gn:country_code":"TR",
    "gn:dem":5,
    "gn:feature_class":"P",
    "gn:feature_code":"PPL",
    "gn:name":"Sar\u0131kemer",
    "gn:population":2698,
    "gn:timezone":"Europe/Istanbul",
    "iso:country":"TR",
    "name:und_x_variant":[
        "Sar\u0131kemer"
    ],
    "wof:name":"Sarikemer",
    "wof:placetype":"locality",
    "wof:population":2698
},
  "geometry": {"coordinates":[27.3643,37.56609],"type":"Point"}
}