{
  "type": "Feature",
  "properties": {
    "gn:admin1_code":"24.0",
    "gn:asciiname":"Boluktepe",
    "gn:country_code":"TR",
    "gn:dem":1808,
    "gn:feature_class":"P",
    "gn:feature_code":"PPL",
    "gn:name":"B\u00f6l\u00fcktepe",
    "gn:population":0,
    "gn:timezone":"Europe/Istanbul",
    "iso:country":"TR",
    "name:tur_x_preferred":[
        "B\u00f6l\u00fcktepe"
    ],
    "wof:name":"Boluktepe",
    "wof:placetype":"locality"
},
  "geometry": {"coordinates":[38.83435,39.76657],"type":"Point"}
}