{
  "type": "Feature",
  "properties": {
    "gn:admin1_code":"72.0",
    "gn:asciiname":"Kislak",
    "gn:country_code":"TR",
    "gn:dem":960,
    "gn:feature_class":"P",
    "gn:feature_code":"PPL",
    "gn:name":"K\u0131\u015flak",
    "gn:population":0,
    "gn:timezone":"Europe/Istanbul",
    "iso:country":"TR",
    "name:tur_x_preferred":[
        "K\u0131\u015flak"
    ],
    "name:und_x_variant":[
        "\u015eutan",
        "Shutan"
    ],
    "wof:name":"Kislak",
    "wof:placetype":"locality"
},
  "geometry": {"coordinates":[40.64668,37.49761],"type":"Point"}
}