{
  "type": "Feature",
  "properties": {
    "gn:admin1_code":"85",
    "gn:asciiname":"Topyani",
    "gn:country_code":"TR",
    "gn:dem":387,
    "gn:feature_class":"P",
    "gn:feature_code":"PPL",
    "gn:name":"Topyan\u0131",
    "gn:population":0,
    "gn:timezone":"Europe/Istanbul",
    "iso:country":"TR",
    "name:tur_x_preferred":[
        "Topyan\u0131"
    ],
    "wof:name":"Topyani",
    "wof:placetype":"locality"
},
  "geometry": {"coordinates":[31.97301,41.20496],"type":"Point"}
}