{
  "type": "Feature",
  "properties": {
    "gn:admin1_code":"34.0",
    "gn:asciiname":"Sofular",
    "gn:country_code":"TR",
    "gn:dem":35,
    "gn:feature_class":"P",
    "gn:feature_code":"PPL",
    "gn:name":"Sofular",
    "gn:population":0,
    "gn:timezone":"Europe/Istanbul",
    "iso:country":"TR",
    "name:aze_x_preferred":[
        "Sofular"
    ],
    "name:ell_x_preferred":[
        "\u03a3\u03bf\u03c6\u03bf\u03c5\u03bb\u03ac\u03c1"
    ],
    "name:ita_x_preferred":[
        "Sofular"
    ],
    "name:msa_x_preferred":[
        "Sofular"
    ],
    "name:tur_x_preferred":[
        "Sofular"
    ],
    "wof:name":"Sofular",
    "wof:placetype":"locality"
},
  "geometry": {"coordinates":[29.49232,41.17286],"type":"Point"}
}