{
  "type": "Feature",
  "properties": {
    "gn:admin1_code":"86.0",
    "gn:asciiname":"Gulyuzu",
    "gn:country_code":"TR",
    "gn:dem":2007,
    "gn:feature_class":"P",
    "gn:feature_code":"PPL",
    "gn:name":"G\u00fcly\u00fcz\u00fc",
    "gn:population":0,
    "gn:timezone":"Europe/Istanbul",
    "iso:country":"TR",
    "name:und_x_variant":[
        "Pekre\u015fen",
        "Pekre\u015fin",
        "G\u00fcly\u00fcz\u00fc"
    ],
    "wof:name":"Gulyuzu",
    "wof:placetype":"locality"
},
  "geometry": {"coordinates":[43.22163,40.99004],"type":"Point"}
}