{
  "type": "Feature",
  "properties": {
    "gn:admin1_code":"58",
    "gn:asciiname":"Derince",
    "gn:cc2":"TR",
    "gn:country_code":"TR",
    "gn:dem":1613,
    "gn:feature_class":"P",
    "gn:feature_code":"PPL",
    "gn:name":"Derince",
    "gn:population":0,
    "gn:timezone":"Europe/Istanbul",
    "iso:country":"TR",
    "name:ara_x_preferred":[
        "\u062f\u0631\u064a\u0646\u062c\u0647"
    ],
    "name:azb_x_preferred":[
        "\u062f\u0631\u06cc\u0646\u062c\u0647"
    ],
    "name:bel_x_preferred":[
        "\u0414\u044d\u0440\u044b\u043d\u0434\u0436\u044d"
    ],
    "name:cat_x_preferred":[
        "Derince"
    ],
    "name:ceb_x_preferred":[
        "Derince \u0130l\u00e7esi"
    ],
    "name:deu_x_preferred":[
        "Derince"
    ],
    "name:diq_x_preferred":[
        "Derince"
    ],
    "name:ell_x_preferred":[
        "\u039d\u03c4\u03b5\u03c1\u03af\u03bd\u03c4\u03b6\u03b5"
    ],
    "name:epo_x_preferred":[
        "Derince"
    ],
    "name:fas_x_preferred":[
        "\u062f\u0631\u06cc\u0646\u062c\u0647"
    ],
    "name:fra_x_preferred":[
        "Derince"
    ],
    "name:ita_x_preferred":[
        "Derince"
    ],
    "name:lit_x_preferred":[
        "Derind\u017e\u0117"
    ],
    "name:lrc_x_preferred":[
        "\u062f\u0631\u06cc\u0646\u062c\u0647"
    ],
    "name:min_x_preferred":[
        "Derince"
    ],
    "name:mrj_x_preferred":[
        "\u0414\u0435\u0440\u0438\u043d\u0434\u0436\u0435"
    ],
    "name:msa_x_preferred":[
        "Derince"
    ],
    "name:nld_x_preferred":[
        "Derince"
    ],
    "name:nno_x_preferred":[
        "Derince"
    ],
    "name:nor_x_preferred":[
        "Derince"
    ],
    "name:pnb_x_preferred":[
        "\u0636\u0644\u0639 \u062f\u06cc\u0631\u0646\u0686\u06d2"
    ],
    "name:pol_x_preferred":[
        "Derince"
    ],
    "name:ron_x_preferred":[
        "Derince"
    ],
    "name:rus_x_preferred":[
        "\u0414\u0435\u0440\u0438\u043d\u0434\u0436\u0435"
    ],
    "name:srp_x_preferred":[
        "\u0414\u0435\u0440\u0438\u043d\u045f\u0435"
    ],
    "name:swa_x_preferred":[
        "Derince"
    ],
    "name:tur_x_preferred":[
        "Derince"
    ],
    "name:und_x_variant":[
        "Alduvaz",
        "Eldivas",
        "Ald\u0131vaz"
    ],
    "name:vie_x_preferred":[
        "Derince"
    ],
    "name:war_x_preferred":[
        "Derince"
    ],
    "name:zho_x_preferred":[
        "\u4ee3\u6797\u5091"
    ],
    "wof:name":"Derince",
    "wof:placetype":"locality"
},
  "geometry": {"coordinates":[37.51667,39.61667],"type":"Point"}
}