{
  "type": "Feature",
  "properties": {
    "gn:admin1_code":"58",
    "gn:asciiname":"Derince",
    "gn:cc2":"TR",
    "gn:country_code":"TR",
    "gn:dem":1613,
    "gn:feature_class":"P",
    "gn:feature_code":"PPL",
    "gn:name":"Derince",
    "gn:population":0,
    "gn:timezone":"Europe/Istanbul",
    "iso:country":"TR",
    "name:und_x_variant":[
        "Alduvaz",
        "Eldivas",
        "Ald\u0131vaz",
        "Derince"
    ],
    "wof:name":"Derince",
    "wof:placetype":"locality"
},
  "geometry": {"coordinates":[37.51667,39.61667],"type":"Point"}
}