{
  "type": "Feature",
  "properties": {
    "gn:admin1_code":"72",
    "gn:asciiname":"Donerdere",
    "gn:country_code":"TR",
    "gn:dem":1067,
    "gn:feature_class":"P",
    "gn:feature_code":"PPL",
    "gn:name":"D\u00f6nerdere",
    "gn:population":0,
    "gn:timezone":"Europe/Istanbul",
    "iso:country":"TR",
    "name:tur_x_preferred":[
        "D\u00f6nerdere"
    ],
    "name:und_x_variant":[
        "Birmezraa",
        "Birmezrea"
    ],
    "wof:name":"Donerdere",
    "wof:placetype":"locality"
},
  "geometry": {"coordinates":[40.92104000000001,37.4273],"type":"Point"}
}