{
  "type": "Feature",
  "properties": {
    "iso:country":"TR",
    "name:eng_x_preferred":[
        "Bostanci"
    ],
    "name:tur_x_preferred":[
        "Bostanc\u0131"
    ],
    "wof:name":"Bostanci",
    "wof:placetype":"neighbourhood"
},
  "geometry": {"coordinates":[29.0967761027804,40.95724589059185],"type":"Point"}
}