{
  "type": "Feature",
  "properties": {
    "gn:admin1_code":"79",
    "gn:asciiname":"Tekke Koy",
    "gn:country_code":"TR",
    "gn:dem":967,
    "gn:feature_class":"P",
    "gn:feature_code":"PPL",
    "gn:name":"Tekke K\u00f6y",
    "gn:population":0,
    "gn:timezone":"Europe/Istanbul",
    "iso:country":"TR",
    "name:und_x_variant":[
        "Tekke K\u00f6y",
        "Tekke"
    ],
    "wof:name":"Tekke Koy",
    "wof:placetype":"locality"
},
  "geometry": {"coordinates":[33.88705,39.81128],"type":"Point"}
}