{
  "type": "Feature",
  "properties": {
    "gn:admin1_code":"44",
    "gn:asciiname":"Kucuklu",
    "gn:country_code":"TR",
    "gn:dem":1123,
    "gn:feature_class":"P",
    "gn:feature_code":"PPL",
    "gn:name":"K\u00fc\u00e7\u00fckl\u00fc",
    "gn:population":0,
    "gn:timezone":"Europe/Istanbul",
    "iso:country":"TR",
    "name:und_x_variant":[
        "K\u00fc\u00e7\u00fckl\u00fck",
        "K\u00fc\u00e7\u00fckl\u00fc"
    ],
    "wof:name":"Kucuklu",
    "wof:placetype":"locality"
},
  "geometry": {"coordinates":[37.68951,38.01234],"type":"Point"}
}