{
  "type": "Feature",
  "properties": {
    "gn:country":"TR",
    "gn:fcode":"PPLX",
    "gn:population":0,
    "iso:country":"TR",
    "qs:name":"G\u00fcrpinar",
    "qs:name_adm0":"Turkey",
    "qs:name_adm1":"Denizli",
    "qs:photos":1,
    "qs:photos_1k":1,
    "qs:photos_9k":1,
    "qs:photos_9r":1,
    "qs:photos_all":1,
    "qs:photos_sr":1,
    "qs:placetype":"Suburb",
    "qs:pop_sr":"0",
    "wof:name":"G\u00fcrpinar",
    "wof:placetype":"neighbourhood",
    "wof:population":0
},
  "geometry": {"coordinates":[28.69208,36.9622],"type":"Point"}
}