{
  "type": "Feature",
  "properties": {
    "gn:admin1_code":"37.0",
    "gn:asciiname":"Devrencik",
    "gn:country_code":"TR",
    "gn:dem":1180,
    "gn:feature_class":"P",
    "gn:feature_code":"PPL",
    "gn:name":"Devrencik",
    "gn:population":0,
    "gn:timezone":"Europe/Istanbul",
    "iso:country":"TR",
    "wof:name":"Devrencik",
    "wof:placetype":"locality"
},
  "geometry": {"coordinates":[33.94615,41.74083],"type":"Point"}
}