{
  "type": "Feature",
  "properties": {
    "gn:admin1_code":"21.0",
    "gn:asciiname":"Balcilar",
    "gn:country_code":"TR",
    "gn:dem":669,
    "gn:feature_class":"P",
    "gn:feature_code":"PPL",
    "gn:name":"Balc\u0131lar",
    "gn:population":0,
    "gn:timezone":"Europe/Istanbul",
    "iso:country":"TR",
    "name:tur_x_preferred":[
        "Balc\u0131lar"
    ],
    "name:und_x_variant":[
        "Salladon",
        "Saladun"
    ],
    "wof:name":"Balcilar",
    "wof:placetype":"locality"
},
  "geometry": {"coordinates":[40.85572,37.74068],"type":"Point"}
}