{
  "type": "Feature",
  "properties": {
    "gn:admin1_code":"20",
    "gn:asciiname":"Tepekoy",
    "gn:cc2":"TR",
    "gn:country_code":"TR",
    "gn:dem":180,
    "gn:feature_class":"P",
    "gn:feature_code":"PPL",
    "gn:name":"Tepek\u00f6y",
    "gn:population":0,
    "gn:timezone":"Europe/Istanbul",
    "iso:country":"TR",
    "name:und_x_variant":[
        "Tepe\u00e7ifli\u011fi",
        "Tepe\u00e7iftlik",
        "Tepek\u00f6y"
    ],
    "wof:name":"Tepekoy",
    "wof:placetype":"locality"
},
  "geometry": {"coordinates":[28.99472,38.00944000000001],"type":"Point"}
}