{
  "type": "Feature",
  "properties": {
    "gn:admin1_code":"52.0",
    "gn:asciiname":"Arikmusa",
    "gn:country_code":"TR",
    "gn:dem":1354,
    "gn:feature_class":"P",
    "gn:feature_code":"PPL",
    "gn:name":"Ar\u0131kmusa",
    "gn:population":0,
    "gn:timezone":"Europe/Istanbul",
    "iso:country":"TR",
    "name:tur_x_preferred":[
        "Ar\u0131kmusa"
    ],
    "wof:name":"Arikmusa",
    "wof:placetype":"locality"
},
  "geometry": {"coordinates":[37.91597,40.44191],"type":"Point"}
}