{
  "type": "Feature",
  "properties": {
    "gn:admin1_code":"14.0",
    "gn:asciiname":"Kasikciseyhler",
    "gn:country_code":"TR",
    "gn:dem":818,
    "gn:feature_class":"P",
    "gn:feature_code":"PPL",
    "gn:name":"Ka\u015f\u0131k\u00e7\u0131\u015feyhler",
    "gn:population":0,
    "gn:timezone":"Europe/Istanbul",
    "iso:country":"TR",
    "name:und_x_variant":[
        "Ka\u015f\u0131k\u00e7\u0131\u015f\u0131hlar",
        "Ka\u015f\u0131k\u00e7\u0131\u015f\u0131hlari",
        "Ka\u015f\u0131k\u00e7\u0131\u015feyhleri",
        "Ka\u015f\u0131k\u00e7\u0131\u015feyhler"
    ],
    "wof:name":"Kasikciseyhler",
    "wof:placetype":"locality"
},
  "geometry": {"coordinates":[30.68655,40.46871],"type":"Point"}
}