{
  "type": "Feature",
  "properties": {
    "gn:admin1_code":"35",
    "gn:asciiname":"Kizilca",
    "gn:country_code":"TR",
    "gn:dem":565,
    "gn:feature_class":"P",
    "gn:feature_code":"PPL",
    "gn:name":"K\u0131z\u0131lca",
    "gn:population":0,
    "gn:timezone":"Europe/Istanbul",
    "iso:country":"TR",
    "name:tur_x_preferred":[
        "K\u0131z\u0131lca"
    ],
    "name:tur_x_variant":[
        "K\u0131z\u0131lcak\u00f6y"
    ],
    "wof:name":"Kizilca",
    "wof:placetype":"locality"
},
  "geometry": {"coordinates":[27.84445,38.29709],"type":"Point"}
}