{
  "type": "Feature",
  "properties": {
    "gn:admin1_code":"25.0",
    "gn:asciiname":"Hozahpur",
    "gn:country_code":"TR",
    "gn:dem":1817,
    "gn:feature_class":"P",
    "gn:feature_code":"PPL",
    "gn:name":"Hozahpur",
    "gn:population":0,
    "gn:timezone":"Europe/Istanbul",
    "iso:country":"TR",
    "wof:name":"Hozahpur",
    "wof:placetype":"locality"
},
  "geometry": {"coordinates":[40.55,40.33333],"type":"Point"}
}