{
  "type": "Feature",
  "properties": {
    "gn:admin1_code":"72",
    "gn:asciiname":"Catalyurt",
    "gn:country_code":"TR",
    "gn:dem":988,
    "gn:feature_class":"P",
    "gn:feature_code":"PPL",
    "gn:name":"\u00c7atalyurt",
    "gn:population":0,
    "gn:timezone":"Europe/Istanbul",
    "iso:country":"TR",
    "name:tur_x_preferred":[
        "\u00c7atalyurt"
    ],
    "name:und_x_variant":[
        "K\u00fcrikmetinan",
        "Kyuryukmetinan",
        "K\u00fcr\u00fckmetinan"
    ],
    "wof:name":"Catalyurt",
    "wof:placetype":"locality"
},
  "geometry": {"coordinates":[41.03758,37.37094],"type":"Point"}
}