{
  "type": "Feature",
  "properties": {
    "gn:country":"TR",
    "gn:fcode":"PPL",
    "gn:pop":334,
    "iso:country":"TR",
    "qs:name":"Delimahmutlu",
    "qs:photos_9r":0,
    "qs:photos_sr":0,
    "qs:pop_sr":"2",
    "wof:name":"Delimahmutlu",
    "wof:placetype":"locality",
    "wof:population":334
},
  "geometry": {"coordinates":[34.35802,37.41271],"type":"Point"}
}