{
  "type": "Feature",
  "properties": {
    "gn:admin1_code":"68.0",
    "gn:asciiname":"Subasi",
    "gn:country_code":"TR",
    "gn:dem":1060,
    "gn:feature_class":"P",
    "gn:feature_code":"PPL",
    "gn:name":"Suba\u015f\u0131",
    "gn:population":0,
    "gn:timezone":"Europe/Istanbul",
    "iso:country":"TR",
    "name:und_x_variant":[
        "Karahisarsuba\u015f\u0131",
        "Suba\u015f\u0131dere",
        "Suba\u015f\u0131"
    ],
    "wof:name":"Subasi",
    "wof:placetype":"locality"
},
  "geometry": {"coordinates":[31.09278,40.18917],"type":"Point"}
}