{
  "type": "Feature",
  "properties": {
    "gn:admin1_code":"82.0",
    "gn:asciiname":"Yalakcukuroren",
    "gn:country_code":"TR",
    "gn:dem":1268,
    "gn:feature_class":"P",
    "gn:feature_code":"PPL",
    "gn:name":"Yalak\u00e7ukur\u00f6ren",
    "gn:population":0,
    "gn:timezone":"Europe/Istanbul",
    "iso:country":"TR",
    "name:und_x_variant":[
        "Yalak\u00e7ukurviran",
        "Yalak\u00e7ukur\u00f6ren"
    ],
    "wof:name":"Yalakcukuroren",
    "wof:placetype":"locality"
},
  "geometry": {"coordinates":[33.01924,40.73116],"type":"Point"}
}