{
  "type": "Feature",
  "properties": {
    "gn:admin1_code":"58",
    "gn:asciiname":"Sandalkoy",
    "gn:country_code":"TR",
    "gn:dem":1454,
    "gn:feature_class":"P",
    "gn:feature_code":"PPL",
    "gn:name":"Sandalk\u00f6y",
    "gn:population":0,
    "gn:timezone":"Europe/Istanbul",
    "iso:country":"TR",
    "name:tur_x_preferred":[
        "Sandalk\u00f6y"
    ],
    "name:tur_x_variant":[
        "Sandal"
    ],
    "wof:name":"Sandalkoy",
    "wof:placetype":"locality"
},
  "geometry": {"coordinates":[36.42918,39.86682],"type":"Point"}
}