{
  "type": "Feature",
  "properties": {
    "gn:admin1_code":"10",
    "gn:asciiname":"Mestanlar",
    "gn:country_code":"TR",
    "gn:dem":466,
    "gn:feature_class":"P",
    "gn:feature_code":"PPL",
    "gn:name":"Mestanlar",
    "gn:population":0,
    "gn:timezone":"Europe/Istanbul",
    "iso:country":"TR",
    "name:tur_x_preferred":[
        "Mestanlar"
    ],
    "wof:name":"Mestanlar",
    "wof:placetype":"locality"
},
  "geometry": {"coordinates":[28.25101,39.72578],"type":"Point"}
}