{
  "type": "Feature",
  "properties": {
    "gn:admin1_code":"17.0",
    "gn:asciiname":"Bezirganlar",
    "gn:country_code":"TR",
    "gn:dem":134,
    "gn:feature_class":"P",
    "gn:feature_code":"PPL",
    "gn:name":"Bezirganlar",
    "gn:population":0,
    "gn:timezone":"Europe/Istanbul",
    "iso:country":"TR",
    "name:tur_x_preferred":[
        "Bezirganlar"
    ],
    "name:tur_x_variant":[
        "Bezierganlar"
    ],
    "wof:name":"Bezirganlar",
    "wof:placetype":"locality"
},
  "geometry": {"coordinates":[26.98971,40.17527000000001],"type":"Point"}
}