{
  "type": "Feature",
  "properties": {
    "gn:admin1_code":"55.0",
    "gn:asciiname":"Kozansiki",
    "gn:country_code":"TR",
    "gn:dem":723,
    "gn:feature_class":"P",
    "gn:feature_code":"PPL",
    "gn:name":"Kozans\u0131k\u0131",
    "gn:population":0,
    "gn:timezone":"Europe/Istanbul",
    "iso:country":"TR",
    "name:und_x_variant":[
        "Kazans\u0131k\u0131",
        "Kozans\u0131k\u0131"
    ],
    "wof:name":"Kozansiki",
    "wof:placetype":"locality"
},
  "geometry": {"coordinates":[36.00473,41.01484],"type":"Point"}
}