{
  "type": "Feature",
  "properties": {
    "gn:admin1_code":"71",
    "gn:asciiname":"Kayacik",
    "gn:country_code":"TR",
    "gn:dem":1005,
    "gn:feature_class":"P",
    "gn:feature_code":"PPL",
    "gn:name":"Kayac\u0131k",
    "gn:population":0,
    "gn:timezone":"Europe/Istanbul",
    "iso:country":"TR",
    "wof:name":"Kayacik",
    "wof:placetype":"locality"
},
  "geometry": {"coordinates":[33.21043,37.59439],"type":"Point"}
}