{
  "type": "Feature",
  "properties": {
    "gn:admin1_code":"80.0",
    "gn:asciiname":"Binave",
    "gn:country_code":"TR",
    "gn:dem":1015,
    "gn:feature_class":"P",
    "gn:feature_code":"PPL",
    "gn:name":"Binave",
    "gn:population":0,
    "gn:timezone":"Europe/Istanbul",
    "iso:country":"TR",
    "name:und_x_variant":[
        "Nivekara"
    ],
    "wof:name":"Binave",
    "wof:placetype":"locality"
},
  "geometry": {"coordinates":[42.50493,37.44804],"type":"Point"}
}