{
  "type": "Feature",
  "properties": {
    "gn:admin1_code":"81",
    "gn:asciiname":"Yalak",
    "gn:country_code":"TR",
    "gn:dem":31,
    "gn:feature_class":"P",
    "gn:feature_code":"PPL",
    "gn:name":"Yalak",
    "gn:population":0,
    "gn:timezone":"Europe/Istanbul",
    "iso:country":"TR",
    "wof:name":"Yalak",
    "wof:placetype":"locality"
},
  "geometry": {"coordinates":[35.93033,37.11095],"type":"Point"}
}