{
  "type": "Feature",
  "properties": {
    "gn:admin1_code":"68",
    "gn:asciiname":"Malikoy",
    "gn:country_code":"TR",
    "gn:dem":743,
    "gn:feature_class":"P",
    "gn:feature_code":"PPL",
    "gn:name":"Mal\u0131k\u00f6y",
    "gn:population":0,
    "gn:timezone":"Europe/Istanbul",
    "iso:country":"TR",
    "wof:name":"Malikoy",
    "wof:placetype":"locality"
},
  "geometry": {"coordinates":[32.38877,39.78344],"type":"Point"}
}