{
  "type": "Feature",
  "properties": {
    "gn:admin1_code":"25.0",
    "gn:asciiname":"Sulunkaya",
    "gn:country_code":"TR",
    "gn:dem":1750,
    "gn:feature_class":"P",
    "gn:feature_code":"PPL",
    "gn:name":"S\u00fcl\u00fcnkaya",
    "gn:population":0,
    "gn:timezone":"Europe/Istanbul",
    "iso:country":"TR",
    "name:tur_x_preferred":[
        "S\u00fcl\u00fcnkaya"
    ],
    "wof:name":"Sulunkaya",
    "wof:placetype":"locality"
},
  "geometry": {"coordinates":[41.9538,40.695],"type":"Point"}
}