{
  "type": "Feature",
  "properties": {
    "gn:admin1_code":"81",
    "gn:asciiname":"Avcilar",
    "gn:country_code":"TR",
    "gn:dem":136,
    "gn:feature_class":"P",
    "gn:feature_code":"PPL",
    "gn:name":"Avc\u0131lar",
    "gn:population":0,
    "gn:timezone":"Europe/Istanbul",
    "iso:country":"TR",
    "wof:name":"Avcilar",
    "wof:placetype":"locality"
},
  "geometry": {"coordinates":[35.61360999999999,37.12333],"type":"Point"}
}