{
  "type": "Feature",
  "properties": {
    "gn:admin1_code":"68.0",
    "gn:asciiname":"Uyurca",
    "gn:country_code":"TR",
    "gn:dem":675,
    "gn:feature_class":"P",
    "gn:feature_code":"PPL",
    "gn:name":"Uyurca",
    "gn:population":0,
    "gn:timezone":"Europe/Istanbul",
    "iso:country":"TR",
    "wof:name":"Uyurca",
    "wof:placetype":"locality"
},
  "geometry": {"coordinates":[33.59101,40.24968],"type":"Point"}
}