{
  "type": "Feature",
  "properties": {
    "iso:country":"TR",
    "name:eng_x_preferred":[
        "B\u00fcy\u00fckdere"
    ],
    "name:tur_x_preferred":[
        "B\u00fcy\u00fckdere"
    ],
    "wof:name":"Buyukdere",
    "wof:placetype":"neighbourhood"
},
  "geometry": {"coordinates":[29.04273099521288,41.16281407455084],"type":"Point"}
}