{
  "type": "Feature",
  "properties": {
    "gn:admin1_code":"81.0",
    "gn:asciiname":"Musafaki",
    "gn:country_code":"TR",
    "gn:dem":1018,
    "gn:feature_class":"P",
    "gn:feature_code":"PPL",
    "gn:name":"Musafak\u0131",
    "gn:population":0,
    "gn:timezone":"Europe/Istanbul",
    "iso:country":"TR",
    "wof:name":"Musafaki",
    "wof:placetype":"locality"
},
  "geometry": {"coordinates":[35.57472,37.58042],"type":"Point"}
}