{
  "type": "Feature",
  "properties": {
    "gn:admin1_code":"48",
    "gn:asciiname":"Asagi Germencik",
    "gn:country_code":"TR",
    "gn:dem":76,
    "gn:feature_class":"P",
    "gn:feature_code":"PPL",
    "gn:name":"A\u015fa\u011f\u0131 Germencik",
    "gn:population":0,
    "gn:timezone":"Europe/Istanbul",
    "iso:country":"TR",
    "name:tur_x_preferred":[
        "A\u015fa\u011f\u0131 Germencik"
    ],
    "wof:name":"Asagi Germencik",
    "wof:placetype":"locality"
},
  "geometry": {"coordinates":[28.08186,36.71257],"type":"Point"}
}