{
  "type": "Feature",
  "properties": {
    "gn:country":"TR",
    "gn:fcode":"PPL",
    "gn:population":6513,
    "iso:country":"TR",
    "name:ceb_x_preferred":[
        "Yenipazar"
    ],
    "name:deu_x_preferred":[
        "Yenipazar"
    ],
    "name:eng_x_preferred":[
        "Yenipazar"
    ],
    "name:epo_x_preferred":[
        "Yenipazar"
    ],
    "name:fra_x_preferred":[
        "Yenipazar"
    ],
    "name:ita_x_preferred":[
        "Distretto di Yenipazar"
    ],
    "name:jpn_x_preferred":[
        "\u30e4\u30cb\u30d1\u30b6\u30fc\u30eb"
    ],
    "name:lbe_x_preferred":[
        "\u0415\u043d\u0438\u043f\u0430\u0437\u0430\u0440"
    ],
    "name:lit_x_preferred":[
        "Jenipazaras"
    ],
    "name:mrj_x_preferred":[
        "\u0415\u043d\u0438\u043f\u0430\u0437\u0430\u0440"
    ],
    "name:msa_x_preferred":[
        "Yenipazar"
    ],
    "name:nan_x_preferred":[
        "Yenipazar"
    ],
    "name:nld_x_preferred":[
        "Yenipazar"
    ],
    "name:nob_x_preferred":[
        "Yenipazar"
    ],
    "name:swa_x_preferred":[
        "Yenipazar"
    ],
    "name:tur_x_preferred":[
        "Yenipazar"
    ],
    "name:urd_x_preferred":[
        "\u06cc\u0646\u067e\u0632\u0627\u0631\u060c \u06cc\u062f\u06cc\u0646"
    ],
    "name:urd_x_variant":[
        "\u06cc\u0646\u067e\u0632\u0627\u0631"
    ],
    "name:vie_x_preferred":[
        "Yenipazar"
    ],
    "qs:name":"Yenipazar",
    "qs:name_adm0":"Turkey",
    "qs:name_adm1":"Ayd\u0131n",
    "qs:photos_9k":1,
    "qs:photos_9r":1,
    "qs:photos_all":1,
    "qs:photos_sr":0,
    "qs:placetype":"Town",
    "qs:pop_sr":"5",
    "wd:wordcount":77,
    "wof:name":"Yenipazar",
    "wof:placetype":"locality",
    "wof:population":6513
},
  "geometry": {"coordinates":[28.19717,37.82419],"type":"Point"}
}