{
  "type": "Feature",
  "properties": {
    "gn:admin1_code":"21",
    "gn:asciiname":"Zumrut",
    "gn:country_code":"TR",
    "gn:dem":894,
    "gn:feature_class":"P",
    "gn:feature_code":"PPL",
    "gn:name":"Z\u00fcmr\u00fct",
    "gn:population":0,
    "gn:timezone":"Europe/Istanbul",
    "iso:country":"TR",
    "name:tur_x_preferred":[
        "Z\u00fcmr\u00fct"
    ],
    "wof:name":"Zumrut",
    "wof:placetype":"locality"
},
  "geometry": {"coordinates":[40.80046,38.45792],"type":"Point"}
}