{
  "type": "Feature",
  "properties": {
    "gn:admin1_code":"72.0",
    "gn:asciiname":"Yedikardes",
    "gn:country_code":"TR",
    "gn:dem":783,
    "gn:feature_class":"P",
    "gn:feature_code":"PPL",
    "gn:name":"Yedikarde\u015f",
    "gn:population":0,
    "gn:timezone":"Europe/Istanbul",
    "iso:country":"TR",
    "name:tur_x_preferred":[
        "Yedikarde\u015f"
    ],
    "wof:name":"Yedikardes",
    "wof:placetype":"locality"
},
  "geometry": {"coordinates":[40.61606,37.3067],"type":"Point"}
}