{
  "type": "Feature",
  "properties": {
    "gn:admin1_code":"8.0",
    "gn:asciiname":"Camurlu",
    "gn:country_code":"TR",
    "gn:dem":161,
    "gn:feature_class":"P",
    "gn:feature_code":"PPL",
    "gn:name":"\u00c7amurlu",
    "gn:population":0,
    "gn:timezone":"Europe/Istanbul",
    "iso:country":"TR",
    "name:tur_x_preferred":[
        "\u00c7amurlu"
    ],
    "wof:name":"Camurlu",
    "wof:placetype":"locality"
},
  "geometry": {"coordinates":[41.57091,41.48877],"type":"Point"}
}