{
  "type": "Feature",
  "properties": {
    "gn:admin1_code":"52.0",
    "gn:asciiname":"Eceli",
    "gn:cc2":"TR",
    "gn:country_code":"TR",
    "gn:dem":1473,
    "gn:feature_class":"P",
    "gn:feature_code":"PPL",
    "gn:name":"Eceli",
    "gn:population":0,
    "gn:timezone":"Europe/Istanbul",
    "iso:country":"TR",
    "name:und_x_variant":[
        "Eceli Yaylas\u0131",
        "Eceli"
    ],
    "wof:name":"Eceli",
    "wof:placetype":"locality"
},
  "geometry": {"coordinates":[37.33333,40.61667],"type":"Point"}
}