{
  "type": "Feature",
  "properties": {
    "gn:admin1_code":"54.0",
    "gn:asciiname":"Hacikisla",
    "gn:country_code":"TR",
    "gn:dem":78,
    "gn:feature_class":"P",
    "gn:feature_code":"PPL",
    "gn:name":"Hac\u0131k\u0131\u015fla",
    "gn:population":0,
    "gn:timezone":"Europe/Istanbul",
    "iso:country":"TR",
    "name:und_x_variant":[
        "Hac\u0131k\u0131\u015fla K\u00f6y\u00fc",
        "Hac\u0131k\u0131\u015fla"
    ],
    "wof:name":"Hacikisla",
    "wof:placetype":"locality"
},
  "geometry": {"coordinates":[30.63908,40.87335],"type":"Point"}
}