{
  "type": "Feature",
  "properties": {
    "gn:country":"TR",
    "gn:fcode":"PPL",
    "gn:pop":1334,
    "iso:country":"TR",
    "name:tur_x_preferred":[
        "\u00c7\u0131naralt\u0131"
    ],
    "name:unk_x_variant":[
        "Rissin"
    ],
    "qs:name":"\u00c7\u0131naralt\u0131",
    "qs:photos_9r":0,
    "qs:photos_sr":0,
    "qs:pop_sr":"3",
    "wof:name":"\u00c7\u0131naralt\u0131",
    "wof:placetype":"locality",
    "wof:population":1334
},
  "geometry": {"coordinates":[40.86,37.38444],"type":"Point"}
}