{
  "type": "Feature",
  "properties": {
    "gn:admin1_code":"66",
    "gn:asciiname":"Kemalli",
    "gn:country_code":"TR",
    "gn:dem":1020,
    "gn:feature_class":"P",
    "gn:feature_code":"PPL",
    "gn:name":"Kemalli",
    "gn:population":0,
    "gn:timezone":"Europe/Istanbul",
    "iso:country":"TR",
    "name:und_x_variant":[
        "Karahisarkemalisi",
        "Karahisarkemallisi",
        "Kemalli"
    ],
    "wof:name":"Kemalli",
    "wof:placetype":"locality"
},
  "geometry": {"coordinates":[35.79068,39.94135],"type":"Point"}
}