{
  "type": "Feature",
  "properties": {
    "gn:admin1_code":"26",
    "gn:asciiname":"Kizilca Yaylasi",
    "gn:country_code":"TR",
    "gn:dem":838,
    "gn:feature_class":"P",
    "gn:feature_code":"PPL",
    "gn:name":"K\u0131z\u0131lca Yaylas\u0131",
    "gn:population":0,
    "gn:timezone":"Europe/Istanbul",
    "iso:country":"TR",
    "wof:name":"Kizilca Yaylasi",
    "wof:placetype":"locality"
},
  "geometry": {"coordinates":[31.3272,39.33411],"type":"Point"}
}