{
  "type": "Feature",
  "properties": {
    "gn:admin1_code":"70.0",
    "gn:asciiname":"Gulluce",
    "gn:country_code":"TR",
    "gn:dem":1923,
    "gn:feature_class":"P",
    "gn:feature_code":"PPL",
    "gn:name":"G\u00fcll\u00fcce",
    "gn:population":0,
    "gn:timezone":"Europe/Istanbul",
    "iso:country":"TR",
    "wof:name":"Gulluce",
    "wof:placetype":"locality"
},
  "geometry": {"coordinates":[44.29,37.59611],"type":"Point"}
}