{
  "type": "Feature",
  "properties": {
    "gn:admin1_code":"15",
    "gn:asciiname":"Aliclikuyu",
    "gn:country_code":"TR",
    "gn:dem":1343,
    "gn:feature_class":"P",
    "gn:feature_code":"PPL",
    "gn:name":"Al\u0131\u00e7l\u0131kuyu",
    "gn:population":0,
    "gn:timezone":"Europe/Istanbul",
    "iso:country":"TR",
    "wof:name":"Aliclikuyu",
    "wof:placetype":"locality"
},
  "geometry": {"coordinates":[29.36556,36.89972],"type":"Point"}
}