{
  "type": "Feature",
  "properties": {
    "gn:admin1_code":"65",
    "gn:asciiname":"Otlakbasi",
    "gn:country_code":"TR",
    "gn:dem":2191,
    "gn:feature_class":"P",
    "gn:feature_code":"PPL",
    "gn:name":"Otlakba\u015f\u0131",
    "gn:population":0,
    "gn:timezone":"Europe/Istanbul",
    "iso:country":"TR",
    "name:und_x_variant":[
        "Mezraak\u00f6p",
        "Otlukba\u015f\u0131",
        "Mezre",
        "Mezrea",
        "Mezra",
        "Otlakba\u015f\u0131"
    ],
    "wof:name":"Otlakbasi",
    "wof:placetype":"locality"
},
  "geometry": {"coordinates":[43.64612,38.86703],"type":"Point"}
}