{
  "type": "Feature",
  "properties": {
    "gn:admin1_code":"28.0",
    "gn:asciiname":"Haci Ahmetoglu",
    "gn:country_code":"TR",
    "gn:dem":1319,
    "gn:feature_class":"P",
    "gn:feature_code":"PPL",
    "gn:name":"Hac\u0131 Ahmeto\u011flu",
    "gn:population":0,
    "gn:timezone":"Europe/Istanbul",
    "iso:country":"TR",
    "name:tur_x_preferred":[
        "Hac\u0131 Ahmeto\u011flu"
    ],
    "name:und_x_variant":[
        "Haciahmeto\u011flu"
    ],
    "wof:name":"Haci Ahmetoglu",
    "wof:placetype":"locality"
},
  "geometry": {"coordinates":[38.68585,40.14993],"type":"Point"}
}