{
  "type": "Feature",
  "properties": {
    "gn:admin1_code":"66.0",
    "gn:asciiname":"Buyuktoraman",
    "gn:country_code":"TR",
    "gn:dem":799,
    "gn:feature_class":"P",
    "gn:feature_code":"PPL",
    "gn:name":"B\u00fcy\u00fcktoraman",
    "gn:population":0,
    "gn:timezone":"Europe/Istanbul",
    "iso:country":"TR",
    "wof:name":"Buyuktoraman",
    "wof:placetype":"locality"
},
  "geometry": {"coordinates":[35.28333,40.18333],"type":"Point"}
}