{
  "type": "Feature",
  "properties": {
    "gn:admin1_code":"37.0",
    "gn:asciiname":"Terme",
    "gn:country_code":"TR",
    "gn:dem":184,
    "gn:feature_class":"P",
    "gn:feature_code":"PPL",
    "gn:name":"Terme",
    "gn:population":0,
    "gn:timezone":"Europe/Istanbul",
    "iso:country":"TR",
    "name:ceb_x_preferred":[
        "Terme"
    ],
    "name:deu_x_preferred":[
        "Terme"
    ],
    "name:fas_x_preferred":[
        "\u062a\u0631\u0645\u0647"
    ],
    "name:ita_x_preferred":[
        "Terme"
    ],
    "name:min_x_preferred":[
        "Terme"
    ],
    "name:nld_x_preferred":[
        "Terme"
    ],
    "name:nno_x_preferred":[
        "Terme"
    ],
    "name:und_x_variant":[
        "G\u00f6k\u00e7e\u00f6ren"
    ],
    "name:vie_x_preferred":[
        "Terme"
    ],
    "name:zho_x_preferred":[
        "\u6cf0\u723e\u6885"
    ],
    "wof:name":"Terme",
    "wof:placetype":"locality"
},
  "geometry": {"coordinates":[33.19605,41.87924],"type":"Point"}
}