{
  "type": "Feature",
  "properties": {
    "gn:admin1_code":"81.0",
    "gn:asciiname":"Kuzucak",
    "gn:country_code":"TR",
    "gn:dem":40,
    "gn:feature_class":"P",
    "gn:feature_code":"PPL",
    "gn:name":"Kuzucak",
    "gn:population":0,
    "gn:timezone":"Europe/Istanbul",
    "iso:country":"TR",
    "wof:name":"Kuzucak",
    "wof:placetype":"locality"
},
  "geometry": {"coordinates":[35.99718,37.0567],"type":"Point"}
}