{
  "type": "Feature",
  "properties": {
    "gn:admin1_code":"43.0",
    "gn:asciiname":"Ustubec",
    "gn:country_code":"TR",
    "gn:dem":979,
    "gn:feature_class":"P",
    "gn:feature_code":"PPL",
    "gn:name":"\u00dcst\u00fcbe\u00e7",
    "gn:population":0,
    "gn:timezone":"Europe/Istanbul",
    "iso:country":"TR",
    "name:tur_x_preferred":[
        "\u00dcst\u00fcbe\u00e7"
    ],
    "name:tur_x_variant":[
        "Ak\u00e7akilise"
    ],
    "wof:name":"Ustubec",
    "wof:placetype":"locality"
},
  "geometry": {"coordinates":[29.69927,39.71374],"type":"Point"}
}