{
  "type": "Feature",
  "properties": {
    "gn:admin1_code":"3.0",
    "gn:asciiname":"Avsar",
    "gn:country_code":"TR",
    "gn:dem":1111,
    "gn:feature_class":"P",
    "gn:feature_code":"PPL",
    "gn:name":"Av\u015far",
    "gn:population":0,
    "gn:timezone":"Europe/Istanbul",
    "iso:country":"TR",
    "name:und_x_variant":[
        "Av\u015far",
        "Af\u015far"
    ],
    "wof:name":"Avsar",
    "wof:placetype":"locality"
},
  "geometry": {"coordinates":[30.18306,38.20889],"type":"Point"}
}