{
  "type": "Feature",
  "properties": {
    "gn:admin1_code":"63",
    "gn:asciiname":"Yaslica",
    "gn:country_code":"TR",
    "gn:dem":573,
    "gn:feature_class":"P",
    "gn:feature_code":"PPL",
    "gn:name":"Yasl\u0131ca",
    "gn:population":0,
    "gn:timezone":"Europe/Istanbul",
    "iso:country":"TR",
    "name:und_x_variant":[
        "Pasl\u0131ca",
        "Yasl\u0131ca"
    ],
    "wof:name":"Yaslica",
    "wof:placetype":"locality"
},
  "geometry": {"coordinates":[38.38911,37.44067],"type":"Point"}
}