{
  "type": "Feature",
  "properties": {
    "gn:admin1_code":"37.0",
    "gn:asciiname":"Gunvakti",
    "gn:country_code":"TR",
    "gn:dem":482,
    "gn:feature_class":"P",
    "gn:feature_code":"PPL",
    "gn:name":"G\u00fcnvakti",
    "gn:population":0,
    "gn:timezone":"Europe/Istanbul",
    "iso:country":"TR",
    "wof:name":"Gunvakti",
    "wof:placetype":"locality"
},
  "geometry": {"coordinates":[33.93833,41.93688],"type":"Point"}
}