{
  "type": "Feature",
  "properties": {
    "gn:admin1_code":"58",
    "gn:asciiname":"Fatmadervis",
    "gn:country_code":"TR",
    "gn:dem":1715,
    "gn:feature_class":"P",
    "gn:feature_code":"PPL",
    "gn:name":"Fatmadervi\u015f",
    "gn:population":0,
    "gn:timezone":"Europe/Istanbul",
    "iso:country":"TR",
    "wof:name":"Fatmadervis",
    "wof:placetype":"locality"
},
  "geometry": {"coordinates":[37.34215,38.61691],"type":"Point"}
}