{
  "type": "Feature",
  "properties": {
    "gn:country":"TR",
    "gn:fcode":"PPL",
    "gn:population":106,
    "iso:country":"TR",
    "name:tur_x_preferred":[
        "\u00c7ataltarla"
    ],
    "name:und_x_variant":[
        "Bename"
    ],
    "qs:name":"\u00c7ataltarla",
    "qs:photos_9r":0,
    "qs:photos_sr":0,
    "qs:pop_sr":"1",
    "wof:name":"\u00c7ataltarla",
    "wof:placetype":"locality",
    "wof:population":106
},
  "geometry": {"coordinates":[40.63043,37.73213],"type":"Point"}
}