{
  "type": "Feature",
  "properties": {
    "gn:admin1_code":"71",
    "gn:asciiname":"Damlakuyu",
    "gn:country_code":"TR",
    "gn:dem":948,
    "gn:feature_class":"P",
    "gn:feature_code":"PPL",
    "gn:name":"Damlakuyu",
    "gn:population":0,
    "gn:timezone":"Europe/Istanbul",
    "iso:country":"TR",
    "name:und_x_variant":[
        "Curca",
        "Curca H\u00fcy\u00fc\u011f\u00fc",
        "\u00c7or\u00e7a",
        "Damlakuyu"
    ],
    "wof:name":"Damlakuyu",
    "wof:placetype":"locality"
},
  "geometry": {"coordinates":[32.91772,38.76092],"type":"Point"}
}