{
  "type": "Feature",
  "properties": {
    "gn:admin1_code":"75",
    "gn:asciiname":"Dikmen",
    "gn:country_code":"TR",
    "gn:dem":1448,
    "gn:feature_class":"P",
    "gn:feature_code":"PPL",
    "gn:name":"Dikmen",
    "gn:population":0,
    "gn:timezone":"Europe/Istanbul",
    "iso:country":"TR",
    "name:ceb_x_preferred":[
        "Dikmen \u0130l\u00e7esi"
    ],
    "name:deu_x_preferred":[
        "Dikmen"
    ],
    "name:fra_x_preferred":[
        "Dikmen"
    ],
    "name:mrj_x_preferred":[
        "\u0414\u0438\u043a\u043c\u0435\u043d"
    ],
    "name:msa_x_preferred":[
        "Dikmen"
    ],
    "name:nor_x_preferred":[
        "Dikmen"
    ],
    "name:swa_x_preferred":[
        "Dikmen"
    ],
    "name:tur_x_preferred":[
        "Dikmen"
    ],
    "name:und_x_variant":[
        "Yukar\u0131 Tokar\u0131z"
    ],
    "name:urd_x_preferred":[
        "\u062f\u06cc\u06a9\u0645\u06cc\u0646"
    ],
    "name:vie_x_preferred":[
        "Dikmen"
    ],
    "wof:name":"Dikmen",
    "wof:placetype":"locality"
},
  "geometry": {"coordinates":[34.11013,38.16488],"type":"Point"}
}