{
  "type": "Feature",
  "properties": {
    "gn:admin1_code":"63.0",
    "gn:asciiname":"Bir Alessebi",
    "gn:country_code":"TR",
    "gn:dem":371,
    "gn:feature_class":"P",
    "gn:feature_code":"PPL",
    "gn:name":"Bir Alessebi",
    "gn:population":0,
    "gn:timezone":"Europe/Istanbul",
    "iso:country":"TR",
    "wof:name":"Bir Alessebi",
    "wof:placetype":"locality"
},
  "geometry": {"coordinates":[39.12361,36.76],"type":"Point"}
}