{
  "type": "Feature",
  "properties": {
    "gn:country":"TR",
    "gn:fcode":"PPLX",
    "gn:pop":5800,
    "iso:country":"TR",
    "name:eng_x_preferred":[
        "Makhmutlar"
    ],
    "name:rus_x_preferred":[
        "\u041c\u0430\u0445\u043c\u0443\u0442\u043b\u0430\u0440"
    ],
    "qs:name":"Mahmutlar",
    "qs:photos_9r":0,
    "qs:photos_sr":0,
    "qs:pop_sr":"5",
    "wd:wordcount":114,
    "wof:name":"Mahmutlar",
    "wof:placetype":"neighbourhood",
    "wof:population":5800
},
  "geometry": {"coordinates":[36.19231,36.949],"type":"Point"}
}