{
  "type": "Feature",
  "properties": {
    "gn:country":"TR",
    "gn:fcode":"PPLX",
    "gn:pop":5800,
    "iso:country":"TR",
    "name:azb_x_preferred":[
        "\u0645\u0627\u062d\u0645\u0648\u062a\u0644\u0627\u0631"
    ],
    "name:ceb_x_preferred":[
        "Mahmutlar"
    ],
    "name:deu_x_preferred":[
        "Mahmutlar"
    ],
    "name:eng_x_preferred":[
        "Makhmutlar"
    ],
    "name:fas_x_preferred":[
        "\u0645\u062d\u0645\u0648\u062f\u0644\u0627\u0631"
    ],
    "name:fra_x_preferred":[
        "Mahmutlar"
    ],
    "name:hye_x_preferred":[
        "\u0544\u0561\u0570\u0574\u0578\u0582\u0569\u056c\u0561\u0580"
    ],
    "name:nld_x_preferred":[
        "Mahmutlar"
    ],
    "name:nno_x_preferred":[
        "Mahmutlar"
    ],
    "name:nor_x_preferred":[
        "Mahmutlar"
    ],
    "name:pol_x_preferred":[
        "Mahmutlar"
    ],
    "name:rus_x_preferred":[
        "\u041c\u0430\u0445\u043c\u0443\u0442\u043b\u0430\u0440"
    ],
    "name:tur_x_preferred":[
        "Mahmutlar"
    ],
    "name:vie_x_preferred":[
        "Mahmutlar"
    ],
    "name:zho_x_preferred":[
        "\u99ac\u8d6b\u7a46\u7279\u62c9\u723e"
    ],
    "qs:name":"Mahmutlar",
    "qs:photos_9r":0,
    "qs:photos_sr":0,
    "qs:pop_sr":"5",
    "wd:wordcount":114,
    "wof:name":"Mahmutlar",
    "wof:placetype":"neighbourhood",
    "wof:population":5800
},
  "geometry": {"coordinates":[36.19231,36.949],"type":"Point"}
}