{
  "type": "Feature",
  "properties": {
    "gn:admin1_code":"89",
    "gn:asciiname":"Yazikavak",
    "gn:country_code":"TR",
    "gn:dem":1060,
    "gn:feature_class":"P",
    "gn:feature_code":"PPL",
    "gn:name":"Yaz\u0131kavak",
    "gn:population":0,
    "gn:timezone":"Europe/Istanbul",
    "iso:country":"TR",
    "wof:name":"Yazikavak",
    "wof:placetype":"locality"
},
  "geometry": {"coordinates":[32.60241,40.95291],"type":"Point"}
}