{
  "type": "Feature",
  "properties": {
    "gn:admin1_code":"17.0",
    "gn:asciiname":"Uzunhizirli",
    "gn:country_code":"TR",
    "gn:dem":62,
    "gn:feature_class":"P",
    "gn:feature_code":"PPL",
    "gn:name":"Uzunh\u0131z\u0131rl\u0131",
    "gn:population":0,
    "gn:timezone":"Europe/Istanbul",
    "iso:country":"TR",
    "name:tur_x_preferred":[
        "Uzunh\u0131z\u0131rl\u0131"
    ],
    "wof:name":"Uzunhizirli",
    "wof:placetype":"locality"
},
  "geometry": {"coordinates":[26.39246,40.30229],"type":"Point"}
}