{
  "type": "Feature",
  "properties": {
    "gn:admin1_code":"31",
    "gn:asciiname":"Kizilkoy Iskan",
    "gn:country_code":"TR",
    "gn:dem":86,
    "gn:feature_class":"P",
    "gn:feature_code":"PPL",
    "gn:name":"K\u0131z\u0131lkoy \u0130skan",
    "gn:population":0,
    "gn:timezone":"Europe/Istanbul",
    "iso:country":"TR",
    "name:tur_x_preferred":[
        "K\u0131z\u0131lkoy \u0130skan"
    ],
    "wof:name":"Kizilkoy Iskan",
    "wof:placetype":"locality"
},
  "geometry": {"coordinates":[36.47613,36.44595],"type":"Point"}
}