{
  "type": "Feature",
  "properties": {
    "gn:admin1_code":"83.0",
    "gn:asciiname":"Dundarli",
    "gn:country_code":"TR",
    "gn:dem":867,
    "gn:feature_class":"P",
    "gn:feature_code":"PPL",
    "gn:name":"D\u00fcndarl\u0131",
    "gn:population":0,
    "gn:timezone":"Europe/Istanbul",
    "iso:country":"TR",
    "name:tur_x_preferred":[
        "D\u00fcndarl\u0131"
    ],
    "wof:name":"Dundarli",
    "wof:placetype":"locality"
},
  "geometry": {"coordinates":[37.39129000000001,37.24561],"type":"Point"}
}