{
  "type": "Feature",
  "properties": {
    "gn:admin1_code":"49",
    "gn:asciiname":"Sungu",
    "gn:country_code":"TR",
    "gn:dem":1263,
    "gn:feature_class":"P",
    "gn:feature_code":"PPL",
    "gn:name":"Sungu",
    "gn:population":0,
    "gn:timezone":"Europe/Istanbul",
    "iso:country":"TR",
    "name:tur_x_preferred":[
        "Sungu"
    ],
    "name:und_x_variant":[
        "Nor\u015fin",
        "Sungur"
    ],
    "wof:name":"Sungu",
    "wof:placetype":"locality"
},
  "geometry": {"coordinates":[41.60912,38.75045],"type":"Point"}
}