{
  "type": "Feature",
  "properties": {
    "gn:admin1_code":"02",
    "gn:asciiname":"Asagi Aratan",
    "gn:country_code":"TR",
    "gn:dem":810,
    "gn:feature_class":"P",
    "gn:feature_code":"PPL",
    "gn:name":"A\u015fa\u011f\u0131 Aratan",
    "gn:population":0,
    "gn:timezone":"Europe/Istanbul",
    "iso:country":"TR",
    "name:tur_x_preferred":[
        "A\u015fa\u011f\u0131 Aratan"
    ],
    "name:und_x_variant":[
        "A\u015fa\u011f\u0131aratan"
    ],
    "wof:name":"Asagi Aratan",
    "wof:placetype":"locality"
},
  "geometry": {"coordinates":[44.55271,39.82824],"type":"Point"}
}