{
  "type": "Feature",
  "properties": {
    "gn:admin1_code":"58.0",
    "gn:asciiname":"Ballidere",
    "gn:country_code":"TR",
    "gn:dem":1127,
    "gn:feature_class":"P",
    "gn:feature_code":"PPL",
    "gn:name":"Ball\u0131dere",
    "gn:population":0,
    "gn:timezone":"Europe/Istanbul",
    "iso:country":"TR",
    "name:und_x_variant":[
        "T\u0131rc\u0131k",
        "Ball\u0131dere"
    ],
    "wof:name":"Ballidere",
    "wof:placetype":"locality"
},
  "geometry": {"coordinates":[38.44731,40.1231],"type":"Point"}
}