{
  "type": "Feature",
  "properties": {
    "gn:admin1_code":"8.0",
    "gn:asciiname":"Akdamla",
    "gn:country_code":"TR",
    "gn:dem":1411,
    "gn:feature_class":"P",
    "gn:feature_code":"PPL",
    "gn:name":"Akdamla",
    "gn:population":0,
    "gn:timezone":"Europe/Istanbul",
    "iso:country":"TR",
    "name:tur_x_preferred":[
        "Akdamla"
    ],
    "wof:name":"Akdamla",
    "wof:placetype":"locality"
},
  "geometry": {"coordinates":[42.38035,41.41122],"type":"Point"}
}