{
  "type": "Feature",
  "properties": {
    "gn:admin1_code":"82.0",
    "gn:asciiname":"Mulayim",
    "gn:country_code":"TR",
    "gn:dem":1283,
    "gn:feature_class":"P",
    "gn:feature_code":"PPL",
    "gn:name":"M\u00fclayim",
    "gn:population":0,
    "gn:timezone":"Europe/Istanbul",
    "iso:country":"TR",
    "wof:name":"Mulayim",
    "wof:placetype":"locality"
},
  "geometry": {"coordinates":[33.70395,41.0204],"type":"Point"}
}