{
  "type": "Feature",
  "properties": {
    "gn:admin1_code":"59.0",
    "gn:asciiname":"Demirler",
    "gn:country_code":"TR",
    "gn:dem":147,
    "gn:feature_class":"P",
    "gn:feature_code":"PPL",
    "gn:name":"Demirler",
    "gn:population":0,
    "gn:timezone":"Europe/Istanbul",
    "iso:country":"TR",
    "name:und_x_variant":[
        "Demiler",
        "Demirler"
    ],
    "wof:name":"Demirler",
    "wof:placetype":"locality"
},
  "geometry": {"coordinates":[27.76084,41.43442],"type":"Point"}
}