{
  "type": "Feature",
  "properties": {
    "gn:admin1_code":"65",
    "gn:asciiname":"Yukari Argit",
    "gn:country_code":"TR",
    "gn:dem":2068,
    "gn:feature_class":"P",
    "gn:feature_code":"PPL",
    "gn:name":"Yukar\u0131 Arg\u0131t",
    "gn:population":0,
    "gn:timezone":"Europe/Istanbul",
    "iso:country":"TR",
    "name:tur_x_preferred":[
        "Yukar\u0131 Arg\u0131t"
    ],
    "name:und_x_variant":[
        "Yukar\u0131 Pete",
        "Yukar\u0131arg\u0131t"
    ],
    "wof:name":"Yukari Argit",
    "wof:placetype":"locality"
},
  "geometry": {"coordinates":[43.7984,39.02977],"type":"Point"}
}