{
  "type": "Feature",
  "properties": {
    "gn:admin1_code":"80",
    "gn:asciiname":"Bermikurik",
    "gn:country_code":"TR",
    "gn:dem":768,
    "gn:feature_class":"P",
    "gn:feature_code":"PPL",
    "gn:name":"Bermik\u00fcrik",
    "gn:population":0,
    "gn:timezone":"Europe/Istanbul",
    "iso:country":"TR",
    "name:tur_x_preferred":[
        "Bermik\u00fcrik"
    ],
    "wof:name":"Bermikurik",
    "wof:placetype":"locality"
},
  "geometry": {"coordinates":[42.2608,37.5032],"type":"Point"}
}