{
  "type": "Feature",
  "properties": {
    "gn:admin1_code":"70",
    "gn:asciiname":"Asagiolcekli",
    "gn:country_code":"TR",
    "gn:dem":1982,
    "gn:feature_class":"P",
    "gn:feature_code":"PPL",
    "gn:name":"A\u015fa\u011f\u0131\u00f6l\u00e7ekli",
    "gn:population":0,
    "gn:timezone":"Europe/Istanbul",
    "iso:country":"TR",
    "wof:name":"Asagiolcekli",
    "wof:placetype":"locality"
},
  "geometry": {"coordinates":[44.41083,37.54278],"type":"Point"}
}