{
  "type": "Feature",
  "properties": {
    "gn:admin1_code":"46",
    "gn:asciiname":"Haciibrahimusagi",
    "gn:cc2":"TR",
    "gn:country_code":"TR",
    "gn:dem":1577,
    "gn:feature_class":"P",
    "gn:feature_code":"PPL",
    "gn:name":"Hac\u0131ibrahimu\u015fa\u011f\u0131",
    "gn:population":0,
    "gn:timezone":"Europe/Istanbul",
    "iso:country":"TR",
    "name:und_x_variant":[
        "Hac\u0131dere",
        "Hac\u0131ibrahimu\u015fa\u011f\u0131"
    ],
    "wof:name":"Haciibrahimusagi",
    "wof:placetype":"locality"
},
  "geometry": {"coordinates":[36.76667,37.91667],"type":"Point"}
}