{
  "type": "Feature",
  "properties": {
    "gn:admin1_code":"49.0",
    "gn:asciiname":"Kardesler",
    "gn:country_code":"TR",
    "gn:dem":1524,
    "gn:feature_class":"P",
    "gn:feature_code":"PPL",
    "gn:name":"Karde\u015fler",
    "gn:population":0,
    "gn:timezone":"Europe/Istanbul",
    "iso:country":"TR",
    "name:tur_x_preferred":[
        "Karde\u015fler"
    ],
    "wof:name":"Kardesler",
    "wof:placetype":"locality"
},
  "geometry": {"coordinates":[41.18811,38.86199000000001],"type":"Point"}
}