{
  "type": "Feature",
  "properties": {
    "gn:admin1_code":"89.0",
    "gn:asciiname":"Karit",
    "gn:country_code":"TR",
    "gn:dem":311,
    "gn:feature_class":"P",
    "gn:feature_code":"PPL",
    "gn:name":"Kar\u0131t",
    "gn:population":0,
    "gn:timezone":"Europe/Istanbul",
    "iso:country":"TR",
    "wof:name":"Karit",
    "wof:placetype":"locality"
},
  "geometry": {"coordinates":[32.70854,41.21299000000001],"type":"Point"}
}