{
  "type": "Feature",
  "properties": {
    "gn:admin1_code":"86.0",
    "gn:asciiname":"Asagi Kurtoglu",
    "gn:country_code":"TR",
    "gn:dem":1976,
    "gn:feature_class":"P",
    "gn:feature_code":"PPL",
    "gn:name":"A\u015fa\u011f\u0131 Kurto\u011flu",
    "gn:population":0,
    "gn:timezone":"Europe/Istanbul",
    "iso:country":"TR",
    "name:tur_x_preferred":[
        "A\u015fa\u011f\u0131 Kurto\u011flu"
    ],
    "name:und_x_variant":[
        "A\u015fa\u011f\u0131kurto\u011flu"
    ],
    "wof:name":"Asagi Kurtoglu",
    "wof:placetype":"locality"
},
  "geometry": {"coordinates":[42.90496,41.02499],"type":"Point"}
}