{
  "type": "Feature",
  "properties": {
    "gn:admin1_code":"62",
    "gn:asciiname":"Yenibas",
    "gn:country_code":"TR",
    "gn:dem":1373,
    "gn:feature_class":"P",
    "gn:feature_code":"PPL",
    "gn:name":"Yeniba\u015f",
    "gn:population":0,
    "gn:timezone":"Europe/Istanbul",
    "iso:country":"TR",
    "wof:name":"Yenibas",
    "wof:placetype":"locality"
},
  "geometry": {"coordinates":[39.08433,39.14399],"type":"Point"}
}