{
  "type": "Feature",
  "properties": {
    "gn:country":"TR",
    "gn:fcode":"PPL",
    "gn:population":11949,
    "iso:country":"TR",
    "name:tur_x_preferred":[
        "Kumburgaz"
    ],
    "qs:name":"Kumburgaz",
    "qs:name_adm0":"Turkey",
    "qs:name_adm1":"\u0130stanbul",
    "qs:photos_9k":1,
    "qs:photos_9r":4,
    "qs:photos_all":231,
    "qs:photos_sr":0,
    "qs:placetype":"Town",
    "qs:pop_sr":"6",
    "wof:name":"Kumburgaz",
    "wof:placetype":"locality",
    "wof:population":11949
},
  "geometry": {"coordinates":[28.47715,41.02107],"type":"Point"}
}