{
  "type": "Feature",
  "properties": {
    "gn:admin1_code":"59.0",
    "gn:asciiname":"Halic",
    "gn:country_code":"TR",
    "gn:dem":223,
    "gn:feature_class":"P",
    "gn:feature_code":"PPL",
    "gn:name":"Hal\u0131\u00e7",
    "gn:population":0,
    "gn:timezone":"Europe/Istanbul",
    "iso:country":"TR",
    "name:deu_x_preferred":[
        "Halic"
    ],
    "name:tur_x_preferred":[
        "Hal\u0131\u00e7"
    ],
    "name:tur_x_variant":[
        "Hali\u00e7"
    ],
    "wof:name":"Halic",
    "wof:placetype":"locality"
},
  "geometry": {"coordinates":[26.78748,40.86623],"type":"Point"}
}