{
  "type": "Feature",
  "properties": {
    "gn:admin1_code":"09",
    "gn:asciiname":"Kullar",
    "gn:country_code":"TR",
    "gn:dem":563,
    "gn:feature_class":"P",
    "gn:feature_code":"PPL",
    "gn:name":"Kullar",
    "gn:population":0,
    "gn:timezone":"Europe/Istanbul",
    "iso:country":"TR",
    "name:tur_x_preferred":[
        "Kullar"
    ],
    "wof:name":"Kullar",
    "wof:placetype":"locality"
},
  "geometry": {"coordinates":[27.70137,37.53384000000001],"type":"Point"}
}