{
  "type": "Feature",
  "properties": {
    "gn:admin1_code":"35",
    "gn:asciiname":"Kurfalli",
    "gn:country_code":"TR",
    "gn:dem":18,
    "gn:feature_class":"P",
    "gn:feature_code":"PPL",
    "gn:name":"Kurfall\u0131",
    "gn:population":0,
    "gn:timezone":"Europe/Istanbul",
    "iso:country":"TR",
    "name:und_x_variant":[
        "Kurfal\u0131",
        "Kurfall\u0131"
    ],
    "wof:name":"Kurfalli",
    "wof:placetype":"locality"
},
  "geometry": {"coordinates":[27.07308,39.01831],"type":"Point"}
}