{
  "type": "Feature",
  "properties": {
    "gn:admin1_code":"91.0",
    "gn:asciiname":"Semerciler",
    "gn:country_code":"TR",
    "gn:dem":277,
    "gn:feature_class":"P",
    "gn:feature_code":"PPL",
    "gn:name":"Semerciler",
    "gn:population":0,
    "gn:timezone":"Europe/Istanbul",
    "iso:country":"TR",
    "wof:name":"Semerciler",
    "wof:placetype":"locality"
},
  "geometry": {"coordinates":[36.19739000000001,37.37172],"type":"Point"}
}