{
  "type": "Feature",
  "properties": {
    "gn:admin1_code":"5.0",
    "gn:asciiname":"Pusacak",
    "gn:country_code":"TR",
    "gn:dem":1129,
    "gn:feature_class":"P",
    "gn:feature_code":"PPL",
    "gn:name":"Pusacak",
    "gn:population":0,
    "gn:timezone":"Europe/Istanbul",
    "iso:country":"TR",
    "name:und_x_variant":[
        "Busac\u0131k",
        "Pusacak"
    ],
    "wof:name":"Pusacak",
    "wof:placetype":"locality"
},
  "geometry": {"coordinates":[35.15489,41.03744],"type":"Point"}
}