{
  "type": "Feature",
  "properties": {
    "gn:admin1_code":"58.0",
    "gn:asciiname":"Ortakoy",
    "gn:country_code":"TR",
    "gn:dem":993,
    "gn:feature_class":"P",
    "gn:feature_code":"PPL",
    "gn:name":"Ortak\u00f6y",
    "gn:population":0,
    "gn:timezone":"Europe/Istanbul",
    "iso:country":"TR",
    "name:eng_x_preferred":[
        "Ortak\u00f6y"
    ],
    "name:rus_x_preferred":[
        "\u041e\u0440\u0442\u0430-\u041a\u0435\u0439"
    ],
    "wof:name":"Ortakoy",
    "wof:placetype":"locality"
},
  "geometry": {"coordinates":[38.41732,40.08998],"type":"Point"}
}