{
  "type": "Feature",
  "properties": {
    "gn:admin1_code":"53.0",
    "gn:asciiname":"Yesildere",
    "gn:country_code":"TR",
    "gn:dem":622,
    "gn:feature_class":"P",
    "gn:feature_code":"PPL",
    "gn:name":"Ye\u015fildere",
    "gn:population":0,
    "gn:timezone":"Europe/Istanbul",
    "iso:country":"TR",
    "name:tur_x_preferred":[
        "Ye\u015fildere"
    ],
    "wof:name":"Yesildere",
    "wof:placetype":"locality"
},
  "geometry": {"coordinates":[40.53104,40.91213],"type":"Point"}
}