{
  "type": "Feature",
  "properties": {
    "gn:admin1_code":"2.0",
    "gn:asciiname":"Samanli",
    "gn:country_code":"TR",
    "gn:dem":646,
    "gn:feature_class":"P",
    "gn:feature_code":"PPL",
    "gn:name":"Samanl\u0131",
    "gn:population":0,
    "gn:timezone":"Europe/Istanbul",
    "iso:country":"TR",
    "name:tur_x_preferred":[
        "Samanl\u0131"
    ],
    "wof:name":"Samanli",
    "wof:placetype":"locality"
},
  "geometry": {"coordinates":[38.87086,37.86786],"type":"Point"}
}