{
  "type": "Feature",
  "properties": {
    "gn:admin1_code":"26",
    "gn:asciiname":"Gokceoglu",
    "gn:country_code":"TR",
    "gn:dem":905,
    "gn:feature_class":"P",
    "gn:feature_code":"PPL",
    "gn:name":"G\u00f6k\u00e7eo\u011flu",
    "gn:population":0,
    "gn:timezone":"Europe/Istanbul",
    "iso:country":"TR",
    "wof:name":"Gokceoglu",
    "wof:placetype":"locality"
},
  "geometry": {"coordinates":[30.87278,39.72583],"type":"Point"}
}