{
  "type": "Feature",
  "properties": {
    "gn:admin1_code":"25",
    "gn:asciiname":"Kazbel",
    "gn:country_code":"TR",
    "gn:dem":2089,
    "gn:feature_class":"P",
    "gn:feature_code":"PPL",
    "gn:name":"Kazbel",
    "gn:population":0,
    "gn:timezone":"Europe/Istanbul",
    "iso:country":"TR",
    "name:und_x_variant":[
        "Kazbe",
        "Kazbel"
    ],
    "wof:name":"Kazbel",
    "wof:placetype":"locality"
},
  "geometry": {"coordinates":[42.01077,39.5913],"type":"Point"}
}