{
  "type": "Feature",
  "properties": {
    "gn:admin1_code":"13",
    "gn:asciiname":"Bolmedere",
    "gn:country_code":"TR",
    "gn:dem":1519,
    "gn:feature_class":"P",
    "gn:feature_code":"PPL",
    "gn:name":"B\u00f6lmedere",
    "gn:population":0,
    "gn:timezone":"Europe/Istanbul",
    "iso:country":"TR",
    "wof:name":"Bolmedere",
    "wof:placetype":"locality"
},
  "geometry": {"coordinates":[42.05,38.53333],"type":"Point"}
}