{
  "type": "Feature",
  "properties": {
    "gn:admin1_code":"82.0",
    "gn:asciiname":"Hacilar",
    "gn:country_code":"TR",
    "gn:dem":1307,
    "gn:feature_class":"P",
    "gn:feature_code":"PPL",
    "gn:name":"Hac\u0131lar",
    "gn:population":0,
    "gn:timezone":"Europe/Istanbul",
    "iso:country":"TR",
    "wof:name":"Hacilar",
    "wof:placetype":"locality"
},
  "geometry": {"coordinates":[32.97514,40.70383],"type":"Point"}
}