{
  "type": "Feature",
  "properties": {
    "gn:admin1_code":"82.0",
    "gn:asciiname":"Yeniyapan",
    "gn:country_code":"TR",
    "gn:dem":776,
    "gn:feature_class":"P",
    "gn:feature_code":"PPL",
    "gn:name":"Yeniyapan",
    "gn:population":0,
    "gn:timezone":"Europe/Istanbul",
    "iso:country":"TR",
    "wof:name":"Yeniyapan",
    "wof:placetype":"locality"
},
  "geometry": {"coordinates":[34.02867,40.51366],"type":"Point"}
}