{
  "type": "Feature",
  "properties": {
    "gn:admin1_code":"25",
    "gn:asciiname":"Yaylimli",
    "gn:country_code":"TR",
    "gn:dem":1820,
    "gn:feature_class":"P",
    "gn:feature_code":"PPL",
    "gn:name":"Yayl\u0131ml\u0131",
    "gn:population":0,
    "gn:timezone":"Europe/Istanbul",
    "iso:country":"TR",
    "name:tur_x_preferred":[
        "Yayl\u0131ml\u0131"
    ],
    "wof:name":"Yaylimli",
    "wof:placetype":"locality"
},
  "geometry": {"coordinates":[40.5478,39.90483],"type":"Point"}
}