{
  "type": "Feature",
  "properties": {
    "gn:admin1_code":"07",
    "gn:asciiname":"Camlica",
    "gn:country_code":"TR",
    "gn:dem":415,
    "gn:feature_class":"P",
    "gn:feature_code":"PPL",
    "gn:name":"\u00c7aml\u0131ca",
    "gn:population":0,
    "gn:timezone":"Europe/Istanbul",
    "iso:country":"TR",
    "wof:name":"Camlica",
    "wof:placetype":"locality"
},
  "geometry": {"coordinates":[32.29001,36.42955],"type":"Point"}
}