{
  "type": "Feature",
  "properties": {
    "gn:admin1_code":"14.0",
    "gn:asciiname":"Husamettindere",
    "gn:country_code":"TR",
    "gn:dem":1173,
    "gn:feature_class":"P",
    "gn:feature_code":"PPL",
    "gn:name":"H\u00fcsamettindere",
    "gn:population":0,
    "gn:timezone":"Europe/Istanbul",
    "iso:country":"TR",
    "name:und_x_variant":[
        "Yenik\u00f6y",
        "H\u00fcsamettindereyeni K\u00f6y",
        "H\u00fcsamettindere"
    ],
    "wof:name":"Husamettindere",
    "wof:placetype":"locality"
},
  "geometry": {"coordinates":[31.11188,40.40291],"type":"Point"}
}