{
  "type": "Feature",
  "properties": {
    "gn:country":"TR",
    "gn:fcode":"PPLX",
    "gn:population":0,
    "iso:country":"TR",
    "name:ara_x_preferred":[
        "\u0634\u064a\u0631\u064a\u0646 \u0627\u064a\u0641\u0644\u0631"
    ],
    "name:cat_x_preferred":[
        "\u015eirinevler"
    ],
    "name:ceb_x_preferred":[
        "\u015eirinevler"
    ],
    "name:ces_x_preferred":[
        "\u015eirinevler"
    ],
    "name:dan_x_preferred":[
        "\u015eirinevler"
    ],
    "name:deu_x_preferred":[
        "\u015eirinevler"
    ],
    "name:eng_x_preferred":[
        "\u015eirinevler"
    ],
    "name:eus_x_preferred":[
        "\u015eirinevler"
    ],
    "name:fin_x_preferred":[
        "\u015eirinevler"
    ],
    "name:glg_x_preferred":[
        "\u015eirinevler"
    ],
    "name:ita_x_preferred":[
        "\u015eirinevler"
    ],
    "name:nld_x_preferred":[
        "\u015eirinevler"
    ],
    "name:nno_x_preferred":[
        "\u015eirinevler"
    ],
    "name:nob_x_preferred":[
        "\u015eirinevler"
    ],
    "name:oci_x_preferred":[
        "\u015eirinevler"
    ],
    "name:pol_x_preferred":[
        "\u015eirinevler"
    ],
    "name:por_x_preferred":[
        "\u015eirinevler"
    ],
    "name:ron_x_preferred":[
        "\u015eirinevler"
    ],
    "name:sco_x_preferred":[
        "\u015eirinevler"
    ],
    "name:slk_x_preferred":[
        "\u015eirinevler"
    ],
    "name:slv_x_preferred":[
        "\u015eirinevler"
    ],
    "name:spa_x_preferred":[
        "\u015eirinevler"
    ],
    "name:swe_x_preferred":[
        "\u015eirinevler"
    ],
    "name:tgl_x_preferred":[
        "\u015eirinevler"
    ],
    "name:tur_x_preferred":[
        "\u015eirinevler"
    ],
    "name:war_x_preferred":[
        "\u015eirinevler"
    ],
    "qs:name":"Sirinevler",
    "qs:name_adm0":"Turkey",
    "qs:name_adm1":"\u0130stanbul",
    "qs:photos_9r":0,
    "qs:photos_sr":0,
    "qs:placetype":"Suburb",
    "qs:pop_sr":"0",
    "wof:name":"Sirinevler",
    "wof:placetype":"neighbourhood",
    "wof:population":0
},
  "geometry": {"coordinates":[28.84503,40.99707],"type":"Point"}
}