{
  "type": "Feature",
  "properties": {
    "gn:country":"TR",
    "gn:fcode":"PPLX",
    "gn:pop":0,
    "iso:country":"TR",
    "name:baq_x_preferred":[
        "\u015eirinevler"
    ],
    "name:cat_x_preferred":[
        "\u015eirinevler"
    ],
    "name:cze_x_preferred":[
        "\u015eirinevler"
    ],
    "name:dan_x_preferred":[
        "\u015eirinevler"
    ],
    "name:dut_x_preferred":[
        "\u015eirinevler"
    ],
    "name:eng_x_preferred":[
        "\u015eirinevler"
    ],
    "name:fin_x_preferred":[
        "\u015eirinevler"
    ],
    "name:ger_x_preferred":[
        "\u015eirinevler"
    ],
    "name:glg_x_preferred":[
        "\u015eirinevler"
    ],
    "name:ita_x_preferred":[
        "\u015eirinevler"
    ],
    "name:nno_x_preferred":[
        "\u015eirinevler"
    ],
    "name:nob_x_preferred":[
        "\u015eirinevler"
    ],
    "name:oci_x_preferred":[
        "\u015eirinevler"
    ],
    "name:pol_x_preferred":[
        "\u015eirinevler"
    ],
    "name:por_x_preferred":[
        "\u015eirinevler"
    ],
    "name:rum_x_preferred":[
        "\u015eirinevler"
    ],
    "name:sco_x_preferred":[
        "\u015eirinevler"
    ],
    "name:slo_x_preferred":[
        "\u015eirinevler"
    ],
    "name:slv_x_preferred":[
        "\u015eirinevler"
    ],
    "name:spa_x_preferred":[
        "\u015eirinevler"
    ],
    "name:swe_x_preferred":[
        "\u015eirinevler"
    ],
    "name:tgl_x_preferred":[
        "\u015eirinevler"
    ],
    "name:tur_x_preferred":[
        "\u015eirinevler"
    ],
    "name:war_x_preferred":[
        "\u015eirinevler"
    ],
    "qs:name":"Sirinevler",
    "qs:name_adm0":"Turkey",
    "qs:name_adm1":"\u0130stanbul",
    "qs:photos_9r":0,
    "qs:photos_sr":0,
    "qs:placetype":"Suburb",
    "qs:pop_sr":"0",
    "wof:name":"Sirinevler",
    "wof:placetype":"neighbourhood",
    "wof:population":0
},
  "geometry": {"coordinates":[28.84503,40.99707],"type":"Point"}
}