{
  "type": "Feature",
  "properties": {
    "gn:admin1_code":"37",
    "gn:asciiname":"Cavandur",
    "gn:country_code":"TR",
    "gn:dem":638,
    "gn:feature_class":"P",
    "gn:feature_code":"PPL",
    "gn:name":"\u00c7avandur",
    "gn:population":0,
    "gn:timezone":"Europe/Istanbul",
    "iso:country":"TR",
    "wof:name":"Cavandur",
    "wof:placetype":"locality"
},
  "geometry": {"coordinates":[33.97772,41.4777],"type":"Point"}
}