{
  "type": "Feature",
  "properties": {
    "gn:admin1_code":"19.0",
    "gn:asciiname":"Kirecocagi",
    "gn:country_code":"TR",
    "gn:dem":1053,
    "gn:feature_class":"P",
    "gn:feature_code":"PPL",
    "gn:name":"Kire\u00e7oca\u011f\u0131",
    "gn:population":0,
    "gn:timezone":"Europe/Istanbul",
    "iso:country":"TR",
    "wof:name":"Kirecocagi",
    "wof:placetype":"locality"
},
  "geometry": {"coordinates":[34.69260999999999,40.45549000000001],"type":"Point"}
}