{
  "type": "Feature",
  "properties": {
    "gn:admin1_code":"70.0",
    "gn:asciiname":"Uzundere",
    "gn:country_code":"TR",
    "gn:dem":1435,
    "gn:feature_class":"P",
    "gn:feature_code":"PPL",
    "gn:name":"Uzundere",
    "gn:population":0,
    "gn:timezone":"Europe/Istanbul",
    "iso:country":"TR",
    "name:tur_x_preferred":[
        "Uzundere"
    ],
    "wof:name":"Uzundere",
    "wof:placetype":"locality"
},
  "geometry": {"coordinates":[43.87626,37.29554],"type":"Point"}
}