{
  "type": "Feature",
  "properties": {
    "gn:admin1_code":"70.0",
    "gn:asciiname":"Uzundere",
    "gn:country_code":"TR",
    "gn:dem":1435,
    "gn:feature_class":"P",
    "gn:feature_code":"PPL",
    "gn:name":"Uzundere",
    "gn:population":0,
    "gn:timezone":"Europe/Istanbul",
    "iso:country":"TR",
    "name:ceb_x_preferred":[
        "Uzundere \u0130l\u00e7esi"
    ],
    "name:deu_x_preferred":[
        "Uzundere"
    ],
    "name:fra_x_preferred":[
        "Uzundere"
    ],
    "name:kur_x_preferred":[
        "Azort"
    ],
    "name:lbe_x_preferred":[
        "\u0423\u0437\u0443\u043d\u0434\u0435\u0440\u0435"
    ],
    "name:mrj_x_preferred":[
        "\u0423\u0437\u0443\u043d\u0434\u0435\u0440\u0435"
    ],
    "name:msa_x_preferred":[
        "Uzundere"
    ],
    "name:nld_x_preferred":[
        "Uzundere"
    ],
    "name:nor_x_preferred":[
        "Uzundere"
    ],
    "name:rus_x_preferred":[
        "\u0423\u0437\u0443\u043d\u0434\u0435\u0440\u0435"
    ],
    "name:swa_x_preferred":[
        "Uzundere"
    ],
    "name:tur_x_preferred":[
        "Uzundere"
    ],
    "name:urd_x_preferred":[
        "\u0627\u0648\u0632\u0648\u0646\u062f\u06cc\u0631\u06d2"
    ],
    "name:vie_x_preferred":[
        "Uzundere"
    ],
    "wof:name":"Uzundere",
    "wof:placetype":"locality"
},
  "geometry": {"coordinates":[43.87626,37.29554],"type":"Point"}
}