{
  "type": "Feature",
  "properties": {
    "gn:admin1_code":"44",
    "gn:asciiname":"Pekisu Koyu",
    "gn:cc2":"TR",
    "gn:country_code":"TR",
    "gn:dem":1027,
    "gn:feature_class":"P",
    "gn:feature_code":"PPL",
    "gn:name":"Pek\u0131su K\u00f6y\u00fc",
    "gn:population":0,
    "gn:timezone":"Europe/Istanbul",
    "iso:country":"TR",
    "name:und_x_variant":[
        "Pek\u00fcs\u00fc",
        "Pek\u0131su K\u00f6y\u00fc"
    ],
    "wof:name":"Pekisu Koyu",
    "wof:placetype":"locality"
},
  "geometry": {"coordinates":[38.65,39.05],"type":"Point"}
}