{
  "type": "Feature",
  "properties": {
    "gn:admin1_code":"63.0",
    "gn:asciiname":"Mahmutkoy",
    "gn:country_code":"TR",
    "gn:dem":585,
    "gn:feature_class":"P",
    "gn:feature_code":"PPL",
    "gn:name":"Mahmutk\u00f6y",
    "gn:population":0,
    "gn:timezone":"Europe/Istanbul",
    "iso:country":"TR",
    "name:rus_x_preferred":[
        "Makhmutk\u00eby"
    ],
    "name:und_x_variant":[
        "Mahmutk\u00f6y"
    ],
    "wof:name":"Mahmutkoy",
    "wof:placetype":"locality"
},
  "geometry": {"coordinates":[38.32588,36.9769],"type":"Point"}
}