{
  "type": "Feature",
  "properties": {
    "gn:admin1_code":"60.0",
    "gn:asciiname":"Aydinca",
    "gn:country_code":"TR",
    "gn:dem":878,
    "gn:feature_class":"P",
    "gn:feature_code":"PPL",
    "gn:name":"Ayd\u0131nca",
    "gn:population":0,
    "gn:timezone":"Europe/Istanbul",
    "iso:country":"TR",
    "wof:name":"Aydinca",
    "wof:placetype":"locality"
},
  "geometry": {"coordinates":[36.54304000000001,40.37143],"type":"Point"}
}