{
  "type": "Feature",
  "properties": {
    "gn:admin1_code":"49.0",
    "gn:asciiname":"Erence",
    "gn:country_code":"TR",
    "gn:dem":1490,
    "gn:feature_class":"P",
    "gn:feature_code":"PPL",
    "gn:name":"Erence",
    "gn:population":0,
    "gn:timezone":"Europe/Istanbul",
    "iso:country":"TR",
    "name:tur_x_preferred":[
        "Erence"
    ],
    "wof:name":"Erence",
    "wof:placetype":"locality"
},
  "geometry": {"coordinates":[42.27038,39.32415],"type":"Point"}
}