{
  "type": "Feature",
  "properties": {
    "gn:admin1_code":"35",
    "gn:asciiname":"Kadiovacik",
    "gn:country_code":"TR",
    "gn:dem":248,
    "gn:feature_class":"P",
    "gn:feature_code":"PPL",
    "gn:name":"Kad\u0131ovac\u0131k",
    "gn:population":0,
    "gn:timezone":"Europe/Istanbul",
    "iso:country":"TR",
    "wof:name":"Kadiovacik",
    "wof:placetype":"locality"
},
  "geometry": {"coordinates":[26.55383,38.34305],"type":"Point"}
}