{
  "type": "Feature",
  "properties": {
    "gn:admin1_code":"71",
    "gn:asciiname":"Kizilgedik",
    "gn:country_code":"TR",
    "gn:dem":1357,
    "gn:feature_class":"P",
    "gn:feature_code":"PPL",
    "gn:name":"K\u0131z\u0131lgedik",
    "gn:population":0,
    "gn:timezone":"Europe/Istanbul",
    "iso:country":"TR",
    "wof:name":"Kizilgedik",
    "wof:placetype":"locality"
},
  "geometry": {"coordinates":[33.89328,37.82656],"type":"Point"}
}