{
  "type": "Feature",
  "properties": {
    "gn:country":"TR",
    "gn:fcode":"PPL",
    "gn:pop":1217,
    "iso:country":"TR",
    "qs:name":"G\u00fczelk\u00f6y",
    "qs:photos_9r":0,
    "qs:photos_sr":0,
    "qs:pop_sr":"3",
    "wof:name":"G\u00fczelk\u00f6y",
    "wof:placetype":"locality",
    "wof:population":1217
},
  "geometry": {"coordinates":[36.2348,36.59616],"type":"Point"}
}