{
  "type": "Feature",
  "properties": {
    "gn:admin1_code":"81",
    "gn:asciiname":"Hamitbey",
    "gn:country_code":"TR",
    "gn:dem":28,
    "gn:feature_class":"P",
    "gn:feature_code":"PPL",
    "gn:name":"Hamitbey",
    "gn:population":0,
    "gn:timezone":"Europe/Istanbul",
    "iso:country":"TR",
    "wof:name":"Hamitbey",
    "wof:placetype":"locality"
},
  "geometry": {"coordinates":[35.82716,37.12204000000001],"type":"Point"}
}