{
  "type": "Feature",
  "properties": {
    "gn:admin1_code":"37.0",
    "gn:asciiname":"Gorpe",
    "gn:cc2":"TR",
    "gn:country_code":"TR",
    "gn:dem":1148,
    "gn:feature_class":"P",
    "gn:feature_code":"PPL",
    "gn:name":"G\u00f6rpe",
    "gn:population":0,
    "gn:timezone":"Europe/Istanbul",
    "iso:country":"TR",
    "name:und_x_variant":[
        "G\u00f6rpek\u00f6y",
        "G\u00f6rpe"
    ],
    "wof:name":"Gorpe",
    "wof:placetype":"locality"
},
  "geometry": {"coordinates":[34.13333,41.36667],"type":"Point"}
}