{
  "type": "Feature",
  "properties": {
    "gn:admin1_code":"58",
    "gn:asciiname":"Bogazkoy",
    "gn:country_code":"TR",
    "gn:dem":1552,
    "gn:feature_class":"P",
    "gn:feature_code":"PPL",
    "gn:name":"Bo\u011fazk\u00f6y",
    "gn:population":0,
    "gn:timezone":"Europe/Istanbul",
    "iso:country":"TR",
    "wof:name":"Bogazkoy",
    "wof:placetype":"locality"
},
  "geometry": {"coordinates":[36.86667,39.41667],"type":"Point"}
}