{
  "type": "Feature",
  "properties": {
    "gn:admin1_code":"15",
    "gn:asciiname":"Karaseki",
    "gn:country_code":"TR",
    "gn:dem":839,
    "gn:feature_class":"P",
    "gn:feature_code":"PPL",
    "gn:name":"Karaseki",
    "gn:population":0,
    "gn:timezone":"Europe/Istanbul",
    "iso:country":"TR",
    "name:msa_x_preferred":[
        "Karaseki"
    ],
    "name:tur_x_preferred":[
        "Karaseki"
    ],
    "name:vie_x_preferred":[
        "Karaseki"
    ],
    "wof:name":"Karaseki",
    "wof:placetype":"locality"
},
  "geometry": {"coordinates":[30.74625,37.35317],"type":"Point"}
}