{
  "type": "Feature",
  "properties": {
    "gn:admin1_code":"85.0",
    "gn:asciiname":"Kandilli",
    "gn:country_code":"TR",
    "gn:dem":231,
    "gn:feature_class":"P",
    "gn:feature_code":"PPL",
    "gn:name":"Kandilli",
    "gn:population":0,
    "gn:timezone":"Europe/Istanbul",
    "iso:country":"TR",
    "name:diq_x_preferred":[
        "Kandilli"
    ],
    "name:msa_x_preferred":[
        "Kandilli"
    ],
    "name:tur_x_preferred":[
        "Kandilli"
    ],
    "name:vie_x_preferred":[
        "Kandilli"
    ],
    "wof:name":"Kandilli",
    "wof:placetype":"locality"
},
  "geometry": {"coordinates":[31.50883,41.35216],"type":"Point"}
}