{
  "type": "Feature",
  "properties": {
    "gn:admin1_code":"83.0",
    "gn:asciiname":"Shinkak",
    "gn:country_code":"TR",
    "gn:dem":508,
    "gn:feature_class":"P",
    "gn:feature_code":"PPL",
    "gn:name":"Shinkak",
    "gn:population":0,
    "gn:timezone":"Europe/Istanbul",
    "iso:country":"TR",
    "name:tur_x_preferred":[
        "K\u0131ra\u00e7g\u00fcl\u00fc"
    ],
    "name:und_x_variant":[
        "\u015einkak"
    ],
    "wof:name":"Shinkak",
    "wof:placetype":"locality"
},
  "geometry": {"coordinates":[37.79106,36.86075],"type":"Point"}
}