{
  "type": "Feature",
  "properties": {
    "gn:admin1_code":"80",
    "gn:asciiname":"Siltek",
    "gn:country_code":"TR",
    "gn:dem":613,
    "gn:feature_class":"P",
    "gn:feature_code":"PPL",
    "gn:name":"Siltek",
    "gn:population":0,
    "gn:timezone":"Europe/Istanbul",
    "iso:country":"TR",
    "name:tur_x_preferred":[
        "Siltek"
    ],
    "wof:name":"Siltek",
    "wof:placetype":"locality"
},
  "geometry": {"coordinates":[42.02102,37.23166],"type":"Point"}
}