{
  "type": "Feature",
  "properties": {
    "gn:admin1_code":"44",
    "gn:asciiname":"Bentkoy",
    "gn:country_code":"TR",
    "gn:dem":1017,
    "gn:feature_class":"P",
    "gn:feature_code":"PPL",
    "gn:name":"Bentk\u00f6y",
    "gn:population":0,
    "gn:timezone":"Europe/Istanbul",
    "iso:country":"TR",
    "name:tur_x_preferred":[
        "Bentk\u00f6y"
    ],
    "name:und_x_variant":[
        "Dutik\u00e2n",
        "Bent"
    ],
    "wof:name":"Bentkoy",
    "wof:placetype":"locality"
},
  "geometry": {"coordinates":[38.71981,38.35623],"type":"Point"}
}