{
  "type": "Feature",
  "properties": {
    "gn:admin1_code":"14",
    "gn:asciiname":"Bayir",
    "gn:country_code":"TR",
    "gn:dem":1163,
    "gn:feature_class":"P",
    "gn:feature_code":"PPL",
    "gn:name":"Bay\u0131r",
    "gn:population":0,
    "gn:timezone":"Europe/Istanbul",
    "iso:country":"TR",
    "wof:name":"Bayir",
    "wof:placetype":"locality"
},
  "geometry": {"coordinates":[32.07792,40.70994],"type":"Point"}
}