{
  "type": "Feature",
  "properties": {
    "gn:admin1_code":"22.0",
    "gn:asciiname":"Sultan",
    "gn:country_code":"TR",
    "gn:dem":56,
    "gn:feature_class":"P",
    "gn:feature_code":"PPL",
    "gn:name":"Sultan",
    "gn:population":0,
    "gn:timezone":"Europe/Istanbul",
    "iso:country":"TR",
    "name:und_x_variant":[
        "Sultank\u00f6y"
    ],
    "name:vie_x_preferred":[
        "Sultan"
    ],
    "wof:name":"Sultan",
    "wof:placetype":"locality"
},
  "geometry": {"coordinates":[26.45235,41.0254],"type":"Point"}
}