{
  "type": "Feature",
  "properties": {
    "gn:admin1_code":"40",
    "gn:asciiname":"Buyukabdiusagi",
    "gn:country_code":"TR",
    "gn:dem":1133,
    "gn:feature_class":"P",
    "gn:feature_code":"PPL",
    "gn:name":"B\u00fcy\u00fckabdiu\u015fa\u011f\u0131",
    "gn:population":0,
    "gn:timezone":"Europe/Istanbul",
    "iso:country":"TR",
    "wof:name":"Buyukabdiusagi",
    "wof:placetype":"locality"
},
  "geometry": {"coordinates":[33.98333,39.59664],"type":"Point"}
}