{
  "type": "Feature",
  "properties": {
    "gn:admin1_code":"2.0",
    "gn:asciiname":"Cilbogaz",
    "gn:country_code":"TR",
    "gn:dem":771,
    "gn:feature_class":"P",
    "gn:feature_code":"PPL",
    "gn:name":"\u00c7ilbo\u011faz",
    "gn:population":0,
    "gn:timezone":"Europe/Istanbul",
    "iso:country":"TR",
    "wof:name":"Cilbogaz",
    "wof:placetype":"locality"
},
  "geometry": {"coordinates":[37.87047000000001,37.71768],"type":"Point"}
}