{
  "type": "Feature",
  "properties": {
    "gn:admin1_code":"13.0",
    "gn:asciiname":"Emek",
    "gn:country_code":"TR",
    "gn:dem":1795,
    "gn:feature_class":"P",
    "gn:feature_code":"PPL",
    "gn:name":"Emek",
    "gn:population":0,
    "gn:timezone":"Europe/Istanbul",
    "iso:country":"TR",
    "name:tur_x_preferred":[
        "Emek"
    ],
    "wof:name":"Emek",
    "wof:placetype":"locality"
},
  "geometry": {"coordinates":[42.58338,38.4053],"type":"Point"}
}