{
  "type": "Feature",
  "properties": {
    "gn:admin1_code":"8.0",
    "gn:asciiname":"Sahmaroglu",
    "gn:country_code":"TR",
    "gn:dem":2021,
    "gn:feature_class":"P",
    "gn:feature_code":"PPL",
    "gn:name":"Sahmaro\u011flu",
    "gn:population":0,
    "gn:timezone":"Europe/Istanbul",
    "iso:country":"TR",
    "wof:name":"Sahmaroglu",
    "wof:placetype":"locality"
},
  "geometry": {"coordinates":[42.51667,41.26667],"type":"Point"}
}