{
  "type": "Feature",
  "properties": {
    "gn:admin1_code":"55.0",
    "gn:asciiname":"Safali",
    "gn:country_code":"TR",
    "gn:dem":63,
    "gn:feature_class":"P",
    "gn:feature_code":"PPL",
    "gn:name":"Safal\u0131",
    "gn:population":0,
    "gn:timezone":"Europe/Istanbul",
    "iso:country":"TR",
    "wof:name":"Safali",
    "wof:placetype":"locality"
},
  "geometry": {"coordinates":[36.70966,41.15417],"type":"Point"}
}