{
  "type": "Feature",
  "properties": {
    "gn:admin1_code":"33",
    "gn:asciiname":"Ulugbey",
    "gn:cc2":"TR",
    "gn:country_code":"TR",
    "gn:dem":1055,
    "gn:feature_class":"P",
    "gn:feature_code":"PPL",
    "gn:name":"Ulu\u011fbey",
    "gn:population":0,
    "gn:timezone":"Europe/Istanbul",
    "iso:country":"TR",
    "name:und_x_variant":[
        "\u0130leg\u00f6p",
        "Ulubey",
        "\u0130leg\u00fcp",
        "Ulu\u011fbey"
    ],
    "wof:name":"Ulugbey",
    "wof:placetype":"locality"
},
  "geometry": {"coordinates":[30.53861,38.13917],"type":"Point"}
}