{
  "type": "Feature",
  "properties": {
    "gn:admin1_code":"71",
    "gn:asciiname":"Susuz",
    "gn:country_code":"TR",
    "gn:dem":1102,
    "gn:feature_class":"P",
    "gn:feature_code":"PPL",
    "gn:name":"Susuz",
    "gn:population":0,
    "gn:timezone":"Europe/Istanbul",
    "iso:country":"TR",
    "wof:name":"Susuz",
    "wof:placetype":"locality"
},
  "geometry": {"coordinates":[31.94297000000001,37.30584],"type":"Point"}
}