{
  "type": "Feature",
  "properties": {
    "gn:admin1_code":"71",
    "gn:asciiname":"Susuz",
    "gn:country_code":"TR",
    "gn:dem":1102,
    "gn:feature_class":"P",
    "gn:feature_code":"PPL",
    "gn:name":"Susuz",
    "gn:population":0,
    "gn:timezone":"Europe/Istanbul",
    "iso:country":"TR",
    "name:aze_x_preferred":[
        "Susuz il\u00e7\u0259si"
    ],
    "name:ceb_x_preferred":[
        "Susuz \u0130l\u00e7esi"
    ],
    "name:deu_x_preferred":[
        "Susuz"
    ],
    "name:diq_x_preferred":[
        "Susuz"
    ],
    "name:fra_x_preferred":[
        "Susuz"
    ],
    "name:kur_x_preferred":[
        "Cilaw\u00fbz"
    ],
    "name:mrj_x_preferred":[
        "\u0421\u0443\u0441\u0443\u0437"
    ],
    "name:msa_x_preferred":[
        "Susuz"
    ],
    "name:nld_x_preferred":[
        "Susuz"
    ],
    "name:nor_x_preferred":[
        "Susuz"
    ],
    "name:pnb_x_preferred":[
        "\u0636\u0644\u0639 \u0633\u0648\u0633\u0648\u0632"
    ],
    "name:rus_x_preferred":[
        "\u0421\u0443\u0441\u0443\u0437"
    ],
    "name:swa_x_preferred":[
        "Susuz"
    ],
    "name:tur_x_preferred":[
        "Susuz"
    ],
    "name:urd_x_preferred":[
        "\u0633\u0648\u0633\u0648\u0632"
    ],
    "name:vie_x_preferred":[
        "Susuz"
    ],
    "wof:name":"Susuz",
    "wof:placetype":"locality"
},
  "geometry": {"coordinates":[31.94297000000001,37.30584],"type":"Point"}
}