{
  "type": "Feature",
  "properties": {
    "gn:admin1_code":"16.0",
    "gn:asciiname":"Karacaahmet",
    "gn:country_code":"TR",
    "gn:dem":355,
    "gn:feature_class":"P",
    "gn:feature_code":"PPL",
    "gn:name":"Karacaahmet",
    "gn:population":0,
    "gn:timezone":"Europe/Istanbul",
    "iso:country":"TR",
    "name:tur_x_preferred":[
        "Karacaahmet"
    ],
    "wof:name":"Karacaahmet",
    "wof:placetype":"locality"
},
  "geometry": {"coordinates":[29.57806,40.18919],"type":"Point"}
}