{
  "type": "Feature",
  "properties": {
    "gn:admin1_code":"62",
    "gn:asciiname":"Dereboyu",
    "gn:country_code":"TR",
    "gn:dem":1681,
    "gn:feature_class":"P",
    "gn:feature_code":"PPL",
    "gn:name":"Dereboyu",
    "gn:population":0,
    "gn:timezone":"Europe/Istanbul",
    "iso:country":"TR",
    "name:tur_x_preferred":[
        "Dereboyu"
    ],
    "name:und_x_variant":[
        "Danzik"
    ],
    "wof:name":"Dereboyu",
    "wof:placetype":"locality"
},
  "geometry": {"coordinates":[39.79832,39.4547],"type":"Point"}
}