{
  "type": "Feature",
  "properties": {
    "gn:admin1_code":"07",
    "gn:asciiname":"Minareli",
    "gn:cc2":"TR",
    "gn:country_code":"TR",
    "gn:dem":852,
    "gn:feature_class":"P",
    "gn:feature_code":"PPL",
    "gn:name":"Minareli",
    "gn:population":0,
    "gn:timezone":"Europe/Istanbul",
    "iso:country":"TR",
    "name:msa_x_preferred":[
        "Minareli"
    ],
    "name:tur_x_preferred":[
        "Minareli"
    ],
    "name:und_x_variant":[
        "Minarelik\u00f6y"
    ],
    "name:vie_x_preferred":[
        "Minareli"
    ],
    "wof:name":"Minareli",
    "wof:placetype":"locality"
},
  "geometry": {"coordinates":[31.67583,37.01944],"type":"Point"}
}