{
  "type": "Feature",
  "properties": {
    "gn:admin1_code":"63.0",
    "gn:asciiname":"Keferkup",
    "gn:country_code":"TR",
    "gn:dem":508,
    "gn:feature_class":"P",
    "gn:feature_code":"PPL",
    "gn:name":"Keferkup",
    "gn:population":0,
    "gn:timezone":"Europe/Istanbul",
    "iso:country":"TR",
    "wof:name":"Keferkup",
    "wof:placetype":"locality"
},
  "geometry": {"coordinates":[38.36961,36.98899],"type":"Point"}
}