{
  "type": "Feature",
  "properties": {
    "gn:admin1_code":"68",
    "gn:asciiname":"Deliler",
    "gn:country_code":"TR",
    "gn:dem":1259,
    "gn:feature_class":"P",
    "gn:feature_code":"PPL",
    "gn:name":"Deliler",
    "gn:population":0,
    "gn:timezone":"Europe/Istanbul",
    "iso:country":"TR",
    "wof:name":"Deliler",
    "wof:placetype":"locality"
},
  "geometry": {"coordinates":[33.675,39.00297],"type":"Point"}
}