{
  "type": "Feature",
  "properties": {
    "gn:admin1_code":"61.0",
    "gn:asciiname":"Ornekalan",
    "gn:country_code":"TR",
    "gn:dem":897,
    "gn:feature_class":"P",
    "gn:feature_code":"PPL",
    "gn:name":"\u00d6rnekalan",
    "gn:population":0,
    "gn:timezone":"Europe/Istanbul",
    "iso:country":"TR",
    "name:tur_x_preferred":[
        "\u00d6rnekalan"
    ],
    "wof:name":"Ornekalan",
    "wof:placetype":"locality"
},
  "geometry": {"coordinates":[39.60993,40.83972],"type":"Point"}
}