{
  "type": "Feature",
  "properties": {
    "gn:admin1_code":"85.0",
    "gn:asciiname":"Baglik",
    "gn:country_code":"TR",
    "gn:dem":74,
    "gn:feature_class":"P",
    "gn:feature_code":"PPL",
    "gn:name":"Ba\u011fl\u0131k",
    "gn:population":0,
    "gn:timezone":"Europe/Istanbul",
    "iso:country":"TR",
    "name:und_x_variant":[
        "Baglar",
        "Ba\u011fl\u0131k"
    ],
    "wof:name":"Baglik",
    "wof:placetype":"locality"
},
  "geometry": {"coordinates":[31.81383,41.46767],"type":"Point"}
}