{
  "type": "Feature",
  "properties": {
    "gn:country":"TR",
    "gn:fcode":"PPL",
    "gn:population":15189,
    "iso:country":"TR",
    "name:cat_x_preferred":[
        "Fo\u00e7a"
    ],
    "name:ceb_x_preferred":[
        "Fo\u00e7a \u0130l\u00e7esi"
    ],
    "name:cym_x_preferred":[
        "Fo\u00e7a"
    ],
    "name:deu_x_preferred":[
        "Fo\u00e7a"
    ],
    "name:diq_x_preferred":[
        "Fo\u00e7a"
    ],
    "name:eng_x_historical":[
        "Phogia"
    ],
    "name:eng_x_preferred":[
        "Fo\u00e7a"
    ],
    "name:eng_x_variant":[
        "Phogia"
    ],
    "name:epo_x_preferred":[
        "Fo\u00e7a"
    ],
    "name:fas_x_preferred":[
        "\u0641\u0648\u0686\u0627"
    ],
    "name:fra_x_preferred":[
        "Fo\u00e7a"
    ],
    "name:hun_x_preferred":[
        "Fo\u00e7a"
    ],
    "name:hye_x_preferred":[
        "\u0556\u0578\u0579\u0561"
    ],
    "name:jpn_x_preferred":[
        "\u30d5\u30a9\u30c1\u30e3"
    ],
    "name:kor_x_preferred":[
        "\ud3ec\ucc28"
    ],
    "name:lit_x_preferred":[
        "Fo\u010da"
    ],
    "name:mrj_x_preferred":[
        "\u0424\u043e\u0447\u0430"
    ],
    "name:msa_x_preferred":[
        "Fo\u00e7a"
    ],
    "name:nan_x_preferred":[
        "Fo\u00e7a"
    ],
    "name:nld_x_preferred":[
        "Fo\u00e7a"
    ],
    "name:nob_x_preferred":[
        "Fo\u00e7a"
    ],
    "name:ron_x_preferred":[
        "Fo\u00e7a"
    ],
    "name:rus_x_preferred":[
        "\u0424\u043e\u0447\u0430"
    ],
    "name:spa_x_preferred":[
        "Fo\u00e7a"
    ],
    "name:swa_x_preferred":[
        "Fo\u00e7a"
    ],
    "name:swe_x_preferred":[
        "Fo\u00e7a"
    ],
    "name:tur_x_preferred":[
        "Fo\u00e7a"
    ],
    "name:und_x_variant":[
        "Karafo\u00e7a"
    ],
    "name:vie_x_preferred":[
        "Fo\u00e7a"
    ],
    "name:zho_x_preferred":[
        "\u798f\u5361"
    ],
    "qs:name":"Fo\u00e7a",
    "qs:photos_9r":0,
    "qs:photos_sr":0,
    "qs:pop_sr":"6",
    "wd:wordcount":622,
    "wof:name":"Fo\u00e7a",
    "wof:placetype":"locality",
    "wof:population":15189
},
  "geometry": {"coordinates":[26.75656,38.6703],"type":"Point"}
}