{
  "type": "Feature",
  "properties": {
    "gn:country":"TR",
    "gn:fcode":"PPL",
    "gn:pop":15189,
    "iso:country":"TR",
    "name:eng_x_historical":[
        "Phogia"
    ],
    "name:eng_x_preferred":[
        "Fo\u00e7a"
    ],
    "name:eng_x_variant":[
        "Phogia"
    ],
    "name:unk_x_variant":[
        "Karafo\u00e7a"
    ],
    "qs:name":"Fo\u00e7a",
    "qs:photos_9r":0,
    "qs:photos_sr":0,
    "qs:pop_sr":"6",
    "wd:wordcount":622,
    "wof:name":"Fo\u00e7a",
    "wof:placetype":"locality",
    "wof:population":15189
},
  "geometry": {"coordinates":[26.75656,38.6703],"type":"Point"}
}