{
  "type": "Feature",
  "properties": {
    "gn:admin1_code":"03",
    "gn:asciiname":"Kuruca",
    "gn:country_code":"TR",
    "gn:dem":944,
    "gn:feature_class":"P",
    "gn:feature_code":"PPL",
    "gn:name":"Kuruca",
    "gn:population":0,
    "gn:timezone":"Europe/Istanbul",
    "iso:country":"TR",
    "wof:name":"Kuruca",
    "wof:placetype":"locality"
},
  "geometry": {"coordinates":[31.18063,39.09527],"type":"Point"}
}