{
  "type": "Feature",
  "properties": {
    "gn:admin1_code":"23",
    "gn:asciiname":"Damlapinar",
    "gn:country_code":"TR",
    "gn:dem":1196,
    "gn:feature_class":"P",
    "gn:feature_code":"PPL",
    "gn:name":"Damlap\u0131nar",
    "gn:population":0,
    "gn:timezone":"Europe/Istanbul",
    "iso:country":"TR",
    "name:tur_x_preferred":[
        "Damlap\u0131nar"
    ],
    "wof:name":"Damlapinar",
    "wof:placetype":"locality"
},
  "geometry": {"coordinates":[40.06778,38.69326],"type":"Point"}
}