{
  "type": "Feature",
  "properties": {
    "gn:admin1_code":"71",
    "gn:asciiname":"Buyuk Aslama",
    "gn:country_code":"TR",
    "gn:dem":1004,
    "gn:feature_class":"P",
    "gn:feature_code":"PPL",
    "gn:name":"B\u00fcy\u00fck A\u015flama",
    "gn:population":0,
    "gn:timezone":"Europe/Istanbul",
    "iso:country":"TR",
    "name:und_x_variant":[
        "B\u00fcy\u00fck A\u015flama",
        "B\u00fcy\u00fcka\u015flama"
    ],
    "wof:name":"Buyuk Aslama",
    "wof:placetype":"locality"
},
  "geometry": {"coordinates":[33.13644,37.64722],"type":"Point"}
}