{
  "type": "Feature",
  "properties": {
    "gn:admin1_code":"21",
    "gn:asciiname":"Malyas",
    "gn:country_code":"TR",
    "gn:dem":696,
    "gn:feature_class":"P",
    "gn:feature_code":"PPL",
    "gn:name":"Malyas",
    "gn:population":0,
    "gn:timezone":"Europe/Istanbul",
    "iso:country":"TR",
    "name:und_x_variant":[
        "Mecinisar",
        "Mecnesar",
        "Malyas",
        "Mecnisar"
    ],
    "wof:name":"Malyas",
    "wof:placetype":"locality"
},
  "geometry": {"coordinates":[40.66043,38.11403],"type":"Point"}
}