{
  "type": "Feature",
  "properties": {
    "gn:admin1_code":"43",
    "gn:asciiname":"Yeni Pinar",
    "gn:country_code":"TR",
    "gn:dem":855,
    "gn:feature_class":"P",
    "gn:feature_code":"PPL",
    "gn:name":"Yeni P\u0131nar",
    "gn:population":0,
    "gn:timezone":"Europe/Istanbul",
    "iso:country":"TR",
    "name:tur_x_preferred":[
        "Yeni P\u0131nar"
    ],
    "name:tur_x_variant":[
        "Arap\u015fah"
    ],
    "wof:name":"Yeni Pinar",
    "wof:placetype":"locality"
},
  "geometry": {"coordinates":[29.16031,39.20911],"type":"Point"}
}