{
  "type": "Feature",
  "properties": {
    "gn:admin1_code":"72.0",
    "gn:asciiname":"Akkoc",
    "gn:country_code":"TR",
    "gn:dem":502,
    "gn:feature_class":"P",
    "gn:feature_code":"PPL",
    "gn:name":"Akko\u00e7",
    "gn:population":0,
    "gn:timezone":"Europe/Istanbul",
    "iso:country":"TR",
    "name:tur_x_preferred":[
        "Akko\u00e7"
    ],
    "wof:name":"Akkoc",
    "wof:placetype":"locality"
},
  "geometry": {"coordinates":[40.39622,37.2217],"type":"Point"}
}