{
  "type": "Feature",
  "properties": {
    "gn:admin1_code":"25.0",
    "gn:asciiname":"Aktas",
    "gn:country_code":"TR",
    "gn:dem":1958,
    "gn:feature_class":"P",
    "gn:feature_code":"PPL",
    "gn:name":"Akta\u015f",
    "gn:population":0,
    "gn:timezone":"Europe/Istanbul",
    "iso:country":"TR",
    "name:fas_x_preferred":[
        "\u0627\u06a9\u062a\u0627\u0633"
    ],
    "name:kaz_x_preferred":[
        "\u0410\u049b\u0442\u0430\u0441"
    ],
    "name:mkd_x_preferred":[
        "\u0410\u043a\u0442\u0430\u0441"
    ],
    "name:msa_x_preferred":[
        "Aktas"
    ],
    "name:rus_x_preferred":[
        "\u0410\u043a\u0442\u0430\u0441"
    ],
    "name:ukr_x_preferred":[
        "\u0410\u043a\u0442\u0430\u0441"
    ],
    "name:und_x_variant":[
        "Pethar",
        "Akta\u015f"
    ],
    "wof:name":"Aktas",
    "wof:placetype":"locality"
},
  "geometry": {"coordinates":[41.53582,40.34336],"type":"Point"}
}