{
  "type": "Feature",
  "properties": {
    "gn:admin1_code":"07",
    "gn:asciiname":"Ova",
    "gn:country_code":"TR",
    "gn:dem":8,
    "gn:feature_class":"P",
    "gn:feature_code":"PPL",
    "gn:name":"Ova",
    "gn:population":0,
    "gn:timezone":"Europe/Istanbul",
    "iso:country":"TR",
    "name:und_x_variant":[
        "Ovak\u00f6y",
        "Ova"
    ],
    "wof:name":"Ova",
    "wof:placetype":"locality"
},
  "geometry": {"coordinates":[29.3232,36.30887],"type":"Point"}
}