{
  "type": "Feature",
  "properties": {
    "gn:admin1_code":"8.0",
    "gn:asciiname":"Suluklu",
    "gn:country_code":"TR",
    "gn:dem":340,
    "gn:feature_class":"P",
    "gn:feature_code":"PPL",
    "gn:name":"S\u00fcl\u00fckl\u00fc",
    "gn:population":0,
    "gn:timezone":"Europe/Istanbul",
    "iso:country":"TR",
    "name:tur_x_preferred":[
        "S\u00fcl\u00fckl\u00fc"
    ],
    "wof:name":"Suluklu",
    "wof:placetype":"locality"
},
  "geometry": {"coordinates":[41.65134000000001,41.32646],"type":"Point"}
}