{
  "type": "Feature",
  "properties": {
    "gn:admin1_code":"68.0",
    "gn:asciiname":"Adakoy",
    "gn:country_code":"TR",
    "gn:dem":1112,
    "gn:feature_class":"P",
    "gn:feature_code":"PPL",
    "gn:name":"Adak\u00f6y",
    "gn:population":0,
    "gn:timezone":"Europe/Istanbul",
    "iso:country":"TR",
    "wof:name":"Adakoy",
    "wof:placetype":"locality"
},
  "geometry": {"coordinates":[32.38851,40.37017],"type":"Point"}
}