{
  "type": "Feature",
  "properties": {
    "gn:admin1_code":"32",
    "gn:asciiname":"Kapizli",
    "gn:country_code":"TR",
    "gn:dem":6,
    "gn:feature_class":"P",
    "gn:feature_code":"PPL",
    "gn:name":"Kap\u0131zl\u0131",
    "gn:population":0,
    "gn:timezone":"Europe/Istanbul",
    "iso:country":"TR",
    "name:tur_x_preferred":[
        "Kap\u0131zl\u0131"
    ],
    "name:tur_x_variant":[
        "Persenti",
        "Sazba\u015f\u0131"
    ],
    "wof:name":"Kapizli",
    "wof:placetype":"locality"
},
  "geometry": {"coordinates":[34.07306,36.40847],"type":"Point"}
}