{
  "type": "Feature",
  "properties": {
    "gn:admin1_code":"14",
    "gn:asciiname":"Kurtlar",
    "gn:country_code":"TR",
    "gn:dem":1260,
    "gn:feature_class":"P",
    "gn:feature_code":"PPL",
    "gn:name":"Kurtlar",
    "gn:population":0,
    "gn:timezone":"Europe/Istanbul",
    "iso:country":"TR",
    "wof:name":"Kurtlar",
    "wof:placetype":"locality"
},
  "geometry": {"coordinates":[32.32485,40.73701],"type":"Point"}
}