{
  "type": "Feature",
  "properties": {
    "gn:admin1_code":"26",
    "gn:asciiname":"Yumaklica",
    "gn:country_code":"TR",
    "gn:dem":1308,
    "gn:feature_class":"P",
    "gn:feature_code":"PPL",
    "gn:name":"Yumakl\u0131ca",
    "gn:population":0,
    "gn:timezone":"Europe/Istanbul",
    "iso:country":"TR",
    "wof:name":"Yumaklica",
    "wof:placetype":"locality"
},
  "geometry": {"coordinates":[31.15028,39.99306],"type":"Point"}
}