{
  "type": "Feature",
  "properties": {
    "gn:country":"TR",
    "gn:fcode":"PPL",
    "gn:pop":256,
    "iso:country":"TR",
    "name:unk_x_variant":[
        "Kyvyrdzhik"
    ],
    "qs:name":"K\u0131v\u0131rc\u0131k",
    "qs:photos_9r":0,
    "qs:photos_sr":0,
    "qs:pop_sr":"2",
    "wof:name":"K\u0131v\u0131rc\u0131k",
    "wof:placetype":"locality",
    "wof:population":256
},
  "geometry": {"coordinates":[37.95139,36.83111],"type":"Point"}
}