{
  "type": "Feature",
  "properties": {
    "gn:admin1_code":"31.0",
    "gn:asciiname":"Gavurkoy",
    "gn:country_code":"TR",
    "gn:dem":85,
    "gn:feature_class":"P",
    "gn:feature_code":"PPL",
    "gn:name":"G\u00e2vurk\u00f6y",
    "gn:population":0,
    "gn:timezone":"Europe/Istanbul",
    "iso:country":"TR",
    "name:tur_x_preferred":[
        "G\u00e2vurk\u00f6y"
    ],
    "wof:name":"Gavurkoy",
    "wof:placetype":"locality"
},
  "geometry": {"coordinates":[36.46278,36.43028],"type":"Point"}
}