{
  "type": "Feature",
  "properties": {
    "gn:admin1_code":"03",
    "gn:asciiname":"Cumali",
    "gn:country_code":"TR",
    "gn:dem":1058,
    "gn:feature_class":"P",
    "gn:feature_code":"PPL",
    "gn:name":"Cumal\u0131",
    "gn:population":0,
    "gn:timezone":"Europe/Istanbul",
    "iso:country":"TR",
    "wof:name":"Cumali",
    "wof:placetype":"locality"
},
  "geometry": {"coordinates":[30.31522,38.98797],"type":"Point"}
}