{
  "type": "Feature",
  "properties": {
    "gn:admin1_code":"49.0",
    "gn:asciiname":"Sipikan",
    "gn:country_code":"TR",
    "gn:dem":2256,
    "gn:feature_class":"P",
    "gn:feature_code":"PPL",
    "gn:name":"Sipikan",
    "gn:population":0,
    "gn:timezone":"Europe/Istanbul",
    "iso:country":"TR",
    "name:tur_x_preferred":[
        "Sipikan"
    ],
    "wof:name":"Sipikan",
    "wof:placetype":"locality"
},
  "geometry": {"coordinates":[41.40549,38.71799],"type":"Point"}
}