{
  "type": "Feature",
  "properties": {
    "gn:admin1_code":"44.0",
    "gn:asciiname":"Korukler",
    "gn:country_code":"TR",
    "gn:dem":1694,
    "gn:feature_class":"P",
    "gn:feature_code":"PPL",
    "gn:name":"K\u00f6r\u00fckler",
    "gn:population":0,
    "gn:timezone":"Europe/Istanbul",
    "iso:country":"TR",
    "name:tur_x_preferred":[
        "K\u00f6r\u00fckler"
    ],
    "name:und_x_variant":[
        "K\u00f6l\u00fckler"
    ],
    "wof:name":"Korukler",
    "wof:placetype":"locality"
},
  "geometry": {"coordinates":[37.76261,38.56628],"type":"Point"}
}