{
  "type": "Feature",
  "properties": {
    "iso:country":"TR",
    "name:tur_x_preferred":[
        "G\u00fcrsel"
    ],
    "wof:name":"Gursel",
    "wof:placetype":"neighbourhood"
},
  "geometry": {"coordinates":[28.9729792206152,41.07120939819745],"type":"Point"}
}