{
  "type": "Feature",
  "properties": {
    "gn:admin1_code":"48",
    "gn:asciiname":"Camkoy",
    "gn:country_code":"TR",
    "gn:dem":551,
    "gn:feature_class":"P",
    "gn:feature_code":"PPL",
    "gn:name":"\u00c7amk\u00f6y",
    "gn:population":0,
    "gn:timezone":"Europe/Istanbul",
    "iso:country":"TR",
    "name:tur_x_preferred":[
        "\u00c7amk\u00f6y"
    ],
    "wof:name":"Camkoy",
    "wof:placetype":"locality"
},
  "geometry": {"coordinates":[28.21171,37.44965],"type":"Point"}
}