{
  "type": "Feature",
  "properties": {
    "gn:admin1_code":"63",
    "gn:asciiname":"Meshketir",
    "gn:country_code":"TR",
    "gn:dem":601,
    "gn:feature_class":"P",
    "gn:feature_code":"PPL",
    "gn:name":"Meshketir",
    "gn:population":0,
    "gn:timezone":"Europe/Istanbul",
    "iso:country":"TR",
    "wof:name":"Meshketir",
    "wof:placetype":"locality"
},
  "geometry": {"coordinates":[38.61423,37.0064],"type":"Point"}
}