{
  "type": "Feature",
  "properties": {
    "gn:admin1_code":"71",
    "gn:asciiname":"Karayuruklu",
    "gn:country_code":"TR",
    "gn:dem":1029,
    "gn:feature_class":"P",
    "gn:feature_code":"PPL",
    "gn:name":"Karay\u00fcr\u00fckl\u00fc",
    "gn:population":0,
    "gn:timezone":"Europe/Istanbul",
    "iso:country":"TR",
    "name:und_x_variant":[
        "Karay\u00fcr\u00fckl\u00fc",
        "Karay\u00f6r\u00fckl\u00fc"
    ],
    "wof:name":"Karayuruklu",
    "wof:placetype":"locality"
},
  "geometry": {"coordinates":[32.27889,38.31531],"type":"Point"}
}