{
  "type": "Feature",
  "properties": {
    "gn:admin1_code":"03",
    "gn:asciiname":"Ikizce",
    "gn:country_code":"TR",
    "gn:dem":926,
    "gn:feature_class":"P",
    "gn:feature_code":"PPL",
    "gn:name":"\u0130kizce",
    "gn:population":0,
    "gn:timezone":"Europe/Istanbul",
    "iso:country":"TR",
    "name:und_x_variant":[
        "\u0130kizce",
        "Ekizce"
    ],
    "wof:name":"Ikizce",
    "wof:placetype":"locality"
},
  "geometry": {"coordinates":[31.24577,39.04524],"type":"Point"}
}