{
  "type": "Feature",
  "properties": {
    "gn:country":"TR",
    "gn:fcode":"PPL",
    "gn:pop":164,
    "iso:country":"TR",
    "name:baq_x_preferred":[
        "Burhaniye"
    ],
    "name:cat_x_preferred":[
        "Burhaniye"
    ],
    "name:cze_x_preferred":[
        "Burhaniye"
    ],
    "name:dan_x_preferred":[
        "Burhaniye"
    ],
    "name:dut_x_preferred":[
        "Burhaniye"
    ],
    "name:eng_x_preferred":[
        "Burhaniye"
    ],
    "name:fin_x_preferred":[
        "Burhaniye"
    ],
    "name:fre_x_preferred":[
        "Burhaniye"
    ],
    "name:hun_x_preferred":[
        "Burhaniye"
    ],
    "name:ind_x_preferred":[
        "Burhaniye"
    ],
    "name:ita_x_preferred":[
        "Burhaniye"
    ],
    "name:nno_x_preferred":[
        "Burhaniye"
    ],
    "name:nob_x_preferred":[
        "Burhaniye"
    ],
    "name:oci_x_preferred":[
        "Burhaniye"
    ],
    "name:pol_x_preferred":[
        "Burhaniye"
    ],
    "name:por_x_preferred":[
        "Burhaniye"
    ],
    "name:rum_x_preferred":[
        "Burhaniye"
    ],
    "name:slo_x_preferred":[
        "Burhaniye"
    ],
    "name:slv_x_preferred":[
        "Burhaniye"
    ],
    "name:spa_x_preferred":[
        "Burhaniye"
    ],
    "name:swe_x_preferred":[
        "Burhaniye"
    ],
    "name:tgl_x_preferred":[
        "Burhaniye"
    ],
    "name:tur_x_preferred":[
        "Burhaniye"
    ],
    "name:vie_x_preferred":[
        "Burhaniye"
    ],
    "name:war_x_preferred":[
        "Burhaniye"
    ],
    "qs:name":"Burhaniye",
    "qs:photos_9r":0,
    "qs:photos_sr":0,
    "qs:pop_sr":"1",
    "wd:wordcount":328,
    "wof:name":"Burhaniye",
    "wof:placetype":"locality",
    "wof:population":164
},
  "geometry": {"coordinates":[29.40705,40.56892],"type":"Point"}
}