{
  "type": "Feature",
  "properties": {
    "gn:admin1_code":"64",
    "gn:asciiname":"Guney",
    "gn:country_code":"TR",
    "gn:dem":860,
    "gn:feature_class":"P",
    "gn:feature_code":"PPL",
    "gn:name":"G\u00fcney",
    "gn:population":0,
    "gn:timezone":"Europe/Istanbul",
    "iso:country":"TR",
    "name:und_x_variant":[
        "G\u00fcneyk\u00f6y",
        "G\u00fcney"
    ],
    "wof:name":"Guney",
    "wof:placetype":"locality"
},
  "geometry": {"coordinates":[28.86856,38.39094],"type":"Point"}
}