{
  "type": "Feature",
  "properties": {
    "gn:admin1_code":"35",
    "gn:asciiname":"Otuzbirler",
    "gn:country_code":"TR",
    "gn:dem":555,
    "gn:feature_class":"P",
    "gn:feature_code":"PPL",
    "gn:name":"Otuzbirler",
    "gn:population":0,
    "gn:timezone":"Europe/Istanbul",
    "iso:country":"TR",
    "name:und_x_variant":[
        "Otuzbirler Yaylasi",
        "Otuzbirler"
    ],
    "wof:name":"Otuzbirler",
    "wof:placetype":"locality"
},
  "geometry": {"coordinates":[27.61563,38.24127],"type":"Point"}
}