{
  "type": "Feature",
  "properties": {
    "gn:admin1_code":"8.0",
    "gn:asciiname":"Vezirkoy",
    "gn:country_code":"TR",
    "gn:dem":587,
    "gn:feature_class":"P",
    "gn:feature_code":"PPL",
    "gn:name":"Vezirk\u00f6y",
    "gn:population":0,
    "gn:timezone":"Europe/Istanbul",
    "iso:country":"TR",
    "name:ceb_x_preferred":[
        "Vezirk\u00f6y"
    ],
    "name:msa_x_preferred":[
        "Vezirk\u00f6y"
    ],
    "name:tur_x_preferred":[
        "Vezirk\u00f6y"
    ],
    "name:und_x_variant":[
        "Vezirk\u00f6y"
    ],
    "name:vie_x_preferred":[
        "Vezirk\u00f6y"
    ],
    "wof:name":"Vezirkoy",
    "wof:placetype":"locality"
},
  "geometry": {"coordinates":[41.85389,41.20069],"type":"Point"}
}