{
  "type": "Feature",
  "properties": {
    "gn:admin1_code":"55",
    "gn:asciiname":"Findicak",
    "gn:country_code":"TR",
    "gn:dem":707,
    "gn:feature_class":"P",
    "gn:feature_code":"PPL",
    "gn:name":"F\u0131nd\u0131cak",
    "gn:population":0,
    "gn:timezone":"Europe/Istanbul",
    "iso:country":"TR",
    "name:tur_x_preferred":[
        "F\u0131nd\u0131cak"
    ],
    "wof:name":"Findicak",
    "wof:placetype":"locality"
},
  "geometry": {"coordinates":[36.38354,41.12676],"type":"Point"}
}