{
  "type": "Feature",
  "properties": {
    "gn:admin1_code":"26",
    "gn:asciiname":"Ima Yaylasi",
    "gn:country_code":"TR",
    "gn:dem":775,
    "gn:feature_class":"P",
    "gn:feature_code":"PPL",
    "gn:name":"\u0130ma Yaylas\u0131",
    "gn:population":0,
    "gn:timezone":"Europe/Istanbul",
    "iso:country":"TR",
    "wof:name":"Ima Yaylasi",
    "wof:placetype":"locality"
},
  "geometry": {"coordinates":[31.90922,39.20875],"type":"Point"}
}