{
  "type": "Feature",
  "properties": {
    "gn:admin1_code":"37.0",
    "gn:asciiname":"Bozarmut",
    "gn:country_code":"TR",
    "gn:dem":1214,
    "gn:feature_class":"P",
    "gn:feature_code":"PPL",
    "gn:name":"Bozarmut",
    "gn:population":0,
    "gn:timezone":"Europe/Istanbul",
    "iso:country":"TR",
    "name:ceb_x_preferred":[
        "Bozarmut"
    ],
    "name:tur_x_preferred":[
        "Bozarmut"
    ],
    "name:vie_x_preferred":[
        "Bozarmut"
    ],
    "wof:name":"Bozarmut",
    "wof:placetype":"locality"
},
  "geometry": {"coordinates":[33.22075,41.54537],"type":"Point"}
}