{
  "type": "Feature",
  "properties": {
    "gn:admin1_code":"54.0",
    "gn:asciiname":"Memnuniye",
    "gn:country_code":"TR",
    "gn:dem":462,
    "gn:feature_class":"P",
    "gn:feature_code":"PPL",
    "gn:name":"Memnuniye",
    "gn:population":0,
    "gn:timezone":"Europe/Istanbul",
    "iso:country":"TR",
    "name:und_x_variant":[
        "Karag\u00f6l",
        "Memnuniye"
    ],
    "wof:name":"Memnuniye",
    "wof:placetype":"locality"
},
  "geometry": {"coordinates":[30.27668,40.66317],"type":"Point"}
}