{
  "type": "Feature",
  "properties": {
    "gn:country":"TR",
    "gn:fcode":"PPL",
    "gn:population":4390,
    "iso:country":"TR",
    "name:aze_x_preferred":[
        "G\u0259rg\u0259r"
    ],
    "name:cat_x_preferred":[
        "Gerger"
    ],
    "name:ceb_x_preferred":[
        "Gerger \u0130l\u00e7esi"
    ],
    "name:ckb_x_preferred":[
        "\u0626\u0627\u0644\u062f\u0648\u0648\u0634"
    ],
    "name:deu_x_preferred":[
        "Gerger"
    ],
    "name:diq_x_preferred":[
        "Aldu\u015f"
    ],
    "name:eng_x_preferred":[
        "Gerger"
    ],
    "name:epo_x_preferred":[
        "Gerger"
    ],
    "name:fas_x_preferred":[
        "\u06af\u0631\u06af\u0631"
    ],
    "name:fra_x_preferred":[
        "Gerger"
    ],
    "name:hye_x_preferred":[
        "\u053f\u0561\u0580\u056f\u0561\u057c"
    ],
    "name:ita_x_preferred":[
        "Gerger"
    ],
    "name:kur_x_preferred":[
        "Ald\u00fb\u015f"
    ],
    "name:lbe_x_preferred":[
        "\u0413\u0435\u0440\u0433\u0435\u0440"
    ],
    "name:mrj_x_preferred":[
        "\u0413\u0435\u0440\u0433\u0435\u0440"
    ],
    "name:msa_x_preferred":[
        "Gerger"
    ],
    "name:nan_x_preferred":[
        "Gerger"
    ],
    "name:nld_x_preferred":[
        "Gerger"
    ],
    "name:nob_x_preferred":[
        "Gerger"
    ],
    "name:ron_x_preferred":[
        "Gerger"
    ],
    "name:rus_x_preferred":[
        "\u0413\u0435\u0440\u0433\u0435\u0440"
    ],
    "name:swa_x_preferred":[
        "Gerger"
    ],
    "name:tur_x_preferred":[
        "Gerger"
    ],
    "name:urd_x_preferred":[
        "\u06af\u0631\u06af\u0631"
    ],
    "name:vie_x_preferred":[
        "Gerger"
    ],
    "qs:name":"Gerger",
    "qs:name_adm0":"Turkey",
    "qs:name_adm1":"Ad\u0131yaman",
    "qs:photos_9k":1,
    "qs:photos_9r":1,
    "qs:photos_all":9,
    "qs:photos_sr":0,
    "qs:placetype":"Town",
    "qs:pop_sr":"4",
    "wd:wordcount":500,
    "wof:name":"Gerger",
    "wof:placetype":"locality",
    "wof:population":4390
},
  "geometry": {"coordinates":[39.01667,37.95],"type":"Point"}
}