{
  "type": "Feature",
  "properties": {
    "gn:country":"TR",
    "gn:fcode":"PPL",
    "gn:pop":4390,
    "iso:country":"TR",
    "qs:name":"Gerger",
    "qs:name_adm0":"Turkey",
    "qs:name_adm1":"Ad\u0131yaman",
    "qs:photos_9k":1,
    "qs:photos_9r":1,
    "qs:photos_all":9,
    "qs:photos_sr":0,
    "qs:placetype":"Town",
    "qs:pop_sr":"4",
    "wd:wordcount":500,
    "wof:name":"Gerger",
    "wof:placetype":"locality",
    "wof:population":4390
},
  "geometry": {"coordinates":[39.01667,37.95],"type":"Point"}
}