{
  "type": "Feature",
  "properties": {
    "gn:admin1_code":"46",
    "gn:asciiname":"Koyulgan",
    "gn:country_code":"TR",
    "gn:dem":1396,
    "gn:feature_class":"P",
    "gn:feature_code":"PPL",
    "gn:name":"Koyulgan",
    "gn:population":0,
    "gn:timezone":"Europe/Istanbul",
    "iso:country":"TR",
    "wof:name":"Koyulgan",
    "wof:placetype":"locality"
},
  "geometry": {"coordinates":[37.58333,37.93333],"type":"Point"}
}