{
  "type": "Feature",
  "properties": {
    "gn:admin1_code":"23",
    "gn:asciiname":"Hamurkesen",
    "gn:country_code":"TR",
    "gn:dem":1263,
    "gn:feature_class":"P",
    "gn:feature_code":"PPL",
    "gn:name":"Hamurkesen",
    "gn:population":0,
    "gn:timezone":"Europe/Istanbul",
    "iso:country":"TR",
    "wof:name":"Hamurkesen",
    "wof:placetype":"locality"
},
  "geometry": {"coordinates":[40.10599000000001,39.09493],"type":"Point"}
}