{
  "type": "Feature",
  "properties": {
    "gn:admin1_code":"13",
    "gn:asciiname":"Karaagac",
    "gn:country_code":"TR",
    "gn:dem":1976,
    "gn:feature_class":"P",
    "gn:feature_code":"PPL",
    "gn:name":"Karaa\u011fa\u00e7",
    "gn:population":0,
    "gn:timezone":"Europe/Istanbul",
    "iso:country":"TR",
    "name:tur_x_preferred":[
        "Karaa\u011fa\u00e7"
    ],
    "name:und_x_variant":[
        "Kirs"
    ],
    "wof:name":"Karaagac",
    "wof:placetype":"locality"
},
  "geometry": {"coordinates":[42.27384,38.88332],"type":"Point"}
}