{
  "type": "Feature",
  "properties": {
    "gn:country":"TR",
    "gn:fcode":"PPL",
    "gn:pop":119370,
    "iso:country":"TR",
    "name:bel_x_preferred":[
        "\u0413\u043e\u0440\u0430\u0434 \u041d\u0430\u0437\u0456\u043b\u0456"
    ],
    "name:eng_x_preferred":[
        "Nazilli"
    ],
    "name:fas_x_preferred":[
        "\u0646\u0627\u0632\u06cc\u0644\u06cc"
    ],
    "name:kaz_x_preferred":[
        "\u041d\u0430\u0437\u0438\u043b\u043b\u0438"
    ],
    "name:lbe_x_preferred":[
        "\u041d\u0430\u0437\u0438\u043b\u043b\u0438"
    ],
    "name:lit_x_preferred":[
        "Nazilis"
    ],
    "name:mrj_x_preferred":[
        "\u041d\u0430\u0437\u0438\u043b\u043b\u0438"
    ],
    "name:pol_x_preferred":[
        "Nazilli"
    ],
    "name:rus_x_preferred":[
        "\u041d\u0430\u0437\u0438\u043b\u043b\u0438"
    ],
    "name:srp_x_preferred":[
        "\u041d\u0430\u0437\u0438\u043b\u0438"
    ],
    "name:tur_x_preferred":[
        "Nazilli"
    ],
    "name:unk_x_variant":[
        "Pazark\u00f6y"
    ],
    "name:zho_x_preferred":[
        "\u7d0d\u6fdf\u5229"
    ],
    "qs:name":"Nazilli",
    "qs:photos_9r":0,
    "qs:photos_sr":0,
    "qs:pop_sr":"9",
    "wd:wordcount":454,
    "wof:name":"Nazilli",
    "wof:placetype":"locality",
    "wof:population":119370
},
  "geometry": {"coordinates":[28.32225,37.91631],"type":"Point"}
}