{
  "type": "Feature",
  "properties": {
    "gn:country":"TR",
    "gn:fcode":"PPL",
    "gn:pop":119370,
    "iso:country":"TR",
    "name:ara_x_preferred":[
        "\u0646\u0627\u0632\u064a\u0644\u0644\u064a"
    ],
    "name:bel_x_preferred":[
        "\u0413\u043e\u0440\u0430\u0434 \u041d\u0430\u0437\u0456\u043b\u0456"
    ],
    "name:cat_x_preferred":[
        "Nazilli"
    ],
    "name:ceb_x_preferred":[
        "Nazilli"
    ],
    "name:dan_x_preferred":[
        "Nazilli"
    ],
    "name:deu_x_preferred":[
        "Nazilli"
    ],
    "name:eng_x_preferred":[
        "Nazilli"
    ],
    "name:epo_x_preferred":[
        "Nazilli"
    ],
    "name:fas_x_preferred":[
        "\u0646\u0627\u0632\u06cc\u0644\u06cc"
    ],
    "name:fra_x_preferred":[
        "Nazilli"
    ],
    "name:gag_x_preferred":[
        "Nazilli"
    ],
    "name:ita_x_preferred":[
        "Nazilli"
    ],
    "name:jpn_x_preferred":[
        "\u30ca\u30ba\u30a3\u30c3\u30ea"
    ],
    "name:kat_x_preferred":[
        "\u10dc\u10d0\u10d6\u10d8\u10da\u10d8"
    ],
    "name:kaz_x_preferred":[
        "\u041d\u0430\u0437\u0438\u043b\u043b\u0438"
    ],
    "name:lbe_x_preferred":[
        "\u041d\u0430\u0437\u0438\u043b\u043b\u0438"
    ],
    "name:lit_x_preferred":[
        "Nazilis"
    ],
    "name:lrc_x_preferred":[
        "\u0646\u0627\u0632\u06cc\u0644\u06cc"
    ],
    "name:min_x_preferred":[
        "Nazilli"
    ],
    "name:mrj_x_preferred":[
        "\u041d\u0430\u0437\u0438\u043b\u043b\u0438"
    ],
    "name:msa_x_preferred":[
        "Nazilli"
    ],
    "name:nan_x_preferred":[
        "Nazilli"
    ],
    "name:nld_x_preferred":[
        "Nazilli"
    ],
    "name:nno_x_preferred":[
        "Nazilli"
    ],
    "name:nob_x_preferred":[
        "Nazilli"
    ],
    "name:pol_x_preferred":[
        "Nazilli"
    ],
    "name:ron_x_preferred":[
        "Nazilli"
    ],
    "name:rus_x_preferred":[
        "\u041d\u0430\u0437\u0438\u043b\u043b\u0438"
    ],
    "name:srp_x_preferred":[
        "\u041d\u0430\u0437\u0438\u043b\u0438"
    ],
    "name:swa_x_preferred":[
        "Nazilli"
    ],
    "name:tur_x_preferred":[
        "Nazilli"
    ],
    "name:unk_x_variant":[
        "Pazark\u00f6y"
    ],
    "name:urd_x_preferred":[
        "\u0646\u0627\u0632\u06cc\u0644\u06cc"
    ],
    "name:vie_x_preferred":[
        "Nazilli"
    ],
    "name:war_x_preferred":[
        "Nazilli"
    ],
    "name:zho_x_preferred":[
        "\u7d0d\u6fdf\u5229"
    ],
    "qs:name":"Nazilli",
    "qs:photos_9r":0,
    "qs:photos_sr":0,
    "qs:pop_sr":"9",
    "wd:wordcount":454,
    "wof:name":"Nazilli",
    "wof:placetype":"locality",
    "wof:population":119370
},
  "geometry": {"coordinates":[28.32225,37.91631],"type":"Point"}
}