{
  "type": "Feature",
  "properties": {
    "gn:admin1_code":"63",
    "gn:asciiname":"Alagun",
    "gn:country_code":"TR",
    "gn:dem":715,
    "gn:feature_class":"P",
    "gn:feature_code":"PPL",
    "gn:name":"Alag\u00fcn",
    "gn:population":0,
    "gn:timezone":"Europe/Istanbul",
    "iso:country":"TR",
    "name:tur_x_preferred":[
        "Alag\u00fcn"
    ],
    "wof:name":"Alagun",
    "wof:placetype":"locality"
},
  "geometry": {"coordinates":[39.42968,37.39719],"type":"Point"}
}