{
  "type": "Feature",
  "properties": {
    "gn:admin1_code":"69.0",
    "gn:asciiname":"Guneycevirme",
    "gn:country_code":"TR",
    "gn:dem":1546,
    "gn:feature_class":"P",
    "gn:feature_code":"PPL",
    "gn:name":"G\u00fcney\u00e7evirme",
    "gn:population":0,
    "gn:timezone":"Europe/Istanbul",
    "iso:country":"TR",
    "name:tur_x_preferred":[
        "G\u00fcney\u00e7evirme"
    ],
    "wof:name":"Guneycevirme",
    "wof:placetype":"locality"
},
  "geometry": {"coordinates":[39.54606,40.15231],"type":"Point"}
}