{
  "type": "Feature",
  "properties": {
    "gn:admin1_code":"09",
    "gn:asciiname":"Bahcearasi",
    "gn:country_code":"TR",
    "gn:dem":45,
    "gn:feature_class":"P",
    "gn:feature_code":"PPL",
    "gn:name":"Bah\u00e7earas\u0131",
    "gn:population":0,
    "gn:timezone":"Europe/Istanbul",
    "iso:country":"TR",
    "name:tur_x_preferred":[
        "Bah\u00e7earas\u0131"
    ],
    "wof:name":"Bahcearasi",
    "wof:placetype":"locality"
},
  "geometry": {"coordinates":[27.8956,37.70678],"type":"Point"}
}