{
  "type": "Feature",
  "properties": {
    "gn:admin1_code":"65",
    "gn:asciiname":"Kurubas",
    "gn:country_code":"TR",
    "gn:dem":1810,
    "gn:feature_class":"P",
    "gn:feature_code":"PPL",
    "gn:name":"Kuruba\u015f",
    "gn:population":0,
    "gn:timezone":"Europe/Istanbul",
    "iso:country":"TR",
    "name:tur_x_preferred":[
        "Kuruba\u015f"
    ],
    "wof:name":"Kurubas",
    "wof:placetype":"locality"
},
  "geometry": {"coordinates":[43.40958,38.45499],"type":"Point"}
}