{
  "type": "Feature",
  "properties": {
    "gn:admin1_code":"16",
    "gn:asciiname":"Doganci",
    "gn:country_code":"TR",
    "gn:dem":274,
    "gn:feature_class":"P",
    "gn:feature_code":"PPL",
    "gn:name":"Do\u011fanc\u0131",
    "gn:population":0,
    "gn:timezone":"Europe/Istanbul",
    "iso:country":"TR",
    "name:tur_x_preferred":[
        "Do\u011fanc\u0131"
    ],
    "wof:name":"Doganci",
    "wof:placetype":"locality"
},
  "geometry": {"coordinates":[28.96466,40.1335],"type":"Point"}
}