{
  "type": "Feature",
  "properties": {
    "gn:admin1_code":"59.0",
    "gn:asciiname":"Biyikali",
    "gn:cc2":"TR",
    "gn:country_code":"TR",
    "gn:dem":216,
    "gn:feature_class":"P",
    "gn:feature_code":"PPL",
    "gn:name":"B\u0131y\u0131kali",
    "gn:population":0,
    "gn:timezone":"Europe/Istanbul",
    "iso:country":"TR",
    "name:und_x_variant":[
        "Boyal\u0131",
        "B\u0131y\u0131kali"
    ],
    "wof:name":"Biyikali",
    "wof:placetype":"locality"
},
  "geometry": {"coordinates":[27.37333,41.01639],"type":"Point"}
}