{
  "type": "Feature",
  "properties": {
    "gn:admin1_code":"24",
    "gn:asciiname":"Altintas",
    "gn:country_code":"TR",
    "gn:dem":1332,
    "gn:feature_class":"P",
    "gn:feature_code":"PPL",
    "gn:name":"Alt\u0131nta\u015f",
    "gn:population":0,
    "gn:timezone":"Europe/Istanbul",
    "iso:country":"TR",
    "name:und_x_variant":[
        "Z\u0131mara",
        "Alt\u0131nta\u015f"
    ],
    "wof:name":"Altintas",
    "wof:placetype":"locality"
},
  "geometry": {"coordinates":[38.34307,39.47199000000001],"type":"Point"}
}