{
  "type": "Feature",
  "properties": {
    "gn:admin1_code":"03",
    "gn:asciiname":"Ovacik",
    "gn:country_code":"TR",
    "gn:dem":1206,
    "gn:feature_class":"P",
    "gn:feature_code":"PPL",
    "gn:name":"Ovac\u0131k",
    "gn:population":0,
    "gn:timezone":"Europe/Istanbul",
    "iso:country":"TR",
    "wof:name":"Ovacik",
    "wof:placetype":"locality"
},
  "geometry": {"coordinates":[30.07475,37.84585],"type":"Point"}
}