{
  "type": "Feature",
  "properties": {
    "gn:admin1_code":"57.0",
    "gn:asciiname":"Zipkin",
    "gn:country_code":"TR",
    "gn:dem":1222,
    "gn:feature_class":"P",
    "gn:feature_code":"PPL",
    "gn:name":"Z\u0131pk\u0131n",
    "gn:population":0,
    "gn:timezone":"Europe/Istanbul",
    "iso:country":"TR",
    "wof:name":"Zipkin",
    "wof:placetype":"locality"
},
  "geometry": {"coordinates":[34.79236,41.69725],"type":"Point"}
}