{
  "type": "Feature",
  "properties": {
    "gn:admin1_code":"34.0",
    "gn:asciiname":"Orencik",
    "gn:country_code":"TR",
    "gn:dem":38,
    "gn:feature_class":"P",
    "gn:feature_code":"PPL",
    "gn:name":"\u00d6rencik",
    "gn:population":0,
    "gn:timezone":"Europe/Istanbul",
    "iso:country":"TR",
    "name:und_x_variant":[
        "Tarfa",
        "\u00d6rencik"
    ],
    "wof:name":"Orencik",
    "wof:placetype":"locality"
},
  "geometry": {"coordinates":[28.48098,41.32876],"type":"Point"}
}