{
  "type": "Feature",
  "properties": {
    "gn:admin1_code":"37.0",
    "gn:asciiname":"Sariseki",
    "gn:country_code":"TR",
    "gn:dem":1436,
    "gn:feature_class":"P",
    "gn:feature_code":"PPL",
    "gn:name":"Sar\u0131seki",
    "gn:population":0,
    "gn:timezone":"Europe/Istanbul",
    "iso:country":"TR",
    "name:und_x_variant":[
        "Sar\u0131seki",
        "Sar\u0131s\u00f6k\u00fc"
    ],
    "wof:name":"Sariseki",
    "wof:placetype":"locality"
},
  "geometry": {"coordinates":[34.24849,41.72746],"type":"Point"}
}