{
  "type": "Feature",
  "properties": {
    "gn:admin1_code":"57.0",
    "gn:asciiname":"Kemerbahce",
    "gn:country_code":"TR",
    "gn:dem":264,
    "gn:feature_class":"P",
    "gn:feature_code":"PPL",
    "gn:name":"Kemerbah\u00e7e",
    "gn:population":0,
    "gn:timezone":"Europe/Istanbul",
    "iso:country":"TR",
    "wof:name":"Kemerbahce",
    "wof:placetype":"locality"
},
  "geometry": {"coordinates":[35.14293,41.34922],"type":"Point"}
}