{
  "type": "Feature",
  "properties": {
    "gn:admin1_code":"04",
    "gn:asciiname":"Cogurlu",
    "gn:country_code":"TR",
    "gn:dem":1914,
    "gn:feature_class":"P",
    "gn:feature_code":"PPL",
    "gn:name":"\u00c7\u00f6\u011f\u00fcrl\u00fc",
    "gn:population":0,
    "gn:timezone":"Europe/Istanbul",
    "iso:country":"TR",
    "name:und_x_variant":[
        "Le\u015fko",
        "\u00c7\u00f6\u011f\u00fcrl\u00fc"
    ],
    "wof:name":"Cogurlu",
    "wof:placetype":"locality"
},
  "geometry": {"coordinates":[43.46632,39.65426],"type":"Point"}
}