{
  "type": "Feature",
  "properties": {
    "gn:admin1_code":"84.0",
    "gn:asciiname":"Yukari Sarikamis",
    "gn:country_code":"TR",
    "gn:dem":2106,
    "gn:feature_class":"P",
    "gn:feature_code":"PPL",
    "gn:name":"Yukar\u0131 Sar\u0131kam\u0131\u015f",
    "gn:population":0,
    "gn:timezone":"Europe/Istanbul",
    "iso:country":"TR",
    "name:tur_x_preferred":[
        "Yukar\u0131 Sar\u0131kam\u0131\u015f"
    ],
    "wof:name":"Yukari Sarikamis",
    "wof:placetype":"locality"
},
  "geometry": {"coordinates":[42.56021,40.33329000000001],"type":"Point"}
}