{
  "type": "Feature",
  "properties": {
    "gn:admin1_code":"07",
    "gn:admin2_code":"7732185.0",
    "gn:asciiname":"Payallar",
    "gn:country_code":"TR",
    "gn:dem":35,
    "gn:feature_class":"P",
    "gn:feature_code":"PPL",
    "gn:name":"Payallar",
    "gn:population":5425,
    "gn:timezone":"Europe/Istanbul",
    "iso:country":"TR",
    "wof:name":"Payallar",
    "wof:placetype":"locality",
    "wof:population":5425
},
  "geometry": {"coordinates":[31.85057,36.6016],"type":"Point"}
}