{
  "type": "Feature",
  "properties": {
    "gn:admin1_code":"22.0",
    "gn:asciiname":"Ahirkoy",
    "gn:country_code":"TR",
    "gn:dem":57,
    "gn:feature_class":"P",
    "gn:feature_code":"PPL",
    "gn:name":"Ah\u0131rk\u00f6y",
    "gn:population":0,
    "gn:timezone":"Europe/Istanbul",
    "iso:country":"TR",
    "name:und_x_variant":[
        "Ah\u0131r",
        "Ah\u0131rk\u00f6y"
    ],
    "wof:name":"Ahirkoy",
    "wof:placetype":"locality"
},
  "geometry": {"coordinates":[26.37342,40.89528],"type":"Point"}
}