{
  "type": "Feature",
  "properties": {
    "gn:admin1_code":"12",
    "gn:asciiname":"Pargesur",
    "gn:country_code":"TR",
    "gn:dem":1449,
    "gn:feature_class":"P",
    "gn:feature_code":"PPL",
    "gn:name":"Pargesur",
    "gn:population":0,
    "gn:timezone":"Europe/Istanbul",
    "iso:country":"TR",
    "wof:name":"Pargesur",
    "wof:placetype":"locality"
},
  "geometry": {"coordinates":[40.01667,39.16667],"type":"Point"}
}