{
  "type": "Feature",
  "properties": {
    "gn:admin1_code":"82.0",
    "gn:asciiname":"Bostanli",
    "gn:country_code":"TR",
    "gn:dem":565,
    "gn:feature_class":"P",
    "gn:feature_code":"PPL",
    "gn:name":"Bostanl\u0131",
    "gn:population":0,
    "gn:timezone":"Europe/Istanbul",
    "iso:country":"TR",
    "wof:name":"Bostanli",
    "wof:placetype":"locality"
},
  "geometry": {"coordinates":[33.81684,40.33098],"type":"Point"}
}