{
  "type": "Feature",
  "properties": {
    "gn:admin1_code":"24",
    "gn:asciiname":"Kurankoy",
    "gn:country_code":"TR",
    "gn:dem":1408,
    "gn:feature_class":"P",
    "gn:feature_code":"PPL",
    "gn:name":"Kurank\u00f6y",
    "gn:population":0,
    "gn:timezone":"Europe/Istanbul",
    "iso:country":"TR",
    "name:tur_x_preferred":[
        "Kurank\u00f6y"
    ],
    "name:tur_x_variant":[
        "Kuran"
    ],
    "wof:name":"Kurankoy",
    "wof:placetype":"locality"
},
  "geometry": {"coordinates":[38.44066,39.69968],"type":"Point"}
}