{
  "type": "Feature",
  "properties": {
    "gn:admin1_code":"59",
    "gn:asciiname":"Hedeyli",
    "gn:country_code":"TR",
    "gn:dem":51,
    "gn:feature_class":"P",
    "gn:feature_code":"PPL",
    "gn:name":"Hedeyli",
    "gn:population":0,
    "gn:timezone":"Europe/Istanbul",
    "iso:country":"TR",
    "name:tur_x_preferred":[
        "Hedeyli"
    ],
    "wof:name":"Hedeyli",
    "wof:placetype":"locality"
},
  "geometry": {"coordinates":[27.02634,41.32972],"type":"Point"}
}