{
  "type": "Feature",
  "properties": {
    "gn:admin1_code":"40",
    "gn:asciiname":"Uzunpinar",
    "gn:country_code":"TR",
    "gn:dem":1218,
    "gn:feature_class":"P",
    "gn:feature_code":"PPL",
    "gn:name":"Uzunp\u0131nar",
    "gn:population":0,
    "gn:timezone":"Europe/Istanbul",
    "iso:country":"TR",
    "name:und_x_variant":[
        "Uzunalip\u0131nar\u0131",
        "Uzunp\u0131nar K\u00f6y",
        "Uzunp\u0131nar"
    ],
    "wof:name":"Uzunpinar",
    "wof:placetype":"locality"
},
  "geometry": {"coordinates":[34.32664,39.43766],"type":"Point"}
}