{
  "type": "Feature",
  "properties": {
    "gn:admin1_code":"43",
    "gn:asciiname":"Ugurluca",
    "gn:cc2":"TR",
    "gn:country_code":"TR",
    "gn:dem":1046,
    "gn:feature_class":"P",
    "gn:feature_code":"PPL",
    "gn:name":"U\u011furluca",
    "gn:population":0,
    "gn:timezone":"Europe/Istanbul",
    "iso:country":"TR",
    "name:und_x_variant":[
        "U\u011frulca",
        "U\u011furluca"
    ],
    "wof:name":"Ugurluca",
    "wof:placetype":"locality"
},
  "geometry": {"coordinates":[29.60444,38.97528],"type":"Point"}
}