{
  "type": "Feature",
  "properties": {
    "gn:country":"TR",
    "gn:fcode":"PPL",
    "gn:population":205,
    "iso:country":"TR",
    "name:tur_x_preferred":[
        "Sevimli"
    ],
    "qs:name":"Sevimli",
    "qs:photos_9r":0,
    "qs:photos_sr":0,
    "qs:pop_sr":"2",
    "wof:name":"Sevimli",
    "wof:placetype":"locality",
    "wof:population":205
},
  "geometry": {"coordinates":[40.52667,37.03722],"type":"Point"}
}