{
  "type": "Feature",
  "properties": {
    "gn:admin1_code":"2.0",
    "gn:asciiname":"Arpatarlasi",
    "gn:country_code":"TR",
    "gn:dem":1386,
    "gn:feature_class":"P",
    "gn:feature_code":"PPL",
    "gn:name":"Arpatarla\u015f\u0131",
    "gn:population":0,
    "gn:timezone":"Europe/Istanbul",
    "iso:country":"TR",
    "wof:name":"Arpatarlasi",
    "wof:placetype":"locality"
},
  "geometry": {"coordinates":[37.75282,37.90827],"type":"Point"}
}