{
  "type": "Feature",
  "properties": {
    "gn:admin1_code":"53.0",
    "gn:asciiname":"Selamet",
    "gn:country_code":"TR",
    "gn:dem":314,
    "gn:feature_class":"P",
    "gn:feature_code":"PPL",
    "gn:name":"Selamet",
    "gn:population":0,
    "gn:timezone":"Europe/Istanbul",
    "iso:country":"TR",
    "name:tur_x_preferred":[
        "Selamet"
    ],
    "wof:name":"Selamet",
    "wof:placetype":"locality"
},
  "geometry": {"coordinates":[40.62624,40.98279],"type":"Point"}
}