{
  "type": "Feature",
  "properties": {
    "gn:admin1_code":"38",
    "gn:asciiname":"Germir Mah. 421. Sok.",
    "gn:country_code":"TR",
    "gn:dem":1084,
    "gn:feature_class":"P",
    "gn:feature_code":"PPL",
    "gn:name":"Germir Mah. 421. Sok.",
    "gn:population":0,
    "gn:timezone":"Europe/Istanbul",
    "iso:country":"TR",
    "wof:name":"Germir Mah. 421. Sok.",
    "wof:placetype":"locality"
},
  "geometry": {"coordinates":[35.54513,38.73945],"type":"Point"}
}