{
  "type": "Feature",
  "properties": {
    "gn:admin1_code":"89.0",
    "gn:asciiname":"Alioglu",
    "gn:country_code":"TR",
    "gn:dem":912,
    "gn:feature_class":"P",
    "gn:feature_code":"PPL",
    "gn:name":"Alio\u011flu",
    "gn:population":0,
    "gn:timezone":"Europe/Istanbul",
    "iso:country":"TR",
    "name:und_x_variant":[
        "Tepecikk\u00f6y",
        "Tepecik",
        "Alio\u011flu"
    ],
    "wof:name":"Alioglu",
    "wof:placetype":"locality"
},
  "geometry": {"coordinates":[32.97859,41.42816],"type":"Point"}
}