{
  "type": "Feature",
  "properties": {
    "gn:admin1_code":"04",
    "gn:asciiname":"Tahir",
    "gn:country_code":"TR",
    "gn:dem":2129,
    "gn:feature_class":"P",
    "gn:feature_code":"PPLA3",
    "gn:name":"Tahir",
    "gn:population":0,
    "gn:timezone":"Europe/Istanbul",
    "iso:country":"TR",
    "name:tur_x_preferred":[
        "Tahir"
    ],
    "wof:name":"Tahir",
    "wof:placetype":"locality"
},
  "geometry": {"coordinates":[42.42834000000001,39.85586],"type":"Point"}
}