{
  "type": "Feature",
  "properties": {
    "gn:admin1_code":"64",
    "gn:asciiname":"Habipler",
    "gn:country_code":"TR",
    "gn:dem":840,
    "gn:feature_class":"P",
    "gn:feature_code":"PPL",
    "gn:name":"Habipler",
    "gn:population":0,
    "gn:timezone":"Europe/Istanbul",
    "iso:country":"TR",
    "name:tur_x_preferred":[
        "Habipler"
    ],
    "wof:name":"Habipler",
    "wof:placetype":"locality"
},
  "geometry": {"coordinates":[29.41155,38.59336],"type":"Point"}
}