{
  "type": "Feature",
  "properties": {
    "gn:admin1_code":"66",
    "gn:asciiname":"Tarhana",
    "gn:country_code":"TR",
    "gn:dem":939,
    "gn:feature_class":"P",
    "gn:feature_code":"PPL",
    "gn:name":"Tarhana",
    "gn:population":0,
    "gn:timezone":"Europe/Istanbul",
    "iso:country":"TR",
    "wof:name":"Tarhana",
    "wof:placetype":"locality"
},
  "geometry": {"coordinates":[35.7137,39.89568],"type":"Point"}
}