{
  "type": "Feature",
  "properties": {
    "gn:admin1_code":"66",
    "gn:asciiname":"Tarhana",
    "gn:country_code":"TR",
    "gn:dem":939,
    "gn:feature_class":"P",
    "gn:feature_code":"PPL",
    "gn:name":"Tarhana",
    "gn:population":0,
    "gn:timezone":"Europe/Istanbul",
    "iso:country":"TR",
    "name:aze_x_preferred":[
        "Tarhana \u015forbas\u0131"
    ],
    "name:bul_x_preferred":[
        "\u0422\u0440\u0430\u0445\u0430\u043d\u0430"
    ],
    "name:ckb_x_preferred":[
        "\u062a\u0631\u062e\u06ce\u0646\u06d5"
    ],
    "name:deu_x_preferred":[
        "Tarhana"
    ],
    "name:ell_x_preferred":[
        "\u03a4\u03c1\u03b1\u03c7\u03b1\u03bd\u03ac\u03c2"
    ],
    "name:epo_x_preferred":[
        "Tarhano"
    ],
    "name:fas_x_preferred":[
        "\u062a\u0631\u062e\u06cc\u0646\u0647"
    ],
    "name:hye_x_preferred":[
        "\u0539\u0561\u0580\u056d\u0561\u0576\u0561"
    ],
    "name:ita_x_preferred":[
        "Tarhana"
    ],
    "name:nor_x_preferred":[
        "Tarhana"
    ],
    "name:por_x_preferred":[
        "Tarhana"
    ],
    "name:rus_x_preferred":[
        "\u0422\u0430\u0440\u0445\u0430\u043d\u0430"
    ],
    "name:spa_x_preferred":[
        "Tarhana"
    ],
    "name:sqi_x_preferred":[
        "Trahana"
    ],
    "name:swe_x_preferred":[
        "Tarhana"
    ],
    "name:tur_x_preferred":[
        "Tarhana \u00e7orbas\u0131"
    ],
    "name:ukr_x_preferred":[
        "\u0422\u0430\u0440\u0445\u0430\u043d\u0430"
    ],
    "wof:name":"Tarhana",
    "wof:placetype":"locality"
},
  "geometry": {"coordinates":[35.7137,39.89568],"type":"Point"}
}