{
  "type": "Feature",
  "properties": {
    "gn:admin1_code":"66",
    "gn:asciiname":"Evci",
    "gn:country_code":"TR",
    "gn:dem":1252,
    "gn:feature_class":"P",
    "gn:feature_code":"PPL",
    "gn:name":"Evci",
    "gn:population":0,
    "gn:timezone":"Europe/Istanbul",
    "iso:country":"TR",
    "name:und_x_variant":[
        "Kazakevcisi",
        "Evci"
    ],
    "wof:name":"Evci",
    "wof:placetype":"locality"
},
  "geometry": {"coordinates":[34.72328,39.87731],"type":"Point"}
}