{
  "type": "Feature",
  "properties": {
    "gn:admin1_code":"87",
    "gn:asciiname":"Sapkoy",
    "gn:country_code":"TR",
    "gn:dem":338,
    "gn:feature_class":"P",
    "gn:feature_code":"PPL",
    "gn:name":"Sapk\u00f6y",
    "gn:population":0,
    "gn:timezone":"Europe/Istanbul",
    "iso:country":"TR",
    "wof:name":"Sapkoy",
    "wof:placetype":"locality"
},
  "geometry": {"coordinates":[32.69822,41.62854],"type":"Point"}
}