{
  "type": "Feature",
  "properties": {
    "gn:admin1_code":"25.0",
    "gn:asciiname":"Hancigaz",
    "gn:country_code":"TR",
    "gn:dem":1922,
    "gn:feature_class":"P",
    "gn:feature_code":"PPL",
    "gn:name":"Hanc\u0131\u011faz",
    "gn:population":0,
    "gn:timezone":"Europe/Istanbul",
    "iso:country":"TR",
    "name:tur_x_preferred":[
        "Hanc\u0131\u011faz"
    ],
    "wof:name":"Hancigaz",
    "wof:placetype":"locality"
},
  "geometry": {"coordinates":[41.44804,39.92404000000001],"type":"Point"}
}