{
  "type": "Feature",
  "properties": {
    "gn:admin1_code":"46",
    "gn:asciiname":"Goynuk",
    "gn:country_code":"TR",
    "gn:dem":920,
    "gn:feature_class":"P",
    "gn:feature_code":"PPL",
    "gn:name":"G\u00f6yn\u00fck",
    "gn:population":0,
    "gn:timezone":"Europe/Istanbul",
    "iso:country":"TR",
    "name:tur_x_preferred":[
        "G\u00f6yn\u00fck"
    ],
    "wof:name":"Goynuk",
    "wof:placetype":"locality"
},
  "geometry": {"coordinates":[37.43426,37.67595],"type":"Point"}
}