{
  "type": "Feature",
  "properties": {
    "gn:admin1_code":"87",
    "gn:asciiname":"Huseyinbasoglu",
    "gn:country_code":"TR",
    "gn:dem":207,
    "gn:feature_class":"P",
    "gn:feature_code":"PPL",
    "gn:name":"H\u00fcseyinba\u015fo\u011flu",
    "gn:population":0,
    "gn:timezone":"Europe/Istanbul",
    "iso:country":"TR",
    "wof:name":"Huseyinbasoglu",
    "wof:placetype":"locality"
},
  "geometry": {"coordinates":[32.61237,41.78786],"type":"Point"}
}