{
  "type": "Feature",
  "properties": {
    "gn:admin1_code":"10",
    "gn:asciiname":"Ericek",
    "gn:country_code":"TR",
    "gn:dem":333,
    "gn:feature_class":"P",
    "gn:feature_code":"PPL",
    "gn:name":"Ericek",
    "gn:population":0,
    "gn:timezone":"Europe/Istanbul",
    "iso:country":"TR",
    "name:tur_x_preferred":[
        "Erecak"
    ],
    "name:tur_x_variant":[
        "Ericek"
    ],
    "name:und_x_variant":[
        "Erecek"
    ],
    "wof:name":"Ericek",
    "wof:placetype":"locality"
},
  "geometry": {"coordinates":[27.91203,39.94664],"type":"Point"}
}