{
  "type": "Feature",
  "properties": {
    "gn:admin1_code":"2.0",
    "gn:asciiname":"Basmakci",
    "gn:country_code":"TR",
    "gn:dem":871,
    "gn:feature_class":"P",
    "gn:feature_code":"PPL",
    "gn:name":"Basmak\u00e7\u0131",
    "gn:population":0,
    "gn:timezone":"Europe/Istanbul",
    "iso:country":"TR",
    "name:tur_x_preferred":[
        "Basmak\u00e7\u0131"
    ],
    "wof:name":"Basmakci",
    "wof:placetype":"locality"
},
  "geometry": {"coordinates":[39.01329000000001,37.96335],"type":"Point"}
}