{
  "type": "Feature",
  "properties": {
    "gn:admin1_code":"04",
    "gn:asciiname":"Gozucu",
    "gn:country_code":"TR",
    "gn:dem":1916,
    "gn:feature_class":"P",
    "gn:feature_code":"PPL",
    "gn:name":"G\u00f6zucu",
    "gn:population":0,
    "gn:timezone":"Europe/Istanbul",
    "iso:country":"TR",
    "name:und_x_variant":[
        "\u015eeyhibrahim",
        "G\u00f6zucu"
    ],
    "wof:name":"Gozucu",
    "wof:placetype":"locality"
},
  "geometry": {"coordinates":[43.28069,39.54784],"type":"Point"}
}