{
  "type": "Feature",
  "properties": {
    "iso:country":"TR",
    "name:eng_x_preferred":[
        "Kazim Karabekir"
    ],
    "name:tur_x_preferred":[
        "Kaz\u0131m Karabekir"
    ],
    "wof:name":"Kazim Karabekir",
    "wof:placetype":"neighbourhood"
},
  "geometry": {"coordinates":[29.10460474582318,41.04028867415957],"type":"Point"}
}