{
  "type": "Feature",
  "properties": {
    "gn:admin1_code":"78",
    "gn:asciiname":"Berendi",
    "gn:country_code":"TR",
    "gn:dem":1646,
    "gn:feature_class":"P",
    "gn:feature_code":"PPL",
    "gn:name":"Berendi",
    "gn:population":0,
    "gn:timezone":"Europe/Istanbul",
    "iso:country":"TR",
    "name:tur_x_preferred":[
        "Berendi"
    ],
    "wof:name":"Berendi",
    "wof:placetype":"locality"
},
  "geometry": {"coordinates":[34.04935,37.2709],"type":"Point"}
}