{
  "type": "Feature",
  "properties": {
    "gn:admin1_code":"93",
    "gn:asciiname":"Feyzioglu",
    "gn:country_code":"TR",
    "gn:dem":478,
    "gn:feature_class":"P",
    "gn:feature_code":"PPL",
    "gn:name":"Feyzio\u011flu",
    "gn:population":0,
    "gn:timezone":"Europe/Istanbul",
    "iso:country":"TR",
    "wof:name":"Feyzioglu",
    "wof:placetype":"locality"
},
  "geometry": {"coordinates":[31.02089,40.97037],"type":"Point"}
}