{
  "type": "Feature",
  "properties": {
    "gn:admin1_code":"55.0",
    "gn:asciiname":"Yagbasan",
    "gn:country_code":"TR",
    "gn:dem":219,
    "gn:feature_class":"P",
    "gn:feature_code":"PPL",
    "gn:name":"Ya\u011fbasan",
    "gn:population":0,
    "gn:timezone":"Europe/Istanbul",
    "iso:country":"TR",
    "wof:name":"Yagbasan",
    "wof:placetype":"locality"
},
  "geometry": {"coordinates":[36.54569,41.0966],"type":"Point"}
}