{
  "type": "Feature",
  "properties": {
    "gn:admin1_code":"20",
    "gn:asciiname":"Eskihisar",
    "gn:country_code":"TR",
    "gn:dem":314,
    "gn:feature_class":"P",
    "gn:feature_code":"PPL",
    "gn:name":"Eskihisar",
    "gn:population":0,
    "gn:timezone":"Europe/Istanbul",
    "iso:country":"TR",
    "name:tur_x_preferred":[
        "Eskihisar"
    ],
    "wof:name":"Eskihisar",
    "wof:placetype":"locality"
},
  "geometry": {"coordinates":[29.10191,37.82],"type":"Point"}
}