{
  "type": "Feature",
  "properties": {
    "gn:country":"TR",
    "gn:fcode":"PPL",
    "gn:pop":43,
    "iso:country":"TR",
    "name:dut_x_preferred":[
        "Ba\u015fark\u00f6y"
    ],
    "name:eng_x_preferred":[
        "Ba\u015fark\u00f6y"
    ],
    "name:may_x_preferred":[
        "Ba\u015fark\u00f6y"
    ],
    "name:tur_x_preferred":[
        "Ba\u015fark\u00f6y"
    ],
    "name:unk_x_variant":[
        "Erdeva"
    ],
    "name:vie_x_preferred":[
        "Ba\u015fark\u00f6y"
    ],
    "qs:name":"Ba\u015fark\u00f6y",
    "qs:photos_9r":0,
    "qs:photos_sr":0,
    "qs:pop_sr":"1",
    "wof:name":"Ba\u015fark\u00f6y",
    "wof:placetype":"locality",
    "wof:population":43
},
  "geometry": {"coordinates":[41.41917,37.62472],"type":"Point"}
}