{
  "type": "Feature",
  "properties": {
    "gn:country":"TR",
    "gn:fcode":"PPL",
    "gn:population":43,
    "iso:country":"TR",
    "name:che_x_preferred":[
        "\u0411\u0430\u0448\u0430\u0440\u043a\u043e\u044c\u0439"
    ],
    "name:deu_x_preferred":[
        "Ba\u015fark\u00f6y"
    ],
    "name:eng_x_preferred":[
        "Ba\u015fark\u00f6y"
    ],
    "name:msa_x_preferred":[
        "Ba\u015fark\u00f6y"
    ],
    "name:nld_x_preferred":[
        "Ba\u015fark\u00f6y"
    ],
    "name:tat_x_preferred":[
        "\u0411\u0430\u0448\u0430\u0440\u043a\u04e9\u0439"
    ],
    "name:tur_x_preferred":[
        "Ba\u015fark\u00f6y"
    ],
    "name:und_x_variant":[
        "Erdeva"
    ],
    "name:vie_x_preferred":[
        "Ba\u015fark\u00f6y"
    ],
    "qs:name":"Ba\u015fark\u00f6y",
    "qs:photos_9r":0,
    "qs:photos_sr":0,
    "qs:pop_sr":"1",
    "wof:name":"Ba\u015fark\u00f6y",
    "wof:placetype":"locality",
    "wof:population":43
},
  "geometry": {"coordinates":[41.41917,37.62472],"type":"Point"}
}