{
  "type": "Feature",
  "properties": {
    "gn:admin1_code":"35",
    "gn:asciiname":"Zeytineli",
    "gn:country_code":"TR",
    "gn:dem":68,
    "gn:feature_class":"P",
    "gn:feature_code":"PPL",
    "gn:name":"Zeytineli",
    "gn:population":0,
    "gn:timezone":"Europe/Istanbul",
    "iso:country":"TR",
    "wof:name":"Zeytineli",
    "wof:placetype":"locality"
},
  "geometry": {"coordinates":[26.50444,38.24189000000001],"type":"Point"}
}