{
  "type": "Feature",
  "properties": {
    "gn:admin1_code":"68.0",
    "gn:asciiname":"Emresultan",
    "gn:country_code":"TR",
    "gn:dem":425,
    "gn:feature_class":"P",
    "gn:feature_code":"PPL",
    "gn:name":"Emresultan",
    "gn:population":0,
    "gn:timezone":"Europe/Istanbul",
    "iso:country":"TR",
    "name:und_x_variant":[
        "Emremsultan",
        "Emresultan"
    ],
    "wof:name":"Emresultan",
    "wof:placetype":"locality"
},
  "geometry": {"coordinates":[31.39502,40.07452],"type":"Point"}
}