{
  "type": "Feature",
  "properties": {
    "gn:admin1_code":"93",
    "gn:asciiname":"Karakilise",
    "gn:country_code":"TR",
    "gn:dem":280,
    "gn:feature_class":"P",
    "gn:feature_code":"PPL",
    "gn:name":"Karakilise",
    "gn:population":0,
    "gn:timezone":"Europe/Istanbul",
    "iso:country":"TR",
    "name:tur_x_preferred":[
        "Karakilise"
    ],
    "wof:name":"Karakilise",
    "wof:placetype":"locality"
},
  "geometry": {"coordinates":[30.93787,40.90449],"type":"Point"}
}