{
  "type": "Feature",
  "properties": {
    "gn:admin1_code":"25.0",
    "gn:asciiname":"Gulluce",
    "gn:country_code":"TR",
    "gn:dem":2028,
    "gn:feature_class":"P",
    "gn:feature_code":"PPL",
    "gn:name":"G\u00fcll\u00fcce",
    "gn:population":0,
    "gn:timezone":"Europe/Istanbul",
    "iso:country":"TR",
    "name:eng_x_preferred":[
        "Pa\u015faki"
    ],
    "name:rus_x_preferred":[
        "\u041f\u0430\u0448\u0430\u043a\u0438"
    ],
    "name:und_x_variant":[
        "G\u00fcll\u00fcce",
        "Pa\u015faki"
    ],
    "wof:name":"Gulluce",
    "wof:placetype":"locality"
},
  "geometry": {"coordinates":[40.82664000000001,40.21485],"type":"Point"}
}