{
  "type": "Feature",
  "properties": {
    "gn:admin1_code":"43",
    "gn:asciiname":"Karaoz",
    "gn:country_code":"TR",
    "gn:dem":1115,
    "gn:feature_class":"P",
    "gn:feature_code":"PPL",
    "gn:name":"Kara\u00f6z",
    "gn:population":0,
    "gn:timezone":"Europe/Istanbul",
    "iso:country":"TR",
    "name:und_x_variant":[
        "Karag\u00f6z",
        "Kara\u00f6z"
    ],
    "wof:name":"Karaoz",
    "wof:placetype":"locality"
},
  "geometry": {"coordinates":[29.92976,39.52228],"type":"Point"}
}