{
  "type": "Feature",
  "properties": {
    "gn:admin1_code":"88.0",
    "gn:asciiname":"Beyoglu",
    "gn:country_code":"TR",
    "gn:dem":2150,
    "gn:feature_class":"P",
    "gn:feature_code":"PPL",
    "gn:name":"Beyo\u011flu",
    "gn:population":0,
    "gn:timezone":"Europe/Istanbul",
    "iso:country":"TR",
    "name:und_x_variant":[
        "Mirzihan",
        "Beyo\u011flu"
    ],
    "wof:name":"Beyoglu",
    "wof:placetype":"locality"
},
  "geometry": {"coordinates":[43.47406,40.02633],"type":"Point"}
}