{
  "type": "Feature",
  "properties": {
    "gn:admin1_code":"60.0",
    "gn:asciiname":"Alankoy",
    "gn:country_code":"TR",
    "gn:dem":1166,
    "gn:feature_class":"P",
    "gn:feature_code":"PPL",
    "gn:name":"Alank\u00f6y",
    "gn:population":0,
    "gn:timezone":"Europe/Istanbul",
    "iso:country":"TR",
    "name:und_x_variant":[
        "Alank\u00f6y",
        "Alan"
    ],
    "wof:name":"Alankoy",
    "wof:placetype":"locality"
},
  "geometry": {"coordinates":[37.0738,40.58096],"type":"Point"}
}