{
  "type": "Feature",
  "properties": {
    "gn:admin1_code":"63",
    "gn:asciiname":"Yukari Goklu",
    "gn:country_code":"TR",
    "gn:dem":604,
    "gn:feature_class":"P",
    "gn:feature_code":"PPL",
    "gn:name":"Yukar\u0131 G\u00f6kl\u00fc",
    "gn:population":0,
    "gn:timezone":"Europe/Istanbul",
    "iso:country":"TR",
    "name:tur_x_preferred":[
        "Yukar\u0131 G\u00f6kl\u00fc"
    ],
    "name:und_x_variant":[
        "B\u00fcy\u00fck G\u00f6kl\u00fc",
        "Yukar\u0131 K\u00f6y",
        "B\u00fcy\u00fckg\u00f6\u011fl\u00fc",
        "Yukar\u0131g\u00f6\u011fl\u00fc"
    ],
    "wof:name":"Yukari Goklu",
    "wof:placetype":"locality"
},
  "geometry": {"coordinates":[37.99043,37.3391],"type":"Point"}
}