{
  "type": "Feature",
  "properties": {
    "gn:admin1_code":"53",
    "gn:asciiname":"Yenisehitlik",
    "gn:country_code":"TR",
    "gn:dem":600,
    "gn:feature_class":"P",
    "gn:feature_code":"PPL",
    "gn:name":"Yeni\u015fehitlik",
    "gn:population":0,
    "gn:timezone":"Europe/Istanbul",
    "iso:country":"TR",
    "name:tur_x_preferred":[
        "Yeni\u015fehitlik"
    ],
    "wof:name":"Yenisehitlik",
    "wof:placetype":"locality"
},
  "geometry": {"coordinates":[41.24129,41.22698],"type":"Point"}
}