{
  "type": "Feature",
  "properties": {
    "gn:admin1_code":"17",
    "gn:asciiname":"Calti",
    "gn:country_code":"TR",
    "gn:dem":335,
    "gn:feature_class":"P",
    "gn:feature_code":"PPL",
    "gn:name":"\u00c7alt\u0131",
    "gn:population":0,
    "gn:timezone":"Europe/Istanbul",
    "iso:country":"TR",
    "name:und_x_variant":[
        "Chalty-Koyu",
        "\u00c7alt\u0131k\u00f6y",
        "\u00c7alt\u0131 K\u00f6y\u00fc",
        "\u00c7alt\u0131"
    ],
    "wof:name":"Calti",
    "wof:placetype":"locality"
},
  "geometry": {"coordinates":[26.52256,39.61484],"type":"Point"}
}