{
  "type": "Feature",
  "properties": {
    "gn:admin1_code":"09",
    "gn:asciiname":"Mutluca",
    "gn:country_code":"TR",
    "gn:dem":327,
    "gn:feature_class":"P",
    "gn:feature_code":"PPL",
    "gn:name":"Mutluca",
    "gn:population":0,
    "gn:timezone":"Europe/Istanbul",
    "iso:country":"TR",
    "name:tur_x_preferred":[
        "Mutluca"
    ],
    "wof:name":"Mutluca",
    "wof:placetype":"locality"
},
  "geometry": {"coordinates":[27.89899,37.51968],"type":"Point"}
}