{
  "type": "Feature",
  "properties": {
    "gn:admin1_code":"52.0",
    "gn:asciiname":"Guzle",
    "gn:country_code":"TR",
    "gn:dem":1385,
    "gn:feature_class":"P",
    "gn:feature_code":"PPL",
    "gn:name":"G\u00fczle",
    "gn:population":0,
    "gn:timezone":"Europe/Istanbul",
    "iso:country":"TR",
    "name:tur_x_preferred":[
        "G\u00fczle"
    ],
    "wof:name":"Guzle",
    "wof:placetype":"locality"
},
  "geometry": {"coordinates":[37.67072,40.49985],"type":"Point"}
}