{
  "type": "Feature",
  "properties": {
    "gn:admin1_code":"20",
    "gn:asciiname":"Kaziklar",
    "gn:country_code":"TR",
    "gn:dem":767,
    "gn:feature_class":"P",
    "gn:feature_code":"PPL",
    "gn:name":"Kaz\u0131klar",
    "gn:population":0,
    "gn:timezone":"Europe/Istanbul",
    "iso:country":"TR",
    "name:tur_x_preferred":[
        "Kaz\u0131klar"
    ],
    "wof:name":"Kaziklar",
    "wof:placetype":"locality"
},
  "geometry": {"coordinates":[28.78646,37.45204],"type":"Point"}
}