{
  "type": "Feature",
  "properties": {
    "gn:admin1_code":"90.0",
    "gn:asciiname":"Melunedolar",
    "gn:cc2":"TR",
    "gn:country_code":"TR",
    "gn:dem":469,
    "gn:feature_class":"P",
    "gn:feature_code":"PPL",
    "gn:name":"Melunedolar",
    "gn:population":0,
    "gn:timezone":"Europe/Istanbul",
    "iso:country":"TR",
    "name:und_x_variant":[
        "Alininev\u0131",
        "Melunedolar"
    ],
    "wof:name":"Melunedolar",
    "wof:placetype":"locality"
},
  "geometry": {"coordinates":[36.99139,36.825],"type":"Point"}
}