{
  "type": "Feature",
  "properties": {
    "gn:admin1_code":"74",
    "gn:asciiname":"Karabag",
    "gn:country_code":"TR",
    "gn:dem":941,
    "gn:feature_class":"P",
    "gn:feature_code":"PPL",
    "gn:name":"Karaba\u011f",
    "gn:population":0,
    "gn:timezone":"Europe/Istanbul",
    "iso:country":"TR",
    "name:tur_x_preferred":[
        "Karaba\u011f"
    ],
    "wof:name":"Karabag",
    "wof:placetype":"locality"
},
  "geometry": {"coordinates":[41.70656,38.039],"type":"Point"}
}