{
  "type": "Feature",
  "properties": {
    "gn:admin1_code":"54.0",
    "gn:asciiname":"Gokceler",
    "gn:country_code":"TR",
    "gn:dem":280,
    "gn:feature_class":"P",
    "gn:feature_code":"PPL",
    "gn:name":"G\u00f6k\u00e7eler",
    "gn:population":0,
    "gn:timezone":"Europe/Istanbul",
    "iso:country":"TR",
    "name:tur_x_preferred":[
        "G\u00f6k\u00e7eler"
    ],
    "wof:name":"Gokceler",
    "wof:placetype":"locality"
},
  "geometry": {"coordinates":[30.76667,40.58678],"type":"Point"}
}