{
  "type": "Feature",
  "properties": {
    "gn:country":"TR",
    "gn:fcode":"PPL",
    "gn:population":7335,
    "iso:country":"TR",
    "name:rus_x_preferred":[
        "\u0411\u0443\u044e\u043a\u0430\u0434\u0430"
    ],
    "name:und_x_variant":[
        "Prinkipo"
    ],
    "qs:name":"Adalar",
    "qs:photos_9r":0,
    "qs:photos_sr":0,
    "qs:pop_sr":"5",
    "wof:name":"Adalar",
    "wof:placetype":"locality",
    "wof:population":7335
},
  "geometry": {"coordinates":[29.13306,40.86778],"type":"Point"}
}