{
  "type": "Feature",
  "properties": {
    "gn:admin1_code":"83.0",
    "gn:asciiname":"Agabey",
    "gn:country_code":"TR",
    "gn:dem":613,
    "gn:feature_class":"P",
    "gn:feature_code":"PPL",
    "gn:name":"A\u011fabey",
    "gn:population":0,
    "gn:timezone":"Europe/Istanbul",
    "iso:country":"TR",
    "name:tur_x_preferred":[
        "A\u011fabey"
    ],
    "name:und_x_variant":[
        "S\u0131\u00e7anbanisi",
        "Agabey-Banysy",
        "A\u011fabeyban\u0131s\u0131"
    ],
    "wof:name":"Agabey",
    "wof:placetype":"locality"
},
  "geometry": {"coordinates":[36.58833,36.9725],"type":"Point"}
}