{
  "type": "Feature",
  "properties": {
    "gn:admin1_code":"32",
    "gn:asciiname":"Kocahasanli",
    "gn:country_code":"TR",
    "gn:dem":26,
    "gn:feature_class":"P",
    "gn:feature_code":"PPL",
    "gn:name":"Kocahasanl\u0131",
    "gn:population":5738,
    "gn:timezone":"Europe/Istanbul",
    "iso:country":"TR",
    "name:und_x_variant":[
        "Kocahasanl\u0131"
    ],
    "wof:name":"Kocahasanli",
    "wof:placetype":"locality",
    "wof:population":5738
},
  "geometry": {"coordinates":[34.27359000000001,36.58417],"type":"Point"}
}