{
  "type": "Feature",
  "properties": {
    "gn:admin1_code":"46",
    "gn:asciiname":"Asagiicme",
    "gn:country_code":"TR",
    "gn:dem":1202,
    "gn:feature_class":"P",
    "gn:feature_code":"PPL",
    "gn:name":"A\u015fa\u011f\u0131i\u00e7me",
    "gn:population":0,
    "gn:timezone":"Europe/Istanbul",
    "iso:country":"TR",
    "name:tur_x_preferred":[
        "A\u015fa\u011f\u0131i\u00e7me"
    ],
    "wof:name":"Asagiicme",
    "wof:placetype":"locality"
},
  "geometry": {"coordinates":[37.15617,38.03633],"type":"Point"}
}