{
  "type": "Feature",
  "properties": {
    "gn:country":"TR",
    "gn:fcode":"PPL",
    "gn:pop":6837,
    "iso:country":"TR",
    "name:ara_x_preferred":[
        "\u0628\u0631\u062a\u0643"
    ],
    "name:ceb_x_preferred":[
        "Pertek \u0130l\u00e7esi"
    ],
    "name:ckb_x_preferred":[
        "\u067e\u06ce\u0631\u062a\u0627\u06af\u06d5"
    ],
    "name:deu_x_preferred":[
        "Pertek"
    ],
    "name:diq_x_preferred":[
        "P\u00eartage"
    ],
    "name:eng_x_preferred":[
        "Pertek"
    ],
    "name:fas_x_preferred":[
        "\u067e\u0631\u062a\u06a9"
    ],
    "name:fra_x_preferred":[
        "Pertek"
    ],
    "name:hye_x_preferred":[
        "\u0532\u0565\u0580\u0564\u0561\u056f"
    ],
    "name:kur_x_preferred":[
        "P\u00eartag"
    ],
    "name:mrj_x_preferred":[
        "\u041f\u0435\u0440\u0442\u0435\u043a"
    ],
    "name:msa_x_preferred":[
        "Pertek"
    ],
    "name:nan_x_preferred":[
        "Pertek"
    ],
    "name:nld_x_preferred":[
        "Pertek"
    ],
    "name:nno_x_preferred":[
        "Pertek"
    ],
    "name:nob_x_preferred":[
        "Pertek"
    ],
    "name:pnb_x_preferred":[
        "\u0636\u0644\u0639 \u067e\u0631\u062a\u06a9"
    ],
    "name:rus_x_preferred":[
        "\u041f\u0435\u0440\u0442\u0435\u043a"
    ],
    "name:swa_x_preferred":[
        "Pertek"
    ],
    "name:tur_x_preferred":[
        "Pertek"
    ],
    "name:urd_x_preferred":[
        "\u067e\u0631\u062a\u06a9"
    ],
    "name:vie_x_preferred":[
        "Pertek"
    ],
    "name:zho_x_preferred":[
        "\u4f69\u723e\u6cf0\u514b"
    ],
    "name:zho_x_variant":[
        "Palamutlu"
    ],
    "qs:name":"Pertek",
    "qs:name_adm0":"Turkey",
    "qs:name_adm1":"Tunceli",
    "qs:photos_9k":1,
    "qs:photos_9r":2,
    "qs:photos_all":27,
    "qs:photos_sr":0,
    "qs:placetype":"Town",
    "qs:pop_sr":"5",
    "wd:wordcount":306,
    "wof:name":"Pertek",
    "wof:placetype":"locality",
    "wof:population":6837
},
  "geometry": {"coordinates":[39.32684,38.86633],"type":"Point"}
}