{
  "type": "Feature",
  "properties": {
    "gn:admin1_code":"74.0",
    "gn:asciiname":"Kekliktepe",
    "gn:country_code":"TR",
    "gn:dem":928,
    "gn:feature_class":"P",
    "gn:feature_code":"PPL",
    "gn:name":"Kekliktepe",
    "gn:population":0,
    "gn:timezone":"Europe/Istanbul",
    "iso:country":"TR",
    "name:tur_x_preferred":[
        "Kekliktepe"
    ],
    "name:und_x_variant":[
        "Halidi",
        "Khalidi",
        "Keliktepe"
    ],
    "wof:name":"Kekliktepe",
    "wof:placetype":"locality"
},
  "geometry": {"coordinates":[42.01167,37.66472],"type":"Point"}
}