{
  "type": "Feature",
  "properties": {
    "gn:admin1_code":"71.0",
    "gn:asciiname":"Adakasim",
    "gn:country_code":"TR",
    "gn:dem":900,
    "gn:feature_class":"P",
    "gn:feature_code":"PPL",
    "gn:name":"Adakas\u0131m",
    "gn:population":0,
    "gn:timezone":"Europe/Istanbul",
    "iso:country":"TR",
    "wof:name":"Adakasim",
    "wof:placetype":"locality"
},
  "geometry": {"coordinates":[31.89306,38.95694],"type":"Point"}
}