{
  "type": "Feature",
  "properties": {
    "gn:admin1_code":"69.0",
    "gn:asciiname":"Reksene",
    "gn:country_code":"TR",
    "gn:dem":1653,
    "gn:feature_class":"P",
    "gn:feature_code":"PPL",
    "gn:name":"Reksene",
    "gn:population":0,
    "gn:timezone":"Europe/Istanbul",
    "iso:country":"TR",
    "name:und_x_variant":[
        "\u00c7at\u0131l\u0131",
        "\u00c7alt\u0131l\u0131"
    ],
    "wof:name":"Reksene",
    "wof:placetype":"locality"
},
  "geometry": {"coordinates":[39.45288,40.34513],"type":"Point"}
}