{
  "type": "Feature",
  "properties": {
    "gn:admin1_code":"25",
    "gn:asciiname":"Ovenler",
    "gn:country_code":"TR",
    "gn:dem":1717,
    "gn:feature_class":"P",
    "gn:feature_code":"PPL",
    "gn:name":"\u00d6venler",
    "gn:population":0,
    "gn:timezone":"Europe/Istanbul",
    "iso:country":"TR",
    "name:tur_x_preferred":[
        "\u00d6venler"
    ],
    "wof:name":"Ovenler",
    "wof:placetype":"locality"
},
  "geometry": {"coordinates":[41.56982,40.00143],"type":"Point"}
}