{
  "type": "Feature",
  "properties": {
    "gn:country":"TR",
    "gn:fcode":"PPL",
    "gn:population":313,
    "iso:country":"TR",
    "name:cat_x_preferred":[
        "Baluni"
    ],
    "name:eng_x_preferred":[
        "Baluni"
    ],
    "name:tur_x_preferred":[
        "\u00c7ak\u0131ll\u0131"
    ],
    "name:und_x_variant":[
        "Yunuslar"
    ],
    "qs:name":"Paluni",
    "qs:photos_9r":0,
    "qs:photos_sr":0,
    "qs:pop_sr":"2",
    "wd:wordcount":72,
    "wof:name":"Paluni",
    "wof:placetype":"locality",
    "wof:population":313
},
  "geometry": {"coordinates":[41.42703,37.9475],"type":"Point"}
}