{
  "type": "Feature",
  "properties": {
    "gn:admin1_code":"17.0",
    "gn:asciiname":"Subasi",
    "gn:country_code":"TR",
    "gn:dem":130,
    "gn:feature_class":"P",
    "gn:feature_code":"PPL",
    "gn:name":"Suba\u015f\u0131",
    "gn:population":0,
    "gn:timezone":"Europe/Istanbul",
    "iso:country":"TR",
    "wof:name":"Subasi",
    "wof:placetype":"locality"
},
  "geometry": {"coordinates":[25.74244,40.10358],"type":"Point"}
}