{
  "type": "Feature",
  "properties": {
    "gn:admin1_code":"76.0",
    "gn:asciiname":"Khirre",
    "gn:country_code":"TR",
    "gn:dem":1209,
    "gn:feature_class":"P",
    "gn:feature_code":"PPL",
    "gn:name":"Khirre",
    "gn:population":0,
    "gn:timezone":"Europe/Istanbul",
    "iso:country":"TR",
    "name:tur_x_preferred":[
        "Ba\u011f\u00f6z\u00fc"
    ],
    "name:und_x_variant":[
        "Hirro",
        "Khirre"
    ],
    "wof:name":"Khirre",
    "wof:placetype":"locality"
},
  "geometry": {"coordinates":[41.17285,37.60162],"type":"Point"}
}