{
  "type": "Feature",
  "properties": {
    "gn:admin1_code":"69.0",
    "gn:asciiname":"Tepedam",
    "gn:country_code":"TR",
    "gn:dem":1530,
    "gn:feature_class":"P",
    "gn:feature_code":"PPL",
    "gn:name":"Tepedam",
    "gn:population":0,
    "gn:timezone":"Europe/Istanbul",
    "iso:country":"TR",
    "name:und_x_variant":[
        "Tepedam K\u00f6y\u00fc",
        "Tepedam"
    ],
    "wof:name":"Tepedam",
    "wof:placetype":"locality"
},
  "geometry": {"coordinates":[39.16701,40.08138],"type":"Point"}
}