{
  "type": "Feature",
  "properties": {
    "gn:admin1_code":"03",
    "gn:asciiname":"Tepekoy",
    "gn:country_code":"TR",
    "gn:dem":1006,
    "gn:feature_class":"P",
    "gn:feature_code":"PPL",
    "gn:name":"Tepek\u00f6y",
    "gn:population":0,
    "gn:timezone":"Europe/Istanbul",
    "iso:country":"TR",
    "wof:name":"Tepekoy",
    "wof:placetype":"locality"
},
  "geometry": {"coordinates":[30.05,37.96667],"type":"Point"}
}