{
  "type": "Feature",
  "properties": {
    "gn:admin1_code":"80",
    "gn:asciiname":"Dereler",
    "gn:country_code":"TR",
    "gn:dem":1451,
    "gn:feature_class":"P",
    "gn:feature_code":"PPL",
    "gn:name":"Dereler",
    "gn:population":0,
    "gn:timezone":"Europe/Istanbul",
    "iso:country":"TR",
    "name:und_x_variant":[
        "Av\u2019yan",
        "Evpiyat",
        "Avyan",
        "Dereler"
    ],
    "wof:name":"Dereler",
    "wof:placetype":"locality"
},
  "geometry": {"coordinates":[42.74781,37.60731],"type":"Point"}
}