{
  "type": "Feature",
  "properties": {
    "gn:admin1_code":"82.0",
    "gn:asciiname":"Cirdak",
    "gn:country_code":"TR",
    "gn:dem":1523,
    "gn:feature_class":"P",
    "gn:feature_code":"PPL",
    "gn:name":"\u00c7\u0131rdak",
    "gn:population":0,
    "gn:timezone":"Europe/Istanbul",
    "iso:country":"TR",
    "wof:name":"Cirdak",
    "wof:placetype":"locality"
},
  "geometry": {"coordinates":[33.32106,40.91852],"type":"Point"}
}