{
  "type": "Feature",
  "properties": {
    "gn:admin1_code":"32",
    "gn:asciiname":"Altay",
    "gn:country_code":"TR",
    "gn:dem":1191,
    "gn:feature_class":"P",
    "gn:feature_code":"PPL",
    "gn:name":"Altay",
    "gn:population":0,
    "gn:timezone":"Europe/Istanbul",
    "iso:country":"TR",
    "name:tur_x_preferred":[
        "Altay"
    ],
    "wof:name":"Altay",
    "wof:placetype":"locality"
},
  "geometry": {"coordinates":[34.45066,37.65765],"type":"Point"}
}