{
  "type": "Feature",
  "properties": {
    "gn:admin1_code":"32",
    "gn:asciiname":"Altay",
    "gn:country_code":"TR",
    "gn:dem":1191,
    "gn:feature_class":"P",
    "gn:feature_code":"PPL",
    "gn:name":"Altay",
    "gn:population":0,
    "gn:timezone":"Europe/Istanbul",
    "iso:country":"TR",
    "name:ara_x_preferred":[
        "\u0623\u0644\u062a\u0627\u064a"
    ],
    "name:aze_x_preferred":[
        "Altay"
    ],
    "name:bre_x_preferred":[
        "Altay"
    ],
    "name:ceb_x_preferred":[
        "Altay"
    ],
    "name:deu_x_preferred":[
        "Altay"
    ],
    "name:hun_x_preferred":[
        "Altaj j\u00e1r\u00e1s"
    ],
    "name:mlg_x_preferred":[
        "Altay"
    ],
    "name:mon_x_preferred":[
        "\u0410\u043b\u0442\u0430\u0439 \u0441\u0443\u043c"
    ],
    "name:pol_x_preferred":[
        "Altay"
    ],
    "name:swe_x_preferred":[
        "Altay"
    ],
    "name:tur_x_preferred":[
        "Altay"
    ],
    "wof:name":"Altay",
    "wof:placetype":"locality"
},
  "geometry": {"coordinates":[34.45066,37.65765],"type":"Point"}
}