{
  "type": "Feature",
  "properties": {
    "gn:admin1_code":"07",
    "gn:asciiname":"Cerdin",
    "gn:country_code":"TR",
    "gn:dem":3,
    "gn:feature_class":"P",
    "gn:feature_code":"PPL",
    "gn:name":"\u00c7erdin",
    "gn:population":0,
    "gn:timezone":"Europe/Istanbul",
    "iso:country":"TR",
    "wof:name":"Cerdin",
    "wof:placetype":"locality"
},
  "geometry": {"coordinates":[30.40909000000001,36.27652],"type":"Point"}
}