{
  "type": "Feature",
  "properties": {
    "gn:admin1_code":"34.0",
    "gn:asciiname":"Karacakoy",
    "gn:country_code":"TR",
    "gn:dem":97,
    "gn:feature_class":"P",
    "gn:feature_code":"PPLA3",
    "gn:name":"Karacak\u00f6y",
    "gn:population":0,
    "gn:timezone":"Europe/Istanbul",
    "iso:country":"TR",
    "name:und_x_variant":[
        "Karaca",
        "Karacak\u00f6y"
    ],
    "wof:name":"Karacakoy",
    "wof:placetype":"locality"
},
  "geometry": {"coordinates":[29.76935,41.15126],"type":"Point"}
}