{
  "type": "Feature",
  "properties": {
    "gn:admin1_code":"81",
    "gn:asciiname":"Beydemir",
    "gn:country_code":"TR",
    "gn:dem":180,
    "gn:feature_class":"P",
    "gn:feature_code":"PPL",
    "gn:name":"Beydemir",
    "gn:population":0,
    "gn:timezone":"Europe/Istanbul",
    "iso:country":"TR",
    "name:und_x_variant":[
        "Camuslu"
    ],
    "wof:name":"Beydemir",
    "wof:placetype":"locality"
},
  "geometry": {"coordinates":[35.14127,37.27458],"type":"Point"}
}