{
  "type": "Feature",
  "properties": {
    "gn:admin1_code":"74",
    "gn:asciiname":"Caykaya",
    "gn:country_code":"TR",
    "gn:dem":598,
    "gn:feature_class":"P",
    "gn:feature_code":"PPL",
    "gn:name":"\u00c7aykaya",
    "gn:population":0,
    "gn:timezone":"Europe/Istanbul",
    "iso:country":"TR",
    "name:tur_x_preferred":[
        "\u00c7aykaya"
    ],
    "wof:name":"Caykaya",
    "wof:placetype":"locality"
},
  "geometry": {"coordinates":[41.76248,38.07705],"type":"Point"}
}