{
  "type": "Feature",
  "properties": {
    "gn:admin1_code":"66",
    "gn:asciiname":"Camurlu",
    "gn:country_code":"TR",
    "gn:dem":1048,
    "gn:feature_class":"P",
    "gn:feature_code":"PPL",
    "gn:name":"\u00c7amurlu",
    "gn:population":0,
    "gn:timezone":"Europe/Istanbul",
    "iso:country":"TR",
    "wof:name":"Camurlu",
    "wof:placetype":"locality"
},
  "geometry": {"coordinates":[35.13647,39.61274],"type":"Point"}
}