{
  "type": "Feature",
  "properties": {
    "gn:admin1_code":"03",
    "gn:asciiname":"Alibeyce",
    "gn:country_code":"TR",
    "gn:dem":1022,
    "gn:feature_class":"P",
    "gn:feature_code":"PPL",
    "gn:name":"Alibeyce",
    "gn:population":0,
    "gn:timezone":"Europe/Istanbul",
    "iso:country":"TR",
    "wof:name":"Alibeyce",
    "wof:placetype":"locality"
},
  "geometry": {"coordinates":[31.11398,39.11483],"type":"Point"}
}