{
  "type": "Feature",
  "properties": {
    "gn:admin1_code":"09",
    "gn:asciiname":"Azizabat",
    "gn:country_code":"TR",
    "gn:dem":115,
    "gn:feature_class":"P",
    "gn:feature_code":"PPL",
    "gn:name":"Azizabat",
    "gn:population":0,
    "gn:timezone":"Europe/Istanbul",
    "iso:country":"TR",
    "name:tur_x_preferred":[
        "Azizabat"
    ],
    "wof:name":"Azizabat",
    "wof:placetype":"locality"
},
  "geometry": {"coordinates":[28.56705,37.87696],"type":"Point"}
}