{
  "type": "Feature",
  "properties": {
    "gn:admin1_code":"44",
    "gn:asciiname":"Kavak",
    "gn:country_code":"TR",
    "gn:dem":1140,
    "gn:feature_class":"P",
    "gn:feature_code":"PPL",
    "gn:name":"Kavak",
    "gn:population":0,
    "gn:timezone":"Europe/Istanbul",
    "iso:country":"TR",
    "wof:name":"Kavak",
    "wof:placetype":"locality"
},
  "geometry": {"coordinates":[38.83333,38.15],"type":"Point"}
}