{
  "type": "Feature",
  "properties": {
    "gn:admin1_code":"89.0",
    "gn:asciiname":"Baglica",
    "gn:country_code":"TR",
    "gn:dem":865,
    "gn:feature_class":"P",
    "gn:feature_code":"PPL",
    "gn:name":"Ba\u011fl\u0131ca",
    "gn:population":0,
    "gn:timezone":"Europe/Istanbul",
    "iso:country":"TR",
    "name:und_x_variant":[
        "Gazye",
        "Gaziye",
        "Ba\u011fl\u0131ca"
    ],
    "wof:name":"Baglica",
    "wof:placetype":"locality"
},
  "geometry": {"coordinates":[32.95591,41.52356],"type":"Point"}
}