{
  "type": "Feature",
  "properties": {
    "gn:admin1_code":"86.0",
    "gn:asciiname":"Hive",
    "gn:country_code":"TR",
    "gn:dem":2005,
    "gn:feature_class":"P",
    "gn:feature_code":"PPL",
    "gn:name":"Hive",
    "gn:population":0,
    "gn:timezone":"Europe/Istanbul",
    "iso:country":"TR",
    "name:und_x_variant":[
        "S\u00fcr\u00fcg\u00fcden"
    ],
    "wof:name":"Hive",
    "wof:placetype":"locality"
},
  "geometry": {"coordinates":[42.63002,40.91238],"type":"Point"}
}