{
  "type": "Feature",
  "properties": {
    "gn:admin1_code":"80",
    "gn:asciiname":"Yesiloz",
    "gn:country_code":"TR",
    "gn:dem":2228,
    "gn:feature_class":"P",
    "gn:feature_code":"PPL",
    "gn:name":"Ye\u015fil\u00f6z",
    "gn:population":0,
    "gn:timezone":"Europe/Istanbul",
    "iso:country":"TR",
    "name:und_x_variant":[
        "Fara\u015fin",
        "Ye\u015fil\u00f6z"
    ],
    "wof:name":"Yesiloz",
    "wof:placetype":"locality"
},
  "geometry": {"coordinates":[43.41946,37.69344],"type":"Point"}
}