{
  "type": "Feature",
  "properties": {
    "gn:admin1_code":"38",
    "gn:asciiname":"Pazaroren",
    "gn:country_code":"TR",
    "gn:dem":1526,
    "gn:feature_class":"P",
    "gn:feature_code":"PPLA3",
    "gn:name":"Pazar\u00f6ren",
    "gn:population":0,
    "gn:timezone":"Europe/Istanbul",
    "iso:country":"TR",
    "name:und_x_variant":[
        "Pazarviran",
        "Pazar\u00f6ren"
    ],
    "wof:name":"Pazaroren",
    "wof:placetype":"locality"
},
  "geometry": {"coordinates":[36.15944,38.67389],"type":"Point"}
}