{
  "type": "Feature",
  "properties": {
    "gn:admin1_code":"07",
    "gn:asciiname":"Kozan",
    "gn:country_code":"TR",
    "gn:dem":465,
    "gn:feature_class":"P",
    "gn:feature_code":"PPL",
    "gn:name":"Kozan",
    "gn:population":0,
    "gn:timezone":"Europe/Istanbul",
    "iso:country":"TR",
    "wof:name":"Kozan",
    "wof:placetype":"locality"
},
  "geometry": {"coordinates":[30.9275,37.2225],"type":"Point"}
}