{
  "type": "Feature",
  "properties": {
    "gn:admin1_code":"21",
    "gn:asciiname":"Polatusagi",
    "gn:country_code":"TR",
    "gn:dem":1235,
    "gn:feature_class":"P",
    "gn:feature_code":"PPL",
    "gn:name":"Polatu\u015fa\u011f\u0131",
    "gn:population":0,
    "gn:timezone":"Europe/Istanbul",
    "iso:country":"TR",
    "name:und_x_variant":[
        "Polat",
        "Polatu\u015fag\u0131 K\u00f6y\u00fc",
        "Polatu\u015fa\u011f\u0131"
    ],
    "wof:name":"Polatusagi",
    "wof:placetype":"locality"
},
  "geometry": {"coordinates":[39.42955,38.27347],"type":"Point"}
}