{
  "type": "Feature",
  "properties": {
    "gn:admin1_code":"11.0",
    "gn:asciiname":"Cavuskoy",
    "gn:country_code":"TR",
    "gn:dem":657,
    "gn:feature_class":"P",
    "gn:feature_code":"PPL",
    "gn:name":"\u00c7avu\u015fk\u00f6y",
    "gn:population":0,
    "gn:timezone":"Europe/Istanbul",
    "iso:country":"TR",
    "name:und_x_variant":[
        "\u00c7avu\u015f",
        "\u00c7avu\u015fk\u00f6y"
    ],
    "wof:name":"Cavuskoy",
    "wof:placetype":"locality"
},
  "geometry": {"coordinates":[29.83997,40.20358],"type":"Point"}
}