{
  "type": "Feature",
  "properties": {
    "gn:admin1_code":"49",
    "gn:asciiname":"Yayla",
    "gn:country_code":"TR",
    "gn:dem":2104,
    "gn:feature_class":"P",
    "gn:feature_code":"PPL",
    "gn:name":"Yayla",
    "gn:population":0,
    "gn:timezone":"Europe/Istanbul",
    "iso:country":"TR",
    "name:und_x_variant":[
        "Rindali",
        "Yayla"
    ],
    "wof:name":"Yayla",
    "wof:placetype":"locality"
},
  "geometry": {"coordinates":[41.28975,39.10502],"type":"Point"}
}