{
  "type": "Feature",
  "properties": {
    "gn:admin1_code":"89",
    "gn:asciiname":"Karagozler",
    "gn:country_code":"TR",
    "gn:dem":316,
    "gn:feature_class":"P",
    "gn:feature_code":"PPL",
    "gn:name":"Karag\u00f6zler",
    "gn:population":0,
    "gn:timezone":"Europe/Istanbul",
    "iso:country":"TR",
    "wof:name":"Karagozler",
    "wof:placetype":"locality"
},
  "geometry": {"coordinates":[32.36285,41.27797],"type":"Point"}
}