{
  "type": "Feature",
  "properties": {
    "gn:admin1_code":"33",
    "gn:asciiname":"Asagitirtar",
    "gn:country_code":"TR",
    "gn:dem":1093,
    "gn:feature_class":"P",
    "gn:feature_code":"PPL",
    "gn:name":"A\u015fa\u011f\u0131t\u0131rtar",
    "gn:population":0,
    "gn:timezone":"Europe/Istanbul",
    "iso:country":"TR",
    "wof:name":"Asagitirtar",
    "wof:placetype":"locality"
},
  "geometry": {"coordinates":[30.90861,38.23333],"type":"Point"}
}