{
  "type": "Feature",
  "properties": {
    "gn:admin1_code":"44.0",
    "gn:asciiname":"Gurkaynak",
    "gn:country_code":"TR",
    "gn:dem":1653,
    "gn:feature_class":"P",
    "gn:feature_code":"PPL",
    "gn:name":"G\u00fcrkaynak",
    "gn:population":0,
    "gn:timezone":"Europe/Istanbul",
    "iso:country":"TR",
    "name:tur_x_preferred":[
        "G\u00fcrkaynak"
    ],
    "wof:name":"Gurkaynak",
    "wof:placetype":"locality"
},
  "geometry": {"coordinates":[37.81757,38.3389],"type":"Point"}
}