{
  "type": "Feature",
  "properties": {
    "gn:admin1_code":"35",
    "gn:asciiname":"Buruncuk",
    "gn:country_code":"TR",
    "gn:dem":12,
    "gn:feature_class":"P",
    "gn:feature_code":"PPL",
    "gn:name":"Buruncuk",
    "gn:population":0,
    "gn:timezone":"Europe/Istanbul",
    "iso:country":"TR",
    "wof:name":"Buruncuk",
    "wof:placetype":"locality"
},
  "geometry": {"coordinates":[27.02743,38.66987],"type":"Point"}
}