{
  "type": "Feature",
  "properties": {
    "gn:admin1_code":"70",
    "gn:asciiname":"Karabey",
    "gn:country_code":"TR",
    "gn:dem":1865,
    "gn:feature_class":"P",
    "gn:feature_code":"PPL",
    "gn:name":"Karabey",
    "gn:population":0,
    "gn:timezone":"Europe/Istanbul",
    "iso:country":"TR",
    "name:und_x_variant":[
        "Karaba\u011f",
        "Karabey"
    ],
    "wof:name":"Karabey",
    "wof:placetype":"locality"
},
  "geometry": {"coordinates":[44.41623,37.4439],"type":"Point"}
}