{
  "type": "Feature",
  "properties": {
    "gn:admin1_code":"84",
    "gn:asciiname":"Esmecayir",
    "gn:country_code":"TR",
    "gn:dem":1964,
    "gn:feature_class":"P",
    "gn:feature_code":"PPL",
    "gn:name":"E\u015fme\u00e7ay\u0131r",
    "gn:population":0,
    "gn:timezone":"Europe/Istanbul",
    "iso:country":"TR",
    "name:tur_x_preferred":[
        "E\u015fme\u00e7ay\u0131r"
    ],
    "wof:name":"Esmecayir",
    "wof:placetype":"locality"
},
  "geometry": {"coordinates":[42.53182,40.05302],"type":"Point"}
}