{
  "type": "Feature",
  "properties": {
    "gn:admin1_code":"49",
    "gn:asciiname":"Bilir",
    "gn:country_code":"TR",
    "gn:dem":1431,
    "gn:feature_class":"P",
    "gn:feature_code":"PPL",
    "gn:name":"Bilir",
    "gn:population":0,
    "gn:timezone":"Europe/Istanbul",
    "iso:country":"TR",
    "name:und_x_variant":[
        "Bilirk\u00f6y",
        "Bilir"
    ],
    "wof:name":"Bilir",
    "wof:placetype":"locality"
},
  "geometry": {"coordinates":[41.3927,38.76179000000001],"type":"Point"}
}