{
  "type": "Feature",
  "properties": {
    "gn:admin1_code":"37.0",
    "gn:asciiname":"Himmetli",
    "gn:country_code":"TR",
    "gn:dem":877,
    "gn:feature_class":"P",
    "gn:feature_code":"PPL",
    "gn:name":"Himmetli",
    "gn:population":0,
    "gn:timezone":"Europe/Istanbul",
    "iso:country":"TR",
    "name:tur_x_preferred":[
        "Himmetli"
    ],
    "name:und_x_variant":[
        "Arapl\u0131",
        "K\u00f6kl\u00fc"
    ],
    "wof:name":"Himmetli",
    "wof:placetype":"locality"
},
  "geometry": {"coordinates":[33.82666,41.33294],"type":"Point"}
}