{
  "type": "Feature",
  "properties": {
    "gn:country":"TR",
    "gn:fcode":"PPL",
    "gn:population":6201,
    "iso:country":"TR",
    "name:ast_x_preferred":[
        "Karacasu"
    ],
    "name:ceb_x_preferred":[
        "Karacasu"
    ],
    "name:che_x_preferred":[
        "\u041a\u0430\u0440\u0430\u0434\u0436\u0430\u0441\u0443"
    ],
    "name:deu_x_preferred":[
        "Karacasu"
    ],
    "name:diq_x_preferred":[
        "Karacasu"
    ],
    "name:eng_x_preferred":[
        "Karacasu"
    ],
    "name:epo_x_preferred":[
        "Karacasu"
    ],
    "name:fas_x_preferred":[
        "\u06a9\u0627\u0631\u0627\u062c\u0627\u0633\u0648"
    ],
    "name:fin_x_preferred":[
        "Karacasu"
    ],
    "name:fra_x_preferred":[
        "Karacasu"
    ],
    "name:lbe_x_preferred":[
        "\u041a\u044a\u0430\u0440\u0430\u0434\u0436\u0430\u0441\u0443"
    ],
    "name:mrj_x_preferred":[
        "\u041a\u0430\u0440\u0430\u0434\u0436\u0430\u0441\u0443"
    ],
    "name:msa_x_preferred":[
        "Karacasu"
    ],
    "name:nan_x_preferred":[
        "Karacasu"
    ],
    "name:nld_x_preferred":[
        "Karacasu"
    ],
    "name:nob_x_preferred":[
        "Karacasu"
    ],
    "name:rus_x_preferred":[
        "\u041a\u0430\u0440\u0430\u0434\u0436\u0430\u0441\u0443"
    ],
    "name:swa_x_preferred":[
        "Karacasu"
    ],
    "name:tat_x_preferred":[
        "\u041a\u0430\u0440\u0430\u0497\u0430\u0441\u0443"
    ],
    "name:tur_x_preferred":[
        "Karacasu"
    ],
    "name:urd_x_preferred":[
        "\u0642\u0631\u06c1 \u062c\u0627\u0633\u0648"
    ],
    "name:vie_x_preferred":[
        "Karacasu"
    ],
    "name:zho_x_preferred":[
        "\u5361\u62c9\u8d3e\u82cf"
    ],
    "qs:name":"Karacasu",
    "qs:photos_9r":0,
    "qs:photos_sr":0,
    "qs:pop_sr":"5",
    "wd:wordcount":245,
    "wof:name":"Karacasu",
    "wof:placetype":"locality",
    "wof:population":6201
},
  "geometry": {"coordinates":[28.60569,37.72816],"type":"Point"}
}