{
  "type": "Feature",
  "properties": {
    "gn:country":"TR",
    "gn:fcode":"PPL",
    "gn:pop":6201,
    "iso:country":"TR",
    "qs:name":"Karacasu",
    "qs:photos_9r":0,
    "qs:photos_sr":0,
    "qs:pop_sr":"5",
    "wd:wordcount":245,
    "wof:name":"Karacasu",
    "wof:placetype":"locality",
    "wof:population":6201
},
  "geometry": {"coordinates":[28.60569,37.72816],"type":"Point"}
}