{
  "type": "Feature",
  "properties": {
    "gn:admin1_code":"61.0",
    "gn:asciiname":"Velikoy",
    "gn:country_code":"TR",
    "gn:dem":268,
    "gn:feature_class":"P",
    "gn:feature_code":"PPL",
    "gn:name":"Velik\u00f6y",
    "gn:population":0,
    "gn:timezone":"Europe/Istanbul",
    "iso:country":"TR",
    "wof:name":"Velikoy",
    "wof:placetype":"locality"
},
  "geometry": {"coordinates":[39.42234000000001,41.07102],"type":"Point"}
}