{
  "type": "Feature",
  "properties": {
    "gn:admin1_code":"59.0",
    "gn:asciiname":"Karacali",
    "gn:country_code":"TR",
    "gn:dem":232,
    "gn:feature_class":"P",
    "gn:feature_code":"PPL",
    "gn:name":"Kara\u00e7al\u0131",
    "gn:population":0,
    "gn:timezone":"Europe/Istanbul",
    "iso:country":"TR",
    "name:und_x_variant":[
        "Kara\u00e7al\u0131l\u0131k",
        "Kara\u00e7al\u0131"
    ],
    "wof:name":"Karacali",
    "wof:placetype":"locality"
},
  "geometry": {"coordinates":[27.28898,40.88804],"type":"Point"}
}