{
  "type": "Feature",
  "properties": {
    "gn:admin1_code":"57.0",
    "gn:asciiname":"Nolut",
    "gn:country_code":"TR",
    "gn:dem":358,
    "gn:feature_class":"P",
    "gn:feature_code":"PPL",
    "gn:name":"Nolut",
    "gn:population":0,
    "gn:timezone":"Europe/Istanbul",
    "iso:country":"TR",
    "wof:name":"Nolut",
    "wof:placetype":"locality"
},
  "geometry": {"coordinates":[34.46667,41.91667],"type":"Point"}
}