{
  "type": "Feature",
  "properties": {
    "gn:admin1_code":"53.0",
    "gn:asciiname":"Caglayan",
    "gn:country_code":"TR",
    "gn:dem":120,
    "gn:feature_class":"P",
    "gn:feature_code":"PPL",
    "gn:name":"\u00c7a\u011flayan",
    "gn:population":0,
    "gn:timezone":"Europe/Istanbul",
    "iso:country":"TR",
    "name:tur_x_preferred":[
        "Abu\u00fclya"
    ],
    "name:tur_x_variant":[
        "Ab\u0131\u00fclya"
    ],
    "name:und_x_variant":[
        "\u00c7a\u011flayan",
        "Yenimahalle"
    ],
    "wof:name":"Caglayan",
    "wof:placetype":"locality"
},
  "geometry": {"coordinates":[41.20349,41.2591],"type":"Point"}
}