{
  "type": "Feature",
  "properties": {
    "gn:admin1_code":"54",
    "gn:asciiname":"Bickiatik",
    "gn:country_code":"TR",
    "gn:dem":445,
    "gn:feature_class":"P",
    "gn:feature_code":"PPL",
    "gn:name":"B\u0131\u00e7k\u0131atik",
    "gn:population":0,
    "gn:timezone":"Europe/Istanbul",
    "iso:country":"TR",
    "name:tur_x_preferred":[
        "B\u0131\u00e7k\u0131atik"
    ],
    "wof:name":"Bickiatik",
    "wof:placetype":"locality"
},
  "geometry": {"coordinates":[30.85953,40.85145],"type":"Point"}
}