{
  "type": "Feature",
  "properties": {
    "gn:admin1_code":"14.0",
    "gn:asciiname":"Kovalaklar",
    "gn:country_code":"TR",
    "gn:dem":764,
    "gn:feature_class":"P",
    "gn:feature_code":"PPL",
    "gn:name":"Kovalaklar",
    "gn:population":0,
    "gn:timezone":"Europe/Istanbul",
    "iso:country":"TR",
    "name:und_x_variant":[
        "Ko\u011fumdivan\u0131",
        "Kovalaklar"
    ],
    "wof:name":"Kovalaklar",
    "wof:placetype":"locality"
},
  "geometry": {"coordinates":[31.81157,40.84086],"type":"Point"}
}