{
  "type": "Feature",
  "properties": {
    "gn:admin1_code":"49",
    "gn:asciiname":"Mollaali",
    "gn:country_code":"TR",
    "gn:dem":1760,
    "gn:feature_class":"P",
    "gn:feature_code":"PPL",
    "gn:name":"Mollaali",
    "gn:population":0,
    "gn:timezone":"Europe/Istanbul",
    "iso:country":"TR",
    "name:tur_x_preferred":[
        "Badem\u00f6z\u00fc"
    ],
    "wof:name":"Mollaali",
    "wof:placetype":"locality"
},
  "geometry": {"coordinates":[42.42211,39.40338],"type":"Point"}
}