{
  "type": "Feature",
  "properties": {
    "gn:admin1_code":"37.0",
    "gn:asciiname":"Akcatas",
    "gn:country_code":"TR",
    "gn:dem":1383,
    "gn:feature_class":"P",
    "gn:feature_code":"PPL",
    "gn:name":"Ak\u00e7ata\u015f",
    "gn:population":0,
    "gn:timezone":"Europe/Istanbul",
    "iso:country":"TR",
    "name:und_x_variant":[
        "Ak\u00e7ata\u015f",
        "Akta\u015f"
    ],
    "wof:name":"Akcatas",
    "wof:placetype":"locality"
},
  "geometry": {"coordinates":[34.01528,41.19323],"type":"Point"}
}