{
  "type": "Feature",
  "properties": {
    "gn:admin1_code":"48",
    "gn:asciiname":"Akbel",
    "gn:country_code":"TR",
    "gn:dem":756,
    "gn:feature_class":"P",
    "gn:feature_code":"PPL",
    "gn:name":"Akbel",
    "gn:population":0,
    "gn:timezone":"Europe/Istanbul",
    "iso:country":"TR",
    "name:tur_x_preferred":[
        "Akbel"
    ],
    "wof:name":"Akbel",
    "wof:placetype":"locality"
},
  "geometry": {"coordinates":[29.00567,36.87789],"type":"Point"}
}