{
  "type": "Feature",
  "properties": {
    "gn:admin1_code":"65",
    "gn:asciiname":"Toklu",
    "gn:country_code":"TR",
    "gn:dem":2327,
    "gn:feature_class":"P",
    "gn:feature_code":"PPL",
    "gn:name":"Toklu",
    "gn:population":0,
    "gn:timezone":"Europe/Istanbul",
    "iso:country":"TR",
    "wof:name":"Toklu",
    "wof:placetype":"locality"
},
  "geometry": {"coordinates":[43.23333,39.21667],"type":"Point"}
}