{
  "type": "Feature",
  "properties": {
    "gn:admin1_code":"91",
    "gn:asciiname":"Karatas",
    "gn:country_code":"TR",
    "gn:dem":884,
    "gn:feature_class":"P",
    "gn:feature_code":"PPL",
    "gn:name":"Karata\u015f",
    "gn:population":0,
    "gn:timezone":"Europe/Istanbul",
    "iso:country":"TR",
    "name:ceb_x_preferred":[
        "Karatas"
    ],
    "name:swe_x_preferred":[
        "Karatas"
    ],
    "wof:name":"Karatas",
    "wof:placetype":"locality"
},
  "geometry": {"coordinates":[36.38455,37.07341],"type":"Point"}
}