{
  "type": "Feature",
  "properties": {
    "gn:admin1_code":"71",
    "gn:asciiname":"Koseler",
    "gn:country_code":"TR",
    "gn:dem":1253,
    "gn:feature_class":"P",
    "gn:feature_code":"PPL",
    "gn:name":"K\u00f6seler",
    "gn:population":0,
    "gn:timezone":"Europe/Istanbul",
    "iso:country":"TR",
    "name:und_x_variant":[
        "K\u00f6seler Yaylas\u0131",
        "K\u00f6seler"
    ],
    "wof:name":"Koseler",
    "wof:placetype":"locality"
},
  "geometry": {"coordinates":[32.35,37.86667],"type":"Point"}
}