{
  "type": "Feature",
  "properties": {
    "gn:admin1_code":"07",
    "gn:asciiname":"Karakaya",
    "gn:country_code":"TR",
    "gn:dem":42,
    "gn:feature_class":"P",
    "gn:feature_code":"PPL",
    "gn:name":"Karakaya",
    "gn:population":0,
    "gn:timezone":"Europe/Istanbul",
    "iso:country":"TR",
    "wof:name":"Karakaya",
    "wof:placetype":"locality"
},
  "geometry": {"coordinates":[31.70919,36.69606],"type":"Point"}
}