{
  "type": "Feature",
  "properties": {
    "gn:admin1_code":"2.0",
    "gn:asciiname":"Karamagar",
    "gn:country_code":"TR",
    "gn:dem":608,
    "gn:feature_class":"P",
    "gn:feature_code":"PPL",
    "gn:name":"Karama\u011far",
    "gn:population":0,
    "gn:timezone":"Europe/Istanbul",
    "iso:country":"TR",
    "name:tur_x_preferred":[
        "Karama\u011far"
    ],
    "wof:name":"Karamagar",
    "wof:placetype":"locality"
},
  "geometry": {"coordinates":[38.72813,37.7674],"type":"Point"}
}