{
  "type": "Feature",
  "properties": {
    "gn:country":"TR",
    "gn:fcode":"PPL",
    "gn:pop":777,
    "iso:country":"TR",
    "name:unk_x_variant":[
        "\u00dczim"
    ],
    "qs:name":"Uzyum",
    "qs:photos_9r":0,
    "qs:photos_sr":0,
    "qs:pop_sr":"2",
    "wof:name":"Uzyum",
    "wof:placetype":"locality",
    "wof:population":777
},
  "geometry": {"coordinates":[42.72319,38.00536],"type":"Point"}
}