{
  "type": "Feature",
  "properties": {
    "gn:admin1_code":"83",
    "gn:asciiname":"Subagi",
    "gn:country_code":"TR",
    "gn:dem":446,
    "gn:feature_class":"P",
    "gn:feature_code":"PPL",
    "gn:name":"Suba\u011f\u0131",
    "gn:population":0,
    "gn:timezone":"Europe/Istanbul",
    "iso:country":"TR",
    "name:rus_x_preferred":[
        "Til\u2019syumen"
    ],
    "name:tur_x_preferred":[
        "Suba\u011f\u0131"
    ],
    "name:tur_x_variant":[
        "Subo\u011faz\u0131"
    ],
    "name:und_x_variant":[
        "Tils\u00fcmen"
    ],
    "wof:name":"Subagi",
    "wof:placetype":"locality"
},
  "geometry": {"coordinates":[37.87589000000001,36.86111],"type":"Point"}
}