{
  "type": "Feature",
  "properties": {
    "gn:admin1_code":"68.0",
    "gn:asciiname":"Guzelyurt",
    "gn:country_code":"TR",
    "gn:dem":1307,
    "gn:feature_class":"P",
    "gn:feature_code":"PPL",
    "gn:name":"G\u00fczelyurt",
    "gn:population":0,
    "gn:timezone":"Europe/Istanbul",
    "iso:country":"TR",
    "name:tur_x_preferred":[
        "G\u00fczelyurt"
    ],
    "name:tur_x_variant":[
        "Geldibuldu"
    ],
    "wof:name":"Guzelyurt",
    "wof:placetype":"locality"
},
  "geometry": {"coordinates":[32.81738,40.17602],"type":"Point"}
}