{
  "type": "Feature",
  "properties": {
    "gn:admin1_code":"54",
    "gn:asciiname":"Korucuk",
    "gn:country_code":"TR",
    "gn:dem":169,
    "gn:feature_class":"P",
    "gn:feature_code":"PPL",
    "gn:name":"Korucuk",
    "gn:population":0,
    "gn:timezone":"Europe/Istanbul",
    "iso:country":"TR",
    "name:tur_x_preferred":[
        "Korucuk"
    ],
    "wof:name":"Korucuk",
    "wof:placetype":"locality"
},
  "geometry": {"coordinates":[30.28246,40.85543],"type":"Point"}
}