{
  "type": "Feature",
  "properties": {
    "gn:admin1_code":"11",
    "gn:asciiname":"Metristepe",
    "gn:country_code":"TR",
    "gn:dem":1175,
    "gn:feature_class":"P",
    "gn:feature_code":"PPL",
    "gn:name":"Metristepe",
    "gn:population":0,
    "gn:timezone":"Europe/Istanbul",
    "iso:country":"TR",
    "name:tur_x_preferred":[
        "Metristepe"
    ],
    "name:und_x_variant":[
        "K\u00e2mrantekke",
        "K\u00e2murantekke"
    ],
    "wof:name":"Metristepe",
    "wof:placetype":"locality"
},
  "geometry": {"coordinates":[30.1772,39.92842],"type":"Point"}
}