{
  "type": "Feature",
  "properties": {
    "gn:admin1_code":"80.0",
    "gn:asciiname":"Benavi",
    "gn:country_code":"TR",
    "gn:dem":1256,
    "gn:feature_class":"P",
    "gn:feature_code":"PPL",
    "gn:name":"Benavi",
    "gn:population":0,
    "gn:timezone":"Europe/Istanbul",
    "iso:country":"TR",
    "wof:name":"Benavi",
    "wof:placetype":"locality"
},
  "geometry": {"coordinates":[42.60444,37.43611],"type":"Point"}
}