{
  "type": "Feature",
  "properties": {
    "gn:admin1_code":"74.0",
    "gn:asciiname":"Derincay",
    "gn:country_code":"TR",
    "gn:dem":1105,
    "gn:feature_class":"P",
    "gn:feature_code":"PPL",
    "gn:name":"Derin\u00e7ay",
    "gn:population":0,
    "gn:timezone":"Europe/Istanbul",
    "iso:country":"TR",
    "name:tur_x_preferred":[
        "Derin\u00e7ay"
    ],
    "wof:name":"Derincay",
    "wof:placetype":"locality"
},
  "geometry": {"coordinates":[42.10437,38.03878],"type":"Point"}
}