{
  "type": "Feature",
  "properties": {
    "iso:country":"TR",
    "name:tur_x_preferred":[
        "\u015ei\u015fhane"
    ],
    "wof:name":"Sishane",
    "wof:placetype":"neighbourhood"
},
  "geometry": {"coordinates":[28.9717928649458,41.02866985579575],"type":"Point"}
}