{
  "type": "Feature",
  "properties": {
    "gn:admin1_code":"00",
    "gn:asciiname":"Kamberk",
    "gn:country_code":"TR",
    "gn:dem":2782,
    "gn:feature_class":"P",
    "gn:feature_code":"PPL",
    "gn:name":"Kamberk",
    "gn:population":0,
    "gn:timezone":"Europe/Istanbul",
    "iso:country":"TR",
    "name:und_x_variant":[
        "Matresa",
        "Kamberk",
        "Medresal"
    ],
    "wof:name":"Kamberk",
    "wof:placetype":"locality"
},
  "geometry": {"coordinates":[44.57122,37.64706],"type":"Point"}
}