{
  "type": "Feature",
  "properties": {
    "gn:admin1_code":"00",
    "gn:asciiname":"Kamberk",
    "gn:country_code":"TR",
    "gn:dem":2782,
    "gn:feature_class":"P",
    "gn:feature_code":"PPL",
    "gn:name":"Kamberk",
    "gn:population":0,
    "gn:timezone":"Europe/Istanbul",
    "iso:country":"TR",
    "name:azb_x_preferred":[
        "\u06a9\u0627\u0645\u0628\u0631\u06a9"
    ],
    "name:ceb_x_preferred":[
        "Zlat\u00e9 Hory"
    ],
    "name:ces_x_preferred":[
        "Kamberk"
    ],
    "name:deu_x_preferred":[
        "Kamberk"
    ],
    "name:eus_x_preferred":[
        "Kamberk"
    ],
    "name:fas_x_preferred":[
        "\u06a9\u0627\u0645\u0628\u0631\u06a9"
    ],
    "name:fra_x_preferred":[
        "Kamberk"
    ],
    "name:hun_x_preferred":[
        "Kamberk"
    ],
    "name:ita_x_preferred":[
        "Kamberk"
    ],
    "name:msa_x_preferred":[
        "Kamberk"
    ],
    "name:nld_x_preferred":[
        "Kamberk"
    ],
    "name:oci_x_preferred":[
        "Kamberk"
    ],
    "name:pol_x_preferred":[
        "Kamberk"
    ],
    "name:por_x_preferred":[
        "Kamberk"
    ],
    "name:slk_x_preferred":[
        "Kamberk"
    ],
    "name:spa_x_preferred":[
        "Kamberk"
    ],
    "name:srp_x_preferred":[
        "\u041a\u0430\u043c\u0431\u0435\u0440\u043a"
    ],
    "name:und_x_variant":[
        "Matresa",
        "Kamberk",
        "Medresal"
    ],
    "name:vie_x_preferred":[
        "Kamberk"
    ],
    "wof:name":"Kamberk",
    "wof:placetype":"locality"
},
  "geometry": {"coordinates":[44.57122,37.64706],"type":"Point"}
}