{
  "type": "Feature",
  "properties": {
    "gn:admin1_code":"32",
    "gn:asciiname":"Evkafciftligi",
    "gn:country_code":"TR",
    "gn:dem":194,
    "gn:feature_class":"P",
    "gn:feature_code":"PPL",
    "gn:name":"Evkaf\u00e7iftli\u011fi",
    "gn:population":0,
    "gn:timezone":"Europe/Istanbul",
    "iso:country":"TR",
    "name:ceb_x_preferred":[
        "Evkaf\u00e7iftli\u011fi"
    ],
    "name:msa_x_preferred":[
        "Evkaf\u00e7iftli\u011fi"
    ],
    "name:tur_x_preferred":[
        "Evkaf\u00e7iftli\u011fik\u00f6y"
    ],
    "name:tur_x_variant":[
        "\u00c7iftlikk\u00f6y"
    ],
    "name:und_x_variant":[
        "Evkaf\u00e7iftli\u011fi"
    ],
    "name:vie_x_preferred":[
        "Evkaf\u00e7iftli\u011fi"
    ],
    "wof:name":"Evkafciftligi",
    "wof:placetype":"locality"
},
  "geometry": {"coordinates":[33.63359000000001,36.45946],"type":"Point"}
}