{
  "type": "Feature",
  "properties": {
    "gn:admin1_code":"49",
    "gn:asciiname":"Ozkonak",
    "gn:country_code":"TR",
    "gn:dem":1553,
    "gn:feature_class":"P",
    "gn:feature_code":"PPL",
    "gn:name":"\u00d6zkonak",
    "gn:population":0,
    "gn:timezone":"Europe/Istanbul",
    "iso:country":"TR",
    "name:und_x_variant":[
        "\u00c7arsan",
        "\u00d6zkonak",
        "\u00c7orsan"
    ],
    "wof:name":"Ozkonak",
    "wof:placetype":"locality"
},
  "geometry": {"coordinates":[41.28194000000001,39.24632],"type":"Point"}
}