{
  "type": "Feature",
  "properties": {
    "gn:admin1_code":"21",
    "gn:asciiname":"Kuslukcayiri",
    "gn:country_code":"TR",
    "gn:dem":1119,
    "gn:feature_class":"P",
    "gn:feature_code":"PPL",
    "gn:name":"Ku\u015fluk\u00e7ay\u0131r\u0131",
    "gn:population":0,
    "gn:timezone":"Europe/Istanbul",
    "iso:country":"TR",
    "name:und_x_variant":[
        "Ku\u015fluk\u00e7ay\u0131r\u0131",
        "Karacek"
    ],
    "wof:name":"Kuslukcayiri",
    "wof:placetype":"locality"
},
  "geometry": {"coordinates":[39.56783,37.90384],"type":"Point"}
}