{
  "type": "Feature",
  "properties": {
    "gn:admin1_code":"55.0",
    "gn:asciiname":"Uzgur",
    "gn:country_code":"TR",
    "gn:dem":239,
    "gn:feature_class":"P",
    "gn:feature_code":"PPL",
    "gn:name":"Uzgur",
    "gn:population":0,
    "gn:timezone":"Europe/Istanbul",
    "iso:country":"TR",
    "name:und_x_variant":[
        "K\u00fcpl\u00fcce"
    ],
    "wof:name":"Uzgur",
    "wof:placetype":"locality"
},
  "geometry": {"coordinates":[36.26445,41.27644],"type":"Point"}
}