{
  "type": "Feature",
  "properties": {
    "gn:admin1_code":"81",
    "gn:asciiname":"Yenimurat",
    "gn:country_code":"TR",
    "gn:dem":4,
    "gn:feature_class":"P",
    "gn:feature_code":"PPL",
    "gn:name":"Yenimurat",
    "gn:population":0,
    "gn:timezone":"Europe/Istanbul",
    "iso:country":"TR",
    "name:und_x_variant":[
        "Ganimebuca\u011f\u0131"
    ],
    "wof:name":"Yenimurat",
    "wof:placetype":"locality"
},
  "geometry": {"coordinates":[35.07680999999999,36.78102],"type":"Point"}
}