{
  "type": "Feature",
  "properties": {
    "gn:admin1_code":"60.0",
    "gn:asciiname":"Selamet",
    "gn:country_code":"TR",
    "gn:dem":908,
    "gn:feature_class":"P",
    "gn:feature_code":"PPL",
    "gn:name":"Sel\u00e2met",
    "gn:population":0,
    "gn:timezone":"Europe/Istanbul",
    "iso:country":"TR",
    "name:und_x_variant":[
        "Abdallar",
        "Aptallar",
        "Sel\u00e2met"
    ],
    "wof:name":"Selamet",
    "wof:placetype":"locality"
},
  "geometry": {"coordinates":[35.98987,40.23546],"type":"Point"}
}