{
  "type": "Feature",
  "properties": {
    "gn:admin1_code":"68",
    "gn:asciiname":"Turkhuyuk",
    "gn:country_code":"TR",
    "gn:dem":892,
    "gn:feature_class":"P",
    "gn:feature_code":"PPL",
    "gn:name":"T\u00fcrkh\u00fcy\u00fck",
    "gn:population":0,
    "gn:timezone":"Europe/Istanbul",
    "iso:country":"TR",
    "name:tur_x_preferred":[
        "T\u00fcrkh\u00fcy\u00fck"
    ],
    "name:tur_x_variant":[
        "T\u00fcrkh\u00fcy\u00fc\u011f\u00fc",
        "T\u00fcrkh\u00f6y\u00fck",
        "H\u00f6y\u00fck"
    ],
    "wof:name":"Turkhuyuk",
    "wof:placetype":"locality"
},
  "geometry": {"coordinates":[32.40424,39.54252],"type":"Point"}
}