{
  "type": "Feature",
  "properties": {
    "gn:country":"TR",
    "gn:fcode":"PPL",
    "gn:pop":253,
    "iso:country":"TR",
    "name:unk_x_variant":[
        "Temerzi"
    ],
    "qs:name":"U\u00e7arl\u0131",
    "qs:photos_9r":0,
    "qs:photos_sr":0,
    "qs:pop_sr":"2",
    "wd:wordcount":51,
    "wof:name":"U\u00e7arl\u0131",
    "wof:placetype":"locality",
    "wof:population":253
},
  "geometry": {"coordinates":[41.71028,37.30028],"type":"Point"}
}