{
  "type": "Feature",
  "properties": {
    "gn:country":"TR",
    "gn:fcode":"PPL",
    "gn:population":253,
    "iso:country":"TR",
    "name:azb_x_preferred":[
        "\u0627\u0648\u062c\u0627\u0631\u0644\u06cc"
    ],
    "name:aze_x_preferred":[
        "Ucarl\u0131"
    ],
    "name:fas_x_preferred":[
        "\u06cc\u0648\u06a9\u0631\u0644\u06cc"
    ],
    "name:ita_x_preferred":[
        "Ucarl\u0131"
    ],
    "name:msa_x_preferred":[
        "Ucarl\u0131"
    ],
    "name:und_x_variant":[
        "Temerzi"
    ],
    "name:urd_x_preferred":[
        "\u0627\u06a9\u0627\u0631\u0644\u06cc"
    ],
    "qs:name":"U\u00e7arl\u0131",
    "qs:photos_9r":0,
    "qs:photos_sr":0,
    "qs:pop_sr":"2",
    "wd:wordcount":51,
    "wof:name":"U\u00e7arl\u0131",
    "wof:placetype":"locality",
    "wof:population":253
},
  "geometry": {"coordinates":[41.71028,37.30028],"type":"Point"}
}