{
  "type": "Feature",
  "properties": {
    "gn:admin1_code":"37.0",
    "gn:asciiname":"Demirtas",
    "gn:country_code":"TR",
    "gn:dem":856,
    "gn:feature_class":"P",
    "gn:feature_code":"PPL",
    "gn:name":"Demirta\u015f",
    "gn:population":0,
    "gn:timezone":"Europe/Istanbul",
    "iso:country":"TR",
    "wof:name":"Demirtas",
    "wof:placetype":"locality"
},
  "geometry": {"coordinates":[32.96072,41.62833],"type":"Point"}
}