{
  "type": "Feature",
  "properties": {
    "iso:country":"TR",
    "name:tur_x_preferred":[
        "\u0130zzetpa\u015fa"
    ],
    "wof:name":"Izzetpasa",
    "wof:placetype":"neighbourhood"
},
  "geometry": {"coordinates":[28.98632589938871,41.06967797565414],"type":"Point"}
}