{
  "type": "Feature",
  "properties": {
    "gn:admin1_code":"58",
    "gn:asciiname":"Irmac",
    "gn:country_code":"TR",
    "gn:dem":1693,
    "gn:feature_class":"P",
    "gn:feature_code":"PPL",
    "gn:name":"Irma\u00e7",
    "gn:population":0,
    "gn:timezone":"Europe/Istanbul",
    "iso:country":"TR",
    "wof:name":"Irmac",
    "wof:placetype":"locality"
},
  "geometry": {"coordinates":[37.15046,38.99201],"type":"Point"}
}