{
  "type": "Feature",
  "properties": {
    "gn:admin1_code":"21.0",
    "gn:asciiname":"Kasrisahin",
    "gn:cc2":"TR",
    "gn:country_code":"TR",
    "gn:dem":540,
    "gn:feature_class":"P",
    "gn:feature_code":"PPL",
    "gn:name":"Kasri\u015fahin",
    "gn:population":0,
    "gn:timezone":"Europe/Istanbul",
    "iso:country":"TR",
    "name:tur_x_preferred":[
        "Kasri\u015fahin"
    ],
    "name:und_x_variant":[
        "Kasrishakhin",
        "\u015eahinli"
    ],
    "wof:name":"Kasrisahin",
    "wof:placetype":"locality"
},
  "geometry": {"coordinates":[41.01583,37.78583],"type":"Point"}
}