{
  "type": "Feature",
  "properties": {
    "gn:admin1_code":"37.0",
    "gn:asciiname":"Hasanaga",
    "gn:country_code":"TR",
    "gn:dem":1192,
    "gn:feature_class":"P",
    "gn:feature_code":"PPL",
    "gn:name":"Hasana\u011fa",
    "gn:population":0,
    "gn:timezone":"Europe/Istanbul",
    "iso:country":"TR",
    "wof:name":"Hasanaga",
    "wof:placetype":"locality"
},
  "geometry": {"coordinates":[33.50269,41.54001],"type":"Point"}
}