{
  "type": "Feature",
  "properties": {
    "gn:admin1_code":"15",
    "gn:asciiname":"Hasanpasa",
    "gn:country_code":"TR",
    "gn:dem":1256,
    "gn:feature_class":"P",
    "gn:feature_code":"PPL",
    "gn:name":"Hasanpa\u015fa",
    "gn:population":0,
    "gn:timezone":"Europe/Istanbul",
    "iso:country":"TR",
    "name:ceb_x_preferred":[
        "Hasanpa\u015fa"
    ],
    "name:tur_x_preferred":[
        "Hasanpa\u015fa"
    ],
    "name:vie_x_preferred":[
        "Hasanpa\u015fa"
    ],
    "wof:name":"Hasanpasa",
    "wof:placetype":"locality"
},
  "geometry": {"coordinates":[29.87539,37.2465],"type":"Point"}
}