{
  "type": "Feature",
  "properties": {
    "gn:admin1_code":"58",
    "gn:asciiname":"Karacalar",
    "gn:country_code":"TR",
    "gn:dem":1394,
    "gn:feature_class":"P",
    "gn:feature_code":"PPL",
    "gn:name":"Karacalar",
    "gn:population":0,
    "gn:timezone":"Europe/Istanbul",
    "iso:country":"TR",
    "name:fra_x_preferred":[
        "Karacalar"
    ],
    "name:tur_x_preferred":[
        "Karacalar"
    ],
    "wof:name":"Karacalar",
    "wof:placetype":"locality"
},
  "geometry": {"coordinates":[36.95413,39.45146],"type":"Point"}
}