{
  "type": "Feature",
  "properties": {
    "gn:admin1_code":"90",
    "gn:asciiname":"Saatli",
    "gn:country_code":"TR",
    "gn:dem":630,
    "gn:feature_class":"P",
    "gn:feature_code":"PPL",
    "gn:name":"Saatli",
    "gn:population":0,
    "gn:timezone":"Europe/Istanbul",
    "iso:country":"TR",
    "wof:name":"Saatli",
    "wof:placetype":"locality"
},
  "geometry": {"coordinates":[36.87141,36.7871],"type":"Point"}
}