{
  "type": "Feature",
  "properties": {
    "iso:country":"TR",
    "name:eng_x_preferred":[
        "Catalca"
    ],
    "name:tur_x_preferred":[
        "\u00c7atalca"
    ],
    "wof:name":"Catalca",
    "wof:placetype":"neighbourhood"
},
  "geometry": {"coordinates":[28.456389188355,41.14493315522586],"type":"Point"}
}