{
  "type": "Feature",
  "properties": {
    "gn:admin1_code":"38",
    "gn:asciiname":"Yesilyurt",
    "gn:country_code":"TR",
    "gn:dem":1320,
    "gn:feature_class":"P",
    "gn:feature_code":"PPL",
    "gn:name":"Ye\u015filyurt",
    "gn:population":0,
    "gn:timezone":"Europe/Istanbul",
    "iso:country":"TR",
    "name:tur_x_preferred":[
        "Ye\u015filyurt"
    ],
    "name:tur_x_variant":[
        "Ya\u011fd\u0131burun"
    ],
    "wof:name":"Yesilyurt",
    "wof:placetype":"locality"
},
  "geometry": {"coordinates":[35.63647,38.30014],"type":"Point"}
}