{
  "type": "Feature",
  "properties": {
    "gn:admin1_code":"76",
    "gn:asciiname":"Tomuk",
    "gn:country_code":"TR",
    "gn:dem":1103,
    "gn:feature_class":"P",
    "gn:feature_code":"PPL",
    "gn:name":"Tomuk",
    "gn:population":0,
    "gn:timezone":"Europe/Istanbul",
    "iso:country":"TR",
    "name:tur_x_preferred":[
        "G\u00fcm\u00fc\u015f\u00f6rg\u00fc"
    ],
    "name:und_x_variant":[
        "Temuk",
        "Temok",
        "Tomuk"
    ],
    "wof:name":"Tomuk",
    "wof:placetype":"locality"
},
  "geometry": {"coordinates":[41.39225,38.26659],"type":"Point"}
}