{
  "type": "Feature",
  "properties": {
    "gn:admin1_code":"11",
    "gn:asciiname":"Ortaca",
    "gn:country_code":"TR",
    "gn:dem":1051,
    "gn:feature_class":"P",
    "gn:feature_code":"PPL",
    "gn:name":"Ortaca",
    "gn:population":0,
    "gn:timezone":"Europe/Istanbul",
    "iso:country":"TR",
    "name:tur_x_preferred":[
        "Ortaca"
    ],
    "wof:name":"Ortaca",
    "wof:placetype":"locality"
},
  "geometry": {"coordinates":[30.33361,39.96222],"type":"Point"}
}