{
  "type": "Feature",
  "properties": {
    "gn:admin1_code":"11",
    "gn:asciiname":"Ortaca",
    "gn:country_code":"TR",
    "gn:dem":1051,
    "gn:feature_class":"P",
    "gn:feature_code":"PPL",
    "gn:name":"Ortaca",
    "gn:population":0,
    "gn:timezone":"Europe/Istanbul",
    "iso:country":"TR",
    "name:ara_x_preferred":[
        "\u0623\u0648\u0631\u0637\u0627\u062c\u0627"
    ],
    "name:ceb_x_preferred":[
        "Ortaca"
    ],
    "name:deu_x_preferred":[
        "Ortaca"
    ],
    "name:epo_x_preferred":[
        "Ortaca"
    ],
    "name:fas_x_preferred":[
        "\u0627\u0648\u0631\u062a\u0627\u062c\u0647"
    ],
    "name:fra_x_preferred":[
        "Ortaca"
    ],
    "name:kaz_x_preferred":[
        "\u041e\u0440\u0442\u0430\u0434\u0436\u0430"
    ],
    "name:min_x_preferred":[
        "Ortaca"
    ],
    "name:mrj_x_preferred":[
        "\u041e\u0440\u0442\u0430\u0434\u0436\u0430"
    ],
    "name:msa_x_preferred":[
        "Ortaca"
    ],
    "name:nld_x_preferred":[
        "Ortaca"
    ],
    "name:nno_x_preferred":[
        "Ortaca"
    ],
    "name:nor_x_preferred":[
        "Ortaca"
    ],
    "name:pnb_x_preferred":[
        "\u0636\u0644\u0639 \u0627\u0648\u0631\u062a\u0627\u062c\u0627"
    ],
    "name:rus_x_preferred":[
        "\u041e\u0440\u0442\u0430\u0434\u0436\u0430"
    ],
    "name:swa_x_preferred":[
        "Ortaca"
    ],
    "name:tur_x_preferred":[
        "Ortaca"
    ],
    "name:urd_x_preferred":[
        "\u0627\u0648\u0631\u062a\u0627\u062c\u0627"
    ],
    "name:vie_x_preferred":[
        "Ortaca"
    ],
    "name:zho_x_preferred":[
        "\u5967\u723e\u5854\u8cc8"
    ],
    "wof:name":"Ortaca",
    "wof:placetype":"locality"
},
  "geometry": {"coordinates":[30.33361,39.96222],"type":"Point"}
}