{
  "type": "Feature",
  "properties": {
    "gn:admin1_code":"24",
    "gn:asciiname":"Doganyuva",
    "gn:country_code":"TR",
    "gn:dem":1797,
    "gn:feature_class":"P",
    "gn:feature_code":"PPL",
    "gn:name":"Do\u011fanyuva",
    "gn:population":0,
    "gn:timezone":"Europe/Istanbul",
    "iso:country":"TR",
    "name:und_x_variant":[
        "Komga",
        "Konga",
        "Do\u011fanyuva"
    ],
    "wof:name":"Doganyuva",
    "wof:placetype":"locality"
},
  "geometry": {"coordinates":[39.86712,39.85645],"type":"Point"}
}