{
  "type": "Feature",
  "properties": {
    "gn:admin1_code":"24",
    "gn:asciiname":"Keklikkayasi",
    "gn:country_code":"TR",
    "gn:dem":1329,
    "gn:feature_class":"P",
    "gn:feature_code":"PPL",
    "gn:name":"Keklikkayas\u0131",
    "gn:population":0,
    "gn:timezone":"Europe/Istanbul",
    "iso:country":"TR",
    "name:und_x_variant":[
        "Keklikkayas\u0131",
        "Ha\u015fha\u015f"
    ],
    "wof:name":"Keklikkayasi",
    "wof:placetype":"locality"
},
  "geometry": {"coordinates":[39.44724,39.79011],"type":"Point"}
}