{
  "type": "Feature",
  "properties": {
    "gn:admin1_code":"09",
    "gn:asciiname":"Mestanlar Mahallesi",
    "gn:country_code":"TR",
    "gn:dem":454,
    "gn:feature_class":"P",
    "gn:feature_code":"PPL",
    "gn:name":"Mestanlar Mahallesi",
    "gn:population":0,
    "gn:timezone":"Europe/Istanbul",
    "iso:country":"TR",
    "name:tur_x_preferred":[
        "Mestanlar Mahallesi"
    ],
    "wof:name":"Mestanlar Mahallesi",
    "wof:placetype":"locality"
},
  "geometry": {"coordinates":[28.17673,37.78205],"type":"Point"}
}