{
  "type": "Feature",
  "properties": {
    "gn:admin1_code":"40",
    "gn:asciiname":"Huseyinli",
    "gn:country_code":"TR",
    "gn:dem":1141,
    "gn:feature_class":"P",
    "gn:feature_code":"PPL",
    "gn:name":"H\u00fcseyinli",
    "gn:population":0,
    "gn:timezone":"Europe/Istanbul",
    "iso:country":"TR",
    "name:und_x_variant":[
        "Hasanl\u0131",
        "H\u00fcseyinli"
    ],
    "wof:name":"Huseyinli",
    "wof:placetype":"locality"
},
  "geometry": {"coordinates":[34.31486,39.39015],"type":"Point"}
}