{
  "type": "Feature",
  "properties": {
    "gn:admin1_code":"11.0",
    "gn:asciiname":"Buyuksurmeli",
    "gn:country_code":"TR",
    "gn:dem":703,
    "gn:feature_class":"P",
    "gn:feature_code":"PPL",
    "gn:name":"B\u00fcy\u00fcks\u00fcrmeli",
    "gn:population":0,
    "gn:timezone":"Europe/Istanbul",
    "iso:country":"TR",
    "name:und_x_variant":[
        "K\u00fc\u00e7\u00fcks\u00fcrmeli",
        "S\u00fcrmeli",
        "B\u00fcy\u00fcks\u00fcrmeli"
    ],
    "wof:name":"Buyuksurmeli",
    "wof:placetype":"locality"
},
  "geometry": {"coordinates":[30.38308,40.30664],"type":"Point"}
}