{
  "type": "Feature",
  "properties": {
    "gn:admin1_code":"13",
    "gn:asciiname":"Yolbilen",
    "gn:country_code":"TR",
    "gn:dem":1528,
    "gn:feature_class":"P",
    "gn:feature_code":"PPL",
    "gn:name":"Yolbilen",
    "gn:population":0,
    "gn:timezone":"Europe/Istanbul",
    "iso:country":"TR",
    "name:tur_x_preferred":[
        "Yolbilen"
    ],
    "wof:name":"Yolbilen",
    "wof:placetype":"locality"
},
  "geometry": {"coordinates":[42.48141,38.11855],"type":"Point"}
}