{
  "type": "Feature",
  "properties": {
    "gn:admin1_code":"10",
    "gn:asciiname":"Kirtik",
    "gn:country_code":"TR",
    "gn:dem":415,
    "gn:feature_class":"P",
    "gn:feature_code":"PPL",
    "gn:name":"K\u0131rt\u0131k",
    "gn:population":0,
    "gn:timezone":"Europe/Istanbul",
    "iso:country":"TR",
    "name:und_x_variant":[
        "K\u0131rt\u0131kk\u00f6y",
        "K\u0131rt\u0131k"
    ],
    "wof:name":"Kirtik",
    "wof:placetype":"locality"
},
  "geometry": {"coordinates":[27.03881,39.38648],"type":"Point"}
}