{
  "type": "Feature",
  "properties": {
    "gn:admin1_code":"63.0",
    "gn:asciiname":"Akcakoy",
    "gn:country_code":"TR",
    "gn:dem":414,
    "gn:feature_class":"P",
    "gn:feature_code":"PPL",
    "gn:name":"Ak\u00e7ak\u00f6y",
    "gn:population":0,
    "gn:timezone":"Europe/Istanbul",
    "iso:country":"TR",
    "name:tur_x_preferred":[
        "Ak\u00e7ak\u00f6y"
    ],
    "wof:name":"Akcakoy",
    "wof:placetype":"locality"
},
  "geometry": {"coordinates":[39.35275,36.69613],"type":"Point"}
}