{
  "type": "Feature",
  "properties": {
    "gn:admin1_code":"70.0",
    "gn:asciiname":"Korgan",
    "gn:country_code":"TR",
    "gn:dem":1727,
    "gn:feature_class":"P",
    "gn:feature_code":"PPL",
    "gn:name":"Korgan",
    "gn:population":0,
    "gn:timezone":"Europe/Istanbul",
    "iso:country":"TR",
    "name:tur_x_preferred":[
        "Korgan"
    ],
    "wof:name":"Korgan",
    "wof:placetype":"locality"
},
  "geometry": {"coordinates":[44.4921,37.40206],"type":"Point"}
}