{
  "type": "Feature",
  "properties": {
    "gn:admin1_code":"70.0",
    "gn:asciiname":"Korgan",
    "gn:country_code":"TR",
    "gn:dem":1727,
    "gn:feature_class":"P",
    "gn:feature_code":"PPL",
    "gn:name":"Korgan",
    "gn:population":0,
    "gn:timezone":"Europe/Istanbul",
    "iso:country":"TR",
    "name:azb_x_preferred":[
        "\u06a9\u0648\u0631\u06af\u0627\u0646"
    ],
    "name:ceb_x_preferred":[
        "Korgan \u0130l\u00e7esi"
    ],
    "name:deu_x_preferred":[
        "Korgan"
    ],
    "name:epo_x_preferred":[
        "Korgan"
    ],
    "name:fas_x_preferred":[
        "\u06a9\u0648\u0631\u06af\u0627\u0646"
    ],
    "name:fra_x_preferred":[
        "Korgan"
    ],
    "name:ita_x_preferred":[
        "Korgan"
    ],
    "name:kat_x_preferred":[
        "\u10e5\u10dd\u10e0\u10d2\u10d0\u10dc\u10d8\u10e1 \u10e0\u10d0\u10d8\u10dd\u10dc\u10d8"
    ],
    "name:mrj_x_preferred":[
        "\u041a\u043e\u0440\u0433\u0430\u043d"
    ],
    "name:msa_x_preferred":[
        "Korgan"
    ],
    "name:nno_x_preferred":[
        "Korgan"
    ],
    "name:nor_x_preferred":[
        "Korgan"
    ],
    "name:pnb_x_preferred":[
        "\u0636\u0644\u0639 \u06a9\u0648\u0631\u06af\u0627\u0646"
    ],
    "name:rus_x_preferred":[
        "\u041a\u043e\u0440\u0433\u0430\u043d"
    ],
    "name:swa_x_preferred":[
        "Korgan"
    ],
    "name:tur_x_preferred":[
        "Korgan"
    ],
    "name:urd_x_preferred":[
        "\u06a9\u0648\u0631\u06af\u0627\u0646"
    ],
    "name:vie_x_preferred":[
        "Korgan"
    ],
    "name:zho_x_preferred":[
        "\u79d1\u723e\u7518"
    ],
    "wof:name":"Korgan",
    "wof:placetype":"locality"
},
  "geometry": {"coordinates":[44.4921,37.40206],"type":"Point"}
}