{
  "type": "Feature",
  "properties": {
    "gn:admin1_code":"81.0",
    "gn:asciiname":"Bamballi",
    "gn:country_code":"TR",
    "gn:dem":830,
    "gn:feature_class":"P",
    "gn:feature_code":"PPL",
    "gn:name":"Bamball\u0131",
    "gn:population":0,
    "gn:timezone":"Europe/Istanbul",
    "iso:country":"TR",
    "wof:name":"Bamballi",
    "wof:placetype":"locality"
},
  "geometry": {"coordinates":[35.79373,37.66014000000001],"type":"Point"}
}