{
  "type": "Feature",
  "properties": {
    "gn:admin1_code":"77.0",
    "gn:asciiname":"Orence",
    "gn:country_code":"TR",
    "gn:dem":1770,
    "gn:feature_class":"P",
    "gn:feature_code":"PPL",
    "gn:name":"\u00d6rence",
    "gn:population":0,
    "gn:timezone":"Europe/Istanbul",
    "iso:country":"TR",
    "name:und_x_variant":[
        "\u00d6rence"
    ],
    "wof:name":"Orence",
    "wof:placetype":"locality"
},
  "geometry": {"coordinates":[40.37937,40.11942],"type":"Point"}
}