{
  "type": "Feature",
  "properties": {
    "gn:admin1_code":"66",
    "gn:asciiname":"Ramazanli",
    "gn:country_code":"TR",
    "gn:dem":1183,
    "gn:feature_class":"P",
    "gn:feature_code":"PPL",
    "gn:name":"Ramazanl\u0131",
    "gn:population":0,
    "gn:timezone":"Europe/Istanbul",
    "iso:country":"TR",
    "wof:name":"Ramazanli",
    "wof:placetype":"locality"
},
  "geometry": {"coordinates":[35.60167,39.55306],"type":"Point"}
}