{
  "type": "Feature",
  "properties": {
    "gn:country":"TR",
    "gn:fcode":"PPL",
    "gn:pop":419,
    "iso:country":"TR",
    "name:tur_x_preferred":[
        "Kaplank\u00f6y"
    ],
    "name:tur_x_variant":[
        "Kaplan"
    ],
    "qs:name":"Kaplank\u00f6y",
    "qs:photos_9r":0,
    "qs:photos_sr":0,
    "qs:pop_sr":"2",
    "wof:name":"Kaplank\u00f6y",
    "wof:placetype":"locality",
    "wof:population":419
},
  "geometry": {"coordinates":[38.55917,36.93722],"type":"Point"}
}