{
  "type": "Feature",
  "properties": {
    "gn:admin1_code":"15",
    "gn:asciiname":"Elsazi",
    "gn:country_code":"TR",
    "gn:dem":289,
    "gn:feature_class":"P",
    "gn:feature_code":"PPL",
    "gn:name":"Elsaz\u0131",
    "gn:population":0,
    "gn:timezone":"Europe/Istanbul",
    "iso:country":"TR",
    "wof:name":"Elsazi",
    "wof:placetype":"locality"
},
  "geometry": {"coordinates":[30.81696,37.44553],"type":"Point"}
}