{
  "type": "Feature",
  "properties": {
    "gn:country":"TR",
    "gn:fcode":"PPLX",
    "gn:population":0,
    "iso:country":"TR",
    "name:tur_x_preferred":[
        "Dereboyu"
    ],
    "qs:name":"Dereboyu",
    "qs:name_adm0":"Turkey",
    "qs:name_adm1":"Ankara",
    "qs:photos":1,
    "qs:photos_1k":1,
    "qs:photos_9k":1,
    "qs:photos_9r":1,
    "qs:photos_all":1,
    "qs:photos_sr":1,
    "qs:placetype":"Suburb",
    "qs:pop_sr":"0",
    "wd:wordcount":36,
    "wof:name":"Dereboyu",
    "wof:placetype":"neighbourhood",
    "wof:population":0
},
  "geometry": {"coordinates":[32.89834,39.98788],"type":"Point"}
}