{
  "type": "Feature",
  "properties": {
    "gn:admin1_code":"38",
    "gn:asciiname":"Eskitekke",
    "gn:country_code":"TR",
    "gn:dem":1683,
    "gn:feature_class":"P",
    "gn:feature_code":"PPL",
    "gn:name":"Eskitekke",
    "gn:population":0,
    "gn:timezone":"Europe/Istanbul",
    "iso:country":"TR",
    "wof:name":"Eskitekke",
    "wof:placetype":"locality"
},
  "geometry": {"coordinates":[36.20932,38.7091],"type":"Point"}
}