{
  "type": "Feature",
  "properties": {
    "gn:admin1_code":"14",
    "gn:asciiname":"Hidirseyhler",
    "gn:country_code":"TR",
    "gn:dem":795,
    "gn:feature_class":"P",
    "gn:feature_code":"PPL",
    "gn:name":"H\u0131d\u0131r\u015feyhler",
    "gn:population":0,
    "gn:timezone":"Europe/Istanbul",
    "iso:country":"TR",
    "name:ceb_x_preferred":[
        "H\u0131d\u0131r\u015feyhler"
    ],
    "name:msa_x_preferred":[
        "H\u0131d\u0131r\u015feyhler"
    ],
    "name:tur_x_preferred":[
        "H\u0131d\u0131r\u015feyhler"
    ],
    "name:vie_x_preferred":[
        "H\u0131d\u0131r\u015feyhler"
    ],
    "wof:name":"Hidirseyhler",
    "wof:placetype":"locality"
},
  "geometry": {"coordinates":[31.59621,40.67361],"type":"Point"}
}