{
  "type": "Feature",
  "properties": {
    "gn:admin1_code":"70",
    "gn:asciiname":"Uguracan",
    "gn:country_code":"TR",
    "gn:dem":1776,
    "gn:feature_class":"P",
    "gn:feature_code":"PPL",
    "gn:name":"U\u011fura\u00e7an",
    "gn:population":0,
    "gn:timezone":"Europe/Istanbul",
    "iso:country":"TR",
    "name:und_x_variant":[
        "Betk\u00e2r",
        "U\u011fur\u00e7an",
        "U\u011fura\u00e7an"
    ],
    "wof:name":"Uguracan",
    "wof:placetype":"locality"
},
  "geometry": {"coordinates":[44.58111,37.32167000000001],"type":"Point"}
}