{
  "type": "Feature",
  "properties": {
    "gn:admin1_code":"31.0",
    "gn:asciiname":"Comcom",
    "gn:country_code":"TR",
    "gn:dem":1208,
    "gn:feature_class":"P",
    "gn:feature_code":"PPL",
    "gn:name":"\u00c7om\u00e7om",
    "gn:population":0,
    "gn:timezone":"Europe/Istanbul",
    "iso:country":"TR",
    "name:fra_x_preferred":[
        "ComCom"
    ],
    "name:tur_x_preferred":[
        "\u00c7om\u00e7om"
    ],
    "wof:name":"Comcom",
    "wof:placetype":"locality"
},
  "geometry": {"coordinates":[36.29694,36.60639000000001],"type":"Point"}
}