{
  "type": "Feature",
  "properties": {
    "gn:admin1_code":"62.0",
    "gn:asciiname":"Cataksu",
    "gn:country_code":"TR",
    "gn:dem":974,
    "gn:feature_class":"P",
    "gn:feature_code":"PPL",
    "gn:name":"\u00c7ataksu",
    "gn:population":0,
    "gn:timezone":"Europe/Istanbul",
    "iso:country":"TR",
    "name:und_x_variant":[
        "Abdol\u0131",
        "\u00c7ataksu",
        "Abdolu"
    ],
    "wof:name":"Cataksu",
    "wof:placetype":"locality"
},
  "geometry": {"coordinates":[39.49771,38.77948],"type":"Point"}
}