{
  "type": "Feature",
  "properties": {
    "gn:admin1_code":"77.0",
    "gn:asciiname":"Darica",
    "gn:country_code":"TR",
    "gn:dem":1846,
    "gn:feature_class":"P",
    "gn:feature_code":"PPL",
    "gn:name":"Dar\u0131ca",
    "gn:population":0,
    "gn:timezone":"Europe/Istanbul",
    "iso:country":"TR",
    "name:und_x_variant":[
        "Dar\u0131ca",
        "Yukar\u0131 Danzut"
    ],
    "wof:name":"Darica",
    "wof:placetype":"locality"
},
  "geometry": {"coordinates":[40.52539,40.42993],"type":"Point"}
}