{
  "type": "Feature",
  "properties": {
    "gn:admin1_code":"45",
    "gn:asciiname":"Imceler",
    "gn:country_code":"TR",
    "gn:dem":829,
    "gn:feature_class":"P",
    "gn:feature_code":"PPL",
    "gn:name":"\u0130mceler",
    "gn:population":0,
    "gn:timezone":"Europe/Istanbul",
    "iso:country":"TR",
    "name:tur_x_preferred":[
        "\u0130mceler"
    ],
    "wof:name":"Imceler",
    "wof:placetype":"locality"
},
  "geometry": {"coordinates":[28.87808,38.94902],"type":"Point"}
}