{
  "type": "Feature",
  "properties": {
    "gn:admin1_code":"31",
    "gn:asciiname":"Kupcikan",
    "gn:country_code":"TR",
    "gn:dem":145,
    "gn:feature_class":"P",
    "gn:feature_code":"PPL",
    "gn:name":"K\u00fcp\u00e7\u0131kan",
    "gn:population":0,
    "gn:timezone":"Europe/Istanbul",
    "iso:country":"TR",
    "name:und_x_variant":[
        "K\u00fcp\u00e7\u0131kan"
    ],
    "wof:name":"Kupcikan",
    "wof:placetype":"locality"
},
  "geometry": {"coordinates":[35.84978,36.34716],"type":"Point"}
}