{
  "type": "Feature",
  "properties": {
    "gn:admin1_code":"65",
    "gn:asciiname":"Anzav",
    "gn:country_code":"TR",
    "gn:dem":1960,
    "gn:feature_class":"P",
    "gn:feature_code":"PPL",
    "gn:name":"Anzav",
    "gn:population":0,
    "gn:timezone":"Europe/Istanbul",
    "iso:country":"TR",
    "name:und_x_variant":[
        "Dere\u00fcst\u00fc"
    ],
    "wof:name":"Anzav",
    "wof:placetype":"locality"
},
  "geometry": {"coordinates":[43.47057,38.55602],"type":"Point"}
}