{
  "type": "Feature",
  "properties": {
    "gn:admin1_code":"21",
    "gn:asciiname":"Kendal",
    "gn:country_code":"TR",
    "gn:dem":1053,
    "gn:feature_class":"P",
    "gn:feature_code":"PPL",
    "gn:name":"Kendal",
    "gn:population":0,
    "gn:timezone":"Europe/Istanbul",
    "iso:country":"TR",
    "name:und_x_variant":[
        "Aynhir",
        "Aynehir",
        "Kendal",
        "Ayinhir"
    ],
    "wof:name":"Kendal",
    "wof:placetype":"locality"
},
  "geometry": {"coordinates":[40.47349000000001,38.4334],"type":"Point"}
}