{
  "type": "Feature",
  "properties": {
    "gn:admin1_code":"04",
    "gn:asciiname":"Gunyolu",
    "gn:country_code":"TR",
    "gn:dem":1663,
    "gn:feature_class":"P",
    "gn:feature_code":"PPL",
    "gn:name":"G\u00fcnyolu",
    "gn:population":0,
    "gn:timezone":"Europe/Istanbul",
    "iso:country":"TR",
    "name:und_x_variant":[
        "\u015eemso",
        "G\u00fcnyolu"
    ],
    "wof:name":"Gunyolu",
    "wof:placetype":"locality"
},
  "geometry": {"coordinates":[43.95741,39.5961],"type":"Point"}
}