{
  "type": "Feature",
  "properties": {
    "gn:admin1_code":"07",
    "gn:admin2_code":"7732193",
    "gn:asciiname":"Kumkoy",
    "gn:country_code":"TR",
    "gn:dem":9,
    "gn:feature_class":"P",
    "gn:feature_code":"PPL",
    "gn:name":"Kumk\u00f6y",
    "gn:population":0,
    "gn:timezone":"Europe/Istanbul",
    "iso:country":"TR",
    "wof:name":"Kumkoy",
    "wof:placetype":"locality"
},
  "geometry": {"coordinates":[31.36159,36.80836],"type":"Point"}
}