{
  "type": "Feature",
  "properties": {
    "gn:admin1_code":"71",
    "gn:asciiname":"Degis",
    "gn:country_code":"TR",
    "gn:dem":1348,
    "gn:feature_class":"P",
    "gn:feature_code":"PPL",
    "gn:name":"De\u011fi\u015f",
    "gn:population":0,
    "gn:timezone":"Europe/Istanbul",
    "iso:country":"TR",
    "wof:name":"Degis",
    "wof:placetype":"locality"
},
  "geometry": {"coordinates":[31.94973,37.93223],"type":"Point"}
}