{
  "type": "Feature",
  "properties": {
    "gn:admin1_code":"10",
    "gn:asciiname":"Hasanoren",
    "gn:country_code":"TR",
    "gn:dem":953,
    "gn:feature_class":"P",
    "gn:feature_code":"PPL",
    "gn:name":"Hasan\u00f6ren",
    "gn:population":0,
    "gn:timezone":"Europe/Istanbul",
    "iso:country":"TR",
    "name:tur_x_preferred":[
        "Hasan\u00f6ren"
    ],
    "name:und_x_variant":[
        "\u00d6ren",
        "Hasanviran"
    ],
    "wof:name":"Hasanoren",
    "wof:placetype":"locality"
},
  "geometry": {"coordinates":[28.95,39.36667],"type":"Point"}
}