{
  "type": "Feature",
  "properties": {
    "gn:admin1_code":"49",
    "gn:asciiname":"Karaali",
    "gn:country_code":"TR",
    "gn:dem":1704,
    "gn:feature_class":"P",
    "gn:feature_code":"PPL",
    "gn:name":"Karaali",
    "gn:population":0,
    "gn:timezone":"Europe/Istanbul",
    "iso:country":"TR",
    "name:tur_x_preferred":[
        "Karaali"
    ],
    "wof:name":"Karaali",
    "wof:placetype":"locality"
},
  "geometry": {"coordinates":[42.54758,39.03872],"type":"Point"}
}