{
  "type": "Feature",
  "properties": {
    "gn:admin1_code":"71",
    "gn:asciiname":"Sorkun",
    "gn:country_code":"TR",
    "gn:dem":965,
    "gn:feature_class":"P",
    "gn:feature_code":"PPL",
    "gn:name":"Sorkun",
    "gn:population":0,
    "gn:timezone":"Europe/Istanbul",
    "iso:country":"TR",
    "name:cat_x_preferred":[
        "Sorkun"
    ],
    "name:eus_x_preferred":[
        "Sorkun"
    ],
    "name:spa_x_preferred":[
        "Sorkun"
    ],
    "wof:name":"Sorkun",
    "wof:placetype":"locality"
},
  "geometry": {"coordinates":[31.41201,38.41882],"type":"Point"}
}