{
  "type": "Feature",
  "properties": {
    "gn:admin1_code":"13",
    "gn:asciiname":"Ballica",
    "gn:country_code":"TR",
    "gn:dem":1733,
    "gn:feature_class":"P",
    "gn:feature_code":"PPL",
    "gn:name":"Ball\u0131ca",
    "gn:population":0,
    "gn:timezone":"Europe/Istanbul",
    "iso:country":"TR",
    "name:tur_x_preferred":[
        "Ball\u0131ca"
    ],
    "name:und_x_variant":[
        "Oranis"
    ],
    "wof:name":"Ballica",
    "wof:placetype":"locality"
},
  "geometry": {"coordinates":[42.53553,38.17796],"type":"Point"}
}