{
  "type": "Feature",
  "properties": {
    "gn:admin1_code":"61.0",
    "gn:asciiname":"Helvaci",
    "gn:country_code":"TR",
    "gn:dem":582,
    "gn:feature_class":"P",
    "gn:feature_code":"PPL",
    "gn:name":"Helvac\u0131",
    "gn:population":0,
    "gn:timezone":"Europe/Istanbul",
    "iso:country":"TR",
    "name:tur_x_preferred":[
        "Helvac\u0131"
    ],
    "wof:name":"Helvaci",
    "wof:placetype":"locality"
},
  "geometry": {"coordinates":[39.5425,40.99212],"type":"Point"}
}