{
  "type": "Feature",
  "properties": {
    "gn:admin1_code":"65",
    "gn:asciiname":"Asagi Akcagedik",
    "gn:country_code":"TR",
    "gn:dem":1941,
    "gn:feature_class":"P",
    "gn:feature_code":"PPL",
    "gn:name":"A\u015fa\u011f\u0131 Ak\u00e7agedik",
    "gn:population":0,
    "gn:timezone":"Europe/Istanbul",
    "iso:country":"TR",
    "name:tur_x_preferred":[
        "A\u015fa\u011f\u0131 Ak\u00e7agedik"
    ],
    "name:und_x_variant":[
        "A\u015fag\u0131 Hi\u015firo",
        "A\u015fa\u011f\u0131ak\u00e7agedik"
    ],
    "wof:name":"Asagi Akcagedik",
    "wof:placetype":"locality"
},
  "geometry": {"coordinates":[43.11600000000001,39.14515],"type":"Point"}
}