{
  "type": "Feature",
  "properties": {
    "gn:admin1_code":"53.0",
    "gn:asciiname":"Arili",
    "gn:country_code":"TR",
    "gn:dem":158,
    "gn:feature_class":"P",
    "gn:feature_code":"PPL",
    "gn:name":"Ar\u0131l\u0131",
    "gn:population":0,
    "gn:timezone":"Europe/Istanbul",
    "iso:country":"TR",
    "name:eng_x_preferred":[
        "Ar\u0131l\u0131"
    ],
    "name:rus_x_preferred":[
        "\u041f\u0438\u0441\u043a\u0430\u043b\u0430\u0441\u044e\u0444\u043b\u044f"
    ],
    "name:und_x_variant":[
        "Piskalas\u00fcfla",
        "Pishalas\u00fcfla"
    ],
    "wof:name":"Arili",
    "wof:placetype":"locality"
},
  "geometry": {"coordinates":[41.16899,41.20945],"type":"Point"}
}