{
  "type": "Feature",
  "properties": {
    "gn:admin1_code":"48",
    "gn:asciiname":"Kizilcayikik",
    "gn:country_code":"TR",
    "gn:dem":40,
    "gn:feature_class":"P",
    "gn:feature_code":"PPL",
    "gn:name":"K\u0131z\u0131lcay\u0131k\u0131k",
    "gn:population":0,
    "gn:timezone":"Europe/Istanbul",
    "iso:country":"TR",
    "name:tur_x_preferred":[
        "K\u0131z\u0131lcay\u0131k\u0131k"
    ],
    "wof:name":"Kizilcayikik",
    "wof:placetype":"locality"
},
  "geometry": {"coordinates":[27.78766,37.36208],"type":"Point"}
}