{
  "type": "Feature",
  "properties": {
    "gn:admin1_code":"10",
    "gn:asciiname":"Iclaliye",
    "gn:country_code":"TR",
    "gn:dem":548,
    "gn:feature_class":"P",
    "gn:feature_code":"PPL",
    "gn:name":"\u0130claliye",
    "gn:population":0,
    "gn:timezone":"Europe/Istanbul",
    "iso:country":"TR",
    "name:tur_x_preferred":[
        "\u0130claliye"
    ],
    "name:und_x_variant":[
        "\u00c7obancal"
    ],
    "wof:name":"Iclaliye",
    "wof:placetype":"locality"
},
  "geometry": {"coordinates":[28.06716,39.97721],"type":"Point"}
}