{
  "type": "Feature",
  "properties": {
    "gn:admin1_code":"89",
    "gn:asciiname":"Balcioglu",
    "gn:country_code":"TR",
    "gn:dem":403,
    "gn:feature_class":"P",
    "gn:feature_code":"PPL",
    "gn:name":"Balc\u0131o\u011flu",
    "gn:population":0,
    "gn:timezone":"Europe/Istanbul",
    "iso:country":"TR",
    "wof:name":"Balcioglu",
    "wof:placetype":"locality"
},
  "geometry": {"coordinates":[32.27238,41.24326],"type":"Point"}
}