{
  "type": "Feature",
  "properties": {
    "gn:admin1_code":"10.0",
    "gn:asciiname":"Armutlu",
    "gn:country_code":"TR",
    "gn:dem":68,
    "gn:feature_class":"P",
    "gn:feature_code":"PPL",
    "gn:name":"Armutlu",
    "gn:population":0,
    "gn:timezone":"Europe/Istanbul",
    "iso:country":"TR",
    "name:und_x_variant":[
        "S\u0131z\u0131k\u00f6y",
        "Armutlu"
    ],
    "wof:name":"Armutlu",
    "wof:placetype":"locality"
},
  "geometry": {"coordinates":[27.52833,40.19033],"type":"Point"}
}