{
  "type": "Feature",
  "properties": {
    "gn:admin1_code":"58",
    "gn:asciiname":"Islim",
    "gn:country_code":"TR",
    "gn:dem":1483,
    "gn:feature_class":"P",
    "gn:feature_code":"PPL",
    "gn:name":"\u0130slim",
    "gn:population":0,
    "gn:timezone":"Europe/Istanbul",
    "iso:country":"TR",
    "name:und_x_variant":[
        "\u0130slim",
        "\u0130slimk\u00f6y"
    ],
    "wof:name":"Islim",
    "wof:placetype":"locality"
},
  "geometry": {"coordinates":[36.66543,40.0021],"type":"Point"}
}