{
  "type": "Feature",
  "properties": {
    "gn:admin1_code":"5.0",
    "gn:asciiname":"Yukari Yapilar",
    "gn:country_code":"TR",
    "gn:dem":526,
    "gn:feature_class":"P",
    "gn:feature_code":"PPL",
    "gn:name":"Yukar\u0131 Yap\u0131lar",
    "gn:population":0,
    "gn:timezone":"Europe/Istanbul",
    "iso:country":"TR",
    "wof:name":"Yukari Yapilar",
    "wof:placetype":"locality"
},
  "geometry": {"coordinates":[35.56001,40.45051],"type":"Point"}
}