{
  "type": "Feature",
  "properties": {
    "gn:admin1_code":"58.0",
    "gn:asciiname":"Alahaci",
    "gn:country_code":"TR",
    "gn:dem":1474,
    "gn:feature_class":"P",
    "gn:feature_code":"PPL",
    "gn:name":"Alahac\u0131",
    "gn:population":0,
    "gn:timezone":"Europe/Istanbul",
    "iso:country":"TR",
    "wof:name":"Alahaci",
    "wof:placetype":"locality"
},
  "geometry": {"coordinates":[37.05917,40.01515],"type":"Point"}
}