{
  "type": "Feature",
  "properties": {
    "gn:admin1_code":"62",
    "gn:asciiname":"Hemzikusagi",
    "gn:country_code":"TR",
    "gn:dem":2036,
    "gn:feature_class":"P",
    "gn:feature_code":"PPL",
    "gn:name":"Hemziku\u015fa\u011f\u0131",
    "gn:population":0,
    "gn:timezone":"Europe/Istanbul",
    "iso:country":"TR",
    "wof:name":"Hemzikusagi",
    "wof:placetype":"locality"
},
  "geometry": {"coordinates":[39.36667,39.45],"type":"Point"}
}