{
  "type": "Feature",
  "properties": {
    "gn:admin1_code":"69.0",
    "gn:asciiname":"Gultepe",
    "gn:country_code":"TR",
    "gn:dem":1828,
    "gn:feature_class":"P",
    "gn:feature_code":"PPL",
    "gn:name":"G\u00fcltepe",
    "gn:population":0,
    "gn:timezone":"Europe/Istanbul",
    "iso:country":"TR",
    "name:und_x_variant":[
        "\u0130\u011fdi\u015f",
        "G\u00fcltepe"
    ],
    "wof:name":"Gultepe",
    "wof:placetype":"locality"
},
  "geometry": {"coordinates":[39.28212,40.04722],"type":"Point"}
}