{
  "type": "Feature",
  "properties": {
    "gn:admin1_code":"13",
    "gn:asciiname":"Cevrekoy",
    "gn:country_code":"TR",
    "gn:dem":1782,
    "gn:feature_class":"P",
    "gn:feature_code":"PPL",
    "gn:name":"\u00c7evrek\u00f6y",
    "gn:population":0,
    "gn:timezone":"Europe/Istanbul",
    "iso:country":"TR",
    "name:tur_x_preferred":[
        "\u00c7evrek\u00f6y"
    ],
    "name:und_x_variant":[
        "\u0130zk\u00f6y",
        "\u0130z",
        "\u00c7evre"
    ],
    "wof:name":"Cevrekoy",
    "wof:placetype":"locality"
},
  "geometry": {"coordinates":[42.35465,38.45567],"type":"Point"}
}