{
  "type": "Feature",
  "properties": {
    "gn:admin1_code":"20",
    "gn:asciiname":"Catmali",
    "gn:country_code":"TR",
    "gn:dem":795,
    "gn:feature_class":"P",
    "gn:feature_code":"PPL",
    "gn:name":"\u00c7atmal\u0131",
    "gn:population":0,
    "gn:timezone":"Europe/Istanbul",
    "iso:country":"TR",
    "name:tur_x_preferred":[
        "\u00c7atmal\u0131"
    ],
    "wof:name":"Catmali",
    "wof:placetype":"locality"
},
  "geometry": {"coordinates":[28.78618,37.33429],"type":"Point"}
}