{
  "type": "Feature",
  "properties": {
    "gn:admin1_code":"65",
    "gn:asciiname":"Orenkale",
    "gn:country_code":"TR",
    "gn:dem":2222,
    "gn:feature_class":"P",
    "gn:feature_code":"PPL",
    "gn:name":"\u00d6renkale",
    "gn:population":0,
    "gn:timezone":"Europe/Istanbul",
    "iso:country":"TR",
    "name:und_x_variant":[
        "Kale Harabesi Pizan",
        "Piran",
        "Pizan",
        "\u00d6renkale"
    ],
    "wof:name":"Orenkale",
    "wof:placetype":"locality"
},
  "geometry": {"coordinates":[43.9513,37.94892],"type":"Point"}
}