{
  "type": "Feature",
  "properties": {
    "gn:admin1_code":"71",
    "gn:asciiname":"Seyhomer",
    "gn:country_code":"TR",
    "gn:dem":1319,
    "gn:feature_class":"P",
    "gn:feature_code":"PPL",
    "gn:name":"\u015eeyh\u00f6mer",
    "gn:population":0,
    "gn:timezone":"Europe/Istanbul",
    "iso:country":"TR",
    "name:und_x_variant":[
        "\u015eeyh\u00f6merli",
        "\u015eeyh\u00f6mer"
    ],
    "wof:name":"Seyhomer",
    "wof:placetype":"locality"
},
  "geometry": {"coordinates":[34.33193,37.5805],"type":"Point"}
}