{
  "type": "Feature",
  "properties": {
    "gn:admin1_code":"14.0",
    "gn:asciiname":"Karaseyhler",
    "gn:country_code":"TR",
    "gn:dem":988,
    "gn:feature_class":"P",
    "gn:feature_code":"PPL",
    "gn:name":"Kara\u015feyhler",
    "gn:population":0,
    "gn:timezone":"Europe/Istanbul",
    "iso:country":"TR",
    "name:und_x_variant":[
        "Kara\u015f\u0131hlar",
        "Kara\u015feyhler"
    ],
    "wof:name":"Karaseyhler",
    "wof:placetype":"locality"
},
  "geometry": {"coordinates":[32.27665,40.9364],"type":"Point"}
}