{
  "type": "Feature",
  "properties": {
    "gn:admin1_code":"35",
    "gn:asciiname":"Eski Orhanli",
    "gn:country_code":"TR",
    "gn:dem":305,
    "gn:feature_class":"P",
    "gn:feature_code":"PPL",
    "gn:name":"Eski Orhanl\u0131",
    "gn:population":0,
    "gn:timezone":"Europe/Istanbul",
    "iso:country":"TR",
    "name:tur_x_preferred":[
        "Eski Orhanl\u0131"
    ],
    "wof:name":"Eski Orhanli",
    "wof:placetype":"locality"
},
  "geometry": {"coordinates":[26.96733,38.19866],"type":"Point"}
}