{
  "type": "Feature",
  "properties": {
    "gn:admin1_code":"66",
    "gn:asciiname":"Kurtini",
    "gn:country_code":"TR",
    "gn:dem":1371,
    "gn:feature_class":"P",
    "gn:feature_code":"PPL",
    "gn:name":"Kurtini",
    "gn:population":0,
    "gn:timezone":"Europe/Istanbul",
    "iso:country":"TR",
    "name:tur_x_preferred":[
        "Kurtini"
    ],
    "wof:name":"Kurtini",
    "wof:placetype":"locality"
},
  "geometry": {"coordinates":[35.96588,39.74136],"type":"Point"}
}