{
  "type": "Feature",
  "properties": {
    "gn:admin1_code":"86.0",
    "gn:asciiname":"Hunemis",
    "gn:country_code":"TR",
    "gn:dem":1671,
    "gn:feature_class":"P",
    "gn:feature_code":"PPL",
    "gn:name":"Hunemis",
    "gn:population":0,
    "gn:timezone":"Europe/Istanbul",
    "iso:country":"TR",
    "name:und_x_variant":[
        "S\u00f6\u011f\u00fctl\u00fckaya"
    ],
    "wof:name":"Hunemis",
    "wof:placetype":"locality"
},
  "geometry": {"coordinates":[42.6893,41.47513],"type":"Point"}
}