{
  "type": "Feature",
  "properties": {
    "gn:admin1_code":"76.0",
    "gn:asciiname":"Shirsh",
    "gn:country_code":"TR",
    "gn:dem":772,
    "gn:feature_class":"P",
    "gn:feature_code":"PPL",
    "gn:name":"Shirsh",
    "gn:population":0,
    "gn:timezone":"Europe/Istanbul",
    "iso:country":"TR",
    "name:tur_x_preferred":[
        "\u015eir\u015f"
    ],
    "wof:name":"Shirsh",
    "wof:placetype":"locality"
},
  "geometry": {"coordinates":[41.29389000000001,37.60611],"type":"Point"}
}