{
  "type": "Feature",
  "properties": {
    "gn:admin1_code":"07",
    "gn:asciiname":"Ishakli",
    "gn:country_code":"TR",
    "gn:dem":75,
    "gn:feature_class":"P",
    "gn:feature_code":"PPL",
    "gn:name":"\u0130shakl\u0131",
    "gn:population":0,
    "gn:timezone":"Europe/Istanbul",
    "iso:country":"TR",
    "wof:name":"Ishakli",
    "wof:placetype":"locality"
},
  "geometry": {"coordinates":[32.16234,36.4329],"type":"Point"}
}