{
  "type": "Feature",
  "properties": {
    "gn:admin1_code":"13.0",
    "gn:asciiname":"Kucukbahce",
    "gn:country_code":"TR",
    "gn:dem":1881,
    "gn:feature_class":"P",
    "gn:feature_code":"PPL",
    "gn:name":"K\u00fc\u00e7\u00fckbah\u00e7e",
    "gn:population":0,
    "gn:timezone":"Europe/Istanbul",
    "iso:country":"TR",
    "name:tur_x_preferred":[
        "K\u00fc\u00e7\u00fckbah\u00e7e"
    ],
    "wof:name":"Kucukbahce",
    "wof:placetype":"locality"
},
  "geometry": {"coordinates":[42.16025,38.78833],"type":"Point"}
}