{
  "type": "Feature",
  "properties": {
    "gn:admin1_code":"14.0",
    "gn:asciiname":"Karapazar",
    "gn:country_code":"TR",
    "gn:dem":1372,
    "gn:feature_class":"P",
    "gn:feature_code":"PPL",
    "gn:name":"Karapazar",
    "gn:population":0,
    "gn:timezone":"Europe/Istanbul",
    "iso:country":"TR",
    "wof:name":"Karapazar",
    "wof:placetype":"locality"
},
  "geometry": {"coordinates":[32.2195,40.58835],"type":"Point"}
}