{
  "type": "Feature",
  "properties": {
    "gn:admin1_code":"57.0",
    "gn:asciiname":"Bayramoglu",
    "gn:country_code":"TR",
    "gn:dem":384,
    "gn:feature_class":"P",
    "gn:feature_code":"PPL",
    "gn:name":"Bayramo\u011flu",
    "gn:population":0,
    "gn:timezone":"Europe/Istanbul",
    "iso:country":"TR",
    "wof:name":"Bayramoglu",
    "wof:placetype":"locality"
},
  "geometry": {"coordinates":[34.28333,41.88333],"type":"Point"}
}