{
  "type": "Feature",
  "properties": {
    "gn:admin1_code":"72",
    "gn:asciiname":"Yaylakoy",
    "gn:country_code":"TR",
    "gn:dem":761,
    "gn:feature_class":"P",
    "gn:feature_code":"PPL",
    "gn:name":"Yaylak\u00f6y",
    "gn:population":0,
    "gn:timezone":"Europe/Istanbul",
    "iso:country":"TR",
    "name:rus_x_preferred":[
        "Kharabeg\u00ebza"
    ],
    "name:und_x_variant":[
        "Harabeg\u00f6za",
        "Yaylak\u00f6y"
    ],
    "wof:name":"Yaylakoy",
    "wof:placetype":"locality"
},
  "geometry": {"coordinates":[41.78699,37.21463],"type":"Point"}
}