{
  "type": "Feature",
  "properties": {
    "gn:admin1_code":"63",
    "gn:asciiname":"Taslidere",
    "gn:country_code":"TR",
    "gn:dem":655,
    "gn:feature_class":"P",
    "gn:feature_code":"PPL",
    "gn:name":"Ta\u015fl\u0131dere",
    "gn:population":0,
    "gn:timezone":"Europe/Istanbul",
    "iso:country":"TR",
    "name:tur_x_preferred":[
        "Ta\u015fl\u0131dere"
    ],
    "name:und_x_variant":[
        "Zorava",
        "Zorova",
        "Biris"
    ],
    "wof:name":"Taslidere",
    "wof:placetype":"locality"
},
  "geometry": {"coordinates":[38.54939,37.3098],"type":"Point"}
}