{
  "type": "Feature",
  "properties": {
    "gn:admin1_code":"62",
    "gn:asciiname":"Kapibasi",
    "gn:country_code":"TR",
    "gn:dem":1662,
    "gn:feature_class":"P",
    "gn:feature_code":"PPL",
    "gn:name":"Kap\u0131ba\u015f\u0131",
    "gn:population":0,
    "gn:timezone":"Europe/Istanbul",
    "iso:country":"TR",
    "name:tur_x_preferred":[
        "Kap\u0131ba\u015f\u0131"
    ],
    "name:und_x_variant":[
        "Kapba\u015f\u0131"
    ],
    "wof:name":"Kapibasi",
    "wof:placetype":"locality"
},
  "geometry": {"coordinates":[39.80481,39.18296],"type":"Point"}
}