{
  "type": "Feature",
  "properties": {
    "gn:admin1_code":"23",
    "gn:asciiname":"Hal",
    "gn:country_code":"TR",
    "gn:dem":1229,
    "gn:feature_class":"P",
    "gn:feature_code":"PPL",
    "gn:name":"Hal",
    "gn:population":0,
    "gn:timezone":"Europe/Istanbul",
    "iso:country":"TR",
    "name:und_x_variant":[
        "Yeni\u00e7ubuk"
    ],
    "wof:name":"Hal",
    "wof:placetype":"locality"
},
  "geometry": {"coordinates":[38.91989,38.77246],"type":"Point"}
}