{
  "type": "Feature",
  "properties": {
    "gn:admin1_code":"83.0",
    "gn:asciiname":"Karaburc",
    "gn:country_code":"TR",
    "gn:dem":670,
    "gn:feature_class":"P",
    "gn:feature_code":"PPL",
    "gn:name":"Karabur\u00e7",
    "gn:population":0,
    "gn:timezone":"Europe/Istanbul",
    "iso:country":"TR",
    "name:und_x_variant":[
        "Karabur\u00e7",
        "Karabur\u00e7lu"
    ],
    "wof:name":"Karaburc",
    "wof:placetype":"locality"
},
  "geometry": {"coordinates":[37.71509,37.22662],"type":"Point"}
}