{
  "type": "Feature",
  "properties": {
    "gn:admin1_code":"33",
    "gn:asciiname":"Balkiri",
    "gn:cc2":"TR",
    "gn:country_code":"TR",
    "gn:dem":941,
    "gn:feature_class":"P",
    "gn:feature_code":"PPL",
    "gn:name":"Balk\u0131r\u0131",
    "gn:population":0,
    "gn:timezone":"Europe/Istanbul",
    "iso:country":"TR",
    "name:und_x_variant":[
        "Cire",
        "Cire K\u00f6y\u00fc",
        "Balk\u0131r\u0131"
    ],
    "wof:name":"Balkiri",
    "wof:placetype":"locality"
},
  "geometry": {"coordinates":[30.85806,37.79333],"type":"Point"}
}