{
  "type": "Feature",
  "properties": {
    "gn:admin1_code":"82.0",
    "gn:asciiname":"Asagi Colkesen",
    "gn:country_code":"TR",
    "gn:dem":607,
    "gn:feature_class":"P",
    "gn:feature_code":"PPL",
    "gn:name":"A\u015fa\u011f\u0131 \u00c7\u00f6lkesen",
    "gn:population":0,
    "gn:timezone":"Europe/Istanbul",
    "iso:country":"TR",
    "wof:name":"Asagi Colkesen",
    "wof:placetype":"locality"
},
  "geometry": {"coordinates":[33.76644,40.46153],"type":"Point"}
}