{
  "type": "Feature",
  "properties": {
    "gn:admin1_code":"93",
    "gn:asciiname":"Kasbasi",
    "gn:country_code":"TR",
    "gn:dem":332,
    "gn:feature_class":"P",
    "gn:feature_code":"PPL",
    "gn:name":"Kasba\u015f\u0131",
    "gn:population":0,
    "gn:timezone":"Europe/Istanbul",
    "iso:country":"TR",
    "wof:name":"Kasbasi",
    "wof:placetype":"locality"
},
  "geometry": {"coordinates":[30.91296,40.91417],"type":"Point"}
}