{
  "type": "Feature",
  "properties": {
    "gn:admin1_code":"93",
    "gn:asciiname":"Varali",
    "gn:country_code":"TR",
    "gn:dem":659,
    "gn:feature_class":"P",
    "gn:feature_code":"PPL",
    "gn:name":"Varali",
    "gn:population":0,
    "gn:timezone":"Europe/Istanbul",
    "iso:country":"TR",
    "name:mal_x_preferred":[
        "\u0d35\u0d30\u0d3e\u0d33\u0d3f"
    ],
    "wof:name":"Varali",
    "wof:placetype":"locality"
},
  "geometry": {"coordinates":[31.26127,40.96643],"type":"Point"}
}