{
  "type": "Feature",
  "properties": {
    "gn:admin1_code":"41",
    "gn:asciiname":"Gebesler",
    "gn:country_code":"TR",
    "gn:dem":153,
    "gn:feature_class":"P",
    "gn:feature_code":"PPL",
    "gn:name":"Gebe\u015fler",
    "gn:population":0,
    "gn:timezone":"Europe/Istanbul",
    "iso:country":"TR",
    "name:tur_x_preferred":[
        "Gebe\u015fler"
    ],
    "wof:name":"Gebesler",
    "wof:placetype":"locality"
},
  "geometry": {"coordinates":[29.99806,41.0076],"type":"Point"}
}