{
  "type": "Feature",
  "properties": {
    "gn:admin1_code":"58",
    "gn:asciiname":"Bahtiyar",
    "gn:country_code":"TR",
    "gn:dem":1437,
    "gn:feature_class":"P",
    "gn:feature_code":"PPL",
    "gn:name":"Bahtiyar",
    "gn:population":0,
    "gn:timezone":"Europe/Istanbul",
    "iso:country":"TR",
    "name:tur_x_preferred":[
        "Bahtiyar"
    ],
    "name:tur_x_variant":[
        "Ya\u011fmuralan"
    ],
    "wof:name":"Bahtiyar",
    "wof:placetype":"locality"
},
  "geometry": {"coordinates":[38.24501,39.73799],"type":"Point"}
}