{
  "type": "Feature",
  "properties": {
    "gn:admin1_code":"86.0",
    "gn:asciiname":"Toptas",
    "gn:country_code":"TR",
    "gn:dem":2320,
    "gn:feature_class":"P",
    "gn:feature_code":"PPL",
    "gn:name":"Topta\u015f",
    "gn:population":0,
    "gn:timezone":"Europe/Istanbul",
    "iso:country":"TR",
    "name:eng_x_preferred":[
        "Topta\u015f"
    ],
    "name:rus_x_preferred":[
        "\u0422\u043e\u043f\u0442\u0430\u0448"
    ],
    "wof:name":"Toptas",
    "wof:placetype":"locality"
},
  "geometry": {"coordinates":[42.71619000000001,40.72184],"type":"Point"}
}