{
  "type": "Feature",
  "properties": {
    "gn:admin1_code":"03",
    "gn:asciiname":"Aydinyaka",
    "gn:cc2":"TR",
    "gn:country_code":"TR",
    "gn:dem":865,
    "gn:feature_class":"P",
    "gn:feature_code":"PPL",
    "gn:name":"Ayd\u0131nyaka",
    "gn:population":0,
    "gn:timezone":"Europe/Istanbul",
    "iso:country":"TR",
    "name:und_x_variant":[
        "Sururiye",
        "Tilkisiyan",
        "Tilkisyen",
        "Tilkisiyen",
        "Ayd\u0131nyaka"
    ],
    "wof:name":"Aydinyaka",
    "wof:placetype":"locality"
},
  "geometry": {"coordinates":[31.27972,39.21556],"type":"Point"}
}