{
  "type": "Feature",
  "properties": {
    "gn:admin1_code":"37.0",
    "gn:asciiname":"Zarpana",
    "gn:country_code":"TR",
    "gn:dem":6,
    "gn:feature_class":"P",
    "gn:feature_code":"PPL",
    "gn:name":"Zarpana",
    "gn:population":0,
    "gn:timezone":"Europe/Istanbul",
    "iso:country":"TR",
    "name:und_x_variant":[
        "A\u015fa\u011f\u0131 Zarbana",
        "Zarpana",
        "A\u015fa\u011f\u0131 Arbana",
        "\u00d6zl\u00fcce"
    ],
    "wof:name":"Zarpana",
    "wof:placetype":"locality"
},
  "geometry": {"coordinates":[33.6034,41.9843],"type":"Point"}
}