{
  "type": "Feature",
  "properties": {
    "gn:admin1_code":"5.0",
    "gn:asciiname":"Karamuk",
    "gn:country_code":"TR",
    "gn:dem":938,
    "gn:feature_class":"P",
    "gn:feature_code":"PPL",
    "gn:name":"Karamuk",
    "gn:population":0,
    "gn:timezone":"Europe/Istanbul",
    "iso:country":"TR",
    "wof:name":"Karamuk",
    "wof:placetype":"locality"
},
  "geometry": {"coordinates":[36.13353,40.86722],"type":"Point"}
}