{
  "type": "Feature",
  "properties": {
    "gn:admin1_code":"80.0",
    "gn:asciiname":"Yokus",
    "gn:country_code":"TR",
    "gn:dem":801,
    "gn:feature_class":"P",
    "gn:feature_code":"PPL",
    "gn:name":"Yoku\u015f",
    "gn:population":0,
    "gn:timezone":"Europe/Istanbul",
    "iso:country":"TR",
    "name:tur_x_preferred":[
        "Yoku\u015f"
    ],
    "name:und_x_variant":[
        "Kandalin"
    ],
    "wof:name":"Yokus",
    "wof:placetype":"locality"
},
  "geometry": {"coordinates":[41.61469,37.39658],"type":"Point"}
}