{
  "type": "Feature",
  "properties": {
    "gn:admin1_code":"03",
    "gn:asciiname":"Kutlu",
    "gn:country_code":"TR",
    "gn:dem":1225,
    "gn:feature_class":"P",
    "gn:feature_code":"PPL",
    "gn:name":"Kutlu",
    "gn:population":0,
    "gn:timezone":"Europe/Istanbul",
    "iso:country":"TR",
    "name:tur_x_preferred":[
        "Kutlu"
    ],
    "wof:name":"Kutlu",
    "wof:placetype":"locality"
},
  "geometry": {"coordinates":[31.07076,38.83416],"type":"Point"}
}