{
  "type": "Feature",
  "properties": {
    "gn:admin1_code":"24",
    "gn:asciiname":"Caykent",
    "gn:country_code":"TR",
    "gn:dem":1454,
    "gn:feature_class":"P",
    "gn:feature_code":"PPL",
    "gn:name":"\u00c7aykent",
    "gn:population":0,
    "gn:timezone":"Europe/Istanbul",
    "iso:country":"TR",
    "name:tur_x_preferred":[
        "\u00c7aykent"
    ],
    "wof:name":"Caykent",
    "wof:placetype":"locality"
},
  "geometry": {"coordinates":[40.16048,39.8093],"type":"Point"}
}