{
  "type": "Feature",
  "properties": {
    "gn:admin1_code":"28.0",
    "gn:asciiname":"Yusufeli",
    "gn:country_code":"TR",
    "gn:dem":1374,
    "gn:feature_class":"P",
    "gn:feature_code":"PPL",
    "gn:name":"Yusufeli",
    "gn:population":0,
    "gn:timezone":"Europe/Istanbul",
    "iso:country":"TR",
    "name:ceb_x_preferred":[
        "Yusufeli"
    ],
    "name:deu_x_preferred":[
        "Yusufeli"
    ],
    "name:diq_x_preferred":[
        "Yusufeli"
    ],
    "name:epo_x_preferred":[
        "Yusufeli"
    ],
    "name:fra_x_preferred":[
        "Yusufeli"
    ],
    "name:hye_x_preferred":[
        "\u0532\u0565\u0580\u0564\u0561\u0563\u0580\u0561\u056f"
    ],
    "name:kat_x_preferred":[
        "\u10d8\u10e3\u10e1\u10e3\u10e4\u10d4\u10da\u10d8"
    ],
    "name:mrj_x_preferred":[
        "\u042e\u0441\u0443\u0444\u0435\u043b\u0438"
    ],
    "name:msa_x_preferred":[
        "Yusufeli"
    ],
    "name:nld_x_preferred":[
        "Yusufeli"
    ],
    "name:nor_x_preferred":[
        "Yusufeli"
    ],
    "name:pol_x_preferred":[
        "Yusufeli"
    ],
    "name:swa_x_preferred":[
        "Yusufeli"
    ],
    "name:tur_x_preferred":[
        "Yusufeli"
    ],
    "name:urd_x_preferred":[
        "\u06cc\u0648\u0633\u0641\u06cc\u0644\u06cc"
    ],
    "name:vie_x_preferred":[
        "Yusufeli"
    ],
    "name:xmf_x_preferred":[
        "\u10d8\u10e3\u10e1\u10e3\u10e4\u10d4\u10da\u10d8"
    ],
    "wof:name":"Yusufeli",
    "wof:placetype":"locality"
},
  "geometry": {"coordinates":[38.66439,40.12302],"type":"Point"}
}