{
  "type": "Feature",
  "properties": {
    "gn:admin1_code":"81",
    "gn:asciiname":"Derebasi",
    "gn:country_code":"TR",
    "gn:dem":601,
    "gn:feature_class":"P",
    "gn:feature_code":"PPL",
    "gn:name":"Dereba\u015f\u0131",
    "gn:population":0,
    "gn:timezone":"Europe/Istanbul",
    "iso:country":"TR",
    "wof:name":"Derebasi",
    "wof:placetype":"locality"
},
  "geometry": {"coordinates":[35.95764000000001,37.69823],"type":"Point"}
}