{
  "type": "Feature",
  "properties": {
    "gn:admin1_code":"48",
    "gn:asciiname":"Yagcilar",
    "gn:country_code":"TR",
    "gn:dem":116,
    "gn:feature_class":"P",
    "gn:feature_code":"PPL",
    "gn:name":"Ya\u011fc\u0131lar",
    "gn:population":0,
    "gn:timezone":"Europe/Istanbul",
    "iso:country":"TR",
    "name:tur_x_preferred":[
        "Ya\u011fc\u0131lar"
    ],
    "wof:name":"Yagcilar",
    "wof:placetype":"locality"
},
  "geometry": {"coordinates":[29.27143,36.39963],"type":"Point"}
}