{
  "type": "Feature",
  "properties": {
    "gn:admin1_code":"60.0",
    "gn:asciiname":"Avunlar",
    "gn:country_code":"TR",
    "gn:dem":967,
    "gn:feature_class":"P",
    "gn:feature_code":"PPL",
    "gn:name":"Avunlar",
    "gn:population":0,
    "gn:timezone":"Europe/Istanbul",
    "iso:country":"TR",
    "name:und_x_variant":[
        "Ortak\u00f6y",
        "Avunlar"
    ],
    "wof:name":"Avunlar",
    "wof:placetype":"locality"
},
  "geometry": {"coordinates":[36.73251,40.53524],"type":"Point"}
}