{
  "type": "Feature",
  "properties": {
    "gn:admin1_code":"81",
    "gn:asciiname":"Handere",
    "gn:country_code":"TR",
    "gn:dem":227,
    "gn:feature_class":"P",
    "gn:feature_code":"PPL",
    "gn:name":"Handere",
    "gn:population":0,
    "gn:timezone":"Europe/Istanbul",
    "iso:country":"TR",
    "name:und_x_variant":[
        "Handeresik\u00f6y",
        "Handere",
        "G\u00f6kb\u00fcket",
        "G\u00f6kb\u00fcvet"
    ],
    "wof:name":"Handere",
    "wof:placetype":"locality"
},
  "geometry": {"coordinates":[35.55759000000001,37.15025],"type":"Point"}
}