{
  "type": "Feature",
  "properties": {
    "gn:admin1_code":"23",
    "gn:asciiname":"Degirmentasi",
    "gn:country_code":"TR",
    "gn:dem":1044,
    "gn:feature_class":"P",
    "gn:feature_code":"PPL",
    "gn:name":"De\u011firmenta\u015f\u0131",
    "gn:population":0,
    "gn:timezone":"Europe/Istanbul",
    "iso:country":"TR",
    "name:und_x_variant":[
        "Piyadin",
        "De\u011firmenka\u015f\u0131",
        "Piyadan",
        "De\u011firmenta\u015f\u0131"
    ],
    "wof:name":"Degirmentasi",
    "wof:placetype":"locality"
},
  "geometry": {"coordinates":[39.75873,38.81799],"type":"Point"}
}