{
  "type": "Feature",
  "properties": {
    "gn:admin1_code":"09",
    "gn:asciiname":"Zeytinkoy",
    "gn:country_code":"TR",
    "gn:dem":262,
    "gn:feature_class":"P",
    "gn:feature_code":"PPL",
    "gn:name":"Zeytink\u00f6y",
    "gn:population":0,
    "gn:timezone":"Europe/Istanbul",
    "iso:country":"TR",
    "name:und_x_variant":[
        "Zeytin",
        "Zeytink\u00f6y"
    ],
    "wof:name":"Zeytinkoy",
    "wof:placetype":"locality"
},
  "geometry": {"coordinates":[27.77126,37.7153],"type":"Point"}
}