{
  "type": "Feature",
  "properties": {
    "gn:admin1_code":"43",
    "gn:asciiname":"Cukurca",
    "gn:country_code":"TR",
    "gn:dem":977,
    "gn:feature_class":"P",
    "gn:feature_code":"PPL",
    "gn:name":"\u00c7ukurca",
    "gn:population":0,
    "gn:timezone":"Europe/Istanbul",
    "iso:country":"TR",
    "wof:name":"Cukurca",
    "wof:placetype":"locality"
},
  "geometry": {"coordinates":[29.69024000000001,39.77947],"type":"Point"}
}