{
  "type": "Feature",
  "properties": {
    "gn:admin1_code":"62",
    "gn:asciiname":"Sarikoc",
    "gn:country_code":"TR",
    "gn:dem":1314,
    "gn:feature_class":"P",
    "gn:feature_code":"PPL",
    "gn:name":"Sar\u0131ko\u00e7",
    "gn:population":0,
    "gn:timezone":"Europe/Istanbul",
    "iso:country":"TR",
    "name:tur_x_preferred":[
        "Sar\u0131ko\u00e7"
    ],
    "wof:name":"Sarikoc",
    "wof:placetype":"locality"
},
  "geometry": {"coordinates":[39.80196,39.02031],"type":"Point"}
}