{
  "type": "Feature",
  "properties": {
    "gn:admin1_code":"09",
    "gn:asciiname":"Dogan",
    "gn:country_code":"TR",
    "gn:dem":201,
    "gn:feature_class":"P",
    "gn:feature_code":"PPL",
    "gn:name":"Do\u011fan",
    "gn:population":0,
    "gn:timezone":"Europe/Istanbul",
    "iso:country":"TR",
    "name:deu_x_preferred":[
        "Do\u011fan"
    ],
    "name:fra_x_preferred":[
        "Do\u011fan"
    ],
    "name:ron_x_preferred":[
        "Dogan"
    ],
    "name:rus_x_preferred":[
        "\u0414\u043e\u0433\u0430\u043d"
    ],
    "name:tur_x_preferred":[
        "Do\u011fan"
    ],
    "wof:name":"Dogan",
    "wof:placetype":"locality"
},
  "geometry": {"coordinates":[27.886,37.86636],"type":"Point"}
}