{
  "type": "Feature",
  "properties": {
    "gn:admin1_code":"88.0",
    "gn:asciiname":"Koprubasi",
    "gn:country_code":"TR",
    "gn:dem":1019,
    "gn:feature_class":"P",
    "gn:feature_code":"PPL",
    "gn:name":"K\u00f6pr\u00fcba\u015f\u0131",
    "gn:population":0,
    "gn:timezone":"Europe/Istanbul",
    "iso:country":"TR",
    "name:und_x_variant":[
        "\u00c7in\u00e7avat",
        "K\u00f6pr\u00fcba\u015f\u0131"
    ],
    "wof:name":"Koprubasi",
    "wof:placetype":"locality"
},
  "geometry": {"coordinates":[43.72222,40.04851],"type":"Point"}
}