{
  "type": "Feature",
  "properties": {
    "gn:admin1_code":"17.0",
    "gn:asciiname":"Koseler",
    "gn:country_code":"TR",
    "gn:dem":398,
    "gn:feature_class":"P",
    "gn:feature_code":"PPL",
    "gn:name":"K\u00f6\u015feler",
    "gn:population":0,
    "gn:timezone":"Europe/Istanbul",
    "iso:country":"TR",
    "wof:name":"Koseler",
    "wof:placetype":"locality"
},
  "geometry": {"coordinates":[26.738,39.8075],"type":"Point"}
}