{
  "type": "Feature",
  "properties": {
    "gn:admin1_code":"48",
    "gn:asciiname":"Ketendere",
    "gn:country_code":"TR",
    "gn:dem":409,
    "gn:feature_class":"P",
    "gn:feature_code":"PPL",
    "gn:name":"Ketendere",
    "gn:population":0,
    "gn:timezone":"Europe/Istanbul",
    "iso:country":"TR",
    "name:tur_x_preferred":[
        "Ketendere"
    ],
    "wof:name":"Ketendere",
    "wof:placetype":"locality"
},
  "geometry": {"coordinates":[27.76612,37.42867],"type":"Point"}
}