{
  "type": "Feature",
  "properties": {
    "gn:admin1_code":"26",
    "gn:asciiname":"Kozkaya",
    "gn:cc2":"TR",
    "gn:country_code":"TR",
    "gn:dem":1006,
    "gn:feature_class":"P",
    "gn:feature_code":"PPL",
    "gn:name":"Kozkaya",
    "gn:population":0,
    "gn:timezone":"Europe/Istanbul",
    "iso:country":"TR",
    "name:und_x_variant":[
        "Kozkay\u0131",
        "Kozkaya K\u00f6y\u00fc",
        "Kozkaya"
    ],
    "wof:name":"Kozkaya",
    "wof:placetype":"locality"
},
  "geometry": {"coordinates":[30.51667,39.88333],"type":"Point"}
}