{
  "type": "Feature",
  "properties": {
    "gn:admin1_code":"58",
    "gn:asciiname":"Arpaozu",
    "gn:country_code":"TR",
    "gn:dem":1352,
    "gn:feature_class":"P",
    "gn:feature_code":"PPL",
    "gn:name":"Arpa\u00f6z\u00fc",
    "gn:population":0,
    "gn:timezone":"Europe/Istanbul",
    "iso:country":"TR",
    "name:und_x_variant":[
        "Arap\u00f6z\u00fc",
        "Alp\u00f6z\u00fc",
        "Arpa\u00f6z\u00fc"
    ],
    "wof:name":"Arpaozu",
    "wof:placetype":"locality"
},
  "geometry": {"coordinates":[35.89997,39.28868],"type":"Point"}
}