{
  "type": "Feature",
  "properties": {
    "gn:admin1_code":"12",
    "gn:asciiname":"Tilki",
    "gn:country_code":"TR",
    "gn:dem":1873,
    "gn:feature_class":"P",
    "gn:feature_code":"PPL",
    "gn:name":"Tilki",
    "gn:population":0,
    "gn:timezone":"Europe/Istanbul",
    "iso:country":"TR",
    "wof:name":"Tilki",
    "wof:placetype":"locality"
},
  "geometry": {"coordinates":[40.23333,39.35],"type":"Point"}
}