{
  "type": "Feature",
  "properties": {
    "iso:country":"TR",
    "name:tur_x_preferred":[
        "G\u00fcne\u015ftepe"
    ],
    "wof:name":"Gunestepe",
    "wof:placetype":"neighbourhood"
},
  "geometry": {"coordinates":[28.86623825747846,41.02471299445389],"type":"Point"}
}