{
  "type": "Feature",
  "properties": {
    "gn:country":"TR",
    "gn:fcode":"PPL",
    "gn:pop":0,
    "iso:country":"TR",
    "name:unk_x_variant":[
        "Resadiye"
    ],
    "qs:name":"Yenikale",
    "qs:name_adm0":"Turkey",
    "qs:name_adm1":"\u0130zmir",
    "qs:photos_9k":1,
    "qs:photos_9r":4,
    "qs:photos_all":188,
    "qs:photos_sr":0,
    "qs:placetype":"Town",
    "qs:pop_sr":"0",
    "wd:wordcount":380,
    "wof:name":"Yenikale",
    "wof:placetype":"locality",
    "wof:population":0
},
  "geometry": {"coordinates":[27.01667,38.41667],"type":"Point"}
}