{
  "type": "Feature",
  "properties": {
    "gn:admin1_code":"72",
    "gn:asciiname":"Esentepe",
    "gn:country_code":"TR",
    "gn:dem":535,
    "gn:feature_class":"P",
    "gn:feature_code":"PPL",
    "gn:name":"Esentepe",
    "gn:population":0,
    "gn:timezone":"Europe/Istanbul",
    "iso:country":"TR",
    "name:tur_x_preferred":[
        "Yukar\u0131 Esentepe"
    ],
    "name:tur_x_variant":[
        "Esentepe"
    ],
    "name:und_x_variant":[
        "Kas\u0131rahmethayre",
        "Kas\u0131rahmethiro",
        "Kas\u0131rahmethayro",
        "Kasr\u0131ahmethayro",
        "Esentepe"
    ],
    "wof:name":"Esentepe",
    "wof:placetype":"locality"
},
  "geometry": {"coordinates":[40.99727,37.13973],"type":"Point"}
}