{
  "type": "Feature",
  "properties": {
    "gn:country":"TR",
    "gn:fcode":"PPL",
    "gn:pop":2583,
    "iso:country":"TR",
    "name:unk_x_variant":[
        "Dzhivinikyan"
    ],
    "qs:name":"Civankan",
    "qs:photos_9r":0,
    "qs:photos_sr":0,
    "qs:pop_sr":"4",
    "wof:name":"Civankan",
    "wof:placetype":"locality",
    "wof:population":2583
},
  "geometry": {"coordinates":[41.87333,37.90583],"type":"Point"}
}