{
  "type": "Feature",
  "properties": {
    "gn:country":"TR",
    "gn:fcode":"PPL",
    "gn:population":3350,
    "iso:country":"TR",
    "name:ceb_x_preferred":[
        "Uluyat\u0131r"
    ],
    "name:che_x_preferred":[
        "\u0423\u043b\u0443\u0439\u0430\u0442\u0438\u0440"
    ],
    "name:deu_x_preferred":[
        "Uluyat\u0131r"
    ],
    "name:eng_x_preferred":[
        "Uluyat\u0131r"
    ],
    "name:fas_x_preferred":[
        "\u0627\u0648\u0644\u0648\u06cc\u0627\u062a\u06cc\u0631"
    ],
    "name:hye_x_preferred":[
        "\u0544\u056b\u0566\u0561\u0580"
    ],
    "name:kur_x_preferred":[
        "M\u00eezar"
    ],
    "name:nld_x_preferred":[
        "Uluyat\u0131r"
    ],
    "name:tat_x_preferred":[
        "\u0423\u043b\u0443\u044f\u0442\u044b\u0440"
    ],
    "name:tur_x_preferred":[
        "Uluyat\u0131r"
    ],
    "name:und_x_variant":[
        "Mizar"
    ],
    "name:vie_x_preferred":[
        "Uluyat\u0131r"
    ],
    "name:yor_x_preferred":[
        "Uluyat\u0131r"
    ],
    "qs:name":"Uluyat\u0131r",
    "qs:photos_9r":0,
    "qs:photos_sr":0,
    "qs:pop_sr":"4",
    "wd:wordcount":110,
    "wof:name":"Uluyat\u0131r",
    "wof:placetype":"locality",
    "wof:population":3350
},
  "geometry": {"coordinates":[37.69361,36.96333],"type":"Point"}
}