{
  "type": "Feature",
  "properties": {
    "gn:country":"TR",
    "gn:fcode":"PPL",
    "gn:pop":3350,
    "iso:country":"TR",
    "name:eng_x_preferred":[
        "Uluyat\u0131r"
    ],
    "name:nld_x_preferred":[
        "Uluyat\u0131r"
    ],
    "name:tur_x_preferred":[
        "Uluyat\u0131r"
    ],
    "name:unk_x_variant":[
        "Mizar"
    ],
    "name:vie_x_preferred":[
        "Uluyat\u0131r"
    ],
    "qs:name":"Uluyat\u0131r",
    "qs:photos_9r":0,
    "qs:photos_sr":0,
    "qs:pop_sr":"4",
    "wd:wordcount":110,
    "wof:name":"Uluyat\u0131r",
    "wof:placetype":"locality",
    "wof:population":3350
},
  "geometry": {"coordinates":[37.69361,36.96333],"type":"Point"}
}