{
  "type": "Feature",
  "properties": {
    "gn:admin1_code":"25.0",
    "gn:asciiname":"Abdalcik",
    "gn:country_code":"TR",
    "gn:dem":1766,
    "gn:feature_class":"P",
    "gn:feature_code":"PPL",
    "gn:name":"Abdalc\u0131k",
    "gn:population":0,
    "gn:timezone":"Europe/Istanbul",
    "iso:country":"TR",
    "name:und_x_variant":[
        "Aptalc\u0131k",
        "Abdalc\u0131k"
    ],
    "wof:name":"Abdalcik",
    "wof:placetype":"locality"
},
  "geometry": {"coordinates":[40.78784,39.88571],"type":"Point"}
}