{
  "type": "Feature",
  "properties": {
    "gn:admin1_code":"31",
    "gn:asciiname":"Huyukkoy",
    "gn:country_code":"TR",
    "gn:dem":61,
    "gn:feature_class":"P",
    "gn:feature_code":"PPL",
    "gn:name":"H\u00fcy\u00fckk\u00f6y",
    "gn:population":0,
    "gn:timezone":"Europe/Istanbul",
    "iso:country":"TR",
    "name:tur_x_preferred":[
        "H\u00fcy\u00fckk\u00f6y"
    ],
    "name:tur_x_variant":[
        "H\u00fcy\u00fck"
    ],
    "wof:name":"Huyukkoy",
    "wof:placetype":"locality"
},
  "geometry": {"coordinates":[35.91448,36.37106],"type":"Point"}
}