{
  "type": "Feature",
  "properties": {
    "iso:country":"TR",
    "name:eng_x_preferred":[
        "Cinardere"
    ],
    "name:tur_x_preferred":[
        "\u00c7\u0131nardere"
    ],
    "wof:name":"Cinardere",
    "wof:placetype":"neighbourhood"
},
  "geometry": {"coordinates":[29.2411354232007,40.89450549300506],"type":"Point"}
}