{
  "type": "Feature",
  "properties": {
    "gn:admin1_code":"13",
    "gn:asciiname":"Yildiz",
    "gn:country_code":"TR",
    "gn:dem":1545,
    "gn:feature_class":"P",
    "gn:feature_code":"PPL",
    "gn:name":"Y\u0131ld\u0131z",
    "gn:population":0,
    "gn:timezone":"Europe/Istanbul",
    "iso:country":"TR",
    "wof:name":"Yildiz",
    "wof:placetype":"locality"
},
  "geometry": {"coordinates":[41.71667,38.41667],"type":"Point"}
}