{
  "type": "Feature",
  "properties": {
    "gn:admin1_code":"25.0",
    "gn:asciiname":"Yesilbaglar",
    "gn:country_code":"TR",
    "gn:dem":983,
    "gn:feature_class":"P",
    "gn:feature_code":"PPL",
    "gn:name":"Ye\u015filba\u011flar",
    "gn:population":0,
    "gn:timezone":"Europe/Istanbul",
    "iso:country":"TR",
    "name:und_x_variant":[
        "Norpet",
        "Ye\u015filba\u011flar"
    ],
    "wof:name":"Yesilbaglar",
    "wof:placetype":"locality"
},
  "geometry": {"coordinates":[42.12334,40.77812],"type":"Point"}
}