{
  "type": "Feature",
  "properties": {
    "iso:country":"TR",
    "name:eng_x_preferred":[
        "Bahcelievler"
    ],
    "name:tur_x_preferred":[
        "Bah\u00e7elievler"
    ],
    "wof:name":"Bahcelievler",
    "wof:placetype":"neighbourhood"
},
  "geometry": {"coordinates":[28.48837544102121,41.01674538905992],"type":"Point"}
}