{
  "type": "Feature",
  "properties": {
    "gn:admin1_code":"28.0",
    "gn:asciiname":"Seku",
    "gn:country_code":"TR",
    "gn:dem":565,
    "gn:feature_class":"P",
    "gn:feature_code":"PPL",
    "gn:name":"Sek\u00fc",
    "gn:population":0,
    "gn:timezone":"Europe/Istanbul",
    "iso:country":"TR",
    "name:ceb_x_preferred":[
        "Seku"
    ],
    "name:srp_x_preferred":[
        "\u0421\u0435\u043a\u0443"
    ],
    "name:swe_x_preferred":[
        "Seku"
    ],
    "name:tur_x_preferred":[
        "Sek\u00fc"
    ],
    "wof:name":"Seku",
    "wof:placetype":"locality"
},
  "geometry": {"coordinates":[38.8949,40.85418],"type":"Point"}
}