{
  "type": "Feature",
  "properties": {
    "gn:admin1_code":"48",
    "gn:asciiname":"Konak",
    "gn:country_code":"TR",
    "gn:dem":542,
    "gn:feature_class":"P",
    "gn:feature_code":"PPL",
    "gn:name":"Konak",
    "gn:population":0,
    "gn:timezone":"Europe/Istanbul",
    "iso:country":"TR",
    "name:tur_x_preferred":[
        "Kodurcak"
    ],
    "name:tur_x_variant":[
        "Konak"
    ],
    "name:und_x_variant":[
        "Kuricak",
        "Kod\u0131cak"
    ],
    "wof:name":"Konak",
    "wof:placetype":"locality"
},
  "geometry": {"coordinates":[27.69504,37.46445],"type":"Point"}
}