{
  "type": "Feature",
  "properties": {
    "gn:admin1_code":"61.0",
    "gn:asciiname":"Arpacili",
    "gn:country_code":"TR",
    "gn:dem":314,
    "gn:feature_class":"P",
    "gn:feature_code":"PPL",
    "gn:name":"Arpac\u0131l\u0131",
    "gn:population":0,
    "gn:timezone":"Europe/Istanbul",
    "iso:country":"TR",
    "name:tur_x_preferred":[
        "Arpac\u0131l\u0131"
    ],
    "wof:name":"Arpacili",
    "wof:placetype":"locality"
},
  "geometry": {"coordinates":[39.47727,40.9568],"type":"Point"}
}