{
  "type": "Feature",
  "properties": {
    "gn:admin1_code":"10",
    "gn:asciiname":"Iskan",
    "gn:country_code":"TR",
    "gn:dem":353,
    "gn:feature_class":"P",
    "gn:feature_code":"PPL",
    "gn:name":"\u0130skan",
    "gn:population":0,
    "gn:timezone":"Europe/Istanbul",
    "iso:country":"TR",
    "name:tur_x_preferred":[
        "\u0130skan"
    ],
    "wof:name":"Iskan",
    "wof:placetype":"locality"
},
  "geometry": {"coordinates":[27.79553,39.50885],"type":"Point"}
}