{
  "type": "Feature",
  "properties": {
    "gn:country":"TR",
    "gn:fcode":"PPL",
    "gn:pop":8105,
    "iso:country":"TR",
    "name:ara_x_preferred":[
        "\u062e\u0648\u0632\u0627\u062a"
    ],
    "name:arm_x_preferred":[
        "\u053d\u0578\u0566\u0561\u0569"
    ],
    "name:ckb_x_preferred":[
        "\u062e\u06c6\u0632\u0627\u062a"
    ],
    "name:diq_x_preferred":[
        "Xozat"
    ],
    "name:dut_x_preferred":[
        "Hozat"
    ],
    "name:eng_x_preferred":[
        "Hozat"
    ],
    "name:fre_x_preferred":[
        "Hozat"
    ],
    "name:ger_x_preferred":[
        "Hozat"
    ],
    "name:hun_x_preferred":[
        "Hozat"
    ],
    "name:ita_x_preferred":[
        "Distretto di Hozat"
    ],
    "name:jpn_x_preferred":[
        "\u30db\u30b6\u30c8"
    ],
    "name:kur_x_preferred":[
        "Xozat"
    ],
    "name:may_x_preferred":[
        "Hozat"
    ],
    "name:mrj_x_preferred":[
        "\u0425\u043e\u0437\u0430\u0442"
    ],
    "name:nan_x_preferred":[
        "Hozat"
    ],
    "name:per_x_preferred":[
        "\u0634\u0647\u0631\u0633\u062a\u0627\u0646 \u062e\u0648\u0632\u0627\u062a"
    ],
    "name:pnb_x_preferred":[
        "\u0636\u0644\u0639 \u06c1\u0648\u0632\u0627\u062a"
    ],
    "name:rus_x_preferred":[
        "\u0425\u043e\u0437\u0430\u0442"
    ],
    "name:swa_x_preferred":[
        "Hozat"
    ],
    "name:tur_x_preferred":[
        "Hozat"
    ],
    "name:unk_x_variant":[
        "Dersim"
    ],
    "name:urd_x_preferred":[
        "\u062e\u0648\u0632\u0627\u062a"
    ],
    "name:vie_x_preferred":[
        "Hozat"
    ],
    "qs:name":"Hozat",
    "qs:name_adm0":"Turkey",
    "qs:name_adm1":"Tunceli",
    "qs:photos_9r":0,
    "qs:photos_sr":0,
    "qs:placetype":"Town",
    "qs:pop_sr":"5",
    "wd:wordcount":159,
    "wof:name":"Hozat",
    "wof:placetype":"locality",
    "wof:population":8105
},
  "geometry": {"coordinates":[39.22127,39.10829],"type":"Point"}
}