{
  "type": "Feature",
  "properties": {
    "gn:admin1_code":"20",
    "gn:asciiname":"Yuregil",
    "gn:country_code":"TR",
    "gn:dem":974,
    "gn:feature_class":"P",
    "gn:feature_code":"PPL",
    "gn:name":"Y\u00fcre\u011fil",
    "gn:population":0,
    "gn:timezone":"Europe/Istanbul",
    "iso:country":"TR",
    "name:bul_x_preferred":[
        "\u042f\u0442\u0430\u0433\u0430\u043d"
    ],
    "name:deu_x_preferred":[
        "Yata\u011fan"
    ],
    "name:nld_x_preferred":[
        "Yata\u011fan"
    ],
    "name:tur_x_preferred":[
        "Yata\u011fan"
    ],
    "name:und_x_variant":[
        "Y\u00fcre\u011fil"
    ],
    "name:vie_x_preferred":[
        "Yata\u011fan"
    ],
    "wof:name":"Yuregil",
    "wof:placetype":"locality"
},
  "geometry": {"coordinates":[29.36311,37.56862],"type":"Point"}
}