{
  "type": "Feature",
  "properties": {
    "gn:admin1_code":"84.0",
    "gn:asciiname":"Boyali",
    "gn:country_code":"TR",
    "gn:dem":2052,
    "gn:feature_class":"P",
    "gn:feature_code":"PPL",
    "gn:name":"Boyal\u0131",
    "gn:population":0,
    "gn:timezone":"Europe/Istanbul",
    "iso:country":"TR",
    "name:tur_x_preferred":[
        "Boyal\u0131"
    ],
    "wof:name":"Boyali",
    "wof:placetype":"locality"
},
  "geometry": {"coordinates":[42.57465,40.44498],"type":"Point"}
}