{
  "type": "Feature",
  "properties": {
    "gn:admin1_code":"44",
    "gn:asciiname":"Aksaray",
    "gn:country_code":"TR",
    "gn:dem":787,
    "gn:feature_class":"P",
    "gn:feature_code":"PPL",
    "gn:name":"Aksaray",
    "gn:population":0,
    "gn:timezone":"Europe/Istanbul",
    "iso:country":"TR",
    "name:und_x_variant":[
        "Zeyve",
        "Aksaray"
    ],
    "wof:name":"Aksaray",
    "wof:placetype":"locality"
},
  "geometry": {"coordinates":[38.13468,38.43722],"type":"Point"}
}