{
  "type": "Feature",
  "properties": {
    "gn:admin1_code":"20",
    "gn:asciiname":"Ayaz",
    "gn:country_code":"TR",
    "gn:dem":1083,
    "gn:feature_class":"P",
    "gn:feature_code":"PPL",
    "gn:name":"Ayaz",
    "gn:population":0,
    "gn:timezone":"Europe/Istanbul",
    "iso:country":"TR",
    "name:cat_x_preferred":[
        "Ayaz"
    ],
    "name:deu_x_preferred":[
        "Ayaz"
    ],
    "name:tur_x_preferred":[
        "Ayaz"
    ],
    "name:und_x_variant":[
        "Ayazk\u00f6y"
    ],
    "wof:name":"Ayaz",
    "wof:placetype":"locality"
},
  "geometry": {"coordinates":[29.35064,37.57952],"type":"Point"}
}