{
  "type": "Feature",
  "properties": {
    "gn:admin1_code":"24.0",
    "gn:asciiname":"Gokseki",
    "gn:country_code":"TR",
    "gn:dem":1683,
    "gn:feature_class":"P",
    "gn:feature_code":"PPL",
    "gn:name":"G\u00f6kseki",
    "gn:population":0,
    "gn:timezone":"Europe/Istanbul",
    "iso:country":"TR",
    "name:und_x_variant":[
        "K\u00f6kseki",
        "G\u00f6kseki"
    ],
    "wof:name":"Gokseki",
    "wof:placetype":"locality"
},
  "geometry": {"coordinates":[38.86283,40.0183],"type":"Point"}
}