{
  "type": "Feature",
  "properties": {
    "gn:admin1_code":"80",
    "gn:asciiname":"Donerdover",
    "gn:country_code":"TR",
    "gn:dem":1255,
    "gn:feature_class":"P",
    "gn:feature_code":"PPL",
    "gn:name":"D\u00f6nerd\u00f6ver",
    "gn:population":0,
    "gn:timezone":"Europe/Istanbul",
    "iso:country":"TR",
    "name:und_x_variant":[
        "Bukat",
        "D\u00f6nerd\u00f6ver"
    ],
    "wof:name":"Donerdover",
    "wof:placetype":"locality"
},
  "geometry": {"coordinates":[42.17246,37.64539],"type":"Point"}
}