{
  "type": "Feature",
  "properties": {
    "gn:admin1_code":"07",
    "gn:asciiname":"Kislabucagi",
    "gn:country_code":"TR",
    "gn:dem":14,
    "gn:feature_class":"P",
    "gn:feature_code":"PPL",
    "gn:name":"K\u0131\u015flabuca\u011f\u0131",
    "gn:population":0,
    "gn:timezone":"Europe/Istanbul",
    "iso:country":"TR",
    "wof:name":"Kislabucagi",
    "wof:placetype":"locality"
},
  "geometry": {"coordinates":[32.29083,36.26917],"type":"Point"}
}