{
  "type": "Feature",
  "properties": {
    "gn:admin1_code":"16.0",
    "gn:asciiname":"Kursunlu",
    "gn:country_code":"TR",
    "gn:dem":17,
    "gn:feature_class":"P",
    "gn:feature_code":"PPL",
    "gn:name":"Kur\u015funlu",
    "gn:population":0,
    "gn:timezone":"Europe/Istanbul",
    "iso:country":"TR",
    "name:tur_x_preferred":[
        "Kur\u015funlu"
    ],
    "wof:name":"Kursunlu",
    "wof:placetype":"locality"
},
  "geometry": {"coordinates":[28.28492,40.39679],"type":"Point"}
}