{
  "type": "Feature",
  "properties": {
    "gn:admin1_code":"19",
    "gn:asciiname":"Korpinar",
    "gn:country_code":"TR",
    "gn:dem":908,
    "gn:feature_class":"P",
    "gn:feature_code":"PPL",
    "gn:name":"K\u00f6rp\u0131nar",
    "gn:population":0,
    "gn:timezone":"Europe/Istanbul",
    "iso:country":"TR",
    "name:tur_x_preferred":[
        "K\u00f6rp\u0131nar"
    ],
    "wof:name":"Korpinar",
    "wof:placetype":"locality"
},
  "geometry": {"coordinates":[35.19871,40.15183],"type":"Point"}
}