{
  "type": "Feature",
  "properties": {
    "gn:admin1_code":"25.0",
    "gn:asciiname":"Dencik",
    "gn:country_code":"TR",
    "gn:dem":2140,
    "gn:feature_class":"P",
    "gn:feature_code":"PPL",
    "gn:name":"Dencik",
    "gn:population":0,
    "gn:timezone":"Europe/Istanbul",
    "iso:country":"TR",
    "name:eng_x_preferred":[
        "Dencik"
    ],
    "name:rus_x_preferred":[
        "\u0414\u0435\u043d\u0447\u0438\u043a"
    ],
    "wof:name":"Dencik",
    "wof:placetype":"locality"
},
  "geometry": {"coordinates":[40.58333,40.05],"type":"Point"}
}