{
  "type": "Feature",
  "properties": {
    "gn:admin1_code":"12",
    "gn:asciiname":"Kirkagil",
    "gn:country_code":"TR",
    "gn:dem":1544,
    "gn:feature_class":"P",
    "gn:feature_code":"PPL",
    "gn:name":"K\u0131rka\u011f\u0131l",
    "gn:population":0,
    "gn:timezone":"Europe/Istanbul",
    "iso:country":"TR",
    "name:tur_x_preferred":[
        "K\u0131rka\u011f\u0131l"
    ],
    "wof:name":"Kirkagil",
    "wof:placetype":"locality"
},
  "geometry": {"coordinates":[40.34553,38.90801],"type":"Point"}
}