{
  "type": "Feature",
  "properties": {
    "gn:country":"TR",
    "gn:fcode":"PPL",
    "gn:pop":87,
    "iso:country":"TR",
    "qs:name":"K\u0131ra\u00e7g\u00fcl\u00fc",
    "qs:photos_9r":0,
    "qs:photos_sr":0,
    "qs:pop_sr":"1",
    "wof:name":"K\u0131ra\u00e7g\u00fcl\u00fc",
    "wof:placetype":"locality",
    "wof:population":87
},
  "geometry": {"coordinates":[37.79139,36.86111],"type":"Point"}
}