{
  "type": "Feature",
  "properties": {
    "gn:admin1_code":"20",
    "gn:asciiname":"Karakoy",
    "gn:country_code":"TR",
    "gn:dem":956,
    "gn:feature_class":"P",
    "gn:feature_code":"PPL",
    "gn:name":"Karak\u00f6y",
    "gn:population":0,
    "gn:timezone":"Europe/Istanbul",
    "iso:country":"TR",
    "wof:name":"Karakoy",
    "wof:placetype":"locality"
},
  "geometry": {"coordinates":[28.83825,37.49829],"type":"Point"}
}