{
  "type": "Feature",
  "properties": {
    "gn:admin1_code":"86.0",
    "gn:asciiname":"Filizli",
    "gn:country_code":"TR",
    "gn:dem":1998,
    "gn:feature_class":"P",
    "gn:feature_code":"PPL",
    "gn:name":"Filizli",
    "gn:population":0,
    "gn:timezone":"Europe/Istanbul",
    "iso:country":"TR",
    "name:und_x_variant":[
        "Sivin",
        "Filizli"
    ],
    "wof:name":"Filizli",
    "wof:placetype":"locality"
},
  "geometry": {"coordinates":[42.64917,40.83341],"type":"Point"}
}