{
  "type": "Feature",
  "properties": {
    "gn:admin1_code":"68",
    "gn:asciiname":"Yarali",
    "gn:country_code":"TR",
    "gn:dem":765,
    "gn:feature_class":"P",
    "gn:feature_code":"PPL",
    "gn:name":"Yaral\u0131",
    "gn:population":0,
    "gn:timezone":"Europe/Istanbul",
    "iso:country":"TR",
    "name:tur_x_preferred":[
        "Yaral\u0131"
    ],
    "wof:name":"Yarali",
    "wof:placetype":"locality"
},
  "geometry": {"coordinates":[32.06576,39.28229],"type":"Point"}
}