{
  "type": "Feature",
  "properties": {
    "gn:admin1_code":"65.0",
    "gn:asciiname":"Yaya",
    "gn:country_code":"TR",
    "gn:dem":2478,
    "gn:feature_class":"P",
    "gn:feature_code":"PPL",
    "gn:name":"Yaya",
    "gn:population":0,
    "gn:timezone":"Europe/Istanbul",
    "iso:country":"TR",
    "name:tur_x_preferred":[
        "Yaya"
    ],
    "wof:name":"Yaya",
    "wof:placetype":"locality"
},
  "geometry": {"coordinates":[43.69167,37.88281],"type":"Point"}
}