{
  "type": "Feature",
  "properties": {
    "gn:country":"TR",
    "gn:fcode":"PPL",
    "gn:pop":76,
    "iso:country":"TR",
    "name:unk_x_variant":[
        "Dzhumay"
    ],
    "qs:name":"Birlikk\u00f6y",
    "qs:photos_9r":0,
    "qs:photos_sr":0,
    "qs:pop_sr":"1",
    "wof:name":"Birlikk\u00f6y",
    "wof:placetype":"locality",
    "wof:population":76
},
  "geometry": {"coordinates":[42.52222,37.24667],"type":"Point"}
}