{
  "type": "Feature",
  "properties": {
    "gn:admin1_code":"07",
    "gn:asciiname":"Hasgebe",
    "gn:country_code":"TR",
    "gn:dem":423,
    "gn:feature_class":"P",
    "gn:feature_code":"PPL",
    "gn:name":"Hasgebe",
    "gn:population":0,
    "gn:timezone":"Europe/Istanbul",
    "iso:country":"TR",
    "wof:name":"Hasgebe",
    "wof:placetype":"locality"
},
  "geometry": {"coordinates":[30.95111,37.22722],"type":"Point"}
}