{
  "type": "Feature",
  "properties": {
    "gn:admin1_code":"25.0",
    "gn:asciiname":"Ulutas",
    "gn:country_code":"TR",
    "gn:dem":2190,
    "gn:feature_class":"P",
    "gn:feature_code":"PPL",
    "gn:name":"Uluta\u015f",
    "gn:population":0,
    "gn:timezone":"Europe/Istanbul",
    "iso:country":"TR",
    "name:und_x_variant":[
        "Hantet",
        "Uluta\u015f",
        "Hantek"
    ],
    "wof:name":"Ulutas",
    "wof:placetype":"locality"
},
  "geometry": {"coordinates":[40.90356,40.57764],"type":"Point"}
}