{
  "type": "Feature",
  "properties": {
    "gn:admin1_code":"24",
    "gn:asciiname":"Cataloren",
    "gn:country_code":"TR",
    "gn:dem":1199,
    "gn:feature_class":"P",
    "gn:feature_code":"PPL",
    "gn:name":"\u00c7atal\u00f6ren",
    "gn:population":0,
    "gn:timezone":"Europe/Istanbul",
    "iso:country":"TR",
    "name:und_x_variant":[
        "Vak\u0131fbrastik",
        "Vak\u0131fb\u0131rastik",
        "\u00c7atal\u00f6ren"
    ],
    "wof:name":"Cataloren",
    "wof:placetype":"locality"
},
  "geometry": {"coordinates":[39.5128,39.66701],"type":"Point"}
}