{
  "type": "Feature",
  "properties": {
    "gn:admin1_code":"07",
    "gn:asciiname":"Kicik",
    "gn:country_code":"TR",
    "gn:dem":273,
    "gn:feature_class":"P",
    "gn:feature_code":"PPL",
    "gn:name":"K\u0131c\u0131k",
    "gn:population":0,
    "gn:timezone":"Europe/Istanbul",
    "iso:country":"TR",
    "wof:name":"Kicik",
    "wof:placetype":"locality"
},
  "geometry": {"coordinates":[32.39472,36.18282],"type":"Point"}
}