{
  "type": "Feature",
  "properties": {
    "gn:admin1_code":"93.0",
    "gn:asciiname":"Kurugol",
    "gn:country_code":"TR",
    "gn:dem":410,
    "gn:feature_class":"P",
    "gn:feature_code":"PPL",
    "gn:name":"Kurug\u00f6l",
    "gn:population":0,
    "gn:timezone":"Europe/Istanbul",
    "iso:country":"TR",
    "name:und_x_variant":[
        "Kurug\u00f6l K\u00f6y\u00fc",
        "Kurug\u00f6l K\u00f6y",
        "Kurug\u00f6l"
    ],
    "wof:name":"Kurugol",
    "wof:placetype":"locality"
},
  "geometry": {"coordinates":[31.0965,41.01669],"type":"Point"}
}