{
  "type": "Feature",
  "properties": {
    "gn:admin1_code":"10",
    "gn:asciiname":"Saribeyler",
    "gn:country_code":"TR",
    "gn:dem":260,
    "gn:feature_class":"P",
    "gn:feature_code":"PPLA3",
    "gn:name":"Sar\u0131beyler",
    "gn:population":0,
    "gn:timezone":"Europe/Istanbul",
    "iso:country":"TR",
    "name:tur_x_preferred":[
        "Sar\u0131beyler"
    ],
    "wof:name":"Saribeyler",
    "wof:placetype":"locality"
},
  "geometry": {"coordinates":[27.57722,39.39833],"type":"Point"}
}