{
  "type": "Feature",
  "properties": {
    "gn:admin1_code":"25",
    "gn:asciiname":"Seyhbizonyurdu",
    "gn:country_code":"TR",
    "gn:dem":2300,
    "gn:feature_class":"P",
    "gn:feature_code":"PPL",
    "gn:name":"Seyhbizonyurdu",
    "gn:population":0,
    "gn:timezone":"Europe/Istanbul",
    "iso:country":"TR",
    "name:und_x_variant":[
        "\u015eihbizinyurdu",
        "\u015e\u0131hb\u0131zunyurdu"
    ],
    "wof:name":"Seyhbizonyurdu",
    "wof:placetype":"locality"
},
  "geometry": {"coordinates":[40.85,39.73333],"type":"Point"}
}