{
  "type": "Feature",
  "properties": {
    "gn:admin1_code":"20",
    "gn:asciiname":"Imamlar",
    "gn:country_code":"TR",
    "gn:dem":1303,
    "gn:feature_class":"P",
    "gn:feature_code":"PPL",
    "gn:name":"\u0130mamlar",
    "gn:population":0,
    "gn:timezone":"Europe/Istanbul",
    "iso:country":"TR",
    "name:tur_x_preferred":[
        "\u0130mamlar"
    ],
    "wof:name":"Imamlar",
    "wof:placetype":"locality"
},
  "geometry": {"coordinates":[29.39246,37.10554000000001],"type":"Point"}
}