{
  "type": "Feature",
  "properties": {
    "gn:admin1_code":"33",
    "gn:asciiname":"Sariyer",
    "gn:country_code":"TR",
    "gn:dem":1918,
    "gn:feature_class":"P",
    "gn:feature_code":"PPL",
    "gn:name":"Sar\u0131yer",
    "gn:population":0,
    "gn:timezone":"Europe/Istanbul",
    "iso:country":"TR",
    "wof:name":"Sariyer",
    "wof:placetype":"locality"
},
  "geometry": {"coordinates":[30.78554,37.70021],"type":"Point"}
}