{
  "type": "Feature",
  "properties": {
    "gn:admin1_code":"71",
    "gn:asciiname":"Oren Boyali",
    "gn:country_code":"TR",
    "gn:dem":1274,
    "gn:feature_class":"P",
    "gn:feature_code":"PPL",
    "gn:name":"\u00d6ren Boyal\u0131",
    "gn:population":0,
    "gn:timezone":"Europe/Istanbul",
    "iso:country":"TR",
    "name:und_x_variant":[
        "\u00d6ren Boyal\u0131",
        "\u00d6renboyal\u0131"
    ],
    "wof:name":"Oren Boyali",
    "wof:placetype":"locality"
},
  "geometry": {"coordinates":[32.64948,37.23543],"type":"Point"}
}