{
  "type": "Feature",
  "properties": {
    "gn:admin1_code":"46",
    "gn:asciiname":"Haciaglar",
    "gn:country_code":"TR",
    "gn:dem":527,
    "gn:feature_class":"P",
    "gn:feature_code":"PPL",
    "gn:name":"Hac\u0131a\u011flar",
    "gn:population":0,
    "gn:timezone":"Europe/Istanbul",
    "iso:country":"TR",
    "name:tur_x_preferred":[
        "Hac\u0131a\u011flar"
    ],
    "wof:name":"Haciaglar",
    "wof:placetype":"locality"
},
  "geometry": {"coordinates":[36.813,37.50592],"type":"Point"}
}