{
  "type": "Feature",
  "properties": {
    "gn:admin1_code":"31",
    "gn:asciiname":"Ciftlik",
    "gn:country_code":"TR",
    "gn:dem":70,
    "gn:feature_class":"P",
    "gn:feature_code":"PPL",
    "gn:name":"\u00c7iftlik",
    "gn:population":0,
    "gn:timezone":"Europe/Istanbul",
    "iso:country":"TR",
    "name:tur_x_preferred":[
        "\u00c7iftlik"
    ],
    "wof:name":"Ciftlik",
    "wof:placetype":"locality"
},
  "geometry": {"coordinates":[35.99462,36.09454],"type":"Point"}
}