{
  "type": "Feature",
  "properties": {
    "gn:admin1_code":"60.0",
    "gn:asciiname":"Batmantas",
    "gn:country_code":"TR",
    "gn:dem":1490,
    "gn:feature_class":"P",
    "gn:feature_code":"PPL",
    "gn:name":"Batmanta\u015f",
    "gn:population":0,
    "gn:timezone":"Europe/Istanbul",
    "iso:country":"TR",
    "name:eng_x_preferred":[
        "Batmanta\u015f"
    ],
    "name:rus_x_preferred":[
        "\u0411\u0430\u0442\u043c\u0430\u043d\u0442\u0430\u0448\u043a\u0435\u0439"
    ],
    "name:und_x_variant":[
        "Batmanta\u015f K\u00f6y\u00fc",
        "Batmanta\u015f"
    ],
    "wof:name":"Batmantas",
    "wof:placetype":"locality"
},
  "geometry": {"coordinates":[36.66356,40.17167],"type":"Point"}
}