{
  "type": "Feature",
  "properties": {
    "gn:admin1_code":"87",
    "gn:asciiname":"Kirlikmuslumhoca",
    "gn:country_code":"TR",
    "gn:dem":119,
    "gn:feature_class":"P",
    "gn:feature_code":"PPL",
    "gn:name":"Kirlikm\u00fcsl\u00fcmhoca",
    "gn:population":0,
    "gn:timezone":"Europe/Istanbul",
    "iso:country":"TR",
    "wof:name":"Kirlikmuslumhoca",
    "wof:placetype":"locality"
},
  "geometry": {"coordinates":[32.71966,41.83517],"type":"Point"}
}