{
  "type": "Feature",
  "properties": {
    "gn:admin1_code":"40.0",
    "gn:asciiname":"Karakutuk",
    "gn:country_code":"TR",
    "gn:dem":1053,
    "gn:feature_class":"P",
    "gn:feature_code":"PPL",
    "gn:name":"Karakutuk",
    "gn:population":0,
    "gn:timezone":"Europe/Istanbul",
    "iso:country":"TR",
    "wof:name":"Karakutuk",
    "wof:placetype":"locality"
},
  "geometry": {"coordinates":[33.79714,39.41074],"type":"Point"}
}