{
  "type": "Feature",
  "properties": {
    "gn:admin1_code":"13.0",
    "gn:asciiname":"Yazikonak",
    "gn:country_code":"TR",
    "gn:dem":1820,
    "gn:feature_class":"P",
    "gn:feature_code":"PPL",
    "gn:name":"Yaz\u0131konak",
    "gn:population":0,
    "gn:timezone":"Europe/Istanbul",
    "iso:country":"TR",
    "name:tur_x_preferred":[
        "Yaz\u0131konak"
    ],
    "wof:name":"Yazikonak",
    "wof:placetype":"locality"
},
  "geometry": {"coordinates":[42.11969000000001,38.5031],"type":"Point"}
}