{
  "type": "Feature",
  "properties": {
    "gn:admin1_code":"09",
    "gn:asciiname":"Camarasi",
    "gn:country_code":"TR",
    "gn:dem":726,
    "gn:feature_class":"P",
    "gn:feature_code":"PPL",
    "gn:name":"\u00c7amaras\u0131",
    "gn:population":0,
    "gn:timezone":"Europe/Istanbul",
    "iso:country":"TR",
    "name:und_x_variant":[
        "Circivan",
        "\u00c7amaras\u0131"
    ],
    "wof:name":"Camarasi",
    "wof:placetype":"locality"
},
  "geometry": {"coordinates":[28.70124,37.65073],"type":"Point"}
}