{
  "type": "Feature",
  "properties": {
    "gn:admin1_code":"19.0",
    "gn:asciiname":"Demirseyh",
    "gn:country_code":"TR",
    "gn:dem":964,
    "gn:feature_class":"P",
    "gn:feature_code":"PPL",
    "gn:name":"Demir\u015feyh",
    "gn:population":0,
    "gn:timezone":"Europe/Istanbul",
    "iso:country":"TR",
    "name:und_x_variant":[
        "Demir\u015fih",
        "Demir\u015feyh"
    ],
    "wof:name":"Demirseyh",
    "wof:placetype":"locality"
},
  "geometry": {"coordinates":[34.51213,40.26942],"type":"Point"}
}