{
  "type": "Feature",
  "properties": {
    "gn:admin1_code":"63.0",
    "gn:asciiname":"Komagil",
    "gn:country_code":"TR",
    "gn:dem":596,
    "gn:feature_class":"P",
    "gn:feature_code":"PPL",
    "gn:name":"K\u00f6ma\u011f\u0131l",
    "gn:population":0,
    "gn:timezone":"Europe/Istanbul",
    "iso:country":"TR",
    "name:tur_x_preferred":[
        "K\u00f6ma\u011f\u0131l"
    ],
    "wof:name":"Komagil",
    "wof:placetype":"locality"
},
  "geometry": {"coordinates":[38.12498,37.02573],"type":"Point"}
}