{
  "type": "Feature",
  "properties": {
    "gn:admin1_code":"44",
    "gn:asciiname":"Karamagara",
    "gn:country_code":"TR",
    "gn:dem":1437,
    "gn:feature_class":"P",
    "gn:feature_code":"PPL",
    "gn:name":"Karama\u011fara",
    "gn:population":0,
    "gn:timezone":"Europe/Istanbul",
    "iso:country":"TR",
    "name:tur_x_preferred":[
        "Karama\u011fara"
    ],
    "wof:name":"Karamagara",
    "wof:placetype":"locality"
},
  "geometry": {"coordinates":[38.0003,38.45396],"type":"Point"}
}