{
  "type": "Feature",
  "properties": {
    "gn:admin1_code":"49",
    "gn:asciiname":"Eryurdu",
    "gn:country_code":"TR",
    "gn:dem":1971,
    "gn:feature_class":"P",
    "gn:feature_code":"PPL",
    "gn:name":"Eryurdu",
    "gn:population":0,
    "gn:timezone":"Europe/Istanbul",
    "iso:country":"TR",
    "name:tur_x_preferred":[
        "Eryurdu"
    ],
    "wof:name":"Eryurdu",
    "wof:placetype":"locality"
},
  "geometry": {"coordinates":[41.26421,39.29137],"type":"Point"}
}