{
  "type": "Feature",
  "properties": {
    "gn:admin1_code":"81",
    "gn:asciiname":"Korkuyu",
    "gn:country_code":"TR",
    "gn:dem":704,
    "gn:feature_class":"P",
    "gn:feature_code":"PPL",
    "gn:name":"K\u00f6rkuyu",
    "gn:population":0,
    "gn:timezone":"Europe/Istanbul",
    "iso:country":"TR",
    "name:und_x_variant":[
        "K\u00f6rkuyu",
        "Domuz\u00e7ukuru"
    ],
    "wof:name":"Korkuyu",
    "wof:placetype":"locality"
},
  "geometry": {"coordinates":[35.37635,37.56229],"type":"Point"}
}