{
  "type": "Feature",
  "properties": {
    "gn:admin1_code":"71",
    "gn:asciiname":"Kabakli Mahallesi",
    "gn:country_code":"TR",
    "gn:dem":1154,
    "gn:feature_class":"P",
    "gn:feature_code":"PPL",
    "gn:name":"Kabakl\u0131 Mahallesi",
    "gn:population":0,
    "gn:timezone":"Europe/Istanbul",
    "iso:country":"TR",
    "name:und_x_variant":[
        "Hatipk\u00f6y",
        "Hatip",
        "Kabakl\u0131 Mahallesi"
    ],
    "wof:name":"Kabakli Mahallesi",
    "wof:placetype":"locality"
},
  "geometry": {"coordinates":[31.65646,38.87172],"type":"Point"}
}