{
  "type": "Feature",
  "properties": {
    "gn:admin1_code":"57.0",
    "gn:asciiname":"Kuzveren",
    "gn:country_code":"TR",
    "gn:dem":417,
    "gn:feature_class":"P",
    "gn:feature_code":"PPL",
    "gn:name":"Kuzveren",
    "gn:population":0,
    "gn:timezone":"Europe/Istanbul",
    "iso:country":"TR",
    "name:tur_x_preferred":[
        "Kuzveren"
    ],
    "name:und_x_variant":[
        "G\u00f6z\u00f6ren"
    ],
    "wof:name":"Kuzveren",
    "wof:placetype":"locality"
},
  "geometry": {"coordinates":[34.8168,41.44107],"type":"Point"}
}