{
  "type": "Feature",
  "properties": {
    "gn:admin1_code":"43",
    "gn:asciiname":"Findikkoy",
    "gn:country_code":"TR",
    "gn:dem":967,
    "gn:feature_class":"P",
    "gn:feature_code":"PPL",
    "gn:name":"F\u0131nd\u0131kk\u00f6y",
    "gn:population":0,
    "gn:timezone":"Europe/Istanbul",
    "iso:country":"TR",
    "name:tur_x_preferred":[
        "F\u0131nd\u0131kk\u00f6y"
    ],
    "name:und_x_variant":[
        "F\u0131nd\u0131k"
    ],
    "wof:name":"Findikkoy",
    "wof:placetype":"locality"
},
  "geometry": {"coordinates":[30.2122,39.56424000000001],"type":"Point"}
}