{
  "type": "Feature",
  "properties": {
    "gn:admin1_code":"19.0",
    "gn:asciiname":"Ibrahimkoy",
    "gn:country_code":"TR",
    "gn:dem":991,
    "gn:feature_class":"P",
    "gn:feature_code":"PPL",
    "gn:name":"\u0130brahimk\u00f6y",
    "gn:population":0,
    "gn:timezone":"Europe/Istanbul",
    "iso:country":"TR",
    "name:tur_x_preferred":[
        "\u0130brahim"
    ],
    "name:und_x_variant":[
        "\u0130brahim",
        "\u0130brahimk\u00f6y\u00fc",
        "\u0130brahimk\u00f6y"
    ],
    "wof:name":"Ibrahimkoy",
    "wof:placetype":"locality"
},
  "geometry": {"coordinates":[34.81104000000001,40.21698],"type":"Point"}
}