{
  "type": "Feature",
  "properties": {
    "gn:admin1_code":"10",
    "gn:asciiname":"Kizilcukur",
    "gn:country_code":"TR",
    "gn:dem":721,
    "gn:feature_class":"P",
    "gn:feature_code":"PPL",
    "gn:name":"K\u0131z\u0131l\u00e7ukur",
    "gn:population":0,
    "gn:timezone":"Europe/Istanbul",
    "iso:country":"TR",
    "name:tur_x_preferred":[
        "K\u0131z\u0131l\u00e7ukur"
    ],
    "wof:name":"Kizilcukur",
    "wof:placetype":"locality"
},
  "geometry": {"coordinates":[28.38929000000001,39.38069],"type":"Point"}
}