{
  "type": "Feature",
  "properties": {
    "gn:admin1_code":"69.0",
    "gn:asciiname":"Cambasi",
    "gn:country_code":"TR",
    "gn:dem":1736,
    "gn:feature_class":"P",
    "gn:feature_code":"PPL",
    "gn:name":"\u00c7amba\u015f\u0131",
    "gn:population":0,
    "gn:timezone":"Europe/Istanbul",
    "iso:country":"TR",
    "name:und_x_variant":[
        "H\u0131nz\u0131r\u0131",
        "\u00c7amba\u015f\u0131"
    ],
    "wof:name":"Cambasi",
    "wof:placetype":"locality"
},
  "geometry": {"coordinates":[39.33384,40.06026],"type":"Point"}
}