{
  "type": "Feature",
  "properties": {
    "gn:admin1_code":"45",
    "gn:asciiname":"Harmandali",
    "gn:country_code":"TR",
    "gn:dem":93,
    "gn:feature_class":"P",
    "gn:feature_code":"PPL",
    "gn:name":"Harmandal\u0131",
    "gn:population":0,
    "gn:timezone":"Europe/Istanbul",
    "iso:country":"TR",
    "wof:name":"Harmandali",
    "wof:placetype":"locality"
},
  "geometry": {"coordinates":[27.68333,38.83333],"type":"Point"}
}