{
  "type": "Feature",
  "properties": {
    "gn:admin1_code":"45",
    "gn:asciiname":"Tepe Eynihan",
    "gn:country_code":"TR",
    "gn:dem":1073,
    "gn:feature_class":"P",
    "gn:feature_code":"PPL",
    "gn:name":"Tepe Eynihan",
    "gn:population":0,
    "gn:timezone":"Europe/Istanbul",
    "iso:country":"TR",
    "name:tur_x_preferred":[
        "Tepe Eynihan"
    ],
    "name:und_x_variant":[
        "Tepeeynihan"
    ],
    "wof:name":"Tepe Eynihan",
    "wof:placetype":"locality"
},
  "geometry": {"coordinates":[28.94083,38.91417],"type":"Point"}
}