{
  "type": "Feature",
  "properties": {
    "gn:admin1_code":"5.0",
    "gn:asciiname":"Ilicakoy",
    "gn:country_code":"TR",
    "gn:dem":315,
    "gn:feature_class":"P",
    "gn:feature_code":"PPL",
    "gn:name":"Il\u0131cak\u00f6y",
    "gn:population":0,
    "gn:timezone":"Europe/Istanbul",
    "iso:country":"TR",
    "name:tur_x_preferred":[
        "Il\u0131cak\u00f6y"
    ],
    "name:tur_x_variant":[
        "Il\u0131ca"
    ],
    "wof:name":"Ilicakoy",
    "wof:placetype":"locality"
},
  "geometry": {"coordinates":[36.1497,40.74788],"type":"Point"}
}