{
  "type": "Feature",
  "properties": {
    "gn:admin1_code":"62",
    "gn:asciiname":"Kaymanas",
    "gn:country_code":"TR",
    "gn:dem":1571,
    "gn:feature_class":"P",
    "gn:feature_code":"PPL",
    "gn:name":"Kaymanas",
    "gn:population":0,
    "gn:timezone":"Europe/Istanbul",
    "iso:country":"TR",
    "wof:name":"Kaymanas",
    "wof:placetype":"locality"
},
  "geometry": {"coordinates":[39.88333,39.45],"type":"Point"}
}