{
  "type": "Feature",
  "properties": {
    "gn:country":"TR",
    "gn:fcode":"PPLA2",
    "gn:pop":7194,
    "iso:country":"TR",
    "name:deu_x_preferred":[
        "\u00d6merli"
    ],
    "name:eng_x_preferred":[
        "\u00d6merli"
    ],
    "name:fra_x_preferred":[
        "\u00d6merli"
    ],
    "name:nld_x_preferred":[
        "\u00d6merli"
    ],
    "name:tur_x_preferred":[
        "\u00d6merli"
    ],
    "name:unk_x_variant":[
        "Maserti"
    ],
    "name:vie_x_preferred":[
        "\u00d6merli"
    ],
    "qs:name":"\u00d6merli",
    "qs:photos_9r":0,
    "qs:photos_sr":0,
    "qs:pop_sr":"5",
    "wd:wordcount":65,
    "wof:name":"\u00d6merli",
    "wof:placetype":"locality",
    "wof:population":7194
},
  "geometry": {"coordinates":[40.95409,37.40222],"type":"Point"}
}