{
  "type": "Feature",
  "properties": {
    "gn:admin1_code":"31.0",
    "gn:asciiname":"Asi",
    "gn:country_code":"TR",
    "gn:dem":74,
    "gn:feature_class":"P",
    "gn:feature_code":"PPL",
    "gn:name":"Asi",
    "gn:population":0,
    "gn:timezone":"Europe/Istanbul",
    "iso:country":"TR",
    "name:tur_x_preferred":[
        "Asi"
    ],
    "wof:name":"Asi",
    "wof:placetype":"locality"
},
  "geometry": {"coordinates":[36.05901,36.09595],"type":"Point"}
}