{
  "type": "Feature",
  "properties": {
    "gn:admin1_code":"11.0",
    "gn:asciiname":"Koprucek",
    "gn:country_code":"TR",
    "gn:dem":306,
    "gn:feature_class":"P",
    "gn:feature_code":"PPL",
    "gn:name":"K\u00f6pr\u00fccek",
    "gn:population":0,
    "gn:timezone":"Europe/Istanbul",
    "iso:country":"TR",
    "name:und_x_variant":[
        "K\u00f6pr\u00fcce",
        "K\u00f6pr\u00fcre",
        "K\u00f6pr\u00fccek"
    ],
    "wof:name":"Koprucek",
    "wof:placetype":"locality"
},
  "geometry": {"coordinates":[30.3684,40.3781],"type":"Point"}
}