{
  "type": "Feature",
  "properties": {
    "gn:admin1_code":"73",
    "gn:asciiname":"Emirler",
    "gn:country_code":"TR",
    "gn:dem":1431,
    "gn:feature_class":"P",
    "gn:feature_code":"PPL",
    "gn:name":"Emirler",
    "gn:population":0,
    "gn:timezone":"Europe/Istanbul",
    "iso:country":"TR",
    "wof:name":"Emirler",
    "wof:placetype":"locality"
},
  "geometry": {"coordinates":[34.50331,37.48627000000001],"type":"Point"}
}