{
  "type": "Feature",
  "properties": {
    "gn:admin1_code":"37.0",
    "gn:asciiname":"Uzuncam",
    "gn:country_code":"TR",
    "gn:dem":710,
    "gn:feature_class":"P",
    "gn:feature_code":"PPL",
    "gn:name":"Uzun\u00e7am",
    "gn:population":0,
    "gn:timezone":"Europe/Istanbul",
    "iso:country":"TR",
    "name:und_x_variant":[
        "Uzun\u00e7am",
        "Demirci"
    ],
    "wof:name":"Uzuncam",
    "wof:placetype":"locality"
},
  "geometry": {"coordinates":[33.08436,41.60248],"type":"Point"}
}