{
  "type": "Feature",
  "properties": {
    "gn:admin1_code":"04",
    "gn:asciiname":"Kokpinar",
    "gn:country_code":"TR",
    "gn:dem":2193,
    "gn:feature_class":"P",
    "gn:feature_code":"PPL",
    "gn:name":"K\u00f6kp\u0131nar",
    "gn:population":0,
    "gn:timezone":"Europe/Istanbul",
    "iso:country":"TR",
    "name:tur_x_preferred":[
        "K\u00f6kp\u0131nar"
    ],
    "wof:name":"Kokpinar",
    "wof:placetype":"locality"
},
  "geometry": {"coordinates":[42.81036,39.97181],"type":"Point"}
}