{
  "type": "Feature",
  "properties": {
    "gn:admin1_code":"19.0",
    "gn:asciiname":"Copluavutmus",
    "gn:country_code":"TR",
    "gn:dem":998,
    "gn:feature_class":"P",
    "gn:feature_code":"PPL",
    "gn:name":"\u00c7\u00f6pl\u00fcavutmu\u015f",
    "gn:population":0,
    "gn:timezone":"Europe/Istanbul",
    "iso:country":"TR",
    "name:tur_x_preferred":[
        "\u00c7\u00f6pl\u00fcavutmu\u015f"
    ],
    "name:tur_x_variant":[
        "Avutmu\u015f"
    ],
    "wof:name":"Copluavutmus",
    "wof:placetype":"locality"
},
  "geometry": {"coordinates":[35.03025,40.17724000000001],"type":"Point"}
}