{
  "type": "Feature",
  "properties": {
    "gn:admin1_code":"44.0",
    "gn:asciiname":"Duztarla",
    "gn:country_code":"TR",
    "gn:dem":710,
    "gn:feature_class":"P",
    "gn:feature_code":"PPL",
    "gn:name":"D\u00fcztarla",
    "gn:population":0,
    "gn:timezone":"Europe/Istanbul",
    "iso:country":"TR",
    "name:tur_x_preferred":[
        "D\u00fcztarla"
    ],
    "wof:name":"Duztarla",
    "wof:placetype":"locality"
},
  "geometry": {"coordinates":[38.75417,38.41559],"type":"Point"}
}