{
  "type": "Feature",
  "properties": {
    "gn:admin1_code":"19.0",
    "gn:asciiname":"Sihlar",
    "gn:country_code":"TR",
    "gn:dem":1573,
    "gn:feature_class":"P",
    "gn:feature_code":"PPL",
    "gn:name":"\u015e\u0131hlar",
    "gn:population":0,
    "gn:timezone":"Europe/Istanbul",
    "iso:country":"TR",
    "wof:name":"Sihlar",
    "wof:placetype":"locality"
},
  "geometry": {"coordinates":[34.37811,41.27931],"type":"Point"}
}