{
  "type": "Feature",
  "properties": {
    "gn:admin1_code":"35",
    "gn:asciiname":"Alabas",
    "gn:country_code":"TR",
    "gn:dem":96,
    "gn:feature_class":"P",
    "gn:feature_code":"PPL",
    "gn:name":"Alaba\u015f",
    "gn:population":0,
    "gn:timezone":"Europe/Istanbul",
    "iso:country":"TR",
    "name:tur_x_preferred":[
        "Alaba\u015f"
    ],
    "wof:name":"Alabas",
    "wof:placetype":"locality"
},
  "geometry": {"coordinates":[27.85638,38.19257],"type":"Point"}
}