{
  "type": "Feature",
  "properties": {
    "gn:admin1_code":"14",
    "gn:asciiname":"Alicoren",
    "gn:country_code":"TR",
    "gn:dem":711,
    "gn:feature_class":"P",
    "gn:feature_code":"PPL",
    "gn:name":"Al\u0131\u00e7\u00f6ren",
    "gn:population":0,
    "gn:timezone":"Europe/Istanbul",
    "iso:country":"TR",
    "name:und_x_variant":[
        "Al\u0131\u00e7\u00f6ren"
    ],
    "wof:name":"Alicoren",
    "wof:placetype":"locality"
},
  "geometry": {"coordinates":[31.76073,40.76614],"type":"Point"}
}