{
  "type": "Feature",
  "properties": {
    "gn:admin1_code":"78",
    "gn:asciiname":"Daga",
    "gn:country_code":"TR",
    "gn:dem":1433,
    "gn:feature_class":"P",
    "gn:feature_code":"PPL",
    "gn:name":"Da\u011fa",
    "gn:population":0,
    "gn:timezone":"Europe/Istanbul",
    "iso:country":"TR",
    "name:ceb_x_preferred":[
        "Daga"
    ],
    "name:fra_x_preferred":[
        "Daga"
    ],
    "name:ita_x_preferred":[
        "Daga"
    ],
    "name:swe_x_preferred":[
        "Daga"
    ],
    "name:tgl_x_preferred":[
        "Daga"
    ],
    "name:tur_x_preferred":[
        "Da\u011fa"
    ],
    "wof:name":"Daga",
    "wof:placetype":"locality"
},
  "geometry": {"coordinates":[33.43333,37.01667],"type":"Point"}
}