{
  "type": "Feature",
  "properties": {
    "gn:admin1_code":"39",
    "gn:asciiname":"Azizbaba",
    "gn:country_code":"TR",
    "gn:dem":88,
    "gn:feature_class":"P",
    "gn:feature_code":"PPL",
    "gn:name":"Azizbaba",
    "gn:population":0,
    "gn:timezone":"Europe/Istanbul",
    "iso:country":"TR",
    "name:tur_x_preferred":[
        "Azizbaba"
    ],
    "wof:name":"Azizbaba",
    "wof:placetype":"locality"
},
  "geometry": {"coordinates":[26.92079,41.61609],"type":"Point"}
}