{
  "type": "Feature",
  "properties": {
    "gn:admin1_code":"41.0",
    "gn:asciiname":"Kayalar",
    "gn:country_code":"TR",
    "gn:dem":299,
    "gn:feature_class":"P",
    "gn:feature_code":"PPL",
    "gn:name":"Kayalar",
    "gn:population":0,
    "gn:timezone":"Europe/Istanbul",
    "iso:country":"TR",
    "name:tur_x_preferred":[
        "Kayalar"
    ],
    "wof:name":"Kayalar",
    "wof:placetype":"locality"
},
  "geometry": {"coordinates":[29.86141,40.86769],"type":"Point"}
}