{
  "type": "Feature",
  "properties": {
    "gn:admin1_code":"49.0",
    "gn:asciiname":"Gultepe",
    "gn:country_code":"TR",
    "gn:dem":1783,
    "gn:feature_class":"P",
    "gn:feature_code":"PPL",
    "gn:name":"G\u00fcltepe",
    "gn:population":0,
    "gn:timezone":"Europe/Istanbul",
    "iso:country":"TR",
    "name:tur_x_preferred":[
        "G\u00fcltepe"
    ],
    "wof:name":"Gultepe",
    "wof:placetype":"locality"
},
  "geometry": {"coordinates":[42.38262,39.33302],"type":"Point"}
}