{
  "type": "Feature",
  "properties": {
    "gn:admin1_code":"11.0",
    "gn:asciiname":"Dereyoruk",
    "gn:country_code":"TR",
    "gn:dem":232,
    "gn:feature_class":"P",
    "gn:feature_code":"PPL",
    "gn:name":"Derey\u00f6r\u00fck",
    "gn:population":0,
    "gn:timezone":"Europe/Istanbul",
    "iso:country":"TR",
    "name:und_x_variant":[
        "Derey\u00f6r\u00fck",
        "Derey\u00fcr\u00fck"
    ],
    "wof:name":"Dereyoruk",
    "wof:placetype":"locality"
},
  "geometry": {"coordinates":[29.85639,40.31528],"type":"Point"}
}