{
  "type": "Feature",
  "properties": {
    "gn:admin1_code":"45",
    "gn:asciiname":"Temrek",
    "gn:country_code":"TR",
    "gn:dem":296,
    "gn:feature_class":"P",
    "gn:feature_code":"PPL",
    "gn:name":"Temrek",
    "gn:population":0,
    "gn:timezone":"Europe/Istanbul",
    "iso:country":"TR",
    "name:tur_x_preferred":[
        "Temrek"
    ],
    "wof:name":"Temrek",
    "wof:placetype":"locality"
},
  "geometry": {"coordinates":[27.73189,38.60955],"type":"Point"}
}