{
  "type": "Feature",
  "properties": {
    "gn:admin1_code":"60.0",
    "gn:asciiname":"Gebeli",
    "gn:country_code":"TR",
    "gn:dem":898,
    "gn:feature_class":"P",
    "gn:feature_code":"PPL",
    "gn:name":"Gebeli",
    "gn:population":0,
    "gn:timezone":"Europe/Istanbul",
    "iso:country":"TR",
    "wof:name":"Gebeli",
    "wof:placetype":"locality"
},
  "geometry": {"coordinates":[37.28209,40.28911],"type":"Point"}
}