{
  "type": "Feature",
  "properties": {
    "gn:admin1_code":"79.0",
    "gn:asciiname":"Kalekisla",
    "gn:country_code":"TR",
    "gn:dem":945,
    "gn:feature_class":"P",
    "gn:feature_code":"PPL",
    "gn:name":"Kalek\u0131\u015fla",
    "gn:population":0,
    "gn:timezone":"Europe/Istanbul",
    "iso:country":"TR",
    "wof:name":"Kalekisla",
    "wof:placetype":"locality"
},
  "geometry": {"coordinates":[33.80945,40.12985],"type":"Point"}
}