{
  "type": "Feature",
  "properties": {
    "gn:admin1_code":"23",
    "gn:asciiname":"Beydere",
    "gn:country_code":"TR",
    "gn:dem":1655,
    "gn:feature_class":"P",
    "gn:feature_code":"PPL",
    "gn:name":"Beydere",
    "gn:population":0,
    "gn:timezone":"Europe/Istanbul",
    "iso:country":"TR",
    "wof:name":"Beydere",
    "wof:placetype":"locality"
},
  "geometry": {"coordinates":[40.06667,39.06667],"type":"Point"}
}