{
  "type": "Feature",
  "properties": {
    "gn:admin1_code":"10",
    "gn:asciiname":"Coruk",
    "gn:country_code":"TR",
    "gn:dem":10,
    "gn:feature_class":"P",
    "gn:feature_code":"PPL",
    "gn:name":"\u00c7oruk",
    "gn:population":0,
    "gn:timezone":"Europe/Istanbul",
    "iso:country":"TR",
    "name:tur_x_preferred":[
        "\u00c7oruk"
    ],
    "wof:name":"Coruk",
    "wof:placetype":"locality"
},
  "geometry": {"coordinates":[26.98528,39.53345],"type":"Point"}
}