{
  "type": "Feature",
  "properties": {
    "gn:admin1_code":"68",
    "gn:asciiname":"Demirayak",
    "gn:country_code":"TR",
    "gn:dem":1091,
    "gn:feature_class":"P",
    "gn:feature_code":"PPL",
    "gn:name":"Demirayak",
    "gn:population":0,
    "gn:timezone":"Europe/Istanbul",
    "iso:country":"TR",
    "name:und_x_variant":[
        "K\u00fcrt\u00fc"
    ],
    "wof:name":"Demirayak",
    "wof:placetype":"locality"
},
  "geometry": {"coordinates":[33.69718,39.04989000000001],"type":"Point"}
}