{
  "type": "Feature",
  "properties": {
    "gn:admin1_code":"60.0",
    "gn:asciiname":"Ogulcuk",
    "gn:country_code":"TR",
    "gn:dem":700,
    "gn:feature_class":"P",
    "gn:feature_code":"PPL",
    "gn:name":"O\u011fulcuk",
    "gn:population":0,
    "gn:timezone":"Europe/Istanbul",
    "iso:country":"TR",
    "name:eng_x_preferred":[
        "O\u011fulcuk"
    ],
    "name:rus_x_preferred":[
        "\u0412\u0430\u0432\u0440\u0443"
    ],
    "name:und_x_variant":[
        "Vavri",
        "O\u011fulcak",
        "Kemalpa\u015fa"
    ],
    "wof:name":"Ogulcuk",
    "wof:placetype":"locality"
},
  "geometry": {"coordinates":[36.50768,40.36441],"type":"Point"}
}