{
  "type": "Feature",
  "properties": {
    "gn:country":"TR",
    "gn:fcode":"PPL",
    "gn:population":14811,
    "iso:country":"TR",
    "name:azb_x_preferred":[
        "\u0628\u0648\u0644\u062f\u0627\u0646"
    ],
    "name:ceb_x_preferred":[
        "Buldan \u0130l\u00e7esi"
    ],
    "name:deu_x_preferred":[
        "Buldan"
    ],
    "name:diq_x_preferred":[
        "Buldan"
    ],
    "name:ell_x_preferred":[
        "\u039c\u03c0\u03bf\u03c5\u03bb\u03bd\u03c4\u03ac\u03bd"
    ],
    "name:eng_x_preferred":[
        "Buldan"
    ],
    "name:epo_x_preferred":[
        "Buldan"
    ],
    "name:fas_x_preferred":[
        "\u0628\u0648\u0644\u062f\u0627\u0646"
    ],
    "name:fra_x_preferred":[
        "Buldan"
    ],
    "name:ita_x_preferred":[
        "Distretto di Buldan"
    ],
    "name:lit_x_preferred":[
        "Buldanas"
    ],
    "name:mrj_x_preferred":[
        "\u0411\u0443\u043b\u0434\u0430\u043d"
    ],
    "name:msa_x_preferred":[
        "Buldan"
    ],
    "name:nan_x_preferred":[
        "Buldan"
    ],
    "name:nld_x_preferred":[
        "Buldan"
    ],
    "name:nno_x_preferred":[
        "Buldan"
    ],
    "name:nob_x_preferred":[
        "Buldan"
    ],
    "name:pnb_x_preferred":[
        "\u0636\u0644\u0639 \u0628\u0644\u062f\u0646"
    ],
    "name:swa_x_preferred":[
        "Buldan"
    ],
    "name:swe_x_preferred":[
        "Buldan"
    ],
    "name:tur_x_preferred":[
        "Buldan"
    ],
    "name:und_x_variant":[
        "Boldan"
    ],
    "name:urd_x_preferred":[
        "\u0628\u0648\u0644\u062f\u0627\u0646"
    ],
    "name:vie_x_preferred":[
        "Buldan"
    ],
    "name:zho_x_preferred":[
        "\u5e03\u723e\u4e39"
    ],
    "qs:name":"Buldan",
    "qs:name_adm0":"Turkey",
    "qs:name_adm1":"Denizli",
    "qs:photos_9k":1,
    "qs:photos_9r":1,
    "qs:photos_all":3,
    "qs:photos_sr":0,
    "qs:placetype":"Town",
    "qs:pop_sr":"6",
    "wd:wordcount":613,
    "wof:name":"Buldan",
    "wof:placetype":"locality",
    "wof:population":14811
},
  "geometry": {"coordinates":[28.83056,38.045],"type":"Point"}
}