{
  "type": "Feature",
  "properties": {
    "gn:admin1_code":"33",
    "gn:asciiname":"Eyupler",
    "gn:country_code":"TR",
    "gn:dem":960,
    "gn:feature_class":"P",
    "gn:feature_code":"PPL",
    "gn:name":"Ey\u00fcpler",
    "gn:population":0,
    "gn:timezone":"Europe/Istanbul",
    "iso:country":"TR",
    "wof:name":"Eyupler",
    "wof:placetype":"locality"
},
  "geometry": {"coordinates":[30.86795,37.77098],"type":"Point"}
}