{
  "type": "Feature",
  "properties": {
    "gn:admin1_code":"04",
    "gn:asciiname":"Suvar",
    "gn:country_code":"TR",
    "gn:dem":1680,
    "gn:feature_class":"P",
    "gn:feature_code":"PPL",
    "gn:name":"Suvar",
    "gn:population":0,
    "gn:timezone":"Europe/Istanbul",
    "iso:country":"TR",
    "name:tur_x_preferred":[
        "Suvar"
    ],
    "wof:name":"Suvar",
    "wof:placetype":"locality"
},
  "geometry": {"coordinates":[42.76007,39.59228],"type":"Point"}
}