{
  "type": "Feature",
  "properties": {
    "gn:country":"TR",
    "gn:fcode":"PPL",
    "gn:pop":107,
    "iso:country":"TR",
    "name:unk_x_variant":[
        "Hemedanfevk\u00e2ni"
    ],
    "qs:name":"Yukar\u0131 Hemedan",
    "qs:photos_9r":0,
    "qs:photos_sr":0,
    "qs:pop_sr":"1",
    "wof:name":"Yukar\u0131 Hemedan",
    "wof:placetype":"locality",
    "wof:population":107
},
  "geometry": {"coordinates":[38.67389,36.97778],"type":"Point"}
}