{
  "type": "Feature",
  "properties": {
    "gn:admin1_code":"48",
    "gn:asciiname":"Kumluova",
    "gn:country_code":"TR",
    "gn:dem":12,
    "gn:feature_class":"P",
    "gn:feature_code":"PPL",
    "gn:name":"Kumluova",
    "gn:population":0,
    "gn:timezone":"Europe/Istanbul",
    "iso:country":"TR",
    "name:tur_x_preferred":[
        "Kumluova"
    ],
    "wof:name":"Kumluova",
    "wof:placetype":"locality"
},
  "geometry": {"coordinates":[29.30383,36.33509],"type":"Point"}
}