{
  "type": "Feature",
  "properties": {
    "gn:admin1_code":"70",
    "gn:asciiname":"Oguzlar",
    "gn:country_code":"TR",
    "gn:dem":1083,
    "gn:feature_class":"P",
    "gn:feature_code":"PPL",
    "gn:name":"O\u011fuzlar",
    "gn:population":0,
    "gn:timezone":"Europe/Istanbul",
    "iso:country":"TR",
    "name:tur_x_preferred":[
        "O\u011fuzlar"
    ],
    "name:und_x_variant":[
        "\u00c7emikurci",
        "Olgunlar",
        "\u00c7emiku"
    ],
    "wof:name":"Oguzlar",
    "wof:placetype":"locality"
},
  "geometry": {"coordinates":[43.5177,37.47407000000001],"type":"Point"}
}