{
  "type": "Feature",
  "properties": {
    "gn:admin1_code":"87",
    "gn:asciiname":"Furunca",
    "gn:country_code":"TR",
    "gn:dem":398,
    "gn:feature_class":"P",
    "gn:feature_code":"PPL",
    "gn:name":"Furunca",
    "gn:population":0,
    "gn:timezone":"Europe/Istanbul",
    "iso:country":"TR",
    "wof:name":"Furunca",
    "wof:placetype":"locality"
},
  "geometry": {"coordinates":[32.53348,41.45969],"type":"Point"}
}