{
  "type": "Feature",
  "properties": {
    "gn:admin1_code":"31",
    "gn:asciiname":"Akbez",
    "gn:country_code":"TR",
    "gn:dem":624,
    "gn:feature_class":"P",
    "gn:feature_code":"PPL",
    "gn:name":"Akbez",
    "gn:population":0,
    "gn:timezone":"Europe/Istanbul",
    "iso:country":"TR",
    "name:fas_x_preferred":[
        "\u0622\u06a9\u0628\u0632"
    ],
    "name:gag_x_preferred":[
        "Akbez"
    ],
    "name:nno_x_preferred":[
        "Akbez"
    ],
    "name:sco_x_preferred":[
        "Akbez"
    ],
    "name:tur_x_preferred":[
        "Salmanu\u015fa\u011f\u0131"
    ],
    "name:tur_x_variant":[
        "Akbez",
        "Akbezsalman U\u015fa\u011f\u0131",
        "Akbaz"
    ],
    "name:urd_x_preferred":[
        "\u0627\u06a9\u0628\u0632"
    ],
    "name:vie_x_preferred":[
        "Akbez"
    ],
    "name:zho_x_preferred":[
        "\u963f\u514b\u8c9d\u8332"
    ],
    "wof:name":"Akbez",
    "wof:placetype":"locality"
},
  "geometry": {"coordinates":[36.51788,36.85551],"type":"Point"}
}