{
  "type": "Feature",
  "properties": {
    "gn:admin1_code":"31",
    "gn:asciiname":"Akbez",
    "gn:country_code":"TR",
    "gn:dem":624,
    "gn:feature_class":"P",
    "gn:feature_code":"PPL",
    "gn:name":"Akbez",
    "gn:population":0,
    "gn:timezone":"Europe/Istanbul",
    "iso:country":"TR",
    "name:tur_x_preferred":[
        "Salmanu\u015fa\u011f\u0131"
    ],
    "name:tur_x_variant":[
        "Akbez",
        "Akbezsalman U\u015fa\u011f\u0131",
        "Akbaz"
    ],
    "wof:name":"Akbez",
    "wof:placetype":"locality"
},
  "geometry": {"coordinates":[36.51788,36.85551],"type":"Point"}
}