{
  "type": "Feature",
  "properties": {
    "gn:admin1_code":"64",
    "gn:asciiname":"Yeni",
    "gn:country_code":"TR",
    "gn:dem":547,
    "gn:feature_class":"P",
    "gn:feature_code":"PPL",
    "gn:name":"Yeni",
    "gn:population":0,
    "gn:timezone":"Europe/Istanbul",
    "iso:country":"TR",
    "name:tur_x_preferred":[
        "Yeni"
    ],
    "wof:name":"Yeni",
    "wof:placetype":"locality"
},
  "geometry": {"coordinates":[29.07316,38.65427],"type":"Point"}
}