{
  "type": "Feature",
  "properties": {
    "gn:admin1_code":"25",
    "gn:asciiname":"Akkavak",
    "gn:country_code":"TR",
    "gn:dem":1686,
    "gn:feature_class":"P",
    "gn:feature_code":"PPL",
    "gn:name":"Akkavak",
    "gn:population":0,
    "gn:timezone":"Europe/Istanbul",
    "iso:country":"TR",
    "name:und_x_variant":[
        "\u00c7a\u00e7ko"
    ],
    "wof:name":"Akkavak",
    "wof:placetype":"locality"
},
  "geometry": {"coordinates":[41.99837,39.27806],"type":"Point"}
}