{
  "type": "Feature",
  "properties": {
    "gn:admin1_code":"63",
    "gn:asciiname":"Pasmakli",
    "gn:country_code":"TR",
    "gn:dem":530,
    "gn:feature_class":"P",
    "gn:feature_code":"PPL",
    "gn:name":"Pa\u015fmakl\u0131",
    "gn:population":0,
    "gn:timezone":"Europe/Istanbul",
    "iso:country":"TR",
    "name:tur_x_preferred":[
        "Pa\u015fmakl\u0131"
    ],
    "wof:name":"Pasmakli",
    "wof:placetype":"locality"
},
  "geometry": {"coordinates":[39.65,37.11667],"type":"Point"}
}