{
  "type": "Feature",
  "properties": {
    "gn:admin1_code":"03",
    "gn:asciiname":"Karapinar",
    "gn:cc2":"TR",
    "gn:country_code":"TR",
    "gn:dem":1246,
    "gn:feature_class":"P",
    "gn:feature_code":"PPL",
    "gn:name":"Karap\u0131nar",
    "gn:population":0,
    "gn:timezone":"Europe/Istanbul",
    "iso:country":"TR",
    "name:und_x_variant":[
        "Karap\u0131nart\u00fcrkmen",
        "Karap\u0131nar"
    ],
    "wof:name":"Karapinar",
    "wof:placetype":"locality"
},
  "geometry": {"coordinates":[31.42806,38.70278],"type":"Point"}
}