{
  "type": "Feature",
  "properties": {
    "gn:admin1_code":"54",
    "gn:asciiname":"Epceler",
    "gn:country_code":"TR",
    "gn:dem":251,
    "gn:feature_class":"P",
    "gn:feature_code":"PPL",
    "gn:name":"Ep\u00e7eler",
    "gn:population":0,
    "gn:timezone":"Europe/Istanbul",
    "iso:country":"TR",
    "name:tur_x_preferred":[
        "Ep\u00e7eler"
    ],
    "wof:name":"Epceler",
    "wof:placetype":"locality"
},
  "geometry": {"coordinates":[30.31778,40.5413],"type":"Point"}
}