{
  "type": "Feature",
  "properties": {
    "gn:admin1_code":"24",
    "gn:asciiname":"Saraycik",
    "gn:country_code":"TR",
    "gn:dem":1551,
    "gn:feature_class":"P",
    "gn:feature_code":"PPL",
    "gn:name":"Sarayc\u0131k",
    "gn:population":0,
    "gn:timezone":"Europe/Istanbul",
    "iso:country":"TR",
    "name:tur_x_preferred":[
        "Sarayc\u0131k"
    ],
    "wof:name":"Saraycik",
    "wof:placetype":"locality"
},
  "geometry": {"coordinates":[40.08586,39.77609],"type":"Point"}
}