{
  "type": "Feature",
  "properties": {
    "gn:admin1_code":"52.0",
    "gn:asciiname":"Kutluca",
    "gn:country_code":"TR",
    "gn:dem":235,
    "gn:feature_class":"P",
    "gn:feature_code":"PPL",
    "gn:name":"Kutluca",
    "gn:population":0,
    "gn:timezone":"Europe/Istanbul",
    "iso:country":"TR",
    "name:tur_x_preferred":[
        "Kutluca"
    ],
    "name:und_x_variant":[
        "Kurtluca"
    ],
    "wof:name":"Kutluca",
    "wof:placetype":"locality"
},
  "geometry": {"coordinates":[37.03333,41.06667],"type":"Point"}
}