{
  "type": "Feature",
  "properties": {
    "gn:admin1_code":"17.0",
    "gn:asciiname":"Hacipehlivan",
    "gn:cc2":"TR",
    "gn:country_code":"TR",
    "gn:dem":98,
    "gn:feature_class":"P",
    "gn:feature_code":"PPL",
    "gn:name":"Hac\u0131pehlivan",
    "gn:population":0,
    "gn:timezone":"Europe/Istanbul",
    "iso:country":"TR",
    "name:und_x_variant":[
        "Filibeliler",
        "Hac\u0131pehlivan"
    ],
    "wof:name":"Hacipehlivan",
    "wof:placetype":"locality"
},
  "geometry": {"coordinates":[27.41333,40.24944],"type":"Point"}
}