{
  "type": "Feature",
  "properties": {
    "gn:admin1_code":"83",
    "gn:asciiname":"Emirler",
    "gn:country_code":"TR",
    "gn:dem":564,
    "gn:feature_class":"P",
    "gn:feature_code":"PPL",
    "gn:name":"Emirler",
    "gn:population":0,
    "gn:timezone":"Europe/Istanbul",
    "iso:country":"TR",
    "name:tur_x_preferred":[
        "Emirler"
    ],
    "wof:name":"Emirler",
    "wof:placetype":"locality"
},
  "geometry": {"coordinates":[36.94675,37.28901],"type":"Point"}
}