{
  "type": "Feature",
  "properties": {
    "gn:country":"TR",
    "gn:fcode":"PPL",
    "gn:population":71063,
    "iso:country":"TR",
    "name:ara_x_preferred":[
        "\u0643\u064a\u0645\u0644\u064a\u0643"
    ],
    "name:ast_x_preferred":[
        "Gemlik"
    ],
    "name:bul_x_preferred":[
        "\u0413\u0435\u043c\u043b\u0438\u043a"
    ],
    "name:cat_x_preferred":[
        "Gemlik"
    ],
    "name:ceb_x_preferred":[
        "Gemlik"
    ],
    "name:che_x_preferred":[
        "\u0413\u0435\u043c\u043b\u0438\u043a"
    ],
    "name:deu_x_preferred":[
        "Gemlik"
    ],
    "name:diq_x_preferred":[
        "Gemlik"
    ],
    "name:ell_x_preferred":[
        "\u0393\u03ba\u03b5\u03bc\u03bb\u03af\u03ba"
    ],
    "name:eng_x_preferred":[
        "Gemlik"
    ],
    "name:fas_x_preferred":[
        "\u06af\u0645\u0644\u06cc\u06a9"
    ],
    "name:fra_x_preferred":[
        "Gemlik"
    ],
    "name:hun_x_preferred":[
        "Gemlik"
    ],
    "name:ind_x_preferred":[
        "Gemlik"
    ],
    "name:ita_x_preferred":[
        "Gemlik"
    ],
    "name:jpn_x_preferred":[
        "\u30b2\u30e0\u30ea\u30af\u6e7e"
    ],
    "name:lit_x_preferred":[
        "Gemlikas"
    ],
    "name:min_x_preferred":[
        "Gemlik"
    ],
    "name:mrj_x_preferred":[
        "\u0413\u0435\u043c\u043b\u0438\u043a"
    ],
    "name:msa_x_preferred":[
        "Gemlik"
    ],
    "name:nan_x_preferred":[
        "Gemlik"
    ],
    "name:nld_x_preferred":[
        "Gemlik"
    ],
    "name:nob_x_preferred":[
        "Gemlik"
    ],
    "name:pnb_x_preferred":[
        "\u0636\u0644\u0639 \u06af\u0645\u0644\u06a9"
    ],
    "name:pol_x_preferred":[
        "Gemlik"
    ],
    "name:ron_x_preferred":[
        "Gemlik"
    ],
    "name:rus_x_preferred":[
        "\u0413\u0435\u043c\u043b\u0438\u043a"
    ],
    "name:spa_x_preferred":[
        "Gemlik"
    ],
    "name:srp_x_preferred":[
        "\u0413\u0435\u043b\u0438\u043a"
    ],
    "name:swa_x_preferred":[
        "Gemlik"
    ],
    "name:swe_x_preferred":[
        "Gemlik"
    ],
    "name:tat_x_preferred":[
        "\u0413\u0435\u043c\u043b\u0438\u043a"
    ],
    "name:tur_x_preferred":[
        "Gemlik"
    ],
    "name:und_x_variant":[
        "Kios"
    ],
    "name:urd_x_preferred":[
        "\u06af\u0645\u0644\u06cc\u06a9"
    ],
    "name:vie_x_preferred":[
        "Gemlik"
    ],
    "name:yor_x_preferred":[
        "Gemlik"
    ],
    "name:zho_x_preferred":[
        "\u84cb\u59c6\u5229\u514b"
    ],
    "qs:name":"Gemlik",
    "qs:photos_9r":0,
    "qs:photos_sr":0,
    "qs:pop_sr":"8",
    "wd:wordcount":442,
    "wof:name":"Gemlik",
    "wof:placetype":"locality",
    "wof:population":71063
},
  "geometry": {"coordinates":[29.15969,40.43094],"type":"Point"}
}