{
  "type": "Feature",
  "properties": {
    "gn:country":"TR",
    "gn:fcode":"PPL",
    "gn:pop":71063,
    "iso:country":"TR",
    "name:deu_x_preferred":[
        "Gemlik"
    ],
    "name:eng_x_preferred":[
        "Gemlik"
    ],
    "name:nld_x_preferred":[
        "Gemlik"
    ],
    "name:pol_x_preferred":[
        "Gemlik"
    ],
    "name:rus_x_preferred":[
        "\u0413\u0435\u043c\u043b\u0438\u043a"
    ],
    "name:swe_x_preferred":[
        "Gemlik"
    ],
    "name:tur_x_preferred":[
        "Gemlik"
    ],
    "name:unk_x_variant":[
        "Kios"
    ],
    "qs:name":"Gemlik",
    "qs:photos_9r":0,
    "qs:photos_sr":0,
    "qs:pop_sr":"8",
    "wd:wordcount":442,
    "wof:name":"Gemlik",
    "wof:placetype":"locality",
    "wof:population":71063
},
  "geometry": {"coordinates":[29.15969,40.43094],"type":"Point"}
}