{
  "type": "Feature",
  "properties": {
    "gn:admin1_code":"81.0",
    "gn:asciiname":"Narlioren",
    "gn:country_code":"TR",
    "gn:dem":184,
    "gn:feature_class":"P",
    "gn:feature_code":"PPL",
    "gn:name":"Narl\u0131\u00f6ren",
    "gn:population":0,
    "gn:timezone":"Europe/Istanbul",
    "iso:country":"TR",
    "wof:name":"Narlioren",
    "wof:placetype":"locality"
},
  "geometry": {"coordinates":[35.67795,37.40663],"type":"Point"}
}