{
  "type": "Feature",
  "properties": {
    "gn:admin1_code":"35",
    "gn:asciiname":"Gokceyurt",
    "gn:country_code":"TR",
    "gn:dem":246,
    "gn:feature_class":"P",
    "gn:feature_code":"PPL",
    "gn:name":"G\u00f6k\u00e7eyurt",
    "gn:population":0,
    "gn:timezone":"Europe/Istanbul",
    "iso:country":"TR",
    "name:tur_x_preferred":[
        "G\u00f6k\u00e7eyurt"
    ],
    "wof:name":"Gokceyurt",
    "wof:placetype":"locality"
},
  "geometry": {"coordinates":[27.6853,38.43408],"type":"Point"}
}