{
  "type": "Feature",
  "properties": {
    "gn:admin1_code":"90.0",
    "gn:asciiname":"Ugurtepe",
    "gn:country_code":"TR",
    "gn:dem":749,
    "gn:feature_class":"P",
    "gn:feature_code":"PPL",
    "gn:name":"U\u011furtepe",
    "gn:population":0,
    "gn:timezone":"Europe/Istanbul",
    "iso:country":"TR",
    "name:tur_x_preferred":[
        "U\u011furtepe"
    ],
    "name:und_x_variant":[
        "Khyrchoglu",
        "H\u0131r\u00e7o\u011flu"
    ],
    "wof:name":"Ugurtepe",
    "wof:placetype":"locality"
},
  "geometry": {"coordinates":[36.97451,36.92676],"type":"Point"}
}