{
  "type": "Feature",
  "properties": {
    "gn:admin1_code":"21",
    "gn:asciiname":"Gommetas",
    "gn:country_code":"TR",
    "gn:dem":789,
    "gn:feature_class":"P",
    "gn:feature_code":"PPL",
    "gn:name":"G\u00f6mmeta\u015f",
    "gn:population":0,
    "gn:timezone":"Europe/Istanbul",
    "iso:country":"TR",
    "name:tur_x_preferred":[
        "G\u00f6mmeta\u015f"
    ],
    "name:und_x_variant":[
        "Sirimi"
    ],
    "wof:name":"Gommetas",
    "wof:placetype":"locality"
},
  "geometry": {"coordinates":[40.04699,37.89296],"type":"Point"}
}