{
  "type": "Feature",
  "properties": {
    "gn:admin1_code":"60",
    "gn:asciiname":"Ihsaniye",
    "gn:country_code":"TR",
    "gn:dem":1241,
    "gn:feature_class":"P",
    "gn:feature_code":"PPL",
    "gn:name":"\u0130hsaniye",
    "gn:population":0,
    "gn:timezone":"Europe/Istanbul",
    "iso:country":"TR",
    "wof:name":"Ihsaniye",
    "wof:placetype":"locality"
},
  "geometry": {"coordinates":[36.50218,40.00356],"type":"Point"}
}