{
  "type": "Feature",
  "properties": {
    "gn:admin1_code":"03",
    "gn:asciiname":"Capali",
    "gn:country_code":"TR",
    "gn:dem":1088,
    "gn:feature_class":"P",
    "gn:feature_code":"PPL",
    "gn:name":"\u00c7apal\u0131",
    "gn:population":0,
    "gn:timezone":"Europe/Istanbul",
    "iso:country":"TR",
    "name:fas_x_preferred":[
        "\u0686\u0627\u067e\u0627\u0644\u06cc"
    ],
    "name:msa_x_preferred":[
        "\u00c7apal\u0131"
    ],
    "name:tur_x_preferred":[
        "\u00c7apal\u0131"
    ],
    "name:vie_x_preferred":[
        "\u00c7apal\u0131"
    ],
    "wof:name":"Capali",
    "wof:placetype":"locality"
},
  "geometry": {"coordinates":[30.30861,38.05667],"type":"Point"}
}