{
  "type": "Feature",
  "properties": {
    "gn:admin1_code":"58.0",
    "gn:asciiname":"Asagi Sarica",
    "gn:country_code":"TR",
    "gn:dem":917,
    "gn:feature_class":"P",
    "gn:feature_code":"PPL",
    "gn:name":"A\u015fa\u011f\u0131 Sar\u0131ca",
    "gn:population":0,
    "gn:timezone":"Europe/Istanbul",
    "iso:country":"TR",
    "name:tur_x_preferred":[
        "A\u015fa\u011f\u0131 Sar\u0131ca"
    ],
    "name:und_x_variant":[
        "A\u015fa\u011f\u0131sar\u0131ca"
    ],
    "wof:name":"Asagi Sarica",
    "wof:placetype":"locality"
},
  "geometry": {"coordinates":[38.13152,40.15753],"type":"Point"}
}