{
  "type": "Feature",
  "properties": {
    "gn:admin1_code":"8.0",
    "gn:asciiname":"Meydancik",
    "gn:country_code":"TR",
    "gn:dem":1474,
    "gn:feature_class":"P",
    "gn:feature_code":"PPLA3",
    "gn:name":"Meydanc\u0131k",
    "gn:population":0,
    "gn:timezone":"Europe/Istanbul",
    "iso:country":"TR",
    "name:und_x_variant":[
        "\u0130merhav",
        "Meydanc\u0131k"
    ],
    "wof:name":"Meydancik",
    "wof:placetype":"locality"
},
  "geometry": {"coordinates":[42.2364,41.40964],"type":"Point"}
}