{
  "type": "Feature",
  "properties": {
    "gn:admin1_code":"64",
    "gn:asciiname":"Hirdirlar",
    "gn:country_code":"TR",
    "gn:dem":854,
    "gn:feature_class":"P",
    "gn:feature_code":"PPL",
    "gn:name":"H\u0131rd\u0131rlar",
    "gn:population":0,
    "gn:timezone":"Europe/Istanbul",
    "iso:country":"TR",
    "name:tur_x_preferred":[
        "H\u0131rd\u0131rlar"
    ],
    "wof:name":"Hirdirlar",
    "wof:placetype":"locality"
},
  "geometry": {"coordinates":[29.27278,38.73817],"type":"Point"}
}