{
  "type": "Feature",
  "properties": {
    "gn:admin1_code":"45",
    "gn:asciiname":"Belenyaka",
    "gn:country_code":"TR",
    "gn:dem":256,
    "gn:feature_class":"P",
    "gn:feature_code":"PPL",
    "gn:name":"Belenyaka",
    "gn:population":0,
    "gn:timezone":"Europe/Istanbul",
    "iso:country":"TR",
    "name:und_x_variant":[
        "Karsala",
        "Belenyaka"
    ],
    "wof:name":"Belenyaka",
    "wof:placetype":"locality"
},
  "geometry": {"coordinates":[28.57195,38.29781],"type":"Point"}
}