{
  "type": "Feature",
  "properties": {
    "gn:country":"TR",
    "gn:fcode":"PPL",
    "gn:pop":339,
    "iso:country":"TR",
    "name:cat_x_preferred":[
        "Ba\u015fa\u011fa\u00e7"
    ],
    "name:ceb_x_preferred":[
        "Ba\u015fa\u011fa\u00e7"
    ],
    "name:ces_x_preferred":[
        "Ba\u015fa\u011fa\u00e7"
    ],
    "name:dan_x_preferred":[
        "Ba\u015fa\u011fa\u00e7"
    ],
    "name:deu_x_preferred":[
        "Ba\u015fa\u011fa\u00e7"
    ],
    "name:eng_x_preferred":[
        "Ba\u015fa\u011fa\u00e7"
    ],
    "name:eus_x_preferred":[
        "Ba\u015fa\u011fa\u00e7"
    ],
    "name:fin_x_preferred":[
        "Ba\u015fa\u011fa\u00e7"
    ],
    "name:fra_x_preferred":[
        "Ba\u015fa\u011fa\u00e7"
    ],
    "name:glg_x_preferred":[
        "Ba\u015fa\u011fa\u00e7"
    ],
    "name:ind_x_preferred":[
        "Ba\u015fa\u011fa\u00e7"
    ],
    "name:ita_x_preferred":[
        "Ba\u015fa\u011fa\u00e7"
    ],
    "name:kur_x_preferred":[
        "Si\u00e7yan"
    ],
    "name:nld_x_preferred":[
        "Ba\u015fa\u011fa\u00e7"
    ],
    "name:nno_x_preferred":[
        "Ba\u015fa\u011fa\u00e7"
    ],
    "name:nob_x_preferred":[
        "Ba\u015fa\u011fa\u00e7"
    ],
    "name:oci_x_preferred":[
        "Ba\u015fa\u011fa\u00e7"
    ],
    "name:pol_x_preferred":[
        "Ba\u015fa\u011fa\u00e7"
    ],
    "name:por_x_preferred":[
        "Ba\u015fa\u011fa\u00e7"
    ],
    "name:ron_x_preferred":[
        "Ba\u015fa\u011fa\u00e7"
    ],
    "name:sco_x_preferred":[
        "Ba\u015fa\u011fa\u00e7"
    ],
    "name:slk_x_preferred":[
        "Ba\u015fa\u011fa\u00e7"
    ],
    "name:slv_x_preferred":[
        "Ba\u015fa\u011fa\u00e7"
    ],
    "name:spa_x_preferred":[
        "Ba\u015fa\u011fa\u00e7"
    ],
    "name:swe_x_preferred":[
        "Ba\u015fa\u011fa\u00e7"
    ],
    "name:tgl_x_preferred":[
        "Ba\u015fa\u011fa\u00e7"
    ],
    "name:tur_x_preferred":[
        "Ba\u015fa\u011fa\u00e7"
    ],
    "name:unk_x_variant":[
        "Si\u00e7van"
    ],
    "name:vie_x_preferred":[
        "Ba\u015fa\u011fa\u00e7"
    ],
    "name:war_x_preferred":[
        "Ba\u015fa\u011fa\u00e7"
    ],
    "qs:name":"Sichvan",
    "qs:photos_9r":0,
    "qs:photos_sr":0,
    "qs:pop_sr":"2",
    "wof:name":"Sichvan",
    "wof:placetype":"locality",
    "wof:population":339
},
  "geometry": {"coordinates":[41.01194,37.61972],"type":"Point"}
}