{
  "type": "Feature",
  "properties": {
    "gn:admin1_code":"55.0",
    "gn:asciiname":"Kokluk",
    "gn:country_code":"TR",
    "gn:dem":15,
    "gn:feature_class":"P",
    "gn:feature_code":"PPL",
    "gn:name":"K\u00f6kl\u00fck",
    "gn:population":0,
    "gn:timezone":"Europe/Istanbul",
    "iso:country":"TR",
    "wof:name":"Kokluk",
    "wof:placetype":"locality"
},
  "geometry": {"coordinates":[36.70415,41.25657],"type":"Point"}
}