{
  "type": "Feature",
  "properties": {
    "gn:admin1_code":"87.0",
    "gn:asciiname":"Adile",
    "gn:country_code":"TR",
    "gn:dem":380,
    "gn:feature_class":"P",
    "gn:feature_code":"PPL",
    "gn:name":"Adile",
    "gn:population":0,
    "gn:timezone":"Europe/Istanbul",
    "iso:country":"TR",
    "name:und_x_variant":[
        "\u00d6ren",
        "Adile"
    ],
    "wof:name":"Adile",
    "wof:placetype":"locality"
},
  "geometry": {"coordinates":[32.63755,41.55281],"type":"Point"}
}