{
  "type": "Feature",
  "properties": {
    "gn:admin1_code":"64",
    "gn:asciiname":"Coguplu",
    "gn:country_code":"TR",
    "gn:dem":834,
    "gn:feature_class":"P",
    "gn:feature_code":"PPL",
    "gn:name":"\u00c7o\u011fuplu",
    "gn:population":0,
    "gn:timezone":"Europe/Istanbul",
    "iso:country":"TR",
    "wof:name":"Coguplu",
    "wof:placetype":"locality"
},
  "geometry": {"coordinates":[29.57639,38.395],"type":"Point"}
}