{
  "type": "Feature",
  "properties": {
    "gn:admin1_code":"80.0",
    "gn:asciiname":"Nizir",
    "gn:country_code":"TR",
    "gn:dem":1082,
    "gn:feature_class":"P",
    "gn:feature_code":"PPL",
    "gn:name":"Nizir",
    "gn:population":0,
    "gn:timezone":"Europe/Istanbul",
    "iso:country":"TR",
    "name:tur_x_preferred":[
        "Nizir"
    ],
    "wof:name":"Nizir",
    "wof:placetype":"locality"
},
  "geometry": {"coordinates":[42.79826,37.47604000000001],"type":"Point"}
}