{
  "type": "Feature",
  "properties": {
    "gn:admin1_code":"2.0",
    "gn:asciiname":"Dibevler",
    "gn:country_code":"TR",
    "gn:dem":1214,
    "gn:feature_class":"P",
    "gn:feature_code":"PPL",
    "gn:name":"Dibevler",
    "gn:population":0,
    "gn:timezone":"Europe/Istanbul",
    "iso:country":"TR",
    "wof:name":"Dibevler",
    "wof:placetype":"locality"
},
  "geometry": {"coordinates":[37.74913,37.70486],"type":"Point"}
}