{
  "type": "Feature",
  "properties": {
    "gn:admin1_code":"66",
    "gn:asciiname":"Calapverdi",
    "gn:country_code":"TR",
    "gn:dem":1094,
    "gn:feature_class":"P",
    "gn:feature_code":"PPL",
    "gn:name":"\u00c7alapverdi",
    "gn:population":0,
    "gn:timezone":"Europe/Istanbul",
    "iso:country":"TR",
    "wof:name":"Calapverdi",
    "wof:placetype":"locality"
},
  "geometry": {"coordinates":[35.30536,39.2313],"type":"Point"}
}