{
  "type": "Feature",
  "properties": {
    "gn:admin1_code":"40",
    "gn:asciiname":"Yesilli",
    "gn:country_code":"TR",
    "gn:dem":1060,
    "gn:feature_class":"P",
    "gn:feature_code":"PPL",
    "gn:name":"Ye\u015filli",
    "gn:population":0,
    "gn:timezone":"Europe/Istanbul",
    "iso:country":"TR",
    "wof:name":"Yesilli",
    "wof:placetype":"locality"
},
  "geometry": {"coordinates":[33.88333,39.13333],"type":"Point"}
}