{
  "type": "Feature",
  "properties": {
    "gn:admin1_code":"07",
    "gn:asciiname":"Ispatli",
    "gn:country_code":"TR",
    "gn:dem":69,
    "gn:feature_class":"P",
    "gn:feature_code":"PPL",
    "gn:name":"\u0130spatl\u0131",
    "gn:population":0,
    "gn:timezone":"Europe/Istanbul",
    "iso:country":"TR",
    "name:und_x_variant":[
        "\u0130sbatl\u0131",
        "\u0130spatl\u0131"
    ],
    "wof:name":"Ispatli",
    "wof:placetype":"locality"
},
  "geometry": {"coordinates":[32.17460999999999,36.44054000000001],"type":"Point"}
}