{
  "type": "Feature",
  "properties": {
    "gn:admin1_code":"65",
    "gn:asciiname":"Lissek",
    "gn:country_code":"TR",
    "gn:dem":2553,
    "gn:feature_class":"P",
    "gn:feature_code":"PPL",
    "gn:name":"Lissek",
    "gn:population":0,
    "gn:timezone":"Europe/Istanbul",
    "iso:country":"TR",
    "wof:name":"Lissek",
    "wof:placetype":"locality"
},
  "geometry": {"coordinates":[44.28333,37.78333],"type":"Point"}
}