{
  "type": "Feature",
  "properties": {
    "gn:admin1_code":"12",
    "gn:asciiname":"Eknik",
    "gn:country_code":"TR",
    "gn:dem":1784,
    "gn:feature_class":"P",
    "gn:feature_code":"PPL",
    "gn:name":"Eknik",
    "gn:population":0,
    "gn:timezone":"Europe/Istanbul",
    "iso:country":"TR",
    "name:und_x_variant":[
        "E\u011fnik"
    ],
    "wof:name":"Eknik",
    "wof:placetype":"locality"
},
  "geometry": {"coordinates":[40.76667,39.11667],"type":"Point"}
}