{
  "type": "Feature",
  "properties": {
    "gn:admin1_code":"14.0",
    "gn:asciiname":"Kocumlar",
    "gn:country_code":"TR",
    "gn:dem":1380,
    "gn:feature_class":"P",
    "gn:feature_code":"PPL",
    "gn:name":"Ko\u00e7umlar",
    "gn:population":0,
    "gn:timezone":"Europe/Istanbul",
    "iso:country":"TR",
    "wof:name":"Kocumlar",
    "wof:placetype":"locality"
},
  "geometry": {"coordinates":[32.24703,40.81203],"type":"Point"}
}