{
  "type": "Feature",
  "properties": {
    "gn:admin1_code":"74",
    "gn:asciiname":"Tinis",
    "gn:country_code":"TR",
    "gn:dem":2271,
    "gn:feature_class":"P",
    "gn:feature_code":"PPL",
    "gn:name":"Tinis",
    "gn:population":0,
    "gn:timezone":"Europe/Istanbul",
    "iso:country":"TR",
    "wof:name":"Tinis",
    "wof:placetype":"locality"
},
  "geometry": {"coordinates":[42.7275,37.98361],"type":"Point"}
}