{
  "type": "Feature",
  "properties": {
    "gn:admin1_code":"19.0",
    "gn:asciiname":"Dorukbekis",
    "gn:country_code":"TR",
    "gn:dem":1156,
    "gn:feature_class":"P",
    "gn:feature_code":"PPL",
    "gn:name":"Dorukbeki\u1e63",
    "gn:population":0,
    "gn:timezone":"Europe/Istanbul",
    "iso:country":"TR",
    "name:tur_x_preferred":[
        "Dorukbeki\u1e63"
    ],
    "name:und_x_variant":[
        "K\u00fc\u00e7\u00fck Beki\u015f"
    ],
    "wof:name":"Dorukbekis",
    "wof:placetype":"locality"
},
  "geometry": {"coordinates":[35.11903,40.5131],"type":"Point"}
}