{
  "type": "Feature",
  "properties": {
    "gn:admin1_code":"23",
    "gn:asciiname":"Sun",
    "gn:country_code":"TR",
    "gn:dem":1180,
    "gn:feature_class":"P",
    "gn:feature_code":"PPL",
    "gn:name":"Sun",
    "gn:population":0,
    "gn:timezone":"Europe/Istanbul",
    "iso:country":"TR",
    "name:und_x_variant":[
        "S\u00fcnk\u00f6y"
    ],
    "wof:name":"Sun",
    "wof:placetype":"locality"
},
  "geometry": {"coordinates":[38.99139,38.67241],"type":"Point"}
}