{
  "type": "Feature",
  "properties": {
    "gn:admin1_code":"07",
    "gn:asciiname":"Kizilagac",
    "gn:country_code":"TR",
    "gn:dem":314,
    "gn:feature_class":"P",
    "gn:feature_code":"PPL",
    "gn:name":"K\u0131z\u0131la\u011fa\u00e7",
    "gn:population":0,
    "gn:timezone":"Europe/Istanbul",
    "iso:country":"TR",
    "name:und_x_variant":[
        "K\u0131z\u0131la\u011fa\u00e7",
        "S\u00fcvecik"
    ],
    "wof:name":"Kizilagac",
    "wof:placetype":"locality"
},
  "geometry": {"coordinates":[29.69664,36.32576],"type":"Point"}
}