{
  "type": "Feature",
  "properties": {
    "gn:admin1_code":"40",
    "gn:asciiname":"Alisar",
    "gn:country_code":"TR",
    "gn:dem":1279,
    "gn:feature_class":"P",
    "gn:feature_code":"PPL",
    "gn:name":"Ali\u015far",
    "gn:population":0,
    "gn:timezone":"Europe/Istanbul",
    "iso:country":"TR",
    "wof:name":"Alisar",
    "wof:placetype":"locality"
},
  "geometry": {"coordinates":[34.06599,39.43953],"type":"Point"}
}