{
  "type": "Feature",
  "properties": {
    "gn:admin1_code":"61.0",
    "gn:asciiname":"Ozbirlik",
    "gn:country_code":"TR",
    "gn:dem":884,
    "gn:feature_class":"P",
    "gn:feature_code":"PPL",
    "gn:name":"\u00d6zbirlik",
    "gn:population":0,
    "gn:timezone":"Europe/Istanbul",
    "iso:country":"TR",
    "name:tur_x_preferred":[
        "\u00d6zbirlik"
    ],
    "wof:name":"Ozbirlik",
    "wof:placetype":"locality"
},
  "geometry": {"coordinates":[39.73475,40.86039],"type":"Point"}
}