{
  "type": "Feature",
  "properties": {
    "gn:admin1_code":"28.0",
    "gn:asciiname":"Boyluca",
    "gn:country_code":"TR",
    "gn:dem":1769,
    "gn:feature_class":"P",
    "gn:feature_code":"PPL",
    "gn:name":"Boyluca",
    "gn:population":0,
    "gn:timezone":"Europe/Istanbul",
    "iso:country":"TR",
    "name:und_x_variant":[
        "Zunk\u00f6y\u00fc",
        "Zumk\u00f6y",
        "Zun",
        "Zunk\u00f6y",
        "Boyluca"
    ],
    "wof:name":"Boyluca",
    "wof:placetype":"locality"
},
  "geometry": {"coordinates":[38.90339,40.36932],"type":"Point"}
}