{
  "type": "Feature",
  "properties": {
    "gn:admin1_code":"12",
    "gn:asciiname":"Masgan",
    "gn:country_code":"TR",
    "gn:dem":1671,
    "gn:feature_class":"P",
    "gn:feature_code":"PPL",
    "gn:name":"Masgan",
    "gn:population":0,
    "gn:timezone":"Europe/Istanbul",
    "iso:country":"TR",
    "name:und_x_variant":[
        "Mask\u00e2nik\u00e2rir",
        "Masgan",
        "Masik\u00e2uk\u00e2rir",
        "Mask\u00e2n",
        "Yakar\u0131mendelli"
    ],
    "wof:name":"Masgan",
    "wof:placetype":"locality"
},
  "geometry": {"coordinates":[40.64106,39.19383],"type":"Point"}
}