{
  "type": "Feature",
  "properties": {
    "gn:admin1_code":"09",
    "gn:asciiname":"Hisarcik",
    "gn:country_code":"TR",
    "gn:dem":636,
    "gn:feature_class":"P",
    "gn:feature_code":"PPL",
    "gn:name":"Hisarc\u0131k",
    "gn:population":0,
    "gn:timezone":"Europe/Istanbul",
    "iso:country":"TR",
    "name:tur_x_preferred":[
        "Hisarc\u0131k"
    ],
    "wof:name":"Hisarcik",
    "wof:placetype":"locality"
},
  "geometry": {"coordinates":[28.37054,38.03872],"type":"Point"}
}