{
  "type": "Feature",
  "properties": {
    "gn:admin1_code":"55",
    "gn:asciiname":"Baskoy",
    "gn:country_code":"TR",
    "gn:dem":668,
    "gn:feature_class":"P",
    "gn:feature_code":"PPL",
    "gn:name":"Ba\u015fk\u00f6y",
    "gn:population":0,
    "gn:timezone":"Europe/Istanbul",
    "iso:country":"TR",
    "wof:name":"Baskoy",
    "wof:placetype":"locality"
},
  "geometry": {"coordinates":[36.39762,41.17192],"type":"Point"}
}