{
  "type": "Feature",
  "properties": {
    "gn:admin1_code":"49.0",
    "gn:asciiname":"Gelirli",
    "gn:country_code":"TR",
    "gn:dem":1303,
    "gn:feature_class":"P",
    "gn:feature_code":"PPL",
    "gn:name":"Gelirli",
    "gn:population":0,
    "gn:timezone":"Europe/Istanbul",
    "iso:country":"TR",
    "name:tur_x_preferred":[
        "Gelirli"
    ],
    "wof:name":"Gelirli",
    "wof:placetype":"locality"
},
  "geometry": {"coordinates":[41.76448,38.74152],"type":"Point"}
}