{
  "type": "Feature",
  "properties": {
    "gn:admin1_code":"25",
    "gn:asciiname":"Kavurmacukuru",
    "gn:cc2":"TR",
    "gn:country_code":"TR",
    "gn:dem":2167,
    "gn:feature_class":"P",
    "gn:feature_code":"PPL",
    "gn:name":"Kavurma\u00e7ukuru",
    "gn:population":0,
    "gn:timezone":"Europe/Istanbul",
    "iso:country":"TR",
    "name:und_x_variant":[
        "Kavurma\u00e7ukuru K\u00f6y\u00fc"
    ],
    "wof:name":"Kavurmacukuru",
    "wof:placetype":"locality"
},
  "geometry": {"coordinates":[40.86667,39.78333],"type":"Point"}
}