{
  "type": "Feature",
  "properties": {
    "gn:admin1_code":"23",
    "gn:asciiname":"Hoh",
    "gn:country_code":"TR",
    "gn:dem":1160,
    "gn:feature_class":"P",
    "gn:feature_code":"PPL",
    "gn:name":"Hoh",
    "gn:population":0,
    "gn:timezone":"Europe/Istanbul",
    "iso:country":"TR",
    "name:und_x_variant":[
        "Yukar\u0131 Hoh",
        "Hoh",
        "Huhu\u00fclya"
    ],
    "wof:name":"Hoh",
    "wof:placetype":"locality"
},
  "geometry": {"coordinates":[39.21667,38.46667],"type":"Point"}
}