{
  "type": "Feature",
  "properties": {
    "gn:admin1_code":"33",
    "gn:asciiname":"Guruz",
    "gn:country_code":"TR",
    "gn:dem":1021,
    "gn:feature_class":"P",
    "gn:feature_code":"PPL",
    "gn:name":"G\u00fcr\u00fcz",
    "gn:population":0,
    "gn:timezone":"Europe/Istanbul",
    "iso:country":"TR",
    "wof:name":"Guruz",
    "wof:placetype":"locality"
},
  "geometry": {"coordinates":[31.19108,37.58034],"type":"Point"}
}