{
  "type": "Feature",
  "properties": {
    "gn:admin1_code":"60.0",
    "gn:asciiname":"Alibagi",
    "gn:country_code":"TR",
    "gn:dem":1139,
    "gn:feature_class":"P",
    "gn:feature_code":"PPL",
    "gn:name":"Aliba\u011f\u0131",
    "gn:population":0,
    "gn:timezone":"Europe/Istanbul",
    "iso:country":"TR",
    "name:und_x_variant":[
        "Aliba\u011f\u0131 K\u00f6y\u00fc",
        "Aliba\u011f\u0131"
    ],
    "wof:name":"Alibagi",
    "wof:placetype":"locality"
},
  "geometry": {"coordinates":[35.99177,40.1849],"type":"Point"}
}