{
  "type": "Feature",
  "properties": {
    "gn:admin1_code":"2.0",
    "gn:asciiname":"Sarisogut",
    "gn:country_code":"TR",
    "gn:dem":635,
    "gn:feature_class":"P",
    "gn:feature_code":"PPL",
    "gn:name":"Sar\u0131s\u00f6\u011f\u00fct",
    "gn:population":0,
    "gn:timezone":"Europe/Istanbul",
    "iso:country":"TR",
    "name:tur_x_preferred":[
        "Sar\u0131s\u00f6\u011f\u00fct"
    ],
    "wof:name":"Sarisogut",
    "wof:placetype":"locality"
},
  "geometry": {"coordinates":[38.74249,37.79024],"type":"Point"}
}