{
  "type": "Feature",
  "properties": {
    "gn:admin1_code":"46",
    "gn:asciiname":"Boynuyogunlu",
    "gn:country_code":"TR",
    "gn:dem":739,
    "gn:feature_class":"P",
    "gn:feature_code":"PPL",
    "gn:name":"Boynuyo\u011funlu",
    "gn:population":0,
    "gn:timezone":"Europe/Istanbul",
    "iso:country":"TR",
    "wof:name":"Boynuyogunlu",
    "wof:placetype":"locality"
},
  "geometry": {"coordinates":[36.44914,37.4379],"type":"Point"}
}