{
  "type": "Feature",
  "properties": {
    "gn:admin1_code":"03",
    "gn:asciiname":"Karamik",
    "gn:country_code":"TR",
    "gn:dem":1021,
    "gn:feature_class":"P",
    "gn:feature_code":"PPL",
    "gn:name":"Karam\u0131k",
    "gn:population":0,
    "gn:timezone":"Europe/Istanbul",
    "iso:country":"TR",
    "wof:name":"Karamik",
    "wof:placetype":"locality"
},
  "geometry": {"coordinates":[30.89419,38.46162],"type":"Point"}
}