{
  "type": "Feature",
  "properties": {
    "gn:admin1_code":"54.0",
    "gn:asciiname":"Buyuk Esence",
    "gn:country_code":"TR",
    "gn:dem":30,
    "gn:feature_class":"P",
    "gn:feature_code":"PPL",
    "gn:name":"B\u00fcy\u00fck Esence",
    "gn:population":0,
    "gn:timezone":"Europe/Istanbul",
    "iso:country":"TR",
    "name:und_x_variant":[
        "B\u00fcy\u00fcktersiye",
        "B\u00fcy\u00fck Esence"
    ],
    "wof:name":"Buyuk Esence",
    "wof:placetype":"locality"
},
  "geometry": {"coordinates":[30.47656,40.75503],"type":"Point"}
}