{
  "type": "Feature",
  "properties": {
    "gn:admin1_code":"21.0",
    "gn:asciiname":"Bozcali",
    "gn:country_code":"TR",
    "gn:dem":535,
    "gn:feature_class":"P",
    "gn:feature_code":"PPL",
    "gn:name":"Boz\u00e7al\u0131",
    "gn:population":0,
    "gn:timezone":"Europe/Istanbul",
    "iso:country":"TR",
    "name:tur_x_preferred":[
        "Boz\u00e7al\u0131"
    ],
    "name:und_x_variant":[
        "Bozdzhaly"
    ],
    "wof:name":"Bozcali",
    "wof:placetype":"locality"
},
  "geometry": {"coordinates":[40.76866,37.80618],"type":"Point"}
}