{
  "type": "Feature",
  "properties": {
    "gn:admin1_code":"86.0",
    "gn:asciiname":"Kayinli",
    "gn:country_code":"TR",
    "gn:dem":1723,
    "gn:feature_class":"P",
    "gn:feature_code":"PPL",
    "gn:name":"Kay\u0131nl\u0131",
    "gn:population":0,
    "gn:timezone":"Europe/Istanbul",
    "iso:country":"TR",
    "name:tur_x_preferred":[
        "Kay\u0131nl\u0131"
    ],
    "wof:name":"Kayinli",
    "wof:placetype":"locality"
},
  "geometry": {"coordinates":[42.7406,41.55748],"type":"Point"}
}