{
  "type": "Feature",
  "properties": {
    "gn:admin1_code":"46",
    "gn:asciiname":"Mimar Sinan",
    "gn:country_code":"TR",
    "gn:dem":726,
    "gn:feature_class":"P",
    "gn:feature_code":"PPL",
    "gn:name":"Mimar Sinan",
    "gn:population":0,
    "gn:timezone":"Europe/Istanbul",
    "iso:country":"TR",
    "name:tur_x_preferred":[
        "Mimar Sinan"
    ],
    "wof:name":"Mimar Sinan",
    "wof:placetype":"locality"
},
  "geometry": {"coordinates":[36.68966,37.69091],"type":"Point"}
}