{
  "type": "Feature",
  "properties": {
    "gn:admin1_code":"93",
    "gn:asciiname":"Kirikdere",
    "gn:country_code":"TR",
    "gn:dem":412,
    "gn:feature_class":"P",
    "gn:feature_code":"PPL",
    "gn:name":"K\u0131r\u0131kdere",
    "gn:population":0,
    "gn:timezone":"Europe/Istanbul",
    "iso:country":"TR",
    "wof:name":"Kirikdere",
    "wof:placetype":"locality"
},
  "geometry": {"coordinates":[31.05261,40.91433],"type":"Point"}
}