{
  "type": "Feature",
  "properties": {
    "gn:admin1_code":"33",
    "gn:asciiname":"Kozlucay",
    "gn:country_code":"TR",
    "gn:dem":1173,
    "gn:feature_class":"P",
    "gn:feature_code":"PPL",
    "gn:name":"Kozlu\u00e7ay",
    "gn:population":0,
    "gn:timezone":"Europe/Istanbul",
    "iso:country":"TR",
    "name:und_x_variant":[
        "Kozlu\u00e7ay",
        "Gelegermi"
    ],
    "wof:name":"Kozlucay",
    "wof:placetype":"locality"
},
  "geometry": {"coordinates":[31.29538,38.20296],"type":"Point"}
}