{
  "type": "Feature",
  "properties": {
    "gn:admin1_code":"80",
    "gn:asciiname":"Narlidere",
    "gn:country_code":"TR",
    "gn:dem":797,
    "gn:feature_class":"P",
    "gn:feature_code":"PPL",
    "gn:name":"Narl\u0131dere",
    "gn:population":0,
    "gn:timezone":"Europe/Istanbul",
    "iso:country":"TR",
    "name:rus_x_preferred":[
        "Bel\u2019dzhunan"
    ],
    "name:rus_x_variant":[
        "\u0411\u0438\u0442\u043b\u0438\u0441"
    ],
    "name:und_x_variant":[
        "Belcunan",
        "Narl\u0131dere"
    ],
    "wof:name":"Narlidere",
    "wof:placetype":"locality"
},
  "geometry": {"coordinates":[41.99744000000001,37.62788],"type":"Point"}
}