{
  "type": "Feature",
  "properties": {
    "gn:admin1_code":"58",
    "gn:asciiname":"Pirhuseyin",
    "gn:country_code":"TR",
    "gn:dem":1566,
    "gn:feature_class":"P",
    "gn:feature_code":"PPL",
    "gn:name":"Pirh\u00fcseyin",
    "gn:population":0,
    "gn:timezone":"Europe/Istanbul",
    "iso:country":"TR",
    "name:tur_x_preferred":[
        "Pirh\u00fcseyin"
    ],
    "wof:name":"Pirhuseyin",
    "wof:placetype":"locality"
},
  "geometry": {"coordinates":[37.62494,39.65745],"type":"Point"}
}