{
  "type": "Feature",
  "properties": {
    "gn:admin1_code":"52.0",
    "gn:asciiname":"Haskoy",
    "gn:country_code":"TR",
    "gn:dem":306,
    "gn:feature_class":"P",
    "gn:feature_code":"PPL",
    "gn:name":"Hask\u00f6y",
    "gn:population":0,
    "gn:timezone":"Europe/Istanbul",
    "iso:country":"TR",
    "wof:name":"Haskoy",
    "wof:placetype":"locality"
},
  "geometry": {"coordinates":[38.06571,40.95076],"type":"Point"}
}