{
  "type": "Feature",
  "properties": {
    "gn:admin1_code":"45",
    "gn:asciiname":"Caglayan",
    "gn:country_code":"TR",
    "gn:dem":413,
    "gn:feature_class":"P",
    "gn:feature_code":"PPL",
    "gn:name":"\u00c7a\u011flayan",
    "gn:population":0,
    "gn:timezone":"Europe/Istanbul",
    "iso:country":"TR",
    "name:tur_x_preferred":[
        "\u00c7a\u011flayan"
    ],
    "name:tur_x_variant":[
        "K\u0131z\u0131llar"
    ],
    "wof:name":"Caglayan",
    "wof:placetype":"locality"
},
  "geometry": {"coordinates":[28.07015,38.78713],"type":"Point"}
}