{
  "type": "Feature",
  "properties": {
    "gn:admin1_code":"82.0",
    "gn:asciiname":"Bozcaarmut",
    "gn:country_code":"TR",
    "gn:dem":1526,
    "gn:feature_class":"P",
    "gn:feature_code":"PPL",
    "gn:name":"Bozcaarmut",
    "gn:population":0,
    "gn:timezone":"Europe/Istanbul",
    "iso:country":"TR",
    "wof:name":"Bozcaarmut",
    "wof:placetype":"locality"
},
  "geometry": {"coordinates":[32.81446,40.69443],"type":"Point"}
}