{
  "type": "Feature",
  "properties": {
    "gn:admin1_code":"71",
    "gn:asciiname":"Digrak",
    "gn:country_code":"TR",
    "gn:dem":1427,
    "gn:feature_class":"P",
    "gn:feature_code":"PPL",
    "gn:name":"D\u0131\u011frak",
    "gn:population":0,
    "gn:timezone":"Europe/Istanbul",
    "iso:country":"TR",
    "name:und_x_variant":[
        "D\u0131\u011frak",
        "Digrak"
    ],
    "wof:name":"Digrak",
    "wof:placetype":"locality"
},
  "geometry": {"coordinates":[31.77868,38.01268],"type":"Point"}
}