{
  "type": "Feature",
  "properties": {
    "gn:admin1_code":"20",
    "gn:asciiname":"Tepecik",
    "gn:country_code":"TR",
    "gn:dem":748,
    "gn:feature_class":"P",
    "gn:feature_code":"PPL",
    "gn:name":"Tepecik",
    "gn:population":0,
    "gn:timezone":"Europe/Istanbul",
    "iso:country":"TR",
    "name:tur_x_preferred":[
        "Tepecik"
    ],
    "wof:name":"Tepecik",
    "wof:placetype":"locality"
},
  "geometry": {"coordinates":[29.16582,37.1471],"type":"Point"}
}