{
  "type": "Feature",
  "properties": {
    "gn:admin1_code":"17.0",
    "gn:asciiname":"Goktepe",
    "gn:country_code":"TR",
    "gn:dem":54,
    "gn:feature_class":"P",
    "gn:feature_code":"PPL",
    "gn:name":"G\u00f6ktepe",
    "gn:population":0,
    "gn:timezone":"Europe/Istanbul",
    "iso:country":"TR",
    "name:und_x_variant":[
        "G\u00f6ktepe K\u00f6y\u00fc",
        "G\u00f6ktepe"
    ],
    "wof:name":"Goktepe",
    "wof:placetype":"locality"
},
  "geometry": {"coordinates":[27.1238,40.28522],"type":"Point"}
}