{
  "type": "Feature",
  "properties": {
    "gn:admin1_code":"12",
    "gn:asciiname":"Yoncalik",
    "gn:country_code":"TR",
    "gn:dem":1933,
    "gn:feature_class":"P",
    "gn:feature_code":"PPL",
    "gn:name":"Yoncal\u0131k",
    "gn:population":0,
    "gn:timezone":"Europe/Istanbul",
    "iso:country":"TR",
    "name:und_x_variant":[
        "Yoncal\u0131k K\u00f6y\u00fc",
        "Yoncal\u0131k"
    ],
    "wof:name":"Yoncalik",
    "wof:placetype":"locality"
},
  "geometry": {"coordinates":[41.07349,39.33859],"type":"Point"}
}