{
  "type": "Feature",
  "properties": {
    "gn:admin1_code":"55.0",
    "gn:asciiname":"Tekkekiran",
    "gn:country_code":"TR",
    "gn:dem":471,
    "gn:feature_class":"P",
    "gn:feature_code":"PPL",
    "gn:name":"Tekkek\u0131ran",
    "gn:population":0,
    "gn:timezone":"Europe/Istanbul",
    "iso:country":"TR",
    "wof:name":"Tekkekiran",
    "wof:placetype":"locality"
},
  "geometry": {"coordinates":[35.6071,41.11748],"type":"Point"}
}