{
  "type": "Feature",
  "properties": {
    "gn:admin1_code":"55.0",
    "gn:asciiname":"Akalan",
    "gn:country_code":"TR",
    "gn:dem":728,
    "gn:feature_class":"P",
    "gn:feature_code":"PPL",
    "gn:name":"Akalan",
    "gn:population":0,
    "gn:timezone":"Europe/Istanbul",
    "iso:country":"TR",
    "name:und_x_variant":[
        "A\u011falan K\u00f6y\u00fc",
        "A\u011falan",
        "Akalan"
    ],
    "wof:name":"Akalan",
    "wof:placetype":"locality"
},
  "geometry": {"coordinates":[35.70301,41.34009],"type":"Point"}
}