{
  "type": "Feature",
  "properties": {
    "gn:admin1_code":"16",
    "gn:asciiname":"Avdan",
    "gn:country_code":"TR",
    "gn:dem":872,
    "gn:feature_class":"P",
    "gn:feature_code":"PPL",
    "gn:name":"Avdan",
    "gn:population":0,
    "gn:timezone":"Europe/Istanbul",
    "iso:country":"TR",
    "name:ceb_x_preferred":[
        "Avdan"
    ],
    "name:deu_x_preferred":[
        "Avdan"
    ],
    "name:tur_x_preferred":[
        "Avdan"
    ],
    "wof:name":"Avdan",
    "wof:placetype":"locality"
},
  "geometry": {"coordinates":[29.20499,39.77879],"type":"Point"}
}