{
  "type": "Feature",
  "properties": {
    "gn:admin1_code":"35.0",
    "gn:asciiname":"Sancak",
    "gn:country_code":"TR",
    "gn:dem":413,
    "gn:feature_class":"P",
    "gn:feature_code":"PPL",
    "gn:name":"Sancak",
    "gn:population":0,
    "gn:timezone":"Europe/Istanbul",
    "iso:country":"TR",
    "name:ceb_x_preferred":[
        "Sancak"
    ],
    "name:tur_x_preferred":[
        "Sancak"
    ],
    "name:vie_x_preferred":[
        "Sancakl\u0131"
    ],
    "wof:name":"Sancak",
    "wof:placetype":"locality"
},
  "geometry": {"coordinates":[27.15517,38.51977],"type":"Point"}
}