{
  "type": "Feature",
  "properties": {
    "gn:admin1_code":"12.0",
    "gn:asciiname":"Goltepesi",
    "gn:country_code":"TR",
    "gn:dem":1606,
    "gn:feature_class":"P",
    "gn:feature_code":"PPL",
    "gn:name":"G\u00f6ltepesi",
    "gn:population":0,
    "gn:timezone":"Europe/Istanbul",
    "iso:country":"TR",
    "name:tur_x_preferred":[
        "G\u00f6ltepesi"
    ],
    "wof:name":"Goltepesi",
    "wof:placetype":"locality"
},
  "geometry": {"coordinates":[40.59216,38.95974],"type":"Point"}
}