{
  "type": "Feature",
  "properties": {
    "gn:admin1_code":"07",
    "gn:asciiname":"Araplar",
    "gn:country_code":"TR",
    "gn:dem":292,
    "gn:feature_class":"P",
    "gn:feature_code":"PPL",
    "gn:name":"Araplar",
    "gn:population":0,
    "gn:timezone":"Europe/Istanbul",
    "iso:country":"TR",
    "wof:name":"Araplar",
    "wof:placetype":"locality"
},
  "geometry": {"coordinates":[30.66667,36.98333],"type":"Point"}
}