{
  "type": "Feature",
  "properties": {
    "gn:admin1_code":"82.0",
    "gn:asciiname":"Yesilyayla",
    "gn:country_code":"TR",
    "gn:dem":1454,
    "gn:feature_class":"P",
    "gn:feature_code":"PPL",
    "gn:name":"Ye\u015filyayla",
    "gn:population":0,
    "gn:timezone":"Europe/Istanbul",
    "iso:country":"TR",
    "wof:name":"Yesilyayla",
    "wof:placetype":"locality"
},
  "geometry": {"coordinates":[34.03277,40.78124],"type":"Point"}
}