{
  "type": "Feature",
  "properties": {
    "gn:admin1_code":"68",
    "gn:asciiname":"Taspinar",
    "gn:country_code":"TR",
    "gn:dem":1205,
    "gn:feature_class":"P",
    "gn:feature_code":"PPL",
    "gn:name":"Ta\u015fp\u0131nar",
    "gn:population":0,
    "gn:timezone":"Europe/Istanbul",
    "iso:country":"TR",
    "wof:name":"Taspinar",
    "wof:placetype":"locality"
},
  "geometry": {"coordinates":[32.75767,39.82936],"type":"Point"}
}