{
  "type": "Feature",
  "properties": {
    "gn:admin1_code":"14",
    "gn:asciiname":"Hacisuleymanbey",
    "gn:country_code":"TR",
    "gn:dem":171,
    "gn:feature_class":"P",
    "gn:feature_code":"PPL",
    "gn:name":"Hac\u0131s\u00fcleymanbey",
    "gn:population":0,
    "gn:timezone":"Europe/Istanbul",
    "iso:country":"TR",
    "name:tur_x_preferred":[
        "Hac\u0131s\u00fcleymanbey"
    ],
    "wof:name":"Hacisuleymanbey",
    "wof:placetype":"locality"
},
  "geometry": {"coordinates":[30.93877,40.762],"type":"Point"}
}