{
  "type": "Feature",
  "properties": {
    "gn:admin1_code":"21.0",
    "gn:asciiname":"Malasemdi",
    "gn:country_code":"TR",
    "gn:dem":965,
    "gn:feature_class":"P",
    "gn:feature_code":"PPL",
    "gn:name":"Malasemdi",
    "gn:population":0,
    "gn:timezone":"Europe/Istanbul",
    "iso:country":"TR",
    "wof:name":"Malasemdi",
    "wof:placetype":"locality"
},
  "geometry": {"coordinates":[41.08051,38.32624000000001],"type":"Point"}
}