{
  "type": "Feature",
  "properties": {
    "gn:admin1_code":"81",
    "gn:asciiname":"Kirazliyurt",
    "gn:country_code":"TR",
    "gn:dem":1441,
    "gn:feature_class":"P",
    "gn:feature_code":"PPL",
    "gn:name":"Kirazl\u0131yurt",
    "gn:population":0,
    "gn:timezone":"Europe/Istanbul",
    "iso:country":"TR",
    "name:deu_x_preferred":[
        "Kirazl\u0131yurt"
    ],
    "name:msa_x_preferred":[
        "Kirazl\u0131yurt"
    ],
    "name:tur_x_preferred":[
        "Kirazl\u0131yurt"
    ],
    "name:vie_x_preferred":[
        "Kirazl\u0131yurt"
    ],
    "wof:name":"Kirazliyurt",
    "wof:placetype":"locality"
},
  "geometry": {"coordinates":[36.28852,38.09763],"type":"Point"}
}