{
  "type": "Feature",
  "properties": {
    "gn:admin1_code":"72",
    "gn:asciiname":"Deyirmetinan",
    "gn:country_code":"TR",
    "gn:dem":1153,
    "gn:feature_class":"P",
    "gn:feature_code":"PPL",
    "gn:name":"Deyirmetinan",
    "gn:population":0,
    "gn:timezone":"Europe/Istanbul",
    "iso:country":"TR",
    "name:tur_x_preferred":[
        "G\u00fcm\u00fc\u015fyuva"
    ],
    "name:und_x_variant":[
        "Derimetinan",
        "Dermitinan",
        "Deyirmetinan"
    ],
    "wof:name":"Deyirmetinan",
    "wof:placetype":"locality"
},
  "geometry": {"coordinates":[40.20198,37.48097],"type":"Point"}
}