{
  "type": "Feature",
  "properties": {
    "gn:admin1_code":"7.0",
    "gn:asciiname":"Ahatli",
    "gn:country_code":"TR",
    "gn:dem":405,
    "gn:feature_class":"P",
    "gn:feature_code":"PPL",
    "gn:name":"Ahatl\u0131",
    "gn:population":0,
    "gn:timezone":"Europe/Istanbul",
    "iso:country":"TR",
    "name:und_x_variant":[
        "Ahatl\u0131",
        "Aksakallar"
    ],
    "wof:name":"Ahatli",
    "wof:placetype":"locality"
},
  "geometry": {"coordinates":[29.73806,36.26583],"type":"Point"}
}