{
  "type": "Feature",
  "properties": {
    "iso:country":"TR",
    "name:ara_x_preferred":[
        "\u064a\u0646\u064a \u0643\u0648\u064a"
    ],
    "name:cat_x_preferred":[
        "Yenik\u00f6y"
    ],
    "name:ell_x_preferred":[
        "\u039d\u03b5\u03bf\u03c7\u03ce\u03c1\u03b9 \u0392\u03bf\u03c3\u03c0\u03cc\u03c1\u03bf\u03c5"
    ],
    "name:eng_x_preferred":[
        "Yenik\u00f6y of Bosporus"
    ],
    "name:fra_x_preferred":[
        "Yenik\u00f6y"
    ],
    "name:ind_x_preferred":[
        "Yenik\u00f6y"
    ],
    "name:mkd_x_preferred":[
        "\u0408\u0435\u043d\u0438\u045c\u043e\u0458"
    ],
    "name:rus_x_preferred":[
        "\u0419\u0435\u043d\u0438\u043a\u0451\u0439"
    ],
    "name:tur_x_preferred":[
        "Yenik\u00f6y"
    ],
    "name:vie_x_preferred":[
        "Yenik\u00f6y"
    ],
    "wof:name":"Yenikoy",
    "wof:placetype":"neighbourhood"
},
  "geometry": {"coordinates":[29.06298704788521,41.12416171656503],"type":"Point"}
}