{
  "type": "Feature",
  "properties": {
    "gn:admin1_code":"28.0",
    "gn:asciiname":"Bakimli",
    "gn:country_code":"TR",
    "gn:dem":339,
    "gn:feature_class":"P",
    "gn:feature_code":"PPL",
    "gn:name":"Bak\u0131ml\u0131",
    "gn:population":0,
    "gn:timezone":"Europe/Istanbul",
    "iso:country":"TR",
    "name:tur_x_preferred":[
        "Bak\u0131ml\u0131"
    ],
    "wof:name":"Bakimli",
    "wof:placetype":"locality"
},
  "geometry": {"coordinates":[38.99341,40.89607],"type":"Point"}
}