{
  "type": "Feature",
  "properties": {
    "gn:admin1_code":"07",
    "gn:asciiname":"Cukurkoy",
    "gn:country_code":"TR",
    "gn:dem":837,
    "gn:feature_class":"P",
    "gn:feature_code":"PPL",
    "gn:name":"\u00c7ukurk\u00f6y",
    "gn:population":0,
    "gn:timezone":"Europe/Istanbul",
    "iso:country":"TR",
    "name:und_x_variant":[
        "Ertese",
        "Eften",
        "\u00c7ukurk\u00f6y"
    ],
    "wof:name":"Cukurkoy",
    "wof:placetype":"locality"
},
  "geometry": {"coordinates":[31.84356,36.87107],"type":"Point"}
}