{
  "type": "Feature",
  "properties": {
    "gn:admin1_code":"38",
    "gn:asciiname":"Karakimse",
    "gn:country_code":"TR",
    "gn:dem":1157,
    "gn:feature_class":"P",
    "gn:feature_code":"PPL",
    "gn:name":"Karakimse",
    "gn:population":0,
    "gn:timezone":"Europe/Istanbul",
    "iso:country":"TR",
    "wof:name":"Karakimse",
    "wof:placetype":"locality"
},
  "geometry": {"coordinates":[35.16846,38.92439],"type":"Point"}
}