{
  "type": "Feature",
  "properties": {
    "gn:admin1_code":"79",
    "gn:asciiname":"Kucuk Ceceli",
    "gn:country_code":"TR",
    "gn:dem":1045,
    "gn:feature_class":"P",
    "gn:feature_code":"PPL",
    "gn:name":"K\u00fc\u00e7\u00fck \u00c7e\u00e7eli",
    "gn:population":0,
    "gn:timezone":"Europe/Istanbul",
    "iso:country":"TR",
    "name:und_x_variant":[
        "Cicelisa\u011fir",
        "K\u00fc\u00e7\u00fck \u00c7e\u00e7eli"
    ],
    "wof:name":"Kucuk Ceceli",
    "wof:placetype":"locality"
},
  "geometry": {"coordinates":[33.81552,39.78015],"type":"Point"}
}