{
  "type": "Feature",
  "properties": {
    "gn:admin1_code":"62.0",
    "gn:asciiname":"Ilisu",
    "gn:country_code":"TR",
    "gn:dem":1345,
    "gn:feature_class":"P",
    "gn:feature_code":"PPL",
    "gn:name":"Il\u0131su",
    "gn:population":0,
    "gn:timezone":"Europe/Istanbul",
    "iso:country":"TR",
    "wof:name":"Ilisu",
    "wof:placetype":"locality"
},
  "geometry": {"coordinates":[39.84804000000001,39.09047],"type":"Point"}
}