{
  "type": "Feature",
  "properties": {
    "gn:admin1_code":"74",
    "gn:asciiname":"Gurzua",
    "gn:cc2":"TR",
    "gn:country_code":"TR",
    "gn:dem":1635,
    "gn:feature_class":"P",
    "gn:feature_code":"PPL",
    "gn:name":"G\u00fcrz\u00fca",
    "gn:population":0,
    "gn:timezone":"Europe/Istanbul",
    "iso:country":"TR",
    "name:und_x_variant":[
        "Ayd\u0131n",
        "G\u00fcrz\u00fca",
        "G\u00fcrzava"
    ],
    "wof:name":"Gurzua",
    "wof:placetype":"locality"
},
  "geometry": {"coordinates":[42.5175,37.8975],"type":"Point"}
}