{
  "type": "Feature",
  "properties": {
    "gn:admin1_code":"83.0",
    "gn:asciiname":"Koklu",
    "gn:cc2":"TR",
    "gn:country_code":"TR",
    "gn:dem":826,
    "gn:feature_class":"P",
    "gn:feature_code":"PPL",
    "gn:name":"K\u00f6kl\u00fc",
    "gn:population":0,
    "gn:timezone":"Europe/Istanbul",
    "iso:country":"TR",
    "name:rus_x_preferred":[
        "K\u00ebklyu"
    ],
    "name:und_x_variant":[
        "K\u00f6kl\u00fc"
    ],
    "wof:name":"Koklu",
    "wof:placetype":"locality"
},
  "geometry": {"coordinates":[36.55806,36.9925],"type":"Point"}
}