{
  "type": "Feature",
  "properties": {
    "gn:admin1_code":"19.0",
    "gn:asciiname":"Asagi Sarilik",
    "gn:country_code":"TR",
    "gn:dem":701,
    "gn:feature_class":"P",
    "gn:feature_code":"PPL",
    "gn:name":"A\u015fa\u011f\u0131 Sar\u0131l\u0131k",
    "gn:population":0,
    "gn:timezone":"Europe/Istanbul",
    "iso:country":"TR",
    "wof:name":"Asagi Sarilik",
    "wof:placetype":"locality"
},
  "geometry": {"coordinates":[35.04516,40.37951],"type":"Point"}
}