{
  "type": "Feature",
  "properties": {
    "gn:admin1_code":"19.0",
    "gn:asciiname":"Kuyumcu",
    "gn:country_code":"TR",
    "gn:dem":593,
    "gn:feature_class":"P",
    "gn:feature_code":"PPL",
    "gn:name":"Kuyumcu",
    "gn:population":0,
    "gn:timezone":"Europe/Istanbul",
    "iso:country":"TR",
    "wof:name":"Kuyumcu",
    "wof:placetype":"locality"
},
  "geometry": {"coordinates":[34.83756,40.78847],"type":"Point"}
}