{
  "type": "Feature",
  "properties": {
    "gn:admin1_code":"19.0",
    "gn:asciiname":"Kiciklar",
    "gn:country_code":"TR",
    "gn:dem":1124,
    "gn:feature_class":"P",
    "gn:feature_code":"PPL",
    "gn:name":"K\u0131c\u0131klar",
    "gn:population":0,
    "gn:timezone":"Europe/Istanbul",
    "iso:country":"TR",
    "wof:name":"Kiciklar",
    "wof:placetype":"locality"
},
  "geometry": {"coordinates":[34.57272,40.86004000000001],"type":"Point"}
}