{
  "type": "Feature",
  "properties": {
    "gn:admin1_code":"58",
    "gn:asciiname":"Harmandali",
    "gn:country_code":"TR",
    "gn:dem":1688,
    "gn:feature_class":"P",
    "gn:feature_code":"PPL",
    "gn:name":"Harmandal\u0131",
    "gn:population":0,
    "gn:timezone":"Europe/Istanbul",
    "iso:country":"TR",
    "name:tur_x_preferred":[
        "Harmandal\u0131"
    ],
    "wof:name":"Harmandali",
    "wof:placetype":"locality"
},
  "geometry": {"coordinates":[36.83496,39.18608],"type":"Point"}
}