{
  "type": "Feature",
  "properties": {
    "gn:admin1_code":"43",
    "gn:asciiname":"Fincanburnu",
    "gn:country_code":"TR",
    "gn:dem":1116,
    "gn:feature_class":"P",
    "gn:feature_code":"PPL",
    "gn:name":"Fincanburnu",
    "gn:population":0,
    "gn:timezone":"Europe/Istanbul",
    "iso:country":"TR",
    "name:tur_x_preferred":[
        "Fincanburnu"
    ],
    "wof:name":"Fincanburnu",
    "wof:placetype":"locality"
},
  "geometry": {"coordinates":[30.3631,39.16463],"type":"Point"}
}