{
  "type": "Feature",
  "properties": {
    "gn:admin1_code":"74.0",
    "gn:asciiname":"Demiryako",
    "gn:cc2":"TR",
    "gn:country_code":"TR",
    "gn:dem":962,
    "gn:feature_class":"P",
    "gn:feature_code":"PPL",
    "gn:name":"Demiryako",
    "gn:population":0,
    "gn:timezone":"Europe/Istanbul",
    "iso:country":"TR",
    "name:rus_x_preferred":[
        "Demir\u2019yako"
    ],
    "wof:name":"Demiryako",
    "wof:placetype":"locality"
},
  "geometry": {"coordinates":[41.9025,37.88917],"type":"Point"}
}