{
  "type": "Feature",
  "properties": {
    "gn:admin1_code":"52",
    "gn:asciiname":"Kocaman",
    "gn:country_code":"TR",
    "gn:dem":394,
    "gn:feature_class":"P",
    "gn:feature_code":"PPL",
    "gn:name":"Kocaman",
    "gn:population":0,
    "gn:timezone":"Europe/Istanbul",
    "iso:country":"TR",
    "name:tur_x_preferred":[
        "Kocaman"
    ],
    "wof:name":"Kocaman",
    "wof:placetype":"locality"
},
  "geometry": {"coordinates":[37.5083,40.91905],"type":"Point"}
}