{
  "type": "Feature",
  "properties": {
    "gn:admin1_code":"09",
    "gn:asciiname":"Asagigorle",
    "gn:country_code":"TR",
    "gn:dem":578,
    "gn:feature_class":"P",
    "gn:feature_code":"PPL",
    "gn:name":"A\u015fa\u011f\u0131g\u00f6rle",
    "gn:population":0,
    "gn:timezone":"Europe/Istanbul",
    "iso:country":"TR",
    "name:tur_x_preferred":[
        "A\u015fa\u011f\u0131g\u00f6rle"
    ],
    "wof:name":"Asagigorle",
    "wof:placetype":"locality"
},
  "geometry": {"coordinates":[28.61919,37.55363],"type":"Point"}
}