{
  "type": "Feature",
  "properties": {
    "gn:admin1_code":"90.0",
    "gn:asciiname":"Oymali",
    "gn:country_code":"TR",
    "gn:dem":506,
    "gn:feature_class":"P",
    "gn:feature_code":"PPL",
    "gn:name":"Oymal\u0131",
    "gn:population":0,
    "gn:timezone":"Europe/Istanbul",
    "iso:country":"TR",
    "name:und_x_variant":[
        "Aynafar",
        "Aynifar",
        "Oymal\u0131"
    ],
    "wof:name":"Oymali",
    "wof:placetype":"locality"
},
  "geometry": {"coordinates":[37.3625,36.68028],"type":"Point"}
}