{
  "type": "Feature",
  "properties": {
    "gn:admin1_code":"21",
    "gn:asciiname":"Saglam",
    "gn:country_code":"TR",
    "gn:dem":886,
    "gn:feature_class":"P",
    "gn:feature_code":"PPL",
    "gn:name":"Sa\u011flam",
    "gn:population":0,
    "gn:timezone":"Europe/Istanbul",
    "iso:country":"TR",
    "name:und_x_variant":[
        "Sa\u011flam",
        "K\u0131z\u0131lan"
    ],
    "wof:name":"Saglam",
    "wof:placetype":"locality"
},
  "geometry": {"coordinates":[40.14135,38.26598],"type":"Point"}
}