{
  "type": "Feature",
  "properties": {
    "gn:admin1_code":"87",
    "gn:asciiname":"Dogan",
    "gn:country_code":"TR",
    "gn:dem":461,
    "gn:feature_class":"P",
    "gn:feature_code":"PPL",
    "gn:name":"Do\u011fan",
    "gn:population":0,
    "gn:timezone":"Europe/Istanbul",
    "iso:country":"TR",
    "wof:name":"Dogan",
    "wof:placetype":"locality"
},
  "geometry": {"coordinates":[32.46939,41.42279],"type":"Point"}
}