{
  "type": "Feature",
  "properties": {
    "gn:admin1_code":"45",
    "gn:asciiname":"Korubasi",
    "gn:country_code":"TR",
    "gn:dem":419,
    "gn:feature_class":"P",
    "gn:feature_code":"PPL",
    "gn:name":"Koruba\u015f\u0131",
    "gn:population":0,
    "gn:timezone":"Europe/Istanbul",
    "iso:country":"TR",
    "name:tur_x_preferred":[
        "Koruba\u015f\u0131"
    ],
    "name:tur_x_variant":[
        "E\u011frit"
    ],
    "wof:name":"Korubasi",
    "wof:placetype":"locality"
},
  "geometry": {"coordinates":[28.22277,38.78911],"type":"Point"}
}