{
  "type": "Feature",
  "properties": {
    "gn:admin1_code":"84.0",
    "gn:asciiname":"Uzunkaya",
    "gn:country_code":"TR",
    "gn:dem":1681,
    "gn:feature_class":"P",
    "gn:feature_code":"PPL",
    "gn:name":"Uzunkaya",
    "gn:population":0,
    "gn:timezone":"Europe/Istanbul",
    "iso:country":"TR",
    "name:tur_x_preferred":[
        "Uzunkaya"
    ],
    "wof:name":"Uzunkaya",
    "wof:placetype":"locality"
},
  "geometry": {"coordinates":[43.42451,40.38678],"type":"Point"}
}