{
  "type": "Feature",
  "properties": {
    "gn:admin1_code":"63",
    "gn:asciiname":"Birbizim",
    "gn:country_code":"TR",
    "gn:dem":968,
    "gn:feature_class":"P",
    "gn:feature_code":"PPL",
    "gn:name":"Birbizim",
    "gn:population":0,
    "gn:timezone":"Europe/Istanbul",
    "iso:country":"TR",
    "wof:name":"Birbizim",
    "wof:placetype":"locality"
},
  "geometry": {"coordinates":[39.38333,37.86667],"type":"Point"}
}