{
  "type": "Feature",
  "properties": {
    "gn:admin1_code":"61.0",
    "gn:asciiname":"Cinarlik",
    "gn:country_code":"TR",
    "gn:dem":388,
    "gn:feature_class":"P",
    "gn:feature_code":"PPL",
    "gn:name":"\u00c7\u0131narl\u0131k",
    "gn:population":0,
    "gn:timezone":"Europe/Istanbul",
    "iso:country":"TR",
    "name:tur_x_preferred":[
        "\u00c7\u0131narl\u0131k"
    ],
    "wof:name":"Cinarlik",
    "wof:placetype":"locality"
},
  "geometry": {"coordinates":[39.52942,40.98188],"type":"Point"}
}