{
  "type": "Feature",
  "properties": {
    "gn:admin1_code":"09",
    "gn:asciiname":"Emirler Mahallesi",
    "gn:country_code":"TR",
    "gn:dem":457,
    "gn:feature_class":"P",
    "gn:feature_code":"PPL",
    "gn:name":"Emirler Mahallesi",
    "gn:population":0,
    "gn:timezone":"Europe/Istanbul",
    "iso:country":"TR",
    "name:tur_x_preferred":[
        "Emirler Mahallesi"
    ],
    "wof:name":"Emirler Mahallesi",
    "wof:placetype":"locality"
},
  "geometry": {"coordinates":[27.90944,37.50834],"type":"Point"}
}