{
  "type": "Feature",
  "properties": {
    "gn:admin1_code":"37.0",
    "gn:asciiname":"Tekkeoglu",
    "gn:country_code":"TR",
    "gn:dem":666,
    "gn:feature_class":"P",
    "gn:feature_code":"PPL",
    "gn:name":"Tekkeo\u011flu",
    "gn:population":0,
    "gn:timezone":"Europe/Istanbul",
    "iso:country":"TR",
    "name:und_x_variant":[
        "Tekkeo\u011flu",
        "Gano"
    ],
    "wof:name":"Tekkeoglu",
    "wof:placetype":"locality"
},
  "geometry": {"coordinates":[34.11318,41.52307],"type":"Point"}
}