{
  "type": "Feature",
  "properties": {
    "gn:admin1_code":"22.0",
    "gn:asciiname":"Kocahidir",
    "gn:country_code":"TR",
    "gn:dem":26,
    "gn:feature_class":"P",
    "gn:feature_code":"PPL",
    "gn:name":"Kocah\u0131d\u0131r",
    "gn:population":0,
    "gn:timezone":"Europe/Istanbul",
    "iso:country":"TR",
    "name:bul_x_preferred":[
        "\u041a\u043e\u0434\u0436\u0430\u0445\u0430\u0434\u044a\u0440"
    ],
    "name:ceb_x_preferred":[
        "Kocah\u0131d\u0131r"
    ],
    "wof:name":"Kocahidir",
    "wof:placetype":"locality"
},
  "geometry": {"coordinates":[26.40439000000001,40.80829],"type":"Point"}
}