{
  "type": "Feature",
  "properties": {
    "gn:admin1_code":"48",
    "gn:asciiname":"Kilavuz",
    "gn:country_code":"TR",
    "gn:dem":484,
    "gn:feature_class":"P",
    "gn:feature_code":"PPL",
    "gn:name":"K\u0131lavuz",
    "gn:population":0,
    "gn:timezone":"Europe/Istanbul",
    "iso:country":"TR",
    "name:tur_x_preferred":[
        "K\u0131lavuz"
    ],
    "wof:name":"Kilavuz",
    "wof:placetype":"locality"
},
  "geometry": {"coordinates":[27.6916,37.41074],"type":"Point"}
}