{
  "type": "Feature",
  "properties": {
    "gn:country":"TR",
    "gn:fcode":"PPL",
    "gn:population":445,
    "iso:country":"TR",
    "name:tur_x_preferred":[
        "Konakl\u0131"
    ],
    "name:und_x_variant":[
        "H\u0131rbekablo"
    ],
    "qs:name":"Konakl\u0131",
    "qs:photos_9r":0,
    "qs:photos_sr":0,
    "qs:pop_sr":"2",
    "wd:wordcount":60,
    "wof:name":"Konakl\u0131",
    "wof:placetype":"locality",
    "wof:population":445
},
  "geometry": {"coordinates":[40.94139,37.23778],"type":"Point"}
}