{
  "type": "Feature",
  "properties": {
    "gn:admin1_code":"16.0",
    "gn:asciiname":"Alacam",
    "gn:country_code":"TR",
    "gn:dem":929,
    "gn:feature_class":"P",
    "gn:feature_code":"PPL",
    "gn:name":"Ala\u00e7am",
    "gn:population":0,
    "gn:timezone":"Europe/Istanbul",
    "iso:country":"TR",
    "name:und_x_variant":[
        "Te\u015fvikiye",
        "Ala\u00e7am"
    ],
    "wof:name":"Alacam",
    "wof:placetype":"locality"
},
  "geometry": {"coordinates":[29.29048,40.12584],"type":"Point"}
}