{
  "type": "Feature",
  "properties": {
    "gn:admin1_code":"55.0",
    "gn:asciiname":"Esencay",
    "gn:country_code":"TR",
    "gn:dem":138,
    "gn:feature_class":"P",
    "gn:feature_code":"PPL",
    "gn:name":"Esen\u00e7ay",
    "gn:population":0,
    "gn:timezone":"Europe/Istanbul",
    "iso:country":"TR",
    "name:und_x_variant":[
        "\u00c7a\u011fsur",
        "Esen\u00e7ay"
    ],
    "wof:name":"Esencay",
    "wof:placetype":"locality"
},
  "geometry": {"coordinates":[35.83333,41.32941],"type":"Point"}
}