{
  "type": "Feature",
  "properties": {
    "gn:admin1_code":"54",
    "gn:asciiname":"Camlik",
    "gn:country_code":"TR",
    "gn:dem":445,
    "gn:feature_class":"P",
    "gn:feature_code":"PPL",
    "gn:name":"\u00c7aml\u0131k",
    "gn:population":0,
    "gn:timezone":"Europe/Istanbul",
    "iso:country":"TR",
    "name:tur_x_preferred":[
        "\u00c7aml\u0131k"
    ],
    "wof:name":"Camlik",
    "wof:placetype":"locality"
},
  "geometry": {"coordinates":[30.35161,40.41219],"type":"Point"}
}