{
  "type": "Feature",
  "properties": {
    "gn:country":"TR",
    "gn:fcode":"PPL",
    "gn:population":1256,
    "iso:country":"TR",
    "name:tur_x_preferred":[
        "\u00c7ak\u0131rca"
    ],
    "qs:name":"\u00c7ak\u0131rca",
    "qs:photos_9r":0,
    "qs:photos_sr":0,
    "qs:pop_sr":"3",
    "wof:name":"\u00c7ak\u0131rca",
    "wof:placetype":"locality",
    "wof:population":1256
},
  "geometry": {"coordinates":[29.66333,40.47056],"type":"Point"}
}