{
  "type": "Feature",
  "properties": {
    "gn:admin1_code":"32",
    "gn:asciiname":"Kulak",
    "gn:country_code":"TR",
    "gn:dem":1,
    "gn:feature_class":"P",
    "gn:feature_code":"PPL",
    "gn:name":"Kulak",
    "gn:population":0,
    "gn:timezone":"Europe/Istanbul",
    "iso:country":"TR",
    "name:ara_x_preferred":[
        "\u0643\u0648\u0644\u0627\u0643"
    ],
    "name:aze_x_preferred":[
        "Qol\u00e7omaq"
    ],
    "name:bul_x_preferred":[
        "\u041a\u0443\u043b\u0430\u043a"
    ],
    "name:cat_x_preferred":[
        "Kulak"
    ],
    "name:ces_x_preferred":[
        "Kulak"
    ],
    "name:dan_x_preferred":[
        "Kulak"
    ],
    "name:deu_x_preferred":[
        "Kulak"
    ],
    "name:epo_x_preferred":[
        "Kulako"
    ],
    "name:est_x_preferred":[
        "Kulak"
    ],
    "name:eus_x_preferred":[
        "Kulak"
    ],
    "name:fas_x_preferred":[
        "\u06a9\u0648\u0644\u0627\u06a9"
    ],
    "name:fin_x_preferred":[
        "Kulakki"
    ],
    "name:fra_x_preferred":[
        "Koulak"
    ],
    "name:gle_x_preferred":[
        "Culacach"
    ],
    "name:heb_x_preferred":[
        "\u05e7\u05d5\u05dc\u05d0\u05e7"
    ],
    "name:hin_x_preferred":[
        "\u0915\u0941\u0932\u0915"
    ],
    "name:hrv_x_preferred":[
        "Kulak"
    ],
    "name:hun_x_preferred":[
        "Kul\u00e1k"
    ],
    "name:hye_x_preferred":[
        "\u053f\u0578\u0582\u056c\u0561\u056f\u0578\u0582\u0569\u0575\u0578\u0582\u0576"
    ],
    "name:ind_x_preferred":[
        "Kulak"
    ],
    "name:ita_x_preferred":[
        "Kulaki"
    ],
    "name:jpn_x_preferred":[
        "\u30af\u30e9\u30fc\u30af"
    ],
    "name:kaz_x_preferred":[
        "\u041a\u0443\u043b\u0430\u043a\u0442\u0430\u0440 \u049b\u0430\u0443\u044b\u043c\u044b"
    ],
    "name:kir_x_preferred":[
        "\u041a\u0443\u043b\u0430\u043a"
    ],
    "name:kor_x_preferred":[
        "\ucfe8\ub77c\ud06c"
    ],
    "name:lit_x_preferred":[
        "Buo\u017e\u0117"
    ],
    "name:nld_x_preferred":[
        "Koelak"
    ],
    "name:nno_x_preferred":[
        "Kulak"
    ],
    "name:nor_x_preferred":[
        "Kulakker"
    ],
    "name:pol_x_preferred":[
        "Ku\u0142ak"
    ],
    "name:por_x_preferred":[
        "C\u00falaque"
    ],
    "name:ron_x_preferred":[
        "Culac"
    ],
    "name:rus_x_preferred":[
        "\u041a\u0443\u043b\u0430\u043a"
    ],
    "name:slk_x_preferred":[
        "Kulak"
    ],
    "name:spa_x_preferred":[
        "Kulak"
    ],
    "name:swe_x_preferred":[
        "Kulak"
    ],
    "name:tat_x_preferred":[
        "\u041a\u0443\u043b\u0430\u043a\u043b\u0430\u0440"
    ],
    "name:tur_x_preferred":[
        "Kulak"
    ],
    "name:ukr_x_preferred":[
        "\u041a\u0443\u0440\u043a\u0443\u043b\u044c"
    ],
    "name:und_x_variant":[
        "Kulakk\u00f6y",
        "Kulakl\u0131",
        "Kulak"
    ],
    "name:vie_x_preferred":[
        "Kulak"
    ],
    "name:zho_x_preferred":[
        "\u5bcc\u8fb2"
    ],
    "wof:name":"Kulak",
    "wof:placetype":"locality"
},
  "geometry": {"coordinates":[34.86832,36.79533],"type":"Point"}
}