{
  "type": "Feature",
  "properties": {
    "gn:admin1_code":"32",
    "gn:asciiname":"Kulak",
    "gn:country_code":"TR",
    "gn:dem":1,
    "gn:feature_class":"P",
    "gn:feature_code":"PPL",
    "gn:name":"Kulak",
    "gn:population":0,
    "gn:timezone":"Europe/Istanbul",
    "iso:country":"TR",
    "name:und_x_variant":[
        "Kulakk\u00f6y",
        "Kulakl\u0131",
        "Kulak"
    ],
    "wof:name":"Kulak",
    "wof:placetype":"locality"
},
  "geometry": {"coordinates":[34.86832,36.79533],"type":"Point"}
}