{
  "type": "Feature",
  "properties": {
    "gn:admin1_code":"45.0",
    "gn:asciiname":"Karayagci Hacilar",
    "gn:country_code":"TR",
    "gn:dem":272,
    "gn:feature_class":"P",
    "gn:feature_code":"PPL",
    "gn:name":"Karaya\u011fc\u0131 Hac\u0131lar",
    "gn:population":0,
    "gn:timezone":"Europe/Istanbul",
    "iso:country":"TR",
    "name:tur_x_preferred":[
        "Karaya\u011fc\u0131 Hac\u0131lar"
    ],
    "wof:name":"Karayagci Hacilar",
    "wof:placetype":"locality"
},
  "geometry": {"coordinates":[27.32915,38.74555],"type":"Point"}
}