{
  "type": "Feature",
  "properties": {
    "gn:admin1_code":"45",
    "gn:asciiname":"Yakuplar",
    "gn:country_code":"TR",
    "gn:dem":284,
    "gn:feature_class":"P",
    "gn:feature_code":"PPL",
    "gn:name":"Yakuplar",
    "gn:population":0,
    "gn:timezone":"Europe/Istanbul",
    "iso:country":"TR",
    "name:tur_x_preferred":[
        "Yakuplar"
    ],
    "wof:name":"Yakuplar",
    "wof:placetype":"locality"
},
  "geometry": {"coordinates":[27.72494,38.61323],"type":"Point"}
}