{
  "type": "Feature",
  "properties": {
    "gn:admin1_code":"35",
    "gn:asciiname":"Yesildere",
    "gn:country_code":"TR",
    "gn:dem":474,
    "gn:feature_class":"P",
    "gn:feature_code":"PPL",
    "gn:name":"Ye\u015fildere",
    "gn:population":0,
    "gn:timezone":"Europe/Istanbul",
    "iso:country":"TR",
    "name:tur_x_preferred":[
        "Ye\u015fildere"
    ],
    "wof:name":"Yesildere",
    "wof:placetype":"locality"
},
  "geometry": {"coordinates":[28.15928,38.26864000000001],"type":"Point"}
}