{
  "type": "Feature",
  "properties": {
    "gn:admin1_code":"72.0",
    "gn:asciiname":"Ulas",
    "gn:country_code":"TR",
    "gn:dem":822,
    "gn:feature_class":"P",
    "gn:feature_code":"PPL",
    "gn:name":"Ula\u015f",
    "gn:population":0,
    "gn:timezone":"Europe/Istanbul",
    "iso:country":"TR",
    "name:und_x_variant":[
        "Dilan",
        "Ula\u015f"
    ],
    "wof:name":"Ulas",
    "wof:placetype":"locality"
},
  "geometry": {"coordinates":[41.83482,37.47721],"type":"Point"}
}