{
  "type": "Feature",
  "properties": {
    "gn:admin1_code":"72",
    "gn:asciiname":"Urunlu",
    "gn:country_code":"TR",
    "gn:dem":1024,
    "gn:feature_class":"P",
    "gn:feature_code":"PPL",
    "gn:name":"\u00dcr\u00fcnl\u00fc",
    "gn:population":0,
    "gn:timezone":"Europe/Istanbul",
    "iso:country":"TR",
    "name:tur_x_preferred":[
        "\u00dcr\u00fcnl\u00fc"
    ],
    "wof:name":"Urunlu",
    "wof:placetype":"locality"
},
  "geometry": {"coordinates":[40.44939,37.37714],"type":"Point"}
}