{
  "type": "Feature",
  "properties": {
    "gn:admin1_code":"65.0",
    "gn:asciiname":"Yaskutuk",
    "gn:country_code":"TR",
    "gn:dem":2277,
    "gn:feature_class":"P",
    "gn:feature_code":"PPL",
    "gn:name":"Yask\u00fct\u00fck",
    "gn:population":0,
    "gn:timezone":"Europe/Istanbul",
    "iso:country":"TR",
    "name:tur_x_preferred":[
        "Yask\u00fct\u00fck"
    ],
    "wof:name":"Yaskutuk",
    "wof:placetype":"locality"
},
  "geometry": {"coordinates":[43.82673,39.22522],"type":"Point"}
}