{
  "type": "Feature",
  "properties": {
    "gn:admin1_code":"44",
    "gn:asciiname":"Bayirkoy",
    "gn:country_code":"TR",
    "gn:dem":1262,
    "gn:feature_class":"P",
    "gn:feature_code":"PPL",
    "gn:name":"Bay\u0131rk\u00f6y",
    "gn:population":0,
    "gn:timezone":"Europe/Istanbul",
    "iso:country":"TR",
    "name:und_x_variant":[
        "Zalimana",
        "Bay\u0131rk\u00f6y"
    ],
    "wof:name":"Bayirkoy",
    "wof:placetype":"locality"
},
  "geometry": {"coordinates":[38.98111,38.24763],"type":"Point"}
}