{
  "type": "Feature",
  "properties": {
    "gn:admin1_code":"69.0",
    "gn:asciiname":"Asagi Yuvali",
    "gn:country_code":"TR",
    "gn:dem":2074,
    "gn:feature_class":"P",
    "gn:feature_code":"PPL",
    "gn:name":"A\u015fa\u011f\u0131 Yuval\u0131",
    "gn:population":0,
    "gn:timezone":"Europe/Istanbul",
    "iso:country":"TR",
    "name:tur_x_preferred":[
        "A\u015fa\u011f\u0131 Yuval\u0131"
    ],
    "name:und_x_variant":[
        "Yuval\u0131",
        "A\u015fa\u011f\u0131yuval\u0131"
    ],
    "wof:name":"Asagi Yuvali",
    "wof:placetype":"locality"
},
  "geometry": {"coordinates":[39.86454000000001,40.54286],"type":"Point"}
}