{
  "type": "Feature",
  "properties": {
    "gn:admin1_code":"68.0",
    "gn:asciiname":"Camiyaka",
    "gn:country_code":"TR",
    "gn:dem":1169,
    "gn:feature_class":"P",
    "gn:feature_code":"PPL",
    "gn:name":"Camiyaka",
    "gn:population":0,
    "gn:timezone":"Europe/Istanbul",
    "iso:country":"TR",
    "wof:name":"Camiyaka",
    "wof:placetype":"locality"
},
  "geometry": {"coordinates":[31.18211,40.25455],"type":"Point"}
}