{
  "type": "Feature",
  "properties": {
    "gn:admin1_code":"46",
    "gn:asciiname":"Topkanli",
    "gn:country_code":"TR",
    "gn:dem":546,
    "gn:feature_class":"P",
    "gn:feature_code":"PPL",
    "gn:name":"Topkanl\u0131",
    "gn:population":0,
    "gn:timezone":"Europe/Istanbul",
    "iso:country":"TR",
    "wof:name":"Topkanli",
    "wof:placetype":"locality"
},
  "geometry": {"coordinates":[36.76267,37.22],"type":"Point"}
}