{
  "type": "Feature",
  "properties": {
    "gn:admin1_code":"85",
    "gn:asciiname":"Yilanlicakuz",
    "gn:country_code":"TR",
    "gn:dem":372,
    "gn:feature_class":"P",
    "gn:feature_code":"PPL",
    "gn:name":"Y\u0131lanl\u0131cakuz",
    "gn:population":0,
    "gn:timezone":"Europe/Istanbul",
    "iso:country":"TR",
    "wof:name":"Yilanlicakuz",
    "wof:placetype":"locality"
},
  "geometry": {"coordinates":[31.93172,41.24455],"type":"Point"}
}