{
  "type": "Feature",
  "properties": {
    "gn:admin1_code":"07",
    "gn:asciiname":"Gelemis",
    "gn:country_code":"TR",
    "gn:dem":7,
    "gn:feature_class":"P",
    "gn:feature_code":"PPL",
    "gn:name":"Gelemi\u015f",
    "gn:population":0,
    "gn:timezone":"Europe/Istanbul",
    "iso:country":"TR",
    "wof:name":"Gelemis",
    "wof:placetype":"locality"
},
  "geometry": {"coordinates":[29.32001,36.27551],"type":"Point"}
}