{
  "type": "Feature",
  "properties": {
    "gn:country":"TR",
    "gn:fcode":"PPL",
    "gn:pop":0,
    "iso:country":"TR",
    "name:unk_x_variant":[
        "\u00c7iftlikk\u00f6y"
    ],
    "qs:name":"\u00c7iftlik",
    "qs:name_adm0":"Turkey",
    "qs:name_adm1":"Samsun",
    "qs:photos":4,
    "qs:photos_1k":1,
    "qs:photos_9k":1,
    "qs:photos_9r":1,
    "qs:photos_all":4,
    "qs:photos_sr":1,
    "qs:placetype":"Suburb",
    "qs:pop_sr":"0",
    "wd:wordcount":113,
    "wof:name":"\u00c7iftlik",
    "wof:placetype":"neighbourhood",
    "wof:population":0
},
  "geometry": {"coordinates":[36.05339,41.41105],"type":"Point"}
}