{
  "type": "Feature",
  "properties": {
    "gn:admin1_code":"79.0",
    "gn:asciiname":"Yoncali",
    "gn:country_code":"TR",
    "gn:dem":1022,
    "gn:feature_class":"P",
    "gn:feature_code":"PPL",
    "gn:name":"Yoncal\u0131",
    "gn:population":0,
    "gn:timezone":"Europe/Istanbul",
    "iso:country":"TR",
    "wof:name":"Yoncali",
    "wof:placetype":"locality"
},
  "geometry": {"coordinates":[33.7784,39.60807],"type":"Point"}
}