{
  "type": "Feature",
  "properties": {
    "gn:admin1_code":"63",
    "gn:asciiname":"Chemlidzhe",
    "gn:country_code":"TR",
    "gn:dem":608,
    "gn:feature_class":"P",
    "gn:feature_code":"PPL",
    "gn:name":"Chemlidzhe",
    "gn:population":0,
    "gn:timezone":"Europe/Istanbul",
    "iso:country":"TR",
    "wof:name":"Chemlidzhe",
    "wof:placetype":"locality"
},
  "geometry": {"coordinates":[38.96094,37.24784],"type":"Point"}
}