{
  "type": "Feature",
  "properties": {
    "gn:admin1_code":"26.0",
    "gn:asciiname":"Abbashalimpasa",
    "gn:country_code":"TR",
    "gn:dem":871,
    "gn:feature_class":"P",
    "gn:feature_code":"PPL",
    "gn:name":"Abbashalimpa\u015fa",
    "gn:population":0,
    "gn:timezone":"Europe/Istanbul",
    "iso:country":"TR",
    "name:und_x_variant":[
        "Mand\u0131ra",
        "Abbashalimpa\u015famand\u0131ras\u0131",
        "Abbashalilpasa Mand\u0131ra",
        "Abbaspa\u015fa",
        "Abbashalimpa\u015fa"
    ],
    "wof:name":"Abbashalimpasa",
    "wof:placetype":"locality"
},
  "geometry": {"coordinates":[31.07823,39.40153],"type":"Point"}
}