{
  "type": "Feature",
  "properties": {
    "gn:admin1_code":"25",
    "gn:asciiname":"Alemdagi",
    "gn:country_code":"TR",
    "gn:dem":2048,
    "gn:feature_class":"P",
    "gn:feature_code":"PPL",
    "gn:name":"Alemda\u011f\u0131",
    "gn:population":0,
    "gn:timezone":"Europe/Istanbul",
    "iso:country":"TR",
    "name:und_x_variant":[
        "Alemda\u011f\u0131",
        "Alemda\u011f"
    ],
    "wof:name":"Alemdagi",
    "wof:placetype":"locality"
},
  "geometry": {"coordinates":[41.89668,39.61033],"type":"Point"}
}