{
  "type": "Feature",
  "properties": {
    "gn:admin1_code":"19.0",
    "gn:asciiname":"Cetederesi",
    "gn:country_code":"TR",
    "gn:dem":1226,
    "gn:feature_class":"P",
    "gn:feature_code":"PPL",
    "gn:name":"\u00c7etederesi",
    "gn:population":0,
    "gn:timezone":"Europe/Istanbul",
    "iso:country":"TR",
    "wof:name":"Cetederesi",
    "wof:placetype":"locality"
},
  "geometry": {"coordinates":[34.90915,40.00354],"type":"Point"}
}