{
  "type": "Feature",
  "properties": {
    "gn:admin1_code":"48",
    "gn:asciiname":"Kucuk Mustafalar",
    "gn:country_code":"TR",
    "gn:dem":326,
    "gn:feature_class":"P",
    "gn:feature_code":"PPL",
    "gn:name":"K\u00fc\u00e7\u00fck Mustafalar",
    "gn:population":0,
    "gn:timezone":"Europe/Istanbul",
    "iso:country":"TR",
    "name:tur_x_preferred":[
        "K\u00fc\u00e7\u00fck Mustafalar"
    ],
    "wof:name":"Kucuk Mustafalar",
    "wof:placetype":"locality"
},
  "geometry": {"coordinates":[28.09056,37.42635],"type":"Point"}
}