{
  "type": "Feature",
  "properties": {
    "gn:admin1_code":"31.0",
    "gn:asciiname":"Zenginharabesi",
    "gn:country_code":"TR",
    "gn:dem":194,
    "gn:feature_class":"P",
    "gn:feature_code":"PPL",
    "gn:name":"Zenginharabesi",
    "gn:population":0,
    "gn:timezone":"Europe/Istanbul",
    "iso:country":"TR",
    "name:und_x_variant":[
        "Zengin-Kharabesi",
        "Zenginharabesi"
    ],
    "wof:name":"Zenginharabesi",
    "wof:placetype":"locality"
},
  "geometry": {"coordinates":[36.5183,36.53588],"type":"Point"}
}