{
  "type": "Feature",
  "properties": {
    "gn:admin1_code":"83",
    "gn:asciiname":"Eski Sarkaya",
    "gn:country_code":"TR",
    "gn:dem":1052,
    "gn:feature_class":"P",
    "gn:feature_code":"PPL",
    "gn:name":"Eski \u015earkaya",
    "gn:population":0,
    "gn:timezone":"Europe/Istanbul",
    "iso:country":"TR",
    "name:tur_x_preferred":[
        "Eski \u015earkaya"
    ],
    "name:und_x_variant":[
        "A\u015fa\u011f\u0131 \u015earkaya",
        "\u015earkaya",
        "Eski\u015farkaya"
    ],
    "wof:name":"Eski Sarkaya",
    "wof:placetype":"locality"
},
  "geometry": {"coordinates":[37.1296,37.21849],"type":"Point"}
}