{
  "type": "Feature",
  "properties": {
    "gn:admin1_code":"65",
    "gn:asciiname":"Asagigulderen",
    "gn:country_code":"TR",
    "gn:dem":2197,
    "gn:feature_class":"P",
    "gn:feature_code":"PPL",
    "gn:name":"A\u015fa\u011f\u0131g\u00fclderen",
    "gn:population":0,
    "gn:timezone":"Europe/Istanbul",
    "iso:country":"TR",
    "name:und_x_variant":[
        "A\u015fa\u011f\u0131nazarova",
        "A\u015fa\u011f\u0131g\u00fclderen"
    ],
    "wof:name":"Asagigulderen",
    "wof:placetype":"locality"
},
  "geometry": {"coordinates":[44.12656,39.04209],"type":"Point"}
}