{
  "type": "Feature",
  "properties": {
    "gn:admin1_code":"49",
    "gn:asciiname":"Molladerman",
    "gn:country_code":"TR",
    "gn:dem":1874,
    "gn:feature_class":"P",
    "gn:feature_code":"PPL",
    "gn:name":"Molladerman",
    "gn:population":0,
    "gn:timezone":"Europe/Istanbul",
    "iso:country":"TR",
    "name:tur_x_preferred":[
        "Molladerman"
    ],
    "wof:name":"Molladerman",
    "wof:placetype":"locality"
},
  "geometry": {"coordinates":[42.52614000000001,39.01083],"type":"Point"}
}