{
  "type": "Feature",
  "properties": {
    "gn:admin1_code":"31",
    "gn:asciiname":"Kislacayi",
    "gn:country_code":"TR",
    "gn:dem":59,
    "gn:feature_class":"P",
    "gn:feature_code":"PPL",
    "gn:name":"K\u0131\u015fla\u00e7ay\u0131",
    "gn:population":0,
    "gn:timezone":"Europe/Istanbul",
    "iso:country":"TR",
    "name:tur_x_preferred":[
        "K\u0131\u015fla\u00e7ay"
    ],
    "name:tur_x_variant":[
        "K\u0131\u015fla\u00e7ay\u0131",
        "K\u0131\u015fla"
    ],
    "wof:name":"Kislacayi",
    "wof:placetype":"locality"
},
  "geometry": {"coordinates":[35.83260999999999,36.35279],"type":"Point"}
}