{
  "type": "Feature",
  "properties": {
    "gn:admin1_code":"57.0",
    "gn:asciiname":"Dibekli",
    "gn:country_code":"TR",
    "gn:dem":33,
    "gn:feature_class":"P",
    "gn:feature_code":"PPL",
    "gn:name":"Dibekli",
    "gn:population":0,
    "gn:timezone":"Europe/Istanbul",
    "iso:country":"TR",
    "name:und_x_variant":[
        "Dibeklik\u00f6y"
    ],
    "wof:name":"Dibekli",
    "wof:placetype":"locality"
},
  "geometry": {"coordinates":[35.01549,42.01958],"type":"Point"}
}