{
  "type": "Feature",
  "properties": {
    "gn:admin1_code":"65.0",
    "gn:asciiname":"Adiguzel",
    "gn:country_code":"TR",
    "gn:dem":1746,
    "gn:feature_class":"P",
    "gn:feature_code":"PPL",
    "gn:name":"Ad\u0131g\u00fczel",
    "gn:population":0,
    "gn:timezone":"Europe/Istanbul",
    "iso:country":"TR",
    "name:tur_x_preferred":[
        "Ad\u0131g\u00fczel"
    ],
    "wof:name":"Adiguzel",
    "wof:placetype":"locality"
},
  "geometry": {"coordinates":[43.45081,38.69238],"type":"Point"}
}