{
  "type": "Feature",
  "properties": {
    "gn:country":"TR",
    "gn:fcode":"PPL",
    "gn:population":0,
    "iso:country":"TR",
    "name:deu_x_preferred":[
        "P\u00fct\u00fcrge"
    ],
    "name:diq_x_preferred":[
        "\u015e\u00earo"
    ],
    "name:eng_x_preferred":[
        "P\u00fct\u00fcrge"
    ],
    "name:fra_x_preferred":[
        "P\u00f6t\u00fcrge"
    ],
    "name:ita_x_preferred":[
        "distretto di P\u00f6t\u00fcrge"
    ],
    "name:kur_x_preferred":[
        "\u015e\u00eero"
    ],
    "name:mrj_x_preferred":[
        "\u041f\u04f1\u0442\u04f1\u0440\u0433\u0435"
    ],
    "name:msa_x_preferred":[
        "P\u00f6t\u00fcrge"
    ],
    "name:nan_x_preferred":[
        "P\u00fct\u00fcrge"
    ],
    "name:nld_x_preferred":[
        "P\u00f6t\u00fcrge"
    ],
    "name:nob_x_preferred":[
        "P\u00fct\u00fcrge"
    ],
    "name:pnb_x_preferred":[
        "\u0636\u0644\u0639 \u067e\u0648\u062a\u0631\u06af"
    ],
    "name:rus_x_preferred":[
        "\u041f\u044e\u0442\u044e\u0440\u0433\u0435"
    ],
    "name:swa_x_preferred":[
        "P\u00f6t\u00fcrge"
    ],
    "name:tur_x_preferred":[
        "P\u00fct\u00fcrge"
    ],
    "name:und_x_variant":[
        "\u0130mron"
    ],
    "name:urd_x_preferred":[
        "\u067e\u0648\u062a\u0648\u0631\u06af\u06d2"
    ],
    "name:vie_x_preferred":[
        "P\u00f6t\u00fcrge"
    ],
    "qs:name":"P\u00fct\u00fcrge",
    "qs:name_adm0":"Turkey",
    "qs:name_adm1":"Malatya",
    "qs:photos_9k":1,
    "qs:photos_9r":1,
    "qs:photos_all":1,
    "qs:photos_sr":0,
    "qs:placetype":"Town",
    "qs:pop_sr":"3",
    "wd:wordcount":60,
    "wof:name":"P\u00fct\u00fcrge",
    "wof:placetype":"locality",
    "wof:population":0
},
  "geometry": {"coordinates":[38.86898,38.19875],"type":"Point"}
}