{
  "type": "Feature",
  "properties": {
    "gn:admin1_code":"07",
    "gn:asciiname":"Koypinar",
    "gn:cc2":"TR",
    "gn:country_code":"TR",
    "gn:dem":997,
    "gn:feature_class":"P",
    "gn:feature_code":"PPL",
    "gn:name":"K\u00f6yp\u0131nar",
    "gn:population":0,
    "gn:timezone":"Europe/Istanbul",
    "iso:country":"TR",
    "name:und_x_variant":[
        "Korp\u0131nardamlar\u0131",
        "K\u00f6yp\u0131nar"
    ],
    "wof:name":"Koypinar",
    "wof:placetype":"locality"
},
  "geometry": {"coordinates":[30.3325,37.00306],"type":"Point"}
}