{
  "type": "Feature",
  "properties": {
    "gn:admin1_code":"35",
    "gn:asciiname":"Karabulu",
    "gn:country_code":"TR",
    "gn:dem":724,
    "gn:feature_class":"P",
    "gn:feature_code":"PPL",
    "gn:name":"Karabulu",
    "gn:population":0,
    "gn:timezone":"Europe/Istanbul",
    "iso:country":"TR",
    "name:tur_x_preferred":[
        "Karabulu"
    ],
    "wof:name":"Karabulu",
    "wof:placetype":"locality"
},
  "geometry": {"coordinates":[28.42259,38.13806],"type":"Point"}
}