{
  "type": "Feature",
  "properties": {
    "gn:admin1_code":"16.0",
    "gn:asciiname":"Garipcetekke",
    "gn:country_code":"TR",
    "gn:dem":289,
    "gn:feature_class":"P",
    "gn:feature_code":"PPL",
    "gn:name":"Garip\u00e7etekke",
    "gn:population":0,
    "gn:timezone":"Europe/Istanbul",
    "iso:country":"TR",
    "name:und_x_variant":[
        "Garib\u00e7etekke",
        "Garip\u00e7etekke"
    ],
    "wof:name":"Garipcetekke",
    "wof:placetype":"locality"
},
  "geometry": {"coordinates":[28.52421,40.06347],"type":"Point"}
}