{
  "type": "Feature",
  "properties": {
    "gn:admin1_code":"03",
    "gn:asciiname":"Gozeli",
    "gn:country_code":"TR",
    "gn:dem":935,
    "gn:feature_class":"P",
    "gn:feature_code":"PPL",
    "gn:name":"G\u00f6zeli",
    "gn:population":0,
    "gn:timezone":"Europe/Istanbul",
    "iso:country":"TR",
    "name:und_x_variant":[
        "G\u00f6zeli",
        "Manahoz"
    ],
    "wof:name":"Gozeli",
    "wof:placetype":"locality"
},
  "geometry": {"coordinates":[31.14032000000001,39.17883],"type":"Point"}
}