{
  "type": "Feature",
  "properties": {
    "gn:admin1_code":"8.0",
    "gn:asciiname":"Guneslikoyu",
    "gn:country_code":"TR",
    "gn:dem":595,
    "gn:feature_class":"P",
    "gn:feature_code":"PPL",
    "gn:name":"G\u00fcne\u015flik\u00f6y\u00fc",
    "gn:population":0,
    "gn:timezone":"Europe/Istanbul",
    "iso:country":"TR",
    "name:tur_x_preferred":[
        "G\u00fcne\u015fli"
    ],
    "name:und_x_variant":[
        "G\u00fcne\u015flik\u00f6y\u00fc",
        "G\u00fcrgenli"
    ],
    "wof:name":"Guneslikoyu",
    "wof:placetype":"locality"
},
  "geometry": {"coordinates":[41.68656,41.46126],"type":"Point"}
}