{
  "type": "Feature",
  "properties": {
    "gn:admin1_code":"24",
    "gn:asciiname":"Bulmus",
    "gn:country_code":"TR",
    "gn:dem":1633,
    "gn:feature_class":"P",
    "gn:feature_code":"PPL",
    "gn:name":"Bulmu\u015f",
    "gn:population":0,
    "gn:timezone":"Europe/Istanbul",
    "iso:country":"TR",
    "name:tur_x_preferred":[
        "Bulmu\u015f"
    ],
    "wof:name":"Bulmus",
    "wof:placetype":"locality"
},
  "geometry": {"coordinates":[40.10589,39.65859],"type":"Point"}
}