{
  "type": "Feature",
  "properties": {
    "gn:admin1_code":"58.0",
    "gn:asciiname":"Akpinar",
    "gn:country_code":"TR",
    "gn:dem":1825,
    "gn:feature_class":"P",
    "gn:feature_code":"PPL",
    "gn:name":"Akp\u0131nar",
    "gn:population":0,
    "gn:timezone":"Europe/Istanbul",
    "iso:country":"TR",
    "wof:name":"Akpinar",
    "wof:placetype":"locality"
},
  "geometry": {"coordinates":[36.87773,38.69199],"type":"Point"}
}