{
  "type": "Feature",
  "properties": {
    "gn:admin1_code":"02",
    "gn:asciiname":"Saglik",
    "gn:country_code":"TR",
    "gn:dem":794,
    "gn:feature_class":"P",
    "gn:feature_code":"PPL",
    "gn:name":"Sa\u011fl\u0131k",
    "gn:population":0,
    "gn:timezone":"Europe/Istanbul",
    "iso:country":"TR",
    "name:und_x_variant":[
        "Sa\u011fl\u0131k",
        "Kesrik"
    ],
    "wof:name":"Saglik",
    "wof:placetype":"locality"
},
  "geometry": {"coordinates":[39.15255,38.05153],"type":"Point"}
}