{
  "type": "Feature",
  "properties": {
    "gn:admin1_code":"52.0",
    "gn:asciiname":"Oyumgurgen",
    "gn:country_code":"TR",
    "gn:dem":434,
    "gn:feature_class":"P",
    "gn:feature_code":"PPL",
    "gn:name":"Oyumg\u00fcrgen",
    "gn:population":0,
    "gn:timezone":"Europe/Istanbul",
    "iso:country":"TR",
    "name:tur_x_preferred":[
        "Oyumg\u00fcrgen"
    ],
    "wof:name":"Oyumgurgen",
    "wof:placetype":"locality"
},
  "geometry": {"coordinates":[37.72537,40.81883],"type":"Point"}
}