{
  "type": "Feature",
  "properties": {
    "gn:admin1_code":"87",
    "gn:asciiname":"Kinakayas",
    "gn:country_code":"TR",
    "gn:dem":460,
    "gn:feature_class":"P",
    "gn:feature_code":"PPL",
    "gn:name":"K\u0131nakayas",
    "gn:population":0,
    "gn:timezone":"Europe/Istanbul",
    "iso:country":"TR",
    "wof:name":"Kinakayas",
    "wof:placetype":"locality"
},
  "geometry": {"coordinates":[32.69082,41.60096],"type":"Point"}
}