{
  "type": "Feature",
  "properties": {
    "gn:admin1_code":"43",
    "gn:asciiname":"Yaylaolu",
    "gn:country_code":"TR",
    "gn:dem":791,
    "gn:feature_class":"P",
    "gn:feature_code":"PPL",
    "gn:name":"Yaylaolu",
    "gn:population":0,
    "gn:timezone":"Europe/Istanbul",
    "iso:country":"TR",
    "name:und_x_variant":[
        "M\u00fcmye",
        "Yaylaolu"
    ],
    "wof:name":"Yaylaolu",
    "wof:placetype":"locality"
},
  "geometry": {"coordinates":[29.23643,39.45389],"type":"Point"}
}