{
  "type": "Feature",
  "properties": {
    "gn:admin1_code":"25.0",
    "gn:asciiname":"Yaylabasi",
    "gn:country_code":"TR",
    "gn:dem":1701,
    "gn:feature_class":"P",
    "gn:feature_code":"PPL",
    "gn:name":"Yaylaba\u015f\u0131",
    "gn:population":0,
    "gn:timezone":"Europe/Istanbul",
    "iso:country":"TR",
    "name:tur_x_preferred":[
        "Yaylaba\u015f\u0131"
    ],
    "wof:name":"Yaylabasi",
    "wof:placetype":"locality"
},
  "geometry": {"coordinates":[42.18138,40.85642],"type":"Point"}
}