{
  "type": "Feature",
  "properties": {
    "gn:admin1_code":"46.0",
    "gn:asciiname":"Igdemli",
    "gn:country_code":"TR",
    "gn:dem":1456,
    "gn:feature_class":"P",
    "gn:feature_code":"PPL",
    "gn:name":"\u0130\u011fdemli",
    "gn:population":0,
    "gn:timezone":"Europe/Istanbul",
    "iso:country":"TR",
    "wof:name":"Igdemli",
    "wof:placetype":"locality"
},
  "geometry": {"coordinates":[36.80574,38.22016],"type":"Point"}
}