{
  "type": "Feature",
  "properties": {
    "gn:admin1_code":"17.0",
    "gn:asciiname":"Kanibey",
    "gn:country_code":"TR",
    "gn:dem":58,
    "gn:feature_class":"P",
    "gn:feature_code":"PPL",
    "gn:name":"Kanibey",
    "gn:population":0,
    "gn:timezone":"Europe/Istanbul",
    "iso:country":"TR",
    "name:tur_x_preferred":[
        "Kanibey"
    ],
    "wof:name":"Kanibey",
    "wof:placetype":"locality"
},
  "geometry": {"coordinates":[27.33411,40.27604],"type":"Point"}
}