{
  "type": "Feature",
  "properties": {
    "gn:admin1_code":"11",
    "gn:asciiname":"Doruk",
    "gn:country_code":"TR",
    "gn:dem":1135,
    "gn:feature_class":"P",
    "gn:feature_code":"PPL",
    "gn:name":"Doruk",
    "gn:population":0,
    "gn:timezone":"Europe/Istanbul",
    "iso:country":"TR",
    "name:ceb_x_preferred":[
        "Doruk"
    ],
    "name:swe_x_preferred":[
        "Doruk"
    ],
    "name:tur_x_preferred":[
        "Doruk"
    ],
    "wof:name":"Doruk",
    "wof:placetype":"locality"
},
  "geometry": {"coordinates":[30.18505,39.91872],"type":"Point"}
}