{
  "type": "Feature",
  "properties": {
    "gn:admin1_code":"89.0",
    "gn:asciiname":"Burnuk",
    "gn:country_code":"TR",
    "gn:dem":799,
    "gn:feature_class":"P",
    "gn:feature_code":"PPL",
    "gn:name":"B\u00fcrn\u00fck",
    "gn:population":0,
    "gn:timezone":"Europe/Istanbul",
    "iso:country":"TR",
    "name:tur_x_preferred":[
        "B\u00fcrn\u00fck"
    ],
    "wof:name":"Burnuk",
    "wof:placetype":"locality"
},
  "geometry": {"coordinates":[32.75668,41.16891],"type":"Point"}
}