{
  "type": "Feature",
  "properties": {
    "gn:admin1_code":"66.0",
    "gn:asciiname":"Demircialan",
    "gn:country_code":"TR",
    "gn:dem":1195,
    "gn:feature_class":"P",
    "gn:feature_code":"PPL",
    "gn:name":"Demircialan",
    "gn:population":0,
    "gn:timezone":"Europe/Istanbul",
    "iso:country":"TR",
    "wof:name":"Demircialan",
    "wof:placetype":"locality"
},
  "geometry": {"coordinates":[35.44462,39.9794],"type":"Point"}
}