{
  "type": "Feature",
  "properties": {
    "gn:admin1_code":"8.0",
    "gn:asciiname":"Aydinlar",
    "gn:country_code":"TR",
    "gn:dem":356,
    "gn:feature_class":"P",
    "gn:feature_code":"PPL",
    "gn:name":"Ayd\u0131nlar",
    "gn:population":0,
    "gn:timezone":"Europe/Istanbul",
    "iso:country":"TR",
    "name:und_x_variant":[
        "Ayd\u0131nk\u00f6y",
        "Ayd\u0131nlar"
    ],
    "wof:name":"Aydinlar",
    "wof:placetype":"locality"
},
  "geometry": {"coordinates":[42.00798,41.20349],"type":"Point"}
}