{
  "type": "Feature",
  "properties": {
    "gn:admin1_code":"26",
    "gn:asciiname":"Turgutlar",
    "gn:cc2":"TR",
    "gn:country_code":"TR",
    "gn:dem":850,
    "gn:feature_class":"P",
    "gn:feature_code":"PPL",
    "gn:name":"Turgutlar",
    "gn:population":0,
    "gn:timezone":"Europe/Istanbul",
    "iso:country":"TR",
    "name:und_x_variant":[
        "Dargutlar",
        "Durgutlar",
        "Elemen",
        "Turgutlar"
    ],
    "wof:name":"Turgutlar",
    "wof:placetype":"locality"
},
  "geometry": {"coordinates":[30.35361,39.775],"type":"Point"}
}