{
  "type": "Feature",
  "properties": {
    "gn:admin1_code":"72.0",
    "gn:asciiname":"Karademir",
    "gn:country_code":"TR",
    "gn:dem":561,
    "gn:feature_class":"P",
    "gn:feature_code":"PPL",
    "gn:name":"Karademir",
    "gn:population":0,
    "gn:timezone":"Europe/Istanbul",
    "iso:country":"TR",
    "name:tur_x_preferred":[
        "Karademir"
    ],
    "name:und_x_variant":[
        "K\u00f6rmusa Harabesi",
        "Kermusa"
    ],
    "wof:name":"Karademir",
    "wof:placetype":"locality"
},
  "geometry": {"coordinates":[40.8093,37.19739000000001],"type":"Point"}
}