{
  "type": "Feature",
  "properties": {
    "gn:admin1_code":"48",
    "gn:asciiname":"Ciftlikkoy",
    "gn:cc2":"TR",
    "gn:country_code":"TR",
    "gn:dem":669,
    "gn:feature_class":"P",
    "gn:feature_code":"PPL",
    "gn:name":"\u00c7iftlikk\u00f6y",
    "gn:population":0,
    "gn:timezone":"Europe/Istanbul",
    "iso:country":"TR",
    "name:und_x_variant":[
        "\u00c7iftlik",
        "\u00c7iftlikk\u00f6y"
    ],
    "wof:name":"Ciftlikkoy",
    "wof:placetype":"locality"
},
  "geometry": {"coordinates":[28.16417,37.18556],"type":"Point"}
}