{
  "type": "Feature",
  "properties": {
    "gn:admin1_code":"28.0",
    "gn:asciiname":"Bektasyayla",
    "gn:country_code":"TR",
    "gn:dem":2003,
    "gn:feature_class":"P",
    "gn:feature_code":"PPL",
    "gn:name":"Bekta\u015fyayla",
    "gn:population":0,
    "gn:timezone":"Europe/Istanbul",
    "iso:country":"TR",
    "name:eng_x_preferred":[
        "Bekta\u015fyayla"
    ],
    "name:rus_x_preferred":[
        "\u0411\u0435\u043a\u0442\u0430\u0448-\u042f\u0439\u043b\u0430"
    ],
    "name:und_x_variant":[
        "Bekta\u015fyayla"
    ],
    "wof:name":"Bektasyayla",
    "wof:placetype":"locality"
},
  "geometry": {"coordinates":[38.25,40.66667],"type":"Point"}
}