{
  "type": "Feature",
  "properties": {
    "gn:admin1_code":"62",
    "gn:asciiname":"Bedretil",
    "gn:country_code":"TR",
    "gn:dem":820,
    "gn:feature_class":"P",
    "gn:feature_code":"PPL",
    "gn:name":"Bedretil",
    "gn:population":0,
    "gn:timezone":"Europe/Istanbul",
    "iso:country":"TR",
    "wof:name":"Bedretil",
    "wof:placetype":"locality"
},
  "geometry": {"coordinates":[38.88333,38.96667],"type":"Point"}
}