{
  "type": "Feature",
  "properties": {
    "gn:admin1_code":"24.0",
    "gn:asciiname":"Oren",
    "gn:country_code":"TR",
    "gn:dem":1851,
    "gn:feature_class":"P",
    "gn:feature_code":"PPL",
    "gn:name":"\u00d6ren",
    "gn:population":0,
    "gn:timezone":"Europe/Istanbul",
    "iso:country":"TR",
    "name:deu_x_preferred":[
        "Oren"
    ],
    "name:ita_x_preferred":[
        "Oren"
    ],
    "name:por_x_preferred":[
        "Oren"
    ],
    "name:und_x_variant":[
        "\u00d6ren"
    ],
    "wof:name":"Oren",
    "wof:placetype":"locality"
},
  "geometry": {"coordinates":[38.89977,40.03172],"type":"Point"}
}