{
  "type": "Feature",
  "properties": {
    "gn:admin1_code":"63",
    "gn:asciiname":"Tanyeli",
    "gn:country_code":"TR",
    "gn:dem":565,
    "gn:feature_class":"P",
    "gn:feature_code":"PPL",
    "gn:name":"Tanyeli",
    "gn:population":0,
    "gn:timezone":"Europe/Istanbul",
    "iso:country":"TR",
    "name:und_x_variant":[
        "Sako",
        "Tanyeli"
    ],
    "wof:name":"Tanyeli",
    "wof:placetype":"locality"
},
  "geometry": {"coordinates":[39.68911,37.22579],"type":"Point"}
}