{
  "type": "Feature",
  "properties": {
    "gn:admin1_code":"76.0",
    "gn:asciiname":"Kirishkhasan",
    "gn:country_code":"TR",
    "gn:dem":1129,
    "gn:feature_class":"P",
    "gn:feature_code":"PPL",
    "gn:name":"Kirishkhasan",
    "gn:population":0,
    "gn:timezone":"Europe/Istanbul",
    "iso:country":"TR",
    "name:und_x_variant":[
        "Kiri\u015fhasan"
    ],
    "wof:name":"Kirishkhasan",
    "wof:placetype":"locality"
},
  "geometry": {"coordinates":[41.63611,37.60722],"type":"Point"}
}