{
  "type": "Feature",
  "properties": {
    "gn:admin1_code":"09",
    "gn:asciiname":"Ziyaretli",
    "gn:country_code":"TR",
    "gn:dem":278,
    "gn:feature_class":"P",
    "gn:feature_code":"PPL",
    "gn:name":"Ziyaretli",
    "gn:population":0,
    "gn:timezone":"Europe/Istanbul",
    "iso:country":"TR",
    "name:tur_x_preferred":[
        "Ziyaretli"
    ],
    "name:tur_x_variant":[
        "Ziyaret\u00e7i"
    ],
    "wof:name":"Ziyaretli",
    "wof:placetype":"locality"
},
  "geometry": {"coordinates":[28.29657000000001,37.68639],"type":"Point"}
}