{
  "type": "Feature",
  "properties": {
    "gn:admin1_code":"43",
    "gn:asciiname":"Goncel",
    "gn:country_code":"TR",
    "gn:dem":1097,
    "gn:feature_class":"P",
    "gn:feature_code":"PPL",
    "gn:name":"G\u00f6ncel",
    "gn:population":0,
    "gn:timezone":"Europe/Istanbul",
    "iso:country":"TR",
    "name:tur_x_preferred":[
        "G\u00f6ncel"
    ],
    "wof:name":"Goncel",
    "wof:placetype":"locality"
},
  "geometry": {"coordinates":[29.15917,39.28194000000001],"type":"Point"}
}