{
  "type": "Feature",
  "properties": {
    "gn:admin1_code":"58.0",
    "gn:asciiname":"Kozcukur",
    "gn:country_code":"TR",
    "gn:dem":1414,
    "gn:feature_class":"P",
    "gn:feature_code":"PPL",
    "gn:name":"Koz\u00e7ukur",
    "gn:population":0,
    "gn:timezone":"Europe/Istanbul",
    "iso:country":"TR",
    "name:tur_x_preferred":[
        "Koz\u00e7ukur"
    ],
    "wof:name":"Kozcukur",
    "wof:placetype":"locality"
},
  "geometry": {"coordinates":[38.00266,40.17542],"type":"Point"}
}