{
  "type": "Feature",
  "properties": {
    "gn:admin1_code":"55.0",
    "gn:asciiname":"Konakoren",
    "gn:country_code":"TR",
    "gn:dem":544,
    "gn:feature_class":"P",
    "gn:feature_code":"PPL",
    "gn:name":"Konak\u00f6ren",
    "gn:population":0,
    "gn:timezone":"Europe/Istanbul",
    "iso:country":"TR",
    "name:und_x_variant":[
        "Bolas",
        "Polas",
        "Konak\u00f6ren"
    ],
    "wof:name":"Konakoren",
    "wof:placetype":"locality"
},
  "geometry": {"coordinates":[36.91739000000001,41.02073],"type":"Point"}
}