{
  "type": "Feature",
  "properties": {
    "gn:admin1_code":"25",
    "gn:asciiname":"Ovacik",
    "gn:country_code":"TR",
    "gn:dem":1998,
    "gn:feature_class":"P",
    "gn:feature_code":"PPL",
    "gn:name":"Ovac\u0131k",
    "gn:population":0,
    "gn:timezone":"Europe/Istanbul",
    "iso:country":"TR",
    "name:tur_x_preferred":[
        "Ovac\u0131k"
    ],
    "wof:name":"Ovacik",
    "wof:placetype":"locality"
},
  "geometry": {"coordinates":[40.61271,39.72001],"type":"Point"}
}