{
  "type": "Feature",
  "properties": {
    "gn:admin1_code":"10",
    "gn:asciiname":"Kadikiri",
    "gn:country_code":"TR",
    "gn:dem":224,
    "gn:feature_class":"P",
    "gn:feature_code":"PPL",
    "gn:name":"Kad\u0131k\u0131r\u0131",
    "gn:population":0,
    "gn:timezone":"Europe/Istanbul",
    "iso:country":"TR",
    "name:tur_x_preferred":[
        "Kad\u0131k\u0131r\u0131"
    ],
    "wof:name":"Kadikiri",
    "wof:placetype":"locality"
},
  "geometry": {"coordinates":[28.12093,39.8737],"type":"Point"}
}