{
  "type": "Feature",
  "properties": {
    "gn:admin1_code":"55.0",
    "gn:asciiname":"Hasirci",
    "gn:country_code":"TR",
    "gn:dem":955,
    "gn:feature_class":"P",
    "gn:feature_code":"PPL",
    "gn:name":"Has\u0131rc\u0131",
    "gn:population":0,
    "gn:timezone":"Europe/Istanbul",
    "iso:country":"TR",
    "wof:name":"Hasirci",
    "wof:placetype":"locality"
},
  "geometry": {"coordinates":[35.93579000000001,40.93625],"type":"Point"}
}