{
  "type": "Feature",
  "properties": {
    "gn:country":"TR",
    "gn:fcode":"PPL",
    "gn:pop":1576,
    "iso:country":"TR",
    "name:tur_x_preferred":[
        "\u015eenocak"
    ],
    "name:unk_x_variant":[
        "\u015euti"
    ],
    "qs:name":"\u015eenocak",
    "qs:photos_9r":0,
    "qs:photos_sr":0,
    "qs:pop_sr":"3",
    "wof:name":"\u015eenocak",
    "wof:placetype":"locality",
    "wof:population":1576
},
  "geometry": {"coordinates":[40.69531,37.65136],"type":"Point"}
}