{
  "type": "Feature",
  "properties": {
    "gn:admin1_code":"64",
    "gn:asciiname":"Yapagilar",
    "gn:cc2":"TR",
    "gn:country_code":"TR",
    "gn:dem":937,
    "gn:feature_class":"P",
    "gn:feature_code":"PPL",
    "gn:name":"Yapa\u011f\u0131lar",
    "gn:population":0,
    "gn:timezone":"Europe/Istanbul",
    "iso:country":"TR",
    "name:und_x_variant":[
        "Yapa\u011flar",
        "Yapa\u011f\u0131lar"
    ],
    "wof:name":"Yapagilar",
    "wof:placetype":"locality"
},
  "geometry": {"coordinates":[29.52056,38.60194],"type":"Point"}
}