{
  "type": "Feature",
  "properties": {
    "gn:admin1_code":"45",
    "gn:asciiname":"Lutfiye",
    "gn:country_code":"TR",
    "gn:dem":62,
    "gn:feature_class":"P",
    "gn:feature_code":"PPL",
    "gn:name":"L\u00fctfiye",
    "gn:population":0,
    "gn:timezone":"Europe/Istanbul",
    "iso:country":"TR",
    "name:und_x_variant":[
        "Arpal\u0131",
        "L\u00fctfiye"
    ],
    "wof:name":"Lutfiye",
    "wof:placetype":"locality"
},
  "geometry": {"coordinates":[27.72739,38.74372],"type":"Point"}
}