{
  "type": "Feature",
  "properties": {
    "gn:admin1_code":"21.0",
    "gn:asciiname":"Kejikan",
    "gn:cc2":"TR",
    "gn:country_code":"TR",
    "gn:dem":715,
    "gn:feature_class":"P",
    "gn:feature_code":"PPL",
    "gn:name":"Kejikan",
    "gn:population":0,
    "gn:timezone":"Europe/Istanbul",
    "iso:country":"TR",
    "name:tur_x_preferred":[
        "Kejikan"
    ],
    "name:und_x_variant":[
        "K\u0131z\u0131rgan",
        "Kezhikan"
    ],
    "wof:name":"Kejikan",
    "wof:placetype":"locality"
},
  "geometry": {"coordinates":[41.0075,37.99167],"type":"Point"}
}