{
  "type": "Feature",
  "properties": {
    "gn:admin1_code":"55.0",
    "gn:asciiname":"Karacaarslan",
    "gn:country_code":"TR",
    "gn:dem":760,
    "gn:feature_class":"P",
    "gn:feature_code":"PPL",
    "gn:name":"Karacaarslan",
    "gn:population":0,
    "gn:timezone":"Europe/Istanbul",
    "iso:country":"TR",
    "name:und_x_variant":[
        "Karaarslan",
        "Karacaarslan"
    ],
    "wof:name":"Karacaarslan",
    "wof:placetype":"locality"
},
  "geometry": {"coordinates":[36.0847,41.19483],"type":"Point"}
}