{
  "type": "Feature",
  "properties": {
    "gn:admin1_code":"20",
    "gn:asciiname":"Golcuk",
    "gn:country_code":"TR",
    "gn:dem":909,
    "gn:feature_class":"P",
    "gn:feature_code":"PPL",
    "gn:name":"G\u00f6lc\u00fck",
    "gn:population":0,
    "gn:timezone":"Europe/Istanbul",
    "iso:country":"TR",
    "name:tur_x_preferred":[
        "G\u00f6lc\u00fck"
    ],
    "wof:name":"Golcuk",
    "wof:placetype":"locality"
},
  "geometry": {"coordinates":[29.78445,37.72253],"type":"Point"}
}