{
  "type": "Feature",
  "properties": {
    "gn:country":"TR",
    "gn:fcode":"PPL",
    "gn:population":1171,
    "iso:country":"TR",
    "name:ceb_x_preferred":[
        "\u00c7ardakl\u0131"
    ],
    "name:che_x_preferred":[
        "\u0427\u0430\u0440\u0434\u0430\u043a\u043b\u0438"
    ],
    "name:deu_x_preferred":[
        "\u00c7ardakl\u0131"
    ],
    "name:eng_x_preferred":[
        "\u00c7ardakl\u0131"
    ],
    "name:kur_x_preferred":[
        "Gund\u00ea Gulan"
    ],
    "name:msa_x_preferred":[
        "\u00c7ardakl\u0131"
    ],
    "name:nld_x_preferred":[
        "\u00c7ardakl\u0131"
    ],
    "name:tat_x_preferred":[
        "\u0427\u0430\u0440\u0434\u0430\u043a\u043b\u044b"
    ],
    "name:tur_x_preferred":[
        "\u00c7ardakl\u0131"
    ],
    "name:vie_x_preferred":[
        "\u00c7ardakl\u0131"
    ],
    "qs:name":"\u00c7ardakl\u0131",
    "qs:photos_9r":0,
    "qs:photos_sr":0,
    "qs:pop_sr":"3",
    "wd:wordcount":55,
    "wof:name":"\u00c7ardakl\u0131",
    "wof:placetype":"locality",
    "wof:population":1171
},
  "geometry": {"coordinates":[42.57028,37.23778],"type":"Point"}
}