{
  "type": "Feature",
  "properties": {
    "gn:country":"TR",
    "gn:fcode":"PPL",
    "gn:population":383,
    "iso:country":"TR",
    "name:tur_x_preferred":[
        "Sugeldi"
    ],
    "qs:name":"Sugeldi",
    "qs:photos_9r":0,
    "qs:photos_sr":0,
    "qs:pop_sr":"2",
    "wof:name":"Sugeldi",
    "wof:placetype":"locality",
    "wof:population":383
},
  "geometry": {"coordinates":[42.99694,37.88028],"type":"Point"}
}