{
  "type": "Feature",
  "properties": {
    "gn:admin1_code":"46",
    "gn:asciiname":"Haciveliusagi",
    "gn:country_code":"TR",
    "gn:dem":289,
    "gn:feature_class":"P",
    "gn:feature_code":"PPL",
    "gn:name":"Hac\u0131veliu\u015fa\u011f\u0131",
    "gn:population":0,
    "gn:timezone":"Europe/Istanbul",
    "iso:country":"TR",
    "wof:name":"Haciveliusagi",
    "wof:placetype":"locality"
},
  "geometry": {"coordinates":[36.34226,37.46717],"type":"Point"}
}