{
  "type": "Feature",
  "properties": {
    "gn:admin1_code":"70.0",
    "gn:asciiname":"Yukari Yigitler",
    "gn:country_code":"TR",
    "gn:dem":1577,
    "gn:feature_class":"P",
    "gn:feature_code":"PPL",
    "gn:name":"Yukar\u0131 Yi\u011fitler",
    "gn:population":0,
    "gn:timezone":"Europe/Istanbul",
    "iso:country":"TR",
    "wof:name":"Yukari Yigitler",
    "wof:placetype":"locality"
},
  "geometry": {"coordinates":[44.57467000000001,37.23647],"type":"Point"}
}