{
  "type": "Feature",
  "properties": {
    "gn:admin1_code":"33",
    "gn:asciiname":"Islamkoy",
    "gn:cc2":"TR",
    "gn:country_code":"TR",
    "gn:dem":971,
    "gn:feature_class":"P",
    "gn:feature_code":"PPL",
    "gn:name":"\u0130sl\u00e2mk\u00f6y",
    "gn:population":0,
    "gn:timezone":"Europe/Istanbul",
    "iso:country":"TR",
    "name:und_x_variant":[
        "\u0130sl\u00e2m",
        "\u0130sl\u00e2mk\u00f6y"
    ],
    "wof:name":"Islamkoy",
    "wof:placetype":"locality"
},
  "geometry": {"coordinates":[30.655,37.92444],"type":"Point"}
}