{
  "type": "Feature",
  "properties": {
    "gn:admin1_code":"2.0",
    "gn:asciiname":"Kustepe",
    "gn:country_code":"TR",
    "gn:dem":688,
    "gn:feature_class":"P",
    "gn:feature_code":"PPL",
    "gn:name":"Ku\u015ftepe",
    "gn:population":0,
    "gn:timezone":"Europe/Istanbul",
    "iso:country":"TR",
    "name:tur_x_preferred":[
        "Ku\u015ftepe"
    ],
    "wof:name":"Kustepe",
    "wof:placetype":"locality"
},
  "geometry": {"coordinates":[38.42824,37.7436],"type":"Point"}
}