{
  "type": "Feature",
  "properties": {
    "gn:admin1_code":"58",
    "gn:asciiname":"Beyyurdu",
    "gn:country_code":"TR",
    "gn:dem":1646,
    "gn:feature_class":"P",
    "gn:feature_code":"PPL",
    "gn:name":"Beyyurdu",
    "gn:population":0,
    "gn:timezone":"Europe/Istanbul",
    "iso:country":"TR",
    "wof:name":"Beyyurdu",
    "wof:placetype":"locality"
},
  "geometry": {"coordinates":[36.19648,39.5188],"type":"Point"}
}