{
  "type": "Feature",
  "properties": {
    "gn:admin1_code":"89.0",
    "gn:asciiname":"Goloren",
    "gn:country_code":"TR",
    "gn:dem":1104,
    "gn:feature_class":"P",
    "gn:feature_code":"PPL",
    "gn:name":"G\u00f6l\u00f6ren",
    "gn:population":0,
    "gn:timezone":"Europe/Istanbul",
    "iso:country":"TR",
    "name:und_x_variant":[
        "G\u00f6lveren",
        "G\u00f6lviran",
        "G\u00f6l\u00f6ren"
    ],
    "wof:name":"Goloren",
    "wof:placetype":"locality"
},
  "geometry": {"coordinates":[32.55801,41.07903],"type":"Point"}
}