{
  "type": "Feature",
  "properties": {
    "gn:admin1_code":"57.0",
    "gn:asciiname":"Alacati",
    "gn:country_code":"TR",
    "gn:dem":1075,
    "gn:feature_class":"P",
    "gn:feature_code":"PPL",
    "gn:name":"Ala\u00e7at\u0131",
    "gn:population":0,
    "gn:timezone":"Europe/Istanbul",
    "iso:country":"TR",
    "wof:name":"Alacati",
    "wof:placetype":"locality"
},
  "geometry": {"coordinates":[34.55,41.36667],"type":"Point"}
}