{
  "type": "Feature",
  "properties": {
    "gn:admin1_code":"63",
    "gn:asciiname":"Terzi",
    "gn:country_code":"TR",
    "gn:dem":640,
    "gn:feature_class":"P",
    "gn:feature_code":"PPL",
    "gn:name":"Terzi",
    "gn:population":0,
    "gn:timezone":"Europe/Istanbul",
    "iso:country":"TR",
    "name:tur_x_preferred":[
        "Terzi"
    ],
    "wof:name":"Terzi",
    "wof:placetype":"locality"
},
  "geometry": {"coordinates":[39.45184,37.22274],"type":"Point"}
}