{
  "type": "Feature",
  "properties": {
    "gn:admin1_code":"13",
    "gn:asciiname":"Yukari Karaboy",
    "gn:country_code":"TR",
    "gn:dem":1724,
    "gn:feature_class":"P",
    "gn:feature_code":"PPL",
    "gn:name":"Yukar\u0131 Karaboy",
    "gn:population":0,
    "gn:timezone":"Europe/Istanbul",
    "iso:country":"TR",
    "name:tur_x_preferred":[
        "Yukar\u0131 Karaboy"
    ],
    "name:und_x_variant":[
        "Karabuyu\u00fclya",
        "Karaboyulya",
        "Yukar\u0131karaboy"
    ],
    "wof:name":"Yukari Karaboy",
    "wof:placetype":"locality"
},
  "geometry": {"coordinates":[41.98284,38.46595],"type":"Point"}
}