{
  "type": "Feature",
  "properties": {
    "gn:admin1_code":"68",
    "gn:asciiname":"Akyarma",
    "gn:country_code":"TR",
    "gn:dem":1458,
    "gn:feature_class":"P",
    "gn:feature_code":"PPL",
    "gn:name":"Akyarma",
    "gn:population":0,
    "gn:timezone":"Europe/Istanbul",
    "iso:country":"TR",
    "wof:name":"Akyarma",
    "wof:placetype":"locality"
},
  "geometry": {"coordinates":[32.43333,40.6333],"type":"Point"}
}