{
  "type": "Feature",
  "properties": {
    "gn:admin1_code":"20",
    "gn:asciiname":"Suller",
    "gn:country_code":"TR",
    "gn:dem":860,
    "gn:feature_class":"P",
    "gn:feature_code":"PPL",
    "gn:name":"S\u00fcller",
    "gn:population":0,
    "gn:timezone":"Europe/Istanbul",
    "iso:country":"TR",
    "wof:name":"Suller",
    "wof:placetype":"locality"
},
  "geometry": {"coordinates":[29.47639,38.15972],"type":"Point"}
}