{
  "type": "Feature",
  "properties": {
    "gn:admin1_code":"57.0",
    "gn:asciiname":"Meydan",
    "gn:country_code":"TR",
    "gn:dem":371,
    "gn:feature_class":"P",
    "gn:feature_code":"PPL",
    "gn:name":"Meydan",
    "gn:population":0,
    "gn:timezone":"Europe/Istanbul",
    "iso:country":"TR",
    "name:tur_x_preferred":[
        "Meydan"
    ],
    "name:und_x_variant":[
        "\u00d6k\u00fcz"
    ],
    "wof:name":"Meydan",
    "wof:placetype":"locality"
},
  "geometry": {"coordinates":[34.82634,41.86727],"type":"Point"}
}