{
  "type": "Feature",
  "properties": {
    "gn:admin1_code":"83",
    "gn:asciiname":"Karaburclu",
    "gn:country_code":"TR",
    "gn:dem":612,
    "gn:feature_class":"P",
    "gn:feature_code":"PPL",
    "gn:name":"Karabur\u00e7lu",
    "gn:population":0,
    "gn:timezone":"Europe/Istanbul",
    "iso:country":"TR",
    "name:tur_x_preferred":[
        "Karabur\u00e7lu"
    ],
    "wof:name":"Karaburclu",
    "wof:placetype":"locality"
},
  "geometry": {"coordinates":[36.68538,37.14065],"type":"Point"}
}