{
  "type": "Feature",
  "properties": {
    "gn:admin1_code":"03",
    "gn:asciiname":"Kazvankuyucak",
    "gn:country_code":"TR",
    "gn:dem":991,
    "gn:feature_class":"P",
    "gn:feature_code":"PPL",
    "gn:name":"Kazvankuyucak",
    "gn:population":0,
    "gn:timezone":"Europe/Istanbul",
    "iso:country":"TR",
    "wof:name":"Kazvankuyucak",
    "wof:placetype":"locality"
},
  "geometry": {"coordinates":[30.17768,38.49788],"type":"Point"}
}