{
  "type": "Feature",
  "properties": {
    "gn:admin1_code":"79",
    "gn:asciiname":"Kecili",
    "gn:country_code":"TR",
    "gn:dem":1001,
    "gn:feature_class":"P",
    "gn:feature_code":"PPL",
    "gn:name":"Ke\u00e7ili",
    "gn:population":0,
    "gn:timezone":"Europe/Istanbul",
    "iso:country":"TR",
    "wof:name":"Kecili",
    "wof:placetype":"locality"
},
  "geometry": {"coordinates":[33.5355,39.99316],"type":"Point"}
}