{
  "type": "Feature",
  "properties": {
    "gn:admin1_code":"04",
    "gn:asciiname":"Asagi Daloren",
    "gn:country_code":"TR",
    "gn:dem":2103,
    "gn:feature_class":"P",
    "gn:feature_code":"PPL",
    "gn:name":"A\u015fa\u011f\u0131 Dal\u00f6ren",
    "gn:population":0,
    "gn:timezone":"Europe/Istanbul",
    "iso:country":"TR",
    "name:tur_x_preferred":[
        "A\u015fa\u011f\u0131 Dal\u00f6ren"
    ],
    "name:und_x_variant":[
        "A\u015fa\u011f\u0131 Biligan",
        "A\u015fa\u011f\u0131dal\u00f6ren"
    ],
    "wof:name":"Asagi Daloren",
    "wof:placetype":"locality"
},
  "geometry": {"coordinates":[43.59787,39.42694],"type":"Point"}
}