{
  "type": "Feature",
  "properties": {
    "gn:admin1_code":"21.0",
    "gn:asciiname":"Gokce",
    "gn:country_code":"TR",
    "gn:dem":974,
    "gn:feature_class":"P",
    "gn:feature_code":"PPL",
    "gn:name":"G\u00f6k\u00e7e",
    "gn:population":0,
    "gn:timezone":"Europe/Istanbul",
    "iso:country":"TR",
    "name:tur_x_preferred":[
        "G\u00f6k\u00e7e"
    ],
    "wof:name":"Gokce",
    "wof:placetype":"locality"
},
  "geometry": {"coordinates":[40.52184000000001,38.34394],"type":"Point"}
}