{
  "type": "Feature",
  "properties": {
    "gn:admin1_code":"28",
    "gn:asciiname":"Adakoy",
    "gn:country_code":"TR",
    "gn:dem":277,
    "gn:feature_class":"P",
    "gn:feature_code":"PPL",
    "gn:name":"Adak\u00f6y",
    "gn:population":0,
    "gn:timezone":"Europe/Istanbul",
    "iso:country":"TR",
    "name:tur_x_preferred":[
        "Adak\u00f6y"
    ],
    "wof:name":"Adakoy",
    "wof:placetype":"locality"
},
  "geometry": {"coordinates":[39.09766,40.99737],"type":"Point"}
}