{
  "type": "Feature",
  "properties": {
    "gn:admin1_code":"14.0",
    "gn:asciiname":"Calislar",
    "gn:country_code":"TR",
    "gn:dem":1191,
    "gn:feature_class":"P",
    "gn:feature_code":"PPL",
    "gn:name":"\u00c7al\u0131\u015flar",
    "gn:population":0,
    "gn:timezone":"Europe/Istanbul",
    "iso:country":"TR",
    "wof:name":"Calislar",
    "wof:placetype":"locality"
},
  "geometry": {"coordinates":[32.40596,40.79009],"type":"Point"}
}