{
  "type": "Feature",
  "properties": {
    "gn:admin1_code":"72",
    "gn:asciiname":"Yuva",
    "gn:country_code":"TR",
    "gn:dem":994,
    "gn:feature_class":"P",
    "gn:feature_code":"PPL",
    "gn:name":"Yuva",
    "gn:population":0,
    "gn:timezone":"Europe/Istanbul",
    "iso:country":"TR",
    "name:ben_x_preferred":[
        "\u09af\u09c1\u09ac\u09be"
    ],
    "name:dan_x_preferred":[
        "Yuva"
    ],
    "name:deu_x_preferred":[
        "Yuva"
    ],
    "name:fas_x_preferred":[
        "\u062c\u0648\u0627\u0646\u06cc"
    ],
    "name:fin_x_preferred":[
        "Yuva"
    ],
    "name:fra_x_preferred":[
        "Yuva"
    ],
    "name:hun_x_preferred":[
        "Juva"
    ],
    "name:ind_x_preferred":[
        "Yuva"
    ],
    "name:ita_x_preferred":[
        "Yuva"
    ],
    "name:new_x_preferred":[
        "\u092f\u0941\u0935\u093e"
    ],
    "name:pol_x_preferred":[
        "Yuva"
    ],
    "name:tam_x_preferred":[
        "\u0baf\u0bc1\u0bb5\u0bbe"
    ],
    "name:tur_x_preferred":[
        "Yuva"
    ],
    "wof:name":"Yuva",
    "wof:placetype":"locality"
},
  "geometry": {"coordinates":[40.4429,37.45],"type":"Point"}
}