{
  "type": "Feature",
  "properties": {
    "gn:admin1_code":"60.0",
    "gn:asciiname":"Golburnu",
    "gn:country_code":"TR",
    "gn:dem":1320,
    "gn:feature_class":"P",
    "gn:feature_code":"PPL",
    "gn:name":"G\u00f6lburnu",
    "gn:population":0,
    "gn:timezone":"Europe/Istanbul",
    "iso:country":"TR",
    "name:tur_x_preferred":[
        "G\u00f6lburnu"
    ],
    "name:und_x_variant":[
        "G\u00fclburnu"
    ],
    "wof:name":"Golburnu",
    "wof:placetype":"locality"
},
  "geometry": {"coordinates":[37.51309000000001,40.2855],"type":"Point"}
}