{
  "type": "Feature",
  "properties": {
    "gn:admin1_code":"21",
    "gn:asciiname":"Kavsan",
    "gn:country_code":"TR",
    "gn:dem":614,
    "gn:feature_class":"P",
    "gn:feature_code":"PPL",
    "gn:name":"Kav\u015fan",
    "gn:population":0,
    "gn:timezone":"Europe/Istanbul",
    "iso:country":"TR",
    "wof:name":"Kavsan",
    "wof:placetype":"locality"
},
  "geometry": {"coordinates":[40.35,38.03333],"type":"Point"}
}