{
  "type": "Feature",
  "properties": {
    "gn:admin1_code":"49",
    "gn:asciiname":"Bugdayli",
    "gn:country_code":"TR",
    "gn:dem":1749,
    "gn:feature_class":"P",
    "gn:feature_code":"PPL",
    "gn:name":"Bu\u011fdayl\u0131",
    "gn:population":0,
    "gn:timezone":"Europe/Istanbul",
    "iso:country":"TR",
    "name:tur_x_preferred":[
        "Bu\u011fdayl\u0131"
    ],
    "name:und_x_variant":[
        "La\u00e7kan"
    ],
    "wof:name":"Bugdayli",
    "wof:placetype":"locality"
},
  "geometry": {"coordinates":[41.28333,38.68333],"type":"Point"}
}