{
  "type": "Feature",
  "properties": {
    "gn:admin1_code":"89",
    "gn:asciiname":"Hatipler",
    "gn:country_code":"TR",
    "gn:dem":263,
    "gn:feature_class":"P",
    "gn:feature_code":"PPL",
    "gn:name":"Hatipler",
    "gn:population":0,
    "gn:timezone":"Europe/Istanbul",
    "iso:country":"TR",
    "wof:name":"Hatipler",
    "wof:placetype":"locality"
},
  "geometry": {"coordinates":[32.27813,41.22495],"type":"Point"}
}