{
  "type": "Feature",
  "properties": {
    "gn:admin1_code":"84.0",
    "gn:asciiname":"Akmazdam",
    "gn:country_code":"TR",
    "gn:dem":2132,
    "gn:feature_class":"P",
    "gn:feature_code":"PPL",
    "gn:name":"Akmazdam",
    "gn:population":0,
    "gn:timezone":"Europe/Istanbul",
    "iso:country":"TR",
    "name:tur_x_preferred":[
        "Akmazdam"
    ],
    "wof:name":"Akmazdam",
    "wof:placetype":"locality"
},
  "geometry": {"coordinates":[43.22714000000001,40.90518],"type":"Point"}
}