{
  "type": "Feature",
  "properties": {
    "gn:admin1_code":"5.0",
    "gn:asciiname":"Belevi",
    "gn:country_code":"TR",
    "gn:dem":413,
    "gn:feature_class":"P",
    "gn:feature_code":"PPL",
    "gn:name":"Belevi",
    "gn:population":0,
    "gn:timezone":"Europe/Istanbul",
    "iso:country":"TR",
    "wof:name":"Belevi",
    "wof:placetype":"locality"
},
  "geometry": {"coordinates":[36.2193,40.69127],"type":"Point"}
}