{
  "type": "Feature",
  "properties": {
    "gn:admin1_code":"63.0",
    "gn:admin2_code":"439166.0",
    "gn:asciiname":"Suvacik",
    "gn:cc2":"TR",
    "gn:country_code":"TR",
    "gn:dem":375,
    "gn:feature_class":"P",
    "gn:feature_code":"PPL",
    "gn:name":"Suvac\u0131k",
    "gn:population":0,
    "gn:timezone":"Europe/Istanbul",
    "iso:country":"TR",
    "name:tur_x_historical":[
        "Savac\u0131k"
    ],
    "name:tur_x_preferred":[
        "Suvac\u0131k"
    ],
    "name:tur_x_variant":[
        "Suyac\u0131k",
        "Savac\u0131k"
    ],
    "name:und_x_variant":[
        "S\u0131vac\u0131k",
        "Syvadzhik"
    ],
    "wof:name":"Suvacik",
    "wof:placetype":"locality"
},
  "geometry": {"coordinates":[39.04028,36.94333],"type":"Point"}
}