{
  "type": "Feature",
  "properties": {
    "gn:admin1_code":"37.0",
    "gn:asciiname":"Yurttepe",
    "gn:country_code":"TR",
    "gn:dem":778,
    "gn:feature_class":"P",
    "gn:feature_code":"PPL",
    "gn:name":"Yurttepe",
    "gn:population":0,
    "gn:timezone":"Europe/Istanbul",
    "iso:country":"TR",
    "name:und_x_variant":[
        "Giremez",
        "Yurttepe"
    ],
    "wof:name":"Yurttepe",
    "wof:placetype":"locality"
},
  "geometry": {"coordinates":[33.3875,41.25401],"type":"Point"}
}