{
  "type": "Feature",
  "properties": {
    "gn:admin1_code":"57.0",
    "gn:asciiname":"Hizircayi",
    "gn:country_code":"TR",
    "gn:dem":83,
    "gn:feature_class":"P",
    "gn:feature_code":"PPL",
    "gn:name":"H\u0131z\u0131r\u00e7ay\u0131",
    "gn:population":0,
    "gn:timezone":"Europe/Istanbul",
    "iso:country":"TR",
    "wof:name":"Hizircayi",
    "wof:placetype":"locality"
},
  "geometry": {"coordinates":[35.20393,41.7651],"type":"Point"}
}