{
  "type": "Feature",
  "properties": {
    "gn:admin1_code":"35",
    "gn:asciiname":"Inesir",
    "gn:country_code":"TR",
    "gn:dem":376,
    "gn:feature_class":"P",
    "gn:feature_code":"PPL",
    "gn:name":"\u0130ne\u015fir",
    "gn:population":0,
    "gn:timezone":"Europe/Istanbul",
    "iso:country":"TR",
    "name:tur_x_preferred":[
        "\u0130ne\u015fir"
    ],
    "wof:name":"Inesir",
    "wof:placetype":"locality"
},
  "geometry": {"coordinates":[27.38262000000001,39.33491],"type":"Point"}
}