{
  "type": "Feature",
  "properties": {
    "gn:admin1_code":"76.0",
    "gn:asciiname":"Cimenli",
    "gn:country_code":"TR",
    "gn:dem":628,
    "gn:feature_class":"P",
    "gn:feature_code":"PPL",
    "gn:name":"Cimenli",
    "gn:population":0,
    "gn:timezone":"Europe/Istanbul",
    "iso:country":"TR",
    "wof:name":"Cimenli",
    "wof:placetype":"locality"
},
  "geometry": {"coordinates":[41.63175,37.78148],"type":"Point"}
}