{
  "type": "Feature",
  "properties": {
    "gn:admin1_code":"28.0",
    "gn:asciiname":"Iklikci",
    "gn:country_code":"TR",
    "gn:dem":623,
    "gn:feature_class":"P",
    "gn:feature_code":"PPL",
    "gn:name":"Ikl\u0131k\u00e7\u0131",
    "gn:population":0,
    "gn:timezone":"Europe/Istanbul",
    "iso:country":"TR",
    "wof:name":"Iklikci",
    "wof:placetype":"locality"
},
  "geometry": {"coordinates":[38.47967,40.80524000000001],"type":"Point"}
}