{
  "type": "Feature",
  "properties": {
    "gn:admin1_code":"63",
    "gn:asciiname":"Kucak",
    "gn:country_code":"TR",
    "gn:dem":693,
    "gn:feature_class":"P",
    "gn:feature_code":"PPL",
    "gn:name":"Kucak",
    "gn:population":0,
    "gn:timezone":"Europe/Istanbul",
    "iso:country":"TR",
    "name:tur_x_preferred":[
        "Kucak"
    ],
    "wof:name":"Kucak",
    "wof:placetype":"locality"
},
  "geometry": {"coordinates":[39.67036,37.34361],"type":"Point"}
}