{
  "type": "Feature",
  "properties": {
    "gn:admin1_code":"43",
    "gn:asciiname":"Koreken",
    "gn:country_code":"TR",
    "gn:dem":1396,
    "gn:feature_class":"P",
    "gn:feature_code":"PPL",
    "gn:name":"K\u00f6reken",
    "gn:population":0,
    "gn:timezone":"Europe/Istanbul",
    "iso:country":"TR",
    "wof:name":"Koreken",
    "wof:placetype":"locality"
},
  "geometry": {"coordinates":[29.72202,39.41029],"type":"Point"}
}