{
  "type": "Feature",
  "properties": {
    "gn:admin1_code":"31",
    "gn:asciiname":"Yilani Iskan",
    "gn:country_code":"TR",
    "gn:dem":291,
    "gn:feature_class":"P",
    "gn:feature_code":"PPL",
    "gn:name":"Y\u0131lan\u0131 \u0130skan",
    "gn:population":0,
    "gn:timezone":"Europe/Istanbul",
    "iso:country":"TR",
    "name:tur_x_preferred":[
        "Y\u0131lan\u0131 \u0130skan"
    ],
    "wof:name":"Yilani Iskan",
    "wof:placetype":"locality"
},
  "geometry": {"coordinates":[36.33304,36.50498],"type":"Point"}
}