{
  "type": "Feature",
  "properties": {
    "gn:admin1_code":"12",
    "gn:asciiname":"Akcayurt",
    "gn:country_code":"TR",
    "gn:dem":829,
    "gn:feature_class":"P",
    "gn:feature_code":"PPL",
    "gn:name":"Ak\u00e7ayurt",
    "gn:population":0,
    "gn:timezone":"Europe/Istanbul",
    "iso:country":"TR",
    "name:und_x_variant":[
        "\u015eelheydan",
        "\u015eelhidan",
        "Ak\u00e7ayurt",
        "\u015eellihaydan"
    ],
    "wof:name":"Akcayurt",
    "wof:placetype":"locality"
},
  "geometry": {"coordinates":[40.36951,38.48512],"type":"Point"}
}