{
  "type": "Feature",
  "properties": {
    "iso:country":"TR",
    "name:eng_x_preferred":[
        "Ertugrul Gazi"
    ],
    "name:tur_x_preferred":[
        "Ertu\u011frul Gazi"
    ],
    "name:tur_x_variant":[
        "Ertu\u011frulgazi"
    ],
    "wof:name":"Ertugrul Gazi",
    "wof:placetype":"neighbourhood"
},
  "geometry": {"coordinates":[29.26342280318906,40.91967447119367],"type":"Point"}
}