{
  "type": "Feature",
  "properties": {
    "gn:admin1_code":"59.0",
    "gn:asciiname":"Ishakca",
    "gn:country_code":"TR",
    "gn:dem":163,
    "gn:feature_class":"P",
    "gn:feature_code":"PPL",
    "gn:name":"\u0130shak\u00e7a",
    "gn:population":0,
    "gn:timezone":"Europe/Istanbul",
    "iso:country":"TR",
    "name:und_x_variant":[
        "\u0130sakca",
        "\u0130shak\u00e7a"
    ],
    "wof:name":"Ishakca",
    "wof:placetype":"locality"
},
  "geometry": {"coordinates":[26.94585,40.9087],"type":"Point"}
}