{
  "type": "Feature",
  "properties": {
    "gn:admin1_code":"21",
    "gn:asciiname":"Vito",
    "gn:country_code":"TR",
    "gn:dem":1180,
    "gn:feature_class":"P",
    "gn:feature_code":"PPL",
    "gn:name":"Vito",
    "gn:population":0,
    "gn:timezone":"Europe/Istanbul",
    "iso:country":"TR",
    "name:ita_x_preferred":[
        "Vito"
    ],
    "name:lat_x_preferred":[
        "Vito"
    ],
    "name:slv_x_preferred":[
        "Vito"
    ],
    "name:und_x_variant":[
        "\u015eahverdiyan"
    ],
    "wof:name":"Vito",
    "wof:placetype":"locality"
},
  "geometry": {"coordinates":[40.5697,38.566],"type":"Point"}
}