{
  "type": "Feature",
  "properties": {
    "gn:admin1_code":"12",
    "gn:asciiname":"Ardictepe",
    "gn:country_code":"TR",
    "gn:dem":1336,
    "gn:feature_class":"P",
    "gn:feature_code":"PPL",
    "gn:name":"Ard\u0131\u00e7tepe",
    "gn:population":0,
    "gn:timezone":"Europe/Istanbul",
    "iso:country":"TR",
    "name:und_x_variant":[
        "Kemalan",
        "Kemalanlar",
        "Ard\u0131\u00e7tepe"
    ],
    "wof:name":"Ardictepe",
    "wof:placetype":"locality"
},
  "geometry": {"coordinates":[40.49237,38.82043],"type":"Point"}
}