{
  "type": "Feature",
  "properties": {
    "gn:admin1_code":"68.0",
    "gn:asciiname":"Balcilar",
    "gn:country_code":"TR",
    "gn:dem":1245,
    "gn:feature_class":"P",
    "gn:feature_code":"PPL",
    "gn:name":"Balc\u0131lar",
    "gn:population":0,
    "gn:timezone":"Europe/Istanbul",
    "iso:country":"TR",
    "name:und_x_variant":[
        "K\u00f6sten",
        "Balc\u0131lar"
    ],
    "wof:name":"Balcilar",
    "wof:placetype":"locality"
},
  "geometry": {"coordinates":[32.79278,40.41777],"type":"Point"}
}