{
  "type": "Feature",
  "properties": {
    "gn:admin1_code":"44.0",
    "gn:asciiname":"Beydagi",
    "gn:country_code":"TR",
    "gn:dem":1208,
    "gn:feature_class":"P",
    "gn:feature_code":"PPL",
    "gn:name":"Beyda\u011f\u0131",
    "gn:population":0,
    "gn:timezone":"Europe/Istanbul",
    "iso:country":"TR",
    "name:tur_x_preferred":[
        "Beyda\u011f\u0131"
    ],
    "wof:name":"Beydagi",
    "wof:placetype":"locality"
},
  "geometry": {"coordinates":[38.45793,38.28617],"type":"Point"}
}