{
  "type": "Feature",
  "properties": {
    "gn:admin1_code":"07",
    "gn:asciiname":"Hacisekiler",
    "gn:country_code":"TR",
    "gn:dem":107,
    "gn:feature_class":"P",
    "gn:feature_code":"PPL",
    "gn:name":"Hac\u0131sekiler",
    "gn:population":0,
    "gn:timezone":"Europe/Istanbul",
    "iso:country":"TR",
    "name:msa_x_preferred":[
        "Hac\u0131sekiler"
    ],
    "name:tur_x_preferred":[
        "Hac\u0131sekililer"
    ],
    "name:und_x_variant":[
        "Hac\u0131sekiler"
    ],
    "name:vie_x_preferred":[
        "Hac\u0131sekililer"
    ],
    "wof:name":"Hacisekiler",
    "wof:placetype":"locality"
},
  "geometry": {"coordinates":[30.51953,36.84202],"type":"Point"}
}