{
  "type": "Feature",
  "properties": {
    "gn:admin1_code":"28.0",
    "gn:asciiname":"Yukari Bogali",
    "gn:country_code":"TR",
    "gn:dem":248,
    "gn:feature_class":"P",
    "gn:feature_code":"PPL",
    "gn:name":"Yukar\u0131 Bo\u011fal\u0131",
    "gn:population":0,
    "gn:timezone":"Europe/Istanbul",
    "iso:country":"TR",
    "name:tur_x_preferred":[
        "Yukar\u0131 Bo\u011fal\u0131"
    ],
    "name:und_x_variant":[
        "Bu\u011fal\u0131bal\u00e2",
        "Bo\u011fal\u0131bal\u00e2",
        "Yukar\u0131bo\u011fal\u0131"
    ],
    "wof:name":"Yukari Bogali",
    "wof:placetype":"locality"
},
  "geometry": {"coordinates":[38.93748,40.99056],"type":"Point"}
}