{
  "type": "Feature",
  "properties": {
    "gn:admin1_code":"25",
    "gn:asciiname":"Danzut",
    "gn:country_code":"TR",
    "gn:dem":1834,
    "gn:feature_class":"P",
    "gn:feature_code":"PPL",
    "gn:name":"Danzut",
    "gn:population":0,
    "gn:timezone":"Europe/Istanbul",
    "iso:country":"TR",
    "wof:name":"Danzut",
    "wof:placetype":"locality"
},
  "geometry": {"coordinates":[40.68333,39.96667],"type":"Point"}
}