{
  "type": "Feature",
  "properties": {
    "gn:admin1_code":"49",
    "gn:asciiname":"Olurdere",
    "gn:country_code":"TR",
    "gn:dem":1446,
    "gn:feature_class":"P",
    "gn:feature_code":"PPL",
    "gn:name":"Olurdere",
    "gn:population":0,
    "gn:timezone":"Europe/Istanbul",
    "iso:country":"TR",
    "name:tur_x_preferred":[
        "Olurdere"
    ],
    "wof:name":"Olurdere",
    "wof:placetype":"locality"
},
  "geometry": {"coordinates":[41.93001,38.9917],"type":"Point"}
}