{
  "type": "Feature",
  "properties": {
    "gn:admin1_code":"11.0",
    "gn:asciiname":"Gunyurdu",
    "gn:country_code":"TR",
    "gn:dem":821,
    "gn:feature_class":"P",
    "gn:feature_code":"PPL",
    "gn:name":"G\u00fcnyurdu",
    "gn:population":0,
    "gn:timezone":"Europe/Istanbul",
    "iso:country":"TR",
    "name:und_x_variant":[
        "Bakraz",
        "Bakras",
        "G\u00fcnyurdu"
    ],
    "wof:name":"Gunyurdu",
    "wof:placetype":"locality"
},
  "geometry": {"coordinates":[29.84387000000001,40.04302],"type":"Point"}
}