{
  "type": "Feature",
  "properties": {
    "gn:admin1_code":"12",
    "gn:asciiname":"Gurpinar",
    "gn:country_code":"TR",
    "gn:dem":1384,
    "gn:feature_class":"P",
    "gn:feature_code":"PPL",
    "gn:name":"G\u00fcrp\u0131nar",
    "gn:population":0,
    "gn:timezone":"Europe/Istanbul",
    "iso:country":"TR",
    "name:tur_x_preferred":[
        "G\u00fcrp\u0131nar"
    ],
    "name:und_x_variant":[
        "Lotan"
    ],
    "wof:name":"Gurpinar",
    "wof:placetype":"locality"
},
  "geometry": {"coordinates":[40.45247,38.78041],"type":"Point"}
}