{
  "type": "Feature",
  "properties": {
    "gn:admin1_code":"58",
    "gn:asciiname":"Bulak",
    "gn:country_code":"TR",
    "gn:dem":1714,
    "gn:feature_class":"P",
    "gn:feature_code":"PPL",
    "gn:name":"Bulak",
    "gn:population":0,
    "gn:timezone":"Europe/Istanbul",
    "iso:country":"TR",
    "name:tur_x_preferred":[
        "Bulak"
    ],
    "wof:name":"Bulak",
    "wof:placetype":"locality"
},
  "geometry": {"coordinates":[37.75,39.18333],"type":"Point"}
}