{
  "type": "Feature",
  "properties": {
    "gn:admin1_code":"44",
    "gn:asciiname":"Asagikoy",
    "gn:country_code":"TR",
    "gn:dem":1428,
    "gn:feature_class":"P",
    "gn:feature_code":"PPL",
    "gn:name":"A\u015fa\u011f\u0131k\u00f6y",
    "gn:population":0,
    "gn:timezone":"Europe/Istanbul",
    "iso:country":"TR",
    "name:tur_x_preferred":[
        "A\u015fa\u011f\u0131k\u00f6y"
    ],
    "wof:name":"Asagikoy",
    "wof:placetype":"locality"
},
  "geometry": {"coordinates":[38.31805,38.14159],"type":"Point"}
}