{
  "type": "Feature",
  "properties": {
    "gn:admin1_code":"82.0",
    "gn:asciiname":"Calcioren",
    "gn:country_code":"TR",
    "gn:dem":1485,
    "gn:feature_class":"P",
    "gn:feature_code":"PPL",
    "gn:name":"\u00c7al\u00e7\u0131\u00f6ren",
    "gn:population":0,
    "gn:timezone":"Europe/Istanbul",
    "iso:country":"TR",
    "wof:name":"Calcioren",
    "wof:placetype":"locality"
},
  "geometry": {"coordinates":[32.95802,40.8659],"type":"Point"}
}