{
  "type": "Feature",
  "properties": {
    "gn:admin1_code":"31.0",
    "gn:asciiname":"Kanlidere",
    "gn:country_code":"TR",
    "gn:dem":388,
    "gn:feature_class":"P",
    "gn:feature_code":"PPL",
    "gn:name":"Kanl\u0131dere",
    "gn:population":0,
    "gn:timezone":"Europe/Istanbul",
    "iso:country":"TR",
    "name:und_x_variant":[
        "Kanlydere",
        "Kanl\u0131dere"
    ],
    "wof:name":"Kanlidere",
    "wof:placetype":"locality"
},
  "geometry": {"coordinates":[36.22167,36.445],"type":"Point"}
}