{
  "type": "Feature",
  "properties": {
    "gn:admin1_code":"25.0",
    "gn:asciiname":"Yellitepe",
    "gn:country_code":"TR",
    "gn:dem":1877,
    "gn:feature_class":"P",
    "gn:feature_code":"PPL",
    "gn:name":"Yellitepe",
    "gn:population":0,
    "gn:timezone":"Europe/Istanbul",
    "iso:country":"TR",
    "name:tur_x_preferred":[
        "Yellitepe"
    ],
    "name:und_x_variant":[
        "Yeliltepe",
        "K\u00e2rinkos"
    ],
    "wof:name":"Yellitepe",
    "wof:placetype":"locality"
},
  "geometry": {"coordinates":[41.38234,40.28957],"type":"Point"}
}