{
  "type": "Feature",
  "properties": {
    "gn:admin1_code":"66",
    "gn:asciiname":"Boyalik",
    "gn:country_code":"TR",
    "gn:dem":940,
    "gn:feature_class":"P",
    "gn:feature_code":"PPL",
    "gn:name":"Boyal\u0131k",
    "gn:population":0,
    "gn:timezone":"Europe/Istanbul",
    "iso:country":"TR",
    "wof:name":"Boyalik",
    "wof:placetype":"locality"
},
  "geometry": {"coordinates":[35.75528,39.88412],"type":"Point"}
}