{
  "type": "Feature",
  "properties": {
    "gn:admin1_code":"87.0",
    "gn:asciiname":"Kirsinler",
    "gn:country_code":"TR",
    "gn:dem":462,
    "gn:feature_class":"P",
    "gn:feature_code":"PPL",
    "gn:name":"Kirsinler",
    "gn:population":0,
    "gn:timezone":"Europe/Istanbul",
    "iso:country":"TR",
    "name:und_x_variant":[
        "Girsin",
        "Kirsin",
        "Kirsinler"
    ],
    "wof:name":"Kirsinler",
    "wof:placetype":"locality"
},
  "geometry": {"coordinates":[32.42684000000001,41.4625],"type":"Point"}
}