{
  "type": "Feature",
  "properties": {
    "gn:admin1_code":"13",
    "gn:asciiname":"Alan",
    "gn:country_code":"TR",
    "gn:dem":2056,
    "gn:feature_class":"P",
    "gn:feature_code":"PPL",
    "gn:name":"Alan",
    "gn:population":0,
    "gn:timezone":"Europe/Istanbul",
    "iso:country":"TR",
    "name:aze_x_preferred":[
        "Alan"
    ],
    "name:bre_x_preferred":[
        "Alan"
    ],
    "name:ceb_x_preferred":[
        "Alan"
    ],
    "name:deu_x_preferred":[
        "Alan"
    ],
    "name:fas_x_preferred":[
        "\u0622\u0644\u0627\u0646"
    ],
    "name:fra_x_preferred":[
        "Alan"
    ],
    "name:hye_x_preferred":[
        "\u0531\u056c\u0561\u0576"
    ],
    "name:nld_x_preferred":[
        "Alan"
    ],
    "name:por_x_preferred":[
        "Alan"
    ],
    "name:rus_x_preferred":[
        "\u0410\u043b\u0430\u043d"
    ],
    "name:slk_x_preferred":[
        "Alan"
    ],
    "name:slv_x_preferred":[
        "Alan"
    ],
    "name:spa_x_preferred":[
        "Alan"
    ],
    "name:srp_x_preferred":[
        "\u0410\u043b\u0430\u043d"
    ],
    "name:swe_x_preferred":[
        "Alan"
    ],
    "name:tat_x_preferred":[
        "\u0410\u043b\u0430\u043d"
    ],
    "name:tur_x_preferred":[
        "Alan"
    ],
    "name:ukr_x_preferred":[
        "\u0410\u043b\u0430\u043d"
    ],
    "name:und_x_variant":[
        "Alank\u00f6y"
    ],
    "wof:name":"Alan",
    "wof:placetype":"locality"
},
  "geometry": {"coordinates":[42.7443,38.34473],"type":"Point"}
}