{
  "type": "Feature",
  "properties": {
    "gn:admin1_code":"13",
    "gn:asciiname":"Alan",
    "gn:country_code":"TR",
    "gn:dem":2056,
    "gn:feature_class":"P",
    "gn:feature_code":"PPL",
    "gn:name":"Alan",
    "gn:population":0,
    "gn:timezone":"Europe/Istanbul",
    "iso:country":"TR",
    "name:tur_x_preferred":[
        "Alan"
    ],
    "name:und_x_variant":[
        "Alank\u00f6y"
    ],
    "wof:name":"Alan",
    "wof:placetype":"locality"
},
  "geometry": {"coordinates":[42.7443,38.34473],"type":"Point"}
}