{
  "type": "Feature",
  "properties": {
    "gn:admin1_code":"57.0",
    "gn:asciiname":"Kocak",
    "gn:country_code":"TR",
    "gn:dem":391,
    "gn:feature_class":"P",
    "gn:feature_code":"PPL",
    "gn:name":"Kocak",
    "gn:population":0,
    "gn:timezone":"Europe/Istanbul",
    "iso:country":"TR",
    "name:tur_x_preferred":[
        "Kocak"
    ],
    "name:und_x_variant":[
        "Urluca"
    ],
    "wof:name":"Kocak",
    "wof:placetype":"locality"
},
  "geometry": {"coordinates":[34.6425,41.59756],"type":"Point"}
}