{
  "type": "Feature",
  "properties": {
    "gn:admin1_code":"24",
    "gn:asciiname":"Sahintepe",
    "gn:country_code":"TR",
    "gn:dem":1042,
    "gn:feature_class":"P",
    "gn:feature_code":"PPL",
    "gn:name":"\u015eahintepe",
    "gn:population":0,
    "gn:timezone":"Europe/Istanbul",
    "iso:country":"TR",
    "name:und_x_variant":[
        "Av\u015fin",
        "Av\u015fen",
        "\u015eahintepe"
    ],
    "wof:name":"Sahintepe",
    "wof:placetype":"locality"
},
  "geometry": {"coordinates":[38.74891,39.51691],"type":"Point"}
}