{
  "type": "Feature",
  "properties": {
    "gn:admin1_code":"72.0",
    "gn:asciiname":"Shinok",
    "gn:country_code":"TR",
    "gn:dem":1118,
    "gn:feature_class":"P",
    "gn:feature_code":"PPL",
    "gn:name":"Shinok",
    "gn:population":0,
    "gn:timezone":"Europe/Istanbul",
    "iso:country":"TR",
    "name:und_x_variant":[
        "\u015einok"
    ],
    "wof:name":"Shinok",
    "wof:placetype":"locality"
},
  "geometry": {"coordinates":[40.94222,37.41111],"type":"Point"}
}