{
  "type": "Feature",
  "properties": {
    "gn:admin1_code":"19.0",
    "gn:asciiname":"Belkavak",
    "gn:country_code":"TR",
    "gn:dem":685,
    "gn:feature_class":"P",
    "gn:feature_code":"PPL",
    "gn:name":"Belkavak",
    "gn:population":0,
    "gn:timezone":"Europe/Istanbul",
    "iso:country":"TR",
    "name:und_x_variant":[
        "Balkavak",
        "Balkavak K\u00f6y",
        "Balkavak K\u00f6y\u00fc",
        "Belkavak"
    ],
    "wof:name":"Belkavak",
    "wof:placetype":"locality"
},
  "geometry": {"coordinates":[34.86724,40.99411],"type":"Point"}
}