{
  "type": "Feature",
  "properties": {
    "gn:admin1_code":"38",
    "gn:asciiname":"Methiye",
    "gn:country_code":"TR",
    "gn:dem":1610,
    "gn:feature_class":"P",
    "gn:feature_code":"PPL",
    "gn:name":"Methiye",
    "gn:population":0,
    "gn:timezone":"Europe/Istanbul",
    "iso:country":"TR",
    "wof:name":"Methiye",
    "wof:placetype":"locality"
},
  "geometry": {"coordinates":[36.70073,39.10231],"type":"Point"}
}