{
  "type": "Feature",
  "properties": {
    "gn:admin1_code":"70",
    "gn:asciiname":"Dereustu",
    "gn:country_code":"TR",
    "gn:dem":1235,
    "gn:feature_class":"P",
    "gn:feature_code":"PPL",
    "gn:name":"Dere\u00fcst\u00fc",
    "gn:population":0,
    "gn:timezone":"Europe/Istanbul",
    "iso:country":"TR",
    "wof:name":"Dereustu",
    "wof:placetype":"locality"
},
  "geometry": {"coordinates":[43.59121,37.50383],"type":"Point"}
}