{
  "type": "Feature",
  "properties": {
    "gn:admin1_code":"40",
    "gn:asciiname":"Cicekli",
    "gn:country_code":"TR",
    "gn:dem":737,
    "gn:feature_class":"P",
    "gn:feature_code":"PPL",
    "gn:name":"\u00c7i\u00e7ekli",
    "gn:population":0,
    "gn:timezone":"Europe/Istanbul",
    "iso:country":"TR",
    "name:und_x_variant":[
        "\u00c7i\u00e7ekli",
        "K\u0131z\u0131losmanl\u0131"
    ],
    "wof:name":"Cicekli",
    "wof:placetype":"locality"
},
  "geometry": {"coordinates":[34.07122,39.76144],"type":"Point"}
}