{
  "type": "Feature",
  "properties": {
    "gn:admin1_code":"48",
    "gn:asciiname":"Karadere",
    "gn:country_code":"TR",
    "gn:dem":23,
    "gn:feature_class":"P",
    "gn:feature_code":"PPL",
    "gn:name":"Karadere",
    "gn:population":0,
    "gn:timezone":"Europe/Istanbul",
    "iso:country":"TR",
    "wof:name":"Karadere",
    "wof:placetype":"locality"
},
  "geometry": {"coordinates":[29.27417,36.34651],"type":"Point"}
}