{
  "type": "Feature",
  "properties": {
    "gn:admin1_code":"58",
    "gn:asciiname":"Yaylacik",
    "gn:country_code":"TR",
    "gn:dem":1870,
    "gn:feature_class":"P",
    "gn:feature_code":"PPL",
    "gn:name":"Yaylac\u0131k",
    "gn:population":0,
    "gn:timezone":"Europe/Istanbul",
    "iso:country":"TR",
    "name:tur_x_preferred":[
        "Yaylac\u0131k"
    ],
    "name:tur_x_variant":[
        "Yukar\u0131yaylac\u0131k"
    ],
    "wof:name":"Yaylacik",
    "wof:placetype":"locality"
},
  "geometry": {"coordinates":[37.06442,38.71798],"type":"Point"}
}