{
  "type": "Feature",
  "properties": {
    "gn:admin1_code":"10.0",
    "gn:asciiname":"Tepecik",
    "gn:country_code":"TR",
    "gn:dem":25,
    "gn:feature_class":"P",
    "gn:feature_code":"PPL",
    "gn:name":"Tepecik",
    "gn:population":0,
    "gn:timezone":"Europe/Istanbul",
    "iso:country":"TR",
    "name:und_x_variant":[
        "D\u00f6mek",
        "D\u00fcmbe",
        "Tepecik"
    ],
    "wof:name":"Tepecik",
    "wof:placetype":"locality"
},
  "geometry": {"coordinates":[28.0494,40.06513],"type":"Point"}
}