{
  "type": "Feature",
  "properties": {
    "gn:admin1_code":"73",
    "gn:asciiname":"Kaynarca",
    "gn:country_code":"TR",
    "gn:dem":1216,
    "gn:feature_class":"P",
    "gn:feature_code":"PPL",
    "gn:name":"Kaynarca",
    "gn:population":0,
    "gn:timezone":"Europe/Istanbul",
    "iso:country":"TR",
    "name:ceb_x_preferred":[
        "Kaynarca"
    ],
    "name:msa_x_preferred":[
        "Kaynarca"
    ],
    "name:swa_x_preferred":[
        "Kaynarca"
    ],
    "name:tur_x_preferred":[
        "Kaynarca"
    ],
    "wof:name":"Kaynarca",
    "wof:placetype":"locality"
},
  "geometry": {"coordinates":[34.63542,37.85384000000001],"type":"Point"}
}