{
  "type": "Feature",
  "properties": {
    "gn:admin1_code":"78",
    "gn:asciiname":"Saray",
    "gn:country_code":"TR",
    "gn:dem":1134,
    "gn:feature_class":"P",
    "gn:feature_code":"PPL",
    "gn:name":"Saray",
    "gn:population":0,
    "gn:timezone":"Europe/Istanbul",
    "iso:country":"TR",
    "name:ara_x_preferred":[
        "\u0633\u0631\u0627\u064a"
    ],
    "name:arg_x_preferred":[
        "Saray"
    ],
    "name:aze_x_preferred":[
        "Saray"
    ],
    "name:ceb_x_preferred":[
        "Saray"
    ],
    "name:che_x_preferred":[
        "\u0411\u043e\u0436\u0430\u043b"
    ],
    "name:deu_x_preferred":[
        "Saray"
    ],
    "name:ell_x_preferred":[
        "\u03a3\u03b1\u03c1\u03ac\u03b9"
    ],
    "name:fas_x_preferred":[
        "\u0633\u0627\u0631\u0627\u06cc"
    ],
    "name:fra_x_preferred":[
        "Saray"
    ],
    "name:heb_x_preferred":[
        "\u05d1\u05d9\u05ea \u05d4\u05e1\u05e8\u05d0\u05d9\u05d9\u05d4"
    ],
    "name:ita_x_preferred":[
        "Saray"
    ],
    "name:kat_x_preferred":[
        "\u10e1\u10d0\u10e0\u10d0\u10d8"
    ],
    "name:kir_x_preferred":[
        "\u0421\u0430\u0440\u0430\u0439"
    ],
    "name:min_x_preferred":[
        "Saray"
    ],
    "name:nld_x_preferred":[
        "Saray"
    ],
    "name:rus_x_preferred":[
        "\u0421\u0430\u0440\u0430\u0439"
    ],
    "name:swe_x_preferred":[
        "Saray"
    ],
    "name:tgl_x_preferred":[
        "Saray"
    ],
    "name:tur_x_preferred":[
        "Saray"
    ],
    "name:ukr_x_preferred":[
        "\u0421\u0430\u0440\u0430\u0439"
    ],
    "name:urd_x_preferred":[
        "\u0633\u0631\u0627\u0626\u06d2"
    ],
    "name:uzb_x_preferred":[
        "Saroy"
    ],
    "wof:name":"Saray",
    "wof:placetype":"locality"
},
  "geometry": {"coordinates":[33.6739,37.38667],"type":"Point"}
}