{
  "type": "Feature",
  "properties": {
    "gn:admin1_code":"28",
    "gn:asciiname":"Cavusoglu",
    "gn:country_code":"TR",
    "gn:dem":148,
    "gn:feature_class":"P",
    "gn:feature_code":"PPL",
    "gn:name":"\u00c7avu\u015fo\u011flu",
    "gn:population":0,
    "gn:timezone":"Europe/Istanbul",
    "iso:country":"TR",
    "name:tur_x_preferred":[
        "\u00c7avu\u015fo\u011flu"
    ],
    "wof:name":"Cavusoglu",
    "wof:placetype":"locality"
},
  "geometry": {"coordinates":[38.42932,40.87834],"type":"Point"}
}