{
  "type": "Feature",
  "properties": {
    "gn:admin1_code":"77.0",
    "gn:asciiname":"Dagtarla",
    "gn:country_code":"TR",
    "gn:dem":1626,
    "gn:feature_class":"P",
    "gn:feature_code":"PPL",
    "gn:name":"Da\u011ftarla",
    "gn:population":0,
    "gn:timezone":"Europe/Istanbul",
    "iso:country":"TR",
    "name:und_x_variant":[
        "Ortu\u011fu",
        "Ortuku",
        "Da\u011ftarla"
    ],
    "wof:name":"Dagtarla",
    "wof:placetype":"locality"
},
  "geometry": {"coordinates":[40.42221,40.34174],"type":"Point"}
}