{
  "type": "Feature",
  "properties": {
    "gn:admin1_code":"31.0",
    "gn:asciiname":"Cevizlidere",
    "gn:country_code":"TR",
    "gn:dem":474,
    "gn:feature_class":"P",
    "gn:feature_code":"PPL",
    "gn:name":"Cevizlidere",
    "gn:population":0,
    "gn:timezone":"Europe/Istanbul",
    "iso:country":"TR",
    "name:und_x_variant":[
        "Dzhevizlidere",
        "Cevizlidere"
    ],
    "wof:name":"Cevizlidere",
    "wof:placetype":"locality"
},
  "geometry": {"coordinates":[36.26986,36.05697],"type":"Point"}
}