{
  "type": "Feature",
  "properties": {
    "gn:admin1_code":"24",
    "gn:asciiname":"Sakaloglu",
    "gn:country_code":"TR",
    "gn:dem":2067,
    "gn:feature_class":"P",
    "gn:feature_code":"PPL",
    "gn:name":"\u015eakalo\u011flu",
    "gn:population":0,
    "gn:timezone":"Europe/Istanbul",
    "iso:country":"TR",
    "name:tur_x_preferred":[
        "\u015eakalo\u011flu"
    ],
    "name:und_x_variant":[
        "Sakao\u011flu"
    ],
    "wof:name":"Sakaloglu",
    "wof:placetype":"locality"
},
  "geometry": {"coordinates":[38.98899,40.00112],"type":"Point"}
}