{
  "type": "Feature",
  "properties": {
    "iso:country":"TR",
    "name:eng_x_preferred":[
        "Ismetpasa"
    ],
    "name:tur_x_preferred":[
        "\u0130smetpa\u015fa"
    ],
    "wof:name":"Ismetpasa",
    "wof:placetype":"neighbourhood"
},
  "geometry": {"coordinates":[28.01622419418734,41.09948413340528],"type":"Point"}
}