{
  "type": "Feature",
  "properties": {
    "gn:admin1_code":"68",
    "gn:asciiname":"Karatas",
    "gn:country_code":"TR",
    "gn:dem":1148,
    "gn:feature_class":"P",
    "gn:feature_code":"PPL",
    "gn:name":"Karata\u015f",
    "gn:population":0,
    "gn:timezone":"Europe/Istanbul",
    "iso:country":"TR",
    "wof:name":"Karatas",
    "wof:placetype":"locality"
},
  "geometry": {"coordinates":[32.89154,39.8166],"type":"Point"}
}