{
  "type": "Feature",
  "properties": {
    "gn:admin1_code":"39.0",
    "gn:asciiname":"Ceylankoy",
    "gn:country_code":"TR",
    "gn:dem":123,
    "gn:feature_class":"P",
    "gn:feature_code":"PPL",
    "gn:name":"Ceylank\u00f6y",
    "gn:population":0,
    "gn:timezone":"Europe/Istanbul",
    "iso:country":"TR",
    "name:und_x_variant":[
        "Mand\u0131r\u0131\u00e7a",
        "Ceylan",
        "Mandari\u00e7a",
        "Ceylank\u00f6y"
    ],
    "wof:name":"Ceylankoy",
    "wof:placetype":"locality"
},
  "geometry": {"coordinates":[27.43107,41.55025],"type":"Point"}
}