{
  "type": "Feature",
  "properties": {
    "gn:admin1_code":"52.0",
    "gn:asciiname":"Cerci",
    "gn:country_code":"TR",
    "gn:dem":1257,
    "gn:feature_class":"P",
    "gn:feature_code":"PPL",
    "gn:name":"\u00c7er\u00e7i",
    "gn:population":0,
    "gn:timezone":"Europe/Istanbul",
    "iso:country":"TR",
    "name:tur_x_preferred":[
        "\u00c7er\u00e7i"
    ],
    "wof:name":"Cerci",
    "wof:placetype":"locality"
},
  "geometry": {"coordinates":[37.76924,40.49514],"type":"Point"}
}