{
  "type": "Feature",
  "properties": {
    "gn:admin1_code":"10",
    "gn:asciiname":"Kurudegirmen",
    "gn:country_code":"TR",
    "gn:dem":55,
    "gn:feature_class":"P",
    "gn:feature_code":"PPL",
    "gn:name":"Kurude\u011firmen",
    "gn:population":0,
    "gn:timezone":"Europe/Istanbul",
    "iso:country":"TR",
    "name:tur_x_preferred":[
        "Kurude\u011firmen"
    ],
    "wof:name":"Kurudegirmen",
    "wof:placetype":"locality"
},
  "geometry": {"coordinates":[27.68983,40.09264],"type":"Point"}
}