{
  "type": "Feature",
  "properties": {
    "gn:admin1_code":"89.0",
    "gn:asciiname":"Topuzlu",
    "gn:country_code":"TR",
    "gn:dem":902,
    "gn:feature_class":"P",
    "gn:feature_code":"PPL",
    "gn:name":"Topuzlu",
    "gn:population":0,
    "gn:timezone":"Europe/Istanbul",
    "iso:country":"TR",
    "wof:name":"Topuzlu",
    "wof:placetype":"locality"
},
  "geometry": {"coordinates":[33.11667,41.41667],"type":"Point"}
}