{
  "type": "Feature",
  "properties": {
    "gn:admin1_code":"61",
    "gn:asciiname":"Cukurca",
    "gn:country_code":"TR",
    "gn:dem":678,
    "gn:feature_class":"P",
    "gn:feature_code":"PPL",
    "gn:name":"\u00c7ukurca",
    "gn:population":0,
    "gn:timezone":"Europe/Istanbul",
    "iso:country":"TR",
    "name:tur_x_preferred":[
        "\u00c7ukurca"
    ],
    "wof:name":"Cukurca",
    "wof:placetype":"locality"
},
  "geometry": {"coordinates":[39.59631,40.89545],"type":"Point"}
}