{
  "type": "Feature",
  "properties": {
    "gn:admin1_code":"81",
    "gn:asciiname":"Salbas",
    "gn:country_code":"TR",
    "gn:dem":100,
    "gn:feature_class":"P",
    "gn:feature_code":"PPL",
    "gn:name":"Salba\u015f",
    "gn:population":0,
    "gn:timezone":"Europe/Istanbul",
    "iso:country":"TR",
    "wof:name":"Salbas",
    "wof:placetype":"locality"
},
  "geometry": {"coordinates":[35.11302,37.10905],"type":"Point"}
}