{
  "type": "Feature",
  "properties": {
    "gn:admin1_code":"65",
    "gn:asciiname":"Bizanis",
    "gn:cc2":"TR",
    "gn:country_code":"TR",
    "gn:dem":2542,
    "gn:feature_class":"P",
    "gn:feature_code":"PPL",
    "gn:name":"Bizanis",
    "gn:population":0,
    "gn:timezone":"Europe/Istanbul",
    "iso:country":"TR",
    "name:und_x_variant":[
        "Biyans",
        "Bizanis"
    ],
    "wof:name":"Bizanis",
    "wof:placetype":"locality"
},
  "geometry": {"coordinates":[43.14056,37.83528],"type":"Point"}
}