{
  "type": "Feature",
  "properties": {
    "gn:admin1_code":"23",
    "gn:asciiname":"Yazibasi",
    "gn:country_code":"TR",
    "gn:dem":916,
    "gn:feature_class":"P",
    "gn:feature_code":"PPL",
    "gn:name":"Yaz\u0131ba\u015f\u0131",
    "gn:population":0,
    "gn:timezone":"Europe/Istanbul",
    "iso:country":"TR",
    "name:tur_x_preferred":[
        "Yaz\u0131ba\u015f\u0131"
    ],
    "name:und_x_variant":[
        "Sekrat",
        "\u015eekerat"
    ],
    "wof:name":"Yazibasi",
    "wof:placetype":"locality"
},
  "geometry": {"coordinates":[39.90337,38.71883],"type":"Point"}
}