{
  "type": "Feature",
  "properties": {
    "gn:admin1_code":"80",
    "gn:asciiname":"Kafaba",
    "gn:cc2":"TR",
    "gn:country_code":"TR",
    "gn:dem":992,
    "gn:feature_class":"P",
    "gn:feature_code":"PPL",
    "gn:name":"Kafaba",
    "gn:population":0,
    "gn:timezone":"Europe/Istanbul",
    "iso:country":"TR",
    "name:tur_x_preferred":[
        "Kalaba"
    ],
    "name:und_x_variant":[
        "Dyukhyuk",
        "D\u00fch\u00fck",
        "Kafaba"
    ],
    "wof:name":"Kafaba",
    "wof:placetype":"locality"
},
  "geometry": {"coordinates":[42.3375,37.55417],"type":"Point"}
}