{
  "type": "Feature",
  "properties": {
    "iso:country":"TR",
    "name:fas_x_preferred":[
        "\u067e\u0627\u06cc\u06af\u0627\u0647 \u0647\u0648\u0627\u06cc\u06cc \u0627\u0631\u062a\u0634\u06cc \u06af\u0648\u0631\u0633\u06cc\u0646\u0644\u06cc\u06a9 \u0622\u0646\u06a9\u0627\u0631\u0627"
    ],
    "name:jpn_x_preferred":[
        "\u30a2\u30f3\u30ab\u30e9\u30fb\u30ae\u30e5\u30f4\u30a7\u30eb\u30b8\u30f3\u30ea\u30af\u9678\u8ecd\u98db\u884c\u5834"
    ],
    "name:msa_x_preferred":[
        "Pengkalan Udara Guvercinlik"
    ],
    "name:nob_x_preferred":[
        "G\u00fcvercinlik flystasjon"
    ],
    "name:tgk_x_preferred":[
        "\u041f\u043e\u0439\u0433\u043e\u04b3\u0438 \u04b3\u0430\u0432\u043e\u0438\u0438 \u0410\u0440\u0442\u0438\u0448\u0438 \u0410\u043d\u043a\u0430\u0440\u0430 \u0413\u044e\u0432\u0435\u0440\u0441\u0438\u043d\u043b\u0438\u043a"
    ],
    "name:tur_x_preferred":[
        "G\u00fcvercinlik Havaliman\u0131"
    ],
    "oa:elevation_ft":"2687",
    "oa:type":"small_airport",
    "woe:hierarchy":{
        "country_id":23424969,
        "county_id":29390874,
        "planet_id":1,
        "state_id":2347263,
        "suburb_id":55865276
    },
    "wof:name":"Guvercinlik Airport",
    "wof:placetype":"campus"
},
  "geometry": {"coordinates":[32.740775,39.93495],"type":"Point"}
}