{
  "type": "Feature",
  "properties": {
    "gn:admin1_code":"58",
    "gn:asciiname":"Cicekliyurt",
    "gn:country_code":"TR",
    "gn:dem":1414,
    "gn:feature_class":"P",
    "gn:feature_code":"PPL",
    "gn:name":"\u00c7i\u00e7ekliyurt",
    "gn:population":0,
    "gn:timezone":"Europe/Istanbul",
    "iso:country":"TR",
    "name:und_x_variant":[
        "\u00c7akal",
        "\u00c7i\u00e7ekliyurt"
    ],
    "wof:name":"Cicekliyurt",
    "wof:placetype":"locality"
},
  "geometry": {"coordinates":[36.279,39.43472],"type":"Point"}
}