{
  "type": "Feature",
  "properties": {
    "gn:admin1_code":"65",
    "gn:asciiname":"Yukarikume",
    "gn:country_code":"TR",
    "gn:dem":2013,
    "gn:feature_class":"P",
    "gn:feature_code":"PPL",
    "gn:name":"Yukar\u0131k\u00fcme",
    "gn:population":0,
    "gn:timezone":"Europe/Istanbul",
    "iso:country":"TR",
    "name:und_x_variant":[
        "Rekan\u00fclya",
        "Yukar\u0131 Rekan",
        "Yukar\u0131k\u00fcme"
    ],
    "wof:name":"Yukarikume",
    "wof:placetype":"locality"
},
  "geometry": {"coordinates":[44.01246,37.94248],"type":"Point"}
}