{
  "type": "Feature",
  "properties": {
    "gn:admin1_code":"84.0",
    "gn:asciiname":"Yerlikavak",
    "gn:country_code":"TR",
    "gn:dem":1600,
    "gn:feature_class":"P",
    "gn:feature_code":"PPL",
    "gn:name":"Yerlikavak",
    "gn:population":0,
    "gn:timezone":"Europe/Istanbul",
    "iso:country":"TR",
    "name:und_x_variant":[
        "Seydi",
        "Yerlikavak"
    ],
    "wof:name":"Yerlikavak",
    "wof:placetype":"locality"
},
  "geometry": {"coordinates":[43.58912,40.81269],"type":"Point"}
}