{
  "type": "Feature",
  "properties": {
    "gn:admin1_code":"12",
    "gn:asciiname":"Balpinar",
    "gn:country_code":"TR",
    "gn:dem":1911,
    "gn:feature_class":"P",
    "gn:feature_code":"PPL",
    "gn:name":"Balp\u0131nar",
    "gn:population":0,
    "gn:timezone":"Europe/Istanbul",
    "iso:country":"TR",
    "name:tur_x_preferred":[
        "Balp\u0131nar"
    ],
    "wof:name":"Balpinar",
    "wof:placetype":"locality"
},
  "geometry": {"coordinates":[40.38817,38.82631],"type":"Point"}
}