{
  "type": "Feature",
  "properties": {
    "gn:admin1_code":"13.0",
    "gn:asciiname":"Tasevler",
    "gn:country_code":"TR",
    "gn:dem":1102,
    "gn:feature_class":"P",
    "gn:feature_code":"PPL",
    "gn:name":"Ta\u015fevler",
    "gn:population":0,
    "gn:timezone":"Europe/Istanbul",
    "iso:country":"TR",
    "name:tur_x_preferred":[
        "Ta\u015fevler"
    ],
    "wof:name":"Tasevler",
    "wof:placetype":"locality"
},
  "geometry": {"coordinates":[42.46886,38.17315],"type":"Point"}
}