{
  "type": "Feature",
  "properties": {
    "gn:admin1_code":"25.0",
    "gn:asciiname":"Asagi Yayla",
    "gn:country_code":"TR",
    "gn:dem":2124,
    "gn:feature_class":"P",
    "gn:feature_code":"PPL",
    "gn:name":"A\u015fa\u011f\u0131 Yayla",
    "gn:population":0,
    "gn:timezone":"Europe/Istanbul",
    "iso:country":"TR",
    "name:und_x_variant":[
        "A\u015fa\u011f\u0131hi\u00e7ov",
        "A\u015fa\u011f\u0131 Yayla"
    ],
    "wof:name":"Asagi Yayla",
    "wof:placetype":"locality"
},
  "geometry": {"coordinates":[41.79867,40.29401],"type":"Point"}
}