{
  "type": "Feature",
  "properties": {
    "gn:admin1_code":"66",
    "gn:asciiname":"Cikrikci",
    "gn:country_code":"TR",
    "gn:dem":1099,
    "gn:feature_class":"P",
    "gn:feature_code":"PPL",
    "gn:name":"\u00c7\u0131kr\u0131k\u00e7\u0131",
    "gn:population":0,
    "gn:timezone":"Europe/Istanbul",
    "iso:country":"TR",
    "wof:name":"Cikrikci",
    "wof:placetype":"locality"
},
  "geometry": {"coordinates":[35.4563,39.54834],"type":"Point"}
}