{
  "type": "Feature",
  "properties": {
    "gn:admin1_code":"55",
    "gn:asciiname":"Talisman",
    "gn:country_code":"TR",
    "gn:dem":753,
    "gn:feature_class":"P",
    "gn:feature_code":"PPL",
    "gn:name":"Tal\u0131\u015fman",
    "gn:population":0,
    "gn:timezone":"Europe/Istanbul",
    "iso:country":"TR",
    "wof:name":"Talisman",
    "wof:placetype":"locality"
},
  "geometry": {"coordinates":[36.18411,41.06472],"type":"Point"}
}