{
  "type": "Feature",
  "properties": {
    "gn:admin1_code":"55",
    "gn:asciiname":"Talisman",
    "gn:country_code":"TR",
    "gn:dem":753,
    "gn:feature_class":"P",
    "gn:feature_code":"PPL",
    "gn:name":"Tal\u0131\u015fman",
    "gn:population":0,
    "gn:timezone":"Europe/Istanbul",
    "iso:country":"TR",
    "name:ara_x_preferred":[
        "\u0637\u0644\u0633\u0645"
    ],
    "name:bel_x_preferred":[
        "\u0422\u0430\u043b\u0456\u0441\u043c\u0430\u043d"
    ],
    "name:cat_x_preferred":[
        "Talism\u00e0"
    ],
    "name:ces_x_preferred":[
        "Talisman"
    ],
    "name:dan_x_preferred":[
        "Talisman"
    ],
    "name:deu_x_preferred":[
        "Talisman"
    ],
    "name:epo_x_preferred":[
        "Talismano"
    ],
    "name:est_x_preferred":[
        "Talisman"
    ],
    "name:eus_x_preferred":[
        "Talisman"
    ],
    "name:fas_x_preferred":[
        "\u0637\u0644\u0633\u0645"
    ],
    "name:fin_x_preferred":[
        "Talismaani"
    ],
    "name:fra_x_preferred":[
        "Talisman"
    ],
    "name:fry_x_preferred":[
        "Talisman"
    ],
    "name:glg_x_preferred":[
        "Talism\u00e1n"
    ],
    "name:hrv_x_preferred":[
        "Talisman"
    ],
    "name:kan_x_preferred":[
        "\u0ca4\u0cbe\u0caf\u0cbf\u0ca4"
    ],
    "name:kaz_x_preferred":[
        "\u0422\u0430\u043b\u0438\u0441\u043c\u0430\u043d"
    ],
    "name:kor_x_preferred":[
        "\ud0e4\ub9ac\uc988\uba3c"
    ],
    "name:lit_x_preferred":[
        "Talismanas"
    ],
    "name:nor_x_preferred":[
        "Talisman"
    ],
    "name:oci_x_preferred":[
        "Talisman"
    ],
    "name:pol_x_preferred":[
        "Talizman"
    ],
    "name:por_x_preferred":[
        "Talism\u00e3"
    ],
    "name:ron_x_preferred":[
        "Talisman"
    ],
    "name:rus_x_preferred":[
        "\u0422\u0430\u043b\u0438\u0441\u043c\u0430\u043d"
    ],
    "name:slk_x_preferred":[
        "Talizman"
    ],
    "name:slv_x_preferred":[
        "Talisman"
    ],
    "name:spa_x_preferred":[
        "Talism\u00e1n"
    ],
    "name:srp_x_preferred":[
        "\u0422\u0430\u043b\u0438\u0441\u043c\u0430\u043d"
    ],
    "name:swe_x_preferred":[
        "Talisman"
    ],
    "name:tam_x_preferred":[
        "\u0ba4\u0bbe\u0baf\u0ba4\u0bcd\u0ba4\u0bc1"
    ],
    "name:tha_x_preferred":[
        "\u0e27\u0e31\u0e15\u0e16\u0e38\u0e21\u0e07\u0e04\u0e25"
    ],
    "wof:name":"Talisman",
    "wof:placetype":"locality"
},
  "geometry": {"coordinates":[36.18411,41.06472],"type":"Point"}
}