{
  "type": "Feature",
  "properties": {
    "gn:admin1_code":"14.0",
    "gn:asciiname":"Kayabuku",
    "gn:country_code":"TR",
    "gn:dem":416,
    "gn:feature_class":"P",
    "gn:feature_code":"PPL",
    "gn:name":"Kayab\u00fck\u00fc",
    "gn:population":0,
    "gn:timezone":"Europe/Istanbul",
    "iso:country":"TR",
    "wof:name":"Kayabuku",
    "wof:placetype":"locality"
},
  "geometry": {"coordinates":[31.91486,40.96708],"type":"Point"}
}