{
  "type": "Feature",
  "properties": {
    "gn:admin1_code":"03",
    "gn:asciiname":"Yenicay",
    "gn:cc2":"TR",
    "gn:country_code":"TR",
    "gn:dem":1078,
    "gn:feature_class":"P",
    "gn:feature_code":"PPL",
    "gn:name":"Yeni\u00e7ay",
    "gn:population":0,
    "gn:timezone":"Europe/Istanbul",
    "iso:country":"TR",
    "name:und_x_variant":[
        "\u00c7ayk\u00f6y",
        "Yeni\u00e7ay"
    ],
    "wof:name":"Yenicay",
    "wof:placetype":"locality"
},
  "geometry": {"coordinates":[30.26667,38.43333],"type":"Point"}
}