{
  "type": "Feature",
  "properties": {
    "gn:admin1_code":"61.0",
    "gn:asciiname":"Yayvanoba",
    "gn:country_code":"TR",
    "gn:dem":231,
    "gn:feature_class":"P",
    "gn:feature_code":"PPL",
    "gn:name":"Yayvanoba",
    "gn:population":0,
    "gn:timezone":"Europe/Istanbul",
    "iso:country":"TR",
    "name:tur_x_preferred":[
        "Yayvanoba"
    ],
    "wof:name":"Yayvanoba",
    "wof:placetype":"locality"
},
  "geometry": {"coordinates":[40.37719,40.90317],"type":"Point"}
}