{
  "type": "Feature",
  "properties": {
    "gn:admin1_code":"37.0",
    "gn:asciiname":"Karabeyler",
    "gn:country_code":"TR",
    "gn:dem":1294,
    "gn:feature_class":"P",
    "gn:feature_code":"PPL",
    "gn:name":"Karabeyler",
    "gn:population":0,
    "gn:timezone":"Europe/Istanbul",
    "iso:country":"TR",
    "wof:name":"Karabeyler",
    "wof:placetype":"locality"
},
  "geometry": {"coordinates":[33.41667,41.55],"type":"Point"}
}