{
  "type": "Feature",
  "properties": {
    "gn:admin1_code":"37.0",
    "gn:asciiname":"Tellikoz",
    "gn:country_code":"TR",
    "gn:dem":861,
    "gn:feature_class":"P",
    "gn:feature_code":"PPL",
    "gn:name":"Tellikoz",
    "gn:population":0,
    "gn:timezone":"Europe/Istanbul",
    "iso:country":"TR",
    "name:tur_x_preferred":[
        "Tellikoz"
    ],
    "wof:name":"Tellikoz",
    "wof:placetype":"locality"
},
  "geometry": {"coordinates":[33.10902,41.19703],"type":"Point"}
}