{
  "type": "Feature",
  "properties": {
    "gn:admin1_code":"70",
    "gn:asciiname":"Besbulak",
    "gn:country_code":"TR",
    "gn:dem":1881,
    "gn:feature_class":"P",
    "gn:feature_code":"PPL",
    "gn:name":"Be\u015fbulak",
    "gn:population":0,
    "gn:timezone":"Europe/Istanbul",
    "iso:country":"TR",
    "name:und_x_variant":[
        "Be\u015fbudak",
        "Be\u015fbulak"
    ],
    "wof:name":"Besbulak",
    "wof:placetype":"locality"
},
  "geometry": {"coordinates":[44.35639000000001,37.52944],"type":"Point"}
}