{
  "type": "Feature",
  "properties": {
    "gn:admin1_code":"16.0",
    "gn:asciiname":"Taspinar",
    "gn:country_code":"TR",
    "gn:dem":402,
    "gn:feature_class":"P",
    "gn:feature_code":"PPL",
    "gn:name":"Ta\u015fp\u0131nar",
    "gn:population":0,
    "gn:timezone":"Europe/Istanbul",
    "iso:country":"TR",
    "name:und_x_variant":[
        "Ta\u015fp\u0131nar K\u00f6y\u00fc",
        "Ta\u015fp\u0131nar"
    ],
    "wof:name":"Taspinar",
    "wof:placetype":"locality"
},
  "geometry": {"coordinates":[28.57162000000001,40.08272],"type":"Point"}
}