{
  "type": "Feature",
  "properties": {
    "gn:country":"TR",
    "gn:fcode":"PPL",
    "gn:population":142,
    "iso:country":"TR",
    "name:rus_x_preferred":[
        "Zerbil\u2019"
    ],
    "name:und_x_variant":[
        "Zerbil"
    ],
    "qs:name":"Koyunoba",
    "qs:photos_9r":0,
    "qs:photos_sr":0,
    "qs:pop_sr":"1",
    "wof:name":"Koyunoba",
    "wof:placetype":"locality",
    "wof:population":142
},
  "geometry": {"coordinates":[43.04,37.54222],"type":"Point"}
}