{
  "type": "Feature",
  "properties": {
    "gn:admin1_code":"19.0",
    "gn:asciiname":"Sinkli",
    "gn:country_code":"TR",
    "gn:dem":1217,
    "gn:feature_class":"P",
    "gn:feature_code":"PPL",
    "gn:name":"S\u0131nkl\u0131",
    "gn:population":0,
    "gn:timezone":"Europe/Istanbul",
    "iso:country":"TR",
    "wof:name":"Sinkli",
    "wof:placetype":"locality"
},
  "geometry": {"coordinates":[34.77172,40.49516],"type":"Point"}
}