{
  "type": "Feature",
  "properties": {
    "gn:admin1_code":"53.0",
    "gn:asciiname":"Cataldere",
    "gn:country_code":"TR",
    "gn:dem":814,
    "gn:feature_class":"P",
    "gn:feature_code":"PPL",
    "gn:name":"\u00c7ataldere",
    "gn:population":0,
    "gn:timezone":"Europe/Istanbul",
    "iso:country":"TR",
    "name:und_x_variant":[
        "\u00c7ataldere K\u00f6y\u00fc",
        "\u00c7ataldere"
    ],
    "wof:name":"Cataldere",
    "wof:placetype":"locality"
},
  "geometry": {"coordinates":[40.76556,40.90387],"type":"Point"}
}