{
  "type": "Feature",
  "properties": {
    "gn:admin1_code":"89.0",
    "gn:asciiname":"Yesiltepe",
    "gn:country_code":"TR",
    "gn:dem":1308,
    "gn:feature_class":"P",
    "gn:feature_code":"PPL",
    "gn:name":"Ye\u015filtepe",
    "gn:population":0,
    "gn:timezone":"Europe/Istanbul",
    "iso:country":"TR",
    "name:und_x_variant":[
        "Ye\u015filtepe",
        "Turbe"
    ],
    "wof:name":"Yesiltepe",
    "wof:placetype":"locality"
},
  "geometry": {"coordinates":[32.52906,41.0669],"type":"Point"}
}