{
  "type": "Feature",
  "properties": {
    "gn:admin1_code":"44.0",
    "gn:asciiname":"Gozluce",
    "gn:country_code":"TR",
    "gn:dem":1353,
    "gn:feature_class":"P",
    "gn:feature_code":"PPL",
    "gn:name":"G\u00f6zl\u00fcce",
    "gn:population":0,
    "gn:timezone":"Europe/Istanbul",
    "iso:country":"TR",
    "name:tur_x_preferred":[
        "G\u00f6zl\u00fcce"
    ],
    "wof:name":"Gozluce",
    "wof:placetype":"locality"
},
  "geometry": {"coordinates":[38.93925,38.23745],"type":"Point"}
}