{
  "type": "Feature",
  "properties": {
    "gn:admin1_code":"83",
    "gn:asciiname":"Terken",
    "gn:country_code":"TR",
    "gn:dem":1004,
    "gn:feature_class":"P",
    "gn:feature_code":"PPL",
    "gn:name":"Terken",
    "gn:population":0,
    "gn:timezone":"Europe/Istanbul",
    "iso:country":"TR",
    "name:ceb_x_preferred":[
        "Terken"
    ],
    "name:msa_x_preferred":[
        "Terken"
    ],
    "name:und_x_variant":[
        "Terk\u00e2n"
    ],
    "name:vie_x_preferred":[
        "Terken"
    ],
    "wof:name":"Terken",
    "wof:placetype":"locality"
},
  "geometry": {"coordinates":[37.00654,37.12364],"type":"Point"}
}