{
  "type": "Feature",
  "properties": {
    "gn:admin1_code":"31",
    "gn:asciiname":"Ekinci",
    "gn:country_code":"TR",
    "gn:dem":150,
    "gn:feature_class":"P",
    "gn:feature_code":"PPL",
    "gn:name":"Ekinci",
    "gn:population":0,
    "gn:timezone":"Europe/Istanbul",
    "iso:country":"TR",
    "name:deu_x_preferred":[
        "Ekinci"
    ],
    "name:tur_x_preferred":[
        "Ekinci"
    ],
    "name:tur_x_variant":[
        "Yukar\u0131 Ekinci"
    ],
    "wof:name":"Ekinci",
    "wof:placetype":"locality"
},
  "geometry": {"coordinates":[36.13543,36.24923],"type":"Point"}
}