{
  "type": "Feature",
  "properties": {
    "gn:admin1_code":"63.0",
    "gn:asciiname":"Kapici",
    "gn:cc2":"TR",
    "gn:country_code":"TR",
    "gn:dem":486,
    "gn:feature_class":"P",
    "gn:feature_code":"PPL",
    "gn:name":"Kap\u0131c\u0131",
    "gn:population":0,
    "gn:timezone":"Europe/Istanbul",
    "iso:country":"TR",
    "name:und_x_variant":[
        "Kapucu",
        "Kapudzhu",
        "Kap\u0131c\u0131"
    ],
    "wof:name":"Kapici",
    "wof:placetype":"locality"
},
  "geometry": {"coordinates":[38.42861,36.93639],"type":"Point"}
}