{
  "type": "Feature",
  "properties": {
    "gn:admin1_code":"03",
    "gn:asciiname":"Cikrik",
    "gn:country_code":"TR",
    "gn:dem":1063,
    "gn:feature_class":"P",
    "gn:feature_code":"PPL",
    "gn:name":"\u00c7\u0131kr\u0131k",
    "gn:population":0,
    "gn:timezone":"Europe/Istanbul",
    "iso:country":"TR",
    "wof:name":"Cikrik",
    "wof:placetype":"locality"
},
  "geometry": {"coordinates":[30.60917,38.87361],"type":"Point"}
}