{
  "type": "Feature",
  "properties": {
    "gn:admin1_code":"46",
    "gn:asciiname":"Igde",
    "gn:country_code":"TR",
    "gn:dem":1173,
    "gn:feature_class":"P",
    "gn:feature_code":"PPL",
    "gn:name":"\u0130\u011fde",
    "gn:population":0,
    "gn:timezone":"Europe/Istanbul",
    "iso:country":"TR",
    "wof:name":"Igde",
    "wof:placetype":"locality"
},
  "geometry": {"coordinates":[37.09399000000001,38.15752],"type":"Point"}
}