{
  "type": "Feature",
  "properties": {
    "gn:admin1_code":"71",
    "gn:asciiname":"Fasillar",
    "gn:country_code":"TR",
    "gn:dem":1235,
    "gn:feature_class":"P",
    "gn:feature_code":"PPL",
    "gn:name":"Fas\u0131llar",
    "gn:population":0,
    "gn:timezone":"Europe/Istanbul",
    "iso:country":"TR",
    "wof:name":"Fasillar",
    "wof:placetype":"locality"
},
  "geometry": {"coordinates":[31.89946,37.65737],"type":"Point"}
}