{
  "type": "Feature",
  "properties": {
    "gn:admin1_code":"31.0",
    "gn:asciiname":"Yaniktepe",
    "gn:country_code":"TR",
    "gn:dem":84,
    "gn:feature_class":"P",
    "gn:feature_code":"PPL",
    "gn:name":"Yan\u0131ktepe",
    "gn:population":0,
    "gn:timezone":"Europe/Istanbul",
    "iso:country":"TR",
    "name:und_x_variant":[
        "Yan\u0131ktepe",
        "Fellahk\u00f6y"
    ],
    "wof:name":"Yaniktepe",
    "wof:placetype":"locality"
},
  "geometry": {"coordinates":[36.39841,36.403],"type":"Point"}
}