{
  "type": "Feature",
  "properties": {
    "gn:admin1_code":"19.0",
    "gn:asciiname":"Ahacik",
    "gn:country_code":"TR",
    "gn:dem":1442,
    "gn:feature_class":"P",
    "gn:feature_code":"PPL",
    "gn:name":"Ahac\u0131k",
    "gn:population":0,
    "gn:timezone":"Europe/Istanbul",
    "iso:country":"TR",
    "name:tur_x_preferred":[
        "Ahac\u0131k"
    ],
    "name:und_x_variant":[
        "Nas\u0131flar"
    ],
    "wof:name":"Ahacik",
    "wof:placetype":"locality"
},
  "geometry": {"coordinates":[34.12682,40.80376],"type":"Point"}
}