{
  "type": "Feature",
  "properties": {
    "gn:admin1_code":"85.0",
    "gn:asciiname":"Koroglu",
    "gn:country_code":"TR",
    "gn:dem":537,
    "gn:feature_class":"P",
    "gn:feature_code":"PPL",
    "gn:name":"K\u00f6ro\u011flu",
    "gn:population":0,
    "gn:timezone":"Europe/Istanbul",
    "iso:country":"TR",
    "name:tur_x_preferred":[
        "K\u00f6ro\u011flu"
    ],
    "wof:name":"Koroglu",
    "wof:placetype":"locality"
},
  "geometry": {"coordinates":[31.91667,41.43333],"type":"Point"}
}