{
  "type": "Feature",
  "properties": {
    "gn:admin1_code":"32.0",
    "gn:asciiname":"Topakli",
    "gn:country_code":"TR",
    "gn:dem":360,
    "gn:feature_class":"P",
    "gn:feature_code":"PPL",
    "gn:name":"Topakl\u0131",
    "gn:population":0,
    "gn:timezone":"Europe/Istanbul",
    "iso:country":"TR",
    "wof:name":"Topakli",
    "wof:placetype":"locality"
},
  "geometry": {"coordinates":[33.29632,36.60715],"type":"Point"}
}