{
  "type": "Feature",
  "properties": {
    "gn:admin1_code":"8.0",
    "gn:asciiname":"Zekeriyakoy",
    "gn:country_code":"TR",
    "gn:dem":1940,
    "gn:feature_class":"P",
    "gn:feature_code":"PPL",
    "gn:name":"Zekeriyak\u00f6y",
    "gn:population":0,
    "gn:timezone":"Europe/Istanbul",
    "iso:country":"TR",
    "name:eng_x_preferred":[
        "Zekeriya"
    ],
    "name:rus_x_preferred":[
        "\u0417\u0435\u043a\u0435\u0440\u0438\u044f"
    ],
    "name:tur_x_preferred":[
        "Zekeriyak\u00f6y"
    ],
    "name:und_x_variant":[
        "Zekeriya"
    ],
    "wof:name":"Zekeriyakoy",
    "wof:placetype":"locality"
},
  "geometry": {"coordinates":[42.15319,40.98429],"type":"Point"}
}