{
  "type": "Feature",
  "properties": {
    "gn:admin1_code":"04",
    "gn:asciiname":"Cumacay",
    "gn:country_code":"TR",
    "gn:dem":1959,
    "gn:feature_class":"P",
    "gn:feature_code":"PPLA3",
    "gn:name":"Cuma\u00e7ay",
    "gn:population":0,
    "gn:timezone":"Europe/Istanbul",
    "iso:country":"TR",
    "name:tur_x_preferred":[
        "Cuma\u00e7ay"
    ],
    "wof:name":"Cumacay",
    "wof:placetype":"locality"
},
  "geometry": {"coordinates":[43.18653,39.91524],"type":"Point"}
}