{
  "type": "Feature",
  "properties": {
    "gn:admin1_code":"58",
    "gn:asciiname":"Incetas",
    "gn:country_code":"TR",
    "gn:dem":1415,
    "gn:feature_class":"P",
    "gn:feature_code":"PPL",
    "gn:name":"\u0130nceta\u015f",
    "gn:population":0,
    "gn:timezone":"Europe/Istanbul",
    "iso:country":"TR",
    "name:und_x_variant":[
        "Pustat",
        "\u0130nceta\u015f"
    ],
    "wof:name":"Incetas",
    "wof:placetype":"locality"
},
  "geometry": {"coordinates":[36.78416,39.94188],"type":"Point"}
}