{
  "type": "Feature",
  "properties": {
    "gn:admin1_code":"35",
    "gn:asciiname":"Dolaylar",
    "gn:country_code":"TR",
    "gn:dem":298,
    "gn:feature_class":"P",
    "gn:feature_code":"PPL",
    "gn:name":"Dolaylar",
    "gn:population":0,
    "gn:timezone":"Europe/Istanbul",
    "iso:country":"TR",
    "name:tur_x_preferred":[
        "Dolaylar"
    ],
    "wof:name":"Dolaylar",
    "wof:placetype":"locality"
},
  "geometry": {"coordinates":[27.98612,38.27663],"type":"Point"}
}