{
  "type": "Feature",
  "properties": {
    "gn:admin1_code":"22.0",
    "gn:asciiname":"Kadikoy",
    "gn:country_code":"TR",
    "gn:dem":78,
    "gn:feature_class":"P",
    "gn:feature_code":"PPL",
    "gn:name":"Kad\u0131k\u00f6y",
    "gn:population":0,
    "gn:timezone":"Europe/Istanbul",
    "iso:country":"TR",
    "wof:name":"Kadikoy",
    "wof:placetype":"locality"
},
  "geometry": {"coordinates":[26.77352,40.78034],"type":"Point"}
}