{
  "type": "Feature",
  "properties": {
    "gn:admin1_code":"63.0",
    "gn:asciiname":"Bentbahcesi",
    "gn:country_code":"TR",
    "gn:dem":450,
    "gn:feature_class":"P",
    "gn:feature_code":"PPL",
    "gn:name":"Bentbah\u00e7esi",
    "gn:population":0,
    "gn:timezone":"Europe/Istanbul",
    "iso:country":"TR",
    "name:und_x_variant":[
        "Bentbah\u00e7esi",
        "Aptallar"
    ],
    "wof:name":"Bentbahcesi",
    "wof:placetype":"locality"
},
  "geometry": {"coordinates":[38.02127,37.02047],"type":"Point"}
}