{
  "type": "Feature",
  "properties": {
    "gn:admin1_code":"04",
    "gn:asciiname":"Budak",
    "gn:country_code":"TR",
    "gn:dem":1701,
    "gn:feature_class":"P",
    "gn:feature_code":"PPL",
    "gn:name":"Budak",
    "gn:population":0,
    "gn:timezone":"Europe/Istanbul",
    "iso:country":"TR",
    "name:bos_x_preferred":[
        "Budak"
    ],
    "name:deu_x_preferred":[
        "Budak"
    ],
    "name:hrv_x_preferred":[
        "Budak"
    ],
    "name:hun_x_preferred":[
        "Budak"
    ],
    "name:nld_x_preferred":[
        "Budak"
    ],
    "name:rus_x_preferred":[
        "\u0411\u0443\u0434\u0430\u043a"
    ],
    "name:slv_x_preferred":[
        "Budak"
    ],
    "name:srp_x_preferred":[
        "\u0411\u0443\u0434\u0430\u043a"
    ],
    "name:tur_x_preferred":[
        "Budak"
    ],
    "wof:name":"Budak",
    "wof:placetype":"locality"
},
  "geometry": {"coordinates":[42.79929,39.09739],"type":"Point"}
}