{
  "type": "Feature",
  "properties": {
    "gn:admin1_code":"68.0",
    "gn:asciiname":"Inli",
    "gn:country_code":"TR",
    "gn:dem":1461,
    "gn:feature_class":"P",
    "gn:feature_code":"PPL",
    "gn:name":"\u0130nli",
    "gn:population":0,
    "gn:timezone":"Europe/Istanbul",
    "iso:country":"TR",
    "wof:name":"Inli",
    "wof:placetype":"locality"
},
  "geometry": {"coordinates":[32.85517,40.37284],"type":"Point"}
}