{
  "type": "Feature",
  "properties": {
    "gn:admin1_code":"12",
    "gn:asciiname":"Dogankaya",
    "gn:country_code":"TR",
    "gn:dem":1546,
    "gn:feature_class":"P",
    "gn:feature_code":"PPL",
    "gn:name":"Do\u011fankaya",
    "gn:population":0,
    "gn:timezone":"Europe/Istanbul",
    "iso:country":"TR",
    "name:tur_x_preferred":[
        "Do\u011fankaya"
    ],
    "wof:name":"Dogankaya",
    "wof:placetype":"locality"
},
  "geometry": {"coordinates":[40.59351,39.20369],"type":"Point"}
}