{
  "type": "Feature",
  "properties": {
    "gn:admin1_code":"58",
    "gn:asciiname":"Eskikarahisar",
    "gn:country_code":"TR",
    "gn:dem":1514,
    "gn:feature_class":"P",
    "gn:feature_code":"PPL",
    "gn:name":"Eskikarahisar",
    "gn:population":0,
    "gn:timezone":"Europe/Istanbul",
    "iso:country":"TR",
    "name:und_x_variant":[
        "Karahisar\u0131atik",
        "Eskikara\u015far",
        "Eskikarahisar"
    ],
    "wof:name":"Eskikarahisar",
    "wof:placetype":"locality"
},
  "geometry": {"coordinates":[37.23107,39.41504000000001],"type":"Point"}
}