{
  "type": "Feature",
  "properties": {
    "gn:admin1_code":"21",
    "gn:asciiname":"Ekinciler",
    "gn:country_code":"TR",
    "gn:dem":785,
    "gn:feature_class":"P",
    "gn:feature_code":"PPL",
    "gn:name":"Ekinciler",
    "gn:population":0,
    "gn:timezone":"Europe/Istanbul",
    "iso:country":"TR",
    "name:tur_x_preferred":[
        "A\u015fa\u011f\u0131ekinciler"
    ],
    "wof:name":"Ekinciler",
    "wof:placetype":"locality"
},
  "geometry": {"coordinates":[39.98178,38.148],"type":"Point"}
}