{
  "type": "Feature",
  "properties": {
    "gn:admin1_code":"16",
    "gn:asciiname":"Gumuspinar",
    "gn:country_code":"TR",
    "gn:dem":532,
    "gn:feature_class":"P",
    "gn:feature_code":"PPL",
    "gn:name":"G\u00fcm\u00fc\u015fp\u0131nar",
    "gn:population":0,
    "gn:timezone":"Europe/Istanbul",
    "iso:country":"TR",
    "name:tur_x_preferred":[
        "G\u00fcm\u00fc\u015fp\u0131nar"
    ],
    "wof:name":"Gumuspinar",
    "wof:placetype":"locality"
},
  "geometry": {"coordinates":[28.86076,39.91541],"type":"Point"}
}