{
  "type": "Feature",
  "properties": {
    "gn:admin1_code":"57.0",
    "gn:asciiname":"Benisli",
    "gn:country_code":"TR",
    "gn:dem":685,
    "gn:feature_class":"P",
    "gn:feature_code":"PPL",
    "gn:name":"Beni\u015fli",
    "gn:population":0,
    "gn:timezone":"Europe/Istanbul",
    "iso:country":"TR",
    "wof:name":"Benisli",
    "wof:placetype":"locality"
},
  "geometry": {"coordinates":[34.68451,41.36196],"type":"Point"}
}