{
  "type": "Feature",
  "properties": {
    "gn:country":"TR",
    "gn:fcode":"PPLA2",
    "gn:pop":0,
    "iso:country":"TR",
    "name:ceb_x_preferred":[
        "Kumlu \u0130l\u00e7esi"
    ],
    "name:deu_x_preferred":[
        "Kumlu"
    ],
    "name:diq_x_preferred":[
        "Kumlu"
    ],
    "name:eng_x_preferred":[
        "Kumlu"
    ],
    "name:epo_x_preferred":[
        "Kumlu"
    ],
    "name:fra_x_preferred":[
        "Kumlu"
    ],
    "name:ita_x_preferred":[
        "Distretto di Kumlu"
    ],
    "name:mrj_x_preferred":[
        "\u041a\u0443\u043c\u043b\u0443"
    ],
    "name:msa_x_preferred":[
        "Kumlu"
    ],
    "name:nan_x_preferred":[
        "Kumlu"
    ],
    "name:nld_x_preferred":[
        "Kumlu"
    ],
    "name:nob_x_preferred":[
        "Kumlu"
    ],
    "name:pnb_x_preferred":[
        "\u0636\u0644\u0639 \u06a9\u0645\u0644\u0648"
    ],
    "name:rus_x_preferred":[
        "\u041a\u0443\u043c\u043b\u0443"
    ],
    "name:sco_x_preferred":[
        "Kumlu"
    ],
    "name:swa_x_preferred":[
        "Kumlu"
    ],
    "name:tur_x_preferred":[
        "Kumlu"
    ],
    "name:unk_x_variant":[
        "Iskan"
    ],
    "name:urd_x_preferred":[
        "\u06a9\u0648\u0645\u0644\u0648"
    ],
    "name:vie_x_preferred":[
        "Kumlu"
    ],
    "qs:name":"Kumlu",
    "qs:photos_9r":0,
    "qs:photos_sr":0,
    "qs:pop_sr":"0",
    "wd:wordcount":254,
    "wof:name":"Kumlu",
    "wof:placetype":"locality",
    "wof:population":0
},
  "geometry": {"coordinates":[36.45502,36.36353],"type":"Point"}
}