{
  "type": "Feature",
  "properties": {
    "gn:admin1_code":"45",
    "gn:asciiname":"Derekoy",
    "gn:country_code":"TR",
    "gn:dem":415,
    "gn:feature_class":"P",
    "gn:feature_code":"PPL",
    "gn:name":"Derek\u00f6y",
    "gn:population":0,
    "gn:timezone":"Europe/Istanbul",
    "iso:country":"TR",
    "wof:name":"Derekoy",
    "wof:placetype":"locality"
},
  "geometry": {"coordinates":[28.76972,38.60111],"type":"Point"}
}