{
  "type": "Feature",
  "properties": {
    "gn:admin1_code":"37.0",
    "gn:asciiname":"Ahlatcik",
    "gn:country_code":"TR",
    "gn:dem":1397,
    "gn:feature_class":"P",
    "gn:feature_code":"PPL",
    "gn:name":"Ahlatc\u0131k",
    "gn:population":0,
    "gn:timezone":"Europe/Istanbul",
    "iso:country":"TR",
    "wof:name":"Ahlatcik",
    "wof:placetype":"locality"
},
  "geometry": {"coordinates":[33.34838,41.10775],"type":"Point"}
}