{
  "type": "Feature",
  "properties": {
    "gn:admin1_code":"84.0",
    "gn:asciiname":"Yarkaya",
    "gn:country_code":"TR",
    "gn:dem":1852,
    "gn:feature_class":"P",
    "gn:feature_code":"PPL",
    "gn:name":"Yarkaya",
    "gn:population":0,
    "gn:timezone":"Europe/Istanbul",
    "iso:country":"TR",
    "name:tur_x_preferred":[
        "Yarkaya"
    ],
    "wof:name":"Yarkaya",
    "wof:placetype":"locality"
},
  "geometry": {"coordinates":[42.84413,40.08918],"type":"Point"}
}