{
  "type": "Feature",
  "properties": {
    "gn:admin1_code":"91.0",
    "gn:asciiname":"Kavramlar",
    "gn:country_code":"TR",
    "gn:dem":438,
    "gn:feature_class":"P",
    "gn:feature_code":"PPL",
    "gn:name":"Kavramlar",
    "gn:population":0,
    "gn:timezone":"Europe/Istanbul",
    "iso:country":"TR",
    "wof:name":"Kavramlar",
    "wof:placetype":"locality"
},
  "geometry": {"coordinates":[36.16868,37.51786],"type":"Point"}
}