{
  "type": "Feature",
  "properties": {
    "gn:admin1_code":"63",
    "gn:asciiname":"Bulgurlu",
    "gn:country_code":"TR",
    "gn:dem":366,
    "gn:feature_class":"P",
    "gn:feature_code":"PPL",
    "gn:name":"Bulgurlu",
    "gn:population":0,
    "gn:timezone":"Europe/Istanbul",
    "iso:country":"TR",
    "name:rus_x_preferred":[
        "Letnik Byuyuk Medintel\u2019far"
    ],
    "name:tur_x_preferred":[
        "Bulgurlu"
    ],
    "name:und_x_variant":[
        "Medinet\u00fclfarikebir",
        "B\u00fcy\u00fckmedinetilfar",
        "B\u00fcy\u00fck Medintelfar Mezraas\u0131"
    ],
    "wof:name":"Bulgurlu",
    "wof:placetype":"locality"
},
  "geometry": {"coordinates":[39.09056,36.81167],"type":"Point"}
}