{
  "type": "Feature",
  "properties": {
    "gn:admin1_code":"28.0",
    "gn:asciiname":"Sinirkoy",
    "gn:country_code":"TR",
    "gn:dem":959,
    "gn:feature_class":"P",
    "gn:feature_code":"PPL",
    "gn:name":"S\u0131n\u0131rk\u00f6y",
    "gn:population":0,
    "gn:timezone":"Europe/Istanbul",
    "iso:country":"TR",
    "name:tur_x_preferred":[
        "S\u0131n\u0131rk\u00f6y"
    ],
    "wof:name":"Sinirkoy",
    "wof:placetype":"locality"
},
  "geometry": {"coordinates":[38.61163,40.68648],"type":"Point"}
}