{
  "type": "Feature",
  "properties": {
    "gn:admin1_code":"35",
    "gn:asciiname":"Pamucak",
    "gn:country_code":"TR",
    "gn:dem":4,
    "gn:feature_class":"P",
    "gn:feature_code":"PPL",
    "gn:name":"Pamucak",
    "gn:population":0,
    "gn:timezone":"Europe/Istanbul",
    "iso:country":"TR",
    "wof:name":"Pamucak",
    "wof:placetype":"locality"
},
  "geometry": {"coordinates":[27.27785,37.93973],"type":"Point"}
}