{
  "type": "Feature",
  "properties": {
    "gn:admin1_code":"70",
    "gn:asciiname":"Cevizli",
    "gn:country_code":"TR",
    "gn:dem":1469,
    "gn:feature_class":"P",
    "gn:feature_code":"PPL",
    "gn:name":"Cevizli",
    "gn:population":0,
    "gn:timezone":"Europe/Istanbul",
    "iso:country":"TR",
    "name:deu_x_preferred":[
        "Cevizli"
    ],
    "name:tur_x_preferred":[
        "Cevizli"
    ],
    "name:und_x_variant":[
        "G\u00fczere\u015f",
        "Cevizli"
    ],
    "wof:name":"Cevizli",
    "wof:placetype":"locality"
},
  "geometry": {"coordinates":[43.71486,37.33155],"type":"Point"}
}