{
  "type": "Feature",
  "properties": {
    "gn:admin1_code":"37.0",
    "gn:asciiname":"Sariomer",
    "gn:country_code":"TR",
    "gn:dem":732,
    "gn:feature_class":"P",
    "gn:feature_code":"PPL",
    "gn:name":"Sar\u0131\u00f6mer",
    "gn:population":0,
    "gn:timezone":"Europe/Istanbul",
    "iso:country":"TR",
    "name:und_x_variant":[
        "Sar\u0131\u00f6mer"
    ],
    "wof:name":"Sariomer",
    "wof:placetype":"locality"
},
  "geometry": {"coordinates":[33.78766,41.44717],"type":"Point"}
}