{
  "type": "Feature",
  "properties": {
    "gn:admin1_code":"21.0",
    "gn:asciiname":"Kalimli",
    "gn:country_code":"TR",
    "gn:dem":835,
    "gn:feature_class":"P",
    "gn:feature_code":"PPL",
    "gn:name":"Kal\u0131ml\u0131",
    "gn:population":0,
    "gn:timezone":"Europe/Istanbul",
    "iso:country":"TR",
    "wof:name":"Kalimli",
    "wof:placetype":"locality"
},
  "geometry": {"coordinates":[40.71856,38.42169000000001],"type":"Point"}
}