{
  "type": "Feature",
  "properties": {
    "gn:admin1_code":"79",
    "gn:asciiname":"Kizildere",
    "gn:country_code":"TR",
    "gn:dem":1149,
    "gn:feature_class":"P",
    "gn:feature_code":"PPL",
    "gn:name":"K\u0131z\u0131ldere",
    "gn:population":0,
    "gn:timezone":"Europe/Istanbul",
    "iso:country":"TR",
    "name:und_x_variant":[
        "K\u0131z\u0131ldere K\u00f6y\u00fc",
        "K\u0131z\u0131ldere"
    ],
    "wof:name":"Kizildere",
    "wof:placetype":"locality"
},
  "geometry": {"coordinates":[33.55,39.93333],"type":"Point"}
}