{
  "type": "Feature",
  "properties": {
    "gn:admin1_code":"25",
    "gn:asciiname":"Demirkiran",
    "gn:country_code":"TR",
    "gn:dem":1795,
    "gn:feature_class":"P",
    "gn:feature_code":"PPL",
    "gn:name":"Demirk\u0131ran",
    "gn:population":0,
    "gn:timezone":"Europe/Istanbul",
    "iso:country":"TR",
    "name:tur_x_preferred":[
        "Demirk\u0131ran"
    ],
    "wof:name":"Demirkiran",
    "wof:placetype":"locality"
},
  "geometry": {"coordinates":[40.68204,39.96242],"type":"Point"}
}