{
  "type": "Feature",
  "properties": {
    "gn:admin1_code":"04",
    "gn:asciiname":"Yalinsaz",
    "gn:country_code":"TR",
    "gn:dem":1728,
    "gn:feature_class":"P",
    "gn:feature_code":"PPL",
    "gn:name":"Yal\u0131nsaz",
    "gn:population":0,
    "gn:timezone":"Europe/Istanbul",
    "iso:country":"TR",
    "name:und_x_variant":[
        "\u00c7algani\u015femsiki",
        "\u00c7alkani\u015femsik",
        "Yal\u0131nsaz"
    ],
    "wof:name":"Yalinsaz",
    "wof:placetype":"locality"
},
  "geometry": {"coordinates":[43.88238,39.60786],"type":"Point"}
}