{
  "type": "Feature",
  "properties": {
    "gn:admin1_code":"64",
    "gn:asciiname":"Ada",
    "gn:country_code":"TR",
    "gn:dem":729,
    "gn:feature_class":"P",
    "gn:feature_code":"PPL",
    "gn:name":"Ada",
    "gn:population":0,
    "gn:timezone":"Europe/Istanbul",
    "iso:country":"TR",
    "name:tur_x_preferred":[
        "Ada"
    ],
    "wof:name":"Ada",
    "wof:placetype":"locality"
},
  "geometry": {"coordinates":[29.23178,38.77528],"type":"Point"}
}