{
  "type": "Feature",
  "properties": {
    "gn:admin1_code":"64",
    "gn:asciiname":"Ada",
    "gn:country_code":"TR",
    "gn:dem":729,
    "gn:feature_class":"P",
    "gn:feature_code":"PPL",
    "gn:name":"Ada",
    "gn:population":0,
    "gn:timezone":"Europe/Istanbul",
    "iso:country":"TR",
    "name:ara_x_preferred":[
        "\u0623\u062f\u0627"
    ],
    "name:bel_x_preferred":[
        "\u0410\u0434\u0430"
    ],
    "name:bos_x_preferred":[
        "Ada"
    ],
    "name:cat_x_preferred":[
        "Ada"
    ],
    "name:ceb_x_preferred":[
        "Ada"
    ],
    "name:ces_x_preferred":[
        "Ada"
    ],
    "name:dan_x_preferred":[
        "Ada"
    ],
    "name:fas_x_preferred":[
        "\u0622\u062f\u0627"
    ],
    "name:fin_x_preferred":[
        "Ada"
    ],
    "name:fra_x_preferred":[
        "Ada"
    ],
    "name:glg_x_preferred":[
        "Ada"
    ],
    "name:heb_x_preferred":[
        "\u05e2\u05d3\u05d4"
    ],
    "name:hrv_x_preferred":[
        "Ada"
    ],
    "name:hun_x_preferred":[
        "Ada"
    ],
    "name:hye_x_preferred":[
        "\u0531\u0564\u0561"
    ],
    "name:ind_x_preferred":[
        "Ada"
    ],
    "name:kaz_x_preferred":[
        "\u0410\u0434\u0430"
    ],
    "name:lav_x_preferred":[
        "Ada"
    ],
    "name:lit_x_preferred":[
        "Ada"
    ],
    "name:nld_x_preferred":[
        "Ada"
    ],
    "name:nno_x_preferred":[
        "Ada"
    ],
    "name:pol_x_preferred":[
        "Ada"
    ],
    "name:rus_x_preferred":[
        "\u0410\u0434\u0430"
    ],
    "name:slk_x_preferred":[
        "Ada"
    ],
    "name:slv_x_preferred":[
        "Ada"
    ],
    "name:spa_x_preferred":[
        "Ada"
    ],
    "name:srp_x_preferred":[
        "\u0410\u0434\u0430"
    ],
    "name:swe_x_preferred":[
        "Ada"
    ],
    "name:tur_x_preferred":[
        "Ada"
    ],
    "name:ukr_x_preferred":[
        "\u0410\u0434\u0430"
    ],
    "name:urd_x_preferred":[
        "\u0627\u06cc\u0688\u0627"
    ],
    "name:vie_x_preferred":[
        "Ada"
    ],
    "name:vol_x_preferred":[
        "Ada"
    ],
    "wof:name":"Ada",
    "wof:placetype":"locality"
},
  "geometry": {"coordinates":[29.23178,38.77528],"type":"Point"}
}