{
  "type": "Feature",
  "properties": {
    "gn:admin1_code":"44",
    "gn:asciiname":"Yazikoy",
    "gn:cc2":"TR",
    "gn:country_code":"TR",
    "gn:dem":1209,
    "gn:feature_class":"P",
    "gn:feature_code":"PPL",
    "gn:name":"Yaz\u0131k\u00f6y",
    "gn:population":0,
    "gn:timezone":"Europe/Istanbul",
    "iso:country":"TR",
    "name:und_x_variant":[
        "Yaz\u0131",
        "Yazk\u00f6y\u00fc",
        "Yaz\u0131 K\u00f6y\u00fc",
        "Yaz\u0131k\u00f6y"
    ],
    "wof:name":"Yazikoy",
    "wof:placetype":"locality"
},
  "geometry": {"coordinates":[37.44528,38.67472],"type":"Point"}
}