{
  "type": "Feature",
  "properties": {
    "gn:admin1_code":"81",
    "gn:asciiname":"Saygecit",
    "gn:country_code":"TR",
    "gn:dem":113,
    "gn:feature_class":"P",
    "gn:feature_code":"PPL",
    "gn:name":"Sayge\u00e7it",
    "gn:population":0,
    "gn:timezone":"Europe/Istanbul",
    "iso:country":"TR",
    "name:und_x_variant":[
        "S\u0131rk\u0131nt\u0131zl\u0131",
        "K\u0131rmit",
        "S\u0131rk\u0131nt\u0131izir",
        "S\u0131rk\u0131nt\u0131zir",
        "S\u0131rk\u0131nt\u0131izi",
        "A\u015fa\u011f\u0131 S\u0131rk\u0131nt\u0131",
        "Sayge\u00e7it"
    ],
    "wof:name":"Saygecit",
    "wof:placetype":"locality"
},
  "geometry": {"coordinates":[35.62554,37.24957],"type":"Point"}
}