{
  "type": "Feature",
  "properties": {
    "gn:admin1_code":"91.0",
    "gn:asciiname":"Dereli",
    "gn:country_code":"TR",
    "gn:dem":154,
    "gn:feature_class":"P",
    "gn:feature_code":"PPL",
    "gn:name":"Dereli",
    "gn:population":0,
    "gn:timezone":"Europe/Istanbul",
    "iso:country":"TR",
    "name:ceb_x_preferred":[
        "Dereli"
    ],
    "name:ces_x_preferred":[
        "Dereli"
    ],
    "name:deu_x_preferred":[
        "Dereli"
    ],
    "name:epo_x_preferred":[
        "Dereli"
    ],
    "name:fra_x_preferred":[
        "Dereli"
    ],
    "name:mrj_x_preferred":[
        "\u0414\u0435\u0440\u0435\u043b\u0438"
    ],
    "name:msa_x_preferred":[
        "Dereli"
    ],
    "name:nld_x_preferred":[
        "Dereli"
    ],
    "name:nor_x_preferred":[
        "Dereli"
    ],
    "name:swa_x_preferred":[
        "Dereli"
    ],
    "name:tur_x_preferred":[
        "Dereli"
    ],
    "name:urd_x_preferred":[
        "\u062f\u06cc\u0631\u06cc\u0644\u06cc"
    ],
    "name:vie_x_preferred":[
        "Dereli"
    ],
    "wof:name":"Dereli",
    "wof:placetype":"locality"
},
  "geometry": {"coordinates":[36.31695,37.10494],"type":"Point"}
}