{
  "type": "Feature",
  "properties": {
    "gn:admin1_code":"14.0",
    "gn:asciiname":"Banaz",
    "gn:country_code":"TR",
    "gn:dem":877,
    "gn:feature_class":"P",
    "gn:feature_code":"PPL",
    "gn:name":"Banaz",
    "gn:population":0,
    "gn:timezone":"Europe/Istanbul",
    "iso:country":"TR",
    "name:und_x_variant":[
        "Banaz\u00e7and\u0131r",
        "Banas",
        "Banaz"
    ],
    "wof:name":"Banaz",
    "wof:placetype":"locality"
},
  "geometry": {"coordinates":[31.73453,40.80947000000001],"type":"Point"}
}