{
  "type": "Feature",
  "properties": {
    "gn:admin1_code":"32",
    "gn:asciiname":"Mucuk",
    "gn:country_code":"TR",
    "gn:dem":130,
    "gn:feature_class":"P",
    "gn:feature_code":"PPL",
    "gn:name":"Mucuk",
    "gn:population":0,
    "gn:timezone":"Europe/Istanbul",
    "iso:country":"TR",
    "wof:name":"Mucuk",
    "wof:placetype":"locality"
},
  "geometry": {"coordinates":[33.37677,36.58644],"type":"Point"}
}