{
  "type": "Feature",
  "properties": {
    "iso:country":"TR",
    "wof:name":"Emniyet Evleri",
    "wof:placetype":"neighbourhood"
},
  "geometry": {"coordinates":[29.00342052011149,41.08639227724019],"type":"Point"}
}