{
  "type": "Feature",
  "properties": {
    "gn:admin1_code":"54.0",
    "gn:asciiname":"Celebiler",
    "gn:country_code":"TR",
    "gn:dem":27,
    "gn:feature_class":"P",
    "gn:feature_code":"PPL",
    "gn:name":"\u00c7elebiler",
    "gn:population":0,
    "gn:timezone":"Europe/Istanbul",
    "iso:country":"TR",
    "name:tur_x_preferred":[
        "\u00c7elebiler"
    ],
    "wof:name":"Celebiler",
    "wof:placetype":"locality"
},
  "geometry": {"coordinates":[30.45607,40.81011],"type":"Point"}
}