{
  "type": "Feature",
  "properties": {
    "gn:admin1_code":"14",
    "gn:asciiname":"Ikinci Afsar",
    "gn:country_code":"TR",
    "gn:dem":1192,
    "gn:feature_class":"P",
    "gn:feature_code":"PPL",
    "gn:name":"\u0130kinci Af\u015far",
    "gn:population":0,
    "gn:timezone":"Europe/Istanbul",
    "iso:country":"TR",
    "name:tur_x_preferred":[
        "\u0130kinci Af\u015far"
    ],
    "wof:name":"Ikinci Afsar",
    "wof:placetype":"locality"
},
  "geometry": {"coordinates":[32.30219,40.74754],"type":"Point"}
}