{
  "type": "Feature",
  "properties": {
    "gn:admin1_code":"73",
    "gn:asciiname":"Himmetli",
    "gn:country_code":"TR",
    "gn:dem":1594,
    "gn:feature_class":"P",
    "gn:feature_code":"PPL",
    "gn:name":"Himmetli",
    "gn:population":0,
    "gn:timezone":"Europe/Istanbul",
    "iso:country":"TR",
    "name:und_x_variant":[
        "Lafsan",
        "Himmetli"
    ],
    "wof:name":"Himmetli",
    "wof:placetype":"locality"
},
  "geometry": {"coordinates":[34.93502,38.02709],"type":"Point"}
}