{
  "type": "Feature",
  "properties": {
    "gn:admin1_code":"82",
    "gn:asciiname":"Yamacbasi",
    "gn:country_code":"TR",
    "gn:dem":1409,
    "gn:feature_class":"P",
    "gn:feature_code":"PPL",
    "gn:name":"Yama\u00e7ba\u015f\u0131",
    "gn:population":0,
    "gn:timezone":"Europe/Istanbul",
    "iso:country":"TR",
    "name:tur_x_preferred":[
        "Yama\u00e7ba\u015f\u0131"
    ],
    "wof:name":"Yamacbasi",
    "wof:placetype":"locality"
},
  "geometry": {"coordinates":[33.94410999999999,40.70911],"type":"Point"}
}