{
  "type": "Feature",
  "properties": {
    "gn:admin1_code":"68.0",
    "gn:asciiname":"Gelegra",
    "gn:country_code":"TR",
    "gn:dem":895,
    "gn:feature_class":"P",
    "gn:feature_code":"PPLA3",
    "gn:name":"Gelegra",
    "gn:population":0,
    "gn:timezone":"Europe/Istanbul",
    "iso:country":"TR",
    "name:und_x_variant":[
        "K\u0131rba\u015f\u0131"
    ],
    "wof:name":"Gelegra",
    "wof:placetype":"locality"
},
  "geometry": {"coordinates":[31.83197,40.01378],"type":"Point"}
}