{
  "type": "Feature",
  "properties": {
    "gn:admin1_code":"04",
    "gn:asciiname":"Sobetas",
    "gn:country_code":"TR",
    "gn:dem":1761,
    "gn:feature_class":"P",
    "gn:feature_code":"PPL",
    "gn:name":"S\u00f6beta\u015f",
    "gn:population":0,
    "gn:timezone":"Europe/Istanbul",
    "iso:country":"TR",
    "name:und_x_variant":[
        "Ha\u015fto",
        "S\u00f6beta\u015f"
    ],
    "wof:name":"Sobetas",
    "wof:placetype":"locality"
},
  "geometry": {"coordinates":[42.7972,39.71038],"type":"Point"}
}