{
  "type": "Feature",
  "properties": {
    "gn:admin1_code":"19.0",
    "gn:asciiname":"Yarimca",
    "gn:country_code":"TR",
    "gn:dem":575,
    "gn:feature_class":"P",
    "gn:feature_code":"PPL",
    "gn:name":"Yar\u0131mca",
    "gn:population":0,
    "gn:timezone":"Europe/Istanbul",
    "iso:country":"TR",
    "wof:name":"Yarimca",
    "wof:placetype":"locality"
},
  "geometry": {"coordinates":[34.34735999999999,40.50588],"type":"Point"}
}