{
  "type": "Feature",
  "properties": {
    "gn:admin1_code":"78",
    "gn:asciiname":"Camlica",
    "gn:country_code":"TR",
    "gn:dem":949,
    "gn:feature_class":"P",
    "gn:feature_code":"PPL",
    "gn:name":"\u00c7aml\u0131ca",
    "gn:population":0,
    "gn:timezone":"Europe/Istanbul",
    "iso:country":"TR",
    "name:und_x_variant":[
        "\u00c7aml\u0131ca",
        "Mihaller"
    ],
    "wof:name":"Camlica",
    "wof:placetype":"locality"
},
  "geometry": {"coordinates":[33.02317,36.61583],"type":"Point"}
}