{
  "type": "Feature",
  "properties": {
    "gn:admin1_code":"48",
    "gn:asciiname":"Deviciler",
    "gn:country_code":"TR",
    "gn:dem":302,
    "gn:feature_class":"P",
    "gn:feature_code":"PPL",
    "gn:name":"Deviciler",
    "gn:population":0,
    "gn:timezone":"Europe/Istanbul",
    "iso:country":"TR",
    "name:tur_x_preferred":[
        "Deviciler"
    ],
    "name:tur_x_variant":[
        "Zeyve"
    ],
    "wof:name":"Deviciler",
    "wof:placetype":"locality"
},
  "geometry": {"coordinates":[29.40936,36.56124000000001],"type":"Point"}
}