{
  "type": "Feature",
  "properties": {
    "gn:admin1_code":"57.0",
    "gn:asciiname":"Cesnigir",
    "gn:country_code":"TR",
    "gn:dem":522,
    "gn:feature_class":"P",
    "gn:feature_code":"PPL",
    "gn:name":"Ce\u015fnigir",
    "gn:population":0,
    "gn:timezone":"Europe/Istanbul",
    "iso:country":"TR",
    "wof:name":"Cesnigir",
    "wof:placetype":"locality"
},
  "geometry": {"coordinates":[34.946,41.55314],"type":"Point"}
}