{
  "type": "Feature",
  "properties": {
    "gn:admin1_code":"82.0",
    "gn:asciiname":"Cicekkoy",
    "gn:country_code":"TR",
    "gn:dem":1316,
    "gn:feature_class":"P",
    "gn:feature_code":"PPL",
    "gn:name":"\u00c7i\u00e7ekk\u00f6y",
    "gn:population":0,
    "gn:timezone":"Europe/Istanbul",
    "iso:country":"TR",
    "name:tur_x_preferred":[
        "\u00c7i\u00e7ek"
    ],
    "name:tur_x_variant":[
        "\u00c7i\u00e7ekk\u00f6y"
    ],
    "wof:name":"Cicekkoy",
    "wof:placetype":"locality"
},
  "geometry": {"coordinates":[34.00489,40.76235],"type":"Point"}
}