{
  "type": "Feature",
  "properties": {
    "gn:admin1_code":"65",
    "gn:asciiname":"Govan",
    "gn:cc2":"TR",
    "gn:country_code":"TR",
    "gn:dem":2323,
    "gn:feature_class":"P",
    "gn:feature_code":"PPL",
    "gn:name":"Govan",
    "gn:population":0,
    "gn:timezone":"Europe/Istanbul",
    "iso:country":"TR",
    "name:afr_x_preferred":[
        "Govan"
    ],
    "name:aze_x_preferred":[
        "Qovan"
    ],
    "name:deu_x_preferred":[
        "Govan"
    ],
    "name:eus_x_preferred":[
        "Govan"
    ],
    "name:fra_x_preferred":[
        "Govan"
    ],
    "name:glg_x_preferred":[
        "Govan"
    ],
    "name:ita_x_preferred":[
        "Govan"
    ],
    "name:nor_x_preferred":[
        "Govan"
    ],
    "name:pol_x_preferred":[
        "Govan"
    ],
    "name:por_x_preferred":[
        "Govan"
    ],
    "name:sco_x_preferred":[
        "Gouan"
    ],
    "name:ukr_x_preferred":[
        "\u0413\u043e\u0432\u0430\u043d\u044c"
    ],
    "name:und_x_variant":[
        "Kovan"
    ],
    "wof:name":"Govan",
    "wof:placetype":"locality"
},
  "geometry": {"coordinates":[43.26778,37.95694],"type":"Point"}
}