{
  "type": "Feature",
  "properties": {
    "gn:admin1_code":"61.0",
    "gn:asciiname":"Seyitahmet",
    "gn:country_code":"TR",
    "gn:dem":235,
    "gn:feature_class":"P",
    "gn:feature_code":"PPL",
    "gn:name":"\u015eeyitahmet",
    "gn:population":0,
    "gn:timezone":"Europe/Istanbul",
    "iso:country":"TR",
    "name:tur_x_preferred":[
        "\u015eeyitahmet"
    ],
    "name:und_x_variant":[
        "\u015eehitahmet",
        "Yuvabolu"
    ],
    "wof:name":"Seyitahmet",
    "wof:placetype":"locality"
},
  "geometry": {"coordinates":[39.17168,41.0641],"type":"Point"}
}