{
  "type": "Feature",
  "properties": {
    "gn:admin1_code":"60.0",
    "gn:asciiname":"Yagsiyan",
    "gn:country_code":"TR",
    "gn:dem":1505,
    "gn:feature_class":"P",
    "gn:feature_code":"PPL",
    "gn:name":"Ya\u011fsiyan",
    "gn:population":0,
    "gn:timezone":"Europe/Istanbul",
    "iso:country":"TR",
    "name:eng_x_preferred":[
        "Ya\u011f\u015f\u0131yan"
    ],
    "name:rus_x_preferred":[
        "\u042f\u0433\u0441\u044b\u044f\u043d"
    ],
    "name:tur_x_preferred":[
        "Ya\u011fsiyan"
    ],
    "name:und_x_variant":[
        "Ya\u011f\u0131s\u0131yan",
        "Ya\u011f\u015f\u0131yan"
    ],
    "wof:name":"Yagsiyan",
    "wof:placetype":"locality"
},
  "geometry": {"coordinates":[37.57714,40.49027],"type":"Point"}
}