{
  "type": "Feature",
  "properties": {
    "gn:admin1_code":"49",
    "gn:asciiname":"Ilica",
    "gn:country_code":"TR",
    "gn:dem":1872,
    "gn:feature_class":"P",
    "gn:feature_code":"PPL",
    "gn:name":"Il\u0131ca",
    "gn:population":0,
    "gn:timezone":"Europe/Istanbul",
    "iso:country":"TR",
    "name:ceb_x_preferred":[
        "Ilica"
    ],
    "name:fra_x_preferred":[
        "Ilica"
    ],
    "name:swe_x_preferred":[
        "Ilica"
    ],
    "name:tur_x_preferred":[
        "Il\u0131ca"
    ],
    "wof:name":"Ilica",
    "wof:placetype":"locality"
},
  "geometry": {"coordinates":[41.51667,38.58333],"type":"Point"}
}