{
  "type": "Feature",
  "properties": {
    "gn:admin1_code":"13",
    "gn:asciiname":"Tihip",
    "gn:country_code":"TR",
    "gn:dem":1616,
    "gn:feature_class":"P",
    "gn:feature_code":"PPL",
    "gn:name":"Tihip",
    "gn:population":0,
    "gn:timezone":"Europe/Istanbul",
    "iso:country":"TR",
    "name:tur_x_preferred":[
        "K\u00fcll\u00fcce"
    ],
    "wof:name":"Tihip",
    "wof:placetype":"locality"
},
  "geometry": {"coordinates":[41.93505,38.55097],"type":"Point"}
}