{
  "type": "Feature",
  "properties": {
    "gn:admin1_code":"90.0",
    "gn:asciiname":"Tatgemrigi",
    "gn:country_code":"TR",
    "gn:dem":682,
    "gn:feature_class":"P",
    "gn:feature_code":"PPL",
    "gn:name":"Tatgemrigi",
    "gn:population":0,
    "gn:timezone":"Europe/Istanbul",
    "iso:country":"TR",
    "wof:name":"Tatgemrigi",
    "wof:placetype":"locality"
},
  "geometry": {"coordinates":[37.00389000000001,36.88917],"type":"Point"}
}