{
  "type": "Feature",
  "properties": {
    "gn:admin1_code":"60.0",
    "gn:asciiname":"Kocak",
    "gn:country_code":"TR",
    "gn:dem":448,
    "gn:feature_class":"P",
    "gn:feature_code":"PPL",
    "gn:name":"Ko\u00e7ak",
    "gn:population":0,
    "gn:timezone":"Europe/Istanbul",
    "iso:country":"TR",
    "name:eng_x_preferred":[
        "Ko\u00e7ak"
    ],
    "name:rus_x_preferred":[
        "\u042d\u043a\u0441\u0435\u043b\u044c"
    ],
    "name:und_x_variant":[
        "Eksel",
        "Ko\u00e7ak"
    ],
    "wof:name":"Kocak",
    "wof:placetype":"locality"
},
  "geometry": {"coordinates":[36.50655,40.64102000000001],"type":"Point"}
}