{
  "type": "Feature",
  "properties": {
    "gn:admin1_code":"28.0",
    "gn:asciiname":"Kizilcainek",
    "gn:country_code":"TR",
    "gn:dem":431,
    "gn:feature_class":"P",
    "gn:feature_code":"PPL",
    "gn:name":"K\u0131z\u0131lcainek",
    "gn:population":0,
    "gn:timezone":"Europe/Istanbul",
    "iso:country":"TR",
    "wof:name":"Kizilcainek",
    "wof:placetype":"locality"
},
  "geometry": {"coordinates":[39.01691,40.90435],"type":"Point"}
}