{
  "type": "Feature",
  "properties": {
    "gn:admin1_code":"74",
    "gn:asciiname":"Belekmer",
    "gn:cc2":"TR",
    "gn:country_code":"TR",
    "gn:dem":774,
    "gn:feature_class":"P",
    "gn:feature_code":"PPL",
    "gn:name":"Belekmer",
    "gn:population":0,
    "gn:timezone":"Europe/Istanbul",
    "iso:country":"TR",
    "name:und_x_variant":[
        "Belkemer",
        "Belekmer"
    ],
    "wof:name":"Belekmer",
    "wof:placetype":"locality"
},
  "geometry": {"coordinates":[41.70194,37.79028],"type":"Point"}
}