{
  "type": "Feature",
  "properties": {
    "gn:admin1_code":"37.0",
    "gn:asciiname":"Citkoy",
    "gn:country_code":"TR",
    "gn:dem":880,
    "gn:feature_class":"P",
    "gn:feature_code":"PPL",
    "gn:name":"\u00c7itk\u00f6y",
    "gn:population":0,
    "gn:timezone":"Europe/Istanbul",
    "iso:country":"TR",
    "name:tur_x_preferred":[
        "\u00c7itk\u00f6y"
    ],
    "name:und_x_variant":[
        "K\u00f6seo\u011flu"
    ],
    "wof:name":"Citkoy",
    "wof:placetype":"locality"
},
  "geometry": {"coordinates":[34.0808,41.41565],"type":"Point"}
}