{
  "type": "Feature",
  "properties": {
    "gn:country":"TR",
    "gn:fcode":"PPL",
    "gn:population":3810,
    "iso:country":"TR",
    "name:ast_x_preferred":[
        "O\u011fuz \u00c7al\u0131\u015fkan"
    ],
    "name:deu_x_preferred":[
        "O\u011fuz \u00c7al\u0131\u015fkan"
    ],
    "name:eng_x_preferred":[
        "O\u011fuz \u00c7al\u0131\u015fkan"
    ],
    "name:fra_x_preferred":[
        "O\u011fuz \u00c7al\u0131\u015fkan"
    ],
    "name:nld_x_preferred":[
        "O\u011fuz \u00c7al\u0131\u015fkan"
    ],
    "name:slv_x_preferred":[
        "O\u011fuz \u00c7al\u0131\u015fkan"
    ],
    "name:spa_x_preferred":[
        "O\u011fuz \u00c7al\u0131\u015fkan"
    ],
    "name:sqi_x_preferred":[
        "O\u011fuz \u00c7al\u0131\u015fkan"
    ],
    "name:tur_x_preferred":[
        "O\u011fuz \u00c7al\u0131\u015fkan"
    ],
    "name:und_x_variant":[
        "Gitta"
    ],
    "qs:name":"\u00c7al\u0131\u015fkan",
    "qs:photos_9r":0,
    "qs:photos_sr":0,
    "qs:pop_sr":"4",
    "wd:wordcount":35,
    "wof:name":"\u00c7al\u0131\u015fkan",
    "wof:placetype":"locality",
    "wof:population":3810
},
  "geometry": {"coordinates":[42.64361,37.29722],"type":"Point"}
}