{
  "type": "Feature",
  "properties": {
    "gn:country":"TR",
    "gn:fcode":"PPL",
    "gn:pop":3810,
    "iso:country":"TR",
    "name:unk_x_variant":[
        "Gitta"
    ],
    "qs:name":"\u00c7al\u0131\u015fkan",
    "qs:photos_9r":0,
    "qs:photos_sr":0,
    "qs:pop_sr":"4",
    "wd:wordcount":35,
    "wof:name":"\u00c7al\u0131\u015fkan",
    "wof:placetype":"locality",
    "wof:population":3810
},
  "geometry": {"coordinates":[42.64361,37.29722],"type":"Point"}
}