{
  "type": "Feature",
  "properties": {
    "gn:admin1_code":"13",
    "gn:asciiname":"Alkoyun",
    "gn:country_code":"TR",
    "gn:dem":1720,
    "gn:feature_class":"P",
    "gn:feature_code":"PPL",
    "gn:name":"Alkoyun",
    "gn:population":0,
    "gn:timezone":"Europe/Istanbul",
    "iso:country":"TR",
    "name:tur_x_preferred":[
        "Alkoyun"
    ],
    "wof:name":"Alkoyun",
    "wof:placetype":"locality"
},
  "geometry": {"coordinates":[41.68936,38.46157],"type":"Point"}
}