{
  "type": "Feature",
  "properties": {
    "gn:admin1_code":"70",
    "gn:asciiname":"Umutlu",
    "gn:country_code":"TR",
    "gn:dem":1730,
    "gn:feature_class":"P",
    "gn:feature_code":"PPL",
    "gn:name":"Umutlu",
    "gn:population":0,
    "gn:timezone":"Europe/Istanbul",
    "iso:country":"TR",
    "name:und_x_variant":[
        "Edrebay",
        "Umutlu",
        "Urya"
    ],
    "wof:name":"Umutlu",
    "wof:placetype":"locality"
},
  "geometry": {"coordinates":[43.60889,37.55181],"type":"Point"}
}