{
  "type": "Feature",
  "properties": {
    "gn:admin1_code":"85.0",
    "gn:asciiname":"Sombeyler",
    "gn:country_code":"TR",
    "gn:dem":745,
    "gn:feature_class":"P",
    "gn:feature_code":"PPL",
    "gn:name":"Sombeyler",
    "gn:population":0,
    "gn:timezone":"Europe/Istanbul",
    "iso:country":"TR",
    "name:und_x_variant":[
        "H\u00fcseyinbeyler"
    ],
    "wof:name":"Sombeyler",
    "wof:placetype":"locality"
},
  "geometry": {"coordinates":[31.86667000000001,41.16667],"type":"Point"}
}