{
  "type": "Feature",
  "properties": {
    "gn:admin1_code":"75",
    "gn:asciiname":"Ceceli",
    "gn:country_code":"TR",
    "gn:dem":1162,
    "gn:feature_class":"P",
    "gn:feature_code":"PPL",
    "gn:name":"Ceceli",
    "gn:population":0,
    "gn:timezone":"Europe/Istanbul",
    "iso:country":"TR",
    "wof:name":"Ceceli",
    "wof:placetype":"locality"
},
  "geometry": {"coordinates":[34.24647,38.73058],"type":"Point"}
}