{
  "type": "Feature",
  "properties": {
    "gn:admin1_code":"16.0",
    "gn:asciiname":"Cayli",
    "gn:country_code":"TR",
    "gn:dem":58,
    "gn:feature_class":"P",
    "gn:feature_code":"PPL",
    "gn:name":"\u00c7ayl\u0131",
    "gn:population":0,
    "gn:timezone":"Europe/Istanbul",
    "iso:country":"TR",
    "name:ceb_x_preferred":[
        "Cayli"
    ],
    "name:swe_x_preferred":[
        "Cayli"
    ],
    "name:und_x_variant":[
        "\u00c7ayl\u0131",
        "Anafor",
        "Anahor"
    ],
    "wof:name":"Cayli",
    "wof:placetype":"locality"
},
  "geometry": {"coordinates":[28.7447,40.27682],"type":"Point"}
}