{
  "type": "Feature",
  "properties": {
    "gn:admin1_code":"44",
    "gn:asciiname":"Konak",
    "gn:country_code":"TR",
    "gn:dem":1117,
    "gn:feature_class":"P",
    "gn:feature_code":"PPL",
    "gn:name":"Konak",
    "gn:population":0,
    "gn:timezone":"Europe/Istanbul",
    "iso:country":"TR",
    "name:bos_x_preferred":[
        "Konak"
    ],
    "name:bul_x_preferred":[
        "\u041a\u043e\u043d\u0430\u043a"
    ],
    "name:ceb_x_preferred":[
        "Konak"
    ],
    "name:deu_x_preferred":[
        "Konak"
    ],
    "name:fra_x_preferred":[
        "Konak"
    ],
    "name:hun_x_preferred":[
        "Konak"
    ],
    "name:nld_x_preferred":[
        "Konak"
    ],
    "name:rus_x_preferred":[
        "\u041a\u043e\u043d\u0430\u043a"
    ],
    "name:slv_x_preferred":[
        "Konak"
    ],
    "name:spa_x_preferred":[
        "Konak"
    ],
    "name:srp_x_preferred":[
        "\u041a\u043e\u043d\u0430\u043a"
    ],
    "name:swe_x_preferred":[
        "Konak"
    ],
    "name:tur_x_preferred":[
        "Konak"
    ],
    "wof:name":"Konak",
    "wof:placetype":"locality"
},
  "geometry": {"coordinates":[38.29811,38.29794],"type":"Point"}
}