{
  "type": "Feature",
  "properties": {
    "gn:admin1_code":"25.0",
    "gn:asciiname":"Sihcek",
    "gn:country_code":"TR",
    "gn:dem":1952,
    "gn:feature_class":"P",
    "gn:feature_code":"PPL",
    "gn:name":"S\u0131h\u00e7ek",
    "gn:population":0,
    "gn:timezone":"Europe/Istanbul",
    "iso:country":"TR",
    "wof:name":"Sihcek",
    "wof:placetype":"locality"
},
  "geometry": {"coordinates":[42.01667,40.63333],"type":"Point"}
}