{
  "type": "Feature",
  "properties": {
    "gn:admin1_code":"83",
    "gn:asciiname":"Mesthuyuk",
    "gn:country_code":"TR",
    "gn:dem":490,
    "gn:feature_class":"P",
    "gn:feature_code":"PPL",
    "gn:name":"Mesth\u00fcy\u00fck",
    "gn:population":0,
    "gn:timezone":"Europe/Istanbul",
    "iso:country":"TR",
    "name:tur_x_preferred":[
        "Mesth\u00fcy\u00fck"
    ],
    "wof:name":"Mesthuyuk",
    "wof:placetype":"locality"
},
  "geometry": {"coordinates":[36.81389,37.21681],"type":"Point"}
}