{
  "type": "Feature",
  "properties": {
    "gn:admin1_code":"84.0",
    "gn:asciiname":"Tsatak",
    "gn:country_code":"TR",
    "gn:dem":1939,
    "gn:feature_class":"P",
    "gn:feature_code":"PPL",
    "gn:name":"Tsatak",
    "gn:population":0,
    "gn:timezone":"Europe/Istanbul",
    "iso:country":"TR",
    "name:ell_x_preferred":[
        "\u03a4\u03c3\u03b1\u03c4\u03ac\u03c7"
    ],
    "name:ell_x_variant":[
        "\u03a4\u03c3\u03b1\u03c4\u03ac\u03ba"
    ],
    "name:eng_x_preferred":[
        "Tsatak"
    ],
    "name:rus_x_preferred":[
        "\u0427\u0430\u0442\u0430\u043a"
    ],
    "name:tur_x_preferred":[
        "\u00c7atak"
    ],
    "wof:name":"Tsatak",
    "wof:placetype":"locality"
},
  "geometry": {"coordinates":[42.67528,40.40154],"type":"Point"}
}