{
  "type": "Feature",
  "properties": {
    "gn:admin1_code":"89.0",
    "gn:asciiname":"Doglacik",
    "gn:country_code":"TR",
    "gn:dem":1154,
    "gn:feature_class":"P",
    "gn:feature_code":"PPL",
    "gn:name":"Do\u011flac\u0131k",
    "gn:population":0,
    "gn:timezone":"Europe/Istanbul",
    "iso:country":"TR",
    "name:und_x_variant":[
        "To\u011flac\u0131k",
        "Tu\u011flac\u0131k",
        "Do\u011flac\u0131k"
    ],
    "wof:name":"Doglacik",
    "wof:placetype":"locality"
},
  "geometry": {"coordinates":[32.69256,40.90404],"type":"Point"}
}