{
  "type": "Feature",
  "properties": {
    "gn:admin1_code":"74.0",
    "gn:asciiname":"Hirbe",
    "gn:country_code":"TR",
    "gn:dem":627,
    "gn:feature_class":"P",
    "gn:feature_code":"PPL",
    "gn:name":"Hirbe",
    "gn:population":0,
    "gn:timezone":"Europe/Istanbul",
    "iso:country":"TR",
    "name:und_x_variant":[
        "Hirbehallak"
    ],
    "wof:name":"Hirbe",
    "wof:placetype":"locality"
},
  "geometry": {"coordinates":[41.70111,37.76528],"type":"Point"}
}