{
  "type": "Feature",
  "properties": {
    "gn:admin1_code":"89.0",
    "gn:asciiname":"Nebioglu",
    "gn:country_code":"TR",
    "gn:dem":434,
    "gn:feature_class":"P",
    "gn:feature_code":"PPL",
    "gn:name":"Nebio\u011flu",
    "gn:population":0,
    "gn:timezone":"Europe/Istanbul",
    "iso:country":"TR",
    "wof:name":"Nebioglu",
    "wof:placetype":"locality"
},
  "geometry": {"coordinates":[32.68367,41.44249],"type":"Point"}
}