{
  "type": "Feature",
  "properties": {
    "iso:country":"TR",
    "name:eng_x_preferred":[
        "Sogullu"
    ],
    "name:tur_x_preferred":[
        "So\u011fullu"
    ],
    "wof:name":"Sogullu",
    "wof:placetype":"neighbourhood"
},
  "geometry": {"coordinates":[29.82185256376316,41.09433252105606],"type":"Point"}
}