{
  "type": "Feature",
  "properties": {
    "gn:admin1_code":"35",
    "gn:asciiname":"Aydogdu",
    "gn:country_code":"TR",
    "gn:dem":351,
    "gn:feature_class":"P",
    "gn:feature_code":"PPL",
    "gn:name":"Aydo\u011fdu",
    "gn:population":0,
    "gn:timezone":"Europe/Istanbul",
    "iso:country":"TR",
    "name:tur_x_preferred":[
        "Aydo\u011fdu"
    ],
    "wof:name":"Aydogdu",
    "wof:placetype":"locality"
},
  "geometry": {"coordinates":[28.2511,38.24218],"type":"Point"}
}