{
  "type": "Feature",
  "properties": {
    "gn:admin1_code":"49",
    "gn:asciiname":"Hosgeldi",
    "gn:country_code":"TR",
    "gn:dem":1427,
    "gn:feature_class":"P",
    "gn:feature_code":"PPL",
    "gn:name":"Ho\u015fgeldi",
    "gn:population":0,
    "gn:timezone":"Europe/Istanbul",
    "iso:country":"TR",
    "name:tur_x_preferred":[
        "Ho\u015fgeldi"
    ],
    "wof:name":"Hosgeldi",
    "wof:placetype":"locality"
},
  "geometry": {"coordinates":[41.98849000000001,39.0539],"type":"Point"}
}