{
  "type": "Feature",
  "properties": {
    "gn:admin1_code":"54",
    "gn:asciiname":"Beylice",
    "gn:country_code":"TR",
    "gn:dem":319,
    "gn:feature_class":"P",
    "gn:feature_code":"PPL",
    "gn:name":"Beylice",
    "gn:population":0,
    "gn:timezone":"Europe/Istanbul",
    "iso:country":"TR",
    "name:tur_x_preferred":[
        "Beylice"
    ],
    "wof:name":"Beylice",
    "wof:placetype":"locality"
},
  "geometry": {"coordinates":[30.86284,40.82797],"type":"Point"}
}