{
  "type": "Feature",
  "properties": {
    "gn:admin1_code":"68",
    "gn:asciiname":"Velihimmetli",
    "gn:country_code":"TR",
    "gn:dem":1126,
    "gn:feature_class":"P",
    "gn:feature_code":"PPL",
    "gn:name":"Velihimmetli",
    "gn:population":0,
    "gn:timezone":"Europe/Istanbul",
    "iso:country":"TR",
    "wof:name":"Velihimmetli",
    "wof:placetype":"locality"
},
  "geometry": {"coordinates":[32.65526,39.68924000000001],"type":"Point"}
}