{
  "type": "Feature",
  "properties": {
    "gn:admin1_code":"15.0",
    "gn:asciiname":"Kiprit",
    "gn:country_code":"TR",
    "gn:dem":1057,
    "gn:feature_class":"P",
    "gn:feature_code":"PPL",
    "gn:name":"Kiprit",
    "gn:population":0,
    "gn:timezone":"Europe/Istanbul",
    "iso:country":"TR",
    "name:tur_x_preferred":[
        "Kiprit"
    ],
    "name:tur_x_variant":[
        "Kibrit"
    ],
    "wof:name":"Kiprit",
    "wof:placetype":"locality"
},
  "geometry": {"coordinates":[30.50722,37.60028],"type":"Point"}
}