{
  "type": "Feature",
  "properties": {
    "gn:admin1_code":"65.0",
    "gn:asciiname":"Ikizdegermen",
    "gn:country_code":"TR",
    "gn:dem":2292,
    "gn:feature_class":"P",
    "gn:feature_code":"PPL",
    "gn:name":"\u0130kizde\u011fermen",
    "gn:population":0,
    "gn:timezone":"Europe/Istanbul",
    "iso:country":"TR",
    "name:tur_x_preferred":[
        "\u0130kizde\u011fermen"
    ],
    "wof:name":"Ikizdegermen",
    "wof:placetype":"locality"
},
  "geometry": {"coordinates":[44.22057,38.26832],"type":"Point"}
}