{
  "type": "Feature",
  "properties": {
    "gn:admin1_code":"44",
    "gn:asciiname":"Zahmettin",
    "gn:country_code":"TR",
    "gn:dem":1640,
    "gn:feature_class":"P",
    "gn:feature_code":"PPL",
    "gn:name":"Zahmettin",
    "gn:population":0,
    "gn:timezone":"Europe/Istanbul",
    "iso:country":"TR",
    "name:und_x_variant":[
        "G\u00fc\u00e7l\u00fc",
        "Zahmettin"
    ],
    "wof:name":"Zahmettin",
    "wof:placetype":"locality"
},
  "geometry": {"coordinates":[37.88174,38.64733],"type":"Point"}
}