{
  "type": "Feature",
  "properties": {
    "gn:admin1_code":"46",
    "gn:asciiname":"Sivricehuyuk",
    "gn:country_code":"TR",
    "gn:dem":542,
    "gn:feature_class":"P",
    "gn:feature_code":"PPL",
    "gn:name":"Sivriceh\u00fcy\u00fck",
    "gn:population":0,
    "gn:timezone":"Europe/Istanbul",
    "iso:country":"TR",
    "name:tur_x_preferred":[
        "Sivriceh\u00fcy\u00fck"
    ],
    "wof:name":"Sivricehuyuk",
    "wof:placetype":"locality"
},
  "geometry": {"coordinates":[37.00771,37.42645],"type":"Point"}
}