{
  "type": "Feature",
  "properties": {
    "iso:country":"TR",
    "name:ceb_x_preferred":[
        "Karaburun \u0130l\u00e7esi"
    ],
    "name:deu_x_preferred":[
        "Karaburun"
    ],
    "name:diq_x_preferred":[
        "Karaburun"
    ],
    "name:epo_x_preferred":[
        "Karaburun"
    ],
    "name:fra_x_preferred":[
        "Karaburun"
    ],
    "name:mrj_x_preferred":[
        "\u041a\u0430\u0440\u0430\u0431\u0443\u0440\u0443\u043d"
    ],
    "name:msa_x_preferred":[
        "Karaburun"
    ],
    "name:nld_x_preferred":[
        "Karaburun"
    ],
    "name:nor_x_preferred":[
        "Karaburun"
    ],
    "name:spa_x_preferred":[
        "Karaburun"
    ],
    "name:swa_x_preferred":[
        "Karaburun"
    ],
    "name:tur_x_preferred":[
        "Karaburun"
    ],
    "name:urd_x_preferred":[
        "\u0642\u0631\u06c1 \u0628\u0648\u0631\u0648\u0646"
    ],
    "name:vie_x_preferred":[
        "Karaburun"
    ],
    "name:zho_x_preferred":[
        "\u5361\u62c9\u5e03\u502b"
    ],
    "wof:name":"Karaburun",
    "wof:placetype":"neighbourhood"
},
  "geometry": {"coordinates":[28.68195235116397,41.34168644335029],"type":"Point"}
}