{
  "type": "Feature",
  "properties": {
    "gn:admin1_code":"65",
    "gn:asciiname":"Mickanis",
    "gn:country_code":"TR",
    "gn:dem":2578,
    "gn:feature_class":"P",
    "gn:feature_code":"PPL",
    "gn:name":"Mi\u00e7k\u00e2nis",
    "gn:population":0,
    "gn:timezone":"Europe/Istanbul",
    "iso:country":"TR",
    "wof:name":"Mickanis",
    "wof:placetype":"locality"
},
  "geometry": {"coordinates":[42.78333,38.21667],"type":"Point"}
}