{
  "type": "Feature",
  "properties": {
    "gn:admin1_code":"71",
    "gn:asciiname":"Dagdere",
    "gn:country_code":"TR",
    "gn:dem":1200,
    "gn:feature_class":"P",
    "gn:feature_code":"PPL",
    "gn:name":"Da\u011fdere",
    "gn:population":0,
    "gn:timezone":"Europe/Istanbul",
    "iso:country":"TR",
    "name:und_x_variant":[
        "Da\u011fdere",
        "Da\u011fderek\u00f6y"
    ],
    "wof:name":"Dagdere",
    "wof:placetype":"locality"
},
  "geometry": {"coordinates":[32.48414,38.17468],"type":"Point"}
}