{
  "type": "Feature",
  "properties": {
    "gn:admin1_code":"32",
    "gn:asciiname":"Guneyli",
    "gn:country_code":"TR",
    "gn:dem":1391,
    "gn:feature_class":"P",
    "gn:feature_code":"PPL",
    "gn:name":"G\u00fcneyli",
    "gn:population":0,
    "gn:timezone":"Europe/Istanbul",
    "iso:country":"TR",
    "name:tur_x_preferred":[
        "G\u00fcneyli"
    ],
    "wof:name":"Guneyli",
    "wof:placetype":"locality"
},
  "geometry": {"coordinates":[34.01225,36.78433],"type":"Point"}
}