{
  "type": "Feature",
  "properties": {
    "gn:admin1_code":"81",
    "gn:asciiname":"Celemli",
    "gn:country_code":"TR",
    "gn:dem":160,
    "gn:feature_class":"P",
    "gn:feature_code":"PPL",
    "gn:name":"\u00c7elemli",
    "gn:population":0,
    "gn:timezone":"Europe/Istanbul",
    "iso:country":"TR",
    "name:und_x_variant":[
        "\u00c7elimli",
        "\u00c7elemli"
    ],
    "wof:name":"Celemli",
    "wof:placetype":"locality"
},
  "geometry": {"coordinates":[35.64867,36.84799],"type":"Point"}
}