{
  "type": "Feature",
  "properties": {
    "gn:admin1_code":"73",
    "gn:asciiname":"Yelatan",
    "gn:country_code":"TR",
    "gn:dem":1296,
    "gn:feature_class":"P",
    "gn:feature_code":"PPL",
    "gn:name":"Yelatan",
    "gn:population":0,
    "gn:timezone":"Europe/Istanbul",
    "iso:country":"TR",
    "wof:name":"Yelatan",
    "wof:placetype":"locality"
},
  "geometry": {"coordinates":[35.01395,37.69128],"type":"Point"}
}