{
  "type": "Feature",
  "properties": {
    "gn:admin1_code":"15",
    "gn:asciiname":"Kozluca",
    "gn:country_code":"TR",
    "gn:dem":1097,
    "gn:feature_class":"P",
    "gn:feature_code":"PPL",
    "gn:name":"Kozluca",
    "gn:population":0,
    "gn:timezone":"Europe/Istanbul",
    "iso:country":"TR",
    "wof:name":"Kozluca",
    "wof:placetype":"locality"
},
  "geometry": {"coordinates":[30.13278,37.49278],"type":"Point"}
}