{
  "type": "Feature",
  "properties": {
    "gn:admin1_code":"10",
    "gn:asciiname":"Karabag",
    "gn:country_code":"TR",
    "gn:dem":63,
    "gn:feature_class":"P",
    "gn:feature_code":"PPL",
    "gn:name":"Karaba\u011f",
    "gn:population":0,
    "gn:timezone":"Europe/Istanbul",
    "iso:country":"TR",
    "name:tur_x_preferred":[
        "Karaba\u011f"
    ],
    "wof:name":"Karabag",
    "wof:placetype":"locality"
},
  "geometry": {"coordinates":[26.88333,39.46667],"type":"Point"}
}