{
  "type": "Feature",
  "properties": {
    "gn:admin1_code":"17",
    "gn:asciiname":"Taslitarla",
    "gn:country_code":"TR",
    "gn:dem":146,
    "gn:feature_class":"P",
    "gn:feature_code":"PPL",
    "gn:name":"Ta\u015fl\u0131tarla",
    "gn:population":0,
    "gn:timezone":"Europe/Istanbul",
    "iso:country":"TR",
    "name:tur_x_preferred":[
        "Ta\u015fl\u0131tarla"
    ],
    "wof:name":"Taslitarla",
    "wof:placetype":"locality"
},
  "geometry": {"coordinates":[26.42282,40.05633],"type":"Point"}
}