{
  "type": "Feature",
  "properties": {
    "gn:admin1_code":"25",
    "gn:asciiname":"Dalsogut",
    "gn:country_code":"TR",
    "gn:dem":2093,
    "gn:feature_class":"P",
    "gn:feature_code":"PPL",
    "gn:name":"Dals\u00f6\u011f\u00fct",
    "gn:population":0,
    "gn:timezone":"Europe/Istanbul",
    "iso:country":"TR",
    "name:tur_x_preferred":[
        "Dals\u00f6\u011f\u00fct"
    ],
    "wof:name":"Dalsogut",
    "wof:placetype":"locality"
},
  "geometry": {"coordinates":[41.22247,39.57353],"type":"Point"}
}