{
  "type": "Feature",
  "properties": {
    "gn:admin1_code":"19.0",
    "gn:asciiname":"Kurtler",
    "gn:country_code":"TR",
    "gn:dem":1124,
    "gn:feature_class":"P",
    "gn:feature_code":"PPL",
    "gn:name":"K\u00fcrtler",
    "gn:population":0,
    "gn:timezone":"Europe/Istanbul",
    "iso:country":"TR",
    "name:tur_x_preferred":[
        "K\u00fcrtler"
    ],
    "name:und_x_variant":[
        "Yatukcu"
    ],
    "wof:name":"Kurtler",
    "wof:placetype":"locality"
},
  "geometry": {"coordinates":[34.29225,40.66109],"type":"Point"}
}