{
  "type": "Feature",
  "properties": {
    "gn:admin1_code":"25.0",
    "gn:asciiname":"Agakoy",
    "gn:country_code":"TR",
    "gn:dem":1963,
    "gn:feature_class":"P",
    "gn:feature_code":"PPL",
    "gn:name":"A\u011fak\u00f6y",
    "gn:population":0,
    "gn:timezone":"Europe/Istanbul",
    "iso:country":"TR",
    "name:tur_x_preferred":[
        "A\u011fak\u00f6y"
    ],
    "wof:name":"Agakoy",
    "wof:placetype":"locality"
},
  "geometry": {"coordinates":[41.0114,39.60584],"type":"Point"}
}