{
  "type": "Feature",
  "properties": {
    "gn:admin1_code":"43",
    "gn:asciiname":"Kutluhallar",
    "gn:country_code":"TR",
    "gn:dem":878,
    "gn:feature_class":"P",
    "gn:feature_code":"PPL",
    "gn:name":"Kutluhallar",
    "gn:population":0,
    "gn:timezone":"Europe/Istanbul",
    "iso:country":"TR",
    "name:tur_x_preferred":[
        "Kutluhallar"
    ],
    "wof:name":"Kutluhallar",
    "wof:placetype":"locality"
},
  "geometry": {"coordinates":[29.22031,39.21788],"type":"Point"}
}