{
  "type": "Feature",
  "properties": {
    "gn:admin1_code":"54.0",
    "gn:asciiname":"Yukarihuseyinseyh",
    "gn:country_code":"TR",
    "gn:dem":288,
    "gn:feature_class":"P",
    "gn:feature_code":"PPL",
    "gn:name":"Yukar\u0131h\u00fcseyin\u015feyh",
    "gn:population":0,
    "gn:timezone":"Europe/Istanbul",
    "iso:country":"TR",
    "name:tur_x_preferred":[
        "Yukar\u0131h\u00fcseyin\u015feyh"
    ],
    "wof:name":"Yukarihuseyinseyh",
    "wof:placetype":"locality"
},
  "geometry": {"coordinates":[30.78909,40.81756],"type":"Point"}
}