{
  "type": "Feature",
  "properties": {
    "gn:admin1_code":"45",
    "gn:asciiname":"Isiklar",
    "gn:country_code":"TR",
    "gn:dem":360,
    "gn:feature_class":"P",
    "gn:feature_code":"PPL",
    "gn:name":"I\u015f\u0131klar",
    "gn:population":0,
    "gn:timezone":"Europe/Istanbul",
    "iso:country":"TR",
    "name:tur_x_preferred":[
        "I\u015f\u0131klar"
    ],
    "wof:name":"Isiklar",
    "wof:placetype":"locality"
},
  "geometry": {"coordinates":[27.87729,39.14823],"type":"Point"}
}