{
  "type": "Feature",
  "properties": {
    "gn:admin1_code":"63",
    "gn:asciiname":"Uzunpinar",
    "gn:country_code":"TR",
    "gn:dem":736,
    "gn:feature_class":"P",
    "gn:feature_code":"PPL",
    "gn:name":"Uzunp\u0131nar",
    "gn:population":0,
    "gn:timezone":"Europe/Istanbul",
    "iso:country":"TR",
    "name:und_x_variant":[
        "Uzunp\u0131nar K\u00f6y\u00fc",
        "Uzunp\u0131nar"
    ],
    "wof:name":"Uzunpinar",
    "wof:placetype":"locality"
},
  "geometry": {"coordinates":[39.33079,37.68222],"type":"Point"}
}