{
  "type": "Feature",
  "properties": {
    "gn:admin1_code":"63",
    "gn:asciiname":"Mutluca",
    "gn:country_code":"TR",
    "gn:dem":410,
    "gn:feature_class":"P",
    "gn:feature_code":"PPL",
    "gn:name":"Mutluca",
    "gn:population":0,
    "gn:timezone":"Europe/Istanbul",
    "iso:country":"TR",
    "name:und_x_variant":[
        "Mucipli",
        "Mutluca",
        "Mudzhipli"
    ],
    "wof:name":"Mutluca",
    "wof:placetype":"locality"
},
  "geometry": {"coordinates":[39.05463,37.0666],"type":"Point"}
}