{
  "type": "Feature",
  "properties": {
    "gn:admin1_code":"09",
    "gn:asciiname":"Yukari Gencelidere",
    "gn:country_code":"TR",
    "gn:dem":648,
    "gn:feature_class":"P",
    "gn:feature_code":"PPL",
    "gn:name":"Yukar\u0131 Gencelidere",
    "gn:population":0,
    "gn:timezone":"Europe/Istanbul",
    "iso:country":"TR",
    "name:tur_x_preferred":[
        "Yukar\u0131 Gencelidere"
    ],
    "wof:name":"Yukari Gencelidere",
    "wof:placetype":"locality"
},
  "geometry": {"coordinates":[28.6484,37.98704],"type":"Point"}
}