{
  "type": "Feature",
  "properties": {
    "gn:admin1_code":"69",
    "gn:asciiname":"Asagi Sipanazat",
    "gn:country_code":"TR",
    "gn:dem":1591,
    "gn:feature_class":"P",
    "gn:feature_code":"PPL",
    "gn:name":"A\u015fa\u011f\u0131 Sipanazat",
    "gn:population":0,
    "gn:timezone":"Europe/Istanbul",
    "iso:country":"TR",
    "name:und_x_variant":[
        "Asa\u011f\u0131s\u0131pamazat",
        "S\u0131panazat\u0131s\u00fbfl\u00fb",
        "A\u015fa\u011f\u0131 Sipanazat",
        "Sipanazalt\u0131s\u00fcfla"
    ],
    "wof:name":"Asagi Sipanazat",
    "wof:placetype":"locality"
},
  "geometry": {"coordinates":[39.54738,39.99426],"type":"Point"}
}