{
  "type": "Feature",
  "properties": {
    "gn:admin1_code":"39.0",
    "gn:asciiname":"Karamusul",
    "gn:country_code":"TR",
    "gn:dem":65,
    "gn:feature_class":"P",
    "gn:feature_code":"PPL",
    "gn:name":"Karamusul",
    "gn:population":0,
    "gn:timezone":"Europe/Istanbul",
    "iso:country":"TR",
    "name:tur_x_preferred":[
        "Karamusul"
    ],
    "wof:name":"Karamusul",
    "wof:placetype":"locality"
},
  "geometry": {"coordinates":[27.45116,41.30368],"type":"Point"}
}