{
  "type": "Feature",
  "properties": {
    "gn:admin1_code":"58.0",
    "gn:asciiname":"Gokcekent",
    "gn:country_code":"TR",
    "gn:dem":1357,
    "gn:feature_class":"P",
    "gn:feature_code":"PPLA3",
    "gn:name":"G\u00f6k\u00e7ekent",
    "gn:population":0,
    "gn:timezone":"Europe/Istanbul",
    "iso:country":"TR",
    "name:eng_x_preferred":[
        "G\u00f6k\u00e7ekent"
    ],
    "name:rus_x_preferred":[
        "\u042e\u043a\u0430\u0440\u044b-\u0413\u0435\u0440\u0435\u0434\u0435"
    ],
    "name:und_x_variant":[
        "Yukar\u0131 Gerede",
        "G\u00f6redeibal\u00e2",
        "Yukar\u0131 G\u00f6rede",
        "Naipli",
        "Yukar\u0131 Gerdek"
    ],
    "wof:name":"Gokcekent",
    "wof:placetype":"locality"
},
  "geometry": {"coordinates":[38.11771,40.28644],"type":"Point"}
}