{
  "type": "Feature",
  "properties": {
    "gn:admin1_code":"37.0",
    "gn:asciiname":"Etciler",
    "gn:country_code":"TR",
    "gn:dem":1058,
    "gn:feature_class":"P",
    "gn:feature_code":"PPL",
    "gn:name":"Et\u00e7iler",
    "gn:population":0,
    "gn:timezone":"Europe/Istanbul",
    "iso:country":"TR",
    "wof:name":"Etciler",
    "wof:placetype":"locality"
},
  "geometry": {"coordinates":[33.8137,41.61313],"type":"Point"}
}