{
  "type": "Feature",
  "properties": {
    "gn:admin1_code":"58",
    "gn:asciiname":"Orencik",
    "gn:country_code":"TR",
    "gn:dem":1603,
    "gn:feature_class":"P",
    "gn:feature_code":"PPL",
    "gn:name":"\u00d6rencik",
    "gn:population":0,
    "gn:timezone":"Europe/Istanbul",
    "iso:country":"TR",
    "wof:name":"Orencik",
    "wof:placetype":"locality"
},
  "geometry": {"coordinates":[37.29325,39.31303],"type":"Point"}
}