{
  "type": "Feature",
  "properties": {
    "gn:admin1_code":"25.0",
    "gn:asciiname":"Tasagil",
    "gn:country_code":"TR",
    "gn:dem":2012,
    "gn:feature_class":"P",
    "gn:feature_code":"PPL",
    "gn:name":"Ta\u015fa\u011f\u0131l",
    "gn:population":0,
    "gn:timezone":"Europe/Istanbul",
    "iso:country":"TR",
    "name:tur_x_preferred":[
        "Ta\u015fa\u011f\u0131l"
    ],
    "wof:name":"Tasagil",
    "wof:placetype":"locality"
},
  "geometry": {"coordinates":[41.56736,39.87707],"type":"Point"}
}