{
  "type": "Feature",
  "properties": {
    "gn:admin1_code":"71",
    "gn:asciiname":"Saraykoy",
    "gn:country_code":"TR",
    "gn:dem":896,
    "gn:feature_class":"P",
    "gn:feature_code":"PPL",
    "gn:name":"Sarayk\u00f6y",
    "gn:population":0,
    "gn:timezone":"Europe/Istanbul",
    "iso:country":"TR",
    "name:und_x_variant":[
        "Saray",
        "Sarayk\u00f6y"
    ],
    "wof:name":"Saraykoy",
    "wof:placetype":"locality"
},
  "geometry": {"coordinates":[31.99139000000001,38.89944000000001],"type":"Point"}
}