{
  "type": "Feature",
  "properties": {
    "gn:admin1_code":"44",
    "gn:asciiname":"Isikli",
    "gn:country_code":"TR",
    "gn:dem":1400,
    "gn:feature_class":"P",
    "gn:feature_code":"PPL",
    "gn:name":"I\u015f\u0131kl\u0131",
    "gn:population":0,
    "gn:timezone":"Europe/Istanbul",
    "iso:country":"TR",
    "name:und_x_variant":[
        "Budalau\u015fa\u011f\u0131",
        "I\u015f\u0131kl\u0131"
    ],
    "wof:name":"Isikli",
    "wof:placetype":"locality"
},
  "geometry": {"coordinates":[38.07524,38.21152],"type":"Point"}
}