{
  "type": "Feature",
  "properties": {
    "gn:admin1_code":"76.0",
    "gn:asciiname":"Merdisi",
    "gn:country_code":"TR",
    "gn:dem":549,
    "gn:feature_class":"P",
    "gn:feature_code":"PPL",
    "gn:name":"Merdisi",
    "gn:population":0,
    "gn:timezone":"Europe/Istanbul",
    "iso:country":"TR",
    "wof:name":"Merdisi",
    "wof:placetype":"locality"
},
  "geometry": {"coordinates":[41.20556,37.72944],"type":"Point"}
}