{
  "type": "Feature",
  "properties": {
    "gn:admin1_code":"93",
    "gn:asciiname":"Domuzdere",
    "gn:country_code":"TR",
    "gn:dem":469,
    "gn:feature_class":"P",
    "gn:feature_code":"PPL",
    "gn:name":"Domuzdere",
    "gn:population":0,
    "gn:timezone":"Europe/Istanbul",
    "iso:country":"TR",
    "wof:name":"Domuzdere",
    "wof:placetype":"locality"
},
  "geometry": {"coordinates":[30.93066,40.74906],"type":"Point"}
}