{
  "type": "Feature",
  "properties": {
    "gn:admin1_code":"09",
    "gn:asciiname":"Asagi Dam",
    "gn:country_code":"TR",
    "gn:dem":772,
    "gn:feature_class":"P",
    "gn:feature_code":"PPL",
    "gn:name":"A\u015fa\u011f\u0131 Dam",
    "gn:population":0,
    "gn:timezone":"Europe/Istanbul",
    "iso:country":"TR",
    "name:tur_x_preferred":[
        "A\u015fa\u011f\u0131 Dam"
    ],
    "wof:name":"Asagi Dam",
    "wof:placetype":"locality"
},
  "geometry": {"coordinates":[28.61936,37.59275],"type":"Point"}
}