{
  "type": "Feature",
  "properties": {
    "gn:admin1_code":"54",
    "gn:asciiname":"Yukari Carigikuru",
    "gn:country_code":"TR",
    "gn:dem":78,
    "gn:feature_class":"P",
    "gn:feature_code":"PPL",
    "gn:name":"Yukar\u0131 \u00c7ar\u0131\u011f\u0131kuru",
    "gn:population":0,
    "gn:timezone":"Europe/Istanbul",
    "iso:country":"TR",
    "name:tur_x_preferred":[
        "Yukar\u0131 \u00c7ar\u0131\u011f\u0131kuru"
    ],
    "wof:name":"Yukari Carigikuru",
    "wof:placetype":"locality"
},
  "geometry": {"coordinates":[30.7401,40.70655],"type":"Point"}
}