{
  "type": "Feature",
  "properties": {
    "gn:admin1_code":"37.0",
    "gn:asciiname":"Karahacilar",
    "gn:country_code":"TR",
    "gn:dem":1371,
    "gn:feature_class":"P",
    "gn:feature_code":"PPL",
    "gn:name":"Karahac\u0131lar",
    "gn:population":0,
    "gn:timezone":"Europe/Istanbul",
    "iso:country":"TR",
    "wof:name":"Karahacilar",
    "wof:placetype":"locality"
},
  "geometry": {"coordinates":[33.83333,41.18333],"type":"Point"}
}