{
  "type": "Feature",
  "properties": {
    "gn:admin1_code":"65.0",
    "gn:asciiname":"Ucogul",
    "gn:country_code":"TR",
    "gn:dem":1724,
    "gn:feature_class":"P",
    "gn:feature_code":"PPL",
    "gn:name":"U\u00e7o\u011ful",
    "gn:population":0,
    "gn:timezone":"Europe/Istanbul",
    "iso:country":"TR",
    "name:tur_x_preferred":[
        "U\u00e7o\u011ful"
    ],
    "wof:name":"Ucogul",
    "wof:placetype":"locality"
},
  "geometry": {"coordinates":[43.27441,39.03216],"type":"Point"}
}