{
  "type": "Feature",
  "properties": {
    "gn:admin1_code":"81",
    "gn:asciiname":"Kayadibi",
    "gn:country_code":"TR",
    "gn:dem":1198,
    "gn:feature_class":"P",
    "gn:feature_code":"PPL",
    "gn:name":"Kayadibi",
    "gn:population":0,
    "gn:timezone":"Europe/Istanbul",
    "iso:country":"TR",
    "name:und_x_variant":[
        "Sar\u0131z",
        "Kayadibi"
    ],
    "wof:name":"Kayadibi",
    "wof:placetype":"locality"
},
  "geometry": {"coordinates":[35.77735,37.7757],"type":"Point"}
}