{
  "type": "Feature",
  "properties": {
    "gn:admin1_code":"52.0",
    "gn:asciiname":"Salihi",
    "gn:country_code":"TR",
    "gn:dem":299,
    "gn:feature_class":"P",
    "gn:feature_code":"PPL",
    "gn:name":"Salihi",
    "gn:population":0,
    "gn:timezone":"Europe/Istanbul",
    "iso:country":"TR",
    "name:und_x_variant":[
        "G\u00fcnali"
    ],
    "wof:name":"Salihi",
    "wof:placetype":"locality"
},
  "geometry": {"coordinates":[37.39776,40.94843],"type":"Point"}
}