{
  "type": "Feature",
  "properties": {
    "gn:admin1_code":"63.0",
    "gn:asciiname":"Kirmitli",
    "gn:country_code":"TR",
    "gn:dem":580,
    "gn:feature_class":"P",
    "gn:feature_code":"PPL",
    "gn:name":"K\u0131rm\u0131tl\u0131",
    "gn:population":0,
    "gn:timezone":"Europe/Istanbul",
    "iso:country":"TR",
    "name:tur_x_preferred":[
        "K\u0131rm\u0131tl\u0131"
    ],
    "wof:name":"Kirmitli",
    "wof:placetype":"locality"
},
  "geometry": {"coordinates":[38.37642,37.09622],"type":"Point"}
}