{
  "type": "Feature",
  "properties": {
    "gn:admin1_code":"48",
    "gn:asciiname":"Ikizkoy",
    "gn:country_code":"TR",
    "gn:dem":204,
    "gn:feature_class":"P",
    "gn:feature_code":"PPL",
    "gn:name":"\u0130kizk\u00f6y",
    "gn:population":0,
    "gn:timezone":"Europe/Istanbul",
    "iso:country":"TR",
    "name:tur_x_preferred":[
        "\u0130kizk\u00f6y"
    ],
    "wof:name":"Ikizkoy",
    "wof:placetype":"locality"
},
  "geometry": {"coordinates":[27.85886,37.17477],"type":"Point"}
}