{
  "type": "Feature",
  "properties": {
    "gn:admin1_code":"57.0",
    "gn:asciiname":"Abdaloglu",
    "gn:country_code":"TR",
    "gn:dem":192,
    "gn:feature_class":"P",
    "gn:feature_code":"PPL",
    "gn:name":"Abdalo\u011flu",
    "gn:population":0,
    "gn:timezone":"Europe/Istanbul",
    "iso:country":"TR",
    "wof:name":"Abdaloglu",
    "wof:placetype":"locality"
},
  "geometry": {"coordinates":[35.17157,41.79874],"type":"Point"}
}