{
  "type": "Feature",
  "properties": {
    "gn:admin1_code":"74",
    "gn:asciiname":"Kanimiri",
    "gn:cc2":"TR",
    "gn:country_code":"TR",
    "gn:dem":488,
    "gn:feature_class":"P",
    "gn:feature_code":"PPL",
    "gn:name":"K\u00e2nimiri",
    "gn:population":0,
    "gn:timezone":"Europe/Istanbul",
    "iso:country":"TR",
    "name:und_x_variant":[
        "Kyanimiry",
        "K\u00e2nimiri"
    ],
    "wof:name":"Kanimiri",
    "wof:placetype":"locality"
},
  "geometry": {"coordinates":[41.79861,37.77111],"type":"Point"}
}