{
  "type": "Feature",
  "properties": {
    "gn:admin1_code":"23",
    "gn:asciiname":"Yedigoze",
    "gn:country_code":"TR",
    "gn:dem":956,
    "gn:feature_class":"P",
    "gn:feature_code":"PPL",
    "gn:name":"Yedig\u00f6ze",
    "gn:population":0,
    "gn:timezone":"Europe/Istanbul",
    "iso:country":"TR",
    "name:tur_x_preferred":[
        "Yedig\u00f6ze"
    ],
    "wof:name":"Yedigoze",
    "wof:placetype":"locality"
},
  "geometry": {"coordinates":[39.26903,38.53025],"type":"Point"}
}