{
  "type": "Feature",
  "properties": {
    "gn:admin1_code":"58",
    "gn:asciiname":"Karayer",
    "gn:country_code":"TR",
    "gn:dem":1279,
    "gn:feature_class":"P",
    "gn:feature_code":"PPL",
    "gn:name":"Karayer",
    "gn:population":0,
    "gn:timezone":"Europe/Istanbul",
    "iso:country":"TR",
    "wof:name":"Karayer",
    "wof:placetype":"locality"
},
  "geometry": {"coordinates":[37.33966,38.71821],"type":"Point"}
}