{
  "type": "Feature",
  "properties": {
    "gn:admin1_code":"19.0",
    "gn:asciiname":"Yesilcat",
    "gn:country_code":"TR",
    "gn:dem":978,
    "gn:feature_class":"P",
    "gn:feature_code":"PPL",
    "gn:name":"Ye\u015fil\u00e7at",
    "gn:population":0,
    "gn:timezone":"Europe/Istanbul",
    "iso:country":"TR",
    "name:tur_x_preferred":[
        "Ye\u015fil\u00e7at"
    ],
    "wof:name":"Yesilcat",
    "wof:placetype":"locality"
},
  "geometry": {"coordinates":[34.12748,40.70617],"type":"Point"}
}