{
  "type": "Feature",
  "properties": {
    "gn:admin1_code":"85.0",
    "gn:asciiname":"Ormeci",
    "gn:country_code":"TR",
    "gn:dem":130,
    "gn:feature_class":"P",
    "gn:feature_code":"PPL",
    "gn:name":"\u00d6rmeci",
    "gn:population":0,
    "gn:timezone":"Europe/Istanbul",
    "iso:country":"TR",
    "name:und_x_variant":[
        "\u00d6rmecik\u00f6y\u00fc",
        "\u00d6rmeci"
    ],
    "wof:name":"Ormeci",
    "wof:placetype":"locality"
},
  "geometry": {"coordinates":[32.05937,41.319],"type":"Point"}
}