{
  "type": "Feature",
  "properties": {
    "gn:admin1_code":"80.0",
    "gn:asciiname":"Harapalisah",
    "gn:country_code":"TR",
    "gn:dem":715,
    "gn:feature_class":"P",
    "gn:feature_code":"PPL",
    "gn:name":"Harapalisah",
    "gn:population":0,
    "gn:timezone":"Europe/Istanbul",
    "iso:country":"TR",
    "name:tur_x_preferred":[
        "Harapalisah"
    ],
    "wof:name":"Harapalisah",
    "wof:placetype":"locality"
},
  "geometry": {"coordinates":[42.26135,37.37996],"type":"Point"}
}