{
  "type": "Feature",
  "properties": {
    "gn:admin1_code":"93",
    "gn:asciiname":"Gaziler",
    "gn:country_code":"TR",
    "gn:dem":510,
    "gn:feature_class":"P",
    "gn:feature_code":"PPL",
    "gn:name":"Gaziler",
    "gn:population":0,
    "gn:timezone":"Europe/Istanbul",
    "iso:country":"TR",
    "wof:name":"Gaziler",
    "wof:placetype":"locality"
},
  "geometry": {"coordinates":[31.55514,40.97718],"type":"Point"}
}