{
  "type": "Feature",
  "properties": {
    "gn:admin1_code":"19.0",
    "gn:asciiname":"Buyukhirka",
    "gn:country_code":"TR",
    "gn:dem":1193,
    "gn:feature_class":"P",
    "gn:feature_code":"PPL",
    "gn:name":"B\u00fcy\u00fckh\u0131rka",
    "gn:population":0,
    "gn:timezone":"Europe/Istanbul",
    "iso:country":"TR",
    "wof:name":"Buyukhirka",
    "wof:placetype":"locality"
},
  "geometry": {"coordinates":[34.7596,40.05528],"type":"Point"}
}