{
  "type": "Feature",
  "properties": {
    "gn:admin1_code":"71",
    "gn:asciiname":"Erler",
    "gn:country_code":"TR",
    "gn:dem":1003,
    "gn:feature_class":"P",
    "gn:feature_code":"PPL",
    "gn:name":"Erler",
    "gn:population":0,
    "gn:timezone":"Europe/Istanbul",
    "iso:country":"TR",
    "name:tur_x_preferred":[
        "Er\u00f6ld\u00fcren"
    ],
    "wof:name":"Erler",
    "wof:placetype":"locality"
},
  "geometry": {"coordinates":[32.66409,37.79865],"type":"Point"}
}