{
  "type": "Feature",
  "properties": {
    "gn:admin1_code":"74",
    "gn:asciiname":"Daracik",
    "gn:country_code":"TR",
    "gn:dem":792,
    "gn:feature_class":"P",
    "gn:feature_code":"PPL",
    "gn:name":"Darac\u0131k",
    "gn:population":0,
    "gn:timezone":"Europe/Istanbul",
    "iso:country":"TR",
    "name:und_x_variant":[
        "Entk\u00f6y",
        "Darac\u0131k",
        "Ent"
    ],
    "wof:name":"Daracik",
    "wof:placetype":"locality"
},
  "geometry": {"coordinates":[42.31294000000001,38.02687],"type":"Point"}
}