{
  "type": "Feature",
  "properties": {
    "gn:admin1_code":"13",
    "gn:asciiname":"Soguksu",
    "gn:country_code":"TR",
    "gn:dem":1396,
    "gn:feature_class":"P",
    "gn:feature_code":"PPL",
    "gn:name":"So\u011fuksu",
    "gn:population":0,
    "gn:timezone":"Europe/Istanbul",
    "iso:country":"TR",
    "name:tur_x_preferred":[
        "So\u011fuksu"
    ],
    "name:tur_x_variant":[
        "Horoz"
    ],
    "name:und_x_variant":[
        "Horozdere",
        "Horuz"
    ],
    "wof:name":"Soguksu",
    "wof:placetype":"locality"
},
  "geometry": {"coordinates":[42.55191,38.11308],"type":"Point"}
}