{
  "type": "Feature",
  "properties": {
    "gn:admin1_code":"66",
    "gn:asciiname":"Bacili",
    "gn:country_code":"TR",
    "gn:dem":1135,
    "gn:feature_class":"P",
    "gn:feature_code":"PPL",
    "gn:name":"Bac\u0131l\u0131",
    "gn:population":0,
    "gn:timezone":"Europe/Istanbul",
    "iso:country":"TR",
    "name:tur_x_preferred":[
        "Bac\u0131l\u0131"
    ],
    "wof:name":"Bacili",
    "wof:placetype":"locality"
},
  "geometry": {"coordinates":[34.5534,39.89585],"type":"Point"}
}