{
  "type": "Feature",
  "properties": {
    "gn:admin1_code":"46",
    "gn:asciiname":"Yeniyapan",
    "gn:country_code":"TR",
    "gn:dem":1607,
    "gn:feature_class":"P",
    "gn:feature_code":"PPL",
    "gn:name":"Yeniyapan",
    "gn:population":0,
    "gn:timezone":"Europe/Istanbul",
    "iso:country":"TR",
    "wof:name":"Yeniyapan",
    "wof:placetype":"locality"
},
  "geometry": {"coordinates":[36.62897,38.14375],"type":"Point"}
}