{
  "type": "Feature",
  "properties": {
    "gn:admin1_code":"62",
    "gn:asciiname":"Kushane",
    "gn:country_code":"TR",
    "gn:dem":1631,
    "gn:feature_class":"P",
    "gn:feature_code":"PPL",
    "gn:name":"Ku\u015fhane",
    "gn:population":0,
    "gn:timezone":"Europe/Istanbul",
    "iso:country":"TR",
    "name:tur_x_preferred":[
        "Ku\u015fhane"
    ],
    "wof:name":"Kushane",
    "wof:placetype":"locality"
},
  "geometry": {"coordinates":[39.71053,39.02566],"type":"Point"}
}