{
  "type": "Feature",
  "properties": {
    "gn:admin1_code":"52.0",
    "gn:asciiname":"Dongelduzu",
    "gn:country_code":"TR",
    "gn:dem":406,
    "gn:feature_class":"P",
    "gn:feature_code":"PPL",
    "gn:name":"D\u00f6ngeld\u00fcz\u00fc",
    "gn:population":0,
    "gn:timezone":"Europe/Istanbul",
    "iso:country":"TR",
    "name:und_x_variant":[
        "T\u00f6ngeld\u00fcz\u00fc",
        "Tengelikd\u00fcz\u00fc",
        "D\u00f6ngeld\u00fcz\u00fc"
    ],
    "wof:name":"Dongelduzu",
    "wof:placetype":"locality"
},
  "geometry": {"coordinates":[37.74061,41.0905],"type":"Point"}
}