{
  "type": "Feature",
  "properties": {
    "gn:admin1_code":"21.0",
    "gn:asciiname":"Hola",
    "gn:cc2":"TR",
    "gn:country_code":"TR",
    "gn:dem":719,
    "gn:feature_class":"P",
    "gn:feature_code":"PPL",
    "gn:name":"Hola",
    "gn:population":0,
    "gn:timezone":"Europe/Istanbul",
    "iso:country":"TR",
    "name:ceb_x_preferred":[
        "Hola"
    ],
    "name:est_x_preferred":[
        "Hola"
    ],
    "name:fra_x_preferred":[
        "Hola"
    ],
    "name:ita_x_preferred":[
        "Hola"
    ],
    "name:lit_x_preferred":[
        "Hola"
    ],
    "name:nld_x_preferred":[
        "Hola"
    ],
    "name:pol_x_preferred":[
        "Hola"
    ],
    "name:spa_x_preferred":[
        "Hola"
    ],
    "name:swe_x_preferred":[
        "Hola"
    ],
    "name:tur_x_preferred":[
        "Hola"
    ],
    "name:ukr_x_preferred":[
        "\u0413\u043e\u043b\u044f"
    ],
    "name:und_x_variant":[
        "Khola",
        "\u00c7ay\u0131rl\u0131"
    ],
    "wof:name":"Hola",
    "wof:placetype":"locality"
},
  "geometry": {"coordinates":[40.88222,37.66861],"type":"Point"}
}