{
  "type": "Feature",
  "properties": {
    "gn:admin1_code":"68.0",
    "gn:asciiname":"Ahmetadil",
    "gn:country_code":"TR",
    "gn:dem":1271,
    "gn:feature_class":"P",
    "gn:feature_code":"PPL",
    "gn:name":"Ahmetadil",
    "gn:population":0,
    "gn:timezone":"Europe/Istanbul",
    "iso:country":"TR",
    "name:und_x_variant":[
        "Ahmedadil",
        "Ahmetadil"
    ],
    "wof:name":"Ahmetadil",
    "wof:placetype":"locality"
},
  "geometry": {"coordinates":[33.23634000000001,40.10684000000001],"type":"Point"}
}