{
  "type": "Feature",
  "properties": {
    "gn:admin1_code":"24",
    "gn:asciiname":"Cibolar",
    "gn:cc2":"TR",
    "gn:country_code":"TR",
    "gn:dem":2298,
    "gn:feature_class":"P",
    "gn:feature_code":"PPL",
    "gn:name":"Cibolar",
    "gn:population":0,
    "gn:timezone":"Europe/Istanbul",
    "iso:country":"TR",
    "name:und_x_variant":[
        "Cibalar",
        "Cibolar"
    ],
    "wof:name":"Cibolar",
    "wof:placetype":"locality"
},
  "geometry": {"coordinates":[38.86667,39.86667],"type":"Point"}
}