{
  "type": "Feature",
  "properties": {
    "gn:admin1_code":"55.0",
    "gn:asciiname":"Deyincek",
    "gn:country_code":"TR",
    "gn:dem":236,
    "gn:feature_class":"P",
    "gn:feature_code":"PPL",
    "gn:name":"Deyincek",
    "gn:population":0,
    "gn:timezone":"Europe/Istanbul",
    "iso:country":"TR",
    "name:und_x_variant":[
        "Selvio\u011flu"
    ],
    "wof:name":"Deyincek",
    "wof:placetype":"locality"
},
  "geometry": {"coordinates":[36.62275,41.08173],"type":"Point"}
}