{
  "type": "Feature",
  "properties": {
    "gn:admin1_code":"46",
    "gn:asciiname":"Haydarli",
    "gn:country_code":"TR",
    "gn:dem":892,
    "gn:feature_class":"P",
    "gn:feature_code":"PPL",
    "gn:name":"Haydarl\u0131",
    "gn:population":0,
    "gn:timezone":"Europe/Istanbul",
    "iso:country":"TR",
    "name:tur_x_preferred":[
        "Haydarl\u0131"
    ],
    "wof:name":"Haydarli",
    "wof:placetype":"locality"
},
  "geometry": {"coordinates":[37.47436,37.57729000000001],"type":"Point"}
}