{
  "type": "Feature",
  "properties": {
    "gn:admin1_code":"71.0",
    "gn:asciiname":"Akorenkisla",
    "gn:country_code":"TR",
    "gn:dem":971,
    "gn:feature_class":"P",
    "gn:feature_code":"PPL",
    "gn:name":"Ak\u00f6renk\u0131\u015fla",
    "gn:population":0,
    "gn:timezone":"Europe/Istanbul",
    "iso:country":"TR",
    "name:und_x_variant":[
        "Akvirank\u0131slak\u00f6y",
        "Ak\u00f6renk\u0131\u015fla"
    ],
    "wof:name":"Akorenkisla",
    "wof:placetype":"locality"
},
  "geometry": {"coordinates":[33.10944,38.34039],"type":"Point"}
}