{
  "type": "Feature",
  "properties": {
    "gn:admin1_code":"26",
    "gn:asciiname":"Yagri Yaylasi",
    "gn:country_code":"TR",
    "gn:dem":758,
    "gn:feature_class":"P",
    "gn:feature_code":"PPL",
    "gn:name":"Ya\u011fr\u0131 Yaylas\u0131",
    "gn:population":0,
    "gn:timezone":"Europe/Istanbul",
    "iso:country":"TR",
    "wof:name":"Yagri Yaylasi",
    "wof:placetype":"locality"
},
  "geometry": {"coordinates":[31.89197,39.383],"type":"Point"}
}