{
  "type": "Feature",
  "properties": {
    "gn:admin1_code":"8.0",
    "gn:asciiname":"Tutunlu",
    "gn:country_code":"TR",
    "gn:dem":1017,
    "gn:feature_class":"P",
    "gn:feature_code":"PPL",
    "gn:name":"T\u00fct\u00fcnl\u00fc",
    "gn:population":0,
    "gn:timezone":"Europe/Istanbul",
    "iso:country":"TR",
    "name:eng_x_preferred":[
        "\u00c7avdargil"
    ],
    "name:rus_x_preferred":[
        "\u0427\u0430\u0432\u0434\u0430\u0440\u0433\u0438\u043b\u044c"
    ],
    "name:und_x_variant":[
        "\u00c7avdargil",
        "T\u00fct\u00fcnl\u00fc"
    ],
    "wof:name":"Tutunlu",
    "wof:placetype":"locality"
},
  "geometry": {"coordinates":[42.09916,41.15367],"type":"Point"}
}