{
  "type": "Feature",
  "properties": {
    "gn:admin1_code":"04",
    "gn:asciiname":"Ormeli",
    "gn:country_code":"TR",
    "gn:dem":2164,
    "gn:feature_class":"P",
    "gn:feature_code":"PPL",
    "gn:name":"\u00d6rmeli",
    "gn:population":0,
    "gn:timezone":"Europe/Istanbul",
    "iso:country":"TR",
    "name:tur_x_preferred":[
        "\u00d6rmeli"
    ],
    "wof:name":"Ormeli",
    "wof:placetype":"locality"
},
  "geometry": {"coordinates":[43.64308,39.72109],"type":"Point"}
}