{
  "type": "Feature",
  "properties": {
    "gn:admin1_code":"16.0",
    "gn:asciiname":"Soldere",
    "gn:country_code":"TR",
    "gn:dem":254,
    "gn:feature_class":"P",
    "gn:feature_code":"PPLA3",
    "gn:name":"Soldere",
    "gn:population":0,
    "gn:timezone":"Europe/Istanbul",
    "iso:country":"TR",
    "name:und_x_variant":[
        "S\u00f6\u011f\u00fctalan"
    ],
    "wof:name":"Soldere",
    "wof:placetype":"locality"
},
  "geometry": {"coordinates":[28.57231,40.06089],"type":"Point"}
}