{
  "type": "Feature",
  "properties": {
    "gn:admin1_code":"7.0",
    "gn:asciiname":"Abdurrahmanlar",
    "gn:country_code":"TR",
    "gn:dem":18,
    "gn:feature_class":"P",
    "gn:feature_code":"PPL",
    "gn:name":"Abdurrahmanlar",
    "gn:population":0,
    "gn:timezone":"Europe/Istanbul",
    "iso:country":"TR",
    "wof:name":"Abdurrahmanlar",
    "wof:placetype":"locality"
},
  "geometry": {"coordinates":[30.93861,36.99],"type":"Point"}
}