{
  "type": "Feature",
  "properties": {
    "gn:admin1_code":"25.0",
    "gn:asciiname":"Sorkunlu",
    "gn:country_code":"TR",
    "gn:dem":1929,
    "gn:feature_class":"P",
    "gn:feature_code":"PPL",
    "gn:name":"Sorkunlu",
    "gn:population":0,
    "gn:timezone":"Europe/Istanbul",
    "iso:country":"TR",
    "name:und_x_variant":[
        "Ziravank",
        "Zirevank",
        "Sorkunlu"
    ],
    "wof:name":"Sorkunlu",
    "wof:placetype":"locality"
},
  "geometry": {"coordinates":[40.95967,40.07755],"type":"Point"}
}