{
  "type": "Feature",
  "properties": {
    "gn:admin1_code":"23",
    "gn:asciiname":"Muratcik",
    "gn:country_code":"TR",
    "gn:dem":855,
    "gn:feature_class":"P",
    "gn:feature_code":"PPL",
    "gn:name":"Murat\u00e7\u0131k",
    "gn:population":0,
    "gn:timezone":"Europe/Istanbul",
    "iso:country":"TR",
    "name:tur_x_preferred":[
        "Murat\u00e7\u0131k"
    ],
    "name:und_x_variant":[
        "Eng\u00fczek",
        "\u00dcng\u00fcrek",
        "Muratc\u0131k",
        "\u00dcng\u00fczek"
    ],
    "wof:name":"Muratcik",
    "wof:placetype":"locality"
},
  "geometry": {"coordinates":[38.96074,38.84644],"type":"Point"}
}