{
  "type": "Feature",
  "properties": {
    "gn:admin1_code":"20",
    "gn:asciiname":"Yesildere",
    "gn:country_code":"TR",
    "gn:dem":903,
    "gn:feature_class":"P",
    "gn:feature_code":"PPL",
    "gn:name":"Ye\u015fildere",
    "gn:population":0,
    "gn:timezone":"Europe/Istanbul",
    "iso:country":"TR",
    "name:tur_x_preferred":[
        "Ye\u015fildere"
    ],
    "name:tur_x_variant":[
        "Derek\u00f6y"
    ],
    "wof:name":"Yesildere",
    "wof:placetype":"locality"
},
  "geometry": {"coordinates":[29.48573,37.40994],"type":"Point"}
}