{
  "type": "Feature",
  "properties": {
    "gn:admin1_code":"14",
    "gn:asciiname":"Alibeyler",
    "gn:country_code":"TR",
    "gn:dem":815,
    "gn:feature_class":"P",
    "gn:feature_code":"PPL",
    "gn:name":"Alibeyler",
    "gn:population":0,
    "gn:timezone":"Europe/Istanbul",
    "iso:country":"TR",
    "wof:name":"Alibeyler",
    "wof:placetype":"locality"
},
  "geometry": {"coordinates":[32.22422,40.93523],"type":"Point"}
}