{
  "type": "Feature",
  "properties": {
    "gn:admin1_code":"61",
    "gn:asciiname":"Yesilyurt",
    "gn:country_code":"TR",
    "gn:dem":918,
    "gn:feature_class":"P",
    "gn:feature_code":"PPL",
    "gn:name":"Ye\u015filyurt",
    "gn:population":0,
    "gn:timezone":"Europe/Istanbul",
    "iso:country":"TR",
    "name:tur_x_preferred":[
        "Ye\u015filyurt"
    ],
    "wof:name":"Yesilyurt",
    "wof:placetype":"locality"
},
  "geometry": {"coordinates":[40.02325,40.75258],"type":"Point"}
}