{
  "type": "Feature",
  "properties": {
    "gn:admin1_code":"8.0",
    "gn:asciiname":"Olgunlar",
    "gn:country_code":"TR",
    "gn:dem":2113,
    "gn:feature_class":"P",
    "gn:feature_code":"PPL",
    "gn:name":"Olgunlar",
    "gn:population":0,
    "gn:timezone":"Europe/Istanbul",
    "iso:country":"TR",
    "wof:name":"Olgunlar",
    "wof:placetype":"locality"
},
  "geometry": {"coordinates":[41.24198,40.85913],"type":"Point"}
}