{
  "type": "Feature",
  "properties": {
    "gn:admin1_code":"12",
    "gn:asciiname":"Ibrahiman",
    "gn:country_code":"TR",
    "gn:dem":1195,
    "gn:feature_class":"P",
    "gn:feature_code":"PPL",
    "gn:name":"\u0130brahiman",
    "gn:population":0,
    "gn:timezone":"Europe/Istanbul",
    "iso:country":"TR",
    "wof:name":"Ibrahiman",
    "wof:placetype":"locality"
},
  "geometry": {"coordinates":[40.66667,38.86667],"type":"Point"}
}