{
  "type": "Feature",
  "properties": {
    "gn:country":"TR",
    "gn:fcode":"PPLA2",
    "gn:pop":2471,
    "iso:country":"TR",
    "name:deu_x_preferred":[
        "La\u00e7in"
    ],
    "name:eng_x_preferred":[
        "La\u00e7in"
    ],
    "name:fra_x_preferred":[
        "La\u00e7in"
    ],
    "name:ita_x_preferred":[
        "Distretto di La\u00e7in"
    ],
    "name:mrj_x_preferred":[
        "\u041b\u0430\u0447\u0438\u043d"
    ],
    "name:msa_x_preferred":[
        "La\u00e7in"
    ],
    "name:nan_x_preferred":[
        "La\u00e7in"
    ],
    "name:nld_x_preferred":[
        "La\u00e7in"
    ],
    "name:swa_x_preferred":[
        "La\u00e7in"
    ],
    "name:tur_x_preferred":[
        "La\u00e7in"
    ],
    "name:urd_x_preferred":[
        "\u0644\u0627\u0686\u06cc\u0646\u060c \u0686\u0648\u0631\u0648\u0645"
    ],
    "name:vie_x_preferred":[
        "La\u00e7in"
    ],
    "qs:name":"B\u00fcy\u00fck L\u00e2\u00e7in",
    "qs:name_adm0":"Turkey",
    "qs:name_adm1":"\u00c7orum",
    "qs:photos_9r":0,
    "qs:photos_sr":0,
    "qs:placetype":"Town",
    "qs:pop_sr":"4",
    "wof:name":"B\u00fcy\u00fck L\u00e2\u00e7in",
    "wof:placetype":"locality",
    "wof:population":2471
},
  "geometry": {"coordinates":[34.89838,40.77018],"type":"Point"}
}