{
  "type": "Feature",
  "properties": {
    "gn:admin1_code":"21",
    "gn:asciiname":"Mehmetsirvan",
    "gn:cc2":"TR",
    "gn:country_code":"TR",
    "gn:dem":669,
    "gn:feature_class":"P",
    "gn:feature_code":"PPL",
    "gn:name":"Mehmet\u015firvan",
    "gn:population":0,
    "gn:timezone":"Europe/Istanbul",
    "iso:country":"TR",
    "name:tur_x_preferred":[
        "Mehmet\u015firvan"
    ],
    "name:und_x_variant":[
        "Mekhmedshirvan",
        "Mehmed\u015firvan"
    ],
    "wof:name":"Mehmetsirvan",
    "wof:placetype":"locality"
},
  "geometry": {"coordinates":[40.63861,37.98667],"type":"Point"}
}