{
  "type": "Feature",
  "properties": {
    "gn:admin1_code":"76",
    "gn:asciiname":"Kislak",
    "gn:country_code":"TR",
    "gn:dem":958,
    "gn:feature_class":"P",
    "gn:feature_code":"PPL",
    "gn:name":"K\u0131\u015flak",
    "gn:population":0,
    "gn:timezone":"Europe/Istanbul",
    "iso:country":"TR",
    "name:tur_x_preferred":[
        "K\u0131\u015flak"
    ],
    "name:und_x_variant":[
        "Zifink",
        "Zivink"
    ],
    "wof:name":"Kislak",
    "wof:placetype":"locality"
},
  "geometry": {"coordinates":[41.12815,37.65165],"type":"Point"}
}