{
  "type": "Feature",
  "properties": {
    "gn:admin1_code":"83",
    "gn:asciiname":"Kuscumustafa",
    "gn:country_code":"TR",
    "gn:dem":822,
    "gn:feature_class":"P",
    "gn:feature_code":"PPL",
    "gn:name":"Ku\u015f\u00e7umustafa",
    "gn:population":0,
    "gn:timezone":"Europe/Istanbul",
    "iso:country":"TR",
    "name:tur_x_preferred":[
        "Ku\u015f\u00e7umustafa"
    ],
    "wof:name":"Kuscumustafa",
    "wof:placetype":"locality"
},
  "geometry": {"coordinates":[36.61782,37.10184],"type":"Point"}
}