{
  "type": "Feature",
  "properties": {
    "gn:country":"TR",
    "gn:fcode":"PPL",
    "gn:pop":1028,
    "iso:country":"TR",
    "name:tur_x_preferred":[
        "Koyunluca"
    ],
    "qs:name":"Koyunluca",
    "qs:photos_9r":0,
    "qs:photos_sr":0,
    "qs:pop_sr":"3",
    "wof:name":"Koyunluca",
    "wof:placetype":"locality",
    "wof:population":1028
},
  "geometry": {"coordinates":[39.34333,36.82278],"type":"Point"}
}