{
  "type": "Feature",
  "properties": {
    "gn:admin1_code":"71",
    "gn:asciiname":"Oguzeli",
    "gn:country_code":"TR",
    "gn:dem":972,
    "gn:feature_class":"P",
    "gn:feature_code":"PPL",
    "gn:name":"O\u011fuzeli",
    "gn:population":0,
    "gn:timezone":"Europe/Istanbul",
    "iso:country":"TR",
    "wof:name":"Oguzeli",
    "wof:placetype":"locality"
},
  "geometry": {"coordinates":[33.10812,38.34636],"type":"Point"}
}