{
  "type": "Feature",
  "properties": {
    "gn:admin1_code":"55.0",
    "gn:asciiname":"Dagdirali",
    "gn:country_code":"TR",
    "gn:dem":17,
    "gn:feature_class":"P",
    "gn:feature_code":"PPL",
    "gn:name":"Da\u011fd\u0131ral\u0131",
    "gn:population":0,
    "gn:timezone":"Europe/Istanbul",
    "iso:country":"TR",
    "wof:name":"Dagdirali",
    "wof:placetype":"locality"
},
  "geometry": {"coordinates":[36.80521,41.23204000000001],"type":"Point"}
}