{
  "type": "Feature",
  "properties": {
    "gn:admin1_code":"90.0",
    "gn:asciiname":"Bektasoglu",
    "gn:country_code":"TR",
    "gn:dem":683,
    "gn:feature_class":"P",
    "gn:feature_code":"PPL",
    "gn:name":"Bekta\u015fo\u011flu",
    "gn:population":0,
    "gn:timezone":"Europe/Istanbul",
    "iso:country":"TR",
    "name:und_x_variant":[
        "Bektashly",
        "Bekta\u015fo\u011flu",
        "Bekta\u015fl\u0131"
    ],
    "wof:name":"Bektasoglu",
    "wof:placetype":"locality"
},
  "geometry": {"coordinates":[37.05611,36.85333],"type":"Point"}
}