{
  "type": "Feature",
  "properties": {
    "gn:admin1_code":"17.0",
    "gn:asciiname":"Cugura",
    "gn:country_code":"TR",
    "gn:dem":148,
    "gn:feature_class":"P",
    "gn:feature_code":"PPL",
    "gn:name":"Cugura",
    "gn:population":0,
    "gn:timezone":"Europe/Istanbul",
    "iso:country":"TR",
    "name:und_x_variant":[
        "Zagura",
        "Cugura"
    ],
    "wof:name":"Cugura",
    "wof:placetype":"locality"
},
  "geometry": {"coordinates":[25.83923,40.13347],"type":"Point"}
}