{
  "type": "Feature",
  "properties": {
    "gn:admin1_code":"41",
    "gn:asciiname":"Babakoy",
    "gn:country_code":"TR",
    "gn:dem":60,
    "gn:feature_class":"P",
    "gn:feature_code":"PPL",
    "gn:name":"Babak\u00f6y",
    "gn:population":0,
    "gn:timezone":"Europe/Istanbul",
    "iso:country":"TR",
    "name:tur_x_preferred":[
        "Babak\u00f6y"
    ],
    "wof:name":"Babakoy",
    "wof:placetype":"locality"
},
  "geometry": {"coordinates":[30.18537,41.10826],"type":"Point"}
}