{
  "type": "Feature",
  "properties": {
    "gn:admin1_code":"49",
    "gn:asciiname":"Kalecik",
    "gn:country_code":"TR",
    "gn:dem":1596,
    "gn:feature_class":"P",
    "gn:feature_code":"PPL",
    "gn:name":"Kalecik",
    "gn:population":0,
    "gn:timezone":"Europe/Istanbul",
    "iso:country":"TR",
    "name:tur_x_preferred":[
        "Kalecik"
    ],
    "wof:name":"Kalecik",
    "wof:placetype":"locality"
},
  "geometry": {"coordinates":[41.33721,39.14158],"type":"Point"}
}