{
  "type": "Feature",
  "properties": {
    "gn:admin1_code":"85.0",
    "gn:asciiname":"Dogancilar",
    "gn:country_code":"TR",
    "gn:dem":126,
    "gn:feature_class":"P",
    "gn:feature_code":"PPL",
    "gn:name":"Do\u011fanc\u0131lar",
    "gn:population":0,
    "gn:timezone":"Europe/Istanbul",
    "iso:country":"TR",
    "wof:name":"Dogancilar",
    "wof:placetype":"locality"
},
  "geometry": {"coordinates":[31.39698,41.09359],"type":"Point"}
}