{
  "type": "Feature",
  "properties": {
    "gn:admin1_code":"34",
    "gn:asciiname":"Sigili",
    "gn:country_code":"TR",
    "gn:dem":24,
    "gn:feature_class":"P",
    "gn:feature_code":"PPL",
    "gn:name":"S\u0131\u011f\u0131l\u0131",
    "gn:population":0,
    "gn:timezone":"Europe/Istanbul",
    "iso:country":"TR",
    "name:tur_x_preferred":[
        "S\u0131\u011f\u0131l\u0131"
    ],
    "wof:name":"Sigili",
    "wof:placetype":"locality"
},
  "geometry": {"coordinates":[29.78269,41.08626],"type":"Point"}
}