{
  "type": "Feature",
  "properties": {
    "gn:admin1_code":"46",
    "gn:asciiname":"Narli",
    "gn:country_code":"TR",
    "gn:dem":588,
    "gn:feature_class":"P",
    "gn:feature_code":"PPLA3",
    "gn:name":"Narl\u0131",
    "gn:population":0,
    "gn:timezone":"Europe/Istanbul",
    "iso:country":"TR",
    "name:fas_x_preferred":[
        "\u0646\u0627\u0631\u0644\u06cc"
    ],
    "name:nno_x_preferred":[
        "Narl\u0131"
    ],
    "name:rus_x_preferred":[
        "\u041d\u0430\u0440\u043b\u044b"
    ],
    "name:tur_x_preferred":[
        "Narl\u0131"
    ],
    "name:und_x_variant":[
        "Narl\u0131"
    ],
    "name:vie_x_preferred":[
        "Narl\u0131"
    ],
    "name:zho_x_preferred":[
        "\u7d0d\u723e\u52d2"
    ],
    "wof:name":"Narli",
    "wof:placetype":"locality"
},
  "geometry": {"coordinates":[37.13614000000001,37.39148],"type":"Point"}
}