{
  "type": "Feature",
  "properties": {
    "gn:admin1_code":"50",
    "gn:asciiname":"Kozluca",
    "gn:country_code":"TR",
    "gn:dem":1168,
    "gn:feature_class":"P",
    "gn:feature_code":"PPL",
    "gn:name":"Kozluca",
    "gn:population":0,
    "gn:timezone":"Europe/Istanbul",
    "iso:country":"TR",
    "name:aze_x_preferred":[
        "Qozluca"
    ],
    "name:bul_x_preferred":[
        "\u041a\u043e\u0437\u043b\u0443\u0434\u0436\u0430"
    ],
    "name:tur_x_preferred":[
        "Kozluca"
    ],
    "wof:name":"Kozluca",
    "wof:placetype":"locality"
},
  "geometry": {"coordinates":[34.40246,38.6114],"type":"Point"}
}