{
  "type": "Feature",
  "properties": {
    "gn:country":"TR",
    "gn:fcode":"PPL",
    "gn:pop":0,
    "iso:country":"TR",
    "name:unk_x_variant":[
        "Ho\u015fap"
    ],
    "qs:name":"G\u00fczelsu",
    "qs:name_adm0":"Turkey",
    "qs:name_adm1":"Van",
    "qs:photos":8,
    "qs:photos_1k":2,
    "qs:photos_9k":1,
    "qs:photos_9r":1,
    "qs:photos_all":8,
    "qs:photos_sr":1,
    "qs:placetype":"Town",
    "qs:pop_sr":"4",
    "wd:wordcount":50,
    "wof:name":"G\u00fczelsu",
    "wof:placetype":"locality",
    "wof:population":0
},
  "geometry": {"coordinates":[43.79622,38.31882],"type":"Point"}
}