{
  "type": "Feature",
  "properties": {
    "gn:admin1_code":"21",
    "gn:asciiname":"Dolunay",
    "gn:country_code":"TR",
    "gn:dem":1049,
    "gn:feature_class":"P",
    "gn:feature_code":"PPL",
    "gn:name":"Dolunay",
    "gn:population":0,
    "gn:timezone":"Europe/Istanbul",
    "iso:country":"TR",
    "name:tur_x_preferred":[
        "Dolunay"
    ],
    "name:und_x_variant":[
        "Zengi"
    ],
    "wof:name":"Dolunay",
    "wof:placetype":"locality"
},
  "geometry": {"coordinates":[40.68065,38.3171],"type":"Point"}
}