{
  "type": "Feature",
  "properties": {
    "gn:admin1_code":"79.0",
    "gn:asciiname":"Cevrimli",
    "gn:country_code":"TR",
    "gn:dem":962,
    "gn:feature_class":"P",
    "gn:feature_code":"PPL",
    "gn:name":"\u00c7evrimli",
    "gn:population":0,
    "gn:timezone":"Europe/Istanbul",
    "iso:country":"TR",
    "name:und_x_variant":[
        "P\u00f6hrenk",
        "\u00c7evrimli"
    ],
    "wof:name":"Cevrimli",
    "wof:placetype":"locality"
},
  "geometry": {"coordinates":[33.75884,40.12034],"type":"Point"}
}