{
  "type": "Feature",
  "properties": {
    "gn:admin1_code":"63.0",
    "gn:asciiname":"Sogukkuyu",
    "gn:country_code":"TR",
    "gn:dem":557,
    "gn:feature_class":"P",
    "gn:feature_code":"PPL",
    "gn:name":"So\u011fukkuyu",
    "gn:population":0,
    "gn:timezone":"Europe/Istanbul",
    "iso:country":"TR",
    "name:tur_x_preferred":[
        "So\u011fukkuyu"
    ],
    "wof:name":"Sogukkuyu",
    "wof:placetype":"locality"
},
  "geometry": {"coordinates":[38.41857,37.34967],"type":"Point"}
}