{
  "type": "Feature",
  "properties": {
    "gn:admin1_code":"25.0",
    "gn:asciiname":"Karnavas",
    "gn:cc2":"TR",
    "gn:country_code":"TR",
    "gn:dem":1271,
    "gn:feature_class":"P",
    "gn:feature_code":"PPL",
    "gn:name":"Karnavas",
    "gn:population":0,
    "gn:timezone":"Europe/Istanbul",
    "iso:country":"TR",
    "name:und_x_variant":[
        "Karnavans",
        "Karnavaz",
        "Karnavas"
    ],
    "wof:name":"Karnavas",
    "wof:placetype":"locality"
},
  "geometry": {"coordinates":[42.06667,40.75],"type":"Point"}
}