{
  "type": "Feature",
  "properties": {
    "gn:admin1_code":"14.0",
    "gn:asciiname":"Yukarikinik",
    "gn:country_code":"TR",
    "gn:dem":1090,
    "gn:feature_class":"P",
    "gn:feature_code":"PPL",
    "gn:name":"Yukar\u0131k\u0131n\u0131k",
    "gn:population":0,
    "gn:timezone":"Europe/Istanbul",
    "iso:country":"TR",
    "name:und_x_variant":[
        "\u0130lyaslar",
        "K\u0131n\u0131kbala",
        "Yukar\u0131k\u0131n\u0131k"
    ],
    "wof:name":"Yukarikinik",
    "wof:placetype":"locality"
},
  "geometry": {"coordinates":[30.69193,40.18912],"type":"Point"}
}