{
  "type": "Feature",
  "properties": {
    "gn:admin1_code":"69.0",
    "gn:asciiname":"Duymadik",
    "gn:country_code":"TR",
    "gn:dem":1987,
    "gn:feature_class":"P",
    "gn:feature_code":"PPL",
    "gn:name":"Duymad\u0131k",
    "gn:population":0,
    "gn:timezone":"Europe/Istanbul",
    "iso:country":"TR",
    "name:tur_x_preferred":[
        "Duymad\u0131k"
    ],
    "wof:name":"Duymadik",
    "wof:placetype":"locality"
},
  "geometry": {"coordinates":[39.83061,40.39806],"type":"Point"}
}