{
  "type": "Feature",
  "properties": {
    "gn:admin1_code":"43",
    "gn:asciiname":"Guvecci",
    "gn:country_code":"TR",
    "gn:dem":1002,
    "gn:feature_class":"P",
    "gn:feature_code":"PPL",
    "gn:name":"G\u00fcve\u00e7ci",
    "gn:population":0,
    "gn:timezone":"Europe/Istanbul",
    "iso:country":"TR",
    "name:tur_x_preferred":[
        "G\u00fcve\u00e7ci"
    ],
    "wof:name":"Guvecci",
    "wof:placetype":"locality"
},
  "geometry": {"coordinates":[29.90812,39.44325],"type":"Point"}
}