{
  "type": "Feature",
  "properties": {
    "gn:admin1_code":"17.0",
    "gn:asciiname":"Guvencik",
    "gn:country_code":"TR",
    "gn:dem":304,
    "gn:feature_class":"P",
    "gn:feature_code":"PPL",
    "gn:name":"G\u00fcvencik",
    "gn:population":0,
    "gn:timezone":"Europe/Istanbul",
    "iso:country":"TR",
    "wof:name":"Guvencik",
    "wof:placetype":"locality"
},
  "geometry": {"coordinates":[26.64013,39.75886],"type":"Point"}
}