{
  "type": "Feature",
  "properties": {
    "gn:admin1_code":"64",
    "gn:asciiname":"Ramazanlar",
    "gn:country_code":"TR",
    "gn:dem":736,
    "gn:feature_class":"P",
    "gn:feature_code":"PPL",
    "gn:name":"Ramazanlar",
    "gn:population":0,
    "gn:timezone":"Europe/Istanbul",
    "iso:country":"TR",
    "name:tur_x_preferred":[
        "Ramazanlar"
    ],
    "wof:name":"Ramazanlar",
    "wof:placetype":"locality"
},
  "geometry": {"coordinates":[29.27143,38.75759],"type":"Point"}
}