{
  "type": "Feature",
  "properties": {
    "gn:admin1_code":"76.0",
    "gn:asciiname":"Ulular",
    "gn:country_code":"TR",
    "gn:dem":475,
    "gn:feature_class":"P",
    "gn:feature_code":"PPL",
    "gn:name":"Ulular",
    "gn:population":0,
    "gn:timezone":"Europe/Istanbul",
    "iso:country":"TR",
    "wof:name":"Ulular",
    "wof:placetype":"locality"
},
  "geometry": {"coordinates":[41.5928,37.75077],"type":"Point"}
}