{
  "type": "Feature",
  "properties": {
    "gn:admin1_code":"89",
    "gn:asciiname":"Kucuksu",
    "gn:country_code":"TR",
    "gn:dem":698,
    "gn:feature_class":"P",
    "gn:feature_code":"PPL",
    "gn:name":"K\u00fc\u00e7\u00fcksu",
    "gn:population":0,
    "gn:timezone":"Europe/Istanbul",
    "iso:country":"TR",
    "wof:name":"Kucuksu",
    "wof:placetype":"locality"
},
  "geometry": {"coordinates":[32.85318,41.11491],"type":"Point"}
}