{
  "type": "Feature",
  "properties": {
    "gn:admin1_code":"61.0",
    "gn:asciiname":"Yenikoy",
    "gn:country_code":"TR",
    "gn:dem":491,
    "gn:feature_class":"P",
    "gn:feature_code":"PPL",
    "gn:name":"Yenik\u00f6y",
    "gn:population":0,
    "gn:timezone":"Europe/Istanbul",
    "iso:country":"TR",
    "name:und_x_variant":[
        "Yenik\u00f6y",
        "\u00c7a\u011flayan"
    ],
    "wof:name":"Yenikoy",
    "wof:placetype":"locality"
},
  "geometry": {"coordinates":[39.67763,40.96115],"type":"Point"}
}