{
  "type": "Feature",
  "properties": {
    "gn:admin1_code":"31.0",
    "gn:asciiname":"Abesler",
    "gn:country_code":"TR",
    "gn:dem":135,
    "gn:feature_class":"P",
    "gn:feature_code":"PPL",
    "gn:name":"Abe\u015fler",
    "gn:population":0,
    "gn:timezone":"Europe/Istanbul",
    "iso:country":"TR",
    "name:tur_x_preferred":[
        "Abe\u015fler"
    ],
    "wof:name":"Abesler",
    "wof:placetype":"locality"
},
  "geometry": {"coordinates":[36.415,36.595],"type":"Point"}
}