{
  "type": "Feature",
  "properties": {
    "gn:admin1_code":"61.0",
    "gn:asciiname":"Yolbasi",
    "gn:country_code":"TR",
    "gn:dem":701,
    "gn:feature_class":"P",
    "gn:feature_code":"PPL",
    "gn:name":"Yolba\u015f\u0131",
    "gn:population":0,
    "gn:timezone":"Europe/Istanbul",
    "iso:country":"TR",
    "name:und_x_variant":[
        "Yolba\u015f\u0131",
        "Kaloyna"
    ],
    "wof:name":"Yolbasi",
    "wof:placetype":"locality"
},
  "geometry": {"coordinates":[39.58333,40.93333],"type":"Point"}
}