{
  "type": "Feature",
  "properties": {
    "gn:admin1_code":"07",
    "gn:asciiname":"Naragaci",
    "gn:country_code":"TR",
    "gn:dem":1247,
    "gn:feature_class":"P",
    "gn:feature_code":"PPL",
    "gn:name":"Nara\u011fac\u0131",
    "gn:population":0,
    "gn:timezone":"Europe/Istanbul",
    "iso:country":"TR",
    "wof:name":"Naragaci",
    "wof:placetype":"locality"
},
  "geometry": {"coordinates":[32.09334,36.80148],"type":"Point"}
}