{
  "type": "Feature",
  "properties": {
    "gn:admin1_code":"65",
    "gn:asciiname":"Yukariegerli",
    "gn:country_code":"TR",
    "gn:dem":2047,
    "gn:feature_class":"P",
    "gn:feature_code":"PPL",
    "gn:name":"Yukar\u0131e\u011ferli",
    "gn:population":0,
    "gn:timezone":"Europe/Istanbul",
    "iso:country":"TR",
    "wof:name":"Yukariegerli",
    "wof:placetype":"locality"
},
  "geometry": {"coordinates":[43.53278,37.91917],"type":"Point"}
}