{
  "type": "Feature",
  "properties": {
    "gn:admin1_code":"85",
    "gn:asciiname":"Cemaller",
    "gn:country_code":"TR",
    "gn:dem":262,
    "gn:feature_class":"P",
    "gn:feature_code":"PPL",
    "gn:name":"Cemaller",
    "gn:population":0,
    "gn:timezone":"Europe/Istanbul",
    "iso:country":"TR",
    "wof:name":"Cemaller",
    "wof:placetype":"locality"
},
  "geometry": {"coordinates":[32.02125,41.23884],"type":"Point"}
}