{
  "type": "Feature",
  "properties": {
    "gn:admin1_code":"63",
    "gn:asciiname":"Yukarialinca",
    "gn:country_code":"TR",
    "gn:dem":742,
    "gn:feature_class":"P",
    "gn:feature_code":"PPL",
    "gn:name":"Yukar\u0131al\u0131nca",
    "gn:population":0,
    "gn:timezone":"Europe/Istanbul",
    "iso:country":"TR",
    "name:tur_x_preferred":[
        "Yukar\u0131al\u0131nca"
    ],
    "wof:name":"Yukarialinca",
    "wof:placetype":"locality"
},
  "geometry": {"coordinates":[39.55416,37.42483],"type":"Point"}
}