{
  "type": "Feature",
  "properties": {
    "gn:admin1_code":"63",
    "gn:asciiname":"Shemsik",
    "gn:country_code":"TR",
    "gn:dem":758,
    "gn:feature_class":"P",
    "gn:feature_code":"PPL",
    "gn:name":"Shemsik",
    "gn:population":0,
    "gn:timezone":"Europe/Istanbul",
    "iso:country":"TR",
    "name:und_x_variant":[
        "G\u00fcn\u0131\u015f\u0131k",
        "\u015eemsik",
        "Shemsik"
    ],
    "wof:name":"Shemsik",
    "wof:placetype":"locality"
},
  "geometry": {"coordinates":[38.76018,37.27927],"type":"Point"}
}