{
  "type": "Feature",
  "properties": {
    "gn:admin1_code":"63",
    "gn:asciiname":"Cekoren",
    "gn:country_code":"TR",
    "gn:dem":637,
    "gn:feature_class":"P",
    "gn:feature_code":"PPL",
    "gn:name":"\u00c7ek\u00f6ren",
    "gn:population":0,
    "gn:timezone":"Europe/Istanbul",
    "iso:country":"TR",
    "wof:name":"Cekoren",
    "wof:placetype":"locality"
},
  "geometry": {"coordinates":[39.03333,37.51667],"type":"Point"}
}