{
  "type": "Feature",
  "properties": {
    "gn:admin1_code":"37.0",
    "gn:asciiname":"Bocuk",
    "gn:country_code":"TR",
    "gn:dem":572,
    "gn:feature_class":"P",
    "gn:feature_code":"PPL",
    "gn:name":"B\u00f6c\u00fck",
    "gn:population":0,
    "gn:timezone":"Europe/Istanbul",
    "iso:country":"TR",
    "name:und_x_variant":[
        "B\u00f6c\u00fck",
        "Hat\u0131plar"
    ],
    "wof:name":"Bocuk",
    "wof:placetype":"locality"
},
  "geometry": {"coordinates":[34.15627,41.4783],"type":"Point"}
}