{
  "type": "Feature",
  "properties": {
    "gn:admin1_code":"8.0",
    "gn:asciiname":"Boyuncak",
    "gn:country_code":"TR",
    "gn:dem":991,
    "gn:feature_class":"P",
    "gn:feature_code":"PPL",
    "gn:name":"Boyuncak",
    "gn:population":0,
    "gn:timezone":"Europe/Istanbul",
    "iso:country":"TR",
    "name:tur_x_preferred":[
        "Boyuncak"
    ],
    "name:tur_x_variant":[
        "Parih"
    ],
    "wof:name":"Boyuncak",
    "wof:placetype":"locality"
},
  "geometry": {"coordinates":[41.46829,41.29982],"type":"Point"}
}