{
  "type": "Feature",
  "properties": {
    "gn:admin1_code":"45",
    "gn:asciiname":"Sarnickoy",
    "gn:country_code":"TR",
    "gn:dem":552,
    "gn:feature_class":"P",
    "gn:feature_code":"PPL",
    "gn:name":"Sarn\u0131\u00e7k\u00f6y",
    "gn:population":0,
    "gn:timezone":"Europe/Istanbul",
    "iso:country":"TR",
    "name:tur_x_preferred":[
        "Sarn\u0131\u00e7k\u00f6y"
    ],
    "name:und_x_variant":[
        "Sarn\u0131\u00e7"
    ],
    "wof:name":"Sarnickoy",
    "wof:placetype":"locality"
},
  "geometry": {"coordinates":[28.76751,38.6207],"type":"Point"}
}