{
  "type": "Feature",
  "properties": {
    "gn:admin1_code":"82.0",
    "gn:asciiname":"Goynukoren",
    "gn:country_code":"TR",
    "gn:dem":1122,
    "gn:feature_class":"P",
    "gn:feature_code":"PPL",
    "gn:name":"G\u00f6yn\u00fck\u00f6ren",
    "gn:population":0,
    "gn:timezone":"Europe/Istanbul",
    "iso:country":"TR",
    "wof:name":"Goynukoren",
    "wof:placetype":"locality"
},
  "geometry": {"coordinates":[33.14772,41.01196],"type":"Point"}
}