{
  "type": "Feature",
  "properties": {
    "gn:admin1_code":"33",
    "gn:asciiname":"Sarikal",
    "gn:country_code":"TR",
    "gn:dem":904,
    "gn:feature_class":"P",
    "gn:feature_code":"PPL",
    "gn:name":"Sar\u0131kal",
    "gn:population":0,
    "gn:timezone":"Europe/Istanbul",
    "iso:country":"TR",
    "wof:name":"Sarikal",
    "wof:placetype":"locality"
},
  "geometry": {"coordinates":[31.28514,37.5247],"type":"Point"}
}