{
  "type": "Feature",
  "properties": {
    "gn:admin1_code":"48.0",
    "gn:asciiname":"Akcapinar",
    "gn:country_code":"TR",
    "gn:dem":11,
    "gn:feature_class":"P",
    "gn:feature_code":"PPL",
    "gn:name":"Ak\u00e7ap\u0131nar",
    "gn:population":0,
    "gn:timezone":"Europe/Istanbul",
    "iso:country":"TR",
    "name:und_x_variant":[
        "Ak\u00e7ap\u0131nar"
    ],
    "wof:name":"Akcapinar",
    "wof:placetype":"locality"
},
  "geometry": {"coordinates":[28.35615,37.02531],"type":"Point"}
}