{
  "type": "Feature",
  "properties": {
    "gn:admin1_code":"93.0",
    "gn:asciiname":"Kuyumcular",
    "gn:country_code":"TR",
    "gn:dem":125,
    "gn:feature_class":"P",
    "gn:feature_code":"PPL",
    "gn:name":"Kuyumcular",
    "gn:population":0,
    "gn:timezone":"Europe/Istanbul",
    "iso:country":"TR",
    "name:und_x_variant":[
        "D\u00f6ngelli",
        "Kuyumcular"
    ],
    "wof:name":"Kuyumcular",
    "wof:placetype":"locality"
},
  "geometry": {"coordinates":[31.03036,40.85409],"type":"Point"}
}