{
  "type": "Feature",
  "properties": {
    "gn:admin1_code":"72.0",
    "gn:asciiname":"Akcay",
    "gn:country_code":"TR",
    "gn:dem":560,
    "gn:feature_class":"P",
    "gn:feature_code":"PPL",
    "gn:name":"Ak\u00e7ay",
    "gn:population":0,
    "gn:timezone":"Europe/Istanbul",
    "iso:country":"TR",
    "name:tur_x_preferred":[
        "Ak\u00e7ay"
    ],
    "wof:name":"Akcay",
    "wof:placetype":"locality"
},
  "geometry": {"coordinates":[40.00487,37.2953],"type":"Point"}
}