{
  "type": "Feature",
  "properties": {
    "gn:admin1_code":"32",
    "gn:asciiname":"Sipahili",
    "gn:country_code":"TR",
    "gn:dem":4,
    "gn:feature_class":"P",
    "gn:feature_code":"PPL",
    "gn:name":"Sipahili",
    "gn:population":0,
    "gn:timezone":"Europe/Istanbul",
    "iso:country":"TR",
    "name:ceb_x_preferred":[
        "Sipahili"
    ],
    "name:msa_x_preferred":[
        "Sipahili"
    ],
    "name:und_x_variant":[
        "Babadil"
    ],
    "name:vie_x_preferred":[
        "Sipahili"
    ],
    "wof:name":"Sipahili",
    "wof:placetype":"locality"
},
  "geometry": {"coordinates":[33.4644,36.16125],"type":"Point"}
}