{
  "type": "Feature",
  "properties": {
    "gn:admin1_code":"60.0",
    "gn:asciiname":"Kuldan",
    "gn:country_code":"TR",
    "gn:dem":926,
    "gn:feature_class":"P",
    "gn:feature_code":"PPL",
    "gn:name":"Kuldan",
    "gn:population":0,
    "gn:timezone":"Europe/Istanbul",
    "iso:country":"TR",
    "name:und_x_variant":[
        "Akk\u0131l\u0131\u00e7"
    ],
    "wof:name":"Kuldan",
    "wof:placetype":"locality"
},
  "geometry": {"coordinates":[35.64119,40.1257],"type":"Point"}
}