{
  "type": "Feature",
  "properties": {
    "gn:admin1_code":"43",
    "gn:asciiname":"Kurtdere",
    "gn:country_code":"TR",
    "gn:dem":951,
    "gn:feature_class":"P",
    "gn:feature_code":"PPL",
    "gn:name":"Kurtdere",
    "gn:population":0,
    "gn:timezone":"Europe/Istanbul",
    "iso:country":"TR",
    "name:und_x_variant":[
        "Kurtderek\u00f6y",
        "Kurtderek\u00f6y\u00fc",
        "Kurtdere"
    ],
    "wof:name":"Kurtdere",
    "wof:placetype":"locality"
},
  "geometry": {"coordinates":[29.18099,39.19111],"type":"Point"}
}