{
  "type": "Feature",
  "properties": {
    "gn:admin1_code":"66",
    "gn:asciiname":"Aydogan",
    "gn:country_code":"TR",
    "gn:dem":1023,
    "gn:feature_class":"P",
    "gn:feature_code":"PPL",
    "gn:name":"Aydo\u011fan",
    "gn:population":0,
    "gn:timezone":"Europe/Istanbul",
    "iso:country":"TR",
    "wof:name":"Aydogan",
    "wof:placetype":"locality"
},
  "geometry": {"coordinates":[34.4216,39.88813],"type":"Point"}
}