{
  "type": "Feature",
  "properties": {
    "gn:admin1_code":"38",
    "gn:asciiname":"Catakdere",
    "gn:country_code":"TR",
    "gn:dem":1494,
    "gn:feature_class":"P",
    "gn:feature_code":"PPL",
    "gn:name":"\u00c7atakdere",
    "gn:population":0,
    "gn:timezone":"Europe/Istanbul",
    "iso:country":"TR",
    "name:und_x_variant":[
        "Dikir",
        "\u00c7atakdere"
    ],
    "wof:name":"Catakdere",
    "wof:placetype":"locality"
},
  "geometry": {"coordinates":[35.71849,38.67187],"type":"Point"}
}