{
  "type": "Feature",
  "properties": {
    "gn:admin1_code":"71",
    "gn:asciiname":"Pinarbasi",
    "gn:country_code":"TR",
    "gn:dem":1325,
    "gn:feature_class":"P",
    "gn:feature_code":"PPL",
    "gn:name":"P\u0131narba\u015f\u0131",
    "gn:population":0,
    "gn:timezone":"Europe/Istanbul",
    "iso:country":"TR",
    "wof:name":"Pinarbasi",
    "wof:placetype":"locality"
},
  "geometry": {"coordinates":[31.585,37.99],"type":"Point"}
}