{
  "type": "Feature",
  "properties": {
    "gn:admin1_code":"25.0",
    "gn:asciiname":"Akyazi",
    "gn:country_code":"TR",
    "gn:dem":2152,
    "gn:feature_class":"P",
    "gn:feature_code":"PPL",
    "gn:name":"Akyaz\u0131",
    "gn:population":0,
    "gn:timezone":"Europe/Istanbul",
    "iso:country":"TR",
    "name:und_x_variant":[
        "Akyaz\u0131",
        "Yukar\u0131akyaz\u0131"
    ],
    "wof:name":"Akyazi",
    "wof:placetype":"locality"
},
  "geometry": {"coordinates":[40.71432,40.12802],"type":"Point"}
}