{
  "type": "Feature",
  "properties": {
    "gn:admin1_code":"25.0",
    "gn:asciiname":"Egerti",
    "gn:country_code":"TR",
    "gn:dem":1947,
    "gn:feature_class":"P",
    "gn:feature_code":"PPL",
    "gn:name":"E\u011ferti",
    "gn:population":0,
    "gn:timezone":"Europe/Istanbul",
    "iso:country":"TR",
    "name:tur_x_preferred":[
        "E\u011ferti"
    ],
    "wof:name":"Egerti",
    "wof:placetype":"locality"
},
  "geometry": {"coordinates":[40.97694,40.10648],"type":"Point"}
}