{
  "type": "Feature",
  "properties": {
    "gn:admin1_code":"64",
    "gn:asciiname":"Yorukler",
    "gn:country_code":"TR",
    "gn:dem":759,
    "gn:feature_class":"P",
    "gn:feature_code":"PPL",
    "gn:name":"Y\u00f6r\u00fckler",
    "gn:population":0,
    "gn:timezone":"Europe/Istanbul",
    "iso:country":"TR",
    "name:tur_x_preferred":[
        "Y\u00f6r\u00fckler"
    ],
    "wof:name":"Yorukler",
    "wof:placetype":"locality"
},
  "geometry": {"coordinates":[29.15892,38.59131],"type":"Point"}
}