{
  "type": "Feature",
  "properties": {
    "gn:admin1_code":"12",
    "gn:asciiname":"Hut",
    "gn:cc2":"TR",
    "gn:country_code":"TR",
    "gn:dem":1456,
    "gn:feature_class":"P",
    "gn:feature_code":"PPL",
    "gn:name":"Hut",
    "gn:population":0,
    "gn:timezone":"Europe/Istanbul",
    "iso:country":"TR",
    "name:ara_x_preferred":[
        "\u0643\u0648\u062e"
    ],
    "name:bar_x_preferred":[
        "Hittn"
    ],
    "name:bjn_x_preferred":[
        "Rarompok"
    ],
    "name:bul_x_preferred":[
        "\u041a\u043e\u043b\u0438\u0431\u0430"
    ],
    "name:bxr_x_preferred":[
        "\u041e\u0431\u043e\u043e\u0445\u043e\u0439"
    ],
    "name:deu_x_preferred":[
        "H\u00fctte"
    ],
    "name:epo_x_preferred":[
        "Kabano"
    ],
    "name:est_x_preferred":[
        "Onn"
    ],
    "name:eus_x_preferred":[
        "Txabola"
    ],
    "name:fas_x_preferred":[
        "\u06a9\u0648\u0645\u0647"
    ],
    "name:fra_x_preferred":[
        "Hutte"
    ],
    "name:gle_x_preferred":[
        "Both\u00e1n"
    ],
    "name:heb_x_preferred":[
        "\u05e1\u05d5\u05db\u05d4"
    ],
    "name:ind_x_preferred":[
        "Pondok"
    ],
    "name:ita_x_preferred":[
        "Capanna"
    ],
    "name:kab_x_preferred":[
        "Ajda\u1e5b"
    ],
    "name:kan_x_preferred":[
        "\u0c97\u0cc1\u0ca1\u0cbf\u0cb8\u0cb2\u0cc1"
    ],
    "name:kor_x_preferred":[
        "\uc624\ub450\ub9c9"
    ],
    "name:lat_x_preferred":[
        "Casa"
    ],
    "name:msa_x_preferred":[
        "Pondok"
    ],
    "name:nld_x_preferred":[
        "Hut"
    ],
    "name:por_x_preferred":[
        "Cabana"
    ],
    "name:rus_x_preferred":[
        "\u0425\u0438\u0436\u0438\u043d\u0430"
    ],
    "name:scn_x_preferred":[
        "Pagghiaru"
    ],
    "name:srp_x_preferred":[
        "\u041a\u043e\u043b\u0438\u0431\u0430"
    ],
    "name:swe_x_preferred":[
        "Koja"
    ],
    "name:tam_x_preferred":[
        "\u0b95\u0bc1\u0b9f\u0bbf\u0b9a\u0bc8"
    ],
    "name:tel_x_preferred":[
        "\u0c17\u0c41\u0c21\u0c3f\u0c38\u0c46"
    ],
    "name:tur_x_preferred":[
        "Kul\u00fcbe"
    ],
    "name:ukr_x_preferred":[
        "\u0425\u0430\u043b\u0430\u0431\u0443\u0434\u0430"
    ],
    "name:und_x_variant":[
        "Hot K\u00f6y\u00fc",
        "Hot"
    ],
    "name:vec_x_preferred":[
        "Capana"
    ],
    "name:vie_x_preferred":[
        "T\u00fap l\u1ec1u"
    ],
    "name:wln_x_preferred":[
        "Cahoute"
    ],
    "wof:name":"Hut",
    "wof:placetype":"locality"
},
  "geometry": {"coordinates":[40.71667,38.76667],"type":"Point"}
}