{
  "type": "Feature",
  "properties": {
    "gn:admin1_code":"12",
    "gn:asciiname":"Hut",
    "gn:cc2":"TR",
    "gn:country_code":"TR",
    "gn:dem":1456,
    "gn:feature_class":"P",
    "gn:feature_code":"PPL",
    "gn:name":"Hut",
    "gn:population":0,
    "gn:timezone":"Europe/Istanbul",
    "iso:country":"TR",
    "name:und_x_variant":[
        "Hot K\u00f6y\u00fc",
        "Hot",
        "Hut"
    ],
    "wof:name":"Hut",
    "wof:placetype":"locality"
},
  "geometry": {"coordinates":[40.71667,38.76667],"type":"Point"}
}