{
  "type": "Feature",
  "properties": {
    "gn:admin1_code":"71",
    "gn:asciiname":"Hasanoba",
    "gn:country_code":"TR",
    "gn:dem":1009,
    "gn:feature_class":"P",
    "gn:feature_code":"PPL",
    "gn:name":"Hasanoba",
    "gn:population":0,
    "gn:timezone":"Europe/Istanbul",
    "iso:country":"TR",
    "wof:name":"Hasanoba",
    "wof:placetype":"locality"
},
  "geometry": {"coordinates":[33.28457,37.58693],"type":"Point"}
}