{
  "type": "Feature",
  "properties": {
    "gn:admin1_code":"16.0",
    "gn:asciiname":"Subasi",
    "gn:country_code":"TR",
    "gn:dem":355,
    "gn:feature_class":"P",
    "gn:feature_code":"PPL",
    "gn:name":"Suba\u015f\u0131",
    "gn:population":0,
    "gn:timezone":"Europe/Istanbul",
    "iso:country":"TR",
    "name:tur_x_preferred":[
        "Suba\u015f\u0131"
    ],
    "wof:name":"Subasi",
    "wof:placetype":"locality"
},
  "geometry": {"coordinates":[29.64861,40.22833],"type":"Point"}
}