{
  "type": "Feature",
  "properties": {
    "gn:admin1_code":"81.0",
    "gn:asciiname":"Cirakli",
    "gn:country_code":"TR",
    "gn:dem":203,
    "gn:feature_class":"P",
    "gn:feature_code":"PPL",
    "gn:name":"C\u0131rakl\u0131",
    "gn:population":0,
    "gn:timezone":"Europe/Istanbul",
    "iso:country":"TR",
    "wof:name":"Cirakli",
    "wof:placetype":"locality"
},
  "geometry": {"coordinates":[35.18444,37.14075],"type":"Point"}
}