{
  "type": "Feature",
  "properties": {
    "gn:admin1_code":"28.0",
    "gn:asciiname":"Armutduzu",
    "gn:country_code":"TR",
    "gn:dem":680,
    "gn:feature_class":"P",
    "gn:feature_code":"PPL",
    "gn:name":"Armutd\u00fcz\u00fc",
    "gn:population":0,
    "gn:timezone":"Europe/Istanbul",
    "iso:country":"TR",
    "name:ell_x_colloquial":[
        "\u03b3\u03bf\u03cd\u03c3\u03c7\u03b1",
        "\u03b3\u03bf\u03cd\u03c3\u03b4\u03b1"
    ],
    "name:ell_x_historical":[
        "\u039a\u03bf\u03cd\u03c3\u03ba\u03b1\u03b3\u03b9\u03b1",
        "\u0393\u03bf\u03cd\u03c3\u03b3\u03b1\u03b3\u03b9\u03b1",
        "\u03b3\u03bf\u03cd\u03c3\u03c7\u03b1",
        "\u03b3\u03bf\u03cd\u03c3\u03b4\u03b1"
    ],
    "name:ell_x_preferred":[
        "\u039a\u03bf\u03cd\u03c3\u03ba\u03b1\u03b3\u03b9\u03b1"
    ],
    "name:ell_x_variant":[
        "\u0393\u03bf\u03cd\u03c3\u03b3\u03b1\u03b3\u03b9\u03b1",
        "\u0391\u03c1\u03bc\u03bf\u03cd\u03c4 \u03bd\u03c4\u03b9\u03b6\u03b9",
        "\u03b3\u03bf\u03cd\u03c3\u03c7\u03b1",
        "\u03b3\u03bf\u03cd\u03c3\u03b4\u03b1"
    ],
    "name:tur_x_preferred":[
        "Armutd\u00fcz\u00fc"
    ],
    "wof:name":"Armutduzu",
    "wof:placetype":"locality"
},
  "geometry": {"coordinates":[38.5444,40.78739],"type":"Point"}
}