{
  "type": "Feature",
  "properties": {
    "gn:admin1_code":"81",
    "gn:asciiname":"Karahan",
    "gn:country_code":"TR",
    "gn:dem":601,
    "gn:feature_class":"P",
    "gn:feature_code":"PPL",
    "gn:name":"Karahan",
    "gn:population":0,
    "gn:timezone":"Europe/Istanbul",
    "iso:country":"TR",
    "name:ceb_x_preferred":[
        "Karahan"
    ],
    "name:deu_x_preferred":[
        "Karahan"
    ],
    "name:swe_x_preferred":[
        "Karahan"
    ],
    "name:tur_x_preferred":[
        "Karahan"
    ],
    "name:und_x_variant":[
        "Karahank\u00f6y",
        "Karahan"
    ],
    "wof:name":"Karahan",
    "wof:placetype":"locality"
},
  "geometry": {"coordinates":[35.53077000000001,37.58486],"type":"Point"}
}