{
  "type": "Feature",
  "properties": {
    "gn:admin1_code":"14.0",
    "gn:asciiname":"Dikmen",
    "gn:country_code":"TR",
    "gn:dem":1270,
    "gn:feature_class":"P",
    "gn:feature_code":"PPL",
    "gn:name":"Dikmen",
    "gn:population":0,
    "gn:timezone":"Europe/Istanbul",
    "iso:country":"TR",
    "wof:name":"Dikmen",
    "wof:placetype":"locality"
},
  "geometry": {"coordinates":[32.27419,40.79363],"type":"Point"}
}