{
  "type": "Feature",
  "properties": {
    "gn:admin1_code":"45",
    "gn:asciiname":"Aptal",
    "gn:country_code":"TR",
    "gn:dem":75,
    "gn:feature_class":"P",
    "gn:feature_code":"PPL",
    "gn:name":"Aptal",
    "gn:population":0,
    "gn:timezone":"Europe/Istanbul",
    "iso:country":"TR",
    "name:tur_x_preferred":[
        "\u00c7ayk\u00f6y"
    ],
    "name:tur_x_variant":[
        "Aptal"
    ],
    "wof:name":"Aptal",
    "wof:placetype":"locality"
},
  "geometry": {"coordinates":[28.06176,38.5322],"type":"Point"}
}