{
  "type": "Feature",
  "properties": {
    "gn:admin1_code":"62",
    "gn:asciiname":"Mezraa",
    "gn:country_code":"TR",
    "gn:dem":1413,
    "gn:feature_class":"P",
    "gn:feature_code":"PPLA3",
    "gn:name":"Mezraa",
    "gn:population":0,
    "gn:timezone":"Europe/Istanbul",
    "iso:country":"TR",
    "name:und_x_variant":[
        "K\u0131rm\u0131z\u0131k\u00f6pr\u00fc",
        "Mezraa"
    ],
    "wof:name":"Mezraa",
    "wof:placetype":"locality"
},
  "geometry": {"coordinates":[39.82439,39.3859],"type":"Point"}
}