{
  "type": "Feature",
  "properties": {
    "gn:admin1_code":"4.0",
    "gn:asciiname":"Asagi Yenigun",
    "gn:country_code":"TR",
    "gn:dem":1946,
    "gn:feature_class":"P",
    "gn:feature_code":"PPL",
    "gn:name":"A\u015fa\u011f\u0131 Yenig\u00fcn",
    "gn:population":0,
    "gn:timezone":"Europe/Istanbul",
    "iso:country":"TR",
    "name:tur_x_preferred":[
        "A\u015fa\u011f\u0131 Yenig\u00fcn"
    ],
    "wof:name":"Asagi Yenigun",
    "wof:placetype":"locality"
},
  "geometry": {"coordinates":[43.06048,39.49381],"type":"Point"}
}