{
  "type": "Feature",
  "properties": {
    "gn:admin1_code":"72",
    "gn:asciiname":"Harbekaya",
    "gn:country_code":"TR",
    "gn:dem":638,
    "gn:feature_class":"P",
    "gn:feature_code":"PPL",
    "gn:name":"Harbekaya",
    "gn:population":0,
    "gn:timezone":"Europe/Istanbul",
    "iso:country":"TR",
    "name:und_x_variant":[
        "Harabekaya K\u00f6y\u00fc"
    ],
    "wof:name":"Harbekaya",
    "wof:placetype":"locality"
},
  "geometry": {"coordinates":[40.25,37.31667],"type":"Point"}
}