{
  "type": "Feature",
  "properties": {
    "gn:admin1_code":"28.0",
    "gn:asciiname":"Tuglacik",
    "gn:country_code":"TR",
    "gn:dem":708,
    "gn:feature_class":"P",
    "gn:feature_code":"PPL",
    "gn:name":"Tu\u011flac\u0131k",
    "gn:population":0,
    "gn:timezone":"Europe/Istanbul",
    "iso:country":"TR",
    "name:tur_x_preferred":[
        "Tu\u011flac\u0131k"
    ],
    "wof:name":"Tuglacik",
    "wof:placetype":"locality"
},
  "geometry": {"coordinates":[38.6298,40.76072],"type":"Point"}
}