{
  "type": "Feature",
  "properties": {
    "gn:admin1_code":"16.0",
    "gn:asciiname":"Cambaz",
    "gn:country_code":"TR",
    "gn:dem":151,
    "gn:feature_class":"P",
    "gn:feature_code":"PPL",
    "gn:name":"Cambaz",
    "gn:population":0,
    "gn:timezone":"Europe/Istanbul",
    "iso:country":"TR",
    "name:und_x_variant":[
        "Canbaz",
        "Cambaz"
    ],
    "wof:name":"Cambaz",
    "wof:placetype":"locality"
},
  "geometry": {"coordinates":[28.50605,40.26453],"type":"Point"}
}