{
  "type": "Feature",
  "properties": {
    "gn:admin1_code":"31.0",
    "gn:asciiname":"Mamykly",
    "gn:country_code":"TR",
    "gn:dem":94,
    "gn:feature_class":"P",
    "gn:feature_code":"PPL",
    "gn:name":"Mamykly",
    "gn:population":0,
    "gn:timezone":"Europe/Istanbul",
    "iso:country":"TR",
    "name:und_x_variant":[
        "Mam\u0131kl\u0131"
    ],
    "wof:name":"Mamykly",
    "wof:placetype":"locality"
},
  "geometry": {"coordinates":[36.48306,36.23278],"type":"Point"}
}