{
  "type": "Feature",
  "properties": {
    "gn:admin1_code":"02",
    "gn:asciiname":"Subasi",
    "gn:country_code":"TR",
    "gn:dem":899,
    "gn:feature_class":"P",
    "gn:feature_code":"PPL",
    "gn:name":"Suba\u015f\u0131",
    "gn:population":0,
    "gn:timezone":"Europe/Istanbul",
    "iso:country":"TR",
    "name:und_x_variant":[
        "T\u0131gn\u0131gar",
        "Suba\u015f\u0131",
        "T\u0131\u011f\u0131nk\u00e2r"
    ],
    "wof:name":"Subasi",
    "wof:placetype":"locality"
},
  "geometry": {"coordinates":[38.70976,38.01996],"type":"Point"}
}