{
  "type": "Feature",
  "properties": {
    "gn:admin1_code":"50.0",
    "gn:asciiname":"Akkoy",
    "gn:country_code":"TR",
    "gn:dem":1357,
    "gn:feature_class":"P",
    "gn:feature_code":"PPL",
    "gn:name":"Akk\u00f6y",
    "gn:population":0,
    "gn:timezone":"Europe/Istanbul",
    "iso:country":"TR",
    "wof:name":"Akkoy",
    "wof:placetype":"locality"
},
  "geometry": {"coordinates":[35.0511,38.5877],"type":"Point"}
}