{
  "type": "Feature",
  "properties": {
    "gn:admin1_code":"61.0",
    "gn:asciiname":"Resullu",
    "gn:country_code":"TR",
    "gn:dem":477,
    "gn:feature_class":"P",
    "gn:feature_code":"PPL",
    "gn:name":"Resull\u00fc",
    "gn:population":0,
    "gn:timezone":"Europe/Istanbul",
    "iso:country":"TR",
    "wof:name":"Resullu",
    "wof:placetype":"locality"
},
  "geometry": {"coordinates":[39.16783,41.01451],"type":"Point"}
}