{
  "type": "Feature",
  "properties": {
    "gn:admin1_code":"77.0",
    "gn:asciiname":"Seydiyakup",
    "gn:country_code":"TR",
    "gn:dem":1755,
    "gn:feature_class":"P",
    "gn:feature_code":"PPL",
    "gn:name":"Seydiyakup",
    "gn:population":0,
    "gn:timezone":"Europe/Istanbul",
    "iso:country":"TR",
    "name:ceb_x_preferred":[
        "Seydiyakup"
    ],
    "name:eng_x_preferred":[
        "Seydiyakup"
    ],
    "name:msa_x_preferred":[
        "Seydiyakup"
    ],
    "name:rus_x_preferred":[
        "\u0421\u0435\u0439\u0434\u0438\u044f\u043a\u0443\u043f"
    ],
    "name:tur_x_preferred":[
        "Seydiyakup"
    ],
    "name:vie_x_preferred":[
        "Seydiyakup"
    ],
    "wof:name":"Seydiyakup",
    "wof:placetype":"locality"
},
  "geometry": {"coordinates":[40.27265,40.4236],"type":"Point"}
}