{
  "type": "Feature",
  "properties": {
    "gn:admin1_code":"62",
    "gn:asciiname":"Cantur",
    "gn:country_code":"TR",
    "gn:dem":1092,
    "gn:feature_class":"P",
    "gn:feature_code":"PPL",
    "gn:name":"Cantur",
    "gn:population":0,
    "gn:timezone":"Europe/Istanbul",
    "iso:country":"TR",
    "name:und_x_variant":[
        "Aky\u00fcnl\u00fc",
        "Cantur"
    ],
    "wof:name":"Cantur",
    "wof:placetype":"locality"
},
  "geometry": {"coordinates":[39.54543,39.04299],"type":"Point"}
}