{
  "type": "Feature",
  "properties": {
    "gn:admin1_code":"68",
    "gn:asciiname":"Kutluhan",
    "gn:cc2":"TR",
    "gn:country_code":"TR",
    "gn:dem":1142,
    "gn:feature_class":"P",
    "gn:feature_code":"PPL",
    "gn:name":"Kutluhan",
    "gn:population":0,
    "gn:timezone":"Europe/Istanbul",
    "iso:country":"TR",
    "name:und_x_variant":[
        "Kutlunan",
        "Kutluhan"
    ],
    "wof:name":"Kutluhan",
    "wof:placetype":"locality"
},
  "geometry": {"coordinates":[32.69028,39.20111],"type":"Point"}
}