{
  "type": "Feature",
  "properties": {
    "gn:admin1_code":"10",
    "gn:asciiname":"Koteyli",
    "gn:country_code":"TR",
    "gn:dem":282,
    "gn:feature_class":"P",
    "gn:feature_code":"PPL",
    "gn:name":"K\u00f6teyli",
    "gn:population":0,
    "gn:timezone":"Europe/Istanbul",
    "iso:country":"TR",
    "name:tur_x_preferred":[
        "K\u00f6teyli"
    ],
    "wof:name":"Koteyli",
    "wof:placetype":"locality"
},
  "geometry": {"coordinates":[27.93538,39.73132],"type":"Point"}
}