{
  "type": "Feature",
  "properties": {
    "gn:admin1_code":"52.0",
    "gn:asciiname":"Yaylali",
    "gn:country_code":"TR",
    "gn:dem":303,
    "gn:feature_class":"P",
    "gn:feature_code":"PPL",
    "gn:name":"Yaylal\u0131",
    "gn:population":0,
    "gn:timezone":"Europe/Istanbul",
    "iso:country":"TR",
    "wof:name":"Yaylali",
    "wof:placetype":"locality"
},
  "geometry": {"coordinates":[37.30495,41.04493],"type":"Point"}
}