{
  "type": "Feature",
  "properties": {
    "gn:admin1_code":"71",
    "gn:asciiname":"Konakkale",
    "gn:country_code":"TR",
    "gn:dem":1476,
    "gn:feature_class":"P",
    "gn:feature_code":"PPL",
    "gn:name":"Konakkale",
    "gn:population":0,
    "gn:timezone":"Europe/Istanbul",
    "iso:country":"TR",
    "name:und_x_variant":[
        "Be\u011fri",
        "Konakkale"
    ],
    "wof:name":"Konakkale",
    "wof:placetype":"locality"
},
  "geometry": {"coordinates":[31.68417,38.01878],"type":"Point"}
}