{
  "type": "Feature",
  "properties": {
    "gn:admin1_code":"60.0",
    "gn:asciiname":"Durudere",
    "gn:country_code":"TR",
    "gn:dem":1087,
    "gn:feature_class":"P",
    "gn:feature_code":"PPL",
    "gn:name":"Durudere",
    "gn:population":0,
    "gn:timezone":"Europe/Istanbul",
    "iso:country":"TR",
    "name:und_x_variant":[
        "Filtise",
        "Durudere"
    ],
    "wof:name":"Durudere",
    "wof:placetype":"locality"
},
  "geometry": {"coordinates":[37.14087,40.35421],"type":"Point"}
}