{
  "type": "Feature",
  "properties": {
    "gn:admin1_code":"69.0",
    "gn:asciiname":"Yukari Yuvali",
    "gn:country_code":"TR",
    "gn:dem":1995,
    "gn:feature_class":"P",
    "gn:feature_code":"PPL",
    "gn:name":"Yukar\u0131 Yuval\u0131",
    "gn:population":0,
    "gn:timezone":"Europe/Istanbul",
    "iso:country":"TR",
    "name:tur_x_preferred":[
        "Yukar\u0131 Yuval\u0131"
    ],
    "name:und_x_variant":[
        "Yukar\u0131yuval\u0131"
    ],
    "wof:name":"Yukari Yuvali",
    "wof:placetype":"locality"
},
  "geometry": {"coordinates":[39.87738,40.52668],"type":"Point"}
}