{
  "type": "Feature",
  "properties": {
    "gn:admin1_code":"63",
    "gn:asciiname":"Kyuchyuk-Naneli",
    "gn:country_code":"TR",
    "gn:dem":512,
    "gn:feature_class":"P",
    "gn:feature_code":"PPL",
    "gn:name":"Kyuchyuk-Naneli",
    "gn:population":0,
    "gn:timezone":"Europe/Istanbul",
    "iso:country":"TR",
    "name:und_x_variant":[
        "Nanelisa\u011fir",
        "Kyuchyuk-Naneli",
        "K\u00fc\u00e7\u00fck Naneli"
    ],
    "wof:name":"Kyuchyuk-Naneli",
    "wof:placetype":"locality"
},
  "geometry": {"coordinates":[38.59472,36.84611],"type":"Point"}
}