{
  "type": "Feature",
  "properties": {
    "gn:admin1_code":"71",
    "gn:asciiname":"Tepearasi",
    "gn:country_code":"TR",
    "gn:dem":1499,
    "gn:feature_class":"P",
    "gn:feature_code":"PPL",
    "gn:name":"Tepearas\u0131",
    "gn:population":0,
    "gn:timezone":"Europe/Istanbul",
    "iso:country":"TR",
    "name:und_x_variant":[
        "Kurdular",
        "Tepearas\u0131"
    ],
    "wof:name":"Tepearasi",
    "wof:placetype":"locality"
},
  "geometry": {"coordinates":[31.6618,37.49571],"type":"Point"}
}