{
  "type": "Feature",
  "properties": {
    "gn:country":"TR",
    "gn:fcode":"PPL",
    "gn:population":1119,
    "iso:country":"TR",
    "name:tur_x_preferred":[
        "Akdiken"
    ],
    "qs:name":"Akdiken",
    "qs:photos_9r":0,
    "qs:photos_sr":0,
    "qs:pop_sr":"3",
    "wof:name":"Akdiken",
    "wof:placetype":"locality",
    "wof:population":1119
},
  "geometry": {"coordinates":[39.30861,36.725],"type":"Point"}
}