{
  "type": "Feature",
  "properties": {
    "gn:admin1_code":"59.0",
    "gn:asciiname":"Husunlu",
    "gn:country_code":"TR",
    "gn:dem":133,
    "gn:feature_class":"P",
    "gn:feature_code":"PPL",
    "gn:name":"H\u00fcs\u00fcnl\u00fc",
    "gn:population":0,
    "gn:timezone":"Europe/Istanbul",
    "iso:country":"TR",
    "wof:name":"Husunlu",
    "wof:placetype":"locality"
},
  "geometry": {"coordinates":[27.6222,41.04642],"type":"Point"}
}