{
  "type": "Feature",
  "properties": {
    "gn:admin1_code":"09",
    "gn:asciiname":"Bulayli",
    "gn:country_code":"TR",
    "gn:dem":226,
    "gn:feature_class":"P",
    "gn:feature_code":"PPL",
    "gn:name":"Bulayl\u0131",
    "gn:population":0,
    "gn:timezone":"Europe/Istanbul",
    "iso:country":"TR",
    "name:tur_x_preferred":[
        "Bulayl\u0131"
    ],
    "wof:name":"Bulayli",
    "wof:placetype":"locality"
},
  "geometry": {"coordinates":[28.44837,37.60785],"type":"Point"}
}