{
  "type": "Feature",
  "properties": {
    "gn:admin1_code":"58.0",
    "gn:asciiname":"Cakirli",
    "gn:country_code":"TR",
    "gn:dem":1324,
    "gn:feature_class":"P",
    "gn:feature_code":"PPL",
    "gn:name":"\u00c7ak\u0131rl\u0131",
    "gn:population":0,
    "gn:timezone":"Europe/Istanbul",
    "iso:country":"TR",
    "name:und_x_variant":[
        "\u00c7ak\u0131r",
        "\u00c7ak\u0131rl\u0131"
    ],
    "wof:name":"Cakirli",
    "wof:placetype":"locality"
},
  "geometry": {"coordinates":[38.20015,40.20267],"type":"Point"}
}