{
  "type": "Feature",
  "properties": {
    "gn:admin1_code":"65",
    "gn:asciiname":"Cancakpur",
    "gn:country_code":"TR",
    "gn:dem":1816,
    "gn:feature_class":"P",
    "gn:feature_code":"PPL",
    "gn:name":"Cancakpur",
    "gn:population":0,
    "gn:timezone":"Europe/Istanbul",
    "iso:country":"TR",
    "wof:name":"Cancakpur",
    "wof:placetype":"locality"
},
  "geometry": {"coordinates":[43.23333,39.01667],"type":"Point"}
}