{
  "type": "Feature",
  "properties": {
    "gn:admin1_code":"63",
    "gn:asciiname":"Saluca",
    "gn:country_code":"TR",
    "gn:dem":691,
    "gn:feature_class":"P",
    "gn:feature_code":"PPL",
    "gn:name":"Saluca",
    "gn:population":0,
    "gn:timezone":"Europe/Istanbul",
    "iso:country":"TR",
    "name:tur_x_preferred":[
        "Saluca"
    ],
    "wof:name":"Saluca",
    "wof:placetype":"locality"
},
  "geometry": {"coordinates":[39.21667,37.53333],"type":"Point"}
}