{
  "type": "Feature",
  "properties": {
    "iso:country":"TR",
    "name:tur_x_preferred":[
        "G\u00fczelyurt"
    ],
    "wof:name":"Guzelyurt",
    "wof:placetype":"neighbourhood"
},
  "geometry": {"coordinates":[28.66630254775756,41.01012866013847],"type":"Point"}
}