{
  "type": "Feature",
  "properties": {
    "gn:admin1_code":"58",
    "gn:asciiname":"Karanlik",
    "gn:country_code":"TR",
    "gn:dem":1502,
    "gn:feature_class":"P",
    "gn:feature_code":"PPL",
    "gn:name":"Karanl\u0131k",
    "gn:population":0,
    "gn:timezone":"Europe/Istanbul",
    "iso:country":"TR",
    "name:und_x_variant":[
        "Karanl\u0131k K\u00f6y\u00fc",
        "Karanl\u0131k"
    ],
    "wof:name":"Karanlik",
    "wof:placetype":"locality"
},
  "geometry": {"coordinates":[37.45052,39.28118],"type":"Point"}
}