{
  "type": "Feature",
  "properties": {
    "gn:admin1_code":"69.0",
    "gn:asciiname":"Asagi Karadere",
    "gn:country_code":"TR",
    "gn:dem":1000,
    "gn:feature_class":"P",
    "gn:feature_code":"PPL",
    "gn:name":"A\u015fa\u011f\u0131 Karadere",
    "gn:population":0,
    "gn:timezone":"Europe/Istanbul",
    "iso:country":"TR",
    "name:tur_x_preferred":[
        "A\u015fa\u011f\u0131 Karadere"
    ],
    "name:und_x_variant":[
        "A\u015fa\u011f\u0131karadere"
    ],
    "wof:name":"Asagi Karadere",
    "wof:placetype":"locality"
},
  "geometry": {"coordinates":[39.16814,40.63325],"type":"Point"}
}