{
  "type": "Feature",
  "properties": {
    "gn:admin1_code":"53.0",
    "gn:asciiname":"Erdemli",
    "gn:country_code":"TR",
    "gn:dem":232,
    "gn:feature_class":"P",
    "gn:feature_code":"PPL",
    "gn:name":"Erdemli",
    "gn:population":0,
    "gn:timezone":"Europe/Istanbul",
    "iso:country":"TR",
    "name:ara_x_preferred":[
        "\u0625\u064a\u0631\u062f\u064a\u0645\u0644\u064a"
    ],
    "name:azb_x_preferred":[
        "\u0627\u0631\u062f\u0645\u0644\u06cc"
    ],
    "name:ceb_x_preferred":[
        "Erdemli \u0130l\u00e7esi"
    ],
    "name:deu_x_preferred":[
        "Erdemli"
    ],
    "name:ell_x_preferred":[
        "\u0395\u03c1\u03bd\u03c4\u03b5\u03bc\u03bb\u03af"
    ],
    "name:epo_x_preferred":[
        "Erdemli"
    ],
    "name:fas_x_preferred":[
        "\u0627\u0631\u062f\u0645\u0644\u06cc"
    ],
    "name:fra_x_preferred":[
        "Erdemli"
    ],
    "name:min_x_preferred":[
        "Erdemli"
    ],
    "name:mrj_x_preferred":[
        "\u042d\u0440\u0434\u0435\u043c\u043b\u0438"
    ],
    "name:msa_x_preferred":[
        "Erdemli"
    ],
    "name:nno_x_preferred":[
        "Erdemli"
    ],
    "name:nor_x_preferred":[
        "Erdemli"
    ],
    "name:pnb_x_preferred":[
        "\u0636\u0644\u0639 \u0627\u0631\u062f\u06cc\u0645\u0644\u06cc"
    ],
    "name:pol_x_preferred":[
        "Erdemli"
    ],
    "name:ron_x_preferred":[
        "Erdemli"
    ],
    "name:rus_x_preferred":[
        "\u042d\u0440\u0434\u0435\u043c\u043b\u0438"
    ],
    "name:swa_x_preferred":[
        "Erdemli"
    ],
    "name:tur_x_preferred":[
        "Erdemli"
    ],
    "name:urd_x_preferred":[
        "\u0627\u0631\u062f\u06cc\u0645\u0644\u06cc"
    ],
    "name:vie_x_preferred":[
        "Erdemli"
    ],
    "name:zho_x_preferred":[
        "\u57c3\u723e\u4ee3\u59c6\u5229"
    ],
    "wof:name":"Erdemli",
    "wof:placetype":"locality"
},
  "geometry": {"coordinates":[40.78843,41.06577],"type":"Point"}
}