{
  "type": "Feature",
  "properties": {
    "gn:admin1_code":"53.0",
    "gn:asciiname":"Erdemli",
    "gn:country_code":"TR",
    "gn:dem":232,
    "gn:feature_class":"P",
    "gn:feature_code":"PPL",
    "gn:name":"Erdemli",
    "gn:population":0,
    "gn:timezone":"Europe/Istanbul",
    "iso:country":"TR",
    "wof:name":"Erdemli",
    "wof:placetype":"locality"
},
  "geometry": {"coordinates":[40.78843,41.06577],"type":"Point"}
}