{
  "type": "Feature",
  "properties": {
    "gn:admin1_code":"66",
    "gn:asciiname":"Caglayan",
    "gn:country_code":"TR",
    "gn:dem":1306,
    "gn:feature_class":"P",
    "gn:feature_code":"PPL",
    "gn:name":"\u00c7a\u011flayan",
    "gn:population":0,
    "gn:timezone":"Europe/Istanbul",
    "iso:country":"TR",
    "wof:name":"Caglayan",
    "wof:placetype":"locality"
},
  "geometry": {"coordinates":[34.99529,39.73137],"type":"Point"}
}