{
  "type": "Feature",
  "properties": {
    "gn:admin1_code":"52.0",
    "gn:asciiname":"Dizdar",
    "gn:country_code":"TR",
    "gn:dem":544,
    "gn:feature_class":"P",
    "gn:feature_code":"PPL",
    "gn:name":"Dizdar",
    "gn:population":0,
    "gn:timezone":"Europe/Istanbul",
    "iso:country":"TR",
    "name:fra_x_preferred":[
        "Disdar"
    ],
    "name:hrv_x_preferred":[
        "Dizdar"
    ],
    "name:rus_x_preferred":[
        "\u0414\u0438\u0437\u0434\u0430\u0440"
    ],
    "name:srp_x_preferred":[
        "\u0414\u0438\u0437\u0434\u0430\u0440"
    ],
    "wof:name":"Dizdar",
    "wof:placetype":"locality"
},
  "geometry": {"coordinates":[37.15662,40.98146],"type":"Point"}
}