{
  "type": "Feature",
  "properties": {
    "gn:admin1_code":"88.0",
    "gn:asciiname":"Incesu",
    "gn:country_code":"TR",
    "gn:dem":1144,
    "gn:feature_class":"P",
    "gn:feature_code":"PPL",
    "gn:name":"\u0130ncesu",
    "gn:population":0,
    "gn:timezone":"Europe/Istanbul",
    "iso:country":"TR",
    "name:tur_x_preferred":[
        "\u0130ncesu"
    ],
    "wof:name":"Incesu",
    "wof:placetype":"locality"
},
  "geometry": {"coordinates":[43.40434000000001,40.10763],"type":"Point"}
}