{
  "type": "Feature",
  "properties": {
    "gn:admin1_code":"83",
    "gn:asciiname":"Yeni Sarkaya",
    "gn:country_code":"TR",
    "gn:dem":1015,
    "gn:feature_class":"P",
    "gn:feature_code":"PPL",
    "gn:name":"Yeni \u015earkaya",
    "gn:population":0,
    "gn:timezone":"Europe/Istanbul",
    "iso:country":"TR",
    "name:tur_x_preferred":[
        "Yeni \u015earkaya"
    ],
    "name:und_x_variant":[
        "Yeni\u015farkaya",
        "\u015e\u00f6hme"
    ],
    "wof:name":"Yeni Sarkaya",
    "wof:placetype":"locality"
},
  "geometry": {"coordinates":[37.15529,37.19604],"type":"Point"}
}