{
  "type": "Feature",
  "properties": {
    "gn:admin1_code":"31",
    "gn:asciiname":"Kusalani",
    "gn:country_code":"TR",
    "gn:dem":33,
    "gn:feature_class":"P",
    "gn:feature_code":"PPL",
    "gn:name":"Ku\u015falan\u0131",
    "gn:population":0,
    "gn:timezone":"Europe/Istanbul",
    "iso:country":"TR",
    "name:ceb_x_preferred":[
        "Ku\u015falan\u0131"
    ],
    "name:tur_x_preferred":[
        "Ku\u015falan\u0131"
    ],
    "name:vie_x_preferred":[
        "Ku\u015falan\u0131"
    ],
    "wof:name":"Kusalani",
    "wof:placetype":"locality"
},
  "geometry": {"coordinates":[36.00976,36.09639],"type":"Point"}
}