{
  "type": "Feature",
  "properties": {
    "gn:admin1_code":"14",
    "gn:asciiname":"Yaylacilar",
    "gn:country_code":"TR",
    "gn:dem":941,
    "gn:feature_class":"P",
    "gn:feature_code":"PPL",
    "gn:name":"Yaylac\u0131lar",
    "gn:population":0,
    "gn:timezone":"Europe/Istanbul",
    "iso:country":"TR",
    "wof:name":"Yaylacilar",
    "wof:placetype":"locality"
},
  "geometry": {"coordinates":[31.12877000000001,40.45387],"type":"Point"}
}