{
  "type": "Feature",
  "properties": {
    "gn:admin1_code":"78",
    "gn:asciiname":"Huyukburun",
    "gn:country_code":"TR",
    "gn:dem":1126,
    "gn:feature_class":"P",
    "gn:feature_code":"PPL",
    "gn:name":"H\u00fcy\u00fckburun",
    "gn:population":0,
    "gn:timezone":"Europe/Istanbul",
    "iso:country":"TR",
    "name:und_x_variant":[
        "H\u00fcy\u00fckburun",
        "H\u00fcy\u00fckburunk\u00f6y",
        "H\u00fcy\u00fckburnu",
        "H\u00f6y\u00fckburun"
    ],
    "wof:name":"Huyukburun",
    "wof:placetype":"locality"
},
  "geometry": {"coordinates":[33.64366,37.36366],"type":"Point"}
}