{
  "type": "Feature",
  "properties": {
    "gn:admin1_code":"54",
    "gn:asciiname":"Sabirli",
    "gn:country_code":"TR",
    "gn:dem":129,
    "gn:feature_class":"P",
    "gn:feature_code":"PPL",
    "gn:name":"Sab\u0131rl\u0131",
    "gn:population":0,
    "gn:timezone":"Europe/Istanbul",
    "iso:country":"TR",
    "name:tur_x_preferred":[
        "Sab\u0131rl\u0131"
    ],
    "wof:name":"Sabirli",
    "wof:placetype":"locality"
},
  "geometry": {"coordinates":[30.30721,40.96939],"type":"Point"}
}