{
  "type": "Feature",
  "properties": {
    "iso:country":"TR",
    "name:tur_x_preferred":[
        "\u0130mrahor"
    ],
    "wof:name":"Imrahor",
    "wof:placetype":"neighbourhood"
},
  "geometry": {"coordinates":[28.92811079507731,40.99646985962849],"type":"Point"}
}