{
  "type": "Feature",
  "properties": {
    "gn:admin1_code":"03",
    "gn:asciiname":"Beltarla",
    "gn:country_code":"TR",
    "gn:dem":1047,
    "gn:feature_class":"P",
    "gn:feature_code":"PPL",
    "gn:name":"Beltarla",
    "gn:population":0,
    "gn:timezone":"Europe/Istanbul",
    "iso:country":"TR",
    "name:und_x_variant":[
        "A\u015fa\u011f\u0131belatarla",
        "Beltarla"
    ],
    "wof:name":"Beltarla",
    "wof:placetype":"locality"
},
  "geometry": {"coordinates":[30.09755,37.89578],"type":"Point"}
}