{
  "type": "Feature",
  "properties": {
    "gn:admin1_code":"09",
    "gn:asciiname":"Umurlu",
    "gn:country_code":"TR",
    "gn:dem":52,
    "gn:feature_class":"P",
    "gn:feature_code":"PPLA3",
    "gn:name":"Umurlu",
    "gn:population":0,
    "gn:timezone":"Europe/Istanbul",
    "iso:country":"TR",
    "name:ceb_x_preferred":[
        "Umurlu"
    ],
    "name:fas_x_preferred":[
        "\u0627\u0648\u0645\u0648\u0631\u0644\u0648"
    ],
    "name:nno_x_preferred":[
        "Umurlu"
    ],
    "name:urd_x_preferred":[
        "\u0627\u0648\u0631\u0645\u0648\u0631\u0644\u0648"
    ],
    "name:vie_x_preferred":[
        "Umurlu"
    ],
    "name:zho_x_preferred":[
        "\u70cf\u7a46\u723e\u76e7"
    ],
    "wof:name":"Umurlu",
    "wof:placetype":"locality"
},
  "geometry": {"coordinates":[27.96275,37.85003],"type":"Point"}
}