{
  "type": "Feature",
  "properties": {
    "gn:admin1_code":"09",
    "gn:asciiname":"Umurlu",
    "gn:country_code":"TR",
    "gn:dem":52,
    "gn:feature_class":"P",
    "gn:feature_code":"PPLA3",
    "gn:name":"Umurlu",
    "gn:population":0,
    "gn:timezone":"Europe/Istanbul",
    "iso:country":"TR",
    "wof:name":"Umurlu",
    "wof:placetype":"locality"
},
  "geometry": {"coordinates":[27.96275,37.85003],"type":"Point"}
}