{
  "type": "Feature",
  "properties": {
    "gn:admin1_code":"45",
    "gn:asciiname":"Ebekaya",
    "gn:country_code":"TR",
    "gn:dem":145,
    "gn:feature_class":"P",
    "gn:feature_code":"PPL",
    "gn:name":"Ebekaya",
    "gn:population":0,
    "gn:timezone":"Europe/Istanbul",
    "iso:country":"TR",
    "name:tur_x_preferred":[
        "Ebekaya"
    ],
    "wof:name":"Ebekaya",
    "wof:placetype":"locality"
},
  "geometry": {"coordinates":[27.8708,38.88538],"type":"Point"}
}