{
  "type": "Feature",
  "properties": {
    "gn:admin1_code":"44",
    "gn:asciiname":"Kisla",
    "gn:country_code":"TR",
    "gn:dem":1005,
    "gn:feature_class":"P",
    "gn:feature_code":"PPL",
    "gn:name":"K\u0131\u015fla",
    "gn:population":0,
    "gn:timezone":"Europe/Istanbul",
    "iso:country":"TR",
    "name:und_x_variant":[
        "K\u0131\u015fla K\u00f6y\u00fc",
        "K\u0131\u015fla"
    ],
    "wof:name":"Kisla",
    "wof:placetype":"locality"
},
  "geometry": {"coordinates":[38.17813,38.73745],"type":"Point"}
}