{
  "type": "Feature",
  "properties": {
    "gn:admin1_code":"02",
    "gn:asciiname":"Tasburun",
    "gn:country_code":"TR",
    "gn:dem":728,
    "gn:feature_class":"P",
    "gn:feature_code":"PPL",
    "gn:name":"Ta\u015fburun",
    "gn:population":0,
    "gn:timezone":"Europe/Istanbul",
    "iso:country":"TR",
    "name:und_x_variant":[
        "Hu\u015ftir",
        "Hi\u015ftur",
        "Ta\u015fburun"
    ],
    "wof:name":"Tasburun",
    "wof:placetype":"locality"
},
  "geometry": {"coordinates":[38.73672,37.85798],"type":"Point"}
}