{
  "type": "Feature",
  "properties": {
    "gn:admin1_code":"32",
    "gn:asciiname":"Gokcetas",
    "gn:country_code":"TR",
    "gn:dem":1693,
    "gn:feature_class":"P",
    "gn:feature_code":"PPL",
    "gn:name":"G\u00f6k\u00e7eta\u015f",
    "gn:population":0,
    "gn:timezone":"Europe/Istanbul",
    "iso:country":"TR",
    "wof:name":"Gokcetas",
    "wof:placetype":"locality"
},
  "geometry": {"coordinates":[33.23333,36.91667],"type":"Point"}
}