{
  "type": "Feature",
  "properties": {
    "gn:admin1_code":"34",
    "gn:asciiname":"Cengili",
    "gn:country_code":"TR",
    "gn:dem":117,
    "gn:feature_class":"P",
    "gn:feature_code":"PPL",
    "gn:name":"\u00c7engili",
    "gn:population":0,
    "gn:timezone":"Europe/Istanbul",
    "iso:country":"TR",
    "name:tur_x_preferred":[
        "\u00c7engili"
    ],
    "wof:name":"Cengili",
    "wof:placetype":"locality"
},
  "geometry": {"coordinates":[29.66312000000001,40.99773],"type":"Point"}
}