{
  "type": "Feature",
  "properties": {
    "gn:admin1_code":"65",
    "gn:asciiname":"Tuygun",
    "gn:country_code":"TR",
    "gn:dem":2412,
    "gn:feature_class":"P",
    "gn:feature_code":"PPL",
    "gn:name":"T\u00fcyg\u00fcn",
    "gn:population":0,
    "gn:timezone":"Europe/Istanbul",
    "iso:country":"TR",
    "wof:name":"Tuygun",
    "wof:placetype":"locality"
},
  "geometry": {"coordinates":[43.94528,38.32333],"type":"Point"}
}