{
  "type": "Feature",
  "properties": {
    "gn:admin1_code":"83",
    "gn:asciiname":"Ulkerli",
    "gn:country_code":"TR",
    "gn:dem":1072,
    "gn:feature_class":"P",
    "gn:feature_code":"PPL",
    "gn:name":"\u00dclkerli",
    "gn:population":0,
    "gn:timezone":"Europe/Istanbul",
    "iso:country":"TR",
    "name:und_x_variant":[
        "G\u00fccege",
        "G\u00fccegi",
        "K\u00f6\u00e7ke",
        "\u00dclkerli"
    ],
    "wof:name":"Ulkerli",
    "wof:placetype":"locality"
},
  "geometry": {"coordinates":[37.24007,37.2211],"type":"Point"}
}