{
  "type": "Feature",
  "properties": {
    "gn:admin1_code":"59",
    "gn:asciiname":"Kuyucu",
    "gn:country_code":"TR",
    "gn:dem":192,
    "gn:feature_class":"P",
    "gn:feature_code":"PPL",
    "gn:name":"Kuyucu",
    "gn:population":0,
    "gn:timezone":"Europe/Istanbul",
    "iso:country":"TR",
    "name:tur_x_preferred":[
        "Kuyucu"
    ],
    "wof:name":"Kuyucu",
    "wof:placetype":"locality"
},
  "geometry": {"coordinates":[27.02689,40.88163],"type":"Point"}
}