{
  "type": "Feature",
  "properties": {
    "gn:admin1_code":"54",
    "gn:asciiname":"Saribeyli",
    "gn:country_code":"TR",
    "gn:dem":147,
    "gn:feature_class":"P",
    "gn:feature_code":"PPL",
    "gn:name":"Sar\u0131beyli",
    "gn:population":0,
    "gn:timezone":"Europe/Istanbul",
    "iso:country":"TR",
    "name:tur_x_preferred":[
        "Sar\u0131beyli"
    ],
    "wof:name":"Saribeyli",
    "wof:placetype":"locality"
},
  "geometry": {"coordinates":[30.34567,41.01198],"type":"Point"}
}