{
  "type": "Feature",
  "properties": {
    "gn:admin1_code":"03",
    "gn:asciiname":"Alacami",
    "gn:country_code":"TR",
    "gn:dem":1021,
    "gn:feature_class":"P",
    "gn:feature_code":"PPL",
    "gn:name":"Alacami",
    "gn:population":0,
    "gn:timezone":"Europe/Istanbul",
    "iso:country":"TR",
    "wof:name":"Alacami",
    "wof:placetype":"locality"
},
  "geometry": {"coordinates":[30.07763,38.51693],"type":"Point"}
}