{
  "type": "Feature",
  "properties": {
    "gn:admin1_code":"24",
    "gn:asciiname":"Apcaga",
    "gn:country_code":"TR",
    "gn:dem":1071,
    "gn:feature_class":"P",
    "gn:feature_code":"PPL",
    "gn:name":"Ap\u00e7a\u011fa",
    "gn:population":0,
    "gn:timezone":"Europe/Istanbul",
    "iso:country":"TR",
    "name:tur_x_preferred":[
        "Ap\u00e7a\u011fa"
    ],
    "wof:name":"Apcaga",
    "wof:placetype":"locality"
},
  "geometry": {"coordinates":[38.50327,39.24105],"type":"Point"}
}