{
  "type": "Feature",
  "properties": {
    "gn:admin1_code":"38",
    "gn:asciiname":"Golcuk",
    "gn:country_code":"TR",
    "gn:dem":1773,
    "gn:feature_class":"P",
    "gn:feature_code":"PPL",
    "gn:name":"G\u00f6lc\u00fck",
    "gn:population":0,
    "gn:timezone":"Europe/Istanbul",
    "iso:country":"TR",
    "wof:name":"Golcuk",
    "wof:placetype":"locality"
},
  "geometry": {"coordinates":[36.42613,38.60436],"type":"Point"}
}