{
  "type": "Feature",
  "properties": {
    "gn:admin1_code":"26",
    "gn:asciiname":"Asagi Kartal",
    "gn:country_code":"TR",
    "gn:dem":939,
    "gn:feature_class":"P",
    "gn:feature_code":"PPL",
    "gn:name":"A\u015fa\u011f\u0131 Kartal",
    "gn:population":0,
    "gn:timezone":"Europe/Istanbul",
    "iso:country":"TR",
    "wof:name":"Asagi Kartal",
    "wof:placetype":"locality"
},
  "geometry": {"coordinates":[30.29489,39.72445],"type":"Point"}
}