{
  "type": "Feature",
  "properties": {
    "gn:admin1_code":"89",
    "gn:asciiname":"Sariahmet",
    "gn:country_code":"TR",
    "gn:dem":968,
    "gn:feature_class":"P",
    "gn:feature_code":"PPL",
    "gn:name":"Sar\u0131ahmet",
    "gn:population":0,
    "gn:timezone":"Europe/Istanbul",
    "iso:country":"TR",
    "wof:name":"Sariahmet",
    "wof:placetype":"locality"
},
  "geometry": {"coordinates":[32.55221,40.92333],"type":"Point"}
}