{
  "type": "Feature",
  "properties": {
    "gn:admin1_code":"2.0",
    "gn:asciiname":"Yolduzu",
    "gn:country_code":"TR",
    "gn:dem":606,
    "gn:feature_class":"P",
    "gn:feature_code":"PPL",
    "gn:name":"Yold\u00fcz\u00fc",
    "gn:population":0,
    "gn:timezone":"Europe/Istanbul",
    "iso:country":"TR",
    "wof:name":"Yolduzu",
    "wof:placetype":"locality"
},
  "geometry": {"coordinates":[37.90664,37.5853],"type":"Point"}
}