{
  "type": "Feature",
  "properties": {
    "gn:admin1_code":"60",
    "gn:asciiname":"Cime",
    "gn:country_code":"TR",
    "gn:dem":1112,
    "gn:feature_class":"P",
    "gn:feature_code":"PPL",
    "gn:name":"\u00c7ime",
    "gn:population":0,
    "gn:timezone":"Europe/Istanbul",
    "iso:country":"TR",
    "wof:name":"Cime",
    "wof:placetype":"locality"
},
  "geometry": {"coordinates":[36.08626,39.95432],"type":"Point"}
}