{
  "type": "Feature",
  "properties": {
    "gn:admin1_code":"48",
    "gn:asciiname":"Toplar",
    "gn:country_code":"TR",
    "gn:dem":161,
    "gn:feature_class":"P",
    "gn:feature_code":"PPL",
    "gn:name":"Toplar",
    "gn:population":0,
    "gn:timezone":"Europe/Istanbul",
    "iso:country":"TR",
    "name:aze_x_preferred":[
        "Toplar"
    ],
    "name:ita_x_preferred":[
        "Toplar"
    ],
    "name:kat_x_preferred":[
        "\u10d7\u10dd\u10e4\u10da\u10d0\u10e0\u10d8"
    ],
    "name:msa_x_preferred":[
        "Toplar"
    ],
    "name:tur_x_preferred":[
        "Toplar"
    ],
    "wof:name":"Toplar",
    "wof:placetype":"locality"
},
  "geometry": {"coordinates":[29.37394,36.66874],"type":"Point"}
}