{
  "type": "Feature",
  "properties": {
    "gn:admin1_code":"14",
    "gn:asciiname":"Tazilar",
    "gn:country_code":"TR",
    "gn:dem":1122,
    "gn:feature_class":"P",
    "gn:feature_code":"PPL",
    "gn:name":"Taz\u0131lar",
    "gn:population":0,
    "gn:timezone":"Europe/Istanbul",
    "iso:country":"TR",
    "wof:name":"Tazilar",
    "wof:placetype":"locality"
},
  "geometry": {"coordinates":[31.71139,40.39189],"type":"Point"}
}