{
  "type": "Feature",
  "properties": {
    "gn:admin1_code":"65.0",
    "gn:asciiname":"Gecerli",
    "gn:country_code":"TR",
    "gn:dem":1886,
    "gn:feature_class":"P",
    "gn:feature_code":"PPL",
    "gn:name":"Ge\u00e7erli",
    "gn:population":0,
    "gn:timezone":"Europe/Istanbul",
    "iso:country":"TR",
    "name:tur_x_preferred":[
        "Ge\u00e7erli"
    ],
    "wof:name":"Gecerli",
    "wof:placetype":"locality"
},
  "geometry": {"coordinates":[43.38197,38.02896],"type":"Point"}
}