{
  "type": "Feature",
  "properties": {
    "gn:admin1_code":"32",
    "gn:asciiname":"Belcinar",
    "gn:country_code":"TR",
    "gn:dem":1177,
    "gn:feature_class":"P",
    "gn:feature_code":"PPL",
    "gn:name":"Bel\u00e7\u0131nar",
    "gn:population":0,
    "gn:timezone":"Europe/Istanbul",
    "iso:country":"TR",
    "name:tur_x_preferred":[
        "Bel\u00e7\u0131nar"
    ],
    "name:und_x_variant":[
        "F\u0131nd\u0131kp\u0131naryaylas\u0131k\u00f6y",
        "F\u0131nd\u0131kp\u0131naryayla"
    ],
    "wof:name":"Belcinar",
    "wof:placetype":"locality"
},
  "geometry": {"coordinates":[34.6623,37.16327],"type":"Point"}
}