{
  "type": "Feature",
  "properties": {
    "gn:admin1_code":"65.0",
    "gn:asciiname":"Dogangun",
    "gn:country_code":"TR",
    "gn:dem":2039,
    "gn:feature_class":"P",
    "gn:feature_code":"PPL",
    "gn:name":"Do\u011fang\u00fcn",
    "gn:population":0,
    "gn:timezone":"Europe/Istanbul",
    "iso:country":"TR",
    "name:tur_x_preferred":[
        "Do\u011fang\u00fcn"
    ],
    "wof:name":"Dogangun",
    "wof:placetype":"locality"
},
  "geometry": {"coordinates":[43.71703,38.7667],"type":"Point"}
}