{
  "type": "Feature",
  "properties": {
    "gn:admin1_code":"25.0",
    "gn:asciiname":"Karakale",
    "gn:country_code":"TR",
    "gn:dem":1282,
    "gn:feature_class":"P",
    "gn:feature_code":"PPL",
    "gn:name":"Karakale",
    "gn:population":0,
    "gn:timezone":"Europe/Istanbul",
    "iso:country":"TR",
    "name:tur_x_preferred":[
        "Karakale"
    ],
    "wof:name":"Karakale",
    "wof:placetype":"locality"
},
  "geometry": {"coordinates":[41.26861,40.70486],"type":"Point"}
}