{
  "type": "Feature",
  "properties": {
    "gn:admin1_code":"74",
    "gn:asciiname":"Sim",
    "gn:country_code":"TR",
    "gn:dem":1547,
    "gn:feature_class":"P",
    "gn:feature_code":"PPL",
    "gn:name":"Sim",
    "gn:population":0,
    "gn:timezone":"Europe/Istanbul",
    "iso:country":"TR",
    "name:bre_x_preferred":[
        "Sim"
    ],
    "name:cat_x_preferred":[
        "Sim"
    ],
    "name:ceb_x_preferred":[
        "Sim"
    ],
    "name:kat_x_preferred":[
        "\u10e1\u10d8\u10db\u10d8"
    ],
    "name:nld_x_preferred":[
        "Sim"
    ],
    "name:nor_x_preferred":[
        "Sim"
    ],
    "name:por_x_preferred":[
        "Sim"
    ],
    "name:spa_x_preferred":[
        "Sim"
    ],
    "name:swe_x_preferred":[
        "SIM"
    ],
    "name:und_x_variant":[
        "S\u00f6\u011f\u00fct\u00f6n\u00fc",
        "Nuresir",
        "Sim"
    ],
    "name:vie_x_preferred":[
        "Sim"
    ],
    "wof:name":"Sim",
    "wof:placetype":"locality"
},
  "geometry": {"coordinates":[42.75671,37.90686],"type":"Point"}
}