{
  "type": "Feature",
  "properties": {
    "gn:admin1_code":"80",
    "gn:asciiname":"Yamacalti",
    "gn:country_code":"TR",
    "gn:dem":2275,
    "gn:feature_class":"P",
    "gn:feature_code":"PPL",
    "gn:name":"Yama\u00e7alt\u0131",
    "gn:population":0,
    "gn:timezone":"Europe/Istanbul",
    "iso:country":"TR",
    "name:tur_x_preferred":[
        "Yama\u00e7alt\u0131"
    ],
    "wof:name":"Yamacalti",
    "wof:placetype":"locality"
},
  "geometry": {"coordinates":[43.23986,37.61441],"type":"Point"}
}