{
  "type": "Feature",
  "properties": {
    "gn:admin1_code":"60.0",
    "gn:asciiname":"Sulugol",
    "gn:country_code":"TR",
    "gn:dem":680,
    "gn:feature_class":"P",
    "gn:feature_code":"PPL",
    "gn:name":"Sulug\u00f6l",
    "gn:population":0,
    "gn:timezone":"Europe/Istanbul",
    "iso:country":"TR",
    "name:und_x_variant":[
        "Sulug\u00f6l K\u00f6y\u00fc",
        "Sulug\u00f6l"
    ],
    "wof:name":"Sulugol",
    "wof:placetype":"locality"
},
  "geometry": {"coordinates":[36.98878,40.54804],"type":"Point"}
}