{
  "type": "Feature",
  "properties": {
    "gn:admin1_code":"13",
    "gn:asciiname":"Yamackoy",
    "gn:country_code":"TR",
    "gn:dem":1317,
    "gn:feature_class":"P",
    "gn:feature_code":"PPL",
    "gn:name":"Yama\u00e7k\u00f6y",
    "gn:population":0,
    "gn:timezone":"Europe/Istanbul",
    "iso:country":"TR",
    "name:tur_x_preferred":[
        "Yama\u00e7"
    ],
    "name:tur_x_variant":[
        "Yama\u00e7k\u00f6y"
    ],
    "name:und_x_variant":[
        "Kotni"
    ],
    "wof:name":"Yamackoy",
    "wof:placetype":"locality"
},
  "geometry": {"coordinates":[41.98302,38.57942],"type":"Point"}
}