{
  "type": "Feature",
  "properties": {
    "gn:admin1_code":"69.0",
    "gn:asciiname":"Dolek",
    "gn:country_code":"TR",
    "gn:dem":1886,
    "gn:feature_class":"P",
    "gn:feature_code":"PPL",
    "gn:name":"D\u00f6lek",
    "gn:population":0,
    "gn:timezone":"Europe/Istanbul",
    "iso:country":"TR",
    "name:und_x_variant":[
        "D\u00f6lek",
        "D\u00f6lekk\u00f6y\u00fc"
    ],
    "wof:name":"Dolek",
    "wof:placetype":"locality"
},
  "geometry": {"coordinates":[39.7103,40.48277],"type":"Point"}
}