{
  "type": "Feature",
  "properties": {
    "gn:admin1_code":"31.0",
    "gn:asciiname":"Narlica",
    "gn:country_code":"TR",
    "gn:dem":128,
    "gn:feature_class":"P",
    "gn:feature_code":"PPL",
    "gn:name":"Narl\u0131ca",
    "gn:population":0,
    "gn:timezone":"Europe/Istanbul",
    "iso:country":"TR",
    "name:azb_x_preferred":[
        "\u0646\u0627\u0631\u0644\u06cc\u062c\u0627"
    ],
    "name:ceb_x_preferred":[
        "Narl\u0131ca"
    ],
    "name:fas_x_preferred":[
        "\u0646\u0627\u0631\u0644\u06cc\u062c\u0627"
    ],
    "name:nno_x_preferred":[
        "Narl\u0131ca"
    ],
    "name:und_x_variant":[
        "Senpiyer",
        "Narl\u0131ca"
    ],
    "name:urd_x_preferred":[
        "\u0646\u0627\u0631\u0644\u06cc\u062c\u0627"
    ],
    "name:vie_x_preferred":[
        "Narl\u0131ca"
    ],
    "name:zho_x_preferred":[
        "\u7d0d\u723e\u52d2\u8cc8"
    ],
    "wof:name":"Narlica",
    "wof:placetype":"locality"
},
  "geometry": {"coordinates":[36.21458,36.23533],"type":"Point"}
}