{
  "type": "Feature",
  "properties": {
    "gn:admin1_code":"8.0",
    "gn:asciiname":"Kavakkoy",
    "gn:country_code":"TR",
    "gn:dem":54,
    "gn:feature_class":"P",
    "gn:feature_code":"PPL",
    "gn:name":"Kavakk\u00f6y",
    "gn:population":0,
    "gn:timezone":"Europe/Istanbul",
    "iso:country":"TR",
    "name:tur_x_preferred":[
        "Kavakk\u00f6y"
    ],
    "name:und_x_variant":[
        "Kavak",
        "Yakovit"
    ],
    "wof:name":"Kavakkoy",
    "wof:placetype":"locality"
},
  "geometry": {"coordinates":[41.30442,41.31449],"type":"Point"}
}