{
  "type": "Feature",
  "properties": {
    "gn:country":"TR",
    "gn:fcode":"PPL",
    "gn:pop":0,
    "iso:country":"TR",
    "qs:name":"B\u00fcy\u00fckdere",
    "qs:name_adm0":"Turkey",
    "qs:name_adm1":"Eski\u015fehir",
    "qs:photos":12,
    "qs:photos_1k":2,
    "qs:photos_9k":1,
    "qs:photos_9r":1,
    "qs:photos_all":12,
    "qs:photos_sr":1,
    "qs:placetype":"Suburb",
    "qs:pop_sr":"0",
    "wd:wordcount":70,
    "wof:name":"B\u00fcy\u00fckdere",
    "wof:placetype":"neighbourhood",
    "wof:population":0
},
  "geometry": {"coordinates":[30.75212,39.58454],"type":"Point"}
}