{
  "type": "Feature",
  "properties": {
    "gn:admin1_code":"7.0",
    "gn:asciiname":"Ahmediye",
    "gn:country_code":"TR",
    "gn:dem":10,
    "gn:feature_class":"P",
    "gn:feature_code":"PPL",
    "gn:name":"Ahmediye",
    "gn:population":0,
    "gn:timezone":"Europe/Istanbul",
    "iso:country":"TR",
    "wof:name":"Ahmediye",
    "wof:placetype":"locality"
},
  "geometry": {"coordinates":[31.15873,36.86075],"type":"Point"}
}