{
  "type": "Feature",
  "properties": {
    "gn:admin1_code":"66",
    "gn:asciiname":"Karakoc",
    "gn:country_code":"TR",
    "gn:dem":1109,
    "gn:feature_class":"P",
    "gn:feature_code":"PPL",
    "gn:name":"Karako\u00e7",
    "gn:population":0,
    "gn:timezone":"Europe/Istanbul",
    "iso:country":"TR",
    "wof:name":"Karakoc",
    "wof:placetype":"locality"
},
  "geometry": {"coordinates":[35.26667,39.15],"type":"Point"}
}