{
  "type": "Feature",
  "properties": {
    "gn:admin1_code":"21",
    "gn:asciiname":"Kortepe",
    "gn:country_code":"TR",
    "gn:dem":752,
    "gn:feature_class":"P",
    "gn:feature_code":"PPL",
    "gn:name":"K\u00f6rtepe",
    "gn:population":0,
    "gn:timezone":"Europe/Istanbul",
    "iso:country":"TR",
    "name:tur_x_preferred":[
        "K\u00f6rtepe"
    ],
    "wof:name":"Kortepe",
    "wof:placetype":"locality"
},
  "geometry": {"coordinates":[40.09264,37.86837],"type":"Point"}
}