{
  "type": "Feature",
  "properties": {
    "gn:admin1_code":"14.0",
    "gn:asciiname":"Guveytepe",
    "gn:country_code":"TR",
    "gn:dem":1053,
    "gn:feature_class":"P",
    "gn:feature_code":"PPL",
    "gn:name":"G\u00fcveytepe",
    "gn:population":0,
    "gn:timezone":"Europe/Istanbul",
    "iso:country":"TR",
    "name:und_x_variant":[
        "\u00c7erkesler",
        "\u00c7erkezler",
        "G\u00fcveytepe"
    ],
    "wof:name":"Guveytepe",
    "wof:placetype":"locality"
},
  "geometry": {"coordinates":[31.0053,40.49871],"type":"Point"}
}