{
  "type": "Feature",
  "properties": {
    "gn:admin1_code":"83",
    "gn:asciiname":"Koksalan",
    "gn:country_code":"TR",
    "gn:dem":895,
    "gn:feature_class":"P",
    "gn:feature_code":"PPL",
    "gn:name":"K\u00f6ksalan",
    "gn:population":0,
    "gn:timezone":"Europe/Istanbul",
    "iso:country":"TR",
    "name:tur_x_preferred":[
        "K\u00f6ksalan"
    ],
    "wof:name":"Koksalan",
    "wof:placetype":"locality"
},
  "geometry": {"coordinates":[37.23905,37.2783],"type":"Point"}
}