{
  "type": "Feature",
  "properties": {
    "gn:admin1_code":"50",
    "gn:asciiname":"Kisecik",
    "gn:country_code":"TR",
    "gn:dem":1158,
    "gn:feature_class":"P",
    "gn:feature_code":"PPL",
    "gn:name":"Kisecik",
    "gn:population":0,
    "gn:timezone":"Europe/Istanbul",
    "iso:country":"TR",
    "name:ceb_x_preferred":[
        "Kisecik"
    ],
    "name:tur_x_preferred":[
        "Kisecik"
    ],
    "name:und_x_variant":[
        "Kay\u0131kisecik",
        "Kay\u0131kesecik"
    ],
    "name:vie_x_preferred":[
        "Kisecik"
    ],
    "wof:name":"Kisecik",
    "wof:placetype":"locality"
},
  "geometry": {"coordinates":[34.48039,38.93451],"type":"Point"}
}