{
  "type": "Feature",
  "properties": {
    "gn:admin1_code":"55.0",
    "gn:asciiname":"Kusculu",
    "gn:country_code":"TR",
    "gn:dem":12,
    "gn:feature_class":"P",
    "gn:feature_code":"PPL",
    "gn:name":"Ku\u015f\u00e7ulu",
    "gn:population":0,
    "gn:timezone":"Europe/Istanbul",
    "iso:country":"TR",
    "wof:name":"Kusculu",
    "wof:placetype":"locality"
},
  "geometry": {"coordinates":[36.8963,41.20134],"type":"Point"}
}