{
  "type": "Feature",
  "properties": {
    "gn:admin1_code":"65",
    "gn:asciiname":"Gozutok",
    "gn:country_code":"TR",
    "gn:dem":1721,
    "gn:feature_class":"P",
    "gn:feature_code":"PPL",
    "gn:name":"G\u00f6z\u00fctok",
    "gn:population":0,
    "gn:timezone":"Europe/Istanbul",
    "iso:country":"TR",
    "name:und_x_variant":[
        "Papi\u015fkin",
        "Pabu\u015fgin",
        "G\u00f6z\u00fctok"
    ],
    "wof:name":"Gozutok",
    "wof:placetype":"locality"
},
  "geometry": {"coordinates":[43.31583,39.09154],"type":"Point"}
}