{
  "type": "Feature",
  "properties": {
    "gn:admin1_code":"20",
    "gn:asciiname":"Irlaganli",
    "gn:country_code":"TR",
    "gn:dem":313,
    "gn:feature_class":"P",
    "gn:feature_code":"PPL",
    "gn:name":"Irlaganl\u0131",
    "gn:population":0,
    "gn:timezone":"Europe/Istanbul",
    "iso:country":"TR",
    "name:und_x_variant":[
        "Irl\u0131\u011fanl\u0131",
        "Irlaganl\u0131"
    ],
    "wof:name":"Irlaganli",
    "wof:placetype":"locality"
},
  "geometry": {"coordinates":[29.17905,37.87921],"type":"Point"}
}