{
  "type": "Feature",
  "properties": {
    "gn:admin1_code":"20",
    "gn:asciiname":"Kadikoy",
    "gn:country_code":"TR",
    "gn:dem":652,
    "gn:feature_class":"P",
    "gn:feature_code":"PPL",
    "gn:name":"Kad\u0131k\u00f6y",
    "gn:population":0,
    "gn:timezone":"Europe/Istanbul",
    "iso:country":"TR",
    "name:tur_x_preferred":[
        "Kad\u0131k\u00f6y"
    ],
    "wof:name":"Kadikoy",
    "wof:placetype":"locality"
},
  "geometry": {"coordinates":[28.76069,38.1534],"type":"Point"}
}