{
  "type": "Feature",
  "properties": {
    "iso:country":"TR",
    "name:tur_x_preferred":[
        "Gedikpa\u015fa"
    ],
    "wof:name":"Gedikpasa",
    "wof:placetype":"neighbourhood"
},
  "geometry": {"coordinates":[28.96695365513034,41.00660010900835],"type":"Point"}
}