{
  "type": "Feature",
  "properties": {
    "gn:admin1_code":"09",
    "gn:asciiname":"Karakollar",
    "gn:country_code":"TR",
    "gn:dem":66,
    "gn:feature_class":"P",
    "gn:feature_code":"PPL",
    "gn:name":"Karakollar",
    "gn:population":0,
    "gn:timezone":"Europe/Istanbul",
    "iso:country":"TR",
    "name:tur_x_preferred":[
        "Karakollar"
    ],
    "wof:name":"Karakollar",
    "wof:placetype":"locality"
},
  "geometry": {"coordinates":[28.03833,37.6158],"type":"Point"}
}