{
  "type": "Feature",
  "properties": {
    "gn:admin1_code":"70",
    "gn:asciiname":"Seckin",
    "gn:country_code":"TR",
    "gn:dem":1898,
    "gn:feature_class":"P",
    "gn:feature_code":"PPL",
    "gn:name":"Se\u00e7kin",
    "gn:population":0,
    "gn:timezone":"Europe/Istanbul",
    "iso:country":"TR",
    "wof:name":"Seckin",
    "wof:placetype":"locality"
},
  "geometry": {"coordinates":[44.64833,37.33389],"type":"Point"}
}