{
  "type": "Feature",
  "properties": {
    "gn:admin1_code":"09",
    "gn:asciiname":"Nesetiye",
    "gn:country_code":"TR",
    "gn:dem":89,
    "gn:feature_class":"P",
    "gn:feature_code":"PPL",
    "gn:name":"Ne\u015fetiye",
    "gn:population":0,
    "gn:timezone":"Europe/Istanbul",
    "iso:country":"TR",
    "name:tur_x_preferred":[
        "Ne\u015fetiye"
    ],
    "wof:name":"Nesetiye",
    "wof:placetype":"locality"
},
  "geometry": {"coordinates":[27.54461,37.89115],"type":"Point"}
}