{
  "type": "Feature",
  "properties": {
    "gn:admin1_code":"44",
    "gn:asciiname":"Esenbey",
    "gn:country_code":"TR",
    "gn:dem":929,
    "gn:feature_class":"P",
    "gn:feature_code":"PPL",
    "gn:name":"Esenbey",
    "gn:population":0,
    "gn:timezone":"Europe/Istanbul",
    "iso:country":"TR",
    "name:und_x_variant":[
        "Kalolar Mezraas\u0131",
        "Kalolar",
        "Esenbey"
    ],
    "wof:name":"Esenbey",
    "wof:placetype":"locality"
},
  "geometry": {"coordinates":[37.76667,38.48006],"type":"Point"}
}