{
  "type": "Feature",
  "properties": {
    "gn:admin1_code":"21.0",
    "gn:asciiname":"Kelemo",
    "gn:country_code":"TR",
    "gn:dem":594,
    "gn:feature_class":"P",
    "gn:feature_code":"PPL",
    "gn:name":"Kelemo",
    "gn:population":0,
    "gn:timezone":"Europe/Istanbul",
    "iso:country":"TR",
    "name:tur_x_preferred":[
        "Kelemo"
    ],
    "wof:name":"Kelemo",
    "wof:placetype":"locality"
},
  "geometry": {"coordinates":[40.88306,37.94667000000001],"type":"Point"}
}