{
  "type": "Feature",
  "properties": {
    "gn:admin1_code":"45",
    "gn:asciiname":"Tirkes",
    "gn:country_code":"TR",
    "gn:dem":189,
    "gn:feature_class":"P",
    "gn:feature_code":"PPL",
    "gn:name":"T\u0131rke\u015f",
    "gn:population":0,
    "gn:timezone":"Europe/Istanbul",
    "iso:country":"TR",
    "name:tur_x_preferred":[
        "T\u0131rke\u015f"
    ],
    "wof:name":"Tirkes",
    "wof:placetype":"locality"
},
  "geometry": {"coordinates":[27.66504,38.80698],"type":"Point"}
}