{
  "type": "Feature",
  "properties": {
    "gn:admin1_code":"58",
    "gn:asciiname":"Avsarcik",
    "gn:country_code":"TR",
    "gn:dem":1821,
    "gn:feature_class":"P",
    "gn:feature_code":"PPL",
    "gn:name":"Av\u015farc\u0131k",
    "gn:population":0,
    "gn:timezone":"Europe/Istanbul",
    "iso:country":"TR",
    "wof:name":"Avsarcik",
    "wof:placetype":"locality"
},
  "geometry": {"coordinates":[37.85,39.26667],"type":"Point"}
}