{
  "type": "Feature",
  "properties": {
    "gn:admin1_code":"48",
    "gn:asciiname":"Bahtiyar",
    "gn:country_code":"TR",
    "gn:dem":469,
    "gn:feature_class":"P",
    "gn:feature_code":"PPL",
    "gn:name":"Bahtiyar",
    "gn:population":0,
    "gn:timezone":"Europe/Istanbul",
    "iso:country":"TR",
    "name:tur_x_preferred":[
        "Bahtiyar"
    ],
    "wof:name":"Bahtiyar",
    "wof:placetype":"locality"
},
  "geometry": {"coordinates":[28.96067,36.87331],"type":"Point"}
}