{
  "type": "Feature",
  "properties": {
    "gn:admin1_code":"89",
    "gn:asciiname":"Kuzlar",
    "gn:country_code":"TR",
    "gn:dem":422,
    "gn:feature_class":"P",
    "gn:feature_code":"PPL",
    "gn:name":"Kuzlar",
    "gn:population":0,
    "gn:timezone":"Europe/Istanbul",
    "iso:country":"TR",
    "wof:name":"Kuzlar",
    "wof:placetype":"locality"
},
  "geometry": {"coordinates":[32.37238,41.22304000000001],"type":"Point"}
}