{
  "type": "Feature",
  "properties": {
    "gn:admin1_code":"13",
    "gn:asciiname":"Dursun",
    "gn:country_code":"TR",
    "gn:dem":1887,
    "gn:feature_class":"P",
    "gn:feature_code":"PPL",
    "gn:name":"Dursun",
    "gn:population":0,
    "gn:timezone":"Europe/Istanbul",
    "iso:country":"TR",
    "name:tur_x_preferred":[
        "Dursun"
    ],
    "name:und_x_variant":[
        "K\u00f6rcan"
    ],
    "wof:name":"Dursun",
    "wof:placetype":"locality"
},
  "geometry": {"coordinates":[42.06842,38.28051],"type":"Point"}
}