{
  "type": "Feature",
  "properties": {
    "gn:admin1_code":"85.0",
    "gn:asciiname":"Akkaya",
    "gn:country_code":"TR",
    "gn:dem":409,
    "gn:feature_class":"P",
    "gn:feature_code":"PPL",
    "gn:name":"Akkaya",
    "gn:population":0,
    "gn:timezone":"Europe/Istanbul",
    "iso:country":"TR",
    "wof:name":"Akkaya",
    "wof:placetype":"locality"
},
  "geometry": {"coordinates":[31.73521,41.28119],"type":"Point"}
}