{
  "type": "Feature",
  "properties": {
    "iso:country":"TR",
    "name:eng_x_preferred":[
        "Sinanoba"
    ],
    "name:tur_x_preferred":[
        "Sinanoba"
    ],
    "wof:name":"Sinanoba",
    "wof:placetype":"neighbourhood"
},
  "geometry": {"coordinates":[28.53712729660549,40.9928227190203],"type":"Point"}
}