{
  "type": "Feature",
  "properties": {
    "gn:admin1_code":"45",
    "gn:asciiname":"Dumanlar",
    "gn:country_code":"TR",
    "gn:dem":817,
    "gn:feature_class":"P",
    "gn:feature_code":"PPL",
    "gn:name":"Dumanlar",
    "gn:population":0,
    "gn:timezone":"Europe/Istanbul",
    "iso:country":"TR",
    "name:tur_x_preferred":[
        "Dumanlar"
    ],
    "wof:name":"Dumanlar",
    "wof:placetype":"locality"
},
  "geometry": {"coordinates":[28.9727,38.75301],"type":"Point"}
}