{
  "type": "Feature",
  "properties": {
    "gn:admin1_code":"93.0",
    "gn:asciiname":"Yaylacik",
    "gn:country_code":"TR",
    "gn:dem":549,
    "gn:feature_class":"P",
    "gn:feature_code":"PPL",
    "gn:name":"Yaylac\u0131k",
    "gn:population":0,
    "gn:timezone":"Europe/Istanbul",
    "iso:country":"TR",
    "wof:name":"Yaylacik",
    "wof:placetype":"locality"
},
  "geometry": {"coordinates":[31.06667,41.01667],"type":"Point"}
}