{
  "type": "Feature",
  "properties": {
    "gn:admin1_code":"38",
    "gn:asciiname":"Fettahdere",
    "gn:country_code":"TR",
    "gn:dem":1661,
    "gn:feature_class":"P",
    "gn:feature_code":"PPL",
    "gn:name":"Fettahdere",
    "gn:population":0,
    "gn:timezone":"Europe/Istanbul",
    "iso:country":"TR",
    "name:tur_x_preferred":[
        "Fettahdere"
    ],
    "wof:name":"Fettahdere",
    "wof:placetype":"locality"
},
  "geometry": {"coordinates":[36.42252,38.42251],"type":"Point"}
}