{
  "type": "Feature",
  "properties": {
    "gn:country":"TR",
    "gn:fcode":"PPLA2",
    "gn:pop":30852,
    "iso:country":"TR",
    "name:azb_x_preferred":[
        "\u0628\u06cc\u06af\u0627 \u060c \u0686\u0627\u0646\u0627\u0642 \u0642\u0627\u0644\u0627"
    ],
    "name:bul_x_preferred":[
        "\u0411\u0438\u0433\u0430"
    ],
    "name:fas_x_preferred":[
        "\u0628\u06cc\u06af\u0627"
    ],
    "name:kbd_x_preferred":[
        "\u0411\u0438\u0433\u044d"
    ],
    "name:mrj_x_preferred":[
        "\u0411\u0438\u0433\u0430"
    ],
    "name:nno_x_preferred":[
        "Biga i \u00c7anakkale"
    ],
    "name:pnb_x_preferred":[
        "\u0636\u0644\u0639 \u0628\u06cc\u06af\u0627"
    ],
    "name:rus_x_preferred":[
        "\u0411\u0438\u0433"
    ],
    "name:rus_x_variant":[
        "\u0411\u0438\u0433\u0430"
    ],
    "name:urd_x_preferred":[
        "\u0628\u06cc\u06af\u0627\u060c \u0686\u0646\u0627\u0642 \u0642\u0644\u0639\u06c1"
    ],
    "name:zho_x_preferred":[
        "\u6bd4\u52a0"
    ],
    "qs:name":"Biga",
    "qs:name_adm0":"Turkey",
    "qs:name_adm1":"\u00c7anakkale",
    "qs:photos":30,
    "qs:photos_1k":6,
    "qs:photos_9k":1,
    "qs:photos_9r":2,
    "qs:photos_all":30,
    "qs:photos_sr":2,
    "qs:placetype":"Town",
    "qs:pop_sr":"7",
    "wd:wordcount":74,
    "wof:name":"Biga",
    "wof:placetype":"locality",
    "wof:population":30852
},
  "geometry": {"coordinates":[27.24222,40.22806],"type":"Point"}
}