{
  "type": "Feature",
  "properties": {
    "gn:admin1_code":"17.0",
    "gn:asciiname":"Harmanli",
    "gn:country_code":"TR",
    "gn:dem":144,
    "gn:feature_class":"P",
    "gn:feature_code":"PPL",
    "gn:name":"Harmanl\u0131",
    "gn:population":0,
    "gn:timezone":"Europe/Istanbul",
    "iso:country":"TR",
    "name:und_x_variant":[
        "Filik-Fili",
        "Filik\u00f6y",
        "Harmanl\u0131"
    ],
    "wof:name":"Harmanli",
    "wof:placetype":"locality"
},
  "geometry": {"coordinates":[27.06242,40.16834],"type":"Point"}
}