{
  "type": "Feature",
  "properties": {
    "gn:admin1_code":"17.0",
    "gn:asciiname":"Harmanli",
    "gn:country_code":"TR",
    "gn:dem":144,
    "gn:feature_class":"P",
    "gn:feature_code":"PPL",
    "gn:name":"Harmanl\u0131",
    "gn:population":0,
    "gn:timezone":"Europe/Istanbul",
    "iso:country":"TR",
    "name:azb_x_preferred":[
        "\u0647\u0627\u0631\u0645\u0627\u0646\u0644\u06cc"
    ],
    "name:bel_x_preferred":[
        "\u0425\u0430\u0440\u043c\u0430\u043d\u043b\u0456"
    ],
    "name:bul_x_preferred":[
        "\u0425\u0430\u0440\u043c\u0430\u043d\u043b\u0438"
    ],
    "name:ceb_x_preferred":[
        "Kharmanli"
    ],
    "name:ckb_x_preferred":[
        "\u062e\u0627\u0631\u0645\u0627\u0646\u0644\u06cc"
    ],
    "name:deu_x_preferred":[
        "Charmanli"
    ],
    "name:fas_x_preferred":[
        "\u0647\u0627\u0631\u0645\u0627\u0646\u0644\u06cc"
    ],
    "name:fin_x_preferred":[
        "Harmanli"
    ],
    "name:fra_x_preferred":[
        "Harmanli"
    ],
    "name:heb_x_preferred":[
        "\u05d7\u05d0\u05e8\u05de\u05d0\u05e0\u05dc\u05d9"
    ],
    "name:hrv_x_preferred":[
        "Harmanli"
    ],
    "name:kaz_x_preferred":[
        "\u0425\u0430\u0440\u043c\u0430\u043d\u043b\u0438"
    ],
    "name:lit_x_preferred":[
        "Charmanli"
    ],
    "name:mkd_x_preferred":[
        "\u0425\u0430\u0440\u043c\u0430\u043d\u043b\u0438"
    ],
    "name:nld_x_preferred":[
        "Charmanli"
    ],
    "name:pol_x_preferred":[
        "Charmanli"
    ],
    "name:por_x_preferred":[
        "Harmanli"
    ],
    "name:ron_x_preferred":[
        "Harmanli"
    ],
    "name:rus_x_preferred":[
        "\u0425\u0430\u0440\u043c\u0430\u043d\u043b\u0438"
    ],
    "name:spa_x_preferred":[
        "Jarmanli"
    ],
    "name:srp_x_preferred":[
        "\u0425\u0430\u0440\u043c\u0430\u043d\u043b\u0438"
    ],
    "name:swe_x_preferred":[
        "Charmanli"
    ],
    "name:tur_x_preferred":[
        "Harmanl\u0131"
    ],
    "name:ukr_x_preferred":[
        "\u0425\u0430\u0440\u043c\u0430\u043d\u043b\u0438"
    ],
    "name:und_x_variant":[
        "Filik-Fili",
        "Filik\u00f6y"
    ],
    "name:vie_x_preferred":[
        "Harmanli"
    ],
    "name:war_x_preferred":[
        "Harmanli"
    ],
    "name:zho_x_preferred":[
        "\u54c8\u723e\u66fc\u5229"
    ],
    "wof:name":"Harmanli",
    "wof:placetype":"locality"
},
  "geometry": {"coordinates":[27.06242,40.16834],"type":"Point"}
}