{
  "type": "Feature",
  "properties": {
    "gn:admin1_code":"10.0",
    "gn:asciiname":"Akcal",
    "gn:country_code":"TR",
    "gn:dem":320,
    "gn:feature_class":"P",
    "gn:feature_code":"PPL",
    "gn:name":"Ak\u00e7al",
    "gn:population":0,
    "gn:timezone":"Europe/Istanbul",
    "iso:country":"TR",
    "name:tur_x_preferred":[
        "Ak\u00e7al"
    ],
    "wof:name":"Akcal",
    "wof:placetype":"locality"
},
  "geometry": {"coordinates":[27.55904,39.60139],"type":"Point"}
}