{
  "type": "Feature",
  "properties": {
    "gn:admin1_code":"37.0",
    "gn:asciiname":"Kirha",
    "gn:country_code":"TR",
    "gn:dem":600,
    "gn:feature_class":"P",
    "gn:feature_code":"PPL",
    "gn:name":"K\u0131rha",
    "gn:population":0,
    "gn:timezone":"Europe/Istanbul",
    "iso:country":"TR",
    "wof:name":"Kirha",
    "wof:placetype":"locality"
},
  "geometry": {"coordinates":[34.19086,41.48884],"type":"Point"}
}