{
  "type": "Feature",
  "properties": {
    "gn:admin1_code":"44.0",
    "gn:asciiname":"Kurtusagi",
    "gn:country_code":"TR",
    "gn:dem":1434,
    "gn:feature_class":"P",
    "gn:feature_code":"PPL",
    "gn:name":"Kurtu\u015fa\u011f\u0131",
    "gn:population":0,
    "gn:timezone":"Europe/Istanbul",
    "iso:country":"TR",
    "name:tur_x_preferred":[
        "Kurtu\u015fa\u011f\u0131"
    ],
    "name:und_x_variant":[
        "Kurta\u015fa\u011f\u0131"
    ],
    "wof:name":"Kurtusagi",
    "wof:placetype":"locality"
},
  "geometry": {"coordinates":[37.84239,38.48034000000001],"type":"Point"}
}