{
  "type": "Feature",
  "properties": {
    "gn:admin1_code":"71",
    "gn:asciiname":"Karatepe",
    "gn:country_code":"TR",
    "gn:dem":1026,
    "gn:feature_class":"P",
    "gn:feature_code":"PPL",
    "gn:name":"Karatepe",
    "gn:population":0,
    "gn:timezone":"Europe/Istanbul",
    "iso:country":"TR",
    "name:und_x_variant":[
        "Ittihadiye",
        "Karatepe"
    ],
    "wof:name":"Karatepe",
    "wof:placetype":"locality"
},
  "geometry": {"coordinates":[32.41111,38.33611],"type":"Point"}
}