{
  "type": "Feature",
  "properties": {
    "gn:admin1_code":"83.0",
    "gn:asciiname":"Kalaycik",
    "gn:cc2":"TR",
    "gn:country_code":"TR",
    "gn:dem":452,
    "gn:feature_class":"P",
    "gn:feature_code":"PPL",
    "gn:name":"Kalayc\u0131k",
    "gn:population":0,
    "gn:timezone":"Europe/Istanbul",
    "iso:country":"TR",
    "name:und_x_variant":[
        "Kalaydzhik",
        "Kalayc\u0131k"
    ],
    "wof:name":"Kalaycik",
    "wof:placetype":"locality"
},
  "geometry": {"coordinates":[36.65167,36.94306],"type":"Point"}
}