{
  "type": "Feature",
  "properties": {
    "gn:admin1_code":"21",
    "gn:asciiname":"Fabrikakoyu",
    "gn:country_code":"TR",
    "gn:dem":605,
    "gn:feature_class":"P",
    "gn:feature_code":"PPL",
    "gn:name":"Fabrikak\u00f6y\u00fc",
    "gn:population":0,
    "gn:timezone":"Europe/Istanbul",
    "iso:country":"TR",
    "name:tur_x_preferred":[
        "Fabrikak\u00f6y\u00fc"
    ],
    "name:und_x_variant":[
        "\u00c7an\u0131kl\u0131 Fabrak\u0131s\u0131"
    ],
    "wof:name":"Fabrikakoyu",
    "wof:placetype":"locality"
},
  "geometry": {"coordinates":[40.23528,37.83778],"type":"Point"}
}