{
  "type": "Feature",
  "properties": {
    "gn:admin1_code":"37.0",
    "gn:asciiname":"Yukaridikmen",
    "gn:country_code":"TR",
    "gn:dem":1242,
    "gn:feature_class":"P",
    "gn:feature_code":"PPL",
    "gn:name":"Yukar\u0131dikmen",
    "gn:population":0,
    "gn:timezone":"Europe/Istanbul",
    "iso:country":"TR",
    "wof:name":"Yukaridikmen",
    "wof:placetype":"locality"
},
  "geometry": {"coordinates":[34.09820999999999,40.94725],"type":"Point"}
}