{
  "type": "Feature",
  "properties": {
    "gn:admin1_code":"86.0",
    "gn:asciiname":"Tasdegirmen",
    "gn:country_code":"TR",
    "gn:dem":1949,
    "gn:feature_class":"P",
    "gn:feature_code":"PPL",
    "gn:name":"Ta\u015fde\u011firmen",
    "gn:population":0,
    "gn:timezone":"Europe/Istanbul",
    "iso:country":"TR",
    "name:eng_x_preferred":[
        "Ta\u015fde\u011firmen"
    ],
    "name:rus_x_preferred":[
        "\u0422\u0430\u0448\u0434\u0435\u0433\u0438\u0440\u043c\u0435\u043d"
    ],
    "name:und_x_variant":[
        "\u00c7amdira",
        "Ta\u015fde\u011firmen"
    ],
    "wof:name":"Tasdegirmen",
    "wof:placetype":"locality"
},
  "geometry": {"coordinates":[43.26235,41.15689],"type":"Point"}
}