{
  "type": "Feature",
  "properties": {
    "gn:admin1_code":"66",
    "gn:asciiname":"Korpeli",
    "gn:country_code":"TR",
    "gn:dem":1128,
    "gn:feature_class":"P",
    "gn:feature_code":"PPL",
    "gn:name":"K\u00f6rpeli",
    "gn:population":0,
    "gn:timezone":"Europe/Istanbul",
    "iso:country":"TR",
    "name:und_x_variant":[
        "G\u00f6rpeli",
        "K\u00f6rpeli"
    ],
    "wof:name":"Korpeli",
    "wof:placetype":"locality"
},
  "geometry": {"coordinates":[34.45903,39.88704],"type":"Point"}
}