{
  "type": "Feature",
  "properties": {
    "gn:admin1_code":"44.0",
    "gn:asciiname":"Davulgu",
    "gn:country_code":"TR",
    "gn:dem":1443,
    "gn:feature_class":"P",
    "gn:feature_code":"PPL",
    "gn:name":"Davulgu",
    "gn:population":0,
    "gn:timezone":"Europe/Istanbul",
    "iso:country":"TR",
    "name:tur_x_preferred":[
        "Davulgu"
    ],
    "wof:name":"Davulgu",
    "wof:placetype":"locality"
},
  "geometry": {"coordinates":[37.83643,38.93893],"type":"Point"}
}