{
  "type": "Feature",
  "properties": {
    "gn:admin1_code":"28",
    "gn:asciiname":"Guneykoy",
    "gn:country_code":"TR",
    "gn:dem":836,
    "gn:feature_class":"P",
    "gn:feature_code":"PPL",
    "gn:name":"G\u00fcneyk\u00f6y",
    "gn:population":0,
    "gn:timezone":"Europe/Istanbul",
    "iso:country":"TR",
    "name:tur_x_preferred":[
        "G\u00fcneyk\u00f6y"
    ],
    "wof:name":"Guneykoy",
    "wof:placetype":"locality"
},
  "geometry": {"coordinates":[38.2002,40.78904],"type":"Point"}
}