{
  "type": "Feature",
  "properties": {
    "gn:admin1_code":"48",
    "gn:asciiname":"Cobanlar",
    "gn:country_code":"TR",
    "gn:dem":197,
    "gn:feature_class":"P",
    "gn:feature_code":"PPL",
    "gn:name":"\u00c7obanlar",
    "gn:population":0,
    "gn:timezone":"Europe/Istanbul",
    "iso:country":"TR",
    "name:tur_x_preferred":[
        "\u00c7obanlar"
    ],
    "wof:name":"Cobanlar",
    "wof:placetype":"locality"
},
  "geometry": {"coordinates":[29.34827,36.73689],"type":"Point"}
}