{
  "type": "Feature",
  "properties": {
    "gn:admin1_code":"37.0",
    "gn:asciiname":"Bahcecik",
    "gn:country_code":"TR",
    "gn:dem":864,
    "gn:feature_class":"P",
    "gn:feature_code":"PPL",
    "gn:name":"Bah\u00e7ecik",
    "gn:population":0,
    "gn:timezone":"Europe/Istanbul",
    "iso:country":"TR",
    "name:und_x_variant":[
        "And\u0131ras",
        "And\u0131vaz",
        "And\u0131raz",
        "Bah\u00e7ecik"
    ],
    "wof:name":"Bahcecik",
    "wof:placetype":"locality"
},
  "geometry": {"coordinates":[33.15667,41.08718],"type":"Point"}
}