{
  "type": "Feature",
  "properties": {
    "gn:admin1_code":"66",
    "gn:asciiname":"Kucukcalagil",
    "gn:country_code":"TR",
    "gn:dem":1198,
    "gn:feature_class":"P",
    "gn:feature_code":"PPL",
    "gn:name":"K\u00fc\u00e7\u00fck\u00e7ala\u011f\u0131l",
    "gn:population":0,
    "gn:timezone":"Europe/Istanbul",
    "iso:country":"TR",
    "name:und_x_variant":[
        "K\u00fc\u00e7\u00fck\u00e7ala\u011f\u0131l",
        "K\u00fc\u00e7\u00fck\u00e7ola\u011fl\u0131"
    ],
    "wof:name":"Kucukcalagil",
    "wof:placetype":"locality"
},
  "geometry": {"coordinates":[35.42801,39.63294000000001],"type":"Point"}
}