{
  "type": "Feature",
  "properties": {
    "gn:admin1_code":"45",
    "gn:asciiname":"Arabacibozkoy",
    "gn:country_code":"TR",
    "gn:dem":434,
    "gn:feature_class":"P",
    "gn:feature_code":"PPL",
    "gn:name":"Arabac\u0131bozk\u00f6y",
    "gn:population":0,
    "gn:timezone":"Europe/Istanbul",
    "iso:country":"TR",
    "name:tur_x_preferred":[
        "Arabacibozk\u00f6y"
    ],
    "name:tur_x_variant":[
        "Arabac\u0131bozk\u00f6y"
    ],
    "name:und_x_variant":[
        "Arabac\u0131ba\u011f"
    ],
    "wof:name":"Arabacibozkoy",
    "wof:placetype":"locality"
},
  "geometry": {"coordinates":[27.51927,38.96835],"type":"Point"}
}