{
  "type": "Feature",
  "properties": {
    "gn:admin1_code":"81.0",
    "gn:asciiname":"Belen",
    "gn:country_code":"TR",
    "gn:dem":1414,
    "gn:feature_class":"P",
    "gn:feature_code":"PPL",
    "gn:name":"Belen",
    "gn:population":0,
    "gn:timezone":"Europe/Istanbul",
    "iso:country":"TR",
    "wof:name":"Belen",
    "wof:placetype":"locality"
},
  "geometry": {"coordinates":[35.87633,37.97284000000001],"type":"Point"}
}