{
  "type": "Feature",
  "properties": {
    "gn:admin1_code":"45",
    "gn:asciiname":"Orcular",
    "gn:country_code":"TR",
    "gn:dem":624,
    "gn:feature_class":"P",
    "gn:feature_code":"PPL",
    "gn:name":"Orcular",
    "gn:population":0,
    "gn:timezone":"Europe/Istanbul",
    "iso:country":"TR",
    "name:tur_x_preferred":[
        "Orcular"
    ],
    "wof:name":"Orcular",
    "wof:placetype":"locality"
},
  "geometry": {"coordinates":[28.15108,38.9587],"type":"Point"}
}