{
  "type": "Feature",
  "properties": {
    "gn:admin1_code":"74",
    "gn:asciiname":"Ozyurt",
    "gn:country_code":"TR",
    "gn:dem":1336,
    "gn:feature_class":"P",
    "gn:feature_code":"PPL",
    "gn:name":"\u00d6zyurt",
    "gn:population":0,
    "gn:timezone":"Europe/Istanbul",
    "iso:country":"TR",
    "name:und_x_variant":[
        "\u00d6zyurt",
        "Osyak"
    ],
    "wof:name":"Ozyurt",
    "wof:placetype":"locality"
},
  "geometry": {"coordinates":[42.08967,38.13709],"type":"Point"}
}