{
  "type": "Feature",
  "properties": {
    "gn:admin1_code":"63.0",
    "gn:asciiname":"Yukari Kosma",
    "gn:country_code":"TR",
    "gn:dem":745,
    "gn:feature_class":"P",
    "gn:feature_code":"PPL",
    "gn:name":"Yukar\u0131 Ko\u015fma",
    "gn:population":0,
    "gn:timezone":"Europe/Istanbul",
    "iso:country":"TR",
    "name:tur_x_preferred":[
        "Yukar\u0131 Ko\u015fma"
    ],
    "name:und_x_variant":[
        "Yukary-Koshma"
    ],
    "wof:name":"Yukari Kosma",
    "wof:placetype":"locality"
},
  "geometry": {"coordinates":[38.51907,37.20286],"type":"Point"}
}