{
  "type": "Feature",
  "properties": {
    "gn:admin1_code":"35",
    "gn:asciiname":"Egriazmak",
    "gn:country_code":"TR",
    "gn:dem":37,
    "gn:feature_class":"P",
    "gn:feature_code":"PPL",
    "gn:name":"E\u011friazmak",
    "gn:population":0,
    "gn:timezone":"Europe/Istanbul",
    "iso:country":"TR",
    "name:tur_x_preferred":[
        "E\u011friazmak"
    ],
    "name:tur_x_variant":[
        "E\u011fricil Mevki"
    ],
    "wof:name":"Egriazmak",
    "wof:placetype":"locality"
},
  "geometry": {"coordinates":[27.66067,38.14266],"type":"Point"}
}