{
  "type": "Feature",
  "properties": {
    "gn:admin1_code":"74",
    "gn:asciiname":"Soran",
    "gn:country_code":"TR",
    "gn:dem":518,
    "gn:feature_class":"P",
    "gn:feature_code":"PPL",
    "gn:name":"Soran",
    "gn:population":0,
    "gn:timezone":"Europe/Istanbul",
    "iso:country":"TR",
    "wof:name":"Soran",
    "wof:placetype":"locality"
},
  "geometry": {"coordinates":[41.80028,37.88111],"type":"Point"}
}