{
  "type": "Feature",
  "properties": {
    "gn:admin1_code":"74",
    "gn:asciiname":"Soran",
    "gn:country_code":"TR",
    "gn:dem":518,
    "gn:feature_class":"P",
    "gn:feature_code":"PPL",
    "gn:name":"Soran",
    "gn:population":0,
    "gn:timezone":"Europe/Istanbul",
    "iso:country":"TR",
    "name:bul_x_preferred":[
        "\u0421\u043e\u0440\u0430\u043d"
    ],
    "name:ceb_x_preferred":[
        "Soran"
    ],
    "name:kur_x_preferred":[
        "Soran"
    ],
    "name:swe_x_preferred":[
        "Soran"
    ],
    "wof:name":"Soran",
    "wof:placetype":"locality"
},
  "geometry": {"coordinates":[41.80028,37.88111],"type":"Point"}
}