{
  "type": "Feature",
  "properties": {
    "gn:admin1_code":"63",
    "gn:asciiname":"Meshref",
    "gn:country_code":"TR",
    "gn:dem":503,
    "gn:feature_class":"P",
    "gn:feature_code":"PPL",
    "gn:name":"Meshref",
    "gn:population":0,
    "gn:timezone":"Europe/Istanbul",
    "iso:country":"TR",
    "wof:name":"Meshref",
    "wof:placetype":"locality"
},
  "geometry": {"coordinates":[38.89372,37.16856],"type":"Point"}
}