{
  "type": "Feature",
  "properties": {
    "gn:admin1_code":"41.0",
    "gn:asciiname":"Camdibi",
    "gn:country_code":"TR",
    "gn:dem":345,
    "gn:feature_class":"P",
    "gn:feature_code":"PPL",
    "gn:name":"\u00c7amdibi",
    "gn:population":0,
    "gn:timezone":"Europe/Istanbul",
    "iso:country":"TR",
    "name:und_x_variant":[
        "K\u00fcrt",
        "K\u00fcrtk\u00f6y",
        "\u00c7amdibi"
    ],
    "wof:name":"Camdibi",
    "wof:placetype":"locality"
},
  "geometry": {"coordinates":[29.56392,40.56211],"type":"Point"}
}