{
  "type": "Feature",
  "properties": {
    "gn:admin1_code":"58",
    "gn:asciiname":"Yagmurluseki",
    "gn:country_code":"TR",
    "gn:dem":1721,
    "gn:feature_class":"P",
    "gn:feature_code":"PPL",
    "gn:name":"Ya\u011fmurluseki",
    "gn:population":0,
    "gn:timezone":"Europe/Istanbul",
    "iso:country":"TR",
    "wof:name":"Yagmurluseki",
    "wof:placetype":"locality"
},
  "geometry": {"coordinates":[37.36456,39.53315],"type":"Point"}
}