{
  "type": "Feature",
  "properties": {
    "gn:admin1_code":"80.0",
    "gn:asciiname":"Altu",
    "gn:country_code":"TR",
    "gn:dem":826,
    "gn:feature_class":"P",
    "gn:feature_code":"PPL",
    "gn:name":"Altu",
    "gn:population":0,
    "gn:timezone":"Europe/Istanbul",
    "iso:country":"TR",
    "wof:name":"Altu",
    "wof:placetype":"locality"
},
  "geometry": {"coordinates":[42.69278,37.47167],"type":"Point"}
}