{
  "type": "Feature",
  "properties": {
    "gn:admin1_code":"12",
    "gn:asciiname":"Topagaclar",
    "gn:country_code":"TR",
    "gn:dem":1316,
    "gn:feature_class":"P",
    "gn:feature_code":"PPL",
    "gn:name":"Topa\u011fa\u00e7lar",
    "gn:population":0,
    "gn:timezone":"Europe/Istanbul",
    "iso:country":"TR",
    "name:und_x_variant":[
        "Topa\u011fa\u00e7lar",
        "Danatepe"
    ],
    "wof:name":"Topagaclar",
    "wof:placetype":"locality"
},
  "geometry": {"coordinates":[40.44824000000001,39.20923],"type":"Point"}
}