{
  "type": "Feature",
  "properties": {
    "gn:admin1_code":"37.0",
    "gn:asciiname":"Maslar",
    "gn:country_code":"TR",
    "gn:dem":773,
    "gn:feature_class":"P",
    "gn:feature_code":"PPL",
    "gn:name":"Maslar",
    "gn:population":0,
    "gn:timezone":"Europe/Istanbul",
    "iso:country":"TR",
    "name:und_x_variant":[
        "\u00dc\u00e7p\u0131nar"
    ],
    "wof:name":"Maslar",
    "wof:placetype":"locality"
},
  "geometry": {"coordinates":[33.05721,41.20779],"type":"Point"}
}