{
  "type": "Feature",
  "properties": {
    "gn:admin1_code":"35",
    "gn:asciiname":"Uzunkuyu",
    "gn:country_code":"TR",
    "gn:dem":244,
    "gn:feature_class":"P",
    "gn:feature_code":"PPLA3",
    "gn:name":"Uzunkuyu",
    "gn:population":0,
    "gn:timezone":"Europe/Istanbul",
    "iso:country":"TR",
    "name:und_x_variant":[
        "Uzunkoyu"
    ],
    "wof:name":"Uzunkuyu",
    "wof:placetype":"locality"
},
  "geometry": {"coordinates":[26.54315,38.27858],"type":"Point"}
}