{
  "type": "Feature",
  "properties": {
    "gn:admin1_code":"8.0",
    "gn:asciiname":"Kisberut",
    "gn:country_code":"TR",
    "gn:dem":884,
    "gn:feature_class":"P",
    "gn:feature_code":"PPL",
    "gn:name":"Kisberut",
    "gn:population":0,
    "gn:timezone":"Europe/Istanbul",
    "iso:country":"TR",
    "wof:name":"Kisberut",
    "wof:placetype":"locality"
},
  "geometry": {"coordinates":[41.51667,40.86667],"type":"Point"}
}