{
  "type": "Feature",
  "properties": {
    "gn:admin1_code":"81.0",
    "gn:asciiname":"Konankli",
    "gn:country_code":"TR",
    "gn:dem":1,
    "gn:feature_class":"P",
    "gn:feature_code":"PPL",
    "gn:name":"Konankl\u0131",
    "gn:population":0,
    "gn:timezone":"Europe/Istanbul",
    "iso:country":"TR",
    "name:und_x_variant":[
        "Konankl\u0131",
        "Tabur"
    ],
    "wof:name":"Konankli",
    "wof:placetype":"locality"
},
  "geometry": {"coordinates":[35.12653,36.67252],"type":"Point"}
}