{
  "type": "Feature",
  "properties": {
    "gn:admin1_code":"45",
    "gn:asciiname":"Borez",
    "gn:country_code":"TR",
    "gn:dem":806,
    "gn:feature_class":"P",
    "gn:feature_code":"PPL",
    "gn:name":"B\u00f6rez",
    "gn:population":0,
    "gn:timezone":"Europe/Istanbul",
    "iso:country":"TR",
    "name:tur_x_preferred":[
        "B\u00f6rez"
    ],
    "wof:name":"Borez",
    "wof:placetype":"locality"
},
  "geometry": {"coordinates":[28.26505,39.01205],"type":"Point"}
}