{
  "type": "Feature",
  "properties": {
    "gn:admin1_code":"33",
    "gn:asciiname":"Oren",
    "gn:country_code":"TR",
    "gn:dem":1268,
    "gn:feature_class":"P",
    "gn:feature_code":"PPL",
    "gn:name":"\u00d6ren",
    "gn:population":0,
    "gn:timezone":"Europe/Istanbul",
    "iso:country":"TR",
    "name:deu_x_preferred":[
        "Oren"
    ],
    "name:ita_x_preferred":[
        "Oren"
    ],
    "name:por_x_preferred":[
        "Oren"
    ],
    "wof:name":"Oren",
    "wof:placetype":"locality"
},
  "geometry": {"coordinates":[31.14222,37.56491],"type":"Point"}
}