{
  "type": "Feature",
  "properties": {
    "gn:admin1_code":"43",
    "gn:asciiname":"Malatya",
    "gn:country_code":"TR",
    "gn:dem":1094,
    "gn:feature_class":"P",
    "gn:feature_code":"PPL",
    "gn:name":"Malatya",
    "gn:population":0,
    "gn:timezone":"Europe/Istanbul",
    "iso:country":"TR",
    "name:rus_x_preferred":[
        "\u041c\u0430\u043b\u0430\u0442\u044c\u044f"
    ],
    "name:tur_x_preferred":[
        "Demir\u00f6z\u00fc"
    ],
    "name:und_x_variant":[
        "Gerizmalatyas\u0131",
        "Malatya"
    ],
    "wof:name":"Malatya",
    "wof:placetype":"locality"
},
  "geometry": {"coordinates":[30.33691,39.20005],"type":"Point"}
}