{
  "type": "Feature",
  "properties": {
    "gn:admin1_code":"76.0",
    "gn:asciiname":"Cocana",
    "gn:country_code":"TR",
    "gn:dem":627,
    "gn:feature_class":"P",
    "gn:feature_code":"PPL",
    "gn:name":"Cocana",
    "gn:population":0,
    "gn:timezone":"Europe/Istanbul",
    "iso:country":"TR",
    "wof:name":"Cocana",
    "wof:placetype":"locality"
},
  "geometry": {"coordinates":[41.35771,37.98788],"type":"Point"}
}