{
  "type": "Feature",
  "properties": {
    "gn:admin1_code":"55.0",
    "gn:asciiname":"Devrek",
    "gn:country_code":"TR",
    "gn:dem":989,
    "gn:feature_class":"P",
    "gn:feature_code":"PPL",
    "gn:name":"Devrek",
    "gn:population":0,
    "gn:timezone":"Europe/Istanbul",
    "iso:country":"TR",
    "name:ceb_x_preferred":[
        "Devrek \u0130l\u00e7esi"
    ],
    "name:deu_x_preferred":[
        "Devrek"
    ],
    "name:fas_x_preferred":[
        "\u062f\u0648\u0631\u06a9"
    ],
    "name:fra_x_preferred":[
        "Devrek"
    ],
    "name:min_x_preferred":[
        "Devrek"
    ],
    "name:mrj_x_preferred":[
        "\u0414\u0435\u0432\u0440\u0435\u043a"
    ],
    "name:msa_x_preferred":[
        "Devrek"
    ],
    "name:nld_x_preferred":[
        "Devrek"
    ],
    "name:nno_x_preferred":[
        "Devrek"
    ],
    "name:nor_x_preferred":[
        "Devrek"
    ],
    "name:swa_x_preferred":[
        "Devrek"
    ],
    "name:tur_x_preferred":[
        "Devrek"
    ],
    "name:urd_x_preferred":[
        "\u062f\u06cc\u0648\u0631\u06a9"
    ],
    "name:vie_x_preferred":[
        "Devrek"
    ],
    "name:zho_x_preferred":[
        "\u4ee3\u592b\u96f7\u514b"
    ],
    "wof:name":"Devrek",
    "wof:placetype":"locality"
},
  "geometry": {"coordinates":[35.03048,41.09629],"type":"Point"}
}