{
  "type": "Feature",
  "properties": {
    "gn:admin1_code":"32",
    "gn:asciiname":"Kurbanli",
    "gn:country_code":"TR",
    "gn:dem":240,
    "gn:feature_class":"P",
    "gn:feature_code":"PPL",
    "gn:name":"Kurbanl\u0131",
    "gn:population":0,
    "gn:timezone":"Europe/Istanbul",
    "iso:country":"TR",
    "name:tur_x_preferred":[
        "Kurbanl\u0131"
    ],
    "name:tur_x_variant":[
        "Bayraml\u0131"
    ],
    "wof:name":"Kurbanli",
    "wof:placetype":"locality"
},
  "geometry": {"coordinates":[34.91437,37.0387],"type":"Point"}
}