{
  "type": "Feature",
  "properties": {
    "gn:admin1_code":"07",
    "gn:asciiname":"Karadag",
    "gn:country_code":"TR",
    "gn:dem":214,
    "gn:feature_class":"P",
    "gn:feature_code":"PPL",
    "gn:name":"Karada\u011f",
    "gn:population":0,
    "gn:timezone":"Europe/Istanbul",
    "iso:country":"TR",
    "name:ceb_x_preferred":[
        "Karadag"
    ],
    "name:swe_x_preferred":[
        "Karadag"
    ],
    "wof:name":"Karadag",
    "wof:placetype":"locality"
},
  "geometry": {"coordinates":[29.86556,36.37917],"type":"Point"}
}