{
  "type": "Feature",
  "properties": {
    "gn:admin1_code":"40.0",
    "gn:asciiname":"Birecik",
    "gn:country_code":"TR",
    "gn:dem":779,
    "gn:feature_class":"P",
    "gn:feature_code":"PPL",
    "gn:name":"Birecik",
    "gn:population":0,
    "gn:timezone":"Europe/Istanbul",
    "iso:country":"TR",
    "name:ara_x_preferred":[
        "\u0627\u0644\u0628\u064a\u0631\u0629"
    ],
    "name:azb_x_preferred":[
        "\u0628\u06cc\u0631\u0647\u200c\u062c\u06cc\u06a9"
    ],
    "name:cat_x_preferred":[
        "Birecik"
    ],
    "name:ceb_x_preferred":[
        "Birecik"
    ],
    "name:ckb_x_preferred":[
        "\u0628\u06ce\u0631\u06d5\u062c\u0648\u0648\u06a9"
    ],
    "name:deu_x_preferred":[
        "Birecik"
    ],
    "name:diq_x_preferred":[
        "B\u00earecu\u011fe"
    ],
    "name:epo_x_preferred":[
        "Birecik"
    ],
    "name:fas_x_preferred":[
        "\u0628\u06cc\u0631\u0647\u200c\u062c\u06a9"
    ],
    "name:fra_x_preferred":[
        "Birecik"
    ],
    "name:ind_x_preferred":[
        "Birecik"
    ],
    "name:kur_x_preferred":[
        "B\u00earec\u00fbk"
    ],
    "name:min_x_preferred":[
        "Birecik"
    ],
    "name:mrj_x_preferred":[
        "\u0411\u0438\u0440\u0435\u0434\u0436\u0438\u043a"
    ],
    "name:msa_x_preferred":[
        "Birecik"
    ],
    "name:nld_x_preferred":[
        "Birecik"
    ],
    "name:nno_x_preferred":[
        "Birecik"
    ],
    "name:nor_x_preferred":[
        "Birecik"
    ],
    "name:pnb_x_preferred":[
        "\u0636\u0644\u0639 \u0628\u0631\u06cc\u062c\u06a9"
    ],
    "name:pol_x_preferred":[
        "Birecik"
    ],
    "name:ron_x_preferred":[
        "Birecik"
    ],
    "name:rus_x_preferred":[
        "\u0411\u0438\u0440\u0435\u0434\u0436\u0438\u043a"
    ],
    "name:sco_x_preferred":[
        "Birecik"
    ],
    "name:swa_x_preferred":[
        "Birecik"
    ],
    "name:tur_x_preferred":[
        "Birecik"
    ],
    "name:urd_x_preferred":[
        "\u0628\u06cc\u0631\u06c1 \u062c\u06a9"
    ],
    "name:vie_x_preferred":[
        "Birecik"
    ],
    "name:zho_x_preferred":[
        "\u6bd4\u96f7\u5409\u514b"
    ],
    "wof:name":"Birecik",
    "wof:placetype":"locality"
},
  "geometry": {"coordinates":[33.89981,39.62648],"type":"Point"}
}