{
  "type": "Feature",
  "properties": {
    "gn:admin1_code":"66",
    "gn:asciiname":"Karahalli",
    "gn:country_code":"TR",
    "gn:dem":1198,
    "gn:feature_class":"P",
    "gn:feature_code":"PPL",
    "gn:name":"Karahall\u0131",
    "gn:population":0,
    "gn:timezone":"Europe/Istanbul",
    "iso:country":"TR",
    "wof:name":"Karahalli",
    "wof:placetype":"locality"
},
  "geometry": {"coordinates":[35.42717000000001,39.38685],"type":"Point"}
}