{
  "type": "Feature",
  "properties": {
    "gn:admin1_code":"37.0",
    "gn:asciiname":"Harmangeris",
    "gn:country_code":"TR",
    "gn:dem":303,
    "gn:feature_class":"P",
    "gn:feature_code":"PPL",
    "gn:name":"Harmangeri\u015f",
    "gn:population":0,
    "gn:timezone":"Europe/Istanbul",
    "iso:country":"TR",
    "name:und_x_variant":[
        "Harmangeri\u015f",
        "Karaman"
    ],
    "wof:name":"Harmangeris",
    "wof:placetype":"locality"
},
  "geometry": {"coordinates":[33.17974,41.78818],"type":"Point"}
}