{
  "type": "Feature",
  "properties": {
    "gn:admin1_code":"84",
    "gn:asciiname":"Cicekli",
    "gn:country_code":"TR",
    "gn:dem":2039,
    "gn:feature_class":"P",
    "gn:feature_code":"PPL",
    "gn:name":"\u00c7i\u00e7ekli",
    "gn:population":0,
    "gn:timezone":"Europe/Istanbul",
    "iso:country":"TR",
    "name:und_x_variant":[
        "\u00c7i\u00e7ekli",
        "Bah\u00e7ecik"
    ],
    "wof:name":"Cicekli",
    "wof:placetype":"locality"
},
  "geometry": {"coordinates":[42.78846,39.97566],"type":"Point"}
}