{
  "type": "Feature",
  "properties": {
    "gn:admin1_code":"52.0",
    "gn:asciiname":"Catili",
    "gn:country_code":"TR",
    "gn:dem":1022,
    "gn:feature_class":"P",
    "gn:feature_code":"PPL",
    "gn:name":"\u00c7at\u0131l\u0131",
    "gn:population":0,
    "gn:timezone":"Europe/Istanbul",
    "iso:country":"TR",
    "name:und_x_variant":[
        "Tevk\u00fcr",
        "Tevg\u00f6r",
        "\u00c7at\u0131l\u0131"
    ],
    "wof:name":"Catili",
    "wof:placetype":"locality"
},
  "geometry": {"coordinates":[37.18921,40.80521],"type":"Point"}
}