{
  "type": "Feature",
  "properties": {
    "gn:admin1_code":"54.0",
    "gn:asciiname":"Aslanbey",
    "gn:country_code":"TR",
    "gn:dem":300,
    "gn:feature_class":"P",
    "gn:feature_code":"PPL",
    "gn:name":"Aslanbey",
    "gn:population":0,
    "gn:timezone":"Europe/Istanbul",
    "iso:country":"TR",
    "name:und_x_variant":[
        "S\u00fcnb\u00fcll\u00fc",
        "\u015e\u00fckriye",
        "S\u00fcmb\u00fcll\u00fc"
    ],
    "wof:name":"Aslanbey",
    "wof:placetype":"locality"
},
  "geometry": {"coordinates":[30.79296,40.73787],"type":"Point"}
}