{
  "type": "Feature",
  "properties": {
    "gn:admin1_code":"48",
    "gn:asciiname":"Turgut",
    "gn:country_code":"TR",
    "gn:dem":893,
    "gn:feature_class":"P",
    "gn:feature_code":"PPL",
    "gn:name":"Turgut",
    "gn:population":0,
    "gn:timezone":"Europe/Istanbul",
    "iso:country":"TR",
    "name:deu_x_preferred":[
        "Turgut"
    ],
    "name:und_x_variant":[
        "Kavak\u00e7al\u0131",
        "Turgut"
    ],
    "wof:name":"Turgut",
    "wof:placetype":"locality"
},
  "geometry": {"coordinates":[28.69615,37.16452],"type":"Point"}
}