{
  "type": "Feature",
  "properties": {
    "gn:admin1_code":"45",
    "gn:asciiname":"Yagbasti",
    "gn:country_code":"TR",
    "gn:dem":661,
    "gn:feature_class":"P",
    "gn:feature_code":"PPL",
    "gn:name":"Ya\u011fbast\u0131",
    "gn:population":0,
    "gn:timezone":"Europe/Istanbul",
    "iso:country":"TR",
    "name:und_x_variant":[
        "Ya\u011fbasd\u0131",
        "Ya\u011fbast\u0131"
    ],
    "wof:name":"Yagbasti",
    "wof:placetype":"locality"
},
  "geometry": {"coordinates":[28.46325,38.65763],"type":"Point"}
}