{
  "type": "Feature",
  "properties": {
    "gn:admin1_code":"65",
    "gn:asciiname":"Yukarikaymaz",
    "gn:country_code":"TR",
    "gn:dem":1751,
    "gn:feature_class":"P",
    "gn:feature_code":"PPL",
    "gn:name":"Yukar\u0131kaymaz",
    "gn:population":0,
    "gn:timezone":"Europe/Istanbul",
    "iso:country":"TR",
    "name:und_x_variant":[
        "Yukar\u0131 Micingir",
        "Yukar\u0131mijingir",
        "Yukar\u0131mejingir",
        "Yukar\u0131kaymaz"
    ],
    "wof:name":"Yukarikaymaz",
    "wof:placetype":"locality"
},
  "geometry": {"coordinates":[43.37886,38.30274],"type":"Point"}
}