{
  "type": "Feature",
  "properties": {
    "gn:admin1_code":"37.0",
    "gn:asciiname":"Tekkeviran",
    "gn:country_code":"TR",
    "gn:dem":1261,
    "gn:feature_class":"P",
    "gn:feature_code":"PPL",
    "gn:name":"Tekkeviran",
    "gn:population":0,
    "gn:timezone":"Europe/Istanbul",
    "iso:country":"TR",
    "wof:name":"Tekkeviran",
    "wof:placetype":"locality"
},
  "geometry": {"coordinates":[33.41667,41.33333],"type":"Point"}
}