{
  "type": "Feature",
  "properties": {
    "gn:admin1_code":"46.0",
    "gn:asciiname":"Reyhanli",
    "gn:country_code":"TR",
    "gn:dem":953,
    "gn:feature_class":"P",
    "gn:feature_code":"PPL",
    "gn:name":"Reyhanl\u0131",
    "gn:population":0,
    "gn:timezone":"Europe/Istanbul",
    "iso:country":"TR",
    "name:tur_x_preferred":[
        "Reyhanl\u0131"
    ],
    "wof:name":"Reyhanli",
    "wof:placetype":"locality"
},
  "geometry": {"coordinates":[36.54581,37.5322],"type":"Point"}
}