{
  "type": "Feature",
  "properties": {
    "gn:admin1_code":"58",
    "gn:asciiname":"Dogancal",
    "gn:country_code":"TR",
    "gn:dem":1587,
    "gn:feature_class":"P",
    "gn:feature_code":"PPL",
    "gn:name":"Do\u011fan\u00e7al",
    "gn:population":0,
    "gn:timezone":"Europe/Istanbul",
    "iso:country":"TR",
    "name:tur_x_preferred":[
        "Do\u011fan\u00e7al"
    ],
    "wof:name":"Dogancal",
    "wof:placetype":"locality"
},
  "geometry": {"coordinates":[38.06597,39.88141],"type":"Point"}
}