{
  "type": "Feature",
  "properties": {
    "gn:admin1_code":"19.0",
    "gn:asciiname":"Gumusoglu",
    "gn:country_code":"TR",
    "gn:dem":1672,
    "gn:feature_class":"P",
    "gn:feature_code":"PPL",
    "gn:name":"G\u00fcm\u00fc\u015fo\u011flu",
    "gn:population":0,
    "gn:timezone":"Europe/Istanbul",
    "iso:country":"TR",
    "name:tur_x_preferred":[
        "G\u00fcm\u00fc\u015fo\u011flu"
    ],
    "name:und_x_variant":[
        "Eskik\u00f6y"
    ],
    "wof:name":"Gumusoglu",
    "wof:placetype":"locality"
},
  "geometry": {"coordinates":[34.34234,41.28059],"type":"Point"}
}