{
  "type": "Feature",
  "properties": {
    "gn:admin1_code":"65",
    "gn:asciiname":"Bagdasan",
    "gn:country_code":"TR",
    "gn:dem":2012,
    "gn:feature_class":"P",
    "gn:feature_code":"PPL",
    "gn:name":"Ba\u011fda\u015fan",
    "gn:population":0,
    "gn:timezone":"Europe/Istanbul",
    "iso:country":"TR",
    "name:tur_x_preferred":[
        "Ba\u011fda\u015fan"
    ],
    "wof:name":"Bagdasan",
    "wof:placetype":"locality"
},
  "geometry": {"coordinates":[43.50906,38.82984],"type":"Point"}
}