{
  "type": "Feature",
  "properties": {
    "gn:admin1_code":"58",
    "gn:asciiname":"Davulbaz",
    "gn:country_code":"TR",
    "gn:dem":1550,
    "gn:feature_class":"P",
    "gn:feature_code":"PPL",
    "gn:name":"Davulbaz",
    "gn:population":0,
    "gn:timezone":"Europe/Istanbul",
    "iso:country":"TR",
    "wof:name":"Davulbaz",
    "wof:placetype":"locality"
},
  "geometry": {"coordinates":[37.39378,39.29275],"type":"Point"}
}