{
  "type": "Feature",
  "properties": {
    "gn:admin1_code":"45.0",
    "gn:asciiname":"Ahmetaga",
    "gn:country_code":"TR",
    "gn:dem":199,
    "gn:feature_class":"P",
    "gn:feature_code":"PPL",
    "gn:name":"Ahmeta\u011fa",
    "gn:population":0,
    "gn:timezone":"Europe/Istanbul",
    "iso:country":"TR",
    "wof:name":"Ahmetaga",
    "wof:placetype":"locality"
},
  "geometry": {"coordinates":[28.64778,38.25694],"type":"Point"}
}