{
  "type": "Feature",
  "properties": {
    "gn:admin1_code":"12",
    "gn:asciiname":"Goynuk",
    "gn:country_code":"TR",
    "gn:dem":1796,
    "gn:feature_class":"P",
    "gn:feature_code":"PPLA3",
    "gn:name":"G\u00f6yn\u00fck",
    "gn:population":0,
    "gn:timezone":"Europe/Istanbul",
    "iso:country":"TR",
    "name:und_x_variant":[
        "O\u011fnut",
        "G\u00f6n\u00fck",
        "G\u00f6yn\u00fck",
        "G\u00f6\u011fn\u00fck"
    ],
    "wof:name":"Goynuk",
    "wof:placetype":"locality"
},
  "geometry": {"coordinates":[40.87438,39.13947],"type":"Point"}
}