{
  "type": "Feature",
  "properties": {
    "gn:admin1_code":"14.0",
    "gn:asciiname":"Karacalar",
    "gn:country_code":"TR",
    "gn:dem":934,
    "gn:feature_class":"P",
    "gn:feature_code":"PPL",
    "gn:name":"Karacalar",
    "gn:population":0,
    "gn:timezone":"Europe/Istanbul",
    "iso:country":"TR",
    "wof:name":"Karacalar",
    "wof:placetype":"locality"
},
  "geometry": {"coordinates":[32.24278,40.95842],"type":"Point"}
}