{
  "type": "Feature",
  "properties": {
    "iso:country":"TR",
    "wof:name":"Habibler",
    "wof:placetype":"neighbourhood"
},
  "geometry": {"coordinates":[28.84701864743691,41.13320523227278],"type":"Point"}
}