{
  "type": "Feature",
  "properties": {
    "gn:country":"TR",
    "gn:fcode":"PPL",
    "gn:population":1094,
    "iso:country":"TR",
    "name:und_x_variant":[
        "Alakamysh"
    ],
    "qs:name":"Alakam\u0131\u015f",
    "qs:photos_9r":0,
    "qs:photos_sr":0,
    "qs:pop_sr":"3",
    "wof:name":"Alakam\u0131\u015f",
    "wof:placetype":"locality",
    "wof:population":1094
},
  "geometry": {"coordinates":[41.78889,37.15917],"type":"Point"}
}