{
  "type": "Feature",
  "properties": {
    "gn:admin1_code":"53.0",
    "gn:asciiname":"Koprulu",
    "gn:country_code":"TR",
    "gn:dem":278,
    "gn:feature_class":"P",
    "gn:feature_code":"PPL",
    "gn:name":"K\u00f6pr\u00fcl\u00fc",
    "gn:population":0,
    "gn:timezone":"Europe/Istanbul",
    "iso:country":"TR",
    "name:tur_x_preferred":[
        "K\u00f6pr\u00fcl\u00fc"
    ],
    "wof:name":"Koprulu",
    "wof:placetype":"locality"
},
  "geometry": {"coordinates":[40.51634,40.9777],"type":"Point"}
}