{
  "type": "Feature",
  "properties": {
    "gn:admin1_code":"93",
    "gn:asciiname":"Soguksu",
    "gn:country_code":"TR",
    "gn:dem":390,
    "gn:feature_class":"P",
    "gn:feature_code":"PPL",
    "gn:name":"So\u011fuksu",
    "gn:population":0,
    "gn:timezone":"Europe/Istanbul",
    "iso:country":"TR",
    "wof:name":"Soguksu",
    "wof:placetype":"locality"
},
  "geometry": {"coordinates":[30.88449,40.85047],"type":"Point"}
}