{
  "type": "Feature",
  "properties": {
    "gn:country":"TR",
    "gn:fcode":"PPL",
    "gn:pop":1256,
    "iso:country":"TR",
    "name:tur_x_preferred":[
        "Aran"
    ],
    "name:unk_x_variant":[
        "Zoni"
    ],
    "qs:name":"Aran",
    "qs:photos_9r":0,
    "qs:photos_sr":0,
    "qs:pop_sr":"3",
    "wd:wordcount":339,
    "wof:name":"Aran",
    "wof:placetype":"locality",
    "wof:population":1256
},
  "geometry": {"coordinates":[40.74656,37.43928],"type":"Point"}
}