{
  "type": "Feature",
  "properties": {
    "gn:country":"TR",
    "gn:fcode":"PPL",
    "gn:population":1256,
    "iso:country":"TR",
    "name:aze_x_preferred":[
        "Aran"
    ],
    "name:bel_x_preferred":[
        "\u0410\u0440\u0430\u043d"
    ],
    "name:bre_x_preferred":[
        "Aran"
    ],
    "name:cat_x_preferred":[
        "Aran"
    ],
    "name:ceb_x_preferred":[
        "Aran"
    ],
    "name:ces_x_preferred":[
        "Aran"
    ],
    "name:cym_x_preferred":[
        "Aran"
    ],
    "name:deu_x_preferred":[
        "Aran"
    ],
    "name:eus_x_preferred":[
        "Aran"
    ],
    "name:fas_x_preferred":[
        "\u0627\u0631\u0627\u0646"
    ],
    "name:fra_x_preferred":[
        "Aran"
    ],
    "name:hye_x_preferred":[
        "\u0531\u0580\u0561\u0576"
    ],
    "name:ita_x_preferred":[
        "Aran"
    ],
    "name:kat_x_preferred":[
        "\u10d0\u10e0\u10d0\u10dc\u10d8"
    ],
    "name:lit_x_preferred":[
        "Aranas"
    ],
    "name:rus_x_preferred":[
        "\u0410\u0440\u0430\u043d"
    ],
    "name:srp_x_preferred":[
        "\u0410\u0440\u0430\u043d"
    ],
    "name:swe_x_preferred":[
        "Aran"
    ],
    "name:tur_x_preferred":[
        "Aran"
    ],
    "name:und_x_variant":[
        "Zoni"
    ],
    "qs:name":"Aran",
    "qs:photos_9r":0,
    "qs:photos_sr":0,
    "qs:pop_sr":"3",
    "wd:wordcount":339,
    "wof:name":"Aran",
    "wof:placetype":"locality",
    "wof:population":1256
},
  "geometry": {"coordinates":[40.74656,37.43928],"type":"Point"}
}