{
  "type": "Feature",
  "properties": {
    "gn:admin1_code":"91",
    "gn:asciiname":"Karatepe",
    "gn:country_code":"TR",
    "gn:dem":281,
    "gn:feature_class":"P",
    "gn:feature_code":"PPL",
    "gn:name":"Karatepe",
    "gn:population":0,
    "gn:timezone":"Europe/Istanbul",
    "iso:country":"TR",
    "wof:name":"Karatepe",
    "wof:placetype":"locality"
},
  "geometry": {"coordinates":[36.23597,37.25934],"type":"Point"}
}