{
  "type": "Feature",
  "properties": {
    "gn:admin1_code":"91",
    "gn:asciiname":"Karatepe",
    "gn:country_code":"TR",
    "gn:dem":281,
    "gn:feature_class":"P",
    "gn:feature_code":"PPL",
    "gn:name":"Karatepe",
    "gn:population":0,
    "gn:timezone":"Europe/Istanbul",
    "iso:country":"TR",
    "name:bel_x_preferred":[
        "\u041a\u0430\u0440\u0430\u0442\u044d\u043f\u044d"
    ],
    "name:cat_x_preferred":[
        "Karatepe"
    ],
    "name:deu_x_preferred":[
        "Karatepe-Arslanta\u015f"
    ],
    "name:fra_x_preferred":[
        "Karatepe"
    ],
    "name:heb_x_preferred":[
        "\u05e7\u05d0\u05e8\u05d0\u05d8\u05e4\u05d4"
    ],
    "name:ita_x_preferred":[
        "Karatepe"
    ],
    "name:jpn_x_preferred":[
        "\u30ab\u30e9\u30c6\u30da"
    ],
    "name:nld_x_preferred":[
        "Karatepe"
    ],
    "name:por_x_preferred":[
        "Karatepe"
    ],
    "name:rus_x_preferred":[
        "\u041a\u0430\u0440\u0430\u0442\u0435\u043f\u0435"
    ],
    "name:sah_x_preferred":[
        "\u041a\u0430\u0440\u0430\u0442\u0435\u043f\u0435"
    ],
    "name:spa_x_preferred":[
        "Karatepe"
    ],
    "name:tur_x_preferred":[
        "Karatepe"
    ],
    "name:vie_x_preferred":[
        "Karatepe"
    ],
    "wof:name":"Karatepe",
    "wof:placetype":"locality"
},
  "geometry": {"coordinates":[36.23597,37.25934],"type":"Point"}
}