{
  "type": "Feature",
  "properties": {
    "gn:admin1_code":"87",
    "gn:asciiname":"Asagi Sofuoglu",
    "gn:country_code":"TR",
    "gn:dem":396,
    "gn:feature_class":"P",
    "gn:feature_code":"PPL",
    "gn:name":"A\u015fa\u011f\u0131 Sofuo\u011flu",
    "gn:population":0,
    "gn:timezone":"Europe/Istanbul",
    "iso:country":"TR",
    "wof:name":"Asagi Sofuoglu",
    "wof:placetype":"locality"
},
  "geometry": {"coordinates":[32.49622,41.44003],"type":"Point"}
}