{
  "type": "Feature",
  "properties": {
    "gn:country":"TR",
    "gn:fcode":"PPL",
    "gn:population":3317,
    "iso:country":"TR",
    "name:ast_x_preferred":[
        "Akk\u0131\u015fla"
    ],
    "name:aze_x_preferred":[
        "A\u011fq\u0131\u015fla"
    ],
    "name:ceb_x_preferred":[
        "Akk\u0131\u015fla \u0130l\u00e7esi"
    ],
    "name:che_x_preferred":[
        "\u0410\u043a\u043a\u0438\u0448\u043b\u0430"
    ],
    "name:deu_x_preferred":[
        "Akk\u0131\u015fla"
    ],
    "name:eng_x_preferred":[
        "Akk\u0131\u015fla"
    ],
    "name:fas_x_preferred":[
        "\u0627\u06a9\u06cc\u0634\u0644\u0627"
    ],
    "name:fra_x_preferred":[
        "Akk\u0131\u015fla"
    ],
    "name:ita_x_preferred":[
        "Distretto di Akk\u0131\u015fla"
    ],
    "name:mrj_x_preferred":[
        "\u0410\u043a\u043a\u044b\u0448\u043b\u0430"
    ],
    "name:msa_x_preferred":[
        "Akk\u0131\u015fla"
    ],
    "name:nan_x_preferred":[
        "Akk\u0131\u015fla"
    ],
    "name:nld_x_preferred":[
        "Akk\u0131\u015fla"
    ],
    "name:nob_x_preferred":[
        "Akk\u0131\u015fla"
    ],
    "name:pnb_x_preferred":[
        "\u0636\u0644\u0639 \u0627\u06a9\u06cc\u0634\u0644\u0627"
    ],
    "name:rus_x_preferred":[
        "\u0410\u043a\u043a\u044b\u0448\u043b\u0430"
    ],
    "name:swa_x_preferred":[
        "Akk\u0131\u015fla"
    ],
    "name:tat_x_preferred":[
        "\u0410\u043a\u043a\u044b\u0448\u043b\u0430"
    ],
    "name:tur_x_preferred":[
        "Akk\u0131\u015fla"
    ],
    "name:urd_x_preferred":[
        "\u0622\u0642\u06a9\u06cc\u0634\u0644\u06c1"
    ],
    "name:uzb_x_preferred":[
        "Akkishla"
    ],
    "name:vie_x_preferred":[
        "Akk\u0131\u015fla"
    ],
    "qs:name":"Akk\u0131\u015fla",
    "qs:name_adm0":"Turkey",
    "qs:name_adm1":"Kayseri",
    "qs:photos_9r":0,
    "qs:photos_sr":0,
    "qs:placetype":"Town",
    "qs:pop_sr":"4",
    "wd:wordcount":144,
    "wof:name":"Akk\u0131\u015fla",
    "wof:placetype":"locality",
    "wof:population":3317
},
  "geometry": {"coordinates":[36.17381,39.00222],"type":"Point"}
}