{
  "type": "Feature",
  "properties": {
    "gn:admin1_code":"66",
    "gn:asciiname":"Asagi Karahacili",
    "gn:cc2":"TR",
    "gn:country_code":"TR",
    "gn:dem":1087,
    "gn:feature_class":"P",
    "gn:feature_code":"PPL",
    "gn:name":"A\u015fa\u011f\u0131 Karahac\u0131l\u0131",
    "gn:population":0,
    "gn:timezone":"Europe/Istanbul",
    "iso:country":"TR",
    "name:und_x_variant":[
        "Karahac\u0131l\u0131",
        "A\u015fa\u011f\u0131 Karahac\u0131l\u0131"
    ],
    "wof:name":"Asagi Karahacili",
    "wof:placetype":"locality"
},
  "geometry": {"coordinates":[35.16667,39.66667],"type":"Point"}
}