{
  "type": "Feature",
  "properties": {
    "gn:admin1_code":"32",
    "gn:asciiname":"Ciftlik",
    "gn:cc2":"TR",
    "gn:country_code":"TR",
    "gn:dem":72,
    "gn:feature_class":"P",
    "gn:feature_code":"PPL",
    "gn:name":"\u00c7iftlik",
    "gn:population":0,
    "gn:timezone":"Europe/Istanbul",
    "iso:country":"TR",
    "name:und_x_variant":[
        "\u00c7iftlikk\u00f6y",
        "\u00c7iftlik"
    ],
    "wof:name":"Ciftlik",
    "wof:placetype":"locality"
},
  "geometry": {"coordinates":[34.53325,36.77956],"type":"Point"}
}