{
  "type": "Feature",
  "properties": {
    "gn:admin1_code":"40",
    "gn:asciiname":"Kurancili",
    "gn:country_code":"TR",
    "gn:dem":1276,
    "gn:feature_class":"P",
    "gn:feature_code":"PPL",
    "gn:name":"Kuranc\u0131l\u0131",
    "gn:population":0,
    "gn:timezone":"Europe/Istanbul",
    "iso:country":"TR",
    "wof:name":"Kurancili",
    "wof:placetype":"locality"
},
  "geometry": {"coordinates":[33.90019,39.33075],"type":"Point"}
}