{
  "type": "Feature",
  "properties": {
    "gn:admin1_code":"75",
    "gn:asciiname":"Cimenliyenikoy",
    "gn:country_code":"TR",
    "gn:dem":1011,
    "gn:feature_class":"P",
    "gn:feature_code":"PPL",
    "gn:name":"\u00c7imenliyenik\u00f6y",
    "gn:population":0,
    "gn:timezone":"Europe/Istanbul",
    "iso:country":"TR",
    "name:und_x_variant":[
        "\u00c7imenliyenik\u00f6y",
        "\u00c7imeliyenik\u00f6y",
        "\u00c7imenli"
    ],
    "wof:name":"Cimenliyenikoy",
    "wof:placetype":"locality"
},
  "geometry": {"coordinates":[33.90671,38.48762],"type":"Point"}
}