{
  "type": "Feature",
  "properties": {
    "gn:admin1_code":"37.0",
    "gn:asciiname":"Pelitoren",
    "gn:country_code":"TR",
    "gn:dem":1055,
    "gn:feature_class":"P",
    "gn:feature_code":"PPL",
    "gn:name":"Pelit\u00f6ren",
    "gn:population":0,
    "gn:timezone":"Europe/Istanbul",
    "iso:country":"TR",
    "name:und_x_variant":[
        "Pelitviran",
        "Pelit\u00f6ren"
    ],
    "wof:name":"Pelitoren",
    "wof:placetype":"locality"
},
  "geometry": {"coordinates":[33.32017,41.30083],"type":"Point"}
}