{
  "type": "Feature",
  "properties": {
    "gn:admin1_code":"85.0",
    "gn:asciiname":"Doplar",
    "gn:country_code":"TR",
    "gn:dem":345,
    "gn:feature_class":"P",
    "gn:feature_code":"PPL",
    "gn:name":"Doplar",
    "gn:population":0,
    "gn:timezone":"Europe/Istanbul",
    "iso:country":"TR",
    "name:und_x_variant":[
        "Musa"
    ],
    "wof:name":"Doplar",
    "wof:placetype":"locality"
},
  "geometry": {"coordinates":[31.62139,41.1778],"type":"Point"}
}