{
  "type": "Feature",
  "properties": {
    "gn:admin1_code":"45",
    "gn:asciiname":"Bunyan Osmaniye",
    "gn:country_code":"TR",
    "gn:dem":159,
    "gn:feature_class":"P",
    "gn:feature_code":"PPL",
    "gn:name":"B\u00fcnyan Osmaniye",
    "gn:population":0,
    "gn:timezone":"Europe/Istanbul",
    "iso:country":"TR",
    "name:tur_x_preferred":[
        "B\u00fcnyan Osmaniye"
    ],
    "wof:name":"Bunyan Osmaniye",
    "wof:placetype":"locality"
},
  "geometry": {"coordinates":[27.70934,38.95961],"type":"Point"}
}