{
  "type": "Feature",
  "properties": {
    "gn:admin1_code":"31.0",
    "gn:asciiname":"Ovakent",
    "gn:country_code":"TR",
    "gn:dem":93,
    "gn:feature_class":"P",
    "gn:feature_code":"PPL",
    "gn:name":"Ovakent",
    "gn:population":0,
    "gn:timezone":"Europe/Istanbul",
    "iso:country":"TR",
    "name:und_x_variant":[
        "Osmana\u011fa"
    ],
    "wof:name":"Ovakent",
    "wof:placetype":"locality"
},
  "geometry": {"coordinates":[36.23619,36.38665],"type":"Point"}
}