{
  "type": "Feature",
  "properties": {
    "gn:country":"TR",
    "gn:fcode":"PPL",
    "gn:population":744,
    "iso:country":"TR",
    "name:tur_x_preferred":[
        "Cevizlik"
    ],
    "name:und_x_variant":[
        "Dzhevzat"
    ],
    "qs:name":"Cevizlik",
    "qs:photos_9r":0,
    "qs:photos_sr":0,
    "qs:pop_sr":"2",
    "wof:name":"Cevizlik",
    "wof:placetype":"locality",
    "wof:population":744
},
  "geometry": {"coordinates":[40.56917,37.38444],"type":"Point"}
}