{
  "type": "Feature",
  "properties": {
    "gn:admin1_code":"58.0",
    "gn:asciiname":"Alibeyli",
    "gn:country_code":"TR",
    "gn:dem":1155,
    "gn:feature_class":"P",
    "gn:feature_code":"PPL",
    "gn:name":"Alibeyli",
    "gn:population":0,
    "gn:timezone":"Europe/Istanbul",
    "iso:country":"TR",
    "name:eng_x_preferred":[
        "Alibeyli"
    ],
    "name:rus_x_preferred":[
        "\u0410\u043b\u0438\u0431\u0435\u0439\u043b\u0438"
    ],
    "wof:name":"Alibeyli",
    "wof:placetype":"locality"
},
  "geometry": {"coordinates":[37.32212,40.15508],"type":"Point"}
}