{
  "type": "Feature",
  "properties": {
    "gn:admin1_code":"45",
    "gn:asciiname":"Karaselendi",
    "gn:country_code":"TR",
    "gn:dem":490,
    "gn:feature_class":"P",
    "gn:feature_code":"PPL",
    "gn:name":"Karaselendi",
    "gn:population":0,
    "gn:timezone":"Europe/Istanbul",
    "iso:country":"TR",
    "name:tur_x_preferred":[
        "Karaselendi"
    ],
    "wof:name":"Karaselendi",
    "wof:placetype":"locality"
},
  "geometry": {"coordinates":[28.82271,38.75365],"type":"Point"}
}