{
  "type": "Feature",
  "properties": {
    "gn:admin1_code":"63.0",
    "gn:asciiname":"Kopuz",
    "gn:country_code":"TR",
    "gn:dem":463,
    "gn:feature_class":"P",
    "gn:feature_code":"PPL",
    "gn:name":"Kopuz",
    "gn:population":0,
    "gn:timezone":"Europe/Istanbul",
    "iso:country":"TR",
    "wof:name":"Kopuz",
    "wof:placetype":"locality"
},
  "geometry": {"coordinates":[38.50056,36.86556],"type":"Point"}
}