{
  "type": "Feature",
  "properties": {
    "gn:admin1_code":"17",
    "gn:asciiname":"Koseler",
    "gn:country_code":"TR",
    "gn:dem":356,
    "gn:feature_class":"P",
    "gn:feature_code":"PPL",
    "gn:name":"K\u00f6seler",
    "gn:population":0,
    "gn:timezone":"Europe/Istanbul",
    "iso:country":"TR",
    "name:tur_x_preferred":[
        "K\u00f6seler"
    ],
    "wof:name":"Koseler",
    "wof:placetype":"locality"
},
  "geometry": {"coordinates":[26.27205,39.67274000000001],"type":"Point"}
}