{
  "type": "Feature",
  "properties": {
    "gn:admin1_code":"87.0",
    "gn:asciiname":"Hatipler",
    "gn:country_code":"TR",
    "gn:dem":59,
    "gn:feature_class":"P",
    "gn:feature_code":"PPL",
    "gn:name":"Hatipler",
    "gn:population":0,
    "gn:timezone":"Europe/Istanbul",
    "iso:country":"TR",
    "name:und_x_variant":[
        "Karada\u011fl\u0131"
    ],
    "wof:name":"Hatipler",
    "wof:placetype":"locality"
},
  "geometry": {"coordinates":[32.1451,41.58689],"type":"Point"}
}