{
  "type": "Feature",
  "properties": {
    "gn:admin1_code":"21.0",
    "gn:asciiname":"Ortulu",
    "gn:country_code":"TR",
    "gn:dem":1135,
    "gn:feature_class":"P",
    "gn:feature_code":"PPL",
    "gn:name":"\u00d6rt\u00fcl\u00fc",
    "gn:population":0,
    "gn:timezone":"Europe/Istanbul",
    "iso:country":"TR",
    "name:tur_x_preferred":[
        "\u00d6rt\u00fcl\u00fc"
    ],
    "wof:name":"Ortulu",
    "wof:placetype":"locality"
},
  "geometry": {"coordinates":[40.54507,38.56212],"type":"Point"}
}