{
  "type": "Feature",
  "properties": {
    "gn:country":"TR",
    "gn:fcode":"PPL",
    "gn:population":811,
    "iso:country":"TR",
    "name:und_x_variant":[
        "\u00c7\u0131g\u0131ran"
    ],
    "qs:name":"Ke\u00e7ik\u0131ran",
    "qs:photos_9r":0,
    "qs:photos_sr":0,
    "qs:pop_sr":"2",
    "wof:name":"Ke\u00e7ik\u0131ran",
    "wof:placetype":"locality",
    "wof:population":811
},
  "geometry": {"coordinates":[38.98472,36.96611],"type":"Point"}
}