{
  "type": "Feature",
  "properties": {
    "gn:admin1_code":"14.0",
    "gn:asciiname":"Asmaca",
    "gn:country_code":"TR",
    "gn:dem":1212,
    "gn:feature_class":"P",
    "gn:feature_code":"PPL",
    "gn:name":"Asmaca",
    "gn:population":0,
    "gn:timezone":"Europe/Istanbul",
    "iso:country":"TR",
    "wof:name":"Asmaca",
    "wof:placetype":"locality"
},
  "geometry": {"coordinates":[32.53592,40.82916],"type":"Point"}
}