{
  "type": "Feature",
  "properties": {
    "gn:admin1_code":"11",
    "gn:asciiname":"Demirhanlar",
    "gn:country_code":"TR",
    "gn:dem":310,
    "gn:feature_class":"P",
    "gn:feature_code":"PPL",
    "gn:name":"Demirhanlar",
    "gn:population":0,
    "gn:timezone":"Europe/Istanbul",
    "iso:country":"TR",
    "name:tur_x_preferred":[
        "Demirhanlar"
    ],
    "wof:name":"Demirhanlar",
    "wof:placetype":"locality"
},
  "geometry": {"coordinates":[30.19106,40.20132],"type":"Point"}
}