{
  "type": "Feature",
  "properties": {
    "gn:admin1_code":"49.0",
    "gn:asciiname":"Asagi Kicik",
    "gn:country_code":"TR",
    "gn:dem":1726,
    "gn:feature_class":"P",
    "gn:feature_code":"PPL",
    "gn:name":"A\u015fa\u011f\u0131 K\u0131c\u0131k",
    "gn:population":0,
    "gn:timezone":"Europe/Istanbul",
    "iso:country":"TR",
    "name:tur_x_preferred":[
        "A\u015fa\u011f\u0131 K\u0131c\u0131k"
    ],
    "wof:name":"Asagi Kicik",
    "wof:placetype":"locality"
},
  "geometry": {"coordinates":[42.38285,39.26812],"type":"Point"}
}