{
  "type": "Feature",
  "properties": {
    "gn:admin1_code":"45",
    "gn:asciiname":"Durasilli",
    "gn:cc2":"TR",
    "gn:country_code":"TR",
    "gn:dem":99,
    "gn:feature_class":"P",
    "gn:feature_code":"PPL",
    "gn:name":"Duras\u0131ll\u0131",
    "gn:population":0,
    "gn:timezone":"Europe/Istanbul",
    "iso:country":"TR",
    "name:tur_x_preferred":[
        "Duras\u0131l"
    ],
    "name:und_x_variant":[
        "Duras\u0131ll\u0131"
    ],
    "wof:name":"Durasilli",
    "wof:placetype":"locality"
},
  "geometry": {"coordinates":[28.24861,38.51806],"type":"Point"}
}