{
  "type": "Feature",
  "properties": {
    "gn:admin1_code":"5.0",
    "gn:asciiname":"Saraycik",
    "gn:country_code":"TR",
    "gn:dem":960,
    "gn:feature_class":"P",
    "gn:feature_code":"PPL",
    "gn:name":"Sarayc\u0131k",
    "gn:population":0,
    "gn:timezone":"Europe/Istanbul",
    "iso:country":"TR",
    "wof:name":"Saraycik",
    "wof:placetype":"locality"
},
  "geometry": {"coordinates":[35.9533,40.62246],"type":"Point"}
}