{
  "type": "Feature",
  "properties": {
    "gn:admin1_code":"17.0",
    "gn:asciiname":"Aladag",
    "gn:country_code":"TR",
    "gn:dem":212,
    "gn:feature_class":"P",
    "gn:feature_code":"PPL",
    "gn:name":"Alada\u011f",
    "gn:population":0,
    "gn:timezone":"Europe/Istanbul",
    "iso:country":"TR",
    "name:tur_x_preferred":[
        "Alada\u011f"
    ],
    "wof:name":"Aladag",
    "wof:placetype":"locality"
},
  "geometry": {"coordinates":[26.26868,39.77003],"type":"Point"}
}