{
  "type": "Feature",
  "properties": {
    "gn:admin1_code":"61.0",
    "gn:asciiname":"Erginkoy",
    "gn:country_code":"TR",
    "gn:dem":853,
    "gn:feature_class":"P",
    "gn:feature_code":"PPL",
    "gn:name":"Ergink\u00f6y",
    "gn:population":0,
    "gn:timezone":"Europe/Istanbul",
    "iso:country":"TR",
    "name:und_x_variant":[
        "Armanos",
        "Ergin",
        "Armenos",
        "Armenoz",
        "Ergink\u00f6y"
    ],
    "wof:name":"Erginkoy",
    "wof:placetype":"locality"
},
  "geometry": {"coordinates":[39.68314,40.7958],"type":"Point"}
}