{
  "type": "Feature",
  "properties": {
    "gn:admin1_code":"25.0",
    "gn:asciiname":"Koguns",
    "gn:country_code":"TR",
    "gn:dem":2503,
    "gn:feature_class":"P",
    "gn:feature_code":"PPL",
    "gn:name":"Koguns",
    "gn:population":0,
    "gn:timezone":"Europe/Istanbul",
    "iso:country":"TR",
    "name:und_x_variant":[
        "Ko\u011fans"
    ],
    "wof:name":"Koguns",
    "wof:placetype":"locality"
},
  "geometry": {"coordinates":[41.25,40.28333],"type":"Point"}
}