{
  "type": "Feature",
  "properties": {
    "gn:admin1_code":"55.0",
    "gn:asciiname":"Sariyurt",
    "gn:country_code":"TR",
    "gn:dem":499,
    "gn:feature_class":"P",
    "gn:feature_code":"PPL",
    "gn:name":"Sar\u0131yurt",
    "gn:population":0,
    "gn:timezone":"Europe/Istanbul",
    "iso:country":"TR",
    "wof:name":"Sariyurt",
    "wof:placetype":"locality"
},
  "geometry": {"coordinates":[36.48149,41.10949],"type":"Point"}
}