{
  "type": "Feature",
  "properties": {
    "gn:admin1_code":"62",
    "gn:asciiname":"Lalusagi",
    "gn:country_code":"TR",
    "gn:dem":820,
    "gn:feature_class":"P",
    "gn:feature_code":"PPL",
    "gn:name":"L\u00e2lu\u015fa\u011f\u0131",
    "gn:population":0,
    "gn:timezone":"Europe/Istanbul",
    "iso:country":"TR",
    "wof:name":"Lalusagi",
    "wof:placetype":"locality"
},
  "geometry": {"coordinates":[38.88333,38.91667],"type":"Point"}
}