{
  "type": "Feature",
  "properties": {
    "gn:admin1_code":"21.0",
    "gn:asciiname":"Yukari Ortaoren",
    "gn:country_code":"TR",
    "gn:dem":861,
    "gn:feature_class":"P",
    "gn:feature_code":"PPL",
    "gn:name":"Yukar\u0131 Orta\u00f6ren",
    "gn:population":0,
    "gn:timezone":"Europe/Istanbul",
    "iso:country":"TR",
    "name:tur_x_preferred":[
        "Yukar\u0131 Orta\u00f6ren"
    ],
    "wof:name":"Yukari Ortaoren",
    "wof:placetype":"locality"
},
  "geometry": {"coordinates":[40.1971,37.56254000000001],"type":"Point"}
}