{
  "type": "Feature",
  "properties": {
    "gn:admin1_code":"13.0",
    "gn:asciiname":"Top",
    "gn:country_code":"TR",
    "gn:dem":1917,
    "gn:feature_class":"P",
    "gn:feature_code":"PPL",
    "gn:name":"Top",
    "gn:population":0,
    "gn:timezone":"Europe/Istanbul",
    "iso:country":"TR",
    "name:tur_x_preferred":[
        "Top"
    ],
    "wof:name":"Top",
    "wof:placetype":"locality"
},
  "geometry": {"coordinates":[42.28334,38.41811],"type":"Point"}
}