{
  "type": "Feature",
  "properties": {
    "gn:admin1_code":"80.0",
    "gn:asciiname":"Camanizar",
    "gn:country_code":"TR",
    "gn:dem":1240,
    "gn:feature_class":"P",
    "gn:feature_code":"PPL",
    "gn:name":"Camanizar",
    "gn:population":0,
    "gn:timezone":"Europe/Istanbul",
    "iso:country":"TR",
    "name:tur_x_preferred":[
        "Camanizar"
    ],
    "wof:name":"Camanizar",
    "wof:placetype":"locality"
},
  "geometry": {"coordinates":[43.12502,37.47289],"type":"Point"}
}