{
  "type": "Feature",
  "properties": {
    "gn:admin1_code":"21",
    "gn:asciiname":"Yesilce",
    "gn:country_code":"TR",
    "gn:dem":922,
    "gn:feature_class":"P",
    "gn:feature_code":"PPL",
    "gn:name":"Ye\u015filce",
    "gn:population":0,
    "gn:timezone":"Europe/Istanbul",
    "iso:country":"TR",
    "name:und_x_variant":[
        "Ye\u015filce",
        "Havrik"
    ],
    "wof:name":"Yesilce",
    "wof:placetype":"locality"
},
  "geometry": {"coordinates":[40.91667,38.43333],"type":"Point"}
}