{
  "type": "Feature",
  "properties": {
    "gn:admin1_code":"25.0",
    "gn:asciiname":"Ahburik",
    "gn:cc2":"TR",
    "gn:country_code":"TR",
    "gn:dem":1841,
    "gn:feature_class":"P",
    "gn:feature_code":"PPL",
    "gn:name":"Ahburik",
    "gn:population":0,
    "gn:timezone":"Europe/Istanbul",
    "iso:country":"TR",
    "name:eng_x_preferred":[
        "Ahburik"
    ],
    "name:rus_x_preferred":[
        "\u0410\u0445\u0431\u0443\u0440\u0438\u043a"
    ],
    "name:und_x_variant":[
        "Ahpirik",
        "Ahpurik Mahallesi",
        "Ahburik"
    ],
    "wof:name":"Ahburik",
    "wof:placetype":"locality"
},
  "geometry": {"coordinates":[41.03333,40.56667],"type":"Point"}
}