{
  "type": "Feature",
  "properties": {
    "gn:admin1_code":"21",
    "gn:asciiname":"Selyazi",
    "gn:country_code":"TR",
    "gn:dem":751,
    "gn:feature_class":"P",
    "gn:feature_code":"PPL",
    "gn:name":"Selyazi",
    "gn:population":0,
    "gn:timezone":"Europe/Istanbul",
    "iso:country":"TR",
    "name:tur_x_preferred":[
        "Selyazi"
    ],
    "name:und_x_variant":[
        "Salyaz\u0131",
        "Melki\u015f"
    ],
    "wof:name":"Selyazi",
    "wof:placetype":"locality"
},
  "geometry": {"coordinates":[40.23939,37.73111],"type":"Point"}
}