{
  "type": "Feature",
  "properties": {
    "gn:admin1_code":"43",
    "gn:asciiname":"Ucler",
    "gn:country_code":"TR",
    "gn:dem":947,
    "gn:feature_class":"P",
    "gn:feature_code":"PPL",
    "gn:name":"\u00dc\u00e7ler",
    "gn:population":0,
    "gn:timezone":"Europe/Istanbul",
    "iso:country":"TR",
    "name:tur_x_preferred":[
        "\u00dc\u00e7ler"
    ],
    "name:tur_x_variant":[
        "B\u00f6l\u00fccek"
    ],
    "wof:name":"Ucler",
    "wof:placetype":"locality"
},
  "geometry": {"coordinates":[29.94178,39.44549],"type":"Point"}
}