{
  "type": "Feature",
  "properties": {
    "gn:admin1_code":"21",
    "gn:asciiname":"Tekkaynak",
    "gn:country_code":"TR",
    "gn:dem":629,
    "gn:feature_class":"P",
    "gn:feature_code":"PPL",
    "gn:name":"Tekkaynak",
    "gn:population":0,
    "gn:timezone":"Europe/Istanbul",
    "iso:country":"TR",
    "name:und_x_variant":[
        "G\u00fczel\u015feyh"
    ],
    "wof:name":"Tekkaynak",
    "wof:placetype":"locality"
},
  "geometry": {"coordinates":[40.42965,37.79284000000001],"type":"Point"}
}