{
  "type": "Feature",
  "properties": {
    "gn:admin1_code":"09",
    "gn:asciiname":"Ortulu",
    "gn:country_code":"TR",
    "gn:dem":838,
    "gn:feature_class":"P",
    "gn:feature_code":"PPL",
    "gn:name":"\u00d6rt\u00fcl\u00fc",
    "gn:population":0,
    "gn:timezone":"Europe/Istanbul",
    "iso:country":"TR",
    "wof:name":"Ortulu",
    "wof:placetype":"locality"
},
  "geometry": {"coordinates":[28.45972,37.54944],"type":"Point"}
}