{
  "type": "Feature",
  "properties": {
    "gn:admin1_code":"57.0",
    "gn:asciiname":"Okcumehmetli",
    "gn:country_code":"TR",
    "gn:dem":324,
    "gn:feature_class":"P",
    "gn:feature_code":"PPL",
    "gn:name":"Ok\u00e7umehmetli",
    "gn:population":0,
    "gn:timezone":"Europe/Istanbul",
    "iso:country":"TR",
    "name:tur_x_preferred":[
        "Ok\u00e7umehmetli"
    ],
    "name:und_x_variant":[
        "Karab\u00fcr\u00e7ek"
    ],
    "wof:name":"Okcumehmetli",
    "wof:placetype":"locality"
},
  "geometry": {"coordinates":[34.66678,41.5785],"type":"Point"}
}