{
  "type": "Feature",
  "properties": {
    "gn:admin1_code":"24",
    "gn:asciiname":"Pinarlikaya",
    "gn:country_code":"TR",
    "gn:dem":1939,
    "gn:feature_class":"P",
    "gn:feature_code":"PPL",
    "gn:name":"P\u0131narl\u0131kaya",
    "gn:population":0,
    "gn:timezone":"Europe/Istanbul",
    "iso:country":"TR",
    "name:tur_x_preferred":[
        "P\u0131narl\u0131kaya"
    ],
    "wof:name":"Pinarlikaya",
    "wof:placetype":"locality"
},
  "geometry": {"coordinates":[39.87065,39.6474],"type":"Point"}
}