{
  "type": "Feature",
  "properties": {
    "gn:admin1_code":"78",
    "gn:asciiname":"Daran",
    "gn:country_code":"TR",
    "gn:dem":877,
    "gn:feature_class":"P",
    "gn:feature_code":"PPL",
    "gn:name":"Daran",
    "gn:population":0,
    "gn:timezone":"Europe/Istanbul",
    "iso:country":"TR",
    "name:und_x_variant":[
        "Darank\u00f6y",
        "Daran"
    ],
    "wof:name":"Daran",
    "wof:placetype":"locality"
},
  "geometry": {"coordinates":[32.68012,36.56314],"type":"Point"}
}