{
  "type": "Feature",
  "properties": {
    "gn:admin1_code":"39.0",
    "gn:asciiname":"Yesilova",
    "gn:cc2":"TR",
    "gn:country_code":"TR",
    "gn:dem":41,
    "gn:feature_class":"P",
    "gn:feature_code":"PPL",
    "gn:name":"Ye\u015filova",
    "gn:population":0,
    "gn:timezone":"Europe/Istanbul",
    "iso:country":"TR",
    "name:und_x_variant":[
        "Burunsuz",
        "Ye\u015filova"
    ],
    "wof:name":"Yesilova",
    "wof:placetype":"locality"
},
  "geometry": {"coordinates":[26.91444000000001,41.42917],"type":"Point"}
}