{
  "type": "Feature",
  "properties": {
    "gn:admin1_code":"14",
    "gn:asciiname":"Deveci",
    "gn:country_code":"TR",
    "gn:dem":1179,
    "gn:feature_class":"P",
    "gn:feature_code":"PPL",
    "gn:name":"Deveci",
    "gn:population":0,
    "gn:timezone":"Europe/Istanbul",
    "iso:country":"TR",
    "name:tur_x_preferred":[
        "Deveci"
    ],
    "name:tur_x_variant":[
        "Deveciler"
    ],
    "wof:name":"Deveci",
    "wof:placetype":"locality"
},
  "geometry": {"coordinates":[31.89023,40.37628],"type":"Point"}
}