{
  "type": "Feature",
  "properties": {
    "gn:admin1_code":"86.0",
    "gn:asciiname":"Yakinsu",
    "gn:country_code":"TR",
    "gn:dem":1906,
    "gn:feature_class":"P",
    "gn:feature_code":"PPL",
    "gn:name":"Yak\u0131nsu",
    "gn:population":0,
    "gn:timezone":"Europe/Istanbul",
    "iso:country":"TR",
    "name:eng_x_preferred":[
        "Yak\u0131nsu"
    ],
    "name:rus_x_preferred":[
        "\u042f\u043a\u044b\u043d\u0441\u0443"
    ],
    "name:und_x_variant":[
        "Suhara"
    ],
    "wof:name":"Yakinsu",
    "wof:placetype":"locality"
},
  "geometry": {"coordinates":[43.21509,41.14194000000001],"type":"Point"}
}