{
  "type": "Feature",
  "properties": {
    "gn:admin1_code":"52.0",
    "gn:asciiname":"Beylerli",
    "gn:country_code":"TR",
    "gn:dem":712,
    "gn:feature_class":"P",
    "gn:feature_code":"PPL",
    "gn:name":"Beylerli",
    "gn:population":0,
    "gn:timezone":"Europe/Istanbul",
    "iso:country":"TR",
    "wof:name":"Beylerli",
    "wof:placetype":"locality"
},
  "geometry": {"coordinates":[37.4611,40.71353],"type":"Point"}
}