{
  "type": "Feature",
  "properties": {
    "gn:admin1_code":"07",
    "gn:asciiname":"Kemerkoy",
    "gn:country_code":"TR",
    "gn:dem":305,
    "gn:feature_class":"P",
    "gn:feature_code":"PPL",
    "gn:name":"Kemerk\u00f6y",
    "gn:population":0,
    "gn:timezone":"Europe/Istanbul",
    "iso:country":"TR",
    "name:und_x_variant":[
        "Kemerk\u00f6y",
        "Kemer"
    ],
    "wof:name":"Kemerkoy",
    "wof:placetype":"locality"
},
  "geometry": {"coordinates":[29.71306,36.35654],"type":"Point"}
}