{
  "type": "Feature",
  "properties": {
    "gn:admin1_code":"16.0",
    "gn:asciiname":"Ipekyayla",
    "gn:country_code":"TR",
    "gn:dem":371,
    "gn:feature_class":"P",
    "gn:feature_code":"PPL",
    "gn:name":"\u0130pekyayla",
    "gn:population":0,
    "gn:timezone":"Europe/Istanbul",
    "iso:country":"TR",
    "name:und_x_variant":[
        "K\u0131z\u0131lk\u00f6y",
        "\u0130pekyayla"
    ],
    "wof:name":"Ipekyayla",
    "wof:placetype":"locality"
},
  "geometry": {"coordinates":[28.823,40.33296],"type":"Point"}
}