{
  "type": "Feature",
  "properties": {
    "gn:admin1_code":"64",
    "gn:asciiname":"Dagdemirler",
    "gn:country_code":"TR",
    "gn:dem":1261,
    "gn:feature_class":"P",
    "gn:feature_code":"PPL",
    "gn:name":"Da\u011fdemirler",
    "gn:population":0,
    "gn:timezone":"Europe/Istanbul",
    "iso:country":"TR",
    "wof:name":"Dagdemirler",
    "wof:placetype":"locality"
},
  "geometry": {"coordinates":[29.45289,38.75495],"type":"Point"}
}