{
  "type": "Feature",
  "properties": {
    "gn:admin1_code":"38",
    "gn:asciiname":"Asagiborandere",
    "gn:country_code":"TR",
    "gn:dem":1585,
    "gn:feature_class":"P",
    "gn:feature_code":"PPL",
    "gn:name":"A\u015fa\u011f\u0131borandere",
    "gn:population":0,
    "gn:timezone":"Europe/Istanbul",
    "iso:country":"TR",
    "name:und_x_variant":[
        "A\u015fa\u011f\u0131boran",
        "A\u015fa\u011f\u0131 Boranderek\u00f6y",
        "A\u015fa\u011f\u0131borandere"
    ],
    "wof:name":"Asagiborandere",
    "wof:placetype":"locality"
},
  "geometry": {"coordinates":[36.51225,38.77639],"type":"Point"}
}