{
  "type": "Feature",
  "properties": {
    "gn:admin1_code":"31.0",
    "gn:asciiname":"Ashagy-Zyulyuflyukhan",
    "gn:country_code":"TR",
    "gn:dem":87,
    "gn:feature_class":"P",
    "gn:feature_code":"PPL",
    "gn:name":"Ashagy-Zyulyuflyukhan",
    "gn:population":0,
    "gn:timezone":"Europe/Istanbul",
    "iso:country":"TR",
    "name:tur_x_preferred":[
        "Z\u00fcl\u00fcfl\u00fchan"
    ],
    "name:und_x_variant":[
        "A\u015fa\u011f\u0131 Z\u00fcl\u00fcfl\u00fchan"
    ],
    "wof:name":"Ashagy-Zyulyuflyukhan",
    "wof:placetype":"locality"
},
  "geometry": {"coordinates":[36.22694,36.32861],"type":"Point"}
}