{
  "type": "Feature",
  "properties": {
    "gn:admin1_code":"92.0",
    "gn:asciiname":"Laledere",
    "gn:country_code":"TR",
    "gn:dem":199,
    "gn:feature_class":"P",
    "gn:feature_code":"PPL",
    "gn:name":"L\u00e2ledere",
    "gn:population":0,
    "gn:timezone":"Europe/Istanbul",
    "iso:country":"TR",
    "name:tur_x_preferred":[
        "L\u00e2ledere"
    ],
    "wof:name":"Laledere",
    "wof:placetype":"locality"
},
  "geometry": {"coordinates":[29.36724,40.60612],"type":"Point"}
}