{
  "type": "Feature",
  "properties": {
    "gn:admin1_code":"07",
    "gn:asciiname":"Kundu",
    "gn:country_code":"TR",
    "gn:dem":4,
    "gn:feature_class":"P",
    "gn:feature_code":"PPL",
    "gn:name":"Kundu",
    "gn:population":0,
    "gn:timezone":"Europe/Istanbul",
    "iso:country":"TR",
    "name:tur_x_preferred":[
        "Kundu"
    ],
    "name:und_x_variant":[
        "\u00d6zl\u00fc"
    ],
    "wof:name":"Kundu",
    "wof:placetype":"locality"
},
  "geometry": {"coordinates":[30.90422,36.87174],"type":"Point"}
}