{
  "type": "Feature",
  "properties": {
    "gn:admin1_code":"17.0",
    "gn:asciiname":"Kirli Ciftligi",
    "gn:country_code":"TR",
    "gn:dem":52,
    "gn:feature_class":"P",
    "gn:feature_code":"PPL",
    "gn:name":"K\u0131rl\u0131 \u00c7iftli\u011fi",
    "gn:population":0,
    "gn:timezone":"Europe/Istanbul",
    "iso:country":"TR",
    "name:tur_x_preferred":[
        "K\u0131rl\u0131 \u00c7iftli\u011fi"
    ],
    "wof:name":"Kirli Ciftligi",
    "wof:placetype":"locality"
},
  "geometry": {"coordinates":[27.22638,40.38359000000001],"type":"Point"}
}