{
  "type": "Feature",
  "properties": {
    "gn:country":"TR",
    "gn:fcode":"PPL",
    "gn:population":0,
    "iso:country":"TR",
    "name:tur_x_preferred":[
        "Hamitler"
    ],
    "qs:name":"Hamitler",
    "qs:name_adm0":"Turkey",
    "qs:name_adm1":"Bursa",
    "qs:photos_9k":1,
    "qs:photos_9r":1,
    "qs:photos_all":1,
    "qs:photos_sr":0,
    "qs:placetype":"Town",
    "qs:pop_sr":"0",
    "wof:name":"Hamitler",
    "wof:placetype":"locality",
    "wof:population":0
},
  "geometry": {"coordinates":[28.98333,40.25],"type":"Point"}
}