{
  "type": "Feature",
  "properties": {
    "gn:admin1_code":"17.0",
    "gn:asciiname":"Korucak",
    "gn:country_code":"TR",
    "gn:dem":426,
    "gn:feature_class":"P",
    "gn:feature_code":"PPL",
    "gn:name":"Korucak",
    "gn:population":0,
    "gn:timezone":"Europe/Istanbul",
    "iso:country":"TR",
    "wof:name":"Korucak",
    "wof:placetype":"locality"
},
  "geometry": {"coordinates":[26.77431,39.86309],"type":"Point"}
}