{
  "type": "Feature",
  "properties": {
    "gn:admin1_code":"64",
    "gn:asciiname":"Payam",
    "gn:country_code":"TR",
    "gn:dem":677,
    "gn:feature_class":"P",
    "gn:feature_code":"PPL",
    "gn:name":"Payam",
    "gn:population":0,
    "gn:timezone":"Europe/Istanbul",
    "iso:country":"TR",
    "name:tur_x_preferred":[
        "Payam"
    ],
    "wof:name":"Payam",
    "wof:placetype":"locality"
},
  "geometry": {"coordinates":[29.18961,38.78505],"type":"Point"}
}