{
  "type": "Feature",
  "properties": {
    "gn:admin1_code":"83.0",
    "gn:asciiname":"Ugurtepe",
    "gn:country_code":"TR",
    "gn:dem":770,
    "gn:feature_class":"P",
    "gn:feature_code":"PPL",
    "gn:name":"U\u011furtepe",
    "gn:population":0,
    "gn:timezone":"Europe/Istanbul",
    "iso:country":"TR",
    "name:und_x_variant":[
        "Tilibrakhim",
        "Tilibrahim",
        "U\u011furtepe"
    ],
    "wof:name":"Ugurtepe",
    "wof:placetype":"locality"
},
  "geometry": {"coordinates":[37.09472,36.9525],"type":"Point"}
}