{
  "type": "Feature",
  "properties": {
    "gn:admin1_code":"63.0",
    "gn:asciiname":"Toytepe",
    "gn:cc2":"TR",
    "gn:country_code":"TR",
    "gn:dem":363,
    "gn:feature_class":"P",
    "gn:feature_code":"PPL",
    "gn:name":"Toytepe",
    "gn:population":0,
    "gn:timezone":"Europe/Istanbul",
    "iso:country":"TR",
    "name:rus_x_preferred":[
        "Resmel\u2019khaber"
    ],
    "name:und_x_variant":[
        "Resmelhaber",
        "Toytepe"
    ],
    "wof:name":"Toytepe",
    "wof:placetype":"locality"
},
  "geometry": {"coordinates":[39.07917,36.84833],"type":"Point"}
}