{
  "type": "Feature",
  "properties": {
    "gn:admin1_code":"61.0",
    "gn:asciiname":"Calli",
    "gn:country_code":"TR",
    "gn:dem":137,
    "gn:feature_class":"P",
    "gn:feature_code":"PPL",
    "gn:name":"\u00c7all\u0131",
    "gn:population":0,
    "gn:timezone":"Europe/Istanbul",
    "iso:country":"TR",
    "name:und_x_variant":[
        "\u00c7all\u0131",
        "Bondika"
    ],
    "wof:name":"Calli",
    "wof:placetype":"locality"
},
  "geometry": {"coordinates":[39.4263,41.04574],"type":"Point"}
}