{
  "type": "Feature",
  "properties": {
    "gn:admin1_code":"17.0",
    "gn:asciiname":"Savastepe",
    "gn:country_code":"TR",
    "gn:dem":52,
    "gn:feature_class":"P",
    "gn:feature_code":"PPL",
    "gn:name":"Sava\u015ftepe",
    "gn:population":0,
    "gn:timezone":"Europe/Istanbul",
    "iso:country":"TR",
    "wof:name":"Savastepe",
    "wof:placetype":"locality"
},
  "geometry": {"coordinates":[27.18574000000001,40.24788],"type":"Point"}
}