{
  "type": "Feature",
  "properties": {
    "gn:admin1_code":"41",
    "gn:asciiname":"Gedikli",
    "gn:country_code":"TR",
    "gn:dem":248,
    "gn:feature_class":"P",
    "gn:feature_code":"PPL",
    "gn:name":"Gedikli",
    "gn:population":0,
    "gn:timezone":"Europe/Istanbul",
    "iso:country":"TR",
    "name:deu_x_preferred":[
        "Gedikli"
    ],
    "name:tur_x_preferred":[
        "Gedikli"
    ],
    "name:und_x_variant":[
        "Kabakl\u0131"
    ],
    "wof:name":"Gedikli",
    "wof:placetype":"locality"
},
  "geometry": {"coordinates":[30.11813,40.81173],"type":"Point"}
}