{
  "type": "Feature",
  "properties": {
    "gn:admin1_code":"71",
    "gn:asciiname":"Hasanmecen Yaylasi",
    "gn:country_code":"TR",
    "gn:dem":972,
    "gn:feature_class":"P",
    "gn:feature_code":"PPL",
    "gn:name":"Hasanme\u00e7en Yaylas\u0131",
    "gn:population":0,
    "gn:timezone":"Europe/Istanbul",
    "iso:country":"TR",
    "name:tur_x_preferred":[
        "Hasanme\u00e7en Yaylas\u0131"
    ],
    "name:und_x_variant":[
        "\u0130lhan Yaylas\u0131",
        "Hac\u0131bey Yaylas\u0131"
    ],
    "wof:name":"Hasanmecen Yaylasi",
    "wof:placetype":"locality"
},
  "geometry": {"coordinates":[32.86667,38.66667],"type":"Point"}
}