{
  "type": "Feature",
  "properties": {
    "gn:admin1_code":"38",
    "gn:asciiname":"Silahtar",
    "gn:country_code":"TR",
    "gn:dem":1493,
    "gn:feature_class":"P",
    "gn:feature_code":"PPL",
    "gn:name":"Silahtar",
    "gn:population":0,
    "gn:timezone":"Europe/Istanbul",
    "iso:country":"TR",
    "name:und_x_variant":[
        "Sil\u00e2hdar",
        "Silahtar"
    ],
    "wof:name":"Silahtar",
    "wof:placetype":"locality"
},
  "geometry": {"coordinates":[35.63874000000001,39.07492],"type":"Point"}
}