{
  "type": "Feature",
  "properties": {
    "gn:admin1_code":"37.0",
    "gn:asciiname":"Abay",
    "gn:country_code":"TR",
    "gn:dem":670,
    "gn:feature_class":"P",
    "gn:feature_code":"PPL",
    "gn:name":"Abay",
    "gn:population":0,
    "gn:timezone":"Europe/Istanbul",
    "iso:country":"TR",
    "name:ceb_x_preferred":[
        "Abay"
    ],
    "name:deu_x_preferred":[
        "Abay"
    ],
    "name:est_x_preferred":[
        "Abai"
    ],
    "name:kaa_x_preferred":[
        "Abay"
    ],
    "name:kaz_x_preferred":[
        "\u0410\u0431\u0430\u0439"
    ],
    "name:lit_x_preferred":[
        "Abajus"
    ],
    "name:rus_x_preferred":[
        "\u0410\u0431\u0430\u0439"
    ],
    "name:spa_x_preferred":[
        "Abay"
    ],
    "name:swe_x_preferred":[
        "Abay"
    ],
    "name:und_x_variant":[
        "Alibey"
    ],
    "name:uzb_x_preferred":[
        "Abay"
    ],
    "wof:name":"Abay",
    "wof:placetype":"locality"
},
  "geometry": {"coordinates":[33.9873,41.43768],"type":"Point"}
}