{
  "type": "Feature",
  "properties": {
    "gn:admin1_code":"61.0",
    "gn:asciiname":"Dagardi",
    "gn:country_code":"TR",
    "gn:dem":867,
    "gn:feature_class":"P",
    "gn:feature_code":"PPL",
    "gn:name":"Da\u011fard\u0131",
    "gn:population":0,
    "gn:timezone":"Europe/Istanbul",
    "iso:country":"TR",
    "wof:name":"Dagardi",
    "wof:placetype":"locality"
},
  "geometry": {"coordinates":[40.13876,40.76029000000001],"type":"Point"}
}