{
  "type": "Feature",
  "properties": {
    "gn:admin1_code":"46.0",
    "gn:asciiname":"Yeniyurt",
    "gn:country_code":"TR",
    "gn:dem":580,
    "gn:feature_class":"P",
    "gn:feature_code":"PPL",
    "gn:name":"Yeniyurt",
    "gn:population":0,
    "gn:timezone":"Europe/Istanbul",
    "iso:country":"TR",
    "name:und_x_variant":[
        "Itu\u015fa\u011f\u0131",
        "Yeniyurt"
    ],
    "wof:name":"Yeniyurt",
    "wof:placetype":"locality"
},
  "geometry": {"coordinates":[37.03631,37.44501],"type":"Point"}
}