{
  "type": "Feature",
  "properties": {
    "gn:admin1_code":"15",
    "gn:asciiname":"Yassipinar",
    "gn:country_code":"TR",
    "gn:dem":528,
    "gn:feature_class":"P",
    "gn:feature_code":"PPL",
    "gn:name":"Yass\u0131p\u0131nar",
    "gn:population":0,
    "gn:timezone":"Europe/Istanbul",
    "iso:country":"TR",
    "wof:name":"Yassipinar",
    "wof:placetype":"locality"
},
  "geometry": {"coordinates":[30.75277,37.27574],"type":"Point"}
}