{
  "type": "Feature",
  "properties": {
    "gn:admin1_code":"22.0",
    "gn:asciiname":"Vakif",
    "gn:country_code":"TR",
    "gn:dem":32,
    "gn:feature_class":"P",
    "gn:feature_code":"PPL",
    "gn:name":"Vak\u0131f",
    "gn:population":0,
    "gn:timezone":"Europe/Istanbul",
    "iso:country":"TR",
    "wof:name":"Vakif",
    "wof:placetype":"locality"
},
  "geometry": {"coordinates":[26.25716,40.61537],"type":"Point"}
}