{
  "type": "Feature",
  "properties": {
    "gn:admin1_code":"09",
    "gn:asciiname":"Alatepe",
    "gn:country_code":"TR",
    "gn:dem":399,
    "gn:feature_class":"P",
    "gn:feature_code":"PPL",
    "gn:name":"Alatepe",
    "gn:population":0,
    "gn:timezone":"Europe/Istanbul",
    "iso:country":"TR",
    "name:tur_x_preferred":[
        "Alatepe"
    ],
    "wof:name":"Alatepe",
    "wof:placetype":"locality"
},
  "geometry": {"coordinates":[27.8228,37.90414000000001],"type":"Point"}
}