{
  "type": "Feature",
  "properties": {
    "gn:admin1_code":"64",
    "gn:asciiname":"Kaykilli",
    "gn:country_code":"TR",
    "gn:dem":992,
    "gn:feature_class":"P",
    "gn:feature_code":"PPL",
    "gn:name":"Kayk\u0131ll\u0131",
    "gn:population":0,
    "gn:timezone":"Europe/Istanbul",
    "iso:country":"TR",
    "name:und_x_variant":[
        "Kayk\u0131l\u0131",
        "Kayk\u0131nl\u0131",
        "Kayk\u0131ll\u0131"
    ],
    "wof:name":"Kaykilli",
    "wof:placetype":"locality"
},
  "geometry": {"coordinates":[29.48567,38.30566],"type":"Point"}
}