{
  "type": "Feature",
  "properties": {
    "gn:admin1_code":"55.0",
    "gn:asciiname":"Devealan",
    "gn:country_code":"TR",
    "gn:dem":933,
    "gn:feature_class":"P",
    "gn:feature_code":"PPL",
    "gn:name":"Devealan",
    "gn:population":0,
    "gn:timezone":"Europe/Istanbul",
    "iso:country":"TR",
    "name:und_x_variant":[
        "Develan",
        "Devealan"
    ],
    "wof:name":"Devealan",
    "wof:placetype":"locality"
},
  "geometry": {"coordinates":[35.66274,41.25236],"type":"Point"}
}