{
  "type": "Feature",
  "properties": {
    "gn:admin1_code":"60.0",
    "gn:asciiname":"Konakkoy",
    "gn:country_code":"TR",
    "gn:dem":1413,
    "gn:feature_class":"P",
    "gn:feature_code":"PPL",
    "gn:name":"Konakk\u00f6y",
    "gn:population":0,
    "gn:timezone":"Europe/Istanbul",
    "iso:country":"TR",
    "name:tur_x_preferred":[
        "Konakk\u00f6y"
    ],
    "name:und_x_variant":[
        "Konak"
    ],
    "wof:name":"Konakkoy",
    "wof:placetype":"locality"
},
  "geometry": {"coordinates":[37.53391,40.48867],"type":"Point"}
}