{
  "type": "Feature",
  "properties": {
    "gn:admin1_code":"81",
    "gn:asciiname":"Ayakkif",
    "gn:country_code":"TR",
    "gn:dem":224,
    "gn:feature_class":"P",
    "gn:feature_code":"PPL",
    "gn:name":"Ayakk\u0131f",
    "gn:population":0,
    "gn:timezone":"Europe/Istanbul",
    "iso:country":"TR",
    "wof:name":"Ayakkif",
    "wof:placetype":"locality"
},
  "geometry": {"coordinates":[35.11667,37.21667],"type":"Point"}
}