{
  "type": "Feature",
  "properties": {
    "gn:admin1_code":"24",
    "gn:asciiname":"Yukari Kartalli",
    "gn:country_code":"TR",
    "gn:dem":1702,
    "gn:feature_class":"P",
    "gn:feature_code":"PPL",
    "gn:name":"Yukar\u0131 Kartall\u0131",
    "gn:population":0,
    "gn:timezone":"Europe/Istanbul",
    "iso:country":"TR",
    "name:tur_x_preferred":[
        "Yukar\u0131 Kartall\u0131"
    ],
    "name:und_x_variant":[
        "Yukar\u0131kartall\u0131"
    ],
    "wof:name":"Yukari Kartalli",
    "wof:placetype":"locality"
},
  "geometry": {"coordinates":[40.13918,39.76259],"type":"Point"}
}