{
  "type": "Feature",
  "properties": {
    "gn:admin1_code":"31.0",
    "gn:asciiname":"Cukuryurt",
    "gn:country_code":"TR",
    "gn:dem":1115,
    "gn:feature_class":"P",
    "gn:feature_code":"PPL",
    "gn:name":"\u00c7ukuryurt",
    "gn:population":0,
    "gn:timezone":"Europe/Istanbul",
    "iso:country":"TR",
    "name:tur_x_preferred":[
        "\u00c7ukuryurt"
    ],
    "wof:name":"Cukuryurt",
    "wof:placetype":"locality"
},
  "geometry": {"coordinates":[36.11195,36.41764000000001],"type":"Point"}
}