{
  "type": "Feature",
  "properties": {
    "gn:admin1_code":"37.0",
    "gn:asciiname":"Ermelik",
    "gn:country_code":"TR",
    "gn:dem":1000,
    "gn:feature_class":"P",
    "gn:feature_code":"PPL",
    "gn:name":"Ermelik",
    "gn:population":0,
    "gn:timezone":"Europe/Istanbul",
    "iso:country":"TR",
    "name:und_x_variant":[
        "Kuzyaka"
    ],
    "wof:name":"Ermelik",
    "wof:placetype":"locality"
},
  "geometry": {"coordinates":[33.98569000000001,41.00275],"type":"Point"}
}