{
  "type": "Feature",
  "properties": {
    "gn:admin1_code":"52.0",
    "gn:asciiname":"Bolatli",
    "gn:country_code":"TR",
    "gn:dem":458,
    "gn:feature_class":"P",
    "gn:feature_code":"PPL",
    "gn:name":"Bolatl\u0131",
    "gn:population":0,
    "gn:timezone":"Europe/Istanbul",
    "iso:country":"TR",
    "wof:name":"Bolatli",
    "wof:placetype":"locality"
},
  "geometry": {"coordinates":[37.71855,41.06728],"type":"Point"}
}