{
  "type": "Feature",
  "properties": {
    "gn:admin1_code":"45",
    "gn:asciiname":"Gerencik",
    "gn:country_code":"TR",
    "gn:dem":349,
    "gn:feature_class":"P",
    "gn:feature_code":"PPL",
    "gn:name":"Gerencik",
    "gn:population":0,
    "gn:timezone":"Europe/Istanbul",
    "iso:country":"TR",
    "name:tur_x_preferred":[
        "Gerencik"
    ],
    "wof:name":"Gerencik",
    "wof:placetype":"locality"
},
  "geometry": {"coordinates":[28.48317,38.73029],"type":"Point"}
}