{
  "type": "Feature",
  "properties": {
    "gn:admin1_code":"58",
    "gn:asciiname":"Danisment",
    "gn:country_code":"TR",
    "gn:dem":1444,
    "gn:feature_class":"P",
    "gn:feature_code":"PPLA3",
    "gn:name":"Dani\u015fment",
    "gn:population":0,
    "gn:timezone":"Europe/Istanbul",
    "iso:country":"TR",
    "name:und_x_variant":[
        "Birestik",
        "Ar\u0131kba\u015f\u0131",
        "Dani\u015fment"
    ],
    "wof:name":"Danisment",
    "wof:placetype":"locality"
},
  "geometry": {"coordinates":[38.19851,39.17153],"type":"Point"}
}