{
  "type": "Feature",
  "properties": {
    "gn:admin1_code":"58",
    "gn:asciiname":"Selimoglu",
    "gn:country_code":"TR",
    "gn:dem":1112,
    "gn:feature_class":"P",
    "gn:feature_code":"PPL",
    "gn:name":"Selimo\u011flu",
    "gn:population":0,
    "gn:timezone":"Europe/Istanbul",
    "iso:country":"TR",
    "wof:name":"Selimoglu",
    "wof:placetype":"locality"
},
  "geometry": {"coordinates":[38.26911,39.22088],"type":"Point"}
}