{
  "type": "Feature",
  "properties": {
    "gn:admin1_code":"73",
    "gn:asciiname":"Imrahor",
    "gn:country_code":"TR",
    "gn:dem":1298,
    "gn:feature_class":"P",
    "gn:feature_code":"PPL",
    "gn:name":"\u0130mrahor",
    "gn:population":0,
    "gn:timezone":"Europe/Istanbul",
    "iso:country":"TR",
    "wof:name":"Imrahor",
    "wof:placetype":"locality"
},
  "geometry": {"coordinates":[34.75,37.66667],"type":"Point"}
}