{
  "type": "Feature",
  "properties": {
    "gn:admin1_code":"24.0",
    "gn:asciiname":"Abrenk",
    "gn:cc2":"TR",
    "gn:country_code":"TR",
    "gn:dem":1610,
    "gn:feature_class":"P",
    "gn:feature_code":"PPL",
    "gn:name":"Abrenk",
    "gn:population":0,
    "gn:timezone":"Europe/Istanbul",
    "iso:country":"TR",
    "name:und_x_variant":[
        "Abrank",
        "Abrenk"
    ],
    "wof:name":"Abrenk",
    "wof:placetype":"locality"
},
  "geometry": {"coordinates":[40.31667,39.68333],"type":"Point"}
}