{
  "type": "Feature",
  "properties": {
    "gn:admin1_code":"76.0",
    "gn:asciiname":"Soganli",
    "gn:country_code":"TR",
    "gn:dem":1541,
    "gn:feature_class":"P",
    "gn:feature_code":"PPL",
    "gn:name":"So\u011fanl\u0131",
    "gn:population":0,
    "gn:timezone":"Europe/Istanbul",
    "iso:country":"TR",
    "name:tur_x_preferred":[
        "So\u011fanl\u0131"
    ],
    "wof:name":"Soganli",
    "wof:placetype":"locality"
},
  "geometry": {"coordinates":[41.4123,38.40261],"type":"Point"}
}