{
  "type": "Feature",
  "properties": {
    "gn:admin1_code":"19.0",
    "gn:asciiname":"Umac",
    "gn:country_code":"TR",
    "gn:dem":598,
    "gn:feature_class":"P",
    "gn:feature_code":"PPL",
    "gn:name":"Uma\u00e7",
    "gn:population":0,
    "gn:timezone":"Europe/Istanbul",
    "iso:country":"TR",
    "wof:name":"Umac",
    "wof:placetype":"locality"
},
  "geometry": {"coordinates":[34.91667,40.93333],"type":"Point"}
}