{
  "type": "Feature",
  "properties": {
    "gn:admin1_code":"87.0",
    "gn:asciiname":"Guneyoren",
    "gn:country_code":"TR",
    "gn:dem":698,
    "gn:feature_class":"P",
    "gn:feature_code":"PPL",
    "gn:name":"G\u00fcney\u00f6ren",
    "gn:population":0,
    "gn:timezone":"Europe/Istanbul",
    "iso:country":"TR",
    "wof:name":"Guneyoren",
    "wof:placetype":"locality"
},
  "geometry": {"coordinates":[32.75629,41.57571],"type":"Point"}
}