{
  "type": "Feature",
  "properties": {
    "gn:admin1_code":"80",
    "gn:asciiname":"Geramus",
    "gn:cc2":"TR",
    "gn:country_code":"TR",
    "gn:dem":1632,
    "gn:feature_class":"P",
    "gn:feature_code":"PPL",
    "gn:name":"Geramus",
    "gn:population":0,
    "gn:timezone":"Europe/Istanbul",
    "iso:country":"TR",
    "name:und_x_variant":[
        "Kerem\u00fcz",
        "Geramus"
    ],
    "wof:name":"Geramus",
    "wof:placetype":"locality"
},
  "geometry": {"coordinates":[43.27944,37.36389000000001],"type":"Point"}
}