{
  "type": "Feature",
  "properties": {
    "gn:admin1_code":"71",
    "gn:asciiname":"Gunyuzu",
    "gn:country_code":"TR",
    "gn:dem":949,
    "gn:feature_class":"P",
    "gn:feature_code":"PPL",
    "gn:name":"G\u00fcny\u00fcz\u00fc",
    "gn:population":0,
    "gn:timezone":"Europe/Istanbul",
    "iso:country":"TR",
    "wof:name":"Gunyuzu",
    "wof:placetype":"locality"
},
  "geometry": {"coordinates":[33.04078,38.51623],"type":"Point"}
}