{
  "type": "Feature",
  "properties": {
    "gn:admin1_code":"37.0",
    "gn:asciiname":"Karaboga",
    "gn:country_code":"TR",
    "gn:dem":1179,
    "gn:feature_class":"P",
    "gn:feature_code":"PPL",
    "gn:name":"Karabo\u011fa",
    "gn:population":0,
    "gn:timezone":"Europe/Istanbul",
    "iso:country":"TR",
    "name:und_x_variant":[
        "Karabu\u011fa",
        "Karabo\u011fa"
    ],
    "wof:name":"Karaboga",
    "wof:placetype":"locality"
},
  "geometry": {"coordinates":[33.55183,41.56467],"type":"Point"}
}