{
  "type": "Feature",
  "properties": {
    "gn:admin1_code":"45",
    "gn:asciiname":"Ardicburun",
    "gn:country_code":"TR",
    "gn:dem":662,
    "gn:feature_class":"P",
    "gn:feature_code":"PPL",
    "gn:name":"Ard\u0131\u00e7burun",
    "gn:population":0,
    "gn:timezone":"Europe/Istanbul",
    "iso:country":"TR",
    "name:tur_x_preferred":[
        "Ard\u0131\u00e7burun"
    ],
    "wof:name":"Ardicburun",
    "wof:placetype":"locality"
},
  "geometry": {"coordinates":[27.92257,39.19562],"type":"Point"}
}