{
  "type": "Feature",
  "properties": {
    "gn:admin1_code":"63.0",
    "gn:asciiname":"Konakkoy",
    "gn:cc2":"TR",
    "gn:country_code":"TR",
    "gn:dem":599,
    "gn:feature_class":"P",
    "gn:feature_code":"PPL",
    "gn:name":"Konakk\u00f6y",
    "gn:population":0,
    "gn:timezone":"Europe/Istanbul",
    "iso:country":"TR",
    "name:und_x_variant":[
        "Konak",
        "Konakk\u00f6y"
    ],
    "wof:name":"Konakkoy",
    "wof:placetype":"locality"
},
  "geometry": {"coordinates":[38.19917,36.93028],"type":"Point"}
}