{
  "type": "Feature",
  "properties": {
    "gn:admin1_code":"23",
    "gn:asciiname":"Gozpinar",
    "gn:country_code":"TR",
    "gn:dem":1371,
    "gn:feature_class":"P",
    "gn:feature_code":"PPL",
    "gn:name":"G\u00f6zp\u0131nar",
    "gn:population":0,
    "gn:timezone":"Europe/Istanbul",
    "iso:country":"TR",
    "name:tur_x_preferred":[
        "G\u00f6zp\u0131nar"
    ],
    "wof:name":"Gozpinar",
    "wof:placetype":"locality"
},
  "geometry": {"coordinates":[39.00719,38.52036],"type":"Point"}
}