{
  "type": "Feature",
  "properties": {
    "gn:admin1_code":"35",
    "gn:asciiname":"Kayali",
    "gn:country_code":"TR",
    "gn:dem":678,
    "gn:feature_class":"P",
    "gn:feature_code":"PPL",
    "gn:name":"Kayal\u0131",
    "gn:population":0,
    "gn:timezone":"Europe/Istanbul",
    "iso:country":"TR",
    "name:tur_x_preferred":[
        "Kayal\u0131"
    ],
    "wof:name":"Kayali",
    "wof:placetype":"locality"
},
  "geometry": {"coordinates":[27.6606,38.02182],"type":"Point"}
}