{
  "type": "Feature",
  "properties": {
    "gn:admin1_code":"09",
    "gn:asciiname":"Kizildere",
    "gn:country_code":"TR",
    "gn:dem":339,
    "gn:feature_class":"P",
    "gn:feature_code":"PPL",
    "gn:name":"K\u0131z\u0131ldere",
    "gn:population":0,
    "gn:timezone":"Europe/Istanbul",
    "iso:country":"TR",
    "name:tur_x_preferred":[
        "K\u0131z\u0131ldere"
    ],
    "wof:name":"Kizildere",
    "wof:placetype":"locality"
},
  "geometry": {"coordinates":[28.38588,38.03861],"type":"Point"}
}