{
  "type": "Feature",
  "properties": {
    "gn:admin1_code":"10.0",
    "gn:asciiname":"Cingekoy",
    "gn:country_code":"TR",
    "gn:dem":132,
    "gn:feature_class":"P",
    "gn:feature_code":"PPL",
    "gn:name":"\u00c7ingek\u00f6y",
    "gn:population":0,
    "gn:timezone":"Europe/Istanbul",
    "iso:country":"TR",
    "name:tur_x_preferred":[
        "\u00c7ingek\u00f6y"
    ],
    "wof:name":"Cingekoy",
    "wof:placetype":"locality"
},
  "geometry": {"coordinates":[27.87014000000001,40.30208],"type":"Point"}
}