{
  "type": "Feature",
  "properties": {
    "gn:admin1_code":"72.0",
    "gn:asciiname":"Yumrucuk",
    "gn:country_code":"TR",
    "gn:dem":471,
    "gn:feature_class":"P",
    "gn:feature_code":"PPL",
    "gn:name":"Yumrucuk",
    "gn:population":0,
    "gn:timezone":"Europe/Istanbul",
    "iso:country":"TR",
    "name:tur_x_preferred":[
        "Yumrucuk"
    ],
    "wof:name":"Yumrucuk",
    "wof:placetype":"locality"
},
  "geometry": {"coordinates":[40.3402,37.12365],"type":"Point"}
}