{
  "type": "Feature",
  "properties": {
    "gn:admin1_code":"24",
    "gn:asciiname":"Onurlu",
    "gn:country_code":"TR",
    "gn:dem":1928,
    "gn:feature_class":"P",
    "gn:feature_code":"PPL",
    "gn:name":"Onurlu",
    "gn:population":0,
    "gn:timezone":"Europe/Istanbul",
    "iso:country":"TR",
    "name:tur_x_preferred":[
        "Onurlu"
    ],
    "wof:name":"Onurlu",
    "wof:placetype":"locality"
},
  "geometry": {"coordinates":[38.78484,39.83361],"type":"Point"}
}