{
  "type": "Feature",
  "properties": {
    "gn:admin1_code":"40",
    "gn:asciiname":"Yesilyurt",
    "gn:country_code":"TR",
    "gn:dem":1257,
    "gn:feature_class":"P",
    "gn:feature_code":"PPL",
    "gn:name":"Ye\u015filyurt",
    "gn:population":0,
    "gn:timezone":"Europe/Istanbul",
    "iso:country":"TR",
    "name:und_x_variant":[
        "B\u00fcy\u00fck K\u00f6pekli",
        "Ye\u015filyurt"
    ],
    "wof:name":"Yesilyurt",
    "wof:placetype":"locality"
},
  "geometry": {"coordinates":[34.30475999999999,39.10286],"type":"Point"}
}