{
  "type": "Feature",
  "properties": {
    "gn:admin1_code":"60.0",
    "gn:asciiname":"Dutdibi",
    "gn:country_code":"TR",
    "gn:dem":1236,
    "gn:feature_class":"P",
    "gn:feature_code":"PPL",
    "gn:name":"Dutdibi",
    "gn:population":0,
    "gn:timezone":"Europe/Istanbul",
    "iso:country":"TR",
    "name:und_x_variant":[
        "Tutdibi",
        "Daldibi",
        "Dutdibi"
    ],
    "wof:name":"Dutdibi",
    "wof:placetype":"locality"
},
  "geometry": {"coordinates":[37.35104000000001,40.28692],"type":"Point"}
}