{
  "type": "Feature",
  "properties": {
    "gn:admin1_code":"59.0",
    "gn:asciiname":"Lahana",
    "gn:country_code":"TR",
    "gn:dem":51,
    "gn:feature_class":"P",
    "gn:feature_code":"PPL",
    "gn:name":"Lahana",
    "gn:population":0,
    "gn:timezone":"Europe/Istanbul",
    "iso:country":"TR",
    "name:und_x_variant":[
        "Yo\u011funba\u011f",
        "Lahana",
        "Lahnak\u00f6y",
        "Lahna"
    ],
    "wof:name":"Lahana",
    "wof:placetype":"locality"
},
  "geometry": {"coordinates":[27.13095,41.29054],"type":"Point"}
}