{
  "type": "Feature",
  "properties": {
    "gn:admin1_code":"58.0",
    "gn:asciiname":"Olukbasi",
    "gn:cc2":"TR",
    "gn:country_code":"TR",
    "gn:dem":1289,
    "gn:feature_class":"P",
    "gn:feature_code":"PPL",
    "gn:name":"Olukba\u015f\u0131",
    "gn:population":0,
    "gn:timezone":"Europe/Istanbul",
    "iso:country":"TR",
    "name:und_x_variant":[
        "\u00d6yk\u00fcr\u00fc",
        "Olukba\u015f\u0131"
    ],
    "wof:name":"Olukbasi",
    "wof:placetype":"locality"
},
  "geometry": {"coordinates":[37.25,40.15],"type":"Point"}
}