{
  "type": "Feature",
  "properties": {
    "gn:admin1_code":"85",
    "gn:asciiname":"Arabanci",
    "gn:country_code":"TR",
    "gn:dem":301,
    "gn:feature_class":"P",
    "gn:feature_code":"PPL",
    "gn:name":"Arabanc\u0131",
    "gn:population":0,
    "gn:timezone":"Europe/Istanbul",
    "iso:country":"TR",
    "wof:name":"Arabanci",
    "wof:placetype":"locality"
},
  "geometry": {"coordinates":[31.81174,41.29641],"type":"Point"}
}