{
  "type": "Feature",
  "properties": {
    "gn:admin1_code":"84.0",
    "gn:asciiname":"Hacipiri",
    "gn:country_code":"TR",
    "gn:dem":1584,
    "gn:feature_class":"P",
    "gn:feature_code":"PPL",
    "gn:name":"Hac\u0131piri",
    "gn:population":0,
    "gn:timezone":"Europe/Istanbul",
    "iso:country":"TR",
    "name:tur_x_preferred":[
        "Hac\u0131piri"
    ],
    "wof:name":"Hacipiri",
    "wof:placetype":"locality"
},
  "geometry": {"coordinates":[43.62486,40.80411],"type":"Point"}
}