{
  "type": "Feature",
  "properties": {
    "gn:admin1_code":"40",
    "gn:asciiname":"Degirmenkasi",
    "gn:country_code":"TR",
    "gn:dem":929,
    "gn:feature_class":"P",
    "gn:feature_code":"PPL",
    "gn:name":"De\u011firmenka\u015f\u0131",
    "gn:population":0,
    "gn:timezone":"Europe/Istanbul",
    "iso:country":"TR",
    "name:und_x_variant":[
        "H\u0131ral\u0131",
        "De\u011firmenka\u015f\u0131"
    ],
    "wof:name":"Degirmenkasi",
    "wof:placetype":"locality"
},
  "geometry": {"coordinates":[34.2106,38.87148],"type":"Point"}
}