{
  "type": "Feature",
  "properties": {
    "gn:admin1_code":"21.0",
    "gn:asciiname":"Sarihuseyin",
    "gn:cc2":"TR",
    "gn:country_code":"TR",
    "gn:dem":630,
    "gn:feature_class":"P",
    "gn:feature_code":"PPL",
    "gn:name":"Sar\u0131h\u00fcseyin",
    "gn:population":0,
    "gn:timezone":"Europe/Istanbul",
    "iso:country":"TR",
    "name:tur_x_preferred":[
        "Sar\u0131h\u00fcseyin"
    ],
    "name:und_x_variant":[
        "Sarykhyuseyn"
    ],
    "wof:name":"Sarihuseyin",
    "wof:placetype":"locality"
},
  "geometry": {"coordinates":[40.69028,37.92139],"type":"Point"}
}