{
  "type": "Feature",
  "properties": {
    "gn:admin1_code":"21",
    "gn:asciiname":"Tepecik",
    "gn:country_code":"TR",
    "gn:dem":856,
    "gn:feature_class":"P",
    "gn:feature_code":"PPL",
    "gn:name":"Tepecik",
    "gn:population":0,
    "gn:timezone":"Europe/Istanbul",
    "iso:country":"TR",
    "name:ceb_x_preferred":[
        "Tepecik"
    ],
    "name:deu_x_preferred":[
        "Tepecik"
    ],
    "name:min_x_preferred":[
        "Tepecik"
    ],
    "name:tur_x_preferred":[
        "Tepecik"
    ],
    "name:und_x_variant":[
        "Tepecikk\u00f6y",
        "Tepecik"
    ],
    "wof:name":"Tepecik",
    "wof:placetype":"locality"
},
  "geometry": {"coordinates":[40.57794000000001,38.26656],"type":"Point"}
}