{
  "type": "Feature",
  "properties": {
    "gn:country":"TR",
    "gn:fcode":"PPL",
    "gn:pop":0,
    "iso:country":"TR",
    "name:eng_x_preferred":[
        "Karao\u011flan"
    ],
    "name:msa_x_preferred":[
        "Karao\u011flan"
    ],
    "name:nan_x_preferred":[
        "Karao\u011flan"
    ],
    "name:tur_x_preferred":[
        "Karao\u011flan"
    ],
    "qs:name":"Karao\u011flan",
    "qs:name_adm0":"Turkey",
    "qs:name_adm1":"Ankara",
    "qs:photos_9k":1,
    "qs:photos_9r":1,
    "qs:photos_all":1,
    "qs:photos_sr":0,
    "qs:placetype":"Town",
    "qs:pop_sr":"0",
    "wd:wordcount":890,
    "wof:name":"Karao\u011flan",
    "wof:placetype":"locality",
    "wof:population":0
},
  "geometry": {"coordinates":[32.8302,39.73447],"type":"Point"}
}