{
  "type": "Feature",
  "properties": {
    "gn:admin1_code":"07",
    "gn:asciiname":"Guzelsu",
    "gn:country_code":"TR",
    "gn:dem":1191,
    "gn:feature_class":"P",
    "gn:feature_code":"PPLA3",
    "gn:name":"G\u00fczelsu",
    "gn:population":0,
    "gn:timezone":"Europe/Istanbul",
    "iso:country":"TR",
    "name:tur_x_preferred":[
        "G\u00fczelsu"
    ],
    "wof:name":"Guzelsu",
    "wof:placetype":"locality"
},
  "geometry": {"coordinates":[31.85639,36.89472],"type":"Point"}
}