{
  "type": "Feature",
  "properties": {
    "gn:admin1_code":"76",
    "gn:asciiname":"Kavaklidere",
    "gn:country_code":"TR",
    "gn:dem":1530,
    "gn:feature_class":"P",
    "gn:feature_code":"PPL",
    "gn:name":"Kavakl\u0131dere",
    "gn:population":0,
    "gn:timezone":"Europe/Istanbul",
    "iso:country":"TR",
    "name:tur_x_preferred":[
        "Kavakl\u0131dere"
    ],
    "wof:name":"Kavaklidere",
    "wof:placetype":"locality"
},
  "geometry": {"coordinates":[38.65745,38.22243],"type":"Point"}
}