{
  "type": "Feature",
  "properties": {
    "gn:admin1_code":"63",
    "gn:asciiname":"Dogrular",
    "gn:country_code":"TR",
    "gn:dem":627,
    "gn:feature_class":"P",
    "gn:feature_code":"PPL",
    "gn:name":"Do\u011frular",
    "gn:population":0,
    "gn:timezone":"Europe/Istanbul",
    "iso:country":"TR",
    "name:und_x_variant":[
        "Do\u011frular",
        "Diru\u015fa"
    ],
    "wof:name":"Dogrular",
    "wof:placetype":"locality"
},
  "geometry": {"coordinates":[39.11951,37.5623],"type":"Point"}
}