{
  "type": "Feature",
  "properties": {
    "gn:admin1_code":"52.0",
    "gn:asciiname":"Yukari Gokce",
    "gn:country_code":"TR",
    "gn:dem":1316,
    "gn:feature_class":"P",
    "gn:feature_code":"PPL",
    "gn:name":"Yukar\u0131 G\u00f6k\u00e7e",
    "gn:population":0,
    "gn:timezone":"Europe/Istanbul",
    "iso:country":"TR",
    "name:tur_x_preferred":[
        "Yukar\u0131 G\u00f6k\u00e7e"
    ],
    "wof:name":"Yukari Gokce",
    "wof:placetype":"locality"
},
  "geometry": {"coordinates":[37.85008,40.47886],"type":"Point"}
}