{
  "type": "Feature",
  "properties": {
    "gn:admin1_code":"37.0",
    "gn:asciiname":"Alamakayis",
    "gn:country_code":"TR",
    "gn:dem":607,
    "gn:feature_class":"P",
    "gn:feature_code":"PPL",
    "gn:name":"Alamakay\u0131\u015f",
    "gn:population":0,
    "gn:timezone":"Europe/Istanbul",
    "iso:country":"TR",
    "name:und_x_variant":[
        "Alamakay\u0131\u015f",
        "Bay\u0131rl\u0131"
    ],
    "wof:name":"Alamakayis",
    "wof:placetype":"locality"
},
  "geometry": {"coordinates":[34.13786,41.47671],"type":"Point"}
}