{
  "type": "Feature",
  "properties": {
    "gn:admin1_code":"85",
    "gn:asciiname":"Tuloglu",
    "gn:country_code":"TR",
    "gn:dem":217,
    "gn:feature_class":"P",
    "gn:feature_code":"PPL",
    "gn:name":"T\u00fclo\u011flu",
    "gn:population":0,
    "gn:timezone":"Europe/Istanbul",
    "iso:country":"TR",
    "wof:name":"Tuloglu",
    "wof:placetype":"locality"
},
  "geometry": {"coordinates":[32.09721,41.5647],"type":"Point"}
}