{
  "type": "Feature",
  "properties": {
    "gn:admin1_code":"81",
    "gn:asciiname":"Altinova",
    "gn:country_code":"TR",
    "gn:dem":128,
    "gn:feature_class":"P",
    "gn:feature_code":"PPL",
    "gn:name":"Alt\u0131nova",
    "gn:population":0,
    "gn:timezone":"Europe/Istanbul",
    "iso:country":"TR",
    "name:und_x_variant":[
        "Alt\u0131nova",
        "Hac\u0131araplar"
    ],
    "wof:name":"Altinova",
    "wof:placetype":"locality"
},
  "geometry": {"coordinates":[35.02313,37.19051],"type":"Point"}
}