{
  "type": "Feature",
  "properties": {
    "gn:admin1_code":"44",
    "gn:asciiname":"Yaka",
    "gn:country_code":"TR",
    "gn:dem":904,
    "gn:feature_class":"P",
    "gn:feature_code":"PPL",
    "gn:name":"Yaka",
    "gn:population":0,
    "gn:timezone":"Europe/Istanbul",
    "iso:country":"TR",
    "name:und_x_variant":[
        "Mezrea",
        "Yaka",
        "Mezraa",
        "Yaka Mahalesi"
    ],
    "wof:name":"Yaka",
    "wof:placetype":"locality"
},
  "geometry": {"coordinates":[38.27362,38.39288],"type":"Point"}
}