{
  "type": "Feature",
  "properties": {
    "gn:admin1_code":"10",
    "gn:asciiname":"Damlali",
    "gn:country_code":"TR",
    "gn:dem":497,
    "gn:feature_class":"P",
    "gn:feature_code":"PPL",
    "gn:name":"Damlal\u0131",
    "gn:population":0,
    "gn:timezone":"Europe/Istanbul",
    "iso:country":"TR",
    "name:und_x_variant":[
        "Sar\u0131lar",
        "Bamlal\u0131",
        "Damlal\u0131"
    ],
    "wof:name":"Damlali",
    "wof:placetype":"locality"
},
  "geometry": {"coordinates":[26.97367,39.35],"type":"Point"}
}