{
  "type": "Feature",
  "properties": {
    "gn:admin1_code":"63.0",
    "gn:asciiname":"Menzele",
    "gn:country_code":"TR",
    "gn:dem":399,
    "gn:feature_class":"P",
    "gn:feature_code":"PPL",
    "gn:name":"Menzele",
    "gn:population":0,
    "gn:timezone":"Europe/Istanbul",
    "iso:country":"TR",
    "wof:name":"Menzele",
    "wof:placetype":"locality"
},
  "geometry": {"coordinates":[39.16222,36.84889],"type":"Point"}
}