{
  "type": "Feature",
  "properties": {
    "gn:admin1_code":"44",
    "gn:asciiname":"Karabacak",
    "gn:country_code":"TR",
    "gn:dem":1558,
    "gn:feature_class":"P",
    "gn:feature_code":"PPL",
    "gn:name":"Karabacak",
    "gn:population":0,
    "gn:timezone":"Europe/Istanbul",
    "iso:country":"TR",
    "name:und_x_variant":[
        "Karabacak Mezraas\u0131",
        "Karabacak"
    ],
    "wof:name":"Karabacak",
    "wof:placetype":"locality"
},
  "geometry": {"coordinates":[37.60772,38.65254],"type":"Point"}
}