{
  "type": "Feature",
  "properties": {
    "gn:admin1_code":"32",
    "gn:asciiname":"Langer",
    "gn:country_code":"TR",
    "gn:dem":962,
    "gn:feature_class":"P",
    "gn:feature_code":"PPL",
    "gn:name":"Langer",
    "gn:population":0,
    "gn:timezone":"Europe/Istanbul",
    "iso:country":"TR",
    "name:deu_x_preferred":[
        "Langer"
    ],
    "name:pol_x_preferred":[
        "Langer"
    ],
    "name:rus_x_preferred":[
        "\u041b\u0430\u043d\u0433\u0435\u0440"
    ],
    "name:tur_x_preferred":[
        "Langer"
    ],
    "wof:name":"Langer",
    "wof:placetype":"locality"
},
  "geometry": {"coordinates":[33.15388,36.24659000000001],"type":"Point"}
}