{
  "type": "Feature",
  "properties": {
    "gn:admin1_code":"37.0",
    "gn:asciiname":"Olucak",
    "gn:country_code":"TR",
    "gn:dem":185,
    "gn:feature_class":"P",
    "gn:feature_code":"PPL",
    "gn:name":"Olucak",
    "gn:population":0,
    "gn:timezone":"Europe/Istanbul",
    "iso:country":"TR",
    "name:und_x_variant":[
        "Fille",
        "Olucak"
    ],
    "wof:name":"Olucak",
    "wof:placetype":"locality"
},
  "geometry": {"coordinates":[32.94083,41.84143],"type":"Point"}
}