{
  "type": "Feature",
  "properties": {
    "gn:admin1_code":"10",
    "gn:asciiname":"Beyoba",
    "gn:country_code":"TR",
    "gn:dem":195,
    "gn:feature_class":"P",
    "gn:feature_code":"PPL",
    "gn:name":"Beyoba",
    "gn:population":0,
    "gn:timezone":"Europe/Istanbul",
    "iso:country":"TR",
    "name:tur_x_preferred":[
        "Beyoba"
    ],
    "wof:name":"Beyoba",
    "wof:placetype":"locality"
},
  "geometry": {"coordinates":[26.93627,39.63795],"type":"Point"}
}