{
  "type": "Feature",
  "properties": {
    "gn:admin1_code":"70",
    "gn:asciiname":"Pavilan",
    "gn:country_code":"TR",
    "gn:dem":1891,
    "gn:feature_class":"P",
    "gn:feature_code":"PPL",
    "gn:name":"Pavilan",
    "gn:population":0,
    "gn:timezone":"Europe/Istanbul",
    "iso:country":"TR",
    "name:und_x_variant":[
        "Bay\u0131lan",
        "Pavilan",
        "G\u00fc\u00e7l\u00fc"
    ],
    "wof:name":"Pavilan",
    "wof:placetype":"locality"
},
  "geometry": {"coordinates":[44.32155,37.56689],"type":"Point"}
}