{
  "type": "Feature",
  "properties": {
    "gn:admin1_code":"37.0",
    "gn:asciiname":"Yamac",
    "gn:country_code":"TR",
    "gn:dem":215,
    "gn:feature_class":"P",
    "gn:feature_code":"PPL",
    "gn:name":"Yama\u00e7",
    "gn:population":0,
    "gn:timezone":"Europe/Istanbul",
    "iso:country":"TR",
    "name:und_x_variant":[
        "Vayra",
        "Yama\u00e7"
    ],
    "wof:name":"Yamac",
    "wof:placetype":"locality"
},
  "geometry": {"coordinates":[33.85101,41.95959000000001],"type":"Point"}
}