{
  "type": "Feature",
  "properties": {
    "gn:admin1_code":"37.0",
    "gn:asciiname":"Ilyasbey",
    "gn:country_code":"TR",
    "gn:dem":169,
    "gn:feature_class":"P",
    "gn:feature_code":"PPL",
    "gn:name":"\u0130lyasbey",
    "gn:population":0,
    "gn:timezone":"Europe/Istanbul",
    "iso:country":"TR",
    "wof:name":"Ilyasbey",
    "wof:placetype":"locality"
},
  "geometry": {"coordinates":[33.35598,42.0089],"type":"Point"}
}