{
  "type": "Feature",
  "properties": {
    "gn:admin1_code":"84.0",
    "gn:asciiname":"Kirac",
    "gn:country_code":"TR",
    "gn:dem":2145,
    "gn:feature_class":"P",
    "gn:feature_code":"PPL",
    "gn:name":"K\u0131ra\u00e7",
    "gn:population":0,
    "gn:timezone":"Europe/Istanbul",
    "iso:country":"TR",
    "name:tur_x_preferred":[
        "K\u0131ra\u00e7"
    ],
    "wof:name":"Kirac",
    "wof:placetype":"locality"
},
  "geometry": {"coordinates":[43.50372,40.9197],"type":"Point"}
}