{
  "type": "Feature",
  "properties": {
    "gn:admin1_code":"68",
    "gn:asciiname":"Selametli",
    "gn:country_code":"TR",
    "gn:dem":1189,
    "gn:feature_class":"P",
    "gn:feature_code":"PPL",
    "gn:name":"Sel\u00e2metli",
    "gn:population":0,
    "gn:timezone":"Europe/Istanbul",
    "iso:country":"TR",
    "wof:name":"Selametli",
    "wof:placetype":"locality"
},
  "geometry": {"coordinates":[32.80860999999999,39.48611],"type":"Point"}
}