{
  "type": "Feature",
  "properties": {
    "gn:country":"TR",
    "gn:fcode":"PPL",
    "gn:pop":2701,
    "iso:country":"TR",
    "name:tur_x_preferred":[
        "Ye\u015fildere"
    ],
    "qs:name":"Ye\u015fildere",
    "qs:photos_9r":0,
    "qs:photos_sr":0,
    "qs:pop_sr":"4",
    "wd:wordcount":47,
    "wof:name":"Ye\u015fildere",
    "wof:placetype":"locality",
    "wof:population":2701
},
  "geometry": {"coordinates":[37.50722,36.98528],"type":"Point"}
}