{
  "type": "Feature",
  "properties": {
    "gn:admin1_code":"5.0",
    "gn:asciiname":"Kulu",
    "gn:country_code":"TR",
    "gn:dem":453,
    "gn:feature_class":"P",
    "gn:feature_code":"PPL",
    "gn:name":"Kulu",
    "gn:population":0,
    "gn:timezone":"Europe/Istanbul",
    "iso:country":"TR",
    "name:tur_x_preferred":[
        "Kulu"
    ],
    "wof:name":"Kulu",
    "wof:placetype":"locality"
},
  "geometry": {"coordinates":[35.62158,40.76364],"type":"Point"}
}