{
  "type": "Feature",
  "properties": {
    "gn:admin1_code":"69.0",
    "gn:asciiname":"Kaynakbasi",
    "gn:country_code":"TR",
    "gn:dem":1500,
    "gn:feature_class":"P",
    "gn:feature_code":"PPL",
    "gn:name":"Kaynakba\u015f\u0131",
    "gn:population":0,
    "gn:timezone":"Europe/Istanbul",
    "iso:country":"TR",
    "name:tur_x_preferred":[
        "Kaynakba\u015f\u0131"
    ],
    "wof:name":"Kaynakbasi",
    "wof:placetype":"locality"
},
  "geometry": {"coordinates":[38.96652,40.18705],"type":"Point"}
}