{
  "type": "Feature",
  "properties": {
    "gn:admin1_code":"81",
    "gn:asciiname":"Camili",
    "gn:country_code":"TR",
    "gn:dem":33,
    "gn:feature_class":"P",
    "gn:feature_code":"PPL",
    "gn:name":"Camili",
    "gn:population":0,
    "gn:timezone":"Europe/Istanbul",
    "iso:country":"TR",
    "name:ceb_x_preferred":[
        "Camili"
    ],
    "name:swe_x_preferred":[
        "Camili"
    ],
    "name:tur_x_preferred":[
        "Camili"
    ],
    "wof:name":"Camili",
    "wof:placetype":"locality"
},
  "geometry": {"coordinates":[35.43170999999999,36.92961],"type":"Point"}
}