{
  "type": "Feature",
  "properties": {
    "gn:admin1_code":"10",
    "gn:asciiname":"Esenli",
    "gn:country_code":"TR",
    "gn:dem":266,
    "gn:feature_class":"P",
    "gn:feature_code":"PPL",
    "gn:name":"Esenli",
    "gn:population":0,
    "gn:timezone":"Europe/Istanbul",
    "iso:country":"TR",
    "name:tur_x_preferred":[
        "Esenli"
    ],
    "wof:name":"Esenli",
    "wof:placetype":"locality"
},
  "geometry": {"coordinates":[28.05131,39.54631],"type":"Point"}
}