{
  "type": "Feature",
  "properties": {
    "gn:admin1_code":"61.0",
    "gn:asciiname":"Kusera",
    "gn:country_code":"TR",
    "gn:dem":1757,
    "gn:feature_class":"P",
    "gn:feature_code":"PPL",
    "gn:name":"Kusera",
    "gn:population":0,
    "gn:timezone":"Europe/Istanbul",
    "iso:country":"TR",
    "name:und_x_variant":[
        "\u00c7aml\u0131d\u00fcz",
        "Kusera"
    ],
    "wof:name":"Kusera",
    "wof:placetype":"locality"
},
  "geometry": {"coordinates":[39.47359,40.76748],"type":"Point"}
}