{
  "type": "Feature",
  "properties": {
    "gn:admin1_code":"74",
    "gn:asciiname":"Belencay",
    "gn:country_code":"TR",
    "gn:dem":1117,
    "gn:feature_class":"P",
    "gn:feature_code":"PPL",
    "gn:name":"Belen\u00e7ay",
    "gn:population":0,
    "gn:timezone":"Europe/Istanbul",
    "iso:country":"TR",
    "name:tur_x_preferred":[
        "Belen\u00e7ay"
    ],
    "name:und_x_variant":[
        "Bele\u00e7ay",
        "Poterver"
    ],
    "wof:name":"Belencay",
    "wof:placetype":"locality"
},
  "geometry": {"coordinates":[42.31533,38.00748],"type":"Point"}
}