{
  "type": "Feature",
  "properties": {
    "gn:admin1_code":"23",
    "gn:asciiname":"Gokdere",
    "gn:country_code":"TR",
    "gn:dem":1179,
    "gn:feature_class":"P",
    "gn:feature_code":"PPLA3",
    "gn:name":"G\u00f6kdere",
    "gn:population":0,
    "gn:timezone":"Europe/Istanbul",
    "iso:country":"TR",
    "name:tur_x_preferred":[
        "G\u00f6kdere"
    ],
    "name:und_x_variant":[
        "Erd\u00fcr\u00fck"
    ],
    "wof:name":"Gokdere",
    "wof:placetype":"locality"
},
  "geometry": {"coordinates":[40.20815,38.7428],"type":"Point"}
}