{
  "type": "Feature",
  "properties": {
    "iso:country":"TR",
    "name:tur_x_preferred":[
        "I\u015f\u0131klar"
    ],
    "wof:name":"Isiklar",
    "wof:placetype":"neighbourhood"
},
  "geometry": {"coordinates":[28.82632311044801,41.22589295572409],"type":"Point"}
}