{
  "type": "Feature",
  "properties": {
    "gn:admin1_code":"13",
    "gn:asciiname":"Yukari Balcilar",
    "gn:country_code":"TR",
    "gn:dem":1701,
    "gn:feature_class":"P",
    "gn:feature_code":"PPL",
    "gn:name":"Yukar\u0131 Balc\u0131lar",
    "gn:population":0,
    "gn:timezone":"Europe/Istanbul",
    "iso:country":"TR",
    "name:tur_x_preferred":[
        "Yukar\u0131 Balc\u0131lar"
    ],
    "name:und_x_variant":[
        "Yukar\u0131balc\u0131lar"
    ],
    "wof:name":"Yukari Balcilar",
    "wof:placetype":"locality"
},
  "geometry": {"coordinates":[42.16631,38.25031],"type":"Point"}
}