{
  "type": "Feature",
  "properties": {
    "gn:admin1_code":"70.0",
    "gn:asciiname":"Mese",
    "gn:country_code":"TR",
    "gn:dem":1123,
    "gn:feature_class":"P",
    "gn:feature_code":"PPL",
    "gn:name":"Mese",
    "gn:population":0,
    "gn:timezone":"Europe/Istanbul",
    "iso:country":"TR",
    "wof:name":"Mese",
    "wof:placetype":"locality"
},
  "geometry": {"coordinates":[44.50052,37.26996],"type":"Point"}
}