{
  "type": "Feature",
  "properties": {
    "gn:admin1_code":"35",
    "gn:asciiname":"Kizilcukur",
    "gn:country_code":"TR",
    "gn:dem":17,
    "gn:feature_class":"P",
    "gn:feature_code":"PPL",
    "gn:name":"K\u0131z\u0131l\u00e7ukur",
    "gn:population":0,
    "gn:timezone":"Europe/Istanbul",
    "iso:country":"TR",
    "name:tur_x_preferred":[
        "K\u0131z\u0131l\u00e7ukur"
    ],
    "wof:name":"Kizilcukur",
    "wof:placetype":"locality"
},
  "geometry": {"coordinates":[26.91439,39.10556],"type":"Point"}
}