{
  "type": "Feature",
  "properties": {
    "gn:admin1_code":"03",
    "gn:asciiname":"Burcek Mahallesi",
    "gn:country_code":"TR",
    "gn:dem":1502,
    "gn:feature_class":"P",
    "gn:feature_code":"PPL",
    "gn:name":"B\u00fcrcek Mahallesi",
    "gn:population":0,
    "gn:timezone":"Europe/Istanbul",
    "iso:country":"TR",
    "wof:name":"Burcek Mahallesi",
    "wof:placetype":"locality"
},
  "geometry": {"coordinates":[30.46707,38.61858],"type":"Point"}
}