{
  "type": "Feature",
  "properties": {
    "gn:admin1_code":"58",
    "gn:asciiname":"Cemalkoy",
    "gn:country_code":"TR",
    "gn:dem":1864,
    "gn:feature_class":"P",
    "gn:feature_code":"PPL",
    "gn:name":"Cemalk\u00f6y",
    "gn:population":0,
    "gn:timezone":"Europe/Istanbul",
    "iso:country":"TR",
    "name:tur_x_preferred":[
        "Cemalk\u00f6y"
    ],
    "name:tur_x_variant":[
        "Cemal"
    ],
    "wof:name":"Cemalkoy",
    "wof:placetype":"locality"
},
  "geometry": {"coordinates":[37.9184,39.75816],"type":"Point"}
}