{
  "type": "Feature",
  "properties": {
    "gn:admin1_code":"55.0",
    "gn:asciiname":"Konukluk",
    "gn:country_code":"TR",
    "gn:dem":490,
    "gn:feature_class":"P",
    "gn:feature_code":"PPL",
    "gn:name":"Konukluk",
    "gn:population":0,
    "gn:timezone":"Europe/Istanbul",
    "iso:country":"TR",
    "wof:name":"Konukluk",
    "wof:placetype":"locality"
},
  "geometry": {"coordinates":[36.47588,40.98326],"type":"Point"}
}