{
  "type": "Feature",
  "properties": {
    "gn:admin1_code":"41.0",
    "gn:asciiname":"Dogancili",
    "gn:country_code":"TR",
    "gn:dem":59,
    "gn:feature_class":"P",
    "gn:feature_code":"PPL",
    "gn:name":"Do\u011fanc\u0131l\u0131",
    "gn:population":0,
    "gn:timezone":"Europe/Istanbul",
    "iso:country":"TR",
    "name:tur_x_preferred":[
        "Burhan"
    ],
    "name:tur_x_variant":[
        "Do\u011fanc\u0131l\u0131"
    ],
    "wof:name":"Dogancili",
    "wof:placetype":"locality"
},
  "geometry": {"coordinates":[30.13644,41.11119],"type":"Point"}
}