{
  "type": "Feature",
  "properties": {
    "gn:admin1_code":"21.0",
    "gn:asciiname":"Censine",
    "gn:country_code":"TR",
    "gn:dem":1133,
    "gn:feature_class":"P",
    "gn:feature_code":"PPL",
    "gn:name":"Censine",
    "gn:population":0,
    "gn:timezone":"Europe/Istanbul",
    "iso:country":"TR",
    "wof:name":"Censine",
    "wof:placetype":"locality"
},
  "geometry": {"coordinates":[41.11993,38.29572],"type":"Point"}
}