{
  "type": "Feature",
  "properties": {
    "gn:admin1_code":"16",
    "gn:asciiname":"Serceler",
    "gn:country_code":"TR",
    "gn:dem":400,
    "gn:feature_class":"P",
    "gn:feature_code":"PPL",
    "gn:name":"Ser\u00e7eler",
    "gn:population":0,
    "gn:timezone":"Europe/Istanbul",
    "iso:country":"TR",
    "name:tur_x_preferred":[
        "Ser\u00e7eler"
    ],
    "wof:name":"Serceler",
    "wof:placetype":"locality"
},
  "geometry": {"coordinates":[28.95317,39.89285],"type":"Point"}
}