{
  "type": "Feature",
  "properties": {
    "gn:admin1_code":"09",
    "gn:asciiname":"Palamutcuk Mahallesi",
    "gn:country_code":"TR",
    "gn:dem":382,
    "gn:feature_class":"P",
    "gn:feature_code":"PPL",
    "gn:name":"Palamut\u00e7uk Mahallesi",
    "gn:population":0,
    "gn:timezone":"Europe/Istanbul",
    "iso:country":"TR",
    "name:tur_x_preferred":[
        "Palamut\u00e7uk Mahallesi"
    ],
    "wof:name":"Palamutcuk Mahallesi",
    "wof:placetype":"locality"
},
  "geometry": {"coordinates":[27.91524,37.87687],"type":"Point"}
}