{
  "type": "Feature",
  "properties": {
    "gn:admin1_code":"63.0",
    "gn:asciiname":"Dayanikli",
    "gn:country_code":"TR",
    "gn:dem":371,
    "gn:feature_class":"P",
    "gn:feature_code":"PPL",
    "gn:name":"Dayan\u0131kl\u0131",
    "gn:population":0,
    "gn:timezone":"Europe/Istanbul",
    "iso:country":"TR",
    "name:tur_x_preferred":[
        "Dayan\u0131kl\u0131"
    ],
    "name:und_x_variant":[
        "Dzhakhshiye",
        "Cah\u015fiye"
    ],
    "wof:name":"Dayanikli",
    "wof:placetype":"locality"
},
  "geometry": {"coordinates":[38.9704,36.92149000000001],"type":"Point"}
}