{
  "type": "Feature",
  "properties": {
    "gn:admin1_code":"32",
    "gn:asciiname":"Korucular",
    "gn:country_code":"TR",
    "gn:dem":528,
    "gn:feature_class":"P",
    "gn:feature_code":"PPL",
    "gn:name":"Korucular",
    "gn:population":0,
    "gn:timezone":"Europe/Istanbul",
    "iso:country":"TR",
    "name:tur_x_preferred":[
        "Korucular"
    ],
    "name:tur_x_variant":[
        "Kurucular"
    ],
    "wof:name":"Korucular",
    "wof:placetype":"locality"
},
  "geometry": {"coordinates":[34.54036,36.92767],"type":"Point"}
}