{
  "type": "Feature",
  "properties": {
    "gn:admin1_code":"69.0",
    "gn:asciiname":"Kucukcit",
    "gn:country_code":"TR",
    "gn:dem":1428,
    "gn:feature_class":"P",
    "gn:feature_code":"PPL",
    "gn:name":"K\u00fc\u00e7\u00fck\u00e7it",
    "gn:population":0,
    "gn:timezone":"Europe/Istanbul",
    "iso:country":"TR",
    "name:tur_x_preferred":[
        "K\u00fc\u00e7\u00fck\u00e7it"
    ],
    "wof:name":"Kucukcit",
    "wof:placetype":"locality"
},
  "geometry": {"coordinates":[39.22792000000001,40.52843],"type":"Point"}
}