{
  "type": "Feature",
  "properties": {
    "gn:admin1_code":"87.0",
    "gn:asciiname":"Sultanca",
    "gn:country_code":"TR",
    "gn:dem":448,
    "gn:feature_class":"P",
    "gn:feature_code":"PPL",
    "gn:name":"Sultanca",
    "gn:population":0,
    "gn:timezone":"Europe/Istanbul",
    "iso:country":"TR",
    "name:und_x_variant":[
        "K\u00f6sek\u00f6y",
        "Sultanca"
    ],
    "wof:name":"Sultanca",
    "wof:placetype":"locality"
},
  "geometry": {"coordinates":[32.56667,41.45],"type":"Point"}
}