{
  "type": "Feature",
  "properties": {
    "gn:admin1_code":"8.0",
    "gn:asciiname":"Pamukcular",
    "gn:country_code":"TR",
    "gn:dem":1122,
    "gn:feature_class":"P",
    "gn:feature_code":"PPL",
    "gn:name":"Pamuk\u00e7ular",
    "gn:population":0,
    "gn:timezone":"Europe/Istanbul",
    "iso:country":"TR",
    "name:und_x_variant":[
        "Ohur",
        "Pamuk\u00e7ular"
    ],
    "wof:name":"Pamukcular",
    "wof:placetype":"locality"
},
  "geometry": {"coordinates":[41.8331,40.78647],"type":"Point"}
}