{
  "type": "Feature",
  "properties": {
    "gn:admin1_code":"35",
    "gn:asciiname":"Yanik",
    "gn:country_code":"TR",
    "gn:dem":48,
    "gn:feature_class":"P",
    "gn:feature_code":"PPL",
    "gn:name":"Yan\u0131k",
    "gn:population":0,
    "gn:timezone":"Europe/Istanbul",
    "iso:country":"TR",
    "name:und_x_variant":[
        "Yan\u0131k",
        "Yan\u0131kk\u00f6y"
    ],
    "wof:name":"Yanik",
    "wof:placetype":"locality"
},
  "geometry": {"coordinates":[27.08322,38.65604],"type":"Point"}
}