{
  "type": "Feature",
  "properties": {
    "gn:admin1_code":"58.0",
    "gn:asciiname":"Dundar",
    "gn:country_code":"TR",
    "gn:dem":1970,
    "gn:feature_class":"P",
    "gn:feature_code":"PPL",
    "gn:name":"D\u00fcndar",
    "gn:population":0,
    "gn:timezone":"Europe/Istanbul",
    "iso:country":"TR",
    "wof:name":"Dundar",
    "wof:placetype":"locality"
},
  "geometry": {"coordinates":[37.42664,40.15147],"type":"Point"}
}