{
  "type": "Feature",
  "properties": {
    "gn:admin1_code":"10",
    "gn:asciiname":"Meyvali",
    "gn:country_code":"TR",
    "gn:dem":1064,
    "gn:feature_class":"P",
    "gn:feature_code":"PPL",
    "gn:name":"Meyval\u0131",
    "gn:population":0,
    "gn:timezone":"Europe/Istanbul",
    "iso:country":"TR",
    "name:tur_x_preferred":[
        "Dervi\u015fler"
    ],
    "name:tur_x_variant":[
        "Meyval\u0131"
    ],
    "wof:name":"Meyvali",
    "wof:placetype":"locality"
},
  "geometry": {"coordinates":[28.59806,39.34694],"type":"Point"}
}