{
  "type": "Feature",
  "properties": {
    "gn:admin1_code":"03",
    "gn:asciiname":"Cakirkoy",
    "gn:country_code":"TR",
    "gn:dem":1040,
    "gn:feature_class":"P",
    "gn:feature_code":"PPL",
    "gn:name":"\u00c7ak\u0131rk\u00f6y",
    "gn:population":0,
    "gn:timezone":"Europe/Istanbul",
    "iso:country":"TR",
    "name:tur_x_preferred":[
        "\u00c7ak\u0131rk\u00f6y"
    ],
    "name:tur_x_variant":[
        "\u00c7ak\u0131r"
    ],
    "wof:name":"Cakirkoy",
    "wof:placetype":"locality"
},
  "geometry": {"coordinates":[30.46906,38.76555],"type":"Point"}
}