{
  "type": "Feature",
  "properties": {
    "gn:admin1_code":"15",
    "gn:asciiname":"Karapinar",
    "gn:country_code":"TR",
    "gn:dem":799,
    "gn:feature_class":"P",
    "gn:feature_code":"PPL",
    "gn:name":"Karap\u0131nar",
    "gn:population":0,
    "gn:timezone":"Europe/Istanbul",
    "iso:country":"TR",
    "wof:name":"Karapinar",
    "wof:placetype":"locality"
},
  "geometry": {"coordinates":[30.53472,37.35806],"type":"Point"}
}