{
  "type": "Feature",
  "properties": {
    "gn:admin1_code":"23",
    "gn:asciiname":"Karoglu",
    "gn:country_code":"TR",
    "gn:dem":1173,
    "gn:feature_class":"P",
    "gn:feature_code":"PPL",
    "gn:name":"Karo\u011flu",
    "gn:population":0,
    "gn:timezone":"Europe/Istanbul",
    "iso:country":"TR",
    "name:tur_x_preferred":[
        "Karo\u011flu"
    ],
    "wof:name":"Karoglu",
    "wof:placetype":"locality"
},
  "geometry": {"coordinates":[38.63634,38.63119],"type":"Point"}
}