{
  "type": "Feature",
  "properties": {
    "gn:country":"TR",
    "gn:fcode":"PPL",
    "gn:pop":1100,
    "iso:country":"TR",
    "name:tur_x_preferred":[
        "Yenip\u0131nar"
    ],
    "name:unk_x_variant":[
        "Ashagy-Keferzo"
    ],
    "qs:name":"Yenip\u0131nar",
    "qs:photos_9r":0,
    "qs:photos_sr":0,
    "qs:pop_sr":"3",
    "wd:wordcount":34,
    "wof:name":"Yenip\u0131nar",
    "wof:placetype":"locality",
    "wof:population":1100
},
  "geometry": {"coordinates":[41.30247,37.84345],"type":"Point"}
}