{
  "type": "Feature",
  "properties": {
    "gn:admin1_code":"37.0",
    "gn:asciiname":"Kapanci",
    "gn:country_code":"TR",
    "gn:dem":484,
    "gn:feature_class":"P",
    "gn:feature_code":"PPL",
    "gn:name":"Kapanc\u0131",
    "gn:population":0,
    "gn:timezone":"Europe/Istanbul",
    "iso:country":"TR",
    "name:und_x_variant":[
        "Mantere\u015f",
        "Menter\u015f",
        "Kapanc\u0131"
    ],
    "wof:name":"Kapanci",
    "wof:placetype":"locality"
},
  "geometry": {"coordinates":[33.00174000000001,41.67584],"type":"Point"}
}