{
  "type": "Feature",
  "properties": {
    "gn:admin1_code":"57.0",
    "gn:asciiname":"Corman",
    "gn:country_code":"TR",
    "gn:dem":446,
    "gn:feature_class":"P",
    "gn:feature_code":"PPL",
    "gn:name":"\u00c7orman",
    "gn:population":0,
    "gn:timezone":"Europe/Istanbul",
    "iso:country":"TR",
    "name:cat_x_preferred":[
        "Corman"
    ],
    "name:deu_x_preferred":[
        "Corman"
    ],
    "name:fra_x_preferred":[
        "Corman"
    ],
    "name:heb_x_preferred":[
        "\u05e7\u05d5\u05e8\u05de\u05df"
    ],
    "name:ita_x_preferred":[
        "Corman"
    ],
    "name:jpn_x_preferred":[
        "\u30b3\u30fc\u30de\u30f3"
    ],
    "name:und_x_variant":[
        "\u00c7oman",
        "\u00c7orman"
    ],
    "wof:name":"Corman",
    "wof:placetype":"locality"
},
  "geometry": {"coordinates":[34.83176,41.34276],"type":"Point"}
}