{
  "type": "Feature",
  "properties": {
    "gn:admin1_code":"09",
    "gn:asciiname":"Keller",
    "gn:country_code":"TR",
    "gn:dem":350,
    "gn:feature_class":"P",
    "gn:feature_code":"PPL",
    "gn:name":"Keller",
    "gn:population":0,
    "gn:timezone":"Europe/Istanbul",
    "iso:country":"TR",
    "name:tur_x_preferred":[
        "Keller"
    ],
    "wof:name":"Keller",
    "wof:placetype":"locality"
},
  "geometry": {"coordinates":[28.06667,37.92571],"type":"Point"}
}