{
  "type": "Feature",
  "properties": {
    "gn:admin1_code":"72",
    "gn:asciiname":"Degerli",
    "gn:country_code":"TR",
    "gn:dem":864,
    "gn:feature_class":"P",
    "gn:feature_code":"PPL",
    "gn:name":"De\u011ferli",
    "gn:population":0,
    "gn:timezone":"Europe/Istanbul",
    "iso:country":"TR",
    "name:und_x_variant":[
        "\u0130van",
        "De\u011ferli"
    ],
    "wof:name":"Degerli",
    "wof:placetype":"locality"
},
  "geometry": {"coordinates":[41.75167,37.45389],"type":"Point"}
}