{
  "type": "Feature",
  "properties": {
    "gn:admin1_code":"58.0",
    "gn:asciiname":"Doganli",
    "gn:country_code":"TR",
    "gn:dem":1396,
    "gn:feature_class":"P",
    "gn:feature_code":"PPL",
    "gn:name":"Do\u011fanl\u0131",
    "gn:population":0,
    "gn:timezone":"Europe/Istanbul",
    "iso:country":"TR",
    "wof:name":"Doganli",
    "wof:placetype":"locality"
},
  "geometry": {"coordinates":[36.72537,40.11291],"type":"Point"}
}