{
  "type": "Feature",
  "properties": {
    "gn:admin1_code":"39.0",
    "gn:asciiname":"Kayali",
    "gn:cc2":"TR",
    "gn:country_code":"TR",
    "gn:dem":255,
    "gn:feature_class":"P",
    "gn:feature_code":"PPL",
    "gn:name":"Kayal\u0131",
    "gn:population":0,
    "gn:timezone":"Europe/Istanbul",
    "iso:country":"TR",
    "name:und_x_variant":[
        "Bedre",
        "Kayal\u0131"
    ],
    "wof:name":"Kayali",
    "wof:placetype":"locality"
},
  "geometry": {"coordinates":[27.09889,41.77778],"type":"Point"}
}