{
  "type": "Feature",
  "properties": {
    "gn:admin1_code":"53.0",
    "gn:asciiname":"Cilingir",
    "gn:country_code":"TR",
    "gn:dem":265,
    "gn:feature_class":"P",
    "gn:feature_code":"PPL",
    "gn:name":"\u00c7ilingir",
    "gn:population":0,
    "gn:timezone":"Europe/Istanbul",
    "iso:country":"TR",
    "wof:name":"Cilingir",
    "wof:placetype":"locality"
},
  "geometry": {"coordinates":[40.79073,41.09215],"type":"Point"}
}