{
  "type": "Feature",
  "properties": {
    "gn:admin1_code":"55.0",
    "gn:asciiname":"Kuflek",
    "gn:country_code":"TR",
    "gn:dem":861,
    "gn:feature_class":"P",
    "gn:feature_code":"PPL",
    "gn:name":"K\u00fcflek",
    "gn:population":0,
    "gn:timezone":"Europe/Istanbul",
    "iso:country":"TR",
    "wof:name":"Kuflek",
    "wof:placetype":"locality"
},
  "geometry": {"coordinates":[35.70206,40.91032],"type":"Point"}
}