{
  "type": "Feature",
  "properties": {
    "gn:admin1_code":"81",
    "gn:asciiname":"Catalcam",
    "gn:country_code":"TR",
    "gn:dem":1582,
    "gn:feature_class":"P",
    "gn:feature_code":"PPL",
    "gn:name":"\u00c7atal\u00e7am",
    "gn:population":0,
    "gn:timezone":"Europe/Istanbul",
    "iso:country":"TR",
    "name:und_x_variant":[
        "\u015ean\u015fa",
        "\u00c7atal\u00e7am"
    ],
    "wof:name":"Catalcam",
    "wof:placetype":"locality"
},
  "geometry": {"coordinates":[36.07861,38.19389],"type":"Point"}
}