{
  "type": "Feature",
  "properties": {
    "gn:admin1_code":"25",
    "gn:asciiname":"Saclik",
    "gn:country_code":"TR",
    "gn:dem":1997,
    "gn:feature_class":"P",
    "gn:feature_code":"PPL",
    "gn:name":"Sa\u00e7l\u0131k",
    "gn:population":0,
    "gn:timezone":"Europe/Istanbul",
    "iso:country":"TR",
    "name:tur_x_preferred":[
        "Sa\u00e7l\u0131k"
    ],
    "wof:name":"Saclik",
    "wof:placetype":"locality"
},
  "geometry": {"coordinates":[42.18761,39.86456],"type":"Point"}
}