{
  "type": "Feature",
  "properties": {
    "gn:admin1_code":"35",
    "gn:asciiname":"Nohutalan",
    "gn:country_code":"TR",
    "gn:dem":199,
    "gn:feature_class":"P",
    "gn:feature_code":"PPL",
    "gn:name":"Nohutalan",
    "gn:population":0,
    "gn:timezone":"Europe/Istanbul",
    "iso:country":"TR",
    "name:tur_x_preferred":[
        "Nohutalan"
    ],
    "wof:name":"Nohutalan",
    "wof:placetype":"locality"
},
  "geometry": {"coordinates":[26.52373,38.29995],"type":"Point"}
}