{
  "type": "Feature",
  "properties": {
    "gn:admin1_code":"44",
    "gn:asciiname":"Biyikbogazi",
    "gn:country_code":"TR",
    "gn:dem":1524,
    "gn:feature_class":"P",
    "gn:feature_code":"PPL",
    "gn:name":"B\u0131y\u0131kbo\u011faz\u0131",
    "gn:population":0,
    "gn:timezone":"Europe/Istanbul",
    "iso:country":"TR",
    "name:tur_x_preferred":[
        "B\u0131y\u0131kbo\u011faz\u0131"
    ],
    "name:und_x_variant":[
        "B\u0131y\u0131kbo\u011faz"
    ],
    "wof:name":"Biyikbogazi",
    "wof:placetype":"locality"
},
  "geometry": {"coordinates":[37.69472,38.9352],"type":"Point"}
}