{
  "type": "Feature",
  "properties": {
    "gn:admin1_code":"12",
    "gn:asciiname":"Kiran",
    "gn:country_code":"TR",
    "gn:dem":1144,
    "gn:feature_class":"P",
    "gn:feature_code":"PPL",
    "gn:name":"K\u0131ran",
    "gn:population":0,
    "gn:timezone":"Europe/Istanbul",
    "iso:country":"TR",
    "name:tur_x_preferred":[
        "K\u0131ran"
    ],
    "wof:name":"Kiran",
    "wof:placetype":"locality"
},
  "geometry": {"coordinates":[40.4189,38.74238],"type":"Point"}
}