{
  "type": "Feature",
  "properties": {
    "gn:admin1_code":"72.0",
    "gn:asciiname":"Ziyarethesp",
    "gn:cc2":"TR",
    "gn:country_code":"TR",
    "gn:dem":979,
    "gn:feature_class":"P",
    "gn:feature_code":"PPL",
    "gn:name":"Ziyarethesp",
    "gn:population":0,
    "gn:timezone":"Europe/Istanbul",
    "iso:country":"TR",
    "name:und_x_variant":[
        "Ziyaretkhesp",
        "Ziyarethesp"
    ],
    "wof:name":"Ziyarethesp",
    "wof:placetype":"locality"
},
  "geometry": {"coordinates":[40.61056,37.46111],"type":"Point"}
}