{
  "type": "Feature",
  "properties": {
    "gn:admin1_code":"25.0",
    "gn:asciiname":"Goresken",
    "gn:country_code":"TR",
    "gn:dem":1896,
    "gn:feature_class":"P",
    "gn:feature_code":"PPL",
    "gn:name":"G\u00f6re\u015fken",
    "gn:population":0,
    "gn:timezone":"Europe/Istanbul",
    "iso:country":"TR",
    "name:tur_x_preferred":[
        "G\u00f6re\u015fken"
    ],
    "wof:name":"Goresken",
    "wof:placetype":"locality"
},
  "geometry": {"coordinates":[42.38366,40.43767],"type":"Point"}
}