{
  "type": "Feature",
  "properties": {
    "gn:admin1_code":"65",
    "gn:asciiname":"Erci",
    "gn:country_code":"TR",
    "gn:dem":1941,
    "gn:feature_class":"P",
    "gn:feature_code":"PPL",
    "gn:name":"Erci",
    "gn:population":0,
    "gn:timezone":"Europe/Istanbul",
    "iso:country":"TR",
    "name:und_x_variant":[
        "Ecri",
        "Erci"
    ],
    "wof:name":"Erci",
    "wof:placetype":"locality"
},
  "geometry": {"coordinates":[44.13333,37.86667],"type":"Point"}
}