{
  "type": "Feature",
  "properties": {
    "gn:admin1_code":"40",
    "gn:asciiname":"Yagmurlusariusagi",
    "gn:country_code":"TR",
    "gn:dem":1313,
    "gn:feature_class":"P",
    "gn:feature_code":"PPL",
    "gn:name":"Ya\u011fmurlusar\u0131u\u015fa\u011f\u0131",
    "gn:population":0,
    "gn:timezone":"Europe/Istanbul",
    "iso:country":"TR",
    "wof:name":"Yagmurlusariusagi",
    "wof:placetype":"locality"
},
  "geometry": {"coordinates":[33.91206,39.25782],"type":"Point"}
}