{
  "type": "Feature",
  "properties": {
    "gn:admin1_code":"83",
    "gn:asciiname":"Kepirler",
    "gn:country_code":"TR",
    "gn:dem":392,
    "gn:feature_class":"P",
    "gn:feature_code":"PPL",
    "gn:name":"Kepirler",
    "gn:population":0,
    "gn:timezone":"Europe/Istanbul",
    "iso:country":"TR",
    "name:tur_x_preferred":[
        "Kepirler"
    ],
    "name:und_x_variant":[
        "Karaamut",
        "Karahamut",
        "Karamut"
    ],
    "wof:name":"Kepirler",
    "wof:placetype":"locality"
},
  "geometry": {"coordinates":[37.95913,36.92816],"type":"Point"}
}