{
  "type": "Feature",
  "properties": {
    "gn:admin1_code":"04",
    "gn:asciiname":"Yukari Duavan",
    "gn:country_code":"TR",
    "gn:dem":2520,
    "gn:feature_class":"P",
    "gn:feature_code":"PPL",
    "gn:name":"Yukar\u0131 Duavan",
    "gn:population":0,
    "gn:timezone":"Europe/Istanbul",
    "iso:country":"TR",
    "wof:name":"Yukari Duavan",
    "wof:placetype":"locality"
},
  "geometry": {"coordinates":[43.71667,39.25],"type":"Point"}
}