{
  "type": "Feature",
  "properties": {
    "gn:admin1_code":"32.0",
    "gn:asciiname":"Cayir Yaylasi",
    "gn:country_code":"TR",
    "gn:dem":1323,
    "gn:feature_class":"P",
    "gn:feature_code":"PPL",
    "gn:name":"\u00c7ay\u0131r Yaylas\u0131",
    "gn:population":0,
    "gn:timezone":"Europe/Istanbul",
    "iso:country":"TR",
    "wof:name":"Cayir Yaylasi",
    "wof:placetype":"locality"
},
  "geometry": {"coordinates":[33.08598,36.4027],"type":"Point"}
}