{
  "type": "Feature",
  "properties": {
    "gn:admin1_code":"38",
    "gn:asciiname":"Cayirozu",
    "gn:country_code":"TR",
    "gn:dem":1085,
    "gn:feature_class":"P",
    "gn:feature_code":"PPL",
    "gn:name":"\u00c7ay\u0131r\u00f6z\u00fc",
    "gn:population":0,
    "gn:timezone":"Europe/Istanbul",
    "iso:country":"TR",
    "wof:name":"Cayirozu",
    "wof:placetype":"locality"
},
  "geometry": {"coordinates":[35.2906,38.42236],"type":"Point"}
}