{
  "type": "Feature",
  "properties": {
    "gn:admin1_code":"44",
    "gn:asciiname":"Yukari Selimli",
    "gn:country_code":"TR",
    "gn:dem":1626,
    "gn:feature_class":"P",
    "gn:feature_code":"PPL",
    "gn:name":"Yukar\u0131 Selimli",
    "gn:population":0,
    "gn:timezone":"Europe/Istanbul",
    "iso:country":"TR",
    "name:tur_x_preferred":[
        "Yukar\u0131 Selimli"
    ],
    "name:und_x_variant":[
        "Selimli",
        "Yukar\u0131selimli"
    ],
    "wof:name":"Yukari Selimli",
    "wof:placetype":"locality"
},
  "geometry": {"coordinates":[37.77775,38.75154000000001],"type":"Point"}
}