{
  "type": "Feature",
  "properties": {
    "gn:admin1_code":"04",
    "gn:asciiname":"Alakoyun",
    "gn:country_code":"TR",
    "gn:dem":1986,
    "gn:feature_class":"P",
    "gn:feature_code":"PPL",
    "gn:name":"Alakoyun",
    "gn:population":0,
    "gn:timezone":"Europe/Istanbul",
    "iso:country":"TR",
    "name:und_x_variant":[
        "Ha\u00e7l\u0131",
        "Alakoyun"
    ],
    "wof:name":"Alakoyun",
    "wof:placetype":"locality"
},
  "geometry": {"coordinates":[43.14183,39.55538],"type":"Point"}
}