{
  "type": "Feature",
  "properties": {
    "gn:admin1_code":"54",
    "gn:asciiname":"Lutfiyekosk",
    "gn:country_code":"TR",
    "gn:dem":102,
    "gn:feature_class":"P",
    "gn:feature_code":"PPL",
    "gn:name":"L\u00fctfiyek\u00f6\u015fk",
    "gn:population":0,
    "gn:timezone":"Europe/Istanbul",
    "iso:country":"TR",
    "name:tur_x_preferred":[
        "L\u00fctfiyek\u00f6\u015fk"
    ],
    "wof:name":"Lutfiyekosk",
    "wof:placetype":"locality"
},
  "geometry": {"coordinates":[30.69647,40.80397],"type":"Point"}
}