{
  "type": "Feature",
  "properties": {
    "gn:admin1_code":"65.0",
    "gn:asciiname":"Agildere",
    "gn:country_code":"TR",
    "gn:dem":2316,
    "gn:feature_class":"P",
    "gn:feature_code":"PPL",
    "gn:name":"A\u011f\u0131ldere",
    "gn:population":0,
    "gn:timezone":"Europe/Istanbul",
    "iso:country":"TR",
    "name:tur_x_preferred":[
        "A\u011f\u0131ldere"
    ],
    "wof:name":"Agildere",
    "wof:placetype":"locality"
},
  "geometry": {"coordinates":[43.90015,38.23168],"type":"Point"}
}