{
  "type": "Feature",
  "properties": {
    "gn:admin1_code":"07",
    "gn:asciiname":"Baskoy",
    "gn:country_code":"TR",
    "gn:dem":647,
    "gn:feature_class":"P",
    "gn:feature_code":"PPL",
    "gn:name":"Ba\u015fk\u00f6y",
    "gn:population":0,
    "gn:timezone":"Europe/Istanbul",
    "iso:country":"TR",
    "name:und_x_variant":[
        "Ba\u015fk\u00f6y",
        "C\u0131rbat"
    ],
    "wof:name":"Baskoy",
    "wof:placetype":"locality"
},
  "geometry": {"coordinates":[32.358,36.45765],"type":"Point"}
}