{
  "type": "Feature",
  "properties": {
    "gn:admin1_code":"70.0",
    "gn:asciiname":"Mollayasin",
    "gn:country_code":"TR",
    "gn:dem":1649,
    "gn:feature_class":"P",
    "gn:feature_code":"PPL",
    "gn:name":"Mollayasin",
    "gn:population":0,
    "gn:timezone":"Europe/Istanbul",
    "iso:country":"TR",
    "wof:name":"Mollayasin",
    "wof:placetype":"locality"
},
  "geometry": {"coordinates":[44.17689,37.29617],"type":"Point"}
}