{
  "type": "Feature",
  "properties": {
    "gn:admin1_code":"37.0",
    "gn:asciiname":"Yamanlar",
    "gn:country_code":"TR",
    "gn:dem":866,
    "gn:feature_class":"P",
    "gn:feature_code":"PPL",
    "gn:name":"Yamanlar",
    "gn:population":0,
    "gn:timezone":"Europe/Istanbul",
    "iso:country":"TR",
    "name:und_x_variant":[
        "Kamana",
        "Yamanlar"
    ],
    "wof:name":"Yamanlar",
    "wof:placetype":"locality"
},
  "geometry": {"coordinates":[32.99247,41.70725],"type":"Point"}
}