{
  "type": "Feature",
  "properties": {
    "gn:admin1_code":"24",
    "gn:asciiname":"Bozyayla",
    "gn:country_code":"TR",
    "gn:dem":1165,
    "gn:feature_class":"P",
    "gn:feature_code":"PPL",
    "gn:name":"Bozyayla",
    "gn:population":0,
    "gn:timezone":"Europe/Istanbul",
    "iso:country":"TR",
    "name:und_x_variant":[
        "\u00c7\u00f6rencil",
        "Bozyayla"
    ],
    "wof:name":"Bozyayla",
    "wof:placetype":"locality"
},
  "geometry": {"coordinates":[38.56244,39.58588],"type":"Point"}
}