{
  "type": "Feature",
  "properties": {
    "gn:admin1_code":"09",
    "gn:admin2_code":"8632401.0",
    "gn:asciiname":"Guzelcamli",
    "gn:cc2":"TR",
    "gn:country_code":"TR",
    "gn:dem":29,
    "gn:feature_class":"P",
    "gn:feature_code":"PPL",
    "gn:name":"G\u00fczel\u00e7aml\u0131",
    "gn:population":0,
    "gn:timezone":"Europe/Istanbul",
    "iso:country":"TR",
    "name:tur_x_preferred":[
        "G\u00fczel\u00e7aml\u0131"
    ],
    "name:und_x_variant":[
        "Ghiour Changli",
        "G\u00fczelcamli"
    ],
    "wof:name":"Guzelcamli",
    "wof:placetype":"locality"
},
  "geometry": {"coordinates":[27.22778,37.71333],"type":"Point"}
}