{
  "type": "Feature",
  "properties": {
    "gn:admin1_code":"87.0",
    "gn:asciiname":"Yanaz",
    "gn:country_code":"TR",
    "gn:dem":109,
    "gn:feature_class":"P",
    "gn:feature_code":"PPL",
    "gn:name":"Yanaz",
    "gn:population":0,
    "gn:timezone":"Europe/Istanbul",
    "iso:country":"TR",
    "name:ceb_x_preferred":[
        "Yanaz"
    ],
    "name:msa_x_preferred":[
        "Yanaz"
    ],
    "name:tur_x_preferred":[
        "Yanaz"
    ],
    "name:und_x_variant":[
        "Ya\u011f\u0131z"
    ],
    "name:urd_x_preferred":[
        "\u06cc\u0646\u0632"
    ],
    "name:vie_x_preferred":[
        "Yanaz"
    ],
    "wof:name":"Yanaz",
    "wof:placetype":"locality"
},
  "geometry": {"coordinates":[32.42759,41.57437],"type":"Point"}
}