{
  "type": "Feature",
  "properties": {
    "gn:admin1_code":"15",
    "gn:asciiname":"Mustalaklar",
    "gn:country_code":"TR",
    "gn:dem":651,
    "gn:feature_class":"P",
    "gn:feature_code":"PPL",
    "gn:name":"Mustalaklar",
    "gn:population":0,
    "gn:timezone":"Europe/Istanbul",
    "iso:country":"TR",
    "wof:name":"Mustalaklar",
    "wof:placetype":"locality"
},
  "geometry": {"coordinates":[30.86344,37.32065],"type":"Point"}
}