{
  "type": "Feature",
  "properties": {
    "gn:admin1_code":"57.0",
    "gn:asciiname":"Samlioglu",
    "gn:country_code":"TR",
    "gn:dem":215,
    "gn:feature_class":"P",
    "gn:feature_code":"PPL",
    "gn:name":"\u015eaml\u0131o\u011flu",
    "gn:population":0,
    "gn:timezone":"Europe/Istanbul",
    "iso:country":"TR",
    "wof:name":"Samlioglu",
    "wof:placetype":"locality"
},
  "geometry": {"coordinates":[35.04237,41.85394],"type":"Point"}
}