{
  "type": "Feature",
  "properties": {
    "gn:admin1_code":"31.0",
    "gn:asciiname":"Baltacik",
    "gn:country_code":"TR",
    "gn:dem":118,
    "gn:feature_class":"P",
    "gn:feature_code":"PPL",
    "gn:name":"Baltac\u0131k",
    "gn:population":0,
    "gn:timezone":"Europe/Istanbul",
    "iso:country":"TR",
    "name:und_x_variant":[
        "Aparly",
        "Aparl\u0131",
        "Baltac\u0131k"
    ],
    "wof:name":"Baltacik",
    "wof:placetype":"locality"
},
  "geometry": {"coordinates":[36.13092,36.19133],"type":"Point"}
}