{
  "type": "Feature",
  "properties": {
    "gn:admin1_code":"81",
    "gn:asciiname":"Kibrislar",
    "gn:cc2":"TR",
    "gn:country_code":"TR",
    "gn:dem":837,
    "gn:feature_class":"P",
    "gn:feature_code":"PPL",
    "gn:name":"K\u0131br\u0131slar",
    "gn:population":0,
    "gn:timezone":"Europe/Istanbul",
    "iso:country":"TR",
    "name:deu_x_preferred":[
        "K\u0131br\u0131slar"
    ],
    "name:msa_x_preferred":[
        "K\u0131br\u0131slar"
    ],
    "name:tur_x_preferred":[
        "K\u0131br\u0131slar"
    ],
    "name:und_x_variant":[
        "K\u0131pr\u0131slar"
    ],
    "name:vie_x_preferred":[
        "K\u0131br\u0131slar"
    ],
    "wof:name":"Kibrislar",
    "wof:placetype":"locality"
},
  "geometry": {"coordinates":[35.70610999999999,37.65111],"type":"Point"}
}