{
  "type": "Feature",
  "properties": {
    "gn:admin1_code":"84.0",
    "gn:asciiname":"Akdam",
    "gn:country_code":"TR",
    "gn:dem":1141,
    "gn:feature_class":"P",
    "gn:feature_code":"PPL",
    "gn:name":"Akdam",
    "gn:population":0,
    "gn:timezone":"Europe/Istanbul",
    "iso:country":"TR",
    "name:deu_x_preferred":[
        "Akdam"
    ],
    "name:eng_x_preferred":[
        "Akdam"
    ],
    "name:rus_x_preferred":[
        "\u0410\u0433\u0434\u0430\u043c"
    ],
    "name:tur_x_preferred":[
        "Akdam"
    ],
    "wof:name":"Akdam",
    "wof:placetype":"locality"
},
  "geometry": {"coordinates":[43.28766,40.16174],"type":"Point"}
}