{
  "type": "Feature",
  "properties": {
    "gn:admin1_code":"65",
    "gn:asciiname":"Kavurgali",
    "gn:cc2":"TR",
    "gn:country_code":"TR",
    "gn:dem":2012,
    "gn:feature_class":"P",
    "gn:feature_code":"PPL",
    "gn:name":"Kavurgal\u0131",
    "gn:population":0,
    "gn:timezone":"Europe/Istanbul",
    "iso:country":"TR",
    "name:und_x_variant":[
        "Heret\u00fcn",
        "Kavurgal\u0131"
    ],
    "wof:name":"Kavurgali",
    "wof:placetype":"locality"
},
  "geometry": {"coordinates":[44.14278,38.08056],"type":"Point"}
}