{
  "type": "Feature",
  "properties": {
    "gn:admin1_code":"11.0",
    "gn:asciiname":"Kumbet",
    "gn:country_code":"TR",
    "gn:dem":702,
    "gn:feature_class":"P",
    "gn:feature_code":"PPL",
    "gn:name":"K\u00fcmbet",
    "gn:population":0,
    "gn:timezone":"Europe/Istanbul",
    "iso:country":"TR",
    "name:tur_x_preferred":[
        "K\u00fcmbet"
    ],
    "wof:name":"Kumbet",
    "wof:placetype":"locality"
},
  "geometry": {"coordinates":[30.37302,40.21803],"type":"Point"}
}