{
  "type": "Feature",
  "properties": {
    "gn:admin1_code":"58",
    "gn:asciiname":"Kuzoren",
    "gn:country_code":"TR",
    "gn:dem":1394,
    "gn:feature_class":"P",
    "gn:feature_code":"PPL",
    "gn:name":"Kuz\u00f6ren",
    "gn:population":0,
    "gn:timezone":"Europe/Istanbul",
    "iso:country":"TR",
    "name:und_x_variant":[
        "Kozverah",
        "Kuzveran",
        "Kuzviran",
        "Kuz\u00f6ren"
    ],
    "wof:name":"Kuzoren",
    "wof:placetype":"locality"
},
  "geometry": {"coordinates":[37.75,39.76667],"type":"Point"}
}