{
  "type": "Feature",
  "properties": {
    "gn:admin1_code":"12.0",
    "gn:asciiname":"Koklu",
    "gn:country_code":"TR",
    "gn:dem":1343,
    "gn:feature_class":"P",
    "gn:feature_code":"PPL",
    "gn:name":"K\u00f6kl\u00fc",
    "gn:population":0,
    "gn:timezone":"Europe/Istanbul",
    "iso:country":"TR",
    "name:tur_x_preferred":[
        "K\u00f6kl\u00fc"
    ],
    "wof:name":"Koklu",
    "wof:placetype":"locality"
},
  "geometry": {"coordinates":[40.62118,38.95136],"type":"Point"}
}