{
  "type": "Feature",
  "properties": {
    "gn:admin1_code":"25.0",
    "gn:asciiname":"Saglicak",
    "gn:country_code":"TR",
    "gn:dem":1087,
    "gn:feature_class":"P",
    "gn:feature_code":"PPL",
    "gn:name":"Sa\u011fl\u0131cak",
    "gn:population":0,
    "gn:timezone":"Europe/Istanbul",
    "iso:country":"TR",
    "name:und_x_variant":[
        "Sa\u011fl\u0131cak",
        "Berdik"
    ],
    "wof:name":"Saglicak",
    "wof:placetype":"locality"
},
  "geometry": {"coordinates":[42.16621,40.69392],"type":"Point"}
}