{
  "type": "Feature",
  "properties": {
    "gn:admin1_code":"28.0",
    "gn:asciiname":"Tekgoz",
    "gn:country_code":"TR",
    "gn:dem":405,
    "gn:feature_class":"P",
    "gn:feature_code":"PPL",
    "gn:name":"Tekg\u00f6z",
    "gn:population":0,
    "gn:timezone":"Europe/Istanbul",
    "iso:country":"TR",
    "name:tur_x_preferred":[
        "Tekg\u00f6z"
    ],
    "wof:name":"Tekgoz",
    "wof:placetype":"locality"
},
  "geometry": {"coordinates":[39.06337,40.96328],"type":"Point"}
}