{
  "type": "Feature",
  "properties": {
    "gn:admin1_code":"49",
    "gn:asciiname":"Yagcilar",
    "gn:country_code":"TR",
    "gn:dem":1348,
    "gn:feature_class":"P",
    "gn:feature_code":"PPL",
    "gn:name":"Ya\u011fc\u0131lar",
    "gn:population":0,
    "gn:timezone":"Europe/Istanbul",
    "iso:country":"TR",
    "name:tur_x_preferred":[
        "Ya\u011fc\u0131lar"
    ],
    "name:und_x_variant":[
        "Evran"
    ],
    "wof:name":"Yagcilar",
    "wof:placetype":"locality"
},
  "geometry": {"coordinates":[41.45361,38.92492],"type":"Point"}
}