{
  "type": "Feature",
  "properties": {
    "gn:admin1_code":"14",
    "gn:asciiname":"Seyitaliler",
    "gn:country_code":"TR",
    "gn:dem":1167,
    "gn:feature_class":"P",
    "gn:feature_code":"PPL",
    "gn:name":"\u015eeyitaliler",
    "gn:population":0,
    "gn:timezone":"Europe/Istanbul",
    "iso:country":"TR",
    "wof:name":"Seyitaliler",
    "wof:placetype":"locality"
},
  "geometry": {"coordinates":[32.09346,40.70388],"type":"Point"}
}