{
  "type": "Feature",
  "properties": {
    "gn:admin1_code":"82.0",
    "gn:asciiname":"Gaziler",
    "gn:country_code":"TR",
    "gn:dem":906,
    "gn:feature_class":"P",
    "gn:feature_code":"PPL",
    "gn:name":"Gaziler",
    "gn:population":0,
    "gn:timezone":"Europe/Istanbul",
    "iso:country":"TR",
    "wof:name":"Gaziler",
    "wof:placetype":"locality"
},
  "geometry": {"coordinates":[33.60239,40.89572],"type":"Point"}
}