{
  "type": "Feature",
  "properties": {
    "gn:admin1_code":"40",
    "gn:asciiname":"Yukariciftlik",
    "gn:country_code":"TR",
    "gn:dem":994,
    "gn:feature_class":"P",
    "gn:feature_code":"PPL",
    "gn:name":"Yukar\u0131\u00e7iftlik",
    "gn:population":0,
    "gn:timezone":"Europe/Istanbul",
    "iso:country":"TR",
    "name:und_x_variant":[
        "\u00c7iftlikb\u00e2l\u00e2",
        "Yukar\u0131\u00e7iftlik"
    ],
    "wof:name":"Yukariciftlik",
    "wof:placetype":"locality"
},
  "geometry": {"coordinates":[33.75682,39.43659],"type":"Point"}
}