{
  "type": "Feature",
  "properties": {
    "gn:admin1_code":"81",
    "gn:asciiname":"Akcali",
    "gn:country_code":"TR",
    "gn:dem":154,
    "gn:feature_class":"P",
    "gn:feature_code":"PPL",
    "gn:name":"Ak\u00e7al\u0131",
    "gn:population":0,
    "gn:timezone":"Europe/Istanbul",
    "iso:country":"TR",
    "name:und_x_variant":[
        "Ak\u00e7al\u0131",
        "M\u00fcsait"
    ],
    "wof:name":"Akcali",
    "wof:placetype":"locality"
},
  "geometry": {"coordinates":[35.17128,37.19316],"type":"Point"}
}