{
  "type": "Feature",
  "properties": {
    "gn:admin1_code":"43",
    "gn:asciiname":"Yesilbayir",
    "gn:country_code":"TR",
    "gn:dem":1250,
    "gn:feature_class":"P",
    "gn:feature_code":"PPL",
    "gn:name":"Ye\u015filbay\u0131r",
    "gn:population":0,
    "gn:timezone":"Europe/Istanbul",
    "iso:country":"TR",
    "name:tur_x_preferred":[
        "Ye\u015filbay\u0131r"
    ],
    "name:tur_x_variant":[
        "Etyemez"
    ],
    "wof:name":"Yesilbayir",
    "wof:placetype":"locality"
},
  "geometry": {"coordinates":[30.38806,39.18472],"type":"Point"}
}