{
  "type": "Feature",
  "properties": {
    "gn:admin1_code":"35",
    "gn:asciiname":"Duverlik",
    "gn:country_code":"TR",
    "gn:dem":222,
    "gn:feature_class":"P",
    "gn:feature_code":"PPL",
    "gn:name":"D\u00fcverlik",
    "gn:population":0,
    "gn:timezone":"Europe/Istanbul",
    "iso:country":"TR",
    "wof:name":"Duverlik",
    "wof:placetype":"locality"
},
  "geometry": {"coordinates":[27.44998,38.21676],"type":"Point"}
}