{
  "type": "Feature",
  "properties": {
    "gn:admin1_code":"63",
    "gn:asciiname":"Kirbirni",
    "gn:country_code":"TR",
    "gn:dem":718,
    "gn:feature_class":"P",
    "gn:feature_code":"PPL",
    "gn:name":"K\u0131rbirni",
    "gn:population":0,
    "gn:timezone":"Europe/Istanbul",
    "iso:country":"TR",
    "name:tur_x_preferred":[
        "K\u0131rbirni"
    ],
    "name:und_x_variant":[
        "Direkli"
    ],
    "wof:name":"Kirbirni",
    "wof:placetype":"locality"
},
  "geometry": {"coordinates":[39.35954,37.26107],"type":"Point"}
}