{
  "type": "Feature",
  "properties": {
    "gn:admin1_code":"5.0",
    "gn:asciiname":"Beyalan",
    "gn:country_code":"TR",
    "gn:dem":922,
    "gn:feature_class":"P",
    "gn:feature_code":"PPL",
    "gn:name":"Beyalan",
    "gn:population":0,
    "gn:timezone":"Europe/Istanbul",
    "iso:country":"TR",
    "wof:name":"Beyalan",
    "wof:placetype":"locality"
},
  "geometry": {"coordinates":[36.33957,40.96048],"type":"Point"}
}