{
  "type": "Feature",
  "properties": {
    "gn:admin1_code":"63.0",
    "gn:asciiname":"Buyuk Celle",
    "gn:country_code":"TR",
    "gn:dem":385,
    "gn:feature_class":"P",
    "gn:feature_code":"PPL",
    "gn:name":"B\u00fcy\u00fck Celle",
    "gn:population":0,
    "gn:timezone":"Europe/Istanbul",
    "iso:country":"TR",
    "name:tur_x_historical":[
        "B\u00fcy\u00fck\u00e7elle"
    ],
    "name:tur_x_preferred":[
        "B\u00fcy\u00fck\u00e7elle"
    ],
    "name:und_x_variant":[
        "Byuyuk Dzhelle",
        "B\u00fcy\u00fck Celle"
    ],
    "wof:name":"Buyuk Celle",
    "wof:placetype":"locality"
},
  "geometry": {"coordinates":[39.12389,36.98972],"type":"Point"}
}