{
  "type": "Feature",
  "properties": {
    "gn:admin1_code":"13",
    "gn:asciiname":"Tasbogaz",
    "gn:country_code":"TR",
    "gn:dem":1526,
    "gn:feature_class":"P",
    "gn:feature_code":"PPL",
    "gn:name":"Ta\u015fbo\u011faz",
    "gn:population":0,
    "gn:timezone":"Europe/Istanbul",
    "iso:country":"TR",
    "name:tur_x_preferred":[
        "Ta\u015fbo\u011faz"
    ],
    "wof:name":"Tasbogaz",
    "wof:placetype":"locality"
},
  "geometry": {"coordinates":[41.77159,38.402],"type":"Point"}
}