{
  "type": "Feature",
  "properties": {
    "gn:admin1_code":"20",
    "gn:asciiname":"Turlubey",
    "gn:country_code":"TR",
    "gn:dem":814,
    "gn:feature_class":"P",
    "gn:feature_code":"PPL",
    "gn:name":"T\u00fcrl\u00fcbey",
    "gn:population":0,
    "gn:timezone":"Europe/Istanbul",
    "iso:country":"TR",
    "name:tur_x_preferred":[
        "T\u00fcrl\u00fcbey"
    ],
    "wof:name":"Turlubey",
    "wof:placetype":"locality"
},
  "geometry": {"coordinates":[28.89339,38.15388],"type":"Point"}
}