{
  "type": "Feature",
  "properties": {
    "gn:admin1_code":"26",
    "gn:asciiname":"Karaalan",
    "gn:country_code":"TR",
    "gn:dem":913,
    "gn:feature_class":"P",
    "gn:feature_code":"PPL",
    "gn:name":"Karaalan",
    "gn:population":0,
    "gn:timezone":"Europe/Istanbul",
    "iso:country":"TR",
    "wof:name":"Karaalan",
    "wof:placetype":"locality"
},
  "geometry": {"coordinates":[30.43881,39.64317],"type":"Point"}
}