{
  "type": "Feature",
  "properties": {
    "gn:admin1_code":"32.0",
    "gn:asciiname":"Adanalioglu",
    "gn:country_code":"TR",
    "gn:dem":7,
    "gn:feature_class":"P",
    "gn:feature_code":"PPL",
    "gn:name":"Adanal\u0131o\u011flu",
    "gn:population":0,
    "gn:timezone":"Europe/Istanbul",
    "iso:country":"TR",
    "name:tur_x_preferred":[
        "Adanal\u0131o\u011flu"
    ],
    "wof:name":"Adanalioglu",
    "wof:placetype":"locality"
},
  "geometry": {"coordinates":[34.80504000000001,36.83751],"type":"Point"}
}