{
  "type": "Feature",
  "properties": {
    "gn:admin1_code":"10",
    "gn:asciiname":"Ibistepe",
    "gn:country_code":"TR",
    "gn:dem":326,
    "gn:feature_class":"P",
    "gn:feature_code":"PPL",
    "gn:name":"\u0130bi\u015ftepe",
    "gn:population":0,
    "gn:timezone":"Europe/Istanbul",
    "iso:country":"TR",
    "name:tur_x_preferred":[
        "\u0130bi\u015ftepe"
    ],
    "wof:name":"Ibistepe",
    "wof:placetype":"locality"
},
  "geometry": {"coordinates":[28.28333,39.25],"type":"Point"}
}