{
  "type": "Feature",
  "properties": {
    "gn:admin1_code":"65.0",
    "gn:asciiname":"Bozyaka",
    "gn:country_code":"TR",
    "gn:dem":1935,
    "gn:feature_class":"P",
    "gn:feature_code":"PPL",
    "gn:name":"Bozyaka",
    "gn:population":0,
    "gn:timezone":"Europe/Istanbul",
    "iso:country":"TR",
    "name:tur_x_preferred":[
        "Bozyaka"
    ],
    "wof:name":"Bozyaka",
    "wof:placetype":"locality"
},
  "geometry": {"coordinates":[43.12535,39.11991],"type":"Point"}
}