{
  "type": "Feature",
  "properties": {
    "gn:admin1_code":"13",
    "gn:asciiname":"Tatlikaynak",
    "gn:country_code":"TR",
    "gn:dem":1512,
    "gn:feature_class":"P",
    "gn:feature_code":"PPL",
    "gn:name":"Tatl\u0131kaynak",
    "gn:population":0,
    "gn:timezone":"Europe/Istanbul",
    "iso:country":"TR",
    "name:und_x_variant":[
        "H\u0131m\u0131\u00e7ur",
        "Tatl\u0131kaynak"
    ],
    "wof:name":"Tatlikaynak",
    "wof:placetype":"locality"
},
  "geometry": {"coordinates":[42.06972,38.3673],"type":"Point"}
}