{
  "type": "Feature",
  "properties": {
    "gn:admin1_code":"04",
    "gn:asciiname":"Asagikent",
    "gn:country_code":"TR",
    "gn:dem":2112,
    "gn:feature_class":"P",
    "gn:feature_code":"PPL",
    "gn:name":"A\u015fa\u011f\u0131kent",
    "gn:population":0,
    "gn:timezone":"Europe/Istanbul",
    "iso:country":"TR",
    "name:tur_x_preferred":[
        "A\u015fa\u011f\u0131kent"
    ],
    "wof:name":"Asagikent",
    "wof:placetype":"locality"
},
  "geometry": {"coordinates":[43.27824,39.95388],"type":"Point"}
}