{
  "type": "Feature",
  "properties": {
    "gn:country":"TR",
    "gn:fcode":"PPL",
    "gn:pop":227,
    "iso:country":"TR",
    "name:unk_x_variant":[
        "Y\u00fcr\u00fck"
    ],
    "qs:name":"Dikki",
    "qs:photos_9r":0,
    "qs:photos_sr":0,
    "qs:pop_sr":"2",
    "wof:name":"Dikki",
    "wof:placetype":"locality",
    "wof:population":227
},
  "geometry": {"coordinates":[42.02056,37.28278],"type":"Point"}
}