{
  "type": "Feature",
  "properties": {
    "gn:admin1_code":"77.0",
    "gn:asciiname":"Salkimsu",
    "gn:country_code":"TR",
    "gn:dem":1991,
    "gn:feature_class":"P",
    "gn:feature_code":"PPL",
    "gn:name":"Salk\u0131msu",
    "gn:population":0,
    "gn:timezone":"Europe/Istanbul",
    "iso:country":"TR",
    "name:ceb_x_preferred":[
        "Salk\u0131msu"
    ],
    "name:eng_x_preferred":[
        "Salk\u0131msu"
    ],
    "name:msa_x_preferred":[
        "Salk\u0131msu"
    ],
    "name:rus_x_preferred":[
        "\u0425\u0435\u0440\u043c\u0435"
    ],
    "name:tur_x_preferred":[
        "Salk\u0131msu"
    ],
    "name:und_x_variant":[
        "H\u00f6rme"
    ],
    "name:vie_x_preferred":[
        "Salk\u0131msu"
    ],
    "wof:name":"Salkimsu",
    "wof:placetype":"locality"
},
  "geometry": {"coordinates":[40.3875,40.26726],"type":"Point"}
}