{
  "type": "Feature",
  "properties": {
    "gn:admin1_code":"11.0",
    "gn:asciiname":"Yakacik",
    "gn:country_code":"TR",
    "gn:dem":167,
    "gn:feature_class":"P",
    "gn:feature_code":"PPL",
    "gn:name":"Yakac\u0131k",
    "gn:population":0,
    "gn:timezone":"Europe/Istanbul",
    "iso:country":"TR",
    "name:und_x_variant":[
        "Esri",
        "Yakac\u0131k"
    ],
    "wof:name":"Yakacik",
    "wof:placetype":"locality"
},
  "geometry": {"coordinates":[30.31598,40.08359],"type":"Point"}
}