{
  "type": "Feature",
  "properties": {
    "gn:admin1_code":"25.0",
    "gn:asciiname":"Ulubel",
    "gn:country_code":"TR",
    "gn:dem":1428,
    "gn:feature_class":"P",
    "gn:feature_code":"PPL",
    "gn:name":"Ulubel",
    "gn:population":0,
    "gn:timezone":"Europe/Istanbul",
    "iso:country":"TR",
    "name:und_x_variant":[
        "Di\u015fasor"
    ],
    "wof:name":"Ulubel",
    "wof:placetype":"locality"
},
  "geometry": {"coordinates":[40.87508,40.42492],"type":"Point"}
}