{
  "type": "Feature",
  "properties": {
    "gn:admin1_code":"43",
    "gn:asciiname":"Bahatlar",
    "gn:country_code":"TR",
    "gn:dem":1093,
    "gn:feature_class":"P",
    "gn:feature_code":"PPL",
    "gn:name":"Bahatlar",
    "gn:population":0,
    "gn:timezone":"Europe/Istanbul",
    "iso:country":"TR",
    "wof:name":"Bahatlar",
    "wof:placetype":"locality"
},
  "geometry": {"coordinates":[29.3213,39.32031],"type":"Point"}
}