{
  "type": "Feature",
  "properties": {
    "gn:admin1_code":"37.0",
    "gn:asciiname":"Demirciler",
    "gn:country_code":"TR",
    "gn:dem":1397,
    "gn:feature_class":"P",
    "gn:feature_code":"PPL",
    "gn:name":"Demirciler",
    "gn:population":0,
    "gn:timezone":"Europe/Istanbul",
    "iso:country":"TR",
    "wof:name":"Demirciler",
    "wof:placetype":"locality"
},
  "geometry": {"coordinates":[34.03333,41.26667],"type":"Point"}
}