{
  "type": "Feature",
  "properties": {
    "gn:admin1_code":"12",
    "gn:asciiname":"Yekmal",
    "gn:country_code":"TR",
    "gn:dem":1738,
    "gn:feature_class":"P",
    "gn:feature_code":"PPL",
    "gn:name":"Yekmal",
    "gn:population":0,
    "gn:timezone":"Europe/Istanbul",
    "iso:country":"TR",
    "wof:name":"Yekmal",
    "wof:placetype":"locality"
},
  "geometry": {"coordinates":[40.78333,39.13333],"type":"Point"}
}