{
  "type": "Feature",
  "properties": {
    "gn:admin1_code":"39.0",
    "gn:asciiname":"Kustepe",
    "gn:country_code":"TR",
    "gn:dem":29,
    "gn:feature_class":"P",
    "gn:feature_code":"PPL",
    "gn:name":"Ku\u015ftepe",
    "gn:population":0,
    "gn:timezone":"Europe/Istanbul",
    "iso:country":"TR",
    "wof:name":"Kustepe",
    "wof:placetype":"locality"
},
  "geometry": {"coordinates":[26.95902,41.3735],"type":"Point"}
}