{
  "type": "Feature",
  "properties": {
    "gn:admin1_code":"64",
    "gn:asciiname":"Kucuk Oturak",
    "gn:country_code":"TR",
    "gn:dem":1018,
    "gn:feature_class":"P",
    "gn:feature_code":"PPL",
    "gn:name":"K\u00fc\u00e7\u00fck Oturak",
    "gn:population":0,
    "gn:timezone":"Europe/Istanbul",
    "iso:country":"TR",
    "name:und_x_variant":[
        "K\u00fc\u00e7\u00fckotrak",
        "K\u00fc\u00e7\u00fck Oturak"
    ],
    "wof:name":"Kucuk Oturak",
    "wof:placetype":"locality"
},
  "geometry": {"coordinates":[29.70709,38.81265],"type":"Point"}
}