{
  "type": "Feature",
  "properties": {
    "gn:country":"TR",
    "gn:fcode":"PPL",
    "gn:population":2000,
    "iso:country":"TR",
    "qs:name":"Ar\u0131k\u00f6y",
    "qs:photos_9r":0,
    "qs:photos_sr":0,
    "qs:pop_sr":"3",
    "wof:name":"Ar\u0131k\u00f6y",
    "wof:placetype":"locality",
    "wof:population":2000
},
  "geometry": {"coordinates":[29.00425,41.23044],"type":"Point"}
}