{
  "type": "Feature",
  "properties": {
    "gn:admin1_code":"37.0",
    "gn:asciiname":"Akmescit",
    "gn:country_code":"TR",
    "gn:dem":1167,
    "gn:feature_class":"P",
    "gn:feature_code":"PPL",
    "gn:name":"Akmescit",
    "gn:population":0,
    "gn:timezone":"Europe/Istanbul",
    "iso:country":"TR",
    "name:tur_x_preferred":[
        "Akmescit"
    ],
    "name:und_x_variant":[
        "G\u00f6\u00e7eler",
        "G\u00f6\u00e7erler",
        "Akmescit"
    ],
    "wof:name":"Akmescit",
    "wof:placetype":"locality"
},
  "geometry": {"coordinates":[33.81836,41.70367],"type":"Point"}
}