{
  "type": "Feature",
  "properties": {
    "gn:admin1_code":"25.0",
    "gn:asciiname":"Tatlisu",
    "gn:country_code":"TR",
    "gn:dem":2148,
    "gn:feature_class":"P",
    "gn:feature_code":"PPL",
    "gn:name":"Tatl\u0131su",
    "gn:population":0,
    "gn:timezone":"Europe/Istanbul",
    "iso:country":"TR",
    "name:und_x_variant":[
        "Tatl\u0131su",
        "K\u0131z\u0131lkilise"
    ],
    "wof:name":"Tatlisu",
    "wof:placetype":"locality"
},
  "geometry": {"coordinates":[41.48787,40.27447],"type":"Point"}
}