{
  "type": "Feature",
  "properties": {
    "gn:admin1_code":"58",
    "gn:asciiname":"Fakili",
    "gn:country_code":"TR",
    "gn:dem":1387,
    "gn:feature_class":"P",
    "gn:feature_code":"PPL",
    "gn:name":"Fak\u0131l\u0131",
    "gn:population":0,
    "gn:timezone":"Europe/Istanbul",
    "iso:country":"TR",
    "name:tur_x_preferred":[
        "Fak\u0131l\u0131"
    ],
    "wof:name":"Fakili",
    "wof:placetype":"locality"
},
  "geometry": {"coordinates":[36.39164,39.44568],"type":"Point"}
}