{
  "type": "Feature",
  "properties": {
    "gn:admin1_code":"24",
    "gn:asciiname":"Kokpinar",
    "gn:country_code":"TR",
    "gn:dem":1615,
    "gn:feature_class":"P",
    "gn:feature_code":"PPL",
    "gn:name":"K\u00f6kp\u0131nar",
    "gn:population":0,
    "gn:timezone":"Europe/Istanbul",
    "iso:country":"TR",
    "name:und_x_variant":[
        "Komsor",
        "K\u00f6kp\u0131nar"
    ],
    "wof:name":"Kokpinar",
    "wof:placetype":"locality"
},
  "geometry": {"coordinates":[40.56845,39.65183],"type":"Point"}
}