{
  "type": "Feature",
  "properties": {
    "gn:admin1_code":"62",
    "gn:asciiname":"Garipusagi",
    "gn:country_code":"TR",
    "gn:dem":1631,
    "gn:feature_class":"P",
    "gn:feature_code":"PPL",
    "gn:name":"Garipu\u015fa\u011f\u0131",
    "gn:population":0,
    "gn:timezone":"Europe/Istanbul",
    "iso:country":"TR",
    "name:tur_x_preferred":[
        "Garipu\u015fa\u011f\u0131"
    ],
    "wof:name":"Garipusagi",
    "wof:placetype":"locality"
},
  "geometry": {"coordinates":[39.31269,39.25394],"type":"Point"}
}