{
  "type": "Feature",
  "properties": {
    "gn:admin1_code":"14.0",
    "gn:asciiname":"Dokumacilar",
    "gn:country_code":"TR",
    "gn:dem":1081,
    "gn:feature_class":"P",
    "gn:feature_code":"PPL",
    "gn:name":"Dokumac\u0131lar",
    "gn:population":0,
    "gn:timezone":"Europe/Istanbul",
    "iso:country":"TR",
    "name:und_x_variant":[
        "Kesnar",
        "Kestar",
        "Dokumac\u0131lar"
    ],
    "wof:name":"Dokumacilar",
    "wof:placetype":"locality"
},
  "geometry": {"coordinates":[31.78013,40.37471],"type":"Point"}
}