{
  "type": "Feature",
  "properties": {
    "gn:admin1_code":"93.0",
    "gn:asciiname":"Yurukler",
    "gn:country_code":"TR",
    "gn:dem":220,
    "gn:feature_class":"P",
    "gn:feature_code":"PPL",
    "gn:name":"Y\u00fcr\u00fckler",
    "gn:population":0,
    "gn:timezone":"Europe/Istanbul",
    "iso:country":"TR",
    "name:und_x_variant":[
        "Be\u00e7iy\u00fcr\u00fckler",
        "Be\u00e7i",
        "Be\u00e7iy\u00f6r\u00fckler",
        "Y\u00fcr\u00fckler",
        "Y\u00f6r\u00fck"
    ],
    "wof:name":"Yurukler",
    "wof:placetype":"locality"
},
  "geometry": {"coordinates":[31.16954,40.90662],"type":"Point"}
}