{
  "type": "Feature",
  "properties": {
    "gn:admin1_code":"55.0",
    "gn:asciiname":"Bilmece",
    "gn:country_code":"TR",
    "gn:dem":714,
    "gn:feature_class":"P",
    "gn:feature_code":"PPL",
    "gn:name":"Bilmece",
    "gn:population":0,
    "gn:timezone":"Europe/Istanbul",
    "iso:country":"TR",
    "wof:name":"Bilmece",
    "wof:placetype":"locality"
},
  "geometry": {"coordinates":[36.15,41.15],"type":"Point"}
}