{
  "type": "Feature",
  "properties": {
    "gn:admin1_code":"81.0",
    "gn:asciiname":"Ormancik",
    "gn:country_code":"TR",
    "gn:dem":1157,
    "gn:feature_class":"P",
    "gn:feature_code":"PPL",
    "gn:name":"Ormanc\u0131k",
    "gn:population":0,
    "gn:timezone":"Europe/Istanbul",
    "iso:country":"TR",
    "wof:name":"Ormancik",
    "wof:placetype":"locality"
},
  "geometry": {"coordinates":[35.68866,37.87064],"type":"Point"}
}