{
  "type": "Feature",
  "properties": {
    "gn:admin1_code":"87",
    "gn:asciiname":"Ahatlar",
    "gn:country_code":"TR",
    "gn:dem":237,
    "gn:feature_class":"P",
    "gn:feature_code":"PPL",
    "gn:name":"Ahatlar",
    "gn:population":0,
    "gn:timezone":"Europe/Istanbul",
    "iso:country":"TR",
    "wof:name":"Ahatlar",
    "wof:placetype":"locality"
},
  "geometry": {"coordinates":[32.43843,41.5266],"type":"Point"}
}