{
  "type": "Feature",
  "properties": {
    "gn:admin1_code":"33",
    "gn:asciiname":"Celtek",
    "gn:country_code":"TR",
    "gn:dem":1134,
    "gn:feature_class":"P",
    "gn:feature_code":"PPL",
    "gn:name":"\u00c7eltek",
    "gn:population":0,
    "gn:timezone":"Europe/Istanbul",
    "iso:country":"TR",
    "name:und_x_variant":[
        "\u00c7eltik",
        "\u00c7eltek"
    ],
    "wof:name":"Celtek",
    "wof:placetype":"locality"
},
  "geometry": {"coordinates":[31.31888,38.01362],"type":"Point"}
}