{
  "type": "Feature",
  "properties": {
    "gn:admin1_code":"02",
    "gn:asciiname":"Kirachayma",
    "gn:country_code":"TR",
    "gn:dem":924,
    "gn:feature_class":"P",
    "gn:feature_code":"PPL",
    "gn:name":"K\u0131ra\u00e7hayma",
    "gn:population":0,
    "gn:timezone":"Europe/Istanbul",
    "iso:country":"TR",
    "name:und_x_variant":[
        "K\u0131ra\u00e7hayma",
        "K\u00f6rtanl\u0131"
    ],
    "wof:name":"Kirachayma",
    "wof:placetype":"locality"
},
  "geometry": {"coordinates":[37.63333,37.58333],"type":"Point"}
}