{
  "type": "Feature",
  "properties": {
    "gn:admin1_code":"68",
    "gn:asciiname":"Kadiobasi",
    "gn:country_code":"TR",
    "gn:dem":1197,
    "gn:feature_class":"P",
    "gn:feature_code":"PPL",
    "gn:name":"Kad\u0131obas\u0131",
    "gn:population":0,
    "gn:timezone":"Europe/Istanbul",
    "iso:country":"TR",
    "name:tur_x_preferred":[
        "Kad\u0131obas\u0131"
    ],
    "name:und_x_variant":[
        "Kad\u0131oba\u015f\u0131",
        "Kad\u0131oba"
    ],
    "wof:name":"Kadiobasi",
    "wof:placetype":"locality"
},
  "geometry": {"coordinates":[33.71667,38.91667],"type":"Point"}
}