{
  "type": "Feature",
  "properties": {
    "gn:admin1_code":"25",
    "gn:asciiname":"Alagoz",
    "gn:country_code":"TR",
    "gn:dem":1797,
    "gn:feature_class":"P",
    "gn:feature_code":"PPL",
    "gn:name":"Alag\u00f6z",
    "gn:population":0,
    "gn:timezone":"Europe/Istanbul",
    "iso:country":"TR",
    "name:tur_x_preferred":[
        "Alag\u00f6z"
    ],
    "wof:name":"Alagoz",
    "wof:placetype":"locality"
},
  "geometry": {"coordinates":[42.19139000000001,39.91358],"type":"Point"}
}