{
  "type": "Feature",
  "properties": {
    "gn:admin1_code":"38",
    "gn:asciiname":"Hasankoy",
    "gn:country_code":"TR",
    "gn:dem":1091,
    "gn:feature_class":"P",
    "gn:feature_code":"PPL",
    "gn:name":"Hasank\u00f6y",
    "gn:population":0,
    "gn:timezone":"Europe/Istanbul",
    "iso:country":"TR",
    "name:tur_x_preferred":[
        "Hasank\u00f6y"
    ],
    "wof:name":"Hasankoy",
    "wof:placetype":"locality"
},
  "geometry": {"coordinates":[35.15,38.38333],"type":"Point"}
}