{
  "type": "Feature",
  "properties": {
    "gn:admin1_code":"15",
    "gn:asciiname":"Dutalani",
    "gn:country_code":"TR",
    "gn:dem":880,
    "gn:feature_class":"P",
    "gn:feature_code":"PPL",
    "gn:name":"Dutalan\u0131",
    "gn:population":0,
    "gn:timezone":"Europe/Istanbul",
    "iso:country":"TR",
    "name:tur_x_preferred":[
        "Dutalan\u0131"
    ],
    "name:tur_x_variant":[
        "Dutalan"
    ],
    "wof:name":"Dutalani",
    "wof:placetype":"locality"
},
  "geometry": {"coordinates":[30.72806,37.41944],"type":"Point"}
}