{
  "type": "Feature",
  "properties": {
    "gn:admin1_code":"20",
    "gn:asciiname":"Yenikonak",
    "gn:country_code":"TR",
    "gn:dem":708,
    "gn:feature_class":"P",
    "gn:feature_code":"PPL",
    "gn:name":"Yenikonak",
    "gn:population":0,
    "gn:timezone":"Europe/Istanbul",
    "iso:country":"TR",
    "wof:name":"Yenikonak",
    "wof:placetype":"locality"
},
  "geometry": {"coordinates":[29.11,38.21556],"type":"Point"}
}