{
  "type": "Feature",
  "properties": {
    "gn:admin1_code":"82.0",
    "gn:asciiname":"Asagidere",
    "gn:country_code":"TR",
    "gn:dem":1022,
    "gn:feature_class":"P",
    "gn:feature_code":"PPL",
    "gn:name":"A\u015fa\u011f\u0131dere",
    "gn:population":0,
    "gn:timezone":"Europe/Istanbul",
    "iso:country":"TR",
    "name:und_x_variant":[
        "A\u015fa\u011f\u0131dere"
    ],
    "wof:name":"Asagidere",
    "wof:placetype":"locality"
},
  "geometry": {"coordinates":[33.63333,40.95],"type":"Point"}
}