{
  "type": "Feature",
  "properties": {
    "gn:country":"TR",
    "gn:fcode":"PPL",
    "gn:pop":0,
    "iso:country":"TR",
    "name:ara_x_preferred":[
        "\u062f\u0631\u064a\u0643\u0627"
    ],
    "name:bel_x_preferred":[
        "\u0413\u043e\u0440\u0430\u0434 \u0414\u0430\u0440\u044b\u0434\u0436\u0430"
    ],
    "name:cat_x_preferred":[
        "Dar\u0131ca"
    ],
    "name:chi_x_preferred":[
        "\u9054\u52d2\u8cc8"
    ],
    "name:dut_x_preferred":[
        "Dar\u0131ca"
    ],
    "name:eng_x_preferred":[
        "Dar\u0131ca"
    ],
    "name:fre_x_preferred":[
        "Dar\u0131ca"
    ],
    "name:ger_x_preferred":[
        "Dar\u0131ca"
    ],
    "name:gre_x_preferred":[
        "\u0391\u03c1\u03b5\u03c4\u03c3\u03bf\u03cd"
    ],
    "name:ita_x_preferred":[
        "Dar\u0131ca"
    ],
    "name:lrc_x_preferred":[
        "\u062f\u0627\u0631\u06cc\u062c\u0627"
    ],
    "name:min_x_preferred":[
        "Dar\u0131ca"
    ],
    "name:mrj_x_preferred":[
        "\u0414\u0430\u0440\u044b\u0434\u0436\u0430"
    ],
    "name:nan_x_preferred":[
        "Dar\u0131ca"
    ],
    "name:nno_x_preferred":[
        "Dar\u0131ca"
    ],
    "name:nob_x_preferred":[
        "Dar\u0131ca"
    ],
    "name:per_x_preferred":[
        "\u062f\u0627\u0631\u06cc\u062c\u0627"
    ],
    "name:pnb_x_preferred":[
        "\u0636\u0644\u0639 \u062f\u0627\u0631\u06cc\u0686\u0627"
    ],
    "name:pol_x_preferred":[
        "Dar\u0131ca"
    ],
    "name:rum_x_preferred":[
        "Dar\u0131ca"
    ],
    "name:rus_x_preferred":[
        "\u0414\u0430\u0440\u044b\u0434\u0436\u0430"
    ],
    "name:srp_x_preferred":[
        "\u0414\u0430\u0440\u0438\u045f\u0430"
    ],
    "name:tur_x_preferred":[
        "Dar\u0131ca"
    ],
    "name:unk_x_variant":[
        "Deridja"
    ],
    "name:urd_x_preferred":[
        "\u062f\u0627\u0631\u06cc\u062c\u0627"
    ],
    "name:vie_x_preferred":[
        "Dar\u0131ca"
    ],
    "qs:name":"Dar\u0131ca",
    "qs:name_adm0":"Turkey",
    "qs:name_adm1":"Kocaeli",
    "qs:photos":224,
    "qs:photos_1k":45,
    "qs:photos_9k":1,
    "qs:photos_9r":4,
    "qs:photos_all":224,
    "qs:photos_sr":4,
    "qs:placetype":"Town",
    "qs:pop_sr":"0",
    "wd:wordcount":476,
    "wof:name":"Dar\u0131ca",
    "wof:placetype":"locality",
    "wof:population":0
},
  "geometry": {"coordinates":[29.39454,40.77973],"type":"Point"}
}