{
  "type": "Feature",
  "properties": {
    "gn:admin1_code":"52.0",
    "gn:asciiname":"Ambarcili",
    "gn:country_code":"TR",
    "gn:dem":218,
    "gn:feature_class":"P",
    "gn:feature_code":"PPL",
    "gn:name":"Ambarc\u0131l\u0131",
    "gn:population":0,
    "gn:timezone":"Europe/Istanbul",
    "iso:country":"TR",
    "name:und_x_variant":[
        "Anbarc\u0131l\u0131",
        "Ambarc\u0131l\u0131"
    ],
    "wof:name":"Ambarcili",
    "wof:placetype":"locality"
},
  "geometry": {"coordinates":[38.08609000000001,40.92561],"type":"Point"}
}