{
  "type": "Feature",
  "properties": {
    "gn:admin1_code":"71",
    "gn:asciiname":"Erdogan",
    "gn:country_code":"TR",
    "gn:dem":1169,
    "gn:feature_class":"P",
    "gn:feature_code":"PPL",
    "gn:name":"Erdo\u011fan",
    "gn:population":0,
    "gn:timezone":"Europe/Istanbul",
    "iso:country":"TR",
    "wof:name":"Erdogan",
    "wof:placetype":"locality"
},
  "geometry": {"coordinates":[32.12106,37.26093],"type":"Point"}
}