{
  "type": "Feature",
  "properties": {
    "gn:admin1_code":"45",
    "gn:asciiname":"Karakoy",
    "gn:country_code":"TR",
    "gn:dem":63,
    "gn:feature_class":"P",
    "gn:feature_code":"PPL",
    "gn:name":"Karak\u00f6y",
    "gn:population":0,
    "gn:timezone":"Europe/Istanbul",
    "iso:country":"TR",
    "wof:name":"Karakoy",
    "wof:placetype":"locality"
},
  "geometry": {"coordinates":[27.87944,38.54],"type":"Point"}
}