{
  "type": "Feature",
  "properties": {
    "gn:admin1_code":"81",
    "gn:asciiname":"Ibrisim",
    "gn:country_code":"TR",
    "gn:dem":894,
    "gn:feature_class":"P",
    "gn:feature_code":"PPL",
    "gn:name":"\u0130bri\u015fim",
    "gn:population":0,
    "gn:timezone":"Europe/Istanbul",
    "iso:country":"TR",
    "wof:name":"Ibrisim",
    "wof:placetype":"locality"
},
  "geometry": {"coordinates":[35.33333,37.52528],"type":"Point"}
}