{
  "type": "Feature",
  "properties": {
    "gn:admin1_code":"63.0",
    "gn:asciiname":"Karaca",
    "gn:country_code":"TR",
    "gn:dem":369,
    "gn:feature_class":"P",
    "gn:feature_code":"PPL",
    "gn:name":"Karaca",
    "gn:population":0,
    "gn:timezone":"Europe/Istanbul",
    "iso:country":"TR",
    "name:aze_x_preferred":[
        "Qaraca"
    ],
    "name:ceb_x_preferred":[
        "Karaca"
    ],
    "name:deu_x_preferred":[
        "Karaca"
    ],
    "name:fra_x_preferred":[
        "Karaca"
    ],
    "name:swe_x_preferred":[
        "Karaca"
    ],
    "name:tur_x_preferred":[
        "Karaca"
    ],
    "name:tur_x_variant":[
        "Kayaca"
    ],
    "wof:name":"Karaca",
    "wof:placetype":"locality"
},
  "geometry": {"coordinates":[39.09884,36.7652],"type":"Point"}
}