{
  "type": "Feature",
  "properties": {
    "gn:admin1_code":"49",
    "gn:asciiname":"Koguktas",
    "gn:country_code":"TR",
    "gn:dem":1362,
    "gn:feature_class":"P",
    "gn:feature_code":"PPL",
    "gn:name":"Ko\u011fukta\u015f",
    "gn:population":0,
    "gn:timezone":"Europe/Istanbul",
    "iso:country":"TR",
    "name:tur_x_preferred":[
        "Ko\u011fukta\u015f"
    ],
    "name:und_x_variant":[
        "Zirkit"
    ],
    "wof:name":"Koguktas",
    "wof:placetype":"locality"
},
  "geometry": {"coordinates":[41.87452,38.59995],"type":"Point"}
}