{
  "type": "Feature",
  "properties": {
    "gn:admin1_code":"28.0",
    "gn:asciiname":"Aksu",
    "gn:country_code":"TR",
    "gn:dem":1779,
    "gn:feature_class":"P",
    "gn:feature_code":"PPL",
    "gn:name":"Aksu",
    "gn:population":0,
    "gn:timezone":"Europe/Istanbul",
    "iso:country":"TR",
    "name:eng_x_preferred":[
        "Aksu"
    ],
    "name:rus_x_preferred":[
        "\u0410\u043a\u0441\u0443\u043a\u0435\u0439"
    ],
    "name:und_x_variant":[
        "Aksuk\u00f6y",
        "Aksu"
    ],
    "wof:name":"Aksu",
    "wof:placetype":"locality"
},
  "geometry": {"coordinates":[38.21604,40.56146],"type":"Point"}
}