{
  "type": "Feature",
  "properties": {
    "gn:admin1_code":"66",
    "gn:asciiname":"Yangi",
    "gn:country_code":"TR",
    "gn:dem":885,
    "gn:feature_class":"P",
    "gn:feature_code":"PPL",
    "gn:name":"Yang\u0131",
    "gn:population":0,
    "gn:timezone":"Europe/Istanbul",
    "iso:country":"TR",
    "name:und_x_variant":[
        "Yank\u0131",
        "Yang\u0131"
    ],
    "wof:name":"Yangi",
    "wof:placetype":"locality"
},
  "geometry": {"coordinates":[35.72226,39.93284],"type":"Point"}
}