{
  "type": "Feature",
  "properties": {
    "gn:admin1_code":"83.0",
    "gn:asciiname":"Akcaburc",
    "gn:country_code":"TR",
    "gn:dem":814,
    "gn:feature_class":"P",
    "gn:feature_code":"PPL",
    "gn:name":"Ak\u00e7abur\u00e7",
    "gn:population":0,
    "gn:timezone":"Europe/Istanbul",
    "iso:country":"TR",
    "name:tur_x_preferred":[
        "Ak\u00e7abur\u00e7"
    ],
    "wof:name":"Akcaburc",
    "wof:placetype":"locality"
},
  "geometry": {"coordinates":[37.32072,37.2495],"type":"Point"}
}