{
  "type": "Feature",
  "properties": {
    "gn:admin1_code":"74.0",
    "gn:asciiname":"Caykoy",
    "gn:country_code":"TR",
    "gn:dem":783,
    "gn:feature_class":"P",
    "gn:feature_code":"PPL",
    "gn:name":"\u00c7ayk\u00f6y",
    "gn:population":0,
    "gn:timezone":"Europe/Istanbul",
    "iso:country":"TR",
    "wof:name":"Caykoy",
    "wof:placetype":"locality"
},
  "geometry": {"coordinates":[41.73444,37.97167],"type":"Point"}
}