{
  "type": "Feature",
  "properties": {
    "gn:admin1_code":"54",
    "gn:asciiname":"Ikramiye",
    "gn:country_code":"TR",
    "gn:dem":99,
    "gn:feature_class":"P",
    "gn:feature_code":"PPL",
    "gn:name":"\u0130kramiye",
    "gn:population":0,
    "gn:timezone":"Europe/Istanbul",
    "iso:country":"TR",
    "name:tur_x_preferred":[
        "\u0130kramiye"
    ],
    "wof:name":"Ikramiye",
    "wof:placetype":"locality"
},
  "geometry": {"coordinates":[30.73681,40.73005],"type":"Point"}
}