{
  "type": "Feature",
  "properties": {
    "gn:admin1_code":"37.0",
    "gn:asciiname":"Yenikoy",
    "gn:country_code":"TR",
    "gn:dem":1360,
    "gn:feature_class":"P",
    "gn:feature_code":"PPL",
    "gn:name":"Yenik\u00f6y",
    "gn:population":0,
    "gn:timezone":"Europe/Istanbul",
    "iso:country":"TR",
    "wof:name":"Yenikoy",
    "wof:placetype":"locality"
},
  "geometry": {"coordinates":[33.27629,41.40737],"type":"Point"}
}