{
  "type": "Feature",
  "properties": {
    "gn:admin1_code":"72",
    "gn:asciiname":"Tosunlu",
    "gn:country_code":"TR",
    "gn:dem":446,
    "gn:feature_class":"P",
    "gn:feature_code":"PPL",
    "gn:name":"Tosunlu",
    "gn:population":0,
    "gn:timezone":"Europe/Istanbul",
    "iso:country":"TR",
    "name:tur_x_preferred":[
        "Tosunlu"
    ],
    "wof:name":"Tosunlu",
    "wof:placetype":"locality"
},
  "geometry": {"coordinates":[40.23873,37.02055],"type":"Point"}
}