{
  "type": "Feature",
  "properties": {
    "gn:admin1_code":"68.0",
    "gn:asciiname":"Fasil",
    "gn:country_code":"TR",
    "gn:dem":562,
    "gn:feature_class":"P",
    "gn:feature_code":"PPL",
    "gn:name":"Fas\u0131l",
    "gn:population":0,
    "gn:timezone":"Europe/Istanbul",
    "iso:country":"TR",
    "name:und_x_variant":[
        "Fas\u0131l \u00c7iftli\u011fi",
        "Fas\u0131l\u0131\u00e7iftli\u011fi K\u00f6y\u00fc",
        "Fas\u0131l"
    ],
    "wof:name":"Fasil",
    "wof:placetype":"locality"
},
  "geometry": {"coordinates":[31.85647,40.10552],"type":"Point"}
}