{
  "type": "Feature",
  "properties": {
    "gn:admin1_code":"68",
    "gn:asciiname":"Inler",
    "gn:cc2":"TR",
    "gn:country_code":"TR",
    "gn:dem":830,
    "gn:feature_class":"P",
    "gn:feature_code":"PPL",
    "gn:name":"\u0130nler",
    "gn:population":0,
    "gn:timezone":"Europe/Istanbul",
    "iso:country":"TR",
    "name:und_x_variant":[
        "\u0130nlerkatranc\u0131",
        "\u0130nler"
    ],
    "wof:name":"Inler",
    "wof:placetype":"locality"
},
  "geometry": {"coordinates":[32.255,39.26056],"type":"Point"}
}