{
  "type": "Feature",
  "properties": {
    "gn:admin1_code":"07",
    "gn:asciiname":"Kazanpinar",
    "gn:country_code":"TR",
    "gn:dem":1102,
    "gn:feature_class":"P",
    "gn:feature_code":"PPL",
    "gn:name":"Kazanp\u0131nar",
    "gn:population":0,
    "gn:timezone":"Europe/Istanbul",
    "iso:country":"TR",
    "wof:name":"Kazanpinar",
    "wof:placetype":"locality"
},
  "geometry": {"coordinates":[29.63333,36.45],"type":"Point"}
}