{
  "type": "Feature",
  "properties": {
    "gn:admin1_code":"64",
    "gn:asciiname":"Keklikli",
    "gn:country_code":"TR",
    "gn:dem":723,
    "gn:feature_class":"P",
    "gn:feature_code":"PPL",
    "gn:name":"Keklikli",
    "gn:population":0,
    "gn:timezone":"Europe/Istanbul",
    "iso:country":"TR",
    "name:tur_x_preferred":[
        "Keklikli"
    ],
    "name:tur_x_variant":[
        "Kelikli"
    ],
    "wof:name":"Keklikli",
    "wof:placetype":"locality"
},
  "geometry": {"coordinates":[29.03566,38.24858],"type":"Point"}
}