{
  "type": "Feature",
  "properties": {
    "gn:admin1_code":"81",
    "gn:asciiname":"Aydin",
    "gn:country_code":"TR",
    "gn:dem":1,
    "gn:feature_class":"P",
    "gn:feature_code":"PPL",
    "gn:name":"Ayd\u0131n",
    "gn:population":0,
    "gn:timezone":"Europe/Istanbul",
    "iso:country":"TR",
    "name:und_x_variant":[
        "Ayd\u0131n",
        "Ayd\u0131nl\u0131lar"
    ],
    "wof:name":"Aydin",
    "wof:placetype":"locality"
},
  "geometry": {"coordinates":[34.99168,36.73726],"type":"Point"}
}