{
  "type": "Feature",
  "properties": {
    "gn:admin1_code":"62",
    "gn:asciiname":"Sokucek",
    "gn:country_code":"TR",
    "gn:dem":1013,
    "gn:feature_class":"P",
    "gn:feature_code":"PPL",
    "gn:name":"S\u00f6k\u00fccek",
    "gn:population":0,
    "gn:timezone":"Europe/Istanbul",
    "iso:country":"TR",
    "name:und_x_variant":[
        "S\u00f6k\u00fccek",
        "\u0130snis"
    ],
    "wof:name":"Sokucek",
    "wof:placetype":"locality"
},
  "geometry": {"coordinates":[39.85595,38.91938],"type":"Point"}
}