{
  "type": "Feature",
  "properties": {
    "gn:admin1_code":"24",
    "gn:asciiname":"Bahik",
    "gn:country_code":"TR",
    "gn:dem":1777,
    "gn:feature_class":"P",
    "gn:feature_code":"PPL",
    "gn:name":"Bahik",
    "gn:population":0,
    "gn:timezone":"Europe/Istanbul",
    "iso:country":"TR",
    "name:aze_x_preferred":[
        "Bahik"
    ],
    "name:fas_x_preferred":[
        "\u0628\u0647\u06cc\u06a9"
    ],
    "name:msa_x_preferred":[
        "Bahik"
    ],
    "wof:name":"Bahik",
    "wof:placetype":"locality"
},
  "geometry": {"coordinates":[39.35,39.85],"type":"Point"}
}