{
  "type": "Feature",
  "properties": {
    "gn:admin1_code":"79",
    "gn:asciiname":"Asagiseyh",
    "gn:country_code":"TR",
    "gn:dem":951,
    "gn:feature_class":"P",
    "gn:feature_code":"PPL",
    "gn:name":"A\u015fa\u011f\u0131\u015feyh",
    "gn:population":0,
    "gn:timezone":"Europe/Istanbul",
    "iso:country":"TR",
    "name:und_x_variant":[
        "A\u015fa\u011f\u0131\u015f\u0131h",
        "A\u015fa\u011f\u0131\u015feyh"
    ],
    "wof:name":"Asagiseyh",
    "wof:placetype":"locality"
},
  "geometry": {"coordinates":[33.61248,39.4936],"type":"Point"}
}