{
  "type": "Feature",
  "properties": {
    "gn:admin1_code":"60.0",
    "gn:asciiname":"Cilehane",
    "gn:country_code":"TR",
    "gn:dem":887,
    "gn:feature_class":"P",
    "gn:feature_code":"PPL",
    "gn:name":"\u00c7ilehane",
    "gn:population":0,
    "gn:timezone":"Europe/Istanbul",
    "iso:country":"TR",
    "name:und_x_variant":[
        "\u00c7ilhane",
        "\u00c7ilehane"
    ],
    "wof:name":"Cilehane",
    "wof:placetype":"locality"
},
  "geometry": {"coordinates":[37.19825,40.32543],"type":"Point"}
}