{
  "type": "Feature",
  "properties": {
    "gn:admin1_code":"24.0",
    "gn:asciiname":"Akdogu",
    "gn:country_code":"TR",
    "gn:dem":1585,
    "gn:feature_class":"P",
    "gn:feature_code":"PPL",
    "gn:name":"Akdo\u011fu",
    "gn:population":0,
    "gn:timezone":"Europe/Istanbul",
    "iso:country":"TR",
    "name:und_x_variant":[
        "Hi\u011fdar",
        "Akdo\u011fu"
    ],
    "wof:name":"Akdogu",
    "wof:placetype":"locality"
},
  "geometry": {"coordinates":[38.77188,39.41284],"type":"Point"}
}