{
  "type": "Feature",
  "properties": {
    "gn:admin1_code":"37.0",
    "gn:asciiname":"Sipahiler",
    "gn:country_code":"TR",
    "gn:dem":1033,
    "gn:feature_class":"P",
    "gn:feature_code":"PPL",
    "gn:name":"Sipahiler",
    "gn:population":0,
    "gn:timezone":"Europe/Istanbul",
    "iso:country":"TR",
    "wof:name":"Sipahiler",
    "wof:placetype":"locality"
},
  "geometry": {"coordinates":[33.58333,41.23333],"type":"Point"}
}