{
  "type": "Feature",
  "properties": {
    "gn:admin1_code":"68.0",
    "gn:asciiname":"Cukuroren",
    "gn:country_code":"TR",
    "gn:dem":1175,
    "gn:feature_class":"P",
    "gn:feature_code":"PPL",
    "gn:name":"\u00c7ukur\u00f6ren",
    "gn:population":0,
    "gn:timezone":"Europe/Istanbul",
    "iso:country":"TR",
    "name:und_x_variant":[
        "\u00c7ukurviran",
        "\u00c7ukur\u00f6ren"
    ],
    "wof:name":"Cukuroren",
    "wof:placetype":"locality"
},
  "geometry": {"coordinates":[32.69911,40.52678],"type":"Point"}
}