{
  "type": "Feature",
  "properties": {
    "iso:country":"TR",
    "name:dan_x_preferred":[
        "Ulo"
    ],
    "name:deu_x_preferred":[
        "Ulu"
    ],
    "name:est_x_preferred":[
        "Ulu"
    ],
    "name:fra_x_preferred":[
        "Ulu"
    ],
    "name:hrv_x_preferred":[
        "Ulu"
    ],
    "name:rus_x_preferred":[
        "\u0423\u043b\u0443"
    ],
    "name:tur_x_preferred":[
        "Ulu"
    ],
    "name:ukr_x_preferred":[
        "\u0423\u043b\u0443"
    ],
    "qs:gn_adm0_cc":"TR",
    "qs:gn_local":750269,
    "qs:local_max":206,
    "qs:local_sum":532,
    "qs:localhoods":7,
    "qs:name":"Ulu",
    "qs:name_adm0":"Turkey",
    "qs:name_adm1":"Bursa",
    "qs:name_adm2":"Osmangazi",
    "qs:name_local":"Bursa",
    "qs:photo_max":25,
    "qs:photo_sum":38,
    "qs:placetype":"Suburb",
    "qs:quad_count":3,
    "qs:woe_adm0":23424969,
    "qs:woe_adm1":2347273,
    "qs:woe_adm2":29390676,
    "qs:woe_lau":0,
    "qs:woe_local":2343843,
    "qs:woe_ver":"7.10.0",
    "qs_pg:name":"Ulu",
    "qs_pg:name_adm0":"Turkey",
    "qs_pg:name_adm1":"Bursa",
    "qs_pg:photos":49,
    "qs_pg:photos_1k":10,
    "qs_pg:photos_9k":1,
    "qs_pg:photos_9r":2,
    "qs_pg:photos_all":49,
    "qs_pg:photos_sr":2,
    "qs_pg:pop_sr":0,
    "qs_pg:qs_pg_placetype":"neighbourhood",
    "qs_pg:qs_pg_placetype_gp":"Suburb",
    "qs_pg:woe_adm0":23424969,
    "woe:adm0_id":23424969,
    "woe:name_adm0":"Turkey",
    "woe:name_adm1":"Bursa",
    "woe:placetype":"Suburb",
    "wof:lang":[
        "unk"
    ],
    "wof:name":"Ulu",
    "wof:placetype":"neighbourhood"
},
  "geometry": {"coordinates":[29.061873,40.196542],"type":"Point"}
}