{
  "type": "Feature",
  "properties": {
    "gn:admin1_code":"17.0",
    "gn:asciiname":"Kirca",
    "gn:country_code":"TR",
    "gn:dem":508,
    "gn:feature_class":"P",
    "gn:feature_code":"PPL",
    "gn:name":"K\u0131rca",
    "gn:population":0,
    "gn:timezone":"Europe/Istanbul",
    "iso:country":"TR",
    "name:tur_x_preferred":[
        "K\u0131rcalar"
    ],
    "name:und_x_variant":[
        "K\u0131rca"
    ],
    "wof:name":"Kirca",
    "wof:placetype":"locality"
},
  "geometry": {"coordinates":[26.55419,39.62965],"type":"Point"}
}