{
  "type": "Feature",
  "properties": {
    "gn:admin1_code":"43.0",
    "gn:asciiname":"Akkaya",
    "gn:country_code":"TR",
    "gn:dem":1046,
    "gn:feature_class":"P",
    "gn:feature_code":"PPL",
    "gn:name":"Akkaya",
    "gn:population":0,
    "gn:timezone":"Europe/Istanbul",
    "iso:country":"TR",
    "wof:name":"Akkaya",
    "wof:placetype":"locality"
},
  "geometry": {"coordinates":[29.41456,39.09512],"type":"Point"}
}