{
  "type": "Feature",
  "properties": {
    "gn:admin1_code":"84.0",
    "gn:asciiname":"Tezekci",
    "gn:country_code":"TR",
    "gn:dem":1150,
    "gn:feature_class":"P",
    "gn:feature_code":"PPL",
    "gn:name":"Tezek\u00e7i",
    "gn:population":0,
    "gn:timezone":"Europe/Istanbul",
    "iso:country":"TR",
    "name:eng_x_preferred":[
        "Tezek\u00e7i"
    ],
    "name:rus_x_preferred":[
        "\u0422\u0435\u0437\u0435\u043a\u0447\u0438"
    ],
    "name:und_x_variant":[
        "Tezek\u00e7i"
    ],
    "wof:name":"Tezekci",
    "wof:placetype":"locality"
},
  "geometry": {"coordinates":[43.41409,40.12841],"type":"Point"}
}