{
  "type": "Feature",
  "properties": {
    "gn:admin1_code":"43",
    "gn:asciiname":"Kutlubeyler",
    "gn:country_code":"TR",
    "gn:dem":1125,
    "gn:feature_class":"P",
    "gn:feature_code":"PPL",
    "gn:name":"Kutlubeyler",
    "gn:population":0,
    "gn:timezone":"Europe/Istanbul",
    "iso:country":"TR",
    "name:tur_x_preferred":[
        "Kutlubeyler"
    ],
    "wof:name":"Kutlubeyler",
    "wof:placetype":"locality"
},
  "geometry": {"coordinates":[29.20855,39.18714],"type":"Point"}
}