{
  "type": "Feature",
  "properties": {
    "gn:admin1_code":"63",
    "gn:asciiname":"Olcektepe",
    "gn:country_code":"TR",
    "gn:dem":535,
    "gn:feature_class":"P",
    "gn:feature_code":"PPL",
    "gn:name":"\u00d6l\u00e7ektepe",
    "gn:population":0,
    "gn:timezone":"Europe/Istanbul",
    "iso:country":"TR",
    "name:tur_x_preferred":[
        "Ocektepe"
    ],
    "name:und_x_variant":[
        "\u00d6l\u00e7ektepe",
        "Himi"
    ],
    "wof:name":"Olcektepe",
    "wof:placetype":"locality"
},
  "geometry": {"coordinates":[38.33919,37.02492],"type":"Point"}
}