{
  "type": "Feature",
  "properties": {
    "gn:admin1_code":"61.0",
    "gn:asciiname":"Bereketli",
    "gn:country_code":"TR",
    "gn:dem":306,
    "gn:feature_class":"P",
    "gn:feature_code":"PPL",
    "gn:name":"Bereketli",
    "gn:population":0,
    "gn:timezone":"Europe/Istanbul",
    "iso:country":"TR",
    "name:und_x_variant":[
        "Mahara",
        "Mahura",
        "Bereketli"
    ],
    "wof:name":"Bereketli",
    "wof:placetype":"locality"
},
  "geometry": {"coordinates":[40.05773,40.86646],"type":"Point"}
}