{
  "type": "Feature",
  "properties": {
    "gn:admin1_code":"07",
    "gn:asciiname":"Bozdogan",
    "gn:country_code":"TR",
    "gn:dem":723,
    "gn:feature_class":"P",
    "gn:feature_code":"PPL",
    "gn:name":"Bozdo\u011fan",
    "gn:population":0,
    "gn:timezone":"Europe/Istanbul",
    "iso:country":"TR",
    "name:und_x_variant":[
        "Bozdo\u011fan",
        "Sazak"
    ],
    "wof:name":"Bozdogan",
    "wof:placetype":"locality"
},
  "geometry": {"coordinates":[30.93416,37.2747],"type":"Point"}
}