{
  "type": "Feature",
  "properties": {
    "gn:admin1_code":"91.0",
    "gn:asciiname":"Alimulayim",
    "gn:country_code":"TR",
    "gn:dem":277,
    "gn:feature_class":"P",
    "gn:feature_code":"PPL",
    "gn:name":"Alim\u00fclayim",
    "gn:population":0,
    "gn:timezone":"Europe/Istanbul",
    "iso:country":"TR",
    "wof:name":"Alimulayim",
    "wof:placetype":"locality"
},
  "geometry": {"coordinates":[36.38675,37.27705],"type":"Point"}
}