{
  "type": "Feature",
  "properties": {
    "gn:admin1_code":"63.0",
    "gn:asciiname":"Biromer",
    "gn:cc2":"TR",
    "gn:country_code":"TR",
    "gn:dem":546,
    "gn:feature_class":"P",
    "gn:feature_code":"PPL",
    "gn:name":"Bir\u00f6mer",
    "gn:population":0,
    "gn:timezone":"Europe/Istanbul",
    "iso:country":"TR",
    "name:rus_x_preferred":[
        "Bir\u00ebmer"
    ],
    "name:und_x_variant":[
        "Bir\u00f6mer"
    ],
    "wof:name":"Biromer",
    "wof:placetype":"locality"
},
  "geometry": {"coordinates":[38.58028,36.97278],"type":"Point"}
}