{
  "type": "Feature",
  "properties": {
    "gn:admin1_code":"19",
    "gn:asciiname":"Eyerci",
    "gn:country_code":"TR",
    "gn:dem":1198,
    "gn:feature_class":"P",
    "gn:feature_code":"PPL",
    "gn:name":"Eyerci",
    "gn:population":0,
    "gn:timezone":"Europe/Istanbul",
    "iso:country":"TR",
    "name:tur_x_preferred":[
        "Eyerci"
    ],
    "name:tur_x_variant":[
        "E\u011ferci"
    ],
    "wof:name":"Eyerci",
    "wof:placetype":"locality"
},
  "geometry": {"coordinates":[34.97477,40.67772],"type":"Point"}
}