{
  "type": "Feature",
  "properties": {
    "gn:admin1_code":"65.0",
    "gn:asciiname":"Karatag",
    "gn:country_code":"TR",
    "gn:dem":2001,
    "gn:feature_class":"P",
    "gn:feature_code":"PPL",
    "gn:name":"Karata\u011f",
    "gn:population":0,
    "gn:timezone":"Europe/Istanbul",
    "iso:country":"TR",
    "name:tur_x_preferred":[
        "Karata\u011f"
    ],
    "wof:name":"Karatag",
    "wof:placetype":"locality"
},
  "geometry": {"coordinates":[43.64658,38.38306],"type":"Point"}
}