{
  "type": "Feature",
  "properties": {
    "gn:admin1_code":"48",
    "gn:asciiname":"Kabacamersin",
    "gn:country_code":"TR",
    "gn:dem":587,
    "gn:feature_class":"P",
    "gn:feature_code":"PPL",
    "gn:name":"Kabacamersin",
    "gn:population":0,
    "gn:timezone":"Europe/Istanbul",
    "iso:country":"TR",
    "name:tur_x_preferred":[
        "Kabacamersin"
    ],
    "wof:name":"Kabacamersin",
    "wof:placetype":"locality"
},
  "geometry": {"coordinates":[29.03362000000001,37.03809],"type":"Point"}
}