{
  "type": "Feature",
  "properties": {
    "gn:admin1_code":"48",
    "gn:asciiname":"Caltiozu",
    "gn:country_code":"TR",
    "gn:dem":92,
    "gn:feature_class":"P",
    "gn:feature_code":"PPL",
    "gn:name":"\u00c7alt\u0131\u00f6z\u00fc",
    "gn:population":0,
    "gn:timezone":"Europe/Istanbul",
    "iso:country":"TR",
    "name:tur_x_preferred":[
        "\u00c7alt\u0131\u00f6z\u00fc"
    ],
    "wof:name":"Caltiozu",
    "wof:placetype":"locality"
},
  "geometry": {"coordinates":[29.33012,36.55717],"type":"Point"}
}