{
  "type": "Feature",
  "properties": {
    "gn:admin1_code":"58",
    "gn:asciiname":"Bozhuyuk",
    "gn:country_code":"TR",
    "gn:dem":1708,
    "gn:feature_class":"P",
    "gn:feature_code":"PPL",
    "gn:name":"Bozh\u00fcy\u00fck",
    "gn:population":0,
    "gn:timezone":"Europe/Istanbul",
    "iso:country":"TR",
    "name:und_x_variant":[
        "Bozh\u00fcy\u00fck K\u00f6y\u00fc",
        "Bozh\u00fcy\u00fck"
    ],
    "wof:name":"Bozhuyuk",
    "wof:placetype":"locality"
},
  "geometry": {"coordinates":[36.78773,38.56135],"type":"Point"}
}