{
  "type": "Feature",
  "properties": {
    "gn:country":"TR",
    "gn:fcode":"PPL",
    "gn:population":0,
    "iso:country":"TR",
    "name:aze_x_preferred":[
        "Yengic\u0259"
    ],
    "name:bul_x_preferred":[
        "\u0419\u0435\u043d\u0438\u0434\u0436\u0435"
    ],
    "name:ceb_x_preferred":[
        "Yenice"
    ],
    "name:che_x_preferred":[
        "\u0419\u0435\u043d\u0438\u0434\u0436\u0435"
    ],
    "name:deu_x_preferred":[
        "Yenice"
    ],
    "name:eng_x_preferred":[
        "Yenice"
    ],
    "name:fas_x_preferred":[
        "\u06cc\u0646\u06cc\u062c\u0647"
    ],
    "name:fra_x_preferred":[
        "Yenice"
    ],
    "name:nld_x_preferred":[
        "Yenice"
    ],
    "name:rus_x_preferred":[
        "\u0415\u043d\u0438\u0434\u0436\u0435"
    ],
    "name:tur_x_preferred":[
        "Yenice"
    ],
    "name:uzb_x_preferred":[
        "Yenice"
    ],
    "name:vie_x_preferred":[
        "Yenice"
    ],
    "qs:name":"Yenice",
    "qs:name_adm0":"Turkey",
    "qs:name_adm1":"\u00c7anakkale",
    "qs:photos_9r":0,
    "qs:photos_sr":0,
    "qs:placetype":"Town",
    "qs:pop_sr":"0",
    "wd:wordcount":331,
    "wof:name":"Yenice",
    "wof:placetype":"locality",
    "wof:population":0
},
  "geometry": {"coordinates":[27.25484,40.22589],"type":"Point"}
}