{
  "type": "Feature",
  "properties": {
    "gn:country":"TR",
    "gn:fcode":"PPL",
    "gn:pop":0,
    "iso:country":"TR",
    "name:tur_x_preferred":[
        "Yenice"
    ],
    "qs:name":"Yenice",
    "qs:name_adm0":"Turkey",
    "qs:name_adm1":"\u00c7anakkale",
    "qs:photos_9r":0,
    "qs:photos_sr":0,
    "qs:placetype":"Town",
    "qs:pop_sr":"0",
    "wd:wordcount":331,
    "wof:name":"Yenice",
    "wof:placetype":"locality",
    "wof:population":0
},
  "geometry": {"coordinates":[27.25484,40.22589],"type":"Point"}
}