{
  "type": "Feature",
  "properties": {
    "gn:admin1_code":"40",
    "gn:asciiname":"Kelismailusagi",
    "gn:country_code":"TR",
    "gn:dem":879,
    "gn:feature_class":"P",
    "gn:feature_code":"PPL",
    "gn:name":"Kelismailu\u015fa\u011f\u0131",
    "gn:population":0,
    "gn:timezone":"Europe/Istanbul",
    "iso:country":"TR",
    "wof:name":"Kelismailusagi",
    "wof:placetype":"locality"
},
  "geometry": {"coordinates":[33.95999,39.64764],"type":"Point"}
}