{
  "type": "Feature",
  "properties": {
    "gn:admin1_code":"08",
    "gn:asciiname":"Yesiloy",
    "gn:country_code":"TR",
    "gn:dem":145,
    "gn:feature_class":"P",
    "gn:feature_code":"PPL",
    "gn:name":"Ye\u015fil\u00f6y",
    "gn:population":0,
    "gn:timezone":"Europe/Istanbul",
    "iso:country":"TR",
    "name:tur_x_preferred":[
        "Ye\u015fil\u00f6y"
    ],
    "wof:name":"Yesiloy",
    "wof:placetype":"locality"
},
  "geometry": {"coordinates":[41.40219,41.36022],"type":"Point"}
}