{
  "type": "Feature",
  "properties": {
    "gn:admin1_code":"52.0",
    "gn:asciiname":"Asagi Kozpinar",
    "gn:country_code":"TR",
    "gn:dem":904,
    "gn:feature_class":"P",
    "gn:feature_code":"PPL",
    "gn:name":"A\u015fa\u011f\u0131 Kozp\u0131nar",
    "gn:population":0,
    "gn:timezone":"Europe/Istanbul",
    "iso:country":"TR",
    "name:tur_x_preferred":[
        "A\u015fa\u011f\u0131 Kozp\u0131nar"
    ],
    "name:und_x_variant":[
        "A\u015fa\u011f\u0131 Kazp\u0131nar",
        "Sar\u0131al\u0131\u00e7"
    ],
    "wof:name":"Asagi Kozpinar",
    "wof:placetype":"locality"
},
  "geometry": {"coordinates":[37.31612,40.7809],"type":"Point"}
}