{
  "type": "Feature",
  "properties": {
    "gn:admin1_code":"68.0",
    "gn:asciiname":"Esmedere",
    "gn:country_code":"TR",
    "gn:dem":898,
    "gn:feature_class":"P",
    "gn:feature_code":"PPL",
    "gn:name":"E\u015fmedere",
    "gn:population":0,
    "gn:timezone":"Europe/Istanbul",
    "iso:country":"TR",
    "name:und_x_variant":[
        "E\u015fmedere K\u00f6y\u00fc",
        "E\u015fmedere"
    ],
    "wof:name":"Esmedere",
    "wof:placetype":"locality"
},
  "geometry": {"coordinates":[33.26434,40.30567],"type":"Point"}
}