{
  "type": "Feature",
  "properties": {
    "gn:admin1_code":"61.0",
    "gn:asciiname":"Serpilkoy",
    "gn:country_code":"TR",
    "gn:dem":153,
    "gn:feature_class":"P",
    "gn:feature_code":"PPL",
    "gn:name":"Serpilk\u00f6y",
    "gn:population":0,
    "gn:timezone":"Europe/Istanbul",
    "iso:country":"TR",
    "wof:name":"Serpilkoy",
    "wof:placetype":"locality"
},
  "geometry": {"coordinates":[39.42139,41.05247],"type":"Point"}
}