{
  "type": "Feature",
  "properties": {
    "gn:admin1_code":"55.0",
    "gn:asciiname":"Koyyeri",
    "gn:cc2":"TR",
    "gn:country_code":"TR",
    "gn:dem":102,
    "gn:feature_class":"P",
    "gn:feature_code":"PPL",
    "gn:name":"K\u00f6yyeri",
    "gn:population":0,
    "gn:timezone":"Europe/Istanbul",
    "iso:country":"TR",
    "name:und_x_variant":[
        "Derek\u00f6y",
        "K\u00f6yyeri"
    ],
    "wof:name":"Koyyeri",
    "wof:placetype":"locality"
},
  "geometry": {"coordinates":[36.09778,41.45417],"type":"Point"}
}