{
  "type": "Feature",
  "properties": {
    "gn:admin1_code":"90.0",
    "gn:asciiname":"Acar",
    "gn:cc2":"TR",
    "gn:country_code":"TR",
    "gn:dem":746,
    "gn:feature_class":"P",
    "gn:feature_code":"PPL",
    "gn:name":"Acar",
    "gn:population":0,
    "gn:timezone":"Europe/Istanbul",
    "iso:country":"TR",
    "name:und_x_variant":[
        "Acark\u00f6y",
        "Acar"
    ],
    "wof:name":"Acar",
    "wof:placetype":"locality"
},
  "geometry": {"coordinates":[37.19306,36.74417],"type":"Point"}
}