{
  "type": "Feature",
  "properties": {
    "gn:admin1_code":"90.0",
    "gn:asciiname":"Acar",
    "gn:cc2":"TR",
    "gn:country_code":"TR",
    "gn:dem":746,
    "gn:feature_class":"P",
    "gn:feature_code":"PPL",
    "gn:name":"Acar",
    "gn:population":0,
    "gn:timezone":"Europe/Istanbul",
    "iso:country":"TR",
    "name:fra_x_preferred":[
        "Achards"
    ],
    "name:ind_x_preferred":[
        "Acar"
    ],
    "name:jav_x_preferred":[
        "Acar"
    ],
    "name:kor_x_preferred":[
        "\uc544\ucc28\ub974"
    ],
    "name:msa_x_preferred":[
        "Acar"
    ],
    "name:nld_x_preferred":[
        "Atjar"
    ],
    "name:rus_x_preferred":[
        "\u0410\u0447\u0430\u0440"
    ],
    "name:spa_x_preferred":[
        "Acar"
    ],
    "name:sun_x_preferred":[
        "Manisan"
    ],
    "name:tha_x_preferred":[
        "\u0e2d\u0e32\u0e08\u0e32\u0e14"
    ],
    "name:ukr_x_preferred":[
        "\u0410\u0447\u0430\u0440"
    ],
    "name:und_x_variant":[
        "Acark\u00f6y"
    ],
    "wof:name":"Acar",
    "wof:placetype":"locality"
},
  "geometry": {"coordinates":[37.19306,36.74417],"type":"Point"}
}