{
  "type": "Feature",
  "properties": {
    "gn:admin1_code":"19.0",
    "gn:asciiname":"Karadona",
    "gn:country_code":"TR",
    "gn:dem":1106,
    "gn:feature_class":"P",
    "gn:feature_code":"PPL",
    "gn:name":"Karadona",
    "gn:population":0,
    "gn:timezone":"Europe/Istanbul",
    "iso:country":"TR",
    "wof:name":"Karadona",
    "wof:placetype":"locality"
},
  "geometry": {"coordinates":[34.64054,40.30291],"type":"Point"}
}