{
  "type": "Feature",
  "properties": {
    "gn:admin1_code":"66.0",
    "gn:asciiname":"Guroglu",
    "gn:country_code":"TR",
    "gn:dem":1119,
    "gn:feature_class":"P",
    "gn:feature_code":"PPL",
    "gn:name":"G\u00fcro\u011flu",
    "gn:population":0,
    "gn:timezone":"Europe/Istanbul",
    "iso:country":"TR",
    "name:und_x_variant":[
        "K\u00f6ro\u011flu",
        "G\u00fcro\u011flu"
    ],
    "wof:name":"Guroglu",
    "wof:placetype":"locality"
},
  "geometry": {"coordinates":[35.24112,40.18886],"type":"Point"}
}