{
  "type": "Feature",
  "properties": {
    "gn:admin1_code":"45",
    "gn:asciiname":"Kizildam",
    "gn:country_code":"TR",
    "gn:dem":718,
    "gn:feature_class":"P",
    "gn:feature_code":"PPL",
    "gn:name":"K\u0131z\u0131ldam",
    "gn:population":0,
    "gn:timezone":"Europe/Istanbul",
    "iso:country":"TR",
    "name:tur_x_preferred":[
        "K\u0131z\u0131ldam"
    ],
    "wof:name":"Kizildam",
    "wof:placetype":"locality"
},
  "geometry": {"coordinates":[28.36444,38.97132],"type":"Point"}
}