{
  "type": "Feature",
  "properties": {
    "gn:admin1_code":"32",
    "gn:asciiname":"Avkadi",
    "gn:country_code":"TR",
    "gn:dem":1364,
    "gn:feature_class":"P",
    "gn:feature_code":"PPL",
    "gn:name":"Avkad\u0131",
    "gn:population":0,
    "gn:timezone":"Europe/Istanbul",
    "iso:country":"TR",
    "name:tur_x_preferred":[
        "Avkad\u0131"
    ],
    "name:und_x_variant":[
        "Augadi",
        "Avkadi",
        "Avgad\u0131"
    ],
    "wof:name":"Avkadi",
    "wof:placetype":"locality"
},
  "geometry": {"coordinates":[34.10408,36.78126],"type":"Point"}
}