{
  "type": "Feature",
  "properties": {
    "gn:admin1_code":"17.0",
    "gn:asciiname":"Tayfurkoy",
    "gn:country_code":"TR",
    "gn:dem":112,
    "gn:feature_class":"P",
    "gn:feature_code":"PPL",
    "gn:name":"Tayfurk\u00f6y",
    "gn:population":0,
    "gn:timezone":"Europe/Istanbul",
    "iso:country":"TR",
    "name:und_x_variant":[
        "Zaylur",
        "Tayfur",
        "Tayfuk",
        "Tailfur",
        "Tayfurk\u00f6y"
    ],
    "wof:name":"Tayfurkoy",
    "wof:placetype":"locality"
},
  "geometry": {"coordinates":[26.47664,40.39743],"type":"Point"}
}