{
  "type": "Feature",
  "properties": {
    "gn:admin1_code":"70",
    "gn:asciiname":"Ericek",
    "gn:country_code":"TR",
    "gn:dem":2165,
    "gn:feature_class":"P",
    "gn:feature_code":"PPL",
    "gn:name":"Ericek",
    "gn:population":0,
    "gn:timezone":"Europe/Istanbul",
    "iso:country":"TR",
    "wof:name":"Ericek",
    "wof:placetype":"locality"
},
  "geometry": {"coordinates":[44.2418,37.66051],"type":"Point"}
}