{
  "type": "Feature",
  "properties": {
    "gn:admin1_code":"10",
    "gn:asciiname":"Coban",
    "gn:country_code":"TR",
    "gn:dem":829,
    "gn:feature_class":"P",
    "gn:feature_code":"PPL",
    "gn:name":"\u00c7oban",
    "gn:population":0,
    "gn:timezone":"Europe/Istanbul",
    "iso:country":"TR",
    "name:tur_x_preferred":[
        "\u00c7oban"
    ],
    "name:und_x_variant":[
        "\u00c7ohan\u0131ndam\u0131"
    ],
    "wof:name":"Coban",
    "wof:placetype":"locality"
},
  "geometry": {"coordinates":[28.68053,39.1937],"type":"Point"}
}