{
  "type": "Feature",
  "properties": {
    "gn:country":"TR",
    "gn:fcode":"PPLA2",
    "gn:pop":6116,
    "iso:country":"TR",
    "name:ceb_x_preferred":[
        "Yal\u0131h\u00fcy\u00fck \u0130l\u00e7esi"
    ],
    "name:deu_x_preferred":[
        "Yal\u0131h\u00fcy\u00fck"
    ],
    "name:diq_x_preferred":[
        "Yal\u0131h\u00fcy\u00fck"
    ],
    "name:eng_x_preferred":[
        "Yal\u0131h\u00fcy\u00fck"
    ],
    "name:fas_x_preferred":[
        "\u06cc\u0627\u0644\u06cc\u200c\u0647\u06cc\u0648\u0642"
    ],
    "name:fra_x_preferred":[
        "Yal\u0131h\u00f6y\u00fck"
    ],
    "name:ita_x_preferred":[
        "Distretto di Yal\u0131h\u00fcy\u00fck"
    ],
    "name:kur_x_preferred":[
        "Yal\u0131h\u00fcy\u00fck"
    ],
    "name:mrj_x_preferred":[
        "\u042f\u043b\u044b\u0445\u04f1\u0439\u04f1\u043a"
    ],
    "name:msa_x_preferred":[
        "Yal\u0131h\u00fcy\u00fck"
    ],
    "name:nan_x_preferred":[
        "Yal\u0131h\u00fcy\u00fck"
    ],
    "name:nld_x_preferred":[
        "Yal\u0131h\u00fcy\u00fck"
    ],
    "name:nob_x_preferred":[
        "Yal\u0131h\u00fcy\u00fck"
    ],
    "name:swa_x_preferred":[
        "Yal\u0131h\u00fcy\u00fck"
    ],
    "name:tur_x_preferred":[
        "Yal\u0131h\u00fcy\u00fck"
    ],
    "name:urd_x_preferred":[
        "\u06cc\u0644\u06cc\u06c1\u0648\u06cc\u0648\u06a9"
    ],
    "name:vie_x_preferred":[
        "Yal\u0131h\u00fcy\u00fck"
    ],
    "qs:name":"Yal\u0131h\u00fcy\u00fck",
    "qs:photos_9r":0,
    "qs:photos_sr":0,
    "qs:pop_sr":"5",
    "wd:wordcount":157,
    "wof:name":"Yal\u0131h\u00fcy\u00fck",
    "wof:placetype":"locality",
    "wof:population":6116
},
  "geometry": {"coordinates":[32.08548,37.30077],"type":"Point"}
}