{
  "type": "Feature",
  "properties": {
    "gn:admin1_code":"53.0",
    "gn:asciiname":"Denizgoren",
    "gn:country_code":"TR",
    "gn:dem":118,
    "gn:feature_class":"P",
    "gn:feature_code":"PPL",
    "gn:name":"Denizg\u00f6ren",
    "gn:population":0,
    "gn:timezone":"Europe/Istanbul",
    "iso:country":"TR",
    "name:tur_x_preferred":[
        "Denizg\u00f6ren"
    ],
    "wof:name":"Denizgoren",
    "wof:placetype":"locality"
},
  "geometry": {"coordinates":[40.37294,40.97348],"type":"Point"}
}