{
  "type": "Feature",
  "properties": {
    "gn:admin1_code":"71",
    "gn:asciiname":"Catkoyu",
    "gn:country_code":"TR",
    "gn:dem":1327,
    "gn:feature_class":"P",
    "gn:feature_code":"PPL",
    "gn:name":"\u00c7atk\u00f6y\u00fc",
    "gn:population":0,
    "gn:timezone":"Europe/Istanbul",
    "iso:country":"TR",
    "name:und_x_variant":[
        "\u00c7at",
        "\u00c7atk\u00f6y\u00fc"
    ],
    "wof:name":"Catkoyu",
    "wof:placetype":"locality"
},
  "geometry": {"coordinates":[34.32027,37.49709],"type":"Point"}
}