{
  "type": "Feature",
  "properties": {
    "gn:admin1_code":"55.0",
    "gn:asciiname":"Kirazpinar",
    "gn:country_code":"TR",
    "gn:dem":875,
    "gn:feature_class":"P",
    "gn:feature_code":"PPL",
    "gn:name":"K\u0131razp\u0131nar",
    "gn:population":0,
    "gn:timezone":"Europe/Istanbul",
    "iso:country":"TR",
    "wof:name":"Kirazpinar",
    "wof:placetype":"locality"
},
  "geometry": {"coordinates":[35.73754,40.9084],"type":"Point"}
}