{
  "type": "Feature",
  "properties": {
    "gn:admin1_code":"81",
    "gn:asciiname":"Urganlar",
    "gn:country_code":"TR",
    "gn:dem":206,
    "gn:feature_class":"P",
    "gn:feature_code":"PPL",
    "gn:name":"Urganlar",
    "gn:population":0,
    "gn:timezone":"Europe/Istanbul",
    "iso:country":"TR",
    "name:und_x_variant":[
        "K\u0131ll\u0131cami"
    ],
    "wof:name":"Urganlar",
    "wof:placetype":"locality"
},
  "geometry": {"coordinates":[35.03537,37.12149],"type":"Point"}
}