{
  "type": "Feature",
  "properties": {
    "gn:admin1_code":"63",
    "gn:asciiname":"Kargili",
    "gn:country_code":"TR",
    "gn:dem":490,
    "gn:feature_class":"P",
    "gn:feature_code":"PPL",
    "gn:name":"Karg\u0131l\u0131",
    "gn:population":0,
    "gn:timezone":"Europe/Istanbul",
    "iso:country":"TR",
    "name:tur_x_preferred":[
        "Karg\u0131l\u0131"
    ],
    "wof:name":"Kargili",
    "wof:placetype":"locality"
},
  "geometry": {"coordinates":[38.2469,37.38025],"type":"Point"}
}