{
  "type": "Feature",
  "properties": {
    "gn:admin1_code":"37.0",
    "gn:asciiname":"Cevlik",
    "gn:country_code":"TR",
    "gn:dem":508,
    "gn:feature_class":"P",
    "gn:feature_code":"PPL",
    "gn:name":"\u00c7evlik",
    "gn:population":0,
    "gn:timezone":"Europe/Istanbul",
    "iso:country":"TR",
    "name:tur_x_preferred":[
        "\u00c7evlik"
    ],
    "wof:name":"Cevlik",
    "wof:placetype":"locality"
},
  "geometry": {"coordinates":[34.22170999999999,41.03062],"type":"Point"}
}