{
  "type": "Feature",
  "properties": {
    "gn:admin1_code":"58",
    "gn:asciiname":"Demircilik",
    "gn:country_code":"TR",
    "gn:dem":1526,
    "gn:feature_class":"P",
    "gn:feature_code":"PPL",
    "gn:name":"Demircilik",
    "gn:population":0,
    "gn:timezone":"Europe/Istanbul",
    "iso:country":"TR",
    "wof:name":"Demircilik",
    "wof:placetype":"locality"
},
  "geometry": {"coordinates":[36.56373,39.70583],"type":"Point"}
}