{
  "type": "Feature",
  "properties": {
    "gn:admin1_code":"87.0",
    "gn:asciiname":"Hisarkoy",
    "gn:country_code":"TR",
    "gn:dem":559,
    "gn:feature_class":"P",
    "gn:feature_code":"PPL",
    "gn:name":"Hisark\u00f6y",
    "gn:population":0,
    "gn:timezone":"Europe/Istanbul",
    "iso:country":"TR",
    "name:tur_x_preferred":[
        "Hisark\u00f6y"
    ],
    "name:tur_x_variant":[
        "\u00d6ren"
    ],
    "wof:name":"Hisarkoy",
    "wof:placetype":"locality"
},
  "geometry": {"coordinates":[32.52394,41.43534],"type":"Point"}
}