{
  "type": "Feature",
  "properties": {
    "gn:admin1_code":"76.0",
    "gn:asciiname":"Karsikaya",
    "gn:country_code":"TR",
    "gn:dem":649,
    "gn:feature_class":"P",
    "gn:feature_code":"PPL",
    "gn:name":"Kar\u015f\u0131kaya",
    "gn:population":0,
    "gn:timezone":"Europe/Istanbul",
    "iso:country":"TR",
    "name:tur_x_preferred":[
        "Kar\u015f\u0131kaya"
    ],
    "name:und_x_variant":[
        "Kar\u015f\u0131yaka"
    ],
    "wof:name":"Karsikaya",
    "wof:placetype":"locality"
},
  "geometry": {"coordinates":[41.55062,38.14091],"type":"Point"}
}