{
  "type": "Feature",
  "properties": {
    "gn:admin1_code":"58.0",
    "gn:asciiname":"Aydinlar",
    "gn:country_code":"TR",
    "gn:dem":1105,
    "gn:feature_class":"P",
    "gn:feature_code":"PPL",
    "gn:name":"Ayd\u0131nlar",
    "gn:population":0,
    "gn:timezone":"Europe/Istanbul",
    "iso:country":"TR",
    "name:und_x_variant":[
        "Allar K\u00f6y\u00fc",
        "Allar",
        "Ayd\u0131nlar"
    ],
    "wof:name":"Aydinlar",
    "wof:placetype":"locality"
},
  "geometry": {"coordinates":[37.98508,40.20679000000001],"type":"Point"}
}