{
  "type": "Feature",
  "properties": {
    "gn:admin1_code":"38",
    "gn:asciiname":"Hayriye",
    "gn:country_code":"TR",
    "gn:dem":1266,
    "gn:feature_class":"P",
    "gn:feature_code":"PPL",
    "gn:name":"Hayriye",
    "gn:population":0,
    "gn:timezone":"Europe/Istanbul",
    "iso:country":"TR",
    "name:und_x_variant":[
        "Kise",
        "Hayriye"
    ],
    "wof:name":"Hayriye",
    "wof:placetype":"locality"
},
  "geometry": {"coordinates":[35.69977,39.09208],"type":"Point"}
}