{
  "type": "Feature",
  "properties": {
    "gn:admin1_code":"20",
    "gn:asciiname":"Hacibicikler",
    "gn:country_code":"TR",
    "gn:dem":889,
    "gn:feature_class":"P",
    "gn:feature_code":"PPL",
    "gn:name":"Hac\u0131bicikler",
    "gn:population":0,
    "gn:timezone":"Europe/Istanbul",
    "iso:country":"TR",
    "name:tur_x_preferred":[
        "Hac\u0131bicikler"
    ],
    "wof:name":"Hacibicikler",
    "wof:placetype":"locality"
},
  "geometry": {"coordinates":[28.99985,38.18035],"type":"Point"}
}