{
  "type": "Feature",
  "properties": {
    "gn:admin1_code":"66.0",
    "gn:asciiname":"Akocak",
    "gn:country_code":"TR",
    "gn:dem":1357,
    "gn:feature_class":"P",
    "gn:feature_code":"PPL",
    "gn:name":"Akocak",
    "gn:population":0,
    "gn:timezone":"Europe/Istanbul",
    "iso:country":"TR",
    "wof:name":"Akocak",
    "wof:placetype":"locality"
},
  "geometry": {"coordinates":[35.23796,39.96709],"type":"Point"}
}