{
  "type": "Feature",
  "properties": {
    "gn:admin1_code":"19.0",
    "gn:asciiname":"Tanrivermis",
    "gn:country_code":"TR",
    "gn:dem":885,
    "gn:feature_class":"P",
    "gn:feature_code":"PPL",
    "gn:name":"Tanr\u0131vermi\u015f",
    "gn:population":0,
    "gn:timezone":"Europe/Istanbul",
    "iso:country":"TR",
    "wof:name":"Tanrivermis",
    "wof:placetype":"locality"
},
  "geometry": {"coordinates":[35.2637,40.63333],"type":"Point"}
}