{
  "type": "Feature",
  "properties": {
    "gn:admin1_code":"5.0",
    "gn:asciiname":"Kalekoy",
    "gn:country_code":"TR",
    "gn:dem":869,
    "gn:feature_class":"P",
    "gn:feature_code":"PPL",
    "gn:name":"Kalek\u00f6y",
    "gn:population":0,
    "gn:timezone":"Europe/Istanbul",
    "iso:country":"TR",
    "name:und_x_variant":[
        "Kale",
        "Kalek\u00f6y"
    ],
    "wof:name":"Kalekoy",
    "wof:placetype":"locality"
},
  "geometry": {"coordinates":[35.93206,40.60225],"type":"Point"}
}