{
  "type": "Feature",
  "properties": {
    "gn:admin1_code":"64",
    "gn:asciiname":"Pasacik",
    "gn:country_code":"TR",
    "gn:dem":1150,
    "gn:feature_class":"P",
    "gn:feature_code":"PPL",
    "gn:name":"Pa\u015fac\u0131k",
    "gn:population":0,
    "gn:timezone":"Europe/Istanbul",
    "iso:country":"TR",
    "wof:name":"Pasacik",
    "wof:placetype":"locality"
},
  "geometry": {"coordinates":[29.91861,38.79389000000001],"type":"Point"}
}