{
  "type": "Feature",
  "properties": {
    "gn:admin1_code":"64",
    "gn:asciiname":"Sehithasan",
    "gn:country_code":"TR",
    "gn:dem":828,
    "gn:feature_class":"P",
    "gn:feature_code":"PPL",
    "gn:name":"\u015eehithasan",
    "gn:population":0,
    "gn:timezone":"Europe/Istanbul",
    "iso:country":"TR",
    "name:tur_x_preferred":[
        "\u015eehithasan"
    ],
    "wof:name":"Sehithasan",
    "wof:placetype":"locality"
},
  "geometry": {"coordinates":[28.966,38.58394000000001],"type":"Point"}
}