{
  "type": "Feature",
  "properties": {
    "gn:admin1_code":"93",
    "gn:asciiname":"Fevziye",
    "gn:country_code":"TR",
    "gn:dem":129,
    "gn:feature_class":"P",
    "gn:feature_code":"PPL",
    "gn:name":"Fevziye",
    "gn:population":0,
    "gn:timezone":"Europe/Istanbul",
    "iso:country":"TR",
    "wof:name":"Fevziye",
    "wof:placetype":"locality"
},
  "geometry": {"coordinates":[31.0608,40.83216],"type":"Point"}
}