{
  "type": "Feature",
  "properties": {
    "gn:admin1_code":"65.0",
    "gn:asciiname":"Cakirbey",
    "gn:country_code":"TR",
    "gn:dem":1777,
    "gn:feature_class":"P",
    "gn:feature_code":"PPL",
    "gn:name":"\u00c7ak\u0131rbey",
    "gn:population":0,
    "gn:timezone":"Europe/Istanbul",
    "iso:country":"TR",
    "name:tur_x_preferred":[
        "\u00c7ak\u0131rbey"
    ],
    "wof:name":"Cakirbey",
    "wof:placetype":"locality"
},
  "geometry": {"coordinates":[43.58752,38.90501],"type":"Point"}
}