{
  "type": "Feature",
  "properties": {
    "iso:country":"TR",
    "name:eng_x_preferred":[
        "Ahmet Yesevi"
    ],
    "name:tur_x_preferred":[
        "Ahmet Yesevi"
    ],
    "wof:name":"Ahmet Yesevi",
    "wof:placetype":"neighbourhood"
},
  "geometry": {"coordinates":[29.30854115779962,40.8682018970141],"type":"Point"}
}