{
  "type": "Feature",
  "properties": {
    "gn:admin1_code":"31.0",
    "gn:asciiname":"Mayadali",
    "gn:country_code":"TR",
    "gn:dem":376,
    "gn:feature_class":"P",
    "gn:feature_code":"PPL",
    "gn:name":"Mayadal\u0131",
    "gn:population":0,
    "gn:timezone":"Europe/Istanbul",
    "iso:country":"TR",
    "name:tur_x_preferred":[
        "Uyand\u0131"
    ],
    "name:und_x_variant":[
        "Mayadaly",
        "Mayadal\u0131"
    ],
    "wof:name":"Mayadali",
    "wof:placetype":"locality"
},
  "geometry": {"coordinates":[36.33506,36.1182],"type":"Point"}
}