{
  "type": "Feature",
  "properties": {
    "gn:admin1_code":"52.0",
    "gn:asciiname":"Cevizlik",
    "gn:country_code":"TR",
    "gn:dem":390,
    "gn:feature_class":"P",
    "gn:feature_code":"PPL",
    "gn:name":"Cevizlik",
    "gn:population":0,
    "gn:timezone":"Europe/Istanbul",
    "iso:country":"TR",
    "name:tur_x_preferred":[
        "Cevizlik"
    ],
    "name:und_x_variant":[
        "\u00c7evizlik"
    ],
    "wof:name":"Cevizlik",
    "wof:placetype":"locality"
},
  "geometry": {"coordinates":[37.79519000000001,40.88872],"type":"Point"}
}