{
  "type": "Feature",
  "properties": {
    "gn:country":"TR",
    "gn:fcode":"PPL",
    "gn:population":20000,
    "iso:country":"TR",
    "name:ceb_x_preferred":[
        "Tekirova"
    ],
    "name:deu_x_preferred":[
        "Tekirova"
    ],
    "name:eng_x_preferred":[
        "Tekirova"
    ],
    "name:fra_x_preferred":[
        "Tekirova"
    ],
    "name:nan_x_preferred":[
        "Tekirova"
    ],
    "name:nld_x_preferred":[
        "Tekirova"
    ],
    "name:ron_x_preferred":[
        "Tekirova"
    ],
    "name:rus_x_preferred":[
        "\u0422\u0435\u043a\u0438\u0440\u043e\u0432\u0430"
    ],
    "name:tur_x_preferred":[
        "Tekirova"
    ],
    "name:ukr_x_preferred":[
        "\u0422\u0435\u043a\u0456\u0440\u043e\u0432\u0430"
    ],
    "name:und_x_variant":[
        "\u00c7eltikli"
    ],
    "name:vie_x_preferred":[
        "Tekirova"
    ],
    "qs:name":"Tekirova",
    "qs:photos_9r":0,
    "qs:photos_sr":0,
    "qs:pop_sr":"6",
    "wd:wordcount":47,
    "wof:name":"Tekirova",
    "wof:placetype":"locality",
    "wof:population":20000
},
  "geometry": {"coordinates":[30.52723,36.5017],"type":"Point"}
}