{
  "type": "Feature",
  "properties": {
    "gn:admin1_code":"60.0",
    "gn:asciiname":"Karayun",
    "gn:country_code":"TR",
    "gn:dem":1108,
    "gn:feature_class":"P",
    "gn:feature_code":"PPL",
    "gn:name":"Karayun",
    "gn:population":0,
    "gn:timezone":"Europe/Istanbul",
    "iso:country":"TR",
    "name:und_x_variant":[
        "Yukar\u0131 Karay\u00fcn",
        "Karayun",
        "K\u00fc\u00e7\u00fckkaray\u00fcn"
    ],
    "wof:name":"Karayun",
    "wof:placetype":"locality"
},
  "geometry": {"coordinates":[35.77057,40.23839],"type":"Point"}
}