{
  "type": "Feature",
  "properties": {
    "iso:country":"TR",
    "name:eng_x_preferred":[
        "Kaleici"
    ],
    "name:tur_x_preferred":[
        "Kalei\u00e7i"
    ],
    "wof:name":"Kaleici",
    "wof:placetype":"neighbourhood"
},
  "geometry": {"coordinates":[28.45375704591734,41.15199949385909],"type":"Point"}
}