{
  "type": "Feature",
  "properties": {
    "gn:admin1_code":"40",
    "gn:asciiname":"Avanoglu",
    "gn:country_code":"TR",
    "gn:dem":811,
    "gn:feature_class":"P",
    "gn:feature_code":"PPL",
    "gn:name":"Avano\u011flu",
    "gn:population":0,
    "gn:timezone":"Europe/Istanbul",
    "iso:country":"TR",
    "wof:name":"Avanoglu",
    "wof:placetype":"locality"
},
  "geometry": {"coordinates":[33.97823,39.6849],"type":"Point"}
}