{
  "type": "Feature",
  "properties": {
    "gn:admin1_code":"54.0",
    "gn:asciiname":"Karapinar",
    "gn:country_code":"TR",
    "gn:dem":26,
    "gn:feature_class":"P",
    "gn:feature_code":"PPL",
    "gn:name":"Karap\u0131nar",
    "gn:population":0,
    "gn:timezone":"Europe/Istanbul",
    "iso:country":"TR",
    "name:tur_x_preferred":[
        "Karap\u0131nar"
    ],
    "wof:name":"Karapinar",
    "wof:placetype":"locality"
},
  "geometry": {"coordinates":[30.62667,41.05556],"type":"Point"}
}