{
  "type": "Feature",
  "properties": {
    "gn:admin1_code":"65",
    "gn:asciiname":"Yucelen",
    "gn:country_code":"TR",
    "gn:dem":2227,
    "gn:feature_class":"P",
    "gn:feature_code":"PPL",
    "gn:name":"Y\u00fccelen",
    "gn:population":0,
    "gn:timezone":"Europe/Istanbul",
    "iso:country":"TR",
    "name:und_x_variant":[
        "\u015eeyhrumi",
        "\u015eehrumi",
        "Y\u00fccelen"
    ],
    "wof:name":"Yucelen",
    "wof:placetype":"locality"
},
  "geometry": {"coordinates":[44.11319,38.9619],"type":"Point"}
}