{
  "type": "Feature",
  "properties": {
    "gn:admin1_code":"58",
    "gn:asciiname":"Suleymaniye",
    "gn:country_code":"TR",
    "gn:dem":1432,
    "gn:feature_class":"P",
    "gn:feature_code":"PPL",
    "gn:name":"S\u00fcleymaniye",
    "gn:population":0,
    "gn:timezone":"Europe/Istanbul",
    "iso:country":"TR",
    "wof:name":"Suleymaniye",
    "wof:placetype":"locality"
},
  "geometry": {"coordinates":[37.48795,39.67641],"type":"Point"}
}