{
  "type": "Feature",
  "properties": {
    "gn:admin1_code":"10",
    "gn:asciiname":"Aziziye",
    "gn:country_code":"TR",
    "gn:dem":831,
    "gn:feature_class":"P",
    "gn:feature_code":"PPL",
    "gn:name":"Aziziye",
    "gn:population":0,
    "gn:timezone":"Europe/Istanbul",
    "iso:country":"TR",
    "name:ceb_x_preferred":[
        "Aziziye"
    ],
    "name:fas_x_preferred":[
        "\u0639\u0632\u06cc\u0632\u06cc\u0647"
    ],
    "name:msa_x_preferred":[
        "Aziziye"
    ],
    "name:und_x_variant":[
        "Da\u011fdekos"
    ],
    "name:urd_x_preferred":[
        "\u0639\u0632\u06cc\u0632\u06cc\u06d2"
    ],
    "wof:name":"Aziziye",
    "wof:placetype":"locality"
},
  "geometry": {"coordinates":[28.77008,39.51238],"type":"Point"}
}