{
  "type": "Feature",
  "properties": {
    "gn:admin1_code":"20",
    "gn:asciiname":"Yilancik",
    "gn:country_code":"TR",
    "gn:dem":1324,
    "gn:feature_class":"P",
    "gn:feature_code":"PPL",
    "gn:name":"Y\u0131lanc\u0131k",
    "gn:population":0,
    "gn:timezone":"Europe/Istanbul",
    "iso:country":"TR",
    "name:tur_x_preferred":[
        "Y\u0131lanc\u0131k"
    ],
    "wof:name":"Yilancik",
    "wof:placetype":"locality"
},
  "geometry": {"coordinates":[29.3688,37.15326],"type":"Point"}
}