{
  "type": "Feature",
  "properties": {
    "gn:admin1_code":"87",
    "gn:asciiname":"Asagicerci",
    "gn:country_code":"TR",
    "gn:dem":286,
    "gn:feature_class":"P",
    "gn:feature_code":"PPL",
    "gn:name":"A\u015fa\u011f\u0131\u00e7erci",
    "gn:population":0,
    "gn:timezone":"Europe/Istanbul",
    "iso:country":"TR",
    "wof:name":"Asagicerci",
    "wof:placetype":"locality"
},
  "geometry": {"coordinates":[32.62208,41.60634],"type":"Point"}
}