{
  "type": "Feature",
  "properties": {
    "gn:admin1_code":"43",
    "gn:asciiname":"Emirler",
    "gn:country_code":"TR",
    "gn:dem":870,
    "gn:feature_class":"P",
    "gn:feature_code":"PPL",
    "gn:name":"Emirler",
    "gn:population":0,
    "gn:timezone":"Europe/Istanbul",
    "iso:country":"TR",
    "name:tur_x_preferred":[
        "Emirler"
    ],
    "wof:name":"Emirler",
    "wof:placetype":"locality"
},
  "geometry": {"coordinates":[29.35911,39.49116],"type":"Point"}
}