{
  "type": "Feature",
  "properties": {
    "gn:admin1_code":"81",
    "gn:asciiname":"Memisli",
    "gn:country_code":"TR",
    "gn:dem":114,
    "gn:feature_class":"P",
    "gn:feature_code":"PPL",
    "gn:name":"Memi\u015fli",
    "gn:population":0,
    "gn:timezone":"Europe/Istanbul",
    "iso:country":"TR",
    "wof:name":"Memisli",
    "wof:placetype":"locality"
},
  "geometry": {"coordinates":[35.22139,37.10639000000001],"type":"Point"}
}