{
  "type": "Feature",
  "properties": {
    "gn:admin1_code":"20",
    "gn:asciiname":"Belence",
    "gn:country_code":"TR",
    "gn:dem":1039,
    "gn:feature_class":"P",
    "gn:feature_code":"PPL",
    "gn:name":"Belence",
    "gn:population":0,
    "gn:timezone":"Europe/Istanbul",
    "iso:country":"TR",
    "name:tur_x_preferred":[
        "Belence"
    ],
    "wof:name":"Belence",
    "wof:placetype":"locality"
},
  "geometry": {"coordinates":[29.84165,38.41483],"type":"Point"}
}