{
  "type": "Feature",
  "properties": {
    "gn:admin1_code":"09",
    "gn:asciiname":"Saricaova",
    "gn:cc2":"TR",
    "gn:country_code":"TR",
    "gn:dem":926,
    "gn:feature_class":"P",
    "gn:feature_code":"PPL",
    "gn:name":"Sar\u0131caova",
    "gn:population":0,
    "gn:timezone":"Europe/Istanbul",
    "iso:country":"TR",
    "name:und_x_variant":[
        "Tahtac\u0131",
        "Sar\u0131caova"
    ],
    "wof:name":"Saricaova",
    "wof:placetype":"locality"
},
  "geometry": {"coordinates":[28.59361,38.06806],"type":"Point"}
}