{
  "type": "Feature",
  "properties": {
    "gn:admin1_code":"85",
    "gn:asciiname":"Kocaoglu",
    "gn:country_code":"TR",
    "gn:dem":409,
    "gn:feature_class":"P",
    "gn:feature_code":"PPL",
    "gn:name":"Kocao\u011flu",
    "gn:population":0,
    "gn:timezone":"Europe/Istanbul",
    "iso:country":"TR",
    "wof:name":"Kocaoglu",
    "wof:placetype":"locality"
},
  "geometry": {"coordinates":[32.00795,41.23256],"type":"Point"}
}