{
  "type": "Feature",
  "properties": {
    "gn:country":"TR",
    "gn:fcode":"PPL",
    "gn:population":123,
    "iso:country":"TR",
    "name:und_x_variant":[
        "Sanuh"
    ],
    "qs:name":"A\u015fa\u011f\u0131balc\u0131lar",
    "qs:photos_9r":0,
    "qs:photos_sr":0,
    "qs:pop_sr":"1",
    "wof:name":"A\u015fa\u011f\u0131balc\u0131lar",
    "wof:placetype":"locality",
    "wof:population":123
},
  "geometry": {"coordinates":[42.59722,37.9275],"type":"Point"}
}