{
  "type": "Feature",
  "properties": {
    "gn:admin1_code":"38.0",
    "gn:asciiname":"Kormez",
    "gn:country_code":"TR",
    "gn:dem":757,
    "gn:feature_class":"P",
    "gn:feature_code":"PPL",
    "gn:name":"K\u00f6rmez",
    "gn:population":0,
    "gn:timezone":"Europe/Istanbul",
    "iso:country":"TR",
    "wof:name":"Kormez",
    "wof:placetype":"locality"
},
  "geometry": {"coordinates":[35.49805,37.86134000000001],"type":"Point"}
}