{
  "type": "Feature",
  "properties": {
    "gn:admin1_code":"26",
    "gn:asciiname":"Dutlu",
    "gn:country_code":"TR",
    "gn:dem":1147,
    "gn:feature_class":"P",
    "gn:feature_code":"PPL",
    "gn:name":"Dutlu",
    "gn:population":0,
    "gn:timezone":"Europe/Istanbul",
    "iso:country":"TR",
    "name:und_x_variant":[
        "Tutlu"
    ],
    "wof:name":"Dutlu",
    "wof:placetype":"locality"
},
  "geometry": {"coordinates":[31.71261,39.39225],"type":"Point"}
}