{
  "type": "Feature",
  "properties": {
    "gn:admin1_code":"02",
    "gn:asciiname":"Sambayat",
    "gn:country_code":"TR",
    "gn:dem":657,
    "gn:feature_class":"P",
    "gn:feature_code":"PPLA3",
    "gn:name":"\u015eambayat",
    "gn:population":0,
    "gn:timezone":"Europe/Istanbul",
    "iso:country":"TR",
    "name:tur_x_preferred":[
        "\u015eambayat"
    ],
    "wof:name":"Sambayat",
    "wof:placetype":"locality"
},
  "geometry": {"coordinates":[38.04676,37.68441],"type":"Point"}
}