{
  "type": "Feature",
  "properties": {
    "gn:admin1_code":"20",
    "gn:asciiname":"Mentese",
    "gn:country_code":"TR",
    "gn:dem":618,
    "gn:feature_class":"P",
    "gn:feature_code":"PPL",
    "gn:name":"Mente\u015fe",
    "gn:population":0,
    "gn:timezone":"Europe/Istanbul",
    "iso:country":"TR",
    "name:tur_x_preferred":[
        "Mente\u015fe"
    ],
    "name:tur_x_variant":[
        "Mente\u015f"
    ],
    "wof:name":"Mentese",
    "wof:placetype":"locality"
},
  "geometry": {"coordinates":[29.31833,37.75],"type":"Point"}
}