{
  "type": "Feature",
  "properties": {
    "iso:country":"TR",
    "name:eng_x_preferred":[
        "Sortullu"
    ],
    "name:tur_x_preferred":[
        "Sortullu"
    ],
    "wof:name":"Sortullu",
    "wof:placetype":"neighbourhood"
},
  "geometry": {"coordinates":[29.73570711941789,41.06926250409616],"type":"Point"}
}