{
  "type": "Feature",
  "properties": {
    "gn:admin1_code":"21.0",
    "gn:asciiname":"Cataksu",
    "gn:country_code":"TR",
    "gn:dem":674,
    "gn:feature_class":"P",
    "gn:feature_code":"PPL",
    "gn:name":"\u00c7ataksu",
    "gn:population":0,
    "gn:timezone":"Europe/Istanbul",
    "iso:country":"TR",
    "name:tur_x_preferred":[
        "\u00c7ataksu"
    ],
    "wof:name":"Cataksu",
    "wof:placetype":"locality"
},
  "geometry": {"coordinates":[40.45438,37.97599],"type":"Point"}
}