{
  "type": "Feature",
  "properties": {
    "gn:admin1_code":"82.0",
    "gn:asciiname":"Yazikoy",
    "gn:country_code":"TR",
    "gn:dem":939,
    "gn:feature_class":"P",
    "gn:feature_code":"PPL",
    "gn:name":"Yaz\u0131k\u00f6y",
    "gn:population":0,
    "gn:timezone":"Europe/Istanbul",
    "iso:country":"TR",
    "name:und_x_variant":[
        "Yaz\u0131",
        "Yaz\u0131k\u00f6y"
    ],
    "wof:name":"Yazikoy",
    "wof:placetype":"locality"
},
  "geometry": {"coordinates":[33.63356,40.93884],"type":"Point"}
}