{
  "type": "Feature",
  "properties": {
    "gn:admin1_code":"66.0",
    "gn:asciiname":"Hanozu",
    "gn:country_code":"TR",
    "gn:dem":1244,
    "gn:feature_class":"P",
    "gn:feature_code":"PPL",
    "gn:name":"Han\u00f6z\u00fc",
    "gn:population":0,
    "gn:timezone":"Europe/Istanbul",
    "iso:country":"TR",
    "name:und_x_variant":[
        "Han\u00f6z\u00fc K\u00f6y\u00fc",
        "Han\u00f6z\u00fc"
    ],
    "wof:name":"Hanozu",
    "wof:placetype":"locality"
},
  "geometry": {"coordinates":[35.80845,40.09308],"type":"Point"}
}