{
  "type": "Feature",
  "properties": {
    "gn:admin1_code":"64",
    "gn:asciiname":"Kozburun",
    "gn:country_code":"TR",
    "gn:dem":889,
    "gn:feature_class":"P",
    "gn:feature_code":"PPL",
    "gn:name":"Kozburun",
    "gn:population":0,
    "gn:timezone":"Europe/Istanbul",
    "iso:country":"TR",
    "wof:name":"Kozburun",
    "wof:placetype":"locality"
},
  "geometry": {"coordinates":[28.92624,38.68412],"type":"Point"}
}