{
  "type": "Feature",
  "properties": {
    "gn:admin1_code":"09",
    "gn:asciiname":"Alemler",
    "gn:country_code":"TR",
    "gn:dem":705,
    "gn:feature_class":"P",
    "gn:feature_code":"PPL",
    "gn:name":"Alemler",
    "gn:population":0,
    "gn:timezone":"Europe/Istanbul",
    "iso:country":"TR",
    "name:tur_x_preferred":[
        "Alemler"
    ],
    "wof:name":"Alemler",
    "wof:placetype":"locality"
},
  "geometry": {"coordinates":[28.56284,37.75603],"type":"Point"}
}