{
  "type": "Feature",
  "properties": {
    "gn:admin1_code":"21",
    "gn:asciiname":"Ambarcik",
    "gn:cc2":"TR",
    "gn:country_code":"TR",
    "gn:dem":631,
    "gn:feature_class":"P",
    "gn:feature_code":"PPL",
    "gn:name":"Ambarc\u0131k",
    "gn:population":0,
    "gn:timezone":"Europe/Istanbul",
    "iso:country":"TR",
    "name:tur_x_preferred":[
        "Ambarc\u0131k"
    ],
    "name:und_x_variant":[
        "Anbarc\u0131yan",
        "Ambardzhiya",
        "Ambarciya"
    ],
    "wof:name":"Ambarcik",
    "wof:placetype":"locality"
},
  "geometry": {"coordinates":[40.80111,37.74333],"type":"Point"}
}