{
  "type": "Feature",
  "properties": {
    "gn:admin1_code":"19.0",
    "gn:asciiname":"Kirkdilim",
    "gn:country_code":"TR",
    "gn:dem":1089,
    "gn:feature_class":"P",
    "gn:feature_code":"PPL",
    "gn:name":"K\u0131rkdilim",
    "gn:population":0,
    "gn:timezone":"Europe/Istanbul",
    "iso:country":"TR",
    "wof:name":"Kirkdilim",
    "wof:placetype":"locality"
},
  "geometry": {"coordinates":[34.90052,40.72209],"type":"Point"}
}