{
  "type": "Feature",
  "properties": {
    "gn:admin1_code":"35",
    "gn:asciiname":"Lalekoy",
    "gn:country_code":"TR",
    "gn:dem":137,
    "gn:feature_class":"P",
    "gn:feature_code":"PPL",
    "gn:name":"L\u00e2lek\u00f6y",
    "gn:population":0,
    "gn:timezone":"Europe/Istanbul",
    "iso:country":"TR",
    "wof:name":"Lalekoy",
    "wof:placetype":"locality"
},
  "geometry": {"coordinates":[26.46667,38.31667],"type":"Point"}
}