{
  "type": "Feature",
  "properties": {
    "gn:admin1_code":"16",
    "gn:asciiname":"Semerici",
    "gn:country_code":"TR",
    "gn:dem":825,
    "gn:feature_class":"P",
    "gn:feature_code":"PPL",
    "gn:name":"Semerici",
    "gn:population":0,
    "gn:timezone":"Europe/Istanbul",
    "iso:country":"TR",
    "name:tur_x_preferred":[
        "Semerici"
    ],
    "wof:name":"Semerici",
    "wof:placetype":"locality"
},
  "geometry": {"coordinates":[29.00044,39.7704],"type":"Point"}
}