{
  "type": "Feature",
  "properties": {
    "gn:admin1_code":"73",
    "gn:asciiname":"Ovacik",
    "gn:country_code":"TR",
    "gn:dem":1363,
    "gn:feature_class":"P",
    "gn:feature_code":"PPL",
    "gn:name":"Ovac\u0131k",
    "gn:population":0,
    "gn:timezone":"Europe/Istanbul",
    "iso:country":"TR",
    "name:und_x_variant":[
        "Semendire",
        "Ovac\u0131k"
    ],
    "wof:name":"Ovacik",
    "wof:placetype":"locality"
},
  "geometry": {"coordinates":[34.81693,38.07322],"type":"Point"}
}