{
  "type": "Feature",
  "properties": {
    "gn:admin1_code":"76",
    "gn:asciiname":"Yedigoz",
    "gn:country_code":"TR",
    "gn:dem":1649,
    "gn:feature_class":"P",
    "gn:feature_code":"PPL",
    "gn:name":"Yedig\u00f6z",
    "gn:population":0,
    "gn:timezone":"Europe/Istanbul",
    "iso:country":"TR",
    "name:tur_x_preferred":[
        "Yedig\u00f6z"
    ],
    "wof:name":"Yedigoz",
    "wof:placetype":"locality"
},
  "geometry": {"coordinates":[41.52262,38.43476],"type":"Point"}
}