{
  "type": "Feature",
  "properties": {
    "gn:admin1_code":"65",
    "gn:asciiname":"Sulav",
    "gn:cc2":"TR",
    "gn:country_code":"TR",
    "gn:dem":2559,
    "gn:feature_class":"P",
    "gn:feature_code":"PPL",
    "gn:name":"Sulav",
    "gn:population":0,
    "gn:timezone":"Europe/Istanbul",
    "iso:country":"TR",
    "name:und_x_variant":[
        "Slav",
        "Sulav"
    ],
    "wof:name":"Sulav",
    "wof:placetype":"locality"
},
  "geometry": {"coordinates":[43.88333,37.86667],"type":"Point"}
}