{
  "type": "Feature",
  "properties": {
    "gn:admin1_code":"48",
    "gn:asciiname":"Dugrek",
    "gn:country_code":"TR",
    "gn:dem":874,
    "gn:feature_class":"P",
    "gn:feature_code":"PPL",
    "gn:name":"D\u00fc\u011frek",
    "gn:population":0,
    "gn:timezone":"Europe/Istanbul",
    "iso:country":"TR",
    "wof:name":"Dugrek",
    "wof:placetype":"locality"
},
  "geometry": {"coordinates":[28.40194,37.21639],"type":"Point"}
}