{
  "type": "Feature",
  "properties": {
    "gn:admin1_code":"28.0",
    "gn:asciiname":"Akinci",
    "gn:country_code":"TR",
    "gn:dem":424,
    "gn:feature_class":"P",
    "gn:feature_code":"PPL",
    "gn:name":"Ak\u0131nc\u0131",
    "gn:population":0,
    "gn:timezone":"Europe/Istanbul",
    "iso:country":"TR",
    "name:und_x_variant":[
        "Ak\u0131nc\u0131",
        "\u0130ndibi"
    ],
    "wof:name":"Akinci",
    "wof:placetype":"locality"
},
  "geometry": {"coordinates":[38.34472,40.85458],"type":"Point"}
}