{
  "type": "Feature",
  "properties": {
    "gn:admin1_code":"02",
    "gn:asciiname":"Bolukyayla",
    "gn:country_code":"TR",
    "gn:dem":786,
    "gn:feature_class":"P",
    "gn:feature_code":"PPL",
    "gn:name":"B\u00f6l\u00fckyayla",
    "gn:population":0,
    "gn:timezone":"Europe/Istanbul",
    "iso:country":"TR",
    "name:und_x_variant":[
        "B\u00f6l\u00fckyayla",
        "Mazil"
    ],
    "wof:name":"Bolukyayla",
    "wof:placetype":"locality"
},
  "geometry": {"coordinates":[38.47844,37.87954000000001],"type":"Point"}
}