{
  "type": "Feature",
  "properties": {
    "gn:admin1_code":"12",
    "gn:asciiname":"Angig",
    "gn:cc2":"TR",
    "gn:country_code":"TR",
    "gn:dem":1923,
    "gn:feature_class":"P",
    "gn:feature_code":"PPL",
    "gn:name":"Angig",
    "gn:population":0,
    "gn:timezone":"Europe/Istanbul",
    "iso:country":"TR",
    "name:und_x_variant":[
        "Anki\u011f",
        "Angig"
    ],
    "wof:name":"Angig",
    "wof:placetype":"locality"
},
  "geometry": {"coordinates":[40.55,39.46667],"type":"Point"}
}