{
  "type": "Feature",
  "properties": {
    "gn:admin1_code":"89.0",
    "gn:asciiname":"Hamamli",
    "gn:country_code":"TR",
    "gn:dem":1006,
    "gn:feature_class":"P",
    "gn:feature_code":"PPL",
    "gn:name":"Hamaml\u0131",
    "gn:population":0,
    "gn:timezone":"Europe/Istanbul",
    "iso:country":"TR",
    "name:und_x_variant":[
        "Hamainli",
        "Hamaml\u0131"
    ],
    "wof:name":"Hamamli",
    "wof:placetype":"locality"
},
  "geometry": {"coordinates":[32.64939,40.86982],"type":"Point"}
}