{
  "type": "Feature",
  "properties": {
    "gn:admin1_code":"03",
    "gn:asciiname":"Kulluagil Mahallesi",
    "gn:country_code":"TR",
    "gn:dem":931,
    "gn:feature_class":"P",
    "gn:feature_code":"PPL",
    "gn:name":"K\u00fcll\u00fca\u011f\u0131l Mahallesi",
    "gn:population":0,
    "gn:timezone":"Europe/Istanbul",
    "iso:country":"TR",
    "wof:name":"Kulluagil Mahallesi",
    "wof:placetype":"locality"
},
  "geometry": {"coordinates":[31.51976,38.97604000000001],"type":"Point"}
}