{
  "type": "Feature",
  "properties": {
    "gn:admin1_code":"19.0",
    "gn:asciiname":"Ahiilyas",
    "gn:country_code":"TR",
    "gn:dem":728,
    "gn:feature_class":"P",
    "gn:feature_code":"PPL",
    "gn:name":"Ahiilyas",
    "gn:population":0,
    "gn:timezone":"Europe/Istanbul",
    "iso:country":"TR",
    "name:und_x_variant":[
        "Ahilyas",
        "Ahiilyas"
    ],
    "wof:name":"Ahiilyas",
    "wof:placetype":"locality"
},
  "geometry": {"coordinates":[34.88326,40.44698],"type":"Point"}
}