{
  "type": "Feature",
  "properties": {
    "gn:admin1_code":"13.0",
    "gn:asciiname":"Kayadeler",
    "gn:country_code":"TR",
    "gn:dem":1585,
    "gn:feature_class":"P",
    "gn:feature_code":"PPL",
    "gn:name":"Kayadeler",
    "gn:population":0,
    "gn:timezone":"Europe/Istanbul",
    "iso:country":"TR",
    "name:tur_x_preferred":[
        "Kayadeler"
    ],
    "wof:name":"Kayadeler",
    "wof:placetype":"locality"
},
  "geometry": {"coordinates":[42.62005,38.25535],"type":"Point"}
}