{
  "type": "Feature",
  "properties": {
    "gn:admin1_code":"43",
    "gn:asciiname":"Altintas",
    "gn:country_code":"TR",
    "gn:dem":785,
    "gn:feature_class":"P",
    "gn:feature_code":"PPL",
    "gn:name":"Alt\u0131nta\u015f",
    "gn:population":0,
    "gn:timezone":"Europe/Istanbul",
    "iso:country":"TR",
    "name:tur_x_preferred":[
        "Alt\u0131nta\u015f"
    ],
    "wof:name":"Altintas",
    "wof:placetype":"locality"
},
  "geometry": {"coordinates":[29.45802,39.00562],"type":"Point"}
}