{
  "type": "Feature",
  "properties": {
    "gn:admin1_code":"70.0",
    "gn:asciiname":"Tokumlu",
    "gn:country_code":"TR",
    "gn:dem":2150,
    "gn:feature_class":"P",
    "gn:feature_code":"PPL",
    "gn:name":"Tokumlu",
    "gn:population":0,
    "gn:timezone":"Europe/Istanbul",
    "iso:country":"TR",
    "wof:name":"Tokumlu",
    "wof:placetype":"locality"
},
  "geometry": {"coordinates":[43.88056,37.37868],"type":"Point"}
}