{
  "type": "Feature",
  "properties": {
    "gn:admin1_code":"61",
    "gn:asciiname":"Esenkoy",
    "gn:country_code":"TR",
    "gn:dem":124,
    "gn:feature_class":"P",
    "gn:feature_code":"PPL",
    "gn:name":"Esenk\u00f6y",
    "gn:population":0,
    "gn:timezone":"Europe/Istanbul",
    "iso:country":"TR",
    "name:tur_x_preferred":[
        "Esenk\u00f6y"
    ],
    "wof:name":"Esenkoy",
    "wof:placetype":"locality"
},
  "geometry": {"coordinates":[40.35111,40.95663],"type":"Point"}
}