{
  "type": "Feature",
  "properties": {
    "gn:admin1_code":"62",
    "gn:asciiname":"Yazeli",
    "gn:country_code":"TR",
    "gn:dem":1302,
    "gn:feature_class":"P",
    "gn:feature_code":"PPL",
    "gn:name":"Yazeli",
    "gn:population":0,
    "gn:timezone":"Europe/Istanbul",
    "iso:country":"TR",
    "name:tur_x_preferred":[
        "Yazeli"
    ],
    "wof:name":"Yazeli",
    "wof:placetype":"locality"
},
  "geometry": {"coordinates":[39.6931,38.96162],"type":"Point"}
}