{
  "type": "Feature",
  "properties": {
    "gn:admin1_code":"72.0",
    "gn:asciiname":"Damlabasi",
    "gn:country_code":"TR",
    "gn:dem":768,
    "gn:feature_class":"P",
    "gn:feature_code":"PPL",
    "gn:name":"Damlaba\u015f\u0131",
    "gn:population":0,
    "gn:timezone":"Europe/Istanbul",
    "iso:country":"TR",
    "name:und_x_variant":[
        "Diploki",
        "Damlaba\u015f\u0131"
    ],
    "wof:name":"Damlabasi",
    "wof:placetype":"locality"
},
  "geometry": {"coordinates":[41.87225,37.47848],"type":"Point"}
}