{
  "type": "Feature",
  "properties": {
    "gn:admin1_code":"25.0",
    "gn:asciiname":"Yesilyayla",
    "gn:country_code":"TR",
    "gn:dem":1787,
    "gn:feature_class":"P",
    "gn:feature_code":"PPL",
    "gn:name":"Ye\u015filyayla",
    "gn:population":0,
    "gn:timezone":"Europe/Istanbul",
    "iso:country":"TR",
    "name:und_x_variant":[
        "Sitavek",
        "Ye\u015filyayla",
        "Sitavuk"
    ],
    "wof:name":"Yesilyayla",
    "wof:placetype":"locality"
},
  "geometry": {"coordinates":[41.27699000000001,40.05405],"type":"Point"}
}