{
  "type": "Feature",
  "properties": {
    "gn:admin1_code":"93",
    "gn:asciiname":"Tavukpinari",
    "gn:country_code":"TR",
    "gn:dem":654,
    "gn:feature_class":"P",
    "gn:feature_code":"PPL",
    "gn:name":"Tavukp\u0131nar\u0131",
    "gn:population":0,
    "gn:timezone":"Europe/Istanbul",
    "iso:country":"TR",
    "wof:name":"Tavukpinari",
    "wof:placetype":"locality"
},
  "geometry": {"coordinates":[31.29639,40.96047],"type":"Point"}
}