{
  "type": "Feature",
  "properties": {
    "gn:country":"TR",
    "gn:fcode":"PPL",
    "gn:population":589,
    "iso:country":"TR",
    "name:tur_x_preferred":[
        "Yukar\u0131ayd\u0131nl\u0131"
    ],
    "name:tur_x_variant":[
        "Yukar\u0131 Ayd\u0131nl\u0131"
    ],
    "name:und_x_variant":[
        "Karasheykh"
    ],
    "qs:name":"Yukar\u0131ayd\u0131nl\u0131",
    "qs:photos_9r":0,
    "qs:photos_sr":0,
    "qs:pop_sr":"2",
    "wof:name":"Yukar\u0131ayd\u0131nl\u0131",
    "wof:placetype":"locality",
    "wof:population":589
},
  "geometry": {"coordinates":[40.89883,37.15935],"type":"Point"}
}