{
  "type": "Feature",
  "properties": {
    "gn:country":"TR",
    "gn:fcode":"PPLA2",
    "gn:pop":5168,
    "iso:country":"TR",
    "name:ceb_x_preferred":[
        "Ar\u0131cak"
    ],
    "name:deu_x_preferred":[
        "Ar\u0131cak"
    ],
    "name:diq_x_preferred":[
        "M\u00earun"
    ],
    "name:eng_x_preferred":[
        "Ar\u0131cak"
    ],
    "name:fra_x_preferred":[
        "Ar\u0131cak"
    ],
    "name:ita_x_preferred":[
        "distretto di Ar\u0131cak"
    ],
    "name:kur_x_preferred":[
        "Qerebaxan"
    ],
    "name:mrj_x_preferred":[
        "\u0410\u0440\u044b\u0434\u0436\u0430\u043a"
    ],
    "name:msa_x_preferred":[
        "Ar\u0131cak"
    ],
    "name:nan_x_preferred":[
        "Ar\u0131cak"
    ],
    "name:nld_x_preferred":[
        "Ar\u0131cak"
    ],
    "name:nob_x_preferred":[
        "Ar\u0131cak"
    ],
    "name:pnb_x_preferred":[
        "\u0636\u0644\u0639 \u0627\u0631\u06cc\u062c\u0627\u06a9"
    ],
    "name:rus_x_preferred":[
        "\u0410\u0440\u044b\u0434\u0436\u0430\u043a"
    ],
    "name:swa_x_preferred":[
        "Ar\u0131cak"
    ],
    "name:tur_x_preferred":[
        "Ar\u0131cak"
    ],
    "name:ukr_x_preferred":[
        "\u0410\u0440\u0438\u0434\u0436\u0430\u043a"
    ],
    "name:unk_x_variant":[
        "Mirivan"
    ],
    "name:urd_x_preferred":[
        "\u0627\u0631\u06cc\u062c\u0627\u06a9"
    ],
    "name:vie_x_preferred":[
        "Aricak"
    ],
    "qs:name":"Ar\u0131cak",
    "qs:name_adm0":"Turkey",
    "qs:name_adm1":"Elaz\u0131\u011f",
    "qs:photos_9r":0,
    "qs:photos_sr":0,
    "qs:placetype":"Town",
    "qs:pop_sr":"5",
    "wd:wordcount":64,
    "wof:name":"Ar\u0131cak",
    "wof:placetype":"locality",
    "wof:population":5168
},
  "geometry": {"coordinates":[40.13472,38.56389],"type":"Point"}
}