{
  "type": "Feature",
  "properties": {
    "gn:admin1_code":"10",
    "gn:asciiname":"Ayvatlar",
    "gn:country_code":"TR",
    "gn:dem":267,
    "gn:feature_class":"P",
    "gn:feature_code":"PPL",
    "gn:name":"Ayvatlar",
    "gn:population":0,
    "gn:timezone":"Europe/Istanbul",
    "iso:country":"TR",
    "name:tur_x_preferred":[
        "Ayvatlar"
    ],
    "wof:name":"Ayvatlar",
    "wof:placetype":"locality"
},
  "geometry": {"coordinates":[27.98878,39.7124],"type":"Point"}
}