{
  "type": "Feature",
  "properties": {
    "gn:admin1_code":"69.0",
    "gn:asciiname":"Saricicek",
    "gn:country_code":"TR",
    "gn:dem":2061,
    "gn:feature_class":"P",
    "gn:feature_code":"PPL",
    "gn:name":"Sar\u0131\u00e7icek",
    "gn:population":0,
    "gn:timezone":"Europe/Istanbul",
    "iso:country":"TR",
    "name:und_x_variant":[
        "\u0130\u015fkilas",
        "Sar\u0131\u00e7icek"
    ],
    "wof:name":"Saricicek",
    "wof:placetype":"locality"
},
  "geometry": {"coordinates":[39.8578,40.44132000000001],"type":"Point"}
}