{
  "type": "Feature",
  "properties": {
    "gn:admin1_code":"14.0",
    "gn:asciiname":"Demirhanlar",
    "gn:country_code":"TR",
    "gn:dem":662,
    "gn:feature_class":"P",
    "gn:feature_code":"PPL",
    "gn:name":"Demirhanlar",
    "gn:population":0,
    "gn:timezone":"Europe/Istanbul",
    "iso:country":"TR",
    "wof:name":"Demirhanlar",
    "wof:placetype":"locality"
},
  "geometry": {"coordinates":[30.88911,40.24196],"type":"Point"}
}