{
  "type": "Feature",
  "properties": {
    "gn:admin1_code":"19.0",
    "gn:asciiname":"Akkil",
    "gn:country_code":"TR",
    "gn:dem":908,
    "gn:feature_class":"P",
    "gn:feature_code":"PPL",
    "gn:name":"Akkil",
    "gn:population":0,
    "gn:timezone":"Europe/Istanbul",
    "iso:country":"TR",
    "wof:name":"Akkil",
    "wof:placetype":"locality"
},
  "geometry": {"coordinates":[34.42105,40.69566],"type":"Point"}
}