{
  "type": "Feature",
  "properties": {
    "gn:admin1_code":"78",
    "gn:asciiname":"Gokcekent",
    "gn:country_code":"TR",
    "gn:dem":1051,
    "gn:feature_class":"P",
    "gn:feature_code":"PPL",
    "gn:name":"G\u00f6k\u00e7ekent",
    "gn:population":0,
    "gn:timezone":"Europe/Istanbul",
    "iso:country":"TR",
    "name:und_x_variant":[
        "G\u00f6k\u00e7ekent",
        "Uluk\u00f6y"
    ],
    "wof:name":"Gokcekent",
    "wof:placetype":"locality"
},
  "geometry": {"coordinates":[32.85809,36.53661],"type":"Point"}
}