{
  "type": "Feature",
  "properties": {
    "gn:admin1_code":"35",
    "gn:asciiname":"Yenice",
    "gn:country_code":"TR",
    "gn:dem":212,
    "gn:feature_class":"P",
    "gn:feature_code":"PPL",
    "gn:name":"Yenice",
    "gn:population":0,
    "gn:timezone":"Europe/Istanbul",
    "iso:country":"TR",
    "name:und_x_variant":[
        "Yenicek\u00f6y",
        "Yenice"
    ],
    "wof:name":"Yenice",
    "wof:placetype":"locality"
},
  "geometry": {"coordinates":[27.01143,39.10431],"type":"Point"}
}