{
  "type": "Feature",
  "properties": {
    "gn:admin1_code":"63",
    "gn:asciiname":"Hora",
    "gn:country_code":"TR",
    "gn:dem":672,
    "gn:feature_class":"P",
    "gn:feature_code":"PPL",
    "gn:name":"Hora",
    "gn:population":0,
    "gn:timezone":"Europe/Istanbul",
    "iso:country":"TR",
    "name:ast_x_preferred":[
        "Hora"
    ],
    "name:ceb_x_preferred":[
        "Hora"
    ],
    "name:ces_x_preferred":[
        "Hora"
    ],
    "name:deu_x_preferred":[
        "Hora"
    ],
    "name:fin_x_preferred":[
        "Hora"
    ],
    "name:fra_x_preferred":[
        "Hora"
    ],
    "name:glg_x_preferred":[
        "Hora"
    ],
    "name:nld_x_preferred":[
        "Hora"
    ],
    "name:por_x_preferred":[
        "Hora"
    ],
    "name:slk_x_preferred":[
        "Hora"
    ],
    "name:spa_x_preferred":[
        "Hora"
    ],
    "name:swe_x_preferred":[
        "Hora"
    ],
    "name:tur_x_preferred":[
        "Hora"
    ],
    "wof:name":"Hora",
    "wof:placetype":"locality"
},
  "geometry": {"coordinates":[39.24632,37.05701],"type":"Point"}
}