{
  "type": "Feature",
  "properties": {
    "gn:admin1_code":"25.0",
    "gn:asciiname":"Kotanduzu",
    "gn:country_code":"TR",
    "gn:dem":2198,
    "gn:feature_class":"P",
    "gn:feature_code":"PPL",
    "gn:name":"Kotand\u00fcz\u00fc",
    "gn:population":0,
    "gn:timezone":"Europe/Istanbul",
    "iso:country":"TR",
    "name:und_x_variant":[
        "Kotand\u00fcz\u00fc K\u00f6y\u00fc",
        "Kotand\u00fcz\u00fc"
    ],
    "wof:name":"Kotanduzu",
    "wof:placetype":"locality"
},
  "geometry": {"coordinates":[41.63396,40.08462],"type":"Point"}
}