{
  "type": "Feature",
  "properties": {
    "gn:admin1_code":"54.0",
    "gn:asciiname":"Meleksesolak",
    "gn:country_code":"TR",
    "gn:dem":376,
    "gn:feature_class":"P",
    "gn:feature_code":"PPL",
    "gn:name":"Melek\u015fesolak",
    "gn:population":0,
    "gn:timezone":"Europe/Istanbul",
    "iso:country":"TR",
    "name:und_x_variant":[
        "Melek\u015fe",
        "Melek\u015fesolak"
    ],
    "wof:name":"Meleksesolak",
    "wof:placetype":"locality"
},
  "geometry": {"coordinates":[30.24518,40.56973],"type":"Point"}
}