{
  "type": "Feature",
  "properties": {
    "gn:country":"TR",
    "gn:fcode":"PPLA2",
    "gn:pop":1938,
    "iso:country":"TR",
    "name:aze_x_preferred":[
        "Musabeyli"
    ],
    "name:dut_x_preferred":[
        "Musabeyli"
    ],
    "name:eng_x_preferred":[
        "Musabeyli"
    ],
    "name:epo_x_preferred":[
        "Musabeyli"
    ],
    "name:fre_x_preferred":[
        "Musabeyli"
    ],
    "name:ger_x_preferred":[
        "Musabeyli"
    ],
    "name:ita_x_preferred":[
        "Distretto di Musabeyli"
    ],
    "name:kur_x_preferred":[
        "Gir\u00ea Murad"
    ],
    "name:may_x_preferred":[
        "Musabeyli"
    ],
    "name:mrj_x_preferred":[
        "\u041c\u0443\u0441\u0430\u0431\u0435\u0439\u043b\u0438"
    ],
    "name:nan_x_preferred":[
        "Musabeyli"
    ],
    "name:pnb_x_preferred":[
        "\u0636\u0644\u0639 \u0645\u0648\u0633\u0627\u0628\u06cc\u0644\u06cc"
    ],
    "name:rus_x_preferred":[
        "\u041c\u0443\u0441\u0430\u0431\u0435\u0439\u043b\u0438"
    ],
    "name:swa_x_preferred":[
        "Musabeyli"
    ],
    "name:tur_x_preferred":[
        "Musabeyli"
    ],
    "name:unk_x_variant":[
        "Murath\u00fcy\u00fc\u011f\u00fc"
    ],
    "name:urd_x_preferred":[
        "\u0645\u0648\u0633\u06cc \u0628\u06d2\u0644\u06cc"
    ],
    "name:vie_x_preferred":[
        "Musabeyli"
    ],
    "qs:name":"Musabeyli",
    "qs:name_adm0":"Turkey",
    "qs:name_adm1":"Kilis",
    "qs:photos_9r":0,
    "qs:photos_sr":0,
    "qs:placetype":"Town",
    "qs:pop_sr":"3",
    "wd:wordcount":81,
    "wof:name":"Musabeyli",
    "wof:placetype":"locality",
    "wof:population":1938
},
  "geometry": {"coordinates":[36.91861,36.88639],"type":"Point"}
}