{
  "type": "Feature",
  "properties": {
    "gn:admin1_code":"25",
    "gn:asciiname":"Karaagil",
    "gn:country_code":"TR",
    "gn:dem":2198,
    "gn:feature_class":"P",
    "gn:feature_code":"PPL",
    "gn:name":"Karaa\u011f\u0131l",
    "gn:population":0,
    "gn:timezone":"Europe/Istanbul",
    "iso:country":"TR",
    "wof:name":"Karaagil",
    "wof:placetype":"locality"
},
  "geometry": {"coordinates":[42.04883,39.69952],"type":"Point"}
}