{
  "type": "Feature",
  "properties": {
    "gn:admin1_code":"8.0",
    "gn:asciiname":"Usluca",
    "gn:country_code":"TR",
    "gn:dem":1496,
    "gn:feature_class":"P",
    "gn:feature_code":"PPL",
    "gn:name":"Usluca",
    "gn:population":0,
    "gn:timezone":"Europe/Istanbul",
    "iso:country":"TR",
    "wof:name":"Usluca",
    "wof:placetype":"locality"
},
  "geometry": {"coordinates":[42.36245,41.31116],"type":"Point"}
}