{
  "type": "Feature",
  "properties": {
    "gn:admin1_code":"41.0",
    "gn:asciiname":"Hacimazli",
    "gn:country_code":"TR",
    "gn:dem":146,
    "gn:feature_class":"P",
    "gn:feature_code":"PPL",
    "gn:name":"Hac\u0131mazl\u0131",
    "gn:population":0,
    "gn:timezone":"Europe/Istanbul",
    "iso:country":"TR",
    "name:tur_x_preferred":[
        "Hac\u0131mazl\u0131"
    ],
    "name:und_x_variant":[
        "Gencali"
    ],
    "wof:name":"Hacimazli",
    "wof:placetype":"locality"
},
  "geometry": {"coordinates":[30.04975,41.09728],"type":"Point"}
}