{
  "type": "Feature",
  "properties": {
    "gn:admin1_code":"89.0",
    "gn:asciiname":"Pelitoren",
    "gn:country_code":"TR",
    "gn:dem":866,
    "gn:feature_class":"P",
    "gn:feature_code":"PPL",
    "gn:name":"Pelit\u00f6ren",
    "gn:population":0,
    "gn:timezone":"Europe/Istanbul",
    "iso:country":"TR",
    "name:und_x_variant":[
        "Pelitveren",
        "Pelitova",
        "Pelitveran",
        "Pelit\u00f6ren"
    ],
    "wof:name":"Pelitoren",
    "wof:placetype":"locality"
},
  "geometry": {"coordinates":[32.86716,41.26239],"type":"Point"}
}