{
  "type": "Feature",
  "properties": {
    "gn:admin1_code":"03",
    "gn:asciiname":"Guneysaray",
    "gn:country_code":"TR",
    "gn:dem":1036,
    "gn:feature_class":"P",
    "gn:feature_code":"PPL",
    "gn:name":"G\u00fcneysaray",
    "gn:population":0,
    "gn:timezone":"Europe/Istanbul",
    "iso:country":"TR",
    "wof:name":"Guneysaray",
    "wof:placetype":"locality"
},
  "geometry": {"coordinates":[31.05608,38.99533],"type":"Point"}
}