{
  "type": "Feature",
  "properties": {
    "gn:admin1_code":"48",
    "gn:asciiname":"Kizlan",
    "gn:cc2":"TR",
    "gn:country_code":"TR",
    "gn:dem":57,
    "gn:feature_class":"P",
    "gn:feature_code":"PPL",
    "gn:name":"K\u0131zlan",
    "gn:population":0,
    "gn:timezone":"Europe/Istanbul",
    "iso:country":"TR",
    "name:und_x_variant":[
        "K\u0131zlank\u00f6y",
        "K\u0131zlan"
    ],
    "wof:name":"Kizlan",
    "wof:placetype":"locality"
},
  "geometry": {"coordinates":[27.69306,36.77444000000001],"type":"Point"}
}