{
  "type": "Feature",
  "properties": {
    "gn:admin1_code":"14.0",
    "gn:asciiname":"Cepni",
    "gn:country_code":"TR",
    "gn:dem":915,
    "gn:feature_class":"P",
    "gn:feature_code":"PPL",
    "gn:name":"\u00c7epni",
    "gn:population":0,
    "gn:timezone":"Europe/Istanbul",
    "iso:country":"TR",
    "name:und_x_variant":[
        "\u00c7epti",
        "\u00c7epni"
    ],
    "wof:name":"Cepni",
    "wof:placetype":"locality"
},
  "geometry": {"coordinates":[31.25169,40.56122],"type":"Point"}
}