{
  "type": "Feature",
  "properties": {
    "gn:admin1_code":"66",
    "gn:asciiname":"Hisarbey",
    "gn:country_code":"TR",
    "gn:dem":1259,
    "gn:feature_class":"P",
    "gn:feature_code":"PPL",
    "gn:name":"Hisarbey",
    "gn:population":0,
    "gn:timezone":"Europe/Istanbul",
    "iso:country":"TR",
    "wof:name":"Hisarbey",
    "wof:placetype":"locality"
},
  "geometry": {"coordinates":[35.64679,39.56812],"type":"Point"}
}