{
  "type": "Feature",
  "properties": {
    "gn:admin1_code":"60.0",
    "gn:asciiname":"Kazili",
    "gn:country_code":"TR",
    "gn:dem":862,
    "gn:feature_class":"P",
    "gn:feature_code":"PPL",
    "gn:name":"Kaz\u0131l\u0131",
    "gn:population":0,
    "gn:timezone":"Europe/Istanbul",
    "iso:country":"TR",
    "name:und_x_variant":[
        "Kaz\u0131kl\u0131",
        "Kaz\u0131l\u0131"
    ],
    "wof:name":"Kazili",
    "wof:placetype":"locality"
},
  "geometry": {"coordinates":[35.6216,40.24612],"type":"Point"}
}