{
  "type": "Feature",
  "properties": {
    "gn:admin1_code":"54",
    "gn:asciiname":"Seyhtiman",
    "gn:country_code":"TR",
    "gn:dem":55,
    "gn:feature_class":"P",
    "gn:feature_code":"PPL",
    "gn:name":"\u015eeyht\u0131man",
    "gn:population":0,
    "gn:timezone":"Europe/Istanbul",
    "iso:country":"TR",
    "name:tur_x_preferred":[
        "\u015eeyht\u0131man"
    ],
    "wof:name":"Seyhtiman",
    "wof:placetype":"locality"
},
  "geometry": {"coordinates":[30.26536,41.00675],"type":"Point"}
}