{
  "type": "Feature",
  "properties": {
    "gn:admin1_code":"52.0",
    "gn:asciiname":"Besdam",
    "gn:country_code":"TR",
    "gn:dem":901,
    "gn:feature_class":"P",
    "gn:feature_code":"PPL",
    "gn:name":"Be\u015fdam",
    "gn:population":0,
    "gn:timezone":"Europe/Istanbul",
    "iso:country":"TR",
    "name:und_x_variant":[
        "Be\u015fdam K\u00f6y\u00fc",
        "Be\u015ftam",
        "Be\u015fdam"
    ],
    "wof:name":"Besdam",
    "wof:placetype":"locality"
},
  "geometry": {"coordinates":[37.39592,40.73193],"type":"Point"}
}