{
  "type": "Feature",
  "properties": {
    "gn:admin1_code":"13",
    "gn:asciiname":"Ortakapi",
    "gn:country_code":"TR",
    "gn:dem":1250,
    "gn:feature_class":"P",
    "gn:feature_code":"PPL",
    "gn:name":"Ortakap\u0131",
    "gn:population":0,
    "gn:timezone":"Europe/Istanbul",
    "iso:country":"TR",
    "name:und_x_variant":[
        "\u015eetek",
        "Ortakap\u0131"
    ],
    "wof:name":"Ortakapi",
    "wof:placetype":"locality"
},
  "geometry": {"coordinates":[42.01294,38.29541],"type":"Point"}
}