{
  "type": "Feature",
  "properties": {
    "gn:country":"TR",
    "gn:fcode":"PPL",
    "gn:population":656,
    "iso:country":"TR",
    "name:rus_x_preferred":[
        "Yukary-Tel\u2019shair"
    ],
    "name:tur_x_preferred":[
        "Arpatepe"
    ],
    "name:und_x_variant":[
        "Tel\u015fair"
    ],
    "qs:name":"Arpatepe",
    "qs:photos_9r":0,
    "qs:photos_sr":0,
    "qs:pop_sr":"2",
    "wof:name":"Arpatepe",
    "wof:placetype":"locality",
    "wof:population":656
},
  "geometry": {"coordinates":[40.79694,37.13917],"type":"Point"}
}