{
  "type": "Feature",
  "properties": {
    "gn:admin1_code":"79",
    "gn:asciiname":"Kavlak",
    "gn:country_code":"TR",
    "gn:dem":1190,
    "gn:feature_class":"P",
    "gn:feature_code":"PPL",
    "gn:name":"Kavlak",
    "gn:population":0,
    "gn:timezone":"Europe/Istanbul",
    "iso:country":"TR",
    "wof:name":"Kavlak",
    "wof:placetype":"locality"
},
  "geometry": {"coordinates":[33.73867,39.75601],"type":"Point"}
}