{
  "type": "Feature",
  "properties": {
    "gn:admin1_code":"62",
    "gn:asciiname":"Gedikler",
    "gn:country_code":"TR",
    "gn:dem":1142,
    "gn:feature_class":"P",
    "gn:feature_code":"PPLA3",
    "gn:name":"Gedikler",
    "gn:population":0,
    "gn:timezone":"Europe/Istanbul",
    "iso:country":"TR",
    "name:und_x_variant":[
        "Germili",
        "Gedikler"
    ],
    "wof:name":"Gedikler",
    "wof:placetype":"locality"
},
  "geometry": {"coordinates":[38.80346,39.08229],"type":"Point"}
}