{
  "type": "Feature",
  "properties": {
    "gn:admin1_code":"58.0",
    "gn:asciiname":"Alikoren",
    "gn:country_code":"TR",
    "gn:dem":1538,
    "gn:feature_class":"P",
    "gn:feature_code":"PPL",
    "gn:name":"Al\u0131k\u00f6ren",
    "gn:population":0,
    "gn:timezone":"Europe/Istanbul",
    "iso:country":"TR",
    "wof:name":"Alikoren",
    "wof:placetype":"locality"
},
  "geometry": {"coordinates":[36.45787,39.44171],"type":"Point"}
}