{
  "type": "Feature",
  "properties": {
    "gn:country":"TR",
    "gn:fcode":"PPL",
    "gn:pop":1660,
    "iso:country":"TR",
    "name:tur_x_preferred":[
        "Karas\u00fcleymanl\u0131"
    ],
    "qs:name":"Karas\u00fcleymanl\u0131",
    "qs:photos_9r":0,
    "qs:photos_sr":0,
    "qs:pop_sr":"3",
    "wd:wordcount":45,
    "wof:name":"Karas\u00fcleymanl\u0131",
    "wof:placetype":"locality",
    "wof:population":1660
},
  "geometry": {"coordinates":[36.414,36.34165],"type":"Point"}
}