{
  "type": "Feature",
  "properties": {
    "gn:admin1_code":"66",
    "gn:asciiname":"Govdecili",
    "gn:country_code":"TR",
    "gn:dem":1040,
    "gn:feature_class":"P",
    "gn:feature_code":"PPL",
    "gn:name":"G\u00f6vdecili",
    "gn:population":0,
    "gn:timezone":"Europe/Istanbul",
    "iso:country":"TR",
    "name:und_x_variant":[
        "Elek\u00e7iler \u00c7iftli\u011fi",
        "G\u00f6kdecili",
        "G\u00f6vdecili"
    ],
    "wof:name":"Govdecili",
    "wof:placetype":"locality"
},
  "geometry": {"coordinates":[35.0162,39.43099],"type":"Point"}
}