{
  "type": "Feature",
  "properties": {
    "iso:country":"TR",
    "name:eng_x_preferred":[
        "Atasehir"
    ],
    "name:tur_x_preferred":[
        "Ata\u015fehir"
    ],
    "wof:name":"Atasehir",
    "wof:placetype":"neighbourhood"
},
  "geometry": {"coordinates":[29.12872318142034,40.98519546417674],"type":"Point"}
}