{
  "type": "Feature",
  "properties": {
    "gn:admin1_code":"84",
    "gn:asciiname":"Telek",
    "gn:country_code":"TR",
    "gn:dem":1699,
    "gn:feature_class":"P",
    "gn:feature_code":"PPL",
    "gn:name":"Telek",
    "gn:population":0,
    "gn:timezone":"Europe/Istanbul",
    "iso:country":"TR",
    "name:tur_x_preferred":[
        "Telek"
    ],
    "wof:name":"Telek",
    "wof:placetype":"locality"
},
  "geometry": {"coordinates":[43.35762,40.85838],"type":"Point"}
}