{
  "type": "Feature",
  "properties": {
    "gn:admin1_code":"07",
    "gn:asciiname":"Isikli",
    "gn:country_code":"TR",
    "gn:dem":134,
    "gn:feature_class":"P",
    "gn:feature_code":"PPL",
    "gn:name":"I\u015f\u0131kl\u0131",
    "gn:population":0,
    "gn:timezone":"Europe/Istanbul",
    "iso:country":"TR",
    "wof:name":"Isikli",
    "wof:placetype":"locality"
},
  "geometry": {"coordinates":[32.2325,36.32861],"type":"Point"}
}