{
  "type": "Feature",
  "properties": {
    "gn:admin1_code":"19.0",
    "gn:asciiname":"Golpinarlar",
    "gn:country_code":"TR",
    "gn:dem":1138,
    "gn:feature_class":"P",
    "gn:feature_code":"PPL",
    "gn:name":"G\u00f6lp\u0131narlar",
    "gn:population":0,
    "gn:timezone":"Europe/Istanbul",
    "iso:country":"TR",
    "name:und_x_variant":[
        "G\u00f6lp\u0131nar",
        "G\u00f6lp\u0131nar K\u00f6y\u00fc",
        "G\u00f6lp\u0131narlar"
    ],
    "wof:name":"Golpinarlar",
    "wof:placetype":"locality"
},
  "geometry": {"coordinates":[34.6828,40.11024000000001],"type":"Point"}
}