{
  "type": "Feature",
  "properties": {
    "gn:admin1_code":"65.0",
    "gn:asciiname":"Askin",
    "gn:country_code":"TR",
    "gn:dem":2191,
    "gn:feature_class":"P",
    "gn:feature_code":"PPL",
    "gn:name":"A\u015fk\u0131n",
    "gn:population":0,
    "gn:timezone":"Europe/Istanbul",
    "iso:country":"TR",
    "name:tur_x_preferred":[
        "A\u015fk\u0131n"
    ],
    "wof:name":"Askin",
    "wof:placetype":"locality"
},
  "geometry": {"coordinates":[44.0307,38.57414],"type":"Point"}
}