{
  "type": "Feature",
  "properties": {
    "gn:admin1_code":"63.0",
    "gn:asciiname":"Ozgoren",
    "gn:country_code":"TR",
    "gn:dem":397,
    "gn:feature_class":"P",
    "gn:feature_code":"PPL",
    "gn:name":"\u00d6zg\u00f6ren",
    "gn:population":0,
    "gn:timezone":"Europe/Istanbul",
    "iso:country":"TR",
    "name:tur_x_preferred":[
        "\u00d6zg\u00f6ren"
    ],
    "wof:name":"Ozgoren",
    "wof:placetype":"locality"
},
  "geometry": {"coordinates":[38.22567,37.44425],"type":"Point"}
}