{
  "type": "Feature",
  "properties": {
    "gn:admin1_code":"81",
    "gn:asciiname":"Altikara",
    "gn:country_code":"TR",
    "gn:dem":36,
    "gn:feature_class":"P",
    "gn:feature_code":"PPL",
    "gn:name":"Alt\u0131kara",
    "gn:population":0,
    "gn:timezone":"Europe/Istanbul",
    "iso:country":"TR",
    "wof:name":"Altikara",
    "wof:placetype":"locality"
},
  "geometry": {"coordinates":[35.71161,37.00184],"type":"Point"}
}