{
  "type": "Feature",
  "properties": {
    "gn:country":"TR",
    "gn:fcode":"PPL",
    "gn:population":567,
    "iso:country":"TR",
    "name:und_x_variant":[
        "Khitmi"
    ],
    "qs:name":"Boyuncuk",
    "qs:photos_9r":0,
    "qs:photos_sr":0,
    "qs:pop_sr":"2",
    "wof:name":"Boyuncuk",
    "wof:placetype":"locality",
    "wof:population":567
},
  "geometry": {"coordinates":[41.90833,37.42667],"type":"Point"}
}