{
  "type": "Feature",
  "properties": {
    "gn:country":"TR",
    "gn:fcode":"PPL",
    "gn:population":436,
    "iso:country":"TR",
    "name:tur_x_preferred":[
        "Dibek"
    ],
    "qs:name":"Dibek",
    "qs:photos_9r":0,
    "qs:photos_sr":0,
    "qs:pop_sr":"2",
    "wof:name":"Dibek",
    "wof:placetype":"locality",
    "wof:population":436
},
  "geometry": {"coordinates":[38.87167,36.91611],"type":"Point"}
}