{
  "type": "Feature",
  "properties": {
    "gn:admin1_code":"57.0",
    "gn:asciiname":"Yazikoy",
    "gn:country_code":"TR",
    "gn:dem":825,
    "gn:feature_class":"P",
    "gn:feature_code":"PPL",
    "gn:name":"Yaz\u0131k\u00f6y",
    "gn:population":0,
    "gn:timezone":"Europe/Istanbul",
    "iso:country":"TR",
    "name:und_x_variant":[
        "\u00d6\u015fek",
        "Yaz\u0131k\u00f6y"
    ],
    "wof:name":"Yazikoy",
    "wof:placetype":"locality"
},
  "geometry": {"coordinates":[34.64764,41.40825],"type":"Point"}
}