{
  "type": "Feature",
  "properties": {
    "gn:admin1_code":"10",
    "gn:asciiname":"Sahinler",
    "gn:country_code":"TR",
    "gn:dem":120,
    "gn:feature_class":"P",
    "gn:feature_code":"PPL",
    "gn:name":"\u015eahinler",
    "gn:population":0,
    "gn:timezone":"Europe/Istanbul",
    "iso:country":"TR",
    "name:und_x_variant":[
        "Karga",
        "\u015eahinler"
    ],
    "wof:name":"Sahinler",
    "wof:placetype":"locality"
},
  "geometry": {"coordinates":[26.94823,39.43925],"type":"Point"}
}