{
  "type": "Feature",
  "properties": {
    "gn:admin1_code":"68.0",
    "gn:asciiname":"Boyali",
    "gn:country_code":"TR",
    "gn:dem":1048,
    "gn:feature_class":"P",
    "gn:feature_code":"PPL",
    "gn:name":"Boyal\u0131",
    "gn:population":0,
    "gn:timezone":"Europe/Istanbul",
    "iso:country":"TR",
    "name:und_x_variant":[
        "Mahyal\u0131",
        "Boyal\u0131"
    ],
    "wof:name":"Boyali",
    "wof:placetype":"locality"
},
  "geometry": {"coordinates":[31.87201,40.24187],"type":"Point"}
}