{
  "type": "Feature",
  "properties": {
    "gn:admin1_code":"46",
    "gn:asciiname":"Yapilipinar",
    "gn:country_code":"TR",
    "gn:dem":1505,
    "gn:feature_class":"P",
    "gn:feature_code":"PPL",
    "gn:name":"Yap\u0131l\u0131p\u0131nar",
    "gn:population":0,
    "gn:timezone":"Europe/Istanbul",
    "iso:country":"TR",
    "name:tur_x_preferred":[
        "Yap\u0131l\u0131p\u0131nar"
    ],
    "name:und_x_variant":[
        "Yap\u0131lp\u0131nar",
        "Kokmu\u015fkuyu"
    ],
    "wof:name":"Yapilipinar",
    "wof:placetype":"locality"
},
  "geometry": {"coordinates":[37.53456,38.29651],"type":"Point"}
}