{
  "type": "Feature",
  "properties": {
    "gn:admin1_code":"45",
    "gn:asciiname":"Buyuk Sumbuller",
    "gn:country_code":"TR",
    "gn:dem":400,
    "gn:feature_class":"P",
    "gn:feature_code":"PPL",
    "gn:name":"B\u00fcy\u00fck S\u00fcmb\u00fcller",
    "gn:population":0,
    "gn:timezone":"Europe/Istanbul",
    "iso:country":"TR",
    "name:tur_x_preferred":[
        "B\u00fcy\u00fck S\u00fcnb\u00fcller"
    ],
    "name:und_x_variant":[
        "B\u00fcy\u00fck S\u00fcmb\u00fcller"
    ],
    "wof:name":"Buyuk Sumbuller",
    "wof:placetype":"locality"
},
  "geometry": {"coordinates":[27.23453,38.73328],"type":"Point"}
}