{
  "type": "Feature",
  "properties": {
    "gn:admin1_code":"58",
    "gn:asciiname":"Avcipinari",
    "gn:country_code":"TR",
    "gn:dem":1455,
    "gn:feature_class":"P",
    "gn:feature_code":"PPL",
    "gn:name":"Avc\u0131p\u0131nar\u0131",
    "gn:population":0,
    "gn:timezone":"Europe/Istanbul",
    "iso:country":"TR",
    "wof:name":"Avcipinari",
    "wof:placetype":"locality"
},
  "geometry": {"coordinates":[36.47247,39.89182],"type":"Point"}
}