{
  "type": "Feature",
  "properties": {
    "gn:admin1_code":"34.0",
    "gn:asciiname":"Kucukkilicli",
    "gn:country_code":"TR",
    "gn:dem":81,
    "gn:feature_class":"P",
    "gn:feature_code":"PPL",
    "gn:name":"K\u00fc\u00e7\u00fckk\u0131l\u0131\u00e7l\u0131",
    "gn:population":0,
    "gn:timezone":"Europe/Istanbul",
    "iso:country":"TR",
    "name:und_x_variant":[
        "K\u00fc\u00e7\u00fck K\u0131l\u0131n\u00e7l\u0131",
        "K\u00fc\u00e7\u00fckk\u0131l\u0131\u00e7l\u0131"
    ],
    "wof:name":"Kucukkilicli",
    "wof:placetype":"locality"
},
  "geometry": {"coordinates":[28.20539,41.13281],"type":"Point"}
}