{
  "type": "Feature",
  "properties": {
    "gn:country":"TR",
    "gn:fcode":"PPLX",
    "gn:population":0,
    "iso:country":"TR",
    "name:arz_x_preferred":[
        "\u0627\u0645\u064a\u0643"
    ],
    "name:ast_x_preferred":[
        "Emek"
    ],
    "name:cat_x_preferred":[
        "Emek"
    ],
    "name:dan_x_preferred":[
        "Emek"
    ],
    "name:deu_x_preferred":[
        "Emek"
    ],
    "name:eng_x_preferred":[
        "Emek"
    ],
    "name:fin_x_preferred":[
        "Emek"
    ],
    "name:fra_x_preferred":[
        "Emek"
    ],
    "name:glg_x_preferred":[
        "Emek"
    ],
    "name:ita_x_preferred":[
        "Emek"
    ],
    "name:min_x_preferred":[
        "Emek"
    ],
    "name:nld_x_preferred":[
        "Emek"
    ],
    "name:nob_x_preferred":[
        "Emek"
    ],
    "name:por_x_preferred":[
        "Emek"
    ],
    "name:rus_x_preferred":[
        "Emek"
    ],
    "name:slv_x_preferred":[
        "Emek"
    ],
    "name:spa_x_preferred":[
        "Emek"
    ],
    "name:sqi_x_preferred":[
        "Emek"
    ],
    "name:swe_x_preferred":[
        "Emek"
    ],
    "name:tur_x_preferred":[
        "Emek"
    ],
    "qs:name":"Emek",
    "qs:name_adm0":"Turkey",
    "qs:name_adm1":"Antalya",
    "qs:photos_9k":1,
    "qs:photos_9r":1,
    "qs:photos_all":3,
    "qs:photos_sr":0,
    "qs:placetype":"Town",
    "qs:pop_sr":"0",
    "wd:wordcount":3022,
    "wof:name":"Emek",
    "wof:placetype":"neighbourhood",
    "wof:population":0
},
  "geometry": {"coordinates":[30.7123,36.91662],"type":"Point"}
}