{
  "type": "Feature",
  "properties": {
    "gn:country":"TR",
    "gn:fcode":"PPL",
    "gn:pop":269,
    "iso:country":"TR",
    "name:aze_x_preferred":[
        "Alag\u00f6z"
    ],
    "name:ceb_x_preferred":[
        "Alag\u00f6z"
    ],
    "name:hye_x_preferred":[
        "\u0531\u056c\u0561\u0563\u0575\u0578\u0566"
    ],
    "name:rus_x_preferred":[
        "Alag\u00ebz"
    ],
    "name:swe_x_preferred":[
        "Alag\u00f6z"
    ],
    "name:tur_x_preferred":[
        "Alag\u00f6z"
    ],
    "qs:name":"Alag\u00f6z",
    "qs:photos_9r":0,
    "qs:photos_sr":0,
    "qs:pop_sr":"2",
    "wd:wordcount":46,
    "wof:name":"Alag\u00f6z",
    "wof:placetype":"locality",
    "wof:population":269
},
  "geometry": {"coordinates":[37.83111,36.79333],"type":"Point"}
}