{
  "type": "Feature",
  "properties": {
    "gn:admin1_code":"09",
    "gn:asciiname":"Tekeliler",
    "gn:country_code":"TR",
    "gn:dem":835,
    "gn:feature_class":"P",
    "gn:feature_code":"PPL",
    "gn:name":"Tekeliler",
    "gn:population":0,
    "gn:timezone":"Europe/Istanbul",
    "iso:country":"TR",
    "name:tur_x_preferred":[
        "Tekeliler"
    ],
    "wof:name":"Tekeliler",
    "wof:placetype":"locality"
},
  "geometry": {"coordinates":[28.67099,37.58118],"type":"Point"}
}