{
  "type": "Feature",
  "properties": {
    "gn:admin1_code":"5.0",
    "gn:asciiname":"Ipekkoy",
    "gn:country_code":"TR",
    "gn:dem":409,
    "gn:feature_class":"P",
    "gn:feature_code":"PPL",
    "gn:name":"\u0130pekk\u00f6y",
    "gn:population":0,
    "gn:timezone":"Europe/Istanbul",
    "iso:country":"TR",
    "name:tur_x_preferred":[
        "\u0130pekk\u00f6y"
    ],
    "name:tur_x_variant":[
        "S\u0131rab\u00f6cekhane"
    ],
    "wof:name":"Ipekkoy",
    "wof:placetype":"locality"
},
  "geometry": {"coordinates":[35.80277,40.59292],"type":"Point"}
}