{
  "type": "Feature",
  "properties": {
    "gn:admin1_code":"78",
    "gn:asciiname":"Yilangomu",
    "gn:country_code":"TR",
    "gn:dem":1400,
    "gn:feature_class":"P",
    "gn:feature_code":"PPL",
    "gn:name":"Y\u0131lang\u00f6m\u00fc",
    "gn:population":0,
    "gn:timezone":"Europe/Istanbul",
    "iso:country":"TR",
    "name:tur_x_preferred":[
        "Y\u0131lang\u00f6m\u00fc"
    ],
    "wof:name":"Yilangomu",
    "wof:placetype":"locality"
},
  "geometry": {"coordinates":[32.95576,37.08693],"type":"Point"}
}