{
  "type": "Feature",
  "properties": {
    "gn:admin1_code":"12",
    "gn:asciiname":"Taslicay",
    "gn:country_code":"TR",
    "gn:dem":1900,
    "gn:feature_class":"P",
    "gn:feature_code":"PPL",
    "gn:name":"Ta\u015fl\u0131\u00e7ay",
    "gn:population":0,
    "gn:timezone":"Europe/Istanbul",
    "iso:country":"TR",
    "name:tur_x_preferred":[
        "Ta\u015fl\u0131\u00e7ay"
    ],
    "wof:name":"Taslicay",
    "wof:placetype":"locality"
},
  "geometry": {"coordinates":[40.95853,39.27988],"type":"Point"}
}