{
  "type": "Feature",
  "properties": {
    "gn:country":"TR",
    "gn:fcode":"PPL",
    "gn:population":0,
    "iso:country":"TR",
    "name:ast_x_preferred":[
        "Kestel"
    ],
    "name:che_x_preferred":[
        "\u041a\u0435\u0441\u0442\u0435\u043b"
    ],
    "name:deu_x_preferred":[
        "Kestel"
    ],
    "name:eng_x_preferred":[
        "Kestel"
    ],
    "name:fas_x_preferred":[
        "\u06a9\u0633\u062a\u0627\u0644"
    ],
    "name:fra_x_preferred":[
        "Kestel"
    ],
    "name:hun_x_preferred":[
        "Kestel"
    ],
    "name:jpn_x_preferred":[
        "\u30b1\u30b9\u30c6\u30eb"
    ],
    "name:lit_x_preferred":[
        "Kestelis"
    ],
    "name:min_x_preferred":[
        "Kestel"
    ],
    "name:msa_x_preferred":[
        "Kestel"
    ],
    "name:nan_x_preferred":[
        "Kestel"
    ],
    "name:nld_x_preferred":[
        "Kestel"
    ],
    "name:tat_x_preferred":[
        "\u041a\u0435\u0441\u0442\u0435\u043b"
    ],
    "name:tur_x_preferred":[
        "Kestel"
    ],
    "name:vie_x_preferred":[
        "Kestel"
    ],
    "qs:name":"Kestel",
    "qs:name_adm0":"Turkey",
    "qs:name_adm1":"Antalya",
    "qs:photos":132,
    "qs:photos_1k":27,
    "qs:photos_9k":1,
    "qs:photos_9r":3,
    "qs:photos_all":132,
    "qs:photos_sr":3,
    "qs:placetype":"Town",
    "qs:pop_sr":"0",
    "wd:wordcount":405,
    "wof:name":"Kestel",
    "wof:placetype":"locality",
    "wof:population":0
},
  "geometry": {"coordinates":[32.07435,36.51614],"type":"Point"}
}