{
  "type": "Feature",
  "properties": {
    "gn:admin1_code":"46.0",
    "gn:asciiname":"Akdemir",
    "gn:country_code":"TR",
    "gn:dem":558,
    "gn:feature_class":"P",
    "gn:feature_code":"PPL",
    "gn:name":"Akdemir",
    "gn:population":0,
    "gn:timezone":"Europe/Istanbul",
    "iso:country":"TR",
    "name:tur_x_preferred":[
        "Akdemir"
    ],
    "wof:name":"Akdemir",
    "wof:placetype":"locality"
},
  "geometry": {"coordinates":[37.01532,37.2758],"type":"Point"}
}