{
  "type": "Feature",
  "properties": {
    "gn:admin1_code":"31",
    "gn:asciiname":"Aydinbahce",
    "gn:country_code":"TR",
    "gn:dem":602,
    "gn:feature_class":"P",
    "gn:feature_code":"PPL",
    "gn:name":"Ayd\u0131nbah\u00e7e",
    "gn:population":0,
    "gn:timezone":"Europe/Istanbul",
    "iso:country":"TR",
    "name:und_x_variant":[
        "G\u00fcvere",
        "Ayd\u0131nbah\u00e7e"
    ],
    "wof:name":"Aydinbahce",
    "wof:placetype":"locality"
},
  "geometry": {"coordinates":[36.01586,36.00627],"type":"Point"}
}