{
  "type": "Feature",
  "properties": {
    "gn:admin1_code":"77.0",
    "gn:asciiname":"Catiksu",
    "gn:country_code":"TR",
    "gn:dem":1589,
    "gn:feature_class":"P",
    "gn:feature_code":"PPL",
    "gn:name":"\u00c7at\u0131ksu",
    "gn:population":0,
    "gn:timezone":"Europe/Istanbul",
    "iso:country":"TR",
    "name:und_x_variant":[
        "Vah\u015fin",
        "\u00c7ataksu",
        "Vah\u015fen",
        "\u00c7at\u0131ksu"
    ],
    "wof:name":"Catiksu",
    "wof:placetype":"locality"
},
  "geometry": {"coordinates":[40.06501,40.40341],"type":"Point"}
}