{
  "type": "Feature",
  "properties": {
    "gn:admin1_code":"93",
    "gn:asciiname":"Sarayyeri",
    "gn:country_code":"TR",
    "gn:dem":143,
    "gn:feature_class":"P",
    "gn:feature_code":"PPL",
    "gn:name":"Sarayyeri",
    "gn:population":0,
    "gn:timezone":"Europe/Istanbul",
    "iso:country":"TR",
    "wof:name":"Sarayyeri",
    "wof:placetype":"locality"
},
  "geometry": {"coordinates":[31.13537,40.86319],"type":"Point"}
}