{
  "type": "Feature",
  "properties": {
    "gn:admin1_code":"23",
    "gn:asciiname":"Kiziltepe",
    "gn:country_code":"TR",
    "gn:dem":1285,
    "gn:feature_class":"P",
    "gn:feature_code":"PPL",
    "gn:name":"K\u0131z\u0131ltepe",
    "gn:population":0,
    "gn:timezone":"Europe/Istanbul",
    "iso:country":"TR",
    "name:tur_x_preferred":[
        "K\u0131z\u0131ltepe"
    ],
    "wof:name":"Kiziltepe",
    "wof:placetype":"locality"
},
  "geometry": {"coordinates":[39.52002,38.48144],"type":"Point"}
}