{
  "type": "Feature",
  "properties": {
    "gn:admin1_code":"72.0",
    "gn:asciiname":"Tanyeri",
    "gn:country_code":"TR",
    "gn:dem":912,
    "gn:feature_class":"P",
    "gn:feature_code":"PPL",
    "gn:name":"Tanyeri",
    "gn:population":0,
    "gn:timezone":"Europe/Istanbul",
    "iso:country":"TR",
    "name:und_x_variant":[
        "Ruvar",
        "Tanyeri"
    ],
    "wof:name":"Tanyeri",
    "wof:placetype":"locality"
},
  "geometry": {"coordinates":[41.68712,37.45748],"type":"Point"}
}