{
  "type": "Feature",
  "properties": {
    "gn:admin1_code":"21.0",
    "gn:asciiname":"Topcay",
    "gn:country_code":"TR",
    "gn:dem":734,
    "gn:feature_class":"P",
    "gn:feature_code":"PPL",
    "gn:name":"Top\u00e7ay",
    "gn:population":0,
    "gn:timezone":"Europe/Istanbul",
    "iso:country":"TR",
    "name:tur_x_preferred":[
        "Top\u00e7ay"
    ],
    "wof:name":"Topcay",
    "wof:placetype":"locality"
},
  "geometry": {"coordinates":[40.70361,38.15139],"type":"Point"}
}