{
  "type": "Feature",
  "properties": {
    "gn:admin1_code":"37.0",
    "gn:asciiname":"Kayakoy",
    "gn:country_code":"TR",
    "gn:dem":996,
    "gn:feature_class":"P",
    "gn:feature_code":"PPL",
    "gn:name":"Kayak\u00f6y",
    "gn:population":0,
    "gn:timezone":"Europe/Istanbul",
    "iso:country":"TR",
    "wof:name":"Kayakoy",
    "wof:placetype":"locality"
},
  "geometry": {"coordinates":[33.56134,41.43983],"type":"Point"}
}