{
  "type": "Feature",
  "properties": {
    "gn:admin1_code":"61.0",
    "gn:asciiname":"Cinali",
    "gn:country_code":"TR",
    "gn:dem":544,
    "gn:feature_class":"P",
    "gn:feature_code":"PPL",
    "gn:name":"\u00c7\u0131nal\u0131",
    "gn:population":0,
    "gn:timezone":"Europe/Istanbul",
    "iso:country":"TR",
    "wof:name":"Cinali",
    "wof:placetype":"locality"
},
  "geometry": {"coordinates":[39.67858,40.80408],"type":"Point"}
}