{
  "type": "Feature",
  "properties": {
    "gn:admin1_code":"69",
    "gn:asciiname":"Belenli",
    "gn:country_code":"TR",
    "gn:dem":1768,
    "gn:feature_class":"P",
    "gn:feature_code":"PPL",
    "gn:name":"Belenli",
    "gn:population":0,
    "gn:timezone":"Europe/Istanbul",
    "iso:country":"TR",
    "name:tur_x_preferred":[
        "Belenli"
    ],
    "wof:name":"Belenli",
    "wof:placetype":"locality"
},
  "geometry": {"coordinates":[39.51328,39.94058],"type":"Point"}
}