{
  "type": "Feature",
  "properties": {
    "iso:country":"TR",
    "name:eng_x_preferred":[
        "Sapan Baglari"
    ],
    "name:tur_x_preferred":[
        "Sapan Ba\u011flar\u0131"
    ],
    "name:tur_x_variant":[
        "Sapanba\u011flar\u0131"
    ],
    "wof:name":"Sapan Baglari",
    "wof:placetype":"neighbourhood"
},
  "geometry": {"coordinates":[29.22213822125942,40.88304221757004],"type":"Point"}
}