{
  "type": "Feature",
  "properties": {
    "gn:admin1_code":"38",
    "gn:asciiname":"Alparslan",
    "gn:country_code":"TR",
    "gn:dem":1071,
    "gn:feature_class":"P",
    "gn:feature_code":"PPL",
    "gn:name":"Alparslan",
    "gn:population":0,
    "gn:timezone":"Europe/Istanbul",
    "iso:country":"TR",
    "name:tur_x_preferred":[
        "Alparslan"
    ],
    "wof:name":"Alparslan",
    "wof:placetype":"locality"
},
  "geometry": {"coordinates":[35.52299,38.72923],"type":"Point"}
}