{
  "type": "Feature",
  "properties": {
    "gn:admin1_code":"26",
    "gn:asciiname":"Pecene",
    "gn:country_code":"TR",
    "gn:dem":1401,
    "gn:feature_class":"P",
    "gn:feature_code":"PPL",
    "gn:name":"Pe\u00e7ene",
    "gn:population":0,
    "gn:timezone":"Europe/Istanbul",
    "iso:country":"TR",
    "wof:name":"Pecene",
    "wof:placetype":"locality"
},
  "geometry": {"coordinates":[30.76083,39.11217],"type":"Point"}
}