{
  "type": "Feature",
  "properties": {
    "gn:admin1_code":"8.0",
    "gn:asciiname":"Boyali",
    "gn:country_code":"TR",
    "gn:dem":1532,
    "gn:feature_class":"P",
    "gn:feature_code":"PPL",
    "gn:name":"Boyal\u0131",
    "gn:population":0,
    "gn:timezone":"Europe/Istanbul",
    "iso:country":"TR",
    "name:und_x_variant":[
        "Sa\u00e7veret",
        "Boyal\u0131"
    ],
    "wof:name":"Boyali",
    "wof:placetype":"locality"
},
  "geometry": {"coordinates":[41.56578,40.98818],"type":"Point"}
}