{
  "type": "Feature",
  "properties": {
    "gn:admin1_code":"40",
    "gn:asciiname":"Sidikliortaoba",
    "gn:country_code":"TR",
    "gn:dem":900,
    "gn:feature_class":"P",
    "gn:feature_code":"PPL",
    "gn:name":"S\u0131d\u0131kl\u0131ortaoba",
    "gn:population":0,
    "gn:timezone":"Europe/Istanbul",
    "iso:country":"TR",
    "wof:name":"Sidikliortaoba",
    "wof:placetype":"locality"
},
  "geometry": {"coordinates":[33.91051,39.08941],"type":"Point"}
}