{
  "type": "Feature",
  "properties": {
    "gn:admin1_code":"19.0",
    "gn:asciiname":"Cevheri",
    "gn:country_code":"TR",
    "gn:dem":899,
    "gn:feature_class":"P",
    "gn:feature_code":"PPL",
    "gn:name":"Cevheri",
    "gn:population":0,
    "gn:timezone":"Europe/Istanbul",
    "iso:country":"TR",
    "name:und_x_variant":[
        "Merkepli",
        "Cevheri K\u00f6y\u00fc",
        "Cevheri"
    ],
    "wof:name":"Cevheri",
    "wof:placetype":"locality"
},
  "geometry": {"coordinates":[34.43044,40.20406],"type":"Point"}
}