{
  "type": "Feature",
  "properties": {
    "gn:admin1_code":"62",
    "gn:asciiname":"Salkimozu",
    "gn:country_code":"TR",
    "gn:dem":1429,
    "gn:feature_class":"P",
    "gn:feature_code":"PPL",
    "gn:name":"Salk\u0131m\u00f6z\u00fc",
    "gn:population":0,
    "gn:timezone":"Europe/Istanbul",
    "iso:country":"TR",
    "name:tur_x_preferred":[
        "Salk\u0131m\u00f6z\u00fc"
    ],
    "wof:name":"Salkimozu",
    "wof:placetype":"locality"
},
  "geometry": {"coordinates":[39.8047,39.60036],"type":"Point"}
}