{
  "type": "Feature",
  "properties": {
    "gn:admin1_code":"22.0",
    "gn:asciiname":"Buyukogunlu",
    "gn:country_code":"TR",
    "gn:dem":256,
    "gn:feature_class":"P",
    "gn:feature_code":"PPL",
    "gn:name":"B\u00fcy\u00fck\u00f6g\u00fcnl\u00fc",
    "gn:population":0,
    "gn:timezone":"Europe/Istanbul",
    "iso:country":"TR",
    "name:und_x_variant":[
        "B\u00fcy\u00fcnl\u00fc",
        "B\u00fcy\u00fck\u00fcnl\u00fc",
        "B\u00fcy\u00fck\u00f6g\u00fcnl\u00fc"
    ],
    "wof:name":"Buyukogunlu",
    "wof:placetype":"locality"
},
  "geometry": {"coordinates":[26.73268,41.88984],"type":"Point"}
}