{
  "type": "Feature",
  "properties": {
    "gn:admin1_code":"10",
    "gn:asciiname":"Kobaklar",
    "gn:country_code":"TR",
    "gn:dem":491,
    "gn:feature_class":"P",
    "gn:feature_code":"PPL",
    "gn:name":"Kobaklar",
    "gn:population":0,
    "gn:timezone":"Europe/Istanbul",
    "iso:country":"TR",
    "name:tur_x_preferred":[
        "Kobaklar"
    ],
    "name:und_x_variant":[
        "Musluk",
        "\u00c7aparlar",
        "\u00c7aparl\u0131"
    ],
    "wof:name":"Kobaklar",
    "wof:placetype":"locality"
},
  "geometry": {"coordinates":[27.31974,39.55865],"type":"Point"}
}