{
  "type": "Feature",
  "properties": {
    "gn:admin1_code":"33",
    "gn:asciiname":"Yakaemir",
    "gn:country_code":"TR",
    "gn:dem":1170,
    "gn:feature_class":"P",
    "gn:feature_code":"PPL",
    "gn:name":"Yakaemir",
    "gn:population":0,
    "gn:timezone":"Europe/Istanbul",
    "iso:country":"TR",
    "wof:name":"Yakaemir",
    "wof:placetype":"locality"
},
  "geometry": {"coordinates":[31.25275,38.07698],"type":"Point"}
}