{
  "type": "Feature",
  "properties": {
    "gn:admin1_code":"32.0",
    "gn:asciiname":"Teknecik",
    "gn:country_code":"TR",
    "gn:dem":752,
    "gn:feature_class":"P",
    "gn:feature_code":"PPL",
    "gn:name":"Teknecik",
    "gn:population":0,
    "gn:timezone":"Europe/Istanbul",
    "iso:country":"TR",
    "name:msa_x_preferred":[
        "Teknecik"
    ],
    "name:tur_x_preferred":[
        "Teknecik"
    ],
    "name:vie_x_preferred":[
        "Teknecik"
    ],
    "wof:name":"Teknecik",
    "wof:placetype":"locality"
},
  "geometry": {"coordinates":[33.31803,36.27057],"type":"Point"}
}