{
  "type": "Feature",
  "properties": {
    "gn:admin1_code":"69",
    "gn:asciiname":"Guzyurdu",
    "gn:country_code":"TR",
    "gn:dem":1842,
    "gn:feature_class":"P",
    "gn:feature_code":"PPL",
    "gn:name":"G\u00fczyurdu",
    "gn:population":0,
    "gn:timezone":"Europe/Istanbul",
    "iso:country":"TR",
    "name:und_x_variant":[
        "Sipik\u00f6r",
        "G\u00fczyurdu"
    ],
    "wof:name":"Guzyurdu",
    "wof:placetype":"locality"
},
  "geometry": {"coordinates":[39.56526,39.91387],"type":"Point"}
}