{
  "type": "Feature",
  "properties": {
    "gn:admin1_code":"10",
    "gn:asciiname":"Fethiye",
    "gn:country_code":"TR",
    "gn:dem":257,
    "gn:feature_class":"P",
    "gn:feature_code":"PPL",
    "gn:name":"Fethiye",
    "gn:population":0,
    "gn:timezone":"Europe/Istanbul",
    "iso:country":"TR",
    "name:ara_x_preferred":[
        "\u0641\u062a\u062d\u064a\u0629"
    ],
    "name:azb_x_preferred":[
        "\u0641\u062a\u062d\u06cc\u0647"
    ],
    "name:aze_x_preferred":[
        "F\u0259thiy\u0259"
    ],
    "name:bak_x_preferred":[
        "\u0424\u04d9\u0442\u0445\u0438\u04d9"
    ],
    "name:bul_x_preferred":[
        "\u0424\u0435\u0442\u0445\u0438\u0435"
    ],
    "name:ceb_x_preferred":[
        "Fethiye"
    ],
    "name:dan_x_preferred":[
        "Fethiye"
    ],
    "name:deu_x_preferred":[
        "Fethiye"
    ],
    "name:ell_x_preferred":[
        "\u03a6\u03b5\u03c4\u03af\u03b3\u03b9\u03b5"
    ],
    "name:epo_x_preferred":[
        "Fethiye"
    ],
    "name:fas_x_preferred":[
        "\u0641\u062a\u062d\u06cc\u0647"
    ],
    "name:fra_x_preferred":[
        "Fethiye"
    ],
    "name:gag_x_preferred":[
        "Fethiye"
    ],
    "name:heb_x_preferred":[
        "\u05e4\u05d8\u05d4\u05d9\u05d9\u05d4"
    ],
    "name:hun_x_preferred":[
        "Fethiye"
    ],
    "name:hye_x_preferred":[
        "\u0556\u0565\u0569\u0570\u056b\u0575\u0565"
    ],
    "name:ind_x_preferred":[
        "Fethiye"
    ],
    "name:ita_x_preferred":[
        "Fethiye"
    ],
    "name:jpn_x_preferred":[
        "\u30d5\u30a7\u30c8\u30d2\u30a4\u30a7"
    ],
    "name:kat_x_preferred":[
        "\u10e4\u10d4\u10d7\u10f0\u10d8\u10d4"
    ],
    "name:kor_x_preferred":[
        "\ud398\ud2f0\uc608"
    ],
    "name:min_x_preferred":[
        "Fethiye"
    ],
    "name:mrj_x_preferred":[
        "\u0424\u0435\u0442\u0445\u0438\u0435"
    ],
    "name:msa_x_preferred":[
        "Fethiye"
    ],
    "name:nld_x_preferred":[
        "Fethiye"
    ],
    "name:nno_x_preferred":[
        "Fethiye"
    ],
    "name:nor_x_preferred":[
        "Fethiye"
    ],
    "name:pnb_x_preferred":[
        "\u0636\u0644\u0639 \u0641\u062a\u06be\u06cc\u06d2"
    ],
    "name:pol_x_preferred":[
        "Fethiye"
    ],
    "name:por_x_preferred":[
        "Fethiye"
    ],
    "name:ron_x_preferred":[
        "Fethiye"
    ],
    "name:rus_x_preferred":[
        "\u0424\u0435\u0442\u0445\u0438\u0435"
    ],
    "name:spa_x_preferred":[
        "Fethiye"
    ],
    "name:swa_x_preferred":[
        "Fethiye"
    ],
    "name:swe_x_preferred":[
        "Fethiye"
    ],
    "name:tur_x_preferred":[
        "Fethiye"
    ],
    "name:ukr_x_preferred":[
        "\u0424\u0435\u0442\u0445\u0456\u0454"
    ],
    "name:urd_x_preferred":[
        "\u0641\u062a\u062d\u06cc\u06d2"
    ],
    "name:vie_x_preferred":[
        "Fethiye"
    ],
    "name:zho_x_preferred":[
        "\u8d39\u7279\u5e0c\u8036"
    ],
    "wof:name":"Fethiye",
    "wof:placetype":"locality"
},
  "geometry": {"coordinates":[27.90566,39.75277],"type":"Point"}
}