{
  "type": "Feature",
  "properties": {
    "gn:admin1_code":"25",
    "gn:asciiname":"Cavuskoy",
    "gn:country_code":"TR",
    "gn:dem":2060,
    "gn:feature_class":"P",
    "gn:feature_code":"PPL",
    "gn:name":"\u00c7avu\u015fk\u00f6y",
    "gn:population":0,
    "gn:timezone":"Europe/Istanbul",
    "iso:country":"TR",
    "name:tur_x_preferred":[
        "\u00c7avu\u015fk\u00f6y"
    ],
    "name:und_x_variant":[
        "\u00c7avu\u015f"
    ],
    "wof:name":"Cavuskoy",
    "wof:placetype":"locality"
},
  "geometry": {"coordinates":[41.96221,39.59817],"type":"Point"}
}