{
  "type": "Feature",
  "properties": {
    "gn:admin1_code":"25",
    "gn:asciiname":"Ardicyayla",
    "gn:country_code":"TR",
    "gn:dem":1803,
    "gn:feature_class":"P",
    "gn:feature_code":"PPL",
    "gn:name":"Ard\u0131\u00e7yayla",
    "gn:population":0,
    "gn:timezone":"Europe/Istanbul",
    "iso:country":"TR",
    "name:tur_x_preferred":[
        "Ard\u0131\u00e7yayla"
    ],
    "wof:name":"Ardicyayla",
    "wof:placetype":"locality"
},
  "geometry": {"coordinates":[40.32452,39.94636],"type":"Point"}
}