{
  "type": "Feature",
  "properties": {
    "gn:admin1_code":"8.0",
    "gn:asciiname":"Kornet",
    "gn:country_code":"TR",
    "gn:dem":1455,
    "gn:feature_class":"P",
    "gn:feature_code":"PPL",
    "gn:name":"Kornet",
    "gn:population":0,
    "gn:timezone":"Europe/Istanbul",
    "iso:country":"TR",
    "wof:name":"Kornet",
    "wof:placetype":"locality"
},
  "geometry": {"coordinates":[41.36667,40.93333],"type":"Point"}
}