{
  "type": "Feature",
  "properties": {
    "gn:admin1_code":"31.0",
    "gn:asciiname":"Benlidere",
    "gn:country_code":"TR",
    "gn:dem":756,
    "gn:feature_class":"P",
    "gn:feature_code":"PPL",
    "gn:name":"Benlidere",
    "gn:population":0,
    "gn:timezone":"Europe/Istanbul",
    "iso:country":"TR",
    "name:und_x_variant":[
        "Benlideresi-Key",
        "Benlideresi K\u00f6y\u00fc",
        "Benlidere"
    ],
    "wof:name":"Benlidere",
    "wof:placetype":"locality"
},
  "geometry": {"coordinates":[36.16315,36.45087],"type":"Point"}
}