{
  "type": "Feature",
  "properties": {
    "gn:admin1_code":"58.0",
    "gn:asciiname":"Guzelyurt",
    "gn:country_code":"TR",
    "gn:dem":1640,
    "gn:feature_class":"P",
    "gn:feature_code":"PPL",
    "gn:name":"G\u00fczelyurt",
    "gn:population":0,
    "gn:timezone":"Europe/Istanbul",
    "iso:country":"TR",
    "name:und_x_variant":[
        "H\u00fcs\u00fcnl\u00fc",
        "G\u00fczelyurt"
    ],
    "wof:name":"Guzelyurt",
    "wof:placetype":"locality"
},
  "geometry": {"coordinates":[38.02183,40.47216],"type":"Point"}
}