{
  "type": "Feature",
  "properties": {
    "gn:admin1_code":"78.0",
    "gn:asciiname":"Kavakozu",
    "gn:country_code":"TR",
    "gn:dem":1574,
    "gn:feature_class":"P",
    "gn:feature_code":"PPL",
    "gn:name":"Kavak\u00f6z\u00fc",
    "gn:population":0,
    "gn:timezone":"Europe/Istanbul",
    "iso:country":"TR",
    "name:tur_x_preferred":[
        "Kavak\u00f6z\u00fc"
    ],
    "wof:name":"Kavakozu",
    "wof:placetype":"locality"
},
  "geometry": {"coordinates":[33.74542,37.16649],"type":"Point"}
}