{
  "type": "Feature",
  "properties": {
    "gn:admin1_code":"71",
    "gn:asciiname":"Sogukkuyu",
    "gn:country_code":"TR",
    "gn:dem":1201,
    "gn:feature_class":"P",
    "gn:feature_code":"PPL",
    "gn:name":"So\u011fukkuyu",
    "gn:population":0,
    "gn:timezone":"Europe/Istanbul",
    "iso:country":"TR",
    "name:und_x_variant":[
        "So\u011fukkuyu",
        "Evliya\u00e7e\u015fme"
    ],
    "wof:name":"Sogukkuyu",
    "wof:placetype":"locality"
},
  "geometry": {"coordinates":[32.88744000000001,39.22511],"type":"Point"}
}