{
  "type": "Feature",
  "properties": {
    "gn:admin1_code":"40",
    "gn:asciiname":"Kabakli",
    "gn:country_code":"TR",
    "gn:dem":963,
    "gn:feature_class":"P",
    "gn:feature_code":"PPL",
    "gn:name":"Kabakl\u0131",
    "gn:population":0,
    "gn:timezone":"Europe/Istanbul",
    "iso:country":"TR",
    "wof:name":"Kabakli",
    "wof:placetype":"locality"
},
  "geometry": {"coordinates":[34.1917,39.68911],"type":"Point"}
}