{
  "type": "Feature",
  "properties": {
    "gn:admin1_code":"10",
    "gn:asciiname":"Kilcilar",
    "gn:country_code":"TR",
    "gn:dem":432,
    "gn:feature_class":"P",
    "gn:feature_code":"PPL",
    "gn:name":"K\u0131lc\u0131lar",
    "gn:population":0,
    "gn:timezone":"Europe/Istanbul",
    "iso:country":"TR",
    "name:tur_x_preferred":[
        "K\u0131lc\u0131lar"
    ],
    "wof:name":"Kilcilar",
    "wof:placetype":"locality"
},
  "geometry": {"coordinates":[27.33333,39.43333],"type":"Point"}
}