{
  "type": "Feature",
  "properties": {
    "gn:country":"TR",
    "gn:fcode":"PPLA2",
    "gn:pop":0,
    "iso:country":"TR",
    "name:deu_x_preferred":[
        "Uluk\u0131\u015fla"
    ],
    "name:eng_x_preferred":[
        "Uluk\u0131\u015fla"
    ],
    "name:fas_x_preferred":[
        "\u0627\u0648\u0644\u0648\u06a9\u06cc\u0634\u0644\u0627"
    ],
    "name:fra_x_preferred":[
        "Uluk\u0131\u015fla"
    ],
    "name:hye_x_preferred":[
        "\u0548\u0582\u056c\u0578\u0582\u0584\u0568\u0577\u056c\u0561"
    ],
    "name:ita_x_preferred":[
        "Distretto di Uluk\u0131\u015fla"
    ],
    "name:jpn_x_preferred":[
        "\u30a6\u30eb\u30af\u30b7\u30e5\u30e9"
    ],
    "name:mrj_x_preferred":[
        "\u0423\u043b\u0443\u043a\u044b\u0448\u043b\u0430"
    ],
    "name:msa_x_preferred":[
        "Uluk\u0131\u015fla"
    ],
    "name:nan_x_preferred":[
        "Uluk\u0131\u015fla"
    ],
    "name:nld_x_preferred":[
        "Uluk\u0131\u015fla"
    ],
    "name:nno_x_preferred":[
        "Uluk\u0131\u015fla"
    ],
    "name:ota_x_preferred":[
        "\u0634\u062c\u0627\u0639\u200c\u0627\u0644\u062f\u06cc\u0646"
    ],
    "name:ota_x_variant":[
        "\u0627\u0648\u0644\u0648\u0642\u0634\u0644\u0627"
    ],
    "name:rus_x_preferred":[
        "\u0423\u043b\u0443\u043a\u044b\u0448\u043b\u0430"
    ],
    "name:swa_x_preferred":[
        "Uluk\u0131\u015fla"
    ],
    "name:tur_x_preferred":[
        "\u015e\u00fccaeddin"
    ],
    "name:unk_x_variant":[
        "Halala"
    ],
    "name:urd_x_preferred":[
        "\u0627\u0648\u0644\u0648\u06a9\u06cc\u0634\u0644\u0627"
    ],
    "name:vie_x_preferred":[
        "Uluk\u0131\u015fla"
    ],
    "name:zho_x_preferred":[
        "\u70cf\u76e7\u514b\u4ec0\u62c9"
    ],
    "qs:name":"Uluk\u0131\u015fla",
    "qs:photos_9r":0,
    "qs:photos_sr":0,
    "qs:pop_sr":"4",
    "wd:wordcount":425,
    "wof:name":"Uluk\u0131\u015fla",
    "wof:placetype":"locality",
    "wof:population":0
},
  "geometry": {"coordinates":[34.48528,37.54776],"type":"Point"}
}