{
  "type": "Feature",
  "properties": {
    "gn:admin1_code":"54.0",
    "gn:asciiname":"Balikliihsaniye",
    "gn:country_code":"TR",
    "gn:dem":76,
    "gn:feature_class":"P",
    "gn:feature_code":"PPL",
    "gn:name":"Bal\u0131kl\u0131ihsaniye",
    "gn:population":0,
    "gn:timezone":"Europe/Istanbul",
    "iso:country":"TR",
    "name:tur_x_preferred":[
        "Bal\u0131kl\u0131ihsaniye"
    ],
    "wof:name":"Balikliihsaniye",
    "wof:placetype":"locality"
},
  "geometry": {"coordinates":[30.75799,40.75932],"type":"Point"}
}