{
  "type": "Feature",
  "properties": {
    "gn:admin1_code":"59.0",
    "gn:asciiname":"Alliisik",
    "gn:country_code":"TR",
    "gn:dem":198,
    "gn:feature_class":"P",
    "gn:feature_code":"PPL",
    "gn:name":"All\u0131\u0131\u015f\u0131k",
    "gn:population":0,
    "gn:timezone":"Europe/Istanbul",
    "iso:country":"TR",
    "name:und_x_variant":[
        "Al\u0131\u015f\u0131k",
        "All\u0131\u0131\u015f\u0131k"
    ],
    "wof:name":"Alliisik",
    "wof:placetype":"locality"
},
  "geometry": {"coordinates":[26.88663,40.81011],"type":"Point"}
}