{
  "type": "Feature",
  "properties": {
    "gn:admin1_code":"37.0",
    "gn:asciiname":"Alakaya",
    "gn:country_code":"TR",
    "gn:dem":1020,
    "gn:feature_class":"P",
    "gn:feature_code":"PPL",
    "gn:name":"Alakaya",
    "gn:population":0,
    "gn:timezone":"Europe/Istanbul",
    "iso:country":"TR",
    "name:und_x_variant":[
        "Dirvana",
        "Alakaya"
    ],
    "wof:name":"Alakaya",
    "wof:placetype":"locality"
},
  "geometry": {"coordinates":[33.10467,41.07719],"type":"Point"}
}