{
  "type": "Feature",
  "properties": {
    "gn:admin1_code":"55.0",
    "gn:asciiname":"Karapinar",
    "gn:country_code":"TR",
    "gn:dem":903,
    "gn:feature_class":"P",
    "gn:feature_code":"PPL",
    "gn:name":"Karap\u0131nar",
    "gn:population":0,
    "gn:timezone":"Europe/Istanbul",
    "iso:country":"TR",
    "wof:name":"Karapinar",
    "wof:placetype":"locality"
},
  "geometry": {"coordinates":[35.23137,41.09804000000001],"type":"Point"}
}