{
  "type": "Feature",
  "properties": {
    "gn:admin1_code":"09",
    "gn:asciiname":"Yaylali",
    "gn:country_code":"TR",
    "gn:dem":974,
    "gn:feature_class":"P",
    "gn:feature_code":"PPL",
    "gn:name":"Yaylal\u0131",
    "gn:population":0,
    "gn:timezone":"Europe/Istanbul",
    "iso:country":"TR",
    "name:tur_x_preferred":[
        "Yaylal\u0131"
    ],
    "wof:name":"Yaylali",
    "wof:placetype":"locality"
},
  "geometry": {"coordinates":[28.51466,38.01795],"type":"Point"}
}