{
  "type": "Feature",
  "properties": {
    "iso:country":"TR",
    "name:tur_x_preferred":[
        "Mare\u015fal \u00c7akmak"
    ],
    "wof:name":"Maresal Cakmak",
    "wof:placetype":"neighbourhood"
},
  "geometry": {"coordinates":[28.86586674197573,41.01761995537387],"type":"Point"}
}