{
  "type": "Feature",
  "properties": {
    "gn:admin1_code":"31",
    "gn:asciiname":"Madenli",
    "gn:country_code":"TR",
    "gn:dem":40,
    "gn:feature_class":"P",
    "gn:feature_code":"PPL",
    "gn:name":"Madenli",
    "gn:population":0,
    "gn:timezone":"Europe/Istanbul",
    "iso:country":"TR",
    "name:msa_x_preferred":[
        "Madenli"
    ],
    "name:tur_x_preferred":[
        "Madenli"
    ],
    "name:urd_x_preferred":[
        "\u0645\u06cc\u0688\u06cc\u0646\u0644\u06cc"
    ],
    "wof:name":"Madenli",
    "wof:placetype":"locality"
},
  "geometry": {"coordinates":[35.98894,36.4594],"type":"Point"}
}