{
  "type": "Feature",
  "properties": {
    "gn:admin1_code":"23",
    "gn:asciiname":"Karaman",
    "gn:country_code":"TR",
    "gn:dem":1266,
    "gn:feature_class":"P",
    "gn:feature_code":"PPL",
    "gn:name":"Karaman",
    "gn:population":0,
    "gn:timezone":"Europe/Istanbul",
    "iso:country":"TR",
    "name:tur_x_preferred":[
        "Karaman"
    ],
    "wof:name":"Karaman",
    "wof:placetype":"locality"
},
  "geometry": {"coordinates":[40.01136,38.75334],"type":"Point"}
}