{
  "type": "Feature",
  "properties": {
    "gn:admin1_code":"13.0",
    "gn:asciiname":"Donertas",
    "gn:country_code":"TR",
    "gn:dem":1573,
    "gn:feature_class":"P",
    "gn:feature_code":"PPL",
    "gn:name":"D\u00f6nerta\u015f",
    "gn:population":0,
    "gn:timezone":"Europe/Istanbul",
    "iso:country":"TR",
    "name:tur_x_preferred":[
        "D\u00f6nerta\u015f"
    ],
    "wof:name":"Donertas",
    "wof:placetype":"locality"
},
  "geometry": {"coordinates":[42.54788,38.31812],"type":"Point"}
}