{
  "type": "Feature",
  "properties": {
    "gn:admin1_code":"37.0",
    "gn:asciiname":"Camalti",
    "gn:country_code":"TR",
    "gn:dem":209,
    "gn:feature_class":"P",
    "gn:feature_code":"PPL",
    "gn:name":"\u00c7amalt\u0131",
    "gn:population":0,
    "gn:timezone":"Europe/Istanbul",
    "iso:country":"TR",
    "name:und_x_variant":[
        "Bedi",
        "\u00c7amalt\u0131"
    ],
    "wof:name":"Camalti",
    "wof:placetype":"locality"
},
  "geometry": {"coordinates":[33.14532,41.93999],"type":"Point"}
}