{
  "type": "Feature",
  "properties": {
    "gn:admin1_code":"37.0",
    "gn:asciiname":"Taspinar",
    "gn:country_code":"TR",
    "gn:dem":880,
    "gn:feature_class":"P",
    "gn:feature_code":"PPL",
    "gn:name":"Ta\u015fp\u0131nar",
    "gn:population":0,
    "gn:timezone":"Europe/Istanbul",
    "iso:country":"TR",
    "wof:name":"Taspinar",
    "wof:placetype":"locality"
},
  "geometry": {"coordinates":[33.02187,41.1683],"type":"Point"}
}