{
  "type": "Feature",
  "properties": {
    "gn:admin1_code":"79",
    "gn:asciiname":"Ceritobasi",
    "gn:country_code":"TR",
    "gn:dem":914,
    "gn:feature_class":"P",
    "gn:feature_code":"PPL",
    "gn:name":"Ceritobas\u0131",
    "gn:population":0,
    "gn:timezone":"Europe/Istanbul",
    "iso:country":"TR",
    "name:und_x_variant":[
        "Ciritobas\u0131",
        "Ciritobas\u0131 K\u00f6y\u00fc",
        "Ceritobas\u0131"
    ],
    "wof:name":"Ceritobasi",
    "wof:placetype":"locality"
},
  "geometry": {"coordinates":[33.80938,39.59647],"type":"Point"}
}