{
  "type": "Feature",
  "properties": {
    "gn:admin1_code":"44",
    "gn:asciiname":"Yesilkoy",
    "gn:country_code":"TR",
    "gn:dem":1564,
    "gn:feature_class":"P",
    "gn:feature_code":"PPL",
    "gn:name":"Ye\u015filk\u00f6y",
    "gn:population":0,
    "gn:timezone":"Europe/Istanbul",
    "iso:country":"TR",
    "name:und_x_variant":[
        "Sevik Mezraas\u0131",
        "Sevik",
        "Ye\u015filk\u00f6y"
    ],
    "wof:name":"Yesilkoy",
    "wof:placetype":"locality"
},
  "geometry": {"coordinates":[37.86072,38.5924],"type":"Point"}
}