{
  "type": "Feature",
  "properties": {
    "gn:admin1_code":"68.0",
    "gn:asciiname":"Atasoy",
    "gn:country_code":"TR",
    "gn:dem":808,
    "gn:feature_class":"P",
    "gn:feature_code":"PPL",
    "gn:name":"Atasoy",
    "gn:population":0,
    "gn:timezone":"Europe/Istanbul",
    "iso:country":"TR",
    "wof:name":"Atasoy",
    "wof:placetype":"locality"
},
  "geometry": {"coordinates":[32.34807,39.88096],"type":"Point"}
}