{
  "type": "Feature",
  "properties": {
    "gn:admin1_code":"26",
    "gn:asciiname":"Akyurt",
    "gn:cc2":"TR",
    "gn:country_code":"TR",
    "gn:dem":904,
    "gn:feature_class":"P",
    "gn:feature_code":"PPL",
    "gn:name":"Akyurt",
    "gn:population":0,
    "gn:timezone":"Europe/Istanbul",
    "iso:country":"TR",
    "name:und_x_variant":[
        "L\u00fctfiye",
        "A\u015fa\u011f\u0131 Kalabak",
        "Akyurt"
    ],
    "wof:name":"Akyurt",
    "wof:placetype":"locality"
},
  "geometry": {"coordinates":[30.88889,39.62389],"type":"Point"}
}