{
  "type": "Feature",
  "properties": {
    "gn:admin1_code":"26",
    "gn:asciiname":"Akyurt",
    "gn:cc2":"TR",
    "gn:country_code":"TR",
    "gn:dem":904,
    "gn:feature_class":"P",
    "gn:feature_code":"PPL",
    "gn:name":"Akyurt",
    "gn:population":0,
    "gn:timezone":"Europe/Istanbul",
    "iso:country":"TR",
    "name:ceb_x_preferred":[
        "Akyurt"
    ],
    "name:deu_x_preferred":[
        "Akyurt"
    ],
    "name:diq_x_preferred":[
        "Akyurt"
    ],
    "name:fas_x_preferred":[
        "\u0627\u06a9\u06cc\u0648\u0631\u062a"
    ],
    "name:fra_x_preferred":[
        "Akyurt"
    ],
    "name:hun_x_preferred":[
        "Akyurt"
    ],
    "name:kin_x_preferred":[
        "Akyurt"
    ],
    "name:koi_x_preferred":[
        "\u0410\u043a\u044c\u044e\u0440\u0442"
    ],
    "name:lbe_x_preferred":[
        "\u0410\u043a\u044a\u044e\u0440\u0442"
    ],
    "name:min_x_preferred":[
        "Akyurt"
    ],
    "name:mrj_x_preferred":[
        "\u0410\u043a\u044c\u044e\u0440\u0442"
    ],
    "name:msa_x_preferred":[
        "Akyurt"
    ],
    "name:nld_x_preferred":[
        "Akyurt"
    ],
    "name:nor_x_preferred":[
        "Akyurt"
    ],
    "name:pnb_x_preferred":[
        "\u0636\u0644\u0639 \u0627\u06a9\u06cc\u0631\u062a"
    ],
    "name:swa_x_preferred":[
        "Akyurt"
    ],
    "name:tur_x_preferred":[
        "Akyurt"
    ],
    "name:und_x_variant":[
        "L\u00fctfiye",
        "A\u015fa\u011f\u0131 Kalabak"
    ],
    "name:urd_x_preferred":[
        "\u0627\u06a9\u06cc\u0648\u0631\u062a"
    ],
    "name:vie_x_preferred":[
        "Akyurt"
    ],
    "wof:name":"Akyurt",
    "wof:placetype":"locality"
},
  "geometry": {"coordinates":[30.88889,39.62389],"type":"Point"}
}