{
  "type": "Feature",
  "properties": {
    "gn:admin1_code":"13",
    "gn:asciiname":"Agacdere",
    "gn:country_code":"TR",
    "gn:dem":1511,
    "gn:feature_class":"P",
    "gn:feature_code":"PPL",
    "gn:name":"A\u011fa\u00e7dere",
    "gn:population":0,
    "gn:timezone":"Europe/Istanbul",
    "iso:country":"TR",
    "name:tur_x_preferred":[
        "A\u011fa\u00e7dere"
    ],
    "name:und_x_variant":[
        "Ha\u00e7uyan"
    ],
    "wof:name":"Agacdere",
    "wof:placetype":"locality"
},
  "geometry": {"coordinates":[42.05132,38.32254],"type":"Point"}
}