{
  "type": "Feature",
  "properties": {
    "gn:admin1_code":"10",
    "gn:asciiname":"Karaman",
    "gn:country_code":"TR",
    "gn:dem":97,
    "gn:feature_class":"P",
    "gn:feature_code":"PPL",
    "gn:name":"Karaman",
    "gn:population":0,
    "gn:timezone":"Europe/Istanbul",
    "iso:country":"TR",
    "name:rus_x_preferred":[
        "\u041a\u0430\u0440\u0430\u043c\u0430\u043d"
    ],
    "name:und_x_variant":[
        "Karamank\u00f6y",
        "Karaman"
    ],
    "wof:name":"Karaman",
    "wof:placetype":"locality"
},
  "geometry": {"coordinates":[27.9926,39.65062],"type":"Point"}
}