{
  "type": "Feature",
  "properties": {
    "gn:admin1_code":"8.0",
    "gn:asciiname":"Kazimiye",
    "gn:country_code":"TR",
    "gn:dem":224,
    "gn:feature_class":"P",
    "gn:feature_code":"PPL",
    "gn:name":"Kazimiye",
    "gn:population":0,
    "gn:timezone":"Europe/Istanbul",
    "iso:country":"TR",
    "name:tur_x_preferred":[
        "Kazimiye"
    ],
    "wof:name":"Kazimiye",
    "wof:placetype":"locality"
},
  "geometry": {"coordinates":[41.56566,41.51051],"type":"Point"}
}