{
  "type": "Feature",
  "properties": {
    "gn:admin1_code":"68",
    "gn:asciiname":"Hallacli",
    "gn:country_code":"TR",
    "gn:dem":1227,
    "gn:feature_class":"P",
    "gn:feature_code":"PPL",
    "gn:name":"Halla\u00e7l\u0131",
    "gn:population":0,
    "gn:timezone":"Europe/Istanbul",
    "iso:country":"TR",
    "name:und_x_variant":[
        "Hala\u00e7l\u0131",
        "Halla\u00e7l\u0131"
    ],
    "wof:name":"Hallacli",
    "wof:placetype":"locality"
},
  "geometry": {"coordinates":[32.60535,39.70803],"type":"Point"}
}