{
  "type": "Feature",
  "properties": {
    "gn:admin1_code":"75",
    "gn:asciiname":"Ortakuyu Yaylasi",
    "gn:country_code":"TR",
    "gn:dem":1009,
    "gn:feature_class":"P",
    "gn:feature_code":"PPL",
    "gn:name":"Ortakuyu Yaylas\u0131",
    "gn:population":0,
    "gn:timezone":"Europe/Istanbul",
    "iso:country":"TR",
    "name:tur_x_preferred":[
        "Ortakuyu Yaylas\u0131"
    ],
    "name:tur_x_variant":[
        "Eskitol Yaylas\u0131"
    ],
    "wof:name":"Ortakuyu Yaylasi",
    "wof:placetype":"locality"
},
  "geometry": {"coordinates":[33.36405,38.13252],"type":"Point"}
}