{
  "type": "Feature",
  "properties": {
    "gn:admin1_code":"16",
    "gn:asciiname":"Cavus",
    "gn:country_code":"TR",
    "gn:dem":60,
    "gn:feature_class":"P",
    "gn:feature_code":"PPL",
    "gn:name":"\u00c7avu\u015f",
    "gn:population":0,
    "gn:timezone":"Europe/Istanbul",
    "iso:country":"TR",
    "name:tur_x_preferred":[
        "\u00c7avu\u015f"
    ],
    "wof:name":"Cavus",
    "wof:placetype":"locality"
},
  "geometry": {"coordinates":[28.51559,39.95068],"type":"Point"}
}