{
  "type": "Feature",
  "properties": {
    "gn:admin1_code":"34.0",
    "gn:asciiname":"Goksu",
    "gn:country_code":"TR",
    "gn:dem":43,
    "gn:feature_class":"P",
    "gn:feature_code":"PPL",
    "gn:name":"G\u00f6ksu",
    "gn:population":0,
    "gn:timezone":"Europe/Istanbul",
    "iso:country":"TR",
    "name:tur_x_preferred":[
        "G\u00f6ksu"
    ],
    "wof:name":"Goksu",
    "wof:placetype":"locality"
},
  "geometry": {"coordinates":[29.77456,41.07899000000001],"type":"Point"}
}