{
  "type": "Feature",
  "properties": {
    "gn:admin1_code":"68.0",
    "gn:asciiname":"Orencik",
    "gn:country_code":"TR",
    "gn:dem":1066,
    "gn:feature_class":"P",
    "gn:feature_code":"PPL",
    "gn:name":"\u00d6rencik",
    "gn:population":0,
    "gn:timezone":"Europe/Istanbul",
    "iso:country":"TR",
    "name:und_x_variant":[
        "Viranc\u0131k",
        "\u00d6rencik"
    ],
    "wof:name":"Orencik",
    "wof:placetype":"locality"
},
  "geometry": {"coordinates":[32.65747,40.25942],"type":"Point"}
}