{
  "type": "Feature",
  "properties": {
    "gn:admin1_code":"37.0",
    "gn:asciiname":"Yogunoluk",
    "gn:country_code":"TR",
    "gn:dem":1211,
    "gn:feature_class":"P",
    "gn:feature_code":"PPL",
    "gn:name":"Yo\u011funoluk",
    "gn:population":0,
    "gn:timezone":"Europe/Istanbul",
    "iso:country":"TR",
    "name:und_x_variant":[
        "Yo\u011funoluk",
        "Hac\u0131l\u0131"
    ],
    "wof:name":"Yogunoluk",
    "wof:placetype":"locality"
},
  "geometry": {"coordinates":[34.35079,41.39882],"type":"Point"}
}