{
  "type": "Feature",
  "properties": {
    "gn:admin1_code":"35",
    "gn:asciiname":"Maltepe",
    "gn:country_code":"TR",
    "gn:dem":21,
    "gn:feature_class":"P",
    "gn:feature_code":"PPL",
    "gn:name":"Maltepe",
    "gn:population":0,
    "gn:timezone":"Europe/Istanbul",
    "iso:country":"TR",
    "name:und_x_variant":[
        "Maltepe K\u00f6y\u00fc",
        "Maltepe"
    ],
    "wof:name":"Maltepe",
    "wof:placetype":"locality"
},
  "geometry": {"coordinates":[26.90988,38.62824000000001],"type":"Point"}
}