{
  "type": "Feature",
  "properties": {
    "gn:country":"TR",
    "gn:fcode":"PPL",
    "gn:pop":411,
    "iso:country":"TR",
    "name:deu_x_preferred":[
        "Maden"
    ],
    "name:fra_x_preferred":[
        "Maden"
    ],
    "name:kur_x_preferred":[
        "Maden"
    ],
    "name:tur_x_preferred":[
        "Maden"
    ],
    "name:unk_x_variant":[
        "Amuazam"
    ],
    "qs:name":"Maden",
    "qs:photos_9r":0,
    "qs:photos_sr":0,
    "qs:pop_sr":"2",
    "wd:wordcount":69,
    "wof:name":"Maden",
    "wof:placetype":"locality",
    "wof:population":411
},
  "geometry": {"coordinates":[40.11972,36.88889],"type":"Point"}
}