{
  "type": "Feature",
  "properties": {
    "gn:admin1_code":"34.0",
    "gn:asciiname":"Satmazli",
    "gn:country_code":"TR",
    "gn:dem":28,
    "gn:feature_class":"P",
    "gn:feature_code":"PPL",
    "gn:name":"Satmazl\u0131",
    "gn:population":0,
    "gn:timezone":"Europe/Istanbul",
    "iso:country":"TR",
    "name:tur_x_preferred":[
        "Satmazl\u0131"
    ],
    "wof:name":"Satmazli",
    "wof:placetype":"locality"
},
  "geometry": {"coordinates":[29.5562,41.12888],"type":"Point"}
}