{
  "type": "Feature",
  "properties": {
    "gn:admin1_code":"2.0",
    "gn:asciiname":"Yennice",
    "gn:country_code":"TR",
    "gn:dem":646,
    "gn:feature_class":"P",
    "gn:feature_code":"PPL",
    "gn:name":"Yennice",
    "gn:population":0,
    "gn:timezone":"Europe/Istanbul",
    "iso:country":"TR",
    "wof:name":"Yennice",
    "wof:placetype":"locality"
},
  "geometry": {"coordinates":[38.80555,37.81014],"type":"Point"}
}