{
  "type": "Feature",
  "properties": {
    "gn:admin1_code":"83.0",
    "gn:asciiname":"Madenevi",
    "gn:cc2":"TR",
    "gn:country_code":"TR",
    "gn:dem":673,
    "gn:feature_class":"P",
    "gn:feature_code":"PPL",
    "gn:name":"Madenevi",
    "gn:population":0,
    "gn:timezone":"Europe/Istanbul",
    "iso:country":"TR",
    "name:und_x_variant":[
        "Madedevi",
        "Madenevi"
    ],
    "wof:name":"Madenevi",
    "wof:placetype":"locality"
},
  "geometry": {"coordinates":[36.6725,36.95167],"type":"Point"}
}