{
  "type": "Feature",
  "properties": {
    "gn:admin1_code":"5.0",
    "gn:asciiname":"Kizilegrek",
    "gn:country_code":"TR",
    "gn:dem":769,
    "gn:feature_class":"P",
    "gn:feature_code":"PPL",
    "gn:name":"K\u0131z\u0131le\u011frek",
    "gn:population":0,
    "gn:timezone":"Europe/Istanbul",
    "iso:country":"TR",
    "wof:name":"Kizilegrek",
    "wof:placetype":"locality"
},
  "geometry": {"coordinates":[35.46672,40.70686],"type":"Point"}
}