{
  "type": "Feature",
  "properties": {
    "gn:admin1_code":"35",
    "gn:asciiname":"Degirmendere",
    "gn:country_code":"TR",
    "gn:dem":152,
    "gn:feature_class":"P",
    "gn:feature_code":"PPLA3",
    "gn:name":"De\u011firmendere",
    "gn:population":0,
    "gn:timezone":"Europe/Istanbul",
    "iso:country":"TR",
    "name:tur_x_preferred":[
        "De\u011firmendere"
    ],
    "wof:name":"Degirmendere",
    "wof:placetype":"locality"
},
  "geometry": {"coordinates":[27.14139,38.11361],"type":"Point"}
}