{
  "type": "Feature",
  "properties": {
    "gn:admin1_code":"17",
    "gn:asciiname":"Alemsah",
    "gn:country_code":"TR",
    "gn:dem":159,
    "gn:feature_class":"P",
    "gn:feature_code":"PPL",
    "gn:name":"Alem\u015fah",
    "gn:population":0,
    "gn:timezone":"Europe/Istanbul",
    "iso:country":"TR",
    "name:tur_x_preferred":[
        "Alem\u015fah"
    ],
    "name:tur_x_variant":[
        "K\u00fc\u00e7\u00fck Alem\u015fah",
        "Kebiralem\u015fah",
        "B\u00fcy\u00fck Alem\u015fah"
    ],
    "wof:name":"Alemsah",
    "wof:placetype":"locality"
},
  "geometry": {"coordinates":[26.2023,39.68991],"type":"Point"}
}