{
  "type": "Feature",
  "properties": {
    "gn:admin1_code":"75",
    "gn:asciiname":"Sirinler Yaylasi",
    "gn:country_code":"TR",
    "gn:dem":1024,
    "gn:feature_class":"P",
    "gn:feature_code":"PPL",
    "gn:name":"\u015eirinler Yaylas\u0131",
    "gn:population":0,
    "gn:timezone":"Europe/Istanbul",
    "iso:country":"TR",
    "wof:name":"Sirinler Yaylasi",
    "wof:placetype":"locality"
},
  "geometry": {"coordinates":[33.31667,38.03333],"type":"Point"}
}