{
  "type": "Feature",
  "properties": {
    "gn:admin1_code":"21",
    "gn:asciiname":"Cukurdere",
    "gn:country_code":"TR",
    "gn:dem":1154,
    "gn:feature_class":"P",
    "gn:feature_code":"PPL",
    "gn:name":"\u00c7ukurdere",
    "gn:population":0,
    "gn:timezone":"Europe/Istanbul",
    "iso:country":"TR",
    "name:tur_x_preferred":[
        "\u00c7ukurdere"
    ],
    "wof:name":"Cukurdere",
    "wof:placetype":"locality"
},
  "geometry": {"coordinates":[39.8081,38.3261],"type":"Point"}
}