{
  "type": "Feature",
  "properties": {
    "gn:admin1_code":"77.0",
    "gn:asciiname":"Konursu",
    "gn:country_code":"TR",
    "gn:dem":1515,
    "gn:feature_class":"P",
    "gn:feature_code":"PPL",
    "gn:name":"Konursu",
    "gn:population":0,
    "gn:timezone":"Europe/Istanbul",
    "iso:country":"TR",
    "name:ceb_x_preferred":[
        "Konursu"
    ],
    "name:und_x_variant":[
        "Konorsu",
        "Konursu"
    ],
    "wof:name":"Konursu",
    "wof:placetype":"locality"
},
  "geometry": {"coordinates":[40.25443,40.39397],"type":"Point"}
}