{
  "type": "Feature",
  "properties": {
    "gn:admin1_code":"24",
    "gn:asciiname":"Salur",
    "gn:country_code":"TR",
    "gn:dem":1638,
    "gn:feature_class":"P",
    "gn:feature_code":"PPL",
    "gn:name":"Salur",
    "gn:population":0,
    "gn:timezone":"Europe/Istanbul",
    "iso:country":"TR",
    "name:und_x_variant":[
        "Salor",
        "Salur"
    ],
    "wof:name":"Salur",
    "wof:placetype":"locality"
},
  "geometry": {"coordinates":[38.50918,39.9265],"type":"Point"}
}