{
  "type": "Feature",
  "properties": {
    "gn:admin1_code":"62",
    "gn:asciiname":"Sogutlu",
    "gn:country_code":"TR",
    "gn:dem":1391,
    "gn:feature_class":"P",
    "gn:feature_code":"PPL",
    "gn:name":"S\u00f6\u011f\u00fctl\u00fc",
    "gn:population":0,
    "gn:timezone":"Europe/Istanbul",
    "iso:country":"TR",
    "name:tur_x_preferred":[
        "S\u00f6\u011f\u00fctl\u00fc"
    ],
    "wof:name":"Sogutlu",
    "wof:placetype":"locality"
},
  "geometry": {"coordinates":[39.05681,39.28451],"type":"Point"}
}