{
  "type": "Feature",
  "properties": {
    "gn:admin1_code":"26",
    "gn:asciiname":"Elcik",
    "gn:country_code":"TR",
    "gn:dem":969,
    "gn:feature_class":"P",
    "gn:feature_code":"PPL",
    "gn:name":"Elcik",
    "gn:population":0,
    "gn:timezone":"Europe/Istanbul",
    "iso:country":"TR",
    "wof:name":"Elcik",
    "wof:placetype":"locality"
},
  "geometry": {"coordinates":[31.57,39.51639],"type":"Point"}
}