{
  "type": "Feature",
  "properties": {
    "gn:admin1_code":"82.0",
    "gn:asciiname":"Kirsakal",
    "gn:country_code":"TR",
    "gn:dem":1236,
    "gn:feature_class":"P",
    "gn:feature_code":"PPL",
    "gn:name":"K\u0131rsakal",
    "gn:population":0,
    "gn:timezone":"Europe/Istanbul",
    "iso:country":"TR",
    "name:und_x_variant":[
        "K\u0131rksakal",
        "K\u0131rsakal"
    ],
    "wof:name":"Kirsakal",
    "wof:placetype":"locality"
},
  "geometry": {"coordinates":[33.15004,40.65855],"type":"Point"}
}