{
  "type": "Feature",
  "properties": {
    "gn:admin1_code":"48",
    "gn:asciiname":"Kavakcali",
    "gn:country_code":"TR",
    "gn:dem":444,
    "gn:feature_class":"P",
    "gn:feature_code":"PPL",
    "gn:name":"Kavak\u00e7al\u0131",
    "gn:population":0,
    "gn:timezone":"Europe/Istanbul",
    "iso:country":"TR",
    "wof:name":"Kavakcali",
    "wof:placetype":"locality"
},
  "geometry": {"coordinates":[28.64083,37.10512],"type":"Point"}
}