{
  "type": "Feature",
  "properties": {
    "gn:admin1_code":"59.0",
    "gn:asciiname":"Gungormez",
    "gn:country_code":"TR",
    "gn:dem":223,
    "gn:feature_class":"P",
    "gn:feature_code":"PPL",
    "gn:name":"G\u00fcng\u00f6rmez",
    "gn:population":0,
    "gn:timezone":"Europe/Istanbul",
    "iso:country":"TR",
    "wof:name":"Gungormez",
    "wof:placetype":"locality"
},
  "geometry": {"coordinates":[27.98556,41.49389],"type":"Point"}
}