{
  "type": "Feature",
  "properties": {
    "gn:admin1_code":"83",
    "gn:asciiname":"Dokur",
    "gn:country_code":"TR",
    "gn:dem":754,
    "gn:feature_class":"P",
    "gn:feature_code":"PPL",
    "gn:name":"Dokur",
    "gn:population":0,
    "gn:timezone":"Europe/Istanbul",
    "iso:country":"TR",
    "wof:name":"Dokur",
    "wof:placetype":"locality"
},
  "geometry": {"coordinates":[37.07281,36.97302],"type":"Point"}
}