{
  "type": "Feature",
  "properties": {
    "gn:admin1_code":"31.0",
    "gn:asciiname":"Kolcular",
    "gn:country_code":"TR",
    "gn:dem":401,
    "gn:feature_class":"P",
    "gn:feature_code":"PPL",
    "gn:name":"Kolcular",
    "gn:population":0,
    "gn:timezone":"Europe/Istanbul",
    "iso:country":"TR",
    "name:und_x_variant":[
        "Ayn-Tlat",
        "Mes\u2019ul",
        "Kolcular"
    ],
    "wof:name":"Kolcular",
    "wof:placetype":"locality"
},
  "geometry": {"coordinates":[36.29559,35.95977],"type":"Point"}
}