{
  "type": "Feature",
  "properties": {
    "gn:admin1_code":"19.0",
    "gn:asciiname":"Cihadiye",
    "gn:country_code":"TR",
    "gn:dem":1241,
    "gn:feature_class":"P",
    "gn:feature_code":"PPL",
    "gn:name":"Cihadiye",
    "gn:population":0,
    "gn:timezone":"Europe/Istanbul",
    "iso:country":"TR",
    "wof:name":"Cihadiye",
    "wof:placetype":"locality"
},
  "geometry": {"coordinates":[34.59951,41.25414],"type":"Point"}
}