{
  "type": "Feature",
  "properties": {
    "gn:admin1_code":"89",
    "gn:asciiname":"Kuzdere",
    "gn:country_code":"TR",
    "gn:dem":1196,
    "gn:feature_class":"P",
    "gn:feature_code":"PPL",
    "gn:name":"Kuzdere",
    "gn:population":0,
    "gn:timezone":"Europe/Istanbul",
    "iso:country":"TR",
    "wof:name":"Kuzdere",
    "wof:placetype":"locality"
},
  "geometry": {"coordinates":[32.35061,40.98464],"type":"Point"}
}