{
  "type": "Feature",
  "properties": {
    "gn:admin1_code":"22.0",
    "gn:asciiname":"Harmanli",
    "gn:country_code":"TR",
    "gn:dem":163,
    "gn:feature_class":"P",
    "gn:feature_code":"PPL",
    "gn:name":"Harmanl\u0131",
    "gn:population":0,
    "gn:timezone":"Europe/Istanbul",
    "iso:country":"TR",
    "name:tur_x_preferred":[
        "Harmanl\u0131"
    ],
    "wof:name":"Harmanli",
    "wof:placetype":"locality"
},
  "geometry": {"coordinates":[26.74515,41.09648],"type":"Point"}
}