{
  "type": "Feature",
  "properties": {
    "gn:admin1_code":"16.0",
    "gn:asciiname":"Sukraniye",
    "gn:cc2":"TR",
    "gn:country_code":"TR",
    "gn:dem":547,
    "gn:feature_class":"P",
    "gn:feature_code":"PPL",
    "gn:name":"\u015e\u00fckraniye",
    "gn:population":0,
    "gn:timezone":"Europe/Istanbul",
    "iso:country":"TR",
    "name:und_x_variant":[
        "Kazanc\u0131",
        "\u015e\u00fckraniye"
    ],
    "wof:name":"Sukraniye",
    "wof:placetype":"locality"
},
  "geometry": {"coordinates":[29.35,40.1525],"type":"Point"}
}