{
  "type": "Feature",
  "properties": {
    "gn:admin1_code":"10",
    "gn:asciiname":"Kozpinar",
    "gn:country_code":"TR",
    "gn:dem":375,
    "gn:feature_class":"P",
    "gn:feature_code":"PPL",
    "gn:name":"Kozp\u0131nar",
    "gn:population":0,
    "gn:timezone":"Europe/Istanbul",
    "iso:country":"TR",
    "name:und_x_variant":[
        "Kozp\u0131nar Koyu",
        "Kozp\u0131nar"
    ],
    "wof:name":"Kozpinar",
    "wof:placetype":"locality"
},
  "geometry": {"coordinates":[28.02052,39.4409],"type":"Point"}
}