{
  "type": "Feature",
  "properties": {
    "gn:admin1_code":"03",
    "gn:asciiname":"Ozburun",
    "gn:country_code":"TR",
    "gn:dem":1143,
    "gn:feature_class":"P",
    "gn:feature_code":"PPL",
    "gn:name":"\u00d6zburun",
    "gn:population":0,
    "gn:timezone":"Europe/Istanbul",
    "iso:country":"TR",
    "wof:name":"Ozburun",
    "wof:placetype":"locality"
},
  "geometry": {"coordinates":[31.00417,38.82833],"type":"Point"}
}