{
  "type": "Feature",
  "properties": {
    "gn:admin1_code":"55.0",
    "gn:asciiname":"Cardak",
    "gn:country_code":"TR",
    "gn:dem":11,
    "gn:feature_class":"P",
    "gn:feature_code":"PPL",
    "gn:name":"\u00c7ardak",
    "gn:population":0,
    "gn:timezone":"Europe/Istanbul",
    "iso:country":"TR",
    "wof:name":"Cardak",
    "wof:placetype":"locality"
},
  "geometry": {"coordinates":[36.92968,41.19904],"type":"Point"}
}