{
  "type": "Feature",
  "properties": {
    "gn:admin1_code":"07",
    "gn:asciiname":"Deniztepesi",
    "gn:country_code":"TR",
    "gn:dem":78,
    "gn:feature_class":"P",
    "gn:feature_code":"PPL",
    "gn:name":"Deniztepesi",
    "gn:population":0,
    "gn:timezone":"Europe/Istanbul",
    "iso:country":"TR",
    "name:und_x_variant":[
        "Deniztepesi K\u00f6y\u00fc",
        "Deniztepesi"
    ],
    "wof:name":"Deniztepesi",
    "wof:placetype":"locality"
},
  "geometry": {"coordinates":[31.12506,36.98084],"type":"Point"}
}