{
  "type": "Feature",
  "properties": {
    "gn:admin1_code":"10",
    "gn:asciiname":"Karadag",
    "gn:country_code":"TR",
    "gn:dem":574,
    "gn:feature_class":"P",
    "gn:feature_code":"PPL",
    "gn:name":"Karada\u011f",
    "gn:population":0,
    "gn:timezone":"Europe/Istanbul",
    "iso:country":"TR",
    "name:ceb_x_preferred":[
        "Karadag"
    ],
    "name:swe_x_preferred":[
        "Karadag"
    ],
    "name:tur_x_preferred":[
        "Karada\u011f"
    ],
    "name:und_x_variant":[
        "L\u00fcleciler"
    ],
    "wof:name":"Karadag",
    "wof:placetype":"locality"
},
  "geometry": {"coordinates":[27.53827,39.84312],"type":"Point"}
}