{
  "type": "Feature",
  "properties": {
    "gn:admin1_code":"83",
    "gn:asciiname":"Yasarkoy",
    "gn:country_code":"TR",
    "gn:dem":405,
    "gn:feature_class":"P",
    "gn:feature_code":"PPL",
    "gn:name":"Ya\u015fark\u00f6y",
    "gn:population":0,
    "gn:timezone":"Europe/Istanbul",
    "iso:country":"TR",
    "name:tur_x_preferred":[
        "Ya\u015fark\u00f6y"
    ],
    "name:tur_x_variant":[
        "Ya\u015far"
    ],
    "name:und_x_variant":[
        "Koyunbad",
        "Koyunbat"
    ],
    "wof:name":"Yasarkoy",
    "wof:placetype":"locality"
},
  "geometry": {"coordinates":[37.94167,36.86972],"type":"Point"}
}