{
  "type": "Feature",
  "properties": {
    "gn:admin1_code":"21",
    "gn:asciiname":"Karakuyu",
    "gn:country_code":"TR",
    "gn:dem":754,
    "gn:feature_class":"P",
    "gn:feature_code":"PPL",
    "gn:name":"Karakuyu",
    "gn:population":0,
    "gn:timezone":"Europe/Istanbul",
    "iso:country":"TR",
    "name:deu_x_preferred":[
        "Karakuyu"
    ],
    "name:tur_x_preferred":[
        "Karakuyu"
    ],
    "wof:name":"Karakuyu",
    "wof:placetype":"locality"
},
  "geometry": {"coordinates":[40.13333,37.91667],"type":"Point"}
}