{
  "type": "Feature",
  "properties": {
    "gn:admin1_code":"37",
    "gn:asciiname":"Seyhkoy",
    "gn:country_code":"TR",
    "gn:dem":1036,
    "gn:feature_class":"P",
    "gn:feature_code":"PPL",
    "gn:name":"\u015eeyhk\u00f6y",
    "gn:population":0,
    "gn:timezone":"Europe/Istanbul",
    "iso:country":"TR",
    "wof:name":"Seyhkoy",
    "wof:placetype":"locality"
},
  "geometry": {"coordinates":[33.75302,41.21612],"type":"Point"}
}