{
  "type": "Feature",
  "properties": {
    "gn:admin1_code":"38",
    "gn:asciiname":"Kahveci",
    "gn:country_code":"TR",
    "gn:dem":1327,
    "gn:feature_class":"P",
    "gn:feature_code":"PPL",
    "gn:name":"Kahveci",
    "gn:population":0,
    "gn:timezone":"Europe/Istanbul",
    "iso:country":"TR",
    "wof:name":"Kahveci",
    "wof:placetype":"locality"
},
  "geometry": {"coordinates":[35.98422,38.91011],"type":"Point"}
}