{
  "type": "Feature",
  "properties": {
    "gn:admin1_code":"65.0",
    "gn:asciiname":"Ulupamir",
    "gn:country_code":"TR",
    "gn:dem":1868,
    "gn:feature_class":"P",
    "gn:feature_code":"PPL",
    "gn:name":"Ulupamir",
    "gn:population":0,
    "gn:timezone":"Europe/Istanbul",
    "iso:country":"TR",
    "name:ceb_x_preferred":[
        "Ulupamir"
    ],
    "name:fra_x_preferred":[
        "Ulupamir"
    ],
    "name:msa_x_preferred":[
        "Ulupamir"
    ],
    "name:tur_x_preferred":[
        "Ulupamir"
    ],
    "name:vie_x_preferred":[
        "Ulupamir"
    ],
    "name:zho_x_preferred":[
        "Ulupamir"
    ],
    "wof:name":"Ulupamir",
    "wof:placetype":"locality"
},
  "geometry": {"coordinates":[43.28429000000001,39.19249],"type":"Point"}
}