{
  "type": "Feature",
  "properties": {
    "gn:admin1_code":"58",
    "gn:asciiname":"Soguksu",
    "gn:country_code":"TR",
    "gn:dem":1505,
    "gn:feature_class":"P",
    "gn:feature_code":"PPL",
    "gn:name":"So\u011fuksu",
    "gn:population":0,
    "gn:timezone":"Europe/Istanbul",
    "iso:country":"TR",
    "name:und_x_variant":[
        "So\u011fuksu",
        "H\u00fcn\u00fc"
    ],
    "wof:name":"Soguksu",
    "wof:placetype":"locality"
},
  "geometry": {"coordinates":[38.54107,39.99274000000001],"type":"Point"}
}