{
  "type": "Feature",
  "properties": {
    "gn:admin1_code":"54",
    "gn:asciiname":"Belpinar",
    "gn:country_code":"TR",
    "gn:dem":759,
    "gn:feature_class":"P",
    "gn:feature_code":"PPL",
    "gn:name":"Belp\u0131nar",
    "gn:population":0,
    "gn:timezone":"Europe/Istanbul",
    "iso:country":"TR",
    "name:tur_x_preferred":[
        "Belp\u0131nar"
    ],
    "wof:name":"Belpinar",
    "wof:placetype":"locality"
},
  "geometry": {"coordinates":[30.49054000000001,40.53793],"type":"Point"}
}