{
  "type": "Feature",
  "properties": {
    "gn:admin1_code":"46",
    "gn:asciiname":"Cobanbeyli",
    "gn:country_code":"TR",
    "gn:dem":1217,
    "gn:feature_class":"P",
    "gn:feature_code":"PPL",
    "gn:name":"\u00c7obanbeyli",
    "gn:population":0,
    "gn:timezone":"Europe/Istanbul",
    "iso:country":"TR",
    "wof:name":"Cobanbeyli",
    "wof:placetype":"locality"
},
  "geometry": {"coordinates":[36.90342,38.31758],"type":"Point"}
}