{
  "type": "Feature",
  "properties": {
    "gn:admin1_code":"21",
    "gn:asciiname":"Asagi Leylegi",
    "gn:cc2":"TR",
    "gn:country_code":"TR",
    "gn:dem":749,
    "gn:feature_class":"P",
    "gn:feature_code":"PPL",
    "gn:name":"A\u015fa\u011f\u0131 Leyle\u011fi",
    "gn:population":0,
    "gn:timezone":"Europe/Istanbul",
    "iso:country":"TR",
    "name:und_x_variant":[
        "Leyle\u011fi",
        "A\u015fa\u011f\u0131le\u011fle\u011fi",
        "A\u015fa\u011f\u0131 Leyle\u011fi"
    ],
    "wof:name":"Asagi Leylegi",
    "wof:placetype":"locality"
},
  "geometry": {"coordinates":[40.05,37.96667],"type":"Point"}
}