{
  "type": "Feature",
  "properties": {
    "gn:admin1_code":"9.0",
    "gn:asciiname":"Agacli",
    "gn:country_code":"TR",
    "gn:dem":204,
    "gn:feature_class":"P",
    "gn:feature_code":"PPL",
    "gn:name":"A\u011fa\u00e7l\u0131",
    "gn:population":0,
    "gn:timezone":"Europe/Istanbul",
    "iso:country":"TR",
    "name:tur_x_preferred":[
        "A\u011fa\u00e7l\u0131"
    ],
    "wof:name":"Agacli",
    "wof:placetype":"locality"
},
  "geometry": {"coordinates":[27.34037,37.73874],"type":"Point"}
}