{
  "type": "Feature",
  "properties": {
    "gn:admin1_code":"28.0",
    "gn:asciiname":"Yumrucaktas",
    "gn:country_code":"TR",
    "gn:dem":1116,
    "gn:feature_class":"P",
    "gn:feature_code":"PPL",
    "gn:name":"Yumrucakta\u015f",
    "gn:population":0,
    "gn:timezone":"Europe/Istanbul",
    "iso:country":"TR",
    "name:tur_x_preferred":[
        "Yumrucakta\u015f"
    ],
    "name:und_x_variant":[
        "Yumru\u00e7akta\u015f"
    ],
    "wof:name":"Yumrucaktas",
    "wof:placetype":"locality"
},
  "geometry": {"coordinates":[38.21229,40.22326],"type":"Point"}
}