{
  "type": "Feature",
  "properties": {
    "gn:admin1_code":"35",
    "gn:asciiname":"Kuskut",
    "gn:country_code":"TR",
    "gn:dem":112,
    "gn:feature_class":"P",
    "gn:feature_code":"PPL",
    "gn:name":"K\u00fcsk\u00fct",
    "gn:population":0,
    "gn:timezone":"Europe/Istanbul",
    "iso:country":"TR",
    "name:tur_x_preferred":[
        "K\u00fcsk\u00fct"
    ],
    "wof:name":"Kuskut",
    "wof:placetype":"locality"
},
  "geometry": {"coordinates":[27.85922,38.20483],"type":"Point"}
}