{
  "type": "Feature",
  "properties": {
    "gn:admin1_code":"12",
    "gn:asciiname":"Kesan",
    "gn:country_code":"TR",
    "gn:dem":1871,
    "gn:feature_class":"P",
    "gn:feature_code":"PPL",
    "gn:name":"Kesan",
    "gn:population":0,
    "gn:timezone":"Europe/Istanbul",
    "iso:country":"TR",
    "name:und_x_variant":[
        "K\u00e2san"
    ],
    "wof:name":"Kesan",
    "wof:placetype":"locality"
},
  "geometry": {"coordinates":[40.16667,38.61667],"type":"Point"}
}