{
  "type": "Feature",
  "properties": {
    "gn:admin1_code":"62",
    "gn:asciiname":"Kayaci",
    "gn:country_code":"TR",
    "gn:dem":991,
    "gn:feature_class":"P",
    "gn:feature_code":"PPL",
    "gn:name":"Kayac\u0131",
    "gn:population":0,
    "gn:timezone":"Europe/Istanbul",
    "iso:country":"TR",
    "name:tur_x_preferred":[
        "Kayac\u0131"
    ],
    "wof:name":"Kayaci",
    "wof:placetype":"locality"
},
  "geometry": {"coordinates":[39.80274,38.88934],"type":"Point"}
}