{
  "type": "Feature",
  "properties": {
    "gn:admin1_code":"80.0",
    "gn:asciiname":"Berezan",
    "gn:country_code":"TR",
    "gn:dem":1139,
    "gn:feature_class":"P",
    "gn:feature_code":"PPL",
    "gn:name":"Berezan",
    "gn:population":0,
    "gn:timezone":"Europe/Istanbul",
    "iso:country":"TR",
    "name:bel_x_preferred":[
        "\u0411\u0435\u0440\u0430\u0437\u0430\u043d\u044c"
    ],
    "name:deu_x_preferred":[
        "Berezan"
    ],
    "name:ita_x_preferred":[
        "Berezan'"
    ],
    "name:rus_x_preferred":[
        "\u0411\u0435\u0440\u0435\u0437\u0430\u043d\u044c"
    ],
    "name:spa_x_preferred":[
        "Berezan"
    ],
    "name:tat_x_preferred":[
        "\u0411\u0435\u0440\u0435\u0437\u0430\u043d\u044c"
    ],
    "name:tur_x_preferred":[
        "Berezan"
    ],
    "name:ukr_x_preferred":[
        "\u0411\u0435\u0440\u0435\u0437\u0430\u043d\u044c"
    ],
    "wof:name":"Berezan",
    "wof:placetype":"locality"
},
  "geometry": {"coordinates":[42.56972,37.53194000000001],"type":"Point"}
}