{
  "type": "Feature",
  "properties": {
    "gn:admin1_code":"16",
    "gn:asciiname":"Alacaat",
    "gn:country_code":"TR",
    "gn:dem":607,
    "gn:feature_class":"P",
    "gn:feature_code":"PPL",
    "gn:name":"Alacaat",
    "gn:population":0,
    "gn:timezone":"Europe/Istanbul",
    "iso:country":"TR",
    "name:tur_x_preferred":[
        "Alacaat"
    ],
    "wof:name":"Alacaat",
    "wof:placetype":"locality"
},
  "geometry": {"coordinates":[28.6575,39.82139],"type":"Point"}
}