{
  "type": "Feature",
  "properties": {
    "gn:admin1_code":"91.0",
    "gn:asciiname":"Kinkli",
    "gn:country_code":"TR",
    "gn:dem":606,
    "gn:feature_class":"P",
    "gn:feature_code":"PPL",
    "gn:name":"K\u0131nkl\u0131",
    "gn:population":0,
    "gn:timezone":"Europe/Istanbul",
    "iso:country":"TR",
    "wof:name":"Kinkli",
    "wof:placetype":"locality"
},
  "geometry": {"coordinates":[36.42911,37.1406],"type":"Point"}
}