{
  "type": "Feature",
  "properties": {
    "gn:admin1_code":"44",
    "gn:asciiname":"Bag",
    "gn:country_code":"TR",
    "gn:dem":1570,
    "gn:feature_class":"P",
    "gn:feature_code":"PPL",
    "gn:name":"Ba\u011f",
    "gn:population":0,
    "gn:timezone":"Europe/Istanbul",
    "iso:country":"TR",
    "name:und_x_variant":[
        "Sarsi",
        "Servi",
        "Ba\u011f"
    ],
    "wof:name":"Bag",
    "wof:placetype":"locality"
},
  "geometry": {"coordinates":[38.31378,38.17441],"type":"Point"}
}