{
  "type": "Feature",
  "properties": {
    "gn:admin1_code":"44",
    "gn:asciiname":"Bag",
    "gn:country_code":"TR",
    "gn:dem":1570,
    "gn:feature_class":"P",
    "gn:feature_code":"PPL",
    "gn:name":"Ba\u011f",
    "gn:population":0,
    "gn:timezone":"Europe/Istanbul",
    "iso:country":"TR",
    "name:ara_x_preferred":[
        "\u062d\u0642\u064a\u0628\u0629"
    ],
    "name:arz_x_preferred":[
        "\u0634\u0646\u0637\u0647"
    ],
    "name:aze_x_preferred":[
        "Kis\u0259"
    ],
    "name:bjn_x_preferred":[
        "Kampil"
    ],
    "name:bre_x_preferred":[
        "Sac'h"
    ],
    "name:dan_x_preferred":[
        "Pose"
    ],
    "name:deu_x_preferred":[
        "Beutel"
    ],
    "name:epo_x_preferred":[
        "Sako"
    ],
    "name:fas_x_preferred":[
        "\u06a9\u06cc\u0641"
    ],
    "name:fin_x_preferred":[
        "Laukku"
    ],
    "name:fra_x_preferred":[
        "Sac"
    ],
    "name:gle_x_preferred":[
        "M\u00e1la"
    ],
    "name:grn_x_preferred":[
        "Vosa"
    ],
    "name:hat_x_preferred":[
        "Sak"
    ],
    "name:heb_x_preferred":[
        "\u05e9\u05e7\u05d9\u05ea"
    ],
    "name:hin_x_preferred":[
        "\u0925\u0948\u0932\u093e"
    ],
    "name:ind_x_preferred":[
        "Tas"
    ],
    "name:isl_x_preferred":[
        "Poki"
    ],
    "name:ita_x_preferred":[
        "Borsa"
    ],
    "name:jav_x_preferred":[
        "Tas"
    ],
    "name:kan_x_preferred":[
        "\u0c9a\u0cc0\u0cb2"
    ],
    "name:lit_x_preferred":[
        "Mai\u0161as"
    ],
    "name:mal_x_preferred":[
        "\u0d38\u0d1e\u0d4d\u0d1a\u0d3f"
    ],
    "name:nep_x_preferred":[
        "\u091d\u094b\u0932\u093e"
    ],
    "name:nld_x_preferred":[
        "Tas"
    ],
    "name:nno_x_preferred":[
        "Veske"
    ],
    "name:nrm_x_preferred":[
        "Pouque"
    ],
    "name:pol_x_preferred":[
        "Torba"
    ],
    "name:que_x_preferred":[
        "Wayaqa"
    ],
    "name:rus_x_preferred":[
        "\u041c\u0435\u0448\u043e\u043a"
    ],
    "name:scn_x_preferred":[
        "Saccu"
    ],
    "name:sco_x_preferred":[
        "Poke"
    ],
    "name:slk_x_preferred":[
        "Ta\u0161ka"
    ],
    "name:snd_x_preferred":[
        "\u067f\u064a\u0644\u06be\u0648"
    ],
    "name:spa_x_preferred":[
        "Bolsa"
    ],
    "name:srp_x_preferred":[
        "\u0422\u043e\u0440\u0431\u0430"
    ],
    "name:sun_x_preferred":[
        "Kantong"
    ],
    "name:swa_x_preferred":[
        "Begi"
    ],
    "name:tel_x_preferred":[
        "\u0c38\u0c02\u0c1a\u0c3f"
    ],
    "name:tha_x_preferred":[
        "\u0e16\u0e38\u0e07"
    ],
    "name:ukr_x_preferred":[
        "\u041c\u0456\u0448\u043e\u043a"
    ],
    "name:und_x_variant":[
        "Sarsi",
        "Servi",
        "Ba\u011f"
    ],
    "name:vec_x_preferred":[
        "Sporta"
    ],
    "name:yid_x_preferred":[
        "\u05d6\u05e2\u05e7\u05dc"
    ],
    "wof:name":"Bag",
    "wof:placetype":"locality"
},
  "geometry": {"coordinates":[38.31378,38.17441],"type":"Point"}
}