{
  "type": "Feature",
  "properties": {
    "gn:country":"TR",
    "gn:fcode":"PPL",
    "gn:population":415,
    "iso:country":"TR",
    "name:ceb_x_preferred":[
        "Mente\u015fe"
    ],
    "name:deu_x_preferred":[
        "Mente\u015fe"
    ],
    "name:tur_x_preferred":[
        "Mente\u015fe"
    ],
    "name:und_x_variant":[
        "Menteshe"
    ],
    "qs:name":"Mente\u015fe",
    "qs:photos_9r":0,
    "qs:photos_sr":0,
    "qs:pop_sr":"2",
    "wd:wordcount":61,
    "wof:name":"Mente\u015fe",
    "wof:placetype":"locality",
    "wof:population":415
},
  "geometry": {"coordinates":[29.525,40.28194],"type":"Point"}
}