{
  "type": "Feature",
  "properties": {
    "gn:admin1_code":"37.0",
    "gn:asciiname":"Burnuk",
    "gn:country_code":"TR",
    "gn:dem":1147,
    "gn:feature_class":"P",
    "gn:feature_code":"PPL",
    "gn:name":"B\u00fcrn\u00fck",
    "gn:population":0,
    "gn:timezone":"Europe/Istanbul",
    "iso:country":"TR",
    "wof:name":"Burnuk",
    "wof:placetype":"locality"
},
  "geometry": {"coordinates":[34.45118,41.70628],"type":"Point"}
}