{
  "type": "Feature",
  "properties": {
    "gn:admin1_code":"81.0",
    "gn:asciiname":"Kesosen",
    "gn:country_code":"TR",
    "gn:dem":489,
    "gn:feature_class":"P",
    "gn:feature_code":"PPL",
    "gn:name":"Kes\u00f6sen",
    "gn:population":0,
    "gn:timezone":"Europe/Istanbul",
    "iso:country":"TR",
    "wof:name":"Kesosen",
    "wof:placetype":"locality"
},
  "geometry": {"coordinates":[35.17975999999999,37.38316],"type":"Point"}
}