{
  "type": "Feature",
  "properties": {
    "gn:admin1_code":"88",
    "gn:asciiname":"Karacomak",
    "gn:country_code":"TR",
    "gn:dem":2070,
    "gn:feature_class":"P",
    "gn:feature_code":"PPL",
    "gn:name":"Kara\u00e7omak",
    "gn:population":0,
    "gn:timezone":"Europe/Istanbul",
    "iso:country":"TR",
    "name:und_x_variant":[
        "Zor",
        "Kara\u00e7omak"
    ],
    "wof:name":"Karacomak",
    "wof:placetype":"locality"
},
  "geometry": {"coordinates":[43.92889,39.77806],"type":"Point"}
}