{
  "type": "Feature",
  "properties": {
    "gn:admin1_code":"31",
    "gn:asciiname":"Asagioba",
    "gn:country_code":"TR",
    "gn:dem":87,
    "gn:feature_class":"P",
    "gn:feature_code":"PPL",
    "gn:name":"A\u015fa\u011f\u0131oba",
    "gn:population":0,
    "gn:timezone":"Europe/Istanbul",
    "iso:country":"TR",
    "name:tur_x_preferred":[
        "A\u015fa\u011f\u0131oba"
    ],
    "wof:name":"Asagioba",
    "wof:placetype":"locality"
},
  "geometry": {"coordinates":[36.25164,36.36146],"type":"Point"}
}