{
  "type": "Feature",
  "properties": {
    "gn:admin1_code":"09",
    "gn:asciiname":"Hasancilar",
    "gn:country_code":"TR",
    "gn:dem":503,
    "gn:feature_class":"P",
    "gn:feature_code":"PPL",
    "gn:name":"Hasanc\u0131lar",
    "gn:population":0,
    "gn:timezone":"Europe/Istanbul",
    "iso:country":"TR",
    "name:tur_x_preferred":[
        "Hasanc\u0131lar"
    ],
    "name:tur_x_variant":[
        "Hasanlar"
    ],
    "wof:name":"Hasancilar",
    "wof:placetype":"locality"
},
  "geometry": {"coordinates":[27.8359,37.68951],"type":"Point"}
}