{
  "type": "Feature",
  "properties": {
    "gn:admin1_code":"83.0",
    "gn:asciiname":"Eskikoyyari",
    "gn:country_code":"TR",
    "gn:dem":496,
    "gn:feature_class":"P",
    "gn:feature_code":"PPL",
    "gn:name":"Eskikoyyari",
    "gn:population":0,
    "gn:timezone":"Europe/Istanbul",
    "iso:country":"TR",
    "wof:name":"Eskikoyyari",
    "wof:placetype":"locality"
},
  "geometry": {"coordinates":[36.62444,36.98389],"type":"Point"}
}