{
  "type": "Feature",
  "properties": {
    "gn:admin1_code":"60.0",
    "gn:asciiname":"Meydanduzu",
    "gn:country_code":"TR",
    "gn:dem":1036,
    "gn:feature_class":"P",
    "gn:feature_code":"PPL",
    "gn:name":"Meydand\u00fcz\u00fc",
    "gn:population":0,
    "gn:timezone":"Europe/Istanbul",
    "iso:country":"TR",
    "wof:name":"Meydanduzu",
    "wof:placetype":"locality"
},
  "geometry": {"coordinates":[36.51722,40.58836],"type":"Point"}
}