{
  "type": "Feature",
  "properties": {
    "gn:admin1_code":"11",
    "gn:asciiname":"Karakoy",
    "gn:country_code":"TR",
    "gn:dem":662,
    "gn:feature_class":"P",
    "gn:feature_code":"PPL",
    "gn:name":"Karak\u00f6y",
    "gn:population":0,
    "gn:timezone":"Europe/Istanbul",
    "iso:country":"TR",
    "name:und_x_variant":[
        "Kerak\u00f6y",
        "Karak\u00f6y"
    ],
    "wof:name":"Karakoy",
    "wof:placetype":"locality"
},
  "geometry": {"coordinates":[30.00148,39.97779],"type":"Point"}
}