{
  "type": "Feature",
  "properties": {
    "gn:admin1_code":"89",
    "gn:asciiname":"Halamoglu",
    "gn:country_code":"TR",
    "gn:dem":489,
    "gn:feature_class":"P",
    "gn:feature_code":"PPL",
    "gn:name":"Halamo\u011flu",
    "gn:population":0,
    "gn:timezone":"Europe/Istanbul",
    "iso:country":"TR",
    "wof:name":"Halamoglu",
    "wof:placetype":"locality"
},
  "geometry": {"coordinates":[32.24279,41.2473],"type":"Point"}
}