{
  "type": "Feature",
  "properties": {
    "gn:admin1_code":"16.0",
    "gn:asciiname":"Karabahadir",
    "gn:country_code":"TR",
    "gn:dem":300,
    "gn:feature_class":"P",
    "gn:feature_code":"PPL",
    "gn:name":"Karabahad\u0131r",
    "gn:population":0,
    "gn:timezone":"Europe/Istanbul",
    "iso:country":"TR",
    "name:tur_x_preferred":[
        "Karabahad\u0131r"
    ],
    "wof:name":"Karabahadir",
    "wof:placetype":"locality"
},
  "geometry": {"coordinates":[29.69955,40.29478],"type":"Point"}
}