{
  "type": "Feature",
  "properties": {
    "gn:admin1_code":"31.0",
    "gn:asciiname":"Yukaribucak",
    "gn:country_code":"TR",
    "gn:dem":583,
    "gn:feature_class":"P",
    "gn:feature_code":"PPL",
    "gn:name":"Yukar\u0131bucak",
    "gn:population":0,
    "gn:timezone":"Europe/Istanbul",
    "iso:country":"TR",
    "name:tur_x_preferred":[
        "Yukar\u0131bucak"
    ],
    "name:tur_x_variant":[
        "Yukar\u0131 Bucak"
    ],
    "wof:name":"Yukaribucak",
    "wof:placetype":"locality"
},
  "geometry": {"coordinates":[36.45958,36.74416],"type":"Point"}
}