{
  "type": "Feature",
  "properties": {
    "gn:admin1_code":"68.0",
    "gn:asciiname":"Karahisar Yaylasi",
    "gn:country_code":"TR",
    "gn:dem":450,
    "gn:feature_class":"P",
    "gn:feature_code":"PPL",
    "gn:name":"Karahisar Yaylas\u0131",
    "gn:population":0,
    "gn:timezone":"Europe/Istanbul",
    "iso:country":"TR",
    "name:und_x_variant":[
        "Karahisar Yaylas\u0131",
        "Karahisarkad\u0131"
    ],
    "wof:name":"Karahisar Yaylasi",
    "wof:placetype":"locality"
},
  "geometry": {"coordinates":[31.30917,40.09165],"type":"Point"}
}