{
  "type": "Feature",
  "properties": {
    "gn:admin1_code":"09",
    "gn:asciiname":"Bayirdami",
    "gn:country_code":"TR",
    "gn:dem":438,
    "gn:feature_class":"P",
    "gn:feature_code":"PPL",
    "gn:name":"Bay\u0131rdam\u0131",
    "gn:population":0,
    "gn:timezone":"Europe/Istanbul",
    "iso:country":"TR",
    "name:tur_x_preferred":[
        "Bay\u0131rdam\u0131"
    ],
    "wof:name":"Bayirdami",
    "wof:placetype":"locality"
},
  "geometry": {"coordinates":[27.55925,37.66968],"type":"Point"}
}