{
  "type": "Feature",
  "properties": {
    "gn:admin1_code":"60.0",
    "gn:asciiname":"Cakir",
    "gn:country_code":"TR",
    "gn:dem":513,
    "gn:feature_class":"P",
    "gn:feature_code":"PPL",
    "gn:name":"\u00c7ak\u0131r",
    "gn:population":0,
    "gn:timezone":"Europe/Istanbul",
    "iso:country":"TR",
    "wof:name":"Cakir",
    "wof:placetype":"locality"
},
  "geometry": {"coordinates":[36.65904000000001,40.62677],"type":"Point"}
}