{
  "type": "Feature",
  "properties": {
    "gn:admin1_code":"8.0",
    "gn:asciiname":"Avcilar",
    "gn:country_code":"TR",
    "gn:dem":1180,
    "gn:feature_class":"P",
    "gn:feature_code":"PPL",
    "gn:name":"Avc\u0131lar",
    "gn:population":0,
    "gn:timezone":"Europe/Istanbul",
    "iso:country":"TR",
    "name:tur_x_preferred":[
        "Avc\u0131lar"
    ],
    "wof:name":"Avcilar",
    "wof:placetype":"locality"
},
  "geometry": {"coordinates":[41.97594,41.12765],"type":"Point"}
}