{
  "type": "Feature",
  "properties": {
    "gn:admin1_code":"21",
    "gn:asciiname":"Darbi",
    "gn:country_code":"TR",
    "gn:dem":1150,
    "gn:feature_class":"P",
    "gn:feature_code":"PPL",
    "gn:name":"Darbi",
    "gn:population":0,
    "gn:timezone":"Europe/Istanbul",
    "iso:country":"TR",
    "name:und_x_variant":[
        "Dahleizol",
        "Darbi",
        "Dahleizole"
    ],
    "wof:name":"Darbi",
    "wof:placetype":"locality"
},
  "geometry": {"coordinates":[39.92459,37.77378],"type":"Point"}
}