{
  "type": "Feature",
  "properties": {
    "gn:admin1_code":"69.0",
    "gn:asciiname":"Subasi",
    "gn:country_code":"TR",
    "gn:dem":1859,
    "gn:feature_class":"P",
    "gn:feature_code":"PPL",
    "gn:name":"Suba\u015f\u0131",
    "gn:population":0,
    "gn:timezone":"Europe/Istanbul",
    "iso:country":"TR",
    "name:und_x_variant":[
        "T\u0131z\u0131k",
        "Suba\u015f\u0131"
    ],
    "wof:name":"Subasi",
    "wof:placetype":"locality"
},
  "geometry": {"coordinates":[39.57428,40.26332],"type":"Point"}
}