{
  "type": "Feature",
  "properties": {
    "gn:admin1_code":"83.0",
    "gn:asciiname":"Serince",
    "gn:cc2":"TR",
    "gn:country_code":"TR",
    "gn:dem":927,
    "gn:feature_class":"P",
    "gn:feature_code":"PPL",
    "gn:name":"Serince",
    "gn:population":0,
    "gn:timezone":"Europe/Istanbul",
    "iso:country":"TR",
    "name:und_x_variant":[
        "Zemge",
        "Serince"
    ],
    "wof:name":"Serince",
    "wof:placetype":"locality"
},
  "geometry": {"coordinates":[37.25389000000001,36.99722],"type":"Point"}
}