{
  "type": "Feature",
  "properties": {
    "gn:admin1_code":"52.0",
    "gn:asciiname":"Alacalar",
    "gn:country_code":"TR",
    "gn:dem":1017,
    "gn:feature_class":"P",
    "gn:feature_code":"PPL",
    "gn:name":"Alacalar",
    "gn:population":0,
    "gn:timezone":"Europe/Istanbul",
    "iso:country":"TR",
    "wof:name":"Alacalar",
    "wof:placetype":"locality"
},
  "geometry": {"coordinates":[37.4484,40.68564],"type":"Point"}
}