{
  "type": "Feature",
  "properties": {
    "gn:admin1_code":"53.0",
    "gn:asciiname":"Dulgerli",
    "gn:country_code":"TR",
    "gn:dem":257,
    "gn:feature_class":"P",
    "gn:feature_code":"PPL",
    "gn:name":"D\u00fclgerli",
    "gn:population":0,
    "gn:timezone":"Europe/Istanbul",
    "iso:country":"TR",
    "name:tur_x_preferred":[
        "D\u00fclgerli"
    ],
    "wof:name":"Dulgerli",
    "wof:placetype":"locality"
},
  "geometry": {"coordinates":[40.46516,40.91296],"type":"Point"}
}