{
  "type": "Feature",
  "properties": {
    "gn:admin1_code":"78",
    "gn:asciiname":"Kozlubucak",
    "gn:country_code":"TR",
    "gn:dem":1380,
    "gn:feature_class":"P",
    "gn:feature_code":"PPL",
    "gn:name":"Kozlubucak",
    "gn:population":0,
    "gn:timezone":"Europe/Istanbul",
    "iso:country":"TR",
    "name:tur_x_preferred":[
        "Kozlubucak"
    ],
    "wof:name":"Kozlubucak",
    "wof:placetype":"locality"
},
  "geometry": {"coordinates":[33.26563,36.99301],"type":"Point"}
}