{
  "type": "Feature",
  "properties": {
    "gn:admin1_code":"16",
    "gn:asciiname":"Balaban",
    "gn:country_code":"TR",
    "gn:dem":744,
    "gn:feature_class":"P",
    "gn:feature_code":"PPL",
    "gn:name":"Balaban",
    "gn:population":0,
    "gn:timezone":"Europe/Istanbul",
    "iso:country":"TR",
    "name:tur_x_preferred":[
        "Balaban"
    ],
    "wof:name":"Balaban",
    "wof:placetype":"locality"
},
  "geometry": {"coordinates":[28.93391,39.76618],"type":"Point"}
}