{
  "type": "Feature",
  "properties": {
    "gn:admin1_code":"39.0",
    "gn:asciiname":"Derekoy",
    "gn:country_code":"TR",
    "gn:dem":490,
    "gn:feature_class":"P",
    "gn:feature_code":"PPLA3",
    "gn:name":"Derek\u00f6y",
    "gn:population":0,
    "gn:timezone":"Europe/Istanbul",
    "iso:country":"TR",
    "name:bul_x_preferred":[
        "\u0414\u0435\u0440\u0435\u043a\u044c\u043e\u0439"
    ],
    "name:ceb_x_preferred":[
        "Derek\u00f6y"
    ],
    "name:deu_x_preferred":[
        "Derek\u00f6y"
    ],
    "name:fas_x_preferred":[
        "\u062f\u0631\u0647\u200c\u06a9\u0648\u06cc"
    ],
    "name:msa_x_preferred":[
        "Derek\u00f6y"
    ],
    "name:tur_x_preferred":[
        "Derek\u00f6y"
    ],
    "name:und_x_variant":[
        "Derek\u00f6y"
    ],
    "name:vie_x_preferred":[
        "Derek\u00f6y"
    ],
    "wof:name":"Derekoy",
    "wof:placetype":"locality"
},
  "geometry": {"coordinates":[27.37052000000001,41.93008],"type":"Point"}
}