{
  "type": "Feature",
  "properties": {
    "gn:admin1_code":"43.0",
    "gn:asciiname":"Agackoy",
    "gn:country_code":"TR",
    "gn:dem":1167,
    "gn:feature_class":"P",
    "gn:feature_code":"PPL",
    "gn:name":"A\u011fa\u00e7k\u00f6y",
    "gn:population":0,
    "gn:timezone":"Europe/Istanbul",
    "iso:country":"TR",
    "name:tur_x_preferred":[
        "A\u011fa\u00e7"
    ],
    "name:und_x_variant":[
        "A\u011fa\u00e7k\u00f6y"
    ],
    "wof:name":"Agackoy",
    "wof:placetype":"locality"
},
  "geometry": {"coordinates":[29.97833,38.90667],"type":"Point"}
}