{
  "type": "Feature",
  "properties": {
    "gn:admin1_code":"75",
    "gn:asciiname":"Hacimahmutusagi",
    "gn:country_code":"TR",
    "gn:dem":1365,
    "gn:feature_class":"P",
    "gn:feature_code":"PPL",
    "gn:name":"Hac\u0131mahmutu\u015fa\u011f\u0131",
    "gn:population":0,
    "gn:timezone":"Europe/Istanbul",
    "iso:country":"TR",
    "name:msa_x_preferred":[
        "Hac\u0131mahmutu\u015fa\u011f\u0131"
    ],
    "name:tur_x_preferred":[
        "Hac\u0131mahmutu\u015fa\u011f\u0131"
    ],
    "name:und_x_variant":[
        "Hac\u0131mahmutu\u015fa\u011f\u0131"
    ],
    "name:vie_x_preferred":[
        "Hac\u0131mahmutu\u015fa\u011f\u0131"
    ],
    "wof:name":"Hacimahmutusagi",
    "wof:placetype":"locality"
},
  "geometry": {"coordinates":[33.94351,38.72924],"type":"Point"}
}