{
  "type": "Feature",
  "properties": {
    "gn:admin1_code":"31.0",
    "gn:asciiname":"Tulek",
    "gn:country_code":"TR",
    "gn:dem":54,
    "gn:feature_class":"P",
    "gn:feature_code":"PPL",
    "gn:name":"T\u00fclek",
    "gn:population":0,
    "gn:timezone":"Europe/Istanbul",
    "iso:country":"TR",
    "name:tur_x_preferred":[
        "T\u00fclek"
    ],
    "wof:name":"Tulek",
    "wof:placetype":"locality"
},
  "geometry": {"coordinates":[35.85478,36.35216],"type":"Point"}
}