{
  "type": "Feature",
  "properties": {
    "gn:admin1_code":"07",
    "gn:asciiname":"Esenyurt",
    "gn:country_code":"TR",
    "gn:dem":865,
    "gn:feature_class":"P",
    "gn:feature_code":"PPL",
    "gn:name":"Esenyurt",
    "gn:population":0,
    "gn:timezone":"Europe/Istanbul",
    "iso:country":"TR",
    "name:und_x_variant":[
        "Karadin"
    ],
    "wof:name":"Esenyurt",
    "wof:placetype":"locality"
},
  "geometry": {"coordinates":[30.34339000000001,37.05668],"type":"Point"}
}