{
  "type": "Feature",
  "properties": {
    "gn:admin1_code":"07",
    "gn:asciiname":"Esenyurt",
    "gn:country_code":"TR",
    "gn:dem":865,
    "gn:feature_class":"P",
    "gn:feature_code":"PPL",
    "gn:name":"Esenyurt",
    "gn:population":0,
    "gn:timezone":"Europe/Istanbul",
    "iso:country":"TR",
    "name:ara_x_preferred":[
        "\u0627\u0633\u0646 \u064a\u0648\u0631\u062a"
    ],
    "name:bre_x_preferred":[
        "Esenyurt"
    ],
    "name:cat_x_preferred":[
        "Esenyurt"
    ],
    "name:ceb_x_preferred":[
        "Esenyurt"
    ],
    "name:dan_x_preferred":[
        "Esenyurt"
    ],
    "name:deu_x_preferred":[
        "Esenyurt"
    ],
    "name:diq_x_preferred":[
        "Esenyurt"
    ],
    "name:ell_x_preferred":[
        "\u0395\u03c3\u03b5\u03bd\u03b3\u03b9\u03bf\u03cd\u03c1\u03c4"
    ],
    "name:fas_x_preferred":[
        "\u0627\u0633\u0646 \u06cc\u0648\u0631\u062a"
    ],
    "name:fra_x_preferred":[
        "Esenyurt"
    ],
    "name:hun_x_preferred":[
        "Esenyurt"
    ],
    "name:hye_x_preferred":[
        "\u0537\u057d\u0565\u0576\u0575\u0578\u0582\u0580\u0569"
    ],
    "name:ita_x_preferred":[
        "Esenyurt"
    ],
    "name:lit_x_preferred":[
        "Esenjurtas"
    ],
    "name:min_x_preferred":[
        "Esenyurt"
    ],
    "name:mrj_x_preferred":[
        "\u042d\u0441\u0435\u043d\u044c\u044e\u0440\u0442"
    ],
    "name:msa_x_preferred":[
        "Esenyurt"
    ],
    "name:nld_x_preferred":[
        "Esenyurt"
    ],
    "name:nor_x_preferred":[
        "Esenyurt"
    ],
    "name:pnb_x_preferred":[
        "\u0627\u0633\u0646\u06cc\u0631\u062a"
    ],
    "name:pol_x_preferred":[
        "Esenyurt"
    ],
    "name:por_x_preferred":[
        "Esenyurt"
    ],
    "name:rus_x_preferred":[
        "\u042d\u0441\u0435\u043d\u044c\u044e\u0440\u0442"
    ],
    "name:sco_x_preferred":[
        "Esenyurt"
    ],
    "name:spa_x_preferred":[
        "Esenyurt"
    ],
    "name:srp_x_preferred":[
        "\u0415\u0441\u0435\u043d\u0458\u0443\u0440\u0442"
    ],
    "name:swa_x_preferred":[
        "Esenyurt"
    ],
    "name:swe_x_preferred":[
        "Esenyurt"
    ],
    "name:tur_x_preferred":[
        "Esenyurt"
    ],
    "name:und_x_variant":[
        "Karadin"
    ],
    "name:urd_x_preferred":[
        "\u0627\u0633\u0646\u06cc\u0648\u0631\u062a"
    ],
    "name:vie_x_preferred":[
        "Esenyurt"
    ],
    "wof:name":"Esenyurt",
    "wof:placetype":"locality"
},
  "geometry": {"coordinates":[30.34339000000001,37.05668],"type":"Point"}
}