{
  "type": "Feature",
  "properties": {
    "gn:country":"TR",
    "gn:fcode":"PPL",
    "gn:population":140,
    "iso:country":"TR",
    "name:rus_x_preferred":[
        "Ch\u00eblkey"
    ],
    "name:und_x_variant":[
        "G\u00f6lk\u00f6y"
    ],
    "qs:name":"\u00c7\u00f6l",
    "qs:photos_9r":0,
    "qs:photos_sr":0,
    "qs:pop_sr":"1",
    "wof:name":"\u00c7\u00f6l",
    "wof:placetype":"locality",
    "wof:population":140
},
  "geometry": {"coordinates":[42.06972,37.8675],"type":"Point"}
}