{
  "type": "Feature",
  "properties": {
    "gn:admin1_code":"24",
    "gn:asciiname":"Dolayli",
    "gn:country_code":"TR",
    "gn:dem":1399,
    "gn:feature_class":"P",
    "gn:feature_code":"PPL",
    "gn:name":"Dolayl\u0131",
    "gn:population":0,
    "gn:timezone":"Europe/Istanbul",
    "iso:country":"TR",
    "name:und_x_variant":[
        "Alacahan Mezraas\u0131",
        "Alacahan",
        "Dolayl\u0131"
    ],
    "wof:name":"Dolayli",
    "wof:placetype":"locality"
},
  "geometry": {"coordinates":[38.80259,39.98391],"type":"Point"}
}