{
  "type": "Feature",
  "properties": {
    "gn:admin1_code":"14.0",
    "gn:asciiname":"Bunus",
    "gn:country_code":"TR",
    "gn:dem":835,
    "gn:feature_class":"P",
    "gn:feature_code":"PPL",
    "gn:name":"B\u00fcn\u00fc\u015f",
    "gn:population":0,
    "gn:timezone":"Europe/Istanbul",
    "iso:country":"TR",
    "name:und_x_variant":[
        "G\u00fcm\u00fc\u015f",
        "B\u00fcn\u00fc\u015f"
    ],
    "wof:name":"Bunus",
    "wof:placetype":"locality"
},
  "geometry": {"coordinates":[31.88347000000001,40.77667],"type":"Point"}
}