{
  "type": "Feature",
  "properties": {
    "gn:admin1_code":"14.0",
    "gn:asciiname":"Bunus",
    "gn:country_code":"TR",
    "gn:dem":835,
    "gn:feature_class":"P",
    "gn:feature_code":"PPL",
    "gn:name":"B\u00fcn\u00fc\u015f",
    "gn:population":0,
    "gn:timezone":"Europe/Istanbul",
    "iso:country":"TR",
    "name:arg_x_preferred":[
        "Bunuze"
    ],
    "name:bre_x_preferred":[
        "Bunuze"
    ],
    "name:cat_x_preferred":[
        "Bunuze"
    ],
    "name:ceb_x_preferred":[
        "Bunus"
    ],
    "name:deu_x_preferred":[
        "Bunus"
    ],
    "name:eus_x_preferred":[
        "Bunuze"
    ],
    "name:fra_x_preferred":[
        "Bunus"
    ],
    "name:hun_x_preferred":[
        "Bunus"
    ],
    "name:ita_x_preferred":[
        "Bunus"
    ],
    "name:kaz_x_preferred":[
        "\u0411\u044e\u043d\u044e\u0441"
    ],
    "name:lat_x_preferred":[
        "Bunus"
    ],
    "name:mlg_x_preferred":[
        "Bunus"
    ],
    "name:msa_x_preferred":[
        "Bunus"
    ],
    "name:nld_x_preferred":[
        "Bunus"
    ],
    "name:oci_x_preferred":[
        "Bunuze"
    ],
    "name:pms_x_preferred":[
        "Bunus"
    ],
    "name:pol_x_preferred":[
        "Bunus"
    ],
    "name:por_x_preferred":[
        "Bunus"
    ],
    "name:ron_x_preferred":[
        "Bunus"
    ],
    "name:rus_x_preferred":[
        "\u0411\u044e\u043d\u044e\u0441"
    ],
    "name:slk_x_preferred":[
        "Bunus"
    ],
    "name:spa_x_preferred":[
        "Bunus"
    ],
    "name:srp_x_preferred":[
        "\u0411\u0438\u043d\u0438"
    ],
    "name:swe_x_preferred":[
        "Bunus"
    ],
    "name:ukr_x_preferred":[
        "\u0411\u044e\u043d\u044e\u0441"
    ],
    "name:und_x_variant":[
        "G\u00fcm\u00fc\u015f",
        "B\u00fcn\u00fc\u015f"
    ],
    "name:uzb_x_preferred":[
        "Bunus"
    ],
    "name:vie_x_preferred":[
        "Bunus"
    ],
    "name:vol_x_preferred":[
        "Bunus"
    ],
    "name:war_x_preferred":[
        "Bunus"
    ],
    "wof:name":"Bunus",
    "wof:placetype":"locality"
},
  "geometry": {"coordinates":[31.88347000000001,40.77667],"type":"Point"}
}