{
  "type": "Feature",
  "properties": {
    "gn:admin1_code":"58",
    "gn:asciiname":"Uzunkaya",
    "gn:country_code":"TR",
    "gn:dem":1582,
    "gn:feature_class":"P",
    "gn:feature_code":"PPL",
    "gn:name":"Uzunkaya",
    "gn:population":0,
    "gn:timezone":"Europe/Istanbul",
    "iso:country":"TR",
    "wof:name":"Uzunkaya",
    "wof:placetype":"locality"
},
  "geometry": {"coordinates":[37.98333,39.28333],"type":"Point"}
}