{
  "type": "Feature",
  "properties": {
    "gn:admin1_code":"74.0",
    "gn:asciiname":"Yatagan",
    "gn:country_code":"TR",
    "gn:dem":819,
    "gn:feature_class":"P",
    "gn:feature_code":"PPL",
    "gn:name":"Yata\u011fan",
    "gn:population":0,
    "gn:timezone":"Europe/Istanbul",
    "iso:country":"TR",
    "name:azb_x_preferred":[
        "\u06cc\u0627\u062a\u0627\u063a\u0627\u0646"
    ],
    "name:bel_x_preferred":[
        "\u042f\u0442\u0430\u0433\u0430\u043d"
    ],
    "name:bos_x_preferred":[
        "Jatagan"
    ],
    "name:bul_x_preferred":[
        "\u042f\u0442\u0430\u0433\u0430\u043d"
    ],
    "name:cat_x_preferred":[
        "Yatagan"
    ],
    "name:deu_x_preferred":[
        "Yatagan"
    ],
    "name:ell_x_preferred":[
        "\u0393\u03b9\u03b1\u03c4\u03b1\u03b3\u03ac\u03bd\u03b9"
    ],
    "name:epo_x_preferred":[
        "Jatagano"
    ],
    "name:fin_x_preferred":[
        "Jatagan"
    ],
    "name:fra_x_preferred":[
        "Yatagan"
    ],
    "name:hrv_x_preferred":[
        "Jatagan"
    ],
    "name:hun_x_preferred":[
        "Jatag\u00e1n"
    ],
    "name:hye_x_preferred":[
        "\u0545\u0561\u0569\u0561\u0572\u0561\u0576"
    ],
    "name:ido_x_preferred":[
        "Yatagano"
    ],
    "name:ita_x_preferred":[
        "Yatagan"
    ],
    "name:jpn_x_preferred":[
        "\u30e4\u30bf\u30ac\u30f3"
    ],
    "name:kor_x_preferred":[
        "\uc57c\ud0c0\uac04"
    ],
    "name:kur_x_preferred":[
        "\u015e\u00fbr\u00ea romiyan"
    ],
    "name:lit_x_preferred":[
        "Jataganas"
    ],
    "name:nld_x_preferred":[
        "Yatagan"
    ],
    "name:oci_x_preferred":[
        "Iatagan"
    ],
    "name:pol_x_preferred":[
        "Jatagan"
    ],
    "name:por_x_preferred":[
        "Iatag\u00e3"
    ],
    "name:ron_x_preferred":[
        "Iatagan"
    ],
    "name:rus_x_preferred":[
        "\u042f\u0442\u0430\u0433\u0430\u043d"
    ],
    "name:spa_x_preferred":[
        "Yatag\u00e1n"
    ],
    "name:sqi_x_preferred":[
        "Jatagani"
    ],
    "name:srp_x_preferred":[
        "\u0408\u0430\u0442\u0430\u0433\u0430\u043d"
    ],
    "name:swe_x_preferred":[
        "Yatagan"
    ],
    "name:tur_x_preferred":[
        "Yata\u011fan"
    ],
    "name:ukr_x_preferred":[
        "\u042f\u0442\u0430\u0433\u0430\u043d"
    ],
    "wof:name":"Yatagan",
    "wof:placetype":"locality"
},
  "geometry": {"coordinates":[42.15074,37.97565],"type":"Point"}
}