{
  "type": "Feature",
  "properties": {
    "gn:admin1_code":"74.0",
    "gn:asciiname":"Yatagan",
    "gn:country_code":"TR",
    "gn:dem":819,
    "gn:feature_class":"P",
    "gn:feature_code":"PPL",
    "gn:name":"Yata\u011fan",
    "gn:population":0,
    "gn:timezone":"Europe/Istanbul",
    "iso:country":"TR",
    "wof:name":"Yatagan",
    "wof:placetype":"locality"
},
  "geometry": {"coordinates":[42.15074,37.97565],"type":"Point"}
}