{
  "type": "Feature",
  "properties": {
    "gn:admin1_code":"24",
    "gn:asciiname":"Asagi Tolus",
    "gn:cc2":"TR",
    "gn:country_code":"TR",
    "gn:dem":1788,
    "gn:feature_class":"P",
    "gn:feature_code":"PPL",
    "gn:name":"A\u015fa\u011f\u0131 Tolus",
    "gn:population":0,
    "gn:timezone":"Europe/Istanbul",
    "iso:country":"TR",
    "name:und_x_variant":[
        "Toluss\u00fcfla",
        "A\u015fa\u011f\u0131tolos",
        "A\u015fa\u011f\u0131 Tulus",
        "A\u015fa\u011f\u0131 Tolus"
    ],
    "wof:name":"Asagi Tolus",
    "wof:placetype":"locality"
},
  "geometry": {"coordinates":[39.96667,39.93333],"type":"Point"}
}