{
  "type": "Feature",
  "properties": {
    "gn:admin1_code":"72",
    "gn:asciiname":"Fistikli",
    "gn:country_code":"TR",
    "gn:dem":1134,
    "gn:feature_class":"P",
    "gn:feature_code":"PPL",
    "gn:name":"F\u0131st\u0131kl\u0131",
    "gn:population":0,
    "gn:timezone":"Europe/Istanbul",
    "iso:country":"TR",
    "name:tur_x_preferred":[
        "F\u0131st\u0131kl\u0131"
    ],
    "name:und_x_variant":[
        "Sheykhmakhmut",
        "Hirbe\u015fehmahmut",
        "\u015eeyhmahmut",
        "Hirbe\u015feyhmahmut",
        "H\u0131rba\u015feyhmahmut"
    ],
    "wof:name":"Fistikli",
    "wof:placetype":"locality"
},
  "geometry": {"coordinates":[40.90569,37.39677],"type":"Point"}
}