{
  "type": "Feature",
  "properties": {
    "gn:admin1_code":"22.0",
    "gn:asciiname":"Serbettar",
    "gn:country_code":"TR",
    "gn:dem":83,
    "gn:feature_class":"P",
    "gn:feature_code":"PPL",
    "gn:name":"\u015eerbettar",
    "gn:population":0,
    "gn:timezone":"Europe/Istanbul",
    "iso:country":"TR",
    "wof:name":"Serbettar",
    "wof:placetype":"locality"
},
  "geometry": {"coordinates":[26.76276,41.46214000000001],"type":"Point"}
}