{
  "type": "Feature",
  "properties": {
    "gn:admin1_code":"58",
    "gn:asciiname":"Culhaali",
    "gn:country_code":"TR",
    "gn:dem":1503,
    "gn:feature_class":"P",
    "gn:feature_code":"PPL",
    "gn:name":"Culhaali",
    "gn:population":0,
    "gn:timezone":"Europe/Istanbul",
    "iso:country":"TR",
    "name:und_x_variant":[
        "\u00c7ulhal\u0131"
    ],
    "wof:name":"Culhaali",
    "wof:placetype":"locality"
},
  "geometry": {"coordinates":[37.7756,39.65648],"type":"Point"}
}