{
  "type": "Feature",
  "properties": {
    "gn:admin1_code":"32",
    "gn:asciiname":"Yalandiz Yaylasi",
    "gn:cc2":"TR",
    "gn:country_code":"TR",
    "gn:dem":776,
    "gn:feature_class":"P",
    "gn:feature_code":"PPL",
    "gn:name":"Yalandiz Yaylas\u0131",
    "gn:population":0,
    "gn:timezone":"Europe/Istanbul",
    "iso:country":"TR",
    "name:und_x_variant":[
        "Balandiz Yaylas\u0131",
        "Yalandiz Yaylas\u0131"
    ],
    "wof:name":"Yalandiz Yaylasi",
    "wof:placetype":"locality"
},
  "geometry": {"coordinates":[33.76667,36.35],"type":"Point"}
}