{
  "type": "Feature",
  "properties": {
    "gn:admin1_code":"60.0",
    "gn:asciiname":"Ugurlu",
    "gn:country_code":"TR",
    "gn:dem":1281,
    "gn:feature_class":"P",
    "gn:feature_code":"PPL",
    "gn:name":"U\u011furlu",
    "gn:population":0,
    "gn:timezone":"Europe/Istanbul",
    "iso:country":"TR",
    "name:und_x_variant":[
        "Ficek",
        "U\u011furlu",
        "U\u011furluk\u00f6y"
    ],
    "wof:name":"Ugurlu",
    "wof:placetype":"locality"
},
  "geometry": {"coordinates":[37.41493,40.27308],"type":"Point"}
}