{
  "type": "Feature",
  "properties": {
    "gn:admin1_code":"38.0",
    "gn:asciiname":"Sofumehmet",
    "gn:country_code":"TR",
    "gn:dem":1446,
    "gn:feature_class":"P",
    "gn:feature_code":"PPL",
    "gn:name":"Sofumehmet",
    "gn:population":0,
    "gn:timezone":"Europe/Istanbul",
    "iso:country":"TR",
    "wof:name":"Sofumehmet",
    "wof:placetype":"locality"
},
  "geometry": {"coordinates":[36.17649,39.06345],"type":"Point"}
}