{
  "type": "Feature",
  "properties": {
    "gn:admin1_code":"8.0",
    "gn:asciiname":"Demirkent",
    "gn:country_code":"TR",
    "gn:dem":1011,
    "gn:feature_class":"P",
    "gn:feature_code":"PPLA3",
    "gn:name":"Demirkent",
    "gn:population":0,
    "gn:timezone":"Europe/Istanbul",
    "iso:country":"TR",
    "name:eng_x_preferred":[
        "Demirkent"
    ],
    "name:rus_x_preferred":[
        "\u0414\u0435\u043c\u0438\u0440\u043a\u0435\u043d\u0442"
    ],
    "wof:name":"Demirkent",
    "wof:placetype":"locality"
},
  "geometry": {"coordinates":[41.72953,40.87908],"type":"Point"}
}