{
  "type": "Feature",
  "properties": {
    "gn:admin1_code":"16.0",
    "gn:asciiname":"Mahmudiye",
    "gn:country_code":"TR",
    "gn:dem":172,
    "gn:feature_class":"P",
    "gn:feature_code":"PPLA3",
    "gn:name":"Mahmudiye",
    "gn:population":0,
    "gn:timezone":"Europe/Istanbul",
    "iso:country":"TR",
    "name:deu_x_preferred":[
        "Mahmudiye"
    ],
    "name:diq_x_preferred":[
        "Mahmudiye"
    ],
    "name:fas_x_preferred":[
        "\u0645\u062d\u0645\u0648\u062f\u06cc\u0647"
    ],
    "name:fra_x_preferred":[
        "Mahmudiye"
    ],
    "name:mrj_x_preferred":[
        "\u041c\u0430\u0445\u043c\u0443\u0434\u0438\u0435"
    ],
    "name:msa_x_preferred":[
        "Mahmudiye"
    ],
    "name:nld_x_preferred":[
        "Mahmudiye"
    ],
    "name:nor_x_preferred":[
        "Mahmudiye"
    ],
    "name:swa_x_preferred":[
        "Mahmudiye"
    ],
    "name:tur_x_preferred":[
        "Mahmudiye"
    ],
    "name:und_x_variant":[
        "S\u00f6\u011f\u00fctp\u0131nar",
        "S\u00f6\u011f\u00fctp\u0131nar\u0131"
    ],
    "name:urd_x_preferred":[
        "\u0645\u062d\u0645\u0648\u062f\u06cc\u06c1"
    ],
    "name:vie_x_preferred":[
        "Mahmudiye"
    ],
    "wof:name":"Mahmudiye",
    "wof:placetype":"locality"
},
  "geometry": {"coordinates":[28.64945,40.33787],"type":"Point"}
}