{
  "type": "Feature",
  "properties": {
    "gn:admin1_code":"16",
    "gn:asciiname":"Tekerler",
    "gn:country_code":"TR",
    "gn:dem":754,
    "gn:feature_class":"P",
    "gn:feature_code":"PPL",
    "gn:name":"Tekerler",
    "gn:population":0,
    "gn:timezone":"Europe/Istanbul",
    "iso:country":"TR",
    "name:tur_x_preferred":[
        "Tekerler"
    ],
    "wof:name":"Tekerler",
    "wof:placetype":"locality"
},
  "geometry": {"coordinates":[28.87735,39.66179],"type":"Point"}
}