{
  "type": "Feature",
  "properties": {
    "gn:admin1_code":"37.0",
    "gn:asciiname":"Piri",
    "gn:country_code":"TR",
    "gn:dem":553,
    "gn:feature_class":"P",
    "gn:feature_code":"PPL",
    "gn:name":"Piri",
    "gn:population":0,
    "gn:timezone":"Europe/Istanbul",
    "iso:country":"TR",
    "wof:name":"Piri",
    "wof:placetype":"locality"
},
  "geometry": {"coordinates":[34.21603,41.87269000000001],"type":"Point"}
}