{
  "type": "Feature",
  "properties": {
    "gn:admin1_code":"54.0",
    "gn:asciiname":"Karaaptiler",
    "gn:country_code":"TR",
    "gn:dem":35,
    "gn:feature_class":"P",
    "gn:feature_code":"PPL",
    "gn:name":"Karaaptiler",
    "gn:population":0,
    "gn:timezone":"Europe/Istanbul",
    "iso:country":"TR",
    "name:tur_x_preferred":[
        "Abdibey"
    ],
    "name:und_x_variant":[
        "Karaabdiler",
        "Karaaptiler"
    ],
    "wof:name":"Karaaptiler",
    "wof:placetype":"locality"
},
  "geometry": {"coordinates":[30.41226,40.7119],"type":"Point"}
}