{
  "type": "Feature",
  "properties": {
    "gn:admin1_code":"8.0",
    "gn:asciiname":"Yagmurcay",
    "gn:country_code":"TR",
    "gn:dem":1507,
    "gn:feature_class":"P",
    "gn:feature_code":"PPL",
    "gn:name":"Ya\u011fmur\u00e7ay",
    "gn:population":0,
    "gn:timezone":"Europe/Istanbul",
    "iso:country":"TR",
    "name:tur_x_preferred":[
        "Ya\u011fmur\u00e7ay"
    ],
    "wof:name":"Yagmurcay",
    "wof:placetype":"locality"
},
  "geometry": {"coordinates":[41.45454,41.00509],"type":"Point"}
}