{
  "type": "Feature",
  "properties": {
    "gn:admin1_code":"14",
    "gn:asciiname":"Ciftlik",
    "gn:country_code":"TR",
    "gn:dem":757,
    "gn:feature_class":"P",
    "gn:feature_code":"PPL",
    "gn:name":"\u00c7iftlik",
    "gn:population":0,
    "gn:timezone":"Europe/Istanbul",
    "iso:country":"TR",
    "wof:name":"Ciftlik",
    "wof:placetype":"locality"
},
  "geometry": {"coordinates":[30.65144,40.46469],"type":"Point"}
}