{
  "type": "Feature",
  "properties": {
    "gn:country":"TR",
    "gn:fcode":"PPL",
    "gn:population":419,
    "iso:country":"TR",
    "name:ceb_x_preferred":[
        "Akk\u00f6y"
    ],
    "name:nld_x_preferred":[
        "Akk\u00f6y"
    ],
    "name:rus_x_preferred":[
        "\u0410\u043a\u043a\u0435\u0439"
    ],
    "name:tur_x_preferred":[
        "Akk\u00f6y"
    ],
    "name:und_x_variant":[
        "Sheykhyusuf"
    ],
    "qs:name":"Akk\u00f6y",
    "qs:photos_9r":0,
    "qs:photos_sr":0,
    "qs:pop_sr":"2",
    "wd:wordcount":46,
    "wof:name":"Akk\u00f6y",
    "wof:placetype":"locality",
    "wof:population":419
},
  "geometry": {"coordinates":[40.92028,37.75583],"type":"Point"}
}