{
  "type": "Feature",
  "properties": {
    "gn:admin1_code":"37.0",
    "gn:asciiname":"Bademci",
    "gn:country_code":"TR",
    "gn:dem":778,
    "gn:feature_class":"P",
    "gn:feature_code":"PPL",
    "gn:name":"Bademci",
    "gn:population":0,
    "gn:timezone":"Europe/Istanbul",
    "iso:country":"TR",
    "wof:name":"Bademci",
    "wof:placetype":"locality"
},
  "geometry": {"coordinates":[34.07195,41.53979],"type":"Point"}
}