{
  "type": "Feature",
  "properties": {
    "gn:admin1_code":"55.0",
    "gn:asciiname":"Ulukoy",
    "gn:country_code":"TR",
    "gn:dem":14,
    "gn:feature_class":"P",
    "gn:feature_code":"PPL",
    "gn:name":"Uluk\u00f6y",
    "gn:population":0,
    "gn:timezone":"Europe/Istanbul",
    "iso:country":"TR",
    "wof:name":"Ulukoy",
    "wof:placetype":"locality"
},
  "geometry": {"coordinates":[36.70923,41.27148],"type":"Point"}
}