{
  "type": "Feature",
  "properties": {
    "gn:country":"TR",
    "gn:fcode":"PPL",
    "gn:population":0,
    "iso:country":"TR",
    "name:tur_x_preferred":[
        "Bah\u00e7ecik"
    ],
    "qs:name":"Bah\u00e7ecik",
    "qs:name_adm0":"Turkey",
    "qs:name_adm1":"Trabzon",
    "qs:photos":6,
    "qs:photos_1k":1,
    "qs:photos_9k":1,
    "qs:photos_9r":1,
    "qs:photos_all":6,
    "qs:photos_sr":1,
    "qs:placetype":"Suburb",
    "qs:pop_sr":"0",
    "wd:wordcount":80,
    "wof:name":"Bah\u00e7ecik",
    "wof:placetype":"neighbourhood",
    "wof:population":0
},
  "geometry": {"coordinates":[40.00477,40.5804],"type":"Point"}
}