{
  "type": "Feature",
  "properties": {
    "gn:admin1_code":"93",
    "gn:asciiname":"Sinirci",
    "gn:country_code":"TR",
    "gn:dem":154,
    "gn:feature_class":"P",
    "gn:feature_code":"PPL",
    "gn:name":"Sinirci",
    "gn:population":0,
    "gn:timezone":"Europe/Istanbul",
    "iso:country":"TR",
    "wof:name":"Sinirci",
    "wof:placetype":"locality"
},
  "geometry": {"coordinates":[31.15847,40.81231],"type":"Point"}
}