{
  "type": "Feature",
  "properties": {
    "gn:admin1_code":"58.0",
    "gn:asciiname":"Akoren",
    "gn:country_code":"TR",
    "gn:dem":1360,
    "gn:feature_class":"P",
    "gn:feature_code":"PPL",
    "gn:name":"Ak\u00f6ren",
    "gn:population":0,
    "gn:timezone":"Europe/Istanbul",
    "iso:country":"TR",
    "name:und_x_variant":[
        "Kurbiy\u0131ld\u0131z",
        "Akverani",
        "Akvirankurbiy\u0131ld\u0131z",
        "Akveranikurbiy\u0131ld\u0131z",
        "Akyurt",
        "Akveranikurb\u0131ly\u0131ldiz",
        "Akverankurbuy\u0131ld\u0131z",
        "Ak\u00f6ren"
    ],
    "wof:name":"Akoren",
    "wof:placetype":"locality"
},
  "geometry": {"coordinates":[36.83891,40.0534],"type":"Point"}
}