{
  "type": "Feature",
  "properties": {
    "gn:admin1_code":"03",
    "gn:asciiname":"Davulga",
    "gn:country_code":"TR",
    "gn:dem":1032,
    "gn:feature_class":"P",
    "gn:feature_code":"PPLA3",
    "gn:name":"Davulga",
    "gn:population":0,
    "gn:timezone":"Europe/Istanbul",
    "iso:country":"TR",
    "name:tur_x_preferred":[
        "Davulga"
    ],
    "wof:name":"Davulga",
    "wof:placetype":"locality"
},
  "geometry": {"coordinates":[31.37139,38.97917],"type":"Point"}
}