{
  "type": "Feature",
  "properties": {
    "gn:admin1_code":"68.0",
    "gn:asciiname":"Kulu",
    "gn:country_code":"TR",
    "gn:dem":713,
    "gn:feature_class":"P",
    "gn:feature_code":"PPL",
    "gn:name":"Kulu",
    "gn:population":0,
    "gn:timezone":"Europe/Istanbul",
    "iso:country":"TR",
    "name:ceb_x_preferred":[
        "Kulu"
    ],
    "name:deu_x_preferred":[
        "Kulu"
    ],
    "name:fra_x_preferred":[
        "Kulu"
    ],
    "name:ita_x_preferred":[
        "Kulu"
    ],
    "name:min_x_preferred":[
        "Kulu"
    ],
    "name:nld_x_preferred":[
        "Kullu"
    ],
    "name:swe_x_preferred":[
        "Kulu"
    ],
    "wof:name":"Kulu",
    "wof:placetype":"locality"
},
  "geometry": {"coordinates":[31.17403,40.11258],"type":"Point"}
}