{
  "type": "Feature",
  "properties": {
    "gn:country":"TR",
    "gn:fcode":"PPL",
    "gn:pop":623,
    "iso:country":"TR",
    "name:unk_x_variant":[
        "Ziramba"
    ],
    "qs:name":"Yakac\u0131k",
    "qs:photos_9r":0,
    "qs:photos_sr":0,
    "qs:pop_sr":"2",
    "wof:name":"Yakac\u0131k",
    "wof:placetype":"locality",
    "wof:population":623
},
  "geometry": {"coordinates":[37.54227,36.89573],"type":"Point"}
}