{
  "type": "Feature",
  "properties": {
    "gn:admin1_code":"65",
    "gn:asciiname":"Beyuzumu",
    "gn:cc2":"TR",
    "gn:country_code":"TR",
    "gn:dem":1709,
    "gn:feature_class":"P",
    "gn:feature_code":"PPL",
    "gn:name":"Bey\u00fcz\u00fcm\u00fc",
    "gn:population":0,
    "gn:timezone":"Europe/Istanbul",
    "iso:country":"TR",
    "name:und_x_variant":[
        "\u015eahba\u011f\u0131",
        "Bey\u00fcz\u00fcm\u00fc"
    ],
    "wof:name":"Beyuzumu",
    "wof:placetype":"locality"
},
  "geometry": {"coordinates":[43.38333,38.53333],"type":"Point"}
}