{
  "type": "Feature",
  "properties": {
    "gn:admin1_code":"64",
    "gn:asciiname":"Karayakuplu",
    "gn:country_code":"TR",
    "gn:dem":827,
    "gn:feature_class":"P",
    "gn:feature_code":"PPL",
    "gn:name":"Karayakuplu",
    "gn:population":0,
    "gn:timezone":"Europe/Istanbul",
    "iso:country":"TR",
    "wof:name":"Karayakuplu",
    "wof:placetype":"locality"
},
  "geometry": {"coordinates":[29.47806,38.43],"type":"Point"}
}