{
  "type": "Feature",
  "properties": {
    "gn:admin1_code":"57.0",
    "gn:asciiname":"Cevikli",
    "gn:country_code":"TR",
    "gn:dem":713,
    "gn:feature_class":"P",
    "gn:feature_code":"PPL",
    "gn:name":"\u00c7evikli",
    "gn:population":0,
    "gn:timezone":"Europe/Istanbul",
    "iso:country":"TR",
    "wof:name":"Cevikli",
    "wof:placetype":"locality"
},
  "geometry": {"coordinates":[35.28777,41.53062],"type":"Point"}
}