{
  "type": "Feature",
  "properties": {
    "gn:admin1_code":"84.0",
    "gn:asciiname":"Tasliagil",
    "gn:country_code":"TR",
    "gn:dem":2009,
    "gn:feature_class":"P",
    "gn:feature_code":"PPL",
    "gn:name":"Ta\u015fl\u0131a\u011f\u0131l",
    "gn:population":0,
    "gn:timezone":"Europe/Istanbul",
    "iso:country":"TR",
    "name:und_x_variant":[
        "Ta\u015fl\u0131a\u011f\u0131l",
        "K\u00fcrtk\u00f6y\u00fc",
        "K\u00fcrk\u00f6y"
    ],
    "wof:name":"Tasliagil",
    "wof:placetype":"locality"
},
  "geometry": {"coordinates":[43.32818,40.92091],"type":"Point"}
}