{
  "type": "Feature",
  "properties": {
    "gn:admin1_code":"15",
    "gn:asciiname":"Dagarcik",
    "gn:country_code":"TR",
    "gn:dem":843,
    "gn:feature_class":"P",
    "gn:feature_code":"PPL",
    "gn:name":"Da\u011farc\u0131k",
    "gn:population":0,
    "gn:timezone":"Europe/Istanbul",
    "iso:country":"TR",
    "wof:name":"Dagarcik",
    "wof:placetype":"locality"
},
  "geometry": {"coordinates":[30.5258,37.51079],"type":"Point"}
}