{
  "type": "Feature",
  "properties": {
    "gn:admin1_code":"85.0",
    "gn:asciiname":"Dagdemirciler",
    "gn:country_code":"TR",
    "gn:dem":372,
    "gn:feature_class":"P",
    "gn:feature_code":"PPL",
    "gn:name":"Da\u011fdemirciler",
    "gn:population":0,
    "gn:timezone":"Europe/Istanbul",
    "iso:country":"TR",
    "name:und_x_variant":[
        "Demirciler",
        "Da\u011fdemirciler"
    ],
    "wof:name":"Dagdemirciler",
    "wof:placetype":"locality"
},
  "geometry": {"coordinates":[32.24375999999999,41.35576],"type":"Point"}
}