{
  "type": "Feature",
  "properties": {
    "gn:admin1_code":"80.0",
    "gn:asciiname":"Dagkonak",
    "gn:country_code":"TR",
    "gn:dem":1141,
    "gn:feature_class":"P",
    "gn:feature_code":"PPL",
    "gn:name":"Da\u011fkonak",
    "gn:population":0,
    "gn:timezone":"Europe/Istanbul",
    "iso:country":"TR",
    "name:und_x_variant":[
        "Ba\u011fkonak",
        "Nerakh",
        "Nerah",
        "Da\u011fkonak"
    ],
    "wof:name":"Dagkonak",
    "wof:placetype":"locality"
},
  "geometry": {"coordinates":[42.50752,37.47611],"type":"Point"}
}