{
  "type": "Feature",
  "properties": {
    "gn:admin1_code":"63",
    "gn:asciiname":"Aylan",
    "gn:country_code":"TR",
    "gn:dem":611,
    "gn:feature_class":"P",
    "gn:feature_code":"PPL",
    "gn:name":"Aylan",
    "gn:population":0,
    "gn:timezone":"Europe/Istanbul",
    "iso:country":"TR",
    "name:und_x_variant":[
        "Karacurun"
    ],
    "wof:name":"Aylan",
    "wof:placetype":"locality"
},
  "geometry": {"coordinates":[38.38078,37.15128],"type":"Point"}
}