{
  "type": "Feature",
  "properties": {
    "gn:admin1_code":"31",
    "gn:asciiname":"Marasbogazi",
    "gn:country_code":"TR",
    "gn:dem":121,
    "gn:feature_class":"P",
    "gn:feature_code":"PPL",
    "gn:name":"Mara\u015fbo\u011faz\u0131",
    "gn:population":0,
    "gn:timezone":"Europe/Istanbul",
    "iso:country":"TR",
    "name:tur_x_preferred":[
        "Mara\u015fba\u011f\u0131"
    ],
    "name:und_x_variant":[
        "Mara\u015fbo\u011faz\u0131 K\u00f6y\u00fc",
        "Mara\u015fbo\u011faz\u0131"
    ],
    "wof:name":"Marasbogazi",
    "wof:placetype":"locality"
},
  "geometry": {"coordinates":[36.2357,36.39992],"type":"Point"}
}