{
  "type": "Feature",
  "properties": {
    "gn:admin1_code":"57.0",
    "gn:asciiname":"Sazli",
    "gn:country_code":"TR",
    "gn:dem":1041,
    "gn:feature_class":"P",
    "gn:feature_code":"PPL",
    "gn:name":"Sazl\u0131",
    "gn:population":0,
    "gn:timezone":"Europe/Istanbul",
    "iso:country":"TR",
    "name:und_x_variant":[
        "Sazl\u0131k\u00f6y",
        "Sazl\u0131"
    ],
    "wof:name":"Sazli",
    "wof:placetype":"locality"
},
  "geometry": {"coordinates":[34.8754,41.72291],"type":"Point"}
}