{
  "type": "Feature",
  "properties": {
    "gn:admin1_code":"13",
    "gn:asciiname":"Geyikpinar",
    "gn:country_code":"TR",
    "gn:dem":1710,
    "gn:feature_class":"P",
    "gn:feature_code":"PPLA3",
    "gn:name":"Geyikp\u0131nar",
    "gn:population":0,
    "gn:timezone":"Europe/Istanbul",
    "iso:country":"TR",
    "name:tur_x_preferred":[
        "Geyikp\u0131nar"
    ],
    "name:und_x_variant":[
        "K\u00f6l\u00e2nis",
        "\u0130\u011fik",
        "Kolaniz",
        "Geyikp\u0131nar\u0131"
    ],
    "wof:name":"Geyikpinar",
    "wof:placetype":"locality"
},
  "geometry": {"coordinates":[41.82065,38.31759],"type":"Point"}
}