{
  "type": "Feature",
  "properties": {
    "gn:admin1_code":"13.0",
    "gn:asciiname":"Degirmenbasi",
    "gn:country_code":"TR",
    "gn:dem":1832,
    "gn:feature_class":"P",
    "gn:feature_code":"PPL",
    "gn:name":"De\u011firmenba\u015f\u0131",
    "gn:population":0,
    "gn:timezone":"Europe/Istanbul",
    "iso:country":"TR",
    "name:tur_x_preferred":[
        "De\u011firmenba\u015f\u0131"
    ],
    "wof:name":"Degirmenbasi",
    "wof:placetype":"locality"
},
  "geometry": {"coordinates":[42.52073,38.40904000000001],"type":"Point"}
}