{
  "type": "Feature",
  "properties": {
    "gn:admin1_code":"14.0",
    "gn:asciiname":"Havullu",
    "gn:country_code":"TR",
    "gn:dem":1304,
    "gn:feature_class":"P",
    "gn:feature_code":"PPL",
    "gn:name":"Havullu",
    "gn:population":0,
    "gn:timezone":"Europe/Istanbul",
    "iso:country":"TR",
    "wof:name":"Havullu",
    "wof:placetype":"locality"
},
  "geometry": {"coordinates":[32.24549,40.65906],"type":"Point"}
}