{
  "type": "Feature",
  "properties": {
    "gn:admin1_code":"71",
    "gn:asciiname":"Cinaroba",
    "gn:country_code":"TR",
    "gn:dem":1191,
    "gn:feature_class":"P",
    "gn:feature_code":"PPL",
    "gn:name":"\u00c7\u0131naroba",
    "gn:population":0,
    "gn:timezone":"Europe/Istanbul",
    "iso:country":"TR",
    "name:und_x_variant":[
        "\u00c7etme",
        "\u00c7\u0131naroba"
    ],
    "wof:name":"Cinaroba",
    "wof:placetype":"locality"
},
  "geometry": {"coordinates":[31.6407,38.17027],"type":"Point"}
}