{
  "type": "Feature",
  "properties": {
    "gn:admin1_code":"2.0",
    "gn:asciiname":"Akcicek",
    "gn:country_code":"TR",
    "gn:dem":911,
    "gn:feature_class":"P",
    "gn:feature_code":"PPL",
    "gn:name":"Ak\u00e7i\u00e7ek",
    "gn:population":0,
    "gn:timezone":"Europe/Istanbul",
    "iso:country":"TR",
    "name:tur_x_preferred":[
        "Ak\u00e7i\u00e7ek"
    ],
    "wof:name":"Akcicek",
    "wof:placetype":"locality"
},
  "geometry": {"coordinates":[39.16331,38.16696],"type":"Point"}
}