{
  "type": "Feature",
  "properties": {
    "gn:admin1_code":"14",
    "gn:asciiname":"Yakabey",
    "gn:country_code":"TR",
    "gn:dem":1318,
    "gn:feature_class":"P",
    "gn:feature_code":"PPL",
    "gn:name":"Yakabey",
    "gn:population":0,
    "gn:timezone":"Europe/Istanbul",
    "iso:country":"TR",
    "wof:name":"Yakabey",
    "wof:placetype":"locality"
},
  "geometry": {"coordinates":[32.28749000000001,40.68081],"type":"Point"}
}