{
  "type": "Feature",
  "properties": {
    "gn:admin1_code":"17",
    "gn:asciiname":"Yigitler",
    "gn:country_code":"TR",
    "gn:dem":174,
    "gn:feature_class":"P",
    "gn:feature_code":"PPLA3",
    "gn:name":"Yi\u011fitler",
    "gn:population":0,
    "gn:timezone":"Europe/Istanbul",
    "iso:country":"TR",
    "name:und_x_variant":[
        "Yi\u011fitaliler",
        "Yi\u011fitler"
    ],
    "wof:name":"Yigitler",
    "wof:placetype":"locality"
},
  "geometry": {"coordinates":[26.61111,39.8675],"type":"Point"}
}