{
  "type": "Feature",
  "properties": {
    "gn:admin1_code":"09",
    "gn:asciiname":"Cilimbiz",
    "gn:country_code":"TR",
    "gn:dem":282,
    "gn:feature_class":"P",
    "gn:feature_code":"PPL",
    "gn:name":"C\u0131l\u0131mb\u0131z",
    "gn:population":0,
    "gn:timezone":"Europe/Istanbul",
    "iso:country":"TR",
    "name:tur_x_preferred":[
        "C\u0131l\u0131mb\u0131z"
    ],
    "wof:name":"Cilimbiz",
    "wof:placetype":"locality"
},
  "geometry": {"coordinates":[27.73524,37.91888],"type":"Point"}
}