{
  "type": "Feature",
  "properties": {
    "gn:admin1_code":"03",
    "gn:asciiname":"Nasuhoglu",
    "gn:country_code":"TR",
    "gn:dem":1048,
    "gn:feature_class":"P",
    "gn:feature_code":"PPL",
    "gn:name":"Nasuho\u011flu",
    "gn:population":0,
    "gn:timezone":"Europe/Istanbul",
    "iso:country":"TR",
    "name:und_x_variant":[
        "Nasuho\u011flu Damlar\u0131",
        "Nasuho\u011flu"
    ],
    "wof:name":"Nasuhoglu",
    "wof:placetype":"locality"
},
  "geometry": {"coordinates":[30.0276,38.49894000000001],"type":"Point"}
}