{
  "type": "Feature",
  "properties": {
    "gn:admin1_code":"55.0",
    "gn:asciiname":"Karabuk",
    "gn:country_code":"TR",
    "gn:dem":817,
    "gn:feature_class":"P",
    "gn:feature_code":"PPL",
    "gn:name":"Karab\u00fck",
    "gn:population":0,
    "gn:timezone":"Europe/Istanbul",
    "iso:country":"TR",
    "name:und_x_variant":[
        "\u0130mircik",
        "Emircik",
        "Karab\u00fck"
    ],
    "wof:name":"Karabuk",
    "wof:placetype":"locality"
},
  "geometry": {"coordinates":[35.60459,41.02059000000001],"type":"Point"}
}