{
  "type": "Feature",
  "properties": {
    "gn:admin1_code":"13.0",
    "gn:asciiname":"Esenyurt",
    "gn:country_code":"TR",
    "gn:dem":1492,
    "gn:feature_class":"P",
    "gn:feature_code":"PPL",
    "gn:name":"Esenyurt",
    "gn:population":0,
    "gn:timezone":"Europe/Istanbul",
    "iso:country":"TR",
    "name:tur_x_preferred":[
        "Esenyurt"
    ],
    "wof:name":"Esenyurt",
    "wof:placetype":"locality"
},
  "geometry": {"coordinates":[41.79745,38.30825],"type":"Point"}
}