{
  "type": "Feature",
  "properties": {
    "gn:admin1_code":"65.0",
    "gn:asciiname":"Karatavuk",
    "gn:country_code":"TR",
    "gn:dem":1853,
    "gn:feature_class":"P",
    "gn:feature_code":"PPL",
    "gn:name":"Karatavuk",
    "gn:population":0,
    "gn:timezone":"Europe/Istanbul",
    "iso:country":"TR",
    "name:tur_x_preferred":[
        "Karatavuk"
    ],
    "wof:name":"Karatavuk",
    "wof:placetype":"locality"
},
  "geometry": {"coordinates":[43.06603,38.96887],"type":"Point"}
}