{
  "type": "Feature",
  "properties": {
    "gn:country":"TR",
    "gn:fcode":"PPL",
    "gn:pop":463,
    "iso:country":"TR",
    "name:unk_x_variant":[
        "Banimehnedan"
    ],
    "qs:name":"Ko\u00e7beyi",
    "qs:photos_9r":0,
    "qs:photos_sr":0,
    "qs:pop_sr":"2",
    "wof:name":"Ko\u00e7beyi",
    "wof:placetype":"locality",
    "wof:population":463
},
  "geometry": {"coordinates":[42.19389,37.42389],"type":"Point"}
}