{
  "type": "Feature",
  "properties": {
    "gn:admin1_code":"74.0",
    "gn:asciiname":"Ulastar",
    "gn:country_code":"TR",
    "gn:dem":869,
    "gn:feature_class":"P",
    "gn:feature_code":"PPL",
    "gn:name":"Ula\u015ftar",
    "gn:population":0,
    "gn:timezone":"Europe/Istanbul",
    "iso:country":"TR",
    "wof:name":"Ulastar",
    "wof:placetype":"locality"
},
  "geometry": {"coordinates":[42.05111,37.80111],"type":"Point"}
}