{
  "type": "Feature",
  "properties": {
    "gn:admin1_code":"71",
    "gn:asciiname":"Polat",
    "gn:country_code":"TR",
    "gn:dem":1430,
    "gn:feature_class":"P",
    "gn:feature_code":"PPL",
    "gn:name":"Polat",
    "gn:population":0,
    "gn:timezone":"Europe/Istanbul",
    "iso:country":"TR",
    "name:nld_x_preferred":[
        "Polat"
    ],
    "name:und_x_variant":[
        "Bolat"
    ],
    "wof:name":"Polat",
    "wof:placetype":"locality"
},
  "geometry": {"coordinates":[32.42081,37.07493],"type":"Point"}
}