{
  "type": "Feature",
  "properties": {
    "gn:admin1_code":"10",
    "gn:asciiname":"Asagigocek",
    "gn:country_code":"TR",
    "gn:dem":616,
    "gn:feature_class":"P",
    "gn:feature_code":"PPL",
    "gn:name":"A\u015fa\u011f\u0131g\u00f6cek",
    "gn:population":0,
    "gn:timezone":"Europe/Istanbul",
    "iso:country":"TR",
    "name:und_x_variant":[
        "A\u015fa\u011f\u0131g\u00f6cek",
        "A\u015fa\u011f\u0131g\u00fcc\u00fck"
    ],
    "wof:name":"Asagigocek",
    "wof:placetype":"locality"
},
  "geometry": {"coordinates":[28.42935,39.40436],"type":"Point"}
}