{
  "type": "Feature",
  "properties": {
    "gn:admin1_code":"04",
    "gn:asciiname":"Bolasli",
    "gn:country_code":"TR",
    "gn:dem":1909,
    "gn:feature_class":"P",
    "gn:feature_code":"PPL",
    "gn:name":"Bola\u015fl\u0131",
    "gn:population":0,
    "gn:timezone":"Europe/Istanbul",
    "iso:country":"TR",
    "name:und_x_variant":[
        "Seyit",
        "Bola\u015fl\u0131"
    ],
    "wof:name":"Bolasli",
    "wof:placetype":"locality"
},
  "geometry": {"coordinates":[42.5366,39.60289],"type":"Point"}
}