{
  "type": "Feature",
  "properties": {
    "gn:admin1_code":"24",
    "gn:asciiname":"Kayacik",
    "gn:country_code":"TR",
    "gn:dem":878,
    "gn:feature_class":"P",
    "gn:feature_code":"PPL",
    "gn:name":"Kayac\u0131k",
    "gn:population":0,
    "gn:timezone":"Europe/Istanbul",
    "iso:country":"TR",
    "name:und_x_variant":[
        "Lordin",
        "Nordun",
        "Kayac\u0131k"
    ],
    "wof:name":"Kayacik",
    "wof:placetype":"locality"
},
  "geometry": {"coordinates":[38.45075,39.43761],"type":"Point"}
}