{
  "type": "Feature",
  "properties": {
    "gn:country":"TR",
    "gn:fcode":"PPLA2",
    "gn:population":18769,
    "iso:country":"TR",
    "name:aze_x_preferred":[
        "Ele\u015fgird rayonu"
    ],
    "name:cat_x_preferred":[
        "Ele\u015fkirt"
    ],
    "name:ceb_x_preferred":[
        "Ele\u015fkirt"
    ],
    "name:ckb_x_preferred":[
        "\u0632\u06ce\u062f\u06a9\u0627\u0646"
    ],
    "name:deu_x_preferred":[
        "Ele\u015fkirt"
    ],
    "name:diq_x_preferred":[
        "Z\u00ead\u0131kan"
    ],
    "name:eng_x_preferred":[
        "Ele\u015fkirt"
    ],
    "name:epo_x_preferred":[
        "Ele\u015fkirt"
    ],
    "name:fas_x_preferred":[
        "\u0627\u0644\u0634\u06a9\u06cc\u0631\u062a"
    ],
    "name:fra_x_preferred":[
        "Ele\u015fkirt"
    ],
    "name:hye_x_preferred":[
        "\u0531\u056c\u0561\u0577\u056f\u0565\u0580\u057f"
    ],
    "name:hyw_x_preferred":[
        "\u0531\u056c\u0561\u0577\u056f\u0565\u0580\u057f"
    ],
    "name:ita_x_preferred":[
        "Ele\u015fkirt"
    ],
    "name:jpn_x_preferred":[
        "\u30a2\u30e9\u30b7\u30e5\u30b1\u30eb\u30c8"
    ],
    "name:kur_x_preferred":[
        "Z\u00eatka"
    ],
    "name:lbe_x_preferred":[
        "\u042d\u043b\u0435\u0448\u043a\u0438\u0440\u0442"
    ],
    "name:mrj_x_preferred":[
        "\u042d\u043b\u0435\u0448\u043a\u0438\u0440\u0442"
    ],
    "name:msa_x_preferred":[
        "Ele\u015fkirt"
    ],
    "name:nan_x_preferred":[
        "Ele\u015fkirt"
    ],
    "name:nld_x_preferred":[
        "Ele\u015fkirt"
    ],
    "name:nno_x_preferred":[
        "Ele\u015fkirt"
    ],
    "name:nob_x_preferred":[
        "Ele\u015fkirt"
    ],
    "name:pnb_x_preferred":[
        "\u0636\u0644\u0639 \u0627\u0644\u0633\u06a9\u0631\u0679"
    ],
    "name:pol_x_preferred":[
        "Ele\u015fkirt"
    ],
    "name:rus_x_preferred":[
        "\u042d\u043b\u0435\u0448\u043a\u0438\u0440\u0442"
    ],
    "name:swa_x_preferred":[
        "Ele\u015fkirt"
    ],
    "name:tur_x_preferred":[
        "Ele\u015fkirt"
    ],
    "name:und_x_variant":[
        "Toprakkale"
    ],
    "name:urd_x_preferred":[
        "\u0627\u0644\u0634\u06a9\u06cc\u0631\u062a"
    ],
    "name:vie_x_preferred":[
        "Ele\u015fkirt"
    ],
    "name:zho_x_preferred":[
        "\u57c3\u840a\u4ec0\u57fa\u723e\u7279"
    ],
    "qs:name":"Ele\u015fkirt",
    "qs:photos_9r":0,
    "qs:photos_sr":0,
    "qs:pop_sr":"6",
    "wd:wordcount":269,
    "wof:name":"Ele\u015fkirt",
    "wof:placetype":"locality",
    "wof:population":18769
},
  "geometry": {"coordinates":[42.67361,39.80333],"type":"Point"}
}