{
  "type": "Feature",
  "properties": {
    "gn:country":"TR",
    "gn:fcode":"PPLA2",
    "gn:pop":18769,
    "iso:country":"TR",
    "name:unk_x_variant":[
        "Toprakkale"
    ],
    "qs:name":"Ele\u015fkirt",
    "qs:photos_9r":0,
    "qs:photos_sr":0,
    "qs:pop_sr":"6",
    "wd:wordcount":269,
    "wof:name":"Ele\u015fkirt",
    "wof:placetype":"locality",
    "wof:population":18769
},
  "geometry": {"coordinates":[42.67361,39.80333],"type":"Point"}
}