{
  "type": "Feature",
  "properties": {
    "gn:admin1_code":"32",
    "gn:asciiname":"Tozkovan",
    "gn:country_code":"TR",
    "gn:dem":958,
    "gn:feature_class":"P",
    "gn:feature_code":"PPL",
    "gn:name":"Tozkovan",
    "gn:population":0,
    "gn:timezone":"Europe/Istanbul",
    "iso:country":"TR",
    "name:tur_x_preferred":[
        "I\u015f\u0131kl\u0131"
    ],
    "name:tur_x_variant":[
        "Tozkovan",
        "Tosgavan"
    ],
    "wof:name":"Tozkovan",
    "wof:placetype":"locality"
},
  "geometry": {"coordinates":[33.36435,36.38535],"type":"Point"}
}