{
  "type": "Feature",
  "properties": {
    "gn:admin1_code":"59.0",
    "gn:asciiname":"Banarli",
    "gn:country_code":"TR",
    "gn:dem":111,
    "gn:feature_class":"P",
    "gn:feature_code":"PPLA3",
    "gn:name":"Banarl\u0131",
    "gn:population":0,
    "gn:timezone":"Europe/Istanbul",
    "iso:country":"TR",
    "name:tur_x_preferred":[
        "Banarl\u0131"
    ],
    "wof:name":"Banarli",
    "wof:placetype":"locality"
},
  "geometry": {"coordinates":[27.33575,41.06702],"type":"Point"}
}