{
  "type": "Feature",
  "properties": {
    "gn:admin1_code":"19.0",
    "gn:asciiname":"Findicak",
    "gn:country_code":"TR",
    "gn:dem":1348,
    "gn:feature_class":"P",
    "gn:feature_code":"PPL",
    "gn:name":"F\u0131nd\u0131cak",
    "gn:population":0,
    "gn:timezone":"Europe/Istanbul",
    "iso:country":"TR",
    "name:tur_x_preferred":[
        "F\u0131nd\u0131cak"
    ],
    "name:und_x_variant":[
        "Kar\u015f\u0131 Mahallesi",
        "Kar\u015f\u0131"
    ],
    "wof:name":"Findicak",
    "wof:placetype":"locality"
},
  "geometry": {"coordinates":[34.12071,40.7946],"type":"Point"}
}