{
  "type": "Feature",
  "properties": {
    "gn:admin1_code":"32",
    "gn:asciiname":"Ciftlikkoy",
    "gn:cc2":"TR",
    "gn:country_code":"TR",
    "gn:dem":370,
    "gn:feature_class":"P",
    "gn:feature_code":"PPL",
    "gn:name":"\u00c7iftlikk\u00f6y",
    "gn:population":0,
    "gn:timezone":"Europe/Istanbul",
    "iso:country":"TR",
    "name:und_x_variant":[
        "Evkaf\u00e7iftli\u011fik\u00f6y",
        "\u00c7iftlikk\u00f6y"
    ],
    "wof:name":"Ciftlikkoy",
    "wof:placetype":"locality"
},
  "geometry": {"coordinates":[33.65,36.45],"type":"Point"}
}