{
  "type": "Feature",
  "properties": {
    "gn:admin1_code":"23",
    "gn:asciiname":"Tarhanakoy",
    "gn:country_code":"TR",
    "gn:dem":1573,
    "gn:feature_class":"P",
    "gn:feature_code":"PPL",
    "gn:name":"Tarhanak\u00f6y",
    "gn:population":0,
    "gn:timezone":"Europe/Istanbul",
    "iso:country":"TR",
    "name:tur_x_preferred":[
        "Tarhanak\u00f6y"
    ],
    "name:und_x_variant":[
        "Tarhana"
    ],
    "wof:name":"Tarhanakoy",
    "wof:placetype":"locality"
},
  "geometry": {"coordinates":[40.03937,38.61578],"type":"Point"}
}