{
  "type": "Feature",
  "properties": {
    "gn:admin1_code":"25",
    "gn:asciiname":"Serdarli",
    "gn:country_code":"TR",
    "gn:dem":1673,
    "gn:feature_class":"P",
    "gn:feature_code":"PPL",
    "gn:name":"Serdarl\u0131",
    "gn:population":0,
    "gn:timezone":"Europe/Istanbul",
    "iso:country":"TR",
    "name:tur_x_preferred":[
        "Serdarl\u0131"
    ],
    "wof:name":"Serdarli",
    "wof:placetype":"locality"
},
  "geometry": {"coordinates":[41.31331,40.47239],"type":"Point"}
}