{
  "type": "Feature",
  "properties": {
    "gn:admin1_code":"63",
    "gn:asciiname":"Kosekoy",
    "gn:country_code":"TR",
    "gn:dem":445,
    "gn:feature_class":"P",
    "gn:feature_code":"PPL",
    "gn:name":"K\u00f6sek\u00f6y",
    "gn:population":0,
    "gn:timezone":"Europe/Istanbul",
    "iso:country":"TR",
    "name:rus_x_preferred":[
        "K\u00ebse"
    ],
    "name:tur_x_preferred":[
        "K\u00f6sek\u00f6y"
    ],
    "wof:name":"Kosekoy",
    "wof:placetype":"locality"
},
  "geometry": {"coordinates":[39.02957,37.12121],"type":"Point"}
}