{
  "type": "Feature",
  "properties": {
    "gn:admin1_code":"45",
    "gn:asciiname":"Cambazli",
    "gn:country_code":"TR",
    "gn:dem":149,
    "gn:feature_class":"P",
    "gn:feature_code":"PPL",
    "gn:name":"Cambazl\u0131",
    "gn:population":0,
    "gn:timezone":"Europe/Istanbul",
    "iso:country":"TR",
    "name:und_x_variant":[
        "Canbazl\u0131",
        "Cambazl\u0131"
    ],
    "wof:name":"Cambazli",
    "wof:placetype":"locality"
},
  "geometry": {"coordinates":[27.8378,38.5761],"type":"Point"}
}