{
  "type": "Feature",
  "properties": {
    "gn:admin1_code":"88",
    "gn:asciiname":"Kulukent",
    "gn:country_code":"TR",
    "gn:dem":826,
    "gn:feature_class":"P",
    "gn:feature_code":"PPL",
    "gn:name":"Kulukent",
    "gn:population":0,
    "gn:timezone":"Europe/Istanbul",
    "iso:country":"TR",
    "wof:name":"Kulukent",
    "wof:placetype":"locality"
},
  "geometry": {"coordinates":[44.35472,39.90472000000001],"type":"Point"}
}