{
  "type": "Feature",
  "properties": {
    "gn:admin1_code":"43",
    "gn:asciiname":"Kayalidere",
    "gn:country_code":"TR",
    "gn:dem":1001,
    "gn:feature_class":"P",
    "gn:feature_code":"PPL",
    "gn:name":"Kayal\u0131dere",
    "gn:population":0,
    "gn:timezone":"Europe/Istanbul",
    "iso:country":"TR",
    "wof:name":"Kayalidere",
    "wof:placetype":"locality"
},
  "geometry": {"coordinates":[28.89417000000001,39.25278],"type":"Point"}
}