{
  "type": "Feature",
  "properties": {
    "iso:country":"TR",
    "name:ast_x_preferred":[
        "K\u00e2z\u0131m Dirik"
    ],
    "name:aze_x_preferred":[
        "Kaz\u0131m Dirik"
    ],
    "name:bul_x_preferred":[
        "\u041c\u0435\u0445\u043c\u0435\u0434 \u041a\u044f\u0437\u044a\u043c \u0414\u0438\u0440\u0438\u043a"
    ],
    "name:bul_x_variant":[
        "\u041a\u044f\u0437\u0438\u043c \u0414\u0438\u0440\u0438\u043a"
    ],
    "name:deu_x_preferred":[
        "K\u00e2z\u0131m Dirik"
    ],
    "name:diq_x_preferred":[
        "K\u00e2z\u0131m Dirik"
    ],
    "name:eng_x_colloquial":[
        "Kazim Dirik"
    ],
    "name:eng_x_preferred":[
        "K\u00e2z\u0131m Dirik"
    ],
    "name:hun_x_preferred":[
        "K\u00e2z\u0131m Dirik"
    ],
    "name:nld_x_preferred":[
        "K\u00e2z\u0131m Dirik"
    ],
    "name:spa_x_preferred":[
        "K\u00e2z\u0131m Dirik"
    ],
    "name:sqi_x_preferred":[
        "Kazim Dirik"
    ],
    "name:tur_x_preferred":[
        "K\u00e2z\u0131m Dirik"
    ],
    "name:und_x_variant":[
        "Kaz\u0131m Dirik"
    ],
    "qs:gn_adm0_cc":"TR",
    "qs:gn_local":311046,
    "qs:gn_nam_loc":"Izmir",
    "qs:gn_namadm1":"35",
    "qs:local_max":696,
    "qs:local_sum":4164,
    "qs:localhoods":19,
    "qs:name":"Kaz\u0131m Dirik",
    "qs:name_adm0":"Turkey",
    "qs:name_adm1":"\u0130zmir",
    "qs:name_adm2":"Bornova",
    "qs:name_local":"\u0130zmir",
    "qs:photo_max":29,
    "qs:photo_sum":176,
    "qs:placetype":"Suburb",
    "qs:quad_count":16,
    "qs:woe_adm0":23424969,
    "qs:woe_adm1":2347290,
    "qs:woe_adm2":29390168,
    "qs:woe_lau":0,
    "qs:woe_local":2344117,
    "qs:woe_ver":"7.10.0",
    "qs_pg:name":"Kaz\u0131m Dirik",
    "qs_pg:name_adm0":"Turkey",
    "qs_pg:name_adm1":"\u0130zmir",
    "qs_pg:photos":172,
    "qs_pg:photos_1k":35,
    "qs_pg:photos_9k":1,
    "qs_pg:photos_9r":4,
    "qs_pg:photos_all":172,
    "qs_pg:photos_sr":4,
    "qs_pg:pop_sr":0,
    "qs_pg:qs_pg_placetype":"neighbourhood",
    "qs_pg:qs_pg_placetype_gp":"Suburb",
    "qs_pg:woe_adm0":23424969,
    "wd:wordcount":116,
    "woe:adm0_id":23424969,
    "woe:name_adm0":"Turkey",
    "woe:name_adm1":"\u0130zmir",
    "woe:placetype":"Suburb",
    "wof:lang":[
        "unk"
    ],
    "wof:name":"Kaz\u0131m Dirik",
    "wof:placetype":"neighbourhood"
},
  "geometry": {"coordinates":[27.209314,38.457085],"type":"Point"}
}