{
  "type": "Feature",
  "properties": {
    "gn:admin1_code":"60.0",
    "gn:asciiname":"Danisment",
    "gn:country_code":"TR",
    "gn:dem":1442,
    "gn:feature_class":"P",
    "gn:feature_code":"PPL",
    "gn:name":"Dani\u015fment",
    "gn:population":0,
    "gn:timezone":"Europe/Istanbul",
    "iso:country":"TR",
    "name:tur_x_preferred":[
        "Dani\u015fment"
    ],
    "wof:name":"Danisment",
    "wof:placetype":"locality"
},
  "geometry": {"coordinates":[37.52954,40.48638],"type":"Point"}
}