{
  "type": "Feature",
  "properties": {
    "gn:admin1_code":"04",
    "gn:asciiname":"Sini",
    "gn:country_code":"TR",
    "gn:dem":1966,
    "gn:feature_class":"P",
    "gn:feature_code":"PPL",
    "gn:name":"Sini",
    "gn:population":0,
    "gn:timezone":"Europe/Istanbul",
    "iso:country":"TR",
    "wof:name":"Sini",
    "wof:placetype":"locality"
},
  "geometry": {"coordinates":[43.71667,39.71667],"type":"Point"}
}