{
  "type": "Feature",
  "properties": {
    "gn:admin1_code":"46.0",
    "gn:asciiname":"Agcasar",
    "gn:country_code":"TR",
    "gn:dem":1543,
    "gn:feature_class":"P",
    "gn:feature_code":"PPL",
    "gn:name":"A\u011fca\u015far",
    "gn:population":0,
    "gn:timezone":"Europe/Istanbul",
    "iso:country":"TR",
    "wof:name":"Agcasar",
    "wof:placetype":"locality"
},
  "geometry": {"coordinates":[37.3499,38.07865],"type":"Point"}
}