{
  "type": "Feature",
  "properties": {
    "gn:admin1_code":"25",
    "gn:asciiname":"Yikilgan",
    "gn:country_code":"TR",
    "gn:dem":2071,
    "gn:feature_class":"P",
    "gn:feature_code":"PPL",
    "gn:name":"Y\u0131k\u0131lgan",
    "gn:population":0,
    "gn:timezone":"Europe/Istanbul",
    "iso:country":"TR",
    "name:und_x_variant":[
        "Nebik\u00f6y",
        "Y\u0131k\u0131lgan",
        "Nebi"
    ],
    "wof:name":"Yikilgan",
    "wof:placetype":"locality"
},
  "geometry": {"coordinates":[41.40482,39.88867],"type":"Point"}
}