{
  "type": "Feature",
  "properties": {
    "gn:admin1_code":"21.0",
    "gn:asciiname":"Altintas",
    "gn:country_code":"TR",
    "gn:dem":754,
    "gn:feature_class":"P",
    "gn:feature_code":"PPL",
    "gn:name":"Alt\u0131nta\u015f",
    "gn:population":0,
    "gn:timezone":"Europe/Istanbul",
    "iso:country":"TR",
    "wof:name":"Altintas",
    "wof:placetype":"locality"
},
  "geometry": {"coordinates":[40.16801,38.33355],"type":"Point"}
}