{
  "type": "Feature",
  "properties": {
    "gn:admin1_code":"13",
    "gn:asciiname":"Kirkbulak",
    "gn:country_code":"TR",
    "gn:dem":1744,
    "gn:feature_class":"P",
    "gn:feature_code":"PPL",
    "gn:name":"K\u0131rkbulak",
    "gn:population":0,
    "gn:timezone":"Europe/Istanbul",
    "iso:country":"TR",
    "name:und_x_variant":[
        "Sakk\u00f6y",
        "Sak",
        "K\u0131rkbulak"
    ],
    "wof:name":"Kirkbulak",
    "wof:placetype":"locality"
},
  "geometry": {"coordinates":[42.26897,38.41195],"type":"Point"}
}