{
  "type": "Feature",
  "properties": {
    "gn:admin1_code":"45",
    "gn:asciiname":"Dibekdere",
    "gn:country_code":"TR",
    "gn:dem":82,
    "gn:feature_class":"P",
    "gn:feature_code":"PPL",
    "gn:name":"Dibekdere",
    "gn:population":0,
    "gn:timezone":"Europe/Istanbul",
    "iso:country":"TR",
    "name:tur_x_preferred":[
        "Dibekdere"
    ],
    "wof:name":"Dibekdere",
    "wof:placetype":"locality"
},
  "geometry": {"coordinates":[27.95939000000001,38.55953],"type":"Point"}
}