{
  "type": "Feature",
  "properties": {
    "gn:admin1_code":"00",
    "gn:asciiname":"Gueneysinir",
    "gn:country_code":"TR",
    "gn:dem":1120,
    "gn:feature_class":"P",
    "gn:feature_code":"PPL",
    "gn:name":"G\u00fcneys\u0131n\u0131r",
    "gn:population":0,
    "gn:timezone":"Europe/Istanbul",
    "iso:country":"TR",
    "name:ceb_x_preferred":[
        "G\u00fcneys\u0131n\u0131r \u0130l\u00e7esi"
    ],
    "name:deu_x_preferred":[
        "G\u00fcneys\u0131n\u0131r"
    ],
    "name:diq_x_preferred":[
        "G\u00fcneys\u0131n\u0131r"
    ],
    "name:fra_x_preferred":[
        "G\u00fcneys\u0131n\u0131r"
    ],
    "name:mrj_x_preferred":[
        "\u0413\u04f1\u043d\u0435\u0439\u0441\u044b\u043d\u044b\u0440"
    ],
    "name:msa_x_preferred":[
        "G\u00fcneys\u0131n\u0131r"
    ],
    "name:nor_x_preferred":[
        "G\u00fcneys\u0131n\u0131r"
    ],
    "name:swa_x_preferred":[
        "G\u00fcneys\u0131n\u0131r"
    ],
    "name:tur_x_preferred":[
        "G\u00fcneys\u0131n\u0131r"
    ],
    "name:tur_x_variant":[
        "G\u00fcneyba\u011f (old)"
    ],
    "name:urd_x_preferred":[
        "\u06af\u0648\u0646\u06cc\u0633\u06cc\u0646\u0627\u0631"
    ],
    "name:vie_x_preferred":[
        "G\u00fcneys\u0131n\u0131r"
    ],
    "wof:name":"Gueneysinir",
    "wof:placetype":"locality"
},
  "geometry": {"coordinates":[32.73305999999999,37.26861],"type":"Point"}
}