{
  "type": "Feature",
  "properties": {
    "gn:admin1_code":"68.0",
    "gn:asciiname":"Incepelit",
    "gn:country_code":"TR",
    "gn:dem":738,
    "gn:feature_class":"P",
    "gn:feature_code":"PPL",
    "gn:name":"\u0130ncepelit",
    "gn:population":0,
    "gn:timezone":"Europe/Istanbul",
    "iso:country":"TR",
    "wof:name":"Incepelit",
    "wof:placetype":"locality"
},
  "geometry": {"coordinates":[32.06907,40.17908],"type":"Point"}
}