{
  "type": "Feature",
  "properties": {
    "gn:admin1_code":"25.0",
    "gn:asciiname":"Esendurak",
    "gn:cc2":"TR",
    "gn:country_code":"TR",
    "gn:dem":2130,
    "gn:feature_class":"P",
    "gn:feature_code":"PPL",
    "gn:name":"Esendurak",
    "gn:population":0,
    "gn:timezone":"Europe/Istanbul",
    "iso:country":"TR",
    "name:und_x_variant":[
        "Sa\u011f\u0131r",
        "Sa\u011fer",
        "Esendurak"
    ],
    "wof:name":"Esendurak",
    "wof:placetype":"locality"
},
  "geometry": {"coordinates":[41.45,40.36667],"type":"Point"}
}