{
  "type": "Feature",
  "properties": {
    "gn:admin1_code":"65.0",
    "gn:asciiname":"Agcac",
    "gn:cc2":"TR",
    "gn:country_code":"TR",
    "gn:dem":2242,
    "gn:feature_class":"P",
    "gn:feature_code":"PPL",
    "gn:name":"A\u011fcac",
    "gn:population":0,
    "gn:timezone":"Europe/Istanbul",
    "iso:country":"TR",
    "name:und_x_variant":[
        "Avca\u00e7",
        "A\u011fcac"
    ],
    "wof:name":"Agcac",
    "wof:placetype":"locality"
},
  "geometry": {"coordinates":[44.01667,39.28333],"type":"Point"}
}