{
  "type": "Feature",
  "properties": {
    "gn:admin1_code":"55",
    "gn:asciiname":"Oymali",
    "gn:country_code":"TR",
    "gn:dem":19,
    "gn:feature_class":"P",
    "gn:feature_code":"PPL",
    "gn:name":"Oymal\u0131",
    "gn:population":0,
    "gn:timezone":"Europe/Istanbul",
    "iso:country":"TR",
    "name:tur_x_preferred":[
        "Oymal\u0131"
    ],
    "wof:name":"Oymali",
    "wof:placetype":"locality"
},
  "geometry": {"coordinates":[36.79722,41.18807],"type":"Point"}
}