{
  "type": "Feature",
  "properties": {
    "gn:admin1_code":"31.0",
    "gn:asciiname":"Letnik Gyumyusholuk",
    "gn:country_code":"TR",
    "gn:dem":698,
    "gn:feature_class":"P",
    "gn:feature_code":"PPL",
    "gn:name":"Letnik Gyumyusholuk",
    "gn:population":0,
    "gn:timezone":"Europe/Istanbul",
    "iso:country":"TR",
    "name:und_x_variant":[
        "G\u00fcm\u00fc\u015foluk Yaylas\u0131",
        "G\u00fcm\u00fc\u015foluk"
    ],
    "wof:name":"Letnik Gyumyusholuk",
    "wof:placetype":"locality"
},
  "geometry": {"coordinates":[36.33924,36.5449],"type":"Point"}
}