{
  "type": "Feature",
  "properties": {
    "gn:admin1_code":"19.0",
    "gn:asciiname":"Ayaz",
    "gn:country_code":"TR",
    "gn:dem":1116,
    "gn:feature_class":"P",
    "gn:feature_code":"PPL",
    "gn:name":"Ayaz",
    "gn:population":0,
    "gn:timezone":"Europe/Istanbul",
    "iso:country":"TR",
    "name:cat_x_preferred":[
        "Ayaz"
    ],
    "name:deu_x_preferred":[
        "Ayaz"
    ],
    "name:tur_x_preferred":[
        "Ayaz"
    ],
    "wof:name":"Ayaz",
    "wof:placetype":"locality"
},
  "geometry": {"coordinates":[34.85729,40.67793],"type":"Point"}
}