{
  "type": "Feature",
  "properties": {
    "iso:country":"TR",
    "name:tur_x_preferred":[
        "\u00c7\u0131ra\u011fan"
    ],
    "wof:name":"Ciragan",
    "wof:placetype":"neighbourhood"
},
  "geometry": {"coordinates":[29.01904171327406,41.0457853243112],"type":"Point"}
}