{
  "type": "Feature",
  "properties": {
    "gn:admin1_code":"38",
    "gn:asciiname":"Ayvacik",
    "gn:country_code":"TR",
    "gn:dem":1417,
    "gn:feature_class":"P",
    "gn:feature_code":"PPL",
    "gn:name":"Ayvac\u0131k",
    "gn:population":0,
    "gn:timezone":"Europe/Istanbul",
    "iso:country":"TR",
    "name:und_x_variant":[
        "Cabe",
        "Ayvac\u0131k"
    ],
    "wof:name":"Ayvacik",
    "wof:placetype":"locality"
},
  "geometry": {"coordinates":[36.03795,38.5912],"type":"Point"}
}