{
  "type": "Feature",
  "properties": {
    "gn:admin1_code":"63",
    "gn:asciiname":"Tatlikuyu",
    "gn:country_code":"TR",
    "gn:dem":382,
    "gn:feature_class":"P",
    "gn:feature_code":"PPL",
    "gn:name":"Tatl\u0131kuyu",
    "gn:population":0,
    "gn:timezone":"Europe/Istanbul",
    "iso:country":"TR",
    "name:tur_x_preferred":[
        "Tatl\u0131kuyu"
    ],
    "wof:name":"Tatlikuyu",
    "wof:placetype":"locality"
},
  "geometry": {"coordinates":[38.73296,36.71758],"type":"Point"}
}