{
  "type": "Feature",
  "properties": {
    "gn:admin1_code":"57",
    "gn:asciiname":"Yesilkoy",
    "gn:country_code":"TR",
    "gn:dem":89,
    "gn:feature_class":"P",
    "gn:feature_code":"PPL",
    "gn:name":"Ye\u015filk\u00f6y",
    "gn:population":0,
    "gn:timezone":"Europe/Istanbul",
    "iso:country":"TR",
    "name:tur_x_preferred":[
        "Ye\u015filk\u00f6y"
    ],
    "wof:name":"Yesilkoy",
    "wof:placetype":"locality"
},
  "geometry": {"coordinates":[35.46502,41.61827],"type":"Point"}
}