{
  "type": "Feature",
  "properties": {
    "gn:admin1_code":"52.0",
    "gn:asciiname":"Nurettinkoy",
    "gn:country_code":"TR",
    "gn:dem":328,
    "gn:feature_class":"P",
    "gn:feature_code":"PPL",
    "gn:name":"Nurettink\u00f6y",
    "gn:population":0,
    "gn:timezone":"Europe/Istanbul",
    "iso:country":"TR",
    "name:tur_x_preferred":[
        "Nurettink\u00f6y"
    ],
    "name:tur_x_variant":[
        "Nurettin"
    ],
    "wof:name":"Nurettinkoy",
    "wof:placetype":"locality"
},
  "geometry": {"coordinates":[37.11132,40.97685],"type":"Point"}
}