{
  "type": "Feature",
  "properties": {
    "gn:admin1_code":"89",
    "gn:asciiname":"Hisarduzu",
    "gn:country_code":"TR",
    "gn:dem":317,
    "gn:feature_class":"P",
    "gn:feature_code":"PPL",
    "gn:name":"Hisard\u00fcz\u00fc",
    "gn:population":0,
    "gn:timezone":"Europe/Istanbul",
    "iso:country":"TR",
    "wof:name":"Hisarduzu",
    "wof:placetype":"locality"
},
  "geometry": {"coordinates":[32.36958,41.29037],"type":"Point"}
}