{
  "type": "Feature",
  "properties": {
    "gn:country":"TR",
    "gn:fcode":"PPL",
    "gn:pop":51792,
    "iso:country":"TR",
    "name:ara_x_preferred":[
        "\u0627\u0648\u0631\u0647\u0627\u0646 \u063a\u0627\u0632\u064a"
    ],
    "name:azb_x_preferred":[
        "\u0627\u0648\u0631\u062e\u0627\u0646 \u063a\u0627\u0632\u06cc"
    ],
    "name:ceb_x_preferred":[
        "Orhangazi"
    ],
    "name:deu_x_preferred":[
        "Orhangazi"
    ],
    "name:eng_x_preferred":[
        "Orhangazi"
    ],
    "name:fas_x_preferred":[
        "\u0627\u0648\u0631\u062e\u0627\u0646 \u063a\u0627\u0632\u06cc"
    ],
    "name:fra_x_preferred":[
        "Orhangazi"
    ],
    "name:gag_x_preferred":[
        "Orhangazi"
    ],
    "name:jpn_x_preferred":[
        "\u30aa\u30eb\u30cf\u30f3\u30ac\u30ba\u30a3"
    ],
    "name:lit_x_preferred":[
        "Orchangazis"
    ],
    "name:min_x_preferred":[
        "Orhangazi"
    ],
    "name:mrj_x_preferred":[
        "\u041e\u0440\u0445\u0430\u043d\u0433\u0430\u0437\u0438"
    ],
    "name:msa_x_preferred":[
        "Orhangazi"
    ],
    "name:nan_x_preferred":[
        "Orhangazi"
    ],
    "name:nld_x_preferred":[
        "Orhangazi"
    ],
    "name:nno_x_preferred":[
        "Orhangazi"
    ],
    "name:nob_x_preferred":[
        "Orhangazi"
    ],
    "name:pnb_x_preferred":[
        "\u0636\u0644\u0639 \u0627\u0648\u0631\u06c1\u0646\u06af\u0627\u0632\u06cc"
    ],
    "name:pol_x_preferred":[
        "Orhangazi"
    ],
    "name:rup_x_preferred":[
        "Orhangazi"
    ],
    "name:rus_x_preferred":[
        "\u041e\u0440\u0445\u0430\u043d\u0433\u0430\u0437\u0438"
    ],
    "name:spa_x_preferred":[
        "Orhangazi"
    ],
    "name:swa_x_preferred":[
        "Orhangazi"
    ],
    "name:tur_x_preferred":[
        "Orhangazi"
    ],
    "name:ukr_x_preferred":[
        "\u041e\u0440\u0445\u0430\u043d\u0433\u0430\u0437\u0456"
    ],
    "name:unk_x_variant":[
        "Pazark\u00f6y"
    ],
    "name:urd_x_preferred":[
        "\u0627\u0648\u0631\u062e\u0627\u0646 \u063a\u0627\u0632\u06cc"
    ],
    "name:vie_x_preferred":[
        "Orhangazi"
    ],
    "name:zho_x_preferred":[
        "\u5967\u723e\u6f22\u52a0\u6fdf"
    ],
    "qs:name":"Orhangazi",
    "qs:name_adm0":"Turkey",
    "qs:name_adm1":"Bursa",
    "qs:photos_9k":1,
    "qs:photos_9r":1,
    "qs:photos_all":5,
    "qs:photos_sr":0,
    "qs:placetype":"Town",
    "qs:pop_sr":"8",
    "wd:wordcount":188,
    "wof:name":"Orhangazi",
    "wof:placetype":"locality",
    "wof:population":51792
},
  "geometry": {"coordinates":[29.30889,40.48917],"type":"Point"}
}