{
  "type": "Feature",
  "properties": {
    "gn:country":"TR",
    "gn:fcode":"PPL",
    "gn:pop":51792,
    "iso:country":"TR",
    "name:unk_x_variant":[
        "Pazark\u00f6y"
    ],
    "qs:name":"Orhangazi",
    "qs:name_adm0":"Turkey",
    "qs:name_adm1":"Bursa",
    "qs:photos_9k":1,
    "qs:photos_9r":1,
    "qs:photos_all":5,
    "qs:photos_sr":0,
    "qs:placetype":"Town",
    "qs:pop_sr":"8",
    "wd:wordcount":188,
    "wof:name":"Orhangazi",
    "wof:placetype":"locality",
    "wof:population":51792
},
  "geometry": {"coordinates":[29.30889,40.48917],"type":"Point"}
}