{
  "type": "Feature",
  "properties": {
    "gn:admin1_code":"09",
    "gn:asciiname":"Mutaflar Mahallesi",
    "gn:country_code":"TR",
    "gn:dem":421,
    "gn:feature_class":"P",
    "gn:feature_code":"PPL",
    "gn:name":"Mutaflar Mahallesi",
    "gn:population":0,
    "gn:timezone":"Europe/Istanbul",
    "iso:country":"TR",
    "name:tur_x_preferred":[
        "Mutaflar Mahallesi"
    ],
    "name:tur_x_variant":[
        "K\u00f6seler"
    ],
    "wof:name":"Mutaflar Mahallesi",
    "wof:placetype":"locality"
},
  "geometry": {"coordinates":[27.87869,37.63007],"type":"Point"}
}