{
  "type": "Feature",
  "properties": {
    "gn:admin1_code":"77.0",
    "gn:asciiname":"Pamuktas",
    "gn:country_code":"TR",
    "gn:dem":1796,
    "gn:feature_class":"P",
    "gn:feature_code":"PPL",
    "gn:name":"Pamukta\u015f",
    "gn:population":0,
    "gn:timezone":"Europe/Istanbul",
    "iso:country":"TR",
    "name:tur_x_preferred":[
        "Pamukta\u015f"
    ],
    "wof:name":"Pamuktas",
    "wof:placetype":"locality"
},
  "geometry": {"coordinates":[39.96748,40.41268],"type":"Point"}
}