{
  "type": "Feature",
  "properties": {
    "gn:admin1_code":"21",
    "gn:asciiname":"Kilavuztepe",
    "gn:country_code":"TR",
    "gn:dem":649,
    "gn:feature_class":"P",
    "gn:feature_code":"PPL",
    "gn:name":"K\u0131lavuztepe",
    "gn:population":0,
    "gn:timezone":"Europe/Istanbul",
    "iso:country":"TR",
    "name:tur_x_preferred":[
        "K\u0131lavuztepe"
    ],
    "wof:name":"Kilavuztepe",
    "wof:placetype":"locality"
},
  "geometry": {"coordinates":[40.6831,37.74872],"type":"Point"}
}