{
  "type": "Feature",
  "properties": {
    "gn:admin1_code":"21",
    "gn:asciiname":"Kesentas",
    "gn:country_code":"TR",
    "gn:dem":866,
    "gn:feature_class":"P",
    "gn:feature_code":"PPL",
    "gn:name":"Kesenta\u015f",
    "gn:population":0,
    "gn:timezone":"Europe/Istanbul",
    "iso:country":"TR",
    "name:und_x_variant":[
        "Kesenta\u015f",
        "Sincik"
    ],
    "wof:name":"Kesentas",
    "wof:placetype":"locality"
},
  "geometry": {"coordinates":[39.59325,38.20434],"type":"Point"}
}