{
  "type": "Feature",
  "properties": {
    "gn:admin1_code":"17.0",
    "gn:asciiname":"Sogucak",
    "gn:country_code":"TR",
    "gn:dem":408,
    "gn:feature_class":"P",
    "gn:feature_code":"PPL",
    "gn:name":"So\u011fucak",
    "gn:population":0,
    "gn:timezone":"Europe/Istanbul",
    "iso:country":"TR",
    "wof:name":"Sogucak",
    "wof:placetype":"locality"
},
  "geometry": {"coordinates":[27.37097,40.0081],"type":"Point"}
}