{
  "type": "Feature",
  "properties": {
    "gn:admin1_code":"65",
    "gn:asciiname":"Garip",
    "gn:country_code":"TR",
    "gn:dem":2678,
    "gn:feature_class":"P",
    "gn:feature_code":"PPL",
    "gn:name":"Garip",
    "gn:population":0,
    "gn:timezone":"Europe/Istanbul",
    "iso:country":"TR",
    "name:ara_x_preferred":[
        "\u062a\u064a\u0627\u0631 \u0627\u0644\u063a\u0631\u064a\u0628"
    ],
    "name:deu_x_preferred":[
        "Garip"
    ],
    "name:diq_x_preferred":[
        "\u011eerib"
    ],
    "name:ell_x_preferred":[
        "\u0393\u03ba\u03b1\u03c1\u03af\u03c0"
    ],
    "name:tur_x_preferred":[
        "Garip hareketi"
    ],
    "name:und_x_variant":[
        "Karip"
    ],
    "wof:name":"Garip",
    "wof:placetype":"locality"
},
  "geometry": {"coordinates":[42.86667,37.96667],"type":"Point"}
}