{
  "type": "Feature",
  "properties": {
    "gn:admin1_code":"65",
    "gn:asciiname":"Garip",
    "gn:country_code":"TR",
    "gn:dem":2678,
    "gn:feature_class":"P",
    "gn:feature_code":"PPL",
    "gn:name":"Garip",
    "gn:population":0,
    "gn:timezone":"Europe/Istanbul",
    "iso:country":"TR",
    "name:und_x_variant":[
        "Karip",
        "Garip"
    ],
    "wof:name":"Garip",
    "wof:placetype":"locality"
},
  "geometry": {"coordinates":[42.86667,37.96667],"type":"Point"}
}