{
  "type": "Feature",
  "properties": {
    "gn:admin1_code":"69.0",
    "gn:asciiname":"Yaylim",
    "gn:country_code":"TR",
    "gn:dem":1816,
    "gn:feature_class":"P",
    "gn:feature_code":"PPL",
    "gn:name":"Yayl\u0131m",
    "gn:population":0,
    "gn:timezone":"Europe/Istanbul",
    "iso:country":"TR",
    "name:und_x_variant":[
        "Kelahbur",
        "Kelahpur",
        "Yayl\u0131m"
    ],
    "wof:name":"Yaylim",
    "wof:placetype":"locality"
},
  "geometry": {"coordinates":[39.73823,40.26174],"type":"Point"}
}