{
  "type": "Feature",
  "properties": {
    "gn:admin1_code":"41",
    "gn:asciiname":"Sekbanli",
    "gn:country_code":"TR",
    "gn:dem":173,
    "gn:feature_class":"P",
    "gn:feature_code":"PPL",
    "gn:name":"Sekbanl\u0131",
    "gn:population":0,
    "gn:timezone":"Europe/Istanbul",
    "iso:country":"TR",
    "name:tur_x_preferred":[
        "Sekbanl\u0131"
    ],
    "wof:name":"Sekbanli",
    "wof:placetype":"locality"
},
  "geometry": {"coordinates":[29.95107,40.81457],"type":"Point"}
}