{
  "type": "Feature",
  "properties": {
    "gn:admin1_code":"43",
    "gn:asciiname":"Abide",
    "gn:country_code":"TR",
    "gn:dem":658,
    "gn:feature_class":"P",
    "gn:feature_code":"PPL",
    "gn:name":"Abide",
    "gn:population":0,
    "gn:timezone":"Europe/Istanbul",
    "iso:country":"TR",
    "name:tur_x_preferred":[
        "Abide"
    ],
    "wof:name":"Abide",
    "wof:placetype":"locality"
},
  "geometry": {"coordinates":[29.30152,38.93069000000001],"type":"Point"}
}