{
  "type": "Feature",
  "properties": {
    "gn:admin1_code":"65.0",
    "gn:asciiname":"Kilictutan",
    "gn:country_code":"TR",
    "gn:dem":2164,
    "gn:feature_class":"P",
    "gn:feature_code":"PPL",
    "gn:name":"K\u0131l\u0131\u00e7tutan",
    "gn:population":0,
    "gn:timezone":"Europe/Istanbul",
    "iso:country":"TR",
    "name:tur_x_preferred":[
        "Kili\u00e7tutan"
    ],
    "name:tur_x_variant":[
        "K\u0131l\u0131\u00e7tutan"
    ],
    "wof:name":"Kilictutan",
    "wof:placetype":"locality"
},
  "geometry": {"coordinates":[43.57665,37.87801],"type":"Point"}
}