{
  "type": "Feature",
  "properties": {
    "gn:admin1_code":"71",
    "gn:asciiname":"Kurthasanli",
    "gn:country_code":"TR",
    "gn:dem":1029,
    "gn:feature_class":"P",
    "gn:feature_code":"PPLA3",
    "gn:name":"Kurthasanl\u0131",
    "gn:population":0,
    "gn:timezone":"Europe/Istanbul",
    "iso:country":"TR",
    "name:tur_x_preferred":[
        "Kurthasanl\u0131"
    ],
    "wof:name":"Kurthasanli",
    "wof:placetype":"locality"
},
  "geometry": {"coordinates":[32.17528,38.32611],"type":"Point"}
}