{
  "type": "Feature",
  "properties": {
    "gn:admin1_code":"52.0",
    "gn:asciiname":"Ilisar",
    "gn:country_code":"TR",
    "gn:dem":1309,
    "gn:feature_class":"P",
    "gn:feature_code":"PPL",
    "gn:name":"Il\u0131\u015far",
    "gn:population":0,
    "gn:timezone":"Europe/Istanbul",
    "iso:country":"TR",
    "name:tur_x_preferred":[
        "Il\u0131\u015far"
    ],
    "wof:name":"Ilisar",
    "wof:placetype":"locality"
},
  "geometry": {"coordinates":[37.72736,40.43857],"type":"Point"}
}