{
  "type": "Feature",
  "properties": {
    "gn:admin1_code":"71.0",
    "gn:asciiname":"Kucuk Afsar",
    "gn:country_code":"TR",
    "gn:dem":1134,
    "gn:feature_class":"P",
    "gn:feature_code":"PPL",
    "gn:name":"K\u00fc\u00e7\u00fck Af\u015far",
    "gn:population":0,
    "gn:timezone":"Europe/Istanbul",
    "iso:country":"TR",
    "name:tur_x_preferred":[
        "K\u00fc\u00e7\u00fck Af\u015far"
    ],
    "name:tur_x_variant":[
        "Af\u1e63ar"
    ],
    "wof:name":"Kucuk Afsar",
    "wof:placetype":"locality"
},
  "geometry": {"coordinates":[31.74041,37.70481],"type":"Point"}
}