{
  "type": "Feature",
  "properties": {
    "gn:admin1_code":"24",
    "gn:asciiname":"Degirmenkoy",
    "gn:country_code":"TR",
    "gn:dem":1186,
    "gn:feature_class":"P",
    "gn:feature_code":"PPL",
    "gn:name":"De\u011firmenk\u00f6y",
    "gn:population":0,
    "gn:timezone":"Europe/Istanbul",
    "iso:country":"TR",
    "name:tur_x_preferred":[
        "De\u011firmenk\u00f6y"
    ],
    "wof:name":"Degirmenkoy",
    "wof:placetype":"locality"
},
  "geometry": {"coordinates":[39.61697,39.63077],"type":"Point"}
}