{
  "type": "Feature",
  "properties": {
    "gn:admin1_code":"87.0",
    "gn:asciiname":"Gurpinar",
    "gn:country_code":"TR",
    "gn:dem":28,
    "gn:feature_class":"P",
    "gn:feature_code":"PPL",
    "gn:name":"G\u00fcrp\u0131nar",
    "gn:population":0,
    "gn:timezone":"Europe/Istanbul",
    "iso:country":"TR",
    "name:und_x_variant":[
        "G\u00fcrp\u0131nar",
        "Derek\u00f6y"
    ],
    "wof:name":"Gurpinar",
    "wof:placetype":"locality"
},
  "geometry": {"coordinates":[32.41748,41.62674000000001],"type":"Point"}
}