{
  "type": "Feature",
  "properties": {
    "gn:admin1_code":"53.0",
    "gn:asciiname":"Cimenli",
    "gn:country_code":"TR",
    "gn:dem":316,
    "gn:feature_class":"P",
    "gn:feature_code":"PPL",
    "gn:name":"\u00c7imenli",
    "gn:population":0,
    "gn:timezone":"Europe/Istanbul",
    "iso:country":"TR",
    "name:tur_x_preferred":[
        "\u00c7imenli"
    ],
    "wof:name":"Cimenli",
    "wof:placetype":"locality"
},
  "geometry": {"coordinates":[40.54706,40.91842000000001],"type":"Point"}
}