{
  "type": "Feature",
  "properties": {
    "gn:admin1_code":"07",
    "gn:asciiname":"Yenikoy",
    "gn:country_code":"TR",
    "gn:dem":1430,
    "gn:feature_class":"P",
    "gn:feature_code":"PPL",
    "gn:name":"Yenik\u00f6y",
    "gn:population":0,
    "gn:timezone":"Europe/Istanbul",
    "iso:country":"TR",
    "name:und_x_variant":[
        "Girenes",
        "Gerenes Yayla",
        "Girense",
        "Yenik\u00f6y"
    ],
    "wof:name":"Yenikoy",
    "wof:placetype":"locality"
},
  "geometry": {"coordinates":[32.26667,36.71667],"type":"Point"}
}