{
  "type": "Feature",
  "properties": {
    "gn:admin1_code":"81",
    "gn:asciiname":"Isahacili",
    "gn:country_code":"TR",
    "gn:dem":3,
    "gn:feature_class":"P",
    "gn:feature_code":"PPL",
    "gn:name":"\u0130sahac\u0131l\u0131",
    "gn:population":0,
    "gn:timezone":"Europe/Istanbul",
    "iso:country":"TR",
    "name:deu_x_preferred":[
        "\u0130sahac\u0131l\u0131"
    ],
    "name:msa_x_preferred":[
        "\u0130sahac\u0131l\u0131"
    ],
    "name:tur_x_preferred":[
        "\u0130sahac\u0131l\u0131"
    ],
    "name:vie_x_preferred":[
        "\u0130sahac\u0131l\u0131"
    ],
    "wof:name":"Isahacili",
    "wof:placetype":"locality"
},
  "geometry": {"coordinates":[35.29126,36.68695],"type":"Point"}
}