{
  "type": "Feature",
  "properties": {
    "gn:admin1_code":"23",
    "gn:asciiname":"Okcular",
    "gn:country_code":"TR",
    "gn:dem":1275,
    "gn:feature_class":"P",
    "gn:feature_code":"PPL",
    "gn:name":"Ok\u00e7ular",
    "gn:population":0,
    "gn:timezone":"Europe/Istanbul",
    "iso:country":"TR",
    "name:und_x_variant":[
        "Ak\u00e7\u0131yan",
        "Ok\u00e7ular",
        "Ok\u00e7\u0131yan"
    ],
    "wof:name":"Okcular",
    "wof:placetype":"locality"
},
  "geometry": {"coordinates":[40.02056,39.07505],"type":"Point"}
}