{
  "type": "Feature",
  "properties": {
    "gn:country":"TR",
    "gn:fcode":"PPL",
    "gn:population":3615,
    "iso:country":"TR",
    "name:ast_x_preferred":[
        "Bekilli"
    ],
    "name:ceb_x_preferred":[
        "Bekilli"
    ],
    "name:deu_x_preferred":[
        "Bekilli"
    ],
    "name:diq_x_preferred":[
        "Bekilli"
    ],
    "name:eng_x_preferred":[
        "Bekilli"
    ],
    "name:epo_x_preferred":[
        "Bekilli"
    ],
    "name:fas_x_preferred":[
        "\u0628\u06a9\u06cc\u0644\u06cc"
    ],
    "name:fra_x_preferred":[
        "Bekilli"
    ],
    "name:ita_x_preferred":[
        "Distretto di Bekilli"
    ],
    "name:lit_x_preferred":[
        "Bekilis"
    ],
    "name:mrj_x_preferred":[
        "\u0411\u0435\u043a\u0438\u043b\u043b\u0438"
    ],
    "name:msa_x_preferred":[
        "Bekilli"
    ],
    "name:nan_x_preferred":[
        "Bekilli"
    ],
    "name:nld_x_preferred":[
        "Bekilli"
    ],
    "name:nob_x_preferred":[
        "Bekilli"
    ],
    "name:pnb_x_preferred":[
        "\u0636\u0644\u0639 \u0628\u06cc\u06a9\u0644\u06cc"
    ],
    "name:swa_x_preferred":[
        "Bekilli"
    ],
    "name:tat_x_preferred":[
        "\u0411\u0435\u043a\u0438\u043b\u043b\u0438"
    ],
    "name:tur_x_preferred":[
        "Bekilli"
    ],
    "name:urd_x_preferred":[
        "\u0628\u06cc\u06a9\u06cc\u0644\u06cc"
    ],
    "name:vie_x_preferred":[
        "Bekilli"
    ],
    "qs:name":"Bekilli",
    "qs:photos_9r":0,
    "qs:photos_sr":0,
    "qs:pop_sr":"4",
    "wd:wordcount":259,
    "wof:name":"Bekilli",
    "wof:placetype":"locality",
    "wof:population":3615
},
  "geometry": {"coordinates":[29.4197,38.23105],"type":"Point"}
}