{
  "type": "Feature",
  "properties": {
    "gn:admin1_code":"41.0",
    "gn:asciiname":"Bagirkanli",
    "gn:country_code":"TR",
    "gn:dem":47,
    "gn:feature_class":"P",
    "gn:feature_code":"PPL",
    "gn:name":"Ba\u011f\u0131rkanl\u0131",
    "gn:population":0,
    "gn:timezone":"Europe/Istanbul",
    "iso:country":"TR",
    "name:tur_x_preferred":[
        "Ba\u011f\u0131rkanl\u0131"
    ],
    "name:und_x_variant":[
        "Parganl\u0131"
    ],
    "wof:name":"Bagirkanli",
    "wof:placetype":"locality"
},
  "geometry": {"coordinates":[30.01073,41.12684],"type":"Point"}
}