{
  "type": "Feature",
  "properties": {
    "gn:admin1_code":"52.0",
    "gn:asciiname":"Bayiralan",
    "gn:country_code":"TR",
    "gn:dem":677,
    "gn:feature_class":"P",
    "gn:feature_code":"PPL",
    "gn:name":"Bay\u0131ralan",
    "gn:population":0,
    "gn:timezone":"Europe/Istanbul",
    "iso:country":"TR",
    "name:und_x_variant":[
        "H\u00f6l\u00fcr",
        "H\u00fcl\u00fcr",
        "Bay\u0131ralan"
    ],
    "wof:name":"Bayiralan",
    "wof:placetype":"locality"
},
  "geometry": {"coordinates":[37.53309,40.71138],"type":"Point"}
}