{
  "type": "Feature",
  "properties": {
    "gn:admin1_code":"87",
    "gn:asciiname":"Yaylayazicilar",
    "gn:country_code":"TR",
    "gn:dem":23,
    "gn:feature_class":"P",
    "gn:feature_code":"PPL",
    "gn:name":"Yaylayaz\u0131c\u0131lar",
    "gn:population":0,
    "gn:timezone":"Europe/Istanbul",
    "iso:country":"TR",
    "wof:name":"Yaylayazicilar",
    "wof:placetype":"locality"
},
  "geometry": {"coordinates":[32.54073,41.77955],"type":"Point"}
}