{
  "type": "Feature",
  "properties": {
    "gn:admin1_code":"4.0",
    "gn:asciiname":"Ucoymak",
    "gn:country_code":"TR",
    "gn:dem":1613,
    "gn:feature_class":"P",
    "gn:feature_code":"PPL",
    "gn:name":"\u00dc\u00e7oymak",
    "gn:population":0,
    "gn:timezone":"Europe/Istanbul",
    "iso:country":"TR",
    "name:tur_x_preferred":[
        "U\u00e7aymak"
    ],
    "name:tur_x_variant":[
        "\u00dc\u00e7oymak"
    ],
    "wof:name":"Ucoymak",
    "wof:placetype":"locality"
},
  "geometry": {"coordinates":[42.7449,39.18195],"type":"Point"}
}