{
  "type": "Feature",
  "properties": {
    "gn:admin1_code":"64",
    "gn:asciiname":"Tasavlu",
    "gn:country_code":"TR",
    "gn:dem":1091,
    "gn:feature_class":"P",
    "gn:feature_code":"PPL",
    "gn:name":"Ta\u015favlu",
    "gn:population":0,
    "gn:timezone":"Europe/Istanbul",
    "iso:country":"TR",
    "name:tur_x_preferred":[
        "Ta\u015favlu"
    ],
    "wof:name":"Tasavlu",
    "wof:placetype":"locality"
},
  "geometry": {"coordinates":[29.36729,38.78367],"type":"Point"}
}