{
  "type": "Feature",
  "properties": {
    "gn:admin1_code":"11.0",
    "gn:asciiname":"Damdindere",
    "gn:country_code":"TR",
    "gn:dem":1243,
    "gn:feature_class":"P",
    "gn:feature_code":"PPL",
    "gn:name":"Damdindere",
    "gn:population":0,
    "gn:timezone":"Europe/Istanbul",
    "iso:country":"TR",
    "name:tur_x_preferred":[
        "Damdindere"
    ],
    "name:und_x_variant":[
        "Dand\u0131norman\u0131",
        "Dandil Orman\u0131"
    ],
    "wof:name":"Damdindere",
    "wof:placetype":"locality"
},
  "geometry": {"coordinates":[29.96,39.66],"type":"Point"}
}