{
  "type": "Feature",
  "properties": {
    "gn:admin1_code":"43",
    "gn:asciiname":"Kinik",
    "gn:country_code":"TR",
    "gn:dem":820,
    "gn:feature_class":"P",
    "gn:feature_code":"PPL",
    "gn:name":"K\u0131n\u0131k",
    "gn:population":0,
    "gn:timezone":"Europe/Istanbul",
    "iso:country":"TR",
    "name:tur_x_preferred":[
        "K\u0131n\u0131k"
    ],
    "wof:name":"Kinik",
    "wof:placetype":"locality"
},
  "geometry": {"coordinates":[28.84819,39.19406],"type":"Point"}
}