{
  "type": "Feature",
  "properties": {
    "gn:admin1_code":"37",
    "gn:asciiname":"Sofular",
    "gn:country_code":"TR",
    "gn:dem":137,
    "gn:feature_class":"P",
    "gn:feature_code":"PPL",
    "gn:name":"Sofular",
    "gn:population":0,
    "gn:timezone":"Europe/Istanbul",
    "iso:country":"TR",
    "wof:name":"Sofular",
    "wof:placetype":"locality"
},
  "geometry": {"coordinates":[32.98275,41.87482],"type":"Point"}
}