{
  "type": "Feature",
  "properties": {
    "gn:admin1_code":"48",
    "gn:asciiname":"Bayir",
    "gn:country_code":"TR",
    "gn:dem":422,
    "gn:feature_class":"P",
    "gn:feature_code":"PPL",
    "gn:name":"Bay\u0131r",
    "gn:population":4005,
    "gn:timezone":"Europe/Istanbul",
    "iso:country":"TR",
    "name:und_x_variant":[
        "Bay\u0131rk\u00f6y",
        "Bay\u0131r"
    ],
    "wof:name":"Bayir",
    "wof:placetype":"locality",
    "wof:population":4005
},
  "geometry": {"coordinates":[28.21677,37.26774],"type":"Point"}
}