{
  "type": "Feature",
  "properties": {
    "gn:admin1_code":"21",
    "gn:asciiname":"Alpu",
    "gn:country_code":"TR",
    "gn:dem":708,
    "gn:feature_class":"P",
    "gn:feature_code":"PPL",
    "gn:name":"Alpu",
    "gn:population":0,
    "gn:timezone":"Europe/Istanbul",
    "iso:country":"TR",
    "name:ceb_x_preferred":[
        "Alpu"
    ],
    "name:deu_x_preferred":[
        "Alpu"
    ],
    "name:fra_x_preferred":[
        "Alpu"
    ],
    "name:mrj_x_preferred":[
        "\u0410\u043b\u043f\u0443"
    ],
    "name:msa_x_preferred":[
        "Alpu"
    ],
    "name:nld_x_preferred":[
        "Alpu"
    ],
    "name:nor_x_preferred":[
        "Alpu"
    ],
    "name:swa_x_preferred":[
        "Alpu"
    ],
    "name:tur_x_preferred":[
        "Alpu"
    ],
    "name:und_x_variant":[
        "Karaver",
        "Karaveri",
        "Alpu",
        "Karaveli"
    ],
    "name:urd_x_preferred":[
        "\u0627\u0644\u067e\u0648"
    ],
    "name:vie_x_preferred":[
        "Alpu"
    ],
    "wof:name":"Alpu",
    "wof:placetype":"locality"
},
  "geometry": {"coordinates":[40.13525,38.04761],"type":"Point"}
}