{
  "type": "Feature",
  "properties": {
    "gn:country":"TR",
    "gn:fcode":"PPLX",
    "gn:pop":0,
    "iso:country":"TR",
    "name:ast_x_preferred":[
        "Bah\u00e7elievler"
    ],
    "name:aze_x_preferred":[
        "Ba\u011f\u00e7al\u0131evl\u0259r"
    ],
    "name:cat_x_preferred":[
        "Bah\u00e7elievler"
    ],
    "name:ceb_x_preferred":[
        "Bah\u00e7elievler"
    ],
    "name:deu_x_preferred":[
        "Bah\u00e7elievler"
    ],
    "name:diq_x_preferred":[
        "Bah\u00e7elievler"
    ],
    "name:fas_x_preferred":[
        "\u0628\u0627\u063a\u0686\u0647\u200c\u0644\u06cc\u200c\u0627\u0648\u0644\u0631"
    ],
    "name:fra_x_preferred":[
        "Bah\u00e7elievler"
    ],
    "name:hun_x_preferred":[
        "Bah\u00e7elievler"
    ],
    "name:hye_x_preferred":[
        "\u0532\u0561\u0570\u0579\u0565\u056c\u056b\u0587\u056c\u0565\u0580"
    ],
    "name:ita_x_preferred":[
        "Bah\u00e7elievler"
    ],
    "name:lav_x_preferred":[
        "Bah\u010delievleras rajons"
    ],
    "name:mrj_x_preferred":[
        "\u0411\u0430\u0445\u0447\u0435\u043b\u0438\u044d\u0432\u043b\u0435\u0440"
    ],
    "name:msa_x_preferred":[
        "Bah\u00e7elievler"
    ],
    "name:nld_x_preferred":[
        "Bah\u00e7elievler"
    ],
    "name:nor_x_preferred":[
        "Bah\u00e7elievler"
    ],
    "name:pnb_x_preferred":[
        "\u0628\u0627\u063a\u0644\u06cc\u0648\u0644\u0631"
    ],
    "name:por_x_preferred":[
        "Bah\u00e7elievler"
    ],
    "name:rus_x_preferred":[
        "\u0411\u0430\u0445\u0447\u0435\u043b\u0438\u044d\u0432\u043b\u0435\u0440"
    ],
    "name:spa_x_preferred":[
        "Bah\u00e7elievler"
    ],
    "name:swa_x_preferred":[
        "Bah\u00e7elievler"
    ],
    "name:tur_x_preferred":[
        "Bah\u00e7elievler"
    ],
    "name:unk_x_variant":[
        "Yukar\u0131 \u0130napl\u0131"
    ],
    "name:urd_x_preferred":[
        "\u0628\u0627\u063a\u0686\u06c1 \u0644\u06cc\u0648\u0644\u0631"
    ],
    "name:vie_x_preferred":[
        "Bah\u00e7elievler"
    ],
    "qs:name":"Bah\u00e7elievler",
    "qs:name_adm0":"Turkey",
    "qs:name_adm1":"Mersin",
    "qs:photos":9,
    "qs:photos_1k":2,
    "qs:photos_9k":1,
    "qs:photos_9r":1,
    "qs:photos_all":9,
    "qs:photos_sr":1,
    "qs:placetype":"Suburb",
    "qs:pop_sr":"0",
    "wd:wordcount":573,
    "wof:name":"Bah\u00e7elievler",
    "wof:placetype":"neighbourhood",
    "wof:population":0
},
  "geometry": {"coordinates":[35.35,36.95],"type":"Point"}
}