{
  "type": "Feature",
  "properties": {
    "gn:country":"TR",
    "gn:fcode":"PPLX",
    "gn:pop":0,
    "iso:country":"TR",
    "name:unk_x_variant":[
        "Yukar\u0131 \u0130napl\u0131"
    ],
    "qs:name":"Bah\u00e7elievler",
    "qs:name_adm0":"Turkey",
    "qs:name_adm1":"Mersin",
    "qs:photos":9,
    "qs:photos_1k":2,
    "qs:photos_9k":1,
    "qs:photos_9r":1,
    "qs:photos_all":9,
    "qs:photos_sr":1,
    "qs:placetype":"Suburb",
    "qs:pop_sr":"0",
    "wd:wordcount":573,
    "wof:name":"Bah\u00e7elievler",
    "wof:placetype":"neighbourhood",
    "wof:population":0
},
  "geometry": {"coordinates":[35.35,36.95],"type":"Point"}
}