{
  "type": "Feature",
  "properties": {
    "gn:admin1_code":"03",
    "gn:asciiname":"Muratli",
    "gn:country_code":"TR",
    "gn:dem":1416,
    "gn:feature_class":"P",
    "gn:feature_code":"PPL",
    "gn:name":"Muratl\u0131",
    "gn:population":0,
    "gn:timezone":"Europe/Istanbul",
    "iso:country":"TR",
    "wof:name":"Muratli",
    "wof:placetype":"locality"
},
  "geometry": {"coordinates":[30.13942,38.17678],"type":"Point"}
}