{
  "type": "Feature",
  "properties": {
    "gn:admin1_code":"38",
    "gn:asciiname":"Baskoy",
    "gn:country_code":"TR",
    "gn:dem":1387,
    "gn:feature_class":"P",
    "gn:feature_code":"PPL",
    "gn:name":"Ba\u015fk\u00f6y",
    "gn:population":0,
    "gn:timezone":"Europe/Istanbul",
    "iso:country":"TR",
    "wof:name":"Baskoy",
    "wof:placetype":"locality"
},
  "geometry": {"coordinates":[34.93675,38.39341],"type":"Point"}
}