{
  "type": "Feature",
  "properties": {
    "gn:admin1_code":"4.0",
    "gn:asciiname":"Kuskaya",
    "gn:country_code":"TR",
    "gn:dem":1678,
    "gn:feature_class":"P",
    "gn:feature_code":"PPL",
    "gn:name":"Ku\u015fkaya",
    "gn:population":0,
    "gn:timezone":"Europe/Istanbul",
    "iso:country":"TR",
    "name:tur_x_preferred":[
        "Ku\u015fkaya"
    ],
    "wof:name":"Kuskaya",
    "wof:placetype":"locality"
},
  "geometry": {"coordinates":[42.81686,39.11489],"type":"Point"}
}