{
  "type": "Feature",
  "properties": {
    "gn:admin1_code":"37.0",
    "gn:asciiname":"Salgam",
    "gn:country_code":"TR",
    "gn:dem":1014,
    "gn:feature_class":"P",
    "gn:feature_code":"PPL",
    "gn:name":"\u015ealgam",
    "gn:population":0,
    "gn:timezone":"Europe/Istanbul",
    "iso:country":"TR",
    "wof:name":"Salgam",
    "wof:placetype":"locality"
},
  "geometry": {"coordinates":[33.66667,41.65],"type":"Point"}
}