{
  "type": "Feature",
  "properties": {
    "gn:admin1_code":"17",
    "gn:asciiname":"Kalkim",
    "gn:country_code":"TR",
    "gn:dem":232,
    "gn:feature_class":"P",
    "gn:feature_code":"PPLA3",
    "gn:name":"Kalk\u0131m",
    "gn:population":2198,
    "gn:timezone":"Europe/Istanbul",
    "iso:country":"TR",
    "name:und_x_variant":[
        "Naipli",
        "Kalk\u0131m"
    ],
    "wof:name":"Kalkim",
    "wof:placetype":"locality",
    "wof:population":2198
},
  "geometry": {"coordinates":[27.215,39.81167],"type":"Point"}
}