{
  "type": "Feature",
  "properties": {
    "gn:admin1_code":"63.0",
    "gn:asciiname":"Aylak",
    "gn:country_code":"TR",
    "gn:dem":399,
    "gn:feature_class":"P",
    "gn:feature_code":"PPL",
    "gn:name":"Aylak",
    "gn:population":0,
    "gn:timezone":"Europe/Istanbul",
    "iso:country":"TR",
    "name:tur_x_preferred":[
        "Aylak"
    ],
    "name:und_x_variant":[
        "Resmel Sayt",
        "Avlak"
    ],
    "wof:name":"Aylak",
    "wof:placetype":"locality"
},
  "geometry": {"coordinates":[39.16194,36.81056],"type":"Point"}
}