{
  "type": "Feature",
  "properties": {
    "gn:admin1_code":"40",
    "gn:asciiname":"Kortolu",
    "gn:country_code":"TR",
    "gn:dem":925,
    "gn:feature_class":"P",
    "gn:feature_code":"PPL",
    "gn:name":"Kortolu",
    "gn:population":0,
    "gn:timezone":"Europe/Istanbul",
    "iso:country":"TR",
    "name:tur_x_preferred":[
        "Kortolu"
    ],
    "name:tur_x_variant":[
        "Kortulu"
    ],
    "wof:name":"Kortolu",
    "wof:placetype":"locality"
},
  "geometry": {"coordinates":[34.01058,39.07585],"type":"Point"}
}