{
  "type": "Feature",
  "properties": {
    "gn:admin1_code":"86.0",
    "gn:asciiname":"Bagdasan",
    "gn:country_code":"TR",
    "gn:dem":1968,
    "gn:feature_class":"P",
    "gn:feature_code":"PPL",
    "gn:name":"Ba\u011fda\u015fan",
    "gn:population":0,
    "gn:timezone":"Europe/Istanbul",
    "iso:country":"TR",
    "name:und_x_variant":[
        "K\u0131nzodamal",
        "Ba\u011fda\u015fan"
    ],
    "wof:name":"Bagdasan",
    "wof:placetype":"locality"
},
  "geometry": {"coordinates":[42.3903,41.05776],"type":"Point"}
}