{
  "type": "Feature",
  "properties": {
    "gn:country":"TR",
    "gn:fcode":"PPL",
    "gn:pop":238,
    "iso:country":"TR",
    "name:unk_x_variant":[
        "\u015eavik"
    ],
    "qs:name":"\u00c7engelli",
    "qs:photos_9r":0,
    "qs:photos_sr":0,
    "qs:pop_sr":"2",
    "wof:name":"\u00c7engelli",
    "wof:placetype":"locality",
    "wof:population":238
},
  "geometry": {"coordinates":[38.48528,36.87833],"type":"Point"}
}