{
  "type": "Feature",
  "properties": {
    "gn:admin1_code":"20",
    "gn:asciiname":"Armutalani",
    "gn:country_code":"TR",
    "gn:dem":1215,
    "gn:feature_class":"P",
    "gn:feature_code":"PPL",
    "gn:name":"Armutalan\u0131",
    "gn:population":0,
    "gn:timezone":"Europe/Istanbul",
    "iso:country":"TR",
    "name:und_x_variant":[
        "Armutalan\u0131",
        "Hamidiye"
    ],
    "wof:name":"Armutalani",
    "wof:placetype":"locality"
},
  "geometry": {"coordinates":[29.60481,37.8956],"type":"Point"}
}