{
  "type": "Feature",
  "properties": {
    "gn:admin1_code":"82.0",
    "gn:asciiname":"Kiranozu",
    "gn:country_code":"TR",
    "gn:dem":1014,
    "gn:feature_class":"P",
    "gn:feature_code":"PPL",
    "gn:name":"Kiran\u00f6z\u00fc",
    "gn:population":0,
    "gn:timezone":"Europe/Istanbul",
    "iso:country":"TR",
    "wof:name":"Kiranozu",
    "wof:placetype":"locality"
},
  "geometry": {"coordinates":[32.78016,40.90598],"type":"Point"}
}