{
  "type": "Feature",
  "properties": {
    "gn:admin1_code":"63",
    "gn:asciiname":"Sultantepe",
    "gn:country_code":"TR",
    "gn:dem":438,
    "gn:feature_class":"P",
    "gn:feature_code":"PPL",
    "gn:name":"Sultantepe",
    "gn:population":0,
    "gn:timezone":"Europe/Istanbul",
    "iso:country":"TR",
    "name:deu_x_preferred":[
        "Sultantepe"
    ],
    "name:fra_x_preferred":[
        "Sultantepe"
    ],
    "name:pol_x_preferred":[
        "Sultantepe"
    ],
    "name:slv_x_preferred":[
        "Sultantepe"
    ],
    "name:tur_x_preferred":[
        "Sultantepe H\u00f6y\u00fc\u011f\u00fc"
    ],
    "wof:name":"Sultantepe",
    "wof:placetype":"locality"
},
  "geometry": {"coordinates":[38.907,37.05081],"type":"Point"}
}