{
  "type": "Feature",
  "properties": {
    "gn:admin1_code":"76",
    "gn:asciiname":"Barinc",
    "gn:country_code":"TR",
    "gn:dem":608,
    "gn:feature_class":"P",
    "gn:feature_code":"PPL",
    "gn:name":"Bar\u0131n\u00e7",
    "gn:population":0,
    "gn:timezone":"Europe/Istanbul",
    "iso:country":"TR",
    "wof:name":"Barinc",
    "wof:placetype":"locality"
},
  "geometry": {"coordinates":[41.36667,38.03333],"type":"Point"}
}