{
  "type": "Feature",
  "properties": {
    "gn:admin1_code":"71",
    "gn:asciiname":"Asagi Kizilca",
    "gn:country_code":"TR",
    "gn:dem":997,
    "gn:feature_class":"P",
    "gn:feature_code":"PPL",
    "gn:name":"A\u015fa\u011f\u0131 K\u0131zilca",
    "gn:population":0,
    "gn:timezone":"Europe/Istanbul",
    "iso:country":"TR",
    "name:und_x_variant":[
        "A\u015fa\u011f\u0131 K\u0131zilca",
        "\u00c7una"
    ],
    "wof:name":"Asagi Kizilca",
    "wof:placetype":"locality"
},
  "geometry": {"coordinates":[32.81038,36.98513],"type":"Point"}
}