{
  "type": "Feature",
  "properties": {
    "gn:admin1_code":"21",
    "gn:asciiname":"Gokpelit",
    "gn:country_code":"TR",
    "gn:dem":987,
    "gn:feature_class":"P",
    "gn:feature_code":"PPL",
    "gn:name":"G\u00f6kpelit",
    "gn:population":0,
    "gn:timezone":"Europe/Istanbul",
    "iso:country":"TR",
    "wof:name":"Gokpelit",
    "wof:placetype":"locality"
},
  "geometry": {"coordinates":[39.46667,38.28333],"type":"Point"}
}