{
  "type": "Feature",
  "properties": {
    "gn:admin1_code":"49.0",
    "gn:asciiname":"Ibrahim",
    "gn:country_code":"TR",
    "gn:dem":1463,
    "gn:feature_class":"P",
    "gn:feature_code":"PPL",
    "gn:name":"\u0130brahim",
    "gn:population":0,
    "gn:timezone":"Europe/Istanbul",
    "iso:country":"TR",
    "name:tur_x_preferred":[
        "\u0130brahim"
    ],
    "wof:name":"Ibrahim",
    "wof:placetype":"locality"
},
  "geometry": {"coordinates":[42.20122,39.08055],"type":"Point"}
}