{
  "type": "Feature",
  "properties": {
    "gn:admin1_code":"52",
    "gn:asciiname":"Gundogdu",
    "gn:country_code":"TR",
    "gn:dem":723,
    "gn:feature_class":"P",
    "gn:feature_code":"PPL",
    "gn:name":"G\u00fcndo\u011fdu",
    "gn:population":0,
    "gn:timezone":"Europe/Istanbul",
    "iso:country":"TR",
    "name:tur_x_preferred":[
        "G\u00fcndo\u011fdu"
    ],
    "wof:name":"Gundogdu",
    "wof:placetype":"locality"
},
  "geometry": {"coordinates":[37.47707,40.84874],"type":"Point"}
}