{
  "type": "Feature",
  "properties": {
    "gn:admin1_code":"57.0",
    "gn:asciiname":"Karamusali",
    "gn:country_code":"TR",
    "gn:dem":1112,
    "gn:feature_class":"P",
    "gn:feature_code":"PPL",
    "gn:name":"Karamusal\u0131",
    "gn:population":0,
    "gn:timezone":"Europe/Istanbul",
    "iso:country":"TR",
    "wof:name":"Karamusali",
    "wof:placetype":"locality"
},
  "geometry": {"coordinates":[34.46606,41.41117],"type":"Point"}
}