{
  "type": "Feature",
  "properties": {
    "gn:admin1_code":"04",
    "gn:asciiname":"Mizrak",
    "gn:country_code":"TR",
    "gn:dem":1949,
    "gn:feature_class":"P",
    "gn:feature_code":"PPL",
    "gn:name":"M\u0131zrak",
    "gn:population":0,
    "gn:timezone":"Europe/Istanbul",
    "iso:country":"TR",
    "name:tur_x_preferred":[
        "M\u0131zrak"
    ],
    "wof:name":"Mizrak",
    "wof:placetype":"locality"
},
  "geometry": {"coordinates":[42.64037,39.67195],"type":"Point"}
}