{
  "type": "Feature",
  "properties": {
    "gn:admin1_code":"10",
    "gn:asciiname":"Kucukilica",
    "gn:cc2":"TR",
    "gn:country_code":"TR",
    "gn:dem":502,
    "gn:feature_class":"P",
    "gn:feature_code":"PPL",
    "gn:name":"K\u00fc\u00e7\u00fck\u0131l\u0131ca",
    "gn:population":0,
    "gn:timezone":"Europe/Istanbul",
    "iso:country":"TR",
    "name:tur_x_preferred":[
        "K\u00fc\u00e7\u00fck Il\u0131ca"
    ],
    "name:und_x_variant":[
        "Il\u0131caisa\u011f\u0131r",
        "K\u00fc\u00e7\u00fck\u0131l\u0131ca"
    ],
    "wof:name":"Kucukilica",
    "wof:placetype":"locality"
},
  "geometry": {"coordinates":[27.26222000000001,39.44],"type":"Point"}
}