{
  "type": "Feature",
  "properties": {
    "gn:admin1_code":"81.0",
    "gn:asciiname":"Dutluca",
    "gn:country_code":"TR",
    "gn:dem":160,
    "gn:feature_class":"P",
    "gn:feature_code":"PPL",
    "gn:name":"Dutluca",
    "gn:population":0,
    "gn:timezone":"Europe/Istanbul",
    "iso:country":"TR",
    "wof:name":"Dutluca",
    "wof:placetype":"locality"
},
  "geometry": {"coordinates":[35.43752,37.15082],"type":"Point"}
}