{
  "type": "Feature",
  "properties": {
    "gn:country":"TR",
    "gn:fcode":"PPLA2",
    "gn:population":3990,
    "iso:country":"TR",
    "name:ceb_x_preferred":[
        "Sar\u0131z \u0130l\u00e7esi"
    ],
    "name:deu_x_preferred":[
        "Sar\u0131z"
    ],
    "name:diq_x_preferred":[
        "Koyri"
    ],
    "name:eng_x_preferred":[
        "Sar\u0131z"
    ],
    "name:fra_x_preferred":[
        "Sar\u0131z"
    ],
    "name:hun_x_preferred":[
        "Sar\u0131z"
    ],
    "name:jpn_x_preferred":[
        "\u30b5\u30eb\u30ba"
    ],
    "name:kur_x_preferred":[
        "Sar\u00eez"
    ],
    "name:mrj_x_preferred":[
        "\u0421\u0430\u0440\u044b\u0437"
    ],
    "name:msa_x_preferred":[
        "Sar\u0131z"
    ],
    "name:nan_x_preferred":[
        "Sar\u0131z"
    ],
    "name:nld_x_preferred":[
        "Sar\u0131z"
    ],
    "name:nob_x_preferred":[
        "Sar\u0131z"
    ],
    "name:pnb_x_preferred":[
        "\u0636\u0644\u0639 \u0633\u0627\u0631\u06cc\u0632"
    ],
    "name:swa_x_preferred":[
        "Sar\u0131z"
    ],
    "name:tur_x_preferred":[
        "Sar\u0131z"
    ],
    "name:und_x_variant":[
        "K\u00f6yyeri"
    ],
    "name:urd_x_preferred":[
        "\u0633\u0627\u0631\u06cc\u0632"
    ],
    "name:vie_x_preferred":[
        "Sar\u0131z"
    ],
    "name:zho_x_preferred":[
        "\u85a9\u723e\u5229\u8332"
    ],
    "qs:name":"Sar\u0131z",
    "qs:photos_9r":0,
    "qs:photos_sr":0,
    "qs:pop_sr":"4",
    "wd:wordcount":65,
    "wof:name":"Sar\u0131z",
    "wof:placetype":"locality",
    "wof:population":3990
},
  "geometry": {"coordinates":[36.49898,38.47917],"type":"Point"}
}