{
  "type": "Feature",
  "properties": {
    "gn:country":"TR",
    "gn:fcode":"PPLA2",
    "gn:pop":3990,
    "iso:country":"TR",
    "name:unk_x_variant":[
        "K\u00f6yyeri"
    ],
    "qs:name":"Sar\u0131z",
    "qs:photos_9r":0,
    "qs:photos_sr":0,
    "qs:pop_sr":"4",
    "wd:wordcount":65,
    "wof:name":"Sar\u0131z",
    "wof:placetype":"locality",
    "wof:population":3990
},
  "geometry": {"coordinates":[36.49898,38.47917],"type":"Point"}
}