{
  "type": "Feature",
  "properties": {
    "gn:admin1_code":"10",
    "gn:asciiname":"Meryemdere",
    "gn:country_code":"TR",
    "gn:dem":362,
    "gn:feature_class":"P",
    "gn:feature_code":"PPL",
    "gn:name":"Meryemdere",
    "gn:population":0,
    "gn:timezone":"Europe/Istanbul",
    "iso:country":"TR",
    "name:tur_x_preferred":[
        "Meryemdere"
    ],
    "wof:name":"Meryemdere",
    "wof:placetype":"locality"
},
  "geometry": {"coordinates":[27.66474,39.54379],"type":"Point"}
}