{
  "type": "Feature",
  "properties": {
    "gn:country":"TR",
    "gn:fcode":"PPL",
    "gn:pop":582666,
    "iso:country":"TR",
    "name:ota_x_preferred":[
        "\u0627\u0633\u06a9\u062f\u0627\u0631"
    ],
    "name:rus_x_preferred":[
        "\u0423\u0441\u043a\u044e\u0434\u0430\u0440"
    ],
    "name:unk_x_variant":[
        "Chrysopolis"
    ],
    "qs:name":"\u00dcsk\u00fcdar",
    "qs:name_adm0":"Turkey",
    "qs:name_adm1":"\u0130stanbul",
    "qs:photos":104,
    "qs:photos_1k":21,
    "qs:photos_9k":1,
    "qs:photos_9r":3,
    "qs:photos_all":104,
    "qs:photos_sr":3,
    "qs:placetype":"Suburb",
    "qs:pop_sr":"11",
    "wd:wordcount":3900,
    "wof:name":"\u00dcsk\u00fcdar",
    "wof:placetype":"neighbourhood",
    "wof:population":582666
},
  "geometry": {"coordinates":[29.02369,41.02252],"type":"Point"}
}