{
  "type": "Feature",
  "properties": {
    "iso:country":"TR",
    "name:eng_x_preferred":[
        "Velibaba"
    ],
    "name:tur_x_preferred":[
        "Velibaba"
    ],
    "wof:name":"Velibaba",
    "wof:placetype":"neighbourhood"
},
  "geometry": {"coordinates":[29.25386698173063,40.90717767083127],"type":"Point"}
}