{
  "type": "Feature",
  "properties": {
    "gn:country":"TR",
    "gn:fcode":"PPL",
    "gn:population":352,
    "iso:country":"TR",
    "name:tur_x_preferred":[
        "Durakba\u015f\u0131"
    ],
    "name:und_x_variant":[
        "Serdzhikhane"
    ],
    "qs:name":"Durakba\u015f\u0131",
    "qs:photos_9r":0,
    "qs:photos_sr":0,
    "qs:pop_sr":"2",
    "wof:name":"Durakba\u015f\u0131",
    "wof:placetype":"locality",
    "wof:population":352
},
  "geometry": {"coordinates":[41.07167,37.105],"type":"Point"}
}