{
  "type": "Feature",
  "properties": {
    "gn:admin1_code":"07",
    "gn:asciiname":"Guzelyali",
    "gn:country_code":"TR",
    "gn:dem":94,
    "gn:feature_class":"P",
    "gn:feature_code":"PPL",
    "gn:name":"G\u00fczelyal\u0131",
    "gn:population":0,
    "gn:timezone":"Europe/Istanbul",
    "iso:country":"TR",
    "name:tur_x_preferred":[
        "G\u00fczelyal\u0131"
    ],
    "wof:name":"Guzelyali",
    "wof:placetype":"locality"
},
  "geometry": {"coordinates":[31.54161,36.88367],"type":"Point"}
}