{
  "type": "Feature",
  "properties": {
    "gn:admin1_code":"84.0",
    "gn:asciiname":"Gurbuzler",
    "gn:country_code":"TR",
    "gn:dem":2043,
    "gn:feature_class":"P",
    "gn:feature_code":"PPL",
    "gn:name":"G\u00fcrb\u00fczler",
    "gn:population":0,
    "gn:timezone":"Europe/Istanbul",
    "iso:country":"TR",
    "name:und_x_variant":[
        "Veri\u015fan",
        "G\u00fcrb\u00fczler"
    ],
    "wof:name":"Gurbuzler",
    "wof:placetype":"locality"
},
  "geometry": {"coordinates":[42.5738,40.4657],"type":"Point"}
}