{
  "type": "Feature",
  "properties": {
    "gn:admin1_code":"87",
    "gn:asciiname":"Dizlermezeci",
    "gn:country_code":"TR",
    "gn:dem":374,
    "gn:feature_class":"P",
    "gn:feature_code":"PPL",
    "gn:name":"Dizlermezeci",
    "gn:population":0,
    "gn:timezone":"Europe/Istanbul",
    "iso:country":"TR",
    "wof:name":"Dizlermezeci",
    "wof:placetype":"locality"
},
  "geometry": {"coordinates":[32.59161,41.80542],"type":"Point"}
}