{
  "type": "Feature",
  "properties": {
    "gn:admin1_code":"15",
    "gn:asciiname":"Koytaani",
    "gn:country_code":"TR",
    "gn:dem":849,
    "gn:feature_class":"P",
    "gn:feature_code":"PPL",
    "gn:name":"K\u00f6ytaan\u0131",
    "gn:population":0,
    "gn:timezone":"Europe/Istanbul",
    "iso:country":"TR",
    "wof:name":"Koytaani",
    "wof:placetype":"locality"
},
  "geometry": {"coordinates":[30.5977,37.25398],"type":"Point"}
}