{
  "type": "Feature",
  "properties": {
    "gn:admin1_code":"21",
    "gn:asciiname":"Durabeyli",
    "gn:country_code":"TR",
    "gn:dem":862,
    "gn:feature_class":"P",
    "gn:feature_code":"PPL",
    "gn:name":"Durabeyli",
    "gn:population":0,
    "gn:timezone":"Europe/Istanbul",
    "iso:country":"TR",
    "name:tur_x_preferred":[
        "Durabeyli"
    ],
    "wof:name":"Durabeyli",
    "wof:placetype":"locality"
},
  "geometry": {"coordinates":[40.23544,38.25515],"type":"Point"}
}