{
  "type": "Feature",
  "properties": {
    "gn:admin1_code":"31",
    "gn:asciiname":"Mahmutlu",
    "gn:country_code":"TR",
    "gn:dem":95,
    "gn:feature_class":"P",
    "gn:feature_code":"PPL",
    "gn:name":"Mahmutlu",
    "gn:population":0,
    "gn:timezone":"Europe/Istanbul",
    "iso:country":"TR",
    "name:tur_x_preferred":[
        "Mahmutlu"
    ],
    "wof:name":"Mahmutlu",
    "wof:placetype":"locality"
},
  "geometry": {"coordinates":[36.3865,36.4919],"type":"Point"}
}