{
  "type": "Feature",
  "properties": {
    "gn:country":"TR",
    "gn:fcode":"PPL",
    "gn:population":3676,
    "iso:country":"TR",
    "name:ara_x_preferred":[
        "\u062d\u0635\u0646 \u0643\u064a\u0641\u0627"
    ],
    "name:aze_x_preferred":[
        "Hasankeyf"
    ],
    "name:cat_x_preferred":[
        "Hasankeyf"
    ],
    "name:ceb_x_preferred":[
        "Hasankeyf"
    ],
    "name:ckb_x_preferred":[
        "\u062d\u06d5\u0633\u06a9\u06cc\u0641"
    ],
    "name:deu_x_preferred":[
        "Hasankeyf"
    ],
    "name:diq_x_preferred":[
        "Hesenk\u00eaf"
    ],
    "name:eng_x_preferred":[
        "Hasankeyf"
    ],
    "name:fas_x_preferred":[
        "\u062d\u0635\u0646 \u06a9\u06cc\u0641\u0627"
    ],
    "name:fin_x_preferred":[
        "Hasankeyf"
    ],
    "name:fra_x_preferred":[
        "Hasankeyf"
    ],
    "name:hun_x_preferred":[
        "Hasankeyf"
    ],
    "name:ind_x_preferred":[
        "Hasankeyf"
    ],
    "name:ita_x_preferred":[
        "Hasankeyf"
    ],
    "name:jpn_x_preferred":[
        "\u30cf\u30b5\u30f3\u30b1\u30a4\u30d5"
    ],
    "name:kor_x_preferred":[
        "\ud558\uc0b0\ucf00\uc774\ud504"
    ],
    "name:kur_x_preferred":[
        "Hesk\u00eef"
    ],
    "name:lit_x_preferred":[
        "Hasankifas"
    ],
    "name:mrj_x_preferred":[
        "\u0425\u0430\u0441\u0430\u043d\u043a\u0435\u0439\u0444"
    ],
    "name:msa_x_preferred":[
        "Hasankeyf"
    ],
    "name:nan_x_preferred":[
        "Hasankeyf"
    ],
    "name:nld_x_preferred":[
        "Hasankeyf"
    ],
    "name:nob_x_preferred":[
        "Hasankeyf"
    ],
    "name:pnb_x_preferred":[
        "\u0636\u0644\u0639 \u06c1\u0627\u0633\u0646\u06a9\u06cc\u0641"
    ],
    "name:pol_x_preferred":[
        "Hasankeyf"
    ],
    "name:rus_x_preferred":[
        "\u0425\u0430\u0441\u0430\u043d\u043a\u0435\u0439\u0444"
    ],
    "name:spa_x_preferred":[
        "Hasankeyf"
    ],
    "name:swa_x_preferred":[
        "Hasankeyf"
    ],
    "name:tur_x_preferred":[
        "Hasankeyf"
    ],
    "name:tur_x_variant":[
        "Odak\u00f6y"
    ],
    "name:ukr_x_preferred":[
        "\u0425\u0430\u0441\u0430\u043d\u043a\u0435\u0439\u0444"
    ],
    "name:und_x_variant":[
        "Khasankeye"
    ],
    "name:urd_x_preferred":[
        "\u062d\u0635\u0646 \u06a9\u06cc\u0641\u0627"
    ],
    "name:vie_x_preferred":[
        "Hasankeyf"
    ],
    "name:zho_x_preferred":[
        "\u54c8\u6851\u51f1\u4f0a\u592b"
    ],
    "qs:name":"Hasankeyf",
    "qs:name_adm0":"Turkey",
    "qs:name_adm1":"Batman",
    "qs:photos":806,
    "qs:photos_1k":163,
    "qs:photos_9k":4,
    "qs:photos_9r":6,
    "qs:photos_all":806,
    "qs:photos_sr":9,
    "qs:placetype":"Town",
    "qs:pop_sr":"4",
    "wd:wordcount":5735,
    "wof:name":"Hasankeyf",
    "wof:placetype":"locality",
    "wof:population":3676
},
  "geometry": {"coordinates":[41.41459,37.71308],"type":"Point"}
}