{
  "type": "Feature",
  "properties": {
    "gn:country":"TR",
    "gn:fcode":"PPL",
    "gn:pop":3676,
    "iso:country":"TR",
    "name:ara_x_preferred":[
        "\u062d\u0635\u0646 \u0643\u064a\u0641\u0627"
    ],
    "name:ckb_x_preferred":[
        "\u062d\u06d5\u0633\u06a9\u06cc\u0641"
    ],
    "name:fas_x_preferred":[
        "\u062d\u0635\u0646 \u06a9\u06cc\u0641\u0627"
    ],
    "name:kor_x_preferred":[
        "\ud558\uc0b0\ucf00\uc774\ud504"
    ],
    "name:kur_x_preferred":[
        "Hesk\u00eef"
    ],
    "name:mrj_x_preferred":[
        "\u0425\u0430\u0441\u0430\u043d\u043a\u0435\u0439\u0444"
    ],
    "name:pnb_x_preferred":[
        "\u0636\u0644\u0639 \u06c1\u0627\u0633\u0646\u06a9\u06cc\u0641"
    ],
    "name:rus_x_preferred":[
        "\u0425\u0430\u0441\u0430\u043d\u043a\u0435\u0439\u0444"
    ],
    "name:tur_x_preferred":[
        "Hasankeyf"
    ],
    "name:ukr_x_preferred":[
        "\u0425\u0430\u0441\u0430\u043d\u043a\u0435\u0439\u0444"
    ],
    "name:unk_x_variant":[
        "Khasankeye"
    ],
    "name:urd_x_preferred":[
        "\u062d\u0635\u0646 \u06a9\u06cc\u0641\u0627"
    ],
    "qs:name":"Hasankeyf",
    "qs:name_adm0":"Turkey",
    "qs:name_adm1":"Batman",
    "qs:photos":806,
    "qs:photos_1k":163,
    "qs:photos_9k":4,
    "qs:photos_9r":6,
    "qs:photos_all":806,
    "qs:photos_sr":9,
    "qs:placetype":"Town",
    "qs:pop_sr":"4",
    "wd:wordcount":5735,
    "wof:name":"Hasankeyf",
    "wof:placetype":"locality",
    "wof:population":3676
},
  "geometry": {"coordinates":[41.41459,37.71308],"type":"Point"}
}