{
  "type": "Feature",
  "properties": {
    "gn:admin1_code":"68.0",
    "gn:asciiname":"Guvenc",
    "gn:country_code":"TR",
    "gn:dem":1000,
    "gn:feature_class":"P",
    "gn:feature_code":"PPL",
    "gn:name":"G\u00fcven\u00e7",
    "gn:population":0,
    "gn:timezone":"Europe/Istanbul",
    "iso:country":"TR",
    "name:und_x_variant":[
        "G\u00fcve\u00e7",
        "G\u00fcven\u00e7"
    ],
    "wof:name":"Guvenc",
    "wof:placetype":"locality"
},
  "geometry": {"coordinates":[32.72404,40.14446],"type":"Point"}
}