{
  "type": "Feature",
  "properties": {
    "gn:admin1_code":"19.0",
    "gn:asciiname":"Cayseki",
    "gn:country_code":"TR",
    "gn:dem":1031,
    "gn:feature_class":"P",
    "gn:feature_code":"PPL",
    "gn:name":"\u00c7ayseki",
    "gn:population":0,
    "gn:timezone":"Europe/Istanbul",
    "iso:country":"TR",
    "wof:name":"Cayseki",
    "wof:placetype":"locality"
},
  "geometry": {"coordinates":[34.66345,40.4903],"type":"Point"}
}