{
  "type": "Feature",
  "properties": {
    "gn:admin1_code":"32",
    "gn:asciiname":"Kerimler",
    "gn:country_code":"TR",
    "gn:dem":641,
    "gn:feature_class":"P",
    "gn:feature_code":"PPL",
    "gn:name":"Kerimler",
    "gn:population":0,
    "gn:timezone":"Europe/Istanbul",
    "iso:country":"TR",
    "name:ceb_x_preferred":[
        "Kerimler"
    ],
    "name:msa_x_preferred":[
        "Kerimler"
    ],
    "name:vie_x_preferred":[
        "Kerimler"
    ],
    "wof:name":"Kerimler",
    "wof:placetype":"locality"
},
  "geometry": {"coordinates":[34.53722,36.92068],"type":"Point"}
}