{
  "type": "Feature",
  "properties": {
    "gn:admin1_code":"57.0",
    "gn:asciiname":"Ballica",
    "gn:country_code":"TR",
    "gn:dem":568,
    "gn:feature_class":"P",
    "gn:feature_code":"PPL",
    "gn:name":"Ballica",
    "gn:population":0,
    "gn:timezone":"Europe/Istanbul",
    "iso:country":"TR",
    "name:und_x_variant":[
        "Ba\u011fl\u0131ca K\u00f6y\u00fc",
        "Ba\u011fl\u0131ca K\u00f6y",
        "Ballica",
        "Ba\u011fl\u0131ca"
    ],
    "wof:name":"Ballica",
    "wof:placetype":"locality"
},
  "geometry": {"coordinates":[34.6202,41.45079000000001],"type":"Point"}
}