{
  "type": "Feature",
  "properties": {
    "gn:admin1_code":"09",
    "gn:asciiname":"Musluca",
    "gn:country_code":"TR",
    "gn:dem":272,
    "gn:feature_class":"P",
    "gn:feature_code":"PPL",
    "gn:name":"Musluca",
    "gn:population":0,
    "gn:timezone":"Europe/Istanbul",
    "iso:country":"TR",
    "name:ceb_x_preferred":[
        "Musluca"
    ],
    "name:msa_x_preferred":[
        "Musluca"
    ],
    "name:tur_x_preferred":[
        "Musluca"
    ],
    "name:vie_x_preferred":[
        "Musluca"
    ],
    "wof:name":"Musluca",
    "wof:placetype":"locality"
},
  "geometry": {"coordinates":[27.97861,37.91028],"type":"Point"}
}