{
  "type": "Feature",
  "properties": {
    "gn:admin1_code":"93.0",
    "gn:asciiname":"Guney",
    "gn:country_code":"TR",
    "gn:dem":302,
    "gn:feature_class":"P",
    "gn:feature_code":"PPL",
    "gn:name":"G\u00fcney",
    "gn:population":0,
    "gn:timezone":"Europe/Istanbul",
    "iso:country":"TR",
    "name:ceb_x_preferred":[
        "Guney"
    ],
    "name:swe_x_preferred":[
        "Guney"
    ],
    "name:und_x_variant":[
        "Seden",
        "\u015eeren",
        "G\u00fcney"
    ],
    "wof:name":"Guney",
    "wof:placetype":"locality"
},
  "geometry": {"coordinates":[31.41305,40.94908],"type":"Point"}
}