{
  "type": "Feature",
  "properties": {
    "gn:admin1_code":"13",
    "gn:asciiname":"Resadiye",
    "gn:country_code":"TR",
    "gn:dem":1670,
    "gn:feature_class":"P",
    "gn:feature_code":"PPLA2",
    "gn:name":"Re\u015fadiye",
    "gn:population":0,
    "gn:timezone":"Europe/Istanbul",
    "iso:country":"TR",
    "name:und_x_variant":[
        "Re\u015fadiye",
        "Yelkenli"
    ],
    "wof:name":"Resadiye",
    "wof:placetype":"locality"
},
  "geometry": {"coordinates":[42.53501,38.48879],"type":"Point"}
}