{
  "type": "Feature",
  "properties": {
    "gn:admin1_code":"26.0",
    "gn:asciiname":"Sakaryakaracaoren",
    "gn:country_code":"TR",
    "gn:dem":283,
    "gn:feature_class":"P",
    "gn:feature_code":"PPL",
    "gn:name":"Sakaryakaraca\u00f6ren",
    "gn:population":0,
    "gn:timezone":"Europe/Istanbul",
    "iso:country":"TR",
    "name:und_x_variant":[
        "Karacaviransakar\u0131",
        "Sakaryakaraca\u00f6ren",
        "Sar\u0131karaca\u00f6ren"
    ],
    "wof:name":"Sakaryakaracaoren",
    "wof:placetype":"locality"
},
  "geometry": {"coordinates":[30.93293,40.03005],"type":"Point"}
}