{
  "type": "Feature",
  "properties": {
    "gn:admin1_code":"65",
    "gn:asciiname":"Anzak",
    "gn:country_code":"TR",
    "gn:dem":2025,
    "gn:feature_class":"P",
    "gn:feature_code":"PPL",
    "gn:name":"Anzak",
    "gn:population":0,
    "gn:timezone":"Europe/Istanbul",
    "iso:country":"TR",
    "name:und_x_variant":[
        "Y\u0131nd\u00f6nd\u00fc"
    ],
    "wof:name":"Anzak",
    "wof:placetype":"locality"
},
  "geometry": {"coordinates":[43.45,38.55],"type":"Point"}
}