{
  "type": "Feature",
  "properties": {
    "gn:admin1_code":"16",
    "gn:asciiname":"Deliballilar",
    "gn:country_code":"TR",
    "gn:dem":394,
    "gn:feature_class":"P",
    "gn:feature_code":"PPL",
    "gn:name":"Deliball\u0131lar",
    "gn:population":0,
    "gn:timezone":"Europe/Istanbul",
    "iso:country":"TR",
    "name:tur_x_preferred":[
        "Deliball\u0131lar"
    ],
    "wof:name":"Deliballilar",
    "wof:placetype":"locality"
},
  "geometry": {"coordinates":[28.99494,39.93225],"type":"Point"}
}