{
  "type": "Feature",
  "properties": {
    "gn:admin1_code":"65.0",
    "gn:asciiname":"Tasbucak",
    "gn:country_code":"TR",
    "gn:dem":1908,
    "gn:feature_class":"P",
    "gn:feature_code":"PPL",
    "gn:name":"Ta\u015fbucak",
    "gn:population":0,
    "gn:timezone":"Europe/Istanbul",
    "iso:country":"TR",
    "name:tur_x_preferred":[
        "Ta\u015fbucak"
    ],
    "wof:name":"Tasbucak",
    "wof:placetype":"locality"
},
  "geometry": {"coordinates":[43.12843,37.85959],"type":"Point"}
}