{
  "type": "Feature",
  "properties": {
    "gn:admin1_code":"15",
    "gn:asciiname":"Belkaya",
    "gn:country_code":"TR",
    "gn:dem":1324,
    "gn:feature_class":"P",
    "gn:feature_code":"PPL",
    "gn:name":"Belkaya",
    "gn:population":0,
    "gn:timezone":"Europe/Istanbul",
    "iso:country":"TR",
    "name:und_x_variant":[
        "Guluman"
    ],
    "wof:name":"Belkaya",
    "wof:placetype":"locality"
},
  "geometry": {"coordinates":[29.60356,37.31079],"type":"Point"}
}