{
  "type": "Feature",
  "properties": {
    "gn:admin1_code":"02",
    "gn:asciiname":"Yaylacik",
    "gn:country_code":"TR",
    "gn:dem":1121,
    "gn:feature_class":"P",
    "gn:feature_code":"PPL",
    "gn:name":"Yaylac\u0131k",
    "gn:population":0,
    "gn:timezone":"Europe/Istanbul",
    "iso:country":"TR",
    "name:und_x_variant":[
        "K\u00f6r\u00fcstan",
        "K\u00fcristan",
        "K\u00f6ristan",
        "Yaylac\u0131k"
    ],
    "wof:name":"Yaylacik",
    "wof:placetype":"locality"
},
  "geometry": {"coordinates":[37.81667,37.83333],"type":"Point"}
}