{
  "type": "Feature",
  "properties": {
    "gn:admin1_code":"26",
    "gn:asciiname":"Bugduz",
    "gn:country_code":"TR",
    "gn:dem":854,
    "gn:feature_class":"P",
    "gn:feature_code":"PPL",
    "gn:name":"B\u00fc\u011fd\u00fcz",
    "gn:population":0,
    "gn:timezone":"Europe/Istanbul",
    "iso:country":"TR",
    "name:und_x_variant":[
        "B\u00fc\u011fd\u00fcz",
        "B\u00fcyd\u00fcz"
    ],
    "wof:name":"Bugduz",
    "wof:placetype":"locality"
},
  "geometry": {"coordinates":[31.08454,39.85207],"type":"Point"}
}