{
  "type": "Feature",
  "properties": {
    "gn:admin1_code":"38",
    "gn:asciiname":"Karaseyh",
    "gn:country_code":"TR",
    "gn:dem":1508,
    "gn:feature_class":"P",
    "gn:feature_code":"PPL",
    "gn:name":"Kara\u015feyh",
    "gn:population":0,
    "gn:timezone":"Europe/Istanbul",
    "iso:country":"TR",
    "name:und_x_variant":[
        "Kara\u015f\u0131h",
        "Kara\u015feyh"
    ],
    "wof:name":"Karaseyh",
    "wof:placetype":"locality"
},
  "geometry": {"coordinates":[35.59087,39.16923],"type":"Point"}
}