{
  "type": "Feature",
  "properties": {
    "gn:admin1_code":"28.0",
    "gn:asciiname":"Ortavami",
    "gn:country_code":"TR",
    "gn:dem":283,
    "gn:feature_class":"P",
    "gn:feature_code":"PPL",
    "gn:name":"Ortavami",
    "gn:population":0,
    "gn:timezone":"Europe/Istanbul",
    "iso:country":"TR",
    "name:tur_x_preferred":[
        "Ortavami"
    ],
    "name:und_x_variant":[
        "Ortacami"
    ],
    "wof:name":"Ortavami",
    "wof:placetype":"locality"
},
  "geometry": {"coordinates":[38.90188,40.98975],"type":"Point"}
}