{
  "type": "Feature",
  "properties": {
    "gn:admin1_code":"65.0",
    "gn:asciiname":"Yalinagac",
    "gn:country_code":"TR",
    "gn:dem":1951,
    "gn:feature_class":"P",
    "gn:feature_code":"PPL",
    "gn:name":"Yal\u0131na\u011fa\u00e7",
    "gn:population":0,
    "gn:timezone":"Europe/Istanbul",
    "iso:country":"TR",
    "name:tur_x_preferred":[
        "Yal\u0131na\u011fa\u00e7"
    ],
    "wof:name":"Yalinagac",
    "wof:placetype":"locality"
},
  "geometry": {"coordinates":[43.56679000000001,38.57572],"type":"Point"}
}