{
  "type": "Feature",
  "properties": {
    "gn:admin1_code":"19.0",
    "gn:asciiname":"Kizilcukur Yaylasi",
    "gn:country_code":"TR",
    "gn:dem":1658,
    "gn:feature_class":"P",
    "gn:feature_code":"PPL",
    "gn:name":"K\u0131z\u0131l\u00e7ukur Yaylas\u0131",
    "gn:population":0,
    "gn:timezone":"Europe/Istanbul",
    "iso:country":"TR",
    "name:tur_x_preferred":[
        "K\u0131z\u0131l\u00e7ukur Yaylas\u0131"
    ],
    "wof:name":"Kizilcukur Yaylasi",
    "wof:placetype":"locality"
},
  "geometry": {"coordinates":[34.023,40.84298],"type":"Point"}
}