{
  "type": "Feature",
  "properties": {
    "gn:admin1_code":"4.0",
    "gn:asciiname":"Agilbasi",
    "gn:country_code":"TR",
    "gn:dem":1663,
    "gn:feature_class":"P",
    "gn:feature_code":"PPL",
    "gn:name":"A\u011f\u0131lba\u015f\u0131",
    "gn:population":0,
    "gn:timezone":"Europe/Istanbul",
    "iso:country":"TR",
    "name:und_x_variant":[
        "Hac\u0131hano",
        "A\u011f\u0131lba\u015f\u0131"
    ],
    "wof:name":"Agilbasi",
    "wof:placetype":"locality"
},
  "geometry": {"coordinates":[42.96936,39.69015],"type":"Point"}
}