{
  "type": "Feature",
  "properties": {
    "gn:admin1_code":"85.0",
    "gn:asciiname":"Dagustu",
    "gn:country_code":"TR",
    "gn:dem":318,
    "gn:feature_class":"P",
    "gn:feature_code":"PPL",
    "gn:name":"Da\u011f\u00fcst\u00fc",
    "gn:population":0,
    "gn:timezone":"Europe/Istanbul",
    "iso:country":"TR",
    "wof:name":"Dagustu",
    "wof:placetype":"locality"
},
  "geometry": {"coordinates":[31.98195,41.38639000000001],"type":"Point"}
}