{
  "type": "Feature",
  "properties": {
    "gn:admin1_code":"72.0",
    "gn:asciiname":"Magarakoy",
    "gn:cc2":"TR",
    "gn:country_code":"TR",
    "gn:dem":898,
    "gn:feature_class":"P",
    "gn:feature_code":"PPL",
    "gn:name":"Ma\u011farak\u00f6y",
    "gn:population":0,
    "gn:timezone":"Europe/Istanbul",
    "iso:country":"TR",
    "name:tur_x_preferred":[
        "Ma\u011farak\u00f6y"
    ],
    "name:und_x_variant":[
        "Birivan",
        "Birivran"
    ],
    "wof:name":"Magarakoy",
    "wof:placetype":"locality"
},
  "geometry": {"coordinates":[41.01778,37.65444],"type":"Point"}
}