{
  "type": "Feature",
  "properties": {
    "gn:admin1_code":"72",
    "gn:asciiname":"Cukurlu",
    "gn:country_code":"TR",
    "gn:dem":805,
    "gn:feature_class":"P",
    "gn:feature_code":"PPL",
    "gn:name":"\u00c7ukurlu",
    "gn:population":0,
    "gn:timezone":"Europe/Istanbul",
    "iso:country":"TR",
    "name:und_x_variant":[
        "Hand\u00fck",
        "Khendyuk",
        "Hend\u00fck",
        "\u00c7ukurlu"
    ],
    "wof:name":"Cukurlu",
    "wof:placetype":"locality"
},
  "geometry": {"coordinates":[41.74069,37.40885],"type":"Point"}
}