{
  "type": "Feature",
  "properties": {
    "gn:admin1_code":"21",
    "gn:asciiname":"Konder",
    "gn:country_code":"TR",
    "gn:dem":780,
    "gn:feature_class":"P",
    "gn:feature_code":"PPL",
    "gn:name":"K\u00f6nder",
    "gn:population":0,
    "gn:timezone":"Europe/Istanbul",
    "iso:country":"TR",
    "wof:name":"Konder",
    "wof:placetype":"locality"
},
  "geometry": {"coordinates":[39.81667,38.03333],"type":"Point"}
}