{
  "type": "Feature",
  "properties": {
    "gn:admin1_code":"44",
    "gn:asciiname":"Ilicak",
    "gn:country_code":"TR",
    "gn:dem":952,
    "gn:feature_class":"P",
    "gn:feature_code":"PPL",
    "gn:name":"Il\u0131cak",
    "gn:population":0,
    "gn:timezone":"Europe/Istanbul",
    "iso:country":"TR",
    "name:tur_x_preferred":[
        "Il\u0131cak"
    ],
    "wof:name":"Ilicak",
    "wof:placetype":"locality"
},
  "geometry": {"coordinates":[38.05596,38.48732],"type":"Point"}
}