{
  "type": "Feature",
  "properties": {
    "gn:country":"TR",
    "gn:fcode":"PPL",
    "gn:pop":2879,
    "iso:country":"TR",
    "name:tur_x_preferred":[
        "Balp\u0131nar"
    ],
    "name:unk_x_variant":[
        "Kersivan"
    ],
    "qs:name":"Balp\u0131nar",
    "qs:photos_9r":0,
    "qs:photos_sr":0,
    "qs:pop_sr":"4",
    "wof:name":"Balp\u0131nar",
    "wof:placetype":"locality",
    "wof:population":2879
},
  "geometry": {"coordinates":[41.05472,37.86833],"type":"Point"}
}