{
  "type": "Feature",
  "properties": {
    "gn:admin1_code":"13.0",
    "gn:asciiname":"Garibat",
    "gn:country_code":"TR",
    "gn:dem":1258,
    "gn:feature_class":"P",
    "gn:feature_code":"PPL",
    "gn:name":"Garibat",
    "gn:population":0,
    "gn:timezone":"Europe/Istanbul",
    "iso:country":"TR",
    "name:tur_x_preferred":[
        "Garibat"
    ],
    "wof:name":"Garibat",
    "wof:placetype":"locality"
},
  "geometry": {"coordinates":[42.15376,38.27877],"type":"Point"}
}