{
  "type": "Feature",
  "properties": {
    "gn:admin1_code":"07",
    "gn:asciiname":"Catallar",
    "gn:country_code":"TR",
    "gn:dem":94,
    "gn:feature_class":"P",
    "gn:feature_code":"PPL",
    "gn:name":"\u00c7atallar",
    "gn:population":0,
    "gn:timezone":"Europe/Istanbul",
    "iso:country":"TR",
    "wof:name":"Catallar",
    "wof:placetype":"locality"
},
  "geometry": {"coordinates":[30.85808,37.1432],"type":"Point"}
}