{
  "type": "Feature",
  "properties": {
    "gn:admin1_code":"20",
    "gn:asciiname":"Bolmekaya",
    "gn:cc2":"TR",
    "gn:country_code":"TR",
    "gn:dem":383,
    "gn:feature_class":"P",
    "gn:feature_code":"PPL",
    "gn:name":"B\u00f6lmekaya",
    "gn:population":0,
    "gn:timezone":"Europe/Istanbul",
    "iso:country":"TR",
    "name:und_x_variant":[
        "Eldirek",
        "B\u00f6lmekaya"
    ],
    "wof:name":"Bolmekaya",
    "wof:placetype":"locality"
},
  "geometry": {"coordinates":[28.89111,38.02028],"type":"Point"}
}