{
  "type": "Feature",
  "properties": {
    "gn:admin1_code":"43",
    "gn:asciiname":"Yesilcam",
    "gn:country_code":"TR",
    "gn:dem":602,
    "gn:feature_class":"P",
    "gn:feature_code":"PPL",
    "gn:name":"Ye\u015fil\u00e7am",
    "gn:population":0,
    "gn:timezone":"Europe/Istanbul",
    "iso:country":"TR",
    "name:tur_x_preferred":[
        "Ye\u015fil\u00e7am"
    ],
    "wof:name":"Yesilcam",
    "wof:placetype":"locality"
},
  "geometry": {"coordinates":[28.76301,39.16597],"type":"Point"}
}