{
  "type": "Feature",
  "properties": {
    "gn:admin1_code":"90.0",
    "gn:asciiname":"Alatepe",
    "gn:country_code":"TR",
    "gn:dem":704,
    "gn:feature_class":"P",
    "gn:feature_code":"PPL",
    "gn:name":"Alatepe",
    "gn:population":0,
    "gn:timezone":"Europe/Istanbul",
    "iso:country":"TR",
    "wof:name":"Alatepe",
    "wof:placetype":"locality"
},
  "geometry": {"coordinates":[37.19833,36.7875],"type":"Point"}
}