{
  "type": "Feature",
  "properties": {
    "gn:admin1_code":"45",
    "gn:asciiname":"Guzelkoy",
    "gn:country_code":"TR",
    "gn:dem":30,
    "gn:feature_class":"P",
    "gn:feature_code":"PPL",
    "gn:name":"G\u00fczelk\u00f6y",
    "gn:population":0,
    "gn:timezone":"Europe/Istanbul",
    "iso:country":"TR",
    "name:tur_x_preferred":[
        "G\u00fczelk\u00f6y"
    ],
    "name:tur_x_variant":[
        "K\u0131z\u0131lk\u00f6y"
    ],
    "wof:name":"Guzelkoy",
    "wof:placetype":"locality"
},
  "geometry": {"coordinates":[27.44562,38.66408],"type":"Point"}
}