{
  "type": "Feature",
  "properties": {
    "gn:admin1_code":"88",
    "gn:asciiname":"Asagi Carikci",
    "gn:country_code":"TR",
    "gn:dem":880,
    "gn:feature_class":"P",
    "gn:feature_code":"PPL",
    "gn:name":"A\u015fa\u011f\u0131 \u00c7ar\u0131k\u00e7\u0131",
    "gn:population":0,
    "gn:timezone":"Europe/Istanbul",
    "iso:country":"TR",
    "name:tur_x_preferred":[
        "A\u015fa\u011f\u0131 \u00c7ar\u0131k\u00e7\u0131"
    ],
    "name:und_x_variant":[
        "A\u015fa\u011f\u0131\u00e7ar\u0131k\u00e7\u0131"
    ],
    "wof:name":"Asagi Carikci",
    "wof:placetype":"locality"
},
  "geometry": {"coordinates":[43.94701,39.93943],"type":"Point"}
}