{
  "type": "Feature",
  "properties": {
    "gn:admin1_code":"34.0",
    "gn:asciiname":"Degirmencayiri",
    "gn:country_code":"TR",
    "gn:dem":152,
    "gn:feature_class":"P",
    "gn:feature_code":"PPL",
    "gn:name":"De\u011firmen\u00e7ay\u0131r\u0131",
    "gn:population":0,
    "gn:timezone":"Europe/Istanbul",
    "iso:country":"TR",
    "name:tur_x_preferred":[
        "De\u011firmen\u00e7ay\u0131r\u0131"
    ],
    "wof:name":"Degirmencayiri",
    "wof:placetype":"locality"
},
  "geometry": {"coordinates":[29.66374,40.97839000000001],"type":"Point"}
}