{
  "type": "Feature",
  "properties": {
    "gn:admin1_code":"31.0",
    "gn:asciiname":"Dikenlihopur",
    "gn:cc2":"TR",
    "gn:country_code":"TR",
    "gn:dem":319,
    "gn:feature_class":"P",
    "gn:feature_code":"PPL",
    "gn:name":"Dikenlihopur",
    "gn:population":0,
    "gn:timezone":"Europe/Istanbul",
    "iso:country":"TR",
    "name:und_x_variant":[
        "Dikenlikhopur",
        "Dikenlihopur"
    ],
    "wof:name":"Dikenlihopur",
    "wof:placetype":"locality"
},
  "geometry": {"coordinates":[36.25167,36.93972],"type":"Point"}
}