{
  "type": "Feature",
  "properties": {
    "gn:admin1_code":"72",
    "gn:asciiname":"Alagoz",
    "gn:country_code":"TR",
    "gn:dem":654,
    "gn:feature_class":"P",
    "gn:feature_code":"PPL",
    "gn:name":"Alag\u00f6z",
    "gn:population":0,
    "gn:timezone":"Europe/Istanbul",
    "iso:country":"TR",
    "name:tur_x_preferred":[
        "Alag\u00f6z"
    ],
    "name:und_x_variant":[
        "Tahtabe\u015f"
    ],
    "wof:name":"Alagoz",
    "wof:placetype":"locality"
},
  "geometry": {"coordinates":[40.16595,37.39772],"type":"Point"}
}