{
  "type": "Feature",
  "properties": {
    "gn:admin1_code":"16.0",
    "gn:asciiname":"Baskoy",
    "gn:country_code":"TR",
    "gn:dem":710,
    "gn:feature_class":"P",
    "gn:feature_code":"PPL",
    "gn:name":"Ba\u015fk\u00f6y",
    "gn:population":0,
    "gn:timezone":"Europe/Istanbul",
    "iso:country":"TR",
    "name:tur_x_preferred":[
        "Ba\u015f"
    ],
    "name:und_x_variant":[
        "Ba\u015fk\u00f6y"
    ],
    "wof:name":"Baskoy",
    "wof:placetype":"locality"
},
  "geometry": {"coordinates":[28.84101,40.05755],"type":"Point"}
}