{
  "type": "Feature",
  "properties": {
    "gn:admin1_code":"48.0",
    "gn:asciiname":"Yaliciftlik",
    "gn:country_code":"TR",
    "gn:dem":48,
    "gn:feature_class":"P",
    "gn:feature_code":"PPL",
    "gn:name":"Yaliciftlik",
    "gn:population":0,
    "gn:timezone":"Europe/Istanbul",
    "iso:country":"TR",
    "wof:name":"Yaliciftlik",
    "wof:placetype":"locality"
},
  "geometry": {"coordinates":[27.56985,36.99597],"type":"Point"}
}