{
  "type": "Feature",
  "properties": {
    "gn:admin1_code":"8.0",
    "gn:asciiname":"Ormanli",
    "gn:country_code":"TR",
    "gn:dem":648,
    "gn:feature_class":"P",
    "gn:feature_code":"PPL",
    "gn:name":"Ormanl\u0131",
    "gn:population":0,
    "gn:timezone":"Europe/Istanbul",
    "iso:country":"TR",
    "name:tur_x_preferred":[
        "Ormanl\u0131"
    ],
    "wof:name":"Ormanli",
    "wof:placetype":"locality"
},
  "geometry": {"coordinates":[41.75696,41.25834],"type":"Point"}
}