{
  "type": "Feature",
  "properties": {
    "gn:admin1_code":"61.0",
    "gn:asciiname":"Karabudak",
    "gn:country_code":"TR",
    "gn:dem":124,
    "gn:feature_class":"P",
    "gn:feature_code":"PPL",
    "gn:name":"Karabudak",
    "gn:population":0,
    "gn:timezone":"Europe/Istanbul",
    "iso:country":"TR",
    "name:und_x_variant":[
        "Kazret"
    ],
    "wof:name":"Karabudak",
    "wof:placetype":"locality"
},
  "geometry": {"coordinates":[40.31645,40.94365],"type":"Point"}
}