{
  "type": "Feature",
  "properties": {
    "gn:admin1_code":"58",
    "gn:asciiname":"Yellice",
    "gn:country_code":"TR",
    "gn:dem":1844,
    "gn:feature_class":"P",
    "gn:feature_code":"PPL",
    "gn:name":"Yellice",
    "gn:population":0,
    "gn:timezone":"Europe/Istanbul",
    "iso:country":"TR",
    "name:tur_x_preferred":[
        "Yellice"
    ],
    "wof:name":"Yellice",
    "wof:placetype":"locality"
},
  "geometry": {"coordinates":[37.78286,39.25073],"type":"Point"}
}