{
  "type": "Feature",
  "properties": {
    "gn:admin1_code":"25.0",
    "gn:asciiname":"Tuykomu",
    "gn:country_code":"TR",
    "gn:dem":1982,
    "gn:feature_class":"P",
    "gn:feature_code":"PPL",
    "gn:name":"Tuykomu",
    "gn:population":0,
    "gn:timezone":"Europe/Istanbul",
    "iso:country":"TR",
    "wof:name":"Tuykomu",
    "wof:placetype":"locality"
},
  "geometry": {"coordinates":[41.43333,40.03333],"type":"Point"}
}