{
  "type": "Feature",
  "properties": {
    "gn:admin1_code":"80.0",
    "gn:asciiname":"Celbiyan",
    "gn:country_code":"TR",
    "gn:dem":1204,
    "gn:feature_class":"P",
    "gn:feature_code":"PPL",
    "gn:name":"Celbiyan",
    "gn:population":0,
    "gn:timezone":"Europe/Istanbul",
    "iso:country":"TR",
    "name:tur_x_preferred":[
        "Celbiyan"
    ],
    "wof:name":"Celbiyan",
    "wof:placetype":"locality"
},
  "geometry": {"coordinates":[42.63698,37.34834],"type":"Point"}
}