{
  "type": "Feature",
  "properties": {
    "gn:admin1_code":"50",
    "gn:asciiname":"Hidirlar",
    "gn:country_code":"TR",
    "gn:dem":1221,
    "gn:feature_class":"P",
    "gn:feature_code":"PPL",
    "gn:name":"H\u0131d\u0131rlar",
    "gn:population":0,
    "gn:timezone":"Europe/Istanbul",
    "iso:country":"TR",
    "wof:name":"Hidirlar",
    "wof:placetype":"locality"
},
  "geometry": {"coordinates":[34.6474,38.94097],"type":"Point"}
}