{
  "type": "Feature",
  "properties": {
    "gn:admin1_code":"80",
    "gn:asciiname":"Eskiyapi",
    "gn:country_code":"TR",
    "gn:dem":645,
    "gn:feature_class":"P",
    "gn:feature_code":"PPL",
    "gn:name":"Eskiyap\u0131",
    "gn:population":0,
    "gn:timezone":"Europe/Istanbul",
    "iso:country":"TR",
    "name:und_x_variant":[
        "Gerre\u015fa\u011fa",
        "Kere\u015fan",
        "Finiki Geli",
        "Eskiyap\u0131"
    ],
    "wof:name":"Eskiyapi",
    "wof:placetype":"locality"
},
  "geometry": {"coordinates":[42.08707,37.41179],"type":"Point"}
}