{
  "type": "Feature",
  "properties": {
    "gn:admin1_code":"82.0",
    "gn:asciiname":"Sakarca",
    "gn:country_code":"TR",
    "gn:dem":558,
    "gn:feature_class":"P",
    "gn:feature_code":"PPL",
    "gn:name":"Sakarca",
    "gn:population":0,
    "gn:timezone":"Europe/Istanbul",
    "iso:country":"TR",
    "name:und_x_variant":[
        "\u0130shakca",
        "Sakarca"
    ],
    "wof:name":"Sakarca",
    "wof:placetype":"locality"
},
  "geometry": {"coordinates":[34.03882,40.38846],"type":"Point"}
}