{
  "type": "Feature",
  "properties": {
    "gn:country":"TR",
    "gn:fcode":"PPLX",
    "gn:population":0,
    "iso:country":"TR",
    "name:ceb_x_preferred":[
        "Ye\u015filyurt"
    ],
    "name:deu_x_preferred":[
        "Ye\u015filyurt"
    ],
    "name:diq_x_preferred":[
        "Ye\u015filyurt"
    ],
    "name:eng_x_preferred":[
        "Ye\u015filyurt"
    ],
    "name:nld_x_preferred":[
        "Ye\u015filyurt"
    ],
    "name:por_x_preferred":[
        "Ye\u015filyurt"
    ],
    "name:spa_x_preferred":[
        "Ye\u015filyurt"
    ],
    "name:swe_x_preferred":[
        "Ye\u015filyurt"
    ],
    "name:tur_x_preferred":[
        "Ye\u015filyurt"
    ],
    "name:uzb_x_preferred":[
        "Ye\u015filyurt"
    ],
    "qs:name":"Yesilyurt",
    "qs:name_adm0":"Turkey",
    "qs:name_adm1":"Antalya",
    "qs:photos_9r":0,
    "qs:photos_sr":0,
    "qs:placetype":"Suburb",
    "qs:pop_sr":"0",
    "wd:wordcount":259,
    "wof:name":"Yesilyurt",
    "wof:placetype":"neighbourhood",
    "wof:population":0
},
  "geometry": {"coordinates":[30.63675,36.9076],"type":"Point"}
}