{
  "type": "Feature",
  "properties": {
    "gn:country":"TR",
    "gn:fcode":"PPLX",
    "gn:pop":0,
    "iso:country":"TR",
    "qs:name":"Yesilyurt",
    "qs:name_adm0":"Turkey",
    "qs:name_adm1":"Antalya",
    "qs:photos_9r":0,
    "qs:photos_sr":0,
    "qs:placetype":"Suburb",
    "qs:pop_sr":"0",
    "wd:wordcount":259,
    "wof:name":"Yesilyurt",
    "wof:placetype":"neighbourhood",
    "wof:population":0
},
  "geometry": {"coordinates":[30.63675,36.9076],"type":"Point"}
}