{
  "type": "Feature",
  "properties": {
    "gn:admin1_code":"5.0",
    "gn:asciiname":"Tekke",
    "gn:country_code":"TR",
    "gn:dem":767,
    "gn:feature_class":"P",
    "gn:feature_code":"PPL",
    "gn:name":"Tekke",
    "gn:population":0,
    "gn:timezone":"Europe/Istanbul",
    "iso:country":"TR",
    "wof:name":"Tekke",
    "wof:placetype":"locality"
},
  "geometry": {"coordinates":[35.57605,40.33158],"type":"Point"}
}