{
  "type": "Feature",
  "properties": {
    "gn:admin1_code":"63.0",
    "gn:asciiname":"Gedik",
    "gn:country_code":"TR",
    "gn:dem":1146,
    "gn:feature_class":"P",
    "gn:feature_code":"PPL",
    "gn:name":"Gedik",
    "gn:population":0,
    "gn:timezone":"Europe/Istanbul",
    "iso:country":"TR",
    "name:tur_x_preferred":[
        "Gedik"
    ],
    "wof:name":"Gedik",
    "wof:placetype":"locality"
},
  "geometry": {"coordinates":[39.68596,37.74862],"type":"Point"}
}