{
  "type": "Feature",
  "properties": {
    "gn:admin1_code":"37.0",
    "gn:asciiname":"Karabuk",
    "gn:country_code":"TR",
    "gn:dem":442,
    "gn:feature_class":"P",
    "gn:feature_code":"PPL",
    "gn:name":"Karab\u00fck",
    "gn:population":0,
    "gn:timezone":"Europe/Istanbul",
    "iso:country":"TR",
    "wof:name":"Karabuk",
    "wof:placetype":"locality"
},
  "geometry": {"coordinates":[34.56178,41.63804],"type":"Point"}
}