{
  "type": "Feature",
  "properties": {
    "gn:admin1_code":"13.0",
    "gn:asciiname":"Cebek",
    "gn:country_code":"TR",
    "gn:dem":1284,
    "gn:feature_class":"P",
    "gn:feature_code":"PPL",
    "gn:name":"Cebek",
    "gn:population":0,
    "gn:timezone":"Europe/Istanbul",
    "iso:country":"TR",
    "name:tur_x_preferred":[
        "Cebek"
    ],
    "wof:name":"Cebek",
    "wof:placetype":"locality"
},
  "geometry": {"coordinates":[41.69395,38.25723],"type":"Point"}
}