{
  "type": "Feature",
  "properties": {
    "gn:country":"TR",
    "gn:fcode":"PPLX",
    "gn:population":0,
    "iso:country":"TR",
    "name:aze_x_preferred":[
        "Liman"
    ],
    "name:bel_x_preferred":[
        "\u041b\u0456\u043c\u0430\u043d"
    ],
    "name:bul_x_preferred":[
        "\u041b\u0438\u043c\u0430\u043d"
    ],
    "name:ceb_x_preferred":[
        "Liman"
    ],
    "name:deu_x_preferred":[
        "Liman"
    ],
    "name:heb_x_preferred":[
        "\u05dc\u05d9\u05de\u05df"
    ],
    "name:hrv_x_preferred":[
        "Liman"
    ],
    "name:hye_x_preferred":[
        "\u053c\u056b\u0574\u0561\u0576"
    ],
    "name:ita_x_preferred":[
        "Liman"
    ],
    "name:pol_x_preferred":[
        "Liman"
    ],
    "name:rus_x_preferred":[
        "\u041b\u0438\u043c\u0430\u043d"
    ],
    "name:slk_x_preferred":[
        "Liman"
    ],
    "name:srp_x_preferred":[
        "\u041b\u0438\u043c\u0430\u043d"
    ],
    "name:swe_x_preferred":[
        "Liman"
    ],
    "name:ukr_x_preferred":[
        "\u041b\u0438\u043c\u0430\u043d"
    ],
    "qs:name":"Liman",
    "qs:name_adm0":"Turkey",
    "qs:name_adm1":"Antalya",
    "qs:photos":16,
    "qs:photos_1k":3,
    "qs:photos_9k":1,
    "qs:photos_9r":1,
    "qs:photos_all":16,
    "qs:photos_sr":1,
    "qs:placetype":"Suburb",
    "qs:pop_sr":"0",
    "wd:wordcount":130,
    "wof:name":"Liman",
    "wof:placetype":"neighbourhood",
    "wof:population":0
},
  "geometry": {"coordinates":[30.61826,36.8524],"type":"Point"}
}