{
  "type": "Feature",
  "properties": {
    "gn:admin1_code":"68.0",
    "gn:asciiname":"Burmaca",
    "gn:country_code":"TR",
    "gn:dem":1065,
    "gn:feature_class":"P",
    "gn:feature_code":"PPL",
    "gn:name":"Burmaca",
    "gn:population":0,
    "gn:timezone":"Europe/Istanbul",
    "iso:country":"TR",
    "name:und_x_variant":[
        "B\u00fcrmece"
    ],
    "wof:name":"Burmaca",
    "wof:placetype":"locality"
},
  "geometry": {"coordinates":[31.48921,40.2676],"type":"Point"}
}