{
  "type": "Feature",
  "properties": {
    "gn:country":"TR",
    "gn:fcode":"PPLA2",
    "gn:pop":4844,
    "iso:country":"TR",
    "name:ara_x_preferred":[
        "\u0627\u0644\u0642\u0635\u064a\u0631"
    ],
    "name:dut_x_preferred":[
        "Alt\u0131n\u00f6z\u00fc"
    ],
    "name:eng_x_preferred":[
        "Alt\u0131n\u00f6z\u00fc"
    ],
    "name:epo_x_preferred":[
        "Alt\u0131n\u00f6z\u00fc"
    ],
    "name:fre_x_preferred":[
        "Alt\u0131n\u00f6z\u00fc"
    ],
    "name:ger_x_preferred":[
        "Alt\u0131n\u00f6z\u00fc"
    ],
    "name:ita_x_preferred":[
        "Distretto di Alt\u0131n\u00f6z\u00fc"
    ],
    "name:jpn_x_preferred":[
        "\u30a2\u30eb\u30c8\u30a5\u30ce\u30b8\u30e5"
    ],
    "name:may_x_preferred":[
        "Alt\u0131n\u00f6z\u00fc"
    ],
    "name:mrj_x_preferred":[
        "\u0410\u043b\u0442\u044b\u043d\u04e7\u0437\u04f1"
    ],
    "name:nan_x_preferred":[
        "Alt\u0131n\u00f6z\u00fc"
    ],
    "name:nob_x_preferred":[
        "Alt\u0131n\u00f6z\u00fc"
    ],
    "name:per_x_preferred":[
        "\u0627\u0644\u062a\u06cc\u0646\u0627\u0632\u0648"
    ],
    "name:pnb_x_preferred":[
        "\u0636\u0644\u0639 \u0627\u0644\u062a\u0646\u0648\u0632\u0648"
    ],
    "name:rus_x_preferred":[
        "\u0410\u043b\u0442\u044b\u043d\u0451\u0437\u044e"
    ],
    "name:sco_x_preferred":[
        "Alt\u0131n\u00f6z\u00fc"
    ],
    "name:swa_x_preferred":[
        "Alt\u0131n\u00f6z\u00fc"
    ],
    "name:tur_x_preferred":[
        "Alt\u0131n\u00f6z\u00fc"
    ],
    "name:unk_x_variant":[
        "Fatikli"
    ],
    "name:urd_x_preferred":[
        "\u0627\u0644\u062a\u06cc\u0646\u0648\u0632\u0648"
    ],
    "name:vie_x_preferred":[
        "Alt\u0131n\u00f6z\u00fc"
    ],
    "qs:name":"Alt\u0131n\u00f6z\u00fc",
    "qs:name_adm0":"Turkey",
    "qs:name_adm1":"Hatay",
    "qs:photos_9k":1,
    "qs:photos_9r":1,
    "qs:photos_all":8,
    "qs:photos_sr":0,
    "qs:placetype":"Town",
    "qs:pop_sr":"4",
    "wd:wordcount":233,
    "wof:name":"Alt\u0131n\u00f6z\u00fc",
    "wof:placetype":"locality",
    "wof:population":4844
},
  "geometry": {"coordinates":[36.24817,36.115],"type":"Point"}
}