{
  "type": "Feature",
  "properties": {
    "gn:admin1_code":"41.0",
    "gn:asciiname":"Dongelli",
    "gn:country_code":"TR",
    "gn:dem":134,
    "gn:feature_class":"P",
    "gn:feature_code":"PPL",
    "gn:name":"D\u00f6ngelli",
    "gn:population":0,
    "gn:timezone":"Europe/Istanbul",
    "iso:country":"TR",
    "name:und_x_variant":[
        "Tongelli",
        "D\u00f6ngelli"
    ],
    "wof:name":"Dongelli",
    "wof:placetype":"locality"
},
  "geometry": {"coordinates":[30.1716,41.01463],"type":"Point"}
}