{
  "type": "Feature",
  "properties": {
    "gn:admin1_code":"55.0",
    "gn:asciiname":"Habilli",
    "gn:country_code":"TR",
    "gn:dem":4,
    "gn:feature_class":"P",
    "gn:feature_code":"PPL",
    "gn:name":"Habilli",
    "gn:population":0,
    "gn:timezone":"Europe/Istanbul",
    "iso:country":"TR",
    "name:und_x_variant":[
        "Hebili",
        "Demircik\u00f6y",
        "Habilli",
        "Hebil\u00fc",
        "Hebilli"
    ],
    "wof:name":"Habilli",
    "wof:placetype":"locality"
},
  "geometry": {"coordinates":[35.73116,41.62941],"type":"Point"}
}