{
  "type": "Feature",
  "properties": {
    "gn:admin1_code":"21.0",
    "gn:asciiname":"Beneklitas",
    "gn:country_code":"TR",
    "gn:dem":734,
    "gn:feature_class":"P",
    "gn:feature_code":"PPL",
    "gn:name":"Beneklita\u015f",
    "gn:population":0,
    "gn:timezone":"Europe/Istanbul",
    "iso:country":"TR",
    "name:tur_x_preferred":[
        "Beneklita\u015f"
    ],
    "wof:name":"Beneklitas",
    "wof:placetype":"locality"
},
  "geometry": {"coordinates":[40.07764,38.01999],"type":"Point"}
}