{
  "type": "Feature",
  "properties": {
    "gn:admin1_code":"44",
    "gn:asciiname":"Nurkuyusu",
    "gn:country_code":"TR",
    "gn:dem":1512,
    "gn:feature_class":"P",
    "gn:feature_code":"PPL",
    "gn:name":"Nurkuyusu",
    "gn:population":0,
    "gn:timezone":"Europe/Istanbul",
    "iso:country":"TR",
    "name:tur_x_preferred":[
        "Nurkuyusu"
    ],
    "wof:name":"Nurkuyusu",
    "wof:placetype":"locality"
},
  "geometry": {"coordinates":[37.63433,38.65739],"type":"Point"}
}