{
  "type": "Feature",
  "properties": {
    "gn:admin1_code":"74",
    "gn:asciiname":"Sirs",
    "gn:country_code":"TR",
    "gn:dem":1041,
    "gn:feature_class":"P",
    "gn:feature_code":"PPL",
    "gn:name":"Sirs",
    "gn:population":0,
    "gn:timezone":"Europe/Istanbul",
    "iso:country":"TR",
    "name:und_x_variant":[
        "K\u00f6m\u00fcrl\u00fc"
    ],
    "wof:name":"Sirs",
    "wof:placetype":"locality"
},
  "geometry": {"coordinates":[41.93692,38.14041],"type":"Point"}
}