{
  "type": "Feature",
  "properties": {
    "gn:admin1_code":"33",
    "gn:asciiname":"Koctepe",
    "gn:country_code":"TR",
    "gn:dem":1012,
    "gn:feature_class":"P",
    "gn:feature_code":"PPL",
    "gn:name":"Ko\u00e7tepe",
    "gn:population":0,
    "gn:timezone":"Europe/Istanbul",
    "iso:country":"TR",
    "name:und_x_variant":[
        "Ko\u00e7tepe",
        "Fandas"
    ],
    "wof:name":"Koctepe",
    "wof:placetype":"locality"
},
  "geometry": {"coordinates":[30.45,37.86667],"type":"Point"}
}