{
  "type": "Feature",
  "properties": {
    "gn:admin1_code":"20",
    "gn:asciiname":"Bulgurlar",
    "gn:country_code":"TR",
    "gn:dem":824,
    "gn:feature_class":"P",
    "gn:feature_code":"PPL",
    "gn:name":"Bulgurlar",
    "gn:population":0,
    "gn:timezone":"Europe/Istanbul",
    "iso:country":"TR",
    "name:tur_x_preferred":[
        "Bulgurlar"
    ],
    "wof:name":"Bulgurlar",
    "wof:placetype":"locality"
},
  "geometry": {"coordinates":[29.73932000000001,38.26925],"type":"Point"}
}