{
  "type": "Feature",
  "properties": {
    "gn:admin1_code":"72.0",
    "gn:asciiname":"Beyazsubasi",
    "gn:country_code":"TR",
    "gn:dem":624,
    "gn:feature_class":"P",
    "gn:feature_code":"PPL",
    "gn:name":"Beyazsuba\u015f\u0131",
    "gn:population":0,
    "gn:timezone":"Europe/Istanbul",
    "iso:country":"TR",
    "name:tur_x_preferred":[
        "Beyazsuba\u015f\u0131"
    ],
    "wof:name":"Beyazsubasi",
    "wof:placetype":"locality"
},
  "geometry": {"coordinates":[41.33168,37.2252],"type":"Point"}
}