{
  "type": "Feature",
  "properties": {
    "gn:admin1_code":"14",
    "gn:asciiname":"Tomanoglu",
    "gn:country_code":"TR",
    "gn:dem":584,
    "gn:feature_class":"P",
    "gn:feature_code":"PPL",
    "gn:name":"Tomano\u011flu",
    "gn:population":0,
    "gn:timezone":"Europe/Istanbul",
    "iso:country":"TR",
    "wof:name":"Tomanoglu",
    "wof:placetype":"locality"
},
  "geometry": {"coordinates":[31.98782000000001,40.94826],"type":"Point"}
}