{
  "type": "Feature",
  "properties": {
    "gn:admin1_code":"49",
    "gn:asciiname":"Erdogan",
    "gn:country_code":"TR",
    "gn:dem":1647,
    "gn:feature_class":"P",
    "gn:feature_code":"PPL",
    "gn:name":"Erdo\u011fan",
    "gn:population":0,
    "gn:timezone":"Europe/Istanbul",
    "iso:country":"TR",
    "name:tur_x_preferred":[
        "Erdo\u011fan"
    ],
    "wof:name":"Erdogan",
    "wof:placetype":"locality"
},
  "geometry": {"coordinates":[41.79243,39.09529000000001],"type":"Point"}
}