{
  "type": "Feature",
  "properties": {
    "gn:admin1_code":"86.0",
    "gn:asciiname":"Kirac",
    "gn:country_code":"TR",
    "gn:dem":1817,
    "gn:feature_class":"P",
    "gn:feature_code":"PPL",
    "gn:name":"K\u0131ra\u00e7",
    "gn:population":0,
    "gn:timezone":"Europe/Istanbul",
    "iso:country":"TR",
    "name:und_x_variant":[
        "K\u0131ra\u00e7"
    ],
    "wof:name":"Kirac",
    "wof:placetype":"locality"
},
  "geometry": {"coordinates":[42.58511,41.13572],"type":"Point"}
}