{
  "type": "Feature",
  "properties": {
    "gn:admin1_code":"70.0",
    "gn:asciiname":"Bozkaya",
    "gn:country_code":"TR",
    "gn:dem":1262,
    "gn:feature_class":"P",
    "gn:feature_code":"PPL",
    "gn:name":"Bozkaya",
    "gn:population":0,
    "gn:timezone":"Europe/Istanbul",
    "iso:country":"TR",
    "name:und_x_variant":[
        "Dozkaya",
        "Bozkaya"
    ],
    "wof:name":"Bozkaya",
    "wof:placetype":"locality"
},
  "geometry": {"coordinates":[44.07699,37.38718],"type":"Point"}
}