{
  "type": "Feature",
  "properties": {
    "gn:admin1_code":"45",
    "gn:asciiname":"Kirazkoy",
    "gn:country_code":"TR",
    "gn:dem":463,
    "gn:feature_class":"P",
    "gn:feature_code":"PPL",
    "gn:name":"Kirazk\u00f6y",
    "gn:population":0,
    "gn:timezone":"Europe/Istanbul",
    "iso:country":"TR",
    "name:tur_x_preferred":[
        "Kirazk\u00f6y"
    ],
    "wof:name":"Kirazkoy",
    "wof:placetype":"locality"
},
  "geometry": {"coordinates":[27.42654000000001,39.35417],"type":"Point"}
}