{
  "type": "Feature",
  "properties": {
    "gn:admin1_code":"65",
    "gn:asciiname":"Atalan",
    "gn:country_code":"TR",
    "gn:dem":1687,
    "gn:feature_class":"P",
    "gn:feature_code":"PPL",
    "gn:name":"Atalan",
    "gn:population":0,
    "gn:timezone":"Europe/Istanbul",
    "iso:country":"TR",
    "name:tur_x_preferred":[
        "Atalan"
    ],
    "wof:name":"Atalan",
    "wof:placetype":"locality"
},
  "geometry": {"coordinates":[43.1539,38.30564],"type":"Point"}
}