{
  "type": "Feature",
  "properties": {
    "gn:admin1_code":"58",
    "gn:asciiname":"Eskikoy",
    "gn:country_code":"TR",
    "gn:dem":1415,
    "gn:feature_class":"P",
    "gn:feature_code":"PPL",
    "gn:name":"Eskik\u00f6y",
    "gn:population":0,
    "gn:timezone":"Europe/Istanbul",
    "iso:country":"TR",
    "name:und_x_variant":[
        "Eski",
        "Eskik\u00f6y"
    ],
    "wof:name":"Eskikoy",
    "wof:placetype":"locality"
},
  "geometry": {"coordinates":[36.802,39.47476],"type":"Point"}
}