{
  "type": "Feature",
  "properties": {
    "gn:admin1_code":"66",
    "gn:asciiname":"Yukaritekke",
    "gn:country_code":"TR",
    "gn:dem":1408,
    "gn:feature_class":"P",
    "gn:feature_code":"PPL",
    "gn:name":"Yukar\u0131tekke",
    "gn:population":0,
    "gn:timezone":"Europe/Istanbul",
    "iso:country":"TR",
    "wof:name":"Yukaritekke",
    "wof:placetype":"locality"
},
  "geometry": {"coordinates":[35.67899,39.35345],"type":"Point"}
}