{
  "type": "Feature",
  "properties": {
    "gn:admin1_code":"17.0",
    "gn:asciiname":"Yaylalar",
    "gn:country_code":"TR",
    "gn:dem":373,
    "gn:feature_class":"P",
    "gn:feature_code":"PPL",
    "gn:name":"Yaylalar",
    "gn:population":0,
    "gn:timezone":"Europe/Istanbul",
    "iso:country":"TR",
    "name:tur_x_preferred":[
        "Yaylalar"
    ],
    "wof:name":"Yaylalar",
    "wof:placetype":"locality"
},
  "geometry": {"coordinates":[26.85272,40.19263],"type":"Point"}
}