{
  "type": "Feature",
  "properties": {
    "gn:admin1_code":"65.0",
    "gn:asciiname":"Cimen",
    "gn:country_code":"TR",
    "gn:dem":1959,
    "gn:feature_class":"P",
    "gn:feature_code":"PPL",
    "gn:name":"\u00c7imen",
    "gn:population":0,
    "gn:timezone":"Europe/Istanbul",
    "iso:country":"TR",
    "name:tur_x_preferred":[
        "Cimenli"
    ],
    "name:tur_x_variant":[
        "\u00c7imen"
    ],
    "wof:name":"Cimen",
    "wof:placetype":"locality"
},
  "geometry": {"coordinates":[43.12166,39.01502],"type":"Point"}
}