{
  "type": "Feature",
  "properties": {
    "gn:admin1_code":"52.0",
    "gn:asciiname":"Ortacokdegirmen",
    "gn:country_code":"TR",
    "gn:dem":728,
    "gn:feature_class":"P",
    "gn:feature_code":"PPL",
    "gn:name":"Orta\u00e7okde\u011firmen",
    "gn:population":0,
    "gn:timezone":"Europe/Istanbul",
    "iso:country":"TR",
    "wof:name":"Ortacokdegirmen",
    "wof:placetype":"locality"
},
  "geometry": {"coordinates":[37.24800000000001,40.9278],"type":"Point"}
}