{
  "type": "Feature",
  "properties": {
    "gn:admin1_code":"44",
    "gn:asciiname":"Kadili",
    "gn:country_code":"TR",
    "gn:dem":1291,
    "gn:feature_class":"P",
    "gn:feature_code":"PPL",
    "gn:name":"Kad\u0131l\u0131",
    "gn:population":0,
    "gn:timezone":"Europe/Istanbul",
    "iso:country":"TR",
    "name:tur_x_preferred":[
        "Kad\u0131l\u0131"
    ],
    "wof:name":"Kadili",
    "wof:placetype":"locality"
},
  "geometry": {"coordinates":[37.78453,38.03664000000001],"type":"Point"}
}