{
  "type": "Feature",
  "properties": {
    "gn:admin1_code":"76.0",
    "gn:asciiname":"Gunluce",
    "gn:country_code":"TR",
    "gn:dem":1156,
    "gn:feature_class":"P",
    "gn:feature_code":"PPL",
    "gn:name":"G\u00fcnl\u00fcce",
    "gn:population":0,
    "gn:timezone":"Europe/Istanbul",
    "iso:country":"TR",
    "name:tur_x_preferred":[
        "G\u00fcnl\u00fcce"
    ],
    "wof:name":"Gunluce",
    "wof:placetype":"locality"
},
  "geometry": {"coordinates":[41.29487,38.40459],"type":"Point"}
}