{
  "type": "Feature",
  "properties": {
    "gn:country":"TR",
    "gn:fcode":"PPL",
    "gn:pop":1433,
    "iso:country":"TR",
    "name:unk_x_variant":[
        "Mihrip"
    ],
    "qs:name":"Sulak",
    "qs:photos_9r":0,
    "qs:photos_sr":0,
    "qs:pop_sr":"3",
    "wd:wordcount":109,
    "wof:name":"Sulak",
    "wof:placetype":"locality",
    "wof:population":1433
},
  "geometry": {"coordinates":[42.12833,37.29639],"type":"Point"}
}