{
  "type": "Feature",
  "properties": {
    "gn:country":"TR",
    "gn:fcode":"PPL",
    "gn:population":1433,
    "iso:country":"TR",
    "name:ceb_x_preferred":[
        "Sulak"
    ],
    "name:deu_x_preferred":[
        "Sulak"
    ],
    "name:fas_x_preferred":[
        "\u0633\u0648\u0644\u06a9"
    ],
    "name:hye_x_preferred":[
        "\u054d\u0578\u0582\u056c\u0561\u056f"
    ],
    "name:rus_x_preferred":[
        "\u0421\u0443\u043b\u0430\u043a"
    ],
    "name:swe_x_preferred":[
        "Sulak"
    ],
    "name:tur_x_preferred":[
        "Sulak"
    ],
    "name:ukr_x_preferred":[
        "\u0421\u0443\u043b\u0430\u043a"
    ],
    "name:und_x_variant":[
        "Mihrip"
    ],
    "qs:name":"Sulak",
    "qs:photos_9r":0,
    "qs:photos_sr":0,
    "qs:pop_sr":"3",
    "wd:wordcount":109,
    "wof:name":"Sulak",
    "wof:placetype":"locality",
    "wof:population":1433
},
  "geometry": {"coordinates":[42.12833,37.29639],"type":"Point"}
}