{
  "type": "Feature",
  "properties": {
    "gn:admin1_code":"33",
    "gn:asciiname":"Kirinti",
    "gn:country_code":"TR",
    "gn:dem":938,
    "gn:feature_class":"P",
    "gn:feature_code":"PPL",
    "gn:name":"K\u0131r\u0131nt\u0131",
    "gn:population":0,
    "gn:timezone":"Europe/Istanbul",
    "iso:country":"TR",
    "name:und_x_variant":[
        "K\u0131r\u0131nt\u0131 K\u00f6y\u00fc",
        "K\u0131r\u0131nt\u0131"
    ],
    "wof:name":"Kirinti",
    "wof:placetype":"locality"
},
  "geometry": {"coordinates":[30.86307,37.65947],"type":"Point"}
}