{
  "type": "Feature",
  "properties": {
    "gn:admin1_code":"63.0",
    "gn:asciiname":"Bugdaytepe",
    "gn:cc2":"TR",
    "gn:country_code":"TR",
    "gn:dem":368,
    "gn:feature_class":"P",
    "gn:feature_code":"PPL",
    "gn:name":"Bu\u011fdaytepe",
    "gn:population":0,
    "gn:timezone":"Europe/Istanbul",
    "iso:country":"TR",
    "name:rus_x_preferred":[
        "Tel\u2019khunta"
    ],
    "name:tur_x_preferred":[
        "Bu\u011fdaytepe"
    ],
    "name:und_x_variant":[
        "Telhunta"
    ],
    "wof:name":"Bugdaytepe",
    "wof:placetype":"locality"
},
  "geometry": {"coordinates":[39.01167,36.89222],"type":"Point"}
}