{
  "type": "Feature",
  "properties": {
    "gn:admin1_code":"55.0",
    "gn:asciiname":"Sirinkoy",
    "gn:country_code":"TR",
    "gn:dem":968,
    "gn:feature_class":"P",
    "gn:feature_code":"PPL",
    "gn:name":"\u015e\u0131r\u0131nk\u00f6y",
    "gn:population":0,
    "gn:timezone":"Europe/Istanbul",
    "iso:country":"TR",
    "name:und_x_variant":[
        "Kavakl\u0131",
        "\u015e\u0131r\u0131nk\u00f6y"
    ],
    "wof:name":"Sirinkoy",
    "wof:placetype":"locality"
},
  "geometry": {"coordinates":[35.48527,41.48268],"type":"Point"}
}