{
  "type": "Feature",
  "properties": {
    "gn:admin1_code":"57.0",
    "gn:asciiname":"Kadinli",
    "gn:country_code":"TR",
    "gn:dem":348,
    "gn:feature_class":"P",
    "gn:feature_code":"PPL",
    "gn:name":"Kad\u0131nl\u0131",
    "gn:population":0,
    "gn:timezone":"Europe/Istanbul",
    "iso:country":"TR",
    "name:und_x_variant":[
        "Kad\u0131n",
        "Kad\u0131nk\u00f6y",
        "Kad\u0131nl\u0131"
    ],
    "wof:name":"Kadinli",
    "wof:placetype":"locality"
},
  "geometry": {"coordinates":[34.72687,41.55646],"type":"Point"}
}