{
  "type": "Feature",
  "properties": {
    "gn:admin1_code":"78",
    "gn:asciiname":"Cicekli Ciftligi",
    "gn:country_code":"TR",
    "gn:dem":1038,
    "gn:feature_class":"P",
    "gn:feature_code":"PPL",
    "gn:name":"\u00c7i\u00e7ekli \u00c7iftli\u011fi",
    "gn:population":0,
    "gn:timezone":"Europe/Istanbul",
    "iso:country":"TR",
    "name:und_x_variant":[
        "\u00c7i\u00e7ekli \u00c7iftli\u011fi",
        "\u00c7i\u00e7ekli"
    ],
    "wof:name":"Cicekli Ciftligi",
    "wof:placetype":"locality"
},
  "geometry": {"coordinates":[32.91206,37.30936],"type":"Point"}
}