{
  "type": "Feature",
  "properties": {
    "gn:admin1_code":"5.0",
    "gn:asciiname":"Cukuroren",
    "gn:country_code":"TR",
    "gn:dem":870,
    "gn:feature_class":"P",
    "gn:feature_code":"PPL",
    "gn:name":"\u00c7ukur\u00f6ren",
    "gn:population":0,
    "gn:timezone":"Europe/Istanbul",
    "iso:country":"TR",
    "wof:name":"Cukuroren",
    "wof:placetype":"locality"
},
  "geometry": {"coordinates":[35.78698,40.80304],"type":"Point"}
}