{
  "type": "Feature",
  "properties": {
    "gn:admin1_code":"35",
    "gn:asciiname":"Ekmeksiz",
    "gn:country_code":"TR",
    "gn:dem":216,
    "gn:feature_class":"P",
    "gn:feature_code":"PPL",
    "gn:name":"Ekmeksiz",
    "gn:population":0,
    "gn:timezone":"Europe/Istanbul",
    "iso:country":"TR",
    "wof:name":"Ekmeksiz",
    "wof:placetype":"locality"
},
  "geometry": {"coordinates":[27.46667,38.46667],"type":"Point"}
}