{
  "type": "Feature",
  "properties": {
    "gn:admin1_code":"49",
    "gn:asciiname":"Bostankaya",
    "gn:country_code":"TR",
    "gn:dem":1585,
    "gn:feature_class":"P",
    "gn:feature_code":"PPL",
    "gn:name":"Bostankaya",
    "gn:population":0,
    "gn:timezone":"Europe/Istanbul",
    "iso:country":"TR",
    "name:tur_x_preferred":[
        "Bostankaya"
    ],
    "wof:name":"Bostankaya",
    "wof:placetype":"locality"
},
  "geometry": {"coordinates":[42.65716,39.20412],"type":"Point"}
}