{
  "type": "Feature",
  "properties": {
    "gn:admin1_code":"57",
    "gn:asciiname":"Incir",
    "gn:country_code":"TR",
    "gn:dem":216,
    "gn:feature_class":"P",
    "gn:feature_code":"PPL",
    "gn:name":"\u0130ncir",
    "gn:population":0,
    "gn:timezone":"Europe/Istanbul",
    "iso:country":"TR",
    "name:tur_x_preferred":[
        "\u0130ncir"
    ],
    "wof:name":"Incir",
    "wof:placetype":"locality"
},
  "geometry": {"coordinates":[34.99735,41.40776],"type":"Point"}
}