{
  "type": "Feature",
  "properties": {
    "gn:admin1_code":"48",
    "gn:asciiname":"Gokseki",
    "gn:country_code":"TR",
    "gn:dem":385,
    "gn:feature_class":"P",
    "gn:feature_code":"PPL",
    "gn:name":"G\u00f6kseki",
    "gn:population":0,
    "gn:timezone":"Europe/Istanbul",
    "iso:country":"TR",
    "name:tur_x_preferred":[
        "G\u00f6kseki"
    ],
    "wof:name":"Gokseki",
    "wof:placetype":"locality"
},
  "geometry": {"coordinates":[27.77548,37.41661],"type":"Point"}
}