{
  "type": "Feature",
  "properties": {
    "gn:admin1_code":"65.0",
    "gn:asciiname":"Ulasir",
    "gn:country_code":"TR",
    "gn:dem":2430,
    "gn:feature_class":"P",
    "gn:feature_code":"PPL",
    "gn:name":"Ulas\u0131r",
    "gn:population":0,
    "gn:timezone":"Europe/Istanbul",
    "iso:country":"TR",
    "name:tur_x_preferred":[
        "Ulas\u0131r"
    ],
    "wof:name":"Ulasir",
    "wof:placetype":"locality"
},
  "geometry": {"coordinates":[43.07755,37.78796],"type":"Point"}
}