{
  "type": "Feature",
  "properties": {
    "gn:admin1_code":"04",
    "gn:asciiname":"Kuruyaka",
    "gn:country_code":"TR",
    "gn:dem":1642,
    "gn:feature_class":"P",
    "gn:feature_code":"PPL",
    "gn:name":"Kuruyaka",
    "gn:population":0,
    "gn:timezone":"Europe/Istanbul",
    "iso:country":"TR",
    "name:und_x_variant":[
        "A\u015fur",
        "Kuruyaka"
    ],
    "wof:name":"Kuruyaka",
    "wof:placetype":"locality"
},
  "geometry": {"coordinates":[42.77731,39.2864],"type":"Point"}
}