{
  "type": "Feature",
  "properties": {
    "gn:admin1_code":"25",
    "gn:asciiname":"Sobecayir",
    "gn:country_code":"TR",
    "gn:dem":1948,
    "gn:feature_class":"P",
    "gn:feature_code":"PPL",
    "gn:name":"S\u00f6be\u00e7ay\u0131r",
    "gn:population":0,
    "gn:timezone":"Europe/Istanbul",
    "iso:country":"TR",
    "name:tur_x_preferred":[
        "S\u00f6be\u00e7ay\u0131r"
    ],
    "name:und_x_variant":[
        "S\u00f6be\u00e7ay\u0131r\u0131"
    ],
    "wof:name":"Sobecayir",
    "wof:placetype":"locality"
},
  "geometry": {"coordinates":[40.71242,39.44005],"type":"Point"}
}