{
  "type": "Feature",
  "properties": {
    "gn:admin1_code":"68",
    "gn:asciiname":"Deliler",
    "gn:country_code":"TR",
    "gn:dem":973,
    "gn:feature_class":"P",
    "gn:feature_code":"PPL",
    "gn:name":"Deliler",
    "gn:population":0,
    "gn:timezone":"Europe/Istanbul",
    "iso:country":"TR",
    "name:und_x_variant":[
        "Deliler \u00c7iftli\u011fi"
    ],
    "wof:name":"Deliler",
    "wof:placetype":"locality"
},
  "geometry": {"coordinates":[32.99406,39.58855],"type":"Point"}
}