{
  "type": "Feature",
  "properties": {
    "gn:admin1_code":"53.0",
    "gn:asciiname":"Cataltepe",
    "gn:country_code":"TR",
    "gn:dem":1769,
    "gn:feature_class":"P",
    "gn:feature_code":"PPL",
    "gn:name":"\u00c7ataltepe",
    "gn:population":0,
    "gn:timezone":"Europe/Istanbul",
    "iso:country":"TR",
    "name:und_x_variant":[
        "\u00c7ataltepe K\u00f6y",
        "\u00c7ataltepe"
    ],
    "wof:name":"Cataltepe",
    "wof:placetype":"locality"
},
  "geometry": {"coordinates":[40.50266,40.62986],"type":"Point"}
}