{
  "type": "Feature",
  "properties": {
    "gn:admin1_code":"84.0",
    "gn:asciiname":"Akcakale",
    "gn:country_code":"TR",
    "gn:dem":1626,
    "gn:feature_class":"P",
    "gn:feature_code":"PPL",
    "gn:name":"Ak\u00e7akale",
    "gn:population":0,
    "gn:timezone":"Europe/Istanbul",
    "iso:country":"TR",
    "name:tur_x_preferred":[
        "Ak\u00e7akale"
    ],
    "name:und_x_variant":[
        "Ke\u00e7eb\u00f6rk",
        "A\u011fcalar",
        "Ke\u00e7eb\u00fcrk"
    ],
    "wof:name":"Akcakale",
    "wof:placetype":"locality"
},
  "geometry": {"coordinates":[43.29963,40.7748],"type":"Point"}
}