{
  "type": "Feature",
  "properties": {
    "gn:admin1_code":"64",
    "gn:asciiname":"Sehit Hocalar",
    "gn:country_code":"TR",
    "gn:dem":651,
    "gn:feature_class":"P",
    "gn:feature_code":"PPL",
    "gn:name":"\u015eehit Hocalar",
    "gn:population":0,
    "gn:timezone":"Europe/Istanbul",
    "iso:country":"TR",
    "wof:name":"Sehit Hocalar",
    "wof:placetype":"locality"
},
  "geometry": {"coordinates":[28.80233,38.36794],"type":"Point"}
}