{
  "type": "Feature",
  "properties": {
    "iso:country":"TR",
    "name:tur_x_preferred":[
        "Ku\u015ftepe"
    ],
    "wof:name":"Kustepe",
    "wof:placetype":"neighbourhood"
},
  "geometry": {"coordinates":[28.99078909743516,41.07282706015343],"type":"Point"}
}