{
  "type": "Feature",
  "properties": {
    "gn:admin1_code":"25",
    "gn:asciiname":"Iligoze",
    "gn:country_code":"TR",
    "gn:dem":1908,
    "gn:feature_class":"P",
    "gn:feature_code":"PPL",
    "gn:name":"Il\u0131g\u00f6ze",
    "gn:population":0,
    "gn:timezone":"Europe/Istanbul",
    "iso:country":"TR",
    "name:tur_x_preferred":[
        "Il\u0131g\u00f6ze"
    ],
    "name:und_x_variant":[
        "Ill\u0131g\u00f6ze"
    ],
    "wof:name":"Iligoze",
    "wof:placetype":"locality"
},
  "geometry": {"coordinates":[41.57399,39.61527],"type":"Point"}
}