{
  "type": "Feature",
  "properties": {
    "gn:admin1_code":"49",
    "gn:asciiname":"Odakoy",
    "gn:country_code":"TR",
    "gn:dem":1695,
    "gn:feature_class":"P",
    "gn:feature_code":"PPL",
    "gn:name":"Odak\u00f6y",
    "gn:population":0,
    "gn:timezone":"Europe/Istanbul",
    "iso:country":"TR",
    "name:und_x_variant":[
        "Yekmal",
        "Odak\u00f6y"
    ],
    "wof:name":"Odakoy",
    "wof:placetype":"locality"
},
  "geometry": {"coordinates":[42.52431,39.03558],"type":"Point"}
}