{
  "type": "Feature",
  "properties": {
    "gn:admin1_code":"60.0",
    "gn:asciiname":"Cat",
    "gn:cc2":"TR",
    "gn:country_code":"TR",
    "gn:dem":1080,
    "gn:feature_class":"P",
    "gn:feature_code":"PPL",
    "gn:name":"\u00c7at",
    "gn:population":0,
    "gn:timezone":"Europe/Istanbul",
    "iso:country":"TR",
    "name:und_x_variant":[
        "Fenk",
        "\u00c7at"
    ],
    "wof:name":"Cat",
    "wof:placetype":"locality"
},
  "geometry": {"coordinates":[36.71667,40.28333],"type":"Point"}
}