{
  "type": "Feature",
  "properties": {
    "gn:admin1_code":"10",
    "gn:asciiname":"Kucukler",
    "gn:country_code":"TR",
    "gn:dem":241,
    "gn:feature_class":"P",
    "gn:feature_code":"PPL",
    "gn:name":"K\u00fc\u00e7\u00fckler",
    "gn:population":0,
    "gn:timezone":"Europe/Istanbul",
    "iso:country":"TR",
    "name:tur_x_preferred":[
        "K\u00fc\u00e7\u00fckler"
    ],
    "wof:name":"Kucukler",
    "wof:placetype":"locality"
},
  "geometry": {"coordinates":[28.32766,39.55136],"type":"Point"}
}