{
  "type": "Feature",
  "properties": {
    "gn:admin1_code":"14",
    "gn:asciiname":"Misirli",
    "gn:country_code":"TR",
    "gn:dem":773,
    "gn:feature_class":"P",
    "gn:feature_code":"PPL",
    "gn:name":"M\u0131s\u0131rl\u0131",
    "gn:population":0,
    "gn:timezone":"Europe/Istanbul",
    "iso:country":"TR",
    "wof:name":"Misirli",
    "wof:placetype":"locality"
},
  "geometry": {"coordinates":[31.94477,40.8791],"type":"Point"}
}