{
  "type": "Feature",
  "properties": {
    "gn:admin1_code":"72",
    "gn:asciiname":"Camlica",
    "gn:country_code":"TR",
    "gn:dem":512,
    "gn:feature_class":"P",
    "gn:feature_code":"PPL",
    "gn:name":"\u00c7aml\u0131ca",
    "gn:population":0,
    "gn:timezone":"Europe/Istanbul",
    "iso:country":"TR",
    "name:tur_x_preferred":[
        "\u00c7aml\u0131ca"
    ],
    "wof:name":"Camlica",
    "wof:placetype":"locality"
},
  "geometry": {"coordinates":[40.70347,37.16701],"type":"Point"}
}