{
  "type": "Feature",
  "properties": {
    "gn:admin1_code":"13.0",
    "gn:asciiname":"Yaylali",
    "gn:country_code":"TR",
    "gn:dem":2403,
    "gn:feature_class":"P",
    "gn:feature_code":"PPL",
    "gn:name":"Yaylal\u0131",
    "gn:population":0,
    "gn:timezone":"Europe/Istanbul",
    "iso:country":"TR",
    "name:tur_x_preferred":[
        "Yaylal\u0131"
    ],
    "wof:name":"Yaylali",
    "wof:placetype":"locality"
},
  "geometry": {"coordinates":[42.66271,38.17213],"type":"Point"}
}