{
  "type": "Feature",
  "properties": {
    "gn:admin1_code":"83.0",
    "gn:asciiname":"Yeniyapan",
    "gn:country_code":"TR",
    "gn:dem":533,
    "gn:feature_class":"P",
    "gn:feature_code":"PPL",
    "gn:name":"Yeniyapan",
    "gn:population":0,
    "gn:timezone":"Europe/Istanbul",
    "iso:country":"TR",
    "name:und_x_variant":[
        "Yeni-Yapan",
        "Yeniyapan"
    ],
    "wof:name":"Yeniyapan",
    "wof:placetype":"locality"
},
  "geometry": {"coordinates":[37.78669,36.89118],"type":"Point"}
}