{
  "type": "Feature",
  "properties": {
    "gn:admin1_code":"31",
    "gn:asciiname":"Sucikagi",
    "gn:country_code":"TR",
    "gn:dem":790,
    "gn:feature_class":"P",
    "gn:feature_code":"PPL",
    "gn:name":"Su\u00e7\u0131ka\u011f\u0131",
    "gn:population":0,
    "gn:timezone":"Europe/Istanbul",
    "iso:country":"TR",
    "name:tur_x_preferred":[
        "Su\u00e7\u0131ka\u011f\u0131"
    ],
    "wof:name":"Sucikagi",
    "wof:placetype":"locality"
},
  "geometry": {"coordinates":[36.23656,36.5414],"type":"Point"}
}