{
  "type": "Feature",
  "properties": {
    "gn:admin1_code":"14",
    "gn:asciiname":"Bozyer",
    "gn:country_code":"TR",
    "gn:dem":834,
    "gn:feature_class":"P",
    "gn:feature_code":"PPL",
    "gn:name":"Bozyer",
    "gn:population":0,
    "gn:timezone":"Europe/Istanbul",
    "iso:country":"TR",
    "wof:name":"Bozyer",
    "wof:placetype":"locality"
},
  "geometry": {"coordinates":[31.58898,40.43318],"type":"Point"}
}