{
  "type": "Feature",
  "properties": {
    "gn:admin1_code":"76.0",
    "gn:asciiname":"Meydancik",
    "gn:country_code":"TR",
    "gn:dem":505,
    "gn:feature_class":"P",
    "gn:feature_code":"PPL",
    "gn:name":"Meydanc\u0131k",
    "gn:population":0,
    "gn:timezone":"Europe/Istanbul",
    "iso:country":"TR",
    "wof:name":"Meydancik",
    "wof:placetype":"locality"
},
  "geometry": {"coordinates":[41.49433,37.81329],"type":"Point"}
}