{
  "type": "Feature",
  "properties": {
    "iso:country":"TR",
    "name:eng_x_preferred":[
        "Adil"
    ],
    "name:tur_x_preferred":[
        "Adil"
    ],
    "wof:name":"Adil",
    "wof:placetype":"neighbourhood"
},
  "geometry": {"coordinates":[29.25944597928868,40.97702564511403],"type":"Point"}
}