{
  "type": "Feature",
  "properties": {
    "gn:admin1_code":"08",
    "gn:asciiname":"Gumusdere",
    "gn:country_code":"TR",
    "gn:dem":227,
    "gn:feature_class":"P",
    "gn:feature_code":"PPL",
    "gn:name":"G\u00fcm\u00fc\u015fdere",
    "gn:population":0,
    "gn:timezone":"Europe/Istanbul",
    "iso:country":"TR",
    "name:tur_x_preferred":[
        "G\u00fcm\u00fc\u015fdere"
    ],
    "wof:name":"Gumusdere",
    "wof:placetype":"locality"
},
  "geometry": {"coordinates":[41.50518,41.45674],"type":"Point"}
}