{
  "type": "Feature",
  "properties": {
    "gn:admin1_code":"23",
    "gn:asciiname":"Balcali",
    "gn:country_code":"TR",
    "gn:dem":950,
    "gn:feature_class":"P",
    "gn:feature_code":"PPL",
    "gn:name":"Balcal\u0131",
    "gn:population":0,
    "gn:timezone":"Europe/Istanbul",
    "iso:country":"TR",
    "name:tur_x_preferred":[
        "Balcal\u0131"
    ],
    "wof:name":"Balcali",
    "wof:placetype":"locality"
},
  "geometry": {"coordinates":[39.8826,39.03125],"type":"Point"}
}