{
  "type": "Feature",
  "properties": {
    "gn:admin1_code":"60.0",
    "gn:asciiname":"Asarcik",
    "gn:country_code":"TR",
    "gn:dem":592,
    "gn:feature_class":"P",
    "gn:feature_code":"PPL",
    "gn:name":"Asarc\u0131k",
    "gn:population":0,
    "gn:timezone":"Europe/Istanbul",
    "iso:country":"TR",
    "wof:name":"Asarcik",
    "wof:placetype":"locality"
},
  "geometry": {"coordinates":[36.21417,40.32705],"type":"Point"}
}