{
  "type": "Feature",
  "properties": {
    "iso:country":"TR",
    "name:eng_x_preferred":[
        "Gumusyaka"
    ],
    "name:tur_x_preferred":[
        "G\u00fcm\u00fc\u015fyaka"
    ],
    "name:tur_x_variant":[
        "G\u00fcm\u00fc\u015fyaka Merkez"
    ],
    "wof:name":"Gumusyaka",
    "wof:placetype":"neighbourhood"
},
  "geometry": {"coordinates":[28.04346114636823,41.04720238404984],"type":"Point"}
}