{
  "type": "Feature",
  "properties": {
    "gn:admin1_code":"65",
    "gn:asciiname":"Yukari Sagmalli",
    "gn:country_code":"TR",
    "gn:dem":2249,
    "gn:feature_class":"P",
    "gn:feature_code":"PPL",
    "gn:name":"Yukar\u0131 Sa\u011fmall\u0131",
    "gn:population":0,
    "gn:timezone":"Europe/Istanbul",
    "iso:country":"TR",
    "name:tur_x_preferred":[
        "Yukar\u0131 Sa\u011fmall\u0131"
    ],
    "name:und_x_variant":[
        "Yukar\u0131no\u015far",
        "Yukar\u0131 Nev\u015far",
        "Yukar\u0131sa\u011fmall\u0131"
    ],
    "wof:name":"Yukari Sagmalli",
    "wof:placetype":"locality"
},
  "geometry": {"coordinates":[43.96506,38.91317],"type":"Point"}
}