{
  "type": "Feature",
  "properties": {
    "gn:admin1_code":"38",
    "gn:asciiname":"Gomec",
    "gn:country_code":"TR",
    "gn:dem":1146,
    "gn:feature_class":"P",
    "gn:feature_code":"PPL",
    "gn:name":"G\u00f6me\u00e7",
    "gn:population":0,
    "gn:timezone":"Europe/Istanbul",
    "iso:country":"TR",
    "wof:name":"Gomec",
    "wof:placetype":"locality"
},
  "geometry": {"coordinates":[35.66582000000001,38.86877],"type":"Point"}
}