{
  "type": "Feature",
  "properties": {
    "gn:admin1_code":"44.0",
    "gn:asciiname":"Duruldu",
    "gn:country_code":"TR",
    "gn:dem":965,
    "gn:feature_class":"P",
    "gn:feature_code":"PPL",
    "gn:name":"Duruldu",
    "gn:population":0,
    "gn:timezone":"Europe/Istanbul",
    "iso:country":"TR",
    "name:tur_x_preferred":[
        "Duruldu"
    ],
    "wof:name":"Duruldu",
    "wof:placetype":"locality"
},
  "geometry": {"coordinates":[38.16216,38.32286],"type":"Point"}
}