{
  "type": "Feature",
  "properties": {
    "gn:admin1_code":"07",
    "gn:asciiname":"Kizilcasehir",
    "gn:country_code":"TR",
    "gn:dem":214,
    "gn:feature_class":"P",
    "gn:feature_code":"PPL",
    "gn:name":"K\u0131z\u0131lca\u015fehir",
    "gn:population":0,
    "gn:timezone":"Europe/Istanbul",
    "iso:country":"TR",
    "wof:name":"Kizilcasehir",
    "wof:placetype":"locality"
},
  "geometry": {"coordinates":[32.09106,36.56488],"type":"Point"}
}