{
  "type": "Feature",
  "properties": {
    "gn:country":"TR",
    "gn:fcode":"PPL",
    "gn:population":0,
    "iso:country":"TR",
    "name:ara_x_preferred":[
        "\u0628\u064a\u0631\u0645 \u0628\u0627\u0634\u0627"
    ],
    "name:aze_x_preferred":[
        "Bayrampa\u015fa"
    ],
    "name:cat_x_preferred":[
        "Bayrampa\u015fa"
    ],
    "name:ceb_x_preferred":[
        "Bayrampa\u015fa"
    ],
    "name:deu_x_preferred":[
        "Bayrampa\u015fa"
    ],
    "name:diq_x_preferred":[
        "Bayrampa\u015fa"
    ],
    "name:eng_x_preferred":[
        "Bayrampa\u015fa"
    ],
    "name:fas_x_preferred":[
        "\u0628\u0627\u06cc\u0631\u0627\u0645 \u067e\u0627\u0634\u0627"
    ],
    "name:fra_x_preferred":[
        "Bayrampa\u015fa"
    ],
    "name:hun_x_preferred":[
        "Bayrampa\u015fa"
    ],
    "name:hye_x_preferred":[
        "\u0532\u0561\u0575\u0580\u0561\u0574\u0583\u0561\u0577\u0561"
    ],
    "name:ind_x_preferred":[
        "Bayrampa\u015fa"
    ],
    "name:ita_x_preferred":[
        "Bayrampa\u015fa"
    ],
    "name:jpn_x_preferred":[
        "\u30d0\u30a4\u30e9\u30e0\u30d1\u30b7\u30e3"
    ],
    "name:kat_x_preferred":[
        "\u10d1\u10d0\u10d8\u10e0\u10d0\u10db\u10e4\u10d0\u10e8\u10d8\u10e1 \u10e0\u10d0\u10d8\u10dd\u10dc\u10d8"
    ],
    "name:lav_x_preferred":[
        "Bajrampa\u0161\u0101 rajons"
    ],
    "name:mkd_x_preferred":[
        "\u0411\u0430\u0458\u0440\u0430\u043c\u043f\u0430\u0448\u0430"
    ],
    "name:mrj_x_preferred":[
        "\u0411\u0430\u0439\u0440\u0430\u043c\u043f\u0430\u0448\u0430"
    ],
    "name:msa_x_preferred":[
        "Bayrampa\u015fa"
    ],
    "name:nan_x_preferred":[
        "Bayrampa\u015fa"
    ],
    "name:nld_x_preferred":[
        "Bayrampa\u015fa"
    ],
    "name:nob_x_preferred":[
        "Bayrampa\u015fa"
    ],
    "name:pnb_x_preferred":[
        "\u0628\u06cc\u0631\u0627\u0645\u067e\u0627\u0634\u0627"
    ],
    "name:por_x_preferred":[
        "Bayrampa\u015fa"
    ],
    "name:rus_x_preferred":[
        "\u0411\u0430\u0439\u0440\u0430\u043c\u043f\u0430\u0448\u0430"
    ],
    "name:sco_x_preferred":[
        "Bayrampa\u015fa"
    ],
    "name:spa_x_preferred":[
        "Bayrampa\u015fa"
    ],
    "name:swa_x_preferred":[
        "Bayrampa\u015fa"
    ],
    "name:tur_x_preferred":[
        "Bayrampa\u015fa"
    ],
    "name:urd_x_preferred":[
        "\u0628\u06cc\u0631\u0645 \u067e\u0627\u0634\u0627"
    ],
    "name:vie_x_preferred":[
        "Bayrampa\u015fa"
    ],
    "qs:name":"Bayrampa\u015fa",
    "qs:name_adm0":"Turkey",
    "qs:name_adm1":"\u0130stanbul",
    "qs:photos":257,
    "qs:photos_1k":52,
    "qs:photos_9k":1,
    "qs:photos_9r":4,
    "qs:photos_all":257,
    "qs:photos_sr":5,
    "qs:placetype":"Town",
    "qs:pop_sr":"0",
    "wd:wordcount":428,
    "wof:name":"Bayrampa\u015fa",
    "wof:placetype":"locality",
    "wof:population":0
},
  "geometry": {"coordinates":[28.89894,41.0523],"type":"Point"}
}