{
  "type": "Feature",
  "properties": {
    "gn:admin1_code":"58.0",
    "gn:asciiname":"Akdede",
    "gn:country_code":"TR",
    "gn:dem":1528,
    "gn:feature_class":"P",
    "gn:feature_code":"PPL",
    "gn:name":"Akdede",
    "gn:population":0,
    "gn:timezone":"Europe/Istanbul",
    "iso:country":"TR",
    "wof:name":"Akdede",
    "wof:placetype":"locality"
},
  "geometry": {"coordinates":[37.76917,39.72207],"type":"Point"}
}