{
  "type": "Feature",
  "properties": {
    "gn:admin1_code":"25.0",
    "gn:asciiname":"Muratgeldi",
    "gn:country_code":"TR",
    "gn:dem":1771,
    "gn:feature_class":"P",
    "gn:feature_code":"PPL",
    "gn:name":"Muratgeldi",
    "gn:population":0,
    "gn:timezone":"Europe/Istanbul",
    "iso:country":"TR",
    "name:und_x_variant":[
        "Donarkom",
        "Dinarkomu",
        "Muratgeldi",
        "Dinarkom"
    ],
    "wof:name":"Muratgeldi",
    "wof:placetype":"locality"
},
  "geometry": {"coordinates":[41.31741,40.05519],"type":"Point"}
}