{
  "type": "Feature",
  "properties": {
    "gn:admin1_code":"58",
    "gn:asciiname":"Cobansaray",
    "gn:country_code":"TR",
    "gn:dem":1388,
    "gn:feature_class":"P",
    "gn:feature_code":"PPL",
    "gn:name":"\u00c7obansaray",
    "gn:population":0,
    "gn:timezone":"Europe/Istanbul",
    "iso:country":"TR",
    "wof:name":"Cobansaray",
    "wof:placetype":"locality"
},
  "geometry": {"coordinates":[36.33203,39.90664],"type":"Point"}
}