{
  "type": "Feature",
  "properties": {
    "gn:country":"TR",
    "gn:fcode":"PPL",
    "gn:pop":9513,
    "iso:country":"TR",
    "name:ara_x_preferred":[
        "\u0627\u0644\u0628\u0634\u064a\u0631\u064a\u0629"
    ],
    "name:chi_x_preferred":[
        "\u8c9d\u5e0c\u91cc"
    ],
    "name:ckb_x_preferred":[
        "\u0642\u0648\u0628\u06cc\u0646"
    ],
    "name:dut_x_preferred":[
        "Be\u015firi"
    ],
    "name:eng_x_preferred":[
        "Be\u015firi"
    ],
    "name:fre_x_preferred":[
        "Be\u015firi"
    ],
    "name:ger_x_preferred":[
        "Be\u015firi"
    ],
    "name:ita_x_preferred":[
        "Distretto di Be\u015firi"
    ],
    "name:kur_x_preferred":[
        "Qub\u00een"
    ],
    "name:may_x_preferred":[
        "Be\u015firi"
    ],
    "name:mrj_x_preferred":[
        "\u0411\u0435\u0448\u0438\u0440\u0438"
    ],
    "name:nan_x_preferred":[
        "Be\u015firi"
    ],
    "name:nno_x_preferred":[
        "Be\u015firi"
    ],
    "name:per_x_preferred":[
        "\u0628\u0634\u0631\u0644\u06cc"
    ],
    "name:pnb_x_preferred":[
        "\u0636\u0644\u0639 \u0628\u06cc\u0634\u0631\u06cc"
    ],
    "name:rus_x_preferred":[
        "\u0411\u0435\u0448\u0438\u0440\u0438"
    ],
    "name:swa_x_preferred":[
        "Be\u015firi"
    ],
    "name:tur_x_preferred":[
        "Be\u015firi"
    ],
    "name:unk_x_variant":[
        "Kobin"
    ],
    "name:urd_x_preferred":[
        "\u0628\u0634\u06cc\u0631\u06cc"
    ],
    "name:vie_x_preferred":[
        "Be\u015firi"
    ],
    "qs:name":"Be\u015firi",
    "qs:name_adm0":"Turkey",
    "qs:name_adm1":"Batman",
    "qs:photos_9r":0,
    "qs:photos_sr":0,
    "qs:placetype":"Town",
    "qs:pop_sr":"5",
    "wd:wordcount":72,
    "wof:name":"Be\u015firi",
    "wof:placetype":"locality",
    "wof:population":9513
},
  "geometry": {"coordinates":[41.2924,37.91838],"type":"Point"}
}