{
  "type": "Feature",
  "properties": {
    "gn:admin1_code":"25.0",
    "gn:asciiname":"Demirdoven",
    "gn:country_code":"TR",
    "gn:dem":1743,
    "gn:feature_class":"P",
    "gn:feature_code":"PPL",
    "gn:name":"Demird\u00f6ven",
    "gn:population":0,
    "gn:timezone":"Europe/Istanbul",
    "iso:country":"TR",
    "name:und_x_variant":[
        "Demirezen",
        "Demird\u00f6ven"
    ],
    "wof:name":"Demirdoven",
    "wof:placetype":"locality"
},
  "geometry": {"coordinates":[41.7364,40.03661],"type":"Point"}
}