{
  "type": "Feature",
  "properties": {
    "gn:admin1_code":"61.0",
    "gn:asciiname":"Kayran",
    "gn:country_code":"TR",
    "gn:dem":954,
    "gn:feature_class":"P",
    "gn:feature_code":"PPL",
    "gn:name":"Kayran",
    "gn:population":0,
    "gn:timezone":"Europe/Istanbul",
    "iso:country":"TR",
    "name:und_x_variant":[
        "\u015eur"
    ],
    "wof:name":"Kayran",
    "wof:placetype":"locality"
},
  "geometry": {"coordinates":[40.27231,40.73849000000001],"type":"Point"}
}