{
  "type": "Feature",
  "properties": {
    "gn:admin1_code":"58",
    "gn:asciiname":"Mehkenli",
    "gn:country_code":"TR",
    "gn:dem":1697,
    "gn:feature_class":"P",
    "gn:feature_code":"PPL",
    "gn:name":"Mehkenli",
    "gn:population":0,
    "gn:timezone":"Europe/Istanbul",
    "iso:country":"TR",
    "name:und_x_variant":[
        "Mahk\u00e2nl\u0131",
        "Mahkenli",
        "A\u011fa\u00e7l\u0131"
    ],
    "wof:name":"Mehkenli",
    "wof:placetype":"locality"
},
  "geometry": {"coordinates":[37.43667,38.73774],"type":"Point"}
}