{
  "type": "Feature",
  "properties": {
    "gn:admin1_code":"35",
    "gn:asciiname":"Seyrekli",
    "gn:country_code":"TR",
    "gn:dem":91,
    "gn:feature_class":"P",
    "gn:feature_code":"PPL",
    "gn:name":"Seyrekli",
    "gn:population":0,
    "gn:timezone":"Europe/Istanbul",
    "iso:country":"TR",
    "name:tur_x_preferred":[
        "Seyrekli"
    ],
    "name:tur_x_variant":[
        "Serekli"
    ],
    "wof:name":"Seyrekli",
    "wof:placetype":"locality"
},
  "geometry": {"coordinates":[27.91667,38.18833],"type":"Point"}
}