{
  "type": "Feature",
  "properties": {
    "gn:admin1_code":"43",
    "gn:asciiname":"Seyhler",
    "gn:country_code":"TR",
    "gn:dem":904,
    "gn:feature_class":"P",
    "gn:feature_code":"PPL",
    "gn:name":"\u015eeyhler",
    "gn:population":0,
    "gn:timezone":"Europe/Istanbul",
    "iso:country":"TR",
    "name:tur_x_preferred":[
        "\u015eeyhler"
    ],
    "wof:name":"Seyhler",
    "wof:placetype":"locality"
},
  "geometry": {"coordinates":[29.32379,39.18505],"type":"Point"}
}