{
  "type": "Feature",
  "properties": {
    "gn:admin1_code":"21",
    "gn:asciiname":"Nefirtas",
    "gn:country_code":"TR",
    "gn:dem":799,
    "gn:feature_class":"P",
    "gn:feature_code":"PPL",
    "gn:name":"Nefirta\u015f",
    "gn:population":0,
    "gn:timezone":"Europe/Istanbul",
    "iso:country":"TR",
    "name:und_x_variant":[
        "Paraliyan",
        "Nefirta\u015f",
        "Yeberaliyan"
    ],
    "wof:name":"Nefirtas",
    "wof:placetype":"locality"
},
  "geometry": {"coordinates":[40.38557,38.26139000000001],"type":"Point"}
}