{
  "type": "Feature",
  "properties": {
    "gn:admin1_code":"58",
    "gn:asciiname":"Asagiyaylacik",
    "gn:country_code":"TR",
    "gn:dem":1826,
    "gn:feature_class":"P",
    "gn:feature_code":"PPL",
    "gn:name":"A\u015fa\u011f\u0131yaylac\u0131k",
    "gn:population":0,
    "gn:timezone":"Europe/Istanbul",
    "iso:country":"TR",
    "wof:name":"Asagiyaylacik",
    "wof:placetype":"locality"
},
  "geometry": {"coordinates":[37.03229,38.69639],"type":"Point"}
}