{
  "type": "Feature",
  "properties": {
    "gn:admin1_code":"8.0",
    "gn:asciiname":"Yukari Maden",
    "gn:country_code":"TR",
    "gn:dem":949,
    "gn:feature_class":"P",
    "gn:feature_code":"PPL",
    "gn:name":"Yukar\u0131 Maden",
    "gn:population":0,
    "gn:timezone":"Europe/Istanbul",
    "iso:country":"TR",
    "name:tur_x_preferred":[
        "Yukar\u0131 Maden"
    ],
    "name:und_x_variant":[
        "Yukar\u0131maden"
    ],
    "wof:name":"Yukari Maden",
    "wof:placetype":"locality"
},
  "geometry": {"coordinates":[41.86536,40.99463],"type":"Point"}
}