{
  "type": "Feature",
  "properties": {
    "gn:admin1_code":"37.0",
    "gn:asciiname":"Belenkoy",
    "gn:country_code":"TR",
    "gn:dem":1291,
    "gn:feature_class":"P",
    "gn:feature_code":"PPL",
    "gn:name":"Belenk\u00f6y",
    "gn:population":0,
    "gn:timezone":"Europe/Istanbul",
    "iso:country":"TR",
    "wof:name":"Belenkoy",
    "wof:placetype":"locality"
},
  "geometry": {"coordinates":[33.68333,41.56667],"type":"Point"}
}