{
  "type": "Feature",
  "properties": {
    "gn:admin1_code":"77.0",
    "gn:asciiname":"Arslandede",
    "gn:country_code":"TR",
    "gn:dem":1449,
    "gn:feature_class":"P",
    "gn:feature_code":"PPL",
    "gn:name":"Arslandede",
    "gn:population":0,
    "gn:timezone":"Europe/Istanbul",
    "iso:country":"TR",
    "name:ceb_x_preferred":[
        "Arslandede"
    ],
    "name:msa_x_preferred":[
        "Arslandede"
    ],
    "name:tur_x_preferred":[
        "Arslandede"
    ],
    "name:und_x_variant":[
        "K\u00e2n",
        "K\u00e2nk\u00f6y",
        "Arslandede"
    ],
    "name:vie_x_preferred":[
        "Arslandede"
    ],
    "wof:name":"Arslandede",
    "wof:placetype":"locality"
},
  "geometry": {"coordinates":[40.47094,40.37758],"type":"Point"}
}