{
  "type": "Feature",
  "properties": {
    "gn:admin1_code":"43",
    "gn:asciiname":"Dudas",
    "gn:country_code":"TR",
    "gn:dem":990,
    "gn:feature_class":"P",
    "gn:feature_code":"PPL",
    "gn:name":"Duda\u015f",
    "gn:population":0,
    "gn:timezone":"Europe/Istanbul",
    "iso:country":"TR",
    "name:und_x_variant":[
        "Dude\u015f",
        "Duda\u015f"
    ],
    "wof:name":"Dudas",
    "wof:placetype":"locality"
},
  "geometry": {"coordinates":[29.62914,39.38785],"type":"Point"}
}