{
  "type": "Feature",
  "properties": {
    "gn:admin1_code":"09",
    "gn:asciiname":"Cobanisa",
    "gn:country_code":"TR",
    "gn:dem":282,
    "gn:feature_class":"P",
    "gn:feature_code":"PPL",
    "gn:name":"\u00c7obanisa",
    "gn:population":0,
    "gn:timezone":"Europe/Istanbul",
    "iso:country":"TR",
    "name:tur_x_preferred":[
        "\u00c7obanisa"
    ],
    "wof:name":"Cobanisa",
    "wof:placetype":"locality"
},
  "geometry": {"coordinates":[28.49014,37.93232],"type":"Point"}
}