{
  "type": "Feature",
  "properties": {
    "gn:admin1_code":"72.0",
    "gn:asciiname":"Kurtulus",
    "gn:country_code":"TR",
    "gn:dem":479,
    "gn:feature_class":"P",
    "gn:feature_code":"PPL",
    "gn:name":"Kurtulus",
    "gn:population":0,
    "gn:timezone":"Europe/Istanbul",
    "iso:country":"TR",
    "name:tur_x_preferred":[
        "Kurtulus"
    ],
    "wof:name":"Kurtulus",
    "wof:placetype":"locality"
},
  "geometry": {"coordinates":[40.57404,37.17302],"type":"Point"}
}