{
  "type": "Feature",
  "properties": {
    "gn:admin1_code":"80.0",
    "gn:asciiname":"Zivi",
    "gn:country_code":"TR",
    "gn:dem":715,
    "gn:feature_class":"P",
    "gn:feature_code":"PPL",
    "gn:name":"Zivi",
    "gn:population":0,
    "gn:timezone":"Europe/Istanbul",
    "iso:country":"TR",
    "wof:name":"Zivi",
    "wof:placetype":"locality"
},
  "geometry": {"coordinates":[42.20694,37.44917],"type":"Point"}
}