{
  "type": "Feature",
  "properties": {
    "gn:admin1_code":"68",
    "gn:asciiname":"Ballikpinar",
    "gn:country_code":"TR",
    "gn:dem":1049,
    "gn:feature_class":"P",
    "gn:feature_code":"PPL",
    "gn:name":"Ball\u0131kp\u0131nar",
    "gn:population":0,
    "gn:timezone":"Europe/Istanbul",
    "iso:country":"TR",
    "name:und_x_variant":[
        "Bal\u0131kp\u0131nar",
        "Ball\u0131kp\u0131nar"
    ],
    "wof:name":"Ballikpinar",
    "wof:placetype":"locality"
},
  "geometry": {"coordinates":[32.71479,39.7344],"type":"Point"}
}