{
  "type": "Feature",
  "properties": {
    "gn:admin1_code":"11.0",
    "gn:asciiname":"Erkoca",
    "gn:country_code":"TR",
    "gn:dem":499,
    "gn:feature_class":"P",
    "gn:feature_code":"PPL",
    "gn:name":"Erkoca",
    "gn:population":0,
    "gn:timezone":"Europe/Istanbul",
    "iso:country":"TR",
    "name:msa_x_preferred":[
        "Erkoca"
    ],
    "name:tur_x_preferred":[
        "Erkoca"
    ],
    "name:und_x_variant":[
        "Arkoca",
        "Erkoca"
    ],
    "name:vie_x_preferred":[
        "Erkoca"
    ],
    "wof:name":"Erkoca",
    "wof:placetype":"locality"
},
  "geometry": {"coordinates":[29.80268,40.21692],"type":"Point"}
}