{
  "type": "Feature",
  "properties": {
    "gn:admin1_code":"26.0",
    "gn:asciiname":"Aksakli",
    "gn:country_code":"TR",
    "gn:dem":925,
    "gn:feature_class":"P",
    "gn:feature_code":"PPL",
    "gn:name":"Aksakl\u0131",
    "gn:population":0,
    "gn:timezone":"Europe/Istanbul",
    "iso:country":"TR",
    "name:und_x_variant":[
        "Aksak\u0131l\u0131",
        "Aksakl\u0131"
    ],
    "wof:name":"Aksakli",
    "wof:placetype":"locality"
},
  "geometry": {"coordinates":[30.74697,39.6118],"type":"Point"}
}