{
  "type": "Feature",
  "properties": {
    "gn:admin1_code":"55.0",
    "gn:asciiname":"Sakarinek",
    "gn:country_code":"TR",
    "gn:dem":1020,
    "gn:feature_class":"P",
    "gn:feature_code":"PPL",
    "gn:name":"Sakarinek",
    "gn:population":0,
    "gn:timezone":"Europe/Istanbul",
    "iso:country":"TR",
    "name:und_x_variant":[
        "Gog\u00f6z"
    ],
    "wof:name":"Sakarinek",
    "wof:placetype":"locality"
},
  "geometry": {"coordinates":[35.47126,41.47221],"type":"Point"}
}