{
  "type": "Feature",
  "properties": {
    "gn:admin1_code":"61.0",
    "gn:asciiname":"Agrit",
    "gn:country_code":"TR",
    "gn:dem":442,
    "gn:feature_class":"P",
    "gn:feature_code":"PPL",
    "gn:name":"A\u011fr\u0131t",
    "gn:population":0,
    "gn:timezone":"Europe/Istanbul",
    "iso:country":"TR",
    "name:und_x_variant":[
        "A\u011fr\u0131t"
    ],
    "wof:name":"Agrit",
    "wof:placetype":"locality"
},
  "geometry": {"coordinates":[39.64856,40.93405],"type":"Point"}
}