{
  "type": "Feature",
  "properties": {
    "gn:admin1_code":"14.0",
    "gn:asciiname":"Ceylanli",
    "gn:country_code":"TR",
    "gn:dem":916,
    "gn:feature_class":"P",
    "gn:feature_code":"PPL",
    "gn:name":"Ceylanl\u0131",
    "gn:population":0,
    "gn:timezone":"Europe/Istanbul",
    "iso:country":"TR",
    "name:und_x_variant":[
        "Dana",
        "Tana",
        "Danak\u00f6y",
        "Ceylanl\u0131"
    ],
    "wof:name":"Ceylanli",
    "wof:placetype":"locality"
},
  "geometry": {"coordinates":[31.03459,40.22904000000001],"type":"Point"}
}