{
  "type": "Feature",
  "properties": {
    "gn:admin1_code":"33",
    "gn:asciiname":"Gulsular",
    "gn:country_code":"TR",
    "gn:dem":1054,
    "gn:feature_class":"P",
    "gn:feature_code":"PPL",
    "gn:name":"G\u00fclsular",
    "gn:population":0,
    "gn:timezone":"Europe/Istanbul",
    "iso:country":"TR",
    "wof:name":"Gulsular",
    "wof:placetype":"locality"
},
  "geometry": {"coordinates":[31.31359,37.53406],"type":"Point"}
}