{
  "type": "Feature",
  "properties": {
    "gn:admin1_code":"71",
    "gn:asciiname":"Suberde",
    "gn:country_code":"TR",
    "gn:dem":1100,
    "gn:feature_class":"P",
    "gn:feature_code":"PPL",
    "gn:name":"Suberde",
    "gn:population":0,
    "gn:timezone":"Europe/Istanbul",
    "iso:country":"TR",
    "name:und_x_variant":[
        "G\u00f6ly\u00fcz\u00fc",
        "Suberde"
    ],
    "wof:name":"Suberde",
    "wof:placetype":"locality"
},
  "geometry": {"coordinates":[31.92696,37.35156],"type":"Point"}
}