{
  "type": "Feature",
  "properties": {
    "gn:country":"TR",
    "gn:fcode":"PPL",
    "gn:population":149,
    "iso:country":"TR",
    "name:cat_x_preferred":[
        "E\u011flence"
    ],
    "name:ceb_x_preferred":[
        "E\u011flence"
    ],
    "name:ces_x_preferred":[
        "E\u011flence"
    ],
    "name:dan_x_preferred":[
        "E\u011flence"
    ],
    "name:deu_x_preferred":[
        "E\u011flence"
    ],
    "name:eng_x_preferred":[
        "E\u011flence"
    ],
    "name:eus_x_preferred":[
        "E\u011flence"
    ],
    "name:fin_x_preferred":[
        "E\u011flence"
    ],
    "name:glg_x_preferred":[
        "E\u011flence"
    ],
    "name:ita_x_preferred":[
        "E\u011flence"
    ],
    "name:kur_x_preferred":[
        "Z\u00eenol"
    ],
    "name:nld_x_preferred":[
        "E\u011flence"
    ],
    "name:nno_x_preferred":[
        "E\u011flence"
    ],
    "name:nob_x_preferred":[
        "E\u011flence"
    ],
    "name:oci_x_preferred":[
        "E\u011flence"
    ],
    "name:pol_x_preferred":[
        "E\u011flence"
    ],
    "name:por_x_preferred":[
        "E\u011flence"
    ],
    "name:ron_x_preferred":[
        "E\u011flence"
    ],
    "name:sco_x_preferred":[
        "E\u011flence"
    ],
    "name:slk_x_preferred":[
        "E\u011flence"
    ],
    "name:slv_x_preferred":[
        "E\u011flence"
    ],
    "name:spa_x_preferred":[
        "E\u011flence"
    ],
    "name:swe_x_preferred":[
        "E\u011flence"
    ],
    "name:tgl_x_preferred":[
        "E\u011flence"
    ],
    "name:tur_x_preferred":[
        "E\u011flence"
    ],
    "name:und_x_variant":[
        "Zinol"
    ],
    "name:vie_x_preferred":[
        "E\u011flence"
    ],
    "name:war_x_preferred":[
        "E\u011flence"
    ],
    "name:yid_x_preferred":[
        "Canakluk"
    ],
    "qs:name":"E\u011flence",
    "qs:photos_9r":0,
    "qs:photos_sr":0,
    "qs:pop_sr":"1",
    "wof:name":"E\u011flence",
    "wof:placetype":"locality",
    "wof:population":149
},
  "geometry": {"coordinates":[41.51154,37.3496],"type":"Point"}
}