{
  "type": "Feature",
  "properties": {
    "gn:admin1_code":"54",
    "gn:asciiname":"Cukurhan",
    "gn:country_code":"TR",
    "gn:dem":277,
    "gn:feature_class":"P",
    "gn:feature_code":"PPL",
    "gn:name":"\u00c7ukurhan",
    "gn:population":0,
    "gn:timezone":"Europe/Istanbul",
    "iso:country":"TR",
    "name:tur_x_preferred":[
        "\u00c7ukurhan"
    ],
    "wof:name":"Cukurhan",
    "wof:placetype":"locality"
},
  "geometry": {"coordinates":[30.88082,40.8302],"type":"Point"}
}