{
  "type": "Feature",
  "properties": {
    "gn:admin1_code":"21.0",
    "gn:asciiname":"Serapguzeli",
    "gn:country_code":"TR",
    "gn:dem":747,
    "gn:feature_class":"P",
    "gn:feature_code":"PPL",
    "gn:name":"\u015eerapg\u00fczeli",
    "gn:population":0,
    "gn:timezone":"Europe/Istanbul",
    "iso:country":"TR",
    "wof:name":"Serapguzeli",
    "wof:placetype":"locality"
},
  "geometry": {"coordinates":[40.0879,37.90799000000001],"type":"Point"}
}