{
  "type": "Feature",
  "properties": {
    "gn:admin1_code":"23",
    "gn:asciiname":"Karacali",
    "gn:cc2":"TR",
    "gn:country_code":"TR",
    "gn:dem":1555,
    "gn:feature_class":"P",
    "gn:feature_code":"PPL",
    "gn:name":"Kara\u00e7al\u0131",
    "gn:population":0,
    "gn:timezone":"Europe/Istanbul",
    "iso:country":"TR",
    "name:und_x_variant":[
        "Kara\u00e7\u0131l\u0131",
        "Kara\u00e7al\u0131"
    ],
    "wof:name":"Karacali",
    "wof:placetype":"locality"
},
  "geometry": {"coordinates":[39.33333,38.43333],"type":"Point"}
}