{
  "type": "Feature",
  "properties": {
    "gn:admin1_code":"13",
    "gn:asciiname":"Oluklu",
    "gn:country_code":"TR",
    "gn:dem":1407,
    "gn:feature_class":"P",
    "gn:feature_code":"PPL",
    "gn:name":"Oluklu",
    "gn:population":0,
    "gn:timezone":"Europe/Istanbul",
    "iso:country":"TR",
    "name:nld_x_preferred":[
        "Oluklu"
    ],
    "name:tur_x_preferred":[
        "Oluklu"
    ],
    "name:und_x_variant":[
        "Tolisor",
        "Talisor"
    ],
    "wof:name":"Oluklu",
    "wof:placetype":"locality"
},
  "geometry": {"coordinates":[41.67938,38.5272],"type":"Point"}
}