{
  "type": "Feature",
  "properties": {
    "gn:admin1_code":"4.0",
    "gn:asciiname":"Boztoprak",
    "gn:country_code":"TR",
    "gn:dem":1841,
    "gn:feature_class":"P",
    "gn:feature_code":"PPL",
    "gn:name":"Boztoprak",
    "gn:population":0,
    "gn:timezone":"Europe/Istanbul",
    "iso:country":"TR",
    "name:tur_x_preferred":[
        "Baztoprak"
    ],
    "name:tur_x_variant":[
        "Boztoprak"
    ],
    "wof:name":"Boztoprak",
    "wof:placetype":"locality"
},
  "geometry": {"coordinates":[43.21201,39.61289],"type":"Point"}
}