{
  "type": "Feature",
  "properties": {
    "gn:admin1_code":"17",
    "gn:asciiname":"Bademli",
    "gn:country_code":"TR",
    "gn:dem":304,
    "gn:feature_class":"P",
    "gn:feature_code":"PPL",
    "gn:name":"Bademli",
    "gn:population":0,
    "gn:timezone":"Europe/Istanbul",
    "iso:country":"TR",
    "name:ceb_x_preferred":[
        "Bademli"
    ],
    "name:tur_x_preferred":[
        "Bademli"
    ],
    "wof:name":"Bademli",
    "wof:placetype":"locality"
},
  "geometry": {"coordinates":[26.16855,39.49606],"type":"Point"}
}