{
  "type": "Feature",
  "properties": {
    "gn:admin1_code":"62",
    "gn:asciiname":"Vartinik",
    "gn:country_code":"TR",
    "gn:dem":1954,
    "gn:feature_class":"P",
    "gn:feature_code":"PPL",
    "gn:name":"Vartinik",
    "gn:population":0,
    "gn:timezone":"Europe/Istanbul",
    "iso:country":"TR",
    "wof:name":"Vartinik",
    "wof:placetype":"locality"
},
  "geometry": {"coordinates":[39.65,39.26667],"type":"Point"}
}