{
  "type": "Feature",
  "properties": {
    "gn:admin1_code":"21",
    "gn:asciiname":"Tavsantepe",
    "gn:country_code":"TR",
    "gn:dem":1130,
    "gn:feature_class":"P",
    "gn:feature_code":"PPL",
    "gn:name":"Tav\u015fantepe",
    "gn:population":0,
    "gn:timezone":"Europe/Istanbul",
    "iso:country":"TR",
    "name:tur_x_preferred":[
        "Tav\u015fantepe"
    ],
    "wof:name":"Tavsantepe",
    "wof:placetype":"locality"
},
  "geometry": {"coordinates":[40.81789000000001,38.22995],"type":"Point"}
}