{
  "type": "Feature",
  "properties": {
    "gn:admin1_code":"19.0",
    "gn:asciiname":"Sogutonu",
    "gn:country_code":"TR",
    "gn:dem":775,
    "gn:feature_class":"P",
    "gn:feature_code":"PPL",
    "gn:name":"S\u00f6\u011f\u00fct\u00f6n\u00fc",
    "gn:population":0,
    "gn:timezone":"Europe/Istanbul",
    "iso:country":"TR",
    "name:und_x_variant":[
        "B\u00fcnyan Osmani",
        "S\u00f6\u011f\u00fct\u00f6n\u00fc",
        "S\u00f6y\u00fct\u00f6n\u00fc"
    ],
    "wof:name":"Sogutonu",
    "wof:placetype":"locality"
},
  "geometry": {"coordinates":[35.34607000000001,40.40838],"type":"Point"}
}