{
  "type": "Feature",
  "properties": {
    "gn:admin1_code":"24",
    "gn:asciiname":"Alirik",
    "gn:cc2":"TR",
    "gn:country_code":"TR",
    "gn:dem":1703,
    "gn:feature_class":"P",
    "gn:feature_code":"PPL",
    "gn:name":"Alirik",
    "gn:population":0,
    "gn:timezone":"Europe/Istanbul",
    "iso:country":"TR",
    "name:und_x_variant":[
        "A\u011fvirik",
        "Alirik"
    ],
    "wof:name":"Alirik",
    "wof:placetype":"locality"
},
  "geometry": {"coordinates":[40.46667,39.65],"type":"Point"}
}