{
  "type": "Feature",
  "properties": {
    "gn:admin1_code":"84.0",
    "gn:asciiname":"Kuloglu",
    "gn:country_code":"TR",
    "gn:dem":1296,
    "gn:feature_class":"P",
    "gn:feature_code":"PPL",
    "gn:name":"Kulo\u011flu",
    "gn:population":0,
    "gn:timezone":"Europe/Istanbul",
    "iso:country":"TR",
    "name:tur_x_preferred":[
        "Kulo\u011flu"
    ],
    "wof:name":"Kuloglu",
    "wof:placetype":"locality"
},
  "geometry": {"coordinates":[42.95406,40.09315],"type":"Point"}
}