{
  "type": "Feature",
  "properties": {
    "gn:admin1_code":"37.0",
    "gn:asciiname":"Yukaricakircay",
    "gn:country_code":"TR",
    "gn:dem":645,
    "gn:feature_class":"P",
    "gn:feature_code":"PPL",
    "gn:name":"Yukar\u0131\u00e7ak\u0131r\u00e7ay",
    "gn:population":0,
    "gn:timezone":"Europe/Istanbul",
    "iso:country":"TR",
    "name:und_x_variant":[
        "Yukar\u0131\u00e7ak\u0131r\u00e7ay",
        "Yenik\u00f6y"
    ],
    "wof:name":"Yukaricakircay",
    "wof:placetype":"locality"
},
  "geometry": {"coordinates":[34.59211,41.65225],"type":"Point"}
}