{
  "type": "Feature",
  "properties": {
    "gn:admin1_code":"14",
    "gn:asciiname":"Seferler",
    "gn:country_code":"TR",
    "gn:dem":1220,
    "gn:feature_class":"P",
    "gn:feature_code":"PPL",
    "gn:name":"Seferler",
    "gn:population":0,
    "gn:timezone":"Europe/Istanbul",
    "iso:country":"TR",
    "wof:name":"Seferler",
    "wof:placetype":"locality"
},
  "geometry": {"coordinates":[30.92971,40.37692],"type":"Point"}
}