{
  "type": "Feature",
  "properties": {
    "gn:admin1_code":"53.0",
    "gn:asciiname":"Islahiye",
    "gn:country_code":"TR",
    "gn:dem":378,
    "gn:feature_class":"P",
    "gn:feature_code":"PPL",
    "gn:name":"\u0130sl\u00e2hiye",
    "gn:population":0,
    "gn:timezone":"Europe/Istanbul",
    "iso:country":"TR",
    "wof:name":"Islahiye",
    "wof:placetype":"locality"
},
  "geometry": {"coordinates":[40.67761,40.96328],"type":"Point"}
}