{
  "type": "Feature",
  "properties": {
    "gn:admin1_code":"37.0",
    "gn:asciiname":"Gurpelit",
    "gn:country_code":"TR",
    "gn:dem":540,
    "gn:feature_class":"P",
    "gn:feature_code":"PPL",
    "gn:name":"G\u00fcrpelit",
    "gn:population":0,
    "gn:timezone":"Europe/Istanbul",
    "iso:country":"TR",
    "name:und_x_variant":[
        "G\u00fcrpelit",
        "Kayrak"
    ],
    "wof:name":"Gurpelit",
    "wof:placetype":"locality"
},
  "geometry": {"coordinates":[33.17213,41.77222],"type":"Point"}
}