{
  "type": "Feature",
  "properties": {
    "gn:admin1_code":"32",
    "gn:asciiname":"Karakaya",
    "gn:country_code":"TR",
    "gn:dem":230,
    "gn:feature_class":"P",
    "gn:feature_code":"PPL",
    "gn:name":"Karakaya",
    "gn:population":0,
    "gn:timezone":"Europe/Istanbul",
    "iso:country":"TR",
    "name:ceb_x_preferred":[
        "Karakaya"
    ],
    "name:deu_x_preferred":[
        "Karakaya"
    ],
    "name:swe_x_preferred":[
        "Karakaya"
    ],
    "name:tur_x_preferred":[
        "Karakaya"
    ],
    "wof:name":"Karakaya",
    "wof:placetype":"locality"
},
  "geometry": {"coordinates":[33.77376,36.42454],"type":"Point"}
}