{
  "type": "Feature",
  "properties": {
    "gn:admin1_code":"52.0",
    "gn:asciiname":"Besbiyik",
    "gn:country_code":"TR",
    "gn:dem":1379,
    "gn:feature_class":"P",
    "gn:feature_code":"PPL",
    "gn:name":"Be\u015fb\u0131y\u0131k",
    "gn:population":0,
    "gn:timezone":"Europe/Istanbul",
    "iso:country":"TR",
    "name:tur_x_preferred":[
        "Be\u015fb\u0131y\u0131k"
    ],
    "wof:name":"Besbiyik",
    "wof:placetype":"locality"
},
  "geometry": {"coordinates":[37.86019,40.46379],"type":"Point"}
}