{
  "type": "Feature",
  "properties": {
    "gn:admin1_code":"37.0",
    "gn:asciiname":"Ogulkoy",
    "gn:country_code":"TR",
    "gn:dem":704,
    "gn:feature_class":"P",
    "gn:feature_code":"PPL",
    "gn:name":"O\u011fulk\u00f6y",
    "gn:population":0,
    "gn:timezone":"Europe/Istanbul",
    "iso:country":"TR",
    "name:und_x_variant":[
        "O\u011ful",
        "O\u011fulk\u00f6y"
    ],
    "wof:name":"Ogulkoy",
    "wof:placetype":"locality"
},
  "geometry": {"coordinates":[33.90578,41.46781],"type":"Point"}
}