{
  "type": "Feature",
  "properties": {
    "gn:admin1_code":"52.0",
    "gn:asciiname":"Mesebuku",
    "gn:country_code":"TR",
    "gn:dem":222,
    "gn:feature_class":"P",
    "gn:feature_code":"PPL",
    "gn:name":"Me\u015feb\u00fck\u00fc",
    "gn:population":0,
    "gn:timezone":"Europe/Istanbul",
    "iso:country":"TR",
    "wof:name":"Mesebuku",
    "wof:placetype":"locality"
},
  "geometry": {"coordinates":[37.48514,40.99564],"type":"Point"}
}