{
  "type": "Feature",
  "properties": {
    "gn:admin1_code":"07",
    "gn:asciiname":"Balkaya",
    "gn:country_code":"TR",
    "gn:dem":1078,
    "gn:feature_class":"P",
    "gn:feature_code":"PPL",
    "gn:name":"Balkaya",
    "gn:population":0,
    "gn:timezone":"Europe/Istanbul",
    "iso:country":"TR",
    "name:tur_x_preferred":[
        "Balkaya"
    ],
    "name:und_x_variant":[
        "Semetk\u00f6y",
        "Semet"
    ],
    "wof:name":"Balkaya",
    "wof:placetype":"locality"
},
  "geometry": {"coordinates":[32.0872,36.75321],"type":"Point"}
}