{
  "type": "Feature",
  "properties": {
    "gn:admin1_code":"28.0",
    "gn:asciiname":"Kuluncak",
    "gn:country_code":"TR",
    "gn:dem":644,
    "gn:feature_class":"P",
    "gn:feature_code":"PPL",
    "gn:name":"Kuluncak",
    "gn:population":0,
    "gn:timezone":"Europe/Istanbul",
    "iso:country":"TR",
    "name:ceb_x_preferred":[
        "Kuluncak"
    ],
    "name:deu_x_preferred":[
        "Kuluncak"
    ],
    "name:fra_x_preferred":[
        "Kuluncak"
    ],
    "name:hye_x_preferred":[
        "\u0531\u0575\u057e\u0561\u056c\u056b"
    ],
    "name:kur_x_preferred":[
        "Aywal\u00ee"
    ],
    "name:mrj_x_preferred":[
        "\u041a\u0443\u043b\u0443\u043d\u0434\u0436\u0430\u043a"
    ],
    "name:msa_x_preferred":[
        "Kuluncak"
    ],
    "name:nld_x_preferred":[
        "Kuluncak"
    ],
    "name:nor_x_preferred":[
        "Kuluncak"
    ],
    "name:pnb_x_preferred":[
        "\u0636\u0644\u0639 \u06a9\u0648\u0644\u0646\u062c\u06a9"
    ],
    "name:rus_x_preferred":[
        "\u041a\u0443\u043b\u0443\u043d\u0434\u0436\u0430\u043a"
    ],
    "name:swa_x_preferred":[
        "Kuluncak"
    ],
    "name:tur_x_preferred":[
        "Kuluncak"
    ],
    "name:und_x_variant":[
        "Kulancak"
    ],
    "name:urd_x_preferred":[
        "\u06a9\u0648\u0644\u0648\u0646\u062c\u0627\u06a9"
    ],
    "name:vie_x_preferred":[
        "Kuluncak"
    ],
    "wof:name":"Kuluncak",
    "wof:placetype":"locality"
},
  "geometry": {"coordinates":[38.7952,40.84498],"type":"Point"}
}