{
  "type": "Feature",
  "properties": {
    "gn:admin1_code":"28.0",
    "gn:asciiname":"Kuluncak",
    "gn:country_code":"TR",
    "gn:dem":644,
    "gn:feature_class":"P",
    "gn:feature_code":"PPL",
    "gn:name":"Kuluncak",
    "gn:population":0,
    "gn:timezone":"Europe/Istanbul",
    "iso:country":"TR",
    "name:tur_x_preferred":[
        "Kuluncak"
    ],
    "name:und_x_variant":[
        "Kulancak"
    ],
    "wof:name":"Kuluncak",
    "wof:placetype":"locality"
},
  "geometry": {"coordinates":[38.7952,40.84498],"type":"Point"}
}