{
  "type": "Feature",
  "properties": {
    "gn:admin1_code":"33",
    "gn:asciiname":"Zamkadin",
    "gn:country_code":"TR",
    "gn:dem":1445,
    "gn:feature_class":"P",
    "gn:feature_code":"PPL",
    "gn:name":"Zamkad\u0131n",
    "gn:population":0,
    "gn:timezone":"Europe/Istanbul",
    "iso:country":"TR",
    "wof:name":"Zamkadin",
    "wof:placetype":"locality"
},
  "geometry": {"coordinates":[30.91701,37.66644],"type":"Point"}
}