{
  "type": "Feature",
  "properties": {
    "gn:admin1_code":"72.0",
    "gn:asciiname":"Demirkapi",
    "gn:country_code":"TR",
    "gn:dem":429,
    "gn:feature_class":"P",
    "gn:feature_code":"PPL",
    "gn:name":"Demirkap\u0131",
    "gn:population":0,
    "gn:timezone":"Europe/Istanbul",
    "iso:country":"TR",
    "name:tur_x_preferred":[
        "Demirkap\u0131"
    ],
    "wof:name":"Demirkapi",
    "wof:placetype":"locality"
},
  "geometry": {"coordinates":[40.46372,37.05291],"type":"Point"}
}