{
  "type": "Feature",
  "properties": {
    "gn:admin1_code":"10",
    "gn:asciiname":"Hacioglu",
    "gn:country_code":"TR",
    "gn:dem":190,
    "gn:feature_class":"P",
    "gn:feature_code":"PPL",
    "gn:name":"Hac\u0131o\u011flu",
    "gn:population":0,
    "gn:timezone":"Europe/Istanbul",
    "iso:country":"TR",
    "name:und_x_variant":[
        "Hac\u0131o\u011flu Obas\u0131",
        "Hac\u0131o\u011flu"
    ],
    "wof:name":"Hacioglu",
    "wof:placetype":"locality"
},
  "geometry": {"coordinates":[26.91629,39.38021],"type":"Point"}
}