{
  "type": "Feature",
  "properties": {
    "gn:admin1_code":"21",
    "gn:asciiname":"Mutluca",
    "gn:country_code":"TR",
    "gn:dem":1036,
    "gn:feature_class":"P",
    "gn:feature_code":"PPL",
    "gn:name":"Mutluca",
    "gn:population":0,
    "gn:timezone":"Europe/Istanbul",
    "iso:country":"TR",
    "name:tur_x_preferred":[
        "Mutluca"
    ],
    "name:und_x_variant":[
        "Berbu\u015f",
        "Barbu\u015f"
    ],
    "wof:name":"Mutluca",
    "wof:placetype":"locality"
},
  "geometry": {"coordinates":[40.90063,38.27663],"type":"Point"}
}