{
  "type": "Feature",
  "properties": {
    "gn:admin1_code":"53.0",
    "gn:asciiname":"Esendere",
    "gn:country_code":"TR",
    "gn:dem":450,
    "gn:feature_class":"P",
    "gn:feature_code":"PPL",
    "gn:name":"Esendere",
    "gn:population":0,
    "gn:timezone":"Europe/Istanbul",
    "iso:country":"TR",
    "name:tur_x_preferred":[
        "Esendere"
    ],
    "wof:name":"Esendere",
    "wof:placetype":"locality"
},
  "geometry": {"coordinates":[40.51149,40.87586],"type":"Point"}
}