{
  "type": "Feature",
  "properties": {
    "gn:admin1_code":"22.0",
    "gn:asciiname":"Buyukdoganca",
    "gn:country_code":"TR",
    "gn:dem":27,
    "gn:feature_class":"P",
    "gn:feature_code":"PPL",
    "gn:name":"B\u00fcy\u00fckdo\u011fanca",
    "gn:population":0,
    "gn:timezone":"Europe/Istanbul",
    "iso:country":"TR",
    "wof:name":"Buyukdoganca",
    "wof:placetype":"locality"
},
  "geometry": {"coordinates":[26.58398,40.77106],"type":"Point"}
}