{
  "type": "Feature",
  "properties": {
    "gn:admin1_code":"21",
    "gn:asciiname":"Omeran",
    "gn:cc2":"TR",
    "gn:country_code":"TR",
    "gn:dem":656,
    "gn:feature_class":"P",
    "gn:feature_code":"PPL",
    "gn:name":"\u00d6meran",
    "gn:population":0,
    "gn:timezone":"Europe/Istanbul",
    "iso:country":"TR",
    "name:und_x_variant":[
        "\u00d6merhan",
        "\u00d6mera\u011fa",
        "\u00d6meran"
    ],
    "wof:name":"Omeran",
    "wof:placetype":"locality"
},
  "geometry": {"coordinates":[40.76667,38.03333],"type":"Point"}
}