{
  "type": "Feature",
  "properties": {
    "gn:admin1_code":"69.0",
    "gn:asciiname":"Akinci",
    "gn:country_code":"TR",
    "gn:dem":1811,
    "gn:feature_class":"P",
    "gn:feature_code":"PPL",
    "gn:name":"Ak\u0131nc\u0131",
    "gn:population":0,
    "gn:timezone":"Europe/Istanbul",
    "iso:country":"TR",
    "wof:name":"Akinci",
    "wof:placetype":"locality"
},
  "geometry": {"coordinates":[39.36667,40.65],"type":"Point"}
}