{
  "type": "Feature",
  "properties": {
    "gn:admin1_code":"45",
    "gn:asciiname":"Vakifli",
    "gn:country_code":"TR",
    "gn:dem":362,
    "gn:feature_class":"P",
    "gn:feature_code":"PPL",
    "gn:name":"Vak\u0131fl\u0131",
    "gn:population":0,
    "gn:timezone":"Europe/Istanbul",
    "iso:country":"TR",
    "name:tur_x_preferred":[
        "Vak\u0131fl\u0131"
    ],
    "wof:name":"Vakifli",
    "wof:placetype":"locality"
},
  "geometry": {"coordinates":[27.51721,39.31629],"type":"Point"}
}