{
  "type": "Feature",
  "properties": {
    "gn:admin1_code":"91",
    "gn:asciiname":"Nohutkoy",
    "gn:country_code":"TR",
    "gn:dem":669,
    "gn:feature_class":"P",
    "gn:feature_code":"PPL",
    "gn:name":"Nohutk\u00f6y",
    "gn:population":0,
    "gn:timezone":"Europe/Istanbul",
    "iso:country":"TR",
    "name:tur_x_preferred":[
        "Nohutk\u00f6y"
    ],
    "name:und_x_variant":[
        "Nohut K\u00f6y\u00fc",
        "Nohut"
    ],
    "wof:name":"Nohutkoy",
    "wof:placetype":"locality"
},
  "geometry": {"coordinates":[36.53028,37.19324],"type":"Point"}
}