{
  "type": "Feature",
  "properties": {
    "gn:admin1_code":"93",
    "gn:asciiname":"Turnacilar",
    "gn:country_code":"TR",
    "gn:dem":281,
    "gn:feature_class":"P",
    "gn:feature_code":"PPL",
    "gn:name":"Turnac\u0131lar",
    "gn:population":0,
    "gn:timezone":"Europe/Istanbul",
    "iso:country":"TR",
    "wof:name":"Turnacilar",
    "wof:placetype":"locality"
},
  "geometry": {"coordinates":[31.29086,40.93227],"type":"Point"}
}