{
  "type": "Feature",
  "properties": {
    "gn:admin1_code":"71",
    "gn:asciiname":"Kabacali",
    "gn:country_code":"TR",
    "gn:dem":1027,
    "gn:feature_class":"P",
    "gn:feature_code":"PPL",
    "gn:name":"Kabacal\u0131",
    "gn:population":0,
    "gn:timezone":"Europe/Istanbul",
    "iso:country":"TR",
    "wof:name":"Kabacali",
    "wof:placetype":"locality"
},
  "geometry": {"coordinates":[32.26528,38.32],"type":"Point"}
}