{
  "type": "Feature",
  "properties": {
    "gn:admin1_code":"54.0",
    "gn:asciiname":"Dogancay",
    "gn:country_code":"TR",
    "gn:dem":64,
    "gn:feature_class":"P",
    "gn:feature_code":"PPLA3",
    "gn:name":"Do\u011fan\u00e7ay",
    "gn:population":0,
    "gn:timezone":"Europe/Istanbul",
    "iso:country":"TR",
    "name:tur_x_preferred":[
        "Do\u011fan\u00e7ay"
    ],
    "wof:name":"Dogancay",
    "wof:placetype":"locality"
},
  "geometry": {"coordinates":[30.33557,40.62647],"type":"Point"}
}