{
  "type": "Feature",
  "properties": {
    "gn:admin1_code":"68.0",
    "gn:asciiname":"Kilcak",
    "gn:country_code":"TR",
    "gn:dem":949,
    "gn:feature_class":"P",
    "gn:feature_code":"PPL",
    "gn:name":"K\u0131l\u00e7ak",
    "gn:population":0,
    "gn:timezone":"Europe/Istanbul",
    "iso:country":"TR",
    "wof:name":"Kilcak",
    "wof:placetype":"locality"
},
  "geometry": {"coordinates":[33.41383,40.21583],"type":"Point"}
}