{
  "type": "Feature",
  "properties": {
    "gn:admin1_code":"21.0",
    "gn:asciiname":"Donacik",
    "gn:country_code":"TR",
    "gn:dem":886,
    "gn:feature_class":"P",
    "gn:feature_code":"PPL",
    "gn:name":"Donac\u0131k",
    "gn:population":0,
    "gn:timezone":"Europe/Istanbul",
    "iso:country":"TR",
    "wof:name":"Donacik",
    "wof:placetype":"locality"
},
  "geometry": {"coordinates":[41.07281,38.46593],"type":"Point"}
}