{
  "type": "Feature",
  "properties": {
    "gn:admin1_code":"90",
    "gn:asciiname":"Taslibakar",
    "gn:cc2":"TR",
    "gn:country_code":"TR",
    "gn:dem":522,
    "gn:feature_class":"P",
    "gn:feature_code":"PPL",
    "gn:name":"Ta\u015fl\u0131bakar",
    "gn:population":0,
    "gn:timezone":"Europe/Istanbul",
    "iso:country":"TR",
    "name:und_x_variant":[
        "Okk\u0131ran",
        "Ta\u015fl\u0131bakar"
    ],
    "wof:name":"Taslibakar",
    "wof:placetype":"locality"
},
  "geometry": {"coordinates":[37.40278,36.69472],"type":"Point"}
}