{
  "type": "Feature",
  "properties": {
    "gn:admin1_code":"14.0",
    "gn:asciiname":"Mircekiraz",
    "gn:country_code":"TR",
    "gn:dem":1174,
    "gn:feature_class":"P",
    "gn:feature_code":"PPL",
    "gn:name":"Mircekiraz",
    "gn:population":0,
    "gn:timezone":"Europe/Istanbul",
    "iso:country":"TR",
    "wof:name":"Mircekiraz",
    "wof:placetype":"locality"
},
  "geometry": {"coordinates":[32.2415,40.70641],"type":"Point"}
}