{
  "type": "Feature",
  "properties": {
    "gn:admin1_code":"20",
    "gn:asciiname":"Yenikoy",
    "gn:country_code":"TR",
    "gn:dem":240,
    "gn:feature_class":"P",
    "gn:feature_code":"PPL",
    "gn:name":"Yenik\u00f6y",
    "gn:population":0,
    "gn:timezone":"Europe/Istanbul",
    "iso:country":"TR",
    "name:tur_x_preferred":[
        "Yenik\u00f6y"
    ],
    "wof:name":"Yenikoy",
    "wof:placetype":"locality"
},
  "geometry": {"coordinates":[29.13857,37.89937000000001],"type":"Point"}
}