{
  "type": "Feature",
  "properties": {
    "gn:admin1_code":"37.0",
    "gn:asciiname":"Omerli",
    "gn:country_code":"TR",
    "gn:dem":1109,
    "gn:feature_class":"P",
    "gn:feature_code":"PPL",
    "gn:name":"\u00d6merli",
    "gn:population":0,
    "gn:timezone":"Europe/Istanbul",
    "iso:country":"TR",
    "name:und_x_variant":[
        "Omarl\u0131",
        "\u00d6merli"
    ],
    "wof:name":"Omerli",
    "wof:placetype":"locality"
},
  "geometry": {"coordinates":[34.22295,41.36902],"type":"Point"}
}