{
  "type": "Feature",
  "properties": {
    "gn:admin1_code":"33.0",
    "gn:asciiname":"Afsar",
    "gn:country_code":"TR",
    "gn:dem":940,
    "gn:feature_class":"P",
    "gn:feature_code":"PPL",
    "gn:name":"Af\u015far",
    "gn:population":0,
    "gn:timezone":"Europe/Istanbul",
    "iso:country":"TR",
    "wof:name":"Afsar",
    "wof:placetype":"locality"
},
  "geometry": {"coordinates":[30.97778,38.13639000000001],"type":"Point"}
}