{
  "type": "Feature",
  "properties": {
    "gn:admin1_code":"72.0",
    "gn:asciiname":"Herdek",
    "gn:cc2":"TR",
    "gn:country_code":"TR",
    "gn:dem":485,
    "gn:feature_class":"P",
    "gn:feature_code":"PPL",
    "gn:name":"Herdek",
    "gn:population":0,
    "gn:timezone":"Europe/Istanbul",
    "iso:country":"TR",
    "name:und_x_variant":[
        "Kherdek",
        "Herdek"
    ],
    "wof:name":"Herdek",
    "wof:placetype":"locality"
},
  "geometry": {"coordinates":[41.8275,37.62889000000001],"type":"Point"}
}