{
  "type": "Feature",
  "properties": {
    "gn:admin1_code":"19.0",
    "gn:asciiname":"Sarayli",
    "gn:country_code":"TR",
    "gn:dem":1136,
    "gn:feature_class":"P",
    "gn:feature_code":"PPL",
    "gn:name":"Sarayl\u0131",
    "gn:population":0,
    "gn:timezone":"Europe/Istanbul",
    "iso:country":"TR",
    "wof:name":"Sarayli",
    "wof:placetype":"locality"
},
  "geometry": {"coordinates":[34.79105999999999,40.56858],"type":"Point"}
}