{
  "type": "Feature",
  "properties": {
    "gn:admin1_code":"17",
    "gn:asciiname":"Cicikler",
    "gn:country_code":"TR",
    "gn:dem":271,
    "gn:feature_class":"P",
    "gn:feature_code":"PPL",
    "gn:name":"Cicikler",
    "gn:population":0,
    "gn:timezone":"Europe/Istanbul",
    "iso:country":"TR",
    "name:tur_x_preferred":[
        "Cicikler"
    ],
    "wof:name":"Cicikler",
    "wof:placetype":"locality"
},
  "geometry": {"coordinates":[26.91296,39.92248],"type":"Point"}
}