{
  "type": "Feature",
  "properties": {
    "gn:admin1_code":"61.0",
    "gn:asciiname":"Yesilalan",
    "gn:country_code":"TR",
    "gn:dem":914,
    "gn:feature_class":"P",
    "gn:feature_code":"PPL",
    "gn:name":"Ye\u015filalan",
    "gn:population":0,
    "gn:timezone":"Europe/Istanbul",
    "iso:country":"TR",
    "name:und_x_variant":[
        "Holay\u0131sa",
        "Holaysa",
        "Ye\u015filalan"
    ],
    "wof:name":"Yesilalan",
    "wof:placetype":"locality"
},
  "geometry": {"coordinates":[40.28082,40.74497],"type":"Point"}
}