{
  "type": "Feature",
  "properties": {
    "gn:admin1_code":"91",
    "gn:asciiname":"Kurtlar",
    "gn:country_code":"TR",
    "gn:dem":817,
    "gn:feature_class":"P",
    "gn:feature_code":"PPL",
    "gn:name":"Kurtlar",
    "gn:population":0,
    "gn:timezone":"Europe/Istanbul",
    "iso:country":"TR",
    "wof:name":"Kurtlar",
    "wof:placetype":"locality"
},
  "geometry": {"coordinates":[36.49233,37.26801],"type":"Point"}
}