{
  "type": "Feature",
  "properties": {
    "gn:admin1_code":"10",
    "gn:asciiname":"Camci",
    "gn:country_code":"TR",
    "gn:dem":105,
    "gn:feature_class":"P",
    "gn:feature_code":"PPL",
    "gn:name":"\u00c7amc\u0131",
    "gn:population":0,
    "gn:timezone":"Europe/Istanbul",
    "iso:country":"TR",
    "name:tur_x_preferred":[
        "\u00c7amc\u0131"
    ],
    "wof:name":"Camci",
    "wof:placetype":"locality"
},
  "geometry": {"coordinates":[27.05385,39.62148],"type":"Point"}
}