{
  "type": "Feature",
  "properties": {
    "gn:admin1_code":"76.0",
    "gn:asciiname":"Yukari Miririk",
    "gn:country_code":"TR",
    "gn:dem":698,
    "gn:feature_class":"P",
    "gn:feature_code":"PPL",
    "gn:name":"Yukar\u0131 Miririk",
    "gn:population":0,
    "gn:timezone":"Europe/Istanbul",
    "iso:country":"TR",
    "wof:name":"Yukari Miririk",
    "wof:placetype":"locality"
},
  "geometry": {"coordinates":[41.42463,38.08752],"type":"Point"}
}