{
  "type": "Feature",
  "properties": {
    "gn:admin1_code":"72.0",
    "gn:asciiname":"Dercomer",
    "gn:country_code":"TR",
    "gn:dem":874,
    "gn:feature_class":"P",
    "gn:feature_code":"PPL",
    "gn:name":"Dercomer",
    "gn:population":0,
    "gn:timezone":"Europe/Istanbul",
    "iso:country":"TR",
    "name:und_x_variant":[
        "Derdzhomer",
        "Dercomer"
    ],
    "wof:name":"Dercomer",
    "wof:placetype":"locality"
},
  "geometry": {"coordinates":[41.3215,37.13201],"type":"Point"}
}