{
  "type": "Feature",
  "properties": {
    "gn:admin1_code":"85",
    "gn:asciiname":"Bakircilar",
    "gn:country_code":"TR",
    "gn:dem":148,
    "gn:feature_class":"P",
    "gn:feature_code":"PPL",
    "gn:name":"Bak\u0131rc\u0131lar",
    "gn:population":0,
    "gn:timezone":"Europe/Istanbul",
    "iso:country":"TR",
    "wof:name":"Bakircilar",
    "wof:placetype":"locality"
},
  "geometry": {"coordinates":[31.98437,41.26608],"type":"Point"}
}