{
  "type": "Feature",
  "properties": {
    "gn:admin1_code":"16",
    "gn:asciiname":"Basak",
    "gn:country_code":"TR",
    "gn:dem":797,
    "gn:feature_class":"P",
    "gn:feature_code":"PPL",
    "gn:name":"Basak",
    "gn:population":0,
    "gn:timezone":"Europe/Istanbul",
    "iso:country":"TR",
    "name:ceb_x_preferred":[
        "Basak"
    ],
    "name:ita_x_preferred":[
        "Basak"
    ],
    "name:swe_x_preferred":[
        "Basak"
    ],
    "name:tur_x_preferred":[
        "Basak"
    ],
    "wof:name":"Basak",
    "wof:placetype":"locality"
},
  "geometry": {"coordinates":[29.24279000000001,39.78137],"type":"Point"}
}