{
  "type": "Feature",
  "properties": {
    "gn:admin1_code":"44",
    "gn:asciiname":"Sogut",
    "gn:country_code":"TR",
    "gn:dem":1473,
    "gn:feature_class":"P",
    "gn:feature_code":"PPL",
    "gn:name":"S\u00f6\u011f\u00fct",
    "gn:population":0,
    "gn:timezone":"Europe/Istanbul",
    "iso:country":"TR",
    "name:tur_x_preferred":[
        "S\u00f6\u011f\u00fct"
    ],
    "wof:name":"Sogut",
    "wof:placetype":"locality"
},
  "geometry": {"coordinates":[37.76683,38.06281],"type":"Point"}
}