{
  "type": "Feature",
  "properties": {
    "gn:admin1_code":"60.0",
    "gn:asciiname":"Kervansaray",
    "gn:country_code":"TR",
    "gn:dem":1158,
    "gn:feature_class":"P",
    "gn:feature_code":"PPL",
    "gn:name":"Kervansaray",
    "gn:population":0,
    "gn:timezone":"Europe/Istanbul",
    "iso:country":"TR",
    "wof:name":"Kervansaray",
    "wof:placetype":"locality"
},
  "geometry": {"coordinates":[35.80293,40.41549000000001],"type":"Point"}
}