{
  "type": "Feature",
  "properties": {
    "gn:admin1_code":"31.0",
    "gn:asciiname":"Tikiroglu",
    "gn:country_code":"TR",
    "gn:dem":167,
    "gn:feature_class":"P",
    "gn:feature_code":"PPL",
    "gn:name":"T\u0131k\u0131ro\u011flu",
    "gn:population":0,
    "gn:timezone":"Europe/Istanbul",
    "iso:country":"TR",
    "name:und_x_variant":[
        "Kefertizaya",
        "Kefer Tizayi",
        "T\u0131k\u0131ro\u011flu"
    ],
    "wof:name":"Tikiroglu",
    "wof:placetype":"locality"
},
  "geometry": {"coordinates":[36.62483,36.28716],"type":"Point"}
}