{
  "type": "Feature",
  "properties": {
    "gn:admin1_code":"14.0",
    "gn:asciiname":"Bedestan",
    "gn:country_code":"TR",
    "gn:dem":1179,
    "gn:feature_class":"P",
    "gn:feature_code":"PPL",
    "gn:name":"Bedestan",
    "gn:population":0,
    "gn:timezone":"Europe/Istanbul",
    "iso:country":"TR",
    "name:und_x_variant":[
        "Yukar\u0131 Belen",
        "Yukar\u0131 Bedestan",
        "Bedestan"
    ],
    "wof:name":"Bedestan",
    "wof:placetype":"locality"
},
  "geometry": {"coordinates":[31.75,40.41667],"type":"Point"}
}