{
  "type": "Feature",
  "properties": {
    "gn:admin1_code":"45",
    "gn:asciiname":"Sakarkaya",
    "gn:country_code":"TR",
    "gn:dem":213,
    "gn:feature_class":"P",
    "gn:feature_code":"PPL",
    "gn:name":"Sakarkaya",
    "gn:population":0,
    "gn:timezone":"Europe/Istanbul",
    "iso:country":"TR",
    "wof:name":"Sakarkaya",
    "wof:placetype":"locality"
},
  "geometry": {"coordinates":[27.60583,38.91917],"type":"Point"}
}