{
  "type": "Feature",
  "properties": {
    "gn:admin1_code":"34.0",
    "gn:asciiname":"Bucakli",
    "gn:country_code":"TR",
    "gn:dem":153,
    "gn:feature_class":"P",
    "gn:feature_code":"PPL",
    "gn:name":"Bucakl\u0131",
    "gn:population":0,
    "gn:timezone":"Europe/Istanbul",
    "iso:country":"TR",
    "wof:name":"Bucakli",
    "wof:placetype":"locality"
},
  "geometry": {"coordinates":[29.88972,41.1222],"type":"Point"}
}