{
  "type": "Feature",
  "properties": {
    "gn:admin1_code":"80",
    "gn:asciiname":"Hurusya",
    "gn:cc2":"TR",
    "gn:country_code":"TR",
    "gn:dem":440,
    "gn:feature_class":"P",
    "gn:feature_code":"PPL",
    "gn:name":"Hurusya",
    "gn:population":0,
    "gn:timezone":"Europe/Istanbul",
    "iso:country":"TR",
    "name:rus_x_preferred":[
        "Razvaliny Khuris\u2019yan"
    ],
    "name:und_x_variant":[
        "Razvaliny Kharabekotik",
        "Hurusya"
    ],
    "wof:name":"Hurusya",
    "wof:placetype":"locality"
},
  "geometry": {"coordinates":[42.38194,37.25222],"type":"Point"}
}