{
  "type": "Feature",
  "properties": {
    "gn:admin1_code":"43",
    "gn:asciiname":"Gazelyakup",
    "gn:country_code":"TR",
    "gn:dem":1146,
    "gn:feature_class":"P",
    "gn:feature_code":"PPL",
    "gn:name":"Gazelyakup",
    "gn:population":0,
    "gn:timezone":"Europe/Istanbul",
    "iso:country":"TR",
    "wof:name":"Gazelyakup",
    "wof:placetype":"locality"
},
  "geometry": {"coordinates":[29.80068,39.64818],"type":"Point"}
}