{
  "type": "Feature",
  "properties": {
    "gn:admin1_code":"37.0",
    "gn:asciiname":"Geris",
    "gn:country_code":"TR",
    "gn:dem":1162,
    "gn:feature_class":"P",
    "gn:feature_code":"PPL",
    "gn:name":"Geris",
    "gn:population":0,
    "gn:timezone":"Europe/Istanbul",
    "iso:country":"TR",
    "name:und_x_variant":[
        "Giri\u015f",
        "Geris"
    ],
    "wof:name":"Geris",
    "wof:placetype":"locality"
},
  "geometry": {"coordinates":[33.32696,41.07104],"type":"Point"}
}