{
  "type": "Feature",
  "properties": {
    "gn:admin1_code":"46.0",
    "gn:asciiname":"Yaprakli",
    "gn:country_code":"TR",
    "gn:dem":1127,
    "gn:feature_class":"P",
    "gn:feature_code":"PPL",
    "gn:name":"Yaprakl\u0131",
    "gn:population":0,
    "gn:timezone":"Europe/Istanbul",
    "iso:country":"TR",
    "wof:name":"Yaprakli",
    "wof:placetype":"locality"
},
  "geometry": {"coordinates":[37.10972,38.23691],"type":"Point"}
}