{
  "type": "Feature",
  "properties": {
    "gn:admin1_code":"72.0",
    "gn:asciiname":"Chalysheykhan",
    "gn:country_code":"TR",
    "gn:dem":983,
    "gn:feature_class":"P",
    "gn:feature_code":"PPL",
    "gn:name":"Chalysheykhan",
    "gn:population":0,
    "gn:timezone":"Europe/Istanbul",
    "iso:country":"TR",
    "name:tur_x_preferred":[
        "Y\u00fcce"
    ],
    "name:und_x_variant":[
        "\u00c7ah\u015feyhan",
        "Chalysheykhan"
    ],
    "wof:name":"Chalysheykhan",
    "wof:placetype":"locality"
},
  "geometry": {"coordinates":[40.62555,37.45621],"type":"Point"}
}