{
  "type": "Feature",
  "properties": {
    "gn:admin1_code":"76",
    "gn:asciiname":"Hurriyet",
    "gn:country_code":"TR",
    "gn:dem":732,
    "gn:feature_class":"P",
    "gn:feature_code":"PPL",
    "gn:name":"H\u00fcrriyet",
    "gn:population":0,
    "gn:timezone":"Europe/Istanbul",
    "iso:country":"TR",
    "wof:name":"Hurriyet",
    "wof:placetype":"locality"
},
  "geometry": {"coordinates":[41.32272,38.18399],"type":"Point"}
}