{
  "type": "Feature",
  "properties": {
    "gn:admin1_code":"04",
    "gn:asciiname":"Yigityatagi",
    "gn:country_code":"TR",
    "gn:dem":2016,
    "gn:feature_class":"P",
    "gn:feature_code":"PPL",
    "gn:name":"Yi\u011fityata\u011f\u0131",
    "gn:population":0,
    "gn:timezone":"Europe/Istanbul",
    "iso:country":"TR",
    "name:und_x_variant":[
        "Z\u0131ndo",
        "Yi\u011fityata\u011f\u0131"
    ],
    "wof:name":"Yigityatagi",
    "wof:placetype":"locality"
},
  "geometry": {"coordinates":[44.26825,39.4094],"type":"Point"}
}