{
  "type": "Feature",
  "properties": {
    "gn:admin1_code":"15",
    "gn:asciiname":"Beskavak",
    "gn:country_code":"TR",
    "gn:dem":1297,
    "gn:feature_class":"P",
    "gn:feature_code":"PPL",
    "gn:name":"Be\u015fkavak",
    "gn:population":0,
    "gn:timezone":"Europe/Istanbul",
    "iso:country":"TR",
    "wof:name":"Beskavak",
    "wof:placetype":"locality"
},
  "geometry": {"coordinates":[30.37527,37.57751],"type":"Point"}
}