{
  "type": "Feature",
  "properties": {
    "gn:admin1_code":"65",
    "gn:asciiname":"Yarimkaya",
    "gn:country_code":"TR",
    "gn:dem":2071,
    "gn:feature_class":"P",
    "gn:feature_code":"PPL",
    "gn:name":"Yar\u0131mkaya",
    "gn:population":0,
    "gn:timezone":"Europe/Istanbul",
    "iso:country":"TR",
    "name:und_x_variant":[
        "Yar\u0131mkaya K\u00f6y\u00fc",
        "Yar\u0131mkaya"
    ],
    "wof:name":"Yarimkaya",
    "wof:placetype":"locality"
},
  "geometry": {"coordinates":[43.83632,38.81583],"type":"Point"}
}