{
  "type": "Feature",
  "properties": {
    "gn:admin1_code":"44",
    "gn:asciiname":"Dursunlu",
    "gn:country_code":"TR",
    "gn:dem":1343,
    "gn:feature_class":"P",
    "gn:feature_code":"PPL",
    "gn:name":"Dursunlu",
    "gn:population":0,
    "gn:timezone":"Europe/Istanbul",
    "iso:country":"TR",
    "name:tur_x_preferred":[
        "Dursunlu"
    ],
    "wof:name":"Dursunlu",
    "wof:placetype":"locality"
},
  "geometry": {"coordinates":[37.8534,38.81573],"type":"Point"}
}