{
  "type": "Feature",
  "properties": {
    "gn:admin1_code":"83",
    "gn:asciiname":"Sogutlu",
    "gn:country_code":"TR",
    "gn:dem":596,
    "gn:feature_class":"P",
    "gn:feature_code":"PPL",
    "gn:name":"S\u00f6\u011f\u00fctl\u00fc",
    "gn:population":0,
    "gn:timezone":"Europe/Istanbul",
    "iso:country":"TR",
    "name:und_x_variant":[
        "S\u00fcg\u00fctl\u00fc",
        "S\u00f6\u011f\u00fctl\u00fc"
    ],
    "wof:name":"Sogutlu",
    "wof:placetype":"locality"
},
  "geometry": {"coordinates":[37.72709,37.00648],"type":"Point"}
}