{
  "type": "Feature",
  "properties": {
    "iso:country":"TR",
    "qs:name":"Terkos",
    "qs:name_adm0":"Turkey",
    "qs:name_adm1":"\u0130stanbul",
    "qs:photos":31,
    "qs:photos_1k":6,
    "qs:photos_9k":1,
    "qs:photos_9r":2,
    "qs:photos_all":31,
    "qs:photos_sr":2,
    "qs:placetype":"Town",
    "qs:pop_sr":"0",
    "wof:name":"Terkos",
    "wof:placetype":"locality"
},
  "geometry": {"coordinates":[28.683586,41.323636],"type":"Point"}
}