{
  "type": "Feature",
  "properties": {
    "gn:country":"TR",
    "gn:fcode":"PPL",
    "gn:population":151,
    "iso:country":"TR",
    "name:aze_x_preferred":[
        "Ula\u015fl\u0131"
    ],
    "name:kat_x_preferred":[
        "\u10e3\u10da\u10d0\u10e8\u10da\u10d8"
    ],
    "name:und_x_variant":[
        "K\u0131nnap"
    ],
    "qs:name":"Ula\u015fl\u0131",
    "qs:photos_9r":0,
    "qs:photos_sr":0,
    "qs:pop_sr":"1",
    "wd:wordcount":39,
    "wof:name":"Ula\u015fl\u0131",
    "wof:placetype":"locality",
    "wof:population":151
},
  "geometry": {"coordinates":[37.655,36.78611],"type":"Point"}
}