{
  "type": "Feature",
  "properties": {
    "gn:admin1_code":"81",
    "gn:asciiname":"Iblioglu",
    "gn:country_code":"TR",
    "gn:dem":860,
    "gn:feature_class":"P",
    "gn:feature_code":"PPL",
    "gn:name":"\u0130blio\u011flu",
    "gn:population":0,
    "gn:timezone":"Europe/Istanbul",
    "iso:country":"TR",
    "name:und_x_variant":[
        "\u0130blio\u011flu",
        "\u00c7\u0131lb\u0131rt\u0131belen"
    ],
    "wof:name":"Iblioglu",
    "wof:placetype":"locality"
},
  "geometry": {"coordinates":[36.0006,37.67137],"type":"Point"}
}