{
  "type": "Feature",
  "properties": {
    "gn:admin1_code":"80",
    "gn:asciiname":"Meryem",
    "gn:country_code":"TR",
    "gn:dem":1062,
    "gn:feature_class":"P",
    "gn:feature_code":"PPL",
    "gn:name":"Meryem",
    "gn:population":0,
    "gn:timezone":"Europe/Istanbul",
    "iso:country":"TR",
    "name:tur_x_preferred":[
        "Meryem"
    ],
    "wof:name":"Meryem",
    "wof:placetype":"locality"
},
  "geometry": {"coordinates":[42.595,37.54139],"type":"Point"}
}