{
  "type": "Feature",
  "properties": {
    "gn:admin1_code":"71",
    "gn:asciiname":"Kotu Mahallesi",
    "gn:country_code":"TR",
    "gn:dem":955,
    "gn:feature_class":"P",
    "gn:feature_code":"PPL",
    "gn:name":"K\u00f6t\u00fc Mahallesi",
    "gn:population":0,
    "gn:timezone":"Europe/Istanbul",
    "iso:country":"TR",
    "name:und_x_variant":[
        "K\u00f6t\u00fc Mahallesi",
        "C\u00fcdk\u00e2nl\u0131"
    ],
    "wof:name":"Kotu Mahallesi",
    "wof:placetype":"locality"
},
  "geometry": {"coordinates":[33.01256,38.50931],"type":"Point"}
}