{
  "type": "Feature",
  "properties": {
    "gn:admin1_code":"38",
    "gn:asciiname":"Buyukpotuklu",
    "gn:country_code":"TR",
    "gn:dem":1519,
    "gn:feature_class":"P",
    "gn:feature_code":"PPL",
    "gn:name":"B\u00fcy\u00fckpotuklu",
    "gn:population":0,
    "gn:timezone":"Europe/Istanbul",
    "iso:country":"TR",
    "name:tur_x_preferred":[
        "B\u00fcy\u00fckpotuklu"
    ],
    "wof:name":"Buyukpotuklu",
    "wof:placetype":"locality"
},
  "geometry": {"coordinates":[36.37067,38.7341],"type":"Point"}
}