{
  "type": "Feature",
  "properties": {
    "gn:admin1_code":"16",
    "gn:asciiname":"Yildirim",
    "gn:country_code":"TR",
    "gn:dem":171,
    "gn:feature_class":"P",
    "gn:feature_code":"PPLA2",
    "gn:name":"Y\u0131ld\u0131r\u0131m",
    "gn:population":0,
    "gn:timezone":"Europe/Istanbul",
    "iso:country":"TR",
    "name:deu_x_preferred":[
        "Y\u0131ld\u0131r\u0131m"
    ],
    "name:eng_x_preferred":[
        "Yildirim"
    ],
    "name:fra_x_preferred":[
        "Y\u0131ld\u0131r\u0131m"
    ],
    "name:mrj_x_preferred":[
        "\u0419\u044b\u043b\u0434\u044b\u0440\u044b\u043c"
    ],
    "name:msa_x_preferred":[
        "Y\u0131ld\u0131r\u0131m"
    ],
    "name:nld_x_preferred":[
        "Y\u0131ld\u0131r\u0131m"
    ],
    "name:nor_x_preferred":[
        "Y\u0131ld\u0131r\u0131m"
    ],
    "name:pnb_x_preferred":[
        "\u0636\u0644\u0639 \u06cc\u0644\u062f\u0631\u0645"
    ],
    "name:rus_x_preferred":[
        "\u0419\u044b\u043b\u0434\u044b\u0440\u044b\u043c"
    ],
    "name:swa_x_preferred":[
        "Y\u0131ld\u0131r\u0131m"
    ],
    "name:tur_x_preferred":[
        "Y\u0131ld\u0131r\u0131m"
    ],
    "name:urd_x_preferred":[
        "\u06cc\u0644\u062f\u0631\u0645"
    ],
    "name:vie_x_preferred":[
        "Y\u0131ld\u0131r\u0131m"
    ],
    "wof:name":"Yildirim",
    "wof:placetype":"locality"
},
  "geometry": {"coordinates":[29.10974,40.18851],"type":"Point"}
}