{
  "type": "Feature",
  "properties": {
    "gn:admin1_code":"04",
    "gn:asciiname":"Guneysogut",
    "gn:country_code":"TR",
    "gn:dem":1976,
    "gn:feature_class":"P",
    "gn:feature_code":"PPL",
    "gn:name":"G\u00fcneys\u00f6\u011f\u00fct",
    "gn:population":0,
    "gn:timezone":"Europe/Istanbul",
    "iso:country":"TR",
    "name:und_x_variant":[
        "\u00c7arhiya",
        "\u00c7arh\u0131yan",
        "\u00c7arkiyan",
        "G\u00fcneys\u00f6\u011f\u00fct"
    ],
    "wof:name":"Guneysogut",
    "wof:placetype":"locality"
},
  "geometry": {"coordinates":[43.30996,39.5616],"type":"Point"}
}