{
  "type": "Feature",
  "properties": {
    "gn:admin1_code":"68",
    "gn:asciiname":"Gelagrayaylasi",
    "gn:country_code":"TR",
    "gn:dem":1013,
    "gn:feature_class":"P",
    "gn:feature_code":"PPL",
    "gn:name":"Gela\u011frayaylas\u0131",
    "gn:population":0,
    "gn:timezone":"Europe/Istanbul",
    "iso:country":"TR",
    "wof:name":"Gelagrayaylasi",
    "wof:placetype":"locality"
},
  "geometry": {"coordinates":[31.83333,39.98333],"type":"Point"}
}