{
  "type": "Feature",
  "properties": {
    "gn:admin1_code":"65.0",
    "gn:asciiname":"Oymakli",
    "gn:country_code":"TR",
    "gn:dem":2084,
    "gn:feature_class":"P",
    "gn:feature_code":"PPL",
    "gn:name":"Oymakl\u0131",
    "gn:population":0,
    "gn:timezone":"Europe/Istanbul",
    "iso:country":"TR",
    "name:tur_x_preferred":[
        "Oymakl\u0131"
    ],
    "wof:name":"Oymakli",
    "wof:placetype":"locality"
},
  "geometry": {"coordinates":[44.17699,38.83335],"type":"Point"}
}