{
  "type": "Feature",
  "properties": {
    "gn:admin1_code":"31.0",
    "gn:asciiname":"Alic",
    "gn:country_code":"TR",
    "gn:dem":1144,
    "gn:feature_class":"P",
    "gn:feature_code":"PPL",
    "gn:name":"Al\u0131\u00e7",
    "gn:population":0,
    "gn:timezone":"Europe/Istanbul",
    "iso:country":"TR",
    "name:und_x_variant":[
        "Al\u0131\u00e7",
        "Al\u0131\u00e7ba\u011f\u0131"
    ],
    "wof:name":"Alic",
    "wof:placetype":"locality"
},
  "geometry": {"coordinates":[36.14432,36.45914000000001],"type":"Point"}
}