{
  "type": "Feature",
  "properties": {
    "gn:admin1_code":"38",
    "gn:asciiname":"Solaklar",
    "gn:country_code":"TR",
    "gn:dem":1620,
    "gn:feature_class":"P",
    "gn:feature_code":"PPL",
    "gn:name":"Solaklar",
    "gn:population":0,
    "gn:timezone":"Europe/Istanbul",
    "iso:country":"TR",
    "wof:name":"Solaklar",
    "wof:placetype":"locality"
},
  "geometry": {"coordinates":[36.36955,38.68761],"type":"Point"}
}