{
  "type": "Feature",
  "properties": {
    "gn:admin1_code":"82.0",
    "gn:asciiname":"Karacaozu",
    "gn:country_code":"TR",
    "gn:dem":1038,
    "gn:feature_class":"P",
    "gn:feature_code":"PPL",
    "gn:name":"Karaca\u00f6z\u00fc",
    "gn:population":0,
    "gn:timezone":"Europe/Istanbul",
    "iso:country":"TR",
    "wof:name":"Karacaozu",
    "wof:placetype":"locality"
},
  "geometry": {"coordinates":[33.77305,40.72852],"type":"Point"}
}