{
  "type": "Feature",
  "properties": {
    "gn:admin1_code":"82.0",
    "gn:asciiname":"Yiprak",
    "gn:country_code":"TR",
    "gn:dem":1202,
    "gn:feature_class":"P",
    "gn:feature_code":"PPL",
    "gn:name":"Y\u0131prak",
    "gn:population":0,
    "gn:timezone":"Europe/Istanbul",
    "iso:country":"TR",
    "name:und_x_variant":[
        "Yaprak",
        "Y\u0131prak"
    ],
    "wof:name":"Yiprak",
    "wof:placetype":"locality"
},
  "geometry": {"coordinates":[32.81647,40.92545],"type":"Point"}
}