{
  "type": "Feature",
  "properties": {
    "gn:admin1_code":"83",
    "gn:asciiname":"Yelliburun",
    "gn:country_code":"TR",
    "gn:dem":472,
    "gn:feature_class":"P",
    "gn:feature_code":"PPL",
    "gn:name":"Yelliburun",
    "gn:population":0,
    "gn:timezone":"Europe/Istanbul",
    "iso:country":"TR",
    "name:tur_x_preferred":[
        "Yelliburun"
    ],
    "wof:name":"Yelliburun",
    "wof:placetype":"locality"
},
  "geometry": {"coordinates":[36.7193,37.02313],"type":"Point"}
}