{
  "type": "Feature",
  "properties": {
    "gn:admin1_code":"23",
    "gn:asciiname":"Tepebagi",
    "gn:country_code":"TR",
    "gn:dem":1077,
    "gn:feature_class":"P",
    "gn:feature_code":"PPL",
    "gn:name":"Tepeba\u011f\u0131",
    "gn:population":0,
    "gn:timezone":"Europe/Istanbul",
    "iso:country":"TR",
    "name:tur_x_preferred":[
        "Tepeba\u011f\u0131"
    ],
    "wof:name":"Tepebagi",
    "wof:placetype":"locality"
},
  "geometry": {"coordinates":[39.81349,38.70423],"type":"Point"}
}