{
  "type": "Feature",
  "properties": {
    "gn:admin1_code":"65.0",
    "gn:asciiname":"Deringecit",
    "gn:country_code":"TR",
    "gn:dem":2092,
    "gn:feature_class":"P",
    "gn:feature_code":"PPL",
    "gn:name":"Deringe\u00e7it",
    "gn:population":0,
    "gn:timezone":"Europe/Istanbul",
    "iso:country":"TR",
    "name:tur_x_preferred":[
        "Deringe\u00e7it"
    ],
    "wof:name":"Deringecit",
    "wof:placetype":"locality"
},
  "geometry": {"coordinates":[44.03256,37.84808],"type":"Point"}
}