{
  "type": "Feature",
  "properties": {
    "gn:admin1_code":"08",
    "gn:asciiname":"Ortairmak",
    "gn:country_code":"TR",
    "gn:dem":78,
    "gn:feature_class":"P",
    "gn:feature_code":"PPL",
    "gn:name":"Orta\u0131rmak",
    "gn:population":0,
    "gn:timezone":"Europe/Istanbul",
    "iso:country":"TR",
    "name:tur_x_preferred":[
        "Orta\u0131rmak"
    ],
    "wof:name":"Ortairmak",
    "wof:placetype":"locality"
},
  "geometry": {"coordinates":[40.93192,41.13286],"type":"Point"}
}