{
  "type": "Feature",
  "properties": {
    "gn:admin1_code":"68.0",
    "gn:asciiname":"Sobran",
    "gn:country_code":"TR",
    "gn:dem":870,
    "gn:feature_class":"P",
    "gn:feature_code":"PPL",
    "gn:name":"Sobran",
    "gn:population":0,
    "gn:timezone":"Europe/Istanbul",
    "iso:country":"TR",
    "name:und_x_variant":[
        "Sobram",
        "Sobran"
    ],
    "wof:name":"Sobran",
    "wof:placetype":"locality"
},
  "geometry": {"coordinates":[31.39275,40.19382],"type":"Point"}
}