{
  "type": "Feature",
  "properties": {
    "gn:admin1_code":"23",
    "gn:asciiname":"Dumluyazi",
    "gn:country_code":"TR",
    "gn:dem":1273,
    "gn:feature_class":"P",
    "gn:feature_code":"PPL",
    "gn:name":"Dumluyaz\u0131",
    "gn:population":0,
    "gn:timezone":"Europe/Istanbul",
    "iso:country":"TR",
    "name:und_x_variant":[
        "Kal\u0131kan",
        "Kolhan",
        "Dumluyaz\u0131",
        "Kolikan"
    ],
    "wof:name":"Dumluyazi",
    "wof:placetype":"locality"
},
  "geometry": {"coordinates":[40.15263,39.15409],"type":"Point"}
}