{
  "type": "Feature",
  "properties": {
    "gn:admin1_code":"68",
    "gn:asciiname":"Mamali",
    "gn:country_code":"TR",
    "gn:dem":1172,
    "gn:feature_class":"P",
    "gn:feature_code":"PPL",
    "gn:name":"Mamal\u0131",
    "gn:population":0,
    "gn:timezone":"Europe/Istanbul",
    "iso:country":"TR",
    "wof:name":"Mamali",
    "wof:placetype":"locality"
},
  "geometry": {"coordinates":[33.78194000000001,38.83464],"type":"Point"}
}