{
  "type": "Feature",
  "properties": {
    "gn:admin1_code":"21",
    "gn:asciiname":"Dislibasak",
    "gn:country_code":"TR",
    "gn:dem":1107,
    "gn:feature_class":"P",
    "gn:feature_code":"PPL",
    "gn:name":"Di\u015fliba\u015fak",
    "gn:population":0,
    "gn:timezone":"Europe/Istanbul",
    "iso:country":"TR",
    "name:tur_x_preferred":[
        "Di\u015fliba\u015fak"
    ],
    "wof:name":"Dislibasak",
    "wof:placetype":"locality"
},
  "geometry": {"coordinates":[39.98581,37.67148],"type":"Point"}
}