{
  "type": "Feature",
  "properties": {
    "gn:admin1_code":"87.0",
    "gn:asciiname":"Cayalti",
    "gn:country_code":"TR",
    "gn:dem":58,
    "gn:feature_class":"P",
    "gn:feature_code":"PPL",
    "gn:name":"\u00c7ayalt\u0131",
    "gn:population":0,
    "gn:timezone":"Europe/Istanbul",
    "iso:country":"TR",
    "name:und_x_variant":[
        "Turabi",
        "\u00c7ayalt\u0131"
    ],
    "wof:name":"Cayalti",
    "wof:placetype":"locality"
},
  "geometry": {"coordinates":[32.66768,41.81433],"type":"Point"}
}