{
  "type": "Feature",
  "properties": {
    "gn:admin1_code":"58",
    "gn:asciiname":"Eskikapumahmut",
    "gn:country_code":"TR",
    "gn:dem":1817,
    "gn:feature_class":"P",
    "gn:feature_code":"PPL",
    "gn:name":"Eskikapumahmut",
    "gn:population":0,
    "gn:timezone":"Europe/Istanbul",
    "iso:country":"TR",
    "name:tur_x_preferred":[
        "Eskikapumahmut"
    ],
    "name:und_x_variant":[
        "Eskikap\u0131mahmut",
        "Cafolar"
    ],
    "wof:name":"Eskikapumahmut",
    "wof:placetype":"locality"
},
  "geometry": {"coordinates":[38.18276,39.95391],"type":"Point"}
}