{
  "type": "Feature",
  "properties": {
    "gn:admin1_code":"14.0",
    "gn:asciiname":"Sahbazlar",
    "gn:country_code":"TR",
    "gn:dem":749,
    "gn:feature_class":"P",
    "gn:feature_code":"PPL",
    "gn:name":"\u015eahbazlar",
    "gn:population":0,
    "gn:timezone":"Europe/Istanbul",
    "iso:country":"TR",
    "name:und_x_variant":[
        "\u015eabanlar",
        "\u015eahbazlar"
    ],
    "wof:name":"Sahbazlar",
    "wof:placetype":"locality"
},
  "geometry": {"coordinates":[31.92726,40.89521],"type":"Point"}
}