{
  "type": "Feature",
  "properties": {
    "gn:admin1_code":"58",
    "gn:asciiname":"Inkoy",
    "gn:country_code":"TR",
    "gn:dem":1555,
    "gn:feature_class":"P",
    "gn:feature_code":"PPL",
    "gn:name":"\u0130nk\u00f6y",
    "gn:population":0,
    "gn:timezone":"Europe/Istanbul",
    "iso:country":"TR",
    "wof:name":"Inkoy",
    "wof:placetype":"locality"
},
  "geometry": {"coordinates":[37.55589000000001,39.6495],"type":"Point"}
}