{
  "type": "Feature",
  "properties": {
    "gn:admin1_code":"04",
    "gn:asciiname":"Besbulak",
    "gn:country_code":"TR",
    "gn:dem":1901,
    "gn:feature_class":"P",
    "gn:feature_code":"PPL",
    "gn:name":"Be\u015fbulak",
    "gn:population":0,
    "gn:timezone":"Europe/Istanbul",
    "iso:country":"TR",
    "name:und_x_variant":[
        "Ganisipi",
        "Kanisipi",
        "Ganispi",
        "Be\u015fbulak"
    ],
    "wof:name":"Besbulak",
    "wof:placetype":"locality"
},
  "geometry": {"coordinates":[43.05191,39.90948],"type":"Point"}
}