{
  "type": "Feature",
  "properties": {
    "gn:admin1_code":"91",
    "gn:asciiname":"Colakli",
    "gn:country_code":"TR",
    "gn:dem":711,
    "gn:feature_class":"P",
    "gn:feature_code":"PPL",
    "gn:name":"\u00c7olakl\u0131",
    "gn:population":0,
    "gn:timezone":"Europe/Istanbul",
    "iso:country":"TR",
    "name:tur_x_preferred":[
        "\u00c7olakl\u0131"
    ],
    "wof:name":"Colakli",
    "wof:placetype":"locality"
},
  "geometry": {"coordinates":[36.54421,37.16608],"type":"Point"}
}