{
  "type": "Feature",
  "properties": {
    "gn:admin1_code":"10.0",
    "gn:asciiname":"Adali",
    "gn:country_code":"TR",
    "gn:dem":386,
    "gn:feature_class":"P",
    "gn:feature_code":"PPL",
    "gn:name":"Adal\u0131",
    "gn:population":0,
    "gn:timezone":"Europe/Istanbul",
    "iso:country":"TR",
    "name:tur_x_preferred":[
        "Adal\u0131"
    ],
    "wof:name":"Adali",
    "wof:placetype":"locality"
},
  "geometry": {"coordinates":[28.28748,39.41101],"type":"Point"}
}