{
  "type": "Feature",
  "properties": {
    "gn:admin1_code":"69.0",
    "gn:asciiname":"Kizilcadam",
    "gn:country_code":"TR",
    "gn:dem":1342,
    "gn:feature_class":"P",
    "gn:feature_code":"PPL",
    "gn:name":"K\u0131z\u0131lcadam",
    "gn:population":0,
    "gn:timezone":"Europe/Istanbul",
    "iso:country":"TR",
    "name:und_x_variant":[
        "K\u0131z\u0131lcadam",
        "Akg\u00fcney"
    ],
    "wof:name":"Kizilcadam",
    "wof:placetype":"locality"
},
  "geometry": {"coordinates":[39.05539,40.61177],"type":"Point"}
}