{
  "type": "Feature",
  "properties": {
    "gn:admin1_code":"34.0",
    "gn:asciiname":"Resadiye",
    "gn:country_code":"TR",
    "gn:dem":209,
    "gn:feature_class":"P",
    "gn:feature_code":"PPL",
    "gn:name":"Re\u015fadiye",
    "gn:population":0,
    "gn:timezone":"Europe/Istanbul",
    "iso:country":"TR",
    "name:tur_x_preferred":[
        "Re\u015fadiye"
    ],
    "wof:name":"Resadiye",
    "wof:placetype":"locality"
},
  "geometry": {"coordinates":[29.25005,41.07681],"type":"Point"}
}