{
  "type": "Feature",
  "properties": {
    "gn:admin1_code":"13.0",
    "gn:asciiname":"Kapisuyu",
    "gn:country_code":"TR",
    "gn:dem":1326,
    "gn:feature_class":"P",
    "gn:feature_code":"PPL",
    "gn:name":"Kap\u0131suyu",
    "gn:population":0,
    "gn:timezone":"Europe/Istanbul",
    "iso:country":"TR",
    "name:tur_x_preferred":[
        "Kap\u0131suyu"
    ],
    "wof:name":"Kapisuyu",
    "wof:placetype":"locality"
},
  "geometry": {"coordinates":[42.39552,38.20368],"type":"Point"}
}