{
  "type": "Feature",
  "properties": {
    "gn:admin1_code":"85.0",
    "gn:asciiname":"Bodac",
    "gn:country_code":"TR",
    "gn:dem":208,
    "gn:feature_class":"P",
    "gn:feature_code":"PPL",
    "gn:name":"Boda\u00e7",
    "gn:population":0,
    "gn:timezone":"Europe/Istanbul",
    "iso:country":"TR",
    "name:und_x_variant":[
        "Boda\u015f",
        "Boda\u00e7"
    ],
    "wof:name":"Bodac",
    "wof:placetype":"locality"
},
  "geometry": {"coordinates":[32.16902,41.27601],"type":"Point"}
}