{
  "type": "Feature",
  "properties": {
    "gn:admin1_code":"37.0",
    "gn:asciiname":"Kepez",
    "gn:country_code":"TR",
    "gn:dem":1498,
    "gn:feature_class":"P",
    "gn:feature_code":"PPL",
    "gn:name":"Kepez",
    "gn:population":0,
    "gn:timezone":"Europe/Istanbul",
    "iso:country":"TR",
    "name:aze_x_preferred":[
        "K\u0259p\u0259z"
    ],
    "name:deu_x_preferred":[
        "Kepez"
    ],
    "name:msa_x_preferred":[
        "Kepez"
    ],
    "name:tur_x_preferred":[
        "Kepez"
    ],
    "wof:name":"Kepez",
    "wof:placetype":"locality"
},
  "geometry": {"coordinates":[34.11667,41.71667],"type":"Point"}
}