{
  "type": "Feature",
  "properties": {
    "gn:admin1_code":"84.0",
    "gn:asciiname":"Asagi Sallipinar",
    "gn:country_code":"TR",
    "gn:dem":1988,
    "gn:feature_class":"P",
    "gn:feature_code":"PPL",
    "gn:name":"A\u015fa\u011f\u0131 Sall\u0131p\u0131nar",
    "gn:population":0,
    "gn:timezone":"Europe/Istanbul",
    "iso:country":"TR",
    "name:tur_x_preferred":[
        "A\u015fa\u011f\u0131 Sall\u0131p\u0131nar"
    ],
    "name:und_x_variant":[
        "A\u015fa\u011f\u0131salut",
        "A\u015fa\u011f\u0131sallap\u0131nar",
        "A\u015fa\u011f\u0131sall\u0131p\u0131nar"
    ],
    "wof:name":"Asagi Sallipinar",
    "wof:placetype":"locality"
},
  "geometry": {"coordinates":[42.61091,40.46038],"type":"Point"}
}