{
  "type": "Feature",
  "properties": {
    "gn:country":"TR",
    "gn:fcode":"PPL",
    "gn:pop":630,
    "iso:country":"TR",
    "name:unk_x_variant":[
        "D\u00f6\u015feme"
    ],
    "qs:name":"N\u00fczhetiye",
    "qs:photos_9r":0,
    "qs:photos_sr":0,
    "qs:pop_sr":"2",
    "wof:name":"N\u00fczhetiye",
    "wof:placetype":"locality",
    "wof:population":630
},
  "geometry": {"coordinates":[29.86306,40.64],"type":"Point"}
}