{
  "type": "Feature",
  "properties": {
    "gn:admin1_code":"26.0",
    "gn:asciiname":"Gokcekaya",
    "gn:country_code":"TR",
    "gn:dem":770,
    "gn:feature_class":"P",
    "gn:feature_code":"PPL",
    "gn:name":"G\u00f6k\u00e7ekaya",
    "gn:population":0,
    "gn:timezone":"Europe/Istanbul",
    "iso:country":"TR",
    "name:und_x_variant":[
        "\u00c7i\u00e7eroz",
        "G\u00f6k\u00e7ekaya"
    ],
    "wof:name":"Gokcekaya",
    "wof:placetype":"locality"
},
  "geometry": {"coordinates":[30.98895,40.01803],"type":"Point"}
}