{
  "type": "Feature",
  "properties": {
    "gn:admin1_code":"74.0",
    "gn:asciiname":"Yukari Baytarun",
    "gn:country_code":"TR",
    "gn:dem":1350,
    "gn:feature_class":"P",
    "gn:feature_code":"PPL",
    "gn:name":"Yukar\u0131 Baytarun",
    "gn:population":0,
    "gn:timezone":"Europe/Istanbul",
    "iso:country":"TR",
    "wof:name":"Yukari Baytarun",
    "wof:placetype":"locality"
},
  "geometry": {"coordinates":[41.90323,38.07844],"type":"Point"}
}