{
  "type": "Feature",
  "properties": {
    "gn:admin1_code":"49.0",
    "gn:asciiname":"Tekneduzu",
    "gn:country_code":"TR",
    "gn:dem":1606,
    "gn:feature_class":"P",
    "gn:feature_code":"PPL",
    "gn:name":"Tekned\u00fcz\u00fc",
    "gn:population":0,
    "gn:timezone":"Europe/Istanbul",
    "iso:country":"TR",
    "name:tur_x_preferred":[
        "Tekned\u00fcz\u00fc"
    ],
    "wof:name":"Tekneduzu",
    "wof:placetype":"locality"
},
  "geometry": {"coordinates":[41.23241,39.2639],"type":"Point"}
}