{
  "type": "Feature",
  "properties": {
    "gn:admin1_code":"63.0",
    "gn:asciiname":"Agilli",
    "gn:country_code":"TR",
    "gn:dem":569,
    "gn:feature_class":"P",
    "gn:feature_code":"PPL",
    "gn:name":"A\u011f\u0131ll\u0131",
    "gn:population":0,
    "gn:timezone":"Europe/Istanbul",
    "iso:country":"TR",
    "name:tur_x_preferred":[
        "A\u011f\u0131ll\u0131"
    ],
    "wof:name":"Agilli",
    "wof:placetype":"locality"
},
  "geometry": {"coordinates":[38.36172,37.30764],"type":"Point"}
}