{
  "type": "Feature",
  "properties": {
    "gn:admin1_code":"25",
    "gn:asciiname":"Dagyurdu",
    "gn:country_code":"TR",
    "gn:dem":2300,
    "gn:feature_class":"P",
    "gn:feature_code":"PPL",
    "gn:name":"Da\u011fyurdu",
    "gn:population":0,
    "gn:timezone":"Europe/Istanbul",
    "iso:country":"TR",
    "name:tur_x_preferred":[
        "Da\u011fyurdu"
    ],
    "wof:name":"Dagyurdu",
    "wof:placetype":"locality"
},
  "geometry": {"coordinates":[40.84679000000001,39.72832],"type":"Point"}
}