{
  "type": "Feature",
  "properties": {
    "gn:admin1_code":"88",
    "gn:asciiname":"Elmalik",
    "gn:country_code":"TR",
    "gn:dem":1857,
    "gn:feature_class":"P",
    "gn:feature_code":"PPL",
    "gn:name":"Elmal\u0131k",
    "gn:population":0,
    "gn:timezone":"Europe/Istanbul",
    "iso:country":"TR",
    "name:und_x_variant":[
        "Ahnalik",
        "Elmal\u0131k"
    ],
    "wof:name":"Elmalik",
    "wof:placetype":"locality"
},
  "geometry": {"coordinates":[43.56667,39.98333],"type":"Point"}
}