{
  "type": "Feature",
  "properties": {
    "gn:admin1_code":"72",
    "gn:asciiname":"Hayirli",
    "gn:country_code":"TR",
    "gn:dem":476,
    "gn:feature_class":"P",
    "gn:feature_code":"PPL",
    "gn:name":"Hay\u0131rl\u0131",
    "gn:population":0,
    "gn:timezone":"Europe/Istanbul",
    "iso:country":"TR",
    "name:tur_x_preferred":[
        "Hay\u0131rl\u0131"
    ],
    "wof:name":"Hayirli",
    "wof:placetype":"locality"
},
  "geometry": {"coordinates":[40.06194,37.22111],"type":"Point"}
}