{
  "type": "Feature",
  "properties": {
    "gn:admin1_code":"68.0",
    "gn:asciiname":"Bercinyaylalar",
    "gn:country_code":"TR",
    "gn:dem":1376,
    "gn:feature_class":"P",
    "gn:feature_code":"PPL",
    "gn:name":"Ber\u00e7inyaylalar",
    "gn:population":0,
    "gn:timezone":"Europe/Istanbul",
    "iso:country":"TR",
    "wof:name":"Bercinyaylalar",
    "wof:placetype":"locality"
},
  "geometry": {"coordinates":[32.50427,40.64091],"type":"Point"}
}