{
  "type": "Feature",
  "properties": {
    "gn:admin1_code":"68.0",
    "gn:asciiname":"Yenikayi",
    "gn:country_code":"TR",
    "gn:dem":994,
    "gn:feature_class":"P",
    "gn:feature_code":"PPL",
    "gn:name":"Yenikay\u0131",
    "gn:population":0,
    "gn:timezone":"Europe/Istanbul",
    "iso:country":"TR",
    "name:und_x_variant":[
        "Kayi",
        "Zirkay\u0131",
        "Yenikay\u0131"
    ],
    "wof:name":"Yenikayi",
    "wof:placetype":"locality"
},
  "geometry": {"coordinates":[32.44164,40.01527],"type":"Point"}
}