{
  "type": "Feature",
  "properties": {
    "gn:admin1_code":"13",
    "gn:asciiname":"Canakyayla",
    "gn:country_code":"TR",
    "gn:dem":2230,
    "gn:feature_class":"P",
    "gn:feature_code":"PPL",
    "gn:name":"\u00c7anakyayla",
    "gn:population":0,
    "gn:timezone":"Europe/Istanbul",
    "iso:country":"TR",
    "name:und_x_variant":[
        "Virangazi",
        "\u00c7anakyayla"
    ],
    "wof:name":"Canakyayla",
    "wof:placetype":"locality"
},
  "geometry": {"coordinates":[42.69964,38.9004],"type":"Point"}
}