{
  "type": "Feature",
  "properties": {
    "gn:admin1_code":"20",
    "gn:asciiname":"Beydilli",
    "gn:country_code":"TR",
    "gn:dem":856,
    "gn:feature_class":"P",
    "gn:feature_code":"PPL",
    "gn:name":"Beydilli",
    "gn:population":0,
    "gn:timezone":"Europe/Istanbul",
    "iso:country":"TR",
    "wof:name":"Beydilli",
    "wof:placetype":"locality"
},
  "geometry": {"coordinates":[29.9225,38.27417],"type":"Point"}
}