{
  "type": "Feature",
  "properties": {
    "gn:admin1_code":"24",
    "gn:asciiname":"Gokdere",
    "gn:country_code":"TR",
    "gn:dem":1902,
    "gn:feature_class":"P",
    "gn:feature_code":"PPL",
    "gn:name":"G\u00f6kdere",
    "gn:population":0,
    "gn:timezone":"Europe/Istanbul",
    "iso:country":"TR",
    "name:tur_x_preferred":[
        "G\u00f6kdere"
    ],
    "wof:name":"Gokdere",
    "wof:placetype":"locality"
},
  "geometry": {"coordinates":[40.5353,39.84016],"type":"Point"}
}