{
  "type": "Feature",
  "properties": {
    "gn:admin1_code":"35",
    "gn:asciiname":"Saruhanli",
    "gn:country_code":"TR",
    "gn:dem":230,
    "gn:feature_class":"P",
    "gn:feature_code":"PPL",
    "gn:name":"Saruhanl\u0131",
    "gn:population":0,
    "gn:timezone":"Europe/Istanbul",
    "iso:country":"TR",
    "name:tur_x_preferred":[
        "Saruhanl\u0131"
    ],
    "wof:name":"Saruhanli",
    "wof:placetype":"locality"
},
  "geometry": {"coordinates":[27.88309000000001,38.08588],"type":"Point"}
}