{
  "type": "Feature",
  "properties": {
    "iso:country":"TR",
    "name:eng_x_preferred":[
        "Kordonboyu"
    ],
    "name:tur_x_preferred":[
        "Kordonboyu"
    ],
    "wof:name":"Kordonboyu",
    "wof:placetype":"neighbourhood"
},
  "geometry": {"coordinates":[29.18729094420445,40.88819012921047],"type":"Point"}
}