{
  "type": "Feature",
  "properties": {
    "gn:admin1_code":"71",
    "gn:asciiname":"Kotukoy Yaylasi",
    "gn:country_code":"TR",
    "gn:dem":1008,
    "gn:feature_class":"P",
    "gn:feature_code":"PPL",
    "gn:name":"K\u00f6t\u00fck\u00f6y Yaylas\u0131",
    "gn:population":0,
    "gn:timezone":"Europe/Istanbul",
    "iso:country":"TR",
    "name:tur_x_preferred":[
        "K\u00f6t\u00fck\u00f6y Yaylas\u0131"
    ],
    "name:tur_x_variant":[
        "Karayusuf Yaylas\u0131"
    ],
    "wof:name":"Kotukoy Yaylasi",
    "wof:placetype":"locality"
},
  "geometry": {"coordinates":[32.77579,38.82615],"type":"Point"}
}