{
  "type": "Feature",
  "properties": {
    "gn:country":"TR",
    "gn:fcode":"PPL",
    "gn:population":723,
    "iso:country":"TR",
    "name:deu_x_preferred":[
        "Ak\u00e7a"
    ],
    "name:eng_x_preferred":[
        "Ak\u00e7a"
    ],
    "name:fas_x_preferred":[
        "\u0627\u06a9\u0633\u0627\u060c \u0628\u062a\u0645\u0646"
    ],
    "name:fas_x_variant":[
        "\u0627\u06a9\u0633\u0627"
    ],
    "name:kur_x_preferred":[
        "Tilmiz"
    ],
    "name:msa_x_preferred":[
        "Ak\u00e7a"
    ],
    "name:nld_x_preferred":[
        "Ak\u00e7a"
    ],
    "name:rus_x_preferred":[
        "Gil\u2019mis"
    ],
    "name:tur_x_preferred":[
        "Ak\u00e7a"
    ],
    "name:tur_x_variant":[
        "\u00c7ukuryurt"
    ],
    "name:vie_x_preferred":[
        "Ak\u00e7a"
    ],
    "qs:name":"Ak\u00e7a",
    "qs:photos_9r":0,
    "qs:photos_sr":0,
    "qs:pop_sr":"2",
    "wd:wordcount":128,
    "wof:name":"Ak\u00e7a",
    "wof:placetype":"locality",
    "wof:population":723
},
  "geometry": {"coordinates":[41.18306,37.85414],"type":"Point"}
}