{
  "type": "Feature",
  "properties": {
    "gn:admin1_code":"43",
    "gn:asciiname":"Omerfaki",
    "gn:country_code":"TR",
    "gn:dem":1356,
    "gn:feature_class":"P",
    "gn:feature_code":"PPL",
    "gn:name":"\u00d6merfak\u0131",
    "gn:population":0,
    "gn:timezone":"Europe/Istanbul",
    "iso:country":"TR",
    "name:tur_x_preferred":[
        "\u00d6merfak\u0131"
    ],
    "wof:name":"Omerfaki",
    "wof:placetype":"locality"
},
  "geometry": {"coordinates":[29.43675,39.25656],"type":"Point"}
}