{
  "type": "Feature",
  "properties": {
    "gn:admin1_code":"81",
    "gn:asciiname":"Yenikonacik",
    "gn:country_code":"TR",
    "gn:dem":1046,
    "gn:feature_class":"P",
    "gn:feature_code":"PPL",
    "gn:name":"Yenikonac\u0131k",
    "gn:population":0,
    "gn:timezone":"Europe/Istanbul",
    "iso:country":"TR",
    "name:deu_x_preferred":[
        "Yenikonac\u0131k"
    ],
    "name:msa_x_preferred":[
        "Yenikonac\u0131k"
    ],
    "name:tur_x_preferred":[
        "Yenikonac\u0131k"
    ],
    "name:und_x_variant":[
        "Yenikonac\u0131k",
        "Yenianah\u015fa"
    ],
    "name:urd_x_preferred":[
        "\u06cc\u0646\u06a9\u0648\u0646\u0627\u06a9\u06cc\u06a9"
    ],
    "name:vie_x_preferred":[
        "Yenikonac\u0131k"
    ],
    "wof:name":"Yenikonacik",
    "wof:placetype":"locality"
},
  "geometry": {"coordinates":[34.84765,37.42305],"type":"Point"}
}