{
  "type": "Feature",
  "properties": {
    "gn:admin1_code":"45",
    "gn:asciiname":"Karaduz",
    "gn:country_code":"TR",
    "gn:dem":617,
    "gn:feature_class":"P",
    "gn:feature_code":"PPL",
    "gn:name":"Karaduz",
    "gn:population":0,
    "gn:timezone":"Europe/Istanbul",
    "iso:country":"TR",
    "name:tur_x_preferred":[
        "Karaduz"
    ],
    "wof:name":"Karaduz",
    "wof:placetype":"locality"
},
  "geometry": {"coordinates":[28.4301,38.82132],"type":"Point"}
}