{
  "type": "Feature",
  "properties": {
    "gn:admin1_code":"19.0",
    "gn:asciiname":"Catak",
    "gn:country_code":"TR",
    "gn:dem":1194,
    "gn:feature_class":"P",
    "gn:feature_code":"PPL",
    "gn:name":"\u00c7atak",
    "gn:population":0,
    "gn:timezone":"Europe/Istanbul",
    "iso:country":"TR",
    "name:und_x_variant":[
        "\u00c7atakk\u00f6y",
        "\u00c7atak"
    ],
    "wof:name":"Catak",
    "wof:placetype":"locality"
},
  "geometry": {"coordinates":[34.83453,40.68783],"type":"Point"}
}