{
  "type": "Feature",
  "properties": {
    "gn:admin1_code":"35",
    "gn:asciiname":"Yenisakran",
    "gn:country_code":"TR",
    "gn:dem":5,
    "gn:feature_class":"P",
    "gn:feature_code":"PPL",
    "gn:name":"Yeni\u015fakran",
    "gn:population":3552,
    "gn:timezone":"Europe/Istanbul",
    "iso:country":"TR",
    "name:ceb_x_preferred":[
        "Yeni\u015fakran"
    ],
    "name:tur_x_preferred":[
        "Yeni\u015fakran"
    ],
    "name:urd_x_preferred":[
        "\u06cc\u0646\u06cc\u0633\u0627\u06a9\u0631\u0646"
    ],
    "name:vie_x_preferred":[
        "Yeni\u015fakran"
    ],
    "wof:name":"Yenisakran",
    "wof:placetype":"locality",
    "wof:population":3552
},
  "geometry": {"coordinates":[27.06694,38.88639000000001],"type":"Point"}
}