{
  "type": "Feature",
  "properties": {
    "gn:admin1_code":"84.0",
    "gn:asciiname":"Alisofu",
    "gn:country_code":"TR",
    "gn:dem":1850,
    "gn:feature_class":"P",
    "gn:feature_code":"PPL",
    "gn:name":"Alisofu",
    "gn:population":0,
    "gn:timezone":"Europe/Istanbul",
    "iso:country":"TR",
    "name:tur_x_preferred":[
        "Alisofu"
    ],
    "wof:name":"Alisofu",
    "wof:placetype":"locality"
},
  "geometry": {"coordinates":[42.84976,40.44317],"type":"Point"}
}