{
  "type": "Feature",
  "properties": {
    "gn:admin1_code":"55.0",
    "gn:asciiname":"Gokcesukent",
    "gn:country_code":"TR",
    "gn:dem":156,
    "gn:feature_class":"P",
    "gn:feature_code":"PPL",
    "gn:name":"G\u00f6k\u00e7esukent",
    "gn:population":0,
    "gn:timezone":"Europe/Istanbul",
    "iso:country":"TR",
    "name:und_x_variant":[
        "G\u00f6k\u00e7esukent"
    ],
    "wof:name":"Gokcesukent",
    "wof:placetype":"locality"
},
  "geometry": {"coordinates":[35.79176,41.5445],"type":"Point"}
}