{
  "type": "Feature",
  "properties": {
    "gn:admin1_code":"60.0",
    "gn:asciiname":"Mahmudiye",
    "gn:country_code":"TR",
    "gn:dem":271,
    "gn:feature_class":"P",
    "gn:feature_code":"PPL",
    "gn:name":"Mahmudiye",
    "gn:population":0,
    "gn:timezone":"Europe/Istanbul",
    "iso:country":"TR",
    "wof:name":"Mahmudiye",
    "wof:placetype":"locality"
},
  "geometry": {"coordinates":[36.85515,40.60758],"type":"Point"}
}