{
  "type": "Feature",
  "properties": {
    "gn:admin1_code":"76.0",
    "gn:asciiname":"Gecitli",
    "gn:country_code":"TR",
    "gn:dem":1354,
    "gn:feature_class":"P",
    "gn:feature_code":"PPL",
    "gn:name":"Ge\u00e7itli",
    "gn:population":0,
    "gn:timezone":"Europe/Istanbul",
    "iso:country":"TR",
    "name:tur_x_preferred":[
        "Ge\u00e7itli"
    ],
    "wof:name":"Gecitli",
    "wof:placetype":"locality"
},
  "geometry": {"coordinates":[41.42359,38.38414],"type":"Point"}
}