{
  "type": "Feature",
  "properties": {
    "gn:admin1_code":"53.0",
    "gn:asciiname":"Pekmezli",
    "gn:country_code":"TR",
    "gn:dem":129,
    "gn:feature_class":"P",
    "gn:feature_code":"PPL",
    "gn:name":"Pekmezli",
    "gn:population":0,
    "gn:timezone":"Europe/Istanbul",
    "iso:country":"TR",
    "wof:name":"Pekmezli",
    "wof:placetype":"locality"
},
  "geometry": {"coordinates":[40.58216,41.01478],"type":"Point"}
}