{
  "type": "Feature",
  "properties": {
    "gn:admin1_code":"45",
    "gn:asciiname":"Salur",
    "gn:country_code":"TR",
    "gn:dem":732,
    "gn:feature_class":"P",
    "gn:feature_code":"PPL",
    "gn:name":"Salur",
    "gn:population":0,
    "gn:timezone":"Europe/Istanbul",
    "iso:country":"TR",
    "name:tur_x_preferred":[
        "Salur"
    ],
    "wof:name":"Salur",
    "wof:placetype":"locality"
},
  "geometry": {"coordinates":[28.33445,39.01452000000001],"type":"Point"}
}