{
  "type": "Feature",
  "properties": {
    "gn:admin1_code":"44",
    "gn:asciiname":"Hamidiye",
    "gn:country_code":"TR",
    "gn:dem":889,
    "gn:feature_class":"P",
    "gn:feature_code":"PPL",
    "gn:name":"Hamidiye",
    "gn:population":0,
    "gn:timezone":"Europe/Istanbul",
    "iso:country":"TR",
    "name:ceb_x_preferred":[
        "Hamidiye"
    ],
    "name:deu_x_preferred":[
        "Hamidiye"
    ],
    "name:fra_x_preferred":[
        "Hamidiye"
    ],
    "name:nld_x_preferred":[
        "Hamidiye"
    ],
    "name:rus_x_preferred":[
        "\u0425\u0430\u043c\u0438\u0434\u0438\u0435"
    ],
    "name:tur_x_preferred":[
        "Hamidiye"
    ],
    "name:ukr_x_preferred":[
        "\u0425\u0430\u043c\u0456\u0434\u0456\u0454"
    ],
    "name:und_x_variant":[
        "Muhacir"
    ],
    "wof:name":"Hamidiye",
    "wof:placetype":"locality"
},
  "geometry": {"coordinates":[38.12559,38.59181],"type":"Point"}
}