{
  "type": "Feature",
  "properties": {
    "gn:admin1_code":"70",
    "gn:asciiname":"Yumrutas",
    "gn:country_code":"TR",
    "gn:dem":1960,
    "gn:feature_class":"P",
    "gn:feature_code":"PPL",
    "gn:name":"Yumruta\u015f",
    "gn:population":0,
    "gn:timezone":"Europe/Istanbul",
    "iso:country":"TR",
    "wof:name":"Yumrutas",
    "wof:placetype":"locality"
},
  "geometry": {"coordinates":[44.41511,37.50156],"type":"Point"}
}