{
  "type": "Feature",
  "properties": {
    "gn:admin1_code":"37.0",
    "gn:asciiname":"Yenidogan",
    "gn:cc2":"TR",
    "gn:country_code":"TR",
    "gn:dem":516,
    "gn:feature_class":"P",
    "gn:feature_code":"PPL",
    "gn:name":"Yenido\u011fan",
    "gn:population":0,
    "gn:timezone":"Europe/Istanbul",
    "iso:country":"TR",
    "name:und_x_variant":[
        "\u00c7akalk\u00f6y",
        "\u00c7akal",
        "Yenido\u011fan"
    ],
    "wof:name":"Yenidogan",
    "wof:placetype":"locality"
},
  "geometry": {"coordinates":[34.18333,41.01667],"type":"Point"}
}