{
  "type": "Feature",
  "properties": {
    "gn:admin1_code":"57",
    "gn:asciiname":"Tepecik",
    "gn:country_code":"TR",
    "gn:dem":353,
    "gn:feature_class":"P",
    "gn:feature_code":"PPL",
    "gn:name":"Tepecik",
    "gn:population":0,
    "gn:timezone":"Europe/Istanbul",
    "iso:country":"TR",
    "name:ceb_x_preferred":[
        "Tepecik"
    ],
    "name:deu_x_preferred":[
        "Tepecik"
    ],
    "name:min_x_preferred":[
        "Tepecik"
    ],
    "name:tur_x_preferred":[
        "Tepecik"
    ],
    "wof:name":"Tepecik",
    "wof:placetype":"locality"
},
  "geometry": {"coordinates":[34.72485,41.91459],"type":"Point"}
}