{
  "type": "Feature",
  "properties": {
    "gn:admin1_code":"54.0",
    "gn:asciiname":"Yenikoy",
    "gn:country_code":"TR",
    "gn:dem":55,
    "gn:feature_class":"P",
    "gn:feature_code":"PPL",
    "gn:name":"Yenik\u00f6y",
    "gn:population":0,
    "gn:timezone":"Europe/Istanbul",
    "iso:country":"TR",
    "name:tur_x_preferred":[
        "Yenik\u00f6y"
    ],
    "wof:name":"Yenikoy",
    "wof:placetype":"locality"
},
  "geometry": {"coordinates":[30.53751,40.90576],"type":"Point"}
}