{
  "type": "Feature",
  "properties": {
    "gn:admin1_code":"16.0",
    "gn:asciiname":"Kiranlar",
    "gn:country_code":"TR",
    "gn:dem":226,
    "gn:feature_class":"P",
    "gn:feature_code":"PPL",
    "gn:name":"K\u0131ranlar",
    "gn:population":0,
    "gn:timezone":"Europe/Istanbul",
    "iso:country":"TR",
    "name:und_x_variant":[
        "K\u0131ranl\u0131",
        "K\u0131ranlar"
    ],
    "wof:name":"Kiranlar",
    "wof:placetype":"locality"
},
  "geometry": {"coordinates":[28.32232,40.27254],"type":"Point"}
}