{
  "type": "Feature",
  "properties": {
    "gn:admin1_code":"40.0",
    "gn:asciiname":"Acioz",
    "gn:country_code":"TR",
    "gn:dem":1004,
    "gn:feature_class":"P",
    "gn:feature_code":"PPL",
    "gn:name":"Ac\u0131\u00f6z",
    "gn:population":0,
    "gn:timezone":"Europe/Istanbul",
    "iso:country":"TR",
    "name:tur_x_preferred":[
        "Ac\u0131\u00f6z"
    ],
    "wof:name":"Acioz",
    "wof:placetype":"locality"
},
  "geometry": {"coordinates":[34.35235,39.02954],"type":"Point"}
}