{
  "type": "Feature",
  "properties": {
    "gn:admin1_code":"63.0",
    "gn:asciiname":"Bulduk",
    "gn:country_code":"TR",
    "gn:dem":398,
    "gn:feature_class":"P",
    "gn:feature_code":"PPL",
    "gn:name":"Bulduk",
    "gn:population":0,
    "gn:timezone":"Europe/Istanbul",
    "iso:country":"TR",
    "name:aze_x_preferred":[
        "Bulduq"
    ],
    "name:nld_x_preferred":[
        "Bulduk"
    ],
    "name:tur_x_preferred":[
        "Bulduk"
    ],
    "wof:name":"Bulduk",
    "wof:placetype":"locality"
},
  "geometry": {"coordinates":[39.10649,37.03339],"type":"Point"}
}