{
  "type": "Feature",
  "properties": {
    "gn:admin1_code":"69.0",
    "gn:asciiname":"Yitirmez",
    "gn:country_code":"TR",
    "gn:dem":1511,
    "gn:feature_class":"P",
    "gn:feature_code":"PPL",
    "gn:name":"Yitirmez",
    "gn:population":0,
    "gn:timezone":"Europe/Istanbul",
    "iso:country":"TR",
    "name:und_x_variant":[
        "Sobran"
    ],
    "wof:name":"Yitirmez",
    "wof:placetype":"locality"
},
  "geometry": {"coordinates":[39.67541,40.45372],"type":"Point"}
}