{
  "type": "Feature",
  "properties": {
    "gn:admin1_code":"75",
    "gn:asciiname":"Karamehmet",
    "gn:country_code":"TR",
    "gn:dem":1361,
    "gn:feature_class":"P",
    "gn:feature_code":"PPL",
    "gn:name":"Karamehmet",
    "gn:population":0,
    "gn:timezone":"Europe/Istanbul",
    "iso:country":"TR",
    "name:und_x_variant":[
        "Karaahmetli",
        "G\u00f6\u011fs\u00fcg\u00fczel",
        "G\u00f6ks\u00fcg\u00fczel"
    ],
    "wof:name":"Karamehmet",
    "wof:placetype":"locality"
},
  "geometry": {"coordinates":[34.16346,38.51559],"type":"Point"}
}