{
  "type": "Feature",
  "properties": {
    "gn:admin1_code":"85.0",
    "gn:asciiname":"Kirmaci",
    "gn:country_code":"TR",
    "gn:dem":179,
    "gn:feature_class":"P",
    "gn:feature_code":"PPL",
    "gn:name":"K\u0131rmac\u0131",
    "gn:population":0,
    "gn:timezone":"Europe/Istanbul",
    "iso:country":"TR",
    "name:und_x_variant":[
        "Kemerk\u00f6y",
        "K\u0131rmac\u0131"
    ],
    "wof:name":"Kirmaci",
    "wof:placetype":"locality"
},
  "geometry": {"coordinates":[31.42416,41.29901],"type":"Point"}
}