{
  "type": "Feature",
  "properties": {
    "gn:admin1_code":"55.0",
    "gn:asciiname":"Tahnel",
    "gn:country_code":"TR",
    "gn:dem":1106,
    "gn:feature_class":"P",
    "gn:feature_code":"PPL",
    "gn:name":"Tahnel",
    "gn:population":0,
    "gn:timezone":"Europe/Istanbul",
    "iso:country":"TR",
    "wof:name":"Tahnel",
    "wof:placetype":"locality"
},
  "geometry": {"coordinates":[36.81421,40.94593],"type":"Point"}
}