{
  "type": "Feature",
  "properties": {
    "gn:admin1_code":"25",
    "gn:asciiname":"Ardi",
    "gn:country_code":"TR",
    "gn:dem":1683,
    "gn:feature_class":"P",
    "gn:feature_code":"PPL",
    "gn:name":"Ard\u0131",
    "gn:population":0,
    "gn:timezone":"Europe/Istanbul",
    "iso:country":"TR",
    "name:tur_x_preferred":[
        "Ard\u0131"
    ],
    "wof:name":"Ardi",
    "wof:placetype":"locality"
},
  "geometry": {"coordinates":[42.11729,39.9512],"type":"Point"}
}