{
  "type": "Feature",
  "properties": {
    "gn:admin1_code":"25",
    "gn:asciiname":"Ardi",
    "gn:country_code":"TR",
    "gn:dem":1683,
    "gn:feature_class":"P",
    "gn:feature_code":"PPL",
    "gn:name":"Ard\u0131",
    "gn:population":0,
    "gn:timezone":"Europe/Istanbul",
    "iso:country":"TR",
    "name:ara_x_preferred":[
        "\u0622\u0631\u062f\u064a"
    ],
    "name:cat_x_preferred":[
        "Ardi"
    ],
    "name:deu_x_preferred":[
        "Ardi"
    ],
    "name:epo_x_preferred":[
        "Ardi"
    ],
    "name:fra_x_preferred":[
        "Ardi"
    ],
    "name:jpn_x_preferred":[
        "\u30a2\u30eb\u30c7\u30a3"
    ],
    "name:nld_x_preferred":[
        "Ardi"
    ],
    "name:por_x_preferred":[
        "Ardi"
    ],
    "name:rus_x_preferred":[
        "\u0410\u0440\u0434\u0438"
    ],
    "name:spa_x_preferred":[
        "Ardi"
    ],
    "name:srp_x_preferred":[
        "\u0410\u0440\u0434\u0438"
    ],
    "name:tur_x_preferred":[
        "Ard\u0131"
    ],
    "name:zho_x_preferred":[
        "\u963f\u723e\u8fea"
    ],
    "wof:name":"Ardi",
    "wof:placetype":"locality"
},
  "geometry": {"coordinates":[42.11729,39.9512],"type":"Point"}
}