{
  "type": "Feature",
  "properties": {
    "gn:admin1_code":"89.0",
    "gn:asciiname":"Hacilarobasi",
    "gn:country_code":"TR",
    "gn:dem":538,
    "gn:feature_class":"P",
    "gn:feature_code":"PPL",
    "gn:name":"Hac\u0131larobas\u0131",
    "gn:population":0,
    "gn:timezone":"Europe/Istanbul",
    "iso:country":"TR",
    "name:und_x_variant":[
        "Hac\u0131lar",
        "Hac\u0131larovas\u0131",
        "Hac\u0131larobas\u0131"
    ],
    "wof:name":"Hacilarobasi",
    "wof:placetype":"locality"
},
  "geometry": {"coordinates":[32.83643,41.15356],"type":"Point"}
}