{
  "type": "Feature",
  "properties": {
    "gn:admin1_code":"02",
    "gn:asciiname":"Karadut",
    "gn:country_code":"TR",
    "gn:dem":996,
    "gn:feature_class":"P",
    "gn:feature_code":"PPL",
    "gn:name":"Karadut",
    "gn:population":0,
    "gn:timezone":"Europe/Istanbul",
    "iso:country":"TR",
    "wof:name":"Karadut",
    "wof:placetype":"locality"
},
  "geometry": {"coordinates":[38.7887,37.92864],"type":"Point"}
}