{
  "type": "Feature",
  "properties": {
    "gn:admin1_code":"15",
    "gn:asciiname":"Bozlar",
    "gn:country_code":"TR",
    "gn:dem":1302,
    "gn:feature_class":"P",
    "gn:feature_code":"PPL",
    "gn:name":"Bozlar",
    "gn:population":0,
    "gn:timezone":"Europe/Istanbul",
    "iso:country":"TR",
    "wof:name":"Bozlar",
    "wof:placetype":"locality"
},
  "geometry": {"coordinates":[30.23083,37.39833],"type":"Point"}
}