{
  "type": "Feature",
  "properties": {
    "gn:admin1_code":"58.0",
    "gn:asciiname":"Catalkaya",
    "gn:country_code":"TR",
    "gn:dem":1733,
    "gn:feature_class":"P",
    "gn:feature_code":"PPL",
    "gn:name":"\u00c7atalkaya",
    "gn:population":0,
    "gn:timezone":"Europe/Istanbul",
    "iso:country":"TR",
    "wof:name":"Catalkaya",
    "wof:placetype":"locality"
},
  "geometry": {"coordinates":[37.12575,39.98883],"type":"Point"}
}