{
  "type": "Feature",
  "properties": {
    "gn:admin1_code":"85.0",
    "gn:asciiname":"Gurcesme",
    "gn:country_code":"TR",
    "gn:dem":203,
    "gn:feature_class":"P",
    "gn:feature_code":"PPL",
    "gn:name":"G\u00fcr\u00e7e\u015fme",
    "gn:population":0,
    "gn:timezone":"Europe/Istanbul",
    "iso:country":"TR",
    "name:und_x_variant":[
        "Badur O\u011flu",
        "Boduro\u011flu",
        "Yapr\u0131o\u011flu",
        "G\u00fcr\u00e7e\u015fme"
    ],
    "wof:name":"Gurcesme",
    "wof:placetype":"locality"
},
  "geometry": {"coordinates":[31.92762,41.21879000000001],"type":"Point"}
}