{
  "type": "Feature",
  "properties": {
    "gn:admin1_code":"74",
    "gn:asciiname":"Banadeli",
    "gn:country_code":"TR",
    "gn:dem":827,
    "gn:feature_class":"P",
    "gn:feature_code":"PPL",
    "gn:name":"Banadeli",
    "gn:population":0,
    "gn:timezone":"Europe/Istanbul",
    "iso:country":"TR",
    "name:und_x_variant":[
        "Verimlli",
        "Banadeli"
    ],
    "wof:name":"Banadeli",
    "wof:placetype":"locality"
},
  "geometry": {"coordinates":[41.9193,37.83789],"type":"Point"}
}