{
  "type": "Feature",
  "properties": {
    "gn:admin1_code":"31.0",
    "gn:asciiname":"Karakurt",
    "gn:country_code":"TR",
    "gn:dem":437,
    "gn:feature_class":"P",
    "gn:feature_code":"PPL",
    "gn:name":"Karakurt",
    "gn:population":0,
    "gn:timezone":"Europe/Istanbul",
    "iso:country":"TR",
    "name:und_x_variant":[
        "Kavkur",
        "Kavkurt",
        "Karakurt"
    ],
    "wof:name":"Karakurt",
    "wof:placetype":"locality"
},
  "geometry": {"coordinates":[36.21776,36.55688],"type":"Point"}
}