{
  "type": "Feature",
  "properties": {
    "gn:admin1_code":"33",
    "gn:asciiname":"Kesmekoy",
    "gn:country_code":"TR",
    "gn:dem":1045,
    "gn:feature_class":"P",
    "gn:feature_code":"PPL",
    "gn:name":"Kesmek\u00f6y",
    "gn:population":0,
    "gn:timezone":"Europe/Istanbul",
    "iso:country":"TR",
    "name:und_x_variant":[
        "Kesmek\u00f6y",
        "Kesme"
    ],
    "wof:name":"Kesmekoy",
    "wof:placetype":"locality"
},
  "geometry": {"coordinates":[31.23028,37.46472],"type":"Point"}
}