{
  "type": "Feature",
  "properties": {
    "gn:admin1_code":"16",
    "gn:asciiname":"Dedekoy",
    "gn:country_code":"TR",
    "gn:dem":124,
    "gn:feature_class":"P",
    "gn:feature_code":"PPL",
    "gn:name":"Dedek\u00f6y",
    "gn:population":0,
    "gn:timezone":"Europe/Istanbul",
    "iso:country":"TR",
    "name:tur_x_preferred":[
        "Dedek\u00f6y"
    ],
    "wof:name":"Dedekoy",
    "wof:placetype":"locality"
},
  "geometry": {"coordinates":[28.84891,40.29428],"type":"Point"}
}