{
  "type": "Feature",
  "properties": {
    "gn:admin1_code":"58",
    "gn:asciiname":"Ozmus",
    "gn:country_code":"TR",
    "gn:dem":1447,
    "gn:feature_class":"P",
    "gn:feature_code":"PPL",
    "gn:name":"\u00d6zmu\u015f",
    "gn:population":0,
    "gn:timezone":"Europe/Istanbul",
    "iso:country":"TR",
    "wof:name":"Ozmus",
    "wof:placetype":"locality"
},
  "geometry": {"coordinates":[36.88486,39.91491],"type":"Point"}
}