{
  "type": "Feature",
  "properties": {
    "gn:admin1_code":"58.0",
    "gn:asciiname":"Dikkoy",
    "gn:country_code":"TR",
    "gn:dem":1294,
    "gn:feature_class":"P",
    "gn:feature_code":"PPL",
    "gn:name":"Dikk\u00f6y",
    "gn:population":0,
    "gn:timezone":"Europe/Istanbul",
    "iso:country":"TR",
    "name:tur_x_preferred":[
        "Dikk\u00f6y"
    ],
    "wof:name":"Dikkoy",
    "wof:placetype":"locality"
},
  "geometry": {"coordinates":[38.57126,40.0696],"type":"Point"}
}