{
  "type": "Feature",
  "properties": {
    "gn:admin1_code":"63",
    "gn:asciiname":"Kurtini",
    "gn:country_code":"TR",
    "gn:dem":860,
    "gn:feature_class":"P",
    "gn:feature_code":"PPL",
    "gn:name":"Kurtini",
    "gn:population":0,
    "gn:timezone":"Europe/Istanbul",
    "iso:country":"TR",
    "name:und_x_variant":[
        "Kurdini",
        "Kurtini"
    ],
    "wof:name":"Kurtini",
    "wof:placetype":"locality"
},
  "geometry": {"coordinates":[39.55694,37.4759],"type":"Point"}
}