{
  "type": "Feature",
  "properties": {
    "gn:admin1_code":"16.0",
    "gn:asciiname":"Ayva",
    "gn:country_code":"TR",
    "gn:dem":258,
    "gn:feature_class":"P",
    "gn:feature_code":"PPL",
    "gn:name":"Ayva",
    "gn:population":0,
    "gn:timezone":"Europe/Istanbul",
    "iso:country":"TR",
    "name:und_x_variant":[
        "Ayvak\u00f6y"
    ],
    "wof:name":"Ayva",
    "wof:placetype":"locality"
},
  "geometry": {"coordinates":[28.70064,40.12696],"type":"Point"}
}