{
  "type": "Feature",
  "properties": {
    "gn:admin1_code":"70.0",
    "gn:asciiname":"Zengil",
    "gn:country_code":"TR",
    "gn:dem":2213,
    "gn:feature_class":"P",
    "gn:feature_code":"PPL",
    "gn:name":"Zengil",
    "gn:population":0,
    "gn:timezone":"Europe/Istanbul",
    "iso:country":"TR",
    "wof:name":"Zengil",
    "wof:placetype":"locality"
},
  "geometry": {"coordinates":[43.59124,37.38941],"type":"Point"}
}