{
  "type": "Feature",
  "properties": {
    "gn:admin1_code":"24",
    "gn:asciiname":"Levent Pinari",
    "gn:country_code":"TR",
    "gn:dem":1433,
    "gn:feature_class":"P",
    "gn:feature_code":"PPL",
    "gn:name":"Levent P\u0131nar\u0131",
    "gn:population":0,
    "gn:timezone":"Europe/Istanbul",
    "iso:country":"TR",
    "name:tur_x_preferred":[
        "Levent P\u0131nar\u0131"
    ],
    "name:und_x_variant":[
        "Erhami",
        "Leventp\u0131nar"
    ],
    "wof:name":"Levent Pinari",
    "wof:placetype":"locality"
},
  "geometry": {"coordinates":[38.61402,39.61823],"type":"Point"}
}