{
  "type": "Feature",
  "properties": {
    "gn:admin1_code":"20",
    "gn:asciiname":"Sariveliler",
    "gn:country_code":"TR",
    "gn:dem":929,
    "gn:feature_class":"P",
    "gn:feature_code":"PPL",
    "gn:name":"Sar\u0131veliler",
    "gn:population":0,
    "gn:timezone":"Europe/Istanbul",
    "iso:country":"TR",
    "name:tur_x_preferred":[
        "Sar\u0131veliler"
    ],
    "wof:name":"Sariveliler",
    "wof:placetype":"locality"
},
  "geometry": {"coordinates":[29.00749,38.19373],"type":"Point"}
}