{
  "type": "Feature",
  "properties": {
    "gn:admin1_code":"15",
    "gn:asciiname":"Bayramlar",
    "gn:country_code":"TR",
    "gn:dem":1257,
    "gn:feature_class":"P",
    "gn:feature_code":"PPL",
    "gn:name":"Bayramlar",
    "gn:population":0,
    "gn:timezone":"Europe/Istanbul",
    "iso:country":"TR",
    "wof:name":"Bayramlar",
    "wof:placetype":"locality"
},
  "geometry": {"coordinates":[29.83162,37.23416],"type":"Point"}
}