{
  "type": "Feature",
  "properties": {
    "gn:admin1_code":"52.0",
    "gn:asciiname":"Cukurkoy",
    "gn:country_code":"TR",
    "gn:dem":1043,
    "gn:feature_class":"P",
    "gn:feature_code":"PPL",
    "gn:name":"\u00c7ukurk\u00f6y",
    "gn:population":0,
    "gn:timezone":"Europe/Istanbul",
    "iso:country":"TR",
    "name:und_x_variant":[
        "\u00c7ukurk\u00f6y",
        "\u00c7ukur"
    ],
    "wof:name":"Cukurkoy",
    "wof:placetype":"locality"
},
  "geometry": {"coordinates":[36.95441,40.77042],"type":"Point"}
}