{
  "type": "Feature",
  "properties": {
    "gn:admin1_code":"80",
    "gn:asciiname":"Kayalicesme",
    "gn:country_code":"TR",
    "gn:dem":2325,
    "gn:feature_class":"P",
    "gn:feature_code":"PPL",
    "gn:name":"Kayal\u0131\u00e7esme",
    "gn:population":0,
    "gn:timezone":"Europe/Istanbul",
    "iso:country":"TR",
    "name:und_x_variant":[
        "Tangakhane",
        "Kayal\u0131\u00e7esme",
        "Tangahane"
    ],
    "wof:name":"Kayalicesme",
    "wof:placetype":"locality"
},
  "geometry": {"coordinates":[43.34575,37.69013],"type":"Point"}
}