{
  "type": "Feature",
  "properties": {
    "gn:admin1_code":"13.0",
    "gn:asciiname":"Kulabik",
    "gn:country_code":"TR",
    "gn:dem":1912,
    "gn:feature_class":"P",
    "gn:feature_code":"PPL",
    "gn:name":"Kulabik",
    "gn:population":0,
    "gn:timezone":"Europe/Istanbul",
    "iso:country":"TR",
    "name:tur_x_preferred":[
        "Kulabik"
    ],
    "wof:name":"Kulabik",
    "wof:placetype":"locality"
},
  "geometry": {"coordinates":[42.15731,38.35405],"type":"Point"}
}