{
  "type": "Feature",
  "properties": {
    "gn:admin1_code":"5.0",
    "gn:asciiname":"Damlacimen",
    "gn:country_code":"TR",
    "gn:dem":576,
    "gn:feature_class":"P",
    "gn:feature_code":"PPL",
    "gn:name":"Damla\u00e7imen",
    "gn:population":0,
    "gn:timezone":"Europe/Istanbul",
    "iso:country":"TR",
    "name:und_x_variant":[
        "\u00c7ozan",
        "\u00c7oran",
        "Damla\u00e7imen"
    ],
    "wof:name":"Damlacimen",
    "wof:placetype":"locality"
},
  "geometry": {"coordinates":[35.42697000000001,40.35657],"type":"Point"}
}