{
  "type": "Feature",
  "properties": {
    "gn:admin1_code":"87.0",
    "gn:asciiname":"Ahmetpasa",
    "gn:country_code":"TR",
    "gn:dem":150,
    "gn:feature_class":"P",
    "gn:feature_code":"PPL",
    "gn:name":"Ahmetpa\u015fa",
    "gn:population":0,
    "gn:timezone":"Europe/Istanbul",
    "iso:country":"TR",
    "name:und_x_variant":[
        "Bay\u0131ry\u00fcz\u00fc",
        "Ahmetpa\u015fa"
    ],
    "wof:name":"Ahmetpasa",
    "wof:placetype":"locality"
},
  "geometry": {"coordinates":[32.2472,41.56721],"type":"Point"}
}