{
  "type": "Feature",
  "properties": {
    "gn:admin1_code":"58.0",
    "gn:asciiname":"Cakmak",
    "gn:country_code":"TR",
    "gn:dem":1508,
    "gn:feature_class":"P",
    "gn:feature_code":"PPL",
    "gn:name":"\u00c7akmak",
    "gn:population":0,
    "gn:timezone":"Europe/Istanbul",
    "iso:country":"TR",
    "name:eng_x_preferred":[
        "\u00c7akmak"
    ],
    "name:rus_x_preferred":[
        "\u0427\u0430\u043a\u043c\u0430\u043a"
    ],
    "name:und_x_variant":[
        "\u00c7akmak"
    ],
    "wof:name":"Cakmak",
    "wof:placetype":"locality"
},
  "geometry": {"coordinates":[37.36556,40.01167],"type":"Point"}
}