{
  "type": "Feature",
  "properties": {
    "gn:admin1_code":"25",
    "gn:asciiname":"Teknecik",
    "gn:country_code":"TR",
    "gn:dem":2094,
    "gn:feature_class":"P",
    "gn:feature_code":"PPL",
    "gn:name":"Teknecik",
    "gn:population":0,
    "gn:timezone":"Europe/Istanbul",
    "iso:country":"TR",
    "name:tur_x_preferred":[
        "Teknecik"
    ],
    "wof:name":"Teknecik",
    "wof:placetype":"locality"
},
  "geometry": {"coordinates":[42.44479000000001,40.01579],"type":"Point"}
}