{
  "type": "Feature",
  "properties": {
    "gn:admin1_code":"10",
    "gn:asciiname":"Yorucekler",
    "gn:country_code":"TR",
    "gn:dem":182,
    "gn:feature_class":"P",
    "gn:feature_code":"PPL",
    "gn:name":"Y\u00f6r\u00fccekler",
    "gn:population":0,
    "gn:timezone":"Europe/Istanbul",
    "iso:country":"TR",
    "name:tur_x_preferred":[
        "Y\u00f6r\u00fccekler"
    ],
    "wof:name":"Yorucekler",
    "wof:placetype":"locality"
},
  "geometry": {"coordinates":[28.07038,39.35958],"type":"Point"}
}