{
  "type": "Feature",
  "properties": {
    "gn:admin1_code":"23",
    "gn:asciiname":"Canakca",
    "gn:country_code":"TR",
    "gn:dem":1028,
    "gn:feature_class":"P",
    "gn:feature_code":"PPL",
    "gn:name":"\u00c7anak\u00e7a",
    "gn:population":0,
    "gn:timezone":"Europe/Istanbul",
    "iso:country":"TR",
    "name:tur_x_preferred":[
        "\u00c7anak\u00e7a"
    ],
    "name:und_x_variant":[
        "A\u015fa\u011f\u0131 Sindi\u011fik",
        "\u00c7anak\u00e7\u0131",
        "A\u015fa\u011f\u0131s\u0131\u011f\u0131k"
    ],
    "wof:name":"Canakca",
    "wof:placetype":"locality"
},
  "geometry": {"coordinates":[39.77591,38.44348],"type":"Point"}
}