{
  "type": "Feature",
  "properties": {
    "gn:country":"TR",
    "gn:fcode":"PPL",
    "gn:pop":230,
    "iso:country":"TR",
    "name:tur_x_preferred":[
        "Sar\u0131k\u00f6y"
    ],
    "qs:name":"Zeri",
    "qs:photos_9r":0,
    "qs:photos_sr":0,
    "qs:pop_sr":"2",
    "wd:wordcount":28,
    "wof:name":"Zeri",
    "wof:placetype":"locality",
    "wof:population":230
},
  "geometry": {"coordinates":[40.81278,37.81472],"type":"Point"}
}