{
  "type": "Feature",
  "properties": {
    "gn:country":"TR",
    "gn:fcode":"PPL",
    "gn:pop":230,
    "iso:country":"TR",
    "name:ara_x_preferred":[
        "\u0632\u0631\u064a"
    ],
    "name:azb_x_preferred":[
        "\u0632\u0631\u06cc"
    ],
    "name:bcl_x_preferred":[
        "Zeri"
    ],
    "name:bel_x_preferred":[
        "\u0426\u044d\u0440\u044b"
    ],
    "name:bre_x_preferred":[
        "Zeri"
    ],
    "name:bul_x_preferred":[
        "\u0414\u0437\u0435\u0440\u0438"
    ],
    "name:cat_x_preferred":[
        "Zeri"
    ],
    "name:ceb_x_preferred":[
        "Zeri"
    ],
    "name:cos_x_preferred":[
        "Zeri"
    ],
    "name:deu_x_preferred":[
        "Zeri"
    ],
    "name:eml_x_preferred":[
        "Z\u00e9ri"
    ],
    "name:eng_x_preferred":[
        "Zeri"
    ],
    "name:epo_x_preferred":[
        "Zeri"
    ],
    "name:eus_x_preferred":[
        "Zeri"
    ],
    "name:fas_x_preferred":[
        "\u0632\u0631\u06cc"
    ],
    "name:fra_x_preferred":[
        "Zeri"
    ],
    "name:hun_x_preferred":[
        "Zeri"
    ],
    "name:hye_x_preferred":[
        "\u0541\u0565\u0580\u056b"
    ],
    "name:ind_x_preferred":[
        "Zeri"
    ],
    "name:ita_x_preferred":[
        "Zeri"
    ],
    "name:jpn_x_preferred":[
        "\u30bc\u30fc\u30ea"
    ],
    "name:kaz_x_preferred":[
        "\u0426\u0435\u0440\u0438"
    ],
    "name:kor_x_preferred":[
        "\uccb4\ub9ac"
    ],
    "name:lat_x_preferred":[
        "Silva Cerri"
    ],
    "name:lmo_x_preferred":[
        "Zeri"
    ],
    "name:msa_x_preferred":[
        "Zeri"
    ],
    "name:nan_x_preferred":[
        "Zeri"
    ],
    "name:nap_x_preferred":[
        "Zeri"
    ],
    "name:nld_x_preferred":[
        "Zeri"
    ],
    "name:nob_x_preferred":[
        "Zeri"
    ],
    "name:oci_x_preferred":[
        "Zeri"
    ],
    "name:pms_x_preferred":[
        "Zeri"
    ],
    "name:pol_x_preferred":[
        "Zeri"
    ],
    "name:por_x_preferred":[
        "Zeri"
    ],
    "name:ron_x_preferred":[
        "Zeri"
    ],
    "name:rus_x_preferred":[
        "\u0426\u0435\u0440\u0438"
    ],
    "name:scn_x_preferred":[
        "Zeri"
    ],
    "name:sco_x_preferred":[
        "Zeri"
    ],
    "name:spa_x_preferred":[
        "Zeri"
    ],
    "name:srp_x_preferred":[
        "Zeri"
    ],
    "name:tgl_x_preferred":[
        "Zeri"
    ],
    "name:tur_x_preferred":[
        "Sar\u0131k\u00f6y"
    ],
    "name:ukr_x_preferred":[
        "\u0426\u0435\u0440\u0456"
    ],
    "name:uzb_x_preferred":[
        "Zeri"
    ],
    "name:vie_x_preferred":[
        "Zeri"
    ],
    "name:vol_x_preferred":[
        "Zeri"
    ],
    "name:war_x_preferred":[
        "Zeri"
    ],
    "name:zho_x_preferred":[
        "\u6cfd\u91cc"
    ],
    "qs:name":"Zeri",
    "qs:photos_9r":0,
    "qs:photos_sr":0,
    "qs:pop_sr":"2",
    "wd:wordcount":28,
    "wof:name":"Zeri",
    "wof:placetype":"locality",
    "wof:population":230
},
  "geometry": {"coordinates":[40.81278,37.81472],"type":"Point"}
}