{
  "type": "Feature",
  "properties": {
    "gn:admin1_code":"80.0",
    "gn:asciiname":"Yumurtali",
    "gn:country_code":"TR",
    "gn:dem":1827,
    "gn:feature_class":"P",
    "gn:feature_code":"PPL",
    "gn:name":"Yumurtal\u0131",
    "gn:population":0,
    "gn:timezone":"Europe/Istanbul",
    "iso:country":"TR",
    "name:tur_x_preferred":[
        "Yumurtal\u0131"
    ],
    "wof:name":"Yumurtali",
    "wof:placetype":"locality"
},
  "geometry": {"coordinates":[42.87581,37.65737],"type":"Point"}
}