{
  "type": "Feature",
  "properties": {
    "gn:admin1_code":"10",
    "gn:asciiname":"Pelitkoy",
    "gn:country_code":"TR",
    "gn:dem":124,
    "gn:feature_class":"P",
    "gn:feature_code":"PPL",
    "gn:name":"Pelitk\u00f6y",
    "gn:population":0,
    "gn:timezone":"Europe/Istanbul",
    "iso:country":"TR",
    "name:msa_x_preferred":[
        "Pelitk\u00f6y"
    ],
    "name:tur_x_preferred":[
        "Pelitk\u00f6y"
    ],
    "name:und_x_variant":[
        "Zeytinp\u0131nar",
        "Pelit",
        "Pelitk\u00f6y"
    ],
    "name:vie_x_preferred":[
        "Pelitk\u00f6y"
    ],
    "wof:name":"Pelitkoy",
    "wof:placetype":"locality"
},
  "geometry": {"coordinates":[26.90059,39.44416],"type":"Point"}
}