{
  "type": "Feature",
  "properties": {
    "gn:admin1_code":"28",
    "gn:asciiname":"Evrenkoy",
    "gn:country_code":"TR",
    "gn:dem":384,
    "gn:feature_class":"P",
    "gn:feature_code":"PPL",
    "gn:name":"Evrenk\u00f6y",
    "gn:population":0,
    "gn:timezone":"Europe/Istanbul",
    "iso:country":"TR",
    "name:tur_x_preferred":[
        "Evrenk\u00f6y"
    ],
    "wof:name":"Evrenkoy",
    "wof:placetype":"locality"
},
  "geometry": {"coordinates":[38.37916,40.85085],"type":"Point"}
}