{
  "type": "Feature",
  "properties": {
    "gn:admin1_code":"50",
    "gn:asciiname":"Kulluce",
    "gn:country_code":"TR",
    "gn:dem":1012,
    "gn:feature_class":"P",
    "gn:feature_code":"PPL",
    "gn:name":"K\u00fcll\u00fcce",
    "gn:population":0,
    "gn:timezone":"Europe/Istanbul",
    "iso:country":"TR",
    "wof:name":"Kulluce",
    "wof:placetype":"locality"
},
  "geometry": {"coordinates":[34.68725,39.22766],"type":"Point"}
}