{
  "type": "Feature",
  "properties": {
    "gn:admin1_code":"54.0",
    "gn:asciiname":"Hirka",
    "gn:country_code":"TR",
    "gn:dem":285,
    "gn:feature_class":"P",
    "gn:feature_code":"PPL",
    "gn:name":"H\u0131rka",
    "gn:population":0,
    "gn:timezone":"Europe/Istanbul",
    "iso:country":"TR",
    "name:tur_x_preferred":[
        "H\u0131rka"
    ],
    "wof:name":"Hirka",
    "wof:placetype":"locality"
},
  "geometry": {"coordinates":[30.30191,40.48042],"type":"Point"}
}