{
  "type": "Feature",
  "properties": {
    "gn:admin1_code":"60.0",
    "gn:asciiname":"Ayan",
    "gn:country_code":"TR",
    "gn:dem":348,
    "gn:feature_class":"P",
    "gn:feature_code":"PPL",
    "gn:name":"Ayan",
    "gn:population":0,
    "gn:timezone":"Europe/Istanbul",
    "iso:country":"TR",
    "name:aze_x_preferred":[
        "Ayan"
    ],
    "name:ceb_x_preferred":[
        "Ayan"
    ],
    "name:deu_x_preferred":[
        "Ayan"
    ],
    "name:rus_x_preferred":[
        "\u0410\u044f\u043d"
    ],
    "name:swe_x_preferred":[
        "Ayan"
    ],
    "name:ukr_x_preferred":[
        "\u0410\u044f\u043d"
    ],
    "wof:name":"Ayan",
    "wof:placetype":"locality"
},
  "geometry": {"coordinates":[36.74834,40.66283],"type":"Point"}
}