{
  "type": "Feature",
  "properties": {
    "gn:admin1_code":"10",
    "gn:asciiname":"Sebiller",
    "gn:country_code":"TR",
    "gn:dem":482,
    "gn:feature_class":"P",
    "gn:feature_code":"PPL",
    "gn:name":"Sebiller",
    "gn:population":0,
    "gn:timezone":"Europe/Istanbul",
    "iso:country":"TR",
    "name:tur_x_preferred":[
        "Sebiller"
    ],
    "wof:name":"Sebiller",
    "wof:placetype":"locality"
},
  "geometry": {"coordinates":[28.38698,39.52569],"type":"Point"}
}