{
  "type": "Feature",
  "properties": {
    "gn:admin1_code":"46.0",
    "gn:asciiname":"Akoren",
    "gn:country_code":"TR",
    "gn:dem":1146,
    "gn:feature_class":"P",
    "gn:feature_code":"PPL",
    "gn:name":"Ak\u00f6ren",
    "gn:population":0,
    "gn:timezone":"Europe/Istanbul",
    "iso:country":"TR",
    "name:und_x_variant":[
        "A\u011fviran",
        "A\u011fveren",
        "Akviran",
        "Akveran",
        "Akveren",
        "Ak\u00f6ren"
    ],
    "wof:name":"Akoren",
    "wof:placetype":"locality"
},
  "geometry": {"coordinates":[37.20908,38.24552],"type":"Point"}
}