{
  "type": "Feature",
  "properties": {
    "gn:admin1_code":"65.0",
    "gn:asciiname":"Kyvris",
    "gn:country_code":"TR",
    "gn:dem":1708,
    "gn:feature_class":"P",
    "gn:feature_code":"PPL",
    "gn:name":"Kyvris",
    "gn:population":0,
    "gn:timezone":"Europe/Istanbul",
    "iso:country":"TR",
    "name:und_x_variant":[
        "K\u0131vris"
    ],
    "wof:name":"Kyvris",
    "wof:placetype":"locality"
},
  "geometry": {"coordinates":[43.07083,37.99167],"type":"Point"}
}