{
  "type": "Feature",
  "properties": {
    "gn:admin1_code":"65.0",
    "gn:asciiname":"Islamkoy",
    "gn:country_code":"TR",
    "gn:dem":2221,
    "gn:feature_class":"P",
    "gn:feature_code":"PPL",
    "gn:name":"\u0130slamk\u00f6y",
    "gn:population":0,
    "gn:timezone":"Europe/Istanbul",
    "iso:country":"TR",
    "name:tur_x_preferred":[
        "\u0130slamk\u00f6y"
    ],
    "wof:name":"Islamkoy",
    "wof:placetype":"locality"
},
  "geometry": {"coordinates":[44.08986,38.48645],"type":"Point"}
}