{
  "type": "Feature",
  "properties": {
    "gn:admin1_code":"43",
    "gn:asciiname":"Kozcagiz",
    "gn:country_code":"TR",
    "gn:dem":961,
    "gn:feature_class":"P",
    "gn:feature_code":"PPL",
    "gn:name":"Kozca\u011f\u0131z",
    "gn:population":0,
    "gn:timezone":"Europe/Istanbul",
    "iso:country":"TR",
    "name:tur_x_preferred":[
        "Kozca\u011f\u0131z"
    ],
    "wof:name":"Kozcagiz",
    "wof:placetype":"locality"
},
  "geometry": {"coordinates":[29.53708,39.68836],"type":"Point"}
}