{
  "type": "Feature",
  "properties": {
    "gn:admin1_code":"23",
    "gn:asciiname":"Bagin",
    "gn:cc2":"TR",
    "gn:country_code":"TR",
    "gn:dem":1569,
    "gn:feature_class":"P",
    "gn:feature_code":"PPL",
    "gn:name":"Ba\u011f\u0131n",
    "gn:population":0,
    "gn:timezone":"Europe/Istanbul",
    "iso:country":"TR",
    "name:und_x_variant":[
        "Gayn"
    ],
    "wof:name":"Bagin",
    "wof:placetype":"locality"
},
  "geometry": {"coordinates":[39.95,38.56667],"type":"Point"}
}