{
  "type": "Feature",
  "properties": {
    "gn:admin1_code":"58",
    "gn:asciiname":"Olcekli",
    "gn:country_code":"TR",
    "gn:dem":1309,
    "gn:feature_class":"P",
    "gn:feature_code":"PPL",
    "gn:name":"\u00d6l\u00e7ekli",
    "gn:population":0,
    "gn:timezone":"Europe/Istanbul",
    "iso:country":"TR",
    "wof:name":"Olcekli",
    "wof:placetype":"locality"
},
  "geometry": {"coordinates":[37.83333,39.45],"type":"Point"}
}