{
  "type": "Feature",
  "properties": {
    "gn:admin1_code":"5.0",
    "gn:asciiname":"Geydogan",
    "gn:country_code":"TR",
    "gn:dem":414,
    "gn:feature_class":"P",
    "gn:feature_code":"PPL",
    "gn:name":"Geydo\u011fan",
    "gn:population":0,
    "gn:timezone":"Europe/Istanbul",
    "iso:country":"TR",
    "name:und_x_variant":[
        "Geyd\u00fc\u011fen",
        "Geydo\u011fan"
    ],
    "wof:name":"Geydogan",
    "wof:placetype":"locality"
},
  "geometry": {"coordinates":[36.24191,40.71092],"type":"Point"}
}