{
  "type": "Feature",
  "properties": {
    "gn:admin1_code":"69.0",
    "gn:asciiname":"Gulacar",
    "gn:country_code":"TR",
    "gn:dem":1461,
    "gn:feature_class":"P",
    "gn:feature_code":"PPL",
    "gn:name":"G\u00fcla\u00e7ar",
    "gn:population":0,
    "gn:timezone":"Europe/Istanbul",
    "iso:country":"TR",
    "name:tur_x_preferred":[
        "G\u00fcla\u00e7ar"
    ],
    "name:und_x_variant":[
        "B\u00fclb\u00fclo\u011fluhni",
        "B\u00fclb\u00fclo\u011fluhan\u0131",
        "G\u00fclacar"
    ],
    "wof:name":"Gulacar",
    "wof:placetype":"locality"
},
  "geometry": {"coordinates":[39.23645,40.39128],"type":"Point"}
}