{
  "type": "Feature",
  "properties": {
    "gn:admin1_code":"63",
    "gn:asciiname":"Buyuktepe",
    "gn:country_code":"TR",
    "gn:dem":960,
    "gn:feature_class":"P",
    "gn:feature_code":"PPL",
    "gn:name":"B\u00fcy\u00fcktepe",
    "gn:population":0,
    "gn:timezone":"Europe/Istanbul",
    "iso:country":"TR",
    "name:und_x_variant":[
        "B\u00fcy\u00fcktil",
        "B\u00fcy\u00fcktepe"
    ],
    "wof:name":"Buyuktepe",
    "wof:placetype":"locality"
},
  "geometry": {"coordinates":[39.18639,37.98333],"type":"Point"}
}