{
  "type": "Feature",
  "properties": {
    "gn:admin1_code":"64",
    "gn:asciiname":"Muratli",
    "gn:country_code":"TR",
    "gn:dem":1123,
    "gn:feature_class":"P",
    "gn:feature_code":"PPL",
    "gn:name":"Muratl\u0131",
    "gn:population":0,
    "gn:timezone":"Europe/Istanbul",
    "iso:country":"TR",
    "name:und_x_variant":[
        "Muratl\u0131",
        "M\u00fcratl\u0131"
    ],
    "wof:name":"Muratli",
    "wof:placetype":"locality"
},
  "geometry": {"coordinates":[29.74278,38.80889000000001],"type":"Point"}
}