{
  "type": "Feature",
  "properties": {
    "gn:admin1_code":"54.0",
    "gn:asciiname":"Kadikoy",
    "gn:country_code":"TR",
    "gn:dem":17,
    "gn:feature_class":"P",
    "gn:feature_code":"PPL",
    "gn:name":"Kad\u0131k\u00f6y",
    "gn:population":0,
    "gn:timezone":"Europe/Istanbul",
    "iso:country":"TR",
    "name:tur_x_preferred":[
        "Kad\u0131k\u00f6y"
    ],
    "name:und_x_variant":[
        "A\u015fa\u011f\u0131 Mahalle",
        "A\u015fa\u011f\u0131 Kocaali"
    ],
    "wof:name":"Kadikoy",
    "wof:placetype":"locality"
},
  "geometry": {"coordinates":[30.88333,41.06667],"type":"Point"}
}