{
  "type": "Feature",
  "properties": {
    "gn:admin1_code":"83",
    "gn:asciiname":"Kazikli",
    "gn:country_code":"TR",
    "gn:dem":466,
    "gn:feature_class":"P",
    "gn:feature_code":"PPL",
    "gn:name":"Kaz\u0131kl\u0131",
    "gn:population":0,
    "gn:timezone":"Europe/Istanbul",
    "iso:country":"TR",
    "wof:name":"Kazikli",
    "wof:placetype":"locality"
},
  "geometry": {"coordinates":[36.70278,36.84056],"type":"Point"}
}