{
  "type": "Feature",
  "properties": {
    "gn:admin1_code":"68.0",
    "gn:asciiname":"Cendere",
    "gn:country_code":"TR",
    "gn:dem":937,
    "gn:feature_class":"P",
    "gn:feature_code":"PPL",
    "gn:name":"Cendere",
    "gn:population":0,
    "gn:timezone":"Europe/Istanbul",
    "iso:country":"TR",
    "name:und_x_variant":[
        "Kendere",
        "Cendere"
    ],
    "wof:name":"Cendere",
    "wof:placetype":"locality"
},
  "geometry": {"coordinates":[31.12261,40.19336],"type":"Point"}
}