{
  "type": "Feature",
  "properties": {
    "gn:admin1_code":"68.0",
    "gn:asciiname":"Yildirimyaglica",
    "gn:country_code":"TR",
    "gn:dem":1465,
    "gn:feature_class":"P",
    "gn:feature_code":"PPL",
    "gn:name":"Y\u0131ld\u0131r\u0131mya\u011fl\u0131ca",
    "gn:population":0,
    "gn:timezone":"Europe/Istanbul",
    "iso:country":"TR",
    "wof:name":"Yildirimyaglica",
    "wof:placetype":"locality"
},
  "geometry": {"coordinates":[32.84008,40.45927],"type":"Point"}
}