{
  "type": "Feature",
  "properties": {
    "iso:country":"TR",
    "name:ceb_x_preferred":[
        "Hamidiye"
    ],
    "name:deu_x_preferred":[
        "Hamidiye"
    ],
    "name:fra_x_preferred":[
        "Hamidiye"
    ],
    "name:nld_x_preferred":[
        "Hamidiye"
    ],
    "name:rus_x_preferred":[
        "\u0425\u0430\u043c\u0438\u0434\u0438\u0435"
    ],
    "name:tur_x_preferred":[
        "Hamidiye"
    ],
    "name:ukr_x_preferred":[
        "\u0425\u0430\u043c\u0456\u0434\u0456\u0454"
    ],
    "name:und_x_preferred":[
        "Hamidiye"
    ],
    "name:unk_x_variant":[
        "So\u011flu",
        "Hamidiye"
    ],
    "qs:gn_adm0_cc":"TR",
    "qs:gn_fcode":"PPL",
    "qs:gn_local":306571,
    "qs:gn_nam_loc":"Konya",
    "qs:gn_namadm1":"78",
    "qs:gn_name":"Hamidiye",
    "qs:local_max":370,
    "qs:local_sum":714,
    "qs:localhoods":5,
    "qs:name":"Hamidiye",
    "qs:name_adm0":"Turkey",
    "qs:name_adm1":"Konya",
    "qs:name_adm2":"Sel\u00e7uklu",
    "qs:name_local":"Konya",
    "qs:photo_max":168,
    "qs:photo_sum":184,
    "qs:placetype":"Suburb",
    "qs:quad_count":4,
    "qs:woe_adm0":23424969,
    "qs:woe_adm1":2347321,
    "qs:woe_adm2":29390742,
    "qs:woe_lau":0,
    "qs:woe_local":2344210,
    "qs:woe_ver":"7.10.0",
    "wd:wordcount":69,
    "wof:lang":[
        "unk"
    ],
    "wof:name":"Hamidiye",
    "wof:placetype":"neighbourhood"
},
  "geometry": {"coordinates":[32.490648,37.873593],"type":"Point"}
}