{
  "type": "Feature",
  "properties": {
    "gn:admin1_code":"63",
    "gn:asciiname":"Ergunkoy",
    "gn:country_code":"TR",
    "gn:dem":721,
    "gn:feature_class":"P",
    "gn:feature_code":"PPL",
    "gn:name":"Erg\u00fcnk\u00f6y",
    "gn:population":0,
    "gn:timezone":"Europe/Istanbul",
    "iso:country":"TR",
    "name:und_x_variant":[
        "Erg\u00fcnk\u00f6y",
        "Zeyto\u011flu"
    ],
    "wof:name":"Ergunkoy",
    "wof:placetype":"locality"
},
  "geometry": {"coordinates":[38.477,37.18037],"type":"Point"}
}