{
  "type": "Feature",
  "properties": {
    "gn:admin1_code":"83.0",
    "gn:asciiname":"Saritepe",
    "gn:country_code":"TR",
    "gn:dem":587,
    "gn:feature_class":"P",
    "gn:feature_code":"PPL",
    "gn:name":"Sar\u0131tepe",
    "gn:population":0,
    "gn:timezone":"Europe/Istanbul",
    "iso:country":"TR",
    "name:tur_x_preferred":[
        "Sar\u0131tepe"
    ],
    "wof:name":"Saritepe",
    "wof:placetype":"locality"
},
  "geometry": {"coordinates":[37.83623,37.39331],"type":"Point"}
}