{
  "type": "Feature",
  "properties": {
    "gn:admin1_code":"65",
    "gn:asciiname":"Arikan",
    "gn:country_code":"TR",
    "gn:dem":1945,
    "gn:feature_class":"P",
    "gn:feature_code":"PPL",
    "gn:name":"Ar\u0131kan",
    "gn:population":0,
    "gn:timezone":"Europe/Istanbul",
    "iso:country":"TR",
    "name:ceb_x_preferred":[
        "\u0100r\u012bk\u0101n"
    ],
    "name:fas_x_preferred":[
        "\u0627\u0631\u06cc\u06a9\u0627\u0646"
    ],
    "name:msa_x_preferred":[
        "Arikan"
    ],
    "name:swe_x_preferred":[
        "\u0100r\u012bk\u0101n"
    ],
    "wof:name":"Arikan",
    "wof:placetype":"locality"
},
  "geometry": {"coordinates":[43.55,38.38333],"type":"Point"}
}