{
  "type": "Feature",
  "properties": {
    "gn:country":"TR",
    "gn:fcode":"PPL",
    "gn:pop":521,
    "iso:country":"TR",
    "name:rus_x_preferred":[
        "Tel\u2019shiriras"
    ],
    "name:tur_x_preferred":[
        "Elbeyli"
    ],
    "name:unk_x_variant":[
        "Tel\u015firiras"
    ],
    "qs:name":"Elbeyli",
    "qs:photos_9r":0,
    "qs:photos_sr":0,
    "qs:pop_sr":"2",
    "wd:wordcount":116,
    "wof:name":"Elbeyli",
    "wof:placetype":"locality",
    "wof:population":521
},
  "geometry": {"coordinates":[40.64306,37.18528],"type":"Point"}
}