{
  "type": "Feature",
  "properties": {
    "gn:country":"TR",
    "gn:fcode":"PPL",
    "gn:population":521,
    "iso:country":"TR",
    "name:aze_x_preferred":[
        "Elbeyli"
    ],
    "name:ceb_x_preferred":[
        "Elbeyli \u0130l\u00e7esi"
    ],
    "name:deu_x_preferred":[
        "Elbeyli"
    ],
    "name:epo_x_preferred":[
        "Elbeyli"
    ],
    "name:fra_x_preferred":[
        "Elbeyli"
    ],
    "name:kur_x_preferred":[
        "Eliy\u00ea Mentar\u00ea"
    ],
    "name:mrj_x_preferred":[
        "\u042d\u043b\u0431\u0435\u0439\u043b\u0438"
    ],
    "name:msa_x_preferred":[
        "Elbeyli"
    ],
    "name:nor_x_preferred":[
        "Elbeyli"
    ],
    "name:pnb_x_preferred":[
        "\u0636\u0644\u0639 \u0627\u0644\u0628\u06cc\u0644\u06cc"
    ],
    "name:rus_x_preferred":[
        "Tel\u2019shiriras"
    ],
    "name:rus_x_variant":[
        "\u042d\u043b\u0431\u0435\u0439\u043b\u0438"
    ],
    "name:sco_x_preferred":[
        "Elbeyli"
    ],
    "name:swa_x_preferred":[
        "Elbeyli"
    ],
    "name:tur_x_preferred":[
        "Elbeyli"
    ],
    "name:und_x_variant":[
        "Tel\u015firiras"
    ],
    "name:urd_x_preferred":[
        "\u0627\u0644 \u0628\u06d2\u0644\u06cc"
    ],
    "name:vie_x_preferred":[
        "Elbeyli"
    ],
    "qs:name":"Elbeyli",
    "qs:photos_9r":0,
    "qs:photos_sr":0,
    "qs:pop_sr":"2",
    "wd:wordcount":116,
    "wof:name":"Elbeyli",
    "wof:placetype":"locality",
    "wof:population":521
},
  "geometry": {"coordinates":[40.64306,37.18528],"type":"Point"}
}