{
  "type": "Feature",
  "properties": {
    "gn:admin1_code":"07",
    "gn:asciiname":"Dudenkoy",
    "gn:country_code":"TR",
    "gn:dem":1034,
    "gn:feature_class":"P",
    "gn:feature_code":"PPL",
    "gn:name":"D\u00fcdenk\u00f6y",
    "gn:population":0,
    "gn:timezone":"Europe/Istanbul",
    "iso:country":"TR",
    "name:und_x_variant":[
        "D\u00fcden",
        "D\u00fcdenk\u00f6y"
    ],
    "wof:name":"Dudenkoy",
    "wof:placetype":"locality"
},
  "geometry": {"coordinates":[29.91187,36.67773],"type":"Point"}
}