{
  "type": "Feature",
  "properties": {
    "gn:admin1_code":"57.0",
    "gn:asciiname":"Boyabuku",
    "gn:country_code":"TR",
    "gn:dem":391,
    "gn:feature_class":"P",
    "gn:feature_code":"PPL",
    "gn:name":"Boyab\u00fck\u00fc",
    "gn:population":0,
    "gn:timezone":"Europe/Istanbul",
    "iso:country":"TR",
    "name:und_x_variant":[
        "Boyab\u00fck\u00fc K\u00f6y\u00fc",
        "Boyab\u00fck\u00fc"
    ],
    "wof:name":"Boyabuku",
    "wof:placetype":"locality"
},
  "geometry": {"coordinates":[35.25626,41.2844],"type":"Point"}
}