{
  "type": "Feature",
  "properties": {
    "gn:admin1_code":"20",
    "gn:asciiname":"Bekirli",
    "gn:country_code":"TR",
    "gn:dem":818,
    "gn:feature_class":"P",
    "gn:feature_code":"PPL",
    "gn:name":"Bekirli",
    "gn:population":0,
    "gn:timezone":"Europe/Istanbul",
    "iso:country":"TR",
    "wof:name":"Bekirli",
    "wof:placetype":"locality"
},
  "geometry": {"coordinates":[29.77972,38.19361],"type":"Point"}
}