{
  "type": "Feature",
  "properties": {
    "gn:admin1_code":"71.0",
    "gn:asciiname":"Adakale",
    "gn:country_code":"TR",
    "gn:dem":1017,
    "gn:feature_class":"P",
    "gn:feature_code":"PPL",
    "gn:name":"Adakale",
    "gn:population":0,
    "gn:timezone":"Europe/Istanbul",
    "iso:country":"TR",
    "name:und_x_variant":[
        "Ada Kale",
        "Adakale"
    ],
    "wof:name":"Adakale",
    "wof:placetype":"locality"
},
  "geometry": {"coordinates":[33.07761,37.51024],"type":"Point"}
}