{
  "type": "Feature",
  "properties": {
    "gn:admin1_code":"31.0",
    "gn:asciiname":"Akcami",
    "gn:cc2":"TR",
    "gn:country_code":"TR",
    "gn:dem":181,
    "gn:feature_class":"P",
    "gn:feature_code":"PPL",
    "gn:name":"Ak\u00e7am\u0131",
    "gn:population":0,
    "gn:timezone":"Europe/Istanbul",
    "iso:country":"TR",
    "name:und_x_variant":[
        "Akdzhami",
        "Ak\u00e7am\u0131"
    ],
    "wof:name":"Akcami",
    "wof:placetype":"locality"
},
  "geometry": {"coordinates":[36.23667,36.73861],"type":"Point"}
}