{
  "type": "Feature",
  "properties": {
    "gn:admin1_code":"58.0",
    "gn:asciiname":"Basekin",
    "gn:country_code":"TR",
    "gn:dem":1564,
    "gn:feature_class":"P",
    "gn:feature_code":"PPL",
    "gn:name":"Ba\u015fekin",
    "gn:population":0,
    "gn:timezone":"Europe/Istanbul",
    "iso:country":"TR",
    "name:und_x_variant":[
        "Be\u015fekin",
        "Ba\u015fekin"
    ],
    "wof:name":"Basekin",
    "wof:placetype":"locality"
},
  "geometry": {"coordinates":[37.42896,40.12804000000001],"type":"Point"}
}