{
  "type": "Feature",
  "properties": {
    "gn:admin1_code":"25",
    "gn:asciiname":"Karasu",
    "gn:country_code":"TR",
    "gn:dem":1560,
    "gn:feature_class":"P",
    "gn:feature_code":"PPL",
    "gn:name":"Karasu",
    "gn:population":0,
    "gn:timezone":"Europe/Istanbul",
    "iso:country":"TR",
    "name:tur_x_preferred":[
        "Karasu"
    ],
    "wof:name":"Karasu",
    "wof:placetype":"locality"
},
  "geometry": {"coordinates":[40.3569,39.93207],"type":"Point"}
}