{
  "type": "Feature",
  "properties": {
    "gn:admin1_code":"81",
    "gn:asciiname":"Cagsirli",
    "gn:country_code":"TR",
    "gn:dem":6,
    "gn:feature_class":"P",
    "gn:feature_code":"PPL",
    "gn:name":"\u00c7a\u011f\u015f\u0131rl\u0131",
    "gn:population":0,
    "gn:timezone":"Europe/Istanbul",
    "iso:country":"TR",
    "name:deu_x_preferred":[
        "\u00c7ak\u015f\u0131rl\u0131"
    ],
    "name:msa_x_preferred":[
        "\u00c7ak\u015f\u0131rl\u0131"
    ],
    "name:tur_x_preferred":[
        "\u00c7a\u011f\u015f\u0131rl\u0131"
    ],
    "name:und_x_variant":[
        "\u00c7ak\u015f\u0131rl\u0131",
        "\u00c7a\u011f\u015f\u0131rl\u0131"
    ],
    "name:vie_x_preferred":[
        "\u00c7a\u011f\u015f\u0131rl\u0131"
    ],
    "wof:name":"Cagsirli",
    "wof:placetype":"locality"
},
  "geometry": {"coordinates":[35.41757,36.7452],"type":"Point"}
}