{
  "type": "Feature",
  "properties": {
    "gn:admin1_code":"8.0",
    "gn:asciiname":"Gigaziler",
    "gn:country_code":"TR",
    "gn:dem":1385,
    "gn:feature_class":"P",
    "gn:feature_code":"PPL",
    "gn:name":"Gigaziler",
    "gn:population":0,
    "gn:timezone":"Europe/Istanbul",
    "iso:country":"TR",
    "wof:name":"Gigaziler",
    "wof:placetype":"locality"
},
  "geometry": {"coordinates":[42.22098,41.3441],"type":"Point"}
}