{
  "type": "Feature",
  "properties": {
    "gn:admin1_code":"58.0",
    "gn:asciiname":"Catakli",
    "gn:country_code":"TR",
    "gn:dem":1215,
    "gn:feature_class":"P",
    "gn:feature_code":"PPL",
    "gn:name":"\u00c7atakl\u0131",
    "gn:population":0,
    "gn:timezone":"Europe/Istanbul",
    "iso:country":"TR",
    "name:eng_x_preferred":[
        "\u00c7atakl\u0131"
    ],
    "name:rus_x_preferred":[
        "\u041a\u0438\u043d\u0434\u0438\u043a"
    ],
    "name:und_x_variant":[
        "Kindik",
        "\u00c7atak"
    ],
    "wof:name":"Catakli",
    "wof:placetype":"locality"
},
  "geometry": {"coordinates":[38.5475,40.07556],"type":"Point"}
}