{
  "type": "Feature",
  "properties": {
    "gn:admin1_code":"80.0",
    "gn:asciiname":"Derav",
    "gn:country_code":"TR",
    "gn:dem":1190,
    "gn:feature_class":"P",
    "gn:feature_code":"PPL",
    "gn:name":"Derav",
    "gn:population":0,
    "gn:timezone":"Europe/Istanbul",
    "iso:country":"TR",
    "name:und_x_variant":[
        "Dirivan"
    ],
    "wof:name":"Derav",
    "wof:placetype":"locality"
},
  "geometry": {"coordinates":[43.11907,37.51667],"type":"Point"}
}