{
  "type": "Feature",
  "properties": {
    "gn:admin1_code":"80.0",
    "gn:asciiname":"Calgitahti",
    "gn:country_code":"TR",
    "gn:dem":741,
    "gn:feature_class":"P",
    "gn:feature_code":"PPL",
    "gn:name":"\u00c7alg\u0131taht\u0131",
    "gn:population":0,
    "gn:timezone":"Europe/Istanbul",
    "iso:country":"TR",
    "name:tur_x_preferred":[
        "\u00c7alg\u0131taht\u0131"
    ],
    "wof:name":"Calgitahti",
    "wof:placetype":"locality"
},
  "geometry": {"coordinates":[41.71331,37.40657],"type":"Point"}
}