{
  "type": "Feature",
  "properties": {
    "gn:admin1_code":"35",
    "gn:asciiname":"Ovakent",
    "gn:country_code":"TR",
    "gn:dem":198,
    "gn:feature_class":"P",
    "gn:feature_code":"PPLA3",
    "gn:name":"Ovakent",
    "gn:population":0,
    "gn:timezone":"Europe/Istanbul",
    "iso:country":"TR",
    "name:und_x_variant":[
        "Abagide",
        "Adagide",
        "Ovakent"
    ],
    "wof:name":"Ovakent",
    "wof:placetype":"locality"
},
  "geometry": {"coordinates":[28.02111,38.10722],"type":"Point"}
}