{
  "type": "Feature",
  "properties": {
    "gn:admin1_code":"20",
    "gn:asciiname":"Camlibel",
    "gn:country_code":"TR",
    "gn:dem":1140,
    "gn:feature_class":"P",
    "gn:feature_code":"PPL",
    "gn:name":"\u00c7aml\u0131bel",
    "gn:population":0,
    "gn:timezone":"Europe/Istanbul",
    "iso:country":"TR",
    "name:tur_x_preferred":[
        "\u00c7aml\u0131bel"
    ],
    "name:tur_x_variant":[
        "Sakals\u0131zlar"
    ],
    "wof:name":"Camlibel",
    "wof:placetype":"locality"
},
  "geometry": {"coordinates":[29.35622,37.1871],"type":"Point"}
}