{
  "type": "Feature",
  "properties": {
    "gn:admin1_code":"63",
    "gn:asciiname":"Harapnur",
    "gn:cc2":"TR",
    "gn:country_code":"TR",
    "gn:dem":525,
    "gn:feature_class":"P",
    "gn:feature_code":"PPL",
    "gn:name":"Harapnur",
    "gn:population":0,
    "gn:timezone":"Europe/Istanbul",
    "iso:country":"TR",
    "name:und_x_variant":[
        "Kharapnur",
        "Haranbur",
        "Harapnur"
    ],
    "wof:name":"Harapnur",
    "wof:placetype":"locality"
},
  "geometry": {"coordinates":[38.6175,36.91028],"type":"Point"}
}