{
  "type": "Feature",
  "properties": {
    "gn:admin1_code":"70",
    "gn:asciiname":"Isikli",
    "gn:country_code":"TR",
    "gn:dem":1597,
    "gn:feature_class":"P",
    "gn:feature_code":"PPL",
    "gn:name":"I\u015f\u0131kl\u0131",
    "gn:population":0,
    "gn:timezone":"Europe/Istanbul",
    "iso:country":"TR",
    "name:tur_x_preferred":[
        "I\u015f\u0131kl\u0131"
    ],
    "wof:name":"Isikli",
    "wof:placetype":"locality"
},
  "geometry": {"coordinates":[43.70355,37.25614],"type":"Point"}
}