{
  "type": "Feature",
  "properties": {
    "gn:admin1_code":"52.0",
    "gn:asciiname":"Yemisken",
    "gn:country_code":"TR",
    "gn:dem":663,
    "gn:feature_class":"P",
    "gn:feature_code":"PPL",
    "gn:name":"Yemi\u015fken",
    "gn:population":0,
    "gn:timezone":"Europe/Istanbul",
    "iso:country":"TR",
    "wof:name":"Yemisken",
    "wof:placetype":"locality"
},
  "geometry": {"coordinates":[37.27792,40.90494],"type":"Point"}
}