{
  "type": "Feature",
  "properties": {
    "gn:admin1_code":"58.0",
    "gn:asciiname":"Abana",
    "gn:country_code":"TR",
    "gn:dem":1222,
    "gn:feature_class":"P",
    "gn:feature_code":"PPL",
    "gn:name":"Abana",
    "gn:population":0,
    "gn:timezone":"Europe/Istanbul",
    "iso:country":"TR",
    "name:ceb_x_preferred":[
        "Abana"
    ],
    "name:deu_x_preferred":[
        "Abana"
    ],
    "name:fra_x_preferred":[
        "Abana"
    ],
    "name:hye_x_preferred":[
        "\u0531\u0562\u0561\u0576\u0561"
    ],
    "name:nld_x_preferred":[
        "Abana"
    ],
    "name:slv_x_preferred":[
        "Abana"
    ],
    "name:swe_x_preferred":[
        "Abana"
    ],
    "name:und_x_variant":[
        "G\u00f6ll\u00fcce",
        "G\u00fcll\u00fcce"
    ],
    "wof:name":"Abana",
    "wof:placetype":"locality"
},
  "geometry": {"coordinates":[38.49726,40.07905],"type":"Point"}
}