{
  "type": "Feature",
  "properties": {
    "gn:admin1_code":"5.0",
    "gn:asciiname":"Fadara",
    "gn:country_code":"TR",
    "gn:dem":804,
    "gn:feature_class":"P",
    "gn:feature_code":"PPL",
    "gn:name":"Fadara",
    "gn:population":0,
    "gn:timezone":"Europe/Istanbul",
    "iso:country":"TR",
    "name:und_x_variant":[
        "Ard\u0131\u00e7\u00f6n\u00fc"
    ],
    "wof:name":"Fadara",
    "wof:placetype":"locality"
},
  "geometry": {"coordinates":[36.34886,40.65719],"type":"Point"}
}