{
  "type": "Feature",
  "properties": {
    "gn:admin1_code":"48",
    "gn:asciiname":"Murucak",
    "gn:country_code":"TR",
    "gn:dem":565,
    "gn:feature_class":"P",
    "gn:feature_code":"PPL",
    "gn:name":"Murucak",
    "gn:population":0,
    "gn:timezone":"Europe/Istanbul",
    "iso:country":"TR",
    "name:tur_x_preferred":[
        "Murucak"
    ],
    "wof:name":"Murucak",
    "wof:placetype":"locality"
},
  "geometry": {"coordinates":[29.42907,36.57444],"type":"Point"}
}