{
  "type": "Feature",
  "properties": {
    "gn:admin1_code":"55.0",
    "gn:asciiname":"Doruk",
    "gn:country_code":"TR",
    "gn:dem":871,
    "gn:feature_class":"P",
    "gn:feature_code":"PPL",
    "gn:name":"Doruk",
    "gn:population":0,
    "gn:timezone":"Europe/Istanbul",
    "iso:country":"TR",
    "name:ceb_x_preferred":[
        "Doruk"
    ],
    "name:swe_x_preferred":[
        "Doruk"
    ],
    "name:tur_x_preferred":[
        "Doruk"
    ],
    "name:tur_x_variant":[
        "L\u00e2dik \u0130stasyonu"
    ],
    "wof:name":"Doruk",
    "wof:placetype":"locality"
},
  "geometry": {"coordinates":[35.86632,41.0095],"type":"Point"}
}