{
  "type": "Feature",
  "properties": {
    "gn:admin1_code":"26",
    "gn:asciiname":"Golbasi Yayalsi",
    "gn:country_code":"TR",
    "gn:dem":890,
    "gn:feature_class":"P",
    "gn:feature_code":"PPL",
    "gn:name":"G\u00f6lba\u015f\u0131 Yayals\u0131",
    "gn:population":0,
    "gn:timezone":"Europe/Istanbul",
    "iso:country":"TR",
    "wof:name":"Golbasi Yayalsi",
    "wof:placetype":"locality"
},
  "geometry": {"coordinates":[31.4554,39.11701],"type":"Point"}
}