{
  "type": "Feature",
  "properties": {
    "gn:admin1_code":"81",
    "gn:asciiname":"Dalyan",
    "gn:country_code":"TR",
    "gn:dem":3,
    "gn:feature_class":"P",
    "gn:feature_code":"PPL",
    "gn:name":"Dalyan",
    "gn:population":0,
    "gn:timezone":"Europe/Istanbul",
    "iso:country":"TR",
    "name:ara_x_preferred":[
        "\u062f\u0627\u0644\u064a\u0627\u0646"
    ],
    "name:bul_x_preferred":[
        "\u0414\u0430\u043b\u044f\u043d"
    ],
    "name:ceb_x_preferred":[
        "Dalyan"
    ],
    "name:deu_x_preferred":[
        "Dalyan"
    ],
    "name:epo_x_preferred":[
        "Dalyan"
    ],
    "name:fas_x_preferred":[
        "\u062f\u0627\u06cc\u0644\u0627\u0646"
    ],
    "name:fra_x_preferred":[
        "Dalyan"
    ],
    "name:ita_x_preferred":[
        "Dalyan"
    ],
    "name:jpn_x_preferred":[
        "\u30c0\u30eb\u30e4\u30f3"
    ],
    "name:kaz_x_preferred":[
        "\u0414\u0430\u043b\u044f\u043d"
    ],
    "name:nld_x_preferred":[
        "Dalyan"
    ],
    "name:pol_x_preferred":[
        "Dalyan"
    ],
    "name:rus_x_preferred":[
        "\u0414\u0430\u043b\u044c\u044f\u043d"
    ],
    "name:spa_x_preferred":[
        "Dalyan"
    ],
    "name:tur_x_preferred":[
        "Dalyan"
    ],
    "name:ukr_x_preferred":[
        "\u0414\u0430\u043b\u044c\u044f\u043d"
    ],
    "name:und_x_variant":[
        "Fevziyebuca\u011f\u0131",
        "Feyziye"
    ],
    "name:vie_x_preferred":[
        "Dalyan"
    ],
    "wof:name":"Dalyan",
    "wof:placetype":"locality"
},
  "geometry": {"coordinates":[35.33545,36.57497],"type":"Point"}
}