{
  "type": "Feature",
  "properties": {
    "gn:admin1_code":"81",
    "gn:asciiname":"Dalyan",
    "gn:country_code":"TR",
    "gn:dem":3,
    "gn:feature_class":"P",
    "gn:feature_code":"PPL",
    "gn:name":"Dalyan",
    "gn:population":0,
    "gn:timezone":"Europe/Istanbul",
    "iso:country":"TR",
    "name:und_x_variant":[
        "Fevziyebuca\u011f\u0131",
        "Feyziye",
        "Dalyan"
    ],
    "wof:name":"Dalyan",
    "wof:placetype":"locality"
},
  "geometry": {"coordinates":[35.33545,36.57497],"type":"Point"}
}