{
  "type": "Feature",
  "properties": {
    "gn:admin1_code":"48",
    "gn:asciiname":"Ucpinar",
    "gn:country_code":"TR",
    "gn:dem":140,
    "gn:feature_class":"P",
    "gn:feature_code":"PPL",
    "gn:name":"\u00dc\u00e7p\u0131nar",
    "gn:population":0,
    "gn:timezone":"Europe/Istanbul",
    "iso:country":"TR",
    "name:und_x_variant":[
        "U\u00e7p\u0131nark\u00f6y",
        "\u00dc\u00e7p\u0131nar"
    ],
    "wof:name":"Ucpinar",
    "wof:placetype":"locality"
},
  "geometry": {"coordinates":[27.63917,37.18652],"type":"Point"}
}