{
  "type": "Feature",
  "properties": {
    "gn:admin1_code":"14.0",
    "gn:asciiname":"Kupluce",
    "gn:country_code":"TR",
    "gn:dem":690,
    "gn:feature_class":"P",
    "gn:feature_code":"PPL",
    "gn:name":"K\u00fcpl\u00fcce",
    "gn:population":0,
    "gn:timezone":"Europe/Istanbul",
    "iso:country":"TR",
    "name:und_x_variant":[
        "K\u00fcpl\u00fcce"
    ],
    "wof:name":"Kupluce",
    "wof:placetype":"locality"
},
  "geometry": {"coordinates":[31.84998,40.85554000000001],"type":"Point"}
}