{
  "type": "Feature",
  "properties": {
    "gn:admin1_code":"60.0",
    "gn:asciiname":"Cambulak",
    "gn:country_code":"TR",
    "gn:dem":1026,
    "gn:feature_class":"P",
    "gn:feature_code":"PPL",
    "gn:name":"\u00c7ambulak",
    "gn:population":0,
    "gn:timezone":"Europe/Istanbul",
    "iso:country":"TR",
    "name:und_x_variant":[
        "Dadukda",
        "Daduhta",
        "\u00c7ambulak"
    ],
    "wof:name":"Cambulak",
    "wof:placetype":"locality"
},
  "geometry": {"coordinates":[36.96357,40.41184000000001],"type":"Point"}
}