{
  "type": "Feature",
  "properties": {
    "gn:admin1_code":"83",
    "gn:asciiname":"Tosunlu",
    "gn:country_code":"TR",
    "gn:dem":379,
    "gn:feature_class":"P",
    "gn:feature_code":"PPL",
    "gn:name":"Tosunlu",
    "gn:population":0,
    "gn:timezone":"Europe/Istanbul",
    "iso:country":"TR",
    "name:tur_x_preferred":[
        "Tosunlu"
    ],
    "name:und_x_variant":[
        "Byuyuk-Shemik",
        "B\u00fcy\u00fck\u015femik"
    ],
    "wof:name":"Tosunlu",
    "wof:placetype":"locality"
},
  "geometry": {"coordinates":[37.97056,36.90611],"type":"Point"}
}