{
  "type": "Feature",
  "properties": {
    "gn:admin1_code":"83",
    "gn:asciiname":"Gebe",
    "gn:cc2":"TR",
    "gn:country_code":"TR",
    "gn:dem":620,
    "gn:feature_class":"P",
    "gn:feature_code":"PPL",
    "gn:name":"Gebe",
    "gn:population":0,
    "gn:timezone":"Europe/Istanbul",
    "iso:country":"TR",
    "name:ara_x_preferred":[
        "\u062c\u064a\u0628\u064a"
    ],
    "name:ceb_x_preferred":[
        "Pulau Gebe"
    ],
    "name:fra_x_preferred":[
        "Gebe"
    ],
    "name:ind_x_preferred":[
        "Pulau Gebe"
    ],
    "name:ita_x_preferred":[
        "Gebe"
    ],
    "name:jav_x_preferred":[
        "Gebe"
    ],
    "name:msa_x_preferred":[
        "Gebe"
    ],
    "name:nld_x_preferred":[
        "Gebe"
    ],
    "name:pol_x_preferred":[
        "Gebe"
    ],
    "name:swe_x_preferred":[
        "Pulau Gebe"
    ],
    "name:und_x_variant":[
        "Kebe",
        "Gebe Mah",
        "Gebe"
    ],
    "wof:name":"Gebe",
    "wof:placetype":"locality"
},
  "geometry": {"coordinates":[37.45,36.81667],"type":"Point"}
}