{
  "type": "Feature",
  "properties": {
    "gn:admin1_code":"0.0",
    "gn:asciiname":"Seyitali",
    "gn:country_code":"TR",
    "gn:dem":1665,
    "gn:feature_class":"P",
    "gn:feature_code":"PPL",
    "gn:name":"Seyitali",
    "gn:population":0,
    "gn:timezone":"Europe/Istanbul",
    "iso:country":"TR",
    "wof:name":"Seyitali",
    "wof:placetype":"locality"
},
  "geometry": {"coordinates":[39.23333,40.73333],"type":"Point"}
}