{
  "type": "Feature",
  "properties": {
    "gn:admin1_code":"23",
    "gn:asciiname":"Gokbelen",
    "gn:country_code":"TR",
    "gn:dem":1413,
    "gn:feature_class":"P",
    "gn:feature_code":"PPL",
    "gn:name":"G\u00f6kbelen",
    "gn:population":0,
    "gn:timezone":"Europe/Istanbul",
    "iso:country":"TR",
    "name:tur_x_preferred":[
        "G\u00f6kbelen"
    ],
    "wof:name":"Gokbelen",
    "wof:placetype":"locality"
},
  "geometry": {"coordinates":[38.6872,38.70073],"type":"Point"}
}