{
  "type": "Feature",
  "properties": {
    "gn:admin1_code":"46",
    "gn:asciiname":"Yesilkoy",
    "gn:country_code":"TR",
    "gn:dem":1370,
    "gn:feature_class":"P",
    "gn:feature_code":"PPL",
    "gn:name":"Ye\u015filk\u00f6y",
    "gn:population":0,
    "gn:timezone":"Europe/Istanbul",
    "iso:country":"TR",
    "name:und_x_variant":[
        "Sinse",
        "Sisne",
        "Ye\u015filk\u00f6y"
    ],
    "wof:name":"Yesilkoy",
    "wof:placetype":"locality"
},
  "geometry": {"coordinates":[36.732,37.99882],"type":"Point"}
}