{
  "type": "Feature",
  "properties": {
    "gn:admin1_code":"87",
    "gn:asciiname":"Bedil",
    "gn:country_code":"TR",
    "gn:dem":140,
    "gn:feature_class":"P",
    "gn:feature_code":"PPL",
    "gn:name":"Bedil",
    "gn:population":0,
    "gn:timezone":"Europe/Istanbul",
    "iso:country":"TR",
    "wof:name":"Bedil",
    "wof:placetype":"locality"
},
  "geometry": {"coordinates":[32.29154,41.48104],"type":"Point"}
}