{
  "type": "Feature",
  "properties": {
    "gn:admin1_code":"02",
    "gn:asciiname":"Kargali",
    "gn:country_code":"TR",
    "gn:dem":647,
    "gn:feature_class":"P",
    "gn:feature_code":"PPL",
    "gn:name":"Kargal\u0131",
    "gn:population":0,
    "gn:timezone":"Europe/Istanbul",
    "iso:country":"TR",
    "wof:name":"Kargali",
    "wof:placetype":"locality"
},
  "geometry": {"coordinates":[37.81667,37.58333],"type":"Point"}
}