{
  "type": "Feature",
  "properties": {
    "gn:admin1_code":"85.0",
    "gn:asciiname":"Emirsah",
    "gn:country_code":"TR",
    "gn:dem":190,
    "gn:feature_class":"P",
    "gn:feature_code":"PPL",
    "gn:name":"Emir\u015fah",
    "gn:population":0,
    "gn:timezone":"Europe/Istanbul",
    "iso:country":"TR",
    "name:deu_x_preferred":[
        "Emir\u015fah"
    ],
    "name:diq_x_preferred":[
        "Emir\u015fah"
    ],
    "name:tur_x_preferred":[
        "Emir\u015fah"
    ],
    "name:vie_x_preferred":[
        "Emir\u015fah"
    ],
    "wof:name":"Emirsah",
    "wof:placetype":"locality"
},
  "geometry": {"coordinates":[32.23911,41.39048],"type":"Point"}
}