{
  "type": "Feature",
  "properties": {
    "gn:admin1_code":"89.0",
    "gn:asciiname":"Akoren",
    "gn:country_code":"TR",
    "gn:dem":930,
    "gn:feature_class":"P",
    "gn:feature_code":"PPL",
    "gn:name":"Ak\u00f6ren",
    "gn:population":0,
    "gn:timezone":"Europe/Istanbul",
    "iso:country":"TR",
    "name:und_x_variant":[
        "Akviran",
        "Akveren",
        "Ak\u00f6ren"
    ],
    "wof:name":"Akoren",
    "wof:placetype":"locality"
},
  "geometry": {"coordinates":[32.96966,41.4355],"type":"Point"}
}