{
  "type": "Feature",
  "properties": {
    "gn:admin1_code":"48",
    "gn:asciiname":"Dere Bogazi",
    "gn:country_code":"TR",
    "gn:dem":176,
    "gn:feature_class":"P",
    "gn:feature_code":"PPL",
    "gn:name":"Dere Bo\u011faz\u0131",
    "gn:population":0,
    "gn:timezone":"Europe/Istanbul",
    "iso:country":"TR",
    "name:tur_x_preferred":[
        "Dere Bo\u011faz\u0131"
    ],
    "wof:name":"Dere Bogazi",
    "wof:placetype":"locality"
},
  "geometry": {"coordinates":[29.23728,36.43231],"type":"Point"}
}