{
  "type": "Feature",
  "properties": {
    "gn:admin1_code":"65.0",
    "gn:asciiname":"Yayiktas",
    "gn:country_code":"TR",
    "gn:dem":1793,
    "gn:feature_class":"P",
    "gn:feature_code":"PPL",
    "gn:name":"Yay\u0131kta\u015f",
    "gn:population":0,
    "gn:timezone":"Europe/Istanbul",
    "iso:country":"TR",
    "name:tur_x_preferred":[
        "Yay\u0131kta\u015f"
    ],
    "wof:name":"Yayiktas",
    "wof:placetype":"locality"
},
  "geometry": {"coordinates":[43.24378,39.01566],"type":"Point"}
}