{
  "type": "Feature",
  "properties": {
    "gn:admin1_code":"78",
    "gn:asciiname":"Suduragi",
    "gn:country_code":"TR",
    "gn:dem":1017,
    "gn:feature_class":"P",
    "gn:feature_code":"PPL",
    "gn:name":"Sudura\u011f\u0131",
    "gn:population":0,
    "gn:timezone":"Europe/Istanbul",
    "iso:country":"TR",
    "name:und_x_variant":[
        "Sidrova",
        "Sudura\u011f\u0131"
    ],
    "wof:name":"Suduragi",
    "wof:placetype":"locality"
},
  "geometry": {"coordinates":[33.36675,37.28756],"type":"Point"}
}