{
  "type": "Feature",
  "properties": {
    "gn:admin1_code":"55.0",
    "gn:asciiname":"Koldere",
    "gn:cc2":"TR",
    "gn:country_code":"TR",
    "gn:dem":120,
    "gn:feature_class":"P",
    "gn:feature_code":"PPL",
    "gn:name":"Koldere",
    "gn:population":0,
    "gn:timezone":"Europe/Istanbul",
    "iso:country":"TR",
    "name:und_x_variant":[
        "Koldere K\u00f6y\u00fc",
        "Koldere"
    ],
    "wof:name":"Koldere",
    "wof:placetype":"locality"
},
  "geometry": {"coordinates":[36.59861,41.10167],"type":"Point"}
}