{
  "type": "Feature",
  "properties": {
    "gn:admin1_code":"68.0",
    "gn:asciiname":"Dogandere",
    "gn:country_code":"TR",
    "gn:dem":825,
    "gn:feature_class":"P",
    "gn:feature_code":"PPL",
    "gn:name":"Do\u011fandere",
    "gn:population":0,
    "gn:timezone":"Europe/Istanbul",
    "iso:country":"TR",
    "name:und_x_variant":[
        "Derehisar",
        "Do\u011fanderesi",
        "Do\u011fandere",
        "Do\u011fanca"
    ],
    "wof:name":"Dogandere",
    "wof:placetype":"locality"
},
  "geometry": {"coordinates":[31.28638,40.30204000000001],"type":"Point"}
}