{
  "type": "Feature",
  "properties": {
    "gn:admin1_code":"38",
    "gn:asciiname":"Kiremit",
    "gn:country_code":"TR",
    "gn:dem":1512,
    "gn:feature_class":"P",
    "gn:feature_code":"PPL",
    "gn:name":"Kiremit",
    "gn:population":0,
    "gn:timezone":"Europe/Istanbul",
    "iso:country":"TR",
    "wof:name":"Kiremit",
    "wof:placetype":"locality"
},
  "geometry": {"coordinates":[35.63333,38.43333],"type":"Point"}
}