{
  "type": "Feature",
  "properties": {
    "gn:admin1_code":"71",
    "gn:asciiname":"Sazgecit",
    "gn:country_code":"TR",
    "gn:dem":1015,
    "gn:feature_class":"P",
    "gn:feature_code":"PPL",
    "gn:name":"Sazge\u00e7it",
    "gn:population":0,
    "gn:timezone":"Europe/Istanbul",
    "iso:country":"TR",
    "name:und_x_variant":[
        "Hortu",
        "Sazge\u00e7it"
    ],
    "wof:name":"Sazgecit",
    "wof:placetype":"locality"
},
  "geometry": {"coordinates":[33.93745,37.59302],"type":"Point"}
}