{
  "type": "Feature",
  "properties": {
    "gn:admin1_code":"68.0",
    "gn:asciiname":"Karacakaya",
    "gn:country_code":"TR",
    "gn:dem":1102,
    "gn:feature_class":"P",
    "gn:feature_code":"PPL",
    "gn:name":"Karacakaya",
    "gn:population":0,
    "gn:timezone":"Europe/Istanbul",
    "iso:country":"TR",
    "wof:name":"Karacakaya",
    "wof:placetype":"locality"
},
  "geometry": {"coordinates":[32.69926,40.05253],"type":"Point"}
}