{
  "type": "Feature",
  "properties": {
    "gn:admin1_code":"31",
    "gn:asciiname":"Kazkeliisk",
    "gn:country_code":"TR",
    "gn:dem":82,
    "gn:feature_class":"P",
    "gn:feature_code":"PPL",
    "gn:name":"Kazkeliisk",
    "gn:population":0,
    "gn:timezone":"Europe/Istanbul",
    "iso:country":"TR",
    "name:tur_x_preferred":[
        "Kazkeliisk"
    ],
    "wof:name":"Kazkeliisk",
    "wof:placetype":"locality"
},
  "geometry": {"coordinates":[36.3649,36.39983],"type":"Point"}
}