{
  "type": "Feature",
  "properties": {
    "gn:admin1_code":"37",
    "gn:asciiname":"Haliloba",
    "gn:country_code":"TR",
    "gn:dem":764,
    "gn:feature_class":"P",
    "gn:feature_code":"PPL",
    "gn:name":"Haliloba",
    "gn:population":0,
    "gn:timezone":"Europe/Istanbul",
    "iso:country":"TR",
    "wof:name":"Haliloba",
    "wof:placetype":"locality"
},
  "geometry": {"coordinates":[33.25585,41.19714000000001],"type":"Point"}
}