{
  "type": "Feature",
  "properties": {
    "gn:admin1_code":"43",
    "gn:asciiname":"Durabey",
    "gn:country_code":"TR",
    "gn:dem":948,
    "gn:feature_class":"P",
    "gn:feature_code":"PPL",
    "gn:name":"Durabey",
    "gn:population":0,
    "gn:timezone":"Europe/Istanbul",
    "iso:country":"TR",
    "name:tur_x_preferred":[
        "Durabey"
    ],
    "wof:name":"Durabey",
    "wof:placetype":"locality"
},
  "geometry": {"coordinates":[29.62938,39.81894000000001],"type":"Point"}
}