{
  "type": "Feature",
  "properties": {
    "gn:admin1_code":"53.0",
    "gn:asciiname":"Bahattinpasa",
    "gn:country_code":"TR",
    "gn:dem":189,
    "gn:feature_class":"P",
    "gn:feature_code":"PPL",
    "gn:name":"Bahattinpa\u015fa",
    "gn:population":0,
    "gn:timezone":"Europe/Istanbul",
    "iso:country":"TR",
    "name:und_x_variant":[
        "Bahattinpa\u015fa",
        "Bahaettinpa\u015fa"
    ],
    "wof:name":"Bahattinpasa",
    "wof:placetype":"locality"
},
  "geometry": {"coordinates":[40.44577,41.0141],"type":"Point"}
}