{
  "type": "Feature",
  "properties": {
    "gn:admin1_code":"52.0",
    "gn:asciiname":"Coteli",
    "gn:country_code":"TR",
    "gn:dem":299,
    "gn:feature_class":"P",
    "gn:feature_code":"PPL",
    "gn:name":"\u00c7\u00f6teli",
    "gn:population":0,
    "gn:timezone":"Europe/Istanbul",
    "iso:country":"TR",
    "wof:name":"Coteli",
    "wof:placetype":"locality"
},
  "geometry": {"coordinates":[37.43678,41.04006],"type":"Point"}
}