{
  "type": "Feature",
  "properties": {
    "gn:admin1_code":"23",
    "gn:asciiname":"Yunluce",
    "gn:country_code":"TR",
    "gn:dem":851,
    "gn:feature_class":"P",
    "gn:feature_code":"PPL",
    "gn:name":"Y\u00fcnl\u00fcce",
    "gn:population":0,
    "gn:timezone":"Europe/Istanbul",
    "iso:country":"TR",
    "name:tur_x_preferred":[
        "Y\u00fcnl\u00fcce"
    ],
    "wof:name":"Yunluce",
    "wof:placetype":"locality"
},
  "geometry": {"coordinates":[39.34453,38.60394],"type":"Point"}
}