{
  "type": "Feature",
  "properties": {
    "gn:admin1_code":"54.0",
    "gn:asciiname":"Asagi Derekoy",
    "gn:country_code":"TR",
    "gn:dem":89,
    "gn:feature_class":"P",
    "gn:feature_code":"PPL",
    "gn:name":"A\u015fa\u011f\u0131 Derek\u00f6y",
    "gn:population":0,
    "gn:timezone":"Europe/Istanbul",
    "iso:country":"TR",
    "name:und_x_variant":[
        "A\u015fa\u011f\u0131 Derek\u00f6y",
        "A\u015fa\u011f\u0131dere"
    ],
    "wof:name":"Asagi Derekoy",
    "wof:placetype":"locality"
},
  "geometry": {"coordinates":[30.2706,40.75575],"type":"Point"}
}