{
  "type": "Feature",
  "properties": {
    "gn:admin1_code":"33",
    "gn:asciiname":"Yaka",
    "gn:country_code":"TR",
    "gn:dem":1009,
    "gn:feature_class":"P",
    "gn:feature_code":"PPL",
    "gn:name":"Yaka",
    "gn:population":0,
    "gn:timezone":"Europe/Istanbul",
    "iso:country":"TR",
    "name:ceb_x_preferred":[
        "Yaka"
    ],
    "name:deu_x_preferred":[
        "Yaka"
    ],
    "name:fra_x_preferred":[
        "Yaka"
    ],
    "name:hrv_x_preferred":[
        "Yaka"
    ],
    "name:ita_x_preferred":[
        "Yaka"
    ],
    "name:swe_x_preferred":[
        "Yaka"
    ],
    "wof:name":"Yaka",
    "wof:placetype":"locality"
},
  "geometry": {"coordinates":[31.30443,37.52871],"type":"Point"}
}