{
  "type": "Feature",
  "properties": {
    "gn:admin1_code":"65.0",
    "gn:asciiname":"Sigircik",
    "gn:country_code":"TR",
    "gn:dem":2360,
    "gn:feature_class":"P",
    "gn:feature_code":"PPL",
    "gn:name":"S\u0131\u011f\u0131rc\u0131k",
    "gn:population":0,
    "gn:timezone":"Europe/Istanbul",
    "iso:country":"TR",
    "name:tur_x_preferred":[
        "S\u0131\u011f\u0131rc\u0131k"
    ],
    "wof:name":"Sigircik",
    "wof:placetype":"locality"
},
  "geometry": {"coordinates":[42.90616,37.99302],"type":"Point"}
}