{
  "type": "Feature",
  "properties": {
    "gn:admin1_code":"31.0",
    "gn:asciiname":"Saraclar",
    "gn:country_code":"TR",
    "gn:dem":69,
    "gn:feature_class":"P",
    "gn:feature_code":"PPL",
    "gn:name":"Sara\u00e7lar",
    "gn:population":0,
    "gn:timezone":"Europe/Istanbul",
    "iso:country":"TR",
    "name:tur_x_preferred":[
        "Sara\u00e7lar"
    ],
    "wof:name":"Saraclar",
    "wof:placetype":"locality"
},
  "geometry": {"coordinates":[36.21837,36.69743],"type":"Point"}
}