{
  "type": "Feature",
  "properties": {
    "gn:admin1_code":"4.0",
    "gn:asciiname":"Bayiralti",
    "gn:country_code":"TR",
    "gn:dem":1736,
    "gn:feature_class":"P",
    "gn:feature_code":"PPL",
    "gn:name":"Bay\u0131ralt\u0131",
    "gn:population":0,
    "gn:timezone":"Europe/Istanbul",
    "iso:country":"TR",
    "name:tur_x_preferred":[
        "Bay\u0131ralt\u0131"
    ],
    "wof:name":"Bayiralti",
    "wof:placetype":"locality"
},
  "geometry": {"coordinates":[43.30896,39.6431],"type":"Point"}
}