{
  "type": "Feature",
  "properties": {
    "gn:admin1_code":"83",
    "gn:asciiname":"Kecebas",
    "gn:cc2":"TR",
    "gn:country_code":"TR",
    "gn:dem":635,
    "gn:feature_class":"P",
    "gn:feature_code":"PPL",
    "gn:name":"Ke\u00e7eba\u015f",
    "gn:population":0,
    "gn:timezone":"Europe/Istanbul",
    "iso:country":"TR",
    "name:und_x_variant":[
        "Ke\u00e7eba\u015f Mezraas\u0131",
        "Ke\u00e7eba\u015f"
    ],
    "wof:name":"Kecebas",
    "wof:placetype":"locality"
},
  "geometry": {"coordinates":[37.35,36.76667],"type":"Point"}
}