{
  "type": "Feature",
  "properties": {
    "gn:admin1_code":"32",
    "gn:asciiname":"Kepirli",
    "gn:country_code":"TR",
    "gn:dem":852,
    "gn:feature_class":"P",
    "gn:feature_code":"PPL",
    "gn:name":"Kepirli",
    "gn:population":0,
    "gn:timezone":"Europe/Istanbul",
    "iso:country":"TR",
    "name:ceb_x_preferred":[
        "Kepirli"
    ],
    "name:deu_x_preferred":[
        "Nurs"
    ],
    "name:kur_x_preferred":[
        "Nors"
    ],
    "name:msa_x_preferred":[
        "Kepirli"
    ],
    "name:rus_x_preferred":[
        "\u041a\u0435\u043f\u0438\u0440\u043b\u0438"
    ],
    "name:tur_x_preferred":[
        "Nurs"
    ],
    "name:und_x_variant":[
        "Kilimas",
        "Kepirli"
    ],
    "name:vie_x_preferred":[
        "Kepirli"
    ],
    "wof:name":"Kepirli",
    "wof:placetype":"locality"
},
  "geometry": {"coordinates":[34.54217,36.94786],"type":"Point"}
}