{
  "type": "Feature",
  "properties": {
    "gn:admin1_code":"16.0",
    "gn:asciiname":"Gurmuzlu",
    "gn:country_code":"TR",
    "gn:dem":548,
    "gn:feature_class":"P",
    "gn:feature_code":"PPL",
    "gn:name":"G\u00fcrm\u00fczl\u00fc",
    "gn:population":0,
    "gn:timezone":"Europe/Istanbul",
    "iso:country":"TR",
    "name:tur_x_preferred":[
        "G\u00fcrm\u00fczl\u00fc"
    ],
    "wof:name":"Gurmuzlu",
    "wof:placetype":"locality"
},
  "geometry": {"coordinates":[29.75962,40.51029000000001],"type":"Point"}
}