{
  "type": "Feature",
  "properties": {
    "gn:admin1_code":"79",
    "gn:asciiname":"Uckuyu",
    "gn:country_code":"TR",
    "gn:dem":1054,
    "gn:feature_class":"P",
    "gn:feature_code":"PPL",
    "gn:name":"\u00dc\u00e7kuyu",
    "gn:population":0,
    "gn:timezone":"Europe/Istanbul",
    "iso:country":"TR",
    "name:und_x_variant":[
        "\u00dc\u00e7kuyu",
        "\u015eedidabdall\u0131"
    ],
    "wof:name":"Uckuyu",
    "wof:placetype":"locality"
},
  "geometry": {"coordinates":[33.7022,39.63886],"type":"Point"}
}