{
  "type": "Feature",
  "properties": {
    "gn:admin1_code":"33",
    "gn:asciiname":"Delioren",
    "gn:country_code":"TR",
    "gn:dem":1344,
    "gn:feature_class":"P",
    "gn:feature_code":"PPL",
    "gn:name":"Deli\u00f6ren",
    "gn:population":0,
    "gn:timezone":"Europe/Istanbul",
    "iso:country":"TR",
    "wof:name":"Delioren",
    "wof:placetype":"locality"
},
  "geometry": {"coordinates":[31.01472,37.40111],"type":"Point"}
}