{
  "type": "Feature",
  "properties": {
    "gn:admin1_code":"54.0",
    "gn:asciiname":"Akcakaya",
    "gn:country_code":"TR",
    "gn:dem":791,
    "gn:feature_class":"P",
    "gn:feature_code":"PPL",
    "gn:name":"Ak\u00e7akaya",
    "gn:population":0,
    "gn:timezone":"Europe/Istanbul",
    "iso:country":"TR",
    "name:tur_x_preferred":[
        "Ak\u00e7akaya"
    ],
    "wof:name":"Akcakaya",
    "wof:placetype":"locality"
},
  "geometry": {"coordinates":[30.01916,40.5091],"type":"Point"}
}