{
  "type": "Feature",
  "properties": {
    "gn:admin1_code":"63",
    "gn:asciiname":"Keremli",
    "gn:country_code":"TR",
    "gn:dem":584,
    "gn:feature_class":"P",
    "gn:feature_code":"PPL",
    "gn:name":"Keremli",
    "gn:population":0,
    "gn:timezone":"Europe/Istanbul",
    "iso:country":"TR",
    "name:tur_x_preferred":[
        "Keremli"
    ],
    "name:und_x_variant":[
        "Akviranchello"
    ],
    "wof:name":"Keremli",
    "wof:placetype":"locality"
},
  "geometry": {"coordinates":[39.06132,37.24314],"type":"Point"}
}