{
  "type": "Feature",
  "properties": {
    "gn:admin1_code":"65",
    "gn:asciiname":"Karagunduz",
    "gn:country_code":"TR",
    "gn:dem":1816,
    "gn:feature_class":"P",
    "gn:feature_code":"PPL",
    "gn:name":"Karag\u00fcnd\u00fcz",
    "gn:population":0,
    "gn:timezone":"Europe/Istanbul",
    "iso:country":"TR",
    "name:tur_x_preferred":[
        "Karag\u00fcnd\u00fcz"
    ],
    "wof:name":"Karagunduz",
    "wof:placetype":"locality"
},
  "geometry": {"coordinates":[43.64422,38.69603],"type":"Point"}
}