{
  "type": "Feature",
  "properties": {
    "gn:admin1_code":"79.0",
    "gn:asciiname":"Kazmaca",
    "gn:country_code":"TR",
    "gn:dem":1064,
    "gn:feature_class":"P",
    "gn:feature_code":"PPL",
    "gn:name":"Kazmaca",
    "gn:population":0,
    "gn:timezone":"Europe/Istanbul",
    "iso:country":"TR",
    "wof:name":"Kazmaca",
    "wof:placetype":"locality"
},
  "geometry": {"coordinates":[33.58501,40.05367],"type":"Point"}
}