{
  "type": "Feature",
  "properties": {
    "gn:admin1_code":"65",
    "gn:asciiname":"Yaylakonak",
    "gn:country_code":"TR",
    "gn:dem":1959,
    "gn:feature_class":"P",
    "gn:feature_code":"PPL",
    "gn:name":"Yaylakonak",
    "gn:population":0,
    "gn:timezone":"Europe/Istanbul",
    "iso:country":"TR",
    "name:und_x_variant":[
        "Taramak",
        "Yaylakonak"
    ],
    "wof:name":"Yaylakonak",
    "wof:placetype":"locality"
},
  "geometry": {"coordinates":[42.71595,38.06312],"type":"Point"}
}