{
  "type": "Feature",
  "properties": {
    "gn:admin1_code":"71",
    "gn:asciiname":"Asagi Gondelen",
    "gn:country_code":"TR",
    "gn:dem":1035,
    "gn:feature_class":"P",
    "gn:feature_code":"PPL",
    "gn:name":"A\u015fa\u011f\u0131 G\u00f6ndelen",
    "gn:population":0,
    "gn:timezone":"Europe/Istanbul",
    "iso:country":"TR",
    "name:und_x_variant":[
        "A\u015fa\u011f\u0131 G\u00f6ndelen",
        "A\u015fa\u011f\u0131g\u00f6ndelen"
    ],
    "wof:name":"Asagi Gondelen",
    "wof:placetype":"locality"
},
  "geometry": {"coordinates":[34.18003,37.71164],"type":"Point"}
}