{
  "type": "Feature",
  "properties": {
    "gn:admin1_code":"17.0",
    "gn:asciiname":"Yukarikaraasik",
    "gn:country_code":"TR",
    "gn:dem":512,
    "gn:feature_class":"P",
    "gn:feature_code":"PPL",
    "gn:name":"Yukar\u0131karaa\u015f\u0131k",
    "gn:population":0,
    "gn:timezone":"Europe/Istanbul",
    "iso:country":"TR",
    "name:und_x_variant":[
        "Yukar\u0131karaa\u015f\u0131k",
        "Yukar\u0131kar\u0131\u015f\u0131k"
    ],
    "wof:name":"Yukarikaraasik",
    "wof:placetype":"locality"
},
  "geometry": {"coordinates":[27.18806,40.00139],"type":"Point"}
}