{
  "type": "Feature",
  "properties": {
    "gn:country":"TR",
    "gn:fcode":"PPLA2",
    "gn:pop":8704,
    "iso:country":"TR",
    "name:cat_x_preferred":[
        "Sar\u0131yah\u015fi"
    ],
    "name:ceb_x_preferred":[
        "Sar\u0131yah\u015fi \u0130l\u00e7esi"
    ],
    "name:deu_x_preferred":[
        "Sar\u0131yah\u015fi"
    ],
    "name:eng_x_preferred":[
        "Sar\u0131yah\u015fi"
    ],
    "name:epo_x_preferred":[
        "Sar\u0131yah\u015fi"
    ],
    "name:fas_x_preferred":[
        "\u0633\u0627\u0631\u06cc\u200c\u06cc\u0627\u062e\u0686\u06cc"
    ],
    "name:fra_x_preferred":[
        "Sar\u0131yah\u015fi"
    ],
    "name:ita_x_preferred":[
        "Distretto di Sar\u0131yah\u015fi"
    ],
    "name:lbe_x_preferred":[
        "\u0421\u0430\u0440\u044b\u044f\u0445\u0448\u0438"
    ],
    "name:nan_x_preferred":[
        "Sar\u0131yah\u015fi"
    ],
    "name:nld_x_preferred":[
        "Sar\u0131yah\u015fi"
    ],
    "name:nob_x_preferred":[
        "Sar\u0131yah\u015fi"
    ],
    "name:tur_x_preferred":[
        "Sar\u0131yah\u015fi"
    ],
    "name:vie_x_preferred":[
        "Sar\u0131yah\u015fi"
    ],
    "qs:name":"Sar\u0131yah\u015fi",
    "qs:name_adm0":"Turkey",
    "qs:name_adm1":"Aksaray",
    "qs:photos_9r":0,
    "qs:photos_sr":0,
    "qs:placetype":"Town",
    "qs:pop_sr":"5",
    "wd:wordcount":299,
    "wof:name":"Sar\u0131yah\u015fi",
    "wof:placetype":"locality",
    "wof:population":8704
},
  "geometry": {"coordinates":[33.84136,38.98349],"type":"Point"}
}