{
  "type": "Feature",
  "properties": {
    "gn:admin1_code":"21",
    "gn:asciiname":"Bagpinar",
    "gn:country_code":"TR",
    "gn:dem":685,
    "gn:feature_class":"P",
    "gn:feature_code":"PPL",
    "gn:name":"Ba\u011fp\u0131nar",
    "gn:population":0,
    "gn:timezone":"Europe/Istanbul",
    "iso:country":"TR",
    "name:tur_x_preferred":[
        "Ba\u011fp\u0131nar"
    ],
    "name:und_x_variant":[
        "B\u00fcy\u00fckzo\u011fzun\u00e7",
        "Zo\u011fzun\u00e7"
    ],
    "wof:name":"Bagpinar",
    "wof:placetype":"locality"
},
  "geometry": {"coordinates":[40.43847,38.00757],"type":"Point"}
}