{
  "type": "Feature",
  "properties": {
    "gn:admin1_code":"91.0",
    "gn:asciiname":"Ciplaklar",
    "gn:country_code":"TR",
    "gn:dem":38,
    "gn:feature_class":"P",
    "gn:feature_code":"PPL",
    "gn:name":"\u00c7\u0131plaklar",
    "gn:population":0,
    "gn:timezone":"Europe/Istanbul",
    "iso:country":"TR",
    "wof:name":"Ciplaklar",
    "wof:placetype":"locality"
},
  "geometry": {"coordinates":[35.97543,37.30529],"type":"Point"}
}