{
  "type": "Feature",
  "properties": {
    "gn:admin1_code":"58",
    "gn:asciiname":"Atgecmez",
    "gn:country_code":"TR",
    "gn:dem":1726,
    "gn:feature_class":"P",
    "gn:feature_code":"PPL",
    "gn:name":"Atge\u00e7mez",
    "gn:population":0,
    "gn:timezone":"Europe/Istanbul",
    "iso:country":"TR",
    "wof:name":"Atgecmez",
    "wof:placetype":"locality"
},
  "geometry": {"coordinates":[37.81061,39.63178],"type":"Point"}
}