{
  "type": "Feature",
  "properties": {
    "iso:country":"TR",
    "name:eng_x_preferred":[
        "Suluntepe"
    ],
    "name:tur_x_preferred":[
        "S\u00fcl\u00fcntepe"
    ],
    "wof:name":"Suluntepe",
    "wof:placetype":"neighbourhood"
},
  "geometry": {"coordinates":[29.28081783147264,40.91396688312213],"type":"Point"}
}