{
  "type": "Feature",
  "properties": {
    "gn:admin1_code":"58",
    "gn:asciiname":"Eymir",
    "gn:country_code":"TR",
    "gn:dem":1336,
    "gn:feature_class":"P",
    "gn:feature_code":"PPL",
    "gn:name":"Eymir",
    "gn:population":0,
    "gn:timezone":"Europe/Istanbul",
    "iso:country":"TR",
    "wof:name":"Eymir",
    "wof:placetype":"locality"
},
  "geometry": {"coordinates":[37.24778,39.84966],"type":"Point"}
}