{
  "type": "Feature",
  "properties": {
    "gn:admin1_code":"60.0",
    "gn:asciiname":"Kuzbagi",
    "gn:country_code":"TR",
    "gn:dem":935,
    "gn:feature_class":"P",
    "gn:feature_code":"PPL",
    "gn:name":"Kuzba\u011f\u0131",
    "gn:population":0,
    "gn:timezone":"Europe/Istanbul",
    "iso:country":"TR",
    "wof:name":"Kuzbagi",
    "wof:placetype":"locality"
},
  "geometry": {"coordinates":[37.41869000000001,40.44242],"type":"Point"}
}