{
  "type": "Feature",
  "properties": {
    "gn:admin1_code":"04",
    "gn:asciiname":"Guvercinli",
    "gn:country_code":"TR",
    "gn:dem":2223,
    "gn:feature_class":"P",
    "gn:feature_code":"PPL",
    "gn:name":"G\u00fcvercinli",
    "gn:population":0,
    "gn:timezone":"Europe/Istanbul",
    "iso:country":"TR",
    "name:und_x_variant":[
        "Yukar\u0131 A\u015faran",
        "G\u00fcvercinli"
    ],
    "wof:name":"Guvercinli",
    "wof:placetype":"locality"
},
  "geometry": {"coordinates":[42.78149000000001,39.00084],"type":"Point"}
}