{
  "type": "Feature",
  "properties": {
    "gn:admin1_code":"21.0",
    "gn:asciiname":"Boncuklu",
    "gn:country_code":"TR",
    "gn:dem":818,
    "gn:feature_class":"P",
    "gn:feature_code":"PPL",
    "gn:name":"Boncuklu",
    "gn:population":0,
    "gn:timezone":"Europe/Istanbul",
    "iso:country":"TR",
    "name:tur_x_preferred":[
        "Boncuklu"
    ],
    "wof:name":"Boncuklu",
    "wof:placetype":"locality"
},
  "geometry": {"coordinates":[39.75059,38.2137],"type":"Point"}
}