{
  "type": "Feature",
  "properties": {
    "gn:admin1_code":"03",
    "gn:asciiname":"Bektas",
    "gn:country_code":"TR",
    "gn:dem":1248,
    "gn:feature_class":"P",
    "gn:feature_code":"PPL",
    "gn:name":"Bekta\u015f",
    "gn:population":0,
    "gn:timezone":"Europe/Istanbul",
    "iso:country":"TR",
    "name:und_x_variant":[
        "Bekta\u015f",
        "Bekta\u015fk\u00f6y"
    ],
    "wof:name":"Bektas",
    "wof:placetype":"locality"
},
  "geometry": {"coordinates":[30.33778,38.43556],"type":"Point"}
}