{
  "type": "Feature",
  "properties": {
    "gn:country":"TR",
    "gn:fcode":"PPL",
    "gn:pop":3461,
    "iso:country":"TR",
    "name:tur_x_preferred":[
        "Kur\u015funlu"
    ],
    "qs:name":"Kur\u015funlu",
    "qs:photos_9r":0,
    "qs:photos_sr":0,
    "qs:pop_sr":"4",
    "wd:wordcount":108,
    "wof:name":"Kur\u015funlu",
    "wof:placetype":"locality",
    "wof:population":3461
},
  "geometry": {"coordinates":[29.66472,40.03361],"type":"Point"}
}