{
  "type": "Feature",
  "properties": {
    "gn:country":"TR",
    "gn:fcode":"PPL",
    "gn:population":3461,
    "iso:country":"TR",
    "name:ceb_x_preferred":[
        "Kur\u015funlu"
    ],
    "name:deu_x_preferred":[
        "Kur\u015funlu"
    ],
    "name:eng_x_preferred":[
        "Kur\u015funlu"
    ],
    "name:fra_x_preferred":[
        "Kur\u015funlu"
    ],
    "name:mrj_x_preferred":[
        "\u041a\u0443\u0440\u0448\u0443\u043d\u043b\u0443"
    ],
    "name:msa_x_preferred":[
        "Kur\u015funlu"
    ],
    "name:nan_x_preferred":[
        "Kur\u015funlu"
    ],
    "name:nld_x_preferred":[
        "Kur\u015funlu"
    ],
    "name:nob_x_preferred":[
        "Kur\u015funlu"
    ],
    "name:swa_x_preferred":[
        "Kur\u015funlu"
    ],
    "name:tur_x_preferred":[
        "Kur\u015funlu"
    ],
    "name:urd_x_preferred":[
        "\u06a9\u0648\u0631\u0634\u0648\u0646\u0644\u0648"
    ],
    "name:vie_x_preferred":[
        "Kur\u015funlu"
    ],
    "qs:name":"Kur\u015funlu",
    "qs:photos_9r":0,
    "qs:photos_sr":0,
    "qs:pop_sr":"4",
    "wd:wordcount":108,
    "wof:name":"Kur\u015funlu",
    "wof:placetype":"locality",
    "wof:population":3461
},
  "geometry": {"coordinates":[29.66472,40.03361],"type":"Point"}
}