{
  "type": "Feature",
  "properties": {
    "gn:admin1_code":"66",
    "gn:asciiname":"Gozbaba",
    "gn:country_code":"TR",
    "gn:dem":1309,
    "gn:feature_class":"P",
    "gn:feature_code":"PPL",
    "gn:name":"G\u00f6zbaba",
    "gn:population":0,
    "gn:timezone":"Europe/Istanbul",
    "iso:country":"TR",
    "wof:name":"Gozbaba",
    "wof:placetype":"locality"
},
  "geometry": {"coordinates":[35.03255,39.76235],"type":"Point"}
}