{
  "type": "Feature",
  "properties": {
    "gn:admin1_code":"16.0",
    "gn:asciiname":"Eski Karaagac",
    "gn:country_code":"TR",
    "gn:dem":17,
    "gn:feature_class":"P",
    "gn:feature_code":"PPL",
    "gn:name":"Eski Karaa\u011fa\u00e7",
    "gn:population":0,
    "gn:timezone":"Europe/Istanbul",
    "iso:country":"TR",
    "name:tur_x_preferred":[
        "Eski Karaa\u011fa\u00e7"
    ],
    "name:und_x_variant":[
        "Karaa\u011fa\u00e7",
        "Eskikaraa\u011fa\u00e7"
    ],
    "wof:name":"Eski Karaagac",
    "wof:placetype":"locality"
},
  "geometry": {"coordinates":[28.61278,40.1875],"type":"Point"}
}