{
  "type": "Feature",
  "properties": {
    "gn:admin1_code":"4.0",
    "gn:asciiname":"Ikiyamac",
    "gn:country_code":"TR",
    "gn:dem":1919,
    "gn:feature_class":"P",
    "gn:feature_code":"PPL",
    "gn:name":"\u0130kiyama\u00e7",
    "gn:population":0,
    "gn:timezone":"Europe/Istanbul",
    "iso:country":"TR",
    "name:tur_x_preferred":[
        "\u0130kiyama\u00e7"
    ],
    "wof:name":"Ikiyamac",
    "wof:placetype":"locality"
},
  "geometry": {"coordinates":[43.37307,39.68349],"type":"Point"}
}