{
  "type": "Feature",
  "properties": {
    "gn:admin1_code":"22.0",
    "gn:asciiname":"Kucukdoganca",
    "gn:country_code":"TR",
    "gn:dem":90,
    "gn:feature_class":"P",
    "gn:feature_code":"PPL",
    "gn:name":"K\u00fc\u00e7\u00fckdo\u011fanca",
    "gn:population":0,
    "gn:timezone":"Europe/Istanbul",
    "iso:country":"TR",
    "name:tur_x_preferred":[
        "K\u00fc\u00e7\u00fckdo\u011fanca"
    ],
    "wof:name":"Kucukdoganca",
    "wof:placetype":"locality"
},
  "geometry": {"coordinates":[26.71472,40.93789],"type":"Point"}
}