{
  "type": "Feature",
  "properties": {
    "iso:country":"TR",
    "name:tur_x_preferred":[
        "B\u00fcy\u00fcklanga"
    ],
    "wof:name":"Buyuklanga",
    "wof:placetype":"neighbourhood"
},
  "geometry": {"coordinates":[28.95646354676986,41.00559251616399],"type":"Point"}
}