{
  "type": "Feature",
  "properties": {
    "gn:admin1_code":"44",
    "gn:asciiname":"Erdemli",
    "gn:country_code":"TR",
    "gn:dem":1004,
    "gn:feature_class":"P",
    "gn:feature_code":"PPL",
    "gn:name":"Erdemli",
    "gn:population":0,
    "gn:timezone":"Europe/Istanbul",
    "iso:country":"TR",
    "name:und_x_variant":[
        "Gevenis",
        "Erdemli"
    ],
    "wof:name":"Erdemli",
    "wof:placetype":"locality"
},
  "geometry": {"coordinates":[38.69463,38.35435],"type":"Point"}
}