{
  "type": "Feature",
  "properties": {
    "gn:admin1_code":"78.0",
    "gn:asciiname":"Gulkaya",
    "gn:country_code":"TR",
    "gn:dem":1217,
    "gn:feature_class":"P",
    "gn:feature_code":"PPL",
    "gn:name":"G\u00fclkaya",
    "gn:population":0,
    "gn:timezone":"Europe/Istanbul",
    "iso:country":"TR",
    "name:tur_x_preferred":[
        "G\u00fclkaya"
    ],
    "name:tur_x_variant":[
        "G\u00f6lkaya"
    ],
    "wof:name":"Gulkaya",
    "wof:placetype":"locality"
},
  "geometry": {"coordinates":[33.39289,37.05187],"type":"Point"}
}