{
  "type": "Feature",
  "properties": {
    "gn:admin1_code":"80.0",
    "gn:asciiname":"Chaglan",
    "gn:country_code":"TR",
    "gn:dem":1722,
    "gn:feature_class":"P",
    "gn:feature_code":"PPL",
    "gn:name":"Chaglan",
    "gn:population":0,
    "gn:timezone":"Europe/Istanbul",
    "iso:country":"TR",
    "name:und_x_variant":[
        "\u00c7a\u011flan"
    ],
    "wof:name":"Chaglan",
    "wof:placetype":"locality"
},
  "geometry": {"coordinates":[42.68333,37.57389000000001],"type":"Point"}
}