{
  "type": "Feature",
  "properties": {
    "gn:admin1_code":"26",
    "gn:asciiname":"Dogancayir",
    "gn:cc2":"TR",
    "gn:country_code":"TR",
    "gn:dem":918,
    "gn:feature_class":"P",
    "gn:feature_code":"PPL",
    "gn:name":"Do\u011fan\u00e7ay\u0131r",
    "gn:population":0,
    "gn:timezone":"Europe/Istanbul",
    "iso:country":"TR",
    "name:epo_x_preferred":[
        "Do\u011fan\u00e7ay\u0131r"
    ],
    "name:tur_x_preferred":[
        "Do\u011fan\u00e7ay\u0131r"
    ],
    "name:und_x_variant":[
        "Arap\u00f6ren"
    ],
    "wof:name":"Dogancayir",
    "wof:placetype":"locality"
},
  "geometry": {"coordinates":[30.83333,39.53361],"type":"Point"}
}