{
  "type": "Feature",
  "properties": {
    "gn:admin1_code":"87.0",
    "gn:asciiname":"Okcular",
    "gn:country_code":"TR",
    "gn:dem":643,
    "gn:feature_class":"P",
    "gn:feature_code":"PPL",
    "gn:name":"Ok\u00e7ular",
    "gn:population":0,
    "gn:timezone":"Europe/Istanbul",
    "iso:country":"TR",
    "name:und_x_variant":[
        "Ok\u00e7ular",
        "Ayazlar"
    ],
    "wof:name":"Okcular",
    "wof:placetype":"locality"
},
  "geometry": {"coordinates":[32.59087,41.63715],"type":"Point"}
}