{
  "type": "Feature",
  "properties": {
    "gn:admin1_code":"23",
    "gn:asciiname":"Topalusagi",
    "gn:country_code":"TR",
    "gn:dem":1402,
    "gn:feature_class":"P",
    "gn:feature_code":"PPL",
    "gn:name":"Topalu\u015fa\u011f\u0131",
    "gn:population":0,
    "gn:timezone":"Europe/Istanbul",
    "iso:country":"TR",
    "name:tur_x_preferred":[
        "Topalu\u015fa\u011f\u0131"
    ],
    "wof:name":"Topalusagi",
    "wof:placetype":"locality"
},
  "geometry": {"coordinates":[39.52801,38.3761],"type":"Point"}
}