{
  "type": "Feature",
  "properties": {
    "gn:admin1_code":"78",
    "gn:asciiname":"Goktepe",
    "gn:country_code":"TR",
    "gn:dem":1278,
    "gn:feature_class":"P",
    "gn:feature_code":"PPLA3",
    "gn:name":"G\u00f6ktepe",
    "gn:population":0,
    "gn:timezone":"Europe/Istanbul",
    "iso:country":"TR",
    "name:und_x_variant":[
        "G\u00f6ktepe"
    ],
    "wof:name":"Goktepe",
    "wof:placetype":"locality"
},
  "geometry": {"coordinates":[32.6228,36.62687],"type":"Point"}
}