{
  "type": "Feature",
  "properties": {
    "gn:admin1_code":"34.0",
    "gn:asciiname":"Kurna",
    "gn:country_code":"TR",
    "gn:dem":44,
    "gn:feature_class":"P",
    "gn:feature_code":"PPL",
    "gn:name":"Kurna",
    "gn:population":0,
    "gn:timezone":"Europe/Istanbul",
    "iso:country":"TR",
    "name:ara_x_preferred":[
        "\u0627\u0644\u0642\u0631\u0646\u0629"
    ],
    "name:ita_x_preferred":[
        "Gurna"
    ],
    "name:nld_x_preferred":[
        "Qurna"
    ],
    "name:pol_x_preferred":[
        "Al-Kurna"
    ],
    "name:ukr_x_preferred":[
        "\u041a\u0443\u0440\u043d\u0430"
    ],
    "name:und_x_variant":[
        "Korna",
        "Kurna"
    ],
    "wof:name":"Kurna",
    "wof:placetype":"locality"
},
  "geometry": {"coordinates":[29.36706,41.19519],"type":"Point"}
}