{
  "type": "Feature",
  "properties": {
    "gn:admin1_code":"34.0",
    "gn:asciiname":"Kurna",
    "gn:country_code":"TR",
    "gn:dem":44,
    "gn:feature_class":"P",
    "gn:feature_code":"PPL",
    "gn:name":"Kurna",
    "gn:population":0,
    "gn:timezone":"Europe/Istanbul",
    "iso:country":"TR",
    "name:und_x_variant":[
        "Korna",
        "Kurna"
    ],
    "wof:name":"Kurna",
    "wof:placetype":"locality"
},
  "geometry": {"coordinates":[29.36706,41.19519],"type":"Point"}
}