{
  "type": "Feature",
  "properties": {
    "gn:admin1_code":"32",
    "gn:asciiname":"Kakliktasi",
    "gn:country_code":"TR",
    "gn:dem":609,
    "gn:feature_class":"P",
    "gn:feature_code":"PPL",
    "gn:name":"Kakl\u0131kta\u015f\u0131",
    "gn:population":0,
    "gn:timezone":"Europe/Istanbul",
    "iso:country":"TR",
    "name:tur_x_preferred":[
        "Kakl\u0131kta\u015f\u0131"
    ],
    "wof:name":"Kakliktasi",
    "wof:placetype":"locality"
},
  "geometry": {"coordinates":[34.67874,37.01971],"type":"Point"}
}