{
  "type": "Feature",
  "properties": {
    "iso:country":"TR",
    "name:tur_x_preferred":[
        "Fevzi \u00c7akmak"
    ],
    "wof:name":"Fevzi Cakmak",
    "wof:placetype":"neighbourhood"
},
  "geometry": {"coordinates":[28.7915675719324,41.00764186847653],"type":"Point"}
}