{
  "type": "Feature",
  "properties": {
    "gn:admin1_code":"21.0",
    "gn:asciiname":"Gurbekli",
    "gn:country_code":"TR",
    "gn:dem":766,
    "gn:feature_class":"P",
    "gn:feature_code":"PPL",
    "gn:name":"G\u00fcrbekli",
    "gn:population":0,
    "gn:timezone":"Europe/Istanbul",
    "iso:country":"TR",
    "name:tur_x_preferred":[
        "Ya\u015filk\u00f6y"
    ],
    "name:und_x_variant":[
        "G\u00fcrbekli"
    ],
    "wof:name":"Gurbekli",
    "wof:placetype":"locality"
},
  "geometry": {"coordinates":[40.12142,37.96382],"type":"Point"}
}