{
  "type": "Feature",
  "properties": {
    "gn:admin1_code":"46",
    "gn:asciiname":"Kallenci",
    "gn:country_code":"TR",
    "gn:dem":200,
    "gn:feature_class":"P",
    "gn:feature_code":"PPL",
    "gn:name":"Kallenci",
    "gn:population":0,
    "gn:timezone":"Europe/Istanbul",
    "iso:country":"TR",
    "name:und_x_variant":[
        "K\u0131y\u0131k\u00e7\u0131",
        "Kallenci"
    ],
    "wof:name":"Kallenci",
    "wof:placetype":"locality"
},
  "geometry": {"coordinates":[36.27788,37.3828],"type":"Point"}
}