{
  "type": "Feature",
  "properties": {
    "gn:admin1_code":"31",
    "gn:asciiname":"Tuerkmenmezraasi",
    "gn:country_code":"TR",
    "gn:dem":382,
    "gn:feature_class":"P",
    "gn:feature_code":"PPL",
    "gn:name":"T\u00fcrkmenmezraas\u0131",
    "gn:population":0,
    "gn:timezone":"Europe/Istanbul",
    "iso:country":"TR",
    "name:tur_x_preferred":[
        "T\u00fcrkmenmezraas\u0131"
    ],
    "name:und_x_variant":[
        "T\u00fcrkmenmezreas\u0131",
        "T\u00fcrkmen",
        "T\u00fcrkmenmezras\u0131"
    ],
    "wof:name":"Tuerkmenmezraasi",
    "wof:placetype":"locality"
},
  "geometry": {"coordinates":[36.27534,36.07765],"type":"Point"}
}