{
  "type": "Feature",
  "properties": {
    "gn:admin1_code":"35",
    "gn:asciiname":"Igdeli",
    "gn:country_code":"TR",
    "gn:dem":905,
    "gn:feature_class":"P",
    "gn:feature_code":"PPL",
    "gn:name":"\u0130\u011fdeli",
    "gn:population":0,
    "gn:timezone":"Europe/Istanbul",
    "iso:country":"TR",
    "name:tur_x_preferred":[
        "\u0130\u011fdeli"
    ],
    "wof:name":"Igdeli",
    "wof:placetype":"locality"
},
  "geometry": {"coordinates":[28.37741,38.21776],"type":"Point"}
}