{
  "type": "Feature",
  "properties": {
    "gn:country":"TR",
    "gn:fcode":"PPL",
    "gn:pop":0,
    "iso:country":"TR",
    "qs:name":"Tav\u015fan\u00e7al\u0131",
    "qs:name_adm0":"Turkey",
    "qs:name_adm1":"Konya",
    "qs:photos_9k":1,
    "qs:photos_9r":1,
    "qs:photos_all":1,
    "qs:photos_sr":0,
    "qs:placetype":"Town",
    "qs:pop_sr":"0",
    "wof:name":"Tav\u015fan\u00e7al\u0131",
    "wof:placetype":"locality",
    "wof:population":0
},
  "geometry": {"coordinates":[33.00583,38.93778],"type":"Point"}
}