{
  "type": "Feature",
  "properties": {
    "gn:admin1_code":"43",
    "gn:asciiname":"Guney",
    "gn:country_code":"TR",
    "gn:dem":802,
    "gn:feature_class":"P",
    "gn:feature_code":"PPL",
    "gn:name":"G\u00fcney",
    "gn:population":0,
    "gn:timezone":"Europe/Istanbul",
    "iso:country":"TR",
    "name:ceb_x_preferred":[
        "Guney"
    ],
    "name:swe_x_preferred":[
        "Guney"
    ],
    "wof:name":"Guney",
    "wof:placetype":"locality"
},
  "geometry": {"coordinates":[28.91722,39.18278],"type":"Point"}
}