{
  "type": "Feature",
  "properties": {
    "gn:admin1_code":"68.0",
    "gn:asciiname":"Durhasan",
    "gn:country_code":"TR",
    "gn:dem":1181,
    "gn:feature_class":"P",
    "gn:feature_code":"PPL",
    "gn:name":"Durhasan",
    "gn:population":0,
    "gn:timezone":"Europe/Istanbul",
    "iso:country":"TR",
    "wof:name":"Durhasan",
    "wof:placetype":"locality"
},
  "geometry": {"coordinates":[32.93654,40.33445],"type":"Point"}
}